{
  "type": "Feature",
  "properties": {
    "gn:admin1_code":"29",
    "gn:admin2_code":"76248.0",
    "gn:asciiname":"El Rosario",
    "gn:country_code":"CO",
    "gn:dem":975,
    "gn:feature_class":"P",
    "gn:feature_code":"PPL",
    "gn:name":"El Rosar\u00edo",
    "gn:population":0,
    "gn:timezone":"America/Bogota",
    "iso:country":"CO",
    "wof:name":"El Rosario",
    "wof:placetype":"locality"
},
  "geometry": {"coordinates":[-76.34194000000002,3.68056],"type":"Point"}
}