{
  "type": "Feature",
  "properties": {
    "gn:admin1_code":"35.0",
    "gn:admin2_code":"13052.0",
    "gn:asciiname":"Loma Larga",
    "gn:country_code":"CO",
    "gn:dem":51,
    "gn:feature_class":"P",
    "gn:feature_code":"PPL",
    "gn:name":"Loma Larga",
    "gn:population":0,
    "gn:timezone":"America/Bogota",
    "iso:country":"CO",
    "wof:name":"Loma Larga",
    "wof:placetype":"locality"
},
  "geometry": {"coordinates":[-75.29584,10.24095],"type":"Point"}
}