{
  "type": "Feature",
  "properties": {
    "gn:admin1_code":"2.0",
    "gn:admin2_code":"5686.0",
    "gn:asciiname":"Chaquiro",
    "gn:country_code":"CO",
    "gn:dem":2664,
    "gn:feature_class":"P",
    "gn:feature_code":"PPL",
    "gn:name":"Chaquiro",
    "gn:population":0,
    "gn:timezone":"America/Bogota",
    "iso:country":"CO",
    "wof:name":"Chaquiro",
    "wof:placetype":"locality"
},
  "geometry": {"coordinates":[-75.54028000000002,6.71556],"type":"Point"}
}