{
  "type": "Feature",
  "properties": {
    "gn:admin1_code":"27.0",
    "gn:admin2_code":"70708.0",
    "gn:asciiname":"Puerto La Playa",
    "gn:country_code":"CO",
    "gn:dem":20,
    "gn:feature_class":"P",
    "gn:feature_code":"PPL",
    "gn:name":"Puerto La Playa",
    "gn:population":0,
    "gn:timezone":"America/Bogota",
    "iso:country":"CO",
    "wof:name":"Puerto La Playa",
    "wof:placetype":"locality"
},
  "geometry": {"coordinates":[-75.14815,8.61382],"type":"Point"}
}