{
  "type": "Feature",
  "properties": {
    "gn:admin1_code":"12",
    "gn:admin2_code":"23570.0",
    "gn:asciiname":"La Granjita",
    "gn:country_code":"CO",
    "gn:dem":112,
    "gn:feature_class":"P",
    "gn:feature_code":"PPL",
    "gn:name":"La Granjita",
    "gn:population":0,
    "gn:timezone":"America/Bogota",
    "iso:country":"CO",
    "name:und_x_variant":[
        "Corregimiento La Granjita",
        "La Granjita"
    ],
    "wof:name":"La Granjita",
    "wof:placetype":"locality"
},
  "geometry": {"coordinates":[-75.52365,8.45244],"type":"Point"}
}