{
  "type": "Feature",
  "properties": {
    "gn:admin1_code":"32",
    "gn:admin2_code":"85162.0",
    "gn:asciiname":"Moriche Solo",
    "gn:country_code":"CO",
    "gn:dem":565,
    "gn:feature_class":"P",
    "gn:feature_code":"PPL",
    "gn:name":"Moriche Solo",
    "gn:population":0,
    "gn:timezone":"America/Bogota",
    "iso:country":"CO",
    "wof:name":"Moriche Solo",
    "wof:placetype":"locality"
},
  "geometry": {"coordinates":[-72.82135,4.91575],"type":"Point"}
}