{
  "type": "Feature",
  "properties": {
    "gn:admin1_code":"17",
    "gn:admin2_code":"44847.0",
    "gn:asciiname":"Mapuakito",
    "gn:country_code":"CO",
    "gn:dem":81,
    "gn:feature_class":"P",
    "gn:feature_code":"PPL",
    "gn:name":"Map\u00faakito",
    "gn:population":0,
    "gn:timezone":"America/Bogota",
    "iso:country":"CO",
    "wof:name":"Mapuakito",
    "wof:placetype":"locality"
},
  "geometry": {"coordinates":[-71.41467,12.05367],"type":"Point"}
}