{
  "type": "Feature",
  "properties": {
    "gn:admin1_code":"4.0",
    "gn:admin2_code":"8001.0",
    "gn:asciiname":"Olaya Herrera",
    "gn:country_code":"CO",
    "gn:dem":105,
    "gn:feature_class":"P",
    "gn:feature_code":"PPL",
    "gn:name":"Olaya Herrera",
    "gn:population":0,
    "gn:timezone":"America/Bogota",
    "iso:country":"CO",
    "wof:name":"Olaya Herrera",
    "wof:placetype":"locality"
},
  "geometry": {"coordinates":[-74.81923,10.99595],"type":"Point"}
}