{
  "type": "Feature",
  "properties": {
    "gn:admin1_code":"26",
    "gn:admin2_code":"68276.0",
    "gn:asciiname":"Villa Josefa",
    "gn:country_code":"CO",
    "gn:dem":1457,
    "gn:feature_class":"P",
    "gn:feature_code":"PPL",
    "gn:name":"Villa Josefa",
    "gn:population":0,
    "gn:timezone":"America/Bogota",
    "iso:country":"CO",
    "name:spa_x_preferred":[
        "Villa Josefa"
    ],
    "name:und_x_variant":[
        "Villa Joseia"
    ],
    "wof:name":"Villa Josefa",
    "wof:placetype":"locality"
},
  "geometry": {"coordinates":[-73.07744,7.10872],"type":"Point"}
}