{
  "type": "Feature",
  "properties": {
    "gn:admin1_code":"38",
    "gn:admin2_code":"47545.0",
    "gn:asciiname":"El Descanso",
    "gn:country_code":"CO",
    "gn:dem":47,
    "gn:feature_class":"P",
    "gn:feature_code":"PPL",
    "gn:name":"El Descanso",
    "gn:population":0,
    "gn:timezone":"America/Bogota",
    "iso:country":"CO",
    "wof:name":"El Descanso",
    "wof:placetype":"locality"
},
  "geometry": {"coordinates":[-74.29655,9.41156],"type":"Point"}
}