{
  "type": "Feature",
  "properties": {
    "gn:admin1_code":"8.0",
    "gn:admin2_code":"18001.0",
    "gn:asciiname":"La Argentina",
    "gn:country_code":"CO",
    "gn:dem":261,
    "gn:feature_class":"P",
    "gn:feature_code":"PPL",
    "gn:name":"La Argentina",
    "gn:population":0,
    "gn:timezone":"America/Bogota",
    "iso:country":"CO",
    "name:spa_x_preferred":[
        "La Argentina"
    ],
    "wof:name":"La Argentina",
    "wof:placetype":"locality"
},
  "geometry": {"coordinates":[-75.58877,1.57957],"type":"Point"}
}