{
  "type": "Feature",
  "properties": {
    "gn:admin1_code":"19",
    "gn:admin2_code":"50689",
    "gn:asciiname":"El Palmar",
    "gn:country_code":"CO",
    "gn:dem":400,
    "gn:feature_class":"P",
    "gn:feature_code":"PPL",
    "gn:name":"El Palmar",
    "gn:population":0,
    "gn:timezone":"America/Bogota",
    "iso:country":"CO",
    "name:ceb_x_preferred":[
        "El Palmar"
    ],
    "name:fra_x_preferred":[
        "El Palmar"
    ],
    "name:glg_x_preferred":[
        "El Palmar"
    ],
    "name:lit_x_preferred":[
        "El Palmaras"
    ],
    "name:spa_x_preferred":[
        "El Palmar"
    ],
    "name:srp_x_preferred":[
        "\u0415\u043b \u041f\u0430\u043b\u043c\u0430\u0440"
    ],
    "name:swe_x_preferred":[
        "El Palmar"
    ],
    "wof:name":"El Palmar",
    "wof:placetype":"locality"
},
  "geometry": {"coordinates":[-73.68879,3.66775],"type":"Point"}
}