{
  "type": "Feature",
  "properties": {
    "gn:admin1_code":"33",
    "gn:admin2_code":"25295.0",
    "gn:asciiname":"El Cerrito",
    "gn:country_code":"CO",
    "gn:dem":2667,
    "gn:feature_class":"P",
    "gn:feature_code":"PPL",
    "gn:name":"El Cerrito",
    "gn:population":0,
    "gn:timezone":"America/Bogota",
    "iso:country":"CO",
    "wof:name":"El Cerrito",
    "wof:placetype":"locality"
},
  "geometry": {"coordinates":[-73.90000000000001,5.01667],"type":"Point"}
}