{
  "type": "Feature",
  "properties": {
    "gn:admin1_code":"15",
    "gn:admin2_code":"94001.0",
    "gn:asciiname":"El Pato",
    "gn:country_code":"CO",
    "gn:dem":90,
    "gn:feature_class":"P",
    "gn:feature_code":"PPL",
    "gn:name":"El Pato",
    "gn:population":0,
    "gn:timezone":"America/Bogota",
    "iso:country":"CO",
    "wof:name":"El Pato",
    "wof:placetype":"locality"
},
  "geometry": {"coordinates":[-67.78439,3.14106],"type":"Point"}
}