{
  "type": "Feature",
  "properties": {
    "gn:admin1_code":"2",
    "gn:admin2_code":"5042.0",
    "gn:asciiname":"Gollas",
    "gn:country_code":"CO",
    "gn:dem":1345,
    "gn:feature_class":"P",
    "gn:feature_code":"PPL",
    "gn:name":"Gollas",
    "gn:population":0,
    "gn:timezone":"America/Bogota",
    "iso:country":"CO",
    "wof:name":"Gollas",
    "wof:placetype":"locality"
},
  "geometry": {"coordinates":[-75.86667,6.61667],"type":"Point"}
}