{
  "type": "Feature",
  "properties": {
    "gn:admin1_code":"24",
    "gn:admin2_code":"66594.0",
    "gn:asciiname":"Irra",
    "gn:cc2":"CO",
    "gn:country_code":"CO",
    "gn:dem":756,
    "gn:feature_class":"P",
    "gn:feature_code":"PPL",
    "gn:name":"Irr\u00e1",
    "gn:population":0,
    "gn:timezone":"America/Bogota",
    "iso:country":"CO",
    "name:und_x_variant":[
        "Irr\u00e1"
    ],
    "wof:name":"Irra",
    "wof:placetype":"locality"
},
  "geometry": {"coordinates":[-75.66639000000001,5.27139],"type":"Point"}
}