{
  "type": "Feature",
  "properties": {
    "gn:admin1_code":"9.0",
    "gn:admin2_code":"19809.0",
    "gn:asciiname":"Los Dos Brazos",
    "gn:country_code":"CO",
    "gn:dem":15,
    "gn:feature_class":"P",
    "gn:feature_code":"PPL",
    "gn:name":"Los Dos Brazos",
    "gn:population":0,
    "gn:timezone":"America/Bogota",
    "iso:country":"CO",
    "wof:name":"Los Dos Brazos",
    "wof:placetype":"locality"
},
  "geometry": {"coordinates":[-77.58385,2.76049],"type":"Point"}
}