{
  "type": "Feature",
  "properties": {
    "gn:admin1_code":"19.0",
    "gn:admin2_code":"50711.0",
    "gn:asciiname":"Caserio Bajo Guani",
    "gn:country_code":"CO",
    "gn:dem":233,
    "gn:feature_class":"P",
    "gn:feature_code":"PPL",
    "gn:name":"Caser\u00edo Bajo Guani",
    "gn:population":0,
    "gn:timezone":"America/Bogota",
    "iso:country":"CO",
    "wof:name":"Caserio Bajo Guani",
    "wof:placetype":"locality"
},
  "geometry": {"coordinates":[-73.63771,2.92004],"type":"Point"}
}