{
  "type": "Feature",
  "properties": {
    "gn:admin1_code":"17",
    "gn:admin2_code":"44001.0",
    "gn:asciiname":"Boca del Monte",
    "gn:country_code":"CO",
    "gn:dem":54,
    "gn:feature_class":"P",
    "gn:feature_code":"PPL",
    "gn:name":"Boca del Monte",
    "gn:population":0,
    "gn:timezone":"America/Bogota",
    "iso:country":"CO",
    "name:ita_x_preferred":[
        "Boca del Monte"
    ],
    "name:spa_x_preferred":[
        "Boca del Monte"
    ],
    "name:zho_x_preferred":[
        "\u535a\u5361\u5fb7\u5c14\u8499\u7279"
    ],
    "wof:name":"Boca del Monte",
    "wof:placetype":"locality"
},
  "geometry": {"coordinates":[-72.82494,11.2572],"type":"Point"}
}