{
  "type": "Feature",
  "properties": {
    "gn:admin1_code":"11.0",
    "gn:admin2_code":"27006.0",
    "gn:asciiname":"Chidima",
    "gn:country_code":"CO",
    "gn:dem":216,
    "gn:feature_class":"P",
    "gn:feature_code":"PPL",
    "gn:name":"Chidima",
    "gn:population":0,
    "gn:timezone":"America/Bogota",
    "iso:country":"CO",
    "wof:name":"Chidima",
    "wof:placetype":"locality"
},
  "geometry": {"coordinates":[-77.21659,8.3375],"type":"Point"}
}