{
  "type": "Feature",
  "properties": {
    "gn:admin1_code":"37",
    "gn:admin2_code":"17088.0",
    "gn:asciiname":"La Habana",
    "gn:country_code":"CO",
    "gn:dem":1655,
    "gn:feature_class":"P",
    "gn:feature_code":"PPL",
    "gn:name":"La Habana",
    "gn:population":0,
    "gn:timezone":"America/Bogota",
    "iso:country":"CO",
    "wof:name":"La Habana",
    "wof:placetype":"locality"
},
  "geometry": {"coordinates":[-75.79805,5.04345],"type":"Point"}
}