{
  "type": "Feature",
  "properties": {
    "gn:admin1_code":"29",
    "gn:admin2_code":"76248.0",
    "gn:asciiname":"Santa Rosalia",
    "gn:country_code":"CO",
    "gn:dem":966,
    "gn:feature_class":"P",
    "gn:feature_code":"PPL",
    "gn:name":"Santa Rosalia",
    "gn:population":0,
    "gn:timezone":"America/Bogota",
    "iso:country":"CO",
    "name:eng_x_preferred":[
        "Santa Rosalia"
    ],
    "wof:name":"Santa Rosalia",
    "wof:placetype":"locality"
},
  "geometry": {"coordinates":[-76.38667,3.66361],"type":"Point"}
}