{
  "type": "Feature",
  "properties": {
    "gn:admin1_code":"2",
    "gn:admin2_code":"5649.0",
    "gn:asciiname":"Playa",
    "gn:country_code":"CO",
    "gn:dem":978,
    "gn:feature_class":"P",
    "gn:feature_code":"PPL",
    "gn:name":"Playa",
    "gn:population":0,
    "gn:timezone":"America/Bogota",
    "iso:country":"CO",
    "name:ceb_x_preferred":[
        "Playa"
    ],
    "name:deu_x_preferred":[
        "Playa"
    ],
    "name:fra_x_preferred":[
        "Playa"
    ],
    "name:hrv_x_preferred":[
        "Playa"
    ],
    "name:ita_x_preferred":[
        "Playa"
    ],
    "name:nld_x_preferred":[
        "Playa"
    ],
    "name:pol_x_preferred":[
        "Playa"
    ],
    "name:rus_x_preferred":[
        "\u041f\u043b\u0430\u044f"
    ],
    "name:spa_x_preferred":[
        "Playa"
    ],
    "name:swe_x_preferred":[
        "Playa"
    ],
    "wof:name":"Playa",
    "wof:placetype":"locality"
},
  "geometry": {"coordinates":[-74.94028,6.30722],"type":"Point"}
}