{
  "type": "Feature",
  "properties": {
    "gn:admin1_code":"37",
    "gn:admin2_code":"17001.0",
    "gn:asciiname":"Cristalina",
    "gn:country_code":"CO",
    "gn:dem":1152,
    "gn:feature_class":"P",
    "gn:feature_code":"PPL",
    "gn:name":"Cristalina",
    "gn:population":0,
    "gn:timezone":"America/Bogota",
    "iso:country":"CO",
    "name:ara_x_preferred":[
        "\u0628\u0644\u062f\u064a\u0629 \u0643\u0631\u064a\u0633\u062a\u0627\u0644\u064a\u0646\u0627"
    ],
    "name:bpy_x_preferred":[
        "\u0995\u09b0\u09bf\u09b8\u099f\u09be\u09b2\u09bf\u09a8\u09be"
    ],
    "name:deu_x_preferred":[
        "Cristalina"
    ],
    "name:eml_x_preferred":[
        "Cristalina"
    ],
    "name:epo_x_preferred":[
        "Cristalina"
    ],
    "name:eus_x_preferred":[
        "Cristalina"
    ],
    "name:fra_x_preferred":[
        "Cristalina"
    ],
    "name:hye_x_preferred":[
        "\u053f\u0580\u056b\u057d\u057f\u0561\u056c\u056b\u0576\u0561"
    ],
    "name:ita_x_preferred":[
        "Cristalina"
    ],
    "name:kat_x_preferred":[
        "\u10d9\u10e0\u10d8\u10e1\u10e2\u10d0\u10da\u10d8\u10dc\u10d0"
    ],
    "name:kaz_x_preferred":[
        "\u041a\u0440\u0438\u0441\u0442\u0430\u043b\u0438\u043d\u0430"
    ],
    "name:mlg_x_preferred":[
        "Cristalina"
    ],
    "name:nld_x_preferred":[
        "Cristalina"
    ],
    "name:nor_x_preferred":[
        "Cristalina"
    ],
    "name:por_x_preferred":[
        "Cristalina"
    ],
    "name:ron_x_preferred":[
        "Cristalina"
    ],
    "name:rus_x_preferred":[
        "\u041a\u0440\u0438\u0441\u0442\u0430\u043b\u0438\u043d\u0430"
    ],
    "name:spa_x_preferred":[
        "Cristalina"
    ],
    "name:vie_x_preferred":[
        "Cristalina"
    ],
    "name:vol_x_preferred":[
        "Cristalina"
    ],
    "name:war_x_preferred":[
        "Cristalina"
    ],
    "name:zho_x_preferred":[
        "\u514b\u91cc\u65af\u5854\u5229\u5a1c"
    ],
    "wof:name":"Cristalina",
    "wof:placetype":"locality"
},
  "geometry": {"coordinates":[-75.58333,5.15],"type":"Point"}
}