{
  "type": "Feature",
  "properties": {
    "gn:admin1_code":"9.0",
    "gn:admin2_code":"19785.0",
    "gn:asciiname":"Tachuelo",
    "gn:country_code":"CO",
    "gn:dem":1604,
    "gn:feature_class":"P",
    "gn:feature_code":"PPL",
    "gn:name":"Tachuelo",
    "gn:population":0,
    "gn:timezone":"America/Bogota",
    "iso:country":"CO",
    "wof:name":"Tachuelo",
    "wof:placetype":"locality"
},
  "geometry": {"coordinates":[-76.89928,2.09362],"type":"Point"}
}