{
  "type": "Feature",
  "properties": {
    "gn:admin1_code":"20.0",
    "gn:admin2_code":"52356.0",
    "gn:asciiname":"Barrial",
    "gn:country_code":"CO",
    "gn:dem":2938,
    "gn:feature_class":"P",
    "gn:feature_code":"PPL",
    "gn:name":"Barrial",
    "gn:population":0,
    "gn:timezone":"America/Bogota",
    "iso:country":"CO",
    "wof:name":"Barrial",
    "wof:placetype":"locality"
},
  "geometry": {"coordinates":[-77.66193,0.82565],"type":"Point"}
}