{
  "type": "Feature",
  "properties": {
    "gn:admin1_code":"2",
    "gn:admin2_code":"5790.0",
    "gn:asciiname":"Mala Noche",
    "gn:country_code":"CO",
    "gn:dem":627,
    "gn:feature_class":"P",
    "gn:feature_code":"PPL",
    "gn:name":"Mala Noche",
    "gn:population":0,
    "gn:timezone":"America/Bogota",
    "iso:country":"CO",
    "wof:name":"Mala Noche",
    "wof:placetype":"locality"
},
  "geometry": {"coordinates":[-75.42471,7.39416],"type":"Point"}
}