{
  "type": "Feature",
  "properties": {
    "gn:admin1_code":"2",
    "gn:admin2_code":"5790.0",
    "gn:asciiname":"Mala Noche",
    "gn:country_code":"CO",
    "gn:dem":627,
    "gn:feature_class":"P",
    "gn:feature_code":"PPL",
    "gn:name":"Mala Noche",
    "gn:population":0,
    "gn:timezone":"America/Bogota",
    "iso:country":"CO",
    "name:deu_x_preferred":[
        "Mala Noche"
    ],
    "name:fas_x_preferred":[
        "\u0634\u0628 \u0628\u062f"
    ],
    "name:fra_x_preferred":[
        "Mala Noche"
    ],
    "name:ita_x_preferred":[
        "Mala Noche"
    ],
    "name:jpn_x_preferred":[
        "\u30de\u30e9\u30ce\u30fc\u30c1\u30a7"
    ],
    "name:nld_x_preferred":[
        "Mala Noche"
    ],
    "name:pol_x_preferred":[
        "Mala Noche"
    ],
    "name:rus_x_preferred":[
        "\u0414\u0443\u0440\u043d\u0430\u044f \u043d\u043e\u0447\u044c"
    ],
    "name:spa_x_preferred":[
        "Mala noche"
    ],
    "wof:name":"Mala Noche",
    "wof:placetype":"locality"
},
  "geometry": {"coordinates":[-75.42471,7.39416],"type":"Point"}
}