{
  "type": "Feature",
  "properties": {
    "gn:admin1_code":"28",
    "gn:admin2_code":"73200.0",
    "gn:asciiname":"El Pital",
    "gn:country_code":"CO",
    "gn:dem":770,
    "gn:feature_class":"P",
    "gn:feature_code":"PPL",
    "gn:name":"El Pital",
    "gn:population":0,
    "gn:timezone":"America/Bogota",
    "iso:country":"CO",
    "wof:name":"El Pital",
    "wof:placetype":"locality"
},
  "geometry": {"coordinates":[-74.88333,4.47339],"type":"Point"}
}