{
  "type": "Feature",
  "properties": {
    "gn:admin1_code":"27",
    "gn:admin2_code":"70215.0",
    "gn:asciiname":"Las Penas",
    "gn:country_code":"CO",
    "gn:dem":162,
    "gn:feature_class":"P",
    "gn:feature_code":"PPL",
    "gn:name":"Las Pe\u00f1as",
    "gn:population":0,
    "gn:timezone":"America/Bogota",
    "iso:country":"CO",
    "wof:name":"Las Penas",
    "wof:placetype":"locality"
},
  "geometry": {"coordinates":[-75.27363000000003,9.22605],"type":"Point"}
}