{
  "type": "Feature",
  "properties": {
    "gn:admin1_code":"16",
    "gn:admin2_code":"41524.0",
    "gn:asciiname":"La Cabana",
    "gn:country_code":"CO",
    "gn:dem":613,
    "gn:feature_class":"P",
    "gn:feature_code":"PPL",
    "gn:name":"La Caba\u00f1a",
    "gn:population":0,
    "gn:timezone":"America/Bogota",
    "iso:country":"CO",
    "wof:name":"La Cabana",
    "wof:placetype":"locality"
},
  "geometry": {"coordinates":[-75.40833000000001,3.01361],"type":"Point"}
}