{
  "type": "Feature",
  "properties": {
    "gn:admin1_code":"26",
    "gn:admin2_code":"68524.0",
    "gn:asciiname":"Barro Blanco",
    "gn:country_code":"CO",
    "gn:dem":1173,
    "gn:feature_class":"P",
    "gn:feature_code":"PPL",
    "gn:name":"Barro Blanco",
    "gn:population":0,
    "gn:timezone":"America/Bogota",
    "iso:country":"CO",
    "wof:name":"Barro Blanco",
    "wof:placetype":"locality"
},
  "geometry": {"coordinates":[-73.29544,6.39045],"type":"Point"}
}