{
  "type": "Feature",
  "properties": {
    "gn:admin1_code":"2.0",
    "gn:asciiname":"Quebrada los Trastos",
    "gn:country_code":"CO",
    "gn:dem":338,
    "gn:feature_class":"P",
    "gn:feature_code":"PPL",
    "gn:name":"Quebrada los Trastos",
    "gn:population":0,
    "gn:timezone":"America/Bogota",
    "iso:country":"CO",
    "wof:name":"Quebrada los Trastos",
    "wof:placetype":"locality"
},
  "geometry": {"coordinates":[-74.34999999999999,7.03333],"type":"Point"}
}