{
  "type": "Feature",
  "properties": {
    "gn:admin1_code":"19",
    "gn:admin2_code":"50330.0",
    "gn:asciiname":"El Santuario",
    "gn:country_code":"CO",
    "gn:dem":563,
    "gn:feature_class":"P",
    "gn:feature_code":"PPL",
    "gn:name":"El Santuario",
    "gn:population":0,
    "gn:timezone":"America/Bogota",
    "iso:country":"CO",
    "wof:name":"El Santuario",
    "wof:placetype":"locality"
},
  "geometry": {"coordinates":[-74.04224000000001,3.42942],"type":"Point"}
}