{
  "type": "Feature",
  "properties": {
    "gn:admin1_code":"20.0",
    "gn:admin2_code":"52835.0",
    "gn:asciiname":"La Honda",
    "gn:country_code":"CO",
    "gn:dem":48,
    "gn:feature_class":"P",
    "gn:feature_code":"PPL",
    "gn:name":"La Honda",
    "gn:population":0,
    "gn:timezone":"America/Bogota",
    "iso:country":"CO",
    "name:und_x_variant":[
        "Honda",
        "La Honda"
    ],
    "wof:name":"La Honda",
    "wof:placetype":"locality"
},
  "geometry": {"coordinates":[-78.64114000000002,1.39864],"type":"Point"}
}