{
  "type": "Feature",
  "properties": {
    "gn:admin1_code":"33",
    "gn:admin2_code":"25612.0",
    "gn:asciiname":"El Asilo",
    "gn:country_code":"CO",
    "gn:dem":280,
    "gn:feature_class":"P",
    "gn:feature_code":"PPL",
    "gn:name":"El Asilo",
    "gn:population":0,
    "gn:timezone":"America/Bogota",
    "iso:country":"CO",
    "wof:name":"El Asilo",
    "wof:placetype":"locality"
},
  "geometry": {"coordinates":[-74.74574,4.25453],"type":"Point"}
}