{
  "type": "Feature",
  "properties": {
    "gn:admin1_code":"28",
    "gn:admin2_code":"73555.0",
    "gn:asciiname":"El Espejo",
    "gn:country_code":"CO",
    "gn:dem":1562,
    "gn:feature_class":"P",
    "gn:feature_code":"PPL",
    "gn:name":"El Espejo",
    "gn:population":0,
    "gn:timezone":"America/Bogota",
    "iso:country":"CO",
    "wof:name":"El Espejo",
    "wof:placetype":"locality"
},
  "geometry": {"coordinates":[-75.80639000000002,3.28611],"type":"Point"}
}