{
  "type": "Feature",
  "properties": {
    "gn:admin1_code":"20.0",
    "gn:admin2_code":"52678.0",
    "gn:asciiname":"German",
    "gn:country_code":"CO",
    "gn:dem":3136,
    "gn:feature_class":"P",
    "gn:feature_code":"PPL",
    "gn:name":"Germ\u00e1n",
    "gn:population":0,
    "gn:timezone":"America/Bogota",
    "iso:country":"CO",
    "wof:name":"German",
    "wof:placetype":"locality"
},
  "geometry": {"coordinates":[-77.56910000000001,1.20617],"type":"Point"}
}