{
  "type": "Feature",
  "properties": {
    "gn:admin1_code":"20.0",
    "gn:admin2_code":"52678.0",
    "gn:asciiname":"German",
    "gn:country_code":"CO",
    "gn:dem":3136,
    "gn:feature_class":"P",
    "gn:feature_code":"PPL",
    "gn:name":"Germ\u00e1n",
    "gn:population":0,
    "gn:timezone":"America/Bogota",
    "iso:country":"CO",
    "name:bel_x_preferred":[
        "\u0413\u0435\u0440\u043c\u0430\u043d"
    ],
    "name:bul_x_preferred":[
        "\u0413\u0435\u0440\u043c\u0430\u043d"
    ],
    "name:ceb_x_preferred":[
        "German"
    ],
    "name:ces_x_preferred":[
        "German"
    ],
    "name:deu_x_preferred":[
        "German"
    ],
    "name:est_x_preferred":[
        "German"
    ],
    "name:fra_x_preferred":[
        "German"
    ],
    "name:heb_x_preferred":[
        "\u05d2\u05e8\u05de\u05df"
    ],
    "name:hrv_x_preferred":[
        "German"
    ],
    "name:hun_x_preferred":[
        "Germ\u00e1n"
    ],
    "name:ind_x_preferred":[
        "German"
    ],
    "name:ita_x_preferred":[
        "German"
    ],
    "name:jpn_x_preferred":[
        "\u30b2\u30eb\u30de\u30f3"
    ],
    "name:kan_x_preferred":[
        "\u0c9c\u0cb0\u0ccd\u0cae\u0ca8\u0ccd"
    ],
    "name:mkd_x_preferred":[
        "\u0413\u0435\u0440\u043c\u0430\u043d"
    ],
    "name:pol_x_preferred":[
        "German"
    ],
    "name:rus_x_preferred":[
        "\u0413\u0435\u0440\u043c\u0430\u043d"
    ],
    "name:sco_x_preferred":[
        "German"
    ],
    "name:srp_x_preferred":[
        "\u0413\u0435\u0440\u043c\u0430\u043d"
    ],
    "name:swe_x_preferred":[
        "German"
    ],
    "name:tha_x_preferred":[
        "\u0e40\u0e22\u0e2d\u0e23\u0e21\u0e31\u0e19"
    ],
    "name:ukr_x_preferred":[
        "\u0413\u0435\u0440\u043c\u0430\u043d"
    ],
    "name:vie_x_preferred":[
        "German"
    ],
    "name:zho_x_preferred":[
        "\u65e5\u8033\u66fc"
    ],
    "wof:name":"German",
    "wof:placetype":"locality"
},
  "geometry": {"coordinates":[-77.56910000000001,1.20617],"type":"Point"}
}