{
  "type": "Feature",
  "properties": {
    "gn:admin1_code":"17",
    "gn:admin2_code":"44430.0",
    "gn:asciiname":"El Sucre",
    "gn:country_code":"CO",
    "gn:dem":94,
    "gn:feature_class":"P",
    "gn:feature_code":"PPL",
    "gn:name":"El Sucre",
    "gn:population":0,
    "gn:timezone":"America/Bogota",
    "iso:country":"CO",
    "wof:name":"El Sucre",
    "wof:placetype":"locality"
},
  "geometry": {"coordinates":[-72.36667,11.31667],"type":"Point"}
}