{
  "type": "Feature",
  "properties": {
    "gn:admin1_code":"36",
    "gn:admin2_code":"15572.0",
    "gn:asciiname":"Los Limones",
    "gn:country_code":"CO",
    "gn:dem":187,
    "gn:feature_class":"P",
    "gn:feature_code":"PPL",
    "gn:name":"Los Limones",
    "gn:population":0,
    "gn:timezone":"America/Bogota",
    "iso:country":"CO",
    "wof:name":"Los Limones",
    "wof:placetype":"locality"
},
  "geometry": {"coordinates":[-74.4528,5.77041],"type":"Point"}
}