{
  "type": "Feature",
  "properties": {
    "gn:admin1_code":"17",
    "gn:admin2_code":"44430.0",
    "gn:asciiname":"Manaramahana",
    "gn:country_code":"CO",
    "gn:dem":15,
    "gn:feature_class":"P",
    "gn:feature_code":"PPL",
    "gn:name":"Ma\u00f1aramahana",
    "gn:population":0,
    "gn:timezone":"America/Bogota",
    "iso:country":"CO",
    "wof:name":"Manaramahana",
    "wof:placetype":"locality"
},
  "geometry": {"coordinates":[-72.08443,11.45497],"type":"Point"}
}