{
  "type": "Feature",
  "properties": {
    "gn:admin1_code":"19.0",
    "gn:admin2_code":"50400.0",
    "gn:asciiname":"Barcelona",
    "gn:country_code":"CO",
    "gn:dem":665,
    "gn:feature_class":"P",
    "gn:feature_code":"PPL",
    "gn:name":"Barcelona",
    "gn:population":0,
    "gn:timezone":"America/Bogota",
    "iso:country":"CO",
    "name:spa_x_preferred":[
        "Barcelona"
    ],
    "wof:name":"Barcelona",
    "wof:placetype":"locality"
},
  "geometry": {"coordinates":[-74.00024000000001,3.53685],"type":"Point"}
}