{
  "type": "Feature",
  "properties": {
    "iso:country":"CO",
    "name:ara_x_preferred":[
        "\u0641\u0627\u0644\u0628\u0627\u0631\u0627\u064a\u0633\u0648"
    ],
    "name:ast_x_preferred":[
        "Valpara\u00edso"
    ],
    "name:ceb_x_preferred":[
        "Valpara\u00edso"
    ],
    "name:eng_x_preferred":[
        "Valpara\u00edso"
    ],
    "name:fra_x_preferred":[
        "Valpara\u00edso"
    ],
    "name:ita_x_preferred":[
        "Valpara\u00edso"
    ],
    "name:jpn_x_preferred":[
        "\u30d0\u30eb\u30d1\u30e9\u30a4\u30bd"
    ],
    "name:msa_x_preferred":[
        "Valpara\u00edso"
    ],
    "name:nan_x_preferred":[
        "Valpara\u00edso"
    ],
    "name:nld_x_preferred":[
        "Valpara\u00edso"
    ],
    "name:por_x_preferred":[
        "Valpara\u00edso"
    ],
    "name:spa_x_preferred":[
        "Valpara\u00edso"
    ],
    "name:swe_x_preferred":[
        "Valpara\u00edso"
    ],
    "name:tgl_x_preferred":[
        "Valpara\u00edso"
    ],
    "name:war_x_preferred":[
        "Valpara\u00edso"
    ],
    "name:zho_x_preferred":[
        "\u74e6\u723e\u5e15\u840a\u7d22"
    ],
    "qs:gn_country":"CO",
    "qs:gn_fcode":"PPL",
    "qs:gn_pop":3767,
    "qs:name":"Valpara\u00edso",
    "qs:name_adm0":"Colombia",
    "qs:name_adm1":"Caqueta",
    "qs:photos":0,
    "qs:photos_1k":0,
    "qs:photos_9k":0,
    "qs:photos_9r":0,
    "qs:photos_all":0,
    "qs:photos_sr":0,
    "qs:placetype":"Town",
    "qs:pop_sr":"4",
    "qs:woe_adm0":23424787,
    "wd:wordcount":37,
    "wof:name":"Valpara\u00edso",
    "wof:placetype":"locality",
    "wof:population":3767
},
  "geometry": {"coordinates":[-75.70705,1.19512],"type":"Point"}
}