{
  "type": "Feature",
  "properties": {
    "gn:admin1_code":"3",
    "gn:admin2_code":"81794.0",
    "gn:asciiname":"Macaguan",
    "gn:country_code":"CO",
    "gn:dem":259,
    "gn:feature_class":"P",
    "gn:feature_code":"PPL",
    "gn:name":"Macagu\u00e1n",
    "gn:population":0,
    "gn:timezone":"America/Bogota",
    "iso:country":"CO",
    "name:spa_x_preferred":[
        "Macaguan"
    ],
    "name:und_x_variant":[
        "Caserio Macagu\u00e1n",
        "Macaguane",
        "Macaguana",
        "Macagu\u00e1n"
    ],
    "wof:name":"Macaguan",
    "wof:placetype":"locality"
},
  "geometry": {"coordinates":[-71.72434,6.5668],"type":"Point"}
}