{
  "type": "Feature",
  "properties": {
    "gn:admin1_code":"19.0",
    "gn:admin2_code":"50325.0",
    "gn:asciiname":"Araracuara",
    "gn:country_code":"CO",
    "gn:dem":181,
    "gn:feature_class":"P",
    "gn:feature_code":"PPL",
    "gn:name":"Araracuara",
    "gn:population":0,
    "gn:timezone":"America/Bogota",
    "iso:country":"CO",
    "name:spa_x_preferred":[
        "Araracuara"
    ],
    "wof:name":"Araracuara",
    "wof:placetype":"locality"
},
  "geometry": {"coordinates":[-71.86591999999997,2.86269],"type":"Point"}
}