{
  "type": "Feature",
  "properties": {
    "gn:admin1_code":"38",
    "gn:admin2_code":"47058.0",
    "gn:asciiname":"El Parejo",
    "gn:country_code":"CO",
    "gn:dem":120,
    "gn:feature_class":"P",
    "gn:feature_code":"PPL",
    "gn:name":"El Parejo",
    "gn:population":0,
    "gn:timezone":"America/Bogota",
    "iso:country":"CO",
    "wof:name":"El Parejo",
    "wof:placetype":"locality"
},
  "geometry": {"coordinates":[-74.08346,9.83574],"type":"Point"}
}