{
  "type": "Feature",
  "properties": {
    "gn:admin1_code":"26",
    "gn:admin2_code":"68575.0",
    "gn:asciiname":"Kilometro 20",
    "gn:country_code":"CO",
    "gn:dem":101,
    "gn:feature_class":"P",
    "gn:feature_code":"PPL",
    "gn:name":"Kil\u00f3metro 20",
    "gn:population":0,
    "gn:timezone":"America/Bogota",
    "iso:country":"CO",
    "name:und_x_variant":[
        "Los Comuneros",
        "Corregimiento Kil\u00f3metro 20",
        "Kil\u00f3metro 20"
    ],
    "wof:name":"Kilometro 20",
    "wof:placetype":"locality"
},
  "geometry": {"coordinates":[-73.73444000000001,7.32889],"type":"Point"}
}