{
  "type": "Feature",
  "properties": {
    "gn:admin1_code":"2",
    "gn:admin2_code":"5854.0",
    "gn:asciiname":"Canarias",
    "gn:country_code":"CO",
    "gn:dem":110,
    "gn:feature_class":"P",
    "gn:feature_code":"PPL",
    "gn:name":"Canarias",
    "gn:population":0,
    "gn:timezone":"America/Bogota",
    "iso:country":"CO",
    "wof:name":"Canarias",
    "wof:placetype":"locality"
},
  "geometry": {"coordinates":[-75.30571999999999,7.40671],"type":"Point"}
}