{
  "type": "Feature",
  "properties": {
    "gn:admin1_code":"19",
    "gn:admin2_code":"50270",
    "gn:asciiname":"La Orquidea",
    "gn:country_code":"CO",
    "gn:dem":614,
    "gn:feature_class":"P",
    "gn:feature_code":"PPL",
    "gn:name":"La Orquidea",
    "gn:population":0,
    "gn:timezone":"America/Bogota",
    "iso:country":"CO",
    "name:spa_x_preferred":[
        "La Orquidea"
    ],
    "wof:name":"La Orquidea",
    "wof:placetype":"locality"
},
  "geometry": {"coordinates":[-73.84296999999999,3.73813],"type":"Point"}
}