{
  "type": "Feature",
  "properties": {
    "gn:admin1_code":"23",
    "gn:asciiname":"Tunidad",
    "gn:country_code":"CO",
    "gn:dem":1362,
    "gn:feature_class":"P",
    "gn:feature_code":"PPL",
    "gn:name":"Tunidad",
    "gn:population":0,
    "gn:timezone":"America/Bogota",
    "iso:country":"CO",
    "wof:name":"Tunidad",
    "wof:placetype":"locality"
},
  "geometry": {"coordinates":[-75.82361,4.21444],"type":"Point"}
}