{
  "type": "Feature",
  "properties": {
    "gn:admin1_code":"29.0",
    "gn:admin2_code":"76113.0",
    "gn:asciiname":"La Palestina",
    "gn:country_code":"CO",
    "gn:dem":936,
    "gn:feature_class":"P",
    "gn:feature_code":"PPL",
    "gn:name":"La Palestina",
    "gn:population":0,
    "gn:timezone":"America/Bogota",
    "iso:country":"CO",
    "wof:name":"La Palestina",
    "wof:placetype":"locality"
},
  "geometry": {"coordinates":[-76.19167,4.20278],"type":"Point"}
}