{
  "type": "Feature",
  "properties": {
    "gn:admin1_code":"38",
    "gn:admin2_code":"47258.0",
    "gn:asciiname":"La Angostura",
    "gn:cc2":"CO",
    "gn:country_code":"CO",
    "gn:dem":8,
    "gn:feature_class":"P",
    "gn:feature_code":"PPL",
    "gn:name":"La Angostura",
    "gn:population":0,
    "gn:timezone":"America/Bogota",
    "iso:country":"CO",
    "name:und_x_variant":[
        "Angostura",
        "La Angostura"
    ],
    "wof:name":"La Angostura",
    "wof:placetype":"locality"
},
  "geometry": {"coordinates":[-74.63333,10.43333],"type":"Point"}
}