{
  "type": "Feature",
  "properties": {
    "gn:admin1_code":"2",
    "gn:admin2_code":"5667.0",
    "gn:asciiname":"Bizcocho",
    "gn:country_code":"CO",
    "gn:dem":1060,
    "gn:feature_class":"P",
    "gn:feature_code":"PPL",
    "gn:name":"Bizcocho",
    "gn:population":0,
    "gn:timezone":"America/Bogota",
    "iso:country":"CO",
    "name:spa_x_preferred":[
        "Bizcocho"
    ],
    "wof:name":"Bizcocho",
    "wof:placetype":"locality"
},
  "geometry": {"coordinates":[-75.07583000000002,6.30707],"type":"Point"}
}