{
  "type": "Feature",
  "properties": {
    "gn:admin1_code":"16.0",
    "gn:asciiname":"Buitrera",
    "gn:country_code":"CO",
    "gn:dem":1180,
    "gn:feature_class":"P",
    "gn:feature_code":"PPL",
    "gn:name":"Buitrera",
    "gn:population":0,
    "gn:timezone":"America/Bogota",
    "iso:country":"CO",
    "name:spa_x_preferred":[
        "Buitrera"
    ],
    "wof:name":"Buitrera",
    "wof:placetype":"locality"
},
  "geometry": {"coordinates":[-74.99944000000001,3.40761],"type":"Point"}
}