{
  "type": "Feature",
  "properties": {
    "gn:admin1_code":"2.0",
    "gn:admin2_code":"5607.0",
    "gn:asciiname":"Holanda",
    "gn:country_code":"CO",
    "gn:dem":2712,
    "gn:feature_class":"P",
    "gn:feature_code":"PPL",
    "gn:name":"Holanda",
    "gn:population":0,
    "gn:timezone":"America/Bogota",
    "iso:country":"CO",
    "name:spa_x_preferred":[
        "Holanda"
    ],
    "wof:name":"Holanda",
    "wof:placetype":"locality"
},
  "geometry": {"coordinates":[-75.57975999999999,6.07447],"type":"Point"}
}