{
  "type": "Feature",
  "properties": {
    "gn:admin1_code":"33.0",
    "gn:admin2_code":"25151.0",
    "gn:asciiname":"Alto del Rodadero",
    "gn:country_code":"CO",
    "gn:dem":2626,
    "gn:feature_class":"P",
    "gn:feature_code":"PPL",
    "gn:name":"Alto del Rodadero",
    "gn:population":0,
    "gn:timezone":"America/Bogota",
    "iso:country":"CO",
    "name:spa_x_preferred":[
        "Alto del Rodadero"
    ],
    "wof:name":"Alto del Rodadero",
    "wof:placetype":"locality"
},
  "geometry": {"coordinates":[-73.96734000000002,4.45725],"type":"Point"}
}