{
  "type": "Feature",
  "properties": {
    "gn:admin1_code":"19.0",
    "gn:admin2_code":"50006.0",
    "gn:asciiname":"Fresco Valle",
    "gn:country_code":"CO",
    "gn:dem":1020,
    "gn:feature_class":"P",
    "gn:feature_code":"PPL",
    "gn:name":"Fresco Valle",
    "gn:population":0,
    "gn:timezone":"America/Bogota",
    "iso:country":"CO",
    "wof:name":"Fresco Valle",
    "wof:placetype":"locality"
},
  "geometry": {"coordinates":[-73.83223000000002,3.97009],"type":"Point"}
}