{
  "type": "Feature",
  "properties": {
    "gn:admin1_code":"12.0",
    "gn:admin2_code":"23574.0",
    "gn:asciiname":"Villa Esther",
    "gn:country_code":"CO",
    "gn:dem":77,
    "gn:feature_class":"P",
    "gn:feature_code":"PPL",
    "gn:name":"Villa Esther",
    "gn:population":0,
    "gn:timezone":"America/Bogota",
    "iso:country":"CO",
    "wof:name":"Villa Esther",
    "wof:placetype":"locality"
},
  "geometry": {"coordinates":[-76.12524999999999,9.06308],"type":"Point"}
}