{
  "type": "Feature",
  "properties": {
    "gn:admin1_code":"32",
    "gn:admin2_code":"85250.0",
    "gn:asciiname":"Hato el Milagro",
    "gn:country_code":"CO",
    "gn:dem":154,
    "gn:feature_class":"P",
    "gn:feature_code":"PPL",
    "gn:name":"Hato el Milagro",
    "gn:population":0,
    "gn:timezone":"America/Bogota",
    "iso:country":"CO",
    "wof:name":"Hato el Milagro",
    "wof:placetype":"locality"
},
  "geometry": {"coordinates":[-71.43933,5.52013],"type":"Point"}
}