{
  "type": "Feature",
  "properties": {
    "gn:admin1_code":"33",
    "gn:admin2_code":"25843.0",
    "gn:asciiname":"Guatancuy",
    "gn:country_code":"CO",
    "gn:dem":2546,
    "gn:feature_class":"P",
    "gn:feature_code":"PPL",
    "gn:name":"Guatancuy",
    "gn:population":0,
    "gn:timezone":"America/Bogota",
    "iso:country":"CO",
    "wof:name":"Guatancuy",
    "wof:placetype":"locality"
},
  "geometry": {"coordinates":[-73.79089999999999,5.34865],"type":"Point"}
}