{
  "type": "Feature",
  "properties": {
    "iso:country":"CO",
    "name:ceb_x_preferred":[
        "G\u00fcic\u00e1n"
    ],
    "name:eng_x_preferred":[
        "G\u00fcic\u00e1n"
    ],
    "name:fra_x_preferred":[
        "G\u00fcic\u00e1n"
    ],
    "name:gla_x_preferred":[
        "G\u00fcic\u00e1n"
    ],
    "name:ita_x_preferred":[
        "G\u00fcic\u00e1n"
    ],
    "name:kat_x_preferred":[
        "\u10d2\u10e3\u10d8\u10d9\u10d0\u10dc\u10d8"
    ],
    "name:msa_x_preferred":[
        "G\u00fcic\u00e1n"
    ],
    "name:nan_x_preferred":[
        "G\u00fcic\u00e1n"
    ],
    "name:nld_x_preferred":[
        "G\u00fcic\u00e1n"
    ],
    "name:por_x_preferred":[
        "G\u00fcic\u00e1n"
    ],
    "name:spa_x_preferred":[
        "G\u00fcic\u00e1n"
    ],
    "name:swe_x_preferred":[
        "G\u00fcic\u00e1n"
    ],
    "name:tgl_x_preferred":[
        "G\u00fcic\u00e1n"
    ],
    "name:vie_x_preferred":[
        "G\u00fcic\u00e1n"
    ],
    "name:war_x_preferred":[
        "G\u00fcic\u00e1n"
    ],
    "name:zho_x_preferred":[
        "\u572d\u574e"
    ],
    "qs:gn_country":"CO",
    "qs:gn_fcode":"PPL",
    "qs:gn_pop":2101,
    "qs:name":"G\u00fcic\u00e1n",
    "qs:name_adm0":"Colombia",
    "qs:name_adm1":"Boyaca",
    "qs:photos":113,
    "qs:photos_1k":23,
    "qs:photos_9k":1,
    "qs:photos_9r":3,
    "qs:photos_all":113,
    "qs:photos_sr":3,
    "qs:placetype":"Town",
    "qs:pop_sr":"4",
    "qs:woe_adm0":23424787,
    "wd:wordcount":68,
    "wof:name":"G\u00fcic\u00e1n",
    "wof:placetype":"locality",
    "wof:population":2101
},
  "geometry": {"coordinates":[-72.41128999999999,6.46184],"type":"Point"}
}