{
  "type": "Feature",
  "properties": {
    "gn:admin1_code":"16",
    "gn:admin2_code":"41797.0",
    "gn:asciiname":"Ambica",
    "gn:country_code":"CO",
    "gn:dem":880,
    "gn:feature_class":"P",
    "gn:feature_code":"PPL",
    "gn:name":"Ambica",
    "gn:population":0,
    "gn:timezone":"America/Bogota",
    "iso:country":"CO",
    "wof:name":"Ambica",
    "wof:placetype":"locality"
},
  "geometry": {"coordinates":[-75.66346999999998,2.58577],"type":"Point"}
}