{
  "type": "Feature",
  "properties": {
    "gn:admin1_code":"19",
    "gn:admin2_code":"50573.0",
    "gn:asciiname":"Las Brisas",
    "gn:country_code":"CO",
    "gn:dem":173,
    "gn:feature_class":"P",
    "gn:feature_code":"PPL",
    "gn:name":"Las Brisas",
    "gn:population":0,
    "gn:timezone":"America/Bogota",
    "iso:country":"CO",
    "wof:name":"Las Brisas",
    "wof:placetype":"locality"
},
  "geometry": {"coordinates":[-72.15666999999998,4.41056],"type":"Point"}
}