{
  "type": "Feature",
  "properties": {
    "gn:admin1_code":"2.0",
    "gn:admin2_code":"5490.0",
    "gn:asciiname":"Sevilla",
    "gn:country_code":"CO",
    "gn:dem":60,
    "gn:feature_class":"P",
    "gn:feature_code":"PPL",
    "gn:name":"Sevilla",
    "gn:population":0,
    "gn:timezone":"America/Bogota",
    "iso:country":"CO",
    "name:spa_x_preferred":[
        "Sevilla"
    ],
    "wof:name":"Sevilla",
    "wof:placetype":"locality"
},
  "geometry": {"coordinates":[-76.6621,8.43896],"type":"Point"}
}