{
  "type": "Feature",
  "properties": {
    "gn:admin1_code":"1",
    "gn:admin2_code":"91530.0",
    "gn:asciiname":"Itiquilla",
    "gn:country_code":"CO",
    "gn:dem":149,
    "gn:feature_class":"P",
    "gn:feature_code":"PPL",
    "gn:name":"Itiquilla",
    "gn:population":0,
    "gn:timezone":"America/Bogota",
    "iso:country":"CO",
    "wof:name":"Itiquilla",
    "wof:placetype":"locality"
},
  "geometry": {"coordinates":[-73.6763,-1.23541],"type":"Point"}
}