{
  "type": "Feature",
  "properties": {
    "gn:admin1_code":"26",
    "gn:admin2_code":"68077.0",
    "gn:asciiname":"Cite",
    "gn:country_code":"CO",
    "gn:dem":1598,
    "gn:feature_class":"P",
    "gn:feature_code":"PPL",
    "gn:name":"Cite",
    "gn:population":0,
    "gn:timezone":"America/Bogota",
    "iso:country":"CO",
    "wof:name":"Cite",
    "wof:placetype":"locality"
},
  "geometry": {"coordinates":[-73.60287,5.96466],"type":"Point"}
}