{
  "type": "Feature",
  "properties": {
    "gn:admin1_code":"9",
    "gn:admin2_code":"19548.0",
    "gn:asciiname":"El Hogar",
    "gn:country_code":"CO",
    "gn:dem":1695,
    "gn:feature_class":"P",
    "gn:feature_code":"PPL",
    "gn:name":"El Hogar",
    "gn:population":0,
    "gn:timezone":"America/Bogota",
    "iso:country":"CO",
    "wof:name":"El Hogar",
    "wof:placetype":"locality"
},
  "geometry": {"coordinates":[-76.53995999999999,2.71221],"type":"Point"}
}