{
  "type": "Feature",
  "properties": {
    "gn:admin1_code":"9",
    "gn:admin2_code":"19001.0",
    "gn:asciiname":"Cesteadero",
    "gn:country_code":"CO",
    "gn:dem":1640,
    "gn:feature_class":"P",
    "gn:feature_code":"PPL",
    "gn:name":"Cesteadero",
    "gn:population":0,
    "gn:timezone":"America/Bogota",
    "iso:country":"CO",
    "wof:name":"Cesteadero",
    "wof:placetype":"locality"
},
  "geometry": {"coordinates":[-76.7381,2.55156],"type":"Point"}
}