{
  "type": "Feature",
  "properties": {
    "gn:admin1_code":"20.0",
    "gn:admin2_code":"52001.0",
    "gn:asciiname":"Villa Loma",
    "gn:country_code":"CO",
    "gn:dem":3129,
    "gn:feature_class":"P",
    "gn:feature_code":"PPL",
    "gn:name":"Villa Loma",
    "gn:population":0,
    "gn:timezone":"America/Bogota",
    "iso:country":"CO",
    "wof:name":"Villa Loma",
    "wof:placetype":"locality"
},
  "geometry": {"coordinates":[-77.26033000000002,1.09201],"type":"Point"}
}