{
  "type": "Feature",
  "properties": {
    "gn:admin1_code":"2",
    "gn:admin2_code":"5670.0",
    "gn:asciiname":"La Chinca",
    "gn:country_code":"CO",
    "gn:dem":818,
    "gn:feature_class":"P",
    "gn:feature_code":"PPL",
    "gn:name":"La Chinca",
    "gn:population":0,
    "gn:timezone":"America/Bogota",
    "iso:country":"CO",
    "wof:name":"La Chinca",
    "wof:placetype":"locality"
},
  "geometry": {"coordinates":[-74.84056,6.46444],"type":"Point"}
}