{
  "type": "Feature",
  "properties": {
    "gn:admin1_code":"2",
    "gn:admin2_code":"5579.0",
    "gn:asciiname":"El Recreo",
    "gn:country_code":"CO",
    "gn:dem":609,
    "gn:feature_class":"P",
    "gn:feature_code":"PPL",
    "gn:name":"El Recreo",
    "gn:population":0,
    "gn:timezone":"America/Bogota",
    "iso:country":"CO",
    "wof:name":"El Recreo",
    "wof:placetype":"locality"
},
  "geometry": {"coordinates":[-74.6725,6.35028],"type":"Point"}
}