{
  "type": "Feature",
  "properties": {
    "gn:admin1_code":"38.0",
    "gn:admin2_code":"47745.0",
    "gn:asciiname":"La Lucha",
    "gn:country_code":"CO",
    "gn:dem":4,
    "gn:feature_class":"P",
    "gn:feature_code":"PPL",
    "gn:name":"La Lucha",
    "gn:population":0,
    "gn:timezone":"America/Bogota",
    "iso:country":"CO",
    "wof:name":"La Lucha",
    "wof:placetype":"locality"
},
  "geometry": {"coordinates":[-74.75655,10.99224],"type":"Point"}
}