{
  "type": "Feature",
  "properties": {
    "gn:admin1_code":"33.0",
    "gn:admin2_code":"25175.0",
    "gn:asciiname":"Puente del Comun",
    "gn:cc2":"CO",
    "gn:country_code":"CO",
    "gn:dem":2545,
    "gn:feature_class":"P",
    "gn:feature_code":"PPL",
    "gn:name":"Puente del Com\u00fan",
    "gn:population":0,
    "gn:timezone":"America/Bogota",
    "iso:country":"CO",
    "name:und_x_variant":[
        "Puente del Com\u00edn",
        "Puente del Com\u00fan"
    ],
    "wof:name":"Puente del Comun",
    "wof:placetype":"locality"
},
  "geometry": {"coordinates":[-74.03333000000001,4.86667],"type":"Point"}
}