{
  "type": "Feature",
  "properties": {
    "gn:admin1_code":"36.0",
    "gn:admin2_code":"15223.0",
    "gn:asciiname":"Tecauca",
    "gn:country_code":"CO",
    "gn:dem":995,
    "gn:feature_class":"P",
    "gn:feature_code":"PPL",
    "gn:name":"Tecauca",
    "gn:population":0,
    "gn:timezone":"America/Bogota",
    "iso:country":"CO",
    "wof:name":"Tecauca",
    "wof:placetype":"locality"
},
  "geometry": {"coordinates":[-72.13333,6.86667],"type":"Point"}
}