{
  "type": "Feature",
  "properties": {
    "iso:country":"CO",
    "name:ceb_x_preferred":[
        "Sitionuevo"
    ],
    "name:eng_x_preferred":[
        "Sitionuevo"
    ],
    "name:fas_x_preferred":[
        "\u0633\u06cc\u062a\u06cc\u0648\u0646\u0648\u0626\u0648\u0648"
    ],
    "name:fra_x_preferred":[
        "Sitionuevo"
    ],
    "name:ita_x_preferred":[
        "Sitionuevo"
    ],
    "name:kat_x_preferred":[
        "\u10e1\u10d8\u10e2\u10d8\u10dd\u10dc\u10e3\u10d4\u10d5\u10dd"
    ],
    "name:msa_x_preferred":[
        "Sitionuevo"
    ],
    "name:nan_x_preferred":[
        "Sitionuevo"
    ],
    "name:nld_x_preferred":[
        "Sitionuevo"
    ],
    "name:por_x_preferred":[
        "Sitionuevo"
    ],
    "name:sco_x_preferred":[
        "Sitionuevo"
    ],
    "name:spa_x_preferred":[
        "Sitionuevo"
    ],
    "name:swe_x_preferred":[
        "Sitionuevo"
    ],
    "name:tgl_x_preferred":[
        "Sitionuevo"
    ],
    "name:vie_x_preferred":[
        "Sitionuevo"
    ],
    "name:war_x_preferred":[
        "Sitio Nuevo"
    ],
    "name:zho_min_nan_x_preferred":[
        "Sitionuevo"
    ],
    "name:zho_x_preferred":[
        "\u932b\u8482\u5967\u52aa\u57c3\u6c83"
    ],
    "qs:gn_country":"CO",
    "qs:gn_fcode":"PPL",
    "qs:gn_pop":11817,
    "qs:name":"Sitionuevo",
    "qs:name_adm0":"Colombia",
    "qs:name_adm1":"Magdalena",
    "qs:photos":0,
    "qs:photos_1k":0,
    "qs:photos_9k":0,
    "qs:photos_9r":0,
    "qs:photos_all":0,
    "qs:photos_sr":0,
    "qs:placetype":"Town",
    "qs:pop_sr":"6",
    "qs:woe_adm0":23424787,
    "wd:wordcount":46,
    "wof:name":"Sitionuevo",
    "wof:placetype":"locality",
    "wof:population":11817
},
  "geometry": {"coordinates":[-74.72049,10.77737],"type":"Point"}
}