{
  "type": "Feature",
  "properties": {
    "gn:admin1_code":"9",
    "gn:admin2_code":"19130.0",
    "gn:asciiname":"El Caimito",
    "gn:country_code":"CO",
    "gn:dem":1741,
    "gn:feature_class":"P",
    "gn:feature_code":"PPL",
    "gn:name":"El Caimito",
    "gn:population":0,
    "gn:timezone":"America/Bogota",
    "iso:country":"CO",
    "wof:name":"El Caimito",
    "wof:placetype":"locality"
},
  "geometry": {"coordinates":[-76.79148000000001,2.69274],"type":"Point"}
}