{
  "type": "Feature",
  "properties": {
    "gn:admin1_code":"36",
    "gn:admin2_code":"15740.0",
    "gn:asciiname":"El Cairo",
    "gn:country_code":"CO",
    "gn:dem":2751,
    "gn:feature_class":"P",
    "gn:feature_code":"PPL",
    "gn:name":"El Cairo",
    "gn:population":0,
    "gn:timezone":"America/Bogota",
    "iso:country":"CO",
    "wof:name":"El Cairo",
    "wof:placetype":"locality"
},
  "geometry": {"coordinates":[-73.22604,5.54478],"type":"Point"}
}