{
  "type": "Feature",
  "properties": {
    "gn:admin1_code":"20",
    "gn:admin2_code":"52233.0",
    "gn:asciiname":"Nulpi",
    "gn:country_code":"CO",
    "gn:dem":452,
    "gn:feature_class":"P",
    "gn:feature_code":"PPL",
    "gn:name":"Nulpi",
    "gn:population":0,
    "gn:timezone":"America/Bogota",
    "iso:country":"CO",
    "wof:name":"Nulpi",
    "wof:placetype":"locality"
},
  "geometry": {"coordinates":[-77.48000999999999,1.61193],"type":"Point"}
}