{
  "type": "Feature",
  "properties": {
    "gn:admin1_code":"36",
    "gn:admin2_code":"15572.0",
    "gn:asciiname":"El Balsamo",
    "gn:country_code":"CO",
    "gn:dem":233,
    "gn:feature_class":"P",
    "gn:feature_code":"PPL",
    "gn:name":"El B\u00e1lsamo",
    "gn:population":0,
    "gn:timezone":"America/Bogota",
    "iso:country":"CO",
    "wof:name":"El Balsamo",
    "wof:placetype":"locality"
},
  "geometry": {"coordinates":[-74.36028,5.81167],"type":"Point"}
}