{
  "type": "Feature",
  "properties": {
    "gn:admin1_code":"2.0",
    "gn:admin2_code":"5380.0",
    "gn:asciiname":"Florerrcia",
    "gn:country_code":"CO",
    "gn:dem":1667,
    "gn:feature_class":"P",
    "gn:feature_code":"PPL",
    "gn:name":"Florerrcia",
    "gn:population":0,
    "gn:timezone":"America/Bogota",
    "iso:country":"CO",
    "name:spa_x_preferred":[
        "Florerrcia"
    ],
    "wof:name":"Florerrcia",
    "wof:placetype":"locality"
},
  "geometry": {"coordinates":[-75.63358000000002,6.14201],"type":"Point"}
}