{
  "type": "Feature",
  "properties": {
    "gn:admin1_code":"36.0",
    "gn:admin2_code":"15180.0",
    "gn:asciiname":"Mendez",
    "gn:cc2":"CO",
    "gn:country_code":"CO",
    "gn:dem":3657,
    "gn:feature_class":"P",
    "gn:feature_code":"PPL",
    "gn:name":"M\u00e9ndez",
    "gn:population":0,
    "gn:timezone":"America/Bogota",
    "iso:country":"CO",
    "name:und_x_variant":[
        "Mendes",
        "M\u00e9ndez"
    ],
    "wof:name":"Mendez",
    "wof:placetype":"locality"
},
  "geometry": {"coordinates":[-72.33333,6.73333],"type":"Point"}
}