{
  "type": "Feature",
  "properties": {
    "gn:admin1_code":"34.0",
    "gn:admin2_code":"11001.0",
    "gn:admin3_code":"1.0",
    "gn:asciiname":"San Carlos",
    "gn:country_code":"CO",
    "gn:dem":2554,
    "gn:feature_class":"P",
    "gn:feature_code":"PPL",
    "gn:name":"San Carlos",
    "gn:population":0,
    "gn:timezone":"America/Bogota",
    "iso:country":"CO",
    "wof:name":"San Carlos",
    "wof:placetype":"locality"
},
  "geometry": {"coordinates":[-74.03959999999999,4.7693],"type":"Point"}
}