{
  "type": "Feature",
  "properties": {
    "gn:admin1_code":"33.0",
    "gn:admin2_code":"25599.0",
    "gn:asciiname":"Vereda Cachimbulo",
    "gn:country_code":"CO",
    "gn:dem":580,
    "gn:feature_class":"P",
    "gn:feature_code":"PPLL",
    "gn:name":"Vereda Cachimbulo",
    "gn:population":0,
    "gn:timezone":"America/Bogota",
    "iso:country":"CO",
    "name:spa_x_preferred":[
        "Vereda Cachimbulo"
    ],
    "wof:name":"Vereda Cachimbulo",
    "wof:placetype":"locality"
},
  "geometry": {"coordinates":[-74.57059,4.45925],"type":"Point"}
}