{
  "type": "Feature",
  "properties": {
    "gn:country":"CO",
    "gn:fcode":"PPL",
    "gn:population":4339,
    "iso:country":"CO",
    "name:ast_x_preferred":[
        "Buenavista"
    ],
    "name:cat_x_preferred":[
        "Buenavista"
    ],
    "name:ceb_x_preferred":[
        "Buenavista"
    ],
    "name:deu_x_preferred":[
        "Buenavista"
    ],
    "name:eng_x_preferred":[
        "Buenavista"
    ],
    "name:epo_x_preferred":[
        "Buenavista"
    ],
    "name:eus_x_preferred":[
        "Buenavista"
    ],
    "name:fra_x_preferred":[
        "Buenavista"
    ],
    "name:glg_x_preferred":[
        "Buenavista"
    ],
    "name:ilo_x_preferred":[
        "Buenavista"
    ],
    "name:ita_x_preferred":[
        "Buenavista"
    ],
    "name:nld_x_preferred":[
        "Buenavista"
    ],
    "name:por_x_preferred":[
        "Buenavista"
    ],
    "name:rus_x_preferred":[
        "\u0411\u0443\u044d\u043d\u0430\u0432\u0438\u0441\u0442\u0430"
    ],
    "name:spa_x_preferred":[
        "Buenavista"
    ],
    "name:srp_x_preferred":[
        "\u0411\u0443\u0435\u043d\u0430\u0432\u0438\u0441\u0442\u0430"
    ],
    "name:swe_x_preferred":[
        "Buenavista"
    ],
    "name:ukr_x_preferred":[
        "\u0411\u0443\u0435\u043d\u0430\u0432\u0456\u0441\u0442\u0430"
    ],
    "name:und_x_variant":[
        "San Zen\u00f3n"
    ],
    "name:vie_x_preferred":[
        "Buenavista"
    ],
    "name:war_x_preferred":[
        "Buenavista"
    ],
    "qs:name":"Buenavista",
    "qs:photos_9r":0,
    "qs:photos_sr":0,
    "qs:pop_sr":"4",
    "wd:wordcount":166,
    "wof:name":"Buenavista",
    "wof:placetype":"locality",
    "wof:population":4339
},
  "geometry": {"coordinates":[-74.31363,9.21433],"type":"Point"}
}