{
  "type": "Feature",
  "properties": {
    "gn:country":"CO",
    "gn:fcode":"PPL",
    "gn:pop":4339,
    "iso:country":"CO",
    "name:unk_x_variant":[
        "San Zen\u00f3n"
    ],
    "qs:name":"Buenavista",
    "qs:photos_9r":0,
    "qs:photos_sr":0,
    "qs:pop_sr":"4",
    "wd:wordcount":166,
    "wof:name":"Buenavista",
    "wof:placetype":"locality",
    "wof:population":4339
},
  "geometry": {"coordinates":[-74.31363,9.21433],"type":"Point"}
}