{
  "type": "Feature",
  "properties": {
    "gn:admin1_code":"20",
    "gn:admin2_code":"52540.0",
    "gn:asciiname":"Castigo",
    "gn:country_code":"CO",
    "gn:dem":806,
    "gn:feature_class":"P",
    "gn:feature_code":"PPL",
    "gn:name":"Castigo",
    "gn:population":0,
    "gn:timezone":"America/Bogota",
    "iso:country":"CO",
    "wof:name":"Castigo",
    "wof:placetype":"locality"
},
  "geometry": {"coordinates":[-77.45858,1.66183],"type":"Point"}
}