{
  "type": "Feature",
  "properties": {
    "gn:admin1_code":"33.0",
    "gn:admin2_code":"25279.0",
    "gn:asciiname":"El Paramo",
    "gn:country_code":"CO",
    "gn:dem":3290,
    "gn:feature_class":"P",
    "gn:feature_code":"PPL",
    "gn:name":"El P\u00e1ramo",
    "gn:population":0,
    "gn:timezone":"America/Bogota",
    "iso:country":"CO",
    "wof:name":"El Paramo",
    "wof:placetype":"locality"
},
  "geometry": {"coordinates":[-73.82363000000002,4.57115],"type":"Point"}
}