{
  "type": "Feature",
  "properties": {
    "gn:admin1_code":"38.0",
    "gn:admin2_code":"47245.0",
    "gn:asciiname":"Negritos",
    "gn:country_code":"CO",
    "gn:dem":26,
    "gn:feature_class":"P",
    "gn:feature_code":"PPL",
    "gn:name":"Negritos",
    "gn:population":0,
    "gn:timezone":"America/Bogota",
    "iso:country":"CO",
    "wof:name":"Negritos",
    "wof:placetype":"locality"
},
  "geometry": {"coordinates":[-74.0904,9.02938],"type":"Point"}
}