{
  "type": "Feature",
  "properties": {
    "gn:admin1_code":"33",
    "gn:admin2_code":"25513.0",
    "gn:asciiname":"El Eden",
    "gn:country_code":"CO",
    "gn:dem":2337,
    "gn:feature_class":"P",
    "gn:feature_code":"PPL",
    "gn:name":"El Ed\u00e9n",
    "gn:population":0,
    "gn:timezone":"America/Bogota",
    "iso:country":"CO",
    "wof:name":"El Eden",
    "wof:placetype":"locality"
},
  "geometry": {"coordinates":[-74.16207,5.07964],"type":"Point"}
}