{
  "type": "Feature",
  "properties": {
    "gn:admin1_code":"9.0",
    "gn:admin2_code":"19256.0",
    "gn:asciiname":"Quilcace",
    "gn:country_code":"CO",
    "gn:dem":841,
    "gn:feature_class":"P",
    "gn:feature_code":"PPL",
    "gn:name":"Quilcac\u00e9",
    "gn:population":0,
    "gn:timezone":"America/Bogota",
    "iso:country":"CO",
    "name:und_x_variant":[
        "Quilcas\u00e9",
        "Quilcac\u00e9"
    ],
    "wof:name":"Quilcace",
    "wof:placetype":"locality"
},
  "geometry": {"coordinates":[-76.86872,2.31904],"type":"Point"}
}