{
  "type": "Feature",
  "properties": {
    "gn:admin1_code":"26",
    "gn:admin2_code":"68615.0",
    "gn:asciiname":"Honda",
    "gn:country_code":"CO",
    "gn:dem":584,
    "gn:feature_class":"P",
    "gn:feature_code":"PPL",
    "gn:name":"Honda",
    "gn:population":0,
    "gn:timezone":"America/Bogota",
    "iso:country":"CO",
    "wof:name":"Honda",
    "wof:placetype":"locality"
},
  "geometry": {"coordinates":[-73.25,7.28333],"type":"Point"}
}