{
  "type": "Feature",
  "properties": {
    "gn:admin1_code":"35",
    "gn:admin2_code":"13052.0",
    "gn:asciiname":"El Mayor",
    "gn:country_code":"CO",
    "gn:dem":40,
    "gn:feature_class":"P",
    "gn:feature_code":"PPL",
    "gn:name":"El Mayor",
    "gn:population":0,
    "gn:timezone":"America/Bogota",
    "iso:country":"CO",
    "wof:name":"El Mayor",
    "wof:placetype":"locality"
},
  "geometry": {"coordinates":[-75.25,10.26667],"type":"Point"}
}