{
  "type": "Feature",
  "properties": {
    "gn:admin1_code":"17",
    "gn:admin2_code":"44650.0",
    "gn:asciiname":"Guamachal",
    "gn:country_code":"CO",
    "gn:dem":210,
    "gn:feature_class":"P",
    "gn:feature_code":"PPL",
    "gn:name":"Guamachal",
    "gn:population":0,
    "gn:timezone":"America/Bogota",
    "iso:country":"CO",
    "wof:name":"Guamachal",
    "wof:placetype":"locality"
},
  "geometry": {"coordinates":[-73.03333000000001,10.75],"type":"Point"}
}