{
  "type": "Feature",
  "properties": {
    "gn:admin1_code":"36",
    "gn:admin2_code":"15572.0",
    "gn:asciiname":"El Diamante",
    "gn:country_code":"CO",
    "gn:dem":213,
    "gn:feature_class":"P",
    "gn:feature_code":"PPL",
    "gn:name":"El Diamante",
    "gn:population":0,
    "gn:timezone":"America/Bogota",
    "iso:country":"CO",
    "wof:name":"El Diamante",
    "wof:placetype":"locality"
},
  "geometry": {"coordinates":[-74.41198,5.82389],"type":"Point"}
}