{
  "type": "Feature",
  "properties": {
    "gn:admin1_code":"20.0",
    "gn:admin2_code":"52838.0",
    "gn:asciiname":"Quinones",
    "gn:country_code":"CO",
    "gn:dem":2871,
    "gn:feature_class":"P",
    "gn:feature_code":"PPL",
    "gn:name":"Qui\u00f1ones",
    "gn:population":0,
    "gn:timezone":"America/Bogota",
    "iso:country":"CO",
    "wof:name":"Quinones",
    "wof:placetype":"locality"
},
  "geometry": {"coordinates":[-77.58875,1.06804],"type":"Point"}
}