{
  "type": "Feature",
  "properties": {
    "gn:admin1_code":"15",
    "gn:admin2_code":"94884.0",
    "gn:asciiname":"Cano Colorado",
    "gn:country_code":"CO",
    "gn:dem":121,
    "gn:feature_class":"P",
    "gn:feature_code":"PPL",
    "gn:name":"Ca\u00f1o Colorado",
    "gn:population":0,
    "gn:timezone":"America/Bogota",
    "iso:country":"CO",
    "wof:name":"Cano Colorado",
    "wof:placetype":"locality"
},
  "geometry": {"coordinates":[-68.35873000000001,2.28184],"type":"Point"}
}