{
  "type": "Feature",
  "properties": {
    "iso:country":"CO",
    "name:unk_x_variant":[
        "Corregimiento San Pablo"
    ],
    "qs:gn_country":"CO",
    "qs:gn_fcode":"PPL",
    "qs:gn_pop":13983,
    "qs:name":"San Pablo",
    "qs:name_adm0":"Colombia",
    "qs:name_adm1":"Bolivar",
    "qs:photos":0,
    "qs:photos_1k":0,
    "qs:photos_9k":0,
    "qs:photos_9r":0,
    "qs:photos_all":0,
    "qs:photos_sr":0,
    "qs:placetype":"Town",
    "qs:pop_sr":"6",
    "qs:woe_adm0":23424787,
    "wof:name":"San Pablo",
    "wof:placetype":"locality",
    "wof:population":13983
},
  "geometry": {"coordinates":[-75.26775000000001,10.05154],"type":"Point"}
}