{
  "type": "Feature",
  "properties": {
    "gn:admin1_code":"28",
    "gn:admin2_code":"73024.0",
    "gn:asciiname":"Los Magueses",
    "gn:country_code":"CO",
    "gn:dem":1186,
    "gn:feature_class":"P",
    "gn:feature_code":"PPL",
    "gn:name":"Los Magueses",
    "gn:population":0,
    "gn:timezone":"America/Bogota",
    "iso:country":"CO",
    "name:spa_x_preferred":[
        "Los Magueses"
    ],
    "wof:name":"Los Magueses",
    "wof:placetype":"locality"
},
  "geometry": {"coordinates":[-75.0325,3.40861],"type":"Point"}
}