{
  "type": "Feature",
  "properties": {
    "gn:admin1_code":"10",
    "gn:admin2_code":"20250.0",
    "gn:asciiname":"La Belleza",
    "gn:country_code":"CO",
    "gn:dem":38,
    "gn:feature_class":"P",
    "gn:feature_code":"PPL",
    "gn:name":"La Belleza",
    "gn:population":0,
    "gn:timezone":"America/Bogota",
    "iso:country":"CO",
    "name:und_x_variant":[
        "Hacienda La Belleza",
        "La Belleza"
    ],
    "wof:name":"La Belleza",
    "wof:placetype":"locality"
},
  "geometry": {"coordinates":[-73.66235999999998,9.58184],"type":"Point"}
}