{
  "type": "Feature",
  "properties": {
    "gn:admin1_code":"33",
    "gn:asciiname":"Belladona",
    "gn:country_code":"CO",
    "gn:dem":344,
    "gn:feature_class":"P",
    "gn:feature_code":"PPL",
    "gn:name":"Belladona",
    "gn:population":0,
    "gn:timezone":"America/Bogota",
    "iso:country":"CO",
    "wof:name":"Belladona",
    "wof:placetype":"locality"
},
  "geometry": {"coordinates":[-73.05835999999999,4.68804],"type":"Point"}
}