{
  "type": "Feature",
  "properties": {
    "gn:admin1_code":"21",
    "gn:admin2_code":"54670.0",
    "gn:asciiname":"El Fique",
    "gn:country_code":"CO",
    "gn:dem":1194,
    "gn:feature_class":"P",
    "gn:feature_code":"PPL",
    "gn:name":"El Fique",
    "gn:population":0,
    "gn:timezone":"America/Bogota",
    "iso:country":"CO",
    "wof:name":"El Fique",
    "wof:placetype":"locality"
},
  "geometry": {"coordinates":[-73.28333000000001,8.36667],"type":"Point"}
}