{
  "type": "Feature",
  "properties": {
    "gn:admin1_code":"32.0",
    "gn:admin2_code":"85250.0",
    "gn:asciiname":"Caserio Las Guamas",
    "gn:country_code":"CO",
    "gn:dem":134,
    "gn:feature_class":"P",
    "gn:feature_code":"PPL",
    "gn:name":"Caser\u00edo Las Guamas",
    "gn:population":0,
    "gn:timezone":"America/Bogota",
    "iso:country":"CO",
    "wof:name":"Caserio Las Guamas",
    "wof:placetype":"locality"
},
  "geometry": {"coordinates":[-70.96861,5.86306],"type":"Point"}
}