{
  "type": "Feature",
  "properties": {
    "iso:country":"CO",
    "name:ast_x_preferred":[
        "Puerto Boyac\u00e1"
    ],
    "name:ceb_x_preferred":[
        "Puerto Boyac\u00e1"
    ],
    "name:deu_x_preferred":[
        "Puerto Boyac\u00e1"
    ],
    "name:eng_x_preferred":[
        "Puerto Boyac\u00e1"
    ],
    "name:fas_x_preferred":[
        "\u067e\u0648\u0631\u062a\u0648 \u0628\u0648\u06cc\u0648\u06a9\u0627"
    ],
    "name:fra_x_preferred":[
        "Puerto Boyac\u00e1"
    ],
    "name:heb_x_preferred":[
        "\u05e4\u05d5\u05d0\u05e8\u05d8\u05d5 \u05d1\u05d5\u05d9\u05d0\u05e7\u05d4"
    ],
    "name:ita_x_preferred":[
        "Puerto Boyac\u00e1"
    ],
    "name:jpn_x_preferred":[
        "\u30d7\u30a8\u30eb\u30c8\u30fb\u30dc\u30e4\u30ab"
    ],
    "name:kat_x_preferred":[
        "\u10de\u10e3\u10d4\u10e0\u10e2\u10dd-\u10d1\u10dd\u10d8\u10d0\u10d9\u10d0"
    ],
    "name:msa_x_preferred":[
        "Puerto Boyac\u00e1"
    ],
    "name:nan_x_preferred":[
        "Puerto Boyac\u00e1"
    ],
    "name:nld_x_preferred":[
        "Puerto Boyac\u00e1"
    ],
    "name:por_x_preferred":[
        "Puerto Boyac\u00e1"
    ],
    "name:rus_x_preferred":[
        "\u041f\u0443\u044d\u0440\u0442\u043e-\u0411\u043e\u044f\u043a\u0430"
    ],
    "name:sco_x_preferred":[
        "Puerto Boyac\u00e1"
    ],
    "name:spa_x_preferred":[
        "Puerto Boyac\u00e1"
    ],
    "name:swe_x_preferred":[
        "Puerto Boyac\u00e1"
    ],
    "name:tgl_x_preferred":[
        "Puerto Boyac\u00e1"
    ],
    "name:vie_x_preferred":[
        "Puerto Boyac\u00e1"
    ],
    "name:war_x_preferred":[
        "Puerto Boyac\u00e1"
    ],
    "name:zho_x_preferred":[
        "\u535a\u4e9e\u5361\u6e2f"
    ],
    "qs:gn_country":"CO",
    "qs:gn_fcode":"PPL",
    "qs:gn_pop":27310,
    "qs:name":"Puerto Boyac\u00e1",
    "qs:name_adm0":"Colombia",
    "qs:name_adm1":"Boyaca",
    "qs:photos":256,
    "qs:photos_1k":52,
    "qs:photos_9k":1,
    "qs:photos_9r":4,
    "qs:photos_all":256,
    "qs:photos_sr":5,
    "qs:placetype":"Town",
    "qs:pop_sr":"7",
    "qs:woe_adm0":23424787,
    "wof:name":"Puerto Boyac\u00e1",
    "wof:placetype":"locality",
    "wof:population":27310
},
  "geometry": {"coordinates":[-74.58846,5.97584],"type":"Point"}
}