{
  "type": "Feature",
  "properties": {
    "gn:admin1_code":"16.0",
    "gn:admin2_code":"41791.0",
    "gn:asciiname":"Eureka",
    "gn:country_code":"CO",
    "gn:dem":1641,
    "gn:feature_class":"P",
    "gn:feature_code":"PPL",
    "gn:name":"Eureka",
    "gn:population":0,
    "gn:timezone":"America/Bogota",
    "iso:country":"CO",
    "name:ara_x_preferred":[
        "\u064a\u0648\u0631\u064a\u0643\u0627"
    ],
    "name:cat_x_preferred":[
        "Eureka"
    ],
    "name:ceb_x_preferred":[
        "Eureka"
    ],
    "name:ces_x_preferred":[
        "Eureka"
    ],
    "name:dan_x_preferred":[
        "Eureka"
    ],
    "name:deu_x_preferred":[
        "Eureka"
    ],
    "name:epo_x_preferred":[
        "Eureka"
    ],
    "name:est_x_preferred":[
        "Eureka"
    ],
    "name:fra_x_preferred":[
        "Eur\u00eaka"
    ],
    "name:glg_x_preferred":[
        "Eureka"
    ],
    "name:heb_x_preferred":[
        "\u05d9\u05d5\u05e8\u05d9\u05e7\u05d4"
    ],
    "name:ind_x_preferred":[
        "Eureka"
    ],
    "name:ita_x_preferred":[
        "Eureka"
    ],
    "name:jpn_x_preferred":[
        "Eureka"
    ],
    "name:kat_x_preferred":[
        "\u10d4\u10d5\u10e0\u10d8\u10d9\u10d0"
    ],
    "name:kor_x_preferred":[
        "\uc720\ub808\uce74"
    ],
    "name:nld_x_preferred":[
        "Eureka"
    ],
    "name:nor_x_preferred":[
        "Eureka"
    ],
    "name:pol_x_preferred":[
        "Eureka"
    ],
    "name:por_x_preferred":[
        "Eureka"
    ],
    "name:rus_x_preferred":[
        "\u042d\u0432\u0440\u0438\u043a\u0430"
    ],
    "name:slk_x_preferred":[
        "Eureka"
    ],
    "name:spa_x_preferred":[
        "Eureka"
    ],
    "name:swe_x_preferred":[
        "Eureka"
    ],
    "name:ukr_x_preferred":[
        "\u0415\u0432\u0440\u0438\u043a\u0430"
    ],
    "name:vol_x_preferred":[
        "Eureka"
    ],
    "wof:name":"Eureka",
    "wof:placetype":"locality"
},
  "geometry": {"coordinates":[-75.86991999999999,2.20859],"type":"Point"}
}