{
  "type": "Feature",
  "properties": {
    "gn:admin1_code":"16.0",
    "gn:admin2_code":"41791.0",
    "gn:asciiname":"Eureka",
    "gn:country_code":"CO",
    "gn:dem":1641,
    "gn:feature_class":"P",
    "gn:feature_code":"PPL",
    "gn:name":"Eureka",
    "gn:population":0,
    "gn:timezone":"America/Bogota",
    "iso:country":"CO",
    "wof:name":"Eureka",
    "wof:placetype":"locality"
},
  "geometry": {"coordinates":[-75.86991999999999,2.20859],"type":"Point"}
}