{
  "type": "Feature",
  "properties": {
    "gn:admin1_code":"38",
    "gn:admin2_code":"47720.0",
    "gn:asciiname":"Las Planadas",
    "gn:country_code":"CO",
    "gn:dem":58,
    "gn:feature_class":"P",
    "gn:feature_code":"PPL",
    "gn:name":"Las Planadas",
    "gn:population":0,
    "gn:timezone":"America/Bogota",
    "iso:country":"CO",
    "wof:name":"Las Planadas",
    "wof:placetype":"locality"
},
  "geometry": {"coordinates":[-74.56255999999998,9.5926],"type":"Point"}
}