{
  "type": "Feature",
  "properties": {
    "gn:admin1_code":"16",
    "gn:admin2_code":"41524.0",
    "gn:asciiname":"Piedramoler",
    "gn:country_code":"CO",
    "gn:dem":953,
    "gn:feature_class":"P",
    "gn:feature_code":"PPL",
    "gn:name":"Piedramoler",
    "gn:population":0,
    "gn:timezone":"America/Bogota",
    "iso:country":"CO",
    "wof:name":"Piedramoler",
    "wof:placetype":"locality"
},
  "geometry": {"coordinates":[-75.51723,2.89584],"type":"Point"}
}