{
  "type": "Feature",
  "properties": {
    "gn:admin1_code":"14.0",
    "gn:admin2_code":"95001.0",
    "gn:asciiname":"Puerto Arturo",
    "gn:country_code":"CO",
    "gn:dem":189,
    "gn:feature_class":"P",
    "gn:feature_code":"PPL",
    "gn:name":"Puerto Arturo",
    "gn:population":0,
    "gn:timezone":"America/Bogota",
    "iso:country":"CO",
    "name:und_x_variant":[
        "Inspecci\u00f3n de Polic\u00eda Puerto Arturo"
    ],
    "wof:name":"Puerto Arturo",
    "wof:placetype":"locality"
},
  "geometry": {"coordinates":[-72.74916,2.56853],"type":"Point"}
}