{
  "type": "Feature",
  "properties": {
    "gn:admin1_code":"33.0",
    "gn:admin2_code":"25612.0",
    "gn:asciiname":"El Recreo",
    "gn:country_code":"CO",
    "gn:dem":300,
    "gn:feature_class":"P",
    "gn:feature_code":"PPL",
    "gn:name":"El Recreo",
    "gn:population":0,
    "gn:timezone":"America/Bogota",
    "iso:country":"CO",
    "name:spa_x_preferred":[
        "El Recreo"
    ],
    "wof:name":"El Recreo",
    "wof:placetype":"locality"
},
  "geometry": {"coordinates":[-74.75187,4.34048],"type":"Point"}
}