{
  "type": "Feature",
  "properties": {
    "gn:admin1_code":"2.0",
    "gn:admin2_code":"5045.0",
    "gn:asciiname":"La Navarra",
    "gn:country_code":"CO",
    "gn:dem":30,
    "gn:feature_class":"P",
    "gn:feature_code":"PPL",
    "gn:name":"La Navarra",
    "gn:population":0,
    "gn:timezone":"America/Bogota",
    "iso:country":"CO",
    "wof:name":"La Navarra",
    "wof:placetype":"locality"
},
  "geometry": {"coordinates":[-76.63778000000001,7.86639],"type":"Point"}
}