{
  "type": "Feature",
  "properties": {
    "gn:admin1_code":"28",
    "gn:admin2_code":"73148.0",
    "gn:asciiname":"Alejandro Bernate",
    "gn:country_code":"CO",
    "gn:dem":292,
    "gn:feature_class":"P",
    "gn:feature_code":"PPL",
    "gn:name":"Alejandro Bernate",
    "gn:population":0,
    "gn:timezone":"America/Bogota",
    "iso:country":"CO",
    "wof:name":"Alejandro Bernate",
    "wof:placetype":"locality"
},
  "geometry": {"coordinates":[-74.75,4.18333],"type":"Point"}
}