{
  "type": "Feature",
  "properties": {
    "gn:admin1_code":"33.0",
    "gn:admin2_code":"25815.0",
    "gn:asciiname":"Paloquemao",
    "gn:country_code":"CO",
    "gn:dem":760,
    "gn:feature_class":"P",
    "gn:feature_code":"PPL",
    "gn:name":"Paloquemao",
    "gn:population":0,
    "gn:timezone":"America/Bogota",
    "iso:country":"CO",
    "name:spa_x_preferred":[
        "Paloquemao"
    ],
    "wof:name":"Paloquemao",
    "wof:placetype":"locality"
},
  "geometry": {"coordinates":[-74.61443,4.48362],"type":"Point"}
}