{
  "type": "Feature",
  "properties": {
    "gn:admin1_code":"12.0",
    "gn:admin2_code":"23001.0",
    "gn:asciiname":"El Cebral",
    "gn:country_code":"CO",
    "gn:dem":33,
    "gn:feature_class":"P",
    "gn:feature_code":"PPL",
    "gn:name":"El Cebral",
    "gn:population":0,
    "gn:timezone":"America/Bogota",
    "iso:country":"CO",
    "wof:name":"El Cebral",
    "wof:placetype":"locality"
},
  "geometry": {"coordinates":[-76.02722,8.37028],"type":"Point"}
}