{
  "type": "Feature",
  "properties": {
    "gn:admin1_code":"4",
    "gn:admin2_code":"8078.0",
    "gn:asciiname":"Campeche",
    "gn:country_code":"CO",
    "gn:dem":109,
    "gn:feature_class":"P",
    "gn:feature_code":"PPL",
    "gn:name":"Campeche",
    "gn:population":0,
    "gn:timezone":"America/Bogota",
    "iso:country":"CO",
    "wof:name":"Campeche",
    "wof:placetype":"locality"
},
  "geometry": {"coordinates":[-74.91538,10.72496],"type":"Point"}
}