{
  "type": "Feature",
  "properties": {
    "gn:admin1_code":"33.0",
    "gn:admin2_code":"25377.0",
    "gn:asciiname":"Siberia",
    "gn:country_code":"CO",
    "gn:dem":2739,
    "gn:feature_class":"P",
    "gn:feature_code":"PPL",
    "gn:name":"Siberia",
    "gn:population":0,
    "gn:timezone":"America/Bogota",
    "iso:country":"CO",
    "wof:name":"Siberia",
    "wof:placetype":"locality"
},
  "geometry": {"coordinates":[-73.9469,4.70893],"type":"Point"}
}