{
  "type": "Feature",
  "properties": {
    "gn:admin1_code":"38",
    "gn:admin2_code":"47551.0",
    "gn:asciiname":"Corralnuevo",
    "gn:country_code":"CO",
    "gn:dem":77,
    "gn:feature_class":"P",
    "gn:feature_code":"PPL",
    "gn:name":"Corralnuevo",
    "gn:population":0,
    "gn:timezone":"America/Bogota",
    "iso:country":"CO",
    "wof:name":"Corralnuevo",
    "wof:placetype":"locality"
},
  "geometry": {"coordinates":[-74.23333000000002,10.45],"type":"Point"}
}