{
  "type": "Feature",
  "properties": {
    "gn:admin1_code":"2.0",
    "gn:admin2_code":"5411.0",
    "gn:asciiname":"La Trampo",
    "gn:country_code":"CO",
    "gn:dem":1413,
    "gn:feature_class":"P",
    "gn:feature_code":"PPL",
    "gn:name":"La Trampo",
    "gn:population":0,
    "gn:timezone":"America/Bogota",
    "iso:country":"CO",
    "wof:name":"La Trampo",
    "wof:placetype":"locality"
},
  "geometry": {"coordinates":[-75.76861,6.72944],"type":"Point"}
}