{
  "type": "Feature",
  "properties": {
    "gn:admin1_code":"10",
    "gn:asciiname":"Los Fiques",
    "gn:country_code":"CO",
    "gn:dem":915,
    "gn:feature_class":"P",
    "gn:feature_code":"PPL",
    "gn:name":"Los Fiques",
    "gn:population":0,
    "gn:timezone":"America/Bogota",
    "iso:country":"CO",
    "wof:name":"Los Fiques",
    "wof:placetype":"locality"
},
  "geometry": {"coordinates":[-73.37721999999999,8.02861],"type":"Point"}
}