{
  "type": "Feature",
  "properties": {
    "gn:admin1_code":"10",
    "gn:admin2_code":"20032.0",
    "gn:asciiname":"Buenos Aires",
    "gn:country_code":"CO",
    "gn:dem":75,
    "gn:feature_class":"P",
    "gn:feature_code":"PPL",
    "gn:name":"Buenos Aires",
    "gn:population":0,
    "gn:timezone":"America/Bogota",
    "iso:country":"CO",
    "wof:name":"Buenos Aires",
    "wof:placetype":"locality"
},
  "geometry": {"coordinates":[-73.91667,9.56667],"type":"Point"}
}