{
  "type": "Feature",
  "properties": {
    "gn:admin1_code":"9.0",
    "gn:admin2_code":"19517.0",
    "gn:asciiname":"La Cruz De Togoima",
    "gn:country_code":"CO",
    "gn:dem":2353,
    "gn:feature_class":"P",
    "gn:feature_code":"PPLL",
    "gn:name":"La Cruz De Togoima",
    "gn:population":0,
    "gn:timezone":"America/Bogota",
    "iso:country":"CO",
    "wof:name":"La Cruz De Togoima",
    "wof:placetype":"locality"
},
  "geometry": {"coordinates":[-76.01397,2.60738],"type":"Point"}
}