{
  "type": "Feature",
  "properties": {
    "gn:admin1_code":"20.0",
    "gn:admin2_code":"52317.0",
    "gn:asciiname":"Cualapud",
    "gn:country_code":"CO",
    "gn:dem":3236,
    "gn:feature_class":"P",
    "gn:feature_code":"PPL",
    "gn:name":"Cualap\u00fad",
    "gn:population":0,
    "gn:timezone":"America/Bogota",
    "iso:country":"CO",
    "wof:name":"Cualapud",
    "wof:placetype":"locality"
},
  "geometry": {"coordinates":[-77.72919,0.93368],"type":"Point"}
}