{
  "type": "Feature",
  "properties": {
    "gn:admin1_code":"19",
    "gn:admin2_code":"50150",
    "gn:asciiname":"El Diluvio",
    "gn:country_code":"CO",
    "gn:dem":439,
    "gn:feature_class":"P",
    "gn:feature_code":"PPL",
    "gn:name":"El Diluvio",
    "gn:population":0,
    "gn:timezone":"America/Bogota",
    "iso:country":"CO",
    "name:spa_x_preferred":[
        "El Diluvio"
    ],
    "wof:name":"El Diluvio",
    "wof:placetype":"locality"
},
  "geometry": {"coordinates":[-73.70484,3.84512],"type":"Point"}
}