{
  "type": "Feature",
  "properties": {
    "gn:admin1_code":"21",
    "gn:admin2_code":"54003.0",
    "gn:asciiname":"Tarra",
    "gn:cc2":"CO",
    "gn:country_code":"CO",
    "gn:dem":1495,
    "gn:feature_class":"P",
    "gn:feature_code":"PPL",
    "gn:name":"Tarr\u00e1",
    "gn:population":0,
    "gn:timezone":"America/Bogota",
    "iso:country":"CO",
    "name:und_x_variant":[
        "El Tarra",
        "Tarr\u00e1"
    ],
    "wof:name":"Tarra",
    "wof:placetype":"locality"
},
  "geometry": {"coordinates":[-73.08360999999999,8.0475],"type":"Point"}
}