{
  "type": "Feature",
  "properties": {
    "gn:country":"CO",
    "gn:fcode":"PPL",
    "gn:population":1467,
    "iso:country":"CO",
    "name:ast_x_preferred":[
        "Florencia"
    ],
    "name:avk_x_preferred":[
        "Florencia"
    ],
    "name:ceb_x_preferred":[
        "Florencia"
    ],
    "name:eng_x_preferred":[
        "Florencia"
    ],
    "name:fas_x_preferred":[
        "\u0641\u0644\u0648\u0631\u0646\u0633\u06cc\u0627"
    ],
    "name:fra_x_preferred":[
        "Florencia"
    ],
    "name:gle_x_preferred":[
        "Florencia"
    ],
    "name:ita_x_preferred":[
        "Florencia"
    ],
    "name:kat_x_preferred":[
        "\u10e4\u10da\u10dd\u10e0\u10d4\u10dc\u10ea\u10d8\u10d0"
    ],
    "name:msa_x_preferred":[
        "Florencia"
    ],
    "name:nan_x_preferred":[
        "Florencia"
    ],
    "name:nld_x_preferred":[
        "Florencia"
    ],
    "name:pol_x_preferred":[
        "Florencia"
    ],
    "name:por_x_preferred":[
        "Florencia"
    ],
    "name:rus_x_preferred":[
        "\u0424\u043b\u043e\u0440\u0435\u043d\u0441\u0438\u044f"
    ],
    "name:sco_x_preferred":[
        "Florencia"
    ],
    "name:spa_x_preferred":[
        "Florencia"
    ],
    "name:swe_x_preferred":[
        "Florencia"
    ],
    "name:tgl_x_preferred":[
        "Florencia"
    ],
    "name:und_x_variant":[
        "Florencio"
    ],
    "name:vie_x_preferred":[
        "Florencia"
    ],
    "name:war_x_preferred":[
        "Florencia"
    ],
    "name:zho_x_preferred":[
        "\u5f17\u6d1b\u502b\u897f\u4e9e"
    ],
    "qs:name":"Florencia",
    "qs:photos_9r":0,
    "qs:photos_sr":0,
    "qs:pop_sr":"3",
    "wd:wordcount":62,
    "wof:name":"Florencia",
    "wof:placetype":"locality",
    "wof:population":1467
},
  "geometry": {"coordinates":[-77.0733,1.68318],"type":"Point"}
}