{
  "type": "Feature",
  "properties": {
    "gn:admin1_code":"32",
    "gn:admin2_code":"85001.0",
    "gn:asciiname":"Juan Mechas",
    "gn:country_code":"CO",
    "gn:dem":201,
    "gn:feature_class":"P",
    "gn:feature_code":"PPL",
    "gn:name":"Juan Mechas",
    "gn:population":0,
    "gn:timezone":"America/Bogota",
    "iso:country":"CO",
    "wof:name":"Juan Mechas",
    "wof:placetype":"locality"
},
  "geometry": {"coordinates":[-72.14039,5.29388],"type":"Point"}
}