{
  "type": "Feature",
  "properties": {
    "gn:admin1_code":"26",
    "gn:admin2_code":"68773.0",
    "gn:asciiname":"Los Pinos",
    "gn:country_code":"CO",
    "gn:dem":2928,
    "gn:feature_class":"P",
    "gn:feature_code":"PPL",
    "gn:name":"Los Pinos",
    "gn:population":0,
    "gn:timezone":"America/Bogota",
    "iso:country":"CO",
    "wof:name":"Los Pinos",
    "wof:placetype":"locality"
},
  "geometry": {"coordinates":[-73.83750000000001,5.92444],"type":"Point"}
}