{
  "type": "Feature",
  "properties": {
    "iso:country":"CO",
    "name:chi_x_preferred":[
        "\u5bcc\u514b\u5167"
    ],
    "name:dut_x_preferred":[
        "F\u00faquene"
    ],
    "name:eng_x_preferred":[
        "F\u00faquene"
    ],
    "name:fre_x_preferred":[
        "F\u00faquene"
    ],
    "name:geo_x_preferred":[
        "\u10e4\u10e3\u10d9\u10d4\u10dc\u10d4"
    ],
    "name:ita_x_preferred":[
        "F\u00faquene"
    ],
    "name:may_x_preferred":[
        "F\u00faquene"
    ],
    "name:nan_x_preferred":[
        "F\u00faquene"
    ],
    "name:sco_x_preferred":[
        "F\u00faquene"
    ],
    "name:spa_x_preferred":[
        "F\u00faquene"
    ],
    "name:swe_x_preferred":[
        "F\u00faquene"
    ],
    "name:tgl_x_preferred":[
        "F\u00faquene"
    ],
    "name:vie_x_preferred":[
        "F\u00faquene"
    ],
    "name:war_x_preferred":[
        "F\u00faquene"
    ],
    "qs:gn_country":"CO",
    "qs:gn_fcode":"PPL",
    "qs:gn_pop":563,
    "qs:name":"F\u00faquene",
    "qs:name_adm0":"Colombia",
    "qs:name_adm1":"Cundinamarca",
    "qs:photos":136,
    "qs:photos_1k":28,
    "qs:photos_9k":1,
    "qs:photos_9r":3,
    "qs:photos_all":136,
    "qs:photos_sr":3,
    "qs:placetype":"Town",
    "qs:pop_sr":"2",
    "qs:woe_adm0":23424787,
    "wof:name":"F\u00faquene",
    "wof:placetype":"locality",
    "wof:population":563
},
  "geometry": {"coordinates":[-73.79640000000001,5.40425],"type":"Point"}
}