{
  "type": "Feature",
  "properties": {
    "gn:admin1_code":"26",
    "gn:admin2_code":"68020.0",
    "gn:asciiname":"Poveda",
    "gn:country_code":"CO",
    "gn:dem":1414,
    "gn:feature_class":"P",
    "gn:feature_code":"PPL",
    "gn:name":"Poveda",
    "gn:population":0,
    "gn:timezone":"America/Bogota",
    "iso:country":"CO",
    "name:ara_x_preferred":[
        "\u0628\u0648\u0641\u064a\u062f\u0627"
    ],
    "name:azb_x_preferred":[
        "\u067e\u0648\u0628\u062f\u0627"
    ],
    "name:cat_x_preferred":[
        "Poveda"
    ],
    "name:ceb_x_preferred":[
        "Poveda"
    ],
    "name:deu_x_preferred":[
        "Poveda"
    ],
    "name:eus_x_preferred":[
        "Poveda"
    ],
    "name:fas_x_preferred":[
        "\u067e\u0648\u0628\u062f\u0627"
    ],
    "name:fra_x_preferred":[
        "Poveda"
    ],
    "name:hun_x_preferred":[
        "Poveda"
    ],
    "name:ina_x_preferred":[
        "Poveda"
    ],
    "name:ita_x_preferred":[
        "Poveda"
    ],
    "name:kaz_x_preferred":[
        "\u041f\u043e\u0432\u0435\u0434\u0430"
    ],
    "name:mkd_x_preferred":[
        "\u041f\u043e\u0432\u0435\u0434\u0430"
    ],
    "name:msa_x_preferred":[
        "Poveda"
    ],
    "name:nld_x_preferred":[
        "Poveda"
    ],
    "name:oci_x_preferred":[
        "Poveda"
    ],
    "name:pol_x_preferred":[
        "Poveda"
    ],
    "name:por_x_preferred":[
        "Poveda"
    ],
    "name:rus_x_preferred":[
        "\u041f\u043e\u0432\u0435\u0434\u0430"
    ],
    "name:spa_x_preferred":[
        "Poveda"
    ],
    "name:ukr_x_preferred":[
        "\u041f\u043e\u0432\u0435\u0434\u0430"
    ],
    "name:uzb_x_preferred":[
        "Poveda"
    ],
    "name:vie_x_preferred":[
        "Poveda"
    ],
    "name:war_x_preferred":[
        "Poveda"
    ],
    "name:zho_x_preferred":[
        "\u6ce2\u97e6\u8fbe"
    ],
    "wof:name":"Poveda",
    "wof:placetype":"locality"
},
  "geometry": {"coordinates":[-73.9325,5.74944],"type":"Point"}
}