{
  "type": "Feature",
  "properties": {
    "gn:admin1_code":"26",
    "gn:admin2_code":"68020.0",
    "gn:asciiname":"Poveda",
    "gn:country_code":"CO",
    "gn:dem":1414,
    "gn:feature_class":"P",
    "gn:feature_code":"PPL",
    "gn:name":"Poveda",
    "gn:population":0,
    "gn:timezone":"America/Bogota",
    "iso:country":"CO",
    "wof:name":"Poveda",
    "wof:placetype":"locality"
},
  "geometry": {"coordinates":[-73.9325,5.74944],"type":"Point"}
}