{
  "type": "Feature",
  "properties": {
    "gn:admin1_code":"20.0",
    "gn:admin2_code":"52835.0",
    "gn:asciiname":"Bernardino Ortiz",
    "gn:country_code":"CO",
    "gn:dem":34,
    "gn:feature_class":"P",
    "gn:feature_code":"PPL",
    "gn:name":"Bernardino Ort\u00edz",
    "gn:population":0,
    "gn:timezone":"America/Bogota",
    "iso:country":"CO",
    "name:und_x_variant":[
        "Tablones",
        "Bernardino Ort\u00edz"
    ],
    "wof:name":"Bernardino Ortiz",
    "wof:placetype":"locality"
},
  "geometry": {"coordinates":[-78.48902,1.7357],"type":"Point"}
}