{
  "type": "Feature",
  "properties": {
    "gn:admin1_code":"36",
    "gn:admin2_code":"15681.0",
    "gn:asciiname":"San Pedro",
    "gn:country_code":"CO",
    "gn:dem":1149,
    "gn:feature_class":"P",
    "gn:feature_code":"PPL",
    "gn:name":"San Pedro",
    "gn:population":0,
    "gn:timezone":"America/Bogota",
    "iso:country":"CO",
    "wof:name":"San Pedro",
    "wof:placetype":"locality"
},
  "geometry": {"coordinates":[-74.06389,5.71583],"type":"Point"}
}