{
  "type": "Feature",
  "properties": {
    "gn:admin1_code":"38",
    "gn:admin2_code":"47170.0",
    "gn:asciiname":"Hacienda El Rosario",
    "gn:country_code":"CO",
    "gn:dem":135,
    "gn:feature_class":"P",
    "gn:feature_code":"PPL",
    "gn:name":"Hacienda El Rosario",
    "gn:population":0,
    "gn:timezone":"America/Bogota",
    "iso:country":"CO",
    "wof:name":"Hacienda El Rosario",
    "wof:placetype":"locality"
},
  "geometry": {"coordinates":[-74.45256999999999,10.11961],"type":"Point"}
}