{
  "type": "Feature",
  "properties": {
    "gn:admin1_code":"20.0",
    "gn:admin2_code":"52435.0",
    "gn:asciiname":"Pialapi",
    "gn:country_code":"CO",
    "gn:dem":2770,
    "gn:feature_class":"P",
    "gn:feature_code":"PPL",
    "gn:name":"Pialap\u00ed",
    "gn:population":0,
    "gn:timezone":"America/Bogota",
    "iso:country":"CO",
    "wof:name":"Pialapi",
    "wof:placetype":"locality"
},
  "geometry": {"coordinates":[-77.8683,1.04834],"type":"Point"}
}