{
  "type": "Feature",
  "properties": {
    "gn:admin1_code":"16",
    "gn:admin2_code":"41001",
    "gn:asciiname":"Vega del Gallo",
    "gn:country_code":"CO",
    "gn:dem":2374,
    "gn:feature_class":"P",
    "gn:feature_code":"PPL",
    "gn:name":"Vega del Gallo",
    "gn:population":0,
    "gn:timezone":"America/Bogota",
    "iso:country":"CO",
    "name:spa_x_preferred":[
        "Vega del Gallo"
    ],
    "wof:name":"Vega del Gallo",
    "wof:placetype":"locality"
},
  "geometry": {"coordinates":[-74.99508,2.88876],"type":"Point"}
}