{
  "type": "Feature",
  "properties": {
    "gn:admin1_code":"33.0",
    "gn:admin2_code":"25181.0",
    "gn:asciiname":"Guasa",
    "gn:country_code":"CO",
    "gn:dem":2066,
    "gn:feature_class":"P",
    "gn:feature_code":"PPL",
    "gn:name":"Guasa",
    "gn:population":0,
    "gn:timezone":"America/Bogota",
    "iso:country":"CO",
    "name:tha_x_preferred":[
        "\u0e01\u0e31\u0e27\u0e0b\u0e48\u0e32"
    ],
    "wof:name":"Guasa",
    "wof:placetype":"locality"
},
  "geometry": {"coordinates":[-73.92985,4.51347],"type":"Point"}
}