{
  "type": "Feature",
  "properties": {
    "gn:admin1_code":"33.0",
    "gn:admin2_code":"25839.0",
    "gn:asciiname":"Boca de Monte",
    "gn:country_code":"CO",
    "gn:dem":924,
    "gn:feature_class":"P",
    "gn:feature_code":"PPL",
    "gn:name":"Boca de Monte",
    "gn:population":0,
    "gn:timezone":"America/Bogota",
    "iso:country":"CO",
    "wof:name":"Boca de Monte",
    "wof:placetype":"locality"
},
  "geometry": {"coordinates":[-73.34409000000002,4.74459],"type":"Point"}
}