{
  "type": "Feature",
  "properties": {
    "gn:admin1_code":"35.0",
    "gn:admin2_code":"13549.0",
    "gn:asciiname":"Palomino",
    "gn:country_code":"CO",
    "gn:dem":18,
    "gn:feature_class":"P",
    "gn:feature_code":"PPL",
    "gn:name":"Palomino",
    "gn:population":0,
    "gn:timezone":"America/Bogota",
    "iso:country":"CO",
    "wof:name":"Palomino",
    "wof:placetype":"locality"
},
  "geometry": {"coordinates":[-74.44237,8.9406],"type":"Point"}
}