{
  "type": "Feature",
  "properties": {
    "gn:admin1_code":"35.0",
    "gn:admin2_code":"13549.0",
    "gn:asciiname":"Palomino",
    "gn:country_code":"CO",
    "gn:dem":18,
    "gn:feature_class":"P",
    "gn:feature_code":"PPL",
    "gn:name":"Palomino",
    "gn:population":0,
    "gn:timezone":"America/Bogota",
    "iso:country":"CO",
    "name:ara_x_preferred":[
        "\u0628\u0627\u0644\u0648\u0645\u064a\u0646\u0648"
    ],
    "name:ast_x_preferred":[
        "Caballu palomino"
    ],
    "name:cat_x_preferred":[
        "Pelatge palomino"
    ],
    "name:ces_x_preferred":[
        "Palomino"
    ],
    "name:dan_x_preferred":[
        "Palomino"
    ],
    "name:fas_x_preferred":[
        "\u067e\u0627\u0644\u0648\u0645\u06cc\u0646\u0648"
    ],
    "name:fin_x_preferred":[
        "Palomino"
    ],
    "name:fra_x_preferred":[
        "Palomino"
    ],
    "name:glg_x_preferred":[
        "Cabalo palomino"
    ],
    "name:ita_x_preferred":[
        "Palomino"
    ],
    "name:nld_x_preferred":[
        "Palomino"
    ],
    "name:pol_x_preferred":[
        "Ma\u015b\u0107 izabelowata"
    ],
    "name:rus_x_preferred":[
        "\u041f\u0430\u043b\u043e\u043c\u0438\u043d\u043e"
    ],
    "name:spa_x_preferred":[
        "Caballo palomino"
    ],
    "name:swe_x_preferred":[
        "Palomino"
    ],
    "name:tat_x_preferred":[
        "\u0421\u0430\u0440\u044b"
    ],
    "name:zho_x_preferred":[
        "\u91d1\u9ec3\u8272"
    ],
    "wof:name":"Palomino",
    "wof:placetype":"locality"
},
  "geometry": {"coordinates":[-74.44237,8.9406],"type":"Point"}
}