{
  "type": "Feature",
  "properties": {
    "gn:admin1_code":"28.0",
    "gn:admin2_code":"73616.0",
    "gn:asciiname":"Albania",
    "gn:country_code":"CO",
    "gn:dem":2468,
    "gn:feature_class":"P",
    "gn:feature_code":"PPL",
    "gn:name":"Albania",
    "gn:population":0,
    "gn:timezone":"America/Bogota",
    "iso:country":"CO",
    "wof:name":"Albania",
    "wof:placetype":"locality"
},
  "geometry": {"coordinates":[-75.85194,3.61528],"type":"Point"}
}