{
  "type": "Feature",
  "properties": {
    "gn:admin1_code":"10.0",
    "gn:admin2_code":"20011.0",
    "gn:asciiname":"Laas Dantas",
    "gn:country_code":"CO",
    "gn:dem":149,
    "gn:feature_class":"P",
    "gn:feature_code":"PPL",
    "gn:name":"Laas Dantas",
    "gn:population":0,
    "gn:timezone":"America/Bogota",
    "iso:country":"CO",
    "name:spa_x_preferred":[
        "Laas Dantas"
    ],
    "wof:name":"Laas Dantas",
    "wof:placetype":"locality"
},
  "geometry": {"coordinates":[-73.55814000000002,8.21312],"type":"Point"}
}