{
  "type": "Feature",
  "properties": {
    "gn:admin1_code":"26",
    "gn:admin2_code":"68498.0",
    "gn:asciiname":"Monchia",
    "gn:country_code":"CO",
    "gn:dem":1622,
    "gn:feature_class":"P",
    "gn:feature_code":"PPL",
    "gn:name":"Monch\u00eda",
    "gn:population":0,
    "gn:timezone":"America/Bogota",
    "iso:country":"CO",
    "wof:name":"Monchia",
    "wof:placetype":"locality"
},
  "geometry": {"coordinates":[-73.09311,6.36991],"type":"Point"}
}