{
  "type": "Feature",
  "properties": {
    "gn:admin1_code":"35",
    "gn:admin2_code":"13468.0",
    "gn:asciiname":"Los Guaimaros",
    "gn:cc2":"CO",
    "gn:country_code":"CO",
    "gn:dem":17,
    "gn:feature_class":"P",
    "gn:feature_code":"PPL",
    "gn:name":"Los G\u00faaimaros",
    "gn:population":0,
    "gn:timezone":"America/Bogota",
    "iso:country":"CO",
    "name:und_x_variant":[
        "Caser\u00edo Los Guaimaros",
        "Los G\u00faaimaros"
    ],
    "wof:name":"Los Guaimaros",
    "wof:placetype":"locality"
},
  "geometry": {"coordinates":[-74.3875,9.20528],"type":"Point"}
}