{
  "type": "Feature",
  "properties": {
    "gn:admin1_code":"35.0",
    "gn:admin2_code":"13657.0",
    "gn:asciiname":"Villa Silvia",
    "gn:country_code":"CO",
    "gn:dem":97,
    "gn:feature_class":"P",
    "gn:feature_code":"PPL",
    "gn:name":"Villa Silvia",
    "gn:population":0,
    "gn:timezone":"America/Bogota",
    "iso:country":"CO",
    "wof:name":"Villa Silvia",
    "wof:placetype":"locality"
},
  "geometry": {"coordinates":[-75.07361999999998,10.05821],"type":"Point"}
}