{
  "type": "Feature",
  "properties": {
    "gn:admin1_code":"10.0",
    "gn:admin2_code":"20001.0",
    "gn:asciiname":"Hacienda El Bandon",
    "gn:country_code":"CO",
    "gn:dem":108,
    "gn:feature_class":"P",
    "gn:feature_code":"PPL",
    "gn:name":"Hacienda El Band\u00f3n",
    "gn:population":0,
    "gn:timezone":"America/Bogota",
    "iso:country":"CO",
    "wof:name":"Hacienda El Bandon",
    "wof:placetype":"locality"
},
  "geometry": {"coordinates":[-73.24901,10.35892],"type":"Point"}
}