{
  "type": "Feature",
  "properties": {
    "gn:admin1_code":"16.0",
    "gn:admin2_code":"41078.0",
    "gn:asciiname":"Soto",
    "gn:country_code":"CO",
    "gn:dem":1515,
    "gn:feature_class":"P",
    "gn:feature_code":"PPL",
    "gn:name":"Soto",
    "gn:population":0,
    "gn:timezone":"America/Bogota",
    "iso:country":"CO",
    "name:spa_x_preferred":[
        "Soto"
    ],
    "wof:name":"Soto",
    "wof:placetype":"locality"
},
  "geometry": {"coordinates":[-74.95889,3.14111],"type":"Point"}
}