{
  "type": "Feature",
  "properties": {
    "iso:country":"CO",
    "name:ast_x_preferred":[
        "L\u00e9rida"
    ],
    "name:avk_x_preferred":[
        "L\u00e9rida"
    ],
    "name:cat_x_preferred":[
        "L\u00e9rida"
    ],
    "name:ceb_x_preferred":[
        "L\u00e9rida"
    ],
    "name:eng_x_preferred":[
        "L\u00e9rida"
    ],
    "name:fas_x_preferred":[
        "\u0644\u0631\u06cc\u062f\u0627"
    ],
    "name:fra_x_preferred":[
        "L\u00e9rida"
    ],
    "name:gle_x_preferred":[
        "L\u00e9rida"
    ],
    "name:glg_x_preferred":[
        "L\u00e9rida"
    ],
    "name:ita_x_preferred":[
        "L\u00e9rida"
    ],
    "name:kat_x_preferred":[
        "\u10da\u10d4\u10e0\u10d8\u10d3\u10d0"
    ],
    "name:lit_x_preferred":[
        "Lerida"
    ],
    "name:msa_x_preferred":[
        "L\u00e9rida"
    ],
    "name:nan_x_preferred":[
        "L\u00e9rida"
    ],
    "name:nld_x_preferred":[
        "L\u00e9rida"
    ],
    "name:pol_x_preferred":[
        "L\u00e9rida"
    ],
    "name:spa_x_preferred":[
        "L\u00e9rida"
    ],
    "name:swe_x_preferred":[
        "L\u00e9rida"
    ],
    "name:war_x_preferred":[
        "L\u00e9rida"
    ],
    "name:zho_x_preferred":[
        "\u840a\u91cc\u9054"
    ],
    "qs:gn_country":"CO",
    "qs:gn_fcode":"PPL",
    "qs:gn_pop":20069,
    "qs:name":"L\u00e9rida",
    "qs:name_adm0":"Colombia",
    "qs:name_adm1":"Tolima",
    "qs:photos":0,
    "qs:photos_1k":0,
    "qs:photos_9k":1,
    "qs:photos_9r":2,
    "qs:photos_all":36,
    "qs:photos_sr":0,
    "qs:placetype":"Town",
    "qs:pop_sr":"7",
    "qs:woe_adm0":23424787,
    "wof:name":"L\u00e9rida",
    "wof:placetype":"locality",
    "wof:population":20069
},
  "geometry": {"coordinates":[-74.90976999999999,4.86242],"type":"Point"}
}