{
  "type": "Feature",
  "properties": {
    "gn:admin1_code":"19.0",
    "gn:admin2_code":"50590.0",
    "gn:asciiname":"Rio Loro",
    "gn:country_code":"CO",
    "gn:dem":236,
    "gn:feature_class":"P",
    "gn:feature_code":"PPLL",
    "gn:name":"R\u00edo Loro",
    "gn:population":0,
    "gn:timezone":"America/Bogota",
    "iso:country":"CO",
    "name:spa_x_preferred":[
        "R\u00edo Loro"
    ],
    "wof:name":"Rio Loro",
    "wof:placetype":"locality"
},
  "geometry": {"coordinates":[-73.137,3.087],"type":"Point"}
}