{
  "type": "Feature",
  "properties": {
    "gn:admin1_code":"9",
    "gn:admin2_code":"19130.0",
    "gn:asciiname":"Tambo Quemado",
    "gn:country_code":"CO",
    "gn:dem":1964,
    "gn:feature_class":"P",
    "gn:feature_code":"PPL",
    "gn:name":"Tambo Quemado",
    "gn:population":0,
    "gn:timezone":"America/Bogota",
    "iso:country":"CO",
    "wof:name":"Tambo Quemado",
    "wof:placetype":"locality"
},
  "geometry": {"coordinates":[-76.82155,2.66684],"type":"Point"}
}