{
  "type": "Feature",
  "properties": {
    "gn:admin1_code":"27",
    "gn:admin2_code":"70702.0",
    "gn:asciiname":"Los Quemados",
    "gn:country_code":"CO",
    "gn:dem":157,
    "gn:feature_class":"P",
    "gn:feature_code":"PPL",
    "gn:name":"Los Quemados",
    "gn:population":0,
    "gn:timezone":"America/Bogota",
    "iso:country":"CO",
    "wof:name":"Los Quemados",
    "wof:placetype":"locality"
},
  "geometry": {"coordinates":[-75.26753000000002,9.22456],"type":"Point"}
}