{
  "type": "Feature",
  "properties": {
    "gn:gn_country":"CO",
    "gn:gn_fcode":"PPLX",
    "gn:gn_pop":0,
    "iso:country":"CO",
    "name:spa_x_colloquial":[
        "Tivoli"
    ],
    "name:spa_x_preferred":[
        "T\u00edvoli"
    ],
    "name:unk_x_variant":[
        "T\u00edvoli"
    ],
    "qs_pg:aaroncc":"CO",
    "qs_pg:gn_country":"CO",
    "qs_pg:gn_fcode":"PPLX",
    "qs_pg:gn_pop":0,
    "qs_pg:name":"T\u00edvoli",
    "qs_pg:name_adm0":"Colombia",
    "qs_pg:name_adm1":"Distrito Especial",
    "qs_pg:photos":184,
    "qs_pg:photos_1k":37,
    "qs_pg:photos_9k":1,
    "qs_pg:photos_9r":4,
    "qs_pg:photos_all":184,
    "qs_pg:photos_sr":4,
    "qs_pg:pop_sr":0,
    "qs_pg:qs_pg_placetype":"neighbourhood",
    "qs_pg:qs_pg_placetype_gp":"Suburb",
    "qs_pg:woe_adm0":23424787,
    "woe:adm0_id":23424787,
    "woe:name_adm0":"Colombia",
    "woe:name_adm1":"Distrito Especial",
    "woe:placetype":"Suburb",
    "wof:name":"T\u00edvoli",
    "wof:placetype":"neighbourhood"
},
  "geometry": {"coordinates":[-74.10142999999999,4.60172],"type":"Point"}
}