{
  "type": "Feature",
  "properties": {
    "gn:admin1_code":"9.0",
    "gn:admin2_code":"19318.0",
    "gn:asciiname":"El Realito",
    "gn:country_code":"CO",
    "gn:dem":33,
    "gn:feature_class":"P",
    "gn:feature_code":"PPL",
    "gn:name":"El Realito",
    "gn:population":0,
    "gn:timezone":"America/Bogota",
    "iso:country":"CO",
    "wof:name":"El Realito",
    "wof:placetype":"locality"
},
  "geometry": {"coordinates":[-77.75644,2.44343],"type":"Point"}
}