{
  "type": "Feature",
  "properties": {
    "gn:admin1_code":"38",
    "gn:admin2_code":"47551.0",
    "gn:asciiname":"El Ocho",
    "gn:country_code":"CO",
    "gn:dem":31,
    "gn:feature_class":"P",
    "gn:feature_code":"PPL",
    "gn:name":"El Ocho",
    "gn:population":0,
    "gn:timezone":"America/Bogota",
    "iso:country":"CO",
    "wof:name":"El Ocho",
    "wof:placetype":"locality"
},
  "geometry": {"coordinates":[-74.28270000000001,10.57158],"type":"Point"}
}