{
  "type": "Feature",
  "properties": {
    "gn:admin1_code":"17",
    "gn:admin2_code":"44847.0",
    "gn:asciiname":"Huatpana",
    "gn:country_code":"CO",
    "gn:dem":-56,
    "gn:feature_class":"P",
    "gn:feature_code":"PPL",
    "gn:name":"Huatpana",
    "gn:population":0,
    "gn:timezone":"America/Bogota",
    "iso:country":"CO",
    "wof:name":"Huatpana",
    "wof:placetype":"locality"
},
  "geometry": {"coordinates":[-71.28213000000002,11.92558],"type":"Point"}
}