{
  "type": "Feature",
  "properties": {
    "gn:admin1_code":"36",
    "gn:admin2_code":"15480.0",
    "gn:asciiname":"Sabripa",
    "gn:country_code":"CO",
    "gn:dem":1236,
    "gn:feature_class":"P",
    "gn:feature_code":"PPL",
    "gn:name":"Sabripa",
    "gn:population":0,
    "gn:timezone":"America/Bogota",
    "iso:country":"CO",
    "wof:name":"Sabripa",
    "wof:placetype":"locality"
},
  "geometry": {"coordinates":[-74.16110999999999,5.56611],"type":"Point"}
}