{
  "type": "Feature",
  "properties": {
    "gn:admin1_code":"10.0",
    "gn:admin2_code":"20011.0",
    "gn:asciiname":"Cascabela",
    "gn:country_code":"CO",
    "gn:dem":152,
    "gn:feature_class":"P",
    "gn:feature_code":"PPL",
    "gn:name":"Cascabela",
    "gn:population":0,
    "gn:timezone":"America/Bogota",
    "iso:country":"CO",
    "name:ceb_x_preferred":[
        "Cascabela"
    ],
    "name:spa_x_preferred":[
        "Cascabela"
    ],
    "name:vie_x_preferred":[
        "Cascabela"
    ],
    "name:war_x_preferred":[
        "Cascabela"
    ],
    "wof:name":"Cascabela",
    "wof:placetype":"locality"
},
  "geometry": {"coordinates":[-73.57203,8.22865],"type":"Point"}
}