{
  "type": "Feature",
  "properties": {
    "gn:admin1_code":"10.0",
    "gn:asciiname":"No Hay Como Dios",
    "gn:country_code":"CO",
    "gn:dem":77,
    "gn:feature_class":"P",
    "gn:feature_code":"PPL",
    "gn:name":"No Hay Como Dios",
    "gn:population":0,
    "gn:timezone":"America/Bogota",
    "iso:country":"CO",
    "wof:name":"No Hay Como Dios",
    "wof:placetype":"locality"
},
  "geometry": {"coordinates":[-74.05086,9.9415],"type":"Point"}
}