{
  "type": "Feature",
  "properties": {
    "gn:admin1_code":"35.0",
    "gn:admin2_code":"13052.0",
    "gn:asciiname":"La Viga",
    "gn:country_code":"CO",
    "gn:dem":37,
    "gn:feature_class":"P",
    "gn:feature_code":"PPL",
    "gn:name":"La Viga",
    "gn:population":0,
    "gn:timezone":"America/Bogota",
    "iso:country":"CO",
    "wof:name":"La Viga",
    "wof:placetype":"locality"
},
  "geometry": {"coordinates":[-75.36805,10.18013],"type":"Point"}
}