{
  "type": "Feature",
  "properties": {
    "gn:admin1_code":"10.0",
    "gn:admin2_code":"20001.0",
    "gn:asciiname":"Petaqueras",
    "gn:country_code":"CO",
    "gn:dem":65,
    "gn:feature_class":"P",
    "gn:feature_code":"PPL",
    "gn:name":"Petaqueras",
    "gn:population":0,
    "gn:timezone":"America/Bogota",
    "iso:country":"CO",
    "wof:name":"Petaqueras",
    "wof:placetype":"locality"
},
  "geometry": {"coordinates":[-73.57890999999999,10.00116],"type":"Point"}
}