{
  "type": "Feature",
  "properties": {
    "gn:admin1_code":"27",
    "gn:admin2_code":"70429.0",
    "gn:asciiname":"Guayabal",
    "gn:country_code":"CO",
    "gn:dem":11,
    "gn:feature_class":"P",
    "gn:feature_code":"PPL",
    "gn:name":"Guayabal",
    "gn:population":0,
    "gn:timezone":"America/Bogota",
    "iso:country":"CO",
    "name:ceb_x_preferred":[
        "Guayabal"
    ],
    "name:deu_x_preferred":[
        "Guayabal"
    ],
    "name:fra_x_preferred":[
        "Guayabal"
    ],
    "name:ita_x_preferred":[
        "Guayabal"
    ],
    "name:nld_x_preferred":[
        "Guayabal"
    ],
    "name:por_x_preferred":[
        "Guayabal"
    ],
    "name:sco_x_preferred":[
        "Guayabal"
    ],
    "name:spa_x_preferred":[
        "Guayabal"
    ],
    "name:swe_x_preferred":[
        "Guayabal"
    ],
    "name:und_x_variant":[
        "Hacienda Guayabal"
    ],
    "wof:name":"Guayabal",
    "wof:placetype":"locality"
},
  "geometry": {"coordinates":[-74.70904,8.69257],"type":"Point"}
}