{
  "type": "Feature",
  "properties": {
    "gn:admin1_code":"32.0",
    "gn:admin2_code":"85230.0",
    "gn:asciiname":"Platanales",
    "gn:cc2":"CO",
    "gn:country_code":"CO",
    "gn:dem":139,
    "gn:feature_class":"P",
    "gn:feature_code":"PPL",
    "gn:name":"Platanales",
    "gn:population":0,
    "gn:timezone":"America/Bogota",
    "iso:country":"CO",
    "name:und_x_variant":[
        "Palamates",
        "Platanales"
    ],
    "wof:name":"Platanales",
    "wof:placetype":"locality"
},
  "geometry": {"coordinates":[-71.73333000000002,4.63333],"type":"Point"}
}