{
  "type": "Feature",
  "properties": {
    "gn:admin1_code":"26",
    "gn:admin2_code":"68689.0",
    "gn:asciiname":"El Seis",
    "gn:country_code":"CO",
    "gn:dem":526,
    "gn:feature_class":"P",
    "gn:feature_code":"PPL",
    "gn:name":"El Seis",
    "gn:population":0,
    "gn:timezone":"America/Bogota",
    "iso:country":"CO",
    "wof:name":"El Seis",
    "wof:placetype":"locality"
},
  "geometry": {"coordinates":[-73.53333000000001,7.01667],"type":"Point"}
}