{
  "type": "Feature",
  "properties": {
    "gn:admin1_code":"20",
    "gn:admin2_code":"52835.0",
    "gn:asciiname":"Guayacanes",
    "gn:cc2":"CO",
    "gn:country_code":"CO",
    "gn:dem":9,
    "gn:feature_class":"P",
    "gn:feature_code":"PPL",
    "gn:name":"Guayacanes",
    "gn:population":0,
    "gn:timezone":"America/Bogota",
    "iso:country":"CO",
    "name:spa_x_preferred":[
        "Guayacanes"
    ],
    "name:und_x_variant":[
        "Guayacana",
        "Guayacanes"
    ],
    "wof:name":"Guayacanes",
    "wof:placetype":"locality"
},
  "geometry": {"coordinates":[-78.75583,1.66972],"type":"Point"}
}