{
  "type": "Feature",
  "properties": {
    "gn:admin1_code":"16.0",
    "gn:admin2_code":"41396.0",
    "gn:asciiname":"Villa Aucia",
    "gn:country_code":"CO",
    "gn:dem":1370,
    "gn:feature_class":"P",
    "gn:feature_code":"PPL",
    "gn:name":"Villa Aucia",
    "gn:population":0,
    "gn:timezone":"America/Bogota",
    "iso:country":"CO",
    "wof:name":"Villa Aucia",
    "wof:placetype":"locality"
},
  "geometry": {"coordinates":[-75.94745,2.45879],"type":"Point"}
}