{
  "type": "Feature",
  "properties": {
    "gn:admin1_code":"36.0",
    "gn:admin2_code":"15276.0",
    "gn:asciiname":"Tobasia",
    "gn:country_code":"CO",
    "gn:dem":2522,
    "gn:feature_class":"P",
    "gn:feature_code":"PPL",
    "gn:name":"Tobas\u00eda",
    "gn:population":0,
    "gn:timezone":"America/Bogota",
    "iso:country":"CO",
    "wof:name":"Tobasia",
    "wof:placetype":"locality"
},
  "geometry": {"coordinates":[-72.94360999999998,5.85812],"type":"Point"}
}