{
  "type": "Feature",
  "properties": {
    "gn:admin1_code":"3",
    "gn:admin2_code":"81220.0",
    "gn:asciiname":"Atanasio",
    "gn:country_code":"CO",
    "gn:dem":109,
    "gn:feature_class":"P",
    "gn:feature_code":"PPL",
    "gn:name":"Atanasio",
    "gn:population":0,
    "gn:timezone":"America/Bogota",
    "iso:country":"CO",
    "name:ita_x_preferred":[
        "Atanasio"
    ],
    "name:spa_x_preferred":[
        "Atanasio"
    ],
    "wof:name":"Atanasio",
    "wof:placetype":"locality"
},
  "geometry": {"coordinates":[-70.51666999999998,6.41667],"type":"Point"}
}