{
  "type": "Feature",
  "properties": {
    "gn:admin1_code":"2.0",
    "gn:admin2_code":"5042.0",
    "gn:asciiname":"El Cinco",
    "gn:country_code":"CO",
    "gn:dem":667,
    "gn:feature_class":"P",
    "gn:feature_code":"PPL",
    "gn:name":"El Cinco",
    "gn:population":0,
    "gn:timezone":"America/Bogota",
    "iso:country":"CO",
    "wof:name":"El Cinco",
    "wof:placetype":"locality"
},
  "geometry": {"coordinates":[-75.87028000000002,6.555],"type":"Point"}
}