{
  "type": "Feature",
  "properties": {
    "gn:admin1_code":"32",
    "gn:admin2_code":"85263.0",
    "gn:asciiname":"Caserio Regalito",
    "gn:country_code":"CO",
    "gn:dem":199,
    "gn:feature_class":"P",
    "gn:feature_code":"PPL",
    "gn:name":"Caser\u00edo Regalito",
    "gn:population":0,
    "gn:timezone":"America/Bogota",
    "iso:country":"CO",
    "wof:name":"Caserio Regalito",
    "wof:placetype":"locality"
},
  "geometry": {"coordinates":[-71.89135999999998,5.56368],"type":"Point"}
}