{
  "type": "Feature",
  "properties": {
    "gn:admin1_code":"17",
    "gn:admin2_code":"44847.0",
    "gn:asciiname":"Jipahin",
    "gn:country_code":"CO",
    "gn:dem":51,
    "gn:feature_class":"P",
    "gn:feature_code":"PPL",
    "gn:name":"Jipahin",
    "gn:population":0,
    "gn:timezone":"America/Bogota",
    "iso:country":"CO",
    "wof:name":"Jipahin",
    "wof:placetype":"locality"
},
  "geometry": {"coordinates":[-72.12628000000002,11.77298],"type":"Point"}
}