{
  "type": "Feature",
  "properties": {
    "gn:admin1_code":"11",
    "gn:admin2_code":"27660.0",
    "gn:asciiname":"El Pozo",
    "gn:country_code":"CO",
    "gn:dem":485,
    "gn:feature_class":"P",
    "gn:feature_code":"PPL",
    "gn:name":"El Pozo",
    "gn:population":0,
    "gn:timezone":"America/Bogota",
    "iso:country":"CO",
    "wof:name":"El Pozo",
    "wof:placetype":"locality"
},
  "geometry": {"coordinates":[-76.38333,4.95],"type":"Point"}
}