{
  "type": "Feature",
  "properties": {
    "gn:admin1_code":"20.0",
    "gn:admin2_code":"52678.0",
    "gn:asciiname":"Sacampues",
    "gn:country_code":"CO",
    "gn:dem":1853,
    "gn:feature_class":"P",
    "gn:feature_code":"PPL",
    "gn:name":"Sacampues",
    "gn:population":0,
    "gn:timezone":"America/Bogota",
    "iso:country":"CO",
    "wof:name":"Sacampues",
    "wof:placetype":"locality"
},
  "geometry": {"coordinates":[-77.58333,1.41667],"type":"Point"}
}