{
  "type": "Feature",
  "properties": {
    "gn:admin1_code":"10.0",
    "gn:admin2_code":"20175.0",
    "gn:asciiname":"Sempegua",
    "gn:country_code":"CO",
    "gn:dem":32,
    "gn:feature_class":"P",
    "gn:feature_code":"PPL",
    "gn:name":"Sempegua",
    "gn:population":0,
    "gn:timezone":"America/Bogota",
    "iso:country":"CO",
    "name:und_x_variant":[
        "Corregimiento Sempegua",
        "Sempegua"
    ],
    "wof:name":"Sempegua",
    "wof:placetype":"locality"
},
  "geometry": {"coordinates":[-73.83776999999998,9.1646],"type":"Point"}
}