{
  "type": "Feature",
  "properties": {
    "gn:admin1_code":"32",
    "gn:admin2_code":"85139.0",
    "gn:asciiname":"La Dorada",
    "gn:cc2":"CO",
    "gn:country_code":"CO",
    "gn:dem":179,
    "gn:feature_class":"P",
    "gn:feature_code":"PPL",
    "gn:name":"La Dorada",
    "gn:population":0,
    "gn:timezone":"America/Bogota",
    "iso:country":"CO",
    "name:und_x_variant":[
        "Dorada",
        "La Dorada"
    ],
    "wof:name":"La Dorada",
    "wof:placetype":"locality"
},
  "geometry": {"coordinates":[-72.28333000000001,4.81667],"type":"Point"}
}