{
  "type": "Feature",
  "properties": {
    "gn:admin1_code":"20",
    "gn:admin2_code":"52786.0",
    "gn:asciiname":"La Cocha",
    "gn:country_code":"CO",
    "gn:dem":1278,
    "gn:feature_class":"P",
    "gn:feature_code":"PPL",
    "gn:name":"La Cocha",
    "gn:population":0,
    "gn:timezone":"America/Bogota",
    "iso:country":"CO",
    "name:ceb_x_preferred":[
        "La Cocha"
    ],
    "name:deu_x_preferred":[
        "La Cocha"
    ],
    "name:ita_x_preferred":[
        "La Cocha"
    ],
    "name:nld_x_preferred":[
        "La Cocha"
    ],
    "name:por_x_preferred":[
        "La Cocha"
    ],
    "name:spa_x_preferred":[
        "La Cocha"
    ],
    "name:urd_x_preferred":[
        "\u0644\u0627 \u06a9\u0648\u0686\u0627"
    ],
    "name:zho_x_preferred":[
        "\u62c9\u79d1\u67e5"
    ],
    "wof:name":"La Cocha",
    "wof:placetype":"locality"
},
  "geometry": {"coordinates":[-77.28986999999999,1.59885],"type":"Point"}
}