{
  "type": "Feature",
  "properties": {
    "gn:admin1_code":"12.0",
    "gn:admin2_code":"23660.0",
    "gn:asciiname":"Salitral",
    "gn:country_code":"CO",
    "gn:dem":78,
    "gn:feature_class":"P",
    "gn:feature_code":"PPLL",
    "gn:name":"Salitral",
    "gn:population":0,
    "gn:timezone":"America/Bogota",
    "iso:country":"CO",
    "wof:name":"Salitral",
    "wof:placetype":"locality"
},
  "geometry": {"coordinates":[-75.52136,8.82554],"type":"Point"}
}