{
  "type": "Feature",
  "properties": {
    "gn:admin1_code":"38.0",
    "gn:admin2_code":"47460.0",
    "gn:asciiname":"Montevirgen",
    "gn:country_code":"CO",
    "gn:dem":80,
    "gn:feature_class":"P",
    "gn:feature_code":"PPL",
    "gn:name":"Montevirgen",
    "gn:population":0,
    "gn:timezone":"America/Bogota",
    "iso:country":"CO",
    "wof:name":"Montevirgen",
    "wof:placetype":"locality"
},
  "geometry": {"coordinates":[-74.396,9.71157],"type":"Point"}
}