{
  "type": "Feature",
  "properties": {
    "gn:admin1_code":"37",
    "gn:admin2_code":"17524.0",
    "gn:asciiname":"El Encanto",
    "gn:cc2":"CO",
    "gn:country_code":"CO",
    "gn:dem":1204,
    "gn:feature_class":"P",
    "gn:feature_code":"PPL",
    "gn:name":"El Encanto",
    "gn:population":0,
    "gn:timezone":"America/Bogota",
    "iso:country":"CO",
    "name:cat_x_preferred":[
        "El Encanto"
    ],
    "name:ceb_x_preferred":[
        "El Encanto"
    ],
    "name:fra_x_preferred":[
        "El Encanto"
    ],
    "name:heb_x_preferred":[
        "\u05d0\u05dc \u05d0\u05e0\u05e7\u05e0\u05d8\u05d5"
    ],
    "name:ilo_x_preferred":[
        "El Encanto"
    ],
    "name:ita_x_preferred":[
        "El Encanto"
    ],
    "name:msa_x_preferred":[
        "El Encanto"
    ],
    "name:nld_x_preferred":[
        "El Encanto"
    ],
    "name:por_x_preferred":[
        "El Encanto"
    ],
    "name:rus_x_preferred":[
        "\u042d\u043b\u044c-\u042d\u043d\u043a\u0430\u043d\u0442\u043e"
    ],
    "name:spa_x_preferred":[
        "El Encanto"
    ],
    "name:swe_x_preferred":[
        "El Encanto"
    ],
    "name:tgl_x_preferred":[
        "El Encanto"
    ],
    "name:und_x_variant":[
        "Encanto",
        "El Encanto"
    ],
    "name:vie_x_preferred":[
        "El Encanto"
    ],
    "name:war_x_preferred":[
        "El Encanto"
    ],
    "name:zho_x_preferred":[
        "\u57c3\u723e\u6069\u574e\u6258"
    ],
    "wof:name":"El Encanto",
    "wof:placetype":"locality"
},
  "geometry": {"coordinates":[-75.63333,5.05],"type":"Point"}
}