{
  "type": "Feature",
  "properties": {
    "gn:admin1_code":"4",
    "gn:admin2_code":"8638.0",
    "gn:asciiname":"Cascajal",
    "gn:country_code":"CO",
    "gn:dem":58,
    "gn:feature_class":"P",
    "gn:feature_code":"PPL",
    "gn:name":"Cascajal",
    "gn:population":0,
    "gn:timezone":"America/Bogota",
    "iso:country":"CO",
    "name:und_x_variant":[
        "Corregimiento Cascajal",
        "Cascajal"
    ],
    "wof:name":"Cascajal",
    "wof:placetype":"locality"
},
  "geometry": {"coordinates":[-74.85008000000001,10.59842],"type":"Point"}
}