{
  "type": "Feature",
  "properties": {
    "gn:admin1_code":"24.0",
    "gn:admin2_code":"66456.0",
    "gn:asciiname":"Hoyo Hondo",
    "gn:country_code":"CO",
    "gn:dem":2393,
    "gn:feature_class":"P",
    "gn:feature_code":"PPL",
    "gn:name":"Hoyo Hondo",
    "gn:population":0,
    "gn:timezone":"America/Bogota",
    "iso:country":"CO",
    "wof:name":"Hoyo Hondo",
    "wof:placetype":"locality"
},
  "geometry": {"coordinates":[-75.85444,5.47917],"type":"Point"}
}