{
  "type": "Feature",
  "properties": {
    "gn:admin1_code":"21",
    "gn:admin2_code":"54206.0",
    "gn:asciiname":"Bohio Okbadukayra",
    "gn:country_code":"CO",
    "gn:dem":97,
    "gn:feature_class":"P",
    "gn:feature_code":"PPL",
    "gn:name":"Boh\u00edo Okbadukayra",
    "gn:population":0,
    "gn:timezone":"America/Bogota",
    "iso:country":"CO",
    "wof:name":"Bohio Okbadukayra",
    "wof:placetype":"locality"
},
  "geometry": {"coordinates":[-73.01286999999998,9.09649],"type":"Point"}
}