{
  "type": "Feature",
  "properties": {
    "gn:admin1_code":"16.0",
    "gn:admin2_code":"41872.0",
    "gn:asciiname":"San Alfonso",
    "gn:country_code":"CO",
    "gn:dem":396,
    "gn:feature_class":"P",
    "gn:feature_code":"PPL",
    "gn:name":"San Alfonso",
    "gn:population":0,
    "gn:timezone":"America/Bogota",
    "iso:country":"CO",
    "name:spa_x_preferred":[
        "San Alfonso"
    ],
    "wof:name":"San Alfonso",
    "wof:placetype":"locality"
},
  "geometry": {"coordinates":[-75.11183,3.37146],"type":"Point"}
}