{
  "type": "Feature",
  "properties": {
    "gn:admin1_code":"20",
    "gn:admin2_code":"52390.0",
    "gn:asciiname":"Los Mulatos",
    "gn:country_code":"CO",
    "gn:dem":1,
    "gn:feature_class":"P",
    "gn:feature_code":"PPL",
    "gn:name":"Los Mulatos",
    "gn:population":0,
    "gn:timezone":"America/Bogota",
    "iso:country":"CO",
    "wof:name":"Los Mulatos",
    "wof:placetype":"locality"
},
  "geometry": {"coordinates":[-78.28583,2.65582],"type":"Point"}
}