{
  "type": "Feature",
  "properties": {
    "gn:admin1_code":"21",
    "gn:admin2_code":"54001.0",
    "gn:asciiname":"Palmarito",
    "gn:cc2":"CO",
    "gn:country_code":"CO",
    "gn:dem":63,
    "gn:feature_class":"P",
    "gn:feature_code":"PPL",
    "gn:name":"Palmarito",
    "gn:population":0,
    "gn:timezone":"America/Bogota",
    "iso:country":"CO",
    "name:spa_x_preferred":[
        "Palmarito"
    ],
    "name:und_x_variant":[
        "Palmarcito"
    ],
    "wof:name":"Palmarito",
    "wof:placetype":"locality"
},
  "geometry": {"coordinates":[-72.48583000000001,8.31361],"type":"Point"}
}