{
  "type": "Feature",
  "properties": {
    "gn:admin1_code":"19",
    "gn:admin2_code":"50001.0",
    "gn:asciiname":"El Cruce de Ocoa",
    "gn:country_code":"CO",
    "gn:dem":235,
    "gn:feature_class":"P",
    "gn:feature_code":"PPL",
    "gn:name":"El Cruce de Ocoa",
    "gn:population":0,
    "gn:timezone":"America/Bogota",
    "iso:country":"CO",
    "wof:name":"El Cruce de Ocoa",
    "wof:placetype":"locality"
},
  "geometry": {"coordinates":[-73.27569,4.11729],"type":"Point"}
}