{
  "type": "Feature",
  "properties": {
    "gn:admin1_code":"12.0",
    "gn:admin2_code":"23001.0",
    "gn:asciiname":"Galilea",
    "gn:country_code":"CO",
    "gn:dem":37,
    "gn:feature_class":"P",
    "gn:feature_code":"PPLL",
    "gn:name":"Galilea",
    "gn:population":0,
    "gn:timezone":"America/Bogota",
    "iso:country":"CO",
    "wof:name":"Galilea",
    "wof:placetype":"locality"
},
  "geometry": {"coordinates":[-75.89694,8.59028],"type":"Point"}
}