{
  "type": "Feature",
  "properties": {
    "gn:admin1_code":"29",
    "gn:admin2_code":"76869.0",
    "gn:asciiname":"La Merceo",
    "gn:country_code":"CO",
    "gn:dem":1445,
    "gn:feature_class":"P",
    "gn:feature_code":"PPL",
    "gn:name":"La Merceo",
    "gn:population":0,
    "gn:timezone":"America/Bogota",
    "iso:country":"CO",
    "wof:name":"La Merceo",
    "wof:placetype":"locality"
},
  "geometry": {"coordinates":[-76.47833,3.79583],"type":"Point"}
}