{
  "type": "Feature",
  "properties": {
    "gn:admin1_code":"17",
    "gn:admin2_code":"44847.0",
    "gn:asciiname":"Katerruohu",
    "gn:cc2":"CO",
    "gn:country_code":"CO",
    "gn:dem":-57,
    "gn:feature_class":"P",
    "gn:feature_code":"PPL",
    "gn:name":"Kat\u00e9rruohu",
    "gn:population":0,
    "gn:timezone":"America/Bogota",
    "iso:country":"CO",
    "name:und_x_variant":[
        "Caterouri",
        "Kat\u00e9rruohu"
    ],
    "wof:name":"Katerruohu",
    "wof:placetype":"locality"
},
  "geometry": {"coordinates":[-71.46666999999999,12.38333],"type":"Point"}
}