{
  "type": "Feature",
  "properties": {
    "gn:admin1_code":"17",
    "gn:admin2_code":"44847.0",
    "gn:asciiname":"Kashure",
    "gn:cc2":"CO",
    "gn:country_code":"CO",
    "gn:dem":13,
    "gn:feature_class":"P",
    "gn:feature_code":"PPL",
    "gn:name":"Kashure",
    "gn:population":0,
    "gn:timezone":"America/Bogota",
    "iso:country":"CO",
    "name:und_x_variant":[
        "Kachure",
        "Kashure"
    ],
    "wof:name":"Kashure",
    "wof:placetype":"locality"
},
  "geometry": {"coordinates":[-72.11667,11.56667],"type":"Point"}
}