{
  "type": "Feature",
  "properties": {
    "gn:admin1_code":"4.0",
    "gn:admin2_code":"8433.0",
    "gn:asciiname":"La Samaria",
    "gn:country_code":"CO",
    "gn:dem":38,
    "gn:feature_class":"P",
    "gn:feature_code":"PPL",
    "gn:name":"La Samaria",
    "gn:population":0,
    "gn:timezone":"America/Bogota",
    "iso:country":"CO",
    "wof:name":"La Samaria",
    "wof:placetype":"locality"
},
  "geometry": {"coordinates":[-74.7932,10.83579],"type":"Point"}
}