{
  "type": "Feature",
  "properties": {
    "gn:admin1_code":"38.0",
    "gn:admin2_code":"47058.0",
    "gn:asciiname":"Quitapesares",
    "gn:country_code":"CO",
    "gn:dem":109,
    "gn:feature_class":"P",
    "gn:feature_code":"PPL",
    "gn:name":"Quitapesares",
    "gn:population":0,
    "gn:timezone":"America/Bogota",
    "iso:country":"CO",
    "wof:name":"Quitapesares",
    "wof:placetype":"locality"
},
  "geometry": {"coordinates":[-74.05,9.85],"type":"Point"}
}