{
  "type": "Feature",
  "properties": {
    "gn:admin1_code":"20",
    "gn:admin2_code":"52256.0",
    "gn:asciiname":"Monton",
    "gn:country_code":"CO",
    "gn:dem":1747,
    "gn:feature_class":"P",
    "gn:feature_code":"PPL",
    "gn:name":"Mont\u00f3n",
    "gn:population":0,
    "gn:timezone":"America/Bogota",
    "iso:country":"CO",
    "wof:name":"Monton",
    "wof:placetype":"locality"
},
  "geometry": {"coordinates":[-77.37626999999998,1.78567],"type":"Point"}
}