{
  "type": "Feature",
  "properties": {
    "gn:admin1_code":"1",
    "gn:admin2_code":"91798.0",
    "gn:asciiname":"Gaudencio",
    "gn:country_code":"CO",
    "gn:dem":86,
    "gn:feature_class":"P",
    "gn:feature_code":"PPL",
    "gn:name":"Gaudencio",
    "gn:population":0,
    "gn:timezone":"America/Bogota",
    "iso:country":"CO",
    "name:und_x_variant":[
        "Candencio",
        "Viriva Gaudencia",
        "Goudencia",
        "Gaudencia",
        "Gaudencio"
    ],
    "wof:name":"Gaudencio",
    "wof:placetype":"locality"
},
  "geometry": {"coordinates":[-70.30634999999999,-2.49595],"type":"Point"}
}