{
  "type": "Feature",
  "properties": {
    "gn:admin1_code":"29",
    "gn:admin2_code":"76130.0",
    "gn:asciiname":"La Alianza",
    "gn:country_code":"CO",
    "gn:dem":976,
    "gn:feature_class":"P",
    "gn:feature_code":"PPL",
    "gn:name":"La Alianza",
    "gn:population":0,
    "gn:timezone":"America/Bogota",
    "iso:country":"CO",
    "wof:name":"La Alianza",
    "wof:placetype":"locality"
},
  "geometry": {"coordinates":[-76.34999999999999,3.38333],"type":"Point"}
}