{
  "type": "Feature",
  "properties": {
    "gn:admin1_code":"2",
    "gn:admin2_code":"5642.0",
    "gn:asciiname":"Capachero",
    "gn:country_code":"CO",
    "gn:dem":1987,
    "gn:feature_class":"P",
    "gn:feature_code":"PPL",
    "gn:name":"Capachero",
    "gn:population":0,
    "gn:timezone":"America/Bogota",
    "iso:country":"CO",
    "wof:name":"Capachero",
    "wof:placetype":"locality"
},
  "geometry": {"coordinates":[-76.01666999999998,6.01667],"type":"Point"}
}