{
  "type": "Feature",
  "properties": {
    "iso:country":"CO",
    "qs:gn_country":"CO",
    "qs:gn_fcode":"PPL",
    "qs:gn_pop":0,
    "qs:name":"Maracaibo",
    "qs:name_adm0":"Venezuela",
    "qs:name_adm1":"Zulia",
    "qs:photos":2830,
    "qs:photos_1k":573,
    "qs:photos_9k":21,
    "qs:photos_9r":13,
    "qs:photos_all":4788,
    "qs:photos_sr":19,
    "qs:placetype":"Town",
    "qs:pop_sr":"0",
    "qs:woe_adm0":23424982,
    "wd:wordcount":3537,
    "wof:name":"Maracaibo",
    "wof:placetype":"locality"
},
  "geometry": {"coordinates":[-72.26043,11.3287],"type":"Point"}
}