{
  "type": "Feature",
  "properties": {
    "gn:admin1_code":"2.0",
    "gn:admin2_code":"5790.0",
    "gn:asciiname":"Puerto Antioquia",
    "gn:country_code":"CO",
    "gn:dem":105,
    "gn:feature_class":"P",
    "gn:feature_code":"PPL",
    "gn:name":"Puerto Antioquia",
    "gn:population":0,
    "gn:timezone":"America/Bogota",
    "iso:country":"CO",
    "name:und_x_variant":[
        "Puerto Ospina",
        "Puerto Antioquia"
    ],
    "wof:name":"Puerto Antioquia",
    "wof:placetype":"locality"
},
  "geometry": {"coordinates":[-75.34390999999999,7.53993],"type":"Point"}
}