{
  "type": "Feature",
  "properties": {
    "gn:admin1_code":"11",
    "gn:admin2_code":"27025.0",
    "gn:asciiname":"Antonio Salguero",
    "gn:country_code":"CO",
    "gn:dem":107,
    "gn:feature_class":"P",
    "gn:feature_code":"PPL",
    "gn:name":"Antonio Salguero",
    "gn:population":0,
    "gn:timezone":"America/Bogota",
    "iso:country":"CO",
    "wof:name":"Antonio Salguero",
    "wof:placetype":"locality"
},
  "geometry": {"coordinates":[-77.01666999999998,5.56667],"type":"Point"}
}