{
  "type": "Feature",
  "properties": {
    "gn:admin1_code":"10",
    "gn:admin2_code":"20383.0",
    "gn:asciiname":"Lucerna",
    "gn:country_code":"CO",
    "gn:dem":36,
    "gn:feature_class":"P",
    "gn:feature_code":"PPL",
    "gn:name":"Lucerna",
    "gn:population":0,
    "gn:timezone":"America/Bogota",
    "iso:country":"CO",
    "name:ceb_x_preferred":[
        "Lucerna"
    ],
    "name:ces_x_preferred":[
        "Lucerna"
    ],
    "name:deu_x_preferred":[
        "Lucerna"
    ],
    "name:fra_x_preferred":[
        "Lucerna"
    ],
    "name:glg_x_preferred":[
        "Lucerna"
    ],
    "name:hun_x_preferred":[
        "Lucerna"
    ],
    "name:ita_x_preferred":[
        "Lucerna"
    ],
    "name:lat_x_preferred":[
        "Lucerna"
    ],
    "name:lav_x_preferred":[
        "Lucerna"
    ],
    "name:nld_x_preferred":[
        "Lucerna"
    ],
    "name:por_x_preferred":[
        "Lucerna"
    ],
    "name:ron_x_preferred":[
        "Lucerna"
    ],
    "name:rus_x_preferred":[
        "\u041b\u044e\u0446\u0435\u0440\u043d\u0430"
    ],
    "name:slk_x_preferred":[
        "Lucerna"
    ],
    "name:spa_x_preferred":[
        "Lucerna"
    ],
    "name:swe_x_preferred":[
        "Lucerna"
    ],
    "name:ukr_x_preferred":[
        "\u041b\u044e\u0446\u0435\u0440\u043d\u0430"
    ],
    "wof:name":"Lucerna",
    "wof:placetype":"locality"
},
  "geometry": {"coordinates":[-73.76666999999998,8.63333],"type":"Point"}
}