{
  "type": "Feature",
  "properties": {
    "gn:admin1_code":"10",
    "gn:admin2_code":"20383.0",
    "gn:asciiname":"Lucerna",
    "gn:country_code":"CO",
    "gn:dem":36,
    "gn:feature_class":"P",
    "gn:feature_code":"PPL",
    "gn:name":"Lucerna",
    "gn:population":0,
    "gn:timezone":"America/Bogota",
    "iso:country":"CO",
    "wof:name":"Lucerna",
    "wof:placetype":"locality"
},
  "geometry": {"coordinates":[-73.76666999999998,8.63333],"type":"Point"}
}