{
  "type": "Feature",
  "properties": {
    "gn:admin1_code":"19.0",
    "gn:admin2_code":"50689.0",
    "gn:asciiname":"El Retiro",
    "gn:country_code":"CO",
    "gn:dem":252,
    "gn:feature_class":"P",
    "gn:feature_code":"PPLL",
    "gn:name":"El Retiro",
    "gn:population":0,
    "gn:timezone":"America/Bogota",
    "iso:country":"CO",
    "name:spa_x_preferred":[
        "El Retiro"
    ],
    "wof:name":"El Retiro",
    "wof:placetype":"locality"
},
  "geometry": {"coordinates":[-73.01958,3.55278],"type":"Point"}
}