{
  "type": "Feature",
  "properties": {
    "gn:admin1_code":"2.0",
    "gn:admin2_code":"5001.0",
    "gn:asciiname":"Morro Contento",
    "gn:country_code":"CO",
    "gn:dem":1878,
    "gn:feature_class":"P",
    "gn:feature_code":"PPL",
    "gn:name":"Morro Contento",
    "gn:population":0,
    "gn:timezone":"America/Bogota",
    "iso:country":"CO",
    "name:spa_x_preferred":[
        "Morro Contento"
    ],
    "wof:name":"Morro Contento",
    "wof:placetype":"locality"
},
  "geometry": {"coordinates":[-75.62599,6.27089],"type":"Point"}
}