{
  "type": "Feature",
  "properties": {
    "gn:admin1_code":"10.0",
    "gn:admin2_code":"20011.0",
    "gn:asciiname":"Bella Luz",
    "gn:country_code":"CO",
    "gn:dem":73,
    "gn:feature_class":"P",
    "gn:feature_code":"PPL",
    "gn:name":"Bella Luz",
    "gn:population":0,
    "gn:timezone":"America/Bogota",
    "iso:country":"CO",
    "name:spa_x_preferred":[
        "Bella Luz"
    ],
    "wof:name":"Bella Luz",
    "wof:placetype":"locality"
},
  "geometry": {"coordinates":[-73.65335,8.14883],"type":"Point"}
}