{
  "type": "Feature",
  "properties": {
    "gn:admin1_code":"2.0",
    "gn:admin2_code":"5042.0",
    "gn:asciiname":"El Catorce",
    "gn:country_code":"CO",
    "gn:dem":996,
    "gn:feature_class":"P",
    "gn:feature_code":"PPL",
    "gn:name":"El Catorce",
    "gn:population":0,
    "gn:timezone":"America/Bogota",
    "iso:country":"CO",
    "wof:name":"El Catorce",
    "wof:placetype":"locality"
},
  "geometry": {"coordinates":[-75.89361,6.61917],"type":"Point"}
}