{
  "type": "Feature",
  "properties": {
    "gn:admin1_code":"28.0",
    "gn:admin2_code":"73504.0",
    "gn:asciiname":"Paloma",
    "gn:cc2":"CO",
    "gn:country_code":"CO",
    "gn:dem":510,
    "gn:feature_class":"P",
    "gn:feature_code":"PPL",
    "gn:name":"Paloma",
    "gn:population":0,
    "gn:timezone":"America/Bogota",
    "iso:country":"CO",
    "name:und_x_variant":[
        "Palomas",
        "Paloma"
    ],
    "wof:name":"Paloma",
    "wof:placetype":"locality"
},
  "geometry": {"coordinates":[-75.30667,3.89722],"type":"Point"}
}