{
  "type": "Feature",
  "properties": {
    "gn:admin1_code":"2.0",
    "gn:admin2_code":"5042.0",
    "gn:asciiname":"Pantanillo",
    "gn:country_code":"CO",
    "gn:dem":1905,
    "gn:feature_class":"P",
    "gn:feature_code":"PPL",
    "gn:name":"Pantanillo",
    "gn:population":0,
    "gn:timezone":"America/Bogota",
    "iso:country":"CO",
    "wof:name":"Pantanillo",
    "wof:placetype":"locality"
},
  "geometry": {"coordinates":[-75.925,6.60278],"type":"Point"}
}