{
  "type": "Feature",
  "properties": {
    "gn:admin1_code":"2.0",
    "gn:admin2_code":"5001.0",
    "gn:asciiname":"Rio de Janeiro",
    "gn:country_code":"CO",
    "gn:dem":1980,
    "gn:feature_class":"P",
    "gn:feature_code":"PPL",
    "gn:name":"R\u00edo de Janeiro",
    "gn:population":0,
    "gn:timezone":"America/Bogota",
    "iso:country":"CO",
    "name:spa_x_preferred":[
        "R\u00edo de Janeiro"
    ],
    "wof:name":"Rio de Janeiro",
    "wof:placetype":"locality"
},
  "geometry": {"coordinates":[-75.61506,6.28635],"type":"Point"}
}