{
  "type": "Feature",
  "properties": {
    "gn:admin1_code":"26.0",
    "gn:admin2_code":"68533.0",
    "gn:asciiname":"El Moral",
    "gn:country_code":"CO",
    "gn:dem":1339,
    "gn:feature_class":"P",
    "gn:feature_code":"PPL",
    "gn:name":"El Moral",
    "gn:population":0,
    "gn:timezone":"America/Bogota",
    "iso:country":"CO",
    "wof:name":"El Moral",
    "wof:placetype":"locality"
},
  "geometry": {"coordinates":[-73.15593,6.45552],"type":"Point"}
}