{
  "type": "Feature",
  "properties": {
    "gn:admin1_code":"27",
    "gn:admin2_code":"70823.0",
    "gn:asciiname":"El Floral",
    "gn:country_code":"CO",
    "gn:dem":81,
    "gn:feature_class":"P",
    "gn:feature_code":"PPL",
    "gn:name":"El Floral",
    "gn:population":0,
    "gn:timezone":"America/Bogota",
    "iso:country":"CO",
    "name:und_x_variant":[
        "Caser\u00edo El Floral",
        "El Floral"
    ],
    "wof:name":"El Floral",
    "wof:placetype":"locality"
},
  "geometry": {"coordinates":[-75.4359,9.40538],"type":"Point"}
}