{
  "type": "Feature",
  "properties": {
    "gn:admin1_code":"38.0",
    "gn:admin2_code":"47318.0",
    "gn:asciiname":"Mogollon",
    "gn:country_code":"CO",
    "gn:dem":57,
    "gn:feature_class":"P",
    "gn:feature_code":"PPL",
    "gn:name":"Mogoll\u00f3n",
    "gn:population":0,
    "gn:timezone":"America/Bogota",
    "iso:country":"CO",
    "name:deu_x_preferred":[
        "Mogollon"
    ],
    "name:ita_x_preferred":[
        "Mogoll\u00f3n"
    ],
    "name:rus_x_preferred":[
        "\u041c\u043e\u0433\u043e\u043b\u044c\u043e\u043d"
    ],
    "name:spa_x_preferred":[
        "Mogoll\u00f3n"
    ],
    "wof:name":"Mogollon",
    "wof:placetype":"locality"
},
  "geometry": {"coordinates":[-74.14165,9.31212],"type":"Point"}
}