{
  "type": "Feature",
  "properties": {
    "gn:admin1_code":"9.0",
    "gn:admin2_code":"19532.0",
    "gn:asciiname":"Santa Cruz",
    "gn:country_code":"CO",
    "gn:dem":1229,
    "gn:feature_class":"P",
    "gn:feature_code":"PPL",
    "gn:name":"Santa Cruz",
    "gn:population":0,
    "gn:timezone":"America/Bogota",
    "iso:country":"CO",
    "name:arg_x_preferred":[
        "Santa Cruz"
    ],
    "name:ast_x_preferred":[
        "Santa Cruz"
    ],
    "name:bel_x_preferred":[
        "\u0421\u0430\u043d\u0442\u0430-\u041a\u0440\u0443\u0441"
    ],
    "name:bre_x_preferred":[
        "Santa Cruz"
    ],
    "name:bul_x_preferred":[
        "\u0421\u0430\u043d\u0442\u0430 \u041a\u0440\u0443\u0437"
    ],
    "name:cat_x_preferred":[
        "Santa Cruz"
    ],
    "name:ceb_x_preferred":[
        "Santa Cruz"
    ],
    "name:ces_x_preferred":[
        "Santa Cruz"
    ],
    "name:cym_x_preferred":[
        "Santa Cruz"
    ],
    "name:dan_x_preferred":[
        "Santa Cruz"
    ],
    "name:deu_x_preferred":[
        "Santa Cruz"
    ],
    "name:ell_x_preferred":[
        "\u03a3\u03ac\u03bd\u03c4\u03b1 \u039a\u03c1\u03bf\u03c5\u03b6"
    ],
    "name:epo_x_preferred":[
        "Santa Cruz"
    ],
    "name:eus_x_preferred":[
        "Santa Cruz"
    ],
    "name:fas_x_preferred":[
        "\u0633\u0627\u0646\u062a\u0627 \u06a9\u0631\u0648\u0633"
    ],
    "name:fin_x_preferred":[
        "Santa Cruz"
    ],
    "name:fra_x_preferred":[
        "Santa Cruz"
    ],
    "name:glg_x_preferred":[
        "Santa Cruz"
    ],
    "name:heb_x_preferred":[
        "\u05e1\u05e0\u05d8\u05d4 \u05e7\u05e8\u05d5\u05e1"
    ],
    "name:hrv_x_preferred":[
        "Santa Cruz"
    ],
    "name:hun_x_preferred":[
        "Santa Cruz"
    ],
    "name:ilo_x_preferred":[
        "Santa Cruz"
    ],
    "name:ita_x_preferred":[
        "Santa Cruz"
    ],
    "name:jpn_x_preferred":[
        "\u30b5\u30f3\u30bf\u30af\u30eb\u30b9"
    ],
    "name:kor_x_preferred":[
        "\uc0b0\ud0c0\ud06c\ub8e8\uc2a4"
    ],
    "name:lav_x_preferred":[
        "Santakrusa"
    ],
    "name:lit_x_preferred":[
        "Santa Krusas"
    ],
    "name:mlg_x_preferred":[
        "Santa Cruz"
    ],
    "name:msa_x_preferred":[
        "Santa Cruz"
    ],
    "name:nds_x_preferred":[
        "Santa Cruz"
    ],
    "name:nld_x_preferred":[
        "Santa Cruz"
    ],
    "name:nor_x_preferred":[
        "Santa Cruz"
    ],
    "name:pol_x_preferred":[
        "Santa Cruz"
    ],
    "name:por_x_preferred":[
        "Santa Cruz"
    ],
    "name:ron_x_preferred":[
        "Santa Cruz"
    ],
    "name:rus_x_preferred":[
        "\u0421\u0430\u043d\u0442\u0430-\u041a\u0440\u0443\u0441"
    ],
    "name:sco_x_preferred":[
        "Santa Cruz"
    ],
    "name:slk_x_preferred":[
        "Santa Cruz"
    ],
    "name:spa_x_preferred":[
        "Santa Cruz"
    ],
    "name:srp_x_preferred":[
        "\u0421\u0430\u043d\u0442\u0430 \u041a\u0440\u0443\u0437"
    ],
    "name:swe_x_preferred":[
        "Santa Cruz"
    ],
    "name:tur_x_preferred":[
        "Santa Cruz"
    ],
    "name:ukr_x_preferred":[
        "\u0421\u0430\u043d\u0442\u0430-\u041a\u0440\u0443\u0441"
    ],
    "name:vie_x_preferred":[
        "Santa Cruz"
    ],
    "name:vol_x_preferred":[
        "Santa Cruz"
    ],
    "name:war_x_preferred":[
        "Santa Cruz"
    ],
    "name:zho_x_preferred":[
        "\u8056\u514b\u9b6f\u65af"
    ],
    "wof:name":"Santa Cruz",
    "wof:placetype":"locality"
},
  "geometry": {"coordinates":[-77.11570999999998,2.17115],"type":"Point"}
}