{
  "type": "Feature",
  "properties": {
    "gn:admin1_code":"33.0",
    "gn:admin2_code":"25438.0",
    "gn:asciiname":"Tunquiza",
    "gn:country_code":"CO",
    "gn:dem":1963,
    "gn:feature_class":"P",
    "gn:feature_code":"PPL",
    "gn:name":"Tunquiza",
    "gn:population":0,
    "gn:timezone":"America/Bogota",
    "iso:country":"CO",
    "wof:name":"Tunquiza",
    "wof:placetype":"locality"
},
  "geometry": {"coordinates":[-73.46666999999999,4.56667],"type":"Point"}
}