{
  "type": "Feature",
  "properties": {
    "gn:admin1_code":"19.0",
    "gn:admin2_code":"50001.0",
    "gn:asciiname":"Manaure",
    "gn:country_code":"CO",
    "gn:dem":380,
    "gn:feature_class":"P",
    "gn:feature_code":"PPL",
    "gn:name":"Manaure",
    "gn:population":0,
    "gn:timezone":"America/Bogota",
    "iso:country":"CO",
    "name:ceb_x_preferred":[
        "Manaure"
    ],
    "name:ita_x_preferred":[
        "Manaure"
    ],
    "name:nld_x_preferred":[
        "Manaure"
    ],
    "name:spa_x_preferred":[
        "Manaure"
    ],
    "name:swe_x_preferred":[
        "Manaure"
    ],
    "wof:name":"Manaure",
    "wof:placetype":"locality"
},
  "geometry": {"coordinates":[-73.57743000000001,4.08847],"type":"Point"}
}