{
  "type": "Feature",
  "properties": {
    "gn:admin1_code":"29",
    "gn:admin2_code":"76233.0",
    "gn:asciiname":"El Pajar",
    "gn:country_code":"CO",
    "gn:dem":1355,
    "gn:feature_class":"P",
    "gn:feature_code":"PPL",
    "gn:name":"El Pajar",
    "gn:population":0,
    "gn:timezone":"America/Bogota",
    "iso:country":"CO",
    "wof:name":"El Pajar",
    "wof:placetype":"locality"
},
  "geometry": {"coordinates":[-76.66667,3.68333],"type":"Point"}
}