{
  "type": "Feature",
  "properties": {
    "gn:admin1_code":"34.0",
    "gn:admin2_code":"11001.0",
    "gn:admin3_code":"5.0",
    "gn:asciiname":"Olarte",
    "gn:country_code":"CO",
    "gn:dem":2937,
    "gn:feature_class":"P",
    "gn:feature_code":"PPL",
    "gn:name":"Olarte",
    "gn:population":0,
    "gn:timezone":"America/Bogota",
    "iso:country":"CO",
    "wof:name":"Olarte",
    "wof:placetype":"locality"
},
  "geometry": {"coordinates":[-74.13333,4.45],"type":"Point"}
}