{
  "type": "Feature",
  "properties": {
    "gn:admin1_code":"33.0",
    "gn:admin2_code":"25754.0",
    "gn:asciiname":"Tequendama",
    "gn:country_code":"CO",
    "gn:dem":2708,
    "gn:feature_class":"P",
    "gn:feature_code":"PPL",
    "gn:name":"Tequendama",
    "gn:population":0,
    "gn:timezone":"America/Bogota",
    "iso:country":"CO",
    "wof:name":"Tequendama",
    "wof:placetype":"locality"
},
  "geometry": {"coordinates":[-74.26666999999998,4.55],"type":"Point"}
}