{
  "type": "Feature",
  "properties": {
    "gn:admin1_code":"22.0",
    "gn:admin2_code":"86571.0",
    "gn:asciiname":"La NuevaUnion",
    "gn:country_code":"CO",
    "gn:dem":261,
    "gn:feature_class":"P",
    "gn:feature_code":"PPL",
    "gn:name":"La NuevaUnion",
    "gn:population":0,
    "gn:timezone":"America/Bogota",
    "iso:country":"CO",
    "wof:name":"La NuevaUnion",
    "wof:placetype":"locality"
},
  "geometry": {"coordinates":[-76.27771,0.8969],"type":"Point"}
}