{
  "type": "Feature",
  "properties": {
    "gn:admin1_code":"12",
    "gn:admin2_code":"23068.0",
    "gn:asciiname":"El Leon",
    "gn:country_code":"CO",
    "gn:dem":22,
    "gn:feature_class":"P",
    "gn:feature_code":"PPL",
    "gn:name":"El Le\u00f3n",
    "gn:population":0,
    "gn:timezone":"America/Bogota",
    "iso:country":"CO",
    "wof:name":"El Leon",
    "wof:placetype":"locality"
},
  "geometry": {"coordinates":[-75.14446,8.32945],"type":"Point"}
}