{
  "type": "Feature",
  "properties": {
    "gn:admin1_code":"33",
    "gn:admin2_code":"25001.0",
    "gn:asciiname":"El Hobal",
    "gn:country_code":"CO",
    "gn:dem":349,
    "gn:feature_class":"P",
    "gn:feature_code":"PPL",
    "gn:name":"El Hobal",
    "gn:population":0,
    "gn:timezone":"America/Bogota",
    "iso:country":"CO",
    "wof:name":"El Hobal",
    "wof:placetype":"locality"
},
  "geometry": {"coordinates":[-74.68878000000002,4.35959],"type":"Point"}
}