{
  "type": "Feature",
  "properties": {
    "gn:admin1_code":"38",
    "gn:admin2_code":"47551.0",
    "gn:asciiname":"La Quiebra",
    "gn:country_code":"CO",
    "gn:dem":37,
    "gn:feature_class":"P",
    "gn:feature_code":"PPL",
    "gn:name":"La Quiebra",
    "gn:population":0,
    "gn:timezone":"America/Bogota",
    "iso:country":"CO",
    "name:und_x_variant":[
        "Hacienda La Quiebra",
        "La Quiebra"
    ],
    "wof:name":"La Quiebra",
    "wof:placetype":"locality"
},
  "geometry": {"coordinates":[-74.43083,10.44433],"type":"Point"}
}