{
  "type": "Feature",
  "properties": {
    "gn:admin1_code":"2",
    "gn:admin2_code":"5034.0",
    "gn:asciiname":"Alto Abejorral",
    "gn:country_code":"CO",
    "gn:dem":1648,
    "gn:feature_class":"P",
    "gn:feature_code":"PPL",
    "gn:name":"Alto Abejorral",
    "gn:population":0,
    "gn:timezone":"America/Bogota",
    "iso:country":"CO",
    "wof:name":"Alto Abejorral",
    "wof:placetype":"locality"
},
  "geometry": {"coordinates":[-75.85829,5.64522],"type":"Point"}
}