{
  "type": "Feature",
  "properties": {
    "gn:admin1_code":"29.0",
    "gn:admin2_code":"76109.0",
    "gn:asciiname":"Quebrada Pitirri",
    "gn:country_code":"CO",
    "gn:dem":9,
    "gn:feature_class":"P",
    "gn:feature_code":"PPL",
    "gn:name":"Quebrada Pitirri",
    "gn:population":0,
    "gn:timezone":"America/Bogota",
    "iso:country":"CO",
    "name:spa_x_preferred":[
        "Quebrada Pitirri"
    ],
    "wof:name":"Quebrada Pitirri",
    "wof:placetype":"locality"
},
  "geometry": {"coordinates":[-77.04259,3.83775],"type":"Point"}
}