{
  "type": "Feature",
  "properties": {
    "gn:admin1_code":"28.0",
    "gn:admin2_code":"73226.0",
    "gn:asciiname":"Vereda La Victoria",
    "gn:country_code":"CO",
    "gn:dem":451,
    "gn:feature_class":"P",
    "gn:feature_code":"PPLL",
    "gn:name":"Vereda La Victoria",
    "gn:population":0,
    "gn:timezone":"America/Bogota",
    "iso:country":"CO",
    "name:spa_x_preferred":[
        "Vereda La Victoria"
    ],
    "wof:name":"Vereda La Victoria",
    "wof:placetype":"locality"
},
  "geometry": {"coordinates":[-74.70539000000002,4.03811],"type":"Point"}
}