{
  "type": "Feature",
  "properties": {
    "gn:admin1_code":"10.0",
    "gn:admin2_code":"20621.0",
    "gn:asciiname":"Yaguara",
    "gn:country_code":"CO",
    "gn:dem":46,
    "gn:feature_class":"P",
    "gn:feature_code":"PPL",
    "gn:name":"Yaguar\u00e1",
    "gn:population":0,
    "gn:timezone":"America/Bogota",
    "iso:country":"CO",
    "wof:name":"Yaguara",
    "wof:placetype":"locality"
},
  "geometry": {"coordinates":[-73.56938000000002,9.82129],"type":"Point"}
}