{
  "type": "Feature",
  "properties": {
    "gn:admin1_code":"8",
    "gn:admin2_code":"18753.0",
    "gn:asciiname":"Inspeccion de Policia Guacamayas",
    "gn:country_code":"CO",
    "gn:dem":498,
    "gn:feature_class":"P",
    "gn:feature_code":"PPL",
    "gn:name":"Inspecci\u00f3n de Polic\u00eda Guacamayas",
    "gn:population":0,
    "gn:timezone":"America/Bogota",
    "iso:country":"CO",
    "name:und_x_variant":[
        "Guacamaya",
        "Guacamayas",
        "Inspecci\u00f3n de Polic\u00eda Guacamayas"
    ],
    "wof:name":"Inspeccion de Policia Guacamayas",
    "wof:placetype":"locality"
},
  "geometry": {"coordinates":[-74.92756999999997,2.36766],"type":"Point"}
}