{
  "type": "Feature",
  "properties": {
    "gn:admin1_code":"12.0",
    "gn:admin2_code":"23570.0",
    "gn:asciiname":"Villafrancia",
    "gn:country_code":"CO",
    "gn:dem":115,
    "gn:feature_class":"P",
    "gn:feature_code":"PPLL",
    "gn:name":"Villafrancia",
    "gn:population":0,
    "gn:timezone":"America/Bogota",
    "iso:country":"CO",
    "wof:name":"Villafrancia",
    "wof:placetype":"locality"
},
  "geometry": {"coordinates":[-75.58173000000002,8.55875],"type":"Point"}
}