{
  "type": "Feature",
  "properties": {
    "gn:admin1_code":"12",
    "gn:admin2_code":"23068.0",
    "gn:asciiname":"La Albania",
    "gn:country_code":"CO",
    "gn:dem":32,
    "gn:feature_class":"P",
    "gn:feature_code":"PPL",
    "gn:name":"La Albania",
    "gn:population":0,
    "gn:timezone":"America/Bogota",
    "iso:country":"CO",
    "wof:name":"La Albania",
    "wof:placetype":"locality"
},
  "geometry": {"coordinates":[-74.91386999999997,8.16507],"type":"Point"}
}