{
  "type": "Feature",
  "properties": {
    "gn:admin1_code":"38",
    "gn:admin2_code":"47001.0",
    "gn:asciiname":"Don Diego",
    "gn:country_code":"CO",
    "gn:dem":8,
    "gn:feature_class":"P",
    "gn:feature_code":"PPL",
    "gn:name":"Don Diego",
    "gn:population":0,
    "gn:timezone":"America/Bogota",
    "iso:country":"CO",
    "name:und_x_variant":[
        "San Diego",
        "Don Diego"
    ],
    "wof:name":"Don Diego",
    "wof:placetype":"locality"
},
  "geometry": {"coordinates":[-73.69963,11.24116],"type":"Point"}
}