{
  "type": "Feature",
  "properties": {
    "iso:country":"CO",
    "name:ast_x_preferred":[
        "Pauna"
    ],
    "name:ceb_x_preferred":[
        "Pauna"
    ],
    "name:eng_x_preferred":[
        "Pauna"
    ],
    "name:fra_x_preferred":[
        "Pauna"
    ],
    "name:ita_x_preferred":[
        "Pauna"
    ],
    "name:kat_x_preferred":[
        "\u10de\u10d0\u10e3\u10dc\u10d0"
    ],
    "name:msa_x_preferred":[
        "Pauna"
    ],
    "name:nan_x_preferred":[
        "Pauna"
    ],
    "name:nld_x_preferred":[
        "Pauna"
    ],
    "name:por_x_preferred":[
        "Pauna"
    ],
    "name:rus_x_preferred":[
        "\u041f\u0430\u0443\u043d\u0430"
    ],
    "name:sco_x_preferred":[
        "Pauna"
    ],
    "name:spa_x_preferred":[
        "Pauna"
    ],
    "name:swe_x_preferred":[
        "Pauna"
    ],
    "name:tgl_x_preferred":[
        "Pauna"
    ],
    "name:vie_x_preferred":[
        "Pauna"
    ],
    "name:war_x_preferred":[
        "Pauna"
    ],
    "name:zho_min_nan_x_preferred":[
        "Pauna"
    ],
    "name:zho_x_preferred":[
        "\u4fdd\u7d0d"
    ],
    "qs:gn_country":"CO",
    "qs:gn_fcode":"PPL",
    "qs:gn_pop":2663,
    "qs:name":"Pauna",
    "qs:name_adm0":"Colombia",
    "qs:name_adm1":"Boyaca",
    "qs:photos":0,
    "qs:photos_1k":0,
    "qs:photos_9k":0,
    "qs:photos_9r":0,
    "qs:photos_all":0,
    "qs:photos_sr":0,
    "qs:placetype":"Town",
    "qs:pop_sr":"4",
    "qs:woe_adm0":23424787,
    "wd:wordcount":38,
    "wof:name":"Pauna",
    "wof:placetype":"locality",
    "wof:population":2663
},
  "geometry": {"coordinates":[-73.9825,5.65861],"type":"Point"}
}