{
  "type": "Feature",
  "properties": {
    "gn:admin1_code":"21",
    "gn:admin2_code":"54520.0",
    "gn:asciiname":"La Dorada",
    "gn:country_code":"CO",
    "gn:dem":1761,
    "gn:feature_class":"P",
    "gn:feature_code":"PPL",
    "gn:name":"La Dorada",
    "gn:population":0,
    "gn:timezone":"America/Bogota",
    "iso:country":"CO",
    "name:ceb_x_preferred":[
        "La Dorada"
    ],
    "name:mlg_x_preferred":[
        "La Dorada"
    ],
    "name:spa_x_preferred":[
        "La Dorada"
    ],
    "name:srp_x_preferred":[
        "\u041b\u0430 \u0414\u043e\u0440\u0430\u0434\u0430"
    ],
    "name:swe_x_preferred":[
        "La Dorada"
    ],
    "wof:name":"La Dorada",
    "wof:placetype":"locality"
},
  "geometry": {"coordinates":[-72.61667,7.55],"type":"Point"}
}