{
  "type": "Feature",
  "properties": {
    "gn:admin1_code":"29",
    "gn:admin2_code":"76520.0",
    "gn:asciiname":"Lano Grande",
    "gn:country_code":"CO",
    "gn:dem":988,
    "gn:feature_class":"P",
    "gn:feature_code":"PPL",
    "gn:name":"Lano Grande",
    "gn:population":0,
    "gn:timezone":"America/Bogota",
    "iso:country":"CO",
    "wof:name":"Lano Grande",
    "wof:placetype":"locality"
},
  "geometry": {"coordinates":[-76.31610999999999,3.50083],"type":"Point"}
}