{
  "type": "Feature",
  "properties": {
    "gn:admin1_code":"20",
    "gn:admin2_code":"52835.0",
    "gn:asciiname":"Congol",
    "gn:cc2":"CO",
    "gn:country_code":"CO",
    "gn:dem":1,
    "gn:feature_class":"P",
    "gn:feature_code":"PPL",
    "gn:name":"Congol",
    "gn:population":0,
    "gn:timezone":"America/Bogota",
    "iso:country":"CO",
    "name:und_x_variant":[
        "Congal",
        "Congol"
    ],
    "wof:name":"Congol",
    "wof:placetype":"locality"
},
  "geometry": {"coordinates":[-78.93333,1.58333],"type":"Point"}
}