{
  "type": "Feature",
  "properties": {
    "gn:admin1_code":"29.0",
    "gn:admin2_code":"76895.0",
    "gn:asciiname":"Santa Helena",
    "gn:country_code":"CO",
    "gn:dem":918,
    "gn:feature_class":"P",
    "gn:feature_code":"PPL",
    "gn:name":"Santa Helena",
    "gn:population":0,
    "gn:timezone":"America/Bogota",
    "iso:country":"CO",
    "name:cat_x_preferred":[
        "Santa Helena"
    ],
    "name:ceb_x_preferred":[
        "Santa Helena"
    ],
    "name:deu_x_preferred":[
        "Santa Helena"
    ],
    "name:fra_x_preferred":[
        "Santa Helena"
    ],
    "name:glg_x_preferred":[
        "Santa Helena"
    ],
    "name:ita_x_preferred":[
        "Santa Helena"
    ],
    "name:nld_x_preferred":[
        "Santa Helena"
    ],
    "name:nor_x_preferred":[
        "Santa Helena"
    ],
    "name:por_x_preferred":[
        "Santa Helena"
    ],
    "name:spa_x_preferred":[
        "Santa Helena"
    ],
    "name:swe_x_preferred":[
        "Santa Helena"
    ],
    "name:vol_x_preferred":[
        "Santa Helena"
    ],
    "wof:name":"Santa Helena",
    "wof:placetype":"locality"
},
  "geometry": {"coordinates":[-76.05778000000002,4.43417],"type":"Point"}
}