{
  "type": "Feature",
  "properties": {
    "gn:admin1_code":"33.0",
    "gn:admin2_code":"25754.0",
    "gn:asciiname":"Vereda Fusunga",
    "gn:country_code":"CO",
    "gn:dem":2849,
    "gn:feature_class":"P",
    "gn:feature_code":"PPLL",
    "gn:name":"Vereda Fusunga",
    "gn:population":0,
    "gn:timezone":"America/Bogota",
    "iso:country":"CO",
    "name:spa_x_preferred":[
        "Vereda Fusunga"
    ],
    "wof:name":"Vereda Fusunga",
    "wof:placetype":"locality"
},
  "geometry": {"coordinates":[-74.19355,4.5294],"type":"Point"}
}