{
  "type": "Feature",
  "properties": {
    "gn:admin1_code":"2.0",
    "gn:admin2_code":"5501.0",
    "gn:asciiname":"Venturosa",
    "gn:country_code":"CO",
    "gn:dem":600,
    "gn:feature_class":"P",
    "gn:feature_code":"PPL",
    "gn:name":"Venturosa",
    "gn:population":0,
    "gn:timezone":"America/Bogota",
    "iso:country":"CO",
    "name:bpy_x_preferred":[
        "\u09ad\u09c7\u09a8\u099f\u09c1\u09b0\u09cb\u09b8\u09be"
    ],
    "name:ceb_x_preferred":[
        "Venturosa"
    ],
    "name:eus_x_preferred":[
        "Venturosa"
    ],
    "name:fas_x_preferred":[
        "\u0648\u0646\u062a\u0648\u0631\u0633\u0627"
    ],
    "name:fra_x_preferred":[
        "Venturosa"
    ],
    "name:ita_x_preferred":[
        "Venturosa"
    ],
    "name:kat_x_preferred":[
        "\u10d5\u10d4\u10dc\u10e2\u10e3\u10e0\u10dd\u10d6\u10d0"
    ],
    "name:kaz_x_preferred":[
        "\u0412\u0435\u043d\u0442\u0443\u0440\u043e\u0437\u0430"
    ],
    "name:mlg_x_preferred":[
        "Venturosa"
    ],
    "name:nld_x_preferred":[
        "Venturosa"
    ],
    "name:nor_x_preferred":[
        "Venturosa"
    ],
    "name:por_x_preferred":[
        "Venturosa"
    ],
    "name:ron_x_preferred":[
        "Venturosa"
    ],
    "name:rus_x_preferred":[
        "\u0412\u0435\u043d\u0442\u0443\u0440\u043e\u0437\u0430"
    ],
    "name:spa_x_preferred":[
        "Venturosa"
    ],
    "name:swe_x_preferred":[
        "Venturosa"
    ],
    "name:vie_x_preferred":[
        "Venturosa"
    ],
    "name:vol_x_preferred":[
        "Venturosa"
    ],
    "name:war_x_preferred":[
        "Venturosa"
    ],
    "name:zho_x_preferred":[
        "\u6587\u56fe\u7f57\u8428"
    ],
    "wof:name":"Venturosa",
    "wof:placetype":"locality"
},
  "geometry": {"coordinates":[-75.78111,6.58972],"type":"Point"}
}