{
  "type": "Feature",
  "properties": {
    "gn:admin1_code":"2.0",
    "gn:admin2_code":"5501.0",
    "gn:asciiname":"Venturosa",
    "gn:country_code":"CO",
    "gn:dem":600,
    "gn:feature_class":"P",
    "gn:feature_code":"PPL",
    "gn:name":"Venturosa",
    "gn:population":0,
    "gn:timezone":"America/Bogota",
    "iso:country":"CO",
    "wof:name":"Venturosa",
    "wof:placetype":"locality"
},
  "geometry": {"coordinates":[-75.78111,6.58972],"type":"Point"}
}