{
  "type": "Feature",
  "properties": {
    "gn:admin1_code":"9.0",
    "gn:admin2_code":"19698.0",
    "gn:asciiname":"El Aguila",
    "gn:country_code":"CO",
    "gn:dem":1608,
    "gn:feature_class":"P",
    "gn:feature_code":"PPL",
    "gn:name":"El Aguila",
    "gn:population":0,
    "gn:timezone":"America/Bogota",
    "iso:country":"CO",
    "name:fas_x_preferred":[
        "\u0627\u0644\u06af\u0648\u0626\u0644\u0627"
    ],
    "name:fra_x_preferred":[
        "El Aguila"
    ],
    "name:ita_x_preferred":[
        "Aguila"
    ],
    "name:spa_x_preferred":[
        "El Aguila"
    ],
    "wof:name":"El Aguila",
    "wof:placetype":"locality"
},
  "geometry": {"coordinates":[-76.45971999999998,2.93823],"type":"Point"}
}