{
  "type": "Feature",
  "properties": {
    "gn:admin1_code":"4",
    "gn:admin2_code":"8560.0",
    "gn:asciiname":"El Uvero",
    "gn:country_code":"CO",
    "gn:dem":7,
    "gn:feature_class":"P",
    "gn:feature_code":"PPL",
    "gn:name":"El Uvero",
    "gn:population":0,
    "gn:timezone":"America/Bogota",
    "iso:country":"CO",
    "wof:name":"El Uvero",
    "wof:placetype":"locality"
},
  "geometry": {"coordinates":[-74.75,10.56667],"type":"Point"}
}