{
  "type": "Feature",
  "properties": {
    "gn:admin1_code":"11.0",
    "gn:admin2_code":"27150.0",
    "gn:asciiname":"Vigia de Curvarado",
    "gn:country_code":"CO",
    "gn:dem":7,
    "gn:feature_class":"P",
    "gn:feature_code":"PPL",
    "gn:name":"Vig\u00eda de Curvarad\u00f3",
    "gn:population":0,
    "gn:timezone":"America/Bogota",
    "iso:country":"CO",
    "name:und_x_variant":[
        "Curbarad\u00f3",
        "Vig\u00eda de Curbarado",
        "Vig\u00eda de Curvarad\u00f3"
    ],
    "wof:name":"Vigia de Curvarado",
    "wof:placetype":"locality"
},
  "geometry": {"coordinates":[-76.92143,7.07416],"type":"Point"}
}