{
  "type": "Feature",
  "properties": {
    "gn:admin1_code":"2",
    "gn:admin2_code":"5034.0",
    "gn:asciiname":"La Siria",
    "gn:country_code":"CO",
    "gn:dem":2041,
    "gn:feature_class":"P",
    "gn:feature_code":"PPL",
    "gn:name":"La Siria",
    "gn:population":0,
    "gn:timezone":"America/Bogota",
    "iso:country":"CO",
    "wof:name":"La Siria",
    "wof:placetype":"locality"
},
  "geometry": {"coordinates":[-75.97555,5.66771],"type":"Point"}
}