{
  "type": "Feature",
  "properties": {
    "gn:admin1_code":"26",
    "gn:admin2_code":"68895.0",
    "gn:asciiname":"El Coscal",
    "gn:country_code":"CO",
    "gn:dem":1014,
    "gn:feature_class":"P",
    "gn:feature_code":"PPL",
    "gn:name":"El Coscal",
    "gn:population":0,
    "gn:timezone":"America/Bogota",
    "iso:country":"CO",
    "name:und_x_variant":[
        "Coscal",
        "El Coscal"
    ],
    "wof:name":"El Coscal",
    "wof:placetype":"locality"
},
  "geometry": {"coordinates":[-73.2449,6.75438],"type":"Point"}
}