{
  "type": "Feature",
  "properties": {
    "gn:admin1_code":"27",
    "gn:admin2_code":"70001.0",
    "gn:asciiname":"El Olivo",
    "gn:country_code":"CO",
    "gn:dem":79,
    "gn:feature_class":"P",
    "gn:feature_code":"PPL",
    "gn:name":"El Olivo",
    "gn:population":0,
    "gn:timezone":"America/Bogota",
    "iso:country":"CO",
    "wof:name":"El Olivo",
    "wof:placetype":"locality"
},
  "geometry": {"coordinates":[-75.44669,9.37794],"type":"Point"}
}