{
  "type": "Feature",
  "properties": {
    "gn:admin1_code":"12",
    "gn:admin2_code":"23678.0",
    "gn:asciiname":"Lamedero",
    "gn:country_code":"CO",
    "gn:dem":38,
    "gn:feature_class":"P",
    "gn:feature_code":"PPLL",
    "gn:name":"Lamedero",
    "gn:population":0,
    "gn:timezone":"America/Bogota",
    "iso:country":"CO",
    "wof:name":"Lamedero",
    "wof:placetype":"locality"
},
  "geometry": {"coordinates":[-75.66110999999999,8.76636],"type":"Point"}
}