{
  "type": "Feature",
  "properties": {
    "gn:admin1_code":"10",
    "gn:admin2_code":"20032.0",
    "gn:asciiname":"La Albania",
    "gn:cc2":"CO",
    "gn:country_code":"CO",
    "gn:dem":72,
    "gn:feature_class":"P",
    "gn:feature_code":"PPL",
    "gn:name":"La Albania",
    "gn:population":0,
    "gn:timezone":"America/Bogota",
    "iso:country":"CO",
    "name:und_x_variant":[
        "Albania",
        "La Albania"
    ],
    "wof:name":"La Albania",
    "wof:placetype":"locality"
},
  "geometry": {"coordinates":[-73.90111,9.55583],"type":"Point"}
}