{
  "type": "Feature",
  "properties": {
    "gn:admin1_code":"16.0",
    "gn:admin2_code":"41872.0",
    "gn:asciiname":"La Borrega",
    "gn:country_code":"CO",
    "gn:dem":550,
    "gn:feature_class":"P",
    "gn:feature_code":"PPL",
    "gn:name":"La Borrega",
    "gn:population":0,
    "gn:timezone":"America/Bogota",
    "iso:country":"CO",
    "name:spa_x_preferred":[
        "La Borrega"
    ],
    "wof:name":"La Borrega",
    "wof:placetype":"locality"
},
  "geometry": {"coordinates":[-75.08528000000003,3.22215],"type":"Point"}
}