{
  "type": "Feature",
  "properties": {
    "gn:admin1_code":"2",
    "gn:admin2_code":"5649.0",
    "gn:asciiname":"Narices",
    "gn:country_code":"CO",
    "gn:dem":794,
    "gn:feature_class":"P",
    "gn:feature_code":"PPL",
    "gn:name":"Narices",
    "gn:population":0,
    "gn:timezone":"America/Bogota",
    "iso:country":"CO",
    "wof:name":"Narices",
    "wof:placetype":"locality"
},
  "geometry": {"coordinates":[-74.80249999999999,6.19833],"type":"Point"}
}