{
  "type": "Feature",
  "properties": {
    "gn:admin1_code":"17",
    "gn:admin2_code":"44560.0",
    "gn:asciiname":"Apotureca",
    "gn:country_code":"CO",
    "gn:dem":39,
    "gn:feature_class":"P",
    "gn:feature_code":"PPL",
    "gn:name":"Apotureca",
    "gn:population":0,
    "gn:timezone":"America/Bogota",
    "iso:country":"CO",
    "wof:name":"Apotureca",
    "wof:placetype":"locality"
},
  "geometry": {"coordinates":[-72.5775,11.485],"type":"Point"}
}