{
  "type": "Feature",
  "properties": {
    "gn:admin1_code":"33.0",
    "gn:admin2_code":"25599.0",
    "gn:asciiname":"Vereda El Trueno",
    "gn:country_code":"CO",
    "gn:dem":768,
    "gn:feature_class":"P",
    "gn:feature_code":"PPLL",
    "gn:name":"Vereda El Trueno",
    "gn:population":0,
    "gn:timezone":"America/Bogota",
    "iso:country":"CO",
    "name:spa_x_preferred":[
        "Vereda El Trueno"
    ],
    "wof:name":"Vereda El Trueno",
    "wof:placetype":"locality"
},
  "geometry": {"coordinates":[-74.59149000000002,4.4886],"type":"Point"}
}