{
  "type": "Feature",
  "properties": {
    "gn:admin1_code":"38.0",
    "gn:admin2_code":"47555.0",
    "gn:asciiname":"Zarate",
    "gn:country_code":"CO",
    "gn:dem":18,
    "gn:feature_class":"P",
    "gn:feature_code":"PPL",
    "gn:name":"Z\u00e1rate",
    "gn:population":0,
    "gn:timezone":"America/Bogota",
    "iso:country":"CO",
    "name:und_x_variant":[
        "Caserio Zarate",
        "Sarat\u00e9",
        "Savate",
        "Z\u00e1rate"
    ],
    "wof:name":"Zarate",
    "wof:placetype":"locality"
},
  "geometry": {"coordinates":[-74.68043,9.72964],"type":"Point"}
}