{
  "type": "Feature",
  "properties": {
    "gn:admin1_code":"31.0",
    "gn:admin2_code":"99773.0",
    "gn:asciiname":"Recta de Sinamaio",
    "gn:country_code":"CO",
    "gn:dem":152,
    "gn:feature_class":"P",
    "gn:feature_code":"PPL",
    "gn:name":"Recta de Sinamaio",
    "gn:population":0,
    "gn:timezone":"America/Bogota",
    "iso:country":"CO",
    "wof:name":"Recta de Sinamaio",
    "wof:placetype":"locality"
},
  "geometry": {"coordinates":[-69.95028000000001,3.59278],"type":"Point"}
}