{
  "type": "Feature",
  "properties": {
    "gn:admin1_code":"32",
    "gn:asciiname":"Cofradia",
    "gn:country_code":"CO",
    "gn:dem":646,
    "gn:feature_class":"P",
    "gn:feature_code":"PPL",
    "gn:name":"Cofrad\u00eda",
    "gn:population":0,
    "gn:timezone":"America/Bogota",
    "iso:country":"CO",
    "wof:name":"Cofradia",
    "wof:placetype":"locality"
},
  "geometry": {"coordinates":[-72.30539,5.58183],"type":"Point"}
}