{
  "type": "Feature",
  "properties": {
    "gn:admin1_code":"16.0",
    "gn:admin2_code":"41396.0",
    "gn:asciiname":"Fatima",
    "gn:country_code":"CO",
    "gn:dem":1606,
    "gn:feature_class":"P",
    "gn:feature_code":"PPL",
    "gn:name":"F\u00e1tima",
    "gn:population":0,
    "gn:timezone":"America/Bogota",
    "iso:country":"CO",
    "wof:name":"Fatima",
    "wof:placetype":"locality"
},
  "geometry": {"coordinates":[-75.93281999999998,2.38804],"type":"Point"}
}