{
  "type": "Feature",
  "properties": {
    "gn:admin1_code":"16.0",
    "gn:admin2_code":"41872.0",
    "gn:asciiname":"Rodeito",
    "gn:country_code":"CO",
    "gn:dem":1366,
    "gn:feature_class":"P",
    "gn:feature_code":"PPL",
    "gn:name":"Rodeito",
    "gn:population":0,
    "gn:timezone":"America/Bogota",
    "iso:country":"CO",
    "name:spa_x_preferred":[
        "Rodeito"
    ],
    "wof:name":"Rodeito",
    "wof:placetype":"locality"
},
  "geometry": {"coordinates":[-75.02831999999999,3.39467],"type":"Point"}
}