{
  "type": "Feature",
  "properties": {
    "gn:admin1_code":"28",
    "gn:admin2_code":"73555.0",
    "gn:asciiname":"Lagunitas",
    "gn:country_code":"CO",
    "gn:dem":2005,
    "gn:feature_class":"P",
    "gn:feature_code":"PPL",
    "gn:name":"Lagunitas",
    "gn:population":0,
    "gn:timezone":"America/Bogota",
    "iso:country":"CO",
    "name:ceb_x_preferred":[
        "Lagunitas"
    ],
    "name:deu_x_preferred":[
        "Lagunitas"
    ],
    "name:fra_x_preferred":[
        "Lagunitas"
    ],
    "name:srp_x_preferred":[
        "\u041b\u0430\u0433\u0443\u043d\u0438\u0442\u0430\u0441"
    ],
    "name:swe_x_preferred":[
        "Lagunitas"
    ],
    "wof:name":"Lagunitas",
    "wof:placetype":"locality"
},
  "geometry": {"coordinates":[-75.67889,3.20583],"type":"Point"}
}