{
  "type": "Feature",
  "properties": {
    "gn:admin1_code":"38",
    "gn:admin2_code":"47707.0",
    "gn:asciiname":"La Lucha",
    "gn:country_code":"CO",
    "gn:dem":28,
    "gn:feature_class":"P",
    "gn:feature_code":"PPL",
    "gn:name":"La Lucha",
    "gn:population":0,
    "gn:timezone":"America/Bogota",
    "iso:country":"CO",
    "name:und_x_variant":[
        "Ca\u00f1o de Agua"
    ],
    "wof:name":"La Lucha",
    "wof:placetype":"locality"
},
  "geometry": {"coordinates":[-74.42454000000002,9.45046],"type":"Point"}
}