{
  "type": "Feature",
  "properties": {
    "gn:admin1_code":"16.0",
    "gn:admin2_code":"41298.0",
    "gn:asciiname":"La Lomita",
    "gn:country_code":"CO",
    "gn:dem":752,
    "gn:feature_class":"P",
    "gn:feature_code":"PPL",
    "gn:name":"La Lomita",
    "gn:population":0,
    "gn:timezone":"America/Bogota",
    "iso:country":"CO",
    "wof:name":"La Lomita",
    "wof:placetype":"locality"
},
  "geometry": {"coordinates":[-75.63683,2.26739],"type":"Point"}
}