{
  "type": "Feature",
  "properties": {
    "gn:admin1_code":"10.0",
    "gn:admin2_code":"20013.0",
    "gn:asciiname":"Cano de La Alegria",
    "gn:country_code":"CO",
    "gn:dem":86,
    "gn:feature_class":"P",
    "gn:feature_code":"PPL",
    "gn:name":"Ca\u00f1o de La Alegr\u00eda",
    "gn:population":0,
    "gn:timezone":"America/Bogota",
    "iso:country":"CO",
    "wof:name":"Cano de La Alegria",
    "wof:placetype":"locality"
},
  "geometry": {"coordinates":[-73.31656,10.05697],"type":"Point"}
}