{
  "type": "Feature",
  "properties": {
    "gn:admin1_code":"16",
    "gn:admin2_code":"41001",
    "gn:asciiname":"El Corial",
    "gn:country_code":"CO",
    "gn:dem":1120,
    "gn:feature_class":"P",
    "gn:feature_code":"PPL",
    "gn:name":"El Corial",
    "gn:population":0,
    "gn:timezone":"America/Bogota",
    "iso:country":"CO",
    "name:spa_x_preferred":[
        "El Corial"
    ],
    "wof:name":"El Corial",
    "wof:placetype":"locality"
},
  "geometry": {"coordinates":[-75.11714000000001,2.89114],"type":"Point"}
}