{
  "type": "Feature",
  "properties": {
    "gn:admin1_code":"38",
    "gn:admin2_code":"47245.0",
    "gn:asciiname":"Campoalegre",
    "gn:country_code":"CO",
    "gn:dem":47,
    "gn:feature_class":"P",
    "gn:feature_code":"PPL",
    "gn:name":"Campoalegre",
    "gn:population":0,
    "gn:timezone":"America/Bogota",
    "iso:country":"CO",
    "wof:name":"Campoalegre",
    "wof:placetype":"locality"
},
  "geometry": {"coordinates":[-73.96826,9.25662],"type":"Point"}
}