{
  "type": "Feature",
  "properties": {
    "gn:admin1_code":"28.0",
    "gn:admin2_code":"73043.0",
    "gn:asciiname":"Meridiano",
    "gn:cc2":"CO",
    "gn:country_code":"CO",
    "gn:dem":3500,
    "gn:feature_class":"P",
    "gn:feature_code":"PPL",
    "gn:name":"Meridiano",
    "gn:population":0,
    "gn:timezone":"America/Bogota",
    "iso:country":"CO",
    "name:ido_x_preferred":[
        "Meridiano"
    ],
    "name:ita_x_preferred":[
        "Meridiano"
    ],
    "name:por_x_preferred":[
        "Meridiano"
    ],
    "name:spa_x_preferred":[
        "Meridiano"
    ],
    "name:und_x_variant":[
        "El Meridiano",
        "Meridiano"
    ],
    "wof:name":"Meridiano",
    "wof:placetype":"locality"
},
  "geometry": {"coordinates":[-75.23333000000002,4.56667],"type":"Point"}
}