{
  "type": "Feature",
  "properties": {
    "gn:admin1_code":"4.0",
    "gn:admin2_code":"8638.0",
    "gn:asciiname":"Mirador",
    "gn:country_code":"CO",
    "gn:dem":114,
    "gn:feature_class":"P",
    "gn:feature_code":"PPL",
    "gn:name":"Mirador",
    "gn:population":0,
    "gn:timezone":"America/Bogota",
    "iso:country":"CO",
    "name:ceb_x_preferred":[
        "Mirador"
    ],
    "name:deu_x_preferred":[
        "Mirador"
    ],
    "name:fra_x_preferred":[
        "Mirador"
    ],
    "name:ita_x_preferred":[
        "Mirador"
    ],
    "name:nld_x_preferred":[
        "Mirador"
    ],
    "name:nor_x_preferred":[
        "Mirador"
    ],
    "name:por_x_preferred":[
        "Mirador"
    ],
    "name:rus_x_preferred":[
        "\u041c\u0438\u0440\u0430\u0434\u043e\u0440"
    ],
    "name:spa_x_preferred":[
        "Mirador"
    ],
    "name:srp_x_preferred":[
        "\u041c\u0438\u0440\u0430\u0434\u043e\u0440"
    ],
    "name:swe_x_preferred":[
        "Mirador"
    ],
    "name:vie_x_preferred":[
        "Mirador"
    ],
    "name:vol_x_preferred":[
        "Mirador"
    ],
    "wof:name":"Mirador",
    "wof:placetype":"locality"
},
  "geometry": {"coordinates":[-74.92309,10.53424],"type":"Point"}
}