{
  "type": "Feature",
  "properties": {
    "gn:admin1_code":"16",
    "gn:admin2_code":"41016.0",
    "gn:asciiname":"La Savila",
    "gn:country_code":"CO",
    "gn:dem":1025,
    "gn:feature_class":"P",
    "gn:feature_code":"PPL",
    "gn:name":"La Savila",
    "gn:population":0,
    "gn:timezone":"America/Bogota",
    "iso:country":"CO",
    "name:und_x_variant":[
        "La Savilla",
        "La Savila"
    ],
    "wof:name":"La Savila",
    "wof:placetype":"locality"
},
  "geometry": {"coordinates":[-75.425,3.31056],"type":"Point"}
}