{
  "type": "Feature",
  "properties": {
    "gn:admin1_code":"29",
    "gn:admin2_code":"76520.0",
    "gn:asciiname":"Guayabal",
    "gn:country_code":"CO",
    "gn:dem":1044,
    "gn:feature_class":"P",
    "gn:feature_code":"PPL",
    "gn:name":"Guayabal",
    "gn:population":0,
    "gn:timezone":"America/Bogota",
    "iso:country":"CO",
    "name:ceb_x_preferred":[
        "Guayabal"
    ],
    "name:deu_x_preferred":[
        "Guayabal"
    ],
    "name:fra_x_preferred":[
        "Guayabal"
    ],
    "name:ita_x_preferred":[
        "Guayabal"
    ],
    "name:nld_x_preferred":[
        "Guayabal"
    ],
    "name:por_x_preferred":[
        "Guayabal"
    ],
    "name:sco_x_preferred":[
        "Guayabal"
    ],
    "name:spa_x_preferred":[
        "Guayabal"
    ],
    "name:swe_x_preferred":[
        "Guayabal"
    ],
    "wof:name":"Guayabal",
    "wof:placetype":"locality"
},
  "geometry": {"coordinates":[-76.26583000000002,3.54694],"type":"Point"}
}