{
  "type": "Feature",
  "properties": {
    "gn:admin1_code":"8.0",
    "gn:admin2_code":"18479.0",
    "gn:asciiname":"San Benito",
    "gn:country_code":"CO",
    "gn:dem":226,
    "gn:feature_class":"P",
    "gn:feature_code":"PPL",
    "gn:name":"San Benito",
    "gn:population":0,
    "gn:timezone":"America/Bogota",
    "iso:country":"CO",
    "name:spa_x_preferred":[
        "San Benito"
    ],
    "wof:name":"San Benito",
    "wof:placetype":"locality"
},
  "geometry": {"coordinates":[-75.59998,1.32996],"type":"Point"}
}