{
  "type": "Feature",
  "properties": {
    "gn:admin1_code":"16.0",
    "gn:admin2_code":"41078.0",
    "gn:asciiname":"Santa Teresa",
    "gn:country_code":"CO",
    "gn:dem":699,
    "gn:feature_class":"P",
    "gn:feature_code":"PPL",
    "gn:name":"Santa Teresa",
    "gn:population":0,
    "gn:timezone":"America/Bogota",
    "iso:country":"CO",
    "name:spa_x_preferred":[
        "Santa Teresa"
    ],
    "wof:name":"Santa Teresa",
    "wof:placetype":"locality"
},
  "geometry": {"coordinates":[-74.93028000000002,3.25889],"type":"Point"}
}