{
  "type": "Feature",
  "properties": {
    "gn:admin1_code":"9.0",
    "gn:asciiname":"Cuchilla El Palacio",
    "gn:country_code":"CO",
    "gn:dem":1765,
    "gn:feature_class":"P",
    "gn:feature_code":"PPL",
    "gn:name":"Cuchilla El Palacio",
    "gn:population":0,
    "gn:timezone":"America/Bogota",
    "iso:country":"CO",
    "wof:name":"Cuchilla El Palacio",
    "wof:placetype":"locality"
},
  "geometry": {"coordinates":[-77.08915,1.6344],"type":"Point"}
}