{
  "type": "Feature",
  "properties": {
    "gn:admin1_code":"17",
    "gn:admin2_code":"44001.0",
    "gn:asciiname":"El Reparo",
    "gn:country_code":"CO",
    "gn:dem":605,
    "gn:feature_class":"P",
    "gn:feature_code":"PPL",
    "gn:name":"El Reparo",
    "gn:population":0,
    "gn:timezone":"America/Bogota",
    "iso:country":"CO",
    "name:und_x_variant":[
        "Caser\u00edo El Reparo",
        "El Reparo"
    ],
    "wof:name":"El Reparo",
    "wof:placetype":"locality"
},
  "geometry": {"coordinates":[-73.11856999999998,10.99251],"type":"Point"}
}