{
  "type": "Feature",
  "properties": {
    "gn:admin1_code":"21",
    "gn:admin2_code":"54820.0",
    "gn:asciiname":"El Piaz",
    "gn:country_code":"CO",
    "gn:dem":599,
    "gn:feature_class":"P",
    "gn:feature_code":"PPL",
    "gn:name":"El Piaz",
    "gn:population":0,
    "gn:timezone":"America/Bogota",
    "iso:country":"CO",
    "wof:name":"El Piaz",
    "wof:placetype":"locality"
},
  "geometry": {"coordinates":[-72.22299,7.06902],"type":"Point"}
}