{
  "type": "Feature",
  "properties": {
    "gn:admin1_code":"38",
    "gn:admin2_code":"47703.0",
    "gn:asciiname":"Bermejal",
    "gn:country_code":"CO",
    "gn:dem":28,
    "gn:feature_class":"P",
    "gn:feature_code":"PPL",
    "gn:name":"Bermejal",
    "gn:population":0,
    "gn:timezone":"America/Bogota",
    "iso:country":"CO",
    "name:und_x_variant":[
        "Bermeja",
        "Caserio Bermejal",
        "Bermejal"
    ],
    "wof:name":"Bermejal",
    "wof:placetype":"locality"
},
  "geometry": {"coordinates":[-74.37560000000001,9.26386],"type":"Point"}
}