{
  "type": "Feature",
  "properties": {
    "gn:admin1_code":"26.0",
    "gn:admin2_code":"68895.0",
    "gn:asciiname":"Monte Grande",
    "gn:country_code":"CO",
    "gn:dem":903,
    "gn:feature_class":"P",
    "gn:feature_code":"PPL",
    "gn:name":"Monte Grande",
    "gn:population":0,
    "gn:timezone":"America/Bogota",
    "iso:country":"CO",
    "wof:name":"Monte Grande",
    "wof:placetype":"locality"
},
  "geometry": {"coordinates":[-73.25,6.73333],"type":"Point"}
}