{
  "type": "Feature",
  "properties": {
    "gn:admin1_code":"9",
    "gn:admin2_code":"19256.0",
    "gn:asciiname":"El Cipres",
    "gn:country_code":"CO",
    "gn:dem":1933,
    "gn:feature_class":"P",
    "gn:feature_code":"PPL",
    "gn:name":"El Cipr\u00e9s",
    "gn:population":0,
    "gn:timezone":"America/Bogota",
    "iso:country":"CO",
    "wof:name":"El Cipres",
    "wof:placetype":"locality"
},
  "geometry": {"coordinates":[-76.89415,2.54427],"type":"Point"}
}