{
  "type": "Feature",
  "properties": {
    "gn:admin1_code":"8",
    "gn:admin2_code":"18756.0",
    "gn:asciiname":"Maranon",
    "gn:country_code":"CO",
    "gn:dem":125,
    "gn:feature_class":"P",
    "gn:feature_code":"PPL",
    "gn:name":"Mara\u00f1\u00f3n",
    "gn:population":0,
    "gn:timezone":"America/Bogota",
    "iso:country":"CO",
    "wof:name":"Maranon",
    "wof:placetype":"locality"
},
  "geometry": {"coordinates":[-72.23385999999998,-0.04285],"type":"Point"}
}