{
  "type": "Feature",
  "properties": {
    "gn:admin1_code":"17",
    "gn:admin2_code":"44078.0",
    "gn:asciiname":"Sabana El Medio",
    "gn:country_code":"CO",
    "gn:dem":173,
    "gn:feature_class":"P",
    "gn:feature_code":"PPL",
    "gn:name":"Sabana El Medio",
    "gn:population":0,
    "gn:timezone":"America/Bogota",
    "iso:country":"CO",
    "wof:name":"Sabana El Medio",
    "wof:placetype":"locality"
},
  "geometry": {"coordinates":[-72.63928,11.00985],"type":"Point"}
}