{
  "type": "Feature",
  "properties": {
    "gn:admin1_code":"21",
    "gn:admin2_code":"54720.0",
    "gn:asciiname":"Corinto",
    "gn:country_code":"CO",
    "gn:dem":278,
    "gn:feature_class":"P",
    "gn:feature_code":"PPL",
    "gn:name":"Corinto",
    "gn:population":0,
    "gn:timezone":"America/Bogota",
    "iso:country":"CO",
    "wof:name":"Corinto",
    "wof:placetype":"locality"
},
  "geometry": {"coordinates":[-72.745,8.37917],"type":"Point"}
}