{
  "type": "Feature",
  "properties": {
    "gn:admin1_code":"27.0",
    "gn:admin2_code":"70820.0",
    "gn:asciiname":"Santa Lucia",
    "gn:country_code":"CO",
    "gn:dem":25,
    "gn:feature_class":"P",
    "gn:feature_code":"PPL",
    "gn:name":"Santa Luc\u00eda",
    "gn:population":0,
    "gn:timezone":"America/Bogota",
    "iso:country":"CO",
    "name:und_x_variant":[
        "Caserio Santa Lucia",
        "Santa Luc\u00eda"
    ],
    "wof:name":"Santa Lucia",
    "wof:placetype":"locality"
},
  "geometry": {"coordinates":[-75.54145,9.46336],"type":"Point"}
}