{
  "type": "Feature",
  "properties": {
    "gn:admin1_code":"35",
    "gn:admin2_code":"13430.0",
    "gn:asciiname":"La Candelaria",
    "gn:country_code":"CO",
    "gn:dem":24,
    "gn:feature_class":"P",
    "gn:feature_code":"PPL",
    "gn:name":"La Candelaria",
    "gn:population":0,
    "gn:timezone":"America/Bogota",
    "iso:country":"CO",
    "name:ceb_x_preferred":[
        "La Candelaria"
    ],
    "name:deu_x_preferred":[
        "La Candelaria"
    ],
    "name:epo_x_preferred":[
        "La Candelaria"
    ],
    "name:fra_x_preferred":[
        "La Candelaria"
    ],
    "name:glg_x_preferred":[
        "La Candelaria"
    ],
    "name:ita_x_preferred":[
        "La Candelaria"
    ],
    "name:msa_x_preferred":[
        "La Candelaria"
    ],
    "name:nor_x_preferred":[
        "La Candelaria"
    ],
    "name:por_x_preferred":[
        "La Candelaria"
    ],
    "name:spa_x_preferred":[
        "La Candelaria"
    ],
    "wof:name":"La Candelaria",
    "wof:placetype":"locality"
},
  "geometry": {"coordinates":[-74.78079,9.29557],"type":"Point"}
}