{
  "type": "Feature",
  "properties": {
    "gn:admin1_code":"29.0",
    "gn:admin2_code":"76100.0",
    "gn:asciiname":"Potosi",
    "gn:country_code":"CO",
    "gn:dem":1949,
    "gn:feature_class":"P",
    "gn:feature_code":"PPL",
    "gn:name":"Potos\u00ed",
    "gn:population":0,
    "gn:timezone":"America/Bogota",
    "iso:country":"CO",
    "wof:name":"Potosi",
    "wof:placetype":"locality"
},
  "geometry": {"coordinates":[-76.28333000000001,4.38333],"type":"Point"}
}