{
  "type": "Feature",
  "properties": {
    "gn:admin1_code":"19",
    "gn:admin2_code":"50689",
    "gn:asciiname":"Planadas",
    "gn:country_code":"CO",
    "gn:dem":428,
    "gn:feature_class":"P",
    "gn:feature_code":"PPL",
    "gn:name":"Planadas",
    "gn:population":0,
    "gn:timezone":"America/Bogota",
    "iso:country":"CO",
    "name:spa_x_preferred":[
        "Planadas"
    ],
    "wof:name":"Planadas",
    "wof:placetype":"locality"
},
  "geometry": {"coordinates":[-73.68355,3.72269],"type":"Point"}
}