{
  "type": "Feature",
  "properties": {
    "gn:admin1_code":"26",
    "gn:admin2_code":"68615.0",
    "gn:asciiname":"La Pastora",
    "gn:country_code":"CO",
    "gn:dem":1365,
    "gn:feature_class":"P",
    "gn:feature_code":"PPL",
    "gn:name":"La Pastora",
    "gn:population":0,
    "gn:timezone":"America/Bogota",
    "iso:country":"CO",
    "name:eus_x_preferred":[
        "La Pastora"
    ],
    "name:ita_x_preferred":[
        "La Pastora"
    ],
    "name:por_x_preferred":[
        "La Pastora"
    ],
    "name:spa_x_preferred":[
        "La Pastora"
    ],
    "name:und_x_variant":[
        "Pastora"
    ],
    "name:urd_x_preferred":[
        "\u0644\u0627 \u067e\u0627\u0633\u0679\u0648\u0631\u0627"
    ],
    "name:zho_x_preferred":[
        "\u62c9\u5e15\u65af\u6258\u62c9"
    ],
    "wof:name":"La Pastora",
    "wof:placetype":"locality"
},
  "geometry": {"coordinates":[-73.11355,7.23693],"type":"Point"}
}