{
  "type": "Feature",
  "properties": {
    "gn:admin1_code":"16.0",
    "gn:admin2_code":"41206.0",
    "gn:asciiname":"Rumania",
    "gn:country_code":"CO",
    "gn:dem":1708,
    "gn:feature_class":"P",
    "gn:feature_code":"PPL",
    "gn:name":"Rumania",
    "gn:population":0,
    "gn:timezone":"America/Bogota",
    "iso:country":"CO",
    "name:spa_x_preferred":[
        "Rumania"
    ],
    "wof:name":"Rumania",
    "wof:placetype":"locality"
},
  "geometry": {"coordinates":[-74.80166,3.17257],"type":"Point"}
}