{
  "type": "Feature",
  "properties": {
    "gn:admin1_code":"31.0",
    "gn:asciiname":"La Potrera",
    "gn:country_code":"CO",
    "gn:dem":123,
    "gn:feature_class":"P",
    "gn:feature_code":"PPL",
    "gn:name":"La Potrera",
    "gn:population":0,
    "gn:timezone":"America/Bogota",
    "iso:country":"CO",
    "wof:name":"La Potrera",
    "wof:placetype":"locality"
},
  "geometry": {"coordinates":[-69.54583000000001,3.67306],"type":"Point"}
}