{
  "type": "Feature",
  "properties": {
    "iso:country":"CO",
    "name:ast_x_preferred":[
        "Susa"
    ],
    "name:ceb_x_preferred":[
        "Susa"
    ],
    "name:eng_x_preferred":[
        "Susa"
    ],
    "name:fra_x_preferred":[
        "Susa"
    ],
    "name:ita_x_preferred":[
        "Susa"
    ],
    "name:kat_x_preferred":[
        "\u10e1\u10e3\u10e1\u10d0"
    ],
    "name:msa_x_preferred":[
        "Susa"
    ],
    "name:nan_x_preferred":[
        "Susa"
    ],
    "name:nld_x_preferred":[
        "Susa"
    ],
    "name:sco_x_preferred":[
        "Susa"
    ],
    "name:spa_x_preferred":[
        "Susa"
    ],
    "name:swe_x_preferred":[
        "Susa"
    ],
    "name:tgl_x_preferred":[
        "Susa"
    ],
    "name:war_x_preferred":[
        "Susa"
    ],
    "name:zho_x_preferred":[
        "\u8607\u85a9"
    ],
    "qs:gn_country":"CO",
    "qs:gn_fcode":"PPL",
    "qs:gn_pop":1608,
    "qs:name":"Susa",
    "qs:name_adm0":"Colombia",
    "qs:name_adm1":"Cundinamarca",
    "qs:photos":27,
    "qs:photos_1k":5,
    "qs:photos_9k":1,
    "qs:photos_9r":2,
    "qs:photos_all":27,
    "qs:photos_sr":2,
    "qs:placetype":"Town",
    "qs:pop_sr":"3",
    "qs:woe_adm0":23424787,
    "wd:wordcount":3731,
    "wof:name":"Susa",
    "wof:placetype":"locality",
    "wof:population":1608
},
  "geometry": {"coordinates":[-73.81435999999999,5.4519],"type":"Point"}
}