{
  "type": "Feature",
  "properties": {
    "iso:country":"CO",
    "name:ceb_x_preferred":[
        "Tocancip\u00e1"
    ],
    "name:chi_x_preferred":[
        "\u6258\u574e\u897f\u5e15"
    ],
    "name:dut_x_preferred":[
        "Tocancip\u00e1"
    ],
    "name:eng_x_preferred":[
        "Tocancip\u00e1"
    ],
    "name:fas_x_preferred":[
        "\u062a\u0648\u06a9\u0627\u0646\u0633\u06cc\u067e\u0627"
    ],
    "name:fra_x_preferred":[
        "Tocancip\u00e1"
    ],
    "name:fre_x_preferred":[
        "Tocancip\u00e1"
    ],
    "name:geo_x_preferred":[
        "\u10e2\u10dd\u10d9\u10d0\u10dc\u10e1\u10d8\u10de\u10d0"
    ],
    "name:ita_x_preferred":[
        "Tocancip\u00e1"
    ],
    "name:kat_x_preferred":[
        "\u10e2\u10dd\u10d9\u10d0\u10dc\u10e1\u10d8\u10de\u10d0"
    ],
    "name:may_x_preferred":[
        "Tocancip\u00e1"
    ],
    "name:msa_x_preferred":[
        "Tocancip\u00e1"
    ],
    "name:nah_x_preferred":[
        "Tocancip\u00e1"
    ],
    "name:nan_x_preferred":[
        "Tocancip\u00e1"
    ],
    "name:nld_x_preferred":[
        "Tocancip\u00e1"
    ],
    "name:per_x_preferred":[
        "\u062a\u0648\u06a9\u0627\u0646\u0633\u06cc\u067e\u0627"
    ],
    "name:sco_x_preferred":[
        "Tocancip\u00e1"
    ],
    "name:spa_x_preferred":[
        "Tocancip\u00e1"
    ],
    "name:swe_x_preferred":[
        "Tocancip\u00e1"
    ],
    "name:tgl_x_preferred":[
        "Tocancip\u00e1"
    ],
    "name:vie_x_preferred":[
        "Tocancip\u00e1"
    ],
    "name:war_x_preferred":[
        "Tocancip\u00e1"
    ],
    "name:zho_x_preferred":[
        "\u6258\u574e\u897f\u5e15"
    ],
    "qs:gn_country":"CO",
    "qs:gn_fcode":"PPL",
    "qs:gn_pop":6027,
    "qs:name":"Tocancip\u00e1",
    "qs:name_adm0":"Colombia",
    "qs:name_adm1":"Cundinamarca",
    "qs:photos":386,
    "qs:photos_1k":78,
    "qs:photos_9k":2,
    "qs:photos_9r":5,
    "qs:photos_all":386,
    "qs:photos_sr":6,
    "qs:placetype":"Town",
    "qs:pop_sr":"5",
    "qs:woe_adm0":23424787,
    "wof:name":"Tocancip\u00e1",
    "wof:placetype":"locality",
    "wof:population":6027
},
  "geometry": {"coordinates":[-73.91301,4.96531],"type":"Point"}
}