{
  "type": "Feature",
  "properties": {
    "gn:admin1_code":"9.0",
    "gn:admin2_code":"19532.0",
    "gn:asciiname":"Pan de Azucar",
    "gn:country_code":"CO",
    "gn:dem":1243,
    "gn:feature_class":"P",
    "gn:feature_code":"PPL",
    "gn:name":"Pan de Az\u00facar",
    "gn:population":0,
    "gn:timezone":"America/Bogota",
    "iso:country":"CO",
    "wof:name":"Pan de Azucar",
    "wof:placetype":"locality"
},
  "geometry": {"coordinates":[-77.13324,2.14881],"type":"Point"}
}