{
  "type": "Feature",
  "properties": {
    "gn:admin1_code":"28.0",
    "gn:admin2_code":"73168.0",
    "gn:asciiname":"Capellania",
    "gn:country_code":"CO",
    "gn:dem":639,
    "gn:feature_class":"P",
    "gn:feature_code":"PPL",
    "gn:name":"Capellania",
    "gn:population":0,
    "gn:timezone":"America/Bogota",
    "iso:country":"CO",
    "wof:name":"Capellania",
    "wof:placetype":"locality"
},
  "geometry": {"coordinates":[-75.3725,3.72639],"type":"Point"}
}