{
  "type": "Feature",
  "properties": {
    "gn:admin1_code":"12",
    "gn:admin2_code":"23001.0",
    "gn:asciiname":"El Socorro",
    "gn:country_code":"CO",
    "gn:dem":55,
    "gn:feature_class":"P",
    "gn:feature_code":"PPL",
    "gn:name":"El Socorro",
    "gn:population":0,
    "gn:timezone":"America/Bogota",
    "iso:country":"CO",
    "name:ceb_x_preferred":[
        "El Socorro"
    ],
    "name:fra_x_preferred":[
        "El Socorro"
    ],
    "name:spa_x_preferred":[
        "El Socorro"
    ],
    "name:swe_x_preferred":[
        "El Socorro"
    ],
    "wof:name":"El Socorro",
    "wof:placetype":"locality"
},
  "geometry": {"coordinates":[-75.81573,8.51994],"type":"Point"}
}