{
  "type": "Feature",
  "properties": {
    "gn:admin1_code":"8.0",
    "gn:admin2_code":"18029.0",
    "gn:asciiname":"La Palmera",
    "gn:country_code":"CO",
    "gn:dem":296,
    "gn:feature_class":"P",
    "gn:feature_code":"PPL",
    "gn:name":"La Palmera",
    "gn:population":0,
    "gn:timezone":"America/Bogota",
    "iso:country":"CO",
    "name:spa_x_preferred":[
        "La Palmera"
    ],
    "wof:name":"La Palmera",
    "wof:placetype":"locality"
},
  "geometry": {"coordinates":[-75.94343000000001,1.27714],"type":"Point"}
}