{
  "type": "Feature",
  "properties": {
    "gn:admin1_code":"20",
    "gn:admin2_code":"52720.0",
    "gn:asciiname":"Malaver",
    "gn:country_code":"CO",
    "gn:dem":2968,
    "gn:feature_class":"P",
    "gn:feature_code":"PPL",
    "gn:name":"Malaver",
    "gn:population":0,
    "gn:timezone":"America/Bogota",
    "iso:country":"CO",
    "wof:name":"Malaver",
    "wof:placetype":"locality"
},
  "geometry": {"coordinates":[-77.6511,1.02929],"type":"Point"}
}