{
  "type": "Feature",
  "properties": {
    "gn:admin1_code":"12",
    "gn:admin2_code":"23182.0",
    "gn:asciiname":"Flecha Sevilla",
    "gn:country_code":"CO",
    "gn:dem":29,
    "gn:feature_class":"P",
    "gn:feature_code":"PPL",
    "gn:name":"Flecha Sevilla",
    "gn:population":0,
    "gn:timezone":"America/Bogota",
    "iso:country":"CO",
    "name:und_x_variant":[
        "Sevilla",
        "Flechas",
        "Flecha",
        "Flecha Sevilla"
    ],
    "wof:name":"Flecha Sevilla",
    "wof:placetype":"locality"
},
  "geometry": {"coordinates":[-75.52563000000001,9.02699],"type":"Point"}
}