{
  "type": "Feature",
  "properties": {
    "gn:admin1_code":"36",
    "gn:admin2_code":"15131.0",
    "gn:asciiname":"Mercadillo",
    "gn:country_code":"CO",
    "gn:dem":2769,
    "gn:feature_class":"P",
    "gn:feature_code":"PPL",
    "gn:name":"Mercadillo",
    "gn:population":0,
    "gn:timezone":"America/Bogota",
    "iso:country":"CO",
    "wof:name":"Mercadillo",
    "wof:placetype":"locality"
},
  "geometry": {"coordinates":[-73.87389,5.62556],"type":"Point"}
}