{
  "type": "Feature",
  "properties": {
    "gn:admin1_code":"29.0",
    "gn:admin2_code":"76001.0",
    "gn:asciiname":"Las Guacas",
    "gn:country_code":"CO",
    "gn:dem":1428,
    "gn:feature_class":"P",
    "gn:feature_code":"PPL",
    "gn:name":"Las Guacas",
    "gn:population":0,
    "gn:timezone":"America/Bogota",
    "iso:country":"CO",
    "wof:name":"Las Guacas",
    "wof:placetype":"locality"
},
  "geometry": {"coordinates":[-76.54709,3.49415],"type":"Point"}
}