{
  "type": "Feature",
  "properties": {
    "gn:admin1_code":"8.0",
    "gn:admin2_code":"18256.0",
    "gn:asciiname":"Concordia",
    "gn:country_code":"CO",
    "gn:dem":260,
    "gn:feature_class":"P",
    "gn:feature_code":"PPL",
    "gn:name":"Concordia",
    "gn:population":0,
    "gn:timezone":"America/Bogota",
    "iso:country":"CO",
    "name:bre_x_preferred":[
        "Concordia"
    ],
    "name:cat_x_preferred":[
        "Conc\u00f2rdia"
    ],
    "name:ceb_x_preferred":[
        "Concordia"
    ],
    "name:ces_x_preferred":[
        "Concordia"
    ],
    "name:cym_x_preferred":[
        "Concordia"
    ],
    "name:dan_x_preferred":[
        "Concordia"
    ],
    "name:deu_x_preferred":[
        "Concordia"
    ],
    "name:est_x_preferred":[
        "Concordia"
    ],
    "name:fas_x_preferred":[
        "\u06a9\u0646\u06a9\u0648\u0631\u062f\u06cc\u0627"
    ],
    "name:fin_x_preferred":[
        "Concordia"
    ],
    "name:fra_x_preferred":[
        "Concordia"
    ],
    "name:heb_x_preferred":[
        "\u05e7\u05d5\u05e0\u05e7\u05d5\u05e8\u05d3\u05d9\u05d4"
    ],
    "name:hye_x_preferred":[
        "\u053f\u0578\u0576\u056f\u0578\u0580\u0564\u056b\u0561"
    ],
    "name:ita_x_preferred":[
        "Concordia"
    ],
    "name:jpn_x_preferred":[
        "\u30b3\u30f3\u30b3\u30eb\u30c7\u30a3\u30a2"
    ],
    "name:kor_x_preferred":[
        "\ucf69\ucf54\ub974\ub514\uc544"
    ],
    "name:lat_x_preferred":[
        "Concordia"
    ],
    "name:mlg_x_preferred":[
        "Concordia"
    ],
    "name:nld_x_preferred":[
        "Concordia"
    ],
    "name:nno_x_preferred":[
        "Concordia"
    ],
    "name:nor_x_preferred":[
        "Concordia"
    ],
    "name:pol_x_preferred":[
        "Concordia"
    ],
    "name:ron_x_preferred":[
        "Concordia"
    ],
    "name:rus_x_preferred":[
        "\u041a\u043e\u043d\u043a\u043e\u0440\u0434\u0438\u044f"
    ],
    "name:sco_x_preferred":[
        "Concordia"
    ],
    "name:slk_x_preferred":[
        "Concordia"
    ],
    "name:spa_x_preferred":[
        "Concordia"
    ],
    "name:srp_x_preferred":[
        "\u041a\u043e\u043d\u043a\u043e\u0440\u0434\u0438\u0458\u0430"
    ],
    "name:swe_x_preferred":[
        "Concordia"
    ],
    "name:ukr_x_preferred":[
        "\u041a\u043e\u043d\u043a\u043e\u0440\u0434\u0456\u044f"
    ],
    "name:urd_x_preferred":[
        "\u06a9\u0648\u0646\u06a9\u0648\u0631\u0688\u06cc\u0627"
    ],
    "name:vie_x_preferred":[
        "Concordia"
    ],
    "name:vol_x_preferred":[
        "Concordia"
    ],
    "name:war_x_preferred":[
        "Concordia"
    ],
    "wof:name":"Concordia",
    "wof:placetype":"locality"
},
  "geometry": {"coordinates":[-75.24574,1.46173],"type":"Point"}
}