{
  "type": "Feature",
  "properties": {
    "gn:admin1_code":"8.0",
    "gn:admin2_code":"18256.0",
    "gn:asciiname":"Concordia",
    "gn:country_code":"CO",
    "gn:dem":260,
    "gn:feature_class":"P",
    "gn:feature_code":"PPL",
    "gn:name":"Concordia",
    "gn:population":0,
    "gn:timezone":"America/Bogota",
    "iso:country":"CO",
    "name:spa_x_preferred":[
        "Concordia"
    ],
    "wof:name":"Concordia",
    "wof:placetype":"locality"
},
  "geometry": {"coordinates":[-75.24574,1.46173],"type":"Point"}
}