{
  "type": "Feature",
  "properties": {
    "gn:admin1_code":"4.0",
    "gn:admin2_code":"8634.0",
    "gn:asciiname":"Valencia",
    "gn:country_code":"CO",
    "gn:dem":17,
    "gn:feature_class":"P",
    "gn:feature_code":"PPL",
    "gn:name":"Valencia",
    "gn:population":0,
    "gn:timezone":"America/Bogota",
    "iso:country":"CO",
    "wof:name":"Valencia",
    "wof:placetype":"locality"
},
  "geometry": {"coordinates":[-74.76666999999998,10.81667],"type":"Point"}
}