{
  "type": "Feature",
  "properties": {
    "gn:admin1_code":"2.0",
    "gn:admin2_code":"5138.0",
    "gn:asciiname":"Barracon",
    "gn:country_code":"CO",
    "gn:dem":1478,
    "gn:feature_class":"P",
    "gn:feature_code":"PPL",
    "gn:name":"Barrac\u00f3n",
    "gn:population":0,
    "gn:timezone":"America/Bogota",
    "iso:country":"CO",
    "wof:name":"Barracon",
    "wof:placetype":"locality"
},
  "geometry": {"coordinates":[-76.04783,6.82291],"type":"Point"}
}