{
  "type": "Feature",
  "properties": {
    "gn:admin1_code":"16.0",
    "gn:admin2_code":"41013.0",
    "gn:asciiname":"Garanon",
    "gn:country_code":"CO",
    "gn:dem":711,
    "gn:feature_class":"P",
    "gn:feature_code":"PPL",
    "gn:name":"Gara\u00f1\u00f3n",
    "gn:population":0,
    "gn:timezone":"America/Bogota",
    "iso:country":"CO",
    "wof:name":"Garanon",
    "wof:placetype":"locality"
},
  "geometry": {"coordinates":[-75.68338,2.24943],"type":"Point"}
}