{
  "type": "Feature",
  "properties": {
    "gn:admin1_code":"29",
    "gn:admin2_code":"76520.0",
    "gn:asciiname":"Madura",
    "gn:country_code":"CO",
    "gn:dem":3307,
    "gn:feature_class":"P",
    "gn:feature_code":"PPL",
    "gn:name":"Madura",
    "gn:population":0,
    "gn:timezone":"America/Bogota",
    "iso:country":"CO",
    "wof:name":"Madura",
    "wof:placetype":"locality"
},
  "geometry": {"coordinates":[-76.0125,3.59722],"type":"Point"}
}