{
  "type": "Feature",
  "properties": {
    "gn:admin1_code":"12.0",
    "gn:admin2_code":"23001.0",
    "gn:asciiname":"Pajonal",
    "gn:country_code":"CO",
    "gn:dem":26,
    "gn:feature_class":"P",
    "gn:feature_code":"PPL",
    "gn:name":"Pajonal",
    "gn:population":0,
    "gn:timezone":"America/Bogota",
    "iso:country":"CO",
    "name:ita_x_preferred":[
        "Pajonal"
    ],
    "name:spa_x_preferred":[
        "Pajonal"
    ],
    "name:zho_x_preferred":[
        "\u5e15\u970d\u7eb3\u5c14"
    ],
    "wof:name":"Pajonal",
    "wof:placetype":"locality"
},
  "geometry": {"coordinates":[-75.95361,8.86778],"type":"Point"}
}