{
  "type": "Feature",
  "properties": {
    "gn:admin1_code":"33.0",
    "gn:asciiname":"Sequile",
    "gn:country_code":"CO",
    "gn:dem":254,
    "gn:feature_class":"P",
    "gn:feature_code":"PPL",
    "gn:name":"Sequil\u00e9",
    "gn:population":0,
    "gn:timezone":"America/Bogota",
    "iso:country":"CO",
    "wof:name":"Sequile",
    "wof:placetype":"locality"
},
  "geometry": {"coordinates":[-74.80083,5.0475],"type":"Point"}
}