{
  "type": "Feature",
  "properties": {
    "gn:admin1_code":"37",
    "gn:admin2_code":"17873.0",
    "gn:asciiname":"Pinares",
    "gn:country_code":"CO",
    "gn:dem":1707,
    "gn:feature_class":"P",
    "gn:feature_code":"PPL",
    "gn:name":"Pinares",
    "gn:population":0,
    "gn:timezone":"America/Bogota",
    "iso:country":"CO",
    "wof:name":"Pinares",
    "wof:placetype":"locality"
},
  "geometry": {"coordinates":[-75.57611,4.95861],"type":"Point"}
}