{
  "type": "Feature",
  "properties": {
    "iso:country":"CO",
    "name:ast_x_preferred":[
        "Saboy\u00e1"
    ],
    "name:cat_x_preferred":[
        "Saboya"
    ],
    "name:ceb_x_preferred":[
        "Saboy\u00e1"
    ],
    "name:eng_x_preferred":[
        "Saboy\u00e1"
    ],
    "name:fra_x_preferred":[
        "Saboy\u00e1"
    ],
    "name:ita_x_preferred":[
        "Saboy\u00e1"
    ],
    "name:kat_x_preferred":[
        "\u10e1\u10d0\u10d1\u10dd\u10d8\u10d0"
    ],
    "name:msa_x_preferred":[
        "Saboy\u00e1"
    ],
    "name:nan_x_preferred":[
        "Saboy\u00e1"
    ],
    "name:nld_x_preferred":[
        "Saboy\u00e1"
    ],
    "name:por_x_preferred":[
        "Saboy\u00e1"
    ],
    "name:rus_x_preferred":[
        "\u0421\u0430\u0431\u043e\u044f"
    ],
    "name:sco_x_preferred":[
        "Saboy\u00e1"
    ],
    "name:spa_x_preferred":[
        "Saboy\u00e1"
    ],
    "name:swe_x_preferred":[
        "Saboy\u00e1"
    ],
    "name:tgl_x_preferred":[
        "Saboy\u00e1"
    ],
    "name:urd_x_preferred":[
        "\u0633\u0628\u0648\u06cc\u0627"
    ],
    "name:vie_x_preferred":[
        "Saboy\u00e1"
    ],
    "name:war_x_preferred":[
        "Saboy\u00e1"
    ],
    "name:zho_x_preferred":[
        "\u85a9\u6c83\u4e9e"
    ],
    "qs:gn_country":"CO",
    "qs:gn_fcode":"PPL",
    "qs:gn_pop":1375,
    "qs:name":"Saboy\u00e1",
    "qs:name_adm0":"Colombia",
    "qs:name_adm1":"Boyaca",
    "qs:photos":0,
    "qs:photos_1k":0,
    "qs:photos_9k":1,
    "qs:photos_9r":1,
    "qs:photos_all":1,
    "qs:photos_sr":0,
    "qs:placetype":"Town",
    "qs:pop_sr":"3",
    "qs:woe_adm0":23424787,
    "wd:wordcount":150,
    "wof:name":"Saboy\u00e1",
    "wof:placetype":"locality",
    "wof:population":1375
},
  "geometry": {"coordinates":[-73.76931999999999,5.69636],"type":"Point"}
}