{
  "type": "Feature",
  "properties": {
    "gn:admin1_code":"16.0",
    "gn:admin2_code":"41668.0",
    "gn:asciiname":"Quebradon",
    "gn:country_code":"CO",
    "gn:dem":1918,
    "gn:feature_class":"P",
    "gn:feature_code":"PPL",
    "gn:name":"Quebrad\u00f3n",
    "gn:population":0,
    "gn:timezone":"America/Bogota",
    "iso:country":"CO",
    "wof:name":"Quebradon",
    "wof:placetype":"locality"
},
  "geometry": {"coordinates":[-76.33903000000002,1.88156],"type":"Point"}
}