{
  "type": "Feature",
  "properties": {
    "gn:admin1_code":"8.0",
    "gn:admin2_code":"18753.0",
    "gn:asciiname":"Caserio Los Espejos",
    "gn:country_code":"CO",
    "gn:dem":219,
    "gn:feature_class":"P",
    "gn:feature_code":"PPL",
    "gn:name":"Caser\u00edo Los Espejos",
    "gn:population":0,
    "gn:timezone":"America/Bogota",
    "iso:country":"CO",
    "wof:name":"Caserio Los Espejos",
    "wof:placetype":"locality"
},
  "geometry": {"coordinates":[-74.79765999999999,1.46798],"type":"Point"}
}