{
  "type": "Feature",
  "properties": {
    "gn:admin1_code":"36",
    "gn:admin2_code":"15572.0",
    "gn:asciiname":"Los Andes",
    "gn:country_code":"CO",
    "gn:dem":1100,
    "gn:feature_class":"P",
    "gn:feature_code":"PPL",
    "gn:name":"Los Andes",
    "gn:population":0,
    "gn:timezone":"America/Bogota",
    "iso:country":"CO",
    "name:ceb_x_preferred":[
        "Los Andes"
    ],
    "name:deu_x_preferred":[
        "Los Andes"
    ],
    "name:hun_x_preferred":[
        "Los Andes"
    ],
    "name:hye_x_preferred":[
        "\u053c\u0578\u057d \u0531\u0576\u0564\u0565\u057d"
    ],
    "name:ita_x_preferred":[
        "Los Andes"
    ],
    "name:nld_x_preferred":[
        "Los Andes"
    ],
    "name:rus_x_preferred":[
        "\u041b\u043e\u0441-\u0410\u043d\u0434\u0435\u0441"
    ],
    "name:sco_x_preferred":[
        "Los Andes"
    ],
    "name:slk_x_preferred":[
        "Los Andes"
    ],
    "name:swe_x_preferred":[
        "Los Andes"
    ],
    "name:war_x_preferred":[
        "Los Andes"
    ],
    "wof:name":"Los Andes",
    "wof:placetype":"locality"
},
  "geometry": {"coordinates":[-74.28382000000001,5.77844],"type":"Point"}
}