{
  "type": "Feature",
  "properties": {
    "gn:admin1_code":"14.0",
    "gn:admin2_code":"95001.0",
    "gn:asciiname":"El Capricho",
    "gn:country_code":"CO",
    "gn:dem":245,
    "gn:feature_class":"P",
    "gn:feature_code":"PPL",
    "gn:name":"El Capricho",
    "gn:population":0,
    "gn:timezone":"America/Bogota",
    "iso:country":"CO",
    "name:cat_x_preferred":[
        "El Capricho"
    ],
    "name:ces_x_preferred":[
        "Casa El Capricho"
    ],
    "name:deu_x_preferred":[
        "Villa Quijano"
    ],
    "name:eus_x_preferred":[
        "El Capricho"
    ],
    "name:ita_x_preferred":[
        "Il Capriccio"
    ],
    "name:nld_x_preferred":[
        "El Capricho"
    ],
    "name:por_x_preferred":[
        "El Capricho"
    ],
    "name:rus_x_preferred":[
        "\u042d\u043b\u044c-\u041a\u0430\u043f\u0440\u0438\u0447\u0447\u043e"
    ],
    "name:spa_x_preferred":[
        "El Capricho"
    ],
    "wof:name":"El Capricho",
    "wof:placetype":"locality"
},
  "geometry": {"coordinates":[-72.83074000000001,2.35224],"type":"Point"}
}