{
  "type": "Feature",
  "properties": {
    "gn:admin1_code":"14.0",
    "gn:admin2_code":"95001.0",
    "gn:asciiname":"El Capricho",
    "gn:country_code":"CO",
    "gn:dem":245,
    "gn:feature_class":"P",
    "gn:feature_code":"PPL",
    "gn:name":"El Capricho",
    "gn:population":0,
    "gn:timezone":"America/Bogota",
    "iso:country":"CO",
    "wof:name":"El Capricho",
    "wof:placetype":"locality"
},
  "geometry": {"coordinates":[-72.83074000000001,2.35224],"type":"Point"}
}