{
  "type": "Feature",
  "properties": {
    "gn:admin1_code":"12.0",
    "gn:admin2_code":"23189.0",
    "gn:asciiname":"La Envidia",
    "gn:country_code":"CO",
    "gn:dem":28,
    "gn:feature_class":"P",
    "gn:feature_code":"PPL",
    "gn:name":"La Envidia",
    "gn:population":0,
    "gn:timezone":"America/Bogota",
    "iso:country":"CO",
    "wof:name":"La Envidia",
    "wof:placetype":"locality"
},
  "geometry": {"coordinates":[-75.55253,8.90712],"type":"Point"}
}