{
  "type": "Feature",
  "properties": {
    "gn:admin1_code":"35.0",
    "gn:admin2_code":"13647.0",
    "gn:asciiname":"Palacio",
    "gn:country_code":"CO",
    "gn:dem":71,
    "gn:feature_class":"P",
    "gn:feature_code":"PPL",
    "gn:name":"Palacio",
    "gn:population":0,
    "gn:timezone":"America/Bogota",
    "iso:country":"CO",
    "wof:name":"Palacio",
    "wof:placetype":"locality"
},
  "geometry": {"coordinates":[-75.23774,10.32015],"type":"Point"}
}