{
  "type": "Feature",
  "properties": {
    "gn:admin1_code":"38",
    "gn:admin2_code":"47707.0",
    "gn:asciiname":"Santa Rosa de Lima",
    "gn:country_code":"CO",
    "gn:dem":53,
    "gn:feature_class":"P",
    "gn:feature_code":"PPL",
    "gn:name":"Santa Rosa de Lima",
    "gn:population":0,
    "gn:timezone":"America/Bogota",
    "iso:country":"CO",
    "name:srp_x_preferred":[
        "\u0421\u0430\u043d\u0442\u0430 \u0420\u043e\u0441\u0430 \u0434\u0435 \u041b\u0438\u043c\u0430"
    ],
    "wof:name":"Santa Rosa de Lima",
    "wof:placetype":"locality"
},
  "geometry": {"coordinates":[-74.46122,9.56351],"type":"Point"}
}