{
  "type": "Feature",
  "properties": {
    "gn:admin1_code":"16.0",
    "gn:admin2_code":"41206.0",
    "gn:asciiname":"Gigante",
    "gn:country_code":"CO",
    "gn:dem":1813,
    "gn:feature_class":"P",
    "gn:feature_code":"PPLL",
    "gn:name":"Gigante",
    "gn:population":0,
    "gn:timezone":"America/Bogota",
    "iso:country":"CO",
    "name:spa_x_preferred":[
        "Gigante"
    ],
    "wof:name":"Gigante",
    "wof:placetype":"locality"
},
  "geometry": {"coordinates":[-74.679,3.646],"type":"Point"}
}