{
  "type": "Feature",
  "properties": {
    "gn:admin1_code":"29",
    "gn:admin2_code":"76248.0",
    "gn:asciiname":"Palmichala",
    "gn:country_code":"CO",
    "gn:dem":2752,
    "gn:feature_class":"P",
    "gn:feature_code":"PPL",
    "gn:name":"Palmichala",
    "gn:population":0,
    "gn:timezone":"America/Bogota",
    "iso:country":"CO",
    "wof:name":"Palmichala",
    "wof:placetype":"locality"
},
  "geometry": {"coordinates":[-76.06444,3.73611],"type":"Point"}
}