{
  "type": "Feature",
  "properties": {
    "gn:admin1_code":"38.0",
    "gn:admin2_code":"47707.0",
    "gn:asciiname":"Tarqui",
    "gn:country_code":"CO",
    "gn:dem":67,
    "gn:feature_class":"P",
    "gn:feature_code":"PPL",
    "gn:name":"Tarqui",
    "gn:population":0,
    "gn:timezone":"America/Bogota",
    "iso:country":"CO",
    "name:und_x_variant":[
        "Hacienda Tarqui",
        "Tarqui"
    ],
    "wof:name":"Tarqui",
    "wof:placetype":"locality"
},
  "geometry": {"coordinates":[-74.22062,9.57492],"type":"Point"}
}