{
  "type": "Feature",
  "properties": {
    "gn:admin1_code":"2.0",
    "gn:admin2_code":"5212.0",
    "gn:asciiname":"Vereda El Noral",
    "gn:country_code":"CO",
    "gn:dem":1620,
    "gn:feature_class":"P",
    "gn:feature_code":"PPLL",
    "gn:name":"Vereda El Noral",
    "gn:population":0,
    "gn:timezone":"America/Bogota",
    "iso:country":"CO",
    "name:spa_x_preferred":[
        "Vereda El Noral"
    ],
    "wof:name":"Vereda El Noral",
    "wof:placetype":"locality"
},
  "geometry": {"coordinates":[-75.51129,6.36148],"type":"Point"}
}