{
  "type": "Feature",
  "properties": {
    "gn:admin1_code":"21",
    "gn:admin2_code":"54810.0",
    "gn:asciiname":"Cordoba",
    "gn:country_code":"CO",
    "gn:dem":55,
    "gn:feature_class":"P",
    "gn:feature_code":"PPL",
    "gn:name":"C\u00f3rdoba",
    "gn:population":0,
    "gn:timezone":"America/Bogota",
    "iso:country":"CO",
    "wof:name":"Cordoba",
    "wof:placetype":"locality"
},
  "geometry": {"coordinates":[-72.64055999999999,8.51139],"type":"Point"}
}