{
  "type": "Feature",
  "properties": {
    "gn:admin1_code":"16",
    "gn:admin2_code":"41206.0",
    "gn:asciiname":"Boqueroncito",
    "gn:cc2":"CO",
    "gn:country_code":"CO",
    "gn:dem":1370,
    "gn:feature_class":"P",
    "gn:feature_code":"PPL",
    "gn:name":"Boqueroncito",
    "gn:population":0,
    "gn:timezone":"America/Bogota",
    "iso:country":"CO",
    "name:und_x_variant":[
        "Boqueron",
        "Boqueroncito"
    ],
    "wof:name":"Boqueroncito",
    "wof:placetype":"locality"
},
  "geometry": {"coordinates":[-74.66667,3.28333],"type":"Point"}
}