{
  "type": "Feature",
  "properties": {
    "gn:admin1_code":"2.0",
    "gn:admin2_code":"5847.0",
    "gn:asciiname":"Pavas",
    "gn:country_code":"CO",
    "gn:dem":2258,
    "gn:feature_class":"P",
    "gn:feature_code":"PPL",
    "gn:name":"Pavas",
    "gn:population":0,
    "gn:timezone":"America/Bogota",
    "iso:country":"CO",
    "wof:name":"Pavas",
    "wof:placetype":"locality"
},
  "geometry": {"coordinates":[-76.13361,6.5175],"type":"Point"}
}