{
  "type": "Feature",
  "properties": {
    "gn:admin1_code":"12",
    "gn:admin2_code":"23162.0",
    "gn:asciiname":"Mateo Gomez",
    "gn:country_code":"CO",
    "gn:dem":16,
    "gn:feature_class":"P",
    "gn:feature_code":"PPL",
    "gn:name":"Mateo G\u00f3mez",
    "gn:population":0,
    "gn:timezone":"America/Bogota",
    "iso:country":"CO",
    "name:und_x_variant":[
        "Mateo",
        "Mateo G\u00f3mez"
    ],
    "wof:name":"Mateo Gomez",
    "wof:placetype":"locality"
},
  "geometry": {"coordinates":[-75.82971999999999,8.84473],"type":"Point"}
}