{
  "type": "Feature",
  "properties": {
    "gn:admin1_code":"20.0",
    "gn:admin2_code":"52621.0",
    "gn:asciiname":"Pumalde",
    "gn:country_code":"CO",
    "gn:dem":17,
    "gn:feature_class":"P",
    "gn:feature_code":"PPL",
    "gn:name":"Pumalde",
    "gn:population":0,
    "gn:timezone":"America/Bogota",
    "iso:country":"CO",
    "wof:name":"Pumalde",
    "wof:placetype":"locality"
},
  "geometry": {"coordinates":[-78.43066999999998,2.00857],"type":"Point"}
}