{
  "type": "Feature",
  "properties": {
    "gn:admin1_code":"20.0",
    "gn:admin2_code":"52720.0",
    "gn:asciiname":"Chilco",
    "gn:country_code":"CO",
    "gn:dem":3158,
    "gn:feature_class":"P",
    "gn:feature_code":"PPL",
    "gn:name":"Chilco",
    "gn:population":0,
    "gn:timezone":"America/Bogota",
    "iso:country":"CO",
    "wof:name":"Chilco",
    "wof:placetype":"locality"
},
  "geometry": {"coordinates":[-77.74101,1.04136],"type":"Point"}
}