{
  "type": "Feature",
  "properties": {
    "gn:admin1_code":"29",
    "gn:admin2_code":"76364.0",
    "gn:asciiname":"La Ferreira",
    "gn:country_code":"CO",
    "gn:dem":1025,
    "gn:feature_class":"P",
    "gn:feature_code":"PPL",
    "gn:name":"La Ferreira",
    "gn:population":0,
    "gn:timezone":"America/Bogota",
    "iso:country":"CO",
    "wof:name":"La Ferreira",
    "wof:placetype":"locality"
},
  "geometry": {"coordinates":[-76.63344000000002,3.15312],"type":"Point"}
}