{
  "type": "Feature",
  "properties": {
    "gn:admin1_code":"38.0",
    "gn:admin2_code":"47692.0",
    "gn:asciiname":"Nuevo Encanto",
    "gn:country_code":"CO",
    "gn:dem":71,
    "gn:feature_class":"P",
    "gn:feature_code":"PPL",
    "gn:name":"Nuevo Encanto",
    "gn:population":0,
    "gn:timezone":"America/Bogota",
    "iso:country":"CO",
    "name:und_x_variant":[
        "Hacienda Nuevo Encanto",
        "Nuevo Encanto"
    ],
    "wof:name":"Nuevo Encanto",
    "wof:placetype":"locality"
},
  "geometry": {"coordinates":[-74.10805999999999,9.37926],"type":"Point"}
}