{
  "type": "Feature",
  "properties": {
    "gn:admin1_code":"17.0",
    "gn:admin2_code":"44650.0",
    "gn:asciiname":"Piloncito",
    "gn:country_code":"CO",
    "gn:dem":486,
    "gn:feature_class":"P",
    "gn:feature_code":"PPL",
    "gn:name":"Piloncito",
    "gn:population":0,
    "gn:timezone":"America/Bogota",
    "iso:country":"CO",
    "wof:name":"Piloncito",
    "wof:placetype":"locality"
},
  "geometry": {"coordinates":[-73.10256,10.86724],"type":"Point"}
}