{
  "type": "Feature",
  "properties": {
    "gn:admin1_code":"2",
    "gn:admin2_code":"5854.0",
    "gn:asciiname":"Clavellino",
    "gn:country_code":"CO",
    "gn:dem":711,
    "gn:feature_class":"P",
    "gn:feature_code":"PPL",
    "gn:name":"Clavellino",
    "gn:population":0,
    "gn:timezone":"America/Bogota",
    "iso:country":"CO",
    "wof:name":"Clavellino",
    "wof:placetype":"locality"
},
  "geometry": {"coordinates":[-75.40196,7.18301],"type":"Point"}
}