{
  "type": "Feature",
  "properties": {
    "gn:admin1_code":"35.0",
    "gn:admin2_code":"13006.0",
    "gn:asciiname":"Vida Tranquila",
    "gn:country_code":"CO",
    "gn:dem":20,
    "gn:feature_class":"P",
    "gn:feature_code":"PPL",
    "gn:name":"Vida Tranquila",
    "gn:population":0,
    "gn:timezone":"America/Bogota",
    "iso:country":"CO",
    "wof:name":"Vida Tranquila",
    "wof:placetype":"locality"
},
  "geometry": {"coordinates":[-74.45154000000002,8.81193],"type":"Point"}
}