{
  "type": "Feature",
  "properties": {
    "gn:admin1_code":"9.0",
    "gn:admin2_code":"19256.0",
    "gn:asciiname":"Pandiguando",
    "gn:country_code":"CO",
    "gn:dem":1804,
    "gn:feature_class":"P",
    "gn:feature_code":"PPL",
    "gn:name":"Pandiguando",
    "gn:population":0,
    "gn:timezone":"America/Bogota",
    "iso:country":"CO",
    "wof:name":"Pandiguando",
    "wof:placetype":"locality"
},
  "geometry": {"coordinates":[-76.86955999999998,2.45228],"type":"Point"}
}