{
  "type": "Feature",
  "properties": {
    "gn:admin1_code":"10",
    "gn:admin2_code":"20175.0",
    "gn:asciiname":"Regimiento",
    "gn:country_code":"CO",
    "gn:dem":37,
    "gn:feature_class":"P",
    "gn:feature_code":"PPL",
    "gn:name":"Regimiento",
    "gn:population":0,
    "gn:timezone":"America/Bogota",
    "iso:country":"CO",
    "wof:name":"Regimiento",
    "wof:placetype":"locality"
},
  "geometry": {"coordinates":[-73.80199999999998,9.43683],"type":"Point"}
}