{
  "type": "Feature",
  "properties": {
    "gn:admin1_code":"28.0",
    "gn:admin2_code":"73217.0",
    "gn:asciiname":"Iguasal",
    "gn:country_code":"CO",
    "gn:dem":325,
    "gn:feature_class":"P",
    "gn:feature_code":"PPL",
    "gn:name":"Iguasal",
    "gn:population":0,
    "gn:timezone":"America/Bogota",
    "iso:country":"CO",
    "name:spa_x_preferred":[
        "Iguasal"
    ],
    "wof:name":"Iguasal",
    "wof:placetype":"locality"
},
  "geometry": {"coordinates":[-75.00861,3.76917],"type":"Point"}
}