{
  "type": "Feature",
  "properties": {
    "gn:admin1_code":"35",
    "gn:admin2_code":"13006.0",
    "gn:asciiname":"Guacamayo",
    "gn:country_code":"CO",
    "gn:dem":18,
    "gn:feature_class":"P",
    "gn:feature_code":"PPL",
    "gn:name":"Guacamayo",
    "gn:population":0,
    "gn:timezone":"America/Bogota",
    "iso:country":"CO",
    "name:und_x_variant":[
        "Corregimiemto Guacamayo",
        "Guacamayas",
        "Guacamayo"
    ],
    "wof:name":"Guacamayo",
    "wof:placetype":"locality"
},
  "geometry": {"coordinates":[-74.52725,8.7272],"type":"Point"}
}