{
  "type": "Feature",
  "properties": {
    "gn:admin1_code":"33.0",
    "gn:admin2_code":"25758.0",
    "gn:asciiname":"Bosconia",
    "gn:country_code":"CO",
    "gn:dem":2860,
    "gn:feature_class":"P",
    "gn:feature_code":"PPL",
    "gn:name":"Bosconia",
    "gn:population":0,
    "gn:timezone":"America/Bogota",
    "iso:country":"CO",
    "wof:name":"Bosconia",
    "wof:placetype":"locality"
},
  "geometry": {"coordinates":[-73.98166999999999,4.85583],"type":"Point"}
}