{
  "type": "Feature",
  "properties": {
    "gn:admin1_code":"33.0",
    "gn:admin2_code":"25758.0",
    "gn:asciiname":"Bosconia",
    "gn:country_code":"CO",
    "gn:dem":2860,
    "gn:feature_class":"P",
    "gn:feature_code":"PPL",
    "gn:name":"Bosconia",
    "gn:population":0,
    "gn:timezone":"America/Bogota",
    "iso:country":"CO",
    "name:ceb_x_preferred":[
        "Bosconia"
    ],
    "name:deu_x_preferred":[
        "Bosconia"
    ],
    "name:fas_x_preferred":[
        "\u0628\u0648\u0633\u06a9\u0648\u0646\u06cc\u0627"
    ],
    "name:fra_x_preferred":[
        "Bosconia"
    ],
    "name:ita_x_preferred":[
        "Bosconia"
    ],
    "name:kat_x_preferred":[
        "\u10d1\u10dd\u10e1\u10d9\u10dd\u10dc\u10d8\u10d0"
    ],
    "name:msa_x_preferred":[
        "Bosconia"
    ],
    "name:nld_x_preferred":[
        "Bosconia"
    ],
    "name:por_x_preferred":[
        "Bosconia"
    ],
    "name:rus_x_preferred":[
        "\u0411\u043e\u0441\u043a\u043e\u043d\u0438\u044f"
    ],
    "name:spa_x_preferred":[
        "Bosconia"
    ],
    "name:swe_x_preferred":[
        "Bosconia"
    ],
    "name:tgl_x_preferred":[
        "Bosconia"
    ],
    "name:vie_x_preferred":[
        "Bosconia"
    ],
    "name:war_x_preferred":[
        "Bosconia"
    ],
    "name:zho_x_preferred":[
        "\u535a\u65af\u79d1\u5c3c\u4e9e"
    ],
    "wof:name":"Bosconia",
    "wof:placetype":"locality"
},
  "geometry": {"coordinates":[-73.98166999999999,4.85583],"type":"Point"}
}