{
  "type": "Feature",
  "properties": {
    "gn:admin1_code":"16.0",
    "gn:admin2_code":"41518.0",
    "gn:asciiname":"La Meseta",
    "gn:country_code":"CO",
    "gn:dem":1562,
    "gn:feature_class":"P",
    "gn:feature_code":"PPL",
    "gn:name":"La Meseta",
    "gn:population":0,
    "gn:timezone":"America/Bogota",
    "iso:country":"CO",
    "wof:name":"La Meseta",
    "wof:placetype":"locality"
},
  "geometry": {"coordinates":[-75.8077,2.38365],"type":"Point"}
}