{
  "type": "Feature",
  "properties": {
    "gn:admin1_code":"28.0",
    "gn:admin2_code":"73270.0",
    "gn:asciiname":"EL Palmar",
    "gn:country_code":"CO",
    "gn:dem":277,
    "gn:feature_class":"P",
    "gn:feature_code":"PPL",
    "gn:name":"EL Palmar",
    "gn:population":0,
    "gn:timezone":"America/Bogota",
    "iso:country":"CO",
    "name:spa_x_preferred":[
        "EL Palmar"
    ],
    "wof:name":"EL Palmar",
    "wof:placetype":"locality"
},
  "geometry": {"coordinates":[-74.89896999999998,5.04009],"type":"Point"}
}