{
  "type": "Feature",
  "properties": {
    "gn:admin1_code":"8.0",
    "gn:admin2_code":"18753.0",
    "gn:asciiname":"Inspeccion de Policia Tres Esquinas",
    "gn:country_code":"CO",
    "gn:dem":240,
    "gn:feature_class":"P",
    "gn:feature_code":"PPL",
    "gn:name":"Inspecci\u00f3n de Polic\u00eda Tres Esquinas",
    "gn:population":0,
    "gn:timezone":"America/Bogota",
    "iso:country":"CO",
    "wof:name":"Inspeccion de Policia Tres Esquinas",
    "wof:placetype":"locality"
},
  "geometry": {"coordinates":[-74.81270000000001,1.86827],"type":"Point"}
}