{
  "type": "Feature",
  "properties": {
    "gn:admin1_code":"26.0",
    "gn:admin2_code":"68689.0",
    "gn:asciiname":"El Castaneto",
    "gn:country_code":"CO",
    "gn:dem":578,
    "gn:feature_class":"P",
    "gn:feature_code":"PPLL",
    "gn:name":"El Casta\u00f1eto",
    "gn:population":0,
    "gn:timezone":"America/Bogota",
    "iso:country":"CO",
    "wof:name":"El Castaneto",
    "wof:placetype":"locality"
},
  "geometry": {"coordinates":[-73.4927,6.88746],"type":"Point"}
}