{
  "type": "Feature",
  "properties": {
    "gn:admin1_code":"16.0",
    "gn:admin2_code":"41807.0",
    "gn:asciiname":"Cosanza",
    "gn:country_code":"CO",
    "gn:dem":1424,
    "gn:feature_class":"P",
    "gn:feature_code":"PPL",
    "gn:name":"Cosanza",
    "gn:population":0,
    "gn:timezone":"America/Bogota",
    "iso:country":"CO",
    "name:spa_x_preferred":[
        "Cosanza"
    ],
    "wof:name":"Cosanza",
    "wof:placetype":"locality"
},
  "geometry": {"coordinates":[-75.8917,1.9786],"type":"Point"}
}