{
  "type": "Feature",
  "properties": {
    "gn:admin1_code":"28",
    "gn:admin2_code":"73678.0",
    "gn:asciiname":"El Triunfo",
    "gn:country_code":"CO",
    "gn:dem":372,
    "gn:feature_class":"P",
    "gn:feature_code":"PPL",
    "gn:name":"El Triunfo",
    "gn:population":0,
    "gn:timezone":"America/Bogota",
    "iso:country":"CO",
    "wof:name":"El Triunfo",
    "wof:placetype":"locality"
},
  "geometry": {"coordinates":[-75.13889,4.03472],"type":"Point"}
}