{
  "type": "Feature",
  "properties": {
    "gn:admin1_code":"4",
    "gn:admin2_code":"8296.0",
    "gn:asciiname":"Camajoru",
    "gn:country_code":"CO",
    "gn:dem":114,
    "gn:feature_class":"P",
    "gn:feature_code":"PPL",
    "gn:name":"Camajoru",
    "gn:population":0,
    "gn:timezone":"America/Bogota",
    "iso:country":"CO",
    "wof:name":"Camajoru",
    "wof:placetype":"locality"
},
  "geometry": {"coordinates":[-74.84999999999999,10.88333],"type":"Point"}
}