{
  "type": "Feature",
  "properties": {
    "gn:admin1_code":"26",
    "gn:admin2_code":"68673.0",
    "gn:asciiname":"La Teja",
    "gn:country_code":"CO",
    "gn:dem":1409,
    "gn:feature_class":"P",
    "gn:feature_code":"PPL",
    "gn:name":"La Teja",
    "gn:population":0,
    "gn:timezone":"America/Bogota",
    "iso:country":"CO",
    "wof:name":"La Teja",
    "wof:placetype":"locality"
},
  "geometry": {"coordinates":[-73.56667,6.06667],"type":"Point"}
}