{
  "type": "Feature",
  "properties": {
    "gn:admin1_code":"29",
    "gn:admin2_code":"76109",
    "gn:asciiname":"Aeropuerto",
    "gn:country_code":"CO",
    "gn:dem":15,
    "gn:feature_class":"P",
    "gn:feature_code":"PPL",
    "gn:name":"Aeropuerto",
    "gn:population":0,
    "gn:timezone":"America/Bogota",
    "iso:country":"CO",
    "wof:name":"Aeropuerto",
    "wof:placetype":"locality"
},
  "geometry": {"coordinates":[-76.99420000000001,3.81904],"type":"Point"}
}