{
  "type": "Feature",
  "properties": {
    "gn:admin1_code":"38.0",
    "gn:admin2_code":"47720.0",
    "gn:asciiname":"Montelargo",
    "gn:country_code":"CO",
    "gn:dem":47,
    "gn:feature_class":"P",
    "gn:feature_code":"PPL",
    "gn:name":"Montelargo",
    "gn:population":0,
    "gn:timezone":"America/Bogota",
    "iso:country":"CO",
    "wof:name":"Montelargo",
    "wof:placetype":"locality"
},
  "geometry": {"coordinates":[-74.65976999999999,9.46708],"type":"Point"}
}