{
  "type": "Feature",
  "properties": {
    "gn:admin1_code":"17",
    "gn:admin2_code":"44847.0",
    "gn:asciiname":"Juruaipa",
    "gn:country_code":"CO",
    "gn:dem":19,
    "gn:feature_class":"P",
    "gn:feature_code":"PPL",
    "gn:name":"J\u00faruaipa",
    "gn:population":0,
    "gn:timezone":"America/Bogota",
    "iso:country":"CO",
    "name:und_x_variant":[
        "Jaraipa",
        "J\u00faruaipa"
    ],
    "wof:name":"Juruaipa",
    "wof:placetype":"locality"
},
  "geometry": {"coordinates":[-72.01961999999997,12.09808],"type":"Point"}
}