{
  "type": "Feature",
  "properties": {
    "gn:admin1_code":"35",
    "gn:admin2_code":"13600.0",
    "gn:asciiname":"Caimital",
    "gn:country_code":"CO",
    "gn:dem":37,
    "gn:feature_class":"P",
    "gn:feature_code":"PPL",
    "gn:name":"Caimital",
    "gn:population":0,
    "gn:timezone":"America/Bogota",
    "iso:country":"CO",
    "name:spa_x_preferred":[
        "Caimital"
    ],
    "name:und_x_variant":[
        "Caserio Caimital",
        "Caimital"
    ],
    "wof:name":"Caimital",
    "wof:placetype":"locality"
},
  "geometry": {"coordinates":[-73.88901,8.61868],"type":"Point"}
}