{
  "type": "Feature",
  "properties": {
    "gn:admin1_code":"27",
    "gn:admin2_code":"70215.0",
    "gn:asciiname":"Don Alonso",
    "gn:country_code":"CO",
    "gn:dem":163,
    "gn:feature_class":"P",
    "gn:feature_code":"PPL",
    "gn:name":"Don Alonso",
    "gn:population":0,
    "gn:timezone":"America/Bogota",
    "iso:country":"CO",
    "name:spa_x_preferred":[
        "Don Alonso"
    ],
    "wof:name":"Don Alonso",
    "wof:placetype":"locality"
},
  "geometry": {"coordinates":[-75.32932,9.2192],"type":"Point"}
}