{
  "type": "Feature",
  "properties": {
    "gn:admin1_code":"11.0",
    "gn:admin2_code":"27615.0",
    "gn:asciiname":"Sicuela",
    "gn:country_code":"CO",
    "gn:dem":2,
    "gn:feature_class":"P",
    "gn:feature_code":"PPL",
    "gn:name":"Sicuela",
    "gn:population":0,
    "gn:timezone":"America/Bogota",
    "iso:country":"CO",
    "name:spa_x_preferred":[
        "Sicuela"
    ],
    "wof:name":"Sicuela",
    "wof:placetype":"locality"
},
  "geometry": {"coordinates":[-77.108,7.41459],"type":"Point"}
}