{
  "type": "Feature",
  "properties": {
    "gn:admin1_code":"19",
    "gn:admin2_code":"50689",
    "gn:asciiname":"Las Acacias",
    "gn:country_code":"CO",
    "gn:dem":379,
    "gn:feature_class":"P",
    "gn:feature_code":"PPL",
    "gn:name":"Las Acacias",
    "gn:population":0,
    "gn:timezone":"America/Bogota",
    "iso:country":"CO",
    "name:spa_x_preferred":[
        "Las Acacias"
    ],
    "wof:name":"Las Acacias",
    "wof:placetype":"locality"
},
  "geometry": {"coordinates":[-73.67793,3.61757],"type":"Point"}
}