{
  "type": "Feature",
  "properties": {
    "iso:country":"CO",
    "name:ast_x_preferred":[
        "Tenjo"
    ],
    "name:ceb_x_preferred":[
        "Tenjo"
    ],
    "name:deu_x_preferred":[
        "Tenjo"
    ],
    "name:eng_x_preferred":[
        "Tenjo"
    ],
    "name:epo_x_preferred":[
        "Tenjo"
    ],
    "name:fin_x_preferred":[
        "Tenjo"
    ],
    "name:fra_x_preferred":[
        "Tenjo"
    ],
    "name:ita_x_preferred":[
        "Tenjo"
    ],
    "name:kat_x_preferred":[
        "\u10e2\u10d4\u10dc\u10ee\u10dd"
    ],
    "name:msa_x_preferred":[
        "Tenjo"
    ],
    "name:nan_x_preferred":[
        "Tenjo"
    ],
    "name:nld_x_preferred":[
        "Tenjo"
    ],
    "name:spa_x_preferred":[
        "Tenjo"
    ],
    "name:swe_x_preferred":[
        "Tenjo"
    ],
    "name:tgl_x_preferred":[
        "Tenjo"
    ],
    "name:vie_x_preferred":[
        "Tenjo"
    ],
    "name:war_x_preferred":[
        "Tenjo"
    ],
    "name:zho_min_nan_x_preferred":[
        "Tenjo"
    ],
    "name:zho_x_preferred":[
        "\u6ed5\u970d"
    ],
    "qs:gn_country":"CO",
    "qs:gn_fcode":"PPL",
    "qs:gn_pop":3858,
    "qs:name":"Tenjo",
    "qs:name_adm0":"Colombia",
    "qs:name_adm1":"Cundinamarca",
    "qs:photos":270,
    "qs:photos_1k":55,
    "qs:photos_9k":1,
    "qs:photos_9r":4,
    "qs:photos_all":270,
    "qs:photos_sr":5,
    "qs:placetype":"Town",
    "qs:pop_sr":"4",
    "qs:woe_adm0":23424787,
    "wof:name":"Tenjo",
    "wof:placetype":"locality",
    "wof:population":3858
},
  "geometry": {"coordinates":[-74.14435,4.8727],"type":"Point"}
}