{
  "type": "Feature",
  "properties": {
    "gn:admin1_code":"16.0",
    "gn:admin2_code":"41078.0",
    "gn:asciiname":"Vegonia",
    "gn:cc2":"CO",
    "gn:country_code":"CO",
    "gn:dem":1187,
    "gn:feature_class":"P",
    "gn:feature_code":"PPL",
    "gn:name":"Vegonia",
    "gn:population":0,
    "gn:timezone":"America/Bogota",
    "iso:country":"CO",
    "name:und_x_variant":[
        "Begonia",
        "Vegonia"
    ],
    "wof:name":"Vegonia",
    "wof:placetype":"locality"
},
  "geometry": {"coordinates":[-74.95,3.23333],"type":"Point"}
}