{
  "type": "Feature",
  "properties": {
    "gn:admin1_code":"36",
    "gn:admin2_code":"15293.0",
    "gn:asciiname":"Jupal",
    "gn:country_code":"CO",
    "gn:dem":2570,
    "gn:feature_class":"P",
    "gn:feature_code":"PPL",
    "gn:name":"Jupal",
    "gn:population":0,
    "gn:timezone":"America/Bogota",
    "iso:country":"CO",
    "wof:name":"Jupal",
    "wof:placetype":"locality"
},
  "geometry": {"coordinates":[-73.52221999999998,5.74389],"type":"Point"}
}