{
  "type": "Feature",
  "properties": {
    "gn:admin1_code":"38",
    "gn:admin2_code":"47660.0",
    "gn:asciiname":"Manantial",
    "gn:country_code":"CO",
    "gn:dem":169,
    "gn:feature_class":"P",
    "gn:feature_code":"PPL",
    "gn:name":"Manantial",
    "gn:population":0,
    "gn:timezone":"America/Bogota",
    "iso:country":"CO",
    "wof:name":"Manantial",
    "wof:placetype":"locality"
},
  "geometry": {"coordinates":[-74.25968,10.01078],"type":"Point"}
}