{
  "type": "Feature",
  "properties": {
    "gn:admin1_code":"29.0",
    "gn:admin2_code":"76616.0",
    "gn:asciiname":"Las Esperanza",
    "gn:country_code":"CO",
    "gn:dem":1458,
    "gn:feature_class":"P",
    "gn:feature_code":"PPL",
    "gn:name":"Las Esperanza",
    "gn:population":0,
    "gn:timezone":"America/Bogota",
    "iso:country":"CO",
    "wof:name":"Las Esperanza",
    "wof:placetype":"locality"
},
  "geometry": {"coordinates":[-76.35805999999999,4.09],"type":"Point"}
}