{
  "type": "Feature",
  "properties": {
    "gn:admin1_code":"20.0",
    "gn:admin2_code":"52001.0",
    "gn:asciiname":"Mujundinoy",
    "gn:country_code":"CO",
    "gn:dem":2835,
    "gn:feature_class":"P",
    "gn:feature_code":"PPL",
    "gn:name":"Mujundinoy",
    "gn:population":0,
    "gn:timezone":"America/Bogota",
    "iso:country":"CO",
    "wof:name":"Mujundinoy",
    "wof:placetype":"locality"
},
  "geometry": {"coordinates":[-77.11496,1.10192],"type":"Point"}
}