{
  "type": "Feature",
  "properties": {
    "gn:admin1_code":"36.0",
    "gn:admin2_code":"15332.0",
    "gn:asciiname":"Lagunas",
    "gn:country_code":"CO",
    "gn:dem":3817,
    "gn:feature_class":"P",
    "gn:feature_code":"PPL",
    "gn:name":"Lagunas",
    "gn:population":0,
    "gn:timezone":"America/Bogota",
    "iso:country":"CO",
    "name:ceb_x_preferred":[
        "Lagunas"
    ],
    "name:deu_x_preferred":[
        "Lagunas"
    ],
    "name:por_x_preferred":[
        "Lagunas"
    ],
    "name:spa_x_preferred":[
        "Lagunas"
    ],
    "name:srp_x_preferred":[
        "\u041b\u0430\u0433\u0443\u043d\u0430\u0441"
    ],
    "name:swe_x_preferred":[
        "Lagunas"
    ],
    "wof:name":"Lagunas",
    "wof:placetype":"locality"
},
  "geometry": {"coordinates":[-72.38514000000001,6.42101],"type":"Point"}
}