{
  "type": "Feature",
  "properties": {
    "gn:admin1_code":"4",
    "gn:admin2_code":"8638.0",
    "gn:asciiname":"Los Campanos",
    "gn:cc2":"CO",
    "gn:country_code":"CO",
    "gn:dem":74,
    "gn:feature_class":"P",
    "gn:feature_code":"PPL",
    "gn:name":"Los Campanos",
    "gn:population":0,
    "gn:timezone":"America/Bogota",
    "iso:country":"CO",
    "name:und_x_variant":[
        "Hacienda Los Campanos",
        "Los Campanos"
    ],
    "wof:name":"Los Campanos",
    "wof:placetype":"locality"
},
  "geometry": {"coordinates":[-74.98333000000002,10.55],"type":"Point"}
}