{
  "type": "Feature",
  "properties": {
    "gn:admin1_code":"12",
    "gn:admin2_code":"23686.0",
    "gn:asciiname":"El Cerrito",
    "gn:country_code":"CO",
    "gn:dem":14,
    "gn:feature_class":"P",
    "gn:feature_code":"PPL",
    "gn:name":"El Cerrito",
    "gn:population":0,
    "gn:timezone":"America/Bogota",
    "iso:country":"CO",
    "wof:name":"El Cerrito",
    "wof:placetype":"locality"
},
  "geometry": {"coordinates":[-75.86717,8.91754],"type":"Point"}
}