{
  "type": "Feature",
  "properties": {
    "gn:admin1_code":"29",
    "gn:admin2_code":"76248.0",
    "gn:asciiname":"Finalfa",
    "gn:country_code":"CO",
    "gn:dem":986,
    "gn:feature_class":"P",
    "gn:feature_code":"PPL",
    "gn:name":"Finalfa",
    "gn:population":0,
    "gn:timezone":"America/Bogota",
    "iso:country":"CO",
    "wof:name":"Finalfa",
    "wof:placetype":"locality"
},
  "geometry": {"coordinates":[-76.35472,3.62028],"type":"Point"}
}