{
  "type": "Feature",
  "properties": {
    "gn:admin1_code":"3.0",
    "gn:admin2_code":"81065.0",
    "gn:asciiname":"Caserio Santa Isabel",
    "gn:country_code":"CO",
    "gn:dem":155,
    "gn:feature_class":"P",
    "gn:feature_code":"PPL",
    "gn:name":"Caser\u00edo Santa Isabel",
    "gn:population":0,
    "gn:timezone":"America/Bogota",
    "iso:country":"CO",
    "wof:name":"Caserio Santa Isabel",
    "wof:placetype":"locality"
},
  "geometry": {"coordinates":[-71.38028,6.80556],"type":"Point"}
}