{
  "type": "Feature",
  "properties": {
    "gn:admin1_code":"33",
    "gn:admin2_code":"25438.0",
    "gn:asciiname":"Lazarza",
    "gn:country_code":"CO",
    "gn:dem":375,
    "gn:feature_class":"P",
    "gn:feature_code":"PPL",
    "gn:name":"Lazarza",
    "gn:population":0,
    "gn:timezone":"America/Bogota",
    "iso:country":"CO",
    "wof:name":"Lazarza",
    "wof:placetype":"locality"
},
  "geometry": {"coordinates":[-73.32619,4.45407],"type":"Point"}
}