{
  "type": "Feature",
  "properties": {
    "gn:admin1_code":"38",
    "gn:admin2_code":"47058.0",
    "gn:asciiname":"Los Andes",
    "gn:country_code":"CO",
    "gn:dem":192,
    "gn:feature_class":"P",
    "gn:feature_code":"PPL",
    "gn:name":"Los Andes",
    "gn:population":0,
    "gn:timezone":"America/Bogota",
    "iso:country":"CO",
    "wof:name":"Los Andes",
    "wof:placetype":"locality"
},
  "geometry": {"coordinates":[-74.25695,9.90028],"type":"Point"}
}