{
  "type": "Feature",
  "properties": {
    "gn:admin1_code":"12",
    "gn:admin2_code":"23182.0",
    "gn:asciiname":"Arrimadero",
    "gn:country_code":"CO",
    "gn:dem":106,
    "gn:feature_class":"P",
    "gn:feature_code":"PPL",
    "gn:name":"Arrimadero",
    "gn:population":0,
    "gn:timezone":"America/Bogota",
    "iso:country":"CO",
    "wof:name":"Arrimadero",
    "wof:placetype":"locality"
},
  "geometry": {"coordinates":[-75.42272,9.04629],"type":"Point"}
}