{
  "type": "Feature",
  "properties": {
    "gn:admin1_code":"12",
    "gn:admin2_code":"23001.0",
    "gn:asciiname":"La Dorada",
    "gn:country_code":"CO",
    "gn:dem":166,
    "gn:feature_class":"P",
    "gn:feature_code":"PPL",
    "gn:name":"La Dorada",
    "gn:population":0,
    "gn:timezone":"America/Bogota",
    "iso:country":"CO",
    "wof:name":"La Dorada",
    "wof:placetype":"locality"
},
  "geometry": {"coordinates":[-76.08389,8.86889],"type":"Point"}
}