{
  "type": "Feature",
  "properties": {
    "gn:admin1_code":"32",
    "gn:admin2_code":"85410.0",
    "gn:asciiname":"El Horizonte",
    "gn:country_code":"CO",
    "gn:dem":163,
    "gn:feature_class":"P",
    "gn:feature_code":"PPL",
    "gn:name":"El Horizonte",
    "gn:population":0,
    "gn:timezone":"America/Bogota",
    "iso:country":"CO",
    "wof:name":"El Horizonte",
    "wof:placetype":"locality"
},
  "geometry": {"coordinates":[-72.39943000000002,4.46913],"type":"Point"}
}