{
  "type": "Feature",
  "properties": {
    "gn:country":"CO",
    "gn:fcode":"PPL",
    "gn:population":3353,
    "iso:country":"CO",
    "name:ast_x_preferred":[
        "Socha"
    ],
    "name:avk_x_preferred":[
        "Socha"
    ],
    "name:ceb_x_preferred":[
        "Socha"
    ],
    "name:eng_x_preferred":[
        "Socha"
    ],
    "name:fas_x_preferred":[
        "\u0633\u0648\u0686\u0627"
    ],
    "name:fra_x_preferred":[
        "Socha"
    ],
    "name:gle_x_preferred":[
        "Socha"
    ],
    "name:glg_x_preferred":[
        "Socha"
    ],
    "name:ita_x_preferred":[
        "Socha"
    ],
    "name:jpn_x_preferred":[
        "\u30bd\u30c1\u30e3"
    ],
    "name:kat_x_preferred":[
        "\u10e1\u10dd\u10e9\u10d0"
    ],
    "name:msa_x_preferred":[
        "Socha"
    ],
    "name:nan_x_preferred":[
        "Socha"
    ],
    "name:nld_x_preferred":[
        "Socha"
    ],
    "name:pol_x_preferred":[
        "Socha"
    ],
    "name:por_x_preferred":[
        "Socha"
    ],
    "name:rus_x_preferred":[
        "\u0421\u043e\u0447\u0430"
    ],
    "name:spa_x_preferred":[
        "Socha"
    ],
    "name:swe_x_preferred":[
        "Socha"
    ],
    "name:tgl_x_preferred":[
        "Socha"
    ],
    "name:vie_x_preferred":[
        "Socha"
    ],
    "name:war_x_preferred":[
        "Socha"
    ],
    "name:zho_x_preferred":[
        "\u7d22\u67e5"
    ],
    "qs_pg:aaroncc":"CO",
    "qs_pg:gn_country":"CO",
    "qs_pg:gn_fcode":"PPL",
    "qs_pg:gn_pop":3353,
    "qs_pg:name":"Socha Viejo",
    "qs_pg:photos_9r":0,
    "qs_pg:photos_sr":0,
    "qs_pg:pop_sr":4,
    "qs_pg:qs_pg_placetype":"locality",
    "wof:name":"Socha Viejo",
    "wof:placetype":"locality",
    "wof:population":3353
},
  "geometry": {"coordinates":[-72.71503,5.9817],"type":"Point"}
}