{
  "type": "Feature",
  "properties": {
    "gn:gn_country":"CO",
    "gn:gn_fcode":"PPL",
    "gn:gn_pop":3353,
    "gn:population":3353,
    "iso:country":"CO",
    "name:eng_x_preferred":[
        "Socha"
    ],
    "name:fra_x_preferred":[
        "Socha"
    ],
    "name:ita_x_preferred":[
        "Socha"
    ],
    "name:kat_x_preferred":[
        "\u10e1\u10dd\u10e9\u10d0"
    ],
    "name:msa_x_preferred":[
        "Socha"
    ],
    "name:nan_x_preferred":[
        "Socha"
    ],
    "name:nld_x_preferred":[
        "Socha"
    ],
    "name:por_x_preferred":[
        "Socha"
    ],
    "name:spa_x_preferred":[
        "Socha"
    ],
    "name:swe_x_preferred":[
        "Socha"
    ],
    "name:tgl_x_preferred":[
        "Socha"
    ],
    "name:unk_x_variant":[
        "Socha"
    ],
    "name:vie_x_preferred":[
        "Socha"
    ],
    "name:war_x_preferred":[
        "Socha"
    ],
    "name:zho_x_preferred":[
        "\u7d22\u67e5"
    ],
    "qs_pg:aaroncc":"CO",
    "qs_pg:gn_country":"CO",
    "qs_pg:gn_fcode":"PPL",
    "qs_pg:gn_pop":3353,
    "qs_pg:name":"Socha Viejo",
    "qs_pg:photos_9r":0,
    "qs_pg:photos_sr":0,
    "qs_pg:pop_sr":4,
    "qs_pg:qs_pg_placetype":"locality",
    "wof:name":"Socha Viejo",
    "wof:placetype":"locality",
    "wof:population":3353
},
  "geometry": {"coordinates":[-72.71503,5.9817],"type":"Point"}
}