{
  "type": "Feature",
  "properties": {
    "gn:admin1_code":"11.0",
    "gn:admin2_code":"27615.0",
    "gn:asciiname":"El Cuna",
    "gn:country_code":"CO",
    "gn:dem":1,
    "gn:feature_class":"P",
    "gn:feature_code":"PPL",
    "gn:name":"El Cuna",
    "gn:population":0,
    "gn:timezone":"America/Bogota",
    "iso:country":"CO",
    "wof:name":"El Cuna",
    "wof:placetype":"locality"
},
  "geometry": {"coordinates":[-77.10179000000002,7.53002],"type":"Point"}
}