{
  "type": "Feature",
  "properties": {
    "gn:admin1_code":"37.0",
    "gn:admin2_code":"17272.0",
    "gn:asciiname":"Villa Martin",
    "gn:country_code":"CO",
    "gn:dem":1203,
    "gn:feature_class":"P",
    "gn:feature_code":"PPL",
    "gn:name":"Villa Mart\u00edn",
    "gn:population":0,
    "gn:timezone":"America/Bogota",
    "iso:country":"CO",
    "wof:name":"Villa Martin",
    "wof:placetype":"locality"
},
  "geometry": {"coordinates":[-75.65000000000001,5.28333],"type":"Point"}
}