{
  "type": "Feature",
  "properties": {
    "gn:admin1_code":"26",
    "gn:admin2_code":"68176.0",
    "gn:asciiname":"Caracoli",
    "gn:country_code":"CO",
    "gn:dem":1406,
    "gn:feature_class":"P",
    "gn:feature_code":"PPL",
    "gn:name":"Caracol\u00ed",
    "gn:population":0,
    "gn:timezone":"America/Bogota",
    "iso:country":"CO",
    "wof:name":"Caracoli",
    "wof:placetype":"locality"
},
  "geometry": {"coordinates":[-73.38257,6.35619],"type":"Point"}
}