{
  "type": "Feature",
  "properties": {
    "gn:admin1_code":"12",
    "gn:admin2_code":"23001.0",
    "gn:asciiname":"El Torno",
    "gn:country_code":"CO",
    "gn:dem":33,
    "gn:feature_class":"P",
    "gn:feature_code":"PPL",
    "gn:name":"El Torno",
    "gn:population":0,
    "gn:timezone":"America/Bogota",
    "iso:country":"CO",
    "name:ara_x_preferred":[
        "\u0625\u0644 \u062a\u0648\u0631\u0646\u0648"
    ],
    "name:ast_x_preferred":[
        "El Torno"
    ],
    "name:cat_x_preferred":[
        "El Torno"
    ],
    "name:ceb_x_preferred":[
        "El Torno"
    ],
    "name:epo_x_preferred":[
        "El Torno"
    ],
    "name:eus_x_preferred":[
        "El Torno"
    ],
    "name:ext_x_preferred":[
        "El Tornu"
    ],
    "name:fra_x_preferred":[
        "El Torno"
    ],
    "name:hun_x_preferred":[
        "El Torno"
    ],
    "name:hye_x_preferred":[
        "\u0537\u056c \u054f\u0578\u0580\u0576\u0578"
    ],
    "name:ina_x_preferred":[
        "El Torno"
    ],
    "name:ita_x_preferred":[
        "El Torno"
    ],
    "name:msa_x_preferred":[
        "El Torno"
    ],
    "name:nld_x_preferred":[
        "El Torno"
    ],
    "name:oci_x_preferred":[
        "El Torno"
    ],
    "name:pol_x_preferred":[
        "El Torno"
    ],
    "name:por_x_preferred":[
        "El Torno"
    ],
    "name:ron_x_preferred":[
        "El Torno"
    ],
    "name:rus_x_preferred":[
        "\u042d\u043b\u044c-\u0422\u043e\u0440\u043d\u043e"
    ],
    "name:spa_x_preferred":[
        "El Torno"
    ],
    "name:ukr_x_preferred":[
        "\u0415\u043b\u044c-\u0422\u043e\u0440\u043d\u043e"
    ],
    "name:uzb_x_preferred":[
        "El Torno"
    ],
    "name:vie_x_preferred":[
        "El Torno"
    ],
    "name:war_x_preferred":[
        "El Torno"
    ],
    "name:zho_x_preferred":[
        "\u57c3\u5c14\u6258\u5c14\u8bfa"
    ],
    "wof:name":"El Torno",
    "wof:placetype":"locality"
},
  "geometry": {"coordinates":[-76.05,8.35],"type":"Point"}
}