{
  "type": "Feature",
  "properties": {
    "iso:country":"CO",
    "name:ast_x_preferred":[
        "Ovejas"
    ],
    "name:ceb_x_preferred":[
        "Ovejas"
    ],
    "name:deu_x_preferred":[
        "Ovejas"
    ],
    "name:eng_x_preferred":[
        "Ovejas"
    ],
    "name:fas_x_preferred":[
        "\u0627\u0648\u0648\u062e\u0627\u0633"
    ],
    "name:fra_x_preferred":[
        "Ovejas"
    ],
    "name:ita_x_preferred":[
        "Ovejas"
    ],
    "name:kat_x_preferred":[
        "\u10dd\u10d5\u10d4\u10ee\u10d0\u10e1\u10d8"
    ],
    "name:msa_x_preferred":[
        "Ovejas"
    ],
    "name:nan_x_preferred":[
        "Ovejas"
    ],
    "name:nld_x_preferred":[
        "Ovejas"
    ],
    "name:spa_x_preferred":[
        "Ovejas"
    ],
    "name:swe_x_preferred":[
        "Ovejas"
    ],
    "name:vie_x_preferred":[
        "Ovejas"
    ],
    "name:war_x_preferred":[
        "Ovejas"
    ],
    "name:zho_x_preferred":[
        "\u5967\u97cb\u54c8\u65af"
    ],
    "qs:gn_country":"CO",
    "qs:gn_fcode":"PPL",
    "qs:gn_pop":13284,
    "qs:name":"Ovejas",
    "qs:name_adm0":"Colombia",
    "qs:name_adm1":"Sucre",
    "qs:photos":20,
    "qs:photos_1k":4,
    "qs:photos_9k":1,
    "qs:photos_9r":1,
    "qs:photos_all":20,
    "qs:photos_sr":1,
    "qs:placetype":"Town",
    "qs:pop_sr":"6",
    "qs:woe_adm0":23424787,
    "wof:name":"Ovejas",
    "wof:placetype":"locality",
    "wof:population":13284
},
  "geometry": {"coordinates":[-75.22382,9.53248],"type":"Point"}
}