{
  "type": "Feature",
  "properties": {
    "gn:admin1_code":"31.0",
    "gn:admin2_code":"99524.0",
    "gn:asciiname":"Santa Librada",
    "gn:country_code":"CO",
    "gn:dem":109,
    "gn:feature_class":"P",
    "gn:feature_code":"PPL",
    "gn:name":"Santa Librada",
    "gn:population":0,
    "gn:timezone":"America/Bogota",
    "iso:country":"CO",
    "wof:name":"Santa Librada",
    "wof:placetype":"locality"
},
  "geometry": {"coordinates":[-69.92497,5.69481],"type":"Point"}
}