{
  "type": "Feature",
  "properties": {
    "gn:admin1_code":"12.0",
    "gn:admin2_code":"23417.0",
    "gn:asciiname":"Vuelta de San Juan",
    "gn:country_code":"CO",
    "gn:dem":5,
    "gn:feature_class":"P",
    "gn:feature_code":"PPL",
    "gn:name":"Vuelta de San Juan",
    "gn:population":0,
    "gn:timezone":"America/Bogota",
    "iso:country":"CO",
    "wof:name":"Vuelta de San Juan",
    "wof:placetype":"locality"
},
  "geometry": {"coordinates":[-75.91729000000002,9.30603],"type":"Point"}
}