{
  "type": "Feature",
  "properties": {
    "gn:admin1_code":"10",
    "gn:admin2_code":"20175.0",
    "gn:asciiname":"La Brillantina",
    "gn:country_code":"CO",
    "gn:dem":34,
    "gn:feature_class":"P",
    "gn:feature_code":"PPL",
    "gn:name":"La Brillantina",
    "gn:population":0,
    "gn:timezone":"America/Bogota",
    "iso:country":"CO",
    "wof:name":"La Brillantina",
    "wof:placetype":"locality"
},
  "geometry": {"coordinates":[-73.75749999999999,9.42556],"type":"Point"}
}