{
  "type": "Feature",
  "properties": {
    "gn:admin1_code":"20",
    "gn:admin2_code":"52405.0",
    "gn:asciiname":"Plan Grande",
    "gn:country_code":"CO",
    "gn:dem":1059,
    "gn:feature_class":"P",
    "gn:feature_code":"PPL",
    "gn:name":"Plan Grande",
    "gn:population":0,
    "gn:timezone":"America/Bogota",
    "iso:country":"CO",
    "wof:name":"Plan Grande",
    "wof:placetype":"locality"
},
  "geometry": {"coordinates":[-77.31222,1.87583],"type":"Point"}
}