{
  "type": "Feature",
  "properties": {
    "gn:admin1_code":"9",
    "gn:admin2_code":"19473.0",
    "gn:asciiname":"Chorrea Blanca",
    "gn:country_code":"CO",
    "gn:dem":2167,
    "gn:feature_class":"P",
    "gn:feature_code":"PPL",
    "gn:name":"Chorrea Blanca",
    "gn:population":0,
    "gn:timezone":"America/Bogota",
    "iso:country":"CO",
    "wof:name":"Chorrea Blanca",
    "wof:placetype":"locality"
},
  "geometry": {"coordinates":[-76.79174,2.78086],"type":"Point"}
}