{
  "type": "Feature",
  "properties": {
    "gn:admin1_code":"32.0",
    "gn:admin2_code":"85139.0",
    "gn:asciiname":"Sonora",
    "gn:country_code":"CO",
    "gn:dem":192,
    "gn:feature_class":"P",
    "gn:feature_code":"PPL",
    "gn:name":"Sonora",
    "gn:population":0,
    "gn:timezone":"America/Bogota",
    "iso:country":"CO",
    "wof:name":"Sonora",
    "wof:placetype":"locality"
},
  "geometry": {"coordinates":[-72.28333000000001,4.98333],"type":"Point"}
}