{
  "type": "Feature",
  "properties": {
    "gn:admin1_code":"27",
    "gn:admin2_code":"70233.0",
    "gn:asciiname":"El Enamorado",
    "gn:country_code":"CO",
    "gn:dem":108,
    "gn:feature_class":"P",
    "gn:feature_code":"PPL",
    "gn:name":"El Enamorado",
    "gn:population":0,
    "gn:timezone":"America/Bogota",
    "iso:country":"CO",
    "wof:name":"El Enamorado",
    "wof:placetype":"locality"
},
  "geometry": {"coordinates":[-75.15373000000002,9.15486],"type":"Point"}
}