{
  "type": "Feature",
  "properties": {
    "gn:admin1_code":"10.0",
    "gn:admin2_code":"20750.0",
    "gn:asciiname":"Hacienda Campo Piedra",
    "gn:country_code":"CO",
    "gn:dem":108,
    "gn:feature_class":"P",
    "gn:feature_code":"PPL",
    "gn:name":"Hacienda Campo Piedra",
    "gn:population":0,
    "gn:timezone":"America/Bogota",
    "iso:country":"CO",
    "wof:name":"Hacienda Campo Piedra",
    "wof:placetype":"locality"
},
  "geometry": {"coordinates":[-73.26729,10.1395],"type":"Point"}
}