{
  "type": "Feature",
  "properties": {
    "gn:admin1_code":"35",
    "gn:admin2_code":"13473.0",
    "gn:asciiname":"Belle Vista",
    "gn:country_code":"CO",
    "gn:dem":38,
    "gn:feature_class":"P",
    "gn:feature_code":"PPL",
    "gn:name":"Belle Vista",
    "gn:population":0,
    "gn:timezone":"America/Bogota",
    "iso:country":"CO",
    "wof:name":"Belle Vista",
    "wof:placetype":"locality"
},
  "geometry": {"coordinates":[-73.78237,8.38293],"type":"Point"}
}