{
  "type": "Feature",
  "properties": {
    "gn:admin1_code":"9.0",
    "gn:asciiname":"La Playa",
    "gn:country_code":"CO",
    "gn:dem":2664,
    "gn:feature_class":"P",
    "gn:feature_code":"PPL",
    "gn:name":"La Playa",
    "gn:population":0,
    "gn:timezone":"America/Bogota",
    "iso:country":"CO",
    "name:spa_x_preferred":[
        "La Playa"
    ],
    "wof:name":"La Playa",
    "wof:placetype":"locality"
},
  "geometry": {"coordinates":[-76.9751,1.47186],"type":"Point"}
}