{
  "type": "Feature",
  "properties": {
    "gn:admin1_code":"17.0",
    "gn:admin2_code":"44090.0",
    "gn:asciiname":"San Miguel",
    "gn:country_code":"CO",
    "gn:dem":74,
    "gn:feature_class":"P",
    "gn:feature_code":"PPL",
    "gn:name":"San Miguel",
    "gn:population":0,
    "gn:timezone":"America/Bogota",
    "iso:country":"CO",
    "wof:name":"San Miguel",
    "wof:placetype":"locality"
},
  "geometry": {"coordinates":[-73.24722,11.21778],"type":"Point"}
}