{
  "type": "Feature",
  "properties": {
    "gn:admin1_code":"2",
    "gn:admin2_code":"5364.0",
    "gn:asciiname":"Tebaida",
    "gn:country_code":"CO",
    "gn:dem":2354,
    "gn:feature_class":"P",
    "gn:feature_code":"PPL",
    "gn:name":"Tebaida",
    "gn:population":0,
    "gn:timezone":"America/Bogota",
    "iso:country":"CO",
    "wof:name":"Tebaida",
    "wof:placetype":"locality"
},
  "geometry": {"coordinates":[-75.78702,5.57322],"type":"Point"}
}