{
  "type": "Feature",
  "properties": {
    "gn:admin1_code":"19.0",
    "gn:admin2_code":"50689.0",
    "gn:asciiname":"Rancho Viejo",
    "gn:country_code":"CO",
    "gn:dem":419,
    "gn:feature_class":"P",
    "gn:feature_code":"PPL",
    "gn:name":"Rancho Viejo",
    "gn:population":0,
    "gn:timezone":"America/Bogota",
    "iso:country":"CO",
    "name:ceb_x_preferred":[
        "Rancho Viejo"
    ],
    "name:deu_x_preferred":[
        "Rancho Viejo"
    ],
    "name:ita_x_preferred":[
        "Rancho Viejo"
    ],
    "name:spa_x_preferred":[
        "Rancho Viejo"
    ],
    "name:srp_x_preferred":[
        "\u0420\u0430\u043d\u0447\u043e \u0412\u0438\u0458\u0435\u0445\u043e"
    ],
    "name:swe_x_preferred":[
        "Rancho Viejo"
    ],
    "wof:name":"Rancho Viejo",
    "wof:placetype":"locality"
},
  "geometry": {"coordinates":[-73.73291999999999,3.66618],"type":"Point"}
}