{
  "type": "Feature",
  "properties": {
    "gn:admin1_code":"33",
    "gn:admin2_code":"25473.0",
    "gn:asciiname":"El Nogal",
    "gn:country_code":"CO",
    "gn:dem":2554,
    "gn:feature_class":"P",
    "gn:feature_code":"PPL",
    "gn:name":"El Nogal",
    "gn:population":0,
    "gn:timezone":"America/Bogota",
    "iso:country":"CO",
    "wof:name":"El Nogal",
    "wof:placetype":"locality"
},
  "geometry": {"coordinates":[-74.23314999999999,4.73473],"type":"Point"}
}