{
  "type": "Feature",
  "properties": {
    "gn:admin1_code":"32",
    "gn:admin2_code":"85430.0",
    "gn:asciiname":"Carimagua",
    "gn:country_code":"CO",
    "gn:dem":130,
    "gn:feature_class":"P",
    "gn:feature_code":"PPL",
    "gn:name":"Carimagua",
    "gn:population":0,
    "gn:timezone":"America/Bogota",
    "iso:country":"CO",
    "wof:name":"Carimagua",
    "wof:placetype":"locality"
},
  "geometry": {"coordinates":[-71.04405,5.39372],"type":"Point"}
}