{
  "type": "Feature",
  "properties": {
    "gn:admin1_code":"20.0",
    "gn:admin2_code":"52224.0",
    "gn:asciiname":"San Bernardo",
    "gn:country_code":"CO",
    "gn:dem":3038,
    "gn:feature_class":"P",
    "gn:feature_code":"PPL",
    "gn:name":"San Bernardo",
    "gn:population":0,
    "gn:timezone":"America/Bogota",
    "iso:country":"CO",
    "name:ceb_x_preferred":[
        "San Bernardo"
    ],
    "name:deu_x_preferred":[
        "San Bernardo"
    ],
    "name:epo_x_preferred":[
        "San Bernardo"
    ],
    "name:fin_x_preferred":[
        "San Bernardo"
    ],
    "name:fra_x_preferred":[
        "San Bernardo"
    ],
    "name:heb_x_preferred":[
        "\u05e1\u05df \u05d1\u05e8\u05e0\u05e8\u05d3\u05d5"
    ],
    "name:hun_x_preferred":[
        "San Bernardo"
    ],
    "name:ita_x_preferred":[
        "San Bernardo"
    ],
    "name:nld_x_preferred":[
        "San Bernardo"
    ],
    "name:pol_x_preferred":[
        "San Bernardo"
    ],
    "name:por_x_preferred":[
        "San Bernardo"
    ],
    "name:ron_x_preferred":[
        "San Bernardo"
    ],
    "name:rus_x_preferred":[
        "\u0421\u0430\u043d-\u0411\u0435\u0440\u043d\u0430\u0440\u0434\u043e"
    ],
    "name:sco_x_preferred":[
        "San Bernardo"
    ],
    "name:spa_x_preferred":[
        "San Bernardo"
    ],
    "name:srp_x_preferred":[
        "San Bernardo"
    ],
    "name:swe_x_preferred":[
        "San Bernardo"
    ],
    "name:tgl_x_preferred":[
        "San Bernardo"
    ],
    "name:vie_x_preferred":[
        "San Bernardo"
    ],
    "name:war_x_preferred":[
        "San Bernardo"
    ],
    "wof:name":"San Bernardo",
    "wof:placetype":"locality"
},
  "geometry": {"coordinates":[-77.73202000000001,0.86091],"type":"Point"}
}