{
  "type": "Feature",
  "properties": {
    "gn:admin1_code":"17",
    "gn:admin2_code":"44560.0",
    "gn:asciiname":"Arirapah",
    "gn:country_code":"CO",
    "gn:dem":23,
    "gn:feature_class":"P",
    "gn:feature_code":"PPL",
    "gn:name":"Ar\u00edrapah",
    "gn:population":0,
    "gn:timezone":"America/Bogota",
    "iso:country":"CO",
    "wof:name":"Arirapah",
    "wof:placetype":"locality"
},
  "geometry": {"coordinates":[-72.46639,11.62861],"type":"Point"}
}