{
  "type": "Feature",
  "properties": {
    "gn:admin1_code":"36",
    "gn:admin2_code":"15176.0",
    "gn:asciiname":"Cunday",
    "gn:country_code":"CO",
    "gn:dem":2702,
    "gn:feature_class":"P",
    "gn:feature_code":"PPL",
    "gn:name":"Cunday",
    "gn:population":0,
    "gn:timezone":"America/Bogota",
    "iso:country":"CO",
    "name:ceb_x_preferred":[
        "Cunday"
    ],
    "name:fra_x_preferred":[
        "Cunday"
    ],
    "name:ita_x_preferred":[
        "Cunday"
    ],
    "name:kat_x_preferred":[
        "\u10d9\u10e3\u10dc\u10d3\u10d0\u10d8"
    ],
    "name:msa_x_preferred":[
        "Cunday"
    ],
    "name:nld_x_preferred":[
        "Cunday"
    ],
    "name:spa_x_preferred":[
        "Cunday"
    ],
    "name:swe_x_preferred":[
        "Cunday"
    ],
    "name:vie_x_preferred":[
        "Cunday"
    ],
    "name:war_x_preferred":[
        "Cunday"
    ],
    "wof:name":"Cunday",
    "wof:placetype":"locality"
},
  "geometry": {"coordinates":[-73.81721999999998,5.63722],"type":"Point"}
}