{
  "type": "Feature",
  "properties": {
    "gn:admin1_code":"2",
    "gn:admin2_code":"5887.0",
    "gn:asciiname":"Barroblanco",
    "gn:country_code":"CO",
    "gn:dem":2186,
    "gn:feature_class":"P",
    "gn:feature_code":"PPL",
    "gn:name":"Barroblanco",
    "gn:population":0,
    "gn:timezone":"America/Bogota",
    "iso:country":"CO",
    "wof:name":"Barroblanco",
    "wof:placetype":"locality"
},
  "geometry": {"coordinates":[-75.45528,7.05361],"type":"Point"}
}