{
  "type": "Feature",
  "properties": {
    "gn:admin1_code":"4",
    "gn:admin2_code":"8436.0",
    "gn:asciiname":"Ambrosio",
    "gn:country_code":"CO",
    "gn:dem":9,
    "gn:feature_class":"P",
    "gn:feature_code":"PPL",
    "gn:name":"Ambrosio",
    "gn:population":0,
    "gn:timezone":"America/Bogota",
    "iso:country":"CO",
    "name:und_x_variant":[
        "Ambrosia",
        "Ambrosio"
    ],
    "wof:name":"Ambrosio",
    "wof:placetype":"locality"
},
  "geometry": {"coordinates":[-75.02589999999999,10.46277],"type":"Point"}
}