{
  "type": "Feature",
  "properties": {
    "gn:admin1_code":"10",
    "gn:admin2_code":"20001.0",
    "gn:asciiname":"Belgica",
    "gn:country_code":"CO",
    "gn:dem":140,
    "gn:feature_class":"P",
    "gn:feature_code":"PPL",
    "gn:name":"B\u00e9lgica",
    "gn:population":0,
    "gn:timezone":"America/Bogota",
    "iso:country":"CO",
    "wof:name":"Belgica",
    "wof:placetype":"locality"
},
  "geometry": {"coordinates":[-73.23233,10.45182],"type":"Point"}
}