{
  "type": "Feature",
  "properties": {
    "gn:admin1_code":"9.0",
    "gn:admin2_code":"19809.0",
    "gn:asciiname":"Angostura",
    "gn:country_code":"CO",
    "gn:dem":31,
    "gn:feature_class":"P",
    "gn:feature_code":"PPL",
    "gn:name":"Angostura",
    "gn:population":0,
    "gn:timezone":"America/Bogota",
    "iso:country":"CO",
    "wof:name":"Angostura",
    "wof:placetype":"locality"
},
  "geometry": {"coordinates":[-77.46983,2.74552],"type":"Point"}
}