{
  "type": "Feature",
  "properties": {
    "gn:admin1_code":"35",
    "gn:admin2_code":"13140.0",
    "gn:asciiname":"Juan Andrea",
    "gn:cc2":"CO",
    "gn:country_code":"CO",
    "gn:dem":75,
    "gn:feature_class":"P",
    "gn:feature_code":"PPL",
    "gn:name":"Juan Andrea",
    "gn:population":0,
    "gn:timezone":"America/Bogota",
    "iso:country":"CO",
    "name:und_x_variant":[
        "Juan Andres",
        "Juan Andrea"
    ],
    "wof:name":"Juan Andrea",
    "wof:placetype":"locality"
},
  "geometry": {"coordinates":[-75.03333000000001,10.11667],"type":"Point"}
}