{
  "type": "Feature",
  "properties": {
    "gn:admin1_code":"32.0",
    "gn:admin2_code":"85125.0",
    "gn:asciiname":"Sevilla",
    "gn:country_code":"CO",
    "gn:dem":201,
    "gn:feature_class":"P",
    "gn:feature_code":"PPL",
    "gn:name":"Sevilla",
    "gn:population":0,
    "gn:timezone":"America/Bogota",
    "iso:country":"CO",
    "name:spa_x_preferred":[
        "Sevilla"
    ],
    "wof:name":"Sevilla",
    "wof:placetype":"locality"
},
  "geometry": {"coordinates":[-71.68713000000002,5.94715],"type":"Point"}
}