{
  "type": "Feature",
  "properties": {
    "gn:admin1_code":"9",
    "gn:admin2_code":"19548.0",
    "gn:asciiname":"Uvales",
    "gn:country_code":"CO",
    "gn:dem":1669,
    "gn:feature_class":"P",
    "gn:feature_code":"PPL",
    "gn:name":"Uvales",
    "gn:population":0,
    "gn:timezone":"America/Bogota",
    "iso:country":"CO",
    "wof:name":"Uvales",
    "wof:placetype":"locality"
},
  "geometry": {"coordinates":[-76.57399000000002,2.7255],"type":"Point"}
}