{
  "type": "Feature",
  "properties": {
    "gn:admin1_code":"26.0",
    "gn:admin2_code":"68167.0",
    "gn:asciiname":"La Granada",
    "gn:country_code":"CO",
    "gn:dem":1678,
    "gn:feature_class":"P",
    "gn:feature_code":"PPL",
    "gn:name":"La Granada",
    "gn:population":0,
    "gn:timezone":"America/Bogota",
    "iso:country":"CO",
    "name:ara_x_preferred":[
        "\u0644\u0627 \u063a\u0631\u0646\u0627\u062f\u0627"
    ],
    "name:arg_x_preferred":[
        "La Granada"
    ],
    "name:ast_x_preferred":[
        "La Granada"
    ],
    "name:cat_x_preferred":[
        "La Granada"
    ],
    "name:eus_x_preferred":[
        "La Granada"
    ],
    "name:fra_x_preferred":[
        "La Granada"
    ],
    "name:hun_x_preferred":[
        "La Granada"
    ],
    "name:hye_x_preferred":[
        "\u053c\u0561 \u0533\u0580\u0561\u0576\u0561\u0564\u0561"
    ],
    "name:ita_x_preferred":[
        "La Granada"
    ],
    "name:kaz_x_preferred":[
        "\u041b\u0430-\u0413\u0440\u0430\u043d\u0430\u0434\u0430"
    ],
    "name:lat_x_preferred":[
        "La Granada"
    ],
    "name:msa_x_preferred":[
        "La Granada"
    ],
    "name:nld_x_preferred":[
        "La Granada"
    ],
    "name:oci_x_preferred":[
        "La Granada"
    ],
    "name:pol_x_preferred":[
        "La Granada"
    ],
    "name:por_x_preferred":[
        "La Granada"
    ],
    "name:ron_x_preferred":[
        "La Granada"
    ],
    "name:rus_x_preferred":[
        "\u041b\u0430-\u0413\u0440\u0430\u043d\u0430\u0434\u0430"
    ],
    "name:sco_x_preferred":[
        "La Granada"
    ],
    "name:spa_x_preferred":[
        "La Granada"
    ],
    "name:sqi_x_preferred":[
        "La Granada"
    ],
    "name:ukr_x_preferred":[
        "\u041b\u0430-\u0413\u0440\u0430\u043d\u0430\u0434\u0430"
    ],
    "name:uzb_x_preferred":[
        "La Granada"
    ],
    "name:vie_x_preferred":[
        "La Granada"
    ],
    "name:war_x_preferred":[
        "La Granada"
    ],
    "name:zho_x_preferred":[
        "\u62c9\u683c\u62c9\u7eb3\u8fbe"
    ],
    "wof:name":"La Granada",
    "wof:placetype":"locality"
},
  "geometry": {"coordinates":[-73.22606999999998,6.11641],"type":"Point"}
}