{
  "type": "Feature",
  "properties": {
    "gn:admin1_code":"3",
    "gn:admin2_code":"81220.0",
    "gn:asciiname":"La Prevencion",
    "gn:country_code":"CO",
    "gn:dem":115,
    "gn:feature_class":"P",
    "gn:feature_code":"PPL",
    "gn:name":"La Prevenci\u00f3n",
    "gn:population":0,
    "gn:timezone":"America/Bogota",
    "iso:country":"CO",
    "name:spa_x_preferred":[
        "La Prevenci\u00f3n"
    ],
    "wof:name":"La Prevencion",
    "wof:placetype":"locality"
},
  "geometry": {"coordinates":[-70.5168,6.53885],"type":"Point"}
}