{
  "type": "Feature",
  "properties": {
    "gn:admin1_code":"9",
    "gn:admin2_code":"19130.0",
    "gn:asciiname":"Santa Barbara",
    "gn:country_code":"CO",
    "gn:dem":1708,
    "gn:feature_class":"P",
    "gn:feature_code":"PPL",
    "gn:name":"Santa B\u00e1rbara",
    "gn:population":0,
    "gn:timezone":"America/Bogota",
    "iso:country":"CO",
    "wof:name":"Santa Barbara",
    "wof:placetype":"locality"
},
  "geometry": {"coordinates":[-76.64734,2.64486],"type":"Point"}
}