{
  "type": "Feature",
  "properties": {
    "gn:admin1_code":"2",
    "gn:admin2_code":"5051.0",
    "gn:asciiname":"El Campano",
    "gn:country_code":"CO",
    "gn:dem":70,
    "gn:feature_class":"P",
    "gn:feature_code":"PPL",
    "gn:name":"El Campano",
    "gn:population":0,
    "gn:timezone":"America/Bogota",
    "iso:country":"CO",
    "wof:name":"El Campano",
    "wof:placetype":"locality"
},
  "geometry": {"coordinates":[-76.4742,8.6656],"type":"Point"}
}