{
  "type": "Feature",
  "properties": {
    "gn:admin1_code":"27",
    "gn:admin2_code":"70742.0",
    "gn:asciiname":"Granada",
    "gn:country_code":"CO",
    "gn:dem":140,
    "gn:feature_class":"P",
    "gn:feature_code":"PPL",
    "gn:name":"Granada",
    "gn:population":0,
    "gn:timezone":"America/Bogota",
    "iso:country":"CO",
    "name:und_x_variant":[
        "Corregimiento Granada",
        "Juan Gordo",
        "Granada"
    ],
    "wof:name":"Granada",
    "wof:placetype":"locality"
},
  "geometry": {"coordinates":[-75.04881999999998,9.31609],"type":"Point"}
}