{
  "type": "Feature",
  "properties": {
    "gn:admin1_code":"28.0",
    "gn:admin2_code":"73483.0",
    "gn:asciiname":"Yavi",
    "gn:country_code":"CO",
    "gn:dem":334,
    "gn:feature_class":"P",
    "gn:feature_code":"PPLL",
    "gn:name":"Yavi",
    "gn:population":0,
    "gn:timezone":"America/Bogota",
    "iso:country":"CO",
    "name:deu_x_preferred":[
        "Yavi"
    ],
    "name:fra_x_preferred":[
        "Yavi"
    ],
    "name:ita_x_preferred":[
        "Yavi"
    ],
    "name:nld_x_preferred":[
        "Yavi"
    ],
    "name:spa_x_preferred":[
        "Yavi"
    ],
    "wof:name":"Yavi",
    "wof:placetype":"locality"
},
  "geometry": {"coordinates":[-74.99732,3.67287],"type":"Point"}
}