{
  "type": "Feature",
  "properties": {
    "gn:admin1_code":"35",
    "gn:admin2_code":"13670.0",
    "gn:asciiname":"Lomafresca",
    "gn:country_code":"CO",
    "gn:dem":74,
    "gn:feature_class":"P",
    "gn:feature_code":"PPL",
    "gn:name":"Lomafresca",
    "gn:population":0,
    "gn:timezone":"America/Bogota",
    "iso:country":"CO",
    "wof:name":"Lomafresca",
    "wof:placetype":"locality"
},
  "geometry": {"coordinates":[-73.93474000000001,7.53115],"type":"Point"}
}