{
  "type": "Feature",
  "properties": {
    "gn:admin1_code":"28",
    "gn:admin2_code":"73555.0",
    "gn:asciiname":"Bisinia",
    "gn:country_code":"CO",
    "gn:dem":847,
    "gn:feature_class":"P",
    "gn:feature_code":"PPL",
    "gn:name":"Bisinia",
    "gn:population":0,
    "gn:timezone":"America/Bogota",
    "iso:country":"CO",
    "wof:name":"Bisinia",
    "wof:placetype":"locality"
},
  "geometry": {"coordinates":[-75.61389,3.26556],"type":"Point"}
}