{
  "type": "Feature",
  "properties": {
    "gn:admin1_code":"17",
    "gn:admin2_code":"44090.0",
    "gn:asciiname":"Caracasaca",
    "gn:country_code":"CO",
    "gn:dem":628,
    "gn:feature_class":"P",
    "gn:feature_code":"PPL",
    "gn:name":"Caracasaca",
    "gn:population":0,
    "gn:timezone":"America/Bogota",
    "iso:country":"CO",
    "wof:name":"Caracasaca",
    "wof:placetype":"locality"
},
  "geometry": {"coordinates":[-73.45,11.08333],"type":"Point"}
}