{
  "type": "Feature",
  "properties": {
    "gn:admin1_code":"4",
    "gn:admin2_code":"8606.0",
    "gn:asciiname":"La Tabla",
    "gn:country_code":"CO",
    "gn:dem":337,
    "gn:feature_class":"P",
    "gn:feature_code":"PPL",
    "gn:name":"La Tabla",
    "gn:population":0,
    "gn:timezone":"America/Bogota",
    "iso:country":"CO",
    "name:und_x_variant":[
        "Tabla",
        "Las Tablas",
        "La Tabla"
    ],
    "wof:name":"La Tabla",
    "wof:placetype":"locality"
},
  "geometry": {"coordinates":[-75.22134,10.51989],"type":"Point"}
}