{
  "type": "Feature",
  "properties": {
    "gn:admin1_code":"38.0",
    "gn:admin2_code":"47258.0",
    "gn:asciiname":"Veranillo",
    "gn:country_code":"CO",
    "gn:dem":40,
    "gn:feature_class":"P",
    "gn:feature_code":"PPL",
    "gn:name":"Veranillo",
    "gn:population":0,
    "gn:timezone":"America/Bogota",
    "iso:country":"CO",
    "name:und_x_variant":[
        "Caser\u00edo Veranillo",
        "Veranillo"
    ],
    "wof:name":"Veranillo",
    "wof:placetype":"locality"
},
  "geometry": {"coordinates":[-74.56556999999999,10.28209],"type":"Point"}
}