{
  "type": "Feature",
  "properties": {
    "gn:admin1_code":"2",
    "gn:asciiname":"Bocas",
    "gn:country_code":"CO",
    "gn:dem":803,
    "gn:feature_class":"P",
    "gn:feature_code":"PPL",
    "gn:name":"Bocas",
    "gn:population":0,
    "gn:timezone":"America/Bogota",
    "iso:country":"CO",
    "wof:name":"Bocas",
    "wof:placetype":"locality"
},
  "geometry": {"coordinates":[-75.59466,5.72898],"type":"Point"}
}