{
  "type": "Feature",
  "properties": {
    "gn:admin1_code":"27",
    "gn:admin2_code":"70670.0",
    "gn:asciiname":"Las Camelias",
    "gn:country_code":"CO",
    "gn:dem":176,
    "gn:feature_class":"P",
    "gn:feature_code":"PPL",
    "gn:name":"Las Camelias",
    "gn:population":0,
    "gn:timezone":"America/Bogota",
    "iso:country":"CO",
    "wof:name":"Las Camelias",
    "wof:placetype":"locality"
},
  "geometry": {"coordinates":[-75.41178000000002,9.22955],"type":"Point"}
}