{
  "type": "Feature",
  "properties": {
    "gn:admin1_code":"29",
    "gn:admin2_code":"76497.0",
    "gn:asciiname":"El Chuzo",
    "gn:country_code":"CO",
    "gn:dem":1325,
    "gn:feature_class":"P",
    "gn:feature_code":"PPL",
    "gn:name":"El Chuzo",
    "gn:population":0,
    "gn:timezone":"America/Bogota",
    "iso:country":"CO",
    "wof:name":"El Chuzo",
    "wof:placetype":"locality"
},
  "geometry": {"coordinates":[-75.92222,4.55917],"type":"Point"}
}