{
  "type": "Feature",
  "properties": {
    "gn:admin1_code":"32",
    "gn:admin2_code":"85162.0",
    "gn:asciiname":"La Pica",
    "gn:country_code":"CO",
    "gn:dem":295,
    "gn:feature_class":"P",
    "gn:feature_code":"PPL",
    "gn:name":"La Pica",
    "gn:population":0,
    "gn:timezone":"America/Bogota",
    "iso:country":"CO",
    "wof:name":"La Pica",
    "wof:placetype":"locality"
},
  "geometry": {"coordinates":[-72.90183,4.7417],"type":"Point"}
}