{
  "type": "Feature",
  "properties": {
    "gn:admin1_code":"29",
    "gn:admin2_code":"76890.0",
    "gn:asciiname":"El Cocal",
    "gn:country_code":"CO",
    "gn:dem":942,
    "gn:feature_class":"P",
    "gn:feature_code":"PPL",
    "gn:name":"El Cocal",
    "gn:population":0,
    "gn:timezone":"America/Bogota",
    "iso:country":"CO",
    "name:ita_x_preferred":[
        "El Cocal"
    ],
    "name:spa_x_preferred":[
        "El Cocal"
    ],
    "name:zho_x_preferred":[
        "\u57c3\u5c14\u79d1\u5361\u5c14"
    ],
    "wof:name":"El Cocal",
    "wof:placetype":"locality"
},
  "geometry": {"coordinates":[-76.38083,3.81417],"type":"Point"}
}