{
  "type": "Feature",
  "properties": {
    "gn:admin1_code":"19",
    "gn:admin2_code":"50573.0",
    "gn:asciiname":"La Floresta",
    "gn:country_code":"CO",
    "gn:dem":169,
    "gn:feature_class":"P",
    "gn:feature_code":"PPL",
    "gn:name":"La Floresta",
    "gn:population":0,
    "gn:timezone":"America/Bogota",
    "iso:country":"CO",
    "wof:name":"La Floresta",
    "wof:placetype":"locality"
},
  "geometry": {"coordinates":[-72.44105999999999,4.32299],"type":"Point"}
}