{
  "type": "Feature",
  "properties": {
    "gn:admin1_code":"23",
    "gn:asciiname":"California",
    "gn:country_code":"CO",
    "gn:dem":1354,
    "gn:feature_class":"P",
    "gn:feature_code":"PPL",
    "gn:name":"California",
    "gn:population":0,
    "gn:timezone":"America/Bogota",
    "iso:country":"CO",
    "wof:name":"California",
    "wof:placetype":"locality"
},
  "geometry": {"coordinates":[-75.82250000000001,4.22306],"type":"Point"}
}