{
  "type": "Feature",
  "properties": {
    "gn:admin1_code":"2.0",
    "gn:admin2_code":"5234.0",
    "gn:asciiname":"El Boton",
    "gn:country_code":"CO",
    "gn:dem":1101,
    "gn:feature_class":"P",
    "gn:feature_code":"PPL",
    "gn:name":"El Bot\u00f3n",
    "gn:population":0,
    "gn:timezone":"America/Bogota",
    "iso:country":"CO",
    "wof:name":"El Boton",
    "wof:placetype":"locality"
},
  "geometry": {"coordinates":[-76.23684,6.91476],"type":"Point"}
}