{
  "type": "Feature",
  "properties": {
    "gn:admin1_code":"19",
    "gn:admin2_code":"50124.0",
    "gn:asciiname":"El Porvenir",
    "gn:country_code":"CO",
    "gn:dem":198,
    "gn:feature_class":"P",
    "gn:feature_code":"PPL",
    "gn:name":"El Porvenir",
    "gn:population":0,
    "gn:timezone":"America/Bogota",
    "iso:country":"CO",
    "wof:name":"El Porvenir",
    "wof:placetype":"locality"
},
  "geometry": {"coordinates":[-73.04611,4.42389],"type":"Point"}
}