{
  "type": "Feature",
  "properties": {
    "gn:admin1_code":"21",
    "gn:admin2_code":"54398.0",
    "gn:asciiname":"El Filo",
    "gn:country_code":"CO",
    "gn:dem":1330,
    "gn:feature_class":"P",
    "gn:feature_code":"PPL",
    "gn:name":"El Filo",
    "gn:population":0,
    "gn:timezone":"America/Bogota",
    "iso:country":"CO",
    "wof:name":"El Filo",
    "wof:placetype":"locality"
},
  "geometry": {"coordinates":[-73.08063,8.20756],"type":"Point"}
}