{
  "type": "Feature",
  "properties": {
    "gn:admin1_code":"31.0",
    "gn:admin2_code":"99773.0",
    "gn:asciiname":"Chololobo",
    "gn:country_code":"CO",
    "gn:dem":126,
    "gn:feature_class":"P",
    "gn:feature_code":"PPL",
    "gn:name":"Chololobo",
    "gn:population":0,
    "gn:timezone":"America/Bogota",
    "iso:country":"CO",
    "wof:name":"Chololobo",
    "wof:placetype":"locality"
},
  "geometry": {"coordinates":[-70.38722,4.28056],"type":"Point"}
}