{
  "type": "Feature",
  "properties": {
    "gn:admin1_code":"35.0",
    "gn:admin2_code":"13430.0",
    "gn:asciiname":"Punta de Cartagena",
    "gn:country_code":"CO",
    "gn:dem":18,
    "gn:feature_class":"P",
    "gn:feature_code":"PPL",
    "gn:name":"Punta de Cartagena",
    "gn:population":0,
    "gn:timezone":"America/Bogota",
    "iso:country":"CO",
    "name:und_x_variant":[
        "Caserio Punta de Cartagena",
        "Punta de Cartagena"
    ],
    "wof:name":"Punta de Cartagena",
    "wof:placetype":"locality"
},
  "geometry": {"coordinates":[-74.4752,8.8859],"type":"Point"}
}