{
  "type": "Feature",
  "properties": {
    "gn:admin1_code":"17",
    "gn:admin2_code":"44874.0",
    "gn:asciiname":"Nolasco",
    "gn:country_code":"CO",
    "gn:dem":249,
    "gn:feature_class":"P",
    "gn:feature_code":"PPL",
    "gn:name":"Nolasco",
    "gn:population":0,
    "gn:timezone":"America/Bogota",
    "iso:country":"CO",
    "name:und_x_variant":[
        "Nolasce",
        "Nolasco"
    ],
    "wof:name":"Nolasco",
    "wof:placetype":"locality"
},
  "geometry": {"coordinates":[-72.95449000000001,10.61022],"type":"Point"}
}