{
  "type": "Feature",
  "properties": {
    "gn:admin1_code":"10.0",
    "gn:admin2_code":"20238.0",
    "gn:asciiname":"Notecanses",
    "gn:country_code":"CO",
    "gn:dem":81,
    "gn:feature_class":"P",
    "gn:feature_code":"PPL",
    "gn:name":"N\u00f3tecanses",
    "gn:population":0,
    "gn:timezone":"America/Bogota",
    "iso:country":"CO",
    "wof:name":"Notecanses",
    "wof:placetype":"locality"
},
  "geometry": {"coordinates":[-73.98333000000002,10.06667],"type":"Point"}
}