{
  "type": "Feature",
  "properties": {
    "gn:admin1_code":"21.0",
    "gn:admin2_code":"54498.0",
    "gn:asciiname":"Palogrande",
    "gn:country_code":"CO",
    "gn:dem":1299,
    "gn:feature_class":"P",
    "gn:feature_code":"PPL",
    "gn:name":"Palogrande",
    "gn:population":0,
    "gn:timezone":"America/Bogota",
    "iso:country":"CO",
    "wof:name":"Palogrande",
    "wof:placetype":"locality"
},
  "geometry": {"coordinates":[-73.30934999999999,8.27877],"type":"Point"}
}