{
  "type": "Feature",
  "properties": {
    "gn:admin1_code":"11.0",
    "gn:admin2_code":"27450.0",
    "gn:asciiname":"Derrumbito",
    "gn:country_code":"CO",
    "gn:dem":23,
    "gn:feature_class":"P",
    "gn:feature_code":"PPLL",
    "gn:name":"Derrumbito",
    "gn:population":0,
    "gn:timezone":"America/Bogota",
    "iso:country":"CO",
    "wof:name":"Derrumbito",
    "wof:placetype":"locality"
},
  "geometry": {"coordinates":[-76.76878000000001,4.9756],"type":"Point"}
}