{
  "type": "Feature",
  "properties": {
    "gn:admin1_code":"8.0",
    "gn:asciiname":"Caserio Caicuche",
    "gn:country_code":"CO",
    "gn:dem":197,
    "gn:feature_class":"P",
    "gn:feature_code":"PPL",
    "gn:name":"Caser\u00edo Caicuche",
    "gn:population":0,
    "gn:timezone":"America/Bogota",
    "iso:country":"CO",
    "wof:name":"Caserio Caicuche",
    "wof:placetype":"locality"
},
  "geometry": {"coordinates":[-75.5813,0.83355],"type":"Point"}
}