{
  "type": "Feature",
  "properties": {
    "gn:admin1_code":"27.0",
    "gn:admin2_code":"70221.0",
    "gn:asciiname":"Torrente",
    "gn:country_code":"CO",
    "gn:dem":17,
    "gn:feature_class":"P",
    "gn:feature_code":"PPL",
    "gn:name":"Torrente",
    "gn:population":0,
    "gn:timezone":"America/Bogota",
    "iso:country":"CO",
    "name:arg_x_preferred":[
        "Torrente"
    ],
    "name:cat_x_preferred":[
        "Torrente"
    ],
    "name:ceb_x_preferred":[
        "Torrente"
    ],
    "name:deu_x_preferred":[
        "Torrente"
    ],
    "name:fra_x_preferred":[
        "Torrente"
    ],
    "name:glg_x_preferred":[
        "Torrente"
    ],
    "name:hun_x_preferred":[
        "Torrente"
    ],
    "name:spa_x_preferred":[
        "Torrente"
    ],
    "name:swe_x_preferred":[
        "Torrente"
    ],
    "name:und_x_variant":[
        "Hacienda Torrente"
    ],
    "wof:name":"Torrente",
    "wof:placetype":"locality"
},
  "geometry": {"coordinates":[-75.65593,9.3762],"type":"Point"}
}