{
  "type": "Feature",
  "properties": {
    "gn:admin1_code":"29",
    "gn:admin2_code":"76834.0",
    "gn:asciiname":"Amalia Lopez",
    "gn:country_code":"CO",
    "gn:dem":1474,
    "gn:feature_class":"P",
    "gn:feature_code":"PPL",
    "gn:name":"Amalia L\u00f3pez",
    "gn:population":0,
    "gn:timezone":"America/Bogota",
    "iso:country":"CO",
    "wof:name":"Amalia Lopez",
    "wof:placetype":"locality"
},
  "geometry": {"coordinates":[-75.98389,4.11111],"type":"Point"}
}