{
  "type": "Feature",
  "properties": {
    "gn:admin1_code":"28",
    "gn:admin2_code":"73001.0",
    "gn:asciiname":"La Linta",
    "gn:country_code":"CO",
    "gn:dem":1900,
    "gn:feature_class":"P",
    "gn:feature_code":"PPL",
    "gn:name":"La Linta",
    "gn:population":0,
    "gn:timezone":"America/Bogota",
    "iso:country":"CO",
    "wof:name":"La Linta",
    "wof:placetype":"locality"
},
  "geometry": {"coordinates":[-75.32417,4.3625],"type":"Point"}
}