{
  "type": "Feature",
  "properties": {
    "gn:admin1_code":"2",
    "gn:admin2_code":"5040.0",
    "gn:asciiname":"Campoalegre",
    "gn:country_code":"CO",
    "gn:dem":781,
    "gn:feature_class":"P",
    "gn:feature_code":"PPL",
    "gn:name":"Campoalegre",
    "gn:population":0,
    "gn:timezone":"America/Bogota",
    "iso:country":"CO",
    "wof:name":"Campoalegre",
    "wof:placetype":"locality"
},
  "geometry": {"coordinates":[-75.22543,7.23909],"type":"Point"}
}