{
  "type": "Feature",
  "properties": {
    "gn:admin1_code":"27.0",
    "gn:admin2_code":"70235.0",
    "gn:asciiname":"Palmital",
    "gn:cc2":"CO",
    "gn:country_code":"CO",
    "gn:dem":46,
    "gn:feature_class":"P",
    "gn:feature_code":"PPL",
    "gn:name":"Palmital",
    "gn:population":0,
    "gn:timezone":"America/Bogota",
    "iso:country":"CO",
    "name:ceb_x_preferred":[
        "Palmital"
    ],
    "name:ita_x_preferred":[
        "Palmital"
    ],
    "name:nld_x_preferred":[
        "Palmital"
    ],
    "name:nor_x_preferred":[
        "Palmital"
    ],
    "name:por_x_preferred":[
        "Palmital"
    ],
    "name:rus_x_preferred":[
        "\u041f\u0430\u043b\u043c\u0438\u0442\u0430\u043b"
    ],
    "name:swe_x_preferred":[
        "Palmital"
    ],
    "name:und_x_variant":[
        "Corregimiento Palmital",
        "Caserio Palmital"
    ],
    "name:vol_x_preferred":[
        "Palmital"
    ],
    "wof:name":"Palmital",
    "wof:placetype":"locality"
},
  "geometry": {"coordinates":[-74.99333,9.06778],"type":"Point"}
}