{
  "type": "Feature",
  "properties": {
    "gn:admin1_code":"32",
    "gn:admin2_code":"85139.0",
    "gn:asciiname":"Corocito",
    "gn:country_code":"CO",
    "gn:dem":154,
    "gn:feature_class":"P",
    "gn:feature_code":"PPL",
    "gn:name":"Corocito",
    "gn:population":0,
    "gn:timezone":"America/Bogota",
    "iso:country":"CO",
    "wof:name":"Corocito",
    "wof:placetype":"locality"
},
  "geometry": {"coordinates":[-72.22499000000001,4.46836],"type":"Point"}
}