{
  "type": "Feature",
  "properties": {
    "gn:admin1_code":"17",
    "gn:admin2_code":"44078.0",
    "gn:asciiname":"Las Pavas",
    "gn:country_code":"CO",
    "gn:dem":1085,
    "gn:feature_class":"P",
    "gn:feature_code":"PPL",
    "gn:name":"Las Pavas",
    "gn:population":0,
    "gn:timezone":"America/Bogota",
    "iso:country":"CO",
    "name:und_x_variant":[
        "Las Pavad",
        "Las Pavas"
    ],
    "wof:name":"Las Pavas",
    "wof:placetype":"locality"
},
  "geometry": {"coordinates":[-72.88434000000002,11.05995],"type":"Point"}
}