{
  "type": "Feature",
  "properties": {
    "gn:admin1_code":"21",
    "gn:admin2_code":"54720.0",
    "gn:asciiname":"Santa Celina",
    "gn:country_code":"CO",
    "gn:dem":188,
    "gn:feature_class":"P",
    "gn:feature_code":"PPL",
    "gn:name":"Santa Celina",
    "gn:population":0,
    "gn:timezone":"America/Bogota",
    "iso:country":"CO",
    "wof:name":"Santa Celina",
    "wof:placetype":"locality"
},
  "geometry": {"coordinates":[-72.925,8.51528],"type":"Point"}
}