{
  "type": "Feature",
  "properties": {
    "gn:admin1_code":"2.0",
    "gn:admin2_code":"5628.0",
    "gn:asciiname":"Genova",
    "gn:country_code":"CO",
    "gn:dem":2747,
    "gn:feature_class":"P",
    "gn:feature_code":"PPL",
    "gn:name":"G\u00e9nova",
    "gn:population":0,
    "gn:timezone":"America/Bogota",
    "iso:country":"CO",
    "wof:name":"Genova",
    "wof:placetype":"locality"
},
  "geometry": {"coordinates":[-75.76333000000002,6.81167],"type":"Point"}
}