{
  "type": "Feature",
  "properties": {
    "gn:admin1_code":"36.0",
    "gn:admin2_code":"15248.0",
    "gn:asciiname":"Guitarrillas",
    "gn:country_code":"CO",
    "gn:dem":2235,
    "gn:feature_class":"P",
    "gn:feature_code":"PPL",
    "gn:name":"Guitarrillas",
    "gn:population":0,
    "gn:timezone":"America/Bogota",
    "iso:country":"CO",
    "name:spa_x_preferred":[
        "Guitarrillas"
    ],
    "wof:name":"Guitarrillas",
    "wof:placetype":"locality"
},
  "geometry": {"coordinates":[-72.47785999999998,6.4667],"type":"Point"}
}