{
  "type": "Feature",
  "properties": {
    "gn:admin1_code":"2",
    "gn:admin2_code":"5361.0",
    "gn:asciiname":"Badillo",
    "gn:country_code":"CO",
    "gn:dem":598,
    "gn:feature_class":"P",
    "gn:feature_code":"PPL",
    "gn:name":"Badillo",
    "gn:population":0,
    "gn:timezone":"America/Bogota",
    "iso:country":"CO",
    "wof:name":"Badillo",
    "wof:placetype":"locality"
},
  "geometry": {"coordinates":[-75.96694000000002,7.35444],"type":"Point"}
}