{
  "type": "Feature",
  "properties": {
    "gn:admin1_code":"2.0",
    "gn:admin2_code":"5001.0",
    "gn:asciiname":"Los Vallados",
    "gn:country_code":"CO",
    "gn:dem":2524,
    "gn:feature_class":"P",
    "gn:feature_code":"PPL",
    "gn:name":"Los Vallados",
    "gn:population":0,
    "gn:timezone":"America/Bogota",
    "iso:country":"CO",
    "name:spa_x_preferred":[
        "Los Vallados"
    ],
    "name:und_x_variant":[
        "Allaos"
    ],
    "wof:name":"Los Vallados",
    "wof:placetype":"locality"
},
  "geometry": {"coordinates":[-75.70232,6.2618],"type":"Point"}
}