{
  "type": "Feature",
  "properties": {
    "gn:admin1_code":"20.0",
    "gn:admin2_code":"52683.0",
    "gn:asciiname":"San Bernardo",
    "gn:country_code":"CO",
    "gn:dem":1648,
    "gn:feature_class":"P",
    "gn:feature_code":"PPL",
    "gn:name":"San Bernardo",
    "gn:population":0,
    "gn:timezone":"America/Bogota",
    "iso:country":"CO",
    "wof:name":"San Bernardo",
    "wof:placetype":"locality"
},
  "geometry": {"coordinates":[-77.48265000000001,1.31194],"type":"Point"}
}