{
  "type": "Feature",
  "properties": {
    "gn:admin1_code":"29",
    "gn:admin2_code":"76834.0",
    "gn:asciiname":"La Albania",
    "gn:country_code":"CO",
    "gn:dem":2822,
    "gn:feature_class":"P",
    "gn:feature_code":"PPL",
    "gn:name":"La Albania",
    "gn:population":0,
    "gn:timezone":"America/Bogota",
    "iso:country":"CO",
    "wof:name":"La Albania",
    "wof:placetype":"locality"
},
  "geometry": {"coordinates":[-75.87389,4.02083],"type":"Point"}
}