{
  "type": "Feature",
  "properties": {
    "iso:country":"CO",
    "name:ast_x_preferred":[
        "Cucunub\u00e1"
    ],
    "name:ceb_x_preferred":[
        "Cucunub\u00e1"
    ],
    "name:dan_x_preferred":[
        "Cucunub\u00e1"
    ],
    "name:eng_x_preferred":[
        "Cucunub\u00e1"
    ],
    "name:fra_x_preferred":[
        "Cucunub\u00e1"
    ],
    "name:gla_x_preferred":[
        "Cucunub\u00e1"
    ],
    "name:ita_x_preferred":[
        "Cucunub\u00e1"
    ],
    "name:jpn_x_preferred":[
        "\u30af\u30af\u30cc\u30d0"
    ],
    "name:kat_x_preferred":[
        "\u10d9\u10e3\u10d9\u10e3\u10dc\u10e3\u10d1\u10d0"
    ],
    "name:msa_x_preferred":[
        "Cucunub\u00e1"
    ],
    "name:nan_x_preferred":[
        "Cucunub\u00e1"
    ],
    "name:nld_x_preferred":[
        "Cucunub\u00e1"
    ],
    "name:sco_x_preferred":[
        "Cucunub\u00e1"
    ],
    "name:spa_x_preferred":[
        "Cucunub\u00e1"
    ],
    "name:swe_x_preferred":[
        "Cucunub\u00e1"
    ],
    "name:tgl_x_preferred":[
        "Cucunub\u00e1"
    ],
    "name:vie_x_preferred":[
        "Cucunub\u00e1"
    ],
    "name:war_x_preferred":[
        "Cucunub\u00e1"
    ],
    "name:zho_x_preferred":[
        "\u5eab\u5eab\u52aa\u5df4"
    ],
    "qs:gn_country":"CO",
    "qs:gn_fcode":"PPL",
    "qs:gn_pop":1699,
    "qs:name":"Cucunub\u00e1",
    "qs:name_adm0":"Colombia",
    "qs:name_adm1":"Cundinamarca",
    "qs:photos":121,
    "qs:photos_1k":25,
    "qs:photos_9k":1,
    "qs:photos_9r":3,
    "qs:photos_all":121,
    "qs:photos_sr":3,
    "qs:placetype":"Town",
    "qs:pop_sr":"3",
    "qs:woe_adm0":23424787,
    "wof:name":"Cucunub\u00e1",
    "wof:placetype":"locality",
    "wof:population":1699
},
  "geometry": {"coordinates":[-73.76609999999999,5.24958],"type":"Point"}
}