{
  "type": "Feature",
  "properties": {
    "gn:gn_country":"CO",
    "gn:gn_fcode":"PPLX",
    "gn:gn_pop":0,
    "iso:country":"CO",
    "name:spa_x_preferred":[
        "San Miguel"
    ],
    "name:spa_x_variant":[
        "S. Miguel",
        "S Miguel"
    ],
    "name:unk_x_variant":[
        "San Miguel"
    ],
    "qs:gn_adm0_cc":"CO",
    "qs:gn_fcode":"PPLX",
    "qs:gn_local":3688465,
    "qs:gn_namadm1":"26",
    "qs:gn_name":"San Miguel",
    "qs:local_max":2559,
    "qs:local_sum":3515,
    "qs:localhoods":7,
    "qs:name":"San Miguel",
    "qs:name_adm0":"Colombia",
    "qs:name_adm1":"Santander",
    "qs:name_adm2":"Bucaramanga",
    "qs:name_local":"Bucaramanga",
    "qs:photo_max":1,
    "qs:photo_sum":1,
    "qs:placetype":"Suburb",
    "qs:quad_count":1,
    "qs:woe_adm0":23424787,
    "qs:woe_adm1":2345071,
    "qs:woe_adm2":26797407,
    "qs:woe_lau":0,
    "qs:woe_local":368152,
    "qs:woe_ver":"7.10.0",
    "qs_pg:aaroncc":"CO",
    "qs_pg:gn_country":"CO",
    "qs_pg:gn_fcode":"PPLX",
    "qs_pg:gn_pop":0,
    "qs_pg:name":"San Miguel",
    "qs_pg:name_adm0":"Colombia",
    "qs_pg:name_adm1":"Santander",
    "qs_pg:photos":34,
    "qs_pg:photos_1k":7,
    "qs_pg:photos_9k":1,
    "qs_pg:photos_9r":2,
    "qs_pg:photos_all":34,
    "qs_pg:photos_sr":2,
    "qs_pg:pop_sr":0,
    "qs_pg:qs_pg_placetype":"neighbourhood",
    "qs_pg:qs_pg_placetype_gp":"Suburb",
    "qs_pg:woe_adm0":23424787,
    "wof:lang":[
        "spa"
    ],
    "wof:name":"San Miguel",
    "wof:placetype":"neighbourhood"
},
  "geometry": {"coordinates":[-73.09478799999999,7.076362],"type":"Point"}
}