{
  "type": "Feature",
  "properties": {
    "gn:admin1_code":"36",
    "gn:admin2_code":"15531.0",
    "gn:asciiname":"Naranjos",
    "gn:country_code":"CO",
    "gn:dem":1234,
    "gn:feature_class":"P",
    "gn:feature_code":"PPL",
    "gn:name":"Naranjos",
    "gn:population":0,
    "gn:timezone":"America/Bogota",
    "iso:country":"CO",
    "name:por_x_preferred":[
        "Naranjos"
    ],
    "name:rus_x_preferred":[
        "\u041d\u0430\u0440\u0430\u043d\u0445\u043e\u0441"
    ],
    "name:spa_x_preferred":[
        "Naranjos"
    ],
    "wof:name":"Naranjos",
    "wof:placetype":"locality"
},
  "geometry": {"coordinates":[-73.97972,5.64583],"type":"Point"}
}