{
  "type": "Feature",
  "properties": {
    "gn:admin1_code":"26.0",
    "gn:admin2_code":"68615.0",
    "gn:asciiname":"El Cerro",
    "gn:country_code":"CO",
    "gn:dem":834,
    "gn:feature_class":"P",
    "gn:feature_code":"PPL",
    "gn:name":"El Cerro",
    "gn:population":0,
    "gn:timezone":"America/Bogota",
    "iso:country":"CO",
    "name:spa_x_preferred":[
        "El Cerro"
    ],
    "wof:name":"El Cerro",
    "wof:placetype":"locality"
},
  "geometry": {"coordinates":[-73.23796,7.28396],"type":"Point"}
}