{
  "type": "Feature",
  "properties": {
    "gn:admin1_code":"35",
    "gn:admin2_code":"13657.0",
    "gn:asciiname":"Jobo",
    "gn:cc2":"CO",
    "gn:country_code":"CO",
    "gn:dem":247,
    "gn:feature_class":"P",
    "gn:feature_code":"PPL",
    "gn:name":"Jobo",
    "gn:population":0,
    "gn:timezone":"America/Bogota",
    "iso:country":"CO",
    "name:und_x_variant":[
        "Hacienda Lobo",
        "Hacienda Jobo",
        "Jobo"
    ],
    "wof:name":"Jobo",
    "wof:placetype":"locality"
},
  "geometry": {"coordinates":[-75.13333,9.98333],"type":"Point"}
}