{
  "type": "Feature",
  "properties": {
    "gn:admin1_code":"10",
    "gn:admin2_code":"20011.0",
    "gn:asciiname":"El Salto",
    "gn:country_code":"CO",
    "gn:dem":48,
    "gn:feature_class":"P",
    "gn:feature_code":"PPL",
    "gn:name":"El Salto",
    "gn:population":0,
    "gn:timezone":"America/Bogota",
    "iso:country":"CO",
    "name:ceb_x_preferred":[
        "El Salto"
    ],
    "name:deu_x_preferred":[
        "El Salto"
    ],
    "name:epo_x_preferred":[
        "El Salto"
    ],
    "name:ita_x_preferred":[
        "El Salto"
    ],
    "name:spa_x_preferred":[
        "El Salto"
    ],
    "name:srp_x_preferred":[
        "\u0415\u043b \u0421\u0430\u043b\u0442\u043e"
    ],
    "name:swe_x_preferred":[
        "El Salto"
    ],
    "name:vie_x_preferred":[
        "El Salto"
    ],
    "wof:name":"El Salto",
    "wof:placetype":"locality"
},
  "geometry": {"coordinates":[-73.71666999999999,8.13333],"type":"Point"}
}