{
  "type": "Feature",
  "properties": {
    "gn:admin1_code":"33.0",
    "gn:admin2_code":"25320.0",
    "gn:asciiname":"Las Aguilas",
    "gn:country_code":"CO",
    "gn:dem":697,
    "gn:feature_class":"P",
    "gn:feature_code":"PPL",
    "gn:name":"Las Aguilas",
    "gn:population":0,
    "gn:timezone":"America/Bogota",
    "iso:country":"CO",
    "name:spa_x_preferred":[
        "Las Aguilas"
    ],
    "wof:name":"Las Aguilas",
    "wof:placetype":"locality"
},
  "geometry": {"coordinates":[-74.54144000000002,5.17133],"type":"Point"}
}