{
  "type": "Feature",
  "properties": {
    "iso:country":"CO",
    "name:deu_x_preferred":[
        "Manrique"
    ],
    "name:fra_x_preferred":[
        "Manrique"
    ],
    "name:rus_x_preferred":[
        "\u041c\u0430\u043d\u0440\u0438\u043a\u0435"
    ],
    "name:spa_x_preferred":[
        "Manrique"
    ],
    "qs:gn_country":"CO",
    "qs:gn_fcode":"PPLX",
    "qs:gn_pop":0,
    "qs:name":"Manrique",
    "qs:name_adm0":"Colombia",
    "qs:name_adm1":"Antioquia",
    "qs:photos":27,
    "qs:photos_1k":5,
    "qs:photos_9k":1,
    "qs:photos_9r":2,
    "qs:photos_all":27,
    "qs:photos_sr":2,
    "qs:placetype":"Suburb",
    "qs:pop_sr":"0",
    "qs:woe_adm0":23424787,
    "wd:wordcount":60,
    "wof:name":"Manrique",
    "wof:placetype":"neighbourhood"
},
  "geometry": {"coordinates":[-75.56732,6.26713],"type":"Point"}
}