{
  "type": "Feature",
  "properties": {
    "gn:admin1_code":"36",
    "gn:admin2_code":"15763.0",
    "gn:asciiname":"El Manzano",
    "gn:country_code":"CO",
    "gn:dem":2534,
    "gn:feature_class":"P",
    "gn:feature_code":"PPL",
    "gn:name":"El Manzano",
    "gn:population":0,
    "gn:timezone":"America/Bogota",
    "iso:country":"CO",
    "name:und_x_variant":[
        "Hacienda El Manzano",
        "El Manzano"
    ],
    "wof:name":"El Manzano",
    "wof:placetype":"locality"
},
  "geometry": {"coordinates":[-73.17402,5.75268],"type":"Point"}
}