{
  "type": "Feature",
  "properties": {
    "gn:admin1_code":"9",
    "gn:admin2_code":"19130.0",
    "gn:asciiname":"Arrayanal",
    "gn:country_code":"CO",
    "gn:dem":1742,
    "gn:feature_class":"P",
    "gn:feature_code":"PPL",
    "gn:name":"Arrayanal",
    "gn:population":0,
    "gn:timezone":"America/Bogota",
    "iso:country":"CO",
    "wof:name":"Arrayanal",
    "wof:placetype":"locality"
},
  "geometry": {"coordinates":[-76.81714000000002,2.68819],"type":"Point"}
}