{
  "type": "Feature",
  "properties": {
    "gn:admin1_code":"33",
    "gn:admin2_code":"25740.0",
    "gn:asciiname":"Eternit",
    "gn:country_code":"CO",
    "gn:dem":2567,
    "gn:feature_class":"P",
    "gn:feature_code":"PPL",
    "gn:name":"Eternit",
    "gn:population":0,
    "gn:timezone":"America/Bogota",
    "iso:country":"CO",
    "name:ces_x_preferred":[
        "Eternit"
    ],
    "name:est_x_preferred":[
        "Eterniit"
    ],
    "name:hun_x_preferred":[
        "Palafed\u00e9s"
    ],
    "name:ind_x_preferred":[
        "Eternit"
    ],
    "name:ita_x_preferred":[
        "Eternit"
    ],
    "name:lit_x_preferred":[
        "\u0160iferis"
    ],
    "name:nld_x_preferred":[
        "Asbestcement"
    ],
    "name:nno_x_preferred":[
        "Eternit"
    ],
    "name:nor_x_preferred":[
        "Eternit"
    ],
    "name:pol_x_preferred":[
        "Eternit"
    ],
    "name:ron_x_preferred":[
        "Azbociment"
    ],
    "name:rus_x_preferred":[
        "\u0410\u0441\u0431\u0435\u0441\u0442\u043e\u0446\u0435\u043c\u0435\u043d\u0442\u043d\u044b\u0439 \u0448\u0438\u0444\u0435\u0440"
    ],
    "name:slk_x_preferred":[
        "Eternit"
    ],
    "name:spa_x_preferred":[
        "Eternit"
    ],
    "name:swe_x_preferred":[
        "Asbestcement"
    ],
    "wof:name":"Eternit",
    "wof:placetype":"locality"
},
  "geometry": {"coordinates":[-74.25,4.53333],"type":"Point"}
}