{
  "type": "Feature",
  "properties": {
    "gn:admin1_code":"26.0",
    "gn:admin2_code":"68547.0",
    "gn:asciiname":"Pozonegro",
    "gn:country_code":"CO",
    "gn:dem":1845,
    "gn:feature_class":"P",
    "gn:feature_code":"PPL",
    "gn:name":"Pozonegro",
    "gn:population":0,
    "gn:timezone":"America/Bogota",
    "iso:country":"CO",
    "name:spa_x_preferred":[
        "Pozonegro"
    ],
    "wof:name":"Pozonegro",
    "wof:placetype":"locality"
},
  "geometry": {"coordinates":[-73.02324,7.00649],"type":"Point"}
}