{
  "type": "Feature",
  "properties": {
    "gn:admin1_code":"16.0",
    "gn:admin2_code":"41206.0",
    "gn:asciiname":"Pie de Pena",
    "gn:country_code":"CO",
    "gn:dem":1079,
    "gn:feature_class":"P",
    "gn:feature_code":"PPLL",
    "gn:name":"Pie de Pe\u00f1a",
    "gn:population":0,
    "gn:timezone":"America/Bogota",
    "iso:country":"CO",
    "name:spa_x_preferred":[
        "Pie de Pe\u00f1a"
    ],
    "wof:name":"Pie de Pena",
    "wof:placetype":"locality"
},
  "geometry": {"coordinates":[-74.76756,3.52483],"type":"Point"}
}