{
  "type": "Feature",
  "properties": {
    "iso:country":"CO",
    "name:arg_x_preferred":[
        "Mosquera"
    ],
    "name:ast_x_preferred":[
        "Mosquera"
    ],
    "name:avk_x_preferred":[
        "Mosquera"
    ],
    "name:ceb_x_preferred":[
        "Mosquera"
    ],
    "name:deu_x_preferred":[
        "Mosquera"
    ],
    "name:eng_x_preferred":[
        "Mosquera"
    ],
    "name:fas_x_preferred":[
        "\u0645\u0648\u0633\u06a9\u0631\u0627"
    ],
    "name:fra_x_preferred":[
        "Mosquera"
    ],
    "name:gle_x_preferred":[
        "Mosquera"
    ],
    "name:ita_x_preferred":[
        "Mosquera"
    ],
    "name:kat_x_preferred":[
        "\u10db\u10dd\u10e1\u10d9\u10d4\u10e0\u10d0"
    ],
    "name:msa_x_preferred":[
        "Mosquera"
    ],
    "name:nan_x_preferred":[
        "Mosquera"
    ],
    "name:nld_x_preferred":[
        "Mosquera"
    ],
    "name:pol_x_preferred":[
        "Mosquera"
    ],
    "name:por_x_preferred":[
        "Mosquera"
    ],
    "name:rus_x_preferred":[
        "\u041c\u043e\u0441\u043a\u0435\u0440\u0430"
    ],
    "name:spa_x_preferred":[
        "Mosquera"
    ],
    "name:swe_x_preferred":[
        "Mosquera"
    ],
    "name:tgl_x_preferred":[
        "Mosquera"
    ],
    "name:ukr_x_preferred":[
        "\u041c\u043e\u0441\u043a\u0435\u0440\u0430"
    ],
    "name:vie_x_preferred":[
        "Mosquera"
    ],
    "name:war_x_preferred":[
        "Mosquera"
    ],
    "name:zho_x_preferred":[
        "\u83ab\u65af\u514b\u62c9"
    ],
    "name:zho_x_variant":[
        "\u4f0a\u57fa\u62c9"
    ],
    "qs:gn_country":"CO",
    "qs:gn_fcode":"PPL",
    "qs:gn_pop":3471,
    "qs:name":"Mosquera",
    "qs:name_adm0":"Colombia",
    "qs:name_adm1":"Narino",
    "qs:photos":0,
    "qs:photos_1k":0,
    "qs:photos_9k":0,
    "qs:photos_9r":0,
    "qs:photos_all":0,
    "qs:photos_sr":0,
    "qs:placetype":"Town",
    "qs:pop_sr":"4",
    "qs:woe_adm0":23424787,
    "wd:wordcount":289,
    "wof:name":"Mosquera",
    "wof:placetype":"locality",
    "wof:population":3471
},
  "geometry": {"coordinates":[-78.4511,2.50861],"type":"Point"}
}