{
  "type": "Feature",
  "properties": {
    "gn:admin1_code":"12",
    "gn:admin2_code":"23815.0",
    "gn:asciiname":"Colombia",
    "gn:country_code":"CO",
    "gn:dem":45,
    "gn:feature_class":"P",
    "gn:feature_code":"PPL",
    "gn:name":"Colombia",
    "gn:population":0,
    "gn:timezone":"America/Bogota",
    "iso:country":"CO",
    "wof:name":"Colombia",
    "wof:placetype":"locality"
},
  "geometry": {"coordinates":[-75.57805999999999,9.23471],"type":"Point"}
}