{
  "type": "Feature",
  "properties": {
    "gn:admin1_code":"15.0",
    "gn:admin2_code":"94886.0",
    "gn:asciiname":"Pueblo Viejo",
    "gn:country_code":"CO",
    "gn:dem":97,
    "gn:feature_class":"P",
    "gn:feature_code":"PPL",
    "gn:name":"Pueblo Viejo",
    "gn:population":0,
    "gn:timezone":"America/Bogota",
    "iso:country":"CO",
    "name:ceb_x_preferred":[
        "Pueblo Viejo"
    ],
    "name:deu_x_preferred":[
        "Pueblo Viejo"
    ],
    "name:fra_x_preferred":[
        "Pueblo Viejo"
    ],
    "name:nds_x_preferred":[
        "Pueblo Viejo"
    ],
    "name:sco_x_preferred":[
        "Pueblo Viejo"
    ],
    "name:spa_x_preferred":[
        "Pueblo Viejo"
    ],
    "name:swe_x_preferred":[
        "Pueblo Viejo"
    ],
    "name:vie_x_preferred":[
        "Pueblo Viejo"
    ],
    "wof:name":"Pueblo Viejo",
    "wof:placetype":"locality"
},
  "geometry": {"coordinates":[-67.43805999999999,3.56806],"type":"Point"}
}