{
  "type": "Feature",
  "properties": {
    "gn:admin1_code":"35",
    "gn:admin2_code":"13430.0",
    "gn:asciiname":"Guayacan",
    "gn:country_code":"CO",
    "gn:dem":18,
    "gn:feature_class":"P",
    "gn:feature_code":"PPL",
    "gn:name":"Guayac\u00e1n",
    "gn:population":0,
    "gn:timezone":"America/Bogota",
    "iso:country":"CO",
    "name:und_x_variant":[
        "Hacienda Guayac\u00e1n",
        "Guayac\u00e1n"
    ],
    "wof:name":"Guayacan",
    "wof:placetype":"locality"
},
  "geometry": {"coordinates":[-74.75464000000002,9.13253],"type":"Point"}
}