{
  "type": "Feature",
  "properties": {
    "gn:admin1_code":"9.0",
    "gn:admin2_code":"19137.0",
    "gn:asciiname":"Plan de Zuniga",
    "gn:country_code":"CO",
    "gn:dem":2026,
    "gn:feature_class":"P",
    "gn:feature_code":"PPL",
    "gn:name":"Plan de Z\u00fa\u00f1iga",
    "gn:population":0,
    "gn:timezone":"America/Bogota",
    "iso:country":"CO",
    "wof:name":"Plan de Zuniga",
    "wof:placetype":"locality"
},
  "geometry": {"coordinates":[-76.40512,2.85389],"type":"Point"}
}