{
  "type": "Feature",
  "properties": {
    "iso:country":"CO",
    "name:ceb_x_preferred":[
        "Fontib\u00f3n"
    ],
    "name:deu_x_preferred":[
        "Fontib\u00f3n"
    ],
    "name:eng_x_preferred":[
        "Fontib\u00f3n"
    ],
    "name:epo_x_preferred":[
        "Fontib\u00f3n"
    ],
    "name:fas_x_preferred":[
        "\u0641\u0648\u0646\u062a\u06cc\u0628\u0648\u0646"
    ],
    "name:fra_x_preferred":[
        "Fontib\u00f3n"
    ],
    "name:gla_x_preferred":[
        "Fontib\u00f3n"
    ],
    "name:glg_x_preferred":[
        "Fontib\u00f3n"
    ],
    "name:ita_x_preferred":[
        "Fontib\u00f3n"
    ],
    "name:msa_x_preferred":[
        "Fontibon"
    ],
    "name:nld_x_preferred":[
        "Fontib\u00f3n"
    ],
    "name:nob_x_preferred":[
        "Fontib\u00f3n"
    ],
    "name:nor_x_preferred":[
        "Fontib\u00f3n"
    ],
    "name:por_x_preferred":[
        "Fontibon"
    ],
    "name:spa_x_preferred":[
        "Fontib\u00f3n"
    ],
    "name:swe_x_preferred":[
        "Fontib\u00f3n"
    ],
    "qs:gn_country":"CO",
    "qs:gn_fcode":"PPL",
    "qs:gn_pop":0,
    "qs:name":"Fontib\u00f3n",
    "qs:name_adm0":"Colombia",
    "qs:name_adm1":"Distrito Especial",
    "qs:photos":982,
    "qs:photos_1k":199,
    "qs:photos_9k":4,
    "qs:photos_9r":6,
    "qs:photos_all":982,
    "qs:photos_sr":10,
    "qs:placetype":"Town",
    "qs:pop_sr":"7",
    "qs:woe_adm0":23424787,
    "wd:wordcount":302,
    "wof:name":"Fontib\u00f3n",
    "wof:placetype":"locality"
},
  "geometry": {"coordinates":[-74.14431999999999,4.67815],"type":"Point"}
}