{
  "type": "Feature",
  "properties": {
    "gn:admin1_code":"2.0",
    "gn:admin2_code":"5088.0",
    "gn:asciiname":"La Garcia",
    "gn:country_code":"CO",
    "gn:dem":2516,
    "gn:feature_class":"P",
    "gn:feature_code":"PPL",
    "gn:name":"La Garc\u00eda",
    "gn:population":0,
    "gn:timezone":"America/Bogota",
    "iso:country":"CO",
    "name:spa_x_preferred":[
        "La Garc\u00eda"
    ],
    "wof:name":"La Garcia",
    "wof:placetype":"locality"
},
  "geometry": {"coordinates":[-75.62931999999998,6.35739],"type":"Point"}
}