{
  "type": "Feature",
  "properties": {
    "gn:admin1_code":"16.0",
    "gn:admin2_code":"41770.0",
    "gn:asciiname":"Montebello",
    "gn:country_code":"CO",
    "gn:dem":1784,
    "gn:feature_class":"P",
    "gn:feature_code":"PPL",
    "gn:name":"Montebello",
    "gn:population":0,
    "gn:timezone":"America/Bogota",
    "iso:country":"CO",
    "name:spa_x_preferred":[
        "Montebello"
    ],
    "wof:name":"Montebello",
    "wof:placetype":"locality"
},
  "geometry": {"coordinates":[-75.74292,1.87649],"type":"Point"}
}