{
  "type": "Feature",
  "properties": {
    "gn:admin1_code":"37.0",
    "gn:admin2_code":"17614.0",
    "gn:asciiname":"Cabarga",
    "gn:country_code":"CO",
    "gn:dem":2091,
    "gn:feature_class":"P",
    "gn:feature_code":"PPL",
    "gn:name":"Cabarga",
    "gn:population":0,
    "gn:timezone":"America/Bogota",
    "iso:country":"CO",
    "wof:name":"Cabarga",
    "wof:placetype":"locality"
},
  "geometry": {"coordinates":[-75.74579,5.47318],"type":"Point"}
}