{
  "type": "Feature",
  "properties": {
    "gn:admin1_code":"3.0",
    "gn:admin2_code":"81794.0",
    "gn:asciiname":"Caserio Las Malvinas",
    "gn:country_code":"CO",
    "gn:dem":376,
    "gn:feature_class":"P",
    "gn:feature_code":"PPL",
    "gn:name":"Caser\u00edo Las Malvinas",
    "gn:population":0,
    "gn:timezone":"America/Bogota",
    "iso:country":"CO",
    "wof:name":"Caserio Las Malvinas",
    "wof:placetype":"locality"
},
  "geometry": {"coordinates":[-71.81028000000001,6.64667],"type":"Point"}
}