{
  "type": "Feature",
  "properties": {
    "gn:admin1_code":"9.0",
    "gn:admin2_code":"19548.0",
    "gn:asciiname":"Tunia",
    "gn:country_code":"CO",
    "gn:dem":1706,
    "gn:feature_class":"P",
    "gn:feature_code":"PPL",
    "gn:name":"Tunia",
    "gn:population":0,
    "gn:timezone":"America/Bogota",
    "iso:country":"CO",
    "wof:name":"Tunia",
    "wof:placetype":"locality"
},
  "geometry": {"coordinates":[-76.53543000000001,2.68038],"type":"Point"}
}