{
  "type": "Feature",
  "properties": {
    "gn:admin1_code":"29",
    "gn:admin2_code":"76364.0",
    "gn:asciiname":"La Chorrera",
    "gn:country_code":"CO",
    "gn:dem":966,
    "gn:feature_class":"P",
    "gn:feature_code":"PPL",
    "gn:name":"La Chorrera",
    "gn:population":0,
    "gn:timezone":"America/Bogota",
    "iso:country":"CO",
    "wof:name":"La Chorrera",
    "wof:placetype":"locality"
},
  "geometry": {"coordinates":[-76.49386,3.21551],"type":"Point"}
}