{
  "type": "Feature",
  "properties": {
    "gn:admin1_code":"20",
    "gn:admin2_code":"52835.0",
    "gn:asciiname":"Guachal",
    "gn:country_code":"CO",
    "gn:dem":14,
    "gn:feature_class":"P",
    "gn:feature_code":"PPL",
    "gn:name":"Guachal",
    "gn:population":0,
    "gn:timezone":"America/Bogota",
    "iso:country":"CO",
    "name:und_x_variant":[
        "Guachali",
        "Guachal"
    ],
    "wof:name":"Guachal",
    "wof:placetype":"locality"
},
  "geometry": {"coordinates":[-78.76931,1.56561],"type":"Point"}
}