{
  "type": "Feature",
  "properties": {
    "gn:admin1_code":"26",
    "gn:admin2_code":"68500.0",
    "gn:asciiname":"La Primavera",
    "gn:country_code":"CO",
    "gn:dem":1404,
    "gn:feature_class":"P",
    "gn:feature_code":"PPL",
    "gn:name":"La Primavera",
    "gn:population":0,
    "gn:timezone":"America/Bogota",
    "iso:country":"CO",
    "wof:name":"La Primavera",
    "wof:placetype":"locality"
},
  "geometry": {"coordinates":[-73.32174999999999,6.19921],"type":"Point"}
}