{
  "type": "Feature",
  "properties": {
    "gn:country":"CO",
    "gn:fcode":"PPL",
    "gn:pop":657,
    "iso:country":"CO",
    "name:eng_x_preferred":[
        "Palmas Socorro"
    ],
    "name:fra_x_preferred":[
        "Palmas del Socorro"
    ],
    "name:ita_x_preferred":[
        "Palmas del Socorro"
    ],
    "name:kat_x_preferred":[
        "\u10de\u10d0\u10da\u10db\u10d0\u10e1-\u10e1\u10dd\u10d9\u10dd\u10e0\u10dd"
    ],
    "name:msa_x_preferred":[
        "Palmas Socorro"
    ],
    "name:nan_x_preferred":[
        "Palmas del Socorro"
    ],
    "name:nld_x_preferred":[
        "Palmas del Socorro"
    ],
    "name:spa_x_preferred":[
        "Palmas del Socorro"
    ],
    "name:swe_x_preferred":[
        "Palmas del Socorro"
    ],
    "name:tgl_x_preferred":[
        "Palmas Socorro"
    ],
    "name:unk_x_variant":[
        "Palmas"
    ],
    "name:vie_x_preferred":[
        "Palmas del Socorro"
    ],
    "name:war_x_preferred":[
        "Palmas Socorro"
    ],
    "name:zho_x_preferred":[
        "\u5e15\u723e\u99ac\u65af\u7d22\u79d1\u7f85"
    ],
    "qs:name":"Palmas del Socorro",
    "qs:photos_9r":0,
    "qs:photos_sr":0,
    "qs:pop_sr":"2",
    "wof:name":"Palmas del Socorro",
    "wof:placetype":"locality",
    "wof:population":657
},
  "geometry": {"coordinates":[-73.28824,6.40756],"type":"Point"}
}