{
  "type": "Feature",
  "properties": {
    "gn:country":"CO",
    "gn:fcode":"PPL",
    "gn:population":657,
    "iso:country":"CO",
    "name:ast_x_preferred":[
        "Palmas del Socorro"
    ],
    "name:avk_x_preferred":[
        "Palmas del Socorro"
    ],
    "name:ceb_x_preferred":[
        "Palmas del Socorro"
    ],
    "name:eng_x_preferred":[
        "Palmas Socorro"
    ],
    "name:fas_x_preferred":[
        "\u067e\u0627\u0644\u0645\u0627\u0633 \u062f\u0644 \u0633\u0648\u06a9\u0648\u0631\u0648"
    ],
    "name:fra_x_preferred":[
        "Palmas del Socorro"
    ],
    "name:gle_x_preferred":[
        "Palmas Socorro"
    ],
    "name:ita_x_preferred":[
        "Palmas del Socorro"
    ],
    "name:kat_x_preferred":[
        "\u10de\u10d0\u10da\u10db\u10d0\u10e1-\u10e1\u10dd\u10d9\u10dd\u10e0\u10dd"
    ],
    "name:msa_x_preferred":[
        "Palmas Socorro"
    ],
    "name:nan_x_preferred":[
        "Palmas del Socorro"
    ],
    "name:nld_x_preferred":[
        "Palmas del Socorro"
    ],
    "name:pol_x_preferred":[
        "Palmas del Socorro"
    ],
    "name:rus_x_preferred":[
        "\u041f\u0430\u043b\u044c\u043c\u0430\u0441-\u0434\u0435\u043b\u044c-\u0421\u043e\u043a\u043e\u0440\u0440\u043e"
    ],
    "name:spa_x_preferred":[
        "Palmas del Socorro"
    ],
    "name:swe_x_preferred":[
        "Palmas del Socorro"
    ],
    "name:tgl_x_preferred":[
        "Palmas Socorro"
    ],
    "name:und_x_variant":[
        "Palmas"
    ],
    "name:vie_x_preferred":[
        "Palmas del Socorro"
    ],
    "name:war_x_preferred":[
        "Palmas Socorro"
    ],
    "name:zho_x_preferred":[
        "\u5e15\u723e\u99ac\u65af\u7d22\u79d1\u7f85"
    ],
    "qs:name":"Palmas del Socorro",
    "qs:photos_9r":0,
    "qs:photos_sr":0,
    "qs:pop_sr":"2",
    "wof:name":"Palmas del Socorro",
    "wof:placetype":"locality",
    "wof:population":657
},
  "geometry": {"coordinates":[-73.28824,6.40756],"type":"Point"}
}