{
  "type": "Feature",
  "properties": {
    "gn:admin1_code":"21",
    "gn:admin2_code":"54003.0",
    "gn:asciiname":"La Hoyada",
    "gn:country_code":"CO",
    "gn:dem":1805,
    "gn:feature_class":"P",
    "gn:feature_code":"PPL",
    "gn:name":"La Hoyada",
    "gn:population":0,
    "gn:timezone":"America/Bogota",
    "iso:country":"CO",
    "name:ceb_x_preferred":[
        "La Hoyada"
    ],
    "name:spa_x_preferred":[
        "La Hoyada"
    ],
    "name:swe_x_preferred":[
        "La Hoyada"
    ],
    "name:urd_x_preferred":[
        "\u0644\u0627 \u06c1\u0648\u06cc\u0627\u0688\u0627"
    ],
    "wof:name":"La Hoyada",
    "wof:placetype":"locality"
},
  "geometry": {"coordinates":[-73.11471999999998,8.17583],"type":"Point"}
}