{
  "type": "Feature",
  "properties": {
    "gn:admin1_code":"27.0",
    "gn:admin2_code":"70678.0",
    "gn:asciiname":"Pasifueres",
    "gn:country_code":"CO",
    "gn:dem":16,
    "gn:feature_class":"P",
    "gn:feature_code":"PPL",
    "gn:name":"Pasifueres",
    "gn:population":0,
    "gn:timezone":"America/Bogota",
    "iso:country":"CO",
    "name:und_x_variant":[
        "Pasifueras",
        "Pasifueres"
    ],
    "wof:name":"Pasifueres",
    "wof:placetype":"locality"
},
  "geometry": {"coordinates":[-74.90594,8.59265],"type":"Point"}
}