{
  "type": "Feature",
  "properties": {
    "gn:admin1_code":"28",
    "gn:admin2_code":"73563.0",
    "gn:asciiname":"La Bodega",
    "gn:country_code":"CO",
    "gn:dem":301,
    "gn:feature_class":"P",
    "gn:feature_code":"PPLL",
    "gn:name":"La Bodega",
    "gn:population":0,
    "gn:timezone":"America/Bogota",
    "iso:country":"CO",
    "name:spa_x_preferred":[
        "La Bodega"
    ],
    "wof:name":"La Bodega",
    "wof:placetype":"locality"
},
  "geometry": {"coordinates":[-74.96194,3.75278],"type":"Point"}
}