{
  "type": "Feature",
  "properties": {
    "gn:admin1_code":"26.0",
    "gn:admin2_code":"68689.0",
    "gn:asciiname":"Buenavista",
    "gn:country_code":"CO",
    "gn:dem":159,
    "gn:feature_class":"P",
    "gn:feature_code":"PPLL",
    "gn:name":"Buenavista",
    "gn:population":0,
    "gn:timezone":"America/Bogota",
    "iso:country":"CO",
    "wof:name":"Buenavista",
    "wof:placetype":"locality"
},
  "geometry": {"coordinates":[-73.74314,6.85296],"type":"Point"}
}