{
  "type": "Feature",
  "properties": {
    "gn:admin1_code":"26.0",
    "gn:admin2_code":"68689.0",
    "gn:asciiname":"El Peligro",
    "gn:country_code":"CO",
    "gn:dem":556,
    "gn:feature_class":"P",
    "gn:feature_code":"PPLL",
    "gn:name":"El Peligro",
    "gn:population":0,
    "gn:timezone":"America/Bogota",
    "iso:country":"CO",
    "wof:name":"El Peligro",
    "wof:placetype":"locality"
},
  "geometry": {"coordinates":[-73.50978000000001,6.90564],"type":"Point"}
}