{
  "type": "Feature",
  "properties": {
    "gn:admin1_code":"2",
    "gn:admin2_code":"5361.0",
    "gn:asciiname":"El Oso",
    "gn:country_code":"CO",
    "gn:dem":2122,
    "gn:feature_class":"P",
    "gn:feature_code":"PPL",
    "gn:name":"El Oso",
    "gn:population":0,
    "gn:timezone":"America/Bogota",
    "iso:country":"CO",
    "wof:name":"El Oso",
    "wof:placetype":"locality"
},
  "geometry": {"coordinates":[-75.74183000000002,7.29858],"type":"Point"}
}