{
  "type": "Feature",
  "properties": {
    "gn:admin1_code":"26",
    "gn:asciiname":"El Rosal",
    "gn:country_code":"CO",
    "gn:dem":2681,
    "gn:feature_class":"P",
    "gn:feature_code":"PPL",
    "gn:name":"El Rosal",
    "gn:population":0,
    "gn:timezone":"America/Bogota",
    "iso:country":"CO",
    "name:ceb_x_preferred":[
        "El Rosal"
    ],
    "name:deu_x_preferred":[
        "El Rosal"
    ],
    "name:fra_x_preferred":[
        "El Rosal"
    ],
    "name:sco_x_preferred":[
        "El Rosal"
    ],
    "name:spa_x_preferred":[
        "El Rosal"
    ],
    "name:srp_x_preferred":[
        "\u0415\u043b \u0420\u043e\u0441\u0430\u043b"
    ],
    "name:swe_x_preferred":[
        "El Rosal"
    ],
    "name:vie_x_preferred":[
        "El Rosal"
    ],
    "wof:name":"El Rosal",
    "wof:placetype":"locality"
},
  "geometry": {"coordinates":[-73.25,5.86667],"type":"Point"}
}