{
  "type": "Feature",
  "properties": {
    "gn:admin1_code":"26",
    "gn:asciiname":"El Rosal",
    "gn:country_code":"CO",
    "gn:dem":2681,
    "gn:feature_class":"P",
    "gn:feature_code":"PPL",
    "gn:name":"El Rosal",
    "gn:population":0,
    "gn:timezone":"America/Bogota",
    "iso:country":"CO",
    "wof:name":"El Rosal",
    "wof:placetype":"locality"
},
  "geometry": {"coordinates":[-73.25,5.86667],"type":"Point"}
}