{
  "type": "Feature",
  "properties": {
    "gn:admin1_code":"28",
    "gn:admin2_code":"73001.0",
    "gn:asciiname":"La Selva",
    "gn:country_code":"CO",
    "gn:dem":2580,
    "gn:feature_class":"P",
    "gn:feature_code":"PPL",
    "gn:name":"La Selva",
    "gn:population":0,
    "gn:timezone":"America/Bogota",
    "iso:country":"CO",
    "name:ceb_x_preferred":[
        "La Selva"
    ],
    "name:deu_x_preferred":[
        "La Selva"
    ],
    "name:srp_x_preferred":[
        "La Selva"
    ],
    "name:swe_x_preferred":[
        "La Selva"
    ],
    "wof:name":"La Selva",
    "wof:placetype":"locality"
},
  "geometry": {"coordinates":[-75.32056,4.49389],"type":"Point"}
}