{
  "type": "Feature",
  "properties": {
    "gn:admin1_code":"29",
    "gn:admin2_code":"76109.0",
    "gn:asciiname":"Mayorquin",
    "gn:country_code":"CO",
    "gn:dem":11,
    "gn:feature_class":"P",
    "gn:feature_code":"PPL",
    "gn:name":"Mayorqu\u00edn",
    "gn:population":0,
    "gn:timezone":"America/Bogota",
    "iso:country":"CO",
    "wof:name":"Mayorquin",
    "wof:placetype":"locality"
},
  "geometry": {"coordinates":[-77.19412,3.60241],"type":"Point"}
}