{
  "type": "Feature",
  "properties": {
    "gn:admin1_code":"20.0",
    "gn:admin2_code":"52079.0",
    "gn:asciiname":"San Lorenzo",
    "gn:country_code":"CO",
    "gn:dem":85,
    "gn:feature_class":"P",
    "gn:feature_code":"PPL",
    "gn:name":"San Lorenzo",
    "gn:population":0,
    "gn:timezone":"America/Bogota",
    "iso:country":"CO",
    "wof:name":"San Lorenzo",
    "wof:placetype":"locality"
},
  "geometry": {"coordinates":[-78.06667,1.68333],"type":"Point"}
}