{
  "type": "Feature",
  "properties": {
    "gn:admin1_code":"20",
    "gn:admin2_code":"52405.0",
    "gn:asciiname":"Palmar",
    "gn:country_code":"CO",
    "gn:dem":936,
    "gn:feature_class":"P",
    "gn:feature_code":"PPL",
    "gn:name":"Palmar",
    "gn:population":0,
    "gn:timezone":"America/Bogota",
    "iso:country":"CO",
    "name:ceb_x_preferred":[
        "Palmar"
    ],
    "name:deu_x_preferred":[
        "Palmar"
    ],
    "name:ita_x_preferred":[
        "Palmar"
    ],
    "name:nld_x_preferred":[
        "Palmar"
    ],
    "name:spa_x_preferred":[
        "Palmar"
    ],
    "name:srp_x_preferred":[
        "\u041f\u0430\u043b\u043c\u0430\u0440"
    ],
    "name:swe_x_preferred":[
        "Palmar"
    ],
    "wof:name":"Palmar",
    "wof:placetype":"locality"
},
  "geometry": {"coordinates":[-77.30611,1.88139],"type":"Point"}
}