{
  "type": "Feature",
  "properties": {
    "gn:admin1_code":"20.0",
    "gn:admin2_code":"52260.0",
    "gn:asciiname":"Potrerillo",
    "gn:country_code":"CO",
    "gn:dem":1881,
    "gn:feature_class":"P",
    "gn:feature_code":"PPL",
    "gn:name":"Potrerillo",
    "gn:population":0,
    "gn:timezone":"America/Bogota",
    "iso:country":"CO",
    "name:spa_x_preferred":[
        "Potrerillo"
    ],
    "wof:name":"Potrerillo",
    "wof:placetype":"locality"
},
  "geometry": {"coordinates":[-77.41667,1.43333],"type":"Point"}
}