{
  "type": "Feature",
  "properties": {
    "gn:admin1_code":"26.0",
    "gn:admin2_code":"68176.0",
    "gn:asciiname":"Tierra Amarilla",
    "gn:country_code":"CO",
    "gn:dem":1396,
    "gn:feature_class":"P",
    "gn:feature_code":"PPL",
    "gn:name":"Tierra Amarilla",
    "gn:population":0,
    "gn:timezone":"America/Bogota",
    "iso:country":"CO",
    "name:ara_x_preferred":[
        "\u062a\u064a\u064a\u0631\u0627 \u0623\u0645\u0627\u0631\u064a\u0644\u0627"
    ],
    "name:ben_x_preferred":[
        "\u09a4\u09bf\u09df\u09c7\u09b0\u09be \u0986\u09ae\u09be\u09b0\u09bf\u09b2\u09cd\u09b2\u09be"
    ],
    "name:deu_x_preferred":[
        "Tierra Amarilla"
    ],
    "name:ell_x_preferred":[
        "\u03a4\u03b9\u03ad\u03c1\u03b1 \u0391\u03bc\u03b1\u03c1\u03af\u03b3\u03b9\u03b1"
    ],
    "name:heb_x_preferred":[
        "\u05d8\u05d9\u05d9\u05e8\u05d4 \u05d0\u05de\u05e8\u05d9\u05dc\u05d9\u05d4"
    ],
    "name:hin_x_preferred":[
        "\u091f\u093f\u092f\u0947\u0930\u093e \u0905\u092e\u093e\u0930\u093f\u0932\u093e"
    ],
    "name:hun_x_preferred":[
        "Tierra Amarilla"
    ],
    "name:ind_x_preferred":[
        "Tierra Amarilla"
    ],
    "name:jpn_x_preferred":[
        "\u30c6\u30a3\u30a8\u30e9\u30fb\u30a2\u30de\u30ea\u30e9"
    ],
    "name:swe_x_preferred":[
        "Tierra Amarilla"
    ],
    "name:tur_x_preferred":[
        "Tierra Amarilla"
    ],
    "name:ukr_x_preferred":[
        "\u0422\u044c\u0454\u0440\u0440\u0430-\u0410\u043c\u0430\u0440\u0456\u043b\u044c\u044f"
    ],
    "name:urd_x_preferred":[
        "\u0679\u06cc\u0631\u0627 \u0627\u06cc\u0645\u0631\u0627\u0631\u06cc\u0644\u0627"
    ],
    "name:vie_x_preferred":[
        "Tierra Amarilla"
    ],
    "wof:name":"Tierra Amarilla",
    "wof:placetype":"locality"
},
  "geometry": {"coordinates":[-73.35005,6.39608],"type":"Point"}
}