{
  "type": "Feature",
  "properties": {
    "gn:admin1_code":"37.0",
    "gn:admin2_code":"17662.0",
    "gn:asciiname":"Tobia",
    "gn:country_code":"CO",
    "gn:dem":849,
    "gn:feature_class":"P",
    "gn:feature_code":"PPL",
    "gn:name":"Tobia",
    "gn:population":0,
    "gn:timezone":"America/Bogota",
    "iso:country":"CO",
    "name:spa_x_preferred":[
        "Tobia"
    ],
    "wof:name":"Tobia",
    "wof:placetype":"locality"
},
  "geometry": {"coordinates":[-74.93468,5.40624],"type":"Point"}
}