{
  "type": "Feature",
  "properties": {
    "gn:admin1_code":"38",
    "gn:admin2_code":"47245.0",
    "gn:asciiname":"Pueblo Nuevo",
    "gn:country_code":"CO",
    "gn:dem":28,
    "gn:feature_class":"P",
    "gn:feature_code":"PPL",
    "gn:name":"Pueblo Nuevo",
    "gn:population":0,
    "gn:timezone":"America/Bogota",
    "iso:country":"CO",
    "wof:name":"Pueblo Nuevo",
    "wof:placetype":"locality"
},
  "geometry": {"coordinates":[-73.98999999999999,9.17861],"type":"Point"}
}