{
  "type": "Feature",
  "properties": {
    "gn:admin1_code":"29.0",
    "gn:admin2_code":"76100.0",
    "gn:asciiname":"Guacos",
    "gn:country_code":"CO",
    "gn:dem":1562,
    "gn:feature_class":"P",
    "gn:feature_code":"PPL",
    "gn:name":"Guacos",
    "gn:population":0,
    "gn:timezone":"America/Bogota",
    "iso:country":"CO",
    "wof:name":"Guacos",
    "wof:placetype":"locality"
},
  "geometry": {"coordinates":[-76.26015,4.34952],"type":"Point"}
}