{
  "type": "Feature",
  "properties": {
    "gn:admin1_code":"38",
    "gn:admin2_code":"47660.0",
    "gn:asciiname":"La Sirena",
    "gn:country_code":"CO",
    "gn:dem":193,
    "gn:feature_class":"P",
    "gn:feature_code":"PPL",
    "gn:name":"La Sirena",
    "gn:population":0,
    "gn:timezone":"America/Bogota",
    "iso:country":"CO",
    "name:und_x_variant":[
        "Hacienda La Sirena",
        "La Sirena"
    ],
    "wof:name":"La Sirena",
    "wof:placetype":"locality"
},
  "geometry": {"coordinates":[-74.28775,9.99766],"type":"Point"}
}