{
  "type": "Feature",
  "properties": {
    "gn:admin1_code":"36.0",
    "gn:admin2_code":"15272.0",
    "gn:asciiname":"Suescun",
    "gn:country_code":"CO",
    "gn:dem":2757,
    "gn:feature_class":"P",
    "gn:feature_code":"PPL",
    "gn:name":"Suesc\u00fan",
    "gn:population":0,
    "gn:timezone":"America/Bogota",
    "iso:country":"CO",
    "wof:name":"Suescun",
    "wof:placetype":"locality"
},
  "geometry": {"coordinates":[-72.98333000000002,5.71667],"type":"Point"}
}