{
  "type": "Feature",
  "properties": {
    "gn:admin1_code":"38",
    "gn:admin2_code":"47555.0",
    "gn:asciiname":"Los Yucales",
    "gn:country_code":"CO",
    "gn:dem":77,
    "gn:feature_class":"P",
    "gn:feature_code":"PPL",
    "gn:name":"Los Yucales",
    "gn:population":0,
    "gn:timezone":"America/Bogota",
    "iso:country":"CO",
    "wof:name":"Los Yucales",
    "wof:placetype":"locality"
},
  "geometry": {"coordinates":[-74.62532,9.70288],"type":"Point"}
}