{
  "type": "Feature",
  "properties": {
    "gn:admin1_code":"29",
    "gn:admin2_code":"76400.0",
    "gn:asciiname":"El Lindero",
    "gn:country_code":"CO",
    "gn:dem":909,
    "gn:feature_class":"P",
    "gn:feature_code":"PPL",
    "gn:name":"El Lindero",
    "gn:population":0,
    "gn:timezone":"America/Bogota",
    "iso:country":"CO",
    "name:spa_x_preferred":[
        "El Lindero"
    ],
    "name:und_x_variant":[
        "Lindero",
        "El Lindero"
    ],
    "wof:name":"El Lindero",
    "wof:placetype":"locality"
},
  "geometry": {"coordinates":[-76.06461,4.5092],"type":"Point"}
}