{
  "type": "Feature",
  "properties": {
    "gn:admin1_code":"38",
    "gn:admin2_code":"47058.0",
    "gn:asciiname":"El Indio",
    "gn:cc2":"CO",
    "gn:country_code":"CO",
    "gn:dem":69,
    "gn:feature_class":"P",
    "gn:feature_code":"PPL",
    "gn:name":"El Indio",
    "gn:population":0,
    "gn:timezone":"America/Bogota",
    "iso:country":"CO",
    "name:ceb_x_preferred":[
        "El Indio"
    ],
    "name:ita_x_preferred":[
        "El Indio"
    ],
    "name:srp_x_preferred":[
        "\u0415\u043b \u0418\u043d\u0434\u0438\u043e"
    ],
    "name:swe_x_preferred":[
        "El Indio"
    ],
    "name:und_x_variant":[
        "Hacienda El Indio",
        "El Indio"
    ],
    "wof:name":"El Indio",
    "wof:placetype":"locality"
},
  "geometry": {"coordinates":[-74.04028000000002,9.965],"type":"Point"}
}