{
  "type": "Feature",
  "properties": {
    "gn:admin1_code":"17",
    "gn:admin2_code":"44650.0",
    "gn:asciiname":"Quinto Patio",
    "gn:country_code":"CO",
    "gn:dem":985,
    "gn:feature_class":"P",
    "gn:feature_code":"PPL",
    "gn:name":"Quinto Patio",
    "gn:population":0,
    "gn:timezone":"America/Bogota",
    "iso:country":"CO",
    "wof:name":"Quinto Patio",
    "wof:placetype":"locality"
},
  "geometry": {"coordinates":[-72.8175,10.62111],"type":"Point"}
}