{
  "type": "Feature",
  "properties": {
    "gn:admin1_code":"12.0",
    "gn:admin2_code":"23001.0",
    "gn:asciiname":"Nueva Lucia",
    "gn:country_code":"CO",
    "gn:dem":43,
    "gn:feature_class":"P",
    "gn:feature_code":"PPL",
    "gn:name":"Nueva Luc\u00eda",
    "gn:population":0,
    "gn:timezone":"America/Bogota",
    "iso:country":"CO",
    "name:und_x_variant":[
        "Bongo Mocho",
        "Nueva Luc\u00eda"
    ],
    "wof:name":"Nueva Lucia",
    "wof:placetype":"locality"
},
  "geometry": {"coordinates":[-75.82589,8.41685],"type":"Point"}
}