{
  "type": "Feature",
  "properties": {
    "gn:admin1_code":"26",
    "gn:admin2_code":"68271.0",
    "gn:asciiname":"Normandia",
    "gn:country_code":"CO",
    "gn:dem":1548,
    "gn:feature_class":"P",
    "gn:feature_code":"PPL",
    "gn:name":"Normand\u00eda",
    "gn:population":0,
    "gn:timezone":"America/Bogota",
    "iso:country":"CO",
    "name:por_x_preferred":[
        "Normandia"
    ],
    "wof:name":"Normandia",
    "wof:placetype":"locality"
},
  "geometry": {"coordinates":[-73.98472,5.77361],"type":"Point"}
}