{
  "type": "Feature",
  "properties": {
    "gn:admin1_code":"10",
    "gn:admin2_code":"20175.0",
    "gn:asciiname":"El Trebol",
    "gn:country_code":"CO",
    "gn:dem":60,
    "gn:feature_class":"P",
    "gn:feature_code":"PPL",
    "gn:name":"El Tr\u00e9bol",
    "gn:population":0,
    "gn:timezone":"America/Bogota",
    "iso:country":"CO",
    "wof:name":"El Trebol",
    "wof:placetype":"locality"
},
  "geometry": {"coordinates":[-73.85186999999998,9.28161],"type":"Point"}
}