{
  "type": "Feature",
  "properties": {
    "gn:admin1_code":"33.0",
    "gn:admin2_code":"25592.0",
    "gn:asciiname":"San Isidre",
    "gn:country_code":"CO",
    "gn:dem":1308,
    "gn:feature_class":"P",
    "gn:feature_code":"PPL",
    "gn:name":"San Isidre",
    "gn:population":0,
    "gn:timezone":"America/Bogota",
    "iso:country":"CO",
    "name:spa_x_preferred":[
        "San Isidre"
    ],
    "wof:name":"San Isidre",
    "wof:placetype":"locality"
},
  "geometry": {"coordinates":[-74.51348,5.09238],"type":"Point"}
}