{
  "type": "Feature",
  "properties": {
    "gn:gn_country":"CO",
    "gn:gn_fcode":"PPLX",
    "gn:gn_pop":0,
    "iso:country":"CO",
    "name:spa_x_preferred":[
        "Tesca"
    ],
    "name:spa_x_variant":[
        "Barrio Tesca"
    ],
    "name:unk_x_variant":[
        "Barrio Tesca",
        "Tesca"
    ],
    "qs_pg:aaroncc":"CO",
    "qs_pg:gn_country":"CO",
    "qs_pg:gn_fcode":"PPLX",
    "qs_pg:gn_pop":0,
    "qs_pg:name":"Tesca",
    "qs_pg:name_adm0":"Colombia",
    "qs_pg:name_adm1":"Bolivar",
    "qs_pg:photos":85,
    "qs_pg:photos_1k":17,
    "qs_pg:photos_9k":1,
    "qs_pg:photos_9r":3,
    "qs_pg:photos_all":85,
    "qs_pg:photos_sr":3,
    "qs_pg:pop_sr":0,
    "qs_pg:qs_pg_placetype":"neighbourhood",
    "qs_pg:qs_pg_placetype_gp":"Suburb",
    "qs_pg:woe_adm0":23424787,
    "woe:adm0_id":23424787,
    "woe:name_adm0":"Colombia",
    "woe:name_adm1":"Bolivar",
    "woe:placetype":"Suburb",
    "wof:name":"Tesca",
    "wof:placetype":"neighbourhood"
},
  "geometry": {"coordinates":[-75.51667,10.41667],"type":"Point"}
}