{
  "type": "Feature",
  "properties": {
    "gn:admin1_code":"19.0",
    "gn:admin2_code":"50001.0",
    "gn:asciiname":"Rancho Grande",
    "gn:country_code":"CO",
    "gn:dem":370,
    "gn:feature_class":"P",
    "gn:feature_code":"PPL",
    "gn:name":"Rancho Grande",
    "gn:population":0,
    "gn:timezone":"America/Bogota",
    "iso:country":"CO",
    "name:spa_x_preferred":[
        "Rancho Grande"
    ],
    "wof:name":"Rancho Grande",
    "wof:placetype":"locality"
},
  "geometry": {"coordinates":[-73.56673000000001,4.10865],"type":"Point"}
}