{
  "type": "Feature",
  "properties": {
    "gn:admin1_code":"36",
    "gn:admin2_code":"15531.0",
    "gn:asciiname":"El Arrayan",
    "gn:country_code":"CO",
    "gn:dem":1176,
    "gn:feature_class":"P",
    "gn:feature_code":"PPL",
    "gn:name":"El Array\u00e1n",
    "gn:population":0,
    "gn:timezone":"America/Bogota",
    "iso:country":"CO",
    "wof:name":"El Arrayan",
    "wof:placetype":"locality"
},
  "geometry": {"coordinates":[-74.00583,5.63667],"type":"Point"}
}