{
  "type": "Feature",
  "properties": {
    "gn:admin1_code":"8.0",
    "gn:admin2_code":"18753.0",
    "gn:asciiname":"Inspeccion de Policia de Rovira",
    "gn:country_code":"CO",
    "gn:dem":1337,
    "gn:feature_class":"P",
    "gn:feature_code":"PPL",
    "gn:name":"Inspecci\u00f3n de Polic\u00eda de Rovira",
    "gn:population":0,
    "gn:timezone":"America/Bogota",
    "iso:country":"CO",
    "wof:name":"Inspeccion de Policia de Rovira",
    "wof:placetype":"locality"
},
  "geometry": {"coordinates":[-74.91674,2.72103],"type":"Point"}
}