{
  "type": "Feature",
  "properties": {
    "gn:admin1_code":"12.0",
    "gn:admin2_code":"23189.0",
    "gn:asciiname":"Salguero",
    "gn:country_code":"CO",
    "gn:dem":56,
    "gn:feature_class":"P",
    "gn:feature_code":"PPL",
    "gn:name":"Salguero",
    "gn:population":0,
    "gn:timezone":"America/Bogota",
    "iso:country":"CO",
    "wof:name":"Salguero",
    "wof:placetype":"locality"
},
  "geometry": {"coordinates":[-75.54314000000002,8.81683],"type":"Point"}
}