{
  "type": "Feature",
  "properties": {
    "gn:admin1_code":"38.0",
    "gn:admin2_code":"47460.0",
    "gn:asciiname":"Polonorte",
    "gn:country_code":"CO",
    "gn:dem":112,
    "gn:feature_class":"P",
    "gn:feature_code":"PPL",
    "gn:name":"Polonorte",
    "gn:population":0,
    "gn:timezone":"America/Bogota",
    "iso:country":"CO",
    "wof:name":"Polonorte",
    "wof:placetype":"locality"
},
  "geometry": {"coordinates":[-74.31551999999998,9.70139],"type":"Point"}
}