{
  "type": "Feature",
  "properties": {
    "gn:admin1_code":"24",
    "gn:admin2_code":"66045.0",
    "gn:asciiname":"La Popa",
    "gn:country_code":"CO",
    "gn:dem":1459,
    "gn:feature_class":"P",
    "gn:feature_code":"PPL",
    "gn:name":"La Popa",
    "gn:population":0,
    "gn:timezone":"America/Bogota",
    "iso:country":"CO",
    "wof:name":"La Popa",
    "wof:placetype":"locality"
},
  "geometry": {"coordinates":[-75.94722,5.12944],"type":"Point"}
}