{
  "type": "Feature",
  "properties": {
    "gn:admin1_code":"11.0",
    "gn:admin2_code":"27050.0",
    "gn:asciiname":"Purre",
    "gn:cc2":"CO",
    "gn:country_code":"CO",
    "gn:dem":92,
    "gn:feature_class":"P",
    "gn:feature_code":"PPL",
    "gn:name":"Purr\u00e9",
    "gn:population":0,
    "gn:timezone":"America/Bogota",
    "iso:country":"CO",
    "name:und_x_variant":[
        "San Jos\u00e9 de Purr\u00e9",
        "Puerr\u00e9",
        "Purr\u00e9"
    ],
    "wof:name":"Purre",
    "wof:placetype":"locality"
},
  "geometry": {"coordinates":[-76.53333000000001,5.63333],"type":"Point"}
}