{
  "type": "Feature",
  "properties": {
    "gn:admin1_code":"20",
    "gn:admin2_code":"52786.0",
    "gn:asciiname":"Cachiquiro",
    "gn:country_code":"CO",
    "gn:dem":1315,
    "gn:feature_class":"P",
    "gn:feature_code":"PPL",
    "gn:name":"Cachiquiro",
    "gn:population":0,
    "gn:timezone":"America/Bogota",
    "iso:country":"CO",
    "wof:name":"Cachiquiro",
    "wof:placetype":"locality"
},
  "geometry": {"coordinates":[-77.30471999999997,1.60056],"type":"Point"}
}