{
  "type": "Feature",
  "properties": {
    "gn:admin1_code":"32",
    "gn:admin2_code":"85139.0",
    "gn:asciiname":"El Limonal",
    "gn:country_code":"CO",
    "gn:dem":142,
    "gn:feature_class":"P",
    "gn:feature_code":"PPL",
    "gn:name":"El Limonal",
    "gn:population":0,
    "gn:timezone":"America/Bogota",
    "iso:country":"CO",
    "wof:name":"El Limonal",
    "wof:placetype":"locality"
},
  "geometry": {"coordinates":[-72.06667,4.40254],"type":"Point"}
}