{
  "type": "Feature",
  "properties": {
    "gn:admin1_code":"9.0",
    "gn:admin2_code":"19824.0",
    "gn:asciiname":"Vereda Las Trochas",
    "gn:country_code":"CO",
    "gn:dem":3380,
    "gn:feature_class":"P",
    "gn:feature_code":"PPLL",
    "gn:name":"Vereda Las Trochas",
    "gn:population":0,
    "gn:timezone":"America/Bogota",
    "iso:country":"CO",
    "name:spa_x_preferred":[
        "Vereda Las Trochas"
    ],
    "wof:name":"Vereda Las Trochas",
    "wof:placetype":"locality"
},
  "geometry": {"coordinates":[-76.34368000000001,2.50491],"type":"Point"}
}