{
  "type": "Feature",
  "properties": {
    "gn:admin1_code":"12.0",
    "gn:admin2_code":"23570.0",
    "gn:asciiname":"Puerto Santo",
    "gn:country_code":"CO",
    "gn:dem":33,
    "gn:feature_class":"P",
    "gn:feature_code":"PPL",
    "gn:name":"Puerto Santo",
    "gn:population":0,
    "gn:timezone":"America/Bogota",
    "iso:country":"CO",
    "wof:name":"Puerto Santo",
    "wof:placetype":"locality"
},
  "geometry": {"coordinates":[-75.31667,8.41266],"type":"Point"}
}