{
  "type": "Feature",
  "properties": {
    "gn:admin1_code":"12.0",
    "gn:admin2_code":"23001.0",
    "gn:asciiname":"Medrano",
    "gn:country_code":"CO",
    "gn:dem":27,
    "gn:feature_class":"P",
    "gn:feature_code":"PPL",
    "gn:name":"Medrano",
    "gn:population":0,
    "gn:timezone":"America/Bogota",
    "iso:country":"CO",
    "name:ceb_x_preferred":[
        "Medrano"
    ],
    "name:deu_x_preferred":[
        "Medrano"
    ],
    "name:fra_x_preferred":[
        "Medrano"
    ],
    "name:ita_x_preferred":[
        "Medrano"
    ],
    "name:por_x_preferred":[
        "Medrano"
    ],
    "name:spa_x_preferred":[
        "Medrano"
    ],
    "name:swe_x_preferred":[
        "Medrano"
    ],
    "wof:name":"Medrano",
    "wof:placetype":"locality"
},
  "geometry": {"coordinates":[-75.98333000000002,8.46667],"type":"Point"}
}