{
  "type": "Feature",
  "properties": {
    "gn:admin1_code":"19.0",
    "gn:admin2_code":"50606.0",
    "gn:asciiname":"Vega Grande",
    "gn:country_code":"CO",
    "gn:dem":340,
    "gn:feature_class":"P",
    "gn:feature_code":"PPL",
    "gn:name":"Vega Grande",
    "gn:population":0,
    "gn:timezone":"America/Bogota",
    "iso:country":"CO",
    "wof:name":"Vega Grande",
    "wof:placetype":"locality"
},
  "geometry": {"coordinates":[-73.47671,4.18508],"type":"Point"}
}