{
  "type": "Feature",
  "properties": {
    "gn:admin1_code":"33.0",
    "gn:admin2_code":"25377.0",
    "gn:asciiname":"Los Corales",
    "gn:country_code":"CO",
    "gn:dem":3162,
    "gn:feature_class":"P",
    "gn:feature_code":"PPL",
    "gn:name":"Los Corales",
    "gn:population":0,
    "gn:timezone":"America/Bogota",
    "iso:country":"CO",
    "wof:name":"Los Corales",
    "wof:placetype":"locality"
},
  "geometry": {"coordinates":[-73.90099000000002,4.71686],"type":"Point"}
}