{
  "type": "Feature",
  "properties": {
    "gn:admin1_code":"28.0",
    "gn:admin2_code":"73001.0",
    "gn:asciiname":"Tapias",
    "gn:country_code":"CO",
    "gn:dem":2019,
    "gn:feature_class":"P",
    "gn:feature_code":"PPL",
    "gn:name":"Tapias",
    "gn:population":0,
    "gn:timezone":"America/Bogota",
    "iso:country":"CO",
    "wof:name":"Tapias",
    "wof:placetype":"locality"
},
  "geometry": {"coordinates":[-75.35833000000002,4.45583],"type":"Point"}
}