{
  "type": "Feature",
  "properties": {
    "gn:admin1_code":"29",
    "gn:admin2_code":"76892.0",
    "gn:asciiname":"Bermejal",
    "gn:country_code":"CO",
    "gn:dem":957,
    "gn:feature_class":"P",
    "gn:feature_code":"PPL",
    "gn:name":"Bermejal",
    "gn:population":0,
    "gn:timezone":"America/Bogota",
    "iso:country":"CO",
    "wof:name":"Bermejal",
    "wof:placetype":"locality"
},
  "geometry": {"coordinates":[-76.47334000000002,3.61935],"type":"Point"}
}