{
  "type": "Feature",
  "properties": {
    "gn:admin1_code":"26",
    "gn:admin2_code":"68001.0",
    "gn:asciiname":"Tiendepalo",
    "gn:country_code":"CO",
    "gn:dem":653,
    "gn:feature_class":"P",
    "gn:feature_code":"PPL",
    "gn:name":"Tiendepalo",
    "gn:population":0,
    "gn:timezone":"America/Bogota",
    "iso:country":"CO",
    "wof:name":"Tiendepalo",
    "wof:placetype":"locality"
},
  "geometry": {"coordinates":[-73.15805999999998,7.12358],"type":"Point"}
}