{
  "type": "Feature",
  "properties": {
    "gn:admin1_code":"12.0",
    "gn:admin2_code":"23678.0",
    "gn:asciiname":"La Chalina",
    "gn:country_code":"CO",
    "gn:dem":30,
    "gn:feature_class":"P",
    "gn:feature_code":"PPLL",
    "gn:name":"La Chalina",
    "gn:population":0,
    "gn:timezone":"America/Bogota",
    "iso:country":"CO",
    "wof:name":"La Chalina",
    "wof:placetype":"locality"
},
  "geometry": {"coordinates":[-75.70483,8.74759],"type":"Point"}
}