{
  "type": "Feature",
  "properties": {
    "gn:admin1_code":"32.0",
    "gn:admin2_code":"85325.0",
    "gn:asciiname":"Caserio El Garrancho",
    "gn:country_code":"CO",
    "gn:dem":181,
    "gn:feature_class":"P",
    "gn:feature_code":"PPL",
    "gn:name":"Caser\u00edo El Garrancho",
    "gn:population":0,
    "gn:timezone":"America/Bogota",
    "iso:country":"CO",
    "wof:name":"Caserio El Garrancho",
    "wof:placetype":"locality"
},
  "geometry": {"coordinates":[-71.81415,5.45765],"type":"Point"}
}