{
  "type": "Feature",
  "properties": {
    "gn:admin1_code":"8.0",
    "gn:admin2_code":"18247.0",
    "gn:asciiname":"Inspeccion de Policia Manguare",
    "gn:country_code":"CO",
    "gn:dem":277,
    "gn:feature_class":"P",
    "gn:feature_code":"PPL",
    "gn:name":"Inspecci\u00f3n de Polic\u00eda Manguare",
    "gn:population":0,
    "gn:timezone":"America/Bogota",
    "iso:country":"CO",
    "wof:name":"Inspeccion de Policia Manguare",
    "wof:placetype":"locality"
},
  "geometry": {"coordinates":[-75.16332,1.64615],"type":"Point"}
}