{
  "type": "Feature",
  "properties": {
    "gn:admin1_code":"17",
    "gn:admin2_code":"44847.0",
    "gn:asciiname":"Jorojoromahana",
    "gn:country_code":"CO",
    "gn:dem":42,
    "gn:feature_class":"P",
    "gn:feature_code":"PPL",
    "gn:name":"Joroj\u00f3romahana",
    "gn:population":0,
    "gn:timezone":"America/Bogota",
    "iso:country":"CO",
    "wof:name":"Jorojoromahana",
    "wof:placetype":"locality"
},
  "geometry": {"coordinates":[-71.86425,12.08404],"type":"Point"}
}