{
  "type": "Feature",
  "properties": {
    "gn:admin1_code":"20.0",
    "gn:admin2_code":"52260.0",
    "gn:asciiname":"Rio Bobo",
    "gn:country_code":"CO",
    "gn:dem":2305,
    "gn:feature_class":"P",
    "gn:feature_code":"PPL",
    "gn:name":"R\u00edo Bobo",
    "gn:population":0,
    "gn:timezone":"America/Bogota",
    "iso:country":"CO",
    "wof:name":"Rio Bobo",
    "wof:placetype":"locality"
},
  "geometry": {"coordinates":[-77.40000000000001,1.36667],"type":"Point"}
}