{
  "type": "Feature",
  "properties": {
    "gn:admin1_code":"33.0",
    "gn:admin2_code":"25320.0",
    "gn:asciiname":"Potosi",
    "gn:country_code":"CO",
    "gn:dem":1675,
    "gn:feature_class":"P",
    "gn:feature_code":"PPL",
    "gn:name":"Potos\u00ed",
    "gn:population":0,
    "gn:timezone":"America/Bogota",
    "iso:country":"CO",
    "wof:name":"Potosi",
    "wof:placetype":"locality"
},
  "geometry": {"coordinates":[-74.56667,5.03333],"type":"Point"}
}