{
  "type": "Feature",
  "properties": {
    "gn:admin1_code":"2.0",
    "gn:admin2_code":"5686.0",
    "gn:asciiname":"La Poa",
    "gn:country_code":"CO",
    "gn:dem":2646,
    "gn:feature_class":"P",
    "gn:feature_code":"PPL",
    "gn:name":"La Poa",
    "gn:population":0,
    "gn:timezone":"America/Bogota",
    "iso:country":"CO",
    "wof:name":"La Poa",
    "wof:placetype":"locality"
},
  "geometry": {"coordinates":[-75.5013,6.70724],"type":"Point"}
}