{
  "type": "Feature",
  "properties": {
    "gn:admin1_code":"3.0",
    "gn:admin2_code":"81591.0",
    "gn:asciiname":"Rosa Blanca",
    "gn:country_code":"CO",
    "gn:dem":128,
    "gn:feature_class":"P",
    "gn:feature_code":"PPL",
    "gn:name":"Rosa Blanca",
    "gn:population":0,
    "gn:timezone":"America/Bogota",
    "iso:country":"CO",
    "name:spa_x_preferred":[
        "Rosa Blanca"
    ],
    "name:und_x_variant":[
        "Fundo Rosa Blanca"
    ],
    "wof:name":"Rosa Blanca",
    "wof:placetype":"locality"
},
  "geometry": {"coordinates":[-70.98474,6.51276],"type":"Point"}
}