{
  "type": "Feature",
  "properties": {
    "iso:country":"CO",
    "name:ast_x_preferred":[
        "Sahag\u00fan"
    ],
    "name:ceb_x_preferred":[
        "Sahag\u00fan"
    ],
    "name:deu_x_preferred":[
        "Sahag\u00fan"
    ],
    "name:eng_x_preferred":[
        "Sahag\u00fan"
    ],
    "name:fas_x_preferred":[
        "\u0633\u0627\u06af\u0648\u0646"
    ],
    "name:fra_x_preferred":[
        "Sahag\u00fan"
    ],
    "name:ita_x_preferred":[
        "Sahag\u00fan"
    ],
    "name:jpn_x_preferred":[
        "\u30b5\u30a2\u30b0\u30f3"
    ],
    "name:kat_x_preferred":[
        "\u10e1\u10d0\u10d2\u10e3\u10dc\u10d8"
    ],
    "name:msa_x_preferred":[
        "Sahag\u00fan"
    ],
    "name:nan_x_preferred":[
        "Sahag\u00fan"
    ],
    "name:nld_x_preferred":[
        "Sahag\u00fan"
    ],
    "name:por_x_preferred":[
        "Sahag\u00fan"
    ],
    "name:spa_x_preferred":[
        "Sahag\u00fan"
    ],
    "name:swe_x_preferred":[
        "Sahag\u00fan"
    ],
    "name:tgl_x_preferred":[
        "Sahag\u00fan"
    ],
    "name:urd_x_preferred":[
        "\u0633\u06c1\u0627\u06af\u0646\u060c \u06a9\u0648\u0631\u0688\u0648\u0628\u0627"
    ],
    "name:urd_x_variant":[
        "\u0633\u06c1\u0627\u06af\u0646"
    ],
    "name:vie_x_preferred":[
        "Sahag\u00fan"
    ],
    "name:war_x_preferred":[
        "Sahag\u00fan"
    ],
    "name:zho_x_preferred":[
        "\u85a9\u54c8\u8ca2"
    ],
    "qs:gn_country":"CO",
    "qs:gn_fcode":"PPL",
    "qs:gn_pop":59188,
    "qs:name":"Sahag\u00fan",
    "qs:name_adm0":"Colombia",
    "qs:name_adm1":"Cordoba",
    "qs:photos":0,
    "qs:photos_1k":0,
    "qs:photos_9k":1,
    "qs:photos_9r":2,
    "qs:photos_all":36,
    "qs:photos_sr":0,
    "qs:placetype":"Town",
    "qs:pop_sr":"8",
    "qs:woe_adm0":23424787,
    "wd:wordcount":47,
    "wof:name":"Sahag\u00fan",
    "wof:placetype":"locality",
    "wof:population":59188
},
  "geometry": {"coordinates":[-75.44275,8.94616],"type":"Point"}
}