{
  "type": "Feature",
  "properties": {
    "gn:admin1_code":"2",
    "gn:admin2_code":"5044.0",
    "gn:asciiname":"Gueintar",
    "gn:country_code":"CO",
    "gn:dem":2723,
    "gn:feature_class":"P",
    "gn:feature_code":"PPL",
    "gn:name":"G\u00fcintar",
    "gn:population":0,
    "gn:timezone":"America/Bogota",
    "iso:country":"CO",
    "wof:name":"Gueintar",
    "wof:placetype":"locality"
},
  "geometry": {"coordinates":[-75.95,6.35],"type":"Point"}
}