{
  "type": "Feature",
  "properties": {
    "gn:admin1_code":"26.0",
    "gn:admin2_code":"68745.0",
    "gn:asciiname":"La Maria",
    "gn:country_code":"CO",
    "gn:dem":123,
    "gn:feature_class":"P",
    "gn:feature_code":"PPLL",
    "gn:name":"La Mar\u00eda",
    "gn:population":0,
    "gn:timezone":"America/Bogota",
    "iso:country":"CO",
    "wof:name":"La Maria",
    "wof:placetype":"locality"
},
  "geometry": {"coordinates":[-73.74639999999999,6.7482],"type":"Point"}
}