{
  "type": "Feature",
  "properties": {
    "gn:admin1_code":"33.0",
    "gn:admin2_code":"25599.0",
    "gn:asciiname":"Cachimbulo",
    "gn:country_code":"CO",
    "gn:dem":403,
    "gn:feature_class":"P",
    "gn:feature_code":"PPL",
    "gn:name":"Cachimbulo",
    "gn:population":0,
    "gn:timezone":"America/Bogota",
    "iso:country":"CO",
    "name:spa_x_preferred":[
        "Cachimbulo"
    ],
    "wof:name":"Cachimbulo",
    "wof:placetype":"locality"
},
  "geometry": {"coordinates":[-74.59390999999999,4.45267],"type":"Point"}
}