{
  "type": "Feature",
  "properties": {
    "gn:admin1_code":"24",
    "gn:admin2_code":"66088.0",
    "gn:asciiname":"El Eden",
    "gn:country_code":"CO",
    "gn:dem":1328,
    "gn:feature_class":"P",
    "gn:feature_code":"PPL",
    "gn:name":"El Eden",
    "gn:population":0,
    "gn:timezone":"America/Bogota",
    "iso:country":"CO",
    "wof:name":"El Eden",
    "wof:placetype":"locality"
},
  "geometry": {"coordinates":[-75.8502,5.23429],"type":"Point"}
}