{
  "type": "Feature",
  "properties": {
    "gn:country":"CO",
    "gn:fcode":"PPL",
    "gn:population":2552,
    "iso:country":"CO",
    "name:ast_x_preferred":[
        "Sucre"
    ],
    "name:ceb_x_preferred":[
        "Sucre"
    ],
    "name:eng_x_preferred":[
        "Sucre"
    ],
    "name:eng_x_variant":[
        "Guaitarilla"
    ],
    "name:fra_x_preferred":[
        "Sucre"
    ],
    "name:ita_x_preferred":[
        "Sucre"
    ],
    "name:kat_x_preferred":[
        "\u10e1\u10e3\u10d9\u10e0\u10d4"
    ],
    "name:msa_x_preferred":[
        "Sucre"
    ],
    "name:nan_x_preferred":[
        "Sucre"
    ],
    "name:nld_x_preferred":[
        "Sucre"
    ],
    "name:sco_x_preferred":[
        "Sucre"
    ],
    "name:spa_x_preferred":[
        "Sucre"
    ],
    "name:swe_x_preferred":[
        "Sucre"
    ],
    "name:tgl_x_preferred":[
        "Sucre"
    ],
    "name:war_x_preferred":[
        "Sucre"
    ],
    "name:zho_x_preferred":[
        "\u8607\u514b\u96f7"
    ],
    "name:zho_x_variant":[
        "\u6cd5\u862d"
    ],
    "qs_pg:aaroncc":"CO",
    "qs_pg:gn_country":"CO",
    "qs_pg:gn_fcode":"PPL",
    "qs_pg:gn_pop":2552,
    "qs_pg:name":"Sucre",
    "qs_pg:photos_9r":0,
    "qs_pg:photos_sr":0,
    "qs_pg:pop_sr":4,
    "qs_pg:qs_pg_placetype":"locality",
    "wof:name":"Sucre",
    "wof:placetype":"locality",
    "wof:population":2552
},
  "geometry": {"coordinates":[-76.92446,2.03805],"type":"Point"}
}