{
  "type": "Feature",
  "properties": {
    "gn:admin1_code":"19.0",
    "gn:admin2_code":"50590.0",
    "gn:asciiname":"El Turpial",
    "gn:country_code":"CO",
    "gn:dem":212,
    "gn:feature_class":"P",
    "gn:feature_code":"PPL",
    "gn:name":"El Turpial",
    "gn:population":0,
    "gn:timezone":"America/Bogota",
    "iso:country":"CO",
    "wof:name":"El Turpial",
    "wof:placetype":"locality"
},
  "geometry": {"coordinates":[-73.30211,2.99004],"type":"Point"}
}