{
  "type": "Feature",
  "properties": {
    "gn:admin1_code":"29",
    "gn:admin2_code":"76736.0",
    "gn:asciiname":"Las Nieves",
    "gn:country_code":"CO",
    "gn:dem":3145,
    "gn:feature_class":"P",
    "gn:feature_code":"PPL",
    "gn:name":"Las Nieves",
    "gn:population":0,
    "gn:timezone":"America/Bogota",
    "iso:country":"CO",
    "name:ceb_x_preferred":[
        "Las Nieves"
    ],
    "name:deu_x_preferred":[
        "Las Nieves"
    ],
    "name:ita_x_preferred":[
        "Las Nieves"
    ],
    "name:nld_x_preferred":[
        "Las Nieves"
    ],
    "name:spa_x_preferred":[
        "Las Nieves"
    ],
    "name:swe_x_preferred":[
        "Las Nieves"
    ],
    "wof:name":"Las Nieves",
    "wof:placetype":"locality"
},
  "geometry": {"coordinates":[-75.83116,4.03234],"type":"Point"}
}