{
  "type": "Feature",
  "properties": {
    "gn:admin1_code":"14.0",
    "gn:admin2_code":"95001.0",
    "gn:asciiname":"El Resbalon",
    "gn:country_code":"CO",
    "gn:dem":190,
    "gn:feature_class":"P",
    "gn:feature_code":"PPL",
    "gn:name":"El Resbal\u00f3n",
    "gn:population":0,
    "gn:timezone":"America/Bogota",
    "iso:country":"CO",
    "wof:name":"El Resbalon",
    "wof:placetype":"locality"
},
  "geometry": {"coordinates":[-72.44523000000002,2.58175],"type":"Point"}
}