{
  "type": "Feature",
  "properties": {
    "gn:admin1_code":"16.0",
    "gn:admin2_code":"41006.0",
    "gn:asciiname":"El Caballito",
    "gn:country_code":"CO",
    "gn:dem":2117,
    "gn:feature_class":"P",
    "gn:feature_code":"PPL",
    "gn:name":"El Caballito",
    "gn:population":0,
    "gn:timezone":"America/Bogota",
    "iso:country":"CO",
    "wof:name":"El Caballito",
    "wof:placetype":"locality"
},
  "geometry": {"coordinates":[-76.11394,1.62249],"type":"Point"}
}