{
  "type": "Feature",
  "properties": {
    "gn:admin1_code":"33",
    "gn:admin2_code":"25530.0",
    "gn:asciiname":"El Viso",
    "gn:country_code":"CO",
    "gn:dem":241,
    "gn:feature_class":"P",
    "gn:feature_code":"PPL",
    "gn:name":"El Viso",
    "gn:population":0,
    "gn:timezone":"America/Bogota",
    "iso:country":"CO",
    "wof:name":"El Viso",
    "wof:placetype":"locality"
},
  "geometry": {"coordinates":[-73.21966,4.31468],"type":"Point"}
}