{
  "type": "Feature",
  "properties": {
    "gn:admin1_code":"2.0",
    "gn:admin2_code":"5887.0",
    "gn:asciiname":"Uraba",
    "gn:country_code":"CO",
    "gn:dem":2766,
    "gn:feature_class":"P",
    "gn:feature_code":"PPL",
    "gn:name":"Urab\u00e1",
    "gn:population":0,
    "gn:timezone":"America/Bogota",
    "iso:country":"CO",
    "wof:name":"Uraba",
    "wof:placetype":"locality"
},
  "geometry": {"coordinates":[-75.51306,6.82833],"type":"Point"}
}