{
  "type": "Feature",
  "properties": {
    "gn:admin1_code":"33",
    "gn:admin2_code":"25402.0",
    "gn:asciiname":"El Chuscal",
    "gn:country_code":"CO",
    "gn:dem":2120,
    "gn:feature_class":"P",
    "gn:feature_code":"PPL",
    "gn:name":"El Chuscal",
    "gn:population":0,
    "gn:timezone":"America/Bogota",
    "iso:country":"CO",
    "wof:name":"El Chuscal",
    "wof:placetype":"locality"
},
  "geometry": {"coordinates":[-74.31667,4.93333],"type":"Point"}
}