{
  "type": "Feature",
  "properties": {
    "gn:admin1_code":"14.0",
    "gn:admin2_code":"95200.0",
    "gn:asciiname":"Puerto Grita",
    "gn:country_code":"CO",
    "gn:dem":189,
    "gn:feature_class":"P",
    "gn:feature_code":"PPL",
    "gn:name":"Puerto Grita",
    "gn:population":0,
    "gn:timezone":"America/Bogota",
    "iso:country":"CO",
    "wof:name":"Puerto Grita",
    "wof:placetype":"locality"
},
  "geometry": {"coordinates":[-71.99583,1.01611],"type":"Point"}
}