{
  "type": "Feature",
  "properties": {
    "gn:admin1_code":"35",
    "gn:admin2_code":"13473.0",
    "gn:asciiname":"Los Palmitos",
    "gn:country_code":"CO",
    "gn:dem":41,
    "gn:feature_class":"P",
    "gn:feature_code":"PPL",
    "gn:name":"Los Palmitos",
    "gn:population":0,
    "gn:timezone":"America/Bogota",
    "iso:country":"CO",
    "name:ceb_x_preferred":[
        "Los Palmitos"
    ],
    "name:diq_x_preferred":[
        "Los Palmitos"
    ],
    "name:fra_x_preferred":[
        "Los Palmitos"
    ],
    "name:ita_x_preferred":[
        "Los Palmitos"
    ],
    "name:kat_x_preferred":[
        "\u10da\u10dd\u10e1-\u10de\u10d0\u10da\u10db\u10d8\u10e2\u10dd\u10e1\u10d8"
    ],
    "name:msa_x_preferred":[
        "Los Palmitos"
    ],
    "name:nld_x_preferred":[
        "Los Palmitos"
    ],
    "name:spa_x_preferred":[
        "Los Palmitos"
    ],
    "name:swe_x_preferred":[
        "Los Palmitos"
    ],
    "name:vie_x_preferred":[
        "Los Palmitos"
    ],
    "name:war_x_preferred":[
        "Los Palmitos"
    ],
    "name:zho_x_preferred":[
        "\u6d1b\u65af\u5e15\u723e\u7c73\u6258\u65af"
    ],
    "wof:name":"Los Palmitos",
    "wof:placetype":"locality"
},
  "geometry": {"coordinates":[-73.80065999999999,8.41141],"type":"Point"}
}