{
  "type": "Feature",
  "properties": {
    "gn:admin1_code":"8.0",
    "gn:admin2_code":"18150.0",
    "gn:asciiname":"Pore",
    "gn:country_code":"CO",
    "gn:dem":195,
    "gn:feature_class":"P",
    "gn:feature_code":"PPL",
    "gn:name":"Pore",
    "gn:population":0,
    "gn:timezone":"America/Bogota",
    "iso:country":"CO",
    "name:ceb_x_preferred":[
        "Pore"
    ],
    "name:dan_x_preferred":[
        "Pore"
    ],
    "name:fra_x_preferred":[
        "Pore"
    ],
    "name:ido_x_preferred":[
        "Poro"
    ],
    "name:swe_x_preferred":[
        "Pore"
    ],
    "wof:name":"Pore",
    "wof:placetype":"locality"
},
  "geometry": {"coordinates":[-74.75285,1.06142],"type":"Point"}
}