{
  "type": "Feature",
  "properties": {
    "gn:admin1_code":"16.0",
    "gn:admin2_code":"41001.0",
    "gn:asciiname":"Motilon",
    "gn:country_code":"CO",
    "gn:dem":2756,
    "gn:feature_class":"P",
    "gn:feature_code":"PPL",
    "gn:name":"Motil\u00f3n",
    "gn:population":0,
    "gn:timezone":"America/Bogota",
    "iso:country":"CO",
    "name:cat_x_preferred":[
        "Bar\u00eds"
    ],
    "name:fra_x_preferred":[
        "Baris"
    ],
    "name:hrv_x_preferred":[
        "Bar\u00ed"
    ],
    "name:ita_x_preferred":[
        "Motilon"
    ],
    "name:lit_x_preferred":[
        "Motilonai"
    ],
    "name:nor_x_preferred":[
        "Bar\u00ed"
    ],
    "name:spa_x_preferred":[
        "Motil\u00f3n"
    ],
    "name:spa_x_variant":[
        "Pueblo Motil\u00f3n-bar\u00ed"
    ],
    "wof:name":"Motilon",
    "wof:placetype":"locality"
},
  "geometry": {"coordinates":[-75.03333000000001,2.85],"type":"Point"}
}