{
  "type": "Feature",
  "properties": {
    "gn:admin1_code":"38",
    "gn:admin2_code":"47605.0",
    "gn:asciiname":"Hacienda Los Papayos",
    "gn:country_code":"CO",
    "gn:dem":5,
    "gn:feature_class":"P",
    "gn:feature_code":"PPL",
    "gn:name":"Hacienda Los Papayos",
    "gn:population":0,
    "gn:timezone":"America/Bogota",
    "iso:country":"CO",
    "wof:name":"Hacienda Los Papayos",
    "wof:placetype":"locality"
},
  "geometry": {"coordinates":[-74.59472,10.56944],"type":"Point"}
}