{
  "type": "Feature",
  "properties": {
    "gn:admin1_code":"35",
    "gn:admin2_code":"13549.0",
    "gn:asciiname":"Aire Libre",
    "gn:country_code":"CO",
    "gn:dem":20,
    "gn:feature_class":"P",
    "gn:feature_code":"PPL",
    "gn:name":"Aire Libre",
    "gn:population":0,
    "gn:timezone":"America/Bogota",
    "iso:country":"CO",
    "wof:name":"Aire Libre",
    "wof:placetype":"locality"
},
  "geometry": {"coordinates":[-74.3852,8.80392],"type":"Point"}
}