{
  "type": "Feature",
  "properties": {
    "gn:admin1_code":"26.0",
    "gn:admin2_code":"68081.0",
    "gn:asciiname":"El Horizonte",
    "gn:country_code":"CO",
    "gn:dem":94,
    "gn:feature_class":"P",
    "gn:feature_code":"PPL",
    "gn:name":"El Horizonte",
    "gn:population":0,
    "gn:timezone":"America/Bogota",
    "iso:country":"CO",
    "wof:name":"El Horizonte",
    "wof:placetype":"locality"
},
  "geometry": {"coordinates":[-73.61941,7.11311],"type":"Point"}
}