{
  "type": "Feature",
  "properties": {
    "gn:admin1_code":"3",
    "gn:admin2_code":"81001.0",
    "gn:asciiname":"La Ahuyama",
    "gn:country_code":"CO",
    "gn:dem":121,
    "gn:feature_class":"P",
    "gn:feature_code":"PPL",
    "gn:name":"La Ahuyama",
    "gn:population":0,
    "gn:timezone":"America/Bogota",
    "iso:country":"CO",
    "name:spa_x_preferred":[
        "La Ahuyama"
    ],
    "name:und_x_variant":[
        "Abuyama",
        "Paso La Ahuyama"
    ],
    "wof:name":"La Ahuyama",
    "wof:placetype":"locality"
},
  "geometry": {"coordinates":[-70.58318,6.8954],"type":"Point"}
}