{
  "type": "Feature",
  "properties": {
    "gn:admin1_code":"19",
    "gn:admin2_code":"50223",
    "gn:asciiname":"Samarcanda",
    "gn:country_code":"CO",
    "gn:dem":548,
    "gn:feature_class":"P",
    "gn:feature_code":"PPL",
    "gn:name":"Samarcanda",
    "gn:population":0,
    "gn:timezone":"America/Bogota",
    "iso:country":"CO",
    "name:spa_x_preferred":[
        "Samarcanda"
    ],
    "wof:name":"Samarcanda",
    "wof:placetype":"locality"
},
  "geometry": {"coordinates":[-73.82064,3.7716],"type":"Point"}
}