{
  "type": "Feature",
  "properties": {
    "gn:admin1_code":"28",
    "gn:admin2_code":"73168.0",
    "gn:asciiname":"La Marina",
    "gn:country_code":"CO",
    "gn:dem":1967,
    "gn:feature_class":"P",
    "gn:feature_code":"PPL",
    "gn:name":"La Marina",
    "gn:population":0,
    "gn:timezone":"America/Bogota",
    "iso:country":"CO",
    "wof:name":"La Marina",
    "wof:placetype":"locality"
},
  "geometry": {"coordinates":[-75.62666999999998,3.72],"type":"Point"}
}