{
  "type": "Feature",
  "properties": {
    "gn:admin1_code":"32.0",
    "gn:admin2_code":"85440.0",
    "gn:asciiname":"Santa Elena de Upia",
    "gn:country_code":"CO",
    "gn:dem":173,
    "gn:feature_class":"P",
    "gn:feature_code":"PPL",
    "gn:name":"Santa Elena de Upia",
    "gn:population":0,
    "gn:timezone":"America/Bogota",
    "iso:country":"CO",
    "name:und_x_variant":[
        "Santa Helene de Upia",
        "Santa Helena de Upia",
        "Santa Helena",
        "Santa Elena de Upia"
    ],
    "wof:name":"Santa Elena de Upia",
    "wof:placetype":"locality"
},
  "geometry": {"coordinates":[-72.74386,4.33509],"type":"Point"}
}