{
  "type": "Feature",
  "properties": {
    "gn:admin1_code":"9",
    "gn:admin2_code":"19473.0",
    "gn:asciiname":"El Vergel",
    "gn:country_code":"CO",
    "gn:dem":1695,
    "gn:feature_class":"P",
    "gn:feature_code":"PPL",
    "gn:name":"El Vergel",
    "gn:population":0,
    "gn:timezone":"America/Bogota",
    "iso:country":"CO",
    "wof:name":"El Vergel",
    "wof:placetype":"locality"
},
  "geometry": {"coordinates":[-76.75483,2.75623],"type":"Point"}
}