{
  "type": "Feature",
  "properties": {
    "gn:admin1_code":"16",
    "gn:admin2_code":"41016.0",
    "gn:asciiname":"El Tamaro",
    "gn:country_code":"CO",
    "gn:dem":1027,
    "gn:feature_class":"P",
    "gn:feature_code":"PPL",
    "gn:name":"El Tamaro",
    "gn:population":0,
    "gn:timezone":"America/Bogota",
    "iso:country":"CO",
    "wof:name":"El Tamaro",
    "wof:placetype":"locality"
},
  "geometry": {"coordinates":[-75.42889,3.295],"type":"Point"}
}