{
  "type": "Feature",
  "properties": {
    "gn:admin1_code":"33",
    "gn:admin2_code":"25293.0",
    "gn:asciiname":"Matefique",
    "gn:country_code":"CO",
    "gn:dem":1796,
    "gn:feature_class":"P",
    "gn:feature_code":"PPL",
    "gn:name":"Matefique",
    "gn:population":0,
    "gn:timezone":"America/Bogota",
    "iso:country":"CO",
    "wof:name":"Matefique",
    "wof:placetype":"locality"
},
  "geometry": {"coordinates":[-73.47711,4.70343],"type":"Point"}
}