{
  "type": "Feature",
  "properties": {
    "gn:admin1_code":"38",
    "gn:admin2_code":"47545.0",
    "gn:asciiname":"Peladeros",
    "gn:country_code":"CO",
    "gn:dem":86,
    "gn:feature_class":"P",
    "gn:feature_code":"PPL",
    "gn:name":"Peladeros",
    "gn:population":0,
    "gn:timezone":"America/Bogota",
    "iso:country":"CO",
    "wof:name":"Peladeros",
    "wof:placetype":"locality"
},
  "geometry": {"coordinates":[-74.0252,9.63969],"type":"Point"}
}