{
  "type": "Feature",
  "properties": {
    "gn:admin1_code":"2.0",
    "gn:admin2_code":"5212.0",
    "gn:asciiname":"El Convento",
    "gn:country_code":"CO",
    "gn:dem":1610,
    "gn:feature_class":"P",
    "gn:feature_code":"PPL",
    "gn:name":"El Convento",
    "gn:population":0,
    "gn:timezone":"America/Bogota",
    "iso:country":"CO",
    "name:spa_x_preferred":[
        "El Convento"
    ],
    "wof:name":"El Convento",
    "wof:placetype":"locality"
},
  "geometry": {"coordinates":[-75.51275,6.33456],"type":"Point"}
}