{
  "type": "Feature",
  "properties": {
    "gn:admin1_code":"22.0",
    "gn:admin2_code":"86001.0",
    "gn:asciiname":"La Pasera",
    "gn:country_code":"CO",
    "gn:dem":453,
    "gn:feature_class":"P",
    "gn:feature_code":"PPL",
    "gn:name":"La Pasera",
    "gn:population":0,
    "gn:timezone":"America/Bogota",
    "iso:country":"CO",
    "name:spa_x_preferred":[
        "La Pasera"
    ],
    "wof:name":"La Pasera",
    "wof:placetype":"locality"
},
  "geometry": {"coordinates":[-76.51076999999999,1.01798],"type":"Point"}
}