{
  "type": "Feature",
  "properties": {
    "gn:admin1_code":"20",
    "gn:admin2_code":"52079.0",
    "gn:asciiname":"Los Brazos",
    "gn:country_code":"CO",
    "gn:dem":113,
    "gn:feature_class":"P",
    "gn:feature_code":"PPL",
    "gn:name":"Los Brazos",
    "gn:population":0,
    "gn:timezone":"America/Bogota",
    "iso:country":"CO",
    "wof:name":"Los Brazos",
    "wof:placetype":"locality"
},
  "geometry": {"coordinates":[-78.21474000000001,1.61474],"type":"Point"}
}