{
  "type": "Feature",
  "properties": {
    "gn:admin1_code":"33.0",
    "gn:admin2_code":"25297.0",
    "gn:asciiname":"El Descansadero",
    "gn:country_code":"CO",
    "gn:dem":2198,
    "gn:feature_class":"P",
    "gn:feature_code":"PPL",
    "gn:name":"El Descansadero",
    "gn:population":0,
    "gn:timezone":"America/Bogota",
    "iso:country":"CO",
    "wof:name":"El Descansadero",
    "wof:placetype":"locality"
},
  "geometry": {"coordinates":[-73.5771,4.87376],"type":"Point"}
}