{
  "type": "Feature",
  "properties": {
    "gn:admin1_code":"26.0",
    "gn:admin2_code":"68081.0",
    "gn:asciiname":"La Raiz",
    "gn:country_code":"CO",
    "gn:dem":90,
    "gn:feature_class":"P",
    "gn:feature_code":"PPL",
    "gn:name":"La Ra\u00edz",
    "gn:population":0,
    "gn:timezone":"America/Bogota",
    "iso:country":"CO",
    "wof:name":"La Raiz",
    "wof:placetype":"locality"
},
  "geometry": {"coordinates":[-73.71194,7.2075],"type":"Point"}
}