{
  "type": "Feature",
  "properties": {
    "gn:admin1_code":"38",
    "gn:admin2_code":"47551.0",
    "gn:asciiname":"Bellavista",
    "gn:cc2":"CO",
    "gn:country_code":"CO",
    "gn:dem":88,
    "gn:feature_class":"P",
    "gn:feature_code":"PPL",
    "gn:name":"Bellavista",
    "gn:population":0,
    "gn:timezone":"America/Bogota",
    "iso:country":"CO",
    "name:cat_x_preferred":[
        "Bellavista"
    ],
    "name:ceb_x_preferred":[
        "Bellavista"
    ],
    "name:deu_x_preferred":[
        "Bellavista"
    ],
    "name:fra_x_preferred":[
        "Bellavista"
    ],
    "name:ita_x_preferred":[
        "Bellavista"
    ],
    "name:kor_x_preferred":[
        "\ubca8\ub77c\ube44\uc2a4\ud0c0"
    ],
    "name:nld_x_preferred":[
        "Bellavista"
    ],
    "name:pol_x_preferred":[
        "Bellavista"
    ],
    "name:por_x_preferred":[
        "Bellavista"
    ],
    "name:spa_x_preferred":[
        "Bellavista"
    ],
    "name:srp_x_preferred":[
        "Bellavista"
    ],
    "name:swe_x_preferred":[
        "Bellavista"
    ],
    "name:und_x_variant":[
        "Hacienda Bellavista"
    ],
    "wof:name":"Bellavista",
    "wof:placetype":"locality"
},
  "geometry": {"coordinates":[-74.40000000000001,10.26667],"type":"Point"}
}