{
  "type": "Feature",
  "properties": {
    "gn:admin1_code":"20.0",
    "gn:admin2_code":"52720.0",
    "gn:asciiname":"Cabanas",
    "gn:country_code":"CO",
    "gn:dem":3147,
    "gn:feature_class":"P",
    "gn:feature_code":"PPL",
    "gn:name":"Caba\u00f1as",
    "gn:population":0,
    "gn:timezone":"America/Bogota",
    "iso:country":"CO",
    "wof:name":"Cabanas",
    "wof:placetype":"locality"
},
  "geometry": {"coordinates":[-77.75524,1.04377],"type":"Point"}
}