{
  "type": "Feature",
  "properties": {
    "iso:country":"CO",
    "qs:gn_country":"CO",
    "qs:gn_fcode":"PPLX",
    "qs:gn_pop":0,
    "qs:name":"Boyac\u00e1",
    "qs:name_adm0":"Colombia",
    "qs:name_adm1":"Atlantico",
    "qs:photos":33,
    "qs:photos_1k":7,
    "qs:photos_9k":1,
    "qs:photos_9r":2,
    "qs:photos_all":33,
    "qs:photos_sr":2,
    "qs:placetype":"Suburb",
    "qs:pop_sr":"0",
    "qs:woe_adm0":23424787,
    "wof:name":"Boyac\u00e1",
    "wof:placetype":"neighbourhood"
},
  "geometry": {"coordinates":[-74.78333000000001,10.95],"type":"Point"}
}