{
  "type": "Feature",
  "properties": {
    "gn:admin1_code":"33.0",
    "gn:admin2_code":"25815.0",
    "gn:asciiname":"La Plata",
    "gn:country_code":"CO",
    "gn:dem":443,
    "gn:feature_class":"P",
    "gn:feature_code":"PPL",
    "gn:name":"La Plata",
    "gn:population":0,
    "gn:timezone":"America/Bogota",
    "iso:country":"CO",
    "name:spa_x_preferred":[
        "La Plata"
    ],
    "wof:name":"La Plata",
    "wof:placetype":"locality"
},
  "geometry": {"coordinates":[-74.67543000000001,4.47314],"type":"Point"}
}