{
  "type": "Feature",
  "properties": {
    "gn:admin1_code":"2",
    "gn:admin2_code":"5361.0",
    "gn:asciiname":"La Aldea",
    "gn:country_code":"CO",
    "gn:dem":1060,
    "gn:feature_class":"P",
    "gn:feature_code":"PPL",
    "gn:name":"La Aldea",
    "gn:population":0,
    "gn:timezone":"America/Bogota",
    "iso:country":"CO",
    "wof:name":"La Aldea",
    "wof:placetype":"locality"
},
  "geometry": {"coordinates":[-75.95971999999998,7.34417],"type":"Point"}
}