{
  "type": "Feature",
  "properties": {
    "gn:admin1_code":"2",
    "gn:admin2_code":"5250.0",
    "gn:asciiname":"Cuturu",
    "gn:cc2":"CO",
    "gn:country_code":"CO",
    "gn:dem":49,
    "gn:feature_class":"P",
    "gn:feature_code":"PPL",
    "gn:name":"Cutur\u00fa",
    "gn:population":0,
    "gn:timezone":"America/Bogota",
    "iso:country":"CO",
    "name:und_x_variant":[
        "Coturu",
        "Cutur\u00fa"
    ],
    "wof:name":"Cuturu",
    "wof:placetype":"locality"
},
  "geometry": {"coordinates":[-74.78333000000001,7.91667],"type":"Point"}
}