{
  "type": "Feature",
  "properties": {
    "gn:admin1_code":"36",
    "gn:admin2_code":"15572.0",
    "gn:asciiname":"La Tribuna",
    "gn:country_code":"CO",
    "gn:dem":341,
    "gn:feature_class":"P",
    "gn:feature_code":"PPL",
    "gn:name":"La Tribuna",
    "gn:population":0,
    "gn:timezone":"America/Bogota",
    "iso:country":"CO",
    "name:spa_x_preferred":[
        "La Tribuna"
    ],
    "wof:name":"La Tribuna",
    "wof:placetype":"locality"
},
  "geometry": {"coordinates":[-74.33400999999998,5.88408],"type":"Point"}
}