{
  "type": "Feature",
  "properties": {
    "gn:admin1_code":"9",
    "gn:admin2_code":"19001.0",
    "gn:asciiname":"La Cabuyera",
    "gn:country_code":"CO",
    "gn:dem":1810,
    "gn:feature_class":"P",
    "gn:feature_code":"PPL",
    "gn:name":"La Cabuyera",
    "gn:population":0,
    "gn:timezone":"America/Bogota",
    "iso:country":"CO",
    "wof:name":"La Cabuyera",
    "wof:placetype":"locality"
},
  "geometry": {"coordinates":[-76.55001,2.52609],"type":"Point"}
}