{
  "type": "Feature",
  "properties": {
    "gn:admin1_code":"28.0",
    "gn:admin2_code":"73616.0",
    "gn:asciiname":"Tolima",
    "gn:country_code":"CO",
    "gn:dem":1522,
    "gn:feature_class":"P",
    "gn:feature_code":"PPL",
    "gn:name":"Tolima",
    "gn:population":0,
    "gn:timezone":"America/Bogota",
    "iso:country":"CO",
    "wof:name":"Tolima",
    "wof:placetype":"locality"
},
  "geometry": {"coordinates":[-75.69278,3.54944],"type":"Point"}
}