{
  "type": "Feature",
  "properties": {
    "gn:admin1_code":"2.0",
    "gn:admin2_code":"5088.0",
    "gn:asciiname":"La Minita",
    "gn:country_code":"CO",
    "gn:dem":2463,
    "gn:feature_class":"P",
    "gn:feature_code":"PPL",
    "gn:name":"La Minita",
    "gn:population":0,
    "gn:timezone":"America/Bogota",
    "iso:country":"CO",
    "name:spa_x_preferred":[
        "La Minita"
    ],
    "wof:name":"La Minita",
    "wof:placetype":"locality"
},
  "geometry": {"coordinates":[-75.60413,6.38493],"type":"Point"}
}