{
  "type": "Feature",
  "properties": {
    "iso:country":"CO",
    "name:ceb_x_preferred":[
        "Morelia"
    ],
    "name:eng_x_preferred":[
        "Morelia"
    ],
    "name:fra_x_preferred":[
        "Morelia"
    ],
    "name:ita_x_preferred":[
        "Morelia"
    ],
    "name:jpn_x_preferred":[
        "\u30e2\u30ec\u30ea\u30a2"
    ],
    "name:kat_x_preferred":[
        "\u10db\u10dd\u10e0\u10d4\u10da\u10d8\u10d0"
    ],
    "name:msa_x_preferred":[
        "Morelia"
    ],
    "name:nan_x_preferred":[
        "Morelia"
    ],
    "name:nld_x_preferred":[
        "Morelia"
    ],
    "name:spa_x_preferred":[
        "Morelia"
    ],
    "name:swe_x_preferred":[
        "Morelia"
    ],
    "name:tgl_x_preferred":[
        "Morelia"
    ],
    "name:unk_x_variant":[
        "Moralia"
    ],
    "name:war_x_preferred":[
        "Morelia"
    ],
    "name:zho_x_preferred":[
        "\u83ab\u96f7\u5229\u4e9e"
    ],
    "qs:gn_country":"CO",
    "qs:gn_fcode":"PPL",
    "qs:gn_pop":2257,
    "qs:name":"Morelia",
    "qs:name_adm0":"Colombia",
    "qs:name_adm1":"Caqueta",
    "qs:photos":0,
    "qs:photos_1k":0,
    "qs:photos_9k":1,
    "qs:photos_9r":1,
    "qs:photos_all":11,
    "qs:photos_sr":0,
    "qs:placetype":"Town",
    "qs:pop_sr":"4",
    "qs:woe_adm0":23424787,
    "wd:wordcount":42,
    "wof:name":"Morelia",
    "wof:placetype":"locality",
    "wof:population":2257
},
  "geometry": {"coordinates":[-75.72581,1.48747],"type":"Point"}
}