{
  "type": "Feature",
  "properties": {
    "gn:admin1_code":"2.0",
    "gn:admin2_code":"5001.0",
    "gn:asciiname":"Los Yarumas",
    "gn:country_code":"CO",
    "gn:dem":2325,
    "gn:feature_class":"P",
    "gn:feature_code":"PPL",
    "gn:name":"Los Yarumas",
    "gn:population":0,
    "gn:timezone":"America/Bogota",
    "iso:country":"CO",
    "name:spa_x_preferred":[
        "Los Yarumas"
    ],
    "wof:name":"Los Yarumas",
    "wof:placetype":"locality"
},
  "geometry": {"coordinates":[-75.51168,6.23915],"type":"Point"}
}