{
  "type": "Feature",
  "properties": {
    "gn:admin1_code":"26.0",
    "gn:admin2_code":"68655.0",
    "gn:asciiname":"La Moneda",
    "gn:country_code":"CO",
    "gn:dem":119,
    "gn:feature_class":"P",
    "gn:feature_code":"PPL",
    "gn:name":"La Moneda",
    "gn:population":0,
    "gn:timezone":"America/Bogota",
    "iso:country":"CO",
    "wof:name":"La Moneda",
    "wof:placetype":"locality"
},
  "geometry": {"coordinates":[-73.57444,7.36444],"type":"Point"}
}