{
  "type": "Feature",
  "properties": {
    "gn:admin1_code":"31",
    "gn:admin2_code":"99773.0",
    "gn:asciiname":"Cumaral",
    "gn:country_code":"CO",
    "gn:dem":127,
    "gn:feature_class":"P",
    "gn:feature_code":"PPL",
    "gn:name":"Cumaral",
    "gn:population":0,
    "gn:timezone":"America/Bogota",
    "iso:country":"CO",
    "wof:name":"Cumaral",
    "wof:placetype":"locality"
},
  "geometry": {"coordinates":[-70.17714000000001,3.35107],"type":"Point"}
}