{
  "type": "Feature",
  "properties": {
    "gn:admin1_code":"32",
    "gn:admin2_code":"85325.0",
    "gn:asciiname":"Las Babas",
    "gn:country_code":"CO",
    "gn:dem":178,
    "gn:feature_class":"P",
    "gn:feature_code":"PPL",
    "gn:name":"Las Babas",
    "gn:population":0,
    "gn:timezone":"America/Bogota",
    "iso:country":"CO",
    "wof:name":"Las Babas",
    "wof:placetype":"locality"
},
  "geometry": {"coordinates":[-71.90449,5.20338],"type":"Point"}
}