{
  "type": "Feature",
  "properties": {
    "gn:admin1_code":"29",
    "gn:admin2_code":"76111.0",
    "gn:asciiname":"El Pensil",
    "gn:country_code":"CO",
    "gn:dem":2606,
    "gn:feature_class":"P",
    "gn:feature_code":"PPL",
    "gn:name":"El Pensil",
    "gn:population":0,
    "gn:timezone":"America/Bogota",
    "iso:country":"CO",
    "wof:name":"El Pensil",
    "wof:placetype":"locality"
},
  "geometry": {"coordinates":[-75.89889000000002,3.92333],"type":"Point"}
}