{
  "type": "Feature",
  "properties": {
    "gn:admin1_code":"28.0",
    "gn:admin2_code":"73236.0",
    "gn:asciiname":"Las Minas",
    "gn:country_code":"CO",
    "gn:dem":1412,
    "gn:feature_class":"P",
    "gn:feature_code":"PPLL",
    "gn:name":"Las Minas",
    "gn:population":0,
    "gn:timezone":"America/Bogota",
    "iso:country":"CO",
    "name:spa_x_preferred":[
        "Las Minas"
    ],
    "wof:name":"Las Minas",
    "wof:placetype":"locality"
},
  "geometry": {"coordinates":[-74.75109,3.64453],"type":"Point"}
}