{
  "type": "Feature",
  "properties": {
    "gn:admin1_code":"29.0",
    "gn:admin2_code":"76250.0",
    "gn:asciiname":"Sirimunda",
    "gn:country_code":"CO",
    "gn:dem":1702,
    "gn:feature_class":"P",
    "gn:feature_code":"PPL",
    "gn:name":"Sirimunda",
    "gn:population":0,
    "gn:timezone":"America/Bogota",
    "iso:country":"CO",
    "name:und_x_variant":[
        "Sirimanda",
        "Sirimunda"
    ],
    "wof:name":"Sirimunda",
    "wof:placetype":"locality"
},
  "geometry": {"coordinates":[-76.27755999999999,4.55028],"type":"Point"}
}