{
  "type": "Feature",
  "properties": {
    "gn:admin1_code":"38",
    "gn:asciiname":"Dona Juana",
    "gn:country_code":"CO",
    "gn:dem":23,
    "gn:feature_class":"P",
    "gn:feature_code":"PPL",
    "gn:name":"Do\u00f1a Juana",
    "gn:population":0,
    "gn:timezone":"America/Bogota",
    "iso:country":"CO",
    "name:und_x_variant":[
        "Corregimiento Do\u00f1a Juana",
        "Do\u00f1a Juana"
    ],
    "wof:name":"Dona Juana",
    "wof:placetype":"locality"
},
  "geometry": {"coordinates":[-74.1927,9.09321],"type":"Point"}
}