{
  "type": "Feature",
  "properties": {
    "iso:country":"CO",
    "name:ceb_x_preferred":[
        "P\u00e1ez"
    ],
    "name:chi_x_preferred":[
        "\u5e15\u57c3\u65af"
    ],
    "name:dut_x_preferred":[
        "P\u00e1ez"
    ],
    "name:eng_x_preferred":[
        "P\u00e1ez"
    ],
    "name:fra_x_preferred":[
        "P\u00e1ez"
    ],
    "name:fre_x_preferred":[
        "P\u00e1ez"
    ],
    "name:geo_x_preferred":[
        "\u10de\u10d0\u10d4\u10e1\u10d8"
    ],
    "name:ita_x_preferred":[
        "P\u00e1ez"
    ],
    "name:kat_x_preferred":[
        "\u10de\u10d0\u10d4\u10e1\u10d8"
    ],
    "name:may_x_preferred":[
        "P\u00e1ez"
    ],
    "name:msa_x_preferred":[
        "P\u00e1ez"
    ],
    "name:nan_x_preferred":[
        "P\u00e1ez"
    ],
    "name:nld_x_preferred":[
        "P\u00e1ez"
    ],
    "name:por_x_preferred":[
        "P\u00e1ez"
    ],
    "name:spa_x_preferred":[
        "P\u00e1ez"
    ],
    "name:swe_x_preferred":[
        "P\u00e1ez"
    ],
    "name:tgl_x_preferred":[
        "P\u00e1ez"
    ],
    "name:vie_x_preferred":[
        "P\u00e1ez"
    ],
    "name:war_x_preferred":[
        "P\u00e1ez"
    ],
    "qs:gn_country":"CO",
    "qs:gn_fcode":"PPL",
    "qs:gn_pop":1220,
    "qs:name":"P\u00e1ez",
    "qs:name_adm0":"Colombia",
    "qs:name_adm1":"Boyaca",
    "qs:photos":0,
    "qs:photos_1k":0,
    "qs:photos_9k":0,
    "qs:photos_9r":0,
    "qs:photos_all":0,
    "qs:photos_sr":0,
    "qs:placetype":"Town",
    "qs:pop_sr":"3",
    "qs:woe_adm0":23424787,
    "wd:wordcount":42,
    "wof:name":"P\u00e1ez",
    "wof:placetype":"locality",
    "wof:population":1220
},
  "geometry": {"coordinates":[-73.05122,5.10112],"type":"Point"}
}