{
  "type": "Feature",
  "properties": {
    "gn:admin1_code":"2.0",
    "gn:admin2_code":"5002.0",
    "gn:asciiname":"Naranjal",
    "gn:country_code":"CO",
    "gn:dem":1925,
    "gn:feature_class":"P",
    "gn:feature_code":"PPL",
    "gn:name":"Naranjal",
    "gn:population":0,
    "gn:timezone":"America/Bogota",
    "iso:country":"CO",
    "name:ceb_x_preferred":[
        "Naranjal"
    ],
    "name:deu_x_preferred":[
        "Naranjal"
    ],
    "name:pol_x_preferred":[
        "Naranjal"
    ],
    "name:spa_x_preferred":[
        "Naranjal"
    ],
    "name:swe_x_preferred":[
        "Naranjal"
    ],
    "wof:name":"Naranjal",
    "wof:placetype":"locality"
},
  "geometry": {"coordinates":[-75.50668,5.76344],"type":"Point"}
}