{
  "type": "Feature",
  "properties": {
    "gn:admin1_code":"17.0",
    "gn:admin2_code":"44560.0",
    "gn:asciiname":"Tucupao",
    "gn:country_code":"CO",
    "gn:dem":7,
    "gn:feature_class":"P",
    "gn:feature_code":"PPL",
    "gn:name":"Tucupao",
    "gn:population":0,
    "gn:timezone":"America/Bogota",
    "iso:country":"CO",
    "wof:name":"Tucupao",
    "wof:placetype":"locality"
},
  "geometry": {"coordinates":[-72.83148,11.52131],"type":"Point"}
}