{
  "type": "Feature",
  "properties": {
    "gn:admin1_code":"38",
    "gn:admin2_code":"47058.0",
    "gn:asciiname":"Carretal",
    "gn:country_code":"CO",
    "gn:dem":152,
    "gn:feature_class":"P",
    "gn:feature_code":"PPL",
    "gn:name":"Carretal",
    "gn:population":0,
    "gn:timezone":"America/Bogota",
    "iso:country":"CO",
    "wof:name":"Carretal",
    "wof:placetype":"locality"
},
  "geometry": {"coordinates":[-74.18940000000001,9.87724],"type":"Point"}
}