{
  "type": "Feature",
  "properties": {
    "gn:admin1_code":"9",
    "gn:admin2_code":"19743.0",
    "gn:asciiname":"Comefiambre",
    "gn:country_code":"CO",
    "gn:dem":2157,
    "gn:feature_class":"P",
    "gn:feature_code":"PPL",
    "gn:name":"Comefiambre",
    "gn:population":0,
    "gn:timezone":"America/Bogota",
    "iso:country":"CO",
    "wof:name":"Comefiambre",
    "wof:placetype":"locality"
},
  "geometry": {"coordinates":[-76.48333000000002,2.71667],"type":"Point"}
}