{
  "type": "Feature",
  "properties": {
    "gn:admin1_code":"32",
    "gn:asciiname":"Cantaclaro",
    "gn:country_code":"CO",
    "gn:dem":172,
    "gn:feature_class":"P",
    "gn:feature_code":"PPL",
    "gn:name":"Cantaclaro",
    "gn:population":0,
    "gn:timezone":"America/Bogota",
    "iso:country":"CO",
    "wof:name":"Cantaclaro",
    "wof:placetype":"locality"
},
  "geometry": {"coordinates":[-72.79781,4.39696],"type":"Point"}
}