{
  "type": "Feature",
  "properties": {
    "gn:admin1_code":"2.0",
    "gn:admin2_code":"5088.0",
    "gn:asciiname":"Los Alpes",
    "gn:country_code":"CO",
    "gn:dem":2455,
    "gn:feature_class":"P",
    "gn:feature_code":"PPL",
    "gn:name":"Los Alpes",
    "gn:population":0,
    "gn:timezone":"America/Bogota",
    "iso:country":"CO",
    "name:spa_x_preferred":[
        "Los Alpes"
    ],
    "wof:name":"Los Alpes",
    "wof:placetype":"locality"
},
  "geometry": {"coordinates":[-75.6104,6.3573],"type":"Point"}
}