{
  "type": "Feature",
  "properties": {
    "gn:admin1_code":"28",
    "gn:admin2_code":"73873",
    "gn:asciiname":"Pueblo Azul",
    "gn:country_code":"CO",
    "gn:dem":1165,
    "gn:feature_class":"P",
    "gn:feature_code":"PPL",
    "gn:name":"Pueblo Azul",
    "gn:population":0,
    "gn:timezone":"America/Bogota",
    "iso:country":"CO",
    "name:spa_x_preferred":[
        "Pueblo Azul"
    ],
    "wof:name":"Pueblo Azul",
    "wof:placetype":"locality"
},
  "geometry": {"coordinates":[-74.69539,3.87171],"type":"Point"}
}