{
  "type": "Feature",
  "properties": {
    "gn:admin1_code":"9.0",
    "gn:admin2_code":"19142.0",
    "gn:asciiname":"Quintero",
    "gn:country_code":"CO",
    "gn:dem":977,
    "gn:feature_class":"P",
    "gn:feature_code":"PPL",
    "gn:name":"Quintero",
    "gn:population":0,
    "gn:timezone":"America/Bogota",
    "iso:country":"CO",
    "name:ast_x_preferred":[
        "Quinteru"
    ],
    "name:ceb_x_preferred":[
        "Quintero"
    ],
    "name:eus_x_preferred":[
        "Quintero"
    ],
    "name:fas_x_preferred":[
        "\u06a9\u06cc\u0646\u062a\u0631\u0648"
    ],
    "name:fra_x_preferred":[
        "Quintero"
    ],
    "name:ita_x_preferred":[
        "Quintero"
    ],
    "name:kor_x_preferred":[
        "\ud0a8\ud14c\ub85c"
    ],
    "name:nld_x_preferred":[
        "Quintero"
    ],
    "name:pol_x_preferred":[
        "Quintero"
    ],
    "name:por_x_preferred":[
        "Quintero"
    ],
    "name:ron_x_preferred":[
        "Quintero"
    ],
    "name:rus_x_preferred":[
        "\u041a\u0438\u043d\u0442\u0435\u0440\u043e"
    ],
    "name:spa_x_preferred":[
        "Quintero"
    ],
    "name:swe_x_preferred":[
        "Quintero"
    ],
    "name:zho_x_preferred":[
        "\u91d1\u7279\u7f85"
    ],
    "wof:name":"Quintero",
    "wof:placetype":"locality"
},
  "geometry": {"coordinates":[-76.43843000000003,3.15433],"type":"Point"}
}