{
  "type": "Feature",
  "properties": {
    "gn:admin1_code":"38",
    "gn:admin2_code":"47460.0",
    "gn:asciiname":"Las Palmitas",
    "gn:country_code":"CO",
    "gn:dem":139,
    "gn:feature_class":"P",
    "gn:feature_code":"PPL",
    "gn:name":"Las Palmitas",
    "gn:population":0,
    "gn:timezone":"America/Bogota",
    "iso:country":"CO",
    "name:ceb_x_preferred":[
        "Las Palmitas"
    ],
    "name:ita_x_preferred":[
        "Las Palmitas"
    ],
    "name:spa_x_preferred":[
        "Las Palmitas"
    ],
    "name:srp_x_preferred":[
        "\u041b\u0430\u0441 \u041f\u0430\u043b\u043c\u0438\u0442\u0430\u0441"
    ],
    "name:swe_x_preferred":[
        "Las Palmitas"
    ],
    "name:und_x_variant":[
        "Hacienda Las Palmitas",
        "Las Palmitas"
    ],
    "wof:name":"Las Palmitas",
    "wof:placetype":"locality"
},
  "geometry": {"coordinates":[-74.38148000000002,9.93],"type":"Point"}
}