{
  "type": "Feature",
  "properties": {
    "gn:admin1_code":"26",
    "gn:admin2_code":"68176.0",
    "gn:asciiname":"Santa Rita",
    "gn:country_code":"CO",
    "gn:dem":1317,
    "gn:feature_class":"P",
    "gn:feature_code":"PPL",
    "gn:name":"Santa Rita",
    "gn:population":0,
    "gn:timezone":"America/Bogota",
    "iso:country":"CO",
    "wof:name":"Santa Rita",
    "wof:placetype":"locality"
},
  "geometry": {"coordinates":[-73.39315000000001,6.36519],"type":"Point"}
}