{
  "type": "Feature",
  "properties": {
    "gn:admin1_code":"19",
    "gn:admin2_code":"50223",
    "gn:asciiname":"Mata Azul",
    "gn:country_code":"CO",
    "gn:dem":517,
    "gn:feature_class":"P",
    "gn:feature_code":"PPL",
    "gn:name":"Mata Azul",
    "gn:population":0,
    "gn:timezone":"America/Bogota",
    "iso:country":"CO",
    "name:spa_x_preferred":[
        "Mata Azul"
    ],
    "wof:name":"Mata Azul",
    "wof:placetype":"locality"
},
  "geometry": {"coordinates":[-73.79241999999998,3.76575],"type":"Point"}
}