{
  "type": "Feature",
  "properties": {
    "gn:admin1_code":"26",
    "gn:admin2_code":"68152.0",
    "gn:asciiname":"El Tobal",
    "gn:cc2":"CO",
    "gn:country_code":"CO",
    "gn:dem":3696,
    "gn:feature_class":"P",
    "gn:feature_code":"PPL",
    "gn:name":"El Tobal",
    "gn:population":0,
    "gn:timezone":"America/Bogota",
    "iso:country":"CO",
    "name:und_x_variant":[
        "Tobal",
        "El Tobal"
    ],
    "wof:name":"El Tobal",
    "wof:placetype":"locality"
},
  "geometry": {"coordinates":[-72.55,6.71667],"type":"Point"}
}