{
  "type": "Feature",
  "properties": {
    "gn:admin1_code":"2",
    "gn:admin2_code":"5579.0",
    "gn:asciiname":"Estacion Sabaletas",
    "gn:country_code":"CO",
    "gn:dem":371,
    "gn:feature_class":"P",
    "gn:feature_code":"PPL",
    "gn:name":"Estaci\u00f3n Sabaletas",
    "gn:population":0,
    "gn:timezone":"America/Bogota",
    "iso:country":"CO",
    "wof:name":"Estacion Sabaletas",
    "wof:placetype":"locality"
},
  "geometry": {"coordinates":[-74.60028,6.39806],"type":"Point"}
}