{
  "type": "Feature",
  "properties": {
    "gn:admin1_code":"17",
    "gn:admin2_code":"44001.0",
    "gn:asciiname":"El Paso",
    "gn:country_code":"CO",
    "gn:dem":14,
    "gn:feature_class":"P",
    "gn:feature_code":"PPL",
    "gn:name":"El Paso",
    "gn:population":0,
    "gn:timezone":"America/Bogota",
    "iso:country":"CO",
    "wof:name":"El Paso",
    "wof:placetype":"locality"
},
  "geometry": {"coordinates":[-72.86778000000002,11.49917],"type":"Point"}
}