{
  "type": "Feature",
  "properties": {
    "gn:admin1_code":"36",
    "gn:admin2_code":"15469.0",
    "gn:asciiname":"Cartagena",
    "gn:country_code":"CO",
    "gn:dem":1747,
    "gn:feature_class":"P",
    "gn:feature_code":"PPL",
    "gn:name":"Cartagena",
    "gn:population":0,
    "gn:timezone":"America/Bogota",
    "iso:country":"CO",
    "wof:name":"Cartagena",
    "wof:placetype":"locality"
},
  "geometry": {"coordinates":[-73.57778,5.82417],"type":"Point"}
}