{
  "type": "Feature",
  "properties": {
    "gn:admin1_code":"21",
    "gn:admin2_code":"54498.0",
    "gn:asciiname":"Libelu",
    "gn:country_code":"CO",
    "gn:dem":1178,
    "gn:feature_class":"P",
    "gn:feature_code":"PPL",
    "gn:name":"Libel\u00fa",
    "gn:population":0,
    "gn:timezone":"America/Bogota",
    "iso:country":"CO",
    "wof:name":"Libelu",
    "wof:placetype":"locality"
},
  "geometry": {"coordinates":[-73.33333,8.28333],"type":"Point"}
}