{
  "type": "Feature",
  "properties": {
    "gn:admin1_code":"35",
    "gn:asciiname":"Tierra Firme",
    "gn:country_code":"CO",
    "gn:dem":24,
    "gn:feature_class":"P",
    "gn:feature_code":"PPL",
    "gn:name":"Tierra Firme",
    "gn:population":0,
    "gn:timezone":"America/Bogota",
    "iso:country":"CO",
    "name:nor_x_preferred":[
        "Tierra Firme"
    ],
    "name:spa_x_preferred":[
        "Tierra firme"
    ],
    "wof:name":"Tierra Firme",
    "wof:placetype":"locality"
},
  "geometry": {"coordinates":[-74.39690999999998,9.22995],"type":"Point"}
}