{
  "type": "Feature",
  "properties": {
    "gn:admin1_code":"22.0",
    "gn:admin2_code":"86320.0",
    "gn:asciiname":"San Antonio del Guamues",
    "gn:country_code":"CO",
    "gn:dem":305,
    "gn:feature_class":"P",
    "gn:feature_code":"PPL",
    "gn:name":"San Antonio del Guamu\u00e9s",
    "gn:population":0,
    "gn:timezone":"America/Bogota",
    "iso:country":"CO",
    "name:eng_x_preferred":[
        "San Antonio del Guamues"
    ],
    "wof:name":"San Antonio del Guamues",
    "wof:placetype":"locality"
},
  "geometry": {"coordinates":[-76.83327,0.56235],"type":"Point"}
}