{
  "type": "Feature",
  "properties": {
    "gn:admin1_code":"9.0",
    "gn:admin2_code":"19824.0",
    "gn:asciiname":"Hacienda Los Chorros",
    "gn:country_code":"CO",
    "gn:dem":3204,
    "gn:feature_class":"P",
    "gn:feature_code":"PPL",
    "gn:name":"Hacienda Los Chorros",
    "gn:population":0,
    "gn:timezone":"America/Bogota",
    "iso:country":"CO",
    "name:spa_x_preferred":[
        "Hacienda Los Chorros"
    ],
    "wof:name":"Hacienda Los Chorros",
    "wof:placetype":"locality"
},
  "geometry": {"coordinates":[-76.29894,2.53559],"type":"Point"}
}