{
  "type": "Feature",
  "properties": {
    "gn:admin1_code":"4",
    "gn:admin2_code":"8685.0",
    "gn:asciiname":"Mapuro",
    "gn:country_code":"CO",
    "gn:dem":50,
    "gn:feature_class":"P",
    "gn:feature_code":"PPL",
    "gn:name":"Mapuro",
    "gn:population":0,
    "gn:timezone":"America/Bogota",
    "iso:country":"CO",
    "wof:name":"Mapuro",
    "wof:placetype":"locality"
},
  "geometry": {"coordinates":[-74.83333,10.73333],"type":"Point"}
}