{
  "type": "Feature",
  "properties": {
    "gn:admin1_code":"16.0",
    "gn:admin2_code":"41013.0",
    "gn:asciiname":"La Trina",
    "gn:country_code":"CO",
    "gn:dem":689,
    "gn:feature_class":"P",
    "gn:feature_code":"PPL",
    "gn:name":"La Trina",
    "gn:population":0,
    "gn:timezone":"America/Bogota",
    "iso:country":"CO",
    "wof:name":"La Trina",
    "wof:placetype":"locality"
},
  "geometry": {"coordinates":[-75.65278000000001,2.30083],"type":"Point"}
}