{
  "type": "Feature",
  "properties": {
    "gn:admin1_code":"26.0",
    "gn:admin2_code":"68684.0",
    "gn:asciiname":"Totumo",
    "gn:country_code":"CO",
    "gn:dem":1105,
    "gn:feature_class":"P",
    "gn:feature_code":"PPL",
    "gn:name":"Totumo",
    "gn:population":0,
    "gn:timezone":"America/Bogota",
    "iso:country":"CO",
    "wof:name":"Totumo",
    "wof:placetype":"locality"
},
  "geometry": {"coordinates":[-72.73333000000002,6.56667],"type":"Point"}
}