{
  "type": "Feature",
  "properties": {
    "iso:country":"CO",
    "name:ceb_x_preferred":[
        "Sabana de Torres"
    ],
    "name:deu_x_preferred":[
        "Sabana de Torres"
    ],
    "name:eng_x_preferred":[
        "Sabana de Torres"
    ],
    "name:fas_x_preferred":[
        "\u0633\u0627\u0628\u0627\u0646\u0627 \u062f \u062a\u0648\u0631\u0633"
    ],
    "name:fra_x_preferred":[
        "Sabana de Torres"
    ],
    "name:ita_x_preferred":[
        "Sabana de Torres"
    ],
    "name:jpn_x_preferred":[
        "\u30b5\u30d0\u30ca\u30fb\u30c7\u30fb\u30c8\u30ec\u30b9"
    ],
    "name:kat_x_preferred":[
        "\u10e1\u10d0\u10d1\u10d0\u10dc\u10d0-\u10d3\u10d4-\u10e2\u10dd\u10e0\u10d4\u10e1\u10d8"
    ],
    "name:msa_x_preferred":[
        "Sabana de Torres"
    ],
    "name:nan_x_preferred":[
        "Sabana de Torres"
    ],
    "name:nld_x_preferred":[
        "Sabana de Torres"
    ],
    "name:rus_x_preferred":[
        "\u0421\u0430\u0431\u0430\u043d\u0430-\u0434\u0435-\u0422\u043e\u0440\u0440\u0435\u0441"
    ],
    "name:spa_x_preferred":[
        "Sabana de Torres"
    ],
    "name:swe_x_preferred":[
        "Sabana de Torres"
    ],
    "name:tgl_x_preferred":[
        "Sabana de Torres"
    ],
    "name:urd_x_preferred":[
        "\u0633\u0628\u0627\u0646\u06c1 \u062f\u06d2 \u062a\u0648\u0631\u0631\u06cc\u0633"
    ],
    "name:vie_x_preferred":[
        "Sabana de Torres"
    ],
    "name:war_x_preferred":[
        "Sabana de Torres"
    ],
    "name:zho_min_nan_x_preferred":[
        "Sabana de Torres"
    ],
    "name:zho_x_preferred":[
        "\u85a9\u74e6\u7d0d\u5fb7\u6258\u96f7\u65af"
    ],
    "qs:gn_country":"CO",
    "qs:gn_fcode":"PPL",
    "qs:gn_pop":11291,
    "qs:name":"Sabana de Torres",
    "qs:name_adm0":"Colombia",
    "qs:name_adm1":"Santander",
    "qs:photos":0,
    "qs:photos_1k":0,
    "qs:photos_9k":1,
    "qs:photos_9r":1,
    "qs:photos_all":1,
    "qs:photos_sr":0,
    "qs:placetype":"Town",
    "qs:pop_sr":"6",
    "qs:woe_adm0":23424787,
    "wd:wordcount":32,
    "wof:name":"Sabana de Torres",
    "wof:placetype":"locality",
    "wof:population":11291
},
  "geometry": {"coordinates":[-73.49574,7.3915],"type":"Point"}
}