{
  "type": "Feature",
  "properties": {
    "iso:country":"CO",
    "name:chi_x_preferred":[
        "\u4ea8\u8afe\u74e6"
    ],
    "name:dut_x_preferred":[
        "G\u00e9nova"
    ],
    "name:eng_x_preferred":[
        "G\u00e9nova"
    ],
    "name:fre_x_preferred":[
        "G\u00e9nova"
    ],
    "name:geo_x_preferred":[
        "\u10ee\u10d4\u10dc\u10dd\u10d5\u10dd"
    ],
    "name:ger_x_preferred":[
        "G\u00e9nova"
    ],
    "name:ita_x_preferred":[
        "G\u00e9nova"
    ],
    "name:jpn_x_preferred":[
        "\u30d8\u30ce\u30d0"
    ],
    "name:may_x_preferred":[
        "Genova"
    ],
    "name:nan_x_preferred":[
        "G\u00e9nova"
    ],
    "name:rus_x_preferred":[
        "\u0425\u0435\u043d\u043e\u0432\u0430"
    ],
    "name:spa_x_preferred":[
        "G\u00e9nova"
    ],
    "name:swe_x_preferred":[
        "G\u00e9nova"
    ],
    "name:tgl_x_preferred":[
        "G\u00e9nova"
    ],
    "name:war_x_preferred":[
        "G\u00e9nova"
    ],
    "qs:gn_country":"CO",
    "qs:gn_fcode":"PPL",
    "qs:gn_pop":7140,
    "qs:name":"Genova",
    "qs:name_adm0":"Colombia",
    "qs:name_adm1":"Quindio",
    "qs:photos":0,
    "qs:photos_1k":0,
    "qs:photos_9k":1,
    "qs:photos_9r":1,
    "qs:photos_all":2,
    "qs:photos_sr":0,
    "qs:placetype":"Town",
    "qs:pop_sr":"5",
    "qs:woe_adm0":23424787,
    "wof:name":"Genova",
    "wof:placetype":"locality",
    "wof:population":7140
},
  "geometry": {"coordinates":[-75.76667,4.31667],"type":"Point"}
}