{
  "type": "Feature",
  "properties": {
    "iso:country":"CO",
    "name:ast_x_preferred":[
        "G\u00e9nova"
    ],
    "name:avk_x_preferred":[
        "G\u00e9nova"
    ],
    "name:ben_x_preferred":[
        "\u099c\u09c7\u09a8\u09cb\u09ad\u09be"
    ],
    "name:cat_x_preferred":[
        "G\u00e8nova"
    ],
    "name:ceb_x_preferred":[
        "G\u00e9nova"
    ],
    "name:dan_x_preferred":[
        "G\u00e9nova"
    ],
    "name:deu_x_preferred":[
        "G\u00e9nova"
    ],
    "name:eng_x_preferred":[
        "G\u00e9nova"
    ],
    "name:fas_x_preferred":[
        "\u062e\u0646\u0648\u0627"
    ],
    "name:fra_x_preferred":[
        "G\u00e9nova"
    ],
    "name:gle_x_preferred":[
        "G\u00e9nova"
    ],
    "name:ita_x_preferred":[
        "G\u00e9nova"
    ],
    "name:jpn_x_preferred":[
        "\u30d8\u30ce\u30d0"
    ],
    "name:kat_x_preferred":[
        "\u10ee\u10d4\u10dc\u10dd\u10d5\u10dd"
    ],
    "name:msa_x_preferred":[
        "Genova"
    ],
    "name:nan_x_preferred":[
        "G\u00e9nova"
    ],
    "name:nld_x_preferred":[
        "G\u00e9nova"
    ],
    "name:pol_x_preferred":[
        "G\u00e9nova"
    ],
    "name:rus_x_preferred":[
        "\u0425\u0435\u043d\u043e\u0432\u0430"
    ],
    "name:spa_x_preferred":[
        "G\u00e9nova"
    ],
    "name:swe_x_preferred":[
        "G\u00e9nova"
    ],
    "name:tgl_x_preferred":[
        "G\u00e9nova"
    ],
    "name:ukr_x_preferred":[
        "\u0425\u0435\u043d\u043e\u0432\u0430"
    ],
    "name:war_x_preferred":[
        "G\u00e9nova"
    ],
    "name:zho_x_preferred":[
        "\u4ea8\u8afe\u74e6"
    ],
    "qs:gn_country":"CO",
    "qs:gn_fcode":"PPL",
    "qs:gn_pop":7140,
    "qs:name":"Genova",
    "qs:name_adm0":"Colombia",
    "qs:name_adm1":"Quindio",
    "qs:photos":0,
    "qs:photos_1k":0,
    "qs:photos_9k":1,
    "qs:photos_9r":1,
    "qs:photos_all":2,
    "qs:photos_sr":0,
    "qs:placetype":"Town",
    "qs:pop_sr":"5",
    "qs:woe_adm0":23424787,
    "wof:name":"Genova",
    "wof:placetype":"locality",
    "wof:population":7140
},
  "geometry": {"coordinates":[-75.76667,4.31667],"type":"Point"}
}