{
  "type": "Feature",
  "properties": {
    "gn:admin1_code":"26",
    "gn:admin2_code":"68324.0",
    "gn:asciiname":"Poppa Norte",
    "gn:country_code":"CO",
    "gn:dem":1693,
    "gn:feature_class":"P",
    "gn:feature_code":"PPL",
    "gn:name":"Poppa Norte",
    "gn:population":0,
    "gn:timezone":"America/Bogota",
    "iso:country":"CO",
    "wof:name":"Poppa Norte",
    "wof:placetype":"locality"
},
  "geometry": {"coordinates":[-73.70333000000002,5.90056],"type":"Point"}
}