{
  "type": "Feature",
  "properties": {
    "gn:admin1_code":"2",
    "gn:admin2_code":"5234.0",
    "gn:asciiname":"Armenia",
    "gn:country_code":"CO",
    "gn:dem":1546,
    "gn:feature_class":"P",
    "gn:feature_code":"PPL",
    "gn:name":"Armenia",
    "gn:population":0,
    "gn:timezone":"America/Bogota",
    "iso:country":"CO",
    "name:und_x_variant":[
        "Camparrusia",
        "Armenia"
    ],
    "wof:name":"Armenia",
    "wof:placetype":"locality"
},
  "geometry": {"coordinates":[-76.03416,7.00631],"type":"Point"}
}