{
  "type": "Feature",
  "properties": {
    "gn:admin1_code":"26",
    "gn:admin2_code":"68655.0",
    "gn:asciiname":"El Chorro",
    "gn:country_code":"CO",
    "gn:dem":161,
    "gn:feature_class":"P",
    "gn:feature_code":"PPL",
    "gn:name":"El Chorro",
    "gn:population":0,
    "gn:timezone":"America/Bogota",
    "iso:country":"CO",
    "name:ceb_x_preferred":[
        "El Chorro"
    ],
    "name:dan_x_preferred":[
        "El Chorro"
    ],
    "name:epo_x_preferred":[
        "El Chorro"
    ],
    "name:eus_x_preferred":[
        "El Chorro"
    ],
    "name:fra_x_preferred":[
        "El Chorro"
    ],
    "name:glg_x_preferred":[
        "El Chorro"
    ],
    "name:hat_x_preferred":[
        "El Chorro"
    ],
    "name:nld_x_preferred":[
        "El Chorro"
    ],
    "name:pol_x_preferred":[
        "El Chorro"
    ],
    "name:spa_x_preferred":[
        "El Chorro"
    ],
    "name:swe_x_preferred":[
        "El Chorro"
    ],
    "wof:name":"El Chorro",
    "wof:placetype":"locality"
},
  "geometry": {"coordinates":[-73.49639000000001,7.30139],"type":"Point"}
}