{
  "type": "Feature",
  "properties": {
    "gn:admin1_code":"8.0",
    "gn:admin2_code":"18150.0",
    "gn:asciiname":"La Bocana",
    "gn:country_code":"CO",
    "gn:dem":210,
    "gn:feature_class":"P",
    "gn:feature_code":"PPL",
    "gn:name":"La Bocana",
    "gn:population":0,
    "gn:timezone":"America/Bogota",
    "iso:country":"CO",
    "wof:name":"La Bocana",
    "wof:placetype":"locality"
},
  "geometry": {"coordinates":[-74.82477,1.37732],"type":"Point"}
}