{
  "type": "Feature",
  "properties": {
    "gn:admin1_code":"36",
    "gn:admin2_code":"15176.0",
    "gn:asciiname":"El Recuerdo",
    "gn:country_code":"CO",
    "gn:dem":2798,
    "gn:feature_class":"P",
    "gn:feature_code":"PPL",
    "gn:name":"El Recuerdo",
    "gn:population":0,
    "gn:timezone":"America/Bogota",
    "iso:country":"CO",
    "wof:name":"El Recuerdo",
    "wof:placetype":"locality"
},
  "geometry": {"coordinates":[-73.71778,5.63167],"type":"Point"}
}