{
  "type": "Feature",
  "properties": {
    "gn:country":"CO",
    "gn:fcode":"PPL",
    "gn:pop":4767,
    "iso:country":"CO",
    "name:eng_x_preferred":[
        "Simijac\u00e1"
    ],
    "name:fra_x_preferred":[
        "Simijaca"
    ],
    "name:ita_x_preferred":[
        "Simijaca"
    ],
    "name:kat_x_preferred":[
        "\u10e1\u10d8\u10db\u10d8\u10ee\u10d0\u10d9\u10d0"
    ],
    "name:msa_x_preferred":[
        "Simijac\u00e1"
    ],
    "name:nan_x_preferred":[
        "Simijaca"
    ],
    "name:nld_x_preferred":[
        "Simijaca"
    ],
    "name:sco_x_preferred":[
        "Simijac\u00e1"
    ],
    "name:spa_x_preferred":[
        "Simijaca"
    ],
    "name:swe_x_preferred":[
        "Simijaca"
    ],
    "name:tgl_x_preferred":[
        "Simijac\u00e1"
    ],
    "name:vie_x_preferred":[
        "Simijaca"
    ],
    "name:war_x_preferred":[
        "Simijac\u00e1"
    ],
    "name:zho_x_preferred":[
        "\u932b\u7c73\u54c8\u5361"
    ],
    "qs:name":"Simijaca",
    "qs:photos_9r":0,
    "qs:photos_sr":0,
    "qs:pop_sr":"4",
    "wd:wordcount":313,
    "wof:name":"Simijaca",
    "wof:placetype":"locality",
    "wof:population":4767
},
  "geometry": {"coordinates":[-73.85227,5.50291],"type":"Point"}
}