{
  "type": "Feature",
  "properties": {
    "gn:admin1_code":"16.0",
    "gn:admin2_code":"41518.0",
    "gn:asciiname":"Los Cauchos",
    "gn:country_code":"CO",
    "gn:dem":1244,
    "gn:feature_class":"P",
    "gn:feature_code":"PPL",
    "gn:name":"Los Cauchos",
    "gn:population":0,
    "gn:timezone":"America/Bogota",
    "iso:country":"CO",
    "wof:name":"Los Cauchos",
    "wof:placetype":"locality"
},
  "geometry": {"coordinates":[-75.70583000000001,2.35833],"type":"Point"}
}