{
  "type": "Feature",
  "properties": {
    "gn:admin1_code":"2.0",
    "gn:admin2_code":"5490.0",
    "gn:asciiname":"El Deseo",
    "gn:country_code":"CO",
    "gn:dem":44,
    "gn:feature_class":"P",
    "gn:feature_code":"PPL",
    "gn:name":"El Deseo",
    "gn:population":0,
    "gn:timezone":"America/Bogota",
    "iso:country":"CO",
    "name:deu_x_preferred":[
        "El Deseo"
    ],
    "name:fra_x_preferred":[
        "El Deseo"
    ],
    "name:heb_x_preferred":[
        "\u05d0\u05dc \u05d3\u05e1\u05d0\u05d5"
    ],
    "name:ita_x_preferred":[
        "El Deseo"
    ],
    "name:kat_x_preferred":[
        "El Deseo"
    ],
    "name:nld_x_preferred":[
        "El Deseo"
    ],
    "name:spa_x_preferred":[
        "El Deseo"
    ],
    "name:ukr_x_preferred":[
        "El Deseo"
    ],
    "wof:name":"El Deseo",
    "wof:placetype":"locality"
},
  "geometry": {"coordinates":[-76.81303,8.51666],"type":"Point"}
}