{
  "type": "Feature",
  "properties": {
    "gn:admin1_code":"10",
    "gn:admin2_code":"20250.0",
    "gn:asciiname":"Matepalma",
    "gn:country_code":"CO",
    "gn:dem":36,
    "gn:feature_class":"P",
    "gn:feature_code":"PPL",
    "gn:name":"Matepalma",
    "gn:population":0,
    "gn:timezone":"America/Bogota",
    "iso:country":"CO",
    "wof:name":"Matepalma",
    "wof:placetype":"locality"
},
  "geometry": {"coordinates":[-73.66667,9.55],"type":"Point"}
}