{
  "type": "Feature",
  "properties": {
    "gn:admin1_code":"8.0",
    "gn:admin2_code":"18479.0",
    "gn:asciiname":"El Trapiche",
    "gn:country_code":"CO",
    "gn:dem":228,
    "gn:feature_class":"P",
    "gn:feature_code":"PPL",
    "gn:name":"El Trapiche",
    "gn:population":0,
    "gn:timezone":"America/Bogota",
    "iso:country":"CO",
    "name:spa_x_preferred":[
        "El Trapiche"
    ],
    "wof:name":"El Trapiche",
    "wof:placetype":"locality"
},
  "geometry": {"coordinates":[-75.65555999999999,1.26036],"type":"Point"}
}