{
  "type": "Feature",
  "properties": {
    "gn:admin1_code":"20",
    "gn:admin2_code":"52405.0",
    "gn:asciiname":"El Cajeto",
    "gn:country_code":"CO",
    "gn:dem":2002,
    "gn:feature_class":"P",
    "gn:feature_code":"PPL",
    "gn:name":"El Cajeto",
    "gn:population":0,
    "gn:timezone":"America/Bogota",
    "iso:country":"CO",
    "wof:name":"El Cajeto",
    "wof:placetype":"locality"
},
  "geometry": {"coordinates":[-77.42,1.92306],"type":"Point"}
}