{
  "type": "Feature",
  "properties": {
    "gn:admin1_code":"27.0",
    "gn:admin2_code":"70265.0",
    "gn:asciiname":"Villa Raquel",
    "gn:country_code":"CO",
    "gn:dem":23,
    "gn:feature_class":"P",
    "gn:feature_code":"PPL",
    "gn:name":"Villa Raquel",
    "gn:population":0,
    "gn:timezone":"America/Bogota",
    "iso:country":"CO",
    "wof:name":"Villa Raquel",
    "wof:placetype":"locality"
},
  "geometry": {"coordinates":[-74.74191,8.35396],"type":"Point"}
}