{
  "type": "Feature",
  "properties": {
    "gn:admin1_code":"24",
    "gn:admin2_code":"66687.0",
    "gn:asciiname":"La Despensa",
    "gn:country_code":"CO",
    "gn:dem":1625,
    "gn:feature_class":"P",
    "gn:feature_code":"PPL",
    "gn:name":"La Despensa",
    "gn:population":0,
    "gn:timezone":"America/Bogota",
    "iso:country":"CO",
    "wof:name":"La Despensa",
    "wof:placetype":"locality"
},
  "geometry": {"coordinates":[-75.96611,5.02306],"type":"Point"}
}