{
  "type": "Feature",
  "properties": {
    "iso:country":"CO",
    "name:ast_x_preferred":[
        "San Rafael"
    ],
    "name:ceb_x_preferred":[
        "San Rafael"
    ],
    "name:eng_x_preferred":[
        "San Rafael"
    ],
    "name:fra_x_preferred":[
        "San Rafael"
    ],
    "name:ile_x_preferred":[
        "San Rafael"
    ],
    "name:ilo_x_preferred":[
        "San Rafael"
    ],
    "name:ita_x_preferred":[
        "San Rafael"
    ],
    "name:kat_x_preferred":[
        "\u10e1\u10d0\u10dc-\u10e0\u10d0\u10e4\u10d0\u10d4\u10da\u10d8"
    ],
    "name:msa_x_preferred":[
        "San Rafael"
    ],
    "name:nan_x_preferred":[
        "San Rafael"
    ],
    "name:nld_x_preferred":[
        "San Rafael"
    ],
    "name:por_x_preferred":[
        "San Rafael"
    ],
    "name:ron_x_preferred":[
        "San Rafael"
    ],
    "name:rus_x_preferred":[
        "\u0421\u0430\u043d-\u0420\u0430\u0444\u0430\u044d\u043b\u044c"
    ],
    "name:sco_x_preferred":[
        "San Rafael"
    ],
    "name:spa_x_preferred":[
        "San Rafael"
    ],
    "name:swe_x_preferred":[
        "San Rafael"
    ],
    "name:tgl_x_preferred":[
        "San Rafael"
    ],
    "name:war_x_preferred":[
        "San Rafael"
    ],
    "name:zho_x_preferred":[
        "\u8056\u62c9\u6590\u723e"
    ],
    "qs:gn_country":"CO",
    "qs:gn_fcode":"PPL",
    "qs:gn_pop":7245,
    "qs:name":"San Rafael",
    "qs:name_adm0":"Colombia",
    "qs:name_adm1":"Antioquia",
    "qs:photos":67,
    "qs:photos_1k":14,
    "qs:photos_9k":1,
    "qs:photos_9r":2,
    "qs:photos_all":67,
    "qs:photos_sr":2,
    "qs:placetype":"Town",
    "qs:pop_sr":"5",
    "qs:woe_adm0":23424787,
    "wof:name":"San Rafael",
    "wof:placetype":"locality",
    "wof:population":7245
},
  "geometry": {"coordinates":[-75.02589,6.29436],"type":"Point"}
}