{
  "type": "Feature",
  "properties": {
    "iso:country":"CO",
    "name:ara_x_preferred":[
        "\u0633\u0627\u0646 \u0631\u0627\u0641\u0627\u0626\u064a\u0644"
    ],
    "name:ast_x_preferred":[
        "San Rafael"
    ],
    "name:ben_x_preferred":[
        "\u09b8\u09be\u09a8 \u09b0\u09be\u09ab\u09be\u09df\u09c7\u09b2"
    ],
    "name:ceb_x_preferred":[
        "San Rafael"
    ],
    "name:ell_x_preferred":[
        "\u03a3\u03b1\u03bd \u03a1\u03b1\u03c6\u03b1\u03ad\u03bb"
    ],
    "name:eng_x_preferred":[
        "San Rafael"
    ],
    "name:fra_x_preferred":[
        "San Rafael"
    ],
    "name:heb_x_preferred":[
        "\u05e1\u05df \u05e8\u05e4\u05d0\u05dc"
    ],
    "name:hin_x_preferred":[
        "\u0938\u0948\u0928 \u0930\u093e\u092b\u093c\u0947\u0932"
    ],
    "name:hun_x_preferred":[
        "San Rafael"
    ],
    "name:ile_x_preferred":[
        "San Rafael"
    ],
    "name:ilo_x_preferred":[
        "San Rafael"
    ],
    "name:ind_x_preferred":[
        "San Rafael"
    ],
    "name:ita_x_preferred":[
        "San Rafael"
    ],
    "name:jpn_x_preferred":[
        "\u30b5\u30f3\u30e9\u30d5\u30a1\u30a8\u30eb"
    ],
    "name:kat_x_preferred":[
        "\u10e1\u10d0\u10dc-\u10e0\u10d0\u10e4\u10d0\u10d4\u10da\u10d8"
    ],
    "name:kor_x_preferred":[
        "\uc0b0 \ub77c\ud30c\uc5d8"
    ],
    "name:msa_x_preferred":[
        "San Rafael"
    ],
    "name:nan_x_preferred":[
        "San Rafael"
    ],
    "name:nld_x_preferred":[
        "San Rafael"
    ],
    "name:por_x_preferred":[
        "San Rafael"
    ],
    "name:ron_x_preferred":[
        "San Rafael"
    ],
    "name:rus_x_preferred":[
        "\u0421\u0430\u043d-\u0420\u0430\u0444\u0430\u044d\u043b\u044c"
    ],
    "name:sco_x_preferred":[
        "San Rafael"
    ],
    "name:spa_x_preferred":[
        "San Rafael"
    ],
    "name:swe_x_preferred":[
        "San Rafael"
    ],
    "name:tgl_x_preferred":[
        "San Rafael"
    ],
    "name:tur_x_preferred":[
        "San Rafael"
    ],
    "name:ukr_x_preferred":[
        "\u0421\u0430\u043d-\u0420\u0430\u0444\u0430\u0435\u043b\u044c"
    ],
    "name:urd_x_preferred":[
        "\u0633\u0627\u0646 \u0631\u0627\u0641\u0627\u0626\u0644"
    ],
    "name:vie_x_preferred":[
        "San Rafael"
    ],
    "name:war_x_preferred":[
        "San Rafael"
    ],
    "name:zho_x_preferred":[
        "\u8056\u62c9\u6590\u723e"
    ],
    "qs:gn_country":"CO",
    "qs:gn_fcode":"PPL",
    "qs:gn_pop":7245,
    "qs:name":"San Rafael",
    "qs:name_adm0":"Colombia",
    "qs:name_adm1":"Antioquia",
    "qs:photos":67,
    "qs:photos_1k":14,
    "qs:photos_9k":1,
    "qs:photos_9r":2,
    "qs:photos_all":67,
    "qs:photos_sr":2,
    "qs:placetype":"Town",
    "qs:pop_sr":"5",
    "qs:woe_adm0":23424787,
    "wof:name":"San Rafael",
    "wof:placetype":"locality",
    "wof:population":7245
},
  "geometry": {"coordinates":[-75.02589,6.29436],"type":"Point"}
}