{
  "type": "Feature",
  "properties": {
    "gn:admin1_code":"19.0",
    "gn:admin2_code":"50689.0",
    "gn:asciiname":"La Marranera",
    "gn:country_code":"CO",
    "gn:dem":246,
    "gn:feature_class":"P",
    "gn:feature_code":"PPLL",
    "gn:name":"La Marranera",
    "gn:population":0,
    "gn:timezone":"America/Bogota",
    "iso:country":"CO",
    "name:spa_x_preferred":[
        "La Marranera"
    ],
    "wof:name":"La Marranera",
    "wof:placetype":"locality"
},
  "geometry": {"coordinates":[-73.35765000000001,3.68561],"type":"Point"}
}