{
  "type": "Feature",
  "properties": {
    "gn:admin1_code":"29.0",
    "gn:admin2_code":"76130.0",
    "gn:asciiname":"Hacienda Las Camelias",
    "gn:country_code":"CO",
    "gn:dem":964,
    "gn:feature_class":"P",
    "gn:feature_code":"PPL",
    "gn:name":"Hacienda Las Camelias",
    "gn:population":0,
    "gn:timezone":"America/Bogota",
    "iso:country":"CO",
    "name:spa_x_preferred":[
        "Hacienda Las Camelias"
    ],
    "wof:name":"Hacienda Las Camelias",
    "wof:placetype":"locality"
},
  "geometry": {"coordinates":[-76.41293,3.30743],"type":"Point"}
}