{
  "type": "Feature",
  "properties": {
    "gn:admin1_code":"28",
    "gn:admin2_code":"73675.0",
    "gn:asciiname":"La Puerquera",
    "gn:country_code":"CO",
    "gn:dem":1410,
    "gn:feature_class":"P",
    "gn:feature_code":"PPL",
    "gn:name":"La Puerquera",
    "gn:population":0,
    "gn:timezone":"America/Bogota",
    "iso:country":"CO",
    "wof:name":"La Puerquera",
    "wof:placetype":"locality"
},
  "geometry": {"coordinates":[-75.49167,4.01056],"type":"Point"}
}