{
  "type": "Feature",
  "properties": {
    "gn:admin1_code":"26",
    "gn:admin2_code":"68861.0",
    "gn:asciiname":"Lagunita",
    "gn:country_code":"CO",
    "gn:dem":2155,
    "gn:feature_class":"P",
    "gn:feature_code":"PPL",
    "gn:name":"Lagunita",
    "gn:population":0,
    "gn:timezone":"America/Bogota",
    "iso:country":"CO",
    "name:nld_x_preferred":[
        "Lagunita"
    ],
    "name:spa_x_preferred":[
        "Lagunita"
    ],
    "name:swe_x_preferred":[
        "Lagunita"
    ],
    "wof:name":"Lagunita",
    "wof:placetype":"locality"
},
  "geometry": {"coordinates":[-73.68324,5.99407],"type":"Point"}
}