{
  "type": "Feature",
  "properties": {
    "gn:admin1_code":"2",
    "gn:admin2_code":"5887.0",
    "gn:asciiname":"El Tabladito",
    "gn:country_code":"CO",
    "gn:dem":2506,
    "gn:feature_class":"P",
    "gn:feature_code":"PPL",
    "gn:name":"El Tabladito",
    "gn:population":0,
    "gn:timezone":"America/Bogota",
    "iso:country":"CO",
    "wof:name":"El Tabladito",
    "wof:placetype":"locality"
},
  "geometry": {"coordinates":[-75.56471999999999,7.00333],"type":"Point"}
}