{
  "type": "Feature",
  "properties": {
    "gn:admin1_code":"20.0",
    "gn:admin2_code":"52352.0",
    "gn:asciiname":"San Francisco",
    "gn:country_code":"CO",
    "gn:dem":2908,
    "gn:feature_class":"P",
    "gn:feature_code":"PPL",
    "gn:name":"San Francisco",
    "gn:population":0,
    "gn:timezone":"America/Bogota",
    "iso:country":"CO",
    "wof:name":"San Francisco",
    "wof:placetype":"locality"
},
  "geometry": {"coordinates":[-77.54829000000002,1.00165],"type":"Point"}
}