{
  "type": "Feature",
  "properties": {
    "gn:admin1_code":"3",
    "gn:admin2_code":"81736.0",
    "gn:asciiname":"Golondrinas",
    "gn:country_code":"CO",
    "gn:dem":181,
    "gn:feature_class":"P",
    "gn:feature_code":"PPL",
    "gn:name":"Golondrinas",
    "gn:population":0,
    "gn:timezone":"America/Caracas",
    "iso:country":"CO",
    "name:ceb_x_preferred":[
        "Golondrinas"
    ],
    "name:spa_x_preferred":[
        "Golondrinas"
    ],
    "name:srp_x_preferred":[
        "\u0413\u043e\u043b\u043e\u043d\u0434\u0440\u0438\u043d\u0430\u0441"
    ],
    "name:swe_x_preferred":[
        "Golondrinas"
    ],
    "wof:name":"Golondrinas",
    "wof:placetype":"locality"
},
  "geometry": {"coordinates":[-71.72516,7.05136],"type":"Point"}
}