{
  "type": "Feature",
  "properties": {
    "gn:admin1_code":"8.0",
    "gn:admin2_code":"18753.0",
    "gn:asciiname":"Troncales",
    "gn:country_code":"CO",
    "gn:dem":357,
    "gn:feature_class":"P",
    "gn:feature_code":"PPL",
    "gn:name":"Troncales",
    "gn:population":0,
    "gn:timezone":"America/Bogota",
    "iso:country":"CO",
    "wof:name":"Troncales",
    "wof:placetype":"locality"
},
  "geometry": {"coordinates":[-74.93002,2.12364],"type":"Point"}
}