{
  "type": "Feature",
  "properties": {
    "gn:admin1_code":"2",
    "gn:admin2_code":"5854.0",
    "gn:asciiname":"San Matias",
    "gn:country_code":"CO",
    "gn:dem":516,
    "gn:feature_class":"P",
    "gn:feature_code":"PPL",
    "gn:name":"San Mat\u00edas",
    "gn:population":0,
    "gn:timezone":"America/Bogota",
    "iso:country":"CO",
    "wof:name":"San Matias",
    "wof:placetype":"locality"
},
  "geometry": {"coordinates":[-75.39771999999998,7.29716],"type":"Point"}
}