{
  "type": "Feature",
  "properties": {
    "gn:admin1_code":"10",
    "gn:admin2_code":"20011.0",
    "gn:asciiname":"Lebrija",
    "gn:country_code":"CO",
    "gn:dem":47,
    "gn:feature_class":"P",
    "gn:feature_code":"PPL",
    "gn:name":"Lebrija",
    "gn:population":0,
    "gn:timezone":"America/Bogota",
    "iso:country":"CO",
    "name:ara_x_preferred":[
        "\u0646\u0628\u0631\u064a\u0634\u0629"
    ],
    "name:arg_x_preferred":[
        "Lebrija"
    ],
    "name:ast_x_preferred":[
        "Lebrija"
    ],
    "name:azb_x_preferred":[
        "\u0644\u0628\u0631\u06cc\u062e\u0627"
    ],
    "name:cat_x_preferred":[
        "Lebrija"
    ],
    "name:ceb_x_preferred":[
        "Lebrija"
    ],
    "name:deu_x_preferred":[
        "Lebrija"
    ],
    "name:epo_x_preferred":[
        "Lebrija"
    ],
    "name:eus_x_preferred":[
        "Lebrija"
    ],
    "name:fas_x_preferred":[
        "\u0644\u0628\u0631\u06cc\u062e\u0627"
    ],
    "name:fin_x_preferred":[
        "Lebrija"
    ],
    "name:fra_x_preferred":[
        "Lebrija"
    ],
    "name:glg_x_preferred":[
        "Lebrija"
    ],
    "name:hat_x_preferred":[
        "Lebrija"
    ],
    "name:hun_x_preferred":[
        "Lebrija"
    ],
    "name:hye_x_preferred":[
        "\u053c\u0565\u0562\u0580\u056b\u056d\u0561"
    ],
    "name:ind_x_preferred":[
        "Lebrija"
    ],
    "name:ita_x_preferred":[
        "Lebrija"
    ],
    "name:kaz_x_preferred":[
        "\u041b\u0435\u0431\u0440\u0438\u0445\u0430"
    ],
    "name:lat_x_preferred":[
        "Veneria"
    ],
    "name:mlg_x_preferred":[
        "Lebrija"
    ],
    "name:msa_x_preferred":[
        "Lebrija"
    ],
    "name:nld_x_preferred":[
        "Lebrija"
    ],
    "name:oci_x_preferred":[
        "Lebrija"
    ],
    "name:pol_x_preferred":[
        "Lebrija"
    ],
    "name:por_x_preferred":[
        "Lebrija"
    ],
    "name:ron_x_preferred":[
        "Lebrija"
    ],
    "name:rus_x_preferred":[
        "\u041b\u0435\u0431\u0440\u0438\u0445\u0430"
    ],
    "name:spa_x_preferred":[
        "Lebrija"
    ],
    "name:srp_x_preferred":[
        "\u041b\u0435\u0431\u0440\u0438\u0445\u0430"
    ],
    "name:swe_x_preferred":[
        "Lebrija"
    ],
    "name:tur_x_preferred":[
        "Lebrija"
    ],
    "name:ukr_x_preferred":[
        "\u041b\u0435\u0431\u0440\u0456\u0445\u0430"
    ],
    "name:urd_x_preferred":[
        "\u0646\u0628\u0631\u06cc\u0634\u06c1"
    ],
    "name:uzb_x_preferred":[
        "Lebrija"
    ],
    "name:vie_x_preferred":[
        "Lebrija"
    ],
    "name:war_x_preferred":[
        "Lebrija"
    ],
    "name:zho_x_preferred":[
        "\u83b1\u592b\u91cc\u54c8"
    ],
    "wof:name":"Lebrija",
    "wof:placetype":"locality"
},
  "geometry": {"coordinates":[-73.72216,8.01292],"type":"Point"}
}