{
  "type": "Feature",
  "properties": {
    "gn:admin1_code":"10",
    "gn:admin2_code":"20011.0",
    "gn:asciiname":"Lebrija",
    "gn:country_code":"CO",
    "gn:dem":47,
    "gn:feature_class":"P",
    "gn:feature_code":"PPL",
    "gn:name":"Lebrija",
    "gn:population":0,
    "gn:timezone":"America/Bogota",
    "iso:country":"CO",
    "wof:name":"Lebrija",
    "wof:placetype":"locality"
},
  "geometry": {"coordinates":[-73.72216,8.01292],"type":"Point"}
}