{
  "type": "Feature",
  "properties": {
    "gn:admin1_code":"2.0",
    "gn:admin2_code":"5001.0",
    "gn:asciiname":"Monte Flor",
    "gn:country_code":"CO",
    "gn:dem":1822,
    "gn:feature_class":"P",
    "gn:feature_code":"PPL",
    "gn:name":"Monte Flor",
    "gn:population":0,
    "gn:timezone":"America/Bogota",
    "iso:country":"CO",
    "name:spa_x_preferred":[
        "Monte Flor"
    ],
    "wof:name":"Monte Flor",
    "wof:placetype":"locality"
},
  "geometry": {"coordinates":[-75.62631999999998,6.24115],"type":"Point"}
}