{
  "type": "Feature",
  "properties": {
    "gn:admin1_code":"17",
    "gn:admin2_code":"44001.0",
    "gn:asciiname":"Aujero",
    "gn:country_code":"CO",
    "gn:dem":11,
    "gn:feature_class":"P",
    "gn:feature_code":"PPL",
    "gn:name":"Aujero",
    "gn:population":0,
    "gn:timezone":"America/Bogota",
    "iso:country":"CO",
    "wof:name":"Aujero",
    "wof:placetype":"locality"
},
  "geometry": {"coordinates":[-72.88667,11.49667],"type":"Point"}
}