{
  "type": "Feature",
  "properties": {
    "gn:admin1_code":"19",
    "gn:admin2_code":"50568.0",
    "gn:asciiname":"Maicao",
    "gn:country_code":"CO",
    "gn:dem":209,
    "gn:feature_class":"P",
    "gn:feature_code":"PPL",
    "gn:name":"Maicao",
    "gn:population":0,
    "gn:timezone":"America/Bogota",
    "iso:country":"CO",
    "name:ceb_x_preferred":[
        "Maicao"
    ],
    "name:deu_x_preferred":[
        "Maicao"
    ],
    "name:fas_x_preferred":[
        "\u0645\u0627\u06cc\u06a9\u0627\u0626\u0648"
    ],
    "name:fin_x_preferred":[
        "Maicao"
    ],
    "name:fra_x_preferred":[
        "Maicao"
    ],
    "name:ita_x_preferred":[
        "Maicao"
    ],
    "name:kat_x_preferred":[
        "\u10db\u10d0\u10d8\u10d9\u10d0\u10dd"
    ],
    "name:lit_x_preferred":[
        "Maikao"
    ],
    "name:msa_x_preferred":[
        "Maicao"
    ],
    "name:nld_x_preferred":[
        "Maicao"
    ],
    "name:pol_x_preferred":[
        "Maicao"
    ],
    "name:por_x_preferred":[
        "Maicao"
    ],
    "name:rus_x_preferred":[
        "\u041c\u0430\u0439\u043a\u0430\u043e"
    ],
    "name:spa_x_preferred":[
        "Maicao"
    ],
    "name:swe_x_preferred":[
        "Maicao"
    ],
    "name:tat_x_preferred":[
        "\u041c\u0430\u0439\u043a\u0430\u043e"
    ],
    "name:tgl_x_preferred":[
        "Maicao"
    ],
    "name:vie_x_preferred":[
        "Maicao"
    ],
    "name:vol_x_preferred":[
        "Maicao"
    ],
    "name:war_x_preferred":[
        "Maicao"
    ],
    "wof:name":"Maicao",
    "wof:placetype":"locality"
},
  "geometry": {"coordinates":[-72.01201,4.20469],"type":"Point"}
}