{
  "type": "Feature",
  "properties": {
    "gn:country":"CO",
    "gn:fcode":"PPL",
    "gn:pop":3360,
    "iso:country":"CO",
    "name:ast_x_preferred":[
        "Nobsa"
    ],
    "name:ceb_x_preferred":[
        "Nobsa"
    ],
    "name:eng_x_preferred":[
        "Nobsa"
    ],
    "name:fra_x_preferred":[
        "Nobsa"
    ],
    "name:glg_x_preferred":[
        "Nobsa"
    ],
    "name:ita_x_preferred":[
        "Nobsa"
    ],
    "name:kat_x_preferred":[
        "\u10dc\u10dd\u10d1\u10e1\u10d0"
    ],
    "name:msa_x_preferred":[
        "Nobsa"
    ],
    "name:nah_x_preferred":[
        "Nobsa"
    ],
    "name:nan_x_preferred":[
        "Nobsa"
    ],
    "name:nld_x_preferred":[
        "Nobsa"
    ],
    "name:por_x_preferred":[
        "Nobsa"
    ],
    "name:rus_x_preferred":[
        "\u041d\u043e\u0431\u0441\u0430"
    ],
    "name:spa_x_preferred":[
        "Nobsa"
    ],
    "name:swe_x_preferred":[
        "Nobsa"
    ],
    "name:tgl_x_preferred":[
        "Nobsa"
    ],
    "name:vie_x_preferred":[
        "Nobsa"
    ],
    "name:war_x_preferred":[
        "Nobsa"
    ],
    "name:zho_x_preferred":[
        "\u8afe\u592b\u85a9"
    ],
    "qs:name":"Nobsa",
    "qs:photos_9r":0,
    "qs:photos_sr":0,
    "qs:pop_sr":"4",
    "wd:wordcount":229,
    "wof:name":"Nobsa",
    "wof:placetype":"locality",
    "wof:population":3360
},
  "geometry": {"coordinates":[-72.94099,5.76978],"type":"Point"}
}