{
  "type": "Feature",
  "properties": {
    "gn:admin1_code":"8.0",
    "gn:admin2_code":"18479.0",
    "gn:asciiname":"Estados Unidos",
    "gn:country_code":"CO",
    "gn:dem":239,
    "gn:feature_class":"P",
    "gn:feature_code":"PPL",
    "gn:name":"Estados Unidos",
    "gn:population":0,
    "gn:timezone":"America/Bogota",
    "iso:country":"CO",
    "name:spa_x_preferred":[
        "Estados Unidos"
    ],
    "wof:name":"Estados Unidos",
    "wof:placetype":"locality"
},
  "geometry": {"coordinates":[-75.60784,1.25446],"type":"Point"}
}