{
  "type": "Feature",
  "properties": {
    "gn:admin1_code":"37",
    "gn:admin2_code":"17001.0",
    "gn:asciiname":"Cuchilla del Salado",
    "gn:country_code":"CO",
    "gn:dem":1341,
    "gn:feature_class":"P",
    "gn:feature_code":"PPL",
    "gn:name":"Cuchilla del Salado",
    "gn:population":0,
    "gn:timezone":"America/Bogota",
    "iso:country":"CO",
    "wof:name":"Cuchilla del Salado",
    "wof:placetype":"locality"
},
  "geometry": {"coordinates":[-75.52951999999998,5.1154],"type":"Point"}
}