{
  "type": "Feature",
  "properties": {
    "gn:admin1_code":"33.0",
    "gn:admin2_code":"25322.0",
    "gn:asciiname":"La Sauceda",
    "gn:country_code":"CO",
    "gn:dem":2645,
    "gn:feature_class":"P",
    "gn:feature_code":"PPL",
    "gn:name":"La Sauceda",
    "gn:population":0,
    "gn:timezone":"America/Bogota",
    "iso:country":"CO",
    "wof:name":"La Sauceda",
    "wof:placetype":"locality"
},
  "geometry": {"coordinates":[-73.89948000000003,4.87664],"type":"Point"}
}