{
  "type": "Feature",
  "properties": {
    "gn:admin1_code":"33.0",
    "gn:admin2_code":"25322.0",
    "gn:asciiname":"Porto Bello",
    "gn:country_code":"CO",
    "gn:dem":2786,
    "gn:feature_class":"P",
    "gn:feature_code":"PPL",
    "gn:name":"Porto Bello",
    "gn:population":0,
    "gn:timezone":"America/Bogota",
    "iso:country":"CO",
    "wof:name":"Porto Bello",
    "wof:placetype":"locality"
},
  "geometry": {"coordinates":[-73.88528000000002,4.82269],"type":"Point"}
}