{
  "type": "Feature",
  "properties": {
    "gn:admin1_code":"21",
    "gn:admin2_code":"54498.0",
    "gn:asciiname":"Libano",
    "gn:country_code":"CO",
    "gn:dem":1179,
    "gn:feature_class":"P",
    "gn:feature_code":"PPL",
    "gn:name":"L\u00edbano",
    "gn:population":0,
    "gn:timezone":"America/Bogota",
    "iso:country":"CO",
    "name:und_x_variant":[
        "El Libano",
        "L\u00edbano"
    ],
    "wof:name":"Libano",
    "wof:placetype":"locality"
},
  "geometry": {"coordinates":[-73.36465,8.27767],"type":"Point"}
}