{
  "type": "Feature",
  "properties": {
    "iso:country":"CO",
    "name:cat_x_preferred":[
        "San Felipe"
    ],
    "name:ceb_x_preferred":[
        "San Felipe"
    ],
    "name:deu_x_preferred":[
        "San Felipe"
    ],
    "name:eng_x_preferred":[
        "San Felipe"
    ],
    "name:fas_x_preferred":[
        "\u0633\u0627\u0646 \u0641\u06cc\u0644\u06cc\u067e\u0647"
    ],
    "name:fra_x_preferred":[
        "San Felipe"
    ],
    "name:glg_x_preferred":[
        "San Felipe"
    ],
    "name:heb_x_preferred":[
        "\u05e1\u05df \u05e4\u05dc\u05d9\u05e4\u05d4"
    ],
    "name:hun_x_preferred":[
        "San Felipe"
    ],
    "name:ita_x_preferred":[
        "San Felipe"
    ],
    "name:kat_x_preferred":[
        "\u10e1\u10d0\u10dc-\u10e4\u10d4\u10da\u10d8\u10de\u10d4"
    ],
    "name:lit_x_preferred":[
        "San Felip\u0117"
    ],
    "name:msa_x_preferred":[
        "San Felipe"
    ],
    "name:nan_x_preferred":[
        "San Felipe"
    ],
    "name:nld_x_preferred":[
        "San Felipe"
    ],
    "name:sco_x_preferred":[
        "San Felipe"
    ],
    "name:spa_x_preferred":[
        "San Felipe"
    ],
    "name:swe_x_preferred":[
        "San Felipe"
    ],
    "name:tgl_x_preferred":[
        "San Felipe"
    ],
    "name:und_x_variant":[
        "Fuerte San Felipe"
    ],
    "name:war_x_preferred":[
        "San Felipe"
    ],
    "name:zho_x_preferred":[
        "\u8056\u83f2\u5229\u4f69"
    ],
    "qs:gn_country":"CO",
    "qs:gn_fcode":"PPL",
    "qs:gn_pop":982,
    "qs:name":"San Felipe",
    "qs:name_adm0":"Colombia",
    "qs:name_adm1":"Guainia",
    "qs:photos":0,
    "qs:photos_1k":0,
    "qs:photos_9k":0,
    "qs:photos_9r":0,
    "qs:photos_all":0,
    "qs:photos_sr":0,
    "qs:placetype":"Town",
    "qs:pop_sr":"2",
    "qs:woe_adm0":23424787,
    "wof:name":"San Felipe",
    "wof:placetype":"locality",
    "wof:population":982
},
  "geometry": {"coordinates":[-67.06995999999999,1.91408],"type":"Point"}
}