{
  "type": "Feature",
  "properties": {
    "gn:admin1_code":"12",
    "gn:admin2_code":"23807.0",
    "gn:asciiname":"Coquito",
    "gn:country_code":"CO",
    "gn:dem":31,
    "gn:feature_class":"P",
    "gn:feature_code":"PPL",
    "gn:name":"Coquito",
    "gn:population":0,
    "gn:timezone":"America/Bogota",
    "iso:country":"CO",
    "name:jpn_x_preferred":[
        "\u30c1\u30ea\u30e4\u30b7"
    ],
    "name:spa_x_preferred":[
        "Coquito"
    ],
    "wof:name":"Coquito",
    "wof:placetype":"locality"
},
  "geometry": {"coordinates":[-75.81667,8.31667],"type":"Point"}
}