{
  "type": "Feature",
  "properties": {
    "gn:admin1_code":"28.0",
    "gn:admin2_code":"73870.0",
    "gn:asciiname":"Quebradanegra",
    "gn:country_code":"CO",
    "gn:dem":3545,
    "gn:feature_class":"P",
    "gn:feature_code":"PPL",
    "gn:name":"Quebradanegra",
    "gn:population":0,
    "gn:timezone":"America/Bogota",
    "iso:country":"CO",
    "wof:name":"Quebradanegra",
    "wof:placetype":"locality"
},
  "geometry": {"coordinates":[-75.25,4.93333],"type":"Point"}
}