{
  "type": "Feature",
  "properties": {
    "gn:country":"CO",
    "gn:fcode":"PPL",
    "gn:population":16579,
    "iso:country":"CO",
    "name:ast_x_preferred":[
        "Corinto"
    ],
    "name:avk_x_preferred":[
        "Corinto"
    ],
    "name:ceb_x_preferred":[
        "Corinto"
    ],
    "name:deu_x_preferred":[
        "Corinto"
    ],
    "name:eng_x_preferred":[
        "Corinto"
    ],
    "name:fas_x_preferred":[
        "\u06a9\u0648\u0631\u06cc\u0646\u062a\u0648"
    ],
    "name:fra_x_preferred":[
        "Corinto"
    ],
    "name:gla_x_preferred":[
        "Corinto"
    ],
    "name:gle_x_preferred":[
        "Corinto"
    ],
    "name:ita_x_preferred":[
        "Corinto"
    ],
    "name:jpn_x_preferred":[
        "\u30b3\u30ea\u30f3\u30c8"
    ],
    "name:kat_x_preferred":[
        "\u10d9\u10dd\u10e0\u10d8\u10dc\u10e2\u10dd"
    ],
    "name:msa_x_preferred":[
        "Corinto"
    ],
    "name:nan_x_preferred":[
        "Corinto"
    ],
    "name:nld_x_preferred":[
        "Corinto"
    ],
    "name:pol_x_preferred":[
        "Corinto"
    ],
    "name:por_x_preferred":[
        "Corinto"
    ],
    "name:rus_x_preferred":[
        "\u041a\u043e\u0440\u0438\u043d\u0442\u043e"
    ],
    "name:spa_x_preferred":[
        "Corinto"
    ],
    "name:swe_x_preferred":[
        "Corinto"
    ],
    "name:tgl_x_preferred":[
        "Corinto"
    ],
    "name:war_x_preferred":[
        "Corinto"
    ],
    "name:zho_x_preferred":[
        "\u79d1\u6797\u6258"
    ],
    "qs_pg:aaroncc":"CO",
    "qs_pg:gn_country":"CO",
    "qs_pg:gn_fcode":"PPL",
    "qs_pg:gn_pop":16579,
    "qs_pg:name":"Corinto",
    "qs_pg:photos_9r":0,
    "qs_pg:photos_sr":0,
    "qs_pg:pop_sr":6,
    "qs_pg:qs_pg_placetype":"locality",
    "wof:name":"Corinto",
    "wof:placetype":"locality",
    "wof:population":16579
},
  "geometry": {"coordinates":[-76.25993,3.17407],"type":"Point"}
}