{
  "type": "Feature",
  "properties": {
    "gn:admin1_code":"2.0",
    "gn:admin2_code":"5129.0",
    "gn:asciiname":"El Trapiche",
    "gn:country_code":"CO",
    "gn:dem":1685,
    "gn:feature_class":"P",
    "gn:feature_code":"PPL",
    "gn:name":"El Trapiche",
    "gn:population":0,
    "gn:timezone":"America/Bogota",
    "iso:country":"CO",
    "name:spa_x_preferred":[
        "El Trapiche"
    ],
    "wof:name":"El Trapiche",
    "wof:placetype":"locality"
},
  "geometry": {"coordinates":[-75.65002,5.99978],"type":"Point"}
}