{
  "type": "Feature",
  "properties": {
    "gn:admin1_code":"17",
    "gn:admin2_code":"44078.0",
    "gn:asciiname":"Las Planadas",
    "gn:country_code":"CO",
    "gn:dem":770,
    "gn:feature_class":"P",
    "gn:feature_code":"PPL",
    "gn:name":"Las Planadas",
    "gn:population":0,
    "gn:timezone":"America/Bogota",
    "iso:country":"CO",
    "name:und_x_variant":[
        "Las Pinnada",
        "Las Planadas"
    ],
    "wof:name":"Las Planadas",
    "wof:placetype":"locality"
},
  "geometry": {"coordinates":[-72.53214,11.00587],"type":"Point"}
}