{
  "type": "Feature",
  "properties": {
    "gn:admin1_code":"20.0",
    "gn:admin2_code":"52356.0",
    "gn:asciiname":"Callejon",
    "gn:country_code":"CO",
    "gn:dem":3299,
    "gn:feature_class":"P",
    "gn:feature_code":"PPL",
    "gn:name":"Callej\u00f3n",
    "gn:population":0,
    "gn:timezone":"America/Bogota",
    "iso:country":"CO",
    "wof:name":"Callejon",
    "wof:placetype":"locality"
},
  "geometry": {"coordinates":[-77.66124000000001,0.7421],"type":"Point"}
}