{
  "type": "Feature",
  "properties": {
    "gn:admin1_code":"21",
    "gn:admin2_code":"54810.0",
    "gn:asciiname":"Vetas",
    "gn:country_code":"CO",
    "gn:dem":40,
    "gn:feature_class":"P",
    "gn:feature_code":"PPL",
    "gn:name":"Vetas",
    "gn:population":0,
    "gn:timezone":"America/Bogota",
    "iso:country":"CO",
    "name:cat_x_preferred":[
        "Vetas"
    ],
    "name:ceb_x_preferred":[
        "Vetas"
    ],
    "name:fas_x_preferred":[
        "\u0648\u062a\u0627\u0633"
    ],
    "name:fra_x_preferred":[
        "Vetas"
    ],
    "name:ita_x_preferred":[
        "Vetas"
    ],
    "name:kat_x_preferred":[
        "\u10d5\u10d4\u10e2\u10d0\u10e1\u10d8"
    ],
    "name:msa_x_preferred":[
        "Vetas"
    ],
    "name:nld_x_preferred":[
        "Vetas"
    ],
    "name:spa_x_preferred":[
        "Vetas"
    ],
    "name:swe_x_preferred":[
        "Vetas"
    ],
    "name:tgl_x_preferred":[
        "Vetas"
    ],
    "name:vie_x_preferred":[
        "Vetas"
    ],
    "name:war_x_preferred":[
        "Vetas"
    ],
    "name:zho_x_preferred":[
        "\u97cb\u5854\u65af"
    ],
    "wof:name":"Vetas",
    "wof:placetype":"locality"
},
  "geometry": {"coordinates":[-72.84828,8.89333],"type":"Point"}
}