{
  "type": "Feature",
  "properties": {
    "gn:admin1_code":"11",
    "gn:admin2_code":"27205.0",
    "gn:asciiname":"La Murina",
    "gn:country_code":"CO",
    "gn:dem":125,
    "gn:feature_class":"P",
    "gn:feature_code":"PPL",
    "gn:name":"La Muri\u00f1a",
    "gn:population":0,
    "gn:timezone":"America/Bogota",
    "iso:country":"CO",
    "wof:name":"La Murina",
    "wof:placetype":"locality"
},
  "geometry": {"coordinates":[-76.58333,5.08333],"type":"Point"}
}