{
  "type": "Feature",
  "properties": {
    "gn:admin1_code":"26.0",
    "gn:admin2_code":"68689.0",
    "gn:asciiname":"Las Margaritas",
    "gn:country_code":"CO",
    "gn:dem":125,
    "gn:feature_class":"P",
    "gn:feature_code":"PPLL",
    "gn:name":"Las Margaritas",
    "gn:population":0,
    "gn:timezone":"America/Bogota",
    "iso:country":"CO",
    "name:ceb_x_preferred":[
        "Las Margaritas"
    ],
    "name:deu_x_preferred":[
        "Las Margaritas"
    ],
    "name:fra_x_preferred":[
        "Las Margaritas"
    ],
    "name:ita_x_preferred":[
        "Las Margaritas"
    ],
    "name:sco_x_preferred":[
        "Las Margaritas"
    ],
    "name:spa_x_preferred":[
        "Las margaritas"
    ],
    "name:srp_x_preferred":[
        "\u041b\u0430\u0441 \u041c\u0430\u0440\u0433\u0430\u0440\u0438\u0442\u0430\u0441"
    ],
    "name:swe_x_preferred":[
        "Las Margaritas"
    ],
    "wof:name":"Las Margaritas",
    "wof:placetype":"locality"
},
  "geometry": {"coordinates":[-73.63353000000002,6.9234],"type":"Point"}
}