{
  "type": "Feature",
  "properties": {
    "iso:country":"CO",
    "name:ast_x_preferred":[
        "El Pital"
    ],
    "name:avk_x_preferred":[
        "El Pital"
    ],
    "name:ceb_x_preferred":[
        "Pital"
    ],
    "name:cym_x_preferred":[
        "Pital"
    ],
    "name:eng_x_preferred":[
        "Pital"
    ],
    "name:fas_x_preferred":[
        "\u067e\u06cc\u062a\u0627\u0644"
    ],
    "name:fra_x_preferred":[
        "El Pital"
    ],
    "name:gle_x_preferred":[
        "Pital"
    ],
    "name:ita_x_preferred":[
        "El Pital"
    ],
    "name:kat_x_preferred":[
        "\u10de\u10d8\u10e2\u10d0\u10da\u10d8"
    ],
    "name:msa_x_preferred":[
        "Pital"
    ],
    "name:nan_x_preferred":[
        "Pital"
    ],
    "name:nld_x_preferred":[
        "Pital"
    ],
    "name:pol_x_preferred":[
        "Pital"
    ],
    "name:por_x_preferred":[
        "Pital"
    ],
    "name:spa_x_preferred":[
        "El Pital"
    ],
    "name:swe_x_preferred":[
        "Pital"
    ],
    "name:tgl_x_preferred":[
        "Pital"
    ],
    "name:vie_x_preferred":[
        "Pital"
    ],
    "name:war_x_preferred":[
        "Pital"
    ],
    "name:zho_x_preferred":[
        "\u76ae\u5854\u723e"
    ],
    "qs:gn_country":"CO",
    "qs:gn_fcode":"PPL",
    "qs:gn_pop":3957,
    "qs:name":"Pital",
    "qs:name_adm0":"Colombia",
    "qs:name_adm1":"Huila",
    "qs:photos":0,
    "qs:photos_1k":0,
    "qs:photos_9k":1,
    "qs:photos_9r":1,
    "qs:photos_all":1,
    "qs:photos_sr":0,
    "qs:placetype":"Town",
    "qs:pop_sr":"4",
    "qs:woe_adm0":23424787,
    "wd:wordcount":84,
    "wof:name":"Pital",
    "wof:placetype":"locality",
    "wof:population":3957
},
  "geometry": {"coordinates":[-75.80441999999999,2.2665],"type":"Point"}
}