{
  "type": "Feature",
  "properties": {
    "gn:admin1_code":"28.0",
    "gn:admin2_code":"73168.0",
    "gn:asciiname":"Betania",
    "gn:country_code":"CO",
    "gn:dem":780,
    "gn:feature_class":"P",
    "gn:feature_code":"PPL",
    "gn:name":"Betania",
    "gn:population":0,
    "gn:timezone":"America/Bogota",
    "iso:country":"CO",
    "wof:name":"Betania",
    "wof:placetype":"locality"
},
  "geometry": {"coordinates":[-75.51139000000001,3.57306],"type":"Point"}
}