{
  "type": "Feature",
  "properties": {
    "gn:admin1_code":"26",
    "gn:admin2_code":"68575.0",
    "gn:asciiname":"La Horqueta",
    "gn:country_code":"CO",
    "gn:dem":62,
    "gn:feature_class":"P",
    "gn:feature_code":"PPL",
    "gn:name":"La Horqueta",
    "gn:population":0,
    "gn:timezone":"America/Bogota",
    "iso:country":"CO",
    "name:cat_x_preferred":[
        "Horqueta"
    ],
    "name:fra_x_preferred":[
        "La Horqueta"
    ],
    "name:spa_x_preferred":[
        "La Horqueta"
    ],
    "name:urd_x_preferred":[
        "\u0644\u0627 \u06c1\u0648\u0631\u06a9\u0648\u06cc\u062a\u0627"
    ],
    "wof:name":"La Horqueta",
    "wof:placetype":"locality"
},
  "geometry": {"coordinates":[-73.89018,7.37371],"type":"Point"}
}