{
  "type": "Feature",
  "properties": {
    "gn:admin1_code":"3.0",
    "gn:admin2_code":"81220.0",
    "gn:asciiname":"La Verdad",
    "gn:country_code":"CO",
    "gn:dem":105,
    "gn:feature_class":"P",
    "gn:feature_code":"PPL",
    "gn:name":"La Verdad",
    "gn:population":0,
    "gn:timezone":"America/Bogota",
    "iso:country":"CO",
    "name:glg_x_preferred":[
        "La Verdad"
    ],
    "name:spa_x_preferred":[
        "La verdad"
    ],
    "name:srp_x_preferred":[
        "\u041b\u0430 \u0412\u0435\u0440\u0434\u0430\u0434"
    ],
    "name:und_x_variant":[
        "Verdad",
        "La Verdad"
    ],
    "wof:name":"La Verdad",
    "wof:placetype":"locality"
},
  "geometry": {"coordinates":[-70.24508,6.59374],"type":"Point"}
}