{
  "type": "Feature",
  "properties": {
    "gn:admin1_code":"19.0",
    "gn:admin2_code":"50001.0",
    "gn:asciiname":"La Maria",
    "gn:country_code":"CO",
    "gn:dem":356,
    "gn:feature_class":"P",
    "gn:feature_code":"PPL",
    "gn:name":"La Mar\u00eda",
    "gn:population":0,
    "gn:timezone":"America/Bogota",
    "iso:country":"CO",
    "name:spa_x_preferred":[
        "La Mar\u00eda"
    ],
    "wof:name":"La Maria",
    "wof:placetype":"locality"
},
  "geometry": {"coordinates":[-73.5365,4.0839],"type":"Point"}
}