{
  "type": "Feature",
  "properties": {
    "gn:admin1_code":"36",
    "gn:admin2_code":"15507.0",
    "gn:asciiname":"Lama Redonda",
    "gn:country_code":"CO",
    "gn:dem":723,
    "gn:feature_class":"P",
    "gn:feature_code":"PPL",
    "gn:name":"Lama Redonda",
    "gn:population":0,
    "gn:timezone":"America/Bogota",
    "iso:country":"CO",
    "wof:name":"Lama Redonda",
    "wof:placetype":"locality"
},
  "geometry": {"coordinates":[-74.17333000000001,5.79083],"type":"Point"}
}