{
  "type": "Feature",
  "properties": {
    "gn:admin1_code":"32",
    "gn:asciiname":"Los Aceites",
    "gn:country_code":"CO",
    "gn:dem":127,
    "gn:feature_class":"P",
    "gn:feature_code":"PPL",
    "gn:name":"Los Aceites",
    "gn:population":0,
    "gn:timezone":"America/Bogota",
    "iso:country":"CO",
    "name:spa_x_preferred":[
        "Los Aceites"
    ],
    "wof:name":"Los Aceites",
    "wof:placetype":"locality"
},
  "geometry": {"coordinates":[-70.93013000000001,6.02565],"type":"Point"}
}