{
  "type": "Feature",
  "properties": {
    "gn:admin1_code":"12",
    "gn:admin2_code":"23419.0",
    "gn:asciiname":"Marcelino Reyes",
    "gn:country_code":"CO",
    "gn:dem":108,
    "gn:feature_class":"P",
    "gn:feature_code":"PPL",
    "gn:name":"Marcelino Reyes",
    "gn:population":0,
    "gn:timezone":"America/Bogota",
    "iso:country":"CO",
    "wof:name":"Marcelino Reyes",
    "wof:placetype":"locality"
},
  "geometry": {"coordinates":[-76.33977,8.85619],"type":"Point"}
}