{
  "type": "Feature",
  "properties": {
    "gn:admin1_code":"32",
    "gn:admin2_code":"85125.0",
    "gn:asciiname":"El Guafal",
    "gn:country_code":"CO",
    "gn:dem":167,
    "gn:feature_class":"P",
    "gn:feature_code":"PPL",
    "gn:name":"El Guafal",
    "gn:population":0,
    "gn:timezone":"America/Bogota",
    "iso:country":"CO",
    "wof:name":"El Guafal",
    "wof:placetype":"locality"
},
  "geometry": {"coordinates":[-71.26666999999998,6.26667],"type":"Point"}
}