{
  "type": "Feature",
  "properties": {
    "gn:admin1_code":"8.0",
    "gn:admin2_code":"18479.0",
    "gn:asciiname":"Alto Bonito",
    "gn:country_code":"CO",
    "gn:dem":232,
    "gn:feature_class":"P",
    "gn:feature_code":"PPL",
    "gn:name":"Alto Bonito",
    "gn:population":0,
    "gn:timezone":"America/Bogota",
    "iso:country":"CO",
    "name:spa_x_preferred":[
        "Alto Bonito"
    ],
    "wof:name":"Alto Bonito",
    "wof:placetype":"locality"
},
  "geometry": {"coordinates":[-75.59349,1.32223],"type":"Point"}
}