{
  "type": "Feature",
  "properties": {
    "gn:admin1_code":"9.0",
    "gn:admin2_code":"19100.0",
    "gn:asciiname":"Corral Viejo",
    "gn:country_code":"CO",
    "gn:dem":816,
    "gn:feature_class":"P",
    "gn:feature_code":"PPL",
    "gn:name":"Corral Viejo",
    "gn:population":0,
    "gn:timezone":"America/Bogota",
    "iso:country":"CO",
    "wof:name":"Corral Viejo",
    "wof:placetype":"locality"
},
  "geometry": {"coordinates":[-77.01989,1.99561],"type":"Point"}
}