{
  "type": "Feature",
  "properties": {
    "gn:admin1_code":"21",
    "gn:admin2_code":"54347.0",
    "gn:asciiname":"La Colorada",
    "gn:country_code":"CO",
    "gn:dem":2483,
    "gn:feature_class":"P",
    "gn:feature_code":"PPL",
    "gn:name":"La Colorada",
    "gn:population":0,
    "gn:timezone":"America/Bogota",
    "iso:country":"CO",
    "name:ceb_x_preferred":[
        "La Colorada"
    ],
    "name:deu_x_preferred":[
        "La Colorada"
    ],
    "name:ita_x_preferred":[
        "La Colorada"
    ],
    "name:spa_x_preferred":[
        "La Colorada"
    ],
    "name:swe_x_preferred":[
        "La Colorada"
    ],
    "wof:name":"La Colorada",
    "wof:placetype":"locality"
},
  "geometry": {"coordinates":[-72.45694,7.44086],"type":"Point"}
}