{
  "type": "Feature",
  "properties": {
    "gn:admin1_code":"29",
    "gn:admin2_code":"76100.0",
    "gn:asciiname":"Chorreras",
    "gn:country_code":"CO",
    "gn:dem":1385,
    "gn:feature_class":"P",
    "gn:feature_code":"PPL",
    "gn:name":"Chorreras",
    "gn:population":0,
    "gn:timezone":"America/Bogota",
    "iso:country":"CO",
    "wof:name":"Chorreras",
    "wof:placetype":"locality"
},
  "geometry": {"coordinates":[-76.23333000000002,4.35],"type":"Point"}
}