{
  "type": "Feature",
  "properties": {
    "gn:admin1_code":"16.0",
    "gn:admin2_code":"41396.0",
    "gn:asciiname":"Casablanca",
    "gn:country_code":"CO",
    "gn:dem":1139,
    "gn:feature_class":"P",
    "gn:feature_code":"PPL",
    "gn:name":"Casablanca",
    "gn:population":0,
    "gn:timezone":"America/Bogota",
    "iso:country":"CO",
    "wof:name":"Casablanca",
    "wof:placetype":"locality"
},
  "geometry": {"coordinates":[-75.91061999999999,2.36247],"type":"Point"}
}