{
  "type": "Feature",
  "properties": {
    "gn:admin1_code":"9.0",
    "gn:admin2_code":"19050.0",
    "gn:asciiname":"Sinai",
    "gn:country_code":"CO",
    "gn:dem":947,
    "gn:feature_class":"P",
    "gn:feature_code":"PPL",
    "gn:name":"Sina\u00ed",
    "gn:population":0,
    "gn:timezone":"America/Bogota",
    "iso:country":"CO",
    "wof:name":"Sinai",
    "wof:placetype":"locality"
},
  "geometry": {"coordinates":[-77.21619,2.3834],"type":"Point"}
}