{
  "type": "Feature",
  "properties": {
    "gn:admin1_code":"36",
    "gn:admin2_code":"15676.0",
    "gn:asciiname":"Montana",
    "gn:country_code":"CO",
    "gn:dem":2539,
    "gn:feature_class":"P",
    "gn:feature_code":"PPL",
    "gn:name":"Monta\u00f1a",
    "gn:population":0,
    "gn:timezone":"America/Bogota",
    "iso:country":"CO",
    "wof:name":"Montana",
    "wof:placetype":"locality"
},
  "geometry": {"coordinates":[-73.78028,5.58611],"type":"Point"}
}