{
  "type": "Feature",
  "properties": {
    "gn:admin1_code":"35",
    "gn:admin2_code":"13600.0",
    "gn:asciiname":"Guepi",
    "gn:country_code":"CO",
    "gn:dem":36,
    "gn:feature_class":"P",
    "gn:feature_code":"PPL",
    "gn:name":"Guepi",
    "gn:population":0,
    "gn:timezone":"America/Bogota",
    "iso:country":"CO",
    "wof:name":"Guepi",
    "wof:placetype":"locality"
},
  "geometry": {"coordinates":[-73.78430999999998,8.51465],"type":"Point"}
}