{
  "type": "Feature",
  "properties": {
    "gn:admin1_code":"33",
    "gn:admin2_code":"25040.0",
    "gn:asciiname":"Ilo",
    "gn:country_code":"CO",
    "gn:dem":1408,
    "gn:feature_class":"P",
    "gn:feature_code":"PPL",
    "gn:name":"Il\u00f3",
    "gn:population":0,
    "gn:timezone":"America/Bogota",
    "iso:country":"CO",
    "name:ben_x_preferred":[
        "\u0987\u09b2\u09cb"
    ],
    "name:ceb_x_preferred":[
        "Ilo"
    ],
    "name:est_x_preferred":[
        "ILO"
    ],
    "name:fin_x_preferred":[
        "Ilo"
    ],
    "name:fra_x_preferred":[
        "Ilo"
    ],
    "name:heb_x_preferred":[
        "\u05d0\u05d9\u05dc\u05d5"
    ],
    "name:hin_x_preferred":[
        "\u0907\u0932\u094b"
    ],
    "name:hun_x_preferred":[
        "Ilo"
    ],
    "name:ind_x_preferred":[
        "Ilo"
    ],
    "name:kor_x_preferred":[
        "\uc77c\ub85c"
    ],
    "name:lit_x_preferred":[
        "Ilas"
    ],
    "name:por_x_preferred":[
        "Ilo"
    ],
    "name:spa_x_preferred":[
        "Ilo"
    ],
    "name:swe_x_preferred":[
        "Ilo"
    ],
    "name:tur_x_preferred":[
        "Ilo"
    ],
    "name:urd_x_preferred":[
        "\u0644\u0648"
    ],
    "name:vie_x_preferred":[
        "Ilo"
    ],
    "name:war_x_preferred":[
        "Ilo"
    ],
    "wof:name":"Ilo",
    "wof:placetype":"locality"
},
  "geometry": {"coordinates":[-74.51667,4.78333],"type":"Point"}
}