{
  "type": "Feature",
  "properties": {
    "gn:admin1_code":"33",
    "gn:admin2_code":"25040.0",
    "gn:asciiname":"Ilo",
    "gn:country_code":"CO",
    "gn:dem":1408,
    "gn:feature_class":"P",
    "gn:feature_code":"PPL",
    "gn:name":"Il\u00f3",
    "gn:population":0,
    "gn:timezone":"America/Bogota",
    "iso:country":"CO",
    "name:ceb_x_preferred":[
        "Ilo"
    ],
    "name:est_x_preferred":[
        "ILO"
    ],
    "name:fin_x_preferred":[
        "Ilo"
    ],
    "name:fra_x_preferred":[
        "Ilo"
    ],
    "name:lit_x_preferred":[
        "Ilas"
    ],
    "name:por_x_preferred":[
        "Ilo"
    ],
    "name:spa_x_preferred":[
        "Ilo"
    ],
    "name:swe_x_preferred":[
        "Ilo"
    ],
    "name:war_x_preferred":[
        "Ilo"
    ],
    "wof:name":"Ilo",
    "wof:placetype":"locality"
},
  "geometry": {"coordinates":[-74.51666999999998,4.78333],"type":"Point"}
}