{
  "type": "Feature",
  "properties": {
    "gn:admin1_code":"2.0",
    "gn:admin2_code":"5088.0",
    "gn:asciiname":"Charco Verde",
    "gn:country_code":"CO",
    "gn:dem":2462,
    "gn:feature_class":"P",
    "gn:feature_code":"PPL",
    "gn:name":"Charco Verde",
    "gn:population":0,
    "gn:timezone":"America/Bogota",
    "iso:country":"CO",
    "name:spa_x_preferred":[
        "Charco Verde"
    ],
    "wof:name":"Charco Verde",
    "wof:placetype":"locality"
},
  "geometry": {"coordinates":[-75.6155,6.36281],"type":"Point"}
}