{
  "type": "Feature",
  "properties": {
    "gn:admin1_code":"33",
    "gn:admin2_code":"25885.0",
    "gn:asciiname":"Llano Mateo",
    "gn:country_code":"CO",
    "gn:dem":1240,
    "gn:feature_class":"P",
    "gn:feature_code":"PPL",
    "gn:name":"Llano Mateo",
    "gn:population":0,
    "gn:timezone":"America/Bogota",
    "iso:country":"CO",
    "wof:name":"Llano Mateo",
    "wof:placetype":"locality"
},
  "geometry": {"coordinates":[-74.39111,5.59222],"type":"Point"}
}