{
  "type": "Feature",
  "properties": {
    "iso:country":"CO",
    "name:ast_x_preferred":[
        "Guachucal"
    ],
    "name:ceb_x_preferred":[
        "Guachucal"
    ],
    "name:eng_x_preferred":[
        "Guachucal"
    ],
    "name:fra_x_preferred":[
        "Guachucal"
    ],
    "name:ita_x_preferred":[
        "Guachucal"
    ],
    "name:kat_x_preferred":[
        "\u10d2\u10e3\u10d0\u10e9\u10e3\u10d9\u10d0\u10da\u10d8"
    ],
    "name:msa_x_preferred":[
        "Guachucal"
    ],
    "name:nan_x_preferred":[
        "Guachucal"
    ],
    "name:nld_x_preferred":[
        "Guachucal"
    ],
    "name:por_x_preferred":[
        "Guachucal"
    ],
    "name:spa_x_preferred":[
        "Guachucal"
    ],
    "name:swe_x_preferred":[
        "Guachucal"
    ],
    "name:tgl_x_preferred":[
        "Guachucal"
    ],
    "name:und_x_variant":[
        "Guachegal"
    ],
    "name:vie_x_preferred":[
        "Guachucal"
    ],
    "name:war_x_preferred":[
        "Guachucal"
    ],
    "name:zho_min_nan_x_preferred":[
        "Guachucal"
    ],
    "name:zho_x_preferred":[
        "\u74dc\u4e18\u5361\u723e"
    ],
    "qs:gn_country":"CO",
    "qs:gn_fcode":"PPL",
    "qs:gn_pop":4014,
    "qs:name":"Guachucal",
    "qs:name_adm0":"Colombia",
    "qs:name_adm1":"Narino",
    "qs:photos":0,
    "qs:photos_1k":0,
    "qs:photos_9k":1,
    "qs:photos_9r":1,
    "qs:photos_all":14,
    "qs:photos_sr":0,
    "qs:placetype":"Town",
    "qs:pop_sr":"4",
    "qs:woe_adm0":23424787,
    "wd:wordcount":34,
    "wof:name":"Guachucal",
    "wof:placetype":"locality",
    "wof:population":4014
},
  "geometry": {"coordinates":[-77.7316,0.96093],"type":"Point"}
}