{
  "type": "Feature",
  "properties": {
    "gn:admin1_code":"36",
    "gn:admin2_code":"15572.0",
    "gn:asciiname":"La Floresta",
    "gn:country_code":"CO",
    "gn:dem":469,
    "gn:feature_class":"P",
    "gn:feature_code":"PPL",
    "gn:name":"La Floresta",
    "gn:population":0,
    "gn:timezone":"America/Bogota",
    "iso:country":"CO",
    "wof:name":"La Floresta",
    "wof:placetype":"locality"
},
  "geometry": {"coordinates":[-74.29971999999999,5.93778],"type":"Point"}
}