{
  "type": "Feature",
  "properties": {
    "gn:admin1_code":"10.0",
    "gn:admin2_code":"20013.0",
    "gn:asciiname":"Monserrate",
    "gn:country_code":"CO",
    "gn:dem":1142,
    "gn:feature_class":"P",
    "gn:feature_code":"PPL",
    "gn:name":"Monserrate",
    "gn:population":0,
    "gn:timezone":"America/Bogota",
    "iso:country":"CO",
    "name:cat_x_preferred":[
        "Monserrate"
    ],
    "name:ceb_x_preferred":[
        "Monserrate"
    ],
    "name:deu_x_preferred":[
        "Monserrate"
    ],
    "name:epo_x_preferred":[
        "Monserrate"
    ],
    "name:glg_x_preferred":[
        "Monserrate"
    ],
    "name:ita_x_preferred":[
        "Monserrate"
    ],
    "name:nld_x_preferred":[
        "Monserrate"
    ],
    "name:nor_x_preferred":[
        "Monserrate"
    ],
    "name:spa_x_preferred":[
        "Monserrate"
    ],
    "name:swe_x_preferred":[
        "Monserrate"
    ],
    "wof:name":"Monserrate",
    "wof:placetype":"locality"
},
  "geometry": {"coordinates":[-73.11358,10.05249],"type":"Point"}
}