{
  "type": "Feature",
  "properties": {
    "gn:admin1_code":"33.0",
    "gn:admin2_code":"25599.0",
    "gn:asciiname":"Vereda El Palmar",
    "gn:country_code":"CO",
    "gn:dem":615,
    "gn:feature_class":"P",
    "gn:feature_code":"PPLL",
    "gn:name":"Vereda El Palmar",
    "gn:population":0,
    "gn:timezone":"America/Bogota",
    "iso:country":"CO",
    "name:spa_x_preferred":[
        "Vereda El Palmar"
    ],
    "wof:name":"Vereda El Palmar",
    "wof:placetype":"locality"
},
  "geometry": {"coordinates":[-74.59534000000002,4.47396],"type":"Point"}
}