{
  "type": "Feature",
  "properties": {
    "gn:admin1_code":"2.0",
    "gn:admin2_code":"5647.0",
    "gn:asciiname":"El Roble",
    "gn:country_code":"CO",
    "gn:dem":2045,
    "gn:feature_class":"P",
    "gn:feature_code":"PPL",
    "gn:name":"El Roble",
    "gn:population":0,
    "gn:timezone":"America/Bogota",
    "iso:country":"CO",
    "name:ceb_x_preferred":[
        "El Roble"
    ],
    "name:fra_x_preferred":[
        "El Roble"
    ],
    "name:ita_x_preferred":[
        "El Roble"
    ],
    "name:nld_x_preferred":[
        "El Roble"
    ],
    "name:srp_x_preferred":[
        "\u0415\u043b \u0420\u043e\u0431\u043b\u0435"
    ],
    "name:swe_x_preferred":[
        "El Roble"
    ],
    "wof:name":"El Roble",
    "wof:placetype":"locality"
},
  "geometry": {"coordinates":[-75.64972,6.94056],"type":"Point"}
}