{
  "type": "Feature",
  "properties": {
    "gn:admin1_code":"2.0",
    "gn:admin2_code":"5647.0",
    "gn:asciiname":"El Roble",
    "gn:country_code":"CO",
    "gn:dem":2045,
    "gn:feature_class":"P",
    "gn:feature_code":"PPL",
    "gn:name":"El Roble",
    "gn:population":0,
    "gn:timezone":"America/Bogota",
    "iso:country":"CO",
    "wof:name":"El Roble",
    "wof:placetype":"locality"
},
  "geometry": {"coordinates":[-75.64972,6.94056],"type":"Point"}
}