{
  "type": "Feature",
  "properties": {
    "gn:admin1_code":"35",
    "gn:admin2_code":"13442.0",
    "gn:asciiname":"Cedro",
    "gn:cc2":"CO",
    "gn:country_code":"CO",
    "gn:dem":15,
    "gn:feature_class":"P",
    "gn:feature_code":"PPL",
    "gn:name":"Cedro",
    "gn:population":0,
    "gn:timezone":"America/Bogota",
    "iso:country":"CO",
    "name:epo_x_preferred":[
        "Cedro"
    ],
    "name:eus_x_preferred":[
        "Cedro"
    ],
    "name:fra_x_preferred":[
        "Cedro"
    ],
    "name:ita_x_preferred":[
        "Cedro"
    ],
    "name:kat_x_preferred":[
        "\u10e1\u10d4\u10e0\u10d3\u10e3"
    ],
    "name:kaz_x_preferred":[
        "\u0421\u0435\u0434\u0440\u0443"
    ],
    "name:nld_x_preferred":[
        "Cedro"
    ],
    "name:nor_x_preferred":[
        "Cedro"
    ],
    "name:por_x_preferred":[
        "Cedro"
    ],
    "name:ron_x_preferred":[
        "Cedro"
    ],
    "name:rus_x_preferred":[
        "\u0421\u0435\u0434\u0440\u0443"
    ],
    "name:spa_x_preferred":[
        "Cedro"
    ],
    "name:und_x_variant":[
        "Hacienda Cedro"
    ],
    "name:vol_x_preferred":[
        "Cedro"
    ],
    "name:war_x_preferred":[
        "Cedro"
    ],
    "name:zho_x_preferred":[
        "\u585e\u5fb7\u9c81"
    ],
    "wof:name":"Cedro",
    "wof:placetype":"locality"
},
  "geometry": {"coordinates":[-75.36667,9.93333],"type":"Point"}
}