{
  "type": "Feature",
  "properties": {
    "iso:country":"CO",
    "name:ast_x_preferred":[
        "Chitag\u00e1"
    ],
    "name:ceb_x_preferred":[
        "Chitag\u00e1"
    ],
    "name:eng_x_preferred":[
        "Chitag\u00e1"
    ],
    "name:fra_x_preferred":[
        "Chitag\u00e1"
    ],
    "name:gla_x_preferred":[
        "Chitag\u00e1"
    ],
    "name:ita_x_preferred":[
        "Chitag\u00e1"
    ],
    "name:kat_x_preferred":[
        "\u10e9\u10d8\u10e2\u10d0\u10d2\u10d0"
    ],
    "name:msa_x_preferred":[
        "Chitag\u00e1"
    ],
    "name:nan_x_preferred":[
        "Chitag\u00e1"
    ],
    "name:nld_x_preferred":[
        "Chitag\u00e1"
    ],
    "name:por_x_preferred":[
        "Chitag\u00e1"
    ],
    "name:spa_x_preferred":[
        "Chitag\u00e1"
    ],
    "name:swe_x_preferred":[
        "Chitag\u00e1"
    ],
    "name:tgl_x_preferred":[
        "Chitag\u00e1"
    ],
    "name:vie_x_preferred":[
        "Chitag\u00e1"
    ],
    "name:war_x_preferred":[
        "Chitag\u00e1"
    ],
    "name:zho_x_preferred":[
        "\u5947\u5854\u52a0"
    ],
    "qs:gn_country":"CO",
    "qs:gn_fcode":"PPL",
    "qs:gn_pop":3871,
    "qs:name":"Chitag\u00e1",
    "qs:name_adm0":"Colombia",
    "qs:name_adm1":"Norte de Santander",
    "qs:photos":0,
    "qs:photos_1k":0,
    "qs:photos_9k":0,
    "qs:photos_9r":0,
    "qs:photos_all":0,
    "qs:photos_sr":0,
    "qs:placetype":"Town",
    "qs:pop_sr":"4",
    "qs:woe_adm0":23424787,
    "wd:wordcount":45,
    "wof:name":"Chitag\u00e1",
    "wof:placetype":"locality",
    "wof:population":3871
},
  "geometry": {"coordinates":[-72.66455999999999,7.13781],"type":"Point"}
}