{
  "type": "Feature",
  "properties": {
    "iso:country":"CO",
    "name:ceb_x_preferred":[
        "Obando"
    ],
    "name:deu_x_preferred":[
        "Obando"
    ],
    "name:fra_x_preferred":[
        "Obando"
    ],
    "name:ita_x_preferred":[
        "Obando"
    ],
    "name:jpn_x_preferred":[
        "\u30aa\u30d0\u30f3\u30c9\u30fc"
    ],
    "name:nds_x_preferred":[
        "Obando"
    ],
    "name:nld_x_preferred":[
        "Obando"
    ],
    "name:sco_x_preferred":[
        "Obando"
    ],
    "name:spa_x_preferred":[
        "Obando"
    ],
    "name:swe_x_preferred":[
        "Obando"
    ],
    "name:tgl_x_preferred":[
        "Obando"
    ],
    "name:war_x_preferred":[
        "Obando"
    ],
    "qs:gn_country":"CO",
    "qs:gn_fcode":"PPL",
    "qs:gn_pop":0,
    "qs:name":"Obando",
    "qs:name_adm0":"Colombia",
    "qs:name_adm1":"Valle del Cauca",
    "qs:photos":289,
    "qs:photos_1k":59,
    "qs:photos_9k":1,
    "qs:photos_9r":4,
    "qs:photos_all":289,
    "qs:photos_sr":5,
    "qs:placetype":"Town",
    "qs:pop_sr":"0",
    "qs:woe_adm0":23424787,
    "wd:wordcount":153,
    "wof:name":"Obando",
    "wof:placetype":"locality"
},
  "geometry": {"coordinates":[-76.40397,3.57557],"type":"Point"}
}