{
  "type": "Feature",
  "properties": {
    "gn:admin1_code":"26",
    "gn:admin2_code":"68081.0",
    "gn:asciiname":"El Llanito",
    "gn:country_code":"CO",
    "gn:dem":81,
    "gn:feature_class":"P",
    "gn:feature_code":"PPL",
    "gn:name":"El Llanito",
    "gn:population":0,
    "gn:timezone":"America/Bogota",
    "iso:country":"CO",
    "name:und_x_variant":[
        "Llanitos",
        "El Llanito"
    ],
    "wof:name":"El Llanito",
    "wof:placetype":"locality"
},
  "geometry": {"coordinates":[-73.84729,7.16693],"type":"Point"}
}