{
  "type": "Feature",
  "properties": {
    "gn:country":"CO",
    "gn:fcode":"PPL",
    "gn:population":2988,
    "iso:country":"CO",
    "name:ast_x_preferred":[
        "San Bernardo"
    ],
    "name:ceb_x_preferred":[
        "San Bernardo"
    ],
    "name:deu_x_preferred":[
        "San Bernardo"
    ],
    "name:eng_x_preferred":[
        "San Bernardo"
    ],
    "name:fra_x_preferred":[
        "San Bernardo"
    ],
    "name:ita_x_preferred":[
        "San Bernardo"
    ],
    "name:kat_x_preferred":[
        "\u10e1\u10d0\u10dc-\u10d1\u10d4\u10e0\u10dc\u10d0\u10e0\u10d3\u10dd"
    ],
    "name:msa_x_preferred":[
        "San Bernardo"
    ],
    "name:nan_x_preferred":[
        "San Bernardo"
    ],
    "name:nld_x_preferred":[
        "San Bernardo"
    ],
    "name:por_x_preferred":[
        "San Bernardo"
    ],
    "name:sco_x_preferred":[
        "San Bernardo"
    ],
    "name:spa_x_preferred":[
        "San Bernardo"
    ],
    "name:swe_x_preferred":[
        "San Bernardo"
    ],
    "name:tgl_x_preferred":[
        "San Bernardo"
    ],
    "name:vie_x_preferred":[
        "San Bernardo"
    ],
    "name:war_x_preferred":[
        "San Bernardo"
    ],
    "name:zho_x_preferred":[
        "\u8056\u8c9d\u723e\u7d0d\u591a"
    ],
    "qs:name":"San Bernardo",
    "qs:photos_9r":0,
    "qs:photos_sr":0,
    "qs:pop_sr":"4",
    "wd:wordcount":122,
    "wof:name":"San Bernardo",
    "wof:placetype":"locality",
    "wof:population":2988
},
  "geometry": {"coordinates":[-77.03091000000001,1.52119],"type":"Point"}
}