{
  "type": "Feature",
  "properties": {
    "gn:admin1_code":"16",
    "gn:admin2_code":"41770.0",
    "gn:asciiname":"Maticas",
    "gn:country_code":"CO",
    "gn:dem":2150,
    "gn:feature_class":"P",
    "gn:feature_code":"PPL",
    "gn:name":"Maticas",
    "gn:population":0,
    "gn:timezone":"America/Bogota",
    "iso:country":"CO",
    "name:und_x_variant":[
        "Marticas",
        "Maticas"
    ],
    "wof:name":"Maticas",
    "wof:placetype":"locality"
},
  "geometry": {"coordinates":[-75.85319,1.75162],"type":"Point"}
}