{
  "type": "Feature",
  "properties": {
    "gn:admin1_code":"17",
    "gn:admin2_code":"44847.0",
    "gn:asciiname":"Arpajaco",
    "gn:cc2":"CO",
    "gn:country_code":"CO",
    "gn:dem":-18,
    "gn:feature_class":"P",
    "gn:feature_code":"PPL",
    "gn:name":"Arpajaco",
    "gn:population":0,
    "gn:timezone":"America/Bogota",
    "iso:country":"CO",
    "name:und_x_variant":[
        "Atpajauohu",
        "Arpajaco"
    ],
    "wof:name":"Arpajaco",
    "wof:placetype":"locality"
},
  "geometry": {"coordinates":[-71.26666999999998,12.23333],"type":"Point"}
}