{
  "type": "Feature",
  "properties": {
    "gn:admin1_code":"33.0",
    "gn:admin2_code":"25290.0",
    "gn:asciiname":"Novillero",
    "gn:country_code":"CO",
    "gn:dem":1536,
    "gn:feature_class":"P",
    "gn:feature_code":"PPL",
    "gn:name":"Novillero",
    "gn:population":0,
    "gn:timezone":"America/Bogota",
    "iso:country":"CO",
    "wof:name":"Novillero",
    "wof:placetype":"locality"
},
  "geometry": {"coordinates":[-74.39579000000001,4.34638],"type":"Point"}
}