{
  "type": "Feature",
  "properties": {
    "gn:admin1_code":"20.0",
    "gn:admin2_code":"52427.0",
    "gn:asciiname":"Boca de Amburgo",
    "gn:country_code":"CO",
    "gn:dem":27,
    "gn:feature_class":"P",
    "gn:feature_code":"PPL",
    "gn:name":"Boca de Amburgo",
    "gn:population":0,
    "gn:timezone":"America/Bogota",
    "iso:country":"CO",
    "wof:name":"Boca de Amburgo",
    "wof:placetype":"locality"
},
  "geometry": {"coordinates":[-78.223,1.83168],"type":"Point"}
}