{
  "type": "Feature",
  "properties": {
    "gn:admin1_code":"10",
    "gn:admin2_code":"20013.0",
    "gn:asciiname":"Platanal",
    "gn:country_code":"CO",
    "gn:dem":60,
    "gn:feature_class":"P",
    "gn:feature_code":"PPL",
    "gn:name":"Platanal",
    "gn:population":0,
    "gn:timezone":"America/Bogota",
    "iso:country":"CO",
    "wof:name":"Platanal",
    "wof:placetype":"locality"
},
  "geometry": {"coordinates":[-73.41731,9.79984],"type":"Point"}
}