{
  "type": "Feature",
  "properties": {
    "gn:admin1_code":"26.0",
    "gn:admin2_code":"68464.0",
    "gn:asciiname":"Pitiguao",
    "gn:country_code":"CO",
    "gn:dem":1691,
    "gn:feature_class":"P",
    "gn:feature_code":"PPL",
    "gn:name":"Pitiguao",
    "gn:population":0,
    "gn:timezone":"America/Bogota",
    "iso:country":"CO",
    "wof:name":"Pitiguao",
    "wof:placetype":"locality"
},
  "geometry": {"coordinates":[-72.96382,6.58689],"type":"Point"}
}