{
  "type": "Feature",
  "properties": {
    "gn:admin1_code":"28.0",
    "gn:admin2_code":"73226.0",
    "gn:asciiname":"Vereda Mesa de Ramirez",
    "gn:country_code":"CO",
    "gn:dem":553,
    "gn:feature_class":"P",
    "gn:feature_code":"PPLL",
    "gn:name":"Vereda Mesa de Ramirez",
    "gn:population":0,
    "gn:timezone":"America/Bogota",
    "iso:country":"CO",
    "name:spa_x_preferred":[
        "Vereda Mesa de Ramirez"
    ],
    "wof:name":"Vereda Mesa de Ramirez",
    "wof:placetype":"locality"
},
  "geometry": {"coordinates":[-74.69826,3.99775],"type":"Point"}
}