{
  "type": "Feature",
  "properties": {
    "gn:admin1_code":"20.0",
    "gn:admin2_code":"52227.0",
    "gn:asciiname":"Tolas",
    "gn:country_code":"CO",
    "gn:dem":3291,
    "gn:feature_class":"P",
    "gn:feature_code":"PPL",
    "gn:name":"Tolas",
    "gn:population":0,
    "gn:timezone":"America/Bogota",
    "iso:country":"CO",
    "wof:name":"Tolas",
    "wof:placetype":"locality"
},
  "geometry": {"coordinates":[-77.81836,0.91887],"type":"Point"}
}