{
  "type": "Feature",
  "properties": {
    "gn:admin1_code":"1.0",
    "gn:admin2_code":"91530.0",
    "gn:asciiname":"Puerto Alegria",
    "gn:country_code":"CO",
    "gn:dem":167,
    "gn:feature_class":"P",
    "gn:feature_code":"PPL",
    "gn:name":"Puerto Alegr\u00eda",
    "gn:population":0,
    "gn:timezone":"America/Bogota",
    "iso:country":"CO",
    "name:und_x_variant":[
        "Puerto Alegr\u00eda"
    ],
    "wof:name":"Puerto Alegria",
    "wof:placetype":"locality"
},
  "geometry": {"coordinates":[-74.03333000000001,-1.03333],"type":"Point"}
}