{
  "type": "Feature",
  "properties": {
    "gn:admin1_code":"1.0",
    "gn:admin2_code":"91530.0",
    "gn:asciiname":"Puerto Alegria",
    "gn:country_code":"CO",
    "gn:dem":167,
    "gn:feature_class":"P",
    "gn:feature_code":"PPL",
    "gn:name":"Puerto Alegr\u00eda",
    "gn:population":0,
    "gn:timezone":"America/Bogota",
    "iso:country":"CO",
    "name:cat_x_preferred":[
        "Puerto Alegr\u00eda"
    ],
    "name:ceb_x_preferred":[
        "Puerto Alegr\u00eda"
    ],
    "name:fra_x_preferred":[
        "Puerto Alegr\u00eda"
    ],
    "name:ilo_x_preferred":[
        "Puerto Alegr\u00eda"
    ],
    "name:ita_x_preferred":[
        "Puerto Alegr\u00eda"
    ],
    "name:kat_x_preferred":[
        "\u10de\u10e3\u10d4\u10e0\u10e2\u10dd-\u10d0\u10da\u10d4\u10d2\u10e0\u10d8\u10d0"
    ],
    "name:msa_x_preferred":[
        "Puerto Alegr\u00eda"
    ],
    "name:nld_x_preferred":[
        "Puerto Alegr\u00eda"
    ],
    "name:rus_x_preferred":[
        "\u041f\u0443\u044d\u0440\u0442\u043e-\u0410\u043b\u0435\u0433\u0440\u0438\u044f"
    ],
    "name:spa_x_preferred":[
        "Puerto Alegr\u00eda"
    ],
    "name:swe_x_preferred":[
        "Puerto Alegr\u00eda"
    ],
    "name:tgl_x_preferred":[
        "Puerto Alegr\u00eda"
    ],
    "name:vie_x_preferred":[
        "Puerto Alegria"
    ],
    "name:war_x_preferred":[
        "Puerto Alegr\u00eda"
    ],
    "name:zho_x_preferred":[
        "\u963f\u840a\u683c\u91cc\u4e9e\u6e2f"
    ],
    "wof:name":"Puerto Alegria",
    "wof:placetype":"locality"
},
  "geometry": {"coordinates":[-74.03333000000001,-1.03333],"type":"Point"}
}