{
  "type": "Feature",
  "properties": {
    "gn:admin1_code":"32.0",
    "gn:admin2_code":"85410.0",
    "gn:asciiname":"Villa Carola",
    "gn:country_code":"CO",
    "gn:dem":219,
    "gn:feature_class":"P",
    "gn:feature_code":"PPL",
    "gn:name":"Villa Carola",
    "gn:population":0,
    "gn:timezone":"America/Bogota",
    "iso:country":"CO",
    "wof:name":"Villa Carola",
    "wof:placetype":"locality"
},
  "geometry": {"coordinates":[-72.71666999999999,4.78333],"type":"Point"}
}