{
  "type": "Feature",
  "properties": {
    "gn:admin1_code":"8.0",
    "gn:admin2_code":"18029.0",
    "gn:asciiname":"La Suiza",
    "gn:country_code":"CO",
    "gn:dem":264,
    "gn:feature_class":"P",
    "gn:feature_code":"PPL",
    "gn:name":"La Suiza",
    "gn:population":0,
    "gn:timezone":"America/Bogota",
    "iso:country":"CO",
    "name:spa_x_preferred":[
        "La Suiza"
    ],
    "wof:name":"La Suiza",
    "wof:placetype":"locality"
},
  "geometry": {"coordinates":[-75.89216999999999,1.21541],"type":"Point"}
}