{
  "type": "Feature",
  "properties": {
    "gn:admin1_code":"14.0",
    "gn:admin2_code":"95001.0",
    "gn:asciiname":"El Yare",
    "gn:country_code":"CO",
    "gn:dem":179,
    "gn:feature_class":"P",
    "gn:feature_code":"PPL",
    "gn:name":"El Yare",
    "gn:population":0,
    "gn:timezone":"America/Bogota",
    "iso:country":"CO",
    "wof:name":"El Yare",
    "wof:placetype":"locality"
},
  "geometry": {"coordinates":[-72.33530999999998,2.70449],"type":"Point"}
}