{
  "type": "Feature",
  "properties": {
    "gn:admin1_code":"2.0",
    "gn:admin2_code":"5380.0",
    "gn:asciiname":"Sitio La Raya",
    "gn:country_code":"CO",
    "gn:dem":1743,
    "gn:feature_class":"P",
    "gn:feature_code":"PPL",
    "gn:name":"Sitio La Raya",
    "gn:population":0,
    "gn:timezone":"America/Bogota",
    "iso:country":"CO",
    "name:spa_x_preferred":[
        "Sitio La Raya"
    ],
    "wof:name":"Sitio La Raya",
    "wof:placetype":"locality"
},
  "geometry": {"coordinates":[-75.63628,6.11201],"type":"Point"}
}