{
  "type": "Feature",
  "properties": {
    "gn:admin1_code":"26.0",
    "gn:admin2_code":"68235.0",
    "gn:asciiname":"Tierra Grata",
    "gn:country_code":"CO",
    "gn:dem":372,
    "gn:feature_class":"P",
    "gn:feature_code":"PPLL",
    "gn:name":"Tierra Grata",
    "gn:population":0,
    "gn:timezone":"America/Bogota",
    "iso:country":"CO",
    "wof:name":"Tierra Grata",
    "wof:placetype":"locality"
},
  "geometry": {"coordinates":[-73.56679,6.69624],"type":"Point"}
}