{
  "type": "Feature",
  "properties": {
    "gn:admin1_code":"32",
    "gn:admin2_code":"85410.0",
    "gn:asciiname":"La Maporita",
    "gn:country_code":"CO",
    "gn:dem":309,
    "gn:feature_class":"P",
    "gn:feature_code":"PPL",
    "gn:name":"La Maporita",
    "gn:population":0,
    "gn:timezone":"America/Bogota",
    "iso:country":"CO",
    "wof:name":"La Maporita",
    "wof:placetype":"locality"
},
  "geometry": {"coordinates":[-72.68836999999998,5.00306],"type":"Point"}
}