{
  "type": "Feature",
  "properties": {
    "gn:admin1_code":"4.0",
    "gn:admin2_code":"8832.0",
    "gn:asciiname":"Charco Grande",
    "gn:country_code":"CO",
    "gn:dem":17,
    "gn:feature_class":"P",
    "gn:feature_code":"PPL",
    "gn:name":"Charco Grande",
    "gn:population":0,
    "gn:timezone":"America/Bogota",
    "iso:country":"CO",
    "wof:name":"Charco Grande",
    "wof:placetype":"locality"
},
  "geometry": {"coordinates":[-75.02457,10.91309],"type":"Point"}
}