{
  "type": "Feature",
  "properties": {
    "gn:admin1_code":"8.0",
    "gn:admin2_code":"18860.0",
    "gn:asciiname":"La Ye",
    "gn:country_code":"CO",
    "gn:dem":232,
    "gn:feature_class":"P",
    "gn:feature_code":"PPL",
    "gn:name":"La Ye",
    "gn:population":0,
    "gn:timezone":"America/Bogota",
    "iso:country":"CO",
    "name:spa_x_preferred":[
        "La Ye"
    ],
    "wof:name":"La Ye",
    "wof:placetype":"locality"
},
  "geometry": {"coordinates":[-75.70031,1.18288],"type":"Point"}
}