{
  "type": "Feature",
  "properties": {
    "gn:admin1_code":"10",
    "gn:admin2_code":"20175.0",
    "gn:asciiname":"Guamal",
    "gn:country_code":"CO",
    "gn:dem":53,
    "gn:feature_class":"P",
    "gn:feature_code":"PPL",
    "gn:name":"Guamal",
    "gn:population":0,
    "gn:timezone":"America/Bogota",
    "iso:country":"CO",
    "name:deu_x_preferred":[
        "Guamal"
    ],
    "name:fas_x_preferred":[
        "\u06af\u0648\u0622\u0645\u0627\u0644"
    ],
    "name:fra_x_preferred":[
        "Guamal"
    ],
    "name:ita_x_preferred":[
        "Guamal"
    ],
    "name:kat_x_preferred":[
        "\u10d2\u10e3\u10d0\u10db\u10d0\u10da\u10d8"
    ],
    "name:msa_x_preferred":[
        "Guamal"
    ],
    "name:nld_x_preferred":[
        "Guamal"
    ],
    "name:por_x_preferred":[
        "Guamal"
    ],
    "name:rus_x_preferred":[
        "\u0413\u0443\u0430\u043c\u0430\u043b\u044c"
    ],
    "name:sco_x_preferred":[
        "Guamal"
    ],
    "name:spa_x_preferred":[
        "Guamal"
    ],
    "name:tgl_x_preferred":[
        "Guamal"
    ],
    "name:vie_x_preferred":[
        "Guamal"
    ],
    "name:war_x_preferred":[
        "Guamal"
    ],
    "name:zho_x_preferred":[
        "\u74dc\u99ac\u723e"
    ],
    "wof:name":"Guamal",
    "wof:placetype":"locality"
},
  "geometry": {"coordinates":[-73.65971999999999,9.07278],"type":"Point"}
}