{
  "type": "Feature",
  "properties": {
    "gn:admin1_code":"31",
    "gn:admin2_code":"99524.0",
    "gn:asciiname":"La Arenosa",
    "gn:country_code":"CO",
    "gn:dem":119,
    "gn:feature_class":"P",
    "gn:feature_code":"PPL",
    "gn:name":"La Arenosa",
    "gn:population":0,
    "gn:timezone":"America/Bogota",
    "iso:country":"CO",
    "wof:name":"La Arenosa",
    "wof:placetype":"locality"
},
  "geometry": {"coordinates":[-70.45,5.41667],"type":"Point"}
}