{
  "type": "Feature",
  "properties": {
    "gn:gn_country":"CO",
    "gn:gn_fcode":"PPL",
    "gn:gn_pop":3724,
    "gn:population":3724,
    "iso:country":"CO",
    "name:deu_x_preferred":[
        "Puerto Rond\u00f3n"
    ],
    "name:eng_x_preferred":[
        "Puerto Rond\u00f3n"
    ],
    "name:fra_x_preferred":[
        "Puerto Rond\u00f3n"
    ],
    "name:ita_x_preferred":[
        "Puerto Rond\u00f3n"
    ],
    "name:kat_x_preferred":[
        "\u10de\u10e3\u10d4\u10e0\u10e2\u10dd-\u10e0\u10dd\u10dc\u10d3\u10dd\u10dc\u10d8"
    ],
    "name:msa_x_preferred":[
        "Puerto Rond\u00f3n"
    ],
    "name:nan_x_preferred":[
        "Puerto Rond\u00f3n"
    ],
    "name:nld_x_preferred":[
        "Puerto Rond\u00f3n"
    ],
    "name:por_x_preferred":[
        "Puerto Rond\u00f3n"
    ],
    "name:rus_x_preferred":[
        "\u041f\u0443\u044d\u0440\u0442\u043e-\u0420\u043e\u043d\u0434\u043e\u043d"
    ],
    "name:sco_x_preferred":[
        "Puerto Rond\u00f3n"
    ],
    "name:spa_x_preferred":[
        "Puerto Rond\u00f3n"
    ],
    "name:swe_x_preferred":[
        "Puerto Rond\u00f3n"
    ],
    "name:tgl_x_preferred":[
        "Puerto Rond\u00f3n"
    ],
    "name:unk_x_variant":[
        "El Padre"
    ],
    "name:vie_x_preferred":[
        "Puerto Rond\u00f3n"
    ],
    "name:war_x_preferred":[
        "Puerto Rond\u00f3n"
    ],
    "name:zho_x_preferred":[
        "\u9f8d\u6771\u6e2f"
    ],
    "qs_pg:aaroncc":"CO",
    "qs_pg:gn_country":"CO",
    "qs_pg:gn_fcode":"PPL",
    "qs_pg:gn_pop":3724,
    "qs_pg:name":"Puerto Rond\u00f3n",
    "qs_pg:photos_9r":0,
    "qs_pg:photos_sr":0,
    "qs_pg:pop_sr":4,
    "qs_pg:qs_pg_placetype":"locality",
    "wof:name":"Puerto Rond\u00f3n",
    "wof:placetype":"locality",
    "wof:population":3724
},
  "geometry": {"coordinates":[-71.09999999999999,6.28048],"type":"Point"}
}