{
  "type": "Feature",
  "properties": {
    "gn:admin1_code":"9.0",
    "gn:admin2_code":"19824.0",
    "gn:asciiname":"Vereda San Jose",
    "gn:country_code":"CO",
    "gn:dem":2326,
    "gn:feature_class":"P",
    "gn:feature_code":"PPLL",
    "gn:name":"Vereda San Jose",
    "gn:population":0,
    "gn:timezone":"America/Bogota",
    "iso:country":"CO",
    "name:spa_x_preferred":[
        "Vereda San Jose"
    ],
    "wof:name":"Vereda San Jose",
    "wof:placetype":"locality"
},
  "geometry": {"coordinates":[-76.44382,2.48168],"type":"Point"}
}