{
  "type": "Feature",
  "properties": {
    "gn:country":"CO",
    "gn:fcode":"PPL",
    "gn:pop":3851,
    "iso:country":"CO",
    "name:chi_x_preferred":[
        "\u62c9\u6885\u723e\u585e"
    ],
    "name:dut_x_preferred":[
        "La Merced"
    ],
    "name:eng_x_preferred":[
        "La Merced"
    ],
    "name:fre_x_preferred":[
        "La Merced"
    ],
    "name:geo_x_preferred":[
        "\u10da\u10d0-\u10db\u10d4\u10e0\u10e1\u10d4\u10d3\u10d8"
    ],
    "name:gla_x_preferred":[
        "La Merced"
    ],
    "name:ita_x_preferred":[
        "La Merced"
    ],
    "name:may_x_preferred":[
        "La Merced"
    ],
    "name:nan_x_preferred":[
        "La Merced"
    ],
    "name:por_x_preferred":[
        "La Merced"
    ],
    "name:rus_x_preferred":[
        "\u041b\u0430-\u041c\u0435\u0440\u0441\u0435\u0434"
    ],
    "name:spa_x_preferred":[
        "La Merced"
    ],
    "name:tgl_x_preferred":[
        "La Merced"
    ],
    "name:urd_x_preferred":[
        "\u0644\u0627 \u0645\u0631\u0633\u06cc\u0688\u060c \u06a9\u0627\u0644\u0688\u0627\u0633"
    ],
    "name:war_x_preferred":[
        "La Merced"
    ],
    "qs:name":"La Merced",
    "qs:photos_9r":0,
    "qs:photos_sr":0,
    "qs:pop_sr":"4",
    "wd:wordcount":106,
    "wof:name":"La Merced",
    "wof:placetype":"locality",
    "wof:population":3851
},
  "geometry": {"coordinates":[-75.88472,5.40194],"type":"Point"}
}