{
  "type": "Feature",
  "properties": {
    "iso:country":"CO",
    "name:ast_x_preferred":[
        "Sardinata"
    ],
    "name:ceb_x_preferred":[
        "Sardinata"
    ],
    "name:deu_x_preferred":[
        "Sardinata"
    ],
    "name:eng_x_preferred":[
        "Sardinata"
    ],
    "name:fas_x_preferred":[
        "\u0633\u0627\u0631\u062f\u06cc\u0646\u0627\u062a\u0627"
    ],
    "name:fra_x_preferred":[
        "Sardinata"
    ],
    "name:ita_x_preferred":[
        "Sardinata"
    ],
    "name:jpn_x_preferred":[
        "\u30b5\u30eb\u30c7\u30a3\u30ca\u30bf"
    ],
    "name:kat_x_preferred":[
        "\u10e1\u10d0\u10e0\u10d3\u10d8\u10dc\u10d0\u10e2\u10d0"
    ],
    "name:msa_x_preferred":[
        "Sardinata"
    ],
    "name:nan_x_preferred":[
        "Sardinata"
    ],
    "name:nld_x_preferred":[
        "Sardinata"
    ],
    "name:por_x_preferred":[
        "Sardinata"
    ],
    "name:spa_x_preferred":[
        "Sardinata"
    ],
    "name:swe_x_preferred":[
        "Sardinata"
    ],
    "name:tgl_x_preferred":[
        "Sardinata"
    ],
    "name:vie_x_preferred":[
        "Sardinata"
    ],
    "name:war_x_preferred":[
        "Sardinata"
    ],
    "name:zho_min_nan_x_preferred":[
        "Sardinata"
    ],
    "name:zho_x_preferred":[
        "\u85a9\u723e\u8fea\u7d0d\u5854"
    ],
    "qs:gn_country":"CO",
    "qs:gn_fcode":"PPL",
    "qs:gn_pop":7872,
    "qs:name":"Sardinata",
    "qs:name_adm0":"Colombia",
    "qs:name_adm1":"Norte de Santander",
    "qs:photos":0,
    "qs:photos_1k":0,
    "qs:photos_9k":0,
    "qs:photos_9r":0,
    "qs:photos_all":0,
    "qs:photos_sr":0,
    "qs:placetype":"Town",
    "qs:pop_sr":"5",
    "qs:woe_adm0":23424787,
    "wd:wordcount":31,
    "wof:name":"Sardinata",
    "wof:placetype":"locality",
    "wof:population":7872
},
  "geometry": {"coordinates":[-72.80071,8.08289],"type":"Point"}
}