{
  "type": "Feature",
  "properties": {
    "gn:admin1_code":"35.0",
    "gn:admin2_code":"13001.0",
    "gn:asciiname":"Rafael Nunez",
    "gn:country_code":"CO",
    "gn:dem":6,
    "gn:feature_class":"P",
    "gn:feature_code":"PPL",
    "gn:name":"Rafael Nu\u00f1ez",
    "gn:population":0,
    "gn:timezone":"America/Bogota",
    "iso:country":"CO",
    "wof:name":"Rafael Nunez",
    "wof:placetype":"locality"
},
  "geometry": {"coordinates":[-75.51519999999999,10.44504],"type":"Point"}
}