{
  "type": "Feature",
  "properties": {
    "gn:admin1_code":"33.0",
    "gn:admin2_code":"25473.0",
    "gn:asciiname":"Mondonedo",
    "gn:country_code":"CO",
    "gn:dem":2558,
    "gn:feature_class":"P",
    "gn:feature_code":"PPL",
    "gn:name":"Mondo\u00f1edo",
    "gn:population":0,
    "gn:timezone":"America/Bogota",
    "iso:country":"CO",
    "wof:name":"Mondonedo",
    "wof:placetype":"locality"
},
  "geometry": {"coordinates":[-74.25323,4.68186],"type":"Point"}
}