{
  "type": "Feature",
  "properties": {
    "iso:country":"CO",
    "name:ceb_x_preferred":[
        "Acand\u00ed"
    ],
    "name:eng_x_preferred":[
        "Acand\u00ed"
    ],
    "name:fas_x_preferred":[
        "\u0627\u06a9\u0627\u0646\u062f\u06cc"
    ],
    "name:fra_x_preferred":[
        "Acand\u00ed"
    ],
    "name:ita_x_preferred":[
        "Acand\u00ed"
    ],
    "name:jpn_x_preferred":[
        "\u30a2\u30ab\u30f3\u30c7\u30a3"
    ],
    "name:kat_x_preferred":[
        "\u10d0\u10d9\u10d0\u10dc\u10d3\u10d8"
    ],
    "name:msa_x_preferred":[
        "Acand\u00ed"
    ],
    "name:nan_x_preferred":[
        "Acand\u00ed"
    ],
    "name:nld_x_preferred":[
        "Acand\u00ed"
    ],
    "name:por_x_preferred":[
        "Acand\u00ed"
    ],
    "name:rus_x_preferred":[
        "\u0410\u043a\u0430\u043d\u0434\u0438"
    ],
    "name:spa_x_preferred":[
        "Acand\u00ed"
    ],
    "name:swe_x_preferred":[
        "Acand\u00ed"
    ],
    "name:tgl_x_preferred":[
        "Acand\u00ed"
    ],
    "name:unk_x_variant":[
        "Acanti"
    ],
    "name:vie_x_preferred":[
        "Acand\u00ed"
    ],
    "name:war_x_preferred":[
        "Acand\u00ed"
    ],
    "name:zho_x_preferred":[
        "\u963f\u574e\u8fea"
    ],
    "qs:gn_country":"CO",
    "qs:gn_fcode":"PPL",
    "qs:gn_pop":4840,
    "qs:name":"Acand\u00ed",
    "qs:name_adm0":"Colombia",
    "qs:name_adm1":"Choco",
    "qs:photos":66,
    "qs:photos_1k":13,
    "qs:photos_9k":1,
    "qs:photos_9r":2,
    "qs:photos_all":66,
    "qs:photos_sr":2,
    "qs:placetype":"Town",
    "qs:pop_sr":"4",
    "qs:woe_adm0":23424787,
    "wof:name":"Acand\u00ed",
    "wof:placetype":"locality",
    "wof:population":4840
},
  "geometry": {"coordinates":[-77.27784,8.50633],"type":"Point"}
}