{
  "type": "Feature",
  "properties": {
    "gn:admin1_code":"12.0",
    "gn:admin2_code":"23001.0",
    "gn:asciiname":"La Viuda",
    "gn:country_code":"CO",
    "gn:dem":80,
    "gn:feature_class":"P",
    "gn:feature_code":"PPL",
    "gn:name":"La Viuda",
    "gn:population":0,
    "gn:timezone":"America/Bogota",
    "iso:country":"CO",
    "wof:name":"La Viuda",
    "wof:placetype":"locality"
},
  "geometry": {"coordinates":[-76.13403000000002,8.4144],"type":"Point"}
}