{
  "type": "Feature",
  "properties": {
    "gn:admin1_code":"26",
    "gn:admin2_code":"68669.0",
    "gn:asciiname":"El Pire",
    "gn:country_code":"CO",
    "gn:dem":2154,
    "gn:feature_class":"P",
    "gn:feature_code":"PPL",
    "gn:name":"El Pire",
    "gn:population":0,
    "gn:timezone":"America/Bogota",
    "iso:country":"CO",
    "name:und_x_variant":[
        "Pire",
        "El Pire"
    ],
    "wof:name":"El Pire",
    "wof:placetype":"locality"
},
  "geometry": {"coordinates":[-72.85892,6.82676],"type":"Point"}
}