{
  "type": "Feature",
  "properties": {
    "gn:admin1_code":"38",
    "gn:admin2_code":"47268.0",
    "gn:asciiname":"Jerusalen",
    "gn:country_code":"CO",
    "gn:dem":21,
    "gn:feature_class":"P",
    "gn:feature_code":"PPL",
    "gn:name":"Jerusal\u00e9n",
    "gn:population":0,
    "gn:timezone":"America/Bogota",
    "iso:country":"CO",
    "name:und_x_variant":[
        "Hacienda Jerusal\u00e9n",
        "Jerusal\u00e9n"
    ],
    "wof:name":"Jerusalen",
    "wof:placetype":"locality"
},
  "geometry": {"coordinates":[-74.2761,10.66285],"type":"Point"}
}