{
  "type": "Feature",
  "properties": {
    "gn:admin1_code":"33.0",
    "gn:admin2_code":"25878.0",
    "gn:asciiname":"Vereda El Espino",
    "gn:country_code":"CO",
    "gn:dem":561,
    "gn:feature_class":"P",
    "gn:feature_code":"PPLL",
    "gn:name":"Vereda El Espino",
    "gn:population":0,
    "gn:timezone":"America/Bogota",
    "iso:country":"CO",
    "name:spa_x_preferred":[
        "Vereda El Espino"
    ],
    "wof:name":"Vereda El Espino",
    "wof:placetype":"locality"
},
  "geometry": {"coordinates":[-74.55565,4.46491],"type":"Point"}
}