{
  "type": "Feature",
  "properties": {
    "gn:admin1_code":"29",
    "gn:admin2_code":"76834.0",
    "gn:asciiname":"La Profunda",
    "gn:country_code":"CO",
    "gn:dem":2196,
    "gn:feature_class":"P",
    "gn:feature_code":"PPL",
    "gn:name":"La Profunda",
    "gn:population":0,
    "gn:timezone":"America/Bogota",
    "iso:country":"CO",
    "wof:name":"La Profunda",
    "wof:placetype":"locality"
},
  "geometry": {"coordinates":[-75.85583000000003,4.03611],"type":"Point"}
}