{
  "type": "Feature",
  "properties": {
    "gn:admin1_code":"22.0",
    "gn:asciiname":"Remolino",
    "gn:country_code":"CO",
    "gn:dem":247,
    "gn:feature_class":"P",
    "gn:feature_code":"PPL",
    "gn:name":"Remolino",
    "gn:population":0,
    "gn:timezone":"America/Bogota",
    "iso:country":"CO",
    "wof:name":"Remolino",
    "wof:placetype":"locality"
},
  "geometry": {"coordinates":[-76.22154999999999,0.37395],"type":"Point"}
}