{
  "type": "Feature",
  "properties": {
    "gn:admin1_code":"20.0",
    "gn:admin2_code":"52378.0",
    "gn:asciiname":"Las Aradas",
    "gn:country_code":"CO",
    "gn:dem":2195,
    "gn:feature_class":"P",
    "gn:feature_code":"PPL",
    "gn:name":"Las Aradas",
    "gn:population":0,
    "gn:timezone":"America/Bogota",
    "iso:country":"CO",
    "name:spa_x_preferred":[
        "Las Aradas"
    ],
    "wof:name":"Las Aradas",
    "wof:placetype":"locality"
},
  "geometry": {"coordinates":[-76.97479,1.62848],"type":"Point"}
}