{
  "type": "Feature",
  "properties": {
    "gn:admin1_code":"2",
    "gn:admin2_code":"5660.0",
    "gn:asciiname":"Buenos Aires",
    "gn:country_code":"CO",
    "gn:dem":1454,
    "gn:feature_class":"P",
    "gn:feature_code":"PPL",
    "gn:name":"Buenos Aires",
    "gn:population":0,
    "gn:timezone":"America/Bogota",
    "iso:country":"CO",
    "wof:name":"Buenos Aires",
    "wof:placetype":"locality"
},
  "geometry": {"coordinates":[-75.05667,6.11357],"type":"Point"}
}