{
  "type": "Feature",
  "properties": {
    "gn:admin1_code":"29",
    "gn:admin2_code":"76616.0",
    "gn:asciiname":"Buenos Aires",
    "gn:country_code":"CO",
    "gn:dem":1667,
    "gn:feature_class":"P",
    "gn:feature_code":"PPL",
    "gn:name":"Buenos Aires",
    "gn:population":0,
    "gn:timezone":"America/Bogota",
    "iso:country":"CO",
    "wof:name":"Buenos Aires",
    "wof:placetype":"locality"
},
  "geometry": {"coordinates":[-76.41667,4.11667],"type":"Point"}
}