{
  "type": "Feature",
  "properties": {
    "gn:admin1_code":"9",
    "gn:admin2_code":"19130.0",
    "gn:asciiname":"El Alto",
    "gn:country_code":"CO",
    "gn:dem":1324,
    "gn:feature_class":"P",
    "gn:feature_code":"PPL",
    "gn:name":"El Alto",
    "gn:population":0,
    "gn:timezone":"America/Bogota",
    "iso:country":"CO",
    "wof:name":"El Alto",
    "wof:placetype":"locality"
},
  "geometry": {"coordinates":[-76.74479000000002,2.7069],"type":"Point"}
}