{
  "type": "Feature",
  "properties": {
    "gn:admin1_code":"29",
    "gn:admin2_code":"76109",
    "gn:asciiname":"Las Palamas",
    "gn:country_code":"CO",
    "gn:dem":6,
    "gn:feature_class":"P",
    "gn:feature_code":"PPL",
    "gn:name":"Las Palamas",
    "gn:population":0,
    "gn:timezone":"America/Bogota",
    "iso:country":"CO",
    "wof:name":"Las Palamas",
    "wof:placetype":"locality"
},
  "geometry": {"coordinates":[-77.16401999999999,3.73802],"type":"Point"}
}