{
  "type": "Feature",
  "properties": {
    "gn:admin1_code":"35.0",
    "gn:admin2_code":"13248.0",
    "gn:asciiname":"Robles",
    "gn:country_code":"CO",
    "gn:dem":12,
    "gn:feature_class":"P",
    "gn:feature_code":"PPL",
    "gn:name":"Robles",
    "gn:population":0,
    "gn:timezone":"America/Bogota",
    "iso:country":"CO",
    "name:und_x_variant":[
        "Corregimiento Robles",
        "Palmar de Roble",
        "Robles"
    ],
    "wof:name":"Robles",
    "wof:placetype":"locality"
},
  "geometry": {"coordinates":[-74.84296999999999,10.07478],"type":"Point"}
}