{
  "type": "Feature",
  "properties": {
    "gn:admin1_code":"2.0",
    "gn:admin2_code":"5042.0",
    "gn:asciiname":"La Palma",
    "gn:country_code":"CO",
    "gn:dem":1779,
    "gn:feature_class":"P",
    "gn:feature_code":"PPL",
    "gn:name":"La Palma",
    "gn:population":0,
    "gn:timezone":"America/Bogota",
    "iso:country":"CO",
    "wof:name":"La Palma",
    "wof:placetype":"locality"
},
  "geometry": {"coordinates":[-75.95416999999998,6.53528],"type":"Point"}
}