{
  "type": "Feature",
  "properties": {
    "gn:admin1_code":"12",
    "gn:admin2_code":"23419.0",
    "gn:asciiname":"Barcelona",
    "gn:country_code":"CO",
    "gn:dem":92,
    "gn:feature_class":"P",
    "gn:feature_code":"PPL",
    "gn:name":"Barcelona",
    "gn:population":0,
    "gn:timezone":"America/Bogota",
    "iso:country":"CO",
    "wof:name":"Barcelona",
    "wof:placetype":"locality"
},
  "geometry": {"coordinates":[-76.19548,8.86623],"type":"Point"}
}