{
  "type": "Feature",
  "properties": {
    "gn:admin1_code":"19.0",
    "gn:admin2_code":"50689.0",
    "gn:asciiname":"Gorongoro",
    "gn:country_code":"CO",
    "gn:dem":298,
    "gn:feature_class":"P",
    "gn:feature_code":"PPLL",
    "gn:name":"Gorongoro",
    "gn:population":0,
    "gn:timezone":"America/Bogota",
    "iso:country":"CO",
    "name:spa_x_preferred":[
        "Gorongoro"
    ],
    "wof:name":"Gorongoro",
    "wof:placetype":"locality"
},
  "geometry": {"coordinates":[-73.44985,3.68958],"type":"Point"}
}