{
  "type": "Feature",
  "properties": {
    "gn:admin1_code":"29",
    "gn:admin2_code":"76736.0",
    "gn:asciiname":"Peralda",
    "gn:country_code":"CO",
    "gn:dem":2890,
    "gn:feature_class":"P",
    "gn:feature_code":"PPL",
    "gn:name":"Peralda",
    "gn:population":0,
    "gn:timezone":"America/Bogota",
    "iso:country":"CO",
    "wof:name":"Peralda",
    "wof:placetype":"locality"
},
  "geometry": {"coordinates":[-75.81056,4.06083],"type":"Point"}
}