{
  "type": "Feature",
  "properties": {
    "gn:admin1_code":"31",
    "gn:admin2_code":"99001.0",
    "gn:asciiname":"Los Paisanos",
    "gn:country_code":"CO",
    "gn:dem":73,
    "gn:feature_class":"P",
    "gn:feature_code":"PPL",
    "gn:name":"Los Paisanos",
    "gn:population":0,
    "gn:timezone":"America/Bogota",
    "iso:country":"CO",
    "name:spa_x_preferred":[
        "Los Paisanos"
    ],
    "wof:name":"Los Paisanos",
    "wof:placetype":"locality"
},
  "geometry": {"coordinates":[-68.47655999999999,6.16482],"type":"Point"}
}