{
  "type": "Feature",
  "properties": {
    "gn:admin1_code":"37",
    "gn:admin2_code":"17877.0",
    "gn:asciiname":"El Danubio",
    "gn:country_code":"CO",
    "gn:dem":925,
    "gn:feature_class":"P",
    "gn:feature_code":"PPL",
    "gn:name":"El Danubio",
    "gn:population":0,
    "gn:timezone":"America/Bogota",
    "iso:country":"CO",
    "wof:name":"El Danubio",
    "wof:placetype":"locality"
},
  "geometry": {"coordinates":[-75.87278000000001,4.99472],"type":"Point"}
}