{
  "type": "Feature",
  "properties": {
    "gn:admin1_code":"9",
    "gn:admin2_code":"19256.0",
    "gn:asciiname":"Rio Honda",
    "gn:country_code":"CO",
    "gn:dem":1588,
    "gn:feature_class":"P",
    "gn:feature_code":"PPL",
    "gn:name":"R\u00edo Honda",
    "gn:population":0,
    "gn:timezone":"America/Bogota",
    "iso:country":"CO",
    "wof:name":"Rio Honda",
    "wof:placetype":"locality"
},
  "geometry": {"coordinates":[-76.77584,2.55104],"type":"Point"}
}