{
  "type": "Feature",
  "properties": {
    "gn:admin1_code":"33",
    "gn:admin2_code":"25035.0",
    "gn:asciiname":"El Higueron",
    "gn:country_code":"CO",
    "gn:dem":842,
    "gn:feature_class":"P",
    "gn:feature_code":"PPL",
    "gn:name":"El Higuer\u00f3n",
    "gn:population":0,
    "gn:timezone":"America/Bogota",
    "iso:country":"CO",
    "wof:name":"El Higueron",
    "wof:placetype":"locality"
},
  "geometry": {"coordinates":[-74.51831,4.58139],"type":"Point"}
}