{
  "type": "Feature",
  "properties": {
    "gn:admin1_code":"19",
    "gn:admin2_code":"50270",
    "gn:asciiname":"Rancho Quemado",
    "gn:country_code":"CO",
    "gn:dem":637,
    "gn:feature_class":"P",
    "gn:feature_code":"PPL",
    "gn:name":"Rancho Quemado",
    "gn:population":0,
    "gn:timezone":"America/Bogota",
    "iso:country":"CO",
    "name:spa_x_preferred":[
        "Rancho Quemado"
    ],
    "wof:name":"Rancho Quemado",
    "wof:placetype":"locality"
},
  "geometry": {"coordinates":[-73.84064000000002,3.71781],"type":"Point"}
}