{
  "type": "Feature",
  "properties": {
    "gn:admin1_code":"26.0",
    "gn:admin2_code":"68770.0",
    "gn:asciiname":"Mutiscua",
    "gn:cc2":"CO",
    "gn:country_code":"CO",
    "gn:dem":1096,
    "gn:feature_class":"P",
    "gn:feature_code":"PPL",
    "gn:name":"Mutiscua",
    "gn:population":0,
    "gn:timezone":"America/Bogota",
    "iso:country":"CO",
    "name:ceb_x_preferred":[
        "Mutiscua"
    ],
    "name:fra_x_preferred":[
        "Mutiscua"
    ],
    "name:ita_x_preferred":[
        "Mutiscua"
    ],
    "name:kat_x_preferred":[
        "\u10db\u10e3\u10e2\u10d8\u10e1\u10d9\u10e3\u10d0"
    ],
    "name:msa_x_preferred":[
        "Mutiscua"
    ],
    "name:nld_x_preferred":[
        "Mutiscua"
    ],
    "name:por_x_preferred":[
        "Mutiscua"
    ],
    "name:spa_x_preferred":[
        "Mutiscua"
    ],
    "name:swe_x_preferred":[
        "Mutiscua"
    ],
    "name:tgl_x_preferred":[
        "Mutiscua"
    ],
    "name:und_x_variant":[
        "Mutisgua"
    ],
    "name:vie_x_preferred":[
        "Mutiscua"
    ],
    "name:war_x_preferred":[
        "Mutiscua"
    ],
    "name:zho_x_preferred":[
        "\u7a46\u8482\u65af\u5938"
    ],
    "wof:name":"Mutiscua",
    "wof:placetype":"locality"
},
  "geometry": {"coordinates":[-73.48333000000002,6.13333],"type":"Point"}
}