{
  "type": "Feature",
  "properties": {
    "gn:admin1_code":"16",
    "gn:admin2_code":"41001.0",
    "gn:asciiname":"Pitajayo",
    "gn:country_code":"CO",
    "gn:dem":904,
    "gn:feature_class":"P",
    "gn:feature_code":"PPL",
    "gn:name":"Pitajayo",
    "gn:population":0,
    "gn:timezone":"America/Bogota",
    "iso:country":"CO",
    "wof:name":"Pitajayo",
    "wof:placetype":"locality"
},
  "geometry": {"coordinates":[-75.45999999999999,3.06361],"type":"Point"}
}