{
  "type": "Feature",
  "properties": {
    "gn:admin1_code":"2",
    "gn:admin2_code":"5282.0",
    "gn:asciiname":"Marsella",
    "gn:country_code":"CO",
    "gn:dem":1467,
    "gn:feature_class":"P",
    "gn:feature_code":"PPL",
    "gn:name":"Marsella",
    "gn:population":0,
    "gn:timezone":"America/Bogota",
    "iso:country":"CO",
    "name:ceb_x_preferred":[
        "Marsella"
    ],
    "name:deu_x_preferred":[
        "Marsella"
    ],
    "name:fas_x_preferred":[
        "\u0645\u0627\u0631\u0633\u06cc\u06cc\u0627"
    ],
    "name:fra_x_preferred":[
        "Marsella"
    ],
    "name:ita_x_preferred":[
        "Marsella"
    ],
    "name:kat_x_preferred":[
        "\u10db\u10d0\u10e0\u10e1\u10d4\u10da\u10d8\u10d0"
    ],
    "name:msa_x_preferred":[
        "Marsella"
    ],
    "name:nld_x_preferred":[
        "Marsella"
    ],
    "name:spa_x_preferred":[
        "Marsella"
    ],
    "name:swe_x_preferred":[
        "Marsella"
    ],
    "name:vie_x_preferred":[
        "Marsella"
    ],
    "name:war_x_preferred":[
        "Marsella"
    ],
    "name:zho_x_preferred":[
        "\u99ac\u723e\u585e\u5229\u4e9e"
    ],
    "wof:name":"Marsella",
    "wof:placetype":"locality"
},
  "geometry": {"coordinates":[-75.68958000000001,5.87197],"type":"Point"}
}