{
  "type": "Feature",
  "properties": {
    "gn:admin1_code":"2",
    "gn:admin2_code":"5282.0",
    "gn:asciiname":"Marsella",
    "gn:country_code":"CO",
    "gn:dem":1467,
    "gn:feature_class":"P",
    "gn:feature_code":"PPL",
    "gn:name":"Marsella",
    "gn:population":0,
    "gn:timezone":"America/Bogota",
    "iso:country":"CO",
    "wof:name":"Marsella",
    "wof:placetype":"locality"
},
  "geometry": {"coordinates":[-75.68958000000001,5.87197],"type":"Point"}
}