{
  "type": "Feature",
  "properties": {
    "gn:admin1_code":"26",
    "gn:admin2_code":"68406.0",
    "gn:asciiname":"Don Rubon",
    "gn:country_code":"CO",
    "gn:dem":1083,
    "gn:feature_class":"P",
    "gn:feature_code":"PPL",
    "gn:name":"Don Rub\u00f3n",
    "gn:population":0,
    "gn:timezone":"America/Bogota",
    "iso:country":"CO",
    "name:spa_x_preferred":[
        "Don Rub\u00f3n"
    ],
    "name:und_x_variant":[
        "Don Rub\u00e9n"
    ],
    "wof:name":"Don Rubon",
    "wof:placetype":"locality"
},
  "geometry": {"coordinates":[-73.18838000000002,7.10693],"type":"Point"}
}