{
  "type": "Feature",
  "properties": {
    "gn:admin1_code":"4",
    "gn:admin2_code":"8558.0",
    "gn:asciiname":"Higueron",
    "gn:country_code":"CO",
    "gn:dem":87,
    "gn:feature_class":"P",
    "gn:feature_code":"PPL",
    "gn:name":"Higuer\u00f3n",
    "gn:population":0,
    "gn:timezone":"America/Bogota",
    "iso:country":"CO",
    "wof:name":"Higueron",
    "wof:placetype":"locality"
},
  "geometry": {"coordinates":[-74.84999999999999,10.78333],"type":"Point"}
}