{
  "type": "Feature",
  "properties": {
    "gn:admin1_code":"26",
    "gn:admin2_code":"68575.0",
    "gn:asciiname":"Italia",
    "gn:cc2":"CO",
    "gn:country_code":"CO",
    "gn:dem":58,
    "gn:feature_class":"P",
    "gn:feature_code":"PPL",
    "gn:name":"Italia",
    "gn:population":0,
    "gn:timezone":"America/Bogota",
    "iso:country":"CO",
    "name:und_x_variant":[
        "Italda",
        "Italia"
    ],
    "wof:name":"Italia",
    "wof:placetype":"locality"
},
  "geometry": {"coordinates":[-73.90000000000001,7.45],"type":"Point"}
}