{
  "type": "Feature",
  "properties": {
    "gn:admin1_code":"29",
    "gn:admin2_code":"76616.0",
    "gn:asciiname":"Bellavista",
    "gn:country_code":"CO",
    "gn:dem":1096,
    "gn:feature_class":"P",
    "gn:feature_code":"PPL",
    "gn:name":"Bellavista",
    "gn:population":0,
    "gn:timezone":"America/Bogota",
    "iso:country":"CO",
    "wof:name":"Bellavista",
    "wof:placetype":"locality"
},
  "geometry": {"coordinates":[-76.33333,4.16667],"type":"Point"}
}