{
  "type": "Feature",
  "properties": {
    "gn:admin1_code":"26",
    "gn:admin2_code":"68615.0",
    "gn:asciiname":"Tambo Quemado",
    "gn:country_code":"CO",
    "gn:dem":526,
    "gn:feature_class":"P",
    "gn:feature_code":"PPL",
    "gn:name":"Tambo Quemado",
    "gn:population":0,
    "gn:timezone":"America/Bogota",
    "iso:country":"CO",
    "wof:name":"Tambo Quemado",
    "wof:placetype":"locality"
},
  "geometry": {"coordinates":[-73.32056,7.385],"type":"Point"}
}