{
  "type": "Feature",
  "properties": {
    "gn:admin1_code":"35",
    "gn:admin2_code":"13212.0",
    "gn:asciiname":"El Bongo",
    "gn:country_code":"CO",
    "gn:dem":66,
    "gn:feature_class":"P",
    "gn:feature_code":"PPL",
    "gn:name":"El Bongo",
    "gn:population":0,
    "gn:timezone":"America/Bogota",
    "iso:country":"CO",
    "name:ita_x_preferred":[
        "El Bongo"
    ],
    "name:spa_x_preferred":[
        "El Bongo"
    ],
    "name:und_x_variant":[
        "Hacienda El Bongo",
        "El Bongo"
    ],
    "name:zho_x_preferred":[
        "\u57c3\u5c14\u90a6\u6208"
    ],
    "wof:name":"El Bongo",
    "wof:placetype":"locality"
},
  "geometry": {"coordinates":[-74.90508,9.53021],"type":"Point"}
}