{
  "type": "Feature",
  "properties": {
    "gn:admin1_code":"27",
    "gn:admin2_code":"70418.0",
    "gn:asciiname":"Los Veranillos",
    "gn:cc2":"CO",
    "gn:country_code":"CO",
    "gn:dem":154,
    "gn:feature_class":"P",
    "gn:feature_code":"PPL",
    "gn:name":"Los Veranillos",
    "gn:population":0,
    "gn:timezone":"America/Bogota",
    "iso:country":"CO",
    "name:und_x_variant":[
        "Veranillos",
        "Hacienda Los Veranillos",
        "Los Veranillos"
    ],
    "wof:name":"Los Veranillos",
    "wof:placetype":"locality"
},
  "geometry": {"coordinates":[-75.15000000000001,9.46667],"type":"Point"}
}