{
  "type": "Feature",
  "properties": {
    "gn:admin1_code":"2",
    "gn:admin2_code":"5361.0",
    "gn:asciiname":"La Descubierta",
    "gn:country_code":"CO",
    "gn:dem":2460,
    "gn:feature_class":"P",
    "gn:feature_code":"PPL",
    "gn:name":"La Descubierta",
    "gn:population":0,
    "gn:timezone":"America/Bogota",
    "iso:country":"CO",
    "name:ceb_x_preferred":[
        "La Descubierta"
    ],
    "name:ita_x_preferred":[
        "La Descubierta"
    ],
    "name:por_x_preferred":[
        "La Descubierta"
    ],
    "name:slv_x_preferred":[
        "La Descubierta"
    ],
    "name:spa_x_preferred":[
        "La Descubierta"
    ],
    "name:swe_x_preferred":[
        "La Descubierta"
    ],
    "name:urd_x_preferred":[
        "\u0644\u0627 \u062f\u06cc\u0633\u06a9\u0648\u0628\u06cc\u0631\u062a\u0627"
    ],
    "name:zho_x_preferred":[
        "\u62c9\u5fb7\u65af\u5eab\u7dad\u8036\u723e\u5854"
    ],
    "wof:name":"La Descubierta",
    "wof:placetype":"locality"
},
  "geometry": {"coordinates":[-75.81056,7.32056],"type":"Point"}
}