{
  "type": "Feature",
  "properties": {
    "gn:admin1_code":"4.0",
    "gn:admin2_code":"8078.0",
    "gn:asciiname":"Sibarco",
    "gn:country_code":"CO",
    "gn:dem":146,
    "gn:feature_class":"P",
    "gn:feature_code":"PPL",
    "gn:name":"Sibarco",
    "gn:population":0,
    "gn:timezone":"America/Bogota",
    "iso:country":"CO",
    "name:und_x_variant":[
        "Caser\u00edo Sibarco",
        "Cibarco",
        "Sibarco"
    ],
    "wof:name":"Sibarco",
    "wof:placetype":"locality"
},
  "geometry": {"coordinates":[-74.97451,10.81546],"type":"Point"}
}