{
  "type": "Feature",
  "properties": {
    "gn:admin1_code":"4",
    "gn:admin2_code":"8560.0",
    "gn:asciiname":"La Montana",
    "gn:country_code":"CO",
    "gn:dem":10,
    "gn:feature_class":"P",
    "gn:feature_code":"PPL",
    "gn:name":"La Monta\u00f1a",
    "gn:population":0,
    "gn:timezone":"America/Bogota",
    "iso:country":"CO",
    "wof:name":"La Montana",
    "wof:placetype":"locality"
},
  "geometry": {"coordinates":[-74.78180999999999,10.56031],"type":"Point"}
}