{
  "type": "Feature",
  "properties": {
    "gn:admin1_code":"35",
    "gn:asciiname":"Hacienda Rancho Grande",
    "gn:country_code":"CO",
    "gn:dem":13,
    "gn:feature_class":"P",
    "gn:feature_code":"PPL",
    "gn:name":"Hacienda Rancho Grande",
    "gn:population":0,
    "gn:timezone":"America/Bogota",
    "iso:country":"CO",
    "wof:name":"Hacienda Rancho Grande",
    "wof:placetype":"locality"
},
  "geometry": {"coordinates":[-75.26666999999998,10.68333],"type":"Point"}
}