{
  "type": "Feature",
  "properties": {
    "gn:admin1_code":"20.0",
    "gn:admin2_code":"52224.0",
    "gn:asciiname":"La Curiquinga",
    "gn:country_code":"CO",
    "gn:dem":2949,
    "gn:feature_class":"P",
    "gn:feature_code":"PPL",
    "gn:name":"La Curiquinga",
    "gn:population":0,
    "gn:timezone":"America/Bogota",
    "iso:country":"CO",
    "wof:name":"La Curiquinga",
    "wof:placetype":"locality"
},
  "geometry": {"coordinates":[-77.70641999999999,0.85398],"type":"Point"}
}