{
  "type": "Feature",
  "properties": {
    "gn:admin1_code":"35",
    "gn:admin2_code":"13650.0",
    "gn:asciiname":"La Costa",
    "gn:country_code":"CO",
    "gn:dem":17,
    "gn:feature_class":"P",
    "gn:feature_code":"PPL",
    "gn:name":"La Costa",
    "gn:population":0,
    "gn:timezone":"America/Bogota",
    "iso:country":"CO",
    "name:ara_x_preferred":[
        "\u0644\u0627 \u0643\u0648\u0633\u062a\u0627"
    ],
    "wof:name":"La Costa",
    "wof:placetype":"locality"
},
  "geometry": {"coordinates":[-74.38283,9.08285],"type":"Point"}
}