{
  "type": "Feature",
  "properties": {
    "gn:admin1_code":"3.0",
    "gn:admin2_code":"81300.0",
    "gn:asciiname":"Caserio Puerto Gloria",
    "gn:country_code":"CO",
    "gn:dem":203,
    "gn:feature_class":"P",
    "gn:feature_code":"PPL",
    "gn:name":"Caser\u00edo Puerto Gloria",
    "gn:population":0,
    "gn:timezone":"America/Bogota",
    "iso:country":"CO",
    "wof:name":"Caserio Puerto Gloria",
    "wof:placetype":"locality"
},
  "geometry": {"coordinates":[-71.62139000000001,6.75694],"type":"Point"}
}