{
  "type": "Feature",
  "properties": {
    "gn:admin1_code":"36",
    "gn:admin2_code":"15632.0",
    "gn:asciiname":"Campo Hermosa",
    "gn:country_code":"CO",
    "gn:dem":2954,
    "gn:feature_class":"P",
    "gn:feature_code":"PPL",
    "gn:name":"Campo Hermosa",
    "gn:population":0,
    "gn:timezone":"America/Bogota",
    "iso:country":"CO",
    "wof:name":"Campo Hermosa",
    "wof:placetype":"locality"
},
  "geometry": {"coordinates":[-73.70829999999999,5.65313],"type":"Point"}
}