{
  "type": "Feature",
  "properties": {
    "gn:admin1_code":"26.0",
    "gn:admin2_code":"68575.0",
    "gn:asciiname":"Puerto Nuevo",
    "gn:country_code":"CO",
    "gn:dem":86,
    "gn:feature_class":"P",
    "gn:feature_code":"PPL",
    "gn:name":"Puerto Nuevo",
    "gn:population":0,
    "gn:timezone":"America/Bogota",
    "iso:country":"CO",
    "name:ceb_x_preferred":[
        "Puerto Nuevo"
    ],
    "name:deu_x_preferred":[
        "Puerto Nuevo"
    ],
    "name:spa_x_preferred":[
        "Puerto Nuevo"
    ],
    "name:srp_x_preferred":[
        "\u041f\u0443\u0435\u0440\u0442\u043e \u041d\u0443\u0435\u0432\u043e"
    ],
    "name:swe_x_preferred":[
        "Puerto Nuevo"
    ],
    "wof:name":"Puerto Nuevo",
    "wof:placetype":"locality"
},
  "geometry": {"coordinates":[-73.78695,7.34675],"type":"Point"}
}