{
  "type": "Feature",
  "properties": {
    "gn:admin1_code":"10.0",
    "gn:admin2_code":"20614.0",
    "gn:asciiname":"Aguablanca",
    "gn:country_code":"CO",
    "gn:dem":236,
    "gn:feature_class":"P",
    "gn:feature_code":"PPL",
    "gn:name":"Aguablanca",
    "gn:population":0,
    "gn:timezone":"America/Bogota",
    "iso:country":"CO",
    "name:spa_x_preferred":[
        "Aguablanca"
    ],
    "wof:name":"Aguablanca",
    "wof:placetype":"locality"
},
  "geometry": {"coordinates":[-73.52445999999998,8.237],"type":"Point"}
}