{
  "type": "Feature",
  "properties": {
    "gn:country":"CO",
    "gn:fcode":"PPL",
    "gn:population":5390,
    "iso:country":"CO",
    "name:ceb_x_preferred":[
        "Piji\u00f1o"
    ],
    "name:eng_x_preferred":[
        "Piji\u00f1o"
    ],
    "name:fas_x_preferred":[
        "\u067e\u06cc\u062e\u06cc\u0646\u06cc\u0648 \u062f\u0644 \u06a9\u0627\u0631\u0645\u0646"
    ],
    "name:fra_x_preferred":[
        "Piji\u00f1o del Carmen"
    ],
    "name:ita_x_preferred":[
        "Piji\u00f1o del Carmen"
    ],
    "name:kat_x_preferred":[
        "\u10de\u10d8\u10ee\u10d8\u10dc\u10d8\u10dd"
    ],
    "name:msa_x_preferred":[
        "Piji\u00f1o"
    ],
    "name:nan_x_preferred":[
        "Piji\u00f1o del Carmen"
    ],
    "name:nld_x_preferred":[
        "Piji\u00f1o del Carmen"
    ],
    "name:oci_x_preferred":[
        "Piji\u00f1o del Carmen"
    ],
    "name:por_x_preferred":[
        "Piji\u00f1o"
    ],
    "name:rus_x_preferred":[
        "\u041f\u0438\u0445\u0438\u043d\u044c\u043e-\u0434\u0435\u043b\u044c-\u041a\u0430\u0440\u043c\u0435\u043d"
    ],
    "name:sco_x_preferred":[
        "Piji\u00f1o"
    ],
    "name:spa_x_preferred":[
        "Piji\u00f1o del Carmen"
    ],
    "name:swe_x_preferred":[
        "Piji\u00f1o"
    ],
    "name:tgl_x_preferred":[
        "Piji\u00f1o"
    ],
    "name:und_x_variant":[
        "Corregimiento Piji\u00f1o"
    ],
    "name:vie_x_preferred":[
        "Piji\u00f1o del Carmen"
    ],
    "name:war_x_preferred":[
        "Piji\u00f1o"
    ],
    "name:zho_x_preferred":[
        "\u76ae\u5e0c\u5c3c\u5967"
    ],
    "qs_pg:aaroncc":"CO",
    "qs_pg:gn_country":"CO",
    "qs_pg:gn_fcode":"PPL",
    "qs_pg:gn_pop":5390,
    "qs_pg:name":"Piji\u00f1o",
    "qs_pg:photos_9r":0,
    "qs_pg:photos_sr":0,
    "qs_pg:pop_sr":5,
    "qs_pg:qs_pg_placetype":"locality",
    "wof:name":"Piji\u00f1o",
    "wof:placetype":"locality",
    "wof:population":5390
},
  "geometry": {"coordinates":[-74.45302,9.32908],"type":"Point"}
}