{
  "type": "Feature",
  "properties": {
    "gn:admin1_code":"31.0",
    "gn:admin2_code":"99773.0",
    "gn:asciiname":"Guarrojo",
    "gn:country_code":"CO",
    "gn:dem":142,
    "gn:feature_class":"P",
    "gn:feature_code":"PPLL",
    "gn:name":"Guarrojo",
    "gn:population":0,
    "gn:timezone":"America/Bogota",
    "iso:country":"CO",
    "wof:name":"Guarrojo",
    "wof:placetype":"locality"
},
  "geometry": {"coordinates":[-70.91778000000002,4.24389],"type":"Point"}
}