{
  "type": "Feature",
  "properties": {
    "gn:admin1_code":"32",
    "gn:admin2_code":"85410.0",
    "gn:asciiname":"El Viento",
    "gn:country_code":"CO",
    "gn:dem":220,
    "gn:feature_class":"P",
    "gn:feature_code":"PPL",
    "gn:name":"El Viento",
    "gn:population":0,
    "gn:timezone":"America/Bogota",
    "iso:country":"CO",
    "name:fra_x_preferred":[
        "El Viento"
    ],
    "name:nld_x_preferred":[
        "El Viento"
    ],
    "name:por_x_preferred":[
        "El Viento"
    ],
    "wof:name":"El Viento",
    "wof:placetype":"locality"
},
  "geometry": {"coordinates":[-72.70184,4.80494],"type":"Point"}
}