{
  "type": "Feature",
  "properties": {
    "gn:admin1_code":"38",
    "gn:admin2_code":"47460.0",
    "gn:asciiname":"Cundinamarca",
    "gn:country_code":"CO",
    "gn:dem":90,
    "gn:feature_class":"P",
    "gn:feature_code":"PPL",
    "gn:name":"Cundinamarca",
    "gn:population":0,
    "gn:timezone":"America/Bogota",
    "iso:country":"CO",
    "name:rus_x_preferred":[
        "\u041a\u0443\u043d\u0434\u0438\u043d\u0430\u043c\u0430\u0440\u043a\u0430"
    ],
    "name:spa_x_preferred":[
        "Cundinamarca"
    ],
    "name:und_x_variant":[
        "Hacienda Cundinamarca"
    ],
    "wof:name":"Cundinamarca",
    "wof:placetype":"locality"
},
  "geometry": {"coordinates":[-74.20295,9.66234],"type":"Point"}
}