{
  "type": "Feature",
  "properties": {
    "gn:admin1_code":"36",
    "gn:admin2_code":"15580.0",
    "gn:asciiname":"Macanal",
    "gn:country_code":"CO",
    "gn:dem":1344,
    "gn:feature_class":"P",
    "gn:feature_code":"PPL",
    "gn:name":"Macanal",
    "gn:population":0,
    "gn:timezone":"America/Bogota",
    "iso:country":"CO",
    "wof:name":"Macanal",
    "wof:placetype":"locality"
},
  "geometry": {"coordinates":[-74.17806,5.58167],"type":"Point"}
}