{
  "type": "Feature",
  "properties": {
    "gn:admin1_code":"36",
    "gn:admin2_code":"15580.0",
    "gn:asciiname":"Macanal",
    "gn:country_code":"CO",
    "gn:dem":1344,
    "gn:feature_class":"P",
    "gn:feature_code":"PPL",
    "gn:name":"Macanal",
    "gn:population":0,
    "gn:timezone":"America/Bogota",
    "iso:country":"CO",
    "name:ceb_x_preferred":[
        "Macanal"
    ],
    "name:fra_x_preferred":[
        "Macanal"
    ],
    "name:ita_x_preferred":[
        "Macanal"
    ],
    "name:kat_x_preferred":[
        "\u10db\u10d0\u10d9\u10d0\u10dc\u10d0\u10da\u10d8"
    ],
    "name:msa_x_preferred":[
        "Macanal"
    ],
    "name:nld_x_preferred":[
        "Macanal"
    ],
    "name:por_x_preferred":[
        "Macanal"
    ],
    "name:rus_x_preferred":[
        "\u041c\u0430\u043a\u0430\u043d\u0430\u043b\u044c"
    ],
    "name:spa_x_preferred":[
        "Macanal"
    ],
    "name:swe_x_preferred":[
        "Macanal"
    ],
    "name:tgl_x_preferred":[
        "Macanal"
    ],
    "name:urd_x_preferred":[
        "\u0645\u06cc\u06a9\u0627\u0646\u0627\u0644"
    ],
    "name:vie_x_preferred":[
        "Macanal"
    ],
    "name:war_x_preferred":[
        "Macanal"
    ],
    "name:zho_x_preferred":[
        "\u99ac\u5361\u7d0d\u723e"
    ],
    "wof:name":"Macanal",
    "wof:placetype":"locality"
},
  "geometry": {"coordinates":[-74.17806,5.58167],"type":"Point"}
}