{
  "type": "Feature",
  "properties": {
    "gn:admin1_code":"16.0",
    "gn:admin2_code":"41206.0",
    "gn:asciiname":"Barbal",
    "gn:country_code":"CO",
    "gn:dem":1722,
    "gn:feature_class":"P",
    "gn:feature_code":"PPL",
    "gn:name":"Barbal",
    "gn:population":0,
    "gn:timezone":"America/Bogota",
    "iso:country":"CO",
    "name:spa_x_preferred":[
        "Barbal"
    ],
    "wof:name":"Barbal",
    "wof:placetype":"locality"
},
  "geometry": {"coordinates":[-74.81719,3.19708],"type":"Point"}
}