{
  "type": "Feature",
  "properties": {
    "gn:admin1_code":"16",
    "gn:admin2_code":"41797.0",
    "gn:asciiname":"Tierra Loca",
    "gn:country_code":"CO",
    "gn:dem":1055,
    "gn:feature_class":"P",
    "gn:feature_code":"PPL",
    "gn:name":"Tierra Loca",
    "gn:population":0,
    "gn:timezone":"America/Bogota",
    "iso:country":"CO",
    "wof:name":"Tierra Loca",
    "wof:placetype":"locality"
},
  "geometry": {"coordinates":[-75.70354,2.59862],"type":"Point"}
}