{
  "type": "Feature",
  "properties": {
    "gn:admin1_code":"16.0",
    "gn:admin2_code":"41078.0",
    "gn:asciiname":"El Playon",
    "gn:country_code":"CO",
    "gn:dem":779,
    "gn:feature_class":"P",
    "gn:feature_code":"PPL",
    "gn:name":"El Play\u00f3n",
    "gn:population":0,
    "gn:timezone":"America/Bogota",
    "iso:country":"CO",
    "name:spa_x_preferred":[
        "El Play\u00f3n"
    ],
    "wof:name":"El Playon",
    "wof:placetype":"locality"
},
  "geometry": {"coordinates":[-74.88589,3.24036],"type":"Point"}
}