{
  "type": "Feature",
  "properties": {
    "gn:admin1_code":"10",
    "gn:admin2_code":"20238.0",
    "gn:asciiname":"Labrador",
    "gn:country_code":"CO",
    "gn:dem":102,
    "gn:feature_class":"P",
    "gn:feature_code":"PPL",
    "gn:name":"Labrador",
    "gn:population":0,
    "gn:timezone":"America/Bogota",
    "iso:country":"CO",
    "name:und_x_variant":[
        "Hacienda Labrada",
        "Hacienda Labrador",
        "Labrador"
    ],
    "wof:name":"Labrador",
    "wof:placetype":"locality"
},
  "geometry": {"coordinates":[-74.06368000000001,10.13256],"type":"Point"}
}