{
  "type": "Feature",
  "properties": {
    "gn:admin1_code":"10",
    "gn:admin2_code":"20238.0",
    "gn:asciiname":"Labrador",
    "gn:country_code":"CO",
    "gn:dem":102,
    "gn:feature_class":"P",
    "gn:feature_code":"PPL",
    "gn:name":"Labrador",
    "gn:population":0,
    "gn:timezone":"America/Bogota",
    "iso:country":"CO",
    "name:ara_x_preferred":[
        "\u0644\u0627\u0628\u0631\u0627\u062f\u0648\u0631"
    ],
    "name:bre_x_preferred":[
        "Labrador"
    ],
    "name:cat_x_preferred":[
        "Labrador"
    ],
    "name:ces_x_preferred":[
        "Labrador"
    ],
    "name:cym_x_preferred":[
        "Labrador"
    ],
    "name:dan_x_preferred":[
        "Labrador"
    ],
    "name:deu_x_preferred":[
        "Labrador"
    ],
    "name:epo_x_preferred":[
        "Labradoro"
    ],
    "name:fas_x_preferred":[
        "\u0644\u0627\u0628\u0631\u0627\u062f\u0648\u0631"
    ],
    "name:fin_x_preferred":[
        "Labrador"
    ],
    "name:fra_x_preferred":[
        "Labrador"
    ],
    "name:fry_x_preferred":[
        "Labrador"
    ],
    "name:gla_x_preferred":[
        "Labrador"
    ],
    "name:gle_x_preferred":[
        "Labradar"
    ],
    "name:ind_x_preferred":[
        "Labrador"
    ],
    "name:ita_x_preferred":[
        "Labrador"
    ],
    "name:jpn_x_preferred":[
        "\u30e9\u30d6\u30e9\u30c9\u30fc\u30eb\u5730\u65b9"
    ],
    "name:kor_x_preferred":[
        "\ub798\ube0c\ub77c\ub3c4"
    ],
    "name:lat_x_preferred":[
        "Terra Laboratoria"
    ],
    "name:lit_x_preferred":[
        "Labradoras"
    ],
    "name:mzn_x_preferred":[
        "\u0644\u0627\u0628\u0631\u0627\u062f\u0648\u0631"
    ],
    "name:nld_x_preferred":[
        "Labrador"
    ],
    "name:nor_x_preferred":[
        "Labrador"
    ],
    "name:oci_x_preferred":[
        "Labrador"
    ],
    "name:pol_x_preferred":[
        "Labrador"
    ],
    "name:por_x_preferred":[
        "Labrador"
    ],
    "name:sco_x_preferred":[
        "Labrador"
    ],
    "name:slk_x_preferred":[
        "Labrador"
    ],
    "name:spa_x_preferred":[
        "Labrador"
    ],
    "name:srp_x_preferred":[
        "\u041b\u0430\u0431\u0440\u0430\u0434\u043e\u0440"
    ],
    "name:swe_x_preferred":[
        "Labrador"
    ],
    "name:tam_x_preferred":[
        "\u0bb2\u0bbe\u0baa\u0bcd\u0bb0\u0b9f\u0bcb\u0bb0\u0bcd"
    ],
    "name:ukr_x_preferred":[
        "\u041b\u0430\u0431\u0440\u0430\u0434\u043e\u0440"
    ],
    "name:und_x_variant":[
        "Hacienda Labrada",
        "Hacienda Labrador"
    ],
    "name:vie_x_preferred":[
        "Labrador"
    ],
    "name:yor_x_preferred":[
        "Labrador"
    ],
    "name:zho_x_preferred":[
        "\u62c9\u5e03\u62c9\u591a"
    ],
    "wof:name":"Labrador",
    "wof:placetype":"locality"
},
  "geometry": {"coordinates":[-74.06368000000001,10.13256],"type":"Point"}
}