{
  "type": "Feature",
  "properties": {
    "gn:admin1_code":"17",
    "gn:admin2_code":"44560.0",
    "gn:asciiname":"Araurio",
    "gn:country_code":"CO",
    "gn:dem":6,
    "gn:feature_class":"P",
    "gn:feature_code":"PPL",
    "gn:name":"Araur\u00edo",
    "gn:population":0,
    "gn:timezone":"America/Bogota",
    "iso:country":"CO",
    "wof:name":"Araurio",
    "wof:placetype":"locality"
},
  "geometry": {"coordinates":[-72.35916999999998,11.80083],"type":"Point"}
}