{
  "type": "Feature",
  "properties": {
    "gn:admin1_code":"17.0",
    "gn:admin2_code":"44847.0",
    "gn:asciiname":"Soripa",
    "gn:country_code":"CO",
    "gn:dem":1,
    "gn:feature_class":"P",
    "gn:feature_code":"PPL",
    "gn:name":"Soripa",
    "gn:population":0,
    "gn:timezone":"America/Bogota",
    "iso:country":"CO",
    "name:und_x_variant":[
        "Solipa",
        "Yahata",
        "Soripa"
    ],
    "wof:name":"Soripa",
    "wof:placetype":"locality"
},
  "geometry": {"coordinates":[-72.20146,11.97132],"type":"Point"}
}