{
  "type": "Feature",
  "properties": {
    "gn:admin1_code":"30.0",
    "gn:asciiname":"Morichal",
    "gn:country_code":"CO",
    "gn:dem":200,
    "gn:feature_class":"P",
    "gn:feature_code":"PPL",
    "gn:name":"Morichal",
    "gn:population":0,
    "gn:timezone":"America/Bogota",
    "iso:country":"CO",
    "wof:name":"Morichal",
    "wof:placetype":"locality"
},
  "geometry": {"coordinates":[-70.56667,2.16667],"type":"Point"}
}