{
  "type": "Feature",
  "properties": {
    "gn:admin1_code":"38",
    "gn:admin2_code":"47245.0",
    "gn:asciiname":"Belencito",
    "gn:country_code":"CO",
    "gn:dem":37,
    "gn:feature_class":"P",
    "gn:feature_code":"PPL",
    "gn:name":"Belencito",
    "gn:population":0,
    "gn:timezone":"America/Bogota",
    "iso:country":"CO",
    "wof:name":"Belencito",
    "wof:placetype":"locality"
},
  "geometry": {"coordinates":[-73.93722,9.08444],"type":"Point"}
}