{
  "type": "Feature",
  "properties": {
    "gn:admin1_code":"1",
    "gn:admin2_code":"91669.0",
    "gn:asciiname":"Bocas de Cahuinari",
    "gn:cc2":"CO",
    "gn:country_code":"CO",
    "gn:dem":100,
    "gn:feature_class":"P",
    "gn:feature_code":"PPL",
    "gn:name":"Bocas de Cahuinar\u00ed",
    "gn:population":0,
    "gn:timezone":"America/Bogota",
    "iso:country":"CO",
    "name:und_x_variant":[
        "Bocas de Cahuinar\u00ed"
    ],
    "wof:name":"Bocas de Cahuinari",
    "wof:placetype":"locality"
},
  "geometry": {"coordinates":[-70.74306,-1.4275],"type":"Point"}
}