{
  "type": "Feature",
  "properties": {
    "gn:admin1_code":"2",
    "gn:admin2_code":"5361.0",
    "gn:asciiname":"Mulato",
    "gn:country_code":"CO",
    "gn:dem":719,
    "gn:feature_class":"P",
    "gn:feature_code":"PPL",
    "gn:name":"Mulato",
    "gn:population":0,
    "gn:timezone":"America/Bogota",
    "iso:country":"CO",
    "wof:name":"Mulato",
    "wof:placetype":"locality"
},
  "geometry": {"coordinates":[-75.69337,7.18024],"type":"Point"}
}