{
  "type": "Feature",
  "properties": {
    "gn:admin1_code":"26.0",
    "gn:admin2_code":"68689.0",
    "gn:asciiname":"El Marcito",
    "gn:country_code":"CO",
    "gn:dem":229,
    "gn:feature_class":"P",
    "gn:feature_code":"PPLL",
    "gn:name":"El Marcito",
    "gn:population":0,
    "gn:timezone":"America/Bogota",
    "iso:country":"CO",
    "wof:name":"El Marcito",
    "wof:placetype":"locality"
},
  "geometry": {"coordinates":[-73.52197,6.84123],"type":"Point"}
}