{
  "type": "Feature",
  "properties": {
    "gn:admin1_code":"22.0",
    "gn:admin2_code":"86569.0",
    "gn:asciiname":"Pena Colorada",
    "gn:country_code":"CO",
    "gn:dem":289,
    "gn:feature_class":"P",
    "gn:feature_code":"PPL",
    "gn:name":"Pe\u00f1a Colorada",
    "gn:population":0,
    "gn:timezone":"America/Bogota",
    "iso:country":"CO",
    "wof:name":"Pena Colorada",
    "wof:placetype":"locality"
},
  "geometry": {"coordinates":[-76.55,0.66667],"type":"Point"}
}