{
  "type": "Feature",
  "properties": {
    "gn:admin1_code":"2",
    "gn:admin2_code":"5585.0",
    "gn:asciiname":"La Clara",
    "gn:country_code":"CO",
    "gn:dem":517,
    "gn:feature_class":"P",
    "gn:feature_code":"PPL",
    "gn:name":"La Clara",
    "gn:population":0,
    "gn:timezone":"America/Bogota",
    "iso:country":"CO",
    "wof:name":"La Clara",
    "wof:placetype":"locality"
},
  "geometry": {"coordinates":[-74.69633,6.20463],"type":"Point"}
}