{
  "type": "Feature",
  "properties": {
    "gn:admin1_code":"37.0",
    "gn:admin2_code":"17867.0",
    "gn:asciiname":"Vega Grande",
    "gn:country_code":"CO",
    "gn:dem":197,
    "gn:feature_class":"P",
    "gn:feature_code":"PPL",
    "gn:name":"Vega Grande",
    "gn:population":0,
    "gn:timezone":"America/Bogota",
    "iso:country":"CO",
    "name:spa_x_preferred":[
        "Vega Grande"
    ],
    "wof:name":"Vega Grande",
    "wof:placetype":"locality"
},
  "geometry": {"coordinates":[-74.76358,5.45667],"type":"Point"}
}