{
  "type": "Feature",
  "properties": {
    "gn:admin1_code":"12",
    "gn:admin2_code":"23855.0",
    "gn:asciiname":"El Jobo",
    "gn:country_code":"CO",
    "gn:dem":88,
    "gn:feature_class":"P",
    "gn:feature_code":"PPL",
    "gn:name":"El Jobo",
    "gn:population":0,
    "gn:timezone":"America/Bogota",
    "iso:country":"CO",
    "wof:name":"El Jobo",
    "wof:placetype":"locality"
},
  "geometry": {"coordinates":[-76.18163,8.1587],"type":"Point"}
}