{
  "type": "Feature",
  "properties": {
    "gn:admin1_code":"3.0",
    "gn:admin2_code":"81794.0",
    "gn:asciiname":"Caserio Botalon",
    "gn:country_code":"CO",
    "gn:dem":197,
    "gn:feature_class":"P",
    "gn:feature_code":"PPL",
    "gn:name":"Caser\u00edo Botal\u00f3n",
    "gn:population":0,
    "gn:timezone":"America/Bogota",
    "iso:country":"CO",
    "wof:name":"Caserio Botalon",
    "wof:placetype":"locality"
},
  "geometry": {"coordinates":[-71.57971999999999,6.63417],"type":"Point"}
}