{
  "type": "Feature",
  "properties": {
    "gn:admin1_code":"26",
    "gn:admin2_code":"68101.0",
    "gn:asciiname":"Mata de Agua",
    "gn:country_code":"CO",
    "gn:dem":173,
    "gn:feature_class":"P",
    "gn:feature_code":"PPL",
    "gn:name":"Mata de Agua",
    "gn:population":0,
    "gn:timezone":"America/Bogota",
    "iso:country":"CO",
    "wof:name":"Mata de Agua",
    "wof:placetype":"locality"
},
  "geometry": {"coordinates":[-74.30221999999998,6.08222],"type":"Point"}
}