{
  "type": "Feature",
  "properties": {
    "gn:admin1_code":"26",
    "gn:admin2_code":"68397.0",
    "gn:asciiname":"Alto Palma",
    "gn:country_code":"CO",
    "gn:dem":959,
    "gn:feature_class":"P",
    "gn:feature_code":"PPL",
    "gn:name":"Alto Palma",
    "gn:population":0,
    "gn:timezone":"America/Bogota",
    "iso:country":"CO",
    "wof:name":"Alto Palma",
    "wof:placetype":"locality"
},
  "geometry": {"coordinates":[-73.65000000000001,6.28333],"type":"Point"}
}