{
  "type": "Feature",
  "properties": {
    "gn:admin1_code":"33.0",
    "gn:admin2_code":"25594.0",
    "gn:asciiname":"Tibrote",
    "gn:country_code":"CO",
    "gn:dem":1895,
    "gn:feature_class":"P",
    "gn:feature_code":"PPL",
    "gn:name":"Tibrote",
    "gn:population":0,
    "gn:timezone":"America/Bogota",
    "iso:country":"CO",
    "name:spa_x_preferred":[
        "Tibrote"
    ],
    "wof:name":"Tibrote",
    "wof:placetype":"locality"
},
  "geometry": {"coordinates":[-73.85114,4.36692],"type":"Point"}
}