{
  "type": "Feature",
  "properties": {
    "gn:admin1_code":"4",
    "gn:admin2_code":"8638.0",
    "gn:asciiname":"La Pena",
    "gn:country_code":"CO",
    "gn:dem":12,
    "gn:feature_class":"P",
    "gn:feature_code":"PPL",
    "gn:name":"La Pe\u00f1a",
    "gn:population":0,
    "gn:timezone":"America/Bogota",
    "iso:country":"CO",
    "name:und_x_variant":[
        "Gu\u00e1jaro",
        "Corregimiento La Pe\u00f1a",
        "La Pe\u00f1a"
    ],
    "wof:name":"La Pena",
    "wof:placetype":"locality"
},
  "geometry": {"coordinates":[-75.02625,10.58366],"type":"Point"}
}