{
  "type": "Feature",
  "properties": {
    "gn:admin1_code":"17",
    "gn:admin2_code":"44420.0",
    "gn:asciiname":"La Jagua del Pedregal",
    "gn:country_code":"CO",
    "gn:dem":204,
    "gn:feature_class":"P",
    "gn:feature_code":"PPL",
    "gn:name":"La Jagua del Pedregal",
    "gn:population":0,
    "gn:timezone":"America/Bogota",
    "iso:country":"CO",
    "name:und_x_variant":[
        "Jagua",
        "La Tranquilidad",
        "Jagua del Pedregal",
        "La Jagua",
        "La Jagua del Pedregal"
    ],
    "wof:name":"La Jagua del Pedregal",
    "wof:placetype":"locality"
},
  "geometry": {"coordinates":[-73.07189,10.508],"type":"Point"}
}