{
  "type": "Feature",
  "properties": {
    "gn:admin1_code":"2",
    "gn:admin2_code":"5847.0",
    "gn:asciiname":"La Lunareja",
    "gn:cc2":"CO",
    "gn:country_code":"CO",
    "gn:dem":2142,
    "gn:feature_class":"P",
    "gn:feature_code":"PPL",
    "gn:name":"La Lunareja",
    "gn:population":0,
    "gn:timezone":"America/Bogota",
    "iso:country":"CO",
    "name:und_x_variant":[
        "Lunareja",
        "La Lunareja"
    ],
    "wof:name":"La Lunareja",
    "wof:placetype":"locality"
},
  "geometry": {"coordinates":[-76.16667,6.43333],"type":"Point"}
}