{
  "type": "Feature",
  "properties": {
    "iso:country":"CO",
    "name:ast_x_preferred":[
        "Nari\u00f1o"
    ],
    "name:avk_x_preferred":[
        "Nari\u00f1o"
    ],
    "name:ceb_x_preferred":[
        "Nari\u00f1o"
    ],
    "name:eng_x_preferred":[
        "Nari\u00f1o"
    ],
    "name:fas_x_preferred":[
        "\u0646\u0627\u0631\u06cc\u0646\u06cc\u0648"
    ],
    "name:fra_x_preferred":[
        "Nari\u00f1o"
    ],
    "name:gle_x_preferred":[
        "Nari\u00f1o"
    ],
    "name:glg_x_preferred":[
        "Nari\u00f1o"
    ],
    "name:ita_x_preferred":[
        "Nari\u00f1o"
    ],
    "name:kat_x_preferred":[
        "\u10dc\u10d0\u10e0\u10d8\u10dc\u10d8\u10dd"
    ],
    "name:msa_x_preferred":[
        "Nari\u00f1o"
    ],
    "name:nan_x_preferred":[
        "Nari\u00f1o"
    ],
    "name:nld_x_preferred":[
        "Nari\u00f1o"
    ],
    "name:pol_x_preferred":[
        "Nari\u00f1o"
    ],
    "name:por_x_preferred":[
        "Nari\u00f1o"
    ],
    "name:sco_x_preferred":[
        "Nari\u00f1o"
    ],
    "name:spa_x_preferred":[
        "Nari\u00f1o"
    ],
    "name:swe_x_preferred":[
        "Nari\u00f1o"
    ],
    "name:tgl_x_preferred":[
        "Nari\u00f1o"
    ],
    "name:vie_x_preferred":[
        "Nari\u00f1o"
    ],
    "name:war_x_preferred":[
        "Nari\u00f1o"
    ],
    "name:zho_x_preferred":[
        "\u7d0d\u91cc\u5c3c\u5967"
    ],
    "qs:gn_country":"CO",
    "qs:gn_fcode":"PPL",
    "qs:gn_pop":1213,
    "qs:name":"Nari\u00f1o",
    "qs:name_adm0":"Colombia",
    "qs:name_adm1":"Cundinamarca",
    "qs:photos":0,
    "qs:photos_1k":0,
    "qs:photos_9k":0,
    "qs:photos_9r":0,
    "qs:photos_all":0,
    "qs:photos_sr":0,
    "qs:placetype":"Town",
    "qs:pop_sr":"3",
    "qs:woe_adm0":23424787,
    "wof:name":"Nari\u00f1o",
    "wof:placetype":"locality",
    "wof:population":1213
},
  "geometry": {"coordinates":[-74.82731,4.39781],"type":"Point"}
}