{
  "type": "Feature",
  "properties": {
    "gn:admin1_code":"31.0",
    "gn:admin2_code":"99524.0",
    "gn:asciiname":"Nueva Antioquia",
    "gn:country_code":"CO",
    "gn:dem":90,
    "gn:feature_class":"P",
    "gn:feature_code":"PPL",
    "gn:name":"Nueva Antioquia",
    "gn:population":0,
    "gn:timezone":"America/Bogota",
    "iso:country":"CO",
    "name:und_x_variant":[
        "Ret\u00e9n Nueva Antioquia",
        "Nueva Antioquia"
    ],
    "wof:name":"Nueva Antioquia",
    "wof:placetype":"locality"
},
  "geometry": {"coordinates":[-69.39146,6.09334],"type":"Point"}
}