{
  "type": "Feature",
  "properties": {
    "gn:admin1_code":"26.0",
    "gn:admin2_code":"68770.0",
    "gn:asciiname":"Los Cedros",
    "gn:country_code":"CO",
    "gn:dem":1722,
    "gn:feature_class":"P",
    "gn:feature_code":"PPL",
    "gn:name":"Los Cedros",
    "gn:population":0,
    "gn:timezone":"America/Bogota",
    "iso:country":"CO",
    "wof:name":"Los Cedros",
    "wof:placetype":"locality"
},
  "geometry": {"coordinates":[-73.34940999999998,6.08879],"type":"Point"}
}