{
  "type": "Feature",
  "properties": {
    "gn:admin1_code":"28.0",
    "gn:admin2_code":"73236.0",
    "gn:asciiname":"Filo La Cuchilla",
    "gn:country_code":"CO",
    "gn:dem":1727,
    "gn:feature_class":"P",
    "gn:feature_code":"PPLL",
    "gn:name":"Filo La Cuchilla",
    "gn:population":0,
    "gn:timezone":"America/Bogota",
    "iso:country":"CO",
    "name:spa_x_preferred":[
        "Filo La Cuchilla"
    ],
    "wof:name":"Filo La Cuchilla",
    "wof:placetype":"locality"
},
  "geometry": {"coordinates":[-74.72963,3.61585],"type":"Point"}
}