{
  "type": "Feature",
  "properties": {
    "gn:admin1_code":"37",
    "gn:admin2_code":"17042.0",
    "gn:asciiname":"La Nubia",
    "gn:country_code":"CO",
    "gn:dem":1686,
    "gn:feature_class":"P",
    "gn:feature_code":"PPL",
    "gn:name":"La Nubia",
    "gn:population":0,
    "gn:timezone":"America/Bogota",
    "iso:country":"CO",
    "name:und_x_variant":[
        "Nubia",
        "La Nubia"
    ],
    "wof:name":"La Nubia",
    "wof:placetype":"locality"
},
  "geometry": {"coordinates":[-75.7728,5.19877],"type":"Point"}
}