{
  "type": "Feature",
  "properties": {
    "gn:admin1_code":"1.0",
    "gn:admin2_code":"91407.0",
    "gn:asciiname":"Puerto Mariti",
    "gn:cc2":"CO",
    "gn:country_code":"CO",
    "gn:dem":131,
    "gn:feature_class":"P",
    "gn:feature_code":"PPL",
    "gn:name":"Puerto Mariti",
    "gn:population":0,
    "gn:timezone":"America/Bogota",
    "iso:country":"CO",
    "name:und_x_variant":[
        "Puerto Miriti",
        "Puerto Miritu",
        "Puerto Mariti"
    ],
    "wof:name":"Puerto Mariti",
    "wof:placetype":"locality"
},
  "geometry": {"coordinates":[-69.98333000000001,-1.16667],"type":"Point"}
}