{
  "type": "Feature",
  "properties": {
    "gn:country":"CO",
    "gn:fcode":"PPL",
    "gn:population":3490,
    "iso:country":"CO",
    "name:ast_x_preferred":[
        "Herveo"
    ],
    "name:avk_x_preferred":[
        "Herveo"
    ],
    "name:cat_x_preferred":[
        "Herveo"
    ],
    "name:ceb_x_preferred":[
        "Herveo"
    ],
    "name:cym_x_preferred":[
        "Herveo"
    ],
    "name:eng_x_preferred":[
        "Herveo"
    ],
    "name:fas_x_preferred":[
        "\u0647\u0631\u0648\u0626\u0648"
    ],
    "name:fra_x_preferred":[
        "Herveo"
    ],
    "name:gle_x_preferred":[
        "Herveo"
    ],
    "name:ita_x_preferred":[
        "Herveo"
    ],
    "name:kat_x_preferred":[
        "\u10d4\u10e0\u10d5\u10d4\u10dd"
    ],
    "name:msa_x_preferred":[
        "Herveo"
    ],
    "name:nan_x_preferred":[
        "Herveo"
    ],
    "name:nld_x_preferred":[
        "Herveo"
    ],
    "name:pol_x_preferred":[
        "Herveo"
    ],
    "name:por_x_preferred":[
        "Herveo"
    ],
    "name:spa_x_preferred":[
        "Herveo"
    ],
    "name:swe_x_preferred":[
        "Herveo"
    ],
    "name:ukr_x_preferred":[
        "\u0415\u0440\u0432\u0435\u043e"
    ],
    "name:und_x_variant":[
        "Herbeo"
    ],
    "name:vie_x_preferred":[
        "Herveo"
    ],
    "name:war_x_preferred":[
        "Herveo"
    ],
    "name:zho_x_preferred":[
        "\u8d6b\u723e\u97cb\u5967"
    ],
    "qs:name":"Herveo",
    "qs:photos_9r":0,
    "qs:photos_sr":0,
    "qs:pop_sr":"4",
    "wd:wordcount":44,
    "wof:name":"Herveo",
    "wof:placetype":"locality",
    "wof:population":3490
},
  "geometry": {"coordinates":[-75.16667,5.08333],"type":"Point"}
}