{
  "type": "Feature",
  "properties": {
    "gn:admin1_code":"17.0",
    "gn:admin2_code":"44560.0",
    "gn:asciiname":"Shichepeho",
    "gn:country_code":"CO",
    "gn:dem":-1,
    "gn:feature_class":"P",
    "gn:feature_code":"PPL",
    "gn:name":"Shichepeho",
    "gn:population":0,
    "gn:timezone":"America/Bogota",
    "iso:country":"CO",
    "wof:name":"Shichepeho",
    "wof:placetype":"locality"
},
  "geometry": {"coordinates":[-72.66444,11.68917],"type":"Point"}
}