{
  "type": "Feature",
  "properties": {
    "gn:admin1_code":"28",
    "gn:admin2_code":"73268.0",
    "gn:asciiname":"Guacimal",
    "gn:country_code":"CO",
    "gn:dem":350,
    "gn:feature_class":"P",
    "gn:feature_code":"PPL",
    "gn:name":"Guacimal",
    "gn:population":0,
    "gn:timezone":"America/Bogota",
    "iso:country":"CO",
    "wof:name":"Guacimal",
    "wof:placetype":"locality"
},
  "geometry": {"coordinates":[-74.94606999999998,4.15432],"type":"Point"}
}