{
  "type": "Feature",
  "properties": {
    "gn:admin1_code":"33",
    "gn:admin2_code":"25001.0",
    "gn:asciiname":"La Balsita",
    "gn:country_code":"CO",
    "gn:dem":332,
    "gn:feature_class":"P",
    "gn:feature_code":"PPL",
    "gn:name":"La Balsita",
    "gn:population":0,
    "gn:timezone":"America/Bogota",
    "iso:country":"CO",
    "name:und_x_variant":[
        "Caser\u00edo La Balsita",
        "Balsita",
        "La Balsita"
    ],
    "wof:name":"La Balsita",
    "wof:placetype":"locality"
},
  "geometry": {"coordinates":[-74.71666999999999,4.35787],"type":"Point"}
}