{
  "type": "Feature",
  "properties": {
    "gn:admin1_code":"9",
    "gn:admin2_code":"19130.0",
    "gn:asciiname":"Bellavista",
    "gn:country_code":"CO",
    "gn:dem":1696,
    "gn:feature_class":"P",
    "gn:feature_code":"PPL",
    "gn:name":"Bellavista",
    "gn:population":0,
    "gn:timezone":"America/Bogota",
    "iso:country":"CO",
    "wof:name":"Bellavista",
    "wof:placetype":"locality"
},
  "geometry": {"coordinates":[-76.73241999999998,2.64993],"type":"Point"}
}