{
  "type": "Feature",
  "properties": {
    "gn:admin1_code":"21",
    "gn:admin2_code":"54001.0",
    "gn:asciiname":"Los Mangos",
    "gn:country_code":"CO",
    "gn:dem":233,
    "gn:feature_class":"P",
    "gn:feature_code":"PPL",
    "gn:name":"Los Mangos",
    "gn:population":0,
    "gn:timezone":"America/Bogota",
    "iso:country":"CO",
    "wof:name":"Los Mangos",
    "wof:placetype":"locality"
},
  "geometry": {"coordinates":[-72.39194000000001,8.07194],"type":"Point"}
}