{
  "type": "Feature",
  "properties": {
    "gn:admin1_code":"2",
    "gn:admin2_code":"5837.0",
    "gn:asciiname":"La Pulga",
    "gn:country_code":"CO",
    "gn:dem":0,
    "gn:feature_class":"P",
    "gn:feature_code":"PPL",
    "gn:name":"La Pulga",
    "gn:population":0,
    "gn:timezone":"America/Bogota",
    "iso:country":"CO",
    "wof:name":"La Pulga",
    "wof:placetype":"locality"
},
  "geometry": {"coordinates":[-77.03333000000001,7.85],"type":"Point"}
}