{
  "type": "Feature",
  "properties": {
    "gn:admin1_code":"29.0",
    "gn:admin2_code":"76001.0",
    "gn:asciiname":"La Buitrera",
    "gn:country_code":"CO",
    "gn:dem":1051,
    "gn:feature_class":"P",
    "gn:feature_code":"PPL",
    "gn:name":"La Buitrera",
    "gn:population":0,
    "gn:timezone":"America/Bogota",
    "iso:country":"CO",
    "wof:name":"La Buitrera",
    "wof:placetype":"locality"
},
  "geometry": {"coordinates":[-76.55847,3.3635],"type":"Point"}
}