{
  "type": "Feature",
  "properties": {
    "gn:admin1_code":"32",
    "gn:admin2_code":"85250.0",
    "gn:asciiname":"Cano Chiquito",
    "gn:country_code":"CO",
    "gn:dem":166,
    "gn:feature_class":"P",
    "gn:feature_code":"PPL",
    "gn:name":"Ca\u00f1o Chiquito",
    "gn:population":0,
    "gn:timezone":"America/Bogota",
    "iso:country":"CO",
    "wof:name":"Cano Chiquito",
    "wof:placetype":"locality"
},
  "geometry": {"coordinates":[-71.48333000000002,5.75],"type":"Point"}
}