{
  "type": "Feature",
  "properties": {
    "gn:admin1_code":"9.0",
    "gn:admin2_code":"19743.0",
    "gn:asciiname":"Tumburao",
    "gn:country_code":"CO",
    "gn:dem":2126,
    "gn:feature_class":"P",
    "gn:feature_code":"PPL",
    "gn:name":"Tumburao",
    "gn:population":0,
    "gn:timezone":"America/Bogota",
    "iso:country":"CO",
    "wof:name":"Tumburao",
    "wof:placetype":"locality"
},
  "geometry": {"coordinates":[-76.48978000000002,2.71681],"type":"Point"}
}