{
  "type": "Feature",
  "properties": {
    "iso:country":"CO",
    "name:ceb_x_preferred":[
        "La Celia"
    ],
    "name:chi_x_preferred":[
        "\u62c9\u897f\u8389\u4e9e"
    ],
    "name:dut_x_preferred":[
        "La Celia"
    ],
    "name:eng_x_preferred":[
        "La Celia"
    ],
    "name:fra_x_preferred":[
        "La Celia"
    ],
    "name:fre_x_preferred":[
        "La Celia"
    ],
    "name:geo_x_preferred":[
        "\u10da\u10d0-\u10e1\u10d4\u10da\u10d8\u10d0"
    ],
    "name:ita_x_preferred":[
        "La Celia"
    ],
    "name:kat_x_preferred":[
        "\u10da\u10d0-\u10e1\u10d4\u10da\u10d8\u10d0"
    ],
    "name:may_x_preferred":[
        "La Celia"
    ],
    "name:msa_x_preferred":[
        "La Celia"
    ],
    "name:nan_x_preferred":[
        "La Celia"
    ],
    "name:nld_x_preferred":[
        "La Celia"
    ],
    "name:spa_x_preferred":[
        "La Celia"
    ],
    "name:swe_x_preferred":[
        "La Celia"
    ],
    "name:tgl_x_preferred":[
        "La Celia"
    ],
    "name:urd_x_preferred":[
        "\u0644\u0627 \u0633\u06cc\u0644\u06cc\u0627"
    ],
    "name:vie_x_preferred":[
        "La Celia"
    ],
    "name:war_x_preferred":[
        "La Celia"
    ],
    "name:zho_min_nan_x_preferred":[
        "La Celia"
    ],
    "name:zho_x_preferred":[
        "\u62c9\u897f\u8389\u4e9e"
    ],
    "qs:gn_country":"CO",
    "qs:gn_fcode":"PPL",
    "qs:gn_pop":4940,
    "qs:name":"La Celia",
    "qs:name_adm0":"Colombia",
    "qs:name_adm1":"Risaralda",
    "qs:photos":0,
    "qs:photos_1k":0,
    "qs:photos_9k":1,
    "qs:photos_9r":1,
    "qs:photos_all":2,
    "qs:photos_sr":0,
    "qs:placetype":"Town",
    "qs:pop_sr":"4",
    "qs:woe_adm0":23424787,
    "wd:wordcount":70,
    "wof:name":"La Celia",
    "wof:placetype":"locality",
    "wof:population":4940
},
  "geometry": {"coordinates":[-76.01667,5.04333],"type":"Point"}
}