{
  "type": "Feature",
  "properties": {
    "gn:admin1_code":"2.0",
    "gn:admin2_code":"5042.0",
    "gn:asciiname":"El Llano de Bolivar",
    "gn:country_code":"CO",
    "gn:dem":597,
    "gn:feature_class":"P",
    "gn:feature_code":"PPL",
    "gn:name":"El Llano de Bolivar",
    "gn:population":0,
    "gn:timezone":"America/Bogota",
    "iso:country":"CO",
    "wof:name":"El Llano de Bolivar",
    "wof:placetype":"locality"
},
  "geometry": {"coordinates":[-75.815,6.56861],"type":"Point"}
}