{
  "type": "Feature",
  "properties": {
    "gn:admin1_code":"9",
    "gn:admin2_code":"19622.0",
    "gn:asciiname":"Derrumbo",
    "gn:country_code":"CO",
    "gn:dem":1776,
    "gn:feature_class":"P",
    "gn:feature_code":"PPL",
    "gn:name":"Derrumbo",
    "gn:population":0,
    "gn:timezone":"America/Bogota",
    "iso:country":"CO",
    "wof:name":"Derrumbo",
    "wof:placetype":"locality"
},
  "geometry": {"coordinates":[-76.71666999999999,2.23333],"type":"Point"}
}