{
  "type": "Feature",
  "properties": {
    "gn:admin1_code":"28",
    "gn:admin2_code":"73678.0",
    "gn:asciiname":"La Esperanza",
    "gn:country_code":"CO",
    "gn:dem":342,
    "gn:feature_class":"P",
    "gn:feature_code":"PPL",
    "gn:name":"La Esperanza",
    "gn:population":0,
    "gn:timezone":"America/Bogota",
    "iso:country":"CO",
    "wof:name":"La Esperanza",
    "wof:placetype":"locality"
},
  "geometry": {"coordinates":[-75.11111,3.9825],"type":"Point"}
}