{
  "type": "Feature",
  "properties": {
    "gn:admin1_code":"20.0",
    "gn:admin2_code":"52490.0",
    "gn:asciiname":"Naranjito",
    "gn:country_code":"CO",
    "gn:dem":39,
    "gn:feature_class":"P",
    "gn:feature_code":"PPL",
    "gn:name":"Naranjito",
    "gn:population":0,
    "gn:timezone":"America/Bogota",
    "iso:country":"CO",
    "name:bre_x_preferred":[
        "Naranjito"
    ],
    "name:ceb_x_preferred":[
        "Naranjito"
    ],
    "name:deu_x_preferred":[
        "Naranjito"
    ],
    "name:ita_x_preferred":[
        "Naranjito"
    ],
    "name:nld_x_preferred":[
        "Naranjito"
    ],
    "name:pol_x_preferred":[
        "Naranjito"
    ],
    "name:slv_x_preferred":[
        "Naranjito"
    ],
    "name:spa_x_preferred":[
        "Naranjito"
    ],
    "name:swe_x_preferred":[
        "Naranjito"
    ],
    "wof:name":"Naranjito",
    "wof:placetype":"locality"
},
  "geometry": {"coordinates":[-78.28591999999998,2.04493],"type":"Point"}
}