{
  "type": "Feature",
  "properties": {
    "gn:admin1_code":"33",
    "gn:admin2_code":"25885.0",
    "gn:asciiname":"Hatico",
    "gn:country_code":"CO",
    "gn:dem":1135,
    "gn:feature_class":"P",
    "gn:feature_code":"PPL",
    "gn:name":"Hatico",
    "gn:population":0,
    "gn:timezone":"America/Bogota",
    "iso:country":"CO",
    "wof:name":"Hatico",
    "wof:placetype":"locality"
},
  "geometry": {"coordinates":[-74.31583000000001,5.52833],"type":"Point"}
}