{
  "type": "Feature",
  "properties": {
    "gn:admin1_code":"22.0",
    "gn:admin2_code":"86571.0",
    "gn:asciiname":"Las Delicias",
    "gn:country_code":"CO",
    "gn:dem":263,
    "gn:feature_class":"P",
    "gn:feature_code":"PPL",
    "gn:name":"Las Delicias",
    "gn:population":0,
    "gn:timezone":"America/Bogota",
    "iso:country":"CO",
    "name:ceb_x_preferred":[
        "Las Delicias"
    ],
    "name:ita_x_preferred":[
        "Las Delicias"
    ],
    "name:swe_x_preferred":[
        "Las Delicias"
    ],
    "wof:name":"Las Delicias",
    "wof:placetype":"locality"
},
  "geometry": {"coordinates":[-76.38627,0.92297],"type":"Point"}
}