{
  "type": "Feature",
  "properties": {
    "gn:admin1_code":"26",
    "gn:admin2_code":"68101.0",
    "gn:asciiname":"Plan de Gracia",
    "gn:country_code":"CO",
    "gn:dem":2852,
    "gn:feature_class":"P",
    "gn:feature_code":"PPL",
    "gn:name":"Plan de Gracia",
    "gn:population":0,
    "gn:timezone":"America/Bogota",
    "iso:country":"CO",
    "wof:name":"Plan de Gracia",
    "wof:placetype":"locality"
},
  "geometry": {"coordinates":[-73.83360999999999,5.98556],"type":"Point"}
}