{
  "type": "Feature",
  "properties": {
    "gn:admin1_code":"36.0",
    "gn:admin2_code":"15516.0",
    "gn:asciiname":"Rondon",
    "gn:country_code":"CO",
    "gn:dem":2525,
    "gn:feature_class":"P",
    "gn:feature_code":"PPL",
    "gn:name":"Rond\u00f3n",
    "gn:population":0,
    "gn:timezone":"America/Bogota",
    "iso:country":"CO",
    "name:bpy_x_preferred":[
        "\u09b0\u09cb\u09a8\u09a1\u09cb\u09a8"
    ],
    "name:ceb_x_preferred":[
        "Rondon"
    ],
    "name:deu_x_preferred":[
        "Rondon"
    ],
    "name:nld_x_preferred":[
        "Rondon"
    ],
    "name:por_x_preferred":[
        "Rondon"
    ],
    "name:rus_x_preferred":[
        "\u0420\u043e\u043d\u0434\u043e\u043d"
    ],
    "name:sco_x_preferred":[
        "Rondon"
    ],
    "name:swe_x_preferred":[
        "Rondon"
    ],
    "wof:name":"Rondon",
    "wof:placetype":"locality"
},
  "geometry": {"coordinates":[-73.07176,5.73657],"type":"Point"}
}