{
  "type": "Feature",
  "properties": {
    "gn:admin1_code":"9",
    "gn:admin2_code":"19450.0",
    "gn:asciiname":"Pilon",
    "gn:country_code":"CO",
    "gn:dem":608,
    "gn:feature_class":"P",
    "gn:feature_code":"PPL",
    "gn:name":"Pil\u00f3n",
    "gn:population":0,
    "gn:timezone":"America/Bogota",
    "iso:country":"CO",
    "name:ceb_x_preferred":[
        "Pilon"
    ],
    "name:deu_x_preferred":[
        "Pilon"
    ],
    "name:fra_x_preferred":[
        "Pilon"
    ],
    "name:hun_x_preferred":[
        "Pilon"
    ],
    "name:nds_x_preferred":[
        "Pilon"
    ],
    "name:pol_x_preferred":[
        "Pilon"
    ],
    "name:slv_x_preferred":[
        "Pilon"
    ],
    "name:swe_x_preferred":[
        "Pilon"
    ],
    "wof:name":"Pilon",
    "wof:placetype":"locality"
},
  "geometry": {"coordinates":[-77.15778,1.93167],"type":"Point"}
}