{
  "type": "Feature",
  "properties": {
    "iso:country":"CO",
    "name:eng_x_preferred":[
        "Angostura"
    ],
    "name:fra_x_preferred":[
        "Angostura"
    ],
    "name:gla_x_preferred":[
        "Angostura"
    ],
    "name:ile_x_preferred":[
        "Angostura"
    ],
    "name:ita_x_preferred":[
        "Angostura"
    ],
    "name:kat_x_preferred":[
        "\u10d0\u10dc\u10d2\u10dd\u10e1\u10e2\u10e3\u10e0\u10d0"
    ],
    "name:msa_x_preferred":[
        "Angostura"
    ],
    "name:nan_x_preferred":[
        "Angostura"
    ],
    "name:nld_x_preferred":[
        "Angostura"
    ],
    "name:por_x_preferred":[
        "Angostura"
    ],
    "name:ron_x_preferred":[
        "Angostura"
    ],
    "name:rus_x_preferred":[
        "\u0410\u043d\u0433\u043e\u0441\u0442\u0443\u0440\u0430"
    ],
    "name:spa_x_preferred":[
        "Angostura"
    ],
    "name:swe_x_preferred":[
        "Angostura"
    ],
    "name:tgl_x_preferred":[
        "Angostura"
    ],
    "name:unk_x_variant":[
        "Angosturas"
    ],
    "name:war_x_preferred":[
        "Angostura"
    ],
    "name:zho_x_preferred":[
        "\u5b89\u6208\u65af\u5716\u62c9"
    ],
    "qs:gn_country":"CO",
    "qs:gn_fcode":"PPL",
    "qs:gn_pop":3639,
    "qs:name":"Angostura",
    "qs:name_adm0":"Colombia",
    "qs:name_adm1":"Antioquia",
    "qs:photos":0,
    "qs:photos_1k":0,
    "qs:photos_9k":0,
    "qs:photos_9r":0,
    "qs:photos_all":0,
    "qs:photos_sr":0,
    "qs:placetype":"Town",
    "qs:pop_sr":"4",
    "qs:woe_adm0":23424787,
    "wof:name":"Angostura",
    "wof:placetype":"locality",
    "wof:population":3639
},
  "geometry": {"coordinates":[-75.33467,6.88508],"type":"Point"}
}