{
  "type": "Feature",
  "properties": {
    "gn:admin1_code":"12.0",
    "gn:admin2_code":"23678.0",
    "gn:asciiname":"Damasco",
    "gn:country_code":"CO",
    "gn:dem":10,
    "gn:feature_class":"P",
    "gn:feature_code":"PPLL",
    "gn:name":"Damasco",
    "gn:population":0,
    "gn:timezone":"America/Bogota",
    "iso:country":"CO",
    "wof:name":"Damasco",
    "wof:placetype":"locality"
},
  "geometry": {"coordinates":[-75.69110999999999,8.80139],"type":"Point"}
}