{
  "type": "Feature",
  "properties": {
    "gn:admin1_code":"28.0",
    "gn:admin2_code":"73067.0",
    "gn:asciiname":"Alcayata",
    "gn:country_code":"CO",
    "gn:dem":1022,
    "gn:feature_class":"P",
    "gn:feature_code":"PPL",
    "gn:name":"Alcayata",
    "gn:population":0,
    "gn:timezone":"America/Bogota",
    "iso:country":"CO",
    "wof:name":"Alcayata",
    "wof:placetype":"locality"
},
  "geometry": {"coordinates":[-75.31583000000001,3.61222],"type":"Point"}
}