{
  "type": "Feature",
  "properties": {
    "gn:admin1_code":"27",
    "gn:admin2_code":"70235.0",
    "gn:asciiname":"El Paraiso",
    "gn:country_code":"CO",
    "gn:dem":34,
    "gn:feature_class":"P",
    "gn:feature_code":"PPL",
    "gn:name":"El Para\u00edso",
    "gn:population":0,
    "gn:timezone":"America/Bogota",
    "iso:country":"CO",
    "wof:name":"El Paraiso",
    "wof:placetype":"locality"
},
  "geometry": {"coordinates":[-74.90966999999998,9.13477],"type":"Point"}
}