{
  "type": "Feature",
  "properties": {
    "gn:admin1_code":"29",
    "gn:admin2_code":"76834.0",
    "gn:asciiname":"Casa de Tabla",
    "gn:country_code":"CO",
    "gn:dem":3208,
    "gn:feature_class":"P",
    "gn:feature_code":"PPL",
    "gn:name":"Casa de Tabla",
    "gn:population":0,
    "gn:timezone":"America/Bogota",
    "iso:country":"CO",
    "wof:name":"Casa de Tabla",
    "wof:placetype":"locality"
},
  "geometry": {"coordinates":[-75.82278000000002,3.94611],"type":"Point"}
}