{
  "type": "Feature",
  "properties": {
    "gn:admin1_code":"12",
    "gn:admin2_code":"23001.0",
    "gn:asciiname":"Maracayo",
    "gn:country_code":"CO",
    "gn:dem":35,
    "gn:feature_class":"P",
    "gn:feature_code":"PPL",
    "gn:name":"Maracayo",
    "gn:population":0,
    "gn:timezone":"America/Bogota",
    "iso:country":"CO",
    "name:und_x_variant":[
        "Maracaibo",
        "Maracayo"
    ],
    "wof:name":"Maracayo",
    "wof:placetype":"locality"
},
  "geometry": {"coordinates":[-75.89276,8.40881],"type":"Point"}
}