{
  "type": "Feature",
  "properties": {
    "gn:admin1_code":"33.0",
    "gn:admin2_code":"25320.0",
    "gn:asciiname":"El Otono Lithia",
    "gn:country_code":"CO",
    "gn:dem":1215,
    "gn:feature_class":"P",
    "gn:feature_code":"PPL",
    "gn:name":"El Otono Lithia",
    "gn:population":0,
    "gn:timezone":"America/Bogota",
    "iso:country":"CO",
    "name:spa_x_preferred":[
        "El Otono Lithia"
    ],
    "wof:name":"El Otono Lithia",
    "wof:placetype":"locality"
},
  "geometry": {"coordinates":[-74.58456,5.08839],"type":"Point"}
}