{
  "type": "Feature",
  "properties": {
    "gn:admin1_code":"20.0",
    "gn:admin2_code":"52490.0",
    "gn:asciiname":"Casitas",
    "gn:country_code":"CO",
    "gn:dem":16,
    "gn:feature_class":"P",
    "gn:feature_code":"PPL",
    "gn:name":"Casitas",
    "gn:population":0,
    "gn:timezone":"America/Bogota",
    "iso:country":"CO",
    "wof:name":"Casitas",
    "wof:placetype":"locality"
},
  "geometry": {"coordinates":[-78.21483000000001,2.15213],"type":"Point"}
}