{
  "type": "Feature",
  "properties": {
    "iso:country":"CO",
    "name:ast_x_preferred":[
        "Candelaria"
    ],
    "name:avk_x_preferred":[
        "Candelaria"
    ],
    "name:cat_x_preferred":[
        "Candelaria"
    ],
    "name:ceb_x_preferred":[
        "Candelaria"
    ],
    "name:deu_x_preferred":[
        "Candelaria"
    ],
    "name:eng_x_preferred":[
        "Candelaria"
    ],
    "name:fas_x_preferred":[
        "\u06a9\u0627\u0646\u062f\u0644\u0627\u0631\u06cc\u0627"
    ],
    "name:fra_x_preferred":[
        "Candelaria"
    ],
    "name:gle_x_preferred":[
        "Candelaria"
    ],
    "name:ita_x_preferred":[
        "Candelaria"
    ],
    "name:kat_x_preferred":[
        "\u10d9\u10d0\u10dc\u10d3\u10d4\u10da\u10d0\u10e0\u10d8\u10d0"
    ],
    "name:msa_x_preferred":[
        "Candelaria"
    ],
    "name:nan_x_preferred":[
        "Candelaria"
    ],
    "name:nld_x_preferred":[
        "Candelaria"
    ],
    "name:pol_x_preferred":[
        "Candelaria"
    ],
    "name:rus_x_preferred":[
        "\u041a\u0430\u043d\u0434\u0435\u043b\u0430\u0440\u0438\u044f"
    ],
    "name:sco_x_preferred":[
        "Candelaria"
    ],
    "name:spa_x_preferred":[
        "Candelaria"
    ],
    "name:swe_x_preferred":[
        "Candelaria"
    ],
    "name:swe_x_variant":[
        "Santa Rosita"
    ],
    "name:vie_x_preferred":[
        "Candelaria"
    ],
    "name:war_x_preferred":[
        "Candelaria"
    ],
    "name:zho_x_preferred":[
        "\u574e\u5fb7\u62c9\u91cc\u4e9e"
    ],
    "qs:gn_country":"CO",
    "qs:gn_fcode":"PPL",
    "qs:gn_pop":23989,
    "qs:name":"Candelaria",
    "qs:name_adm0":"Colombia",
    "qs:name_adm1":"Valle del Cauca",
    "qs:photos":35,
    "qs:photos_1k":7,
    "qs:photos_9k":1,
    "qs:photos_9r":2,
    "qs:photos_all":35,
    "qs:photos_sr":2,
    "qs:placetype":"Town",
    "qs:pop_sr":"7",
    "qs:woe_adm0":23424787,
    "wof:name":"Candelaria",
    "wof:placetype":"locality",
    "wof:population":23989
},
  "geometry": {"coordinates":[-76.34819,3.40671],"type":"Point"}
}