{
  "type": "Feature",
  "properties": {
    "gn:admin1_code":"2.0",
    "gn:admin2_code":"5264.0",
    "gn:asciiname":"Mestizal",
    "gn:country_code":"CO",
    "gn:dem":2505,
    "gn:feature_class":"P",
    "gn:feature_code":"PPL",
    "gn:name":"Mestizal",
    "gn:population":0,
    "gn:timezone":"America/Bogota",
    "iso:country":"CO",
    "wof:name":"Mestizal",
    "wof:placetype":"locality"
},
  "geometry": {"coordinates":[-75.58028,6.64139],"type":"Point"}
}