{
  "type": "Feature",
  "properties": {
    "gn:admin1_code":"29",
    "gn:admin2_code":"76520.0",
    "gn:asciiname":"Boyaca",
    "gn:country_code":"CO",
    "gn:dem":1052,
    "gn:feature_class":"P",
    "gn:feature_code":"PPL",
    "gn:name":"Boyac\u00e1",
    "gn:population":0,
    "gn:timezone":"America/Bogota",
    "iso:country":"CO",
    "wof:name":"Boyaca",
    "wof:placetype":"locality"
},
  "geometry": {"coordinates":[-76.24972,3.60306],"type":"Point"}
}