{
  "type": "Feature",
  "properties": {
    "gn:admin1_code":"10.0",
    "gn:admin2_code":"20178.0",
    "gn:asciiname":"San Juan de Tupe",
    "gn:country_code":"CO",
    "gn:dem":33,
    "gn:feature_class":"P",
    "gn:feature_code":"PPL",
    "gn:name":"San Juan de Tupe",
    "gn:population":0,
    "gn:timezone":"America/Bogota",
    "iso:country":"CO",
    "wof:name":"San Juan de Tupe",
    "wof:placetype":"locality"
},
  "geometry": {"coordinates":[-73.55073,9.39957],"type":"Point"}
}