{
  "type": "Feature",
  "properties": {
    "gn:admin1_code":"19",
    "gn:admin2_code":"50001.0",
    "gn:asciiname":"La Primavera",
    "gn:country_code":"CO",
    "gn:dem":310,
    "gn:feature_class":"P",
    "gn:feature_code":"PPL",
    "gn:name":"La Primavera",
    "gn:population":0,
    "gn:timezone":"America/Bogota",
    "iso:country":"CO",
    "wof:name":"La Primavera",
    "wof:placetype":"locality"
},
  "geometry": {"coordinates":[-73.46149,4.01319],"type":"Point"}
}