{
  "type": "Feature",
  "properties": {
    "gn:admin1_code":"10",
    "gn:admin2_code":"20238.0",
    "gn:asciiname":"La Constancia",
    "gn:country_code":"CO",
    "gn:dem":111,
    "gn:feature_class":"P",
    "gn:feature_code":"PPL",
    "gn:name":"La Constancia",
    "gn:population":0,
    "gn:timezone":"America/Bogota",
    "iso:country":"CO",
    "wof:name":"La Constancia",
    "wof:placetype":"locality"
},
  "geometry": {"coordinates":[-73.93333,10.08333],"type":"Point"}
}