{
  "type": "Feature",
  "properties": {
    "gn:admin1_code":"9.0",
    "gn:admin2_code":"19256.0",
    "gn:asciiname":"La Emboscada",
    "gn:country_code":"CO",
    "gn:dem":464,
    "gn:feature_class":"P",
    "gn:feature_code":"PPL",
    "gn:name":"La Emboscada",
    "gn:population":0,
    "gn:timezone":"America/Bogota",
    "iso:country":"CO",
    "wof:name":"La Emboscada",
    "wof:placetype":"locality"
},
  "geometry": {"coordinates":[-77.21885999999998,2.5388],"type":"Point"}
}