{
  "type": "Feature",
  "properties": {
    "gn:admin1_code":"29.0",
    "gn:admin2_code":"76001.0",
    "gn:asciiname":"Caserio La Pena",
    "gn:country_code":"CO",
    "gn:dem":1507,
    "gn:feature_class":"P",
    "gn:feature_code":"PPLL",
    "gn:name":"Caserio La Pe\u00f1a",
    "gn:population":0,
    "gn:timezone":"America/Bogota",
    "iso:country":"CO",
    "name:spa_x_preferred":[
        "Caserio La Pe\u00f1a"
    ],
    "wof:name":"Caserio La Pena",
    "wof:placetype":"locality"
},
  "geometry": {"coordinates":[-76.61948000000002,3.32836],"type":"Point"}
}