{
  "type": "Feature",
  "properties": {
    "gn:admin1_code":"36",
    "gn:admin2_code":"15776.0",
    "gn:asciiname":"Chupadero",
    "gn:country_code":"CO",
    "gn:dem":2215,
    "gn:feature_class":"P",
    "gn:feature_code":"PPL",
    "gn:name":"Chupadero",
    "gn:population":0,
    "gn:timezone":"America/Bogota",
    "iso:country":"CO",
    "wof:name":"Chupadero",
    "wof:placetype":"locality"
},
  "geometry": {"coordinates":[-73.59278,5.67444],"type":"Point"}
}