{
  "type": "Feature",
  "properties": {
    "gn:admin1_code":"17",
    "gn:admin2_code":"44430.0",
    "gn:asciiname":"Maranamahana",
    "gn:country_code":"CO",
    "gn:dem":77,
    "gn:feature_class":"P",
    "gn:feature_code":"PPL",
    "gn:name":"Mara\u00f1amahana",
    "gn:population":0,
    "gn:timezone":"America/Bogota",
    "iso:country":"CO",
    "name:und_x_variant":[
        "Mara\u00f1amana",
        "Mara\u00f1amahana"
    ],
    "wof:name":"Maranamahana",
    "wof:placetype":"locality"
},
  "geometry": {"coordinates":[-72.38849,11.3673],"type":"Point"}
}