{
  "type": "Feature",
  "properties": {
    "gn:admin1_code":"22.0",
    "gn:admin2_code":"86571.0",
    "gn:asciiname":"La Palmera",
    "gn:country_code":"CO",
    "gn:dem":272,
    "gn:feature_class":"P",
    "gn:feature_code":"PPL",
    "gn:name":"La Palmera",
    "gn:population":0,
    "gn:timezone":"America/Bogota",
    "iso:country":"CO",
    "wof:name":"La Palmera",
    "wof:placetype":"locality"
},
  "geometry": {"coordinates":[-76.38319,0.95248],"type":"Point"}
}