{
  "type": "Feature",
  "properties": {
    "gn:admin1_code":"2.0",
    "gn:admin2_code":"5789.0",
    "gn:asciiname":"Palermo",
    "gn:country_code":"CO",
    "gn:dem":1239,
    "gn:feature_class":"P",
    "gn:feature_code":"PPL",
    "gn:name":"Palermo",
    "gn:population":0,
    "gn:timezone":"America/Bogota",
    "iso:country":"CO",
    "wof:name":"Palermo",
    "wof:placetype":"locality"
},
  "geometry": {"coordinates":[-75.69479,5.73145],"type":"Point"}
}