{
  "type": "Feature",
  "properties": {
    "gn:admin1_code":"2.0",
    "gn:admin2_code":"5789.0",
    "gn:asciiname":"Palermo",
    "gn:country_code":"CO",
    "gn:dem":1239,
    "gn:feature_class":"P",
    "gn:feature_code":"PPL",
    "gn:name":"Palermo",
    "gn:population":0,
    "gn:timezone":"America/Bogota",
    "iso:country":"CO",
    "name:ben_x_preferred":[
        "\u09aa\u09be\u09b2\u09c7\u09b0\u09ae\u09cb"
    ],
    "name:hin_x_preferred":[
        "\u092a\u0932\u0947\u0930\u094d\u092e\u094b"
    ],
    "wof:name":"Palermo",
    "wof:placetype":"locality"
},
  "geometry": {"coordinates":[-75.69479,5.73145],"type":"Point"}
}