{
  "type": "Feature",
  "properties": {
    "gn:admin1_code":"2.0",
    "gn:admin2_code":"5837.0",
    "gn:asciiname":"Yarumal",
    "gn:country_code":"CO",
    "gn:dem":5,
    "gn:feature_class":"P",
    "gn:feature_code":"PPL",
    "gn:name":"Yarumal",
    "gn:population":0,
    "gn:timezone":"America/Bogota",
    "iso:country":"CO",
    "name:und_x_variant":[
        "Yaruma",
        "Yarumal"
    ],
    "wof:name":"Yarumal",
    "wof:placetype":"locality"
},
  "geometry": {"coordinates":[-76.7364,8.12355],"type":"Point"}
}