{
  "type": "Feature",
  "properties": {
    "gn:admin1_code":"2.0",
    "gn:admin2_code":"5837.0",
    "gn:asciiname":"Yarumal",
    "gn:country_code":"CO",
    "gn:dem":5,
    "gn:feature_class":"P",
    "gn:feature_code":"PPL",
    "gn:name":"Yarumal",
    "gn:population":0,
    "gn:timezone":"America/Bogota",
    "iso:country":"CO",
    "name:ara_x_preferred":[
        "\u0628\u0644\u062f\u064a\u0629 \u064a\u0627\u0631\u0648\u0645\u0627\u0644"
    ],
    "name:deu_x_preferred":[
        "Yarumal"
    ],
    "name:fas_x_preferred":[
        "\u06cc\u0627\u0631\u0648\u0645\u0627\u0644"
    ],
    "name:fra_x_preferred":[
        "Yarumal"
    ],
    "name:ile_x_preferred":[
        "Yarumal"
    ],
    "name:ilo_x_preferred":[
        "Yarumal"
    ],
    "name:ita_x_preferred":[
        "Yarumal"
    ],
    "name:kat_x_preferred":[
        "\u10d8\u10d0\u10e0\u10e3\u10db\u10d0\u10da\u10d8"
    ],
    "name:kor_x_preferred":[
        "\uc57c\ub8e8\ub9d0"
    ],
    "name:msa_x_preferred":[
        "Yarumal"
    ],
    "name:nld_x_preferred":[
        "Yarumal"
    ],
    "name:por_x_preferred":[
        "Yarumal"
    ],
    "name:ron_x_preferred":[
        "Yarumal"
    ],
    "name:rus_x_preferred":[
        "\u042f\u0440\u0443\u043c\u0430\u043b\u044c"
    ],
    "name:spa_x_preferred":[
        "Yarumal"
    ],
    "name:tgl_x_preferred":[
        "Yarumal"
    ],
    "name:ukr_x_preferred":[
        "\u042f\u0440\u0443\u043c\u0430\u043b\u044c"
    ],
    "name:und_x_variant":[
        "Yaruma"
    ],
    "name:urd_x_preferred":[
        "\u06cc\u0627\u0631\u0648\u0645\u0627\u0644"
    ],
    "name:vie_x_preferred":[
        "Yarumal"
    ],
    "name:war_x_preferred":[
        "Yarumal"
    ],
    "name:zho_x_preferred":[
        "\u4e9e\u9b6f\u99ac\u723e"
    ],
    "wof:name":"Yarumal",
    "wof:placetype":"locality"
},
  "geometry": {"coordinates":[-76.7364,8.12355],"type":"Point"}
}