{
  "type": "Feature",
  "properties": {
    "gn:admin1_code":"29",
    "gn:admin2_code":"76834.0",
    "gn:asciiname":"El Delirio",
    "gn:country_code":"CO",
    "gn:dem":3267,
    "gn:feature_class":"P",
    "gn:feature_code":"PPL",
    "gn:name":"El Delirio",
    "gn:population":0,
    "gn:timezone":"America/Bogota",
    "iso:country":"CO",
    "wof:name":"El Delirio",
    "wof:placetype":"locality"
},
  "geometry": {"coordinates":[-75.90916999999997,4.00361],"type":"Point"}
}