{
  "type": "Feature",
  "properties": {
    "gn:admin1_code":"20.0",
    "gn:admin2_code":"52001.0",
    "gn:asciiname":"Daza",
    "gn:country_code":"CO",
    "gn:dem":2825,
    "gn:feature_class":"P",
    "gn:feature_code":"PPL",
    "gn:name":"Daza",
    "gn:population":0,
    "gn:timezone":"America/Bogota",
    "iso:country":"CO",
    "name:deu_x_preferred":[
        "Daza"
    ],
    "name:fra_x_preferred":[
        "Daza"
    ],
    "name:spa_x_preferred":[
        "Daza"
    ],
    "wof:name":"Daza",
    "wof:placetype":"locality"
},
  "geometry": {"coordinates":[-77.27849000000001,1.26643],"type":"Point"}
}