{
  "type": "Feature",
  "properties": {
    "gn:admin1_code":"32.0",
    "gn:admin2_code":"85440.0",
    "gn:asciiname":"Viso del Toro",
    "gn:country_code":"CO",
    "gn:dem":181,
    "gn:feature_class":"P",
    "gn:feature_code":"PPL",
    "gn:name":"Viso del Toro",
    "gn:population":0,
    "gn:timezone":"America/Bogota",
    "iso:country":"CO",
    "wof:name":"Viso del Toro",
    "wof:placetype":"locality"
},
  "geometry": {"coordinates":[-72.80932,4.44229],"type":"Point"}
}