{
  "type": "Feature",
  "properties": {
    "gn:admin1_code":"2",
    "gn:admin2_code":"5649.0",
    "gn:asciiname":"La Bella",
    "gn:country_code":"CO",
    "gn:dem":886,
    "gn:feature_class":"P",
    "gn:feature_code":"PPL",
    "gn:name":"La Bella",
    "gn:population":0,
    "gn:timezone":"America/Bogota",
    "iso:country":"CO",
    "name:cat_x_preferred":[
        "La bella"
    ],
    "name:eus_x_preferred":[
        "Ederra"
    ],
    "name:fra_x_preferred":[
        "La Bella"
    ],
    "name:ita_x_preferred":[
        "La Bella"
    ],
    "name:mal_x_preferred":[
        "\u0d32 \u0d2c\u0d46\u0d32\u0d4d\u0d32"
    ],
    "name:pol_x_preferred":[
        "Portret kobiety"
    ],
    "name:rus_x_preferred":[
        "\u041a\u0440\u0430\u0441\u0430\u0432\u0438\u0446\u0430"
    ],
    "name:spa_x_preferred":[
        "La bella"
    ],
    "name:swe_x_preferred":[
        "La Bella"
    ],
    "name:ukr_x_preferred":[
        "\u041a\u0440\u0430\u0441\u0443\u043d\u044f"
    ],
    "wof:name":"La Bella",
    "wof:placetype":"locality"
},
  "geometry": {"coordinates":[-74.85167,6.28556],"type":"Point"}
}