{
  "type": "Feature",
  "properties": {
    "gn:admin1_code":"2",
    "gn:admin2_code":"5649.0",
    "gn:asciiname":"La Bella",
    "gn:country_code":"CO",
    "gn:dem":886,
    "gn:feature_class":"P",
    "gn:feature_code":"PPL",
    "gn:name":"La Bella",
    "gn:population":0,
    "gn:timezone":"America/Bogota",
    "iso:country":"CO",
    "wof:name":"La Bella",
    "wof:placetype":"locality"
},
  "geometry": {"coordinates":[-74.85167,6.28556],"type":"Point"}
}