{
  "type": "Feature",
  "properties": {
    "gn:admin1_code":"32",
    "gn:admin2_code":"85139.0",
    "gn:asciiname":"Matechiguiro",
    "gn:country_code":"CO",
    "gn:dem":167,
    "gn:feature_class":"P",
    "gn:feature_code":"PPL",
    "gn:name":"Matechiguiro",
    "gn:population":0,
    "gn:timezone":"America/Bogota",
    "iso:country":"CO",
    "wof:name":"Matechiguiro",
    "wof:placetype":"locality"
},
  "geometry": {"coordinates":[-72.095,4.80278],"type":"Point"}
}