{
  "type": "Feature",
  "properties": {
    "gn:admin1_code":"3",
    "gn:admin2_code":"81220.0",
    "gn:asciiname":"Altagracia",
    "gn:country_code":"CO",
    "gn:dem":107,
    "gn:feature_class":"P",
    "gn:feature_code":"PPL",
    "gn:name":"Altagracia",
    "gn:population":0,
    "gn:timezone":"America/Bogota",
    "iso:country":"CO",
    "name:cat_x_preferred":[
        "Altagracia"
    ],
    "name:fas_x_preferred":[
        "\u0627\u0644\u062a\u0627\u06af\u0631\u0627\u0634\u06cc\u0627"
    ],
    "name:fra_x_preferred":[
        "Altagracia"
    ],
    "name:ita_x_preferred":[
        "Altagracia"
    ],
    "name:spa_x_preferred":[
        "Altagracia"
    ],
    "name:swe_x_preferred":[
        "Altagracia"
    ],
    "name:urd_x_preferred":[
        "\u0627\u0644\u062a\u0627\u06af\u0631\u0627\u0633\u06cc\u0627"
    ],
    "name:vie_x_preferred":[
        "Altagracia"
    ],
    "name:zho_x_preferred":[
        "\u963f\u723e\u5854\u683c\u62c9\u897f\u4e9e"
    ],
    "wof:name":"Altagracia",
    "wof:placetype":"locality"
},
  "geometry": {"coordinates":[-70.48730999999999,6.34319],"type":"Point"}
}