{
  "type": "Feature",
  "properties": {
    "gn:admin1_code":"3",
    "gn:admin2_code":"81220.0",
    "gn:asciiname":"Altagracia",
    "gn:country_code":"CO",
    "gn:dem":107,
    "gn:feature_class":"P",
    "gn:feature_code":"PPL",
    "gn:name":"Altagracia",
    "gn:population":0,
    "gn:timezone":"America/Bogota",
    "iso:country":"CO",
    "wof:name":"Altagracia",
    "wof:placetype":"locality"
},
  "geometry": {"coordinates":[-70.48730999999999,6.34319],"type":"Point"}
}