{
  "type": "Feature",
  "properties": {
    "gn:admin1_code":"16",
    "gn:admin2_code":"41078",
    "gn:asciiname":"Santa Marta",
    "gn:country_code":"CO",
    "gn:dem":2250,
    "gn:feature_class":"P",
    "gn:feature_code":"PPL",
    "gn:name":"Santa Marta",
    "gn:population":0,
    "gn:timezone":"America/Bogota",
    "iso:country":"CO",
    "name:spa_x_preferred":[
        "Santa Marta"
    ],
    "wof:name":"Santa Marta",
    "wof:placetype":"locality"
},
  "geometry": {"coordinates":[-74.94296,2.95562],"type":"Point"}
}