{
  "type": "Feature",
  "properties": {
    "gn:admin1_code":"36",
    "gn:admin2_code":"15696.0",
    "gn:asciiname":"Santa Juana",
    "gn:country_code":"CO",
    "gn:dem":2049,
    "gn:feature_class":"P",
    "gn:feature_code":"PPL",
    "gn:name":"Santa Juana",
    "gn:population":0,
    "gn:timezone":"America/Bogota",
    "iso:country":"CO",
    "wof:name":"Santa Juana",
    "wof:placetype":"locality"
},
  "geometry": {"coordinates":[-73.595,5.78722],"type":"Point"}
}