{
  "type": "Feature",
  "properties": {
    "gn:admin1_code":"28",
    "gn:admin2_code":"73483.0",
    "gn:asciiname":"Celiano Dussan",
    "gn:cc2":"CO",
    "gn:country_code":"CO",
    "gn:dem":374,
    "gn:feature_class":"P",
    "gn:feature_code":"PPL",
    "gn:name":"Celiano Duss\u00e1n",
    "gn:population":0,
    "gn:timezone":"America/Bogota",
    "iso:country":"CO",
    "name:und_x_variant":[
        "Celiano",
        "Celiano Duss\u00e1n"
    ],
    "wof:name":"Celiano Dussan",
    "wof:placetype":"locality"
},
  "geometry": {"coordinates":[-75.11667,3.51667],"type":"Point"}
}