{
  "type": "Feature",
  "properties": {
    "gn:admin1_code":"12",
    "gn:admin2_code":"23586.0",
    "gn:asciiname":"Malena",
    "gn:country_code":"CO",
    "gn:dem":85,
    "gn:feature_class":"P",
    "gn:feature_code":"PPL",
    "gn:name":"Malena",
    "gn:population":0,
    "gn:timezone":"America/Bogota",
    "iso:country":"CO",
    "name:deu_x_preferred":[
        "Malena"
    ],
    "name:fra_x_preferred":[
        "Malena"
    ],
    "name:ita_x_preferred":[
        "Malena"
    ],
    "name:rus_x_preferred":[
        "\u041c\u0430\u043b\u0435\u043d\u0430"
    ],
    "name:spa_x_preferred":[
        "Malena"
    ],
    "wof:name":"Malena",
    "wof:placetype":"locality"
},
  "geometry": {"coordinates":[-75.72819,9.30679],"type":"Point"}
}