{
  "type": "Feature",
  "properties": {
    "gn:admin1_code":"33.0",
    "gn:admin2_code":"25839.0",
    "gn:asciiname":"Barro Blanco",
    "gn:country_code":"CO",
    "gn:dem":479,
    "gn:feature_class":"P",
    "gn:feature_code":"PPL",
    "gn:name":"Barro Blanco",
    "gn:population":0,
    "gn:timezone":"America/Bogota",
    "iso:country":"CO",
    "wof:name":"Barro Blanco",
    "wof:placetype":"locality"
},
  "geometry": {"coordinates":[-73.23535,4.71181],"type":"Point"}
}