{
  "type": "Feature",
  "properties": {
    "gn:admin1_code":"28.0",
    "gn:admin2_code":"73283.0",
    "gn:asciiname":"Partidas",
    "gn:country_code":"CO",
    "gn:dem":1942,
    "gn:feature_class":"P",
    "gn:feature_code":"PPL",
    "gn:name":"Partidas",
    "gn:population":0,
    "gn:timezone":"America/Bogota",
    "iso:country":"CO",
    "wof:name":"Partidas",
    "wof:placetype":"locality"
},
  "geometry": {"coordinates":[-75.09563,5.16382],"type":"Point"}
}