{
  "type": "Feature",
  "properties": {
    "gn:admin1_code":"35.0",
    "gn:admin2_code":"13212.0",
    "gn:asciiname":"Santa Lucia",
    "gn:country_code":"CO",
    "gn:dem":26,
    "gn:feature_class":"P",
    "gn:feature_code":"PPL",
    "gn:name":"Santa Luc\u00eda",
    "gn:population":0,
    "gn:timezone":"America/Bogota",
    "iso:country":"CO",
    "name:und_x_variant":[
        "Caser\u00edo Santa Lucia",
        "Santa Luc\u00eda"
    ],
    "wof:name":"Santa Lucia",
    "wof:placetype":"locality"
},
  "geometry": {"coordinates":[-74.85092,9.45866],"type":"Point"}
}