{
  "type": "Feature",
  "properties": {
    "gn:admin1_code":"33.0",
    "gn:admin2_code":"25279.0",
    "gn:asciiname":"Vereda De Guane",
    "gn:country_code":"CO",
    "gn:dem":2023,
    "gn:feature_class":"P",
    "gn:feature_code":"PPL",
    "gn:name":"Vereda De Guane",
    "gn:population":0,
    "gn:timezone":"America/Bogota",
    "iso:country":"CO",
    "name:spa_x_preferred":[
        "De Guane"
    ],
    "wof:name":"Vereda De Guane",
    "wof:placetype":"locality"
},
  "geometry": {"coordinates":[-73.85032,4.44361],"type":"Point"}
}