{
  "type": "Feature",
  "properties": {
    "gn:admin1_code":"16.0",
    "gn:admin2_code":"41551.0",
    "gn:asciiname":"El Higueron",
    "gn:country_code":"CO",
    "gn:dem":1423,
    "gn:feature_class":"P",
    "gn:feature_code":"PPL",
    "gn:name":"El Higuer\u00f3n",
    "gn:population":0,
    "gn:timezone":"America/Bogota",
    "iso:country":"CO",
    "name:spa_x_preferred":[
        "El Higuer\u00f3n"
    ],
    "wof:name":"El Higueron",
    "wof:placetype":"locality"
},
  "geometry": {"coordinates":[-76.00497,1.83937],"type":"Point"}
}