{
  "type": "Feature",
  "properties": {
    "iso:country":"CO",
    "name:ceb_x_preferred":[
        "Fuente de Oro"
    ],
    "name:eng_x_preferred":[
        "Fuente de Oro"
    ],
    "name:fra_x_preferred":[
        "Fuente de Oro"
    ],
    "name:ita_x_preferred":[
        "Fuente de Oro"
    ],
    "name:kat_x_preferred":[
        "\u10e4\u10e3\u10d4\u10dc\u10e2\u10d4-\u10d3\u10d4-\u10dd\u10e0\u10dd"
    ],
    "name:msa_x_preferred":[
        "Fuente de Oro"
    ],
    "name:nan_x_preferred":[
        "Fuente de Oro"
    ],
    "name:nld_x_preferred":[
        "Fuente de Oro"
    ],
    "name:por_x_preferred":[
        "Fuente de Oro"
    ],
    "name:spa_x_preferred":[
        "Fuente de Oro"
    ],
    "name:swe_x_preferred":[
        "Fuente de Oro"
    ],
    "name:tgl_x_preferred":[
        "Fuente de Oro"
    ],
    "name:und_x_variant":[
        "Municipio Fuente de Oro"
    ],
    "name:vie_x_preferred":[
        "Fuente de Oro"
    ],
    "name:war_x_preferred":[
        "Fuente de Oro"
    ],
    "name:zho_min_nan_x_preferred":[
        "Fuente de Oro"
    ],
    "name:zho_x_preferred":[
        "\u5bcc\u6069\u7279\u5fb7\u5967\u7f85"
    ],
    "qs:gn_country":"CO",
    "qs:gn_fcode":"PPL",
    "qs:gn_pop":3609,
    "qs:name":"Fuente de Oro",
    "qs:name_adm0":"Colombia",
    "qs:name_adm1":"Meta",
    "qs:photos":0,
    "qs:photos_1k":0,
    "qs:photos_9k":0,
    "qs:photos_9r":0,
    "qs:photos_all":0,
    "qs:photos_sr":0,
    "qs:placetype":"Town",
    "qs:pop_sr":"4",
    "qs:woe_adm0":23424787,
    "wd:wordcount":34,
    "wof:name":"Fuente de Oro",
    "wof:placetype":"locality",
    "wof:population":3609
},
  "geometry": {"coordinates":[-73.61278,3.45944],"type":"Point"}
}