{
  "type": "Feature",
  "properties": {
    "gn:admin1_code":"35",
    "gn:admin2_code":"13442.0",
    "gn:asciiname":"Majagua",
    "gn:country_code":"CO",
    "gn:dem":31,
    "gn:feature_class":"P",
    "gn:feature_code":"PPL",
    "gn:name":"Majagua",
    "gn:population":0,
    "gn:timezone":"America/Bogota",
    "iso:country":"CO",
    "name:ceb_x_preferred":[
        "Majagua"
    ],
    "name:fra_x_preferred":[
        "Majagua"
    ],
    "name:pol_x_preferred":[
        "Majagua"
    ],
    "name:spa_x_preferred":[
        "Majagua"
    ],
    "name:swe_x_preferred":[
        "Majagua"
    ],
    "wof:name":"Majagua",
    "wof:placetype":"locality"
},
  "geometry": {"coordinates":[-75.26224999999999,9.99504],"type":"Point"}
}