{
  "type": "Feature",
  "properties": {
    "gn:admin1_code":"32.0",
    "gn:admin2_code":"85400.0",
    "gn:asciiname":"San Cayetano",
    "gn:country_code":"CO",
    "gn:dem":1266,
    "gn:feature_class":"P",
    "gn:feature_code":"PPL",
    "gn:name":"San Cayetano",
    "gn:population":0,
    "gn:timezone":"America/Bogota",
    "iso:country":"CO",
    "name:ceb_x_preferred":[
        "San Cayetano"
    ],
    "name:deu_x_preferred":[
        "San Cayetano"
    ],
    "name:fra_x_preferred":[
        "San Cayetano"
    ],
    "name:ita_x_preferred":[
        "San Cayetano"
    ],
    "name:msa_x_preferred":[
        "San Cayetano"
    ],
    "name:nld_x_preferred":[
        "San Cayetano"
    ],
    "name:por_x_preferred":[
        "San Cayetano"
    ],
    "name:sco_x_preferred":[
        "San Cayetano"
    ],
    "name:spa_x_preferred":[
        "San Cayetano"
    ],
    "name:swe_x_preferred":[
        "San Cayetano"
    ],
    "name:war_x_preferred":[
        "San Cayetano"
    ],
    "wof:name":"San Cayetano",
    "wof:placetype":"locality"
},
  "geometry": {"coordinates":[-72.18262,5.92205],"type":"Point"}
}