{
  "type": "Feature",
  "properties": {
    "gn:admin1_code":"12",
    "gn:admin2_code":"23090.0",
    "gn:asciiname":"Juan Leon",
    "gn:country_code":"CO",
    "gn:dem":60,
    "gn:feature_class":"P",
    "gn:feature_code":"PPL",
    "gn:name":"Juan Leon",
    "gn:population":0,
    "gn:timezone":"America/Bogota",
    "iso:country":"CO",
    "wof:name":"Juan Leon",
    "wof:placetype":"locality"
},
  "geometry": {"coordinates":[-76.28388000000002,8.78063],"type":"Point"}
}