{
  "type": "Feature",
  "properties": {
    "gn:admin1_code":"33.0",
    "gn:admin2_code":"25181.0",
    "gn:asciiname":"Pena Blanca",
    "gn:country_code":"CO",
    "gn:dem":2474,
    "gn:feature_class":"P",
    "gn:feature_code":"PPL",
    "gn:name":"Pe\u00f1a Blanca",
    "gn:population":0,
    "gn:timezone":"America/Bogota",
    "iso:country":"CO",
    "wof:name":"Pena Blanca",
    "wof:placetype":"locality"
},
  "geometry": {"coordinates":[-73.86173000000002,4.63049],"type":"Point"}
}