{
  "type": "Feature",
  "properties": {
    "gn:admin1_code":"16.0",
    "gn:admin2_code":"41548.0",
    "gn:asciiname":"Versalles",
    "gn:country_code":"CO",
    "gn:dem":1942,
    "gn:feature_class":"P",
    "gn:feature_code":"PPL",
    "gn:name":"Versalles",
    "gn:population":0,
    "gn:timezone":"America/Bogota",
    "iso:country":"CO",
    "name:ceb_x_preferred":[
        "Versalles"
    ],
    "name:fra_x_preferred":[
        "Versalles"
    ],
    "name:ita_x_preferred":[
        "Versalles"
    ],
    "name:kat_x_preferred":[
        "\u10d5\u10d4\u10e0\u10e1\u10d0\u10da\u10d8\u10d4\u10e1\u10d8"
    ],
    "name:msa_x_preferred":[
        "Versalles"
    ],
    "name:nld_x_preferred":[
        "Versalles"
    ],
    "name:sco_x_preferred":[
        "Versalles"
    ],
    "name:spa_x_preferred":[
        "Versalles"
    ],
    "name:swe_x_preferred":[
        "Versalles"
    ],
    "name:vie_x_preferred":[
        "Versalles"
    ],
    "name:war_x_preferred":[
        "Versalles"
    ],
    "name:zho_x_preferred":[
        "\u8c9d\u723e\u85a9\u8036\u65af"
    ],
    "wof:name":"Versalles",
    "wof:placetype":"locality"
},
  "geometry": {"coordinates":[-75.87124,2.28501],"type":"Point"}
}