{
  "type": "Feature",
  "properties": {
    "gn:admin1_code":"28.0",
    "gn:admin2_code":"73024.0",
    "gn:asciiname":"El Pedregal",
    "gn:country_code":"CO",
    "gn:dem":1241,
    "gn:feature_class":"P",
    "gn:feature_code":"PPL",
    "gn:name":"El Pedregal",
    "gn:population":0,
    "gn:timezone":"America/Bogota",
    "iso:country":"CO",
    "name:spa_x_preferred":[
        "El Pedregal"
    ],
    "wof:name":"El Pedregal",
    "wof:placetype":"locality"
},
  "geometry": {"coordinates":[-74.98778,3.47972],"type":"Point"}
}