{
  "type": "Feature",
  "properties": {
    "gn:admin1_code":"32",
    "gn:admin2_code":"85410.0",
    "gn:asciiname":"Gibraltar",
    "gn:country_code":"CO",
    "gn:dem":426,
    "gn:feature_class":"P",
    "gn:feature_code":"PPL",
    "gn:name":"Gibraltar",
    "gn:population":0,
    "gn:timezone":"America/Bogota",
    "iso:country":"CO",
    "wof:name":"Gibraltar",
    "wof:placetype":"locality"
},
  "geometry": {"coordinates":[-72.77594999999999,4.93842],"type":"Point"}
}