{
  "type": "Feature",
  "properties": {
    "gn:admin1_code":"1.0",
    "gn:admin2_code":"91540.0",
    "gn:asciiname":"San Juan de Soco",
    "gn:country_code":"CO",
    "gn:dem":97,
    "gn:feature_class":"P",
    "gn:feature_code":"PPL",
    "gn:name":"San Juan de Soco",
    "gn:population":0,
    "gn:timezone":"America/Bogota",
    "iso:country":"CO",
    "wof:name":"San Juan de Soco",
    "wof:placetype":"locality"
},
  "geometry": {"coordinates":[-70.49278000000002,-3.73611],"type":"Point"}
}