{
  "type": "Feature",
  "properties": {
    "gn:admin1_code":"12.0",
    "gn:admin2_code":"23807.0",
    "gn:asciiname":"Macieriejo",
    "gn:country_code":"CO",
    "gn:dem":45,
    "gn:feature_class":"P",
    "gn:feature_code":"PPL",
    "gn:name":"Macieriejo",
    "gn:population":0,
    "gn:timezone":"America/Bogota",
    "iso:country":"CO",
    "wof:name":"Macieriejo",
    "wof:placetype":"locality"
},
  "geometry": {"coordinates":[-76.03775,8.23888],"type":"Point"}
}