{
  "type": "Feature",
  "properties": {
    "gn:admin1_code":"19.0",
    "gn:admin2_code":"50251.0",
    "gn:asciiname":"Buenavista",
    "gn:country_code":"CO",
    "gn:dem":944,
    "gn:feature_class":"P",
    "gn:feature_code":"PPL",
    "gn:name":"Buenavista",
    "gn:population":0,
    "gn:timezone":"America/Bogota",
    "iso:country":"CO",
    "name:ast_x_preferred":[
        "Buenavista"
    ],
    "name:cat_x_preferred":[
        "Buenavista"
    ],
    "name:ceb_x_preferred":[
        "Buenavista"
    ],
    "name:deu_x_preferred":[
        "Buenavista"
    ],
    "name:epo_x_preferred":[
        "Buenavista"
    ],
    "name:eus_x_preferred":[
        "Buenavista"
    ],
    "name:fra_x_preferred":[
        "Buenavista"
    ],
    "name:ilo_x_preferred":[
        "Buenavista"
    ],
    "name:ita_x_preferred":[
        "Buenavista"
    ],
    "name:nld_x_preferred":[
        "Buenavista"
    ],
    "name:por_x_preferred":[
        "Buenavista"
    ],
    "name:rus_x_preferred":[
        "\u0411\u0443\u044d\u043d\u0430\u0432\u0438\u0441\u0442\u0430"
    ],
    "name:spa_x_preferred":[
        "Buenavista"
    ],
    "name:srp_x_preferred":[
        "\u0411\u0443\u0435\u043d\u0430\u0432\u0438\u0441\u0442\u0430"
    ],
    "name:swe_x_preferred":[
        "Buenavista"
    ],
    "name:ukr_x_preferred":[
        "\u0411\u0443\u0435\u043d\u0430\u0432\u0456\u0441\u0442\u0430"
    ],
    "name:war_x_preferred":[
        "Buenavista"
    ],
    "wof:name":"Buenavista",
    "wof:placetype":"locality"
},
  "geometry": {"coordinates":[-73.94091999999998,3.61908],"type":"Point"}
}