{
  "type": "Feature",
  "properties": {
    "gn:admin1_code":"21",
    "gn:admin2_code":"54810.0",
    "gn:asciiname":"Ayacucho",
    "gn:country_code":"CO",
    "gn:dem":28,
    "gn:feature_class":"P",
    "gn:feature_code":"PPL",
    "gn:name":"Ayacucho",
    "gn:population":0,
    "gn:timezone":"America/Bogota",
    "iso:country":"CO",
    "name:ara_x_preferred":[
        "\u0623\u064a\u0627\u0643\u0648\u062a\u0634\u0648"
    ],
    "name:aym_x_preferred":[
        "Ayaquchu"
    ],
    "name:bel_x_preferred":[
        "\u0410\u044f\u043a\u0443\u0447\u0430"
    ],
    "name:bul_x_preferred":[
        "\u0410\u044f\u043a\u0443\u0447\u043e"
    ],
    "name:ceb_x_preferred":[
        "Ayacucho"
    ],
    "name:ces_x_preferred":[
        "Ayacucho"
    ],
    "name:deu_x_preferred":[
        "Huamanga"
    ],
    "name:epo_x_preferred":[
        "Ajaku\u0109o"
    ],
    "name:eus_x_preferred":[
        "Ayacucho"
    ],
    "name:fas_x_preferred":[
        "\u0622\u06cc\u0627\u06a9\u0648\u0686\u0648"
    ],
    "name:fin_x_preferred":[
        "Ayacucho"
    ],
    "name:fra_x_preferred":[
        "Ayacucho"
    ],
    "name:heb_x_preferred":[
        "\u05d0\u05d9\u05d9\u05e7\u05d5\u05e7\u05d5"
    ],
    "name:ind_x_preferred":[
        "Ayacucho"
    ],
    "name:ita_x_preferred":[
        "Ayacucho"
    ],
    "name:jpn_x_preferred":[
        "\u30a2\u30e4\u30af\u30fc\u30c1\u30e7"
    ],
    "name:kat_x_preferred":[
        "\u10d0\u10d8\u10d0\u10d9\u10e3\u10e9\u10dd"
    ],
    "name:kor_x_preferred":[
        "\uc544\uc57c\ucfe0\ucd08"
    ],
    "name:lit_x_preferred":[
        "Ajaku\u010das"
    ],
    "name:nau_x_preferred":[
        "Ayacucho"
    ],
    "name:nld_x_preferred":[
        "Ayacucho"
    ],
    "name:pol_x_preferred":[
        "Ayacucho"
    ],
    "name:por_x_preferred":[
        "Ayacucho"
    ],
    "name:que_x_preferred":[
        "Wamanqa"
    ],
    "name:ron_x_preferred":[
        "Ayacucho"
    ],
    "name:rus_x_preferred":[
        "\u0410\u044f\u043a\u0443\u0447\u043e"
    ],
    "name:spa_x_preferred":[
        "Ayacucho"
    ],
    "name:swe_x_preferred":[
        "Ayacucho"
    ],
    "name:tat_x_preferred":[
        "\u0410\u044f\u043a\u0443\u0447\u043e"
    ],
    "name:tur_x_preferred":[
        "Ayacucho"
    ],
    "name:ukr_x_preferred":[
        "\u0410\u044f\u043a\u0443\u0447\u043e"
    ],
    "name:urd_x_preferred":[
        "\u0627\u06cc\u0627\u06a9\u0648\u0686\u0648"
    ],
    "name:vie_x_preferred":[
        "Ayacucho"
    ],
    "name:vol_x_preferred":[
        "Ayacucho"
    ],
    "name:war_x_preferred":[
        "Ayacucho"
    ],
    "name:zho_x_preferred":[
        "\u963f\u4e9a\u5e93\u4e54"
    ],
    "wof:name":"Ayacucho",
    "wof:placetype":"locality"
},
  "geometry": {"coordinates":[-72.79300000000001,9.06899],"type":"Point"}
}