{
  "type": "Feature",
  "properties": {
    "gn:admin1_code":"21",
    "gn:admin2_code":"54810.0",
    "gn:asciiname":"Ayacucho",
    "gn:country_code":"CO",
    "gn:dem":28,
    "gn:feature_class":"P",
    "gn:feature_code":"PPL",
    "gn:name":"Ayacucho",
    "gn:population":0,
    "gn:timezone":"America/Bogota",
    "iso:country":"CO",
    "wof:name":"Ayacucho",
    "wof:placetype":"locality"
},
  "geometry": {"coordinates":[-72.79300000000001,9.06899],"type":"Point"}
}