{
  "type": "Feature",
  "properties": {
    "gn:country":"CO",
    "gn:fcode":"PPL",
    "gn:population":4133,
    "iso:country":"CO",
    "name:ast_x_preferred":[
        "Pore"
    ],
    "name:ceb_x_preferred":[
        "Pore"
    ],
    "name:eng_x_preferred":[
        "Pore"
    ],
    "name:fas_x_preferred":[
        "\u067e\u0648\u0631\u0647"
    ],
    "name:fra_x_preferred":[
        "Pore"
    ],
    "name:gle_x_preferred":[
        "Pore"
    ],
    "name:ita_x_preferred":[
        "Pore"
    ],
    "name:kat_x_preferred":[
        "\u10de\u10dd\u10e0\u10d4"
    ],
    "name:msa_x_preferred":[
        "Pore"
    ],
    "name:nan_x_preferred":[
        "Pore"
    ],
    "name:nld_x_preferred":[
        "Pore"
    ],
    "name:pol_x_preferred":[
        "Pore"
    ],
    "name:por_x_preferred":[
        "Pore"
    ],
    "name:spa_x_preferred":[
        "Municipio Pore"
    ],
    "name:spa_x_variant":[
        "Pore"
    ],
    "name:swe_x_preferred":[
        "Pore"
    ],
    "name:swe_x_variant":[
        "Corinto"
    ],
    "name:tgl_x_preferred":[
        "Pore"
    ],
    "name:vie_x_preferred":[
        "Pore"
    ],
    "name:war_x_preferred":[
        "Pore"
    ],
    "name:zho_x_preferred":[
        "\u6ce2\u96f7"
    ],
    "qs_pg:aaroncc":"CO",
    "qs_pg:gn_country":"CO",
    "qs_pg:gn_fcode":"PPL",
    "qs_pg:gn_pop":4133,
    "qs_pg:name":"Pore",
    "qs_pg:photos_9r":0,
    "qs_pg:photos_sr":0,
    "qs_pg:pop_sr":4,
    "qs_pg:qs_pg_placetype":"locality",
    "wof:name":"Pore",
    "wof:placetype":"locality",
    "wof:population":4133
},
  "geometry": {"coordinates":[-71.99472,5.72722],"type":"Point"}
}