{
  "type": "Feature",
  "properties": {
    "gn:admin1_code":"36",
    "gn:admin2_code":"15664.0",
    "gn:asciiname":"Munones",
    "gn:country_code":"CO",
    "gn:dem":1689,
    "gn:feature_class":"P",
    "gn:feature_code":"PPL",
    "gn:name":"Mu\u00f1ones",
    "gn:population":0,
    "gn:timezone":"America/Bogota",
    "iso:country":"CO",
    "wof:name":"Munones",
    "wof:placetype":"locality"
},
  "geometry": {"coordinates":[-73.56693,5.96501],"type":"Point"}
}