{
  "type": "Feature",
  "properties": {
    "gn:admin1_code":"22.0",
    "gn:admin2_code":"86571.0",
    "gn:asciiname":"Lucitana",
    "gn:country_code":"CO",
    "gn:dem":228,
    "gn:feature_class":"P",
    "gn:feature_code":"PPL",
    "gn:name":"Lucitana",
    "gn:population":0,
    "gn:timezone":"America/Bogota",
    "iso:country":"CO",
    "wof:name":"Lucitana",
    "wof:placetype":"locality"
},
  "geometry": {"coordinates":[-75.59358,0.80898],"type":"Point"}
}