{
  "type": "Feature",
  "properties": {
    "gn:admin1_code":"15",
    "gn:admin2_code":"94886.0",
    "gn:asciiname":"Corona",
    "gn:country_code":"CO",
    "gn:dem":86,
    "gn:feature_class":"P",
    "gn:feature_code":"PPL",
    "gn:name":"Corona",
    "gn:population":0,
    "gn:timezone":"America/Bogota",
    "iso:country":"CO",
    "wof:name":"Corona",
    "wof:placetype":"locality"
},
  "geometry": {"coordinates":[-67.33333,3.35],"type":"Point"}
}