{
  "type": "Feature",
  "properties": {
    "gn:admin1_code":"38",
    "gn:admin2_code":"47660.0",
    "gn:asciiname":"La Esmeralda",
    "gn:country_code":"CO",
    "gn:dem":177,
    "gn:feature_class":"P",
    "gn:feature_code":"PPL",
    "gn:name":"La Esmeralda",
    "gn:population":0,
    "gn:timezone":"America/Bogota",
    "iso:country":"CO",
    "name:und_x_variant":[
        "Hacienda Esmeralda",
        "La Esmeralda"
    ],
    "wof:name":"La Esmeralda",
    "wof:placetype":"locality"
},
  "geometry": {"coordinates":[-74.29393,10.20913],"type":"Point"}
}