{
  "type": "Feature",
  "properties": {
    "gn:admin1_code":"2.0",
    "gn:admin2_code":"5665.0",
    "gn:asciiname":"El Playon",
    "gn:country_code":"CO",
    "gn:dem":67,
    "gn:feature_class":"P",
    "gn:feature_code":"PPL",
    "gn:name":"El Play\u00f3n",
    "gn:population":0,
    "gn:timezone":"America/Bogota",
    "iso:country":"CO",
    "wof:name":"El Playon",
    "wof:placetype":"locality"
},
  "geometry": {"coordinates":[-76.28496,8.47358],"type":"Point"}
}