{
  "type": "Feature",
  "properties": {
    "gn:admin1_code":"29.0",
    "gn:admin2_code":"76834.0",
    "gn:asciiname":"Vereda Ginebra",
    "gn:country_code":"CO",
    "gn:dem":942,
    "gn:feature_class":"P",
    "gn:feature_code":"PPL",
    "gn:name":"Vereda Ginebra",
    "gn:population":0,
    "gn:timezone":"America/Bogota",
    "iso:country":"CO",
    "wof:name":"Vereda Ginebra",
    "wof:placetype":"locality"
},
  "geometry": {"coordinates":[-76.23170999999998,4.1106],"type":"Point"}
}