{
  "type": "Feature",
  "properties": {
    "gn:admin1_code":"17.0",
    "gn:admin2_code":"44090.0",
    "gn:asciiname":"Puente Bomba",
    "gn:country_code":"CO",
    "gn:dem":13,
    "gn:feature_class":"P",
    "gn:feature_code":"PPL",
    "gn:name":"Puente Bomba",
    "gn:population":0,
    "gn:timezone":"America/Bogota",
    "iso:country":"CO",
    "name:und_x_variant":[
        "Hacienda Puente Bomba",
        "La Bomba",
        "Puente Bomba"
    ],
    "wof:name":"Puente Bomba",
    "wof:placetype":"locality"
},
  "geometry": {"coordinates":[-73.17246,11.26275],"type":"Point"}
}