{
  "type": "Feature",
  "properties": {
    "gn:admin1_code":"8.0",
    "gn:admin2_code":"18756.0",
    "gn:asciiname":"Salado Hachuela",
    "gn:country_code":"CO",
    "gn:dem":150,
    "gn:feature_class":"P",
    "gn:feature_code":"PPL",
    "gn:name":"Salado Hachuela",
    "gn:population":0,
    "gn:timezone":"America/Bogota",
    "iso:country":"CO",
    "wof:name":"Salado Hachuela",
    "wof:placetype":"locality"
},
  "geometry": {"coordinates":[-72.24229,0.13758],"type":"Point"}
}