{
  "type": "Feature",
  "properties": {
    "gn:admin1_code":"16.0",
    "gn:admin2_code":"41306.0",
    "gn:asciiname":"Cascadalito",
    "gn:country_code":"CO",
    "gn:dem":819,
    "gn:feature_class":"P",
    "gn:feature_code":"PPL",
    "gn:name":"Cascadalito",
    "gn:population":0,
    "gn:timezone":"America/Bogota",
    "iso:country":"CO",
    "wof:name":"Cascadalito",
    "wof:placetype":"locality"
},
  "geometry": {"coordinates":[-75.5895,2.30743],"type":"Point"}
}