{
  "type": "Feature",
  "properties": {
    "gn:admin1_code":"19",
    "gn:admin2_code":"50590.0",
    "gn:asciiname":"Charco Carbon",
    "gn:country_code":"CO",
    "gn:dem":182,
    "gn:feature_class":"P",
    "gn:feature_code":"PPL",
    "gn:name":"Charco Carb\u00f3n",
    "gn:population":0,
    "gn:timezone":"America/Bogota",
    "iso:country":"CO",
    "name:und_x_variant":[
        "Charco Carb\u00f3n",
        "Charco Cart\u00f3n"
    ],
    "wof:name":"Charco Carbon",
    "wof:placetype":"locality"
},
  "geometry": {"coordinates":[-72.95201,2.52107],"type":"Point"}
}