{
  "type": "Feature",
  "properties": {
    "gn:admin1_code":"2",
    "gn:admin2_code":"5361.0",
    "gn:asciiname":"El Candelillo",
    "gn:country_code":"CO",
    "gn:dem":932,
    "gn:feature_class":"P",
    "gn:feature_code":"PPL",
    "gn:name":"El Candelillo",
    "gn:population":0,
    "gn:timezone":"America/Bogota",
    "iso:country":"CO",
    "wof:name":"El Candelillo",
    "wof:placetype":"locality"
},
  "geometry": {"coordinates":[-75.92278,7.3575],"type":"Point"}
}