{
  "type": "Feature",
  "properties": {
    "gn:admin1_code":"17.0",
    "gn:admin2_code":"44847.0",
    "gn:asciiname":"Shoi",
    "gn:country_code":"CO",
    "gn:dem":5,
    "gn:feature_class":"P",
    "gn:feature_code":"PPL",
    "gn:name":"Shoi",
    "gn:population":0,
    "gn:timezone":"America/Bogota",
    "iso:country":"CO",
    "name:und_x_variant":[
        "Shohi",
        "Shoi"
    ],
    "wof:name":"Shoi",
    "wof:placetype":"locality"
},
  "geometry": {"coordinates":[-71.86389,12.34167],"type":"Point"}
}