{
  "type": "Feature",
  "properties": {
    "gn:admin1_code":"3",
    "gn:admin2_code":"81736.0",
    "gn:asciiname":"Indios Tunebos",
    "gn:country_code":"CO",
    "gn:dem":409,
    "gn:feature_class":"P",
    "gn:feature_code":"PPL",
    "gn:name":"Indios Tunebos",
    "gn:population":0,
    "gn:timezone":"America/Bogota",
    "iso:country":"CO",
    "name:spa_x_preferred":[
        "Indios Tunebos"
    ],
    "wof:name":"Indios Tunebos",
    "wof:placetype":"locality"
},
  "geometry": {"coordinates":[-71.96970999999998,6.88044],"type":"Point"}
}