{
  "type": "Feature",
  "properties": {
    "gn:admin1_code":"17",
    "gn:admin2_code":"44847.0",
    "gn:asciiname":"Rancheria Anteshiruhu",
    "gn:country_code":"CO",
    "gn:dem":36,
    "gn:feature_class":"P",
    "gn:feature_code":"PPL",
    "gn:name":"Rancher\u00eda Ant\u00e9shiruhu",
    "gn:population":0,
    "gn:timezone":"America/Bogota",
    "iso:country":"CO",
    "name:und_x_variant":[
        "Antechiro",
        "Ant\u00e9shiruhu",
        "Rancher\u00eda Ant\u00e9shiruhu"
    ],
    "wof:name":"Rancheria Anteshiruhu",
    "wof:placetype":"locality"
},
  "geometry": {"coordinates":[-71.37855999999999,12.0823],"type":"Point"}
}