{
  "type": "Feature",
  "properties": {
    "gn:admin1_code":"2.0",
    "gn:admin2_code":"5138.0",
    "gn:asciiname":"La Quiebra",
    "gn:country_code":"CO",
    "gn:dem":1573,
    "gn:feature_class":"P",
    "gn:feature_code":"PPL",
    "gn:name":"La Quiebra",
    "gn:population":0,
    "gn:timezone":"America/Bogota",
    "iso:country":"CO",
    "wof:name":"La Quiebra",
    "wof:placetype":"locality"
},
  "geometry": {"coordinates":[-76.09305999999999,6.86778],"type":"Point"}
}