{
  "type": "Feature",
  "properties": {
    "gn:admin1_code":"26",
    "gn:admin2_code":"68101.0",
    "gn:asciiname":"Claro",
    "gn:country_code":"CO",
    "gn:dem":1741,
    "gn:feature_class":"P",
    "gn:feature_code":"PPL",
    "gn:name":"Claro",
    "gn:population":0,
    "gn:timezone":"America/Bogota",
    "iso:country":"CO",
    "name:als_x_preferred":[
        "Claro"
    ],
    "name:ceb_x_preferred":[
        "Claro"
    ],
    "name:deu_x_preferred":[
        "Claro"
    ],
    "name:eus_x_preferred":[
        "Claro"
    ],
    "name:fra_x_preferred":[
        "Claro"
    ],
    "name:ita_x_preferred":[
        "Claro"
    ],
    "name:lit_x_preferred":[
        "Klaras"
    ],
    "name:por_x_preferred":[
        "Claro"
    ],
    "name:spa_x_preferred":[
        "Claro"
    ],
    "name:swe_x_preferred":[
        "Claro"
    ],
    "wof:name":"Claro",
    "wof:placetype":"locality"
},
  "geometry": {"coordinates":[-73.76666999999998,6.13333],"type":"Point"}
}