{
  "type": "Feature",
  "properties": {
    "gn:admin1_code":"3",
    "gn:admin2_code":"81001.0",
    "gn:asciiname":"Campoalegre",
    "gn:country_code":"CO",
    "gn:dem":124,
    "gn:feature_class":"P",
    "gn:feature_code":"PPL",
    "gn:name":"Campoalegre",
    "gn:population":0,
    "gn:timezone":"America/Bogota",
    "iso:country":"CO",
    "name:ceb_x_preferred":[
        "Campoalegre"
    ],
    "name:deu_x_preferred":[
        "Campoalegre"
    ],
    "name:fas_x_preferred":[
        "\u06a9\u0627\u0645\u067e\u0648\u0622\u0644\u06af\u0631\u0647"
    ],
    "name:fra_x_preferred":[
        "Campoalegre"
    ],
    "name:gla_x_preferred":[
        "Campoalegre"
    ],
    "name:ita_x_preferred":[
        "Campoalegre"
    ],
    "name:kat_x_preferred":[
        "\u10d9\u10d0\u10db\u10de\u10dd\u10d0\u10da\u10d4\u10d2\u10e0\u10d4"
    ],
    "name:msa_x_preferred":[
        "Campoalegre"
    ],
    "name:nld_x_preferred":[
        "Campoalegre"
    ],
    "name:por_x_preferred":[
        "Campoalegre"
    ],
    "name:sco_x_preferred":[
        "Campoalegre"
    ],
    "name:spa_x_preferred":[
        "Campoalegre"
    ],
    "name:swe_x_preferred":[
        "Campoalegre"
    ],
    "name:tgl_x_preferred":[
        "Campoalegre"
    ],
    "name:vie_x_preferred":[
        "Campoalegre"
    ],
    "name:war_x_preferred":[
        "Campoalegre"
    ],
    "name:zho_x_preferred":[
        "\u574e\u6ce2\u963f\u840a\u683c\u96f7"
    ],
    "wof:name":"Campoalegre",
    "wof:placetype":"locality"
},
  "geometry": {"coordinates":[-70.53296999999998,6.93985],"type":"Point"}
}