{
  "type": "Feature",
  "properties": {
    "gn:admin1_code":"3",
    "gn:admin2_code":"81001.0",
    "gn:asciiname":"Campoalegre",
    "gn:country_code":"CO",
    "gn:dem":124,
    "gn:feature_class":"P",
    "gn:feature_code":"PPL",
    "gn:name":"Campoalegre",
    "gn:population":0,
    "gn:timezone":"America/Bogota",
    "iso:country":"CO",
    "wof:name":"Campoalegre",
    "wof:placetype":"locality"
},
  "geometry": {"coordinates":[-70.53296999999998,6.93985],"type":"Point"}
}