{
  "type": "Feature",
  "properties": {
    "gn:admin1_code":"12.0",
    "gn:admin2_code":"23001.0",
    "gn:asciiname":"Filadelfia",
    "gn:country_code":"CO",
    "gn:dem":67,
    "gn:feature_class":"P",
    "gn:feature_code":"PPL",
    "gn:name":"Filadelfia",
    "gn:population":0,
    "gn:timezone":"America/Bogota",
    "iso:country":"CO",
    "wof:name":"Filadelfia",
    "wof:placetype":"locality"
},
  "geometry": {"coordinates":[-76.0937,8.47767],"type":"Point"}
}