{
  "type": "Feature",
  "properties": {
    "gn:admin1_code":"38.0",
    "gn:admin2_code":"47660.0",
    "gn:asciiname":"Pajalito",
    "gn:country_code":"CO",
    "gn:dem":99,
    "gn:feature_class":"P",
    "gn:feature_code":"PPL",
    "gn:name":"Pajalito",
    "gn:population":0,
    "gn:timezone":"America/Bogota",
    "iso:country":"CO",
    "wof:name":"Pajalito",
    "wof:placetype":"locality"
},
  "geometry": {"coordinates":[-74.14188,9.96952],"type":"Point"}
}