{
  "type": "Feature",
  "properties": {
    "gn:admin1_code":"4.0",
    "gn:asciiname":"Pacheco",
    "gn:country_code":"CO",
    "gn:dem":279,
    "gn:feature_class":"P",
    "gn:feature_code":"PPL",
    "gn:name":"Pacheco",
    "gn:population":0,
    "gn:timezone":"America/Bogota",
    "iso:country":"CO",
    "name:kor_x_preferred":[
        "\ud30c\uccb4\ucf54"
    ],
    "wof:name":"Pacheco",
    "wof:placetype":"locality"
},
  "geometry": {"coordinates":[-75.23194000000002,10.47778],"type":"Point"}
}