{
  "type": "Feature",
  "properties": {
    "gn:admin1_code":"33.0",
    "gn:admin2_code":"25885.0",
    "gn:asciiname":"Teran",
    "gn:country_code":"CO",
    "gn:dem":212,
    "gn:feature_class":"P",
    "gn:feature_code":"PPL",
    "gn:name":"Ter\u00e1n",
    "gn:population":0,
    "gn:timezone":"America/Bogota",
    "iso:country":"CO",
    "name:deu_x_preferred":[
        "Teran"
    ],
    "name:lfn_x_preferred":[
        "Teran"
    ],
    "name:srp_x_preferred":[
        "\u0422\u0435\u0440\u0430\u043d"
    ],
    "wof:name":"Teran",
    "wof:placetype":"locality"
},
  "geometry": {"coordinates":[-74.4478,5.70894],"type":"Point"}
}