{
  "type": "Feature",
  "properties": {
    "gn:admin1_code":"35.0",
    "gn:admin2_code":"13006.0",
    "gn:asciiname":"Puerto Isabel",
    "gn:country_code":"CO",
    "gn:dem":22,
    "gn:feature_class":"P",
    "gn:feature_code":"PPL",
    "gn:name":"Puerto Isabel",
    "gn:population":0,
    "gn:timezone":"America/Bogota",
    "iso:country":"CO",
    "wof:name":"Puerto Isabel",
    "wof:placetype":"locality"
},
  "geometry": {"coordinates":[-74.51822,8.62916],"type":"Point"}
}