{
  "type": "Feature",
  "properties": {
    "gn:admin1_code":"8",
    "gn:admin2_code":"18001.0",
    "gn:asciiname":"Tres Esquinas",
    "gn:country_code":"CO",
    "gn:dem":341,
    "gn:feature_class":"P",
    "gn:feature_code":"PPL",
    "gn:name":"Tres Esquinas",
    "gn:population":0,
    "gn:timezone":"America/Bogota",
    "iso:country":"CO",
    "name:spa_x_preferred":[
        "Tres Esquinas"
    ],
    "wof:name":"Tres Esquinas",
    "wof:placetype":"locality"
},
  "geometry": {"coordinates":[-75.69835999999999,1.54307],"type":"Point"}
}