{
  "type": "Feature",
  "properties": {
    "gn:admin1_code":"35.0",
    "gn:admin2_code":"13433.0",
    "gn:asciiname":"Dacali",
    "gn:country_code":"CO",
    "gn:dem":19,
    "gn:feature_class":"P",
    "gn:feature_code":"PPL",
    "gn:name":"Dacali",
    "gn:population":0,
    "gn:timezone":"America/Bogota",
    "iso:country":"CO",
    "wof:name":"Dacali",
    "wof:placetype":"locality"
},
  "geometry": {"coordinates":[-75.23528,10.12139],"type":"Point"}
}