{
  "type": "Feature",
  "properties": {
    "gn:admin1_code":"35.0",
    "gn:admin2_code":"13549.0",
    "gn:asciiname":"Santacoa",
    "gn:country_code":"CO",
    "gn:dem":20,
    "gn:feature_class":"P",
    "gn:feature_code":"PPL",
    "gn:name":"Santacoa",
    "gn:population":0,
    "gn:timezone":"America/Bogota",
    "iso:country":"CO",
    "name:und_x_variant":[
        "Corregimiento Santacoa",
        "Santacoa"
    ],
    "wof:name":"Santacoa",
    "wof:placetype":"locality"
},
  "geometry": {"coordinates":[-74.52,8.9588],"type":"Point"}
}