{
  "type": "Feature",
  "properties": {
    "iso:country":"CO",
    "name:ast_x_preferred":[
        "La Monta\u00f1ita"
    ],
    "name:cat_x_preferred":[
        "La Monta\u00f1ita"
    ],
    "name:ceb_x_preferred":[
        "La Monta\u00f1ita"
    ],
    "name:deu_x_preferred":[
        "La Monta\u00f1ita"
    ],
    "name:eng_x_preferred":[
        "La Monta\u00f1ita"
    ],
    "name:fas_x_preferred":[
        "\u0644\u0627 \u0645\u0648\u0646\u062a\u0627\u0646\u06cc\u062a\u0627"
    ],
    "name:fra_x_preferred":[
        "La Monta\u00f1ita"
    ],
    "name:ita_x_preferred":[
        "La Monta\u00f1ita"
    ],
    "name:jpn_x_preferred":[
        "\u30e9\u30fb\u30e2\u30f3\u30bf\u30fc\u30cb\u30bf"
    ],
    "name:kat_x_preferred":[
        "\u10da\u10d0-\u10db\u10dd\u10dc\u10e2\u10d0\u10dc\u10d8\u10e2\u10d0"
    ],
    "name:msa_x_preferred":[
        "La Monta\u00f1ita"
    ],
    "name:nan_x_preferred":[
        "La Monta\u00f1ita"
    ],
    "name:nld_x_preferred":[
        "La Monta\u00f1ita"
    ],
    "name:por_x_preferred":[
        "La Monta\u00f1ita"
    ],
    "name:spa_x_preferred":[
        "La Monta\u00f1ita"
    ],
    "name:swe_x_preferred":[
        "La Monta\u00f1ita"
    ],
    "name:tgl_x_preferred":[
        "La Monta\u00f1ita"
    ],
    "name:unk_x_variant":[
        "Monta\u00f1ita"
    ],
    "name:urd_x_preferred":[
        "\u0644\u0627 \u0645\u0648\u0646\u0679\u0627\u0646\u06cc\u0679\u0627"
    ],
    "name:vie_x_preferred":[
        "La Monta\u00f1ita"
    ],
    "name:war_x_preferred":[
        "La Monta\u00f1ita"
    ],
    "name:zho_x_preferred":[
        "\u62c9\u8499\u5854\u5c3c\u5854"
    ],
    "qs:gn_country":"CO",
    "qs:gn_fcode":"PPL",
    "qs:gn_pop":3305,
    "qs:name":"La Monta\u00f1ita",
    "qs:name_adm0":"Colombia",
    "qs:name_adm1":"Caqueta",
    "qs:photos":0,
    "qs:photos_1k":0,
    "qs:photos_9k":1,
    "qs:photos_9r":1,
    "qs:photos_all":1,
    "qs:photos_sr":0,
    "qs:placetype":"Town",
    "qs:pop_sr":"4",
    "qs:woe_adm0":23424787,
    "wd:wordcount":28,
    "wof:name":"La Monta\u00f1ita",
    "wof:placetype":"locality",
    "wof:population":3305
},
  "geometry": {"coordinates":[-75.43980000000001,1.4766],"type":"Point"}
}