{
  "type": "Feature",
  "properties": {
    "gn:admin1_code":"21",
    "gn:admin2_code":"54206.0",
    "gn:asciiname":"Elias Perez Ramirez",
    "gn:country_code":"CO",
    "gn:dem":1009,
    "gn:feature_class":"P",
    "gn:feature_code":"PPL",
    "gn:name":"El\u00edas P\u00e9rez Ram\u00edrez",
    "gn:population":0,
    "gn:timezone":"America/Bogota",
    "iso:country":"CO",
    "wof:name":"Elias Perez Ramirez",
    "wof:placetype":"locality"
},
  "geometry": {"coordinates":[-73.33734,8.45372],"type":"Point"}
}