{
  "type": "Feature",
  "properties": {
    "gn:admin1_code":"8.0",
    "gn:admin2_code":"18860.0",
    "gn:asciiname":"Belgica",
    "gn:country_code":"CO",
    "gn:dem":233,
    "gn:feature_class":"P",
    "gn:feature_code":"PPL",
    "gn:name":"B\u00e9lgica",
    "gn:population":0,
    "gn:timezone":"America/Bogota",
    "iso:country":"CO",
    "name:spa_x_preferred":[
        "B\u00e9lgica"
    ],
    "wof:name":"Belgica",
    "wof:placetype":"locality"
},
  "geometry": {"coordinates":[-75.68599,1.11397],"type":"Point"}
}