{
  "type": "Feature",
  "properties": {
    "gn:admin1_code":"38",
    "gn:admin2_code":"47288.0",
    "gn:asciiname":"Hacienda Caraballo",
    "gn:country_code":"CO",
    "gn:dem":142,
    "gn:feature_class":"P",
    "gn:feature_code":"PPL",
    "gn:name":"Hacienda Caraballo",
    "gn:population":0,
    "gn:timezone":"America/Bogota",
    "iso:country":"CO",
    "wof:name":"Hacienda Caraballo",
    "wof:placetype":"locality"
},
  "geometry": {"coordinates":[-74.06667,10.38333],"type":"Point"}
}