{
  "type": "Feature",
  "properties": {
    "gn:admin1_code":"26",
    "gn:admin2_code":"68406.0",
    "gn:asciiname":"Nuevo Mundo",
    "gn:country_code":"CO",
    "gn:dem":804,
    "gn:feature_class":"P",
    "gn:feature_code":"PPL",
    "gn:name":"Nuevo Mundo",
    "gn:population":0,
    "gn:timezone":"America/Bogota",
    "iso:country":"CO",
    "name:ceb_x_preferred":[
        "Nuevo Mundo"
    ],
    "name:deu_x_preferred":[
        "Nuevo Mundo"
    ],
    "name:fra_x_preferred":[
        "Nuevo Mundo"
    ],
    "name:por_x_preferred":[
        "Novo Mundo"
    ],
    "name:spa_x_preferred":[
        "Nuevo Mundo"
    ],
    "name:swe_x_preferred":[
        "Nuevo Mundo"
    ],
    "wof:name":"Nuevo Mundo",
    "wof:placetype":"locality"
},
  "geometry": {"coordinates":[-73.30944000000002,7.30361],"type":"Point"}
}