{
  "type": "Feature",
  "properties": {
    "gn:admin1_code":"38.0",
    "gn:admin2_code":"47001.0",
    "gn:asciiname":"Palmichal",
    "gn:country_code":"CO",
    "gn:dem":3744,
    "gn:feature_class":"P",
    "gn:feature_code":"PPL",
    "gn:name":"Palmichal",
    "gn:population":0,
    "gn:timezone":"America/Bogota",
    "iso:country":"CO",
    "wof:name":"Palmichal",
    "wof:placetype":"locality"
},
  "geometry": {"coordinates":[-73.86667,10.93333],"type":"Point"}
}