{
  "type": "Feature",
  "properties": {
    "gn:admin1_code":"2.0",
    "gn:admin2_code":"5837.0",
    "gn:asciiname":"Playa La Martina",
    "gn:country_code":"CO",
    "gn:dem":5,
    "gn:feature_class":"P",
    "gn:feature_code":"PPL",
    "gn:name":"Playa La Martina",
    "gn:population":0,
    "gn:timezone":"America/Bogota",
    "iso:country":"CO",
    "wof:name":"Playa La Martina",
    "wof:placetype":"locality"
},
  "geometry": {"coordinates":[-76.73699000000001,8.16641],"type":"Point"}
}