{
  "type": "Feature",
  "properties": {
    "gn:admin1_code":"38",
    "gn:admin2_code":"47460.0",
    "gn:asciiname":"El Canal",
    "gn:country_code":"CO",
    "gn:dem":102,
    "gn:feature_class":"P",
    "gn:feature_code":"PPL",
    "gn:name":"El Canal",
    "gn:population":0,
    "gn:timezone":"America/Bogota",
    "iso:country":"CO",
    "name:und_x_variant":[
        "Hacienda El Canal",
        "El Canal"
    ],
    "wof:name":"El Canal",
    "wof:placetype":"locality"
},
  "geometry": {"coordinates":[-74.17999,9.67224],"type":"Point"}
}