{
  "type": "Feature",
  "properties": {
    "gn:admin1_code":"36",
    "gn:admin2_code":"15109.0",
    "gn:asciiname":"El Cerezo",
    "gn:country_code":"CO",
    "gn:dem":1888,
    "gn:feature_class":"P",
    "gn:feature_code":"PPL",
    "gn:name":"El Cerezo",
    "gn:population":0,
    "gn:timezone":"America/Bogota",
    "iso:country":"CO",
    "wof:name":"El Cerezo",
    "wof:placetype":"locality"
},
  "geometry": {"coordinates":[-73.96916999999998,5.50833],"type":"Point"}
}