{
  "type": "Feature",
  "properties": {
    "iso:country":"CO",
    "name:ceb_x_preferred":[
        "Ragonvalia"
    ],
    "name:eng_x_preferred":[
        "Ragonvalia"
    ],
    "name:fra_x_preferred":[
        "Ragonvalia"
    ],
    "name:ita_x_preferred":[
        "Ragonvalia"
    ],
    "name:kat_x_preferred":[
        "\u10e0\u10d0\u10d2\u10dd\u10dc\u10d5\u10d0\u10da\u10d8\u10d0"
    ],
    "name:msa_x_preferred":[
        "Ragonvalia"
    ],
    "name:nan_x_preferred":[
        "Ragonvalia"
    ],
    "name:nld_x_preferred":[
        "Ragonvalia"
    ],
    "name:por_x_preferred":[
        "Ragonvalia"
    ],
    "name:spa_x_preferred":[
        "Ragonvalia"
    ],
    "name:swe_x_preferred":[
        "Ragonvalia"
    ],
    "name:tgl_x_preferred":[
        "Ragonvalia"
    ],
    "name:unk_x_variant":[
        "Rangovalia"
    ],
    "name:vie_x_preferred":[
        "Ragonvalia"
    ],
    "name:war_x_preferred":[
        "Ragonvalia"
    ],
    "name:zho_min_nan_x_preferred":[
        "Ragonvalia"
    ],
    "name:zho_x_preferred":[
        "\u62c9\u8ca2\u74e6\u5229\u4e9e"
    ],
    "qs:gn_country":"CO",
    "qs:gn_fcode":"PPL",
    "qs:gn_pop":3543,
    "qs:name":"Ragonvalia",
    "qs:name_adm0":"Colombia",
    "qs:name_adm1":"Norte de Santander",
    "qs:photos":0,
    "qs:photos_1k":0,
    "qs:photos_9k":1,
    "qs:photos_9r":1,
    "qs:photos_all":1,
    "qs:photos_sr":0,
    "qs:placetype":"Town",
    "qs:pop_sr":"4",
    "qs:woe_adm0":23424787,
    "wd:wordcount":45,
    "wof:name":"Ragonvalia",
    "wof:placetype":"locality",
    "wof:population":3543
},
  "geometry": {"coordinates":[-72.47574,7.57749],"type":"Point"}
}