{
  "type": "Feature",
  "properties": {
    "gn:admin1_code":"26",
    "gn:admin2_code":"68101.0",
    "gn:asciiname":"El Trapa",
    "gn:country_code":"CO",
    "gn:dem":2671,
    "gn:feature_class":"P",
    "gn:feature_code":"PPL",
    "gn:name":"El Trapa",
    "gn:population":0,
    "gn:timezone":"America/Bogota",
    "iso:country":"CO",
    "wof:name":"El Trapa",
    "wof:placetype":"locality"
},
  "geometry": {"coordinates":[-73.84028000000001,5.99194],"type":"Point"}
}