{
  "type": "Feature",
  "properties": {
    "gn:admin1_code":"33",
    "gn:admin2_code":"25295.0",
    "gn:asciiname":"Berlin",
    "gn:country_code":"CO",
    "gn:dem":2560,
    "gn:feature_class":"P",
    "gn:feature_code":"PPL",
    "gn:name":"Berl\u00edn",
    "gn:population":0,
    "gn:timezone":"America/Bogota",
    "iso:country":"CO",
    "wof:name":"Berlin",
    "wof:placetype":"locality"
},
  "geometry": {"coordinates":[-73.86667,5.03333],"type":"Point"}
}