{
  "type": "Feature",
  "properties": {
    "gn:admin1_code":"33.0",
    "gn:admin2_code":"25322.0",
    "gn:asciiname":"Palacio",
    "gn:country_code":"CO",
    "gn:dem":3642,
    "gn:feature_class":"P",
    "gn:feature_code":"PPL",
    "gn:name":"Palacio",
    "gn:population":0,
    "gn:timezone":"America/Bogota",
    "iso:country":"CO",
    "name:und_x_variant":[
        "Palacios"
    ],
    "wof:name":"Palacio",
    "wof:placetype":"locality"
},
  "geometry": {"coordinates":[-73.82170000000001,4.71493],"type":"Point"}
}