{
  "type": "Feature",
  "properties": {
    "gn:admin1_code":"2",
    "gn:admin2_code":"5034.0",
    "gn:asciiname":"La Carmelita",
    "gn:country_code":"CO",
    "gn:dem":1735,
    "gn:feature_class":"P",
    "gn:feature_code":"PPL",
    "gn:name":"La Carmelita",
    "gn:population":0,
    "gn:timezone":"America/Bogota",
    "iso:country":"CO",
    "wof:name":"La Carmelita",
    "wof:placetype":"locality"
},
  "geometry": {"coordinates":[-75.84571,5.6948],"type":"Point"}
}