{
  "type": "Feature",
  "properties": {
    "gn:admin1_code":"2.0",
    "gn:admin2_code":"5088.0",
    "gn:asciiname":"Lilandia",
    "gn:country_code":"CO",
    "gn:dem":2477,
    "gn:feature_class":"P",
    "gn:feature_code":"PPL",
    "gn:name":"Lilandia",
    "gn:population":0,
    "gn:timezone":"America/Bogota",
    "iso:country":"CO",
    "name:spa_x_preferred":[
        "Lilandia"
    ],
    "wof:name":"Lilandia",
    "wof:placetype":"locality"
},
  "geometry": {"coordinates":[-75.60526999999998,6.35281],"type":"Point"}
}