{
  "type": "Feature",
  "properties": {
    "gn:admin1_code":"30",
    "gn:admin2_code":"97666.0",
    "gn:asciiname":"Casa Indigena",
    "gn:country_code":"CO",
    "gn:dem":117,
    "gn:feature_class":"P",
    "gn:feature_code":"PPL",
    "gn:name":"Casa Ind\u00edgena",
    "gn:population":0,
    "gn:timezone":"America/Bogota",
    "iso:country":"CO",
    "wof:name":"Casa Indigena",
    "wof:placetype":"locality"
},
  "geometry": {"coordinates":[-70.23333000000001,-0.43333],"type":"Point"}
}