{
  "type": "Feature",
  "properties": {
    "gn:admin1_code":"21",
    "gn:admin2_code":"54874.0",
    "gn:asciiname":"Juan Frio",
    "gn:country_code":"CO",
    "gn:dem":474,
    "gn:feature_class":"P",
    "gn:feature_code":"PPL",
    "gn:name":"Juan Fr\u00edo",
    "gn:population":0,
    "gn:timezone":"America/Bogota",
    "iso:country":"CO",
    "wof:name":"Juan Frio",
    "wof:placetype":"locality"
},
  "geometry": {"coordinates":[-72.47139,7.79389],"type":"Point"}
}