{
  "type": "Feature",
  "properties": {
    "gn:admin1_code":"29.0",
    "gn:admin2_code":"76109.0",
    "gn:asciiname":"San Francisco Javier",
    "gn:cc2":"CO",
    "gn:country_code":"CO",
    "gn:dem":48,
    "gn:feature_class":"P",
    "gn:feature_code":"PPL",
    "gn:name":"San Francisco Javier",
    "gn:population":0,
    "gn:timezone":"America/Bogota",
    "iso:country":"CO",
    "name:ceb_x_preferred":[
        "San Francisco Javier"
    ],
    "name:ita_x_preferred":[
        "San Francisco Javier"
    ],
    "name:por_x_preferred":[
        "San Francisco Javier"
    ],
    "name:spa_x_preferred":[
        "San Francisco Javier"
    ],
    "name:und_x_variant":[
        "San Francisco"
    ],
    "name:zho_x_preferred":[
        "\u8056\u5f17\u862d\u897f\u65af\u79d1\u54c8\u7dad\u723e"
    ],
    "wof:name":"San Francisco Javier",
    "wof:placetype":"locality"
},
  "geometry": {"coordinates":[-77.01666999999998,3.66667],"type":"Point"}
}