{
  "type": "Feature",
  "properties": {
    "gn:admin1_code":"33.0",
    "gn:admin2_code":"25322.0",
    "gn:asciiname":"La Esperaza",
    "gn:country_code":"CO",
    "gn:dem":3003,
    "gn:feature_class":"P",
    "gn:feature_code":"PPL",
    "gn:name":"La Esperaza",
    "gn:population":0,
    "gn:timezone":"America/Bogota",
    "iso:country":"CO",
    "wof:name":"La Esperaza",
    "wof:placetype":"locality"
},
  "geometry": {"coordinates":[-73.85778000000001,4.81833],"type":"Point"}
}