{
  "type": "Feature",
  "properties": {
    "gn:admin1_code":"17",
    "gn:admin2_code":"44874.0",
    "gn:asciiname":"Las Mercedes",
    "gn:country_code":"CO",
    "gn:dem":194,
    "gn:feature_class":"P",
    "gn:feature_code":"PPL",
    "gn:name":"Las Mercedes",
    "gn:population":0,
    "gn:timezone":"America/Bogota",
    "iso:country":"CO",
    "name:ceb_x_preferred":[
        "Las Mercedes"
    ],
    "name:deu_x_preferred":[
        "Las Mercedes"
    ],
    "name:spa_x_preferred":[
        "Las Mercedes"
    ],
    "name:swe_x_preferred":[
        "Las Mercedes"
    ],
    "wof:name":"Las Mercedes",
    "wof:placetype":"locality"
},
  "geometry": {"coordinates":[-72.99083,10.64194],"type":"Point"}
}