{
  "type": "Feature",
  "properties": {
    "gn:admin1_code":"26",
    "gn:admin2_code":"68498.0",
    "gn:asciiname":"Macanal",
    "gn:country_code":"CO",
    "gn:dem":1333,
    "gn:feature_class":"P",
    "gn:feature_code":"PPL",
    "gn:name":"Macanal",
    "gn:population":0,
    "gn:timezone":"America/Bogota",
    "iso:country":"CO",
    "wof:name":"Macanal",
    "wof:placetype":"locality"
},
  "geometry": {"coordinates":[-73.13882,6.29652],"type":"Point"}
}