{
  "type": "Feature",
  "properties": {
    "gn:admin1_code":"36",
    "gn:admin2_code":"15507.0",
    "gn:asciiname":"El Guelito",
    "gn:country_code":"CO",
    "gn:dem":1069,
    "gn:feature_class":"P",
    "gn:feature_code":"PPL",
    "gn:name":"El Guelito",
    "gn:population":0,
    "gn:timezone":"America/Bogota",
    "iso:country":"CO",
    "wof:name":"El Guelito",
    "wof:placetype":"locality"
},
  "geometry": {"coordinates":[-74.26734,5.76379],"type":"Point"}
}