{
  "type": "Feature",
  "properties": {
    "gn:admin1_code":"33.0",
    "gn:admin2_code":"25322.0",
    "gn:asciiname":"San Ignacio",
    "gn:country_code":"CO",
    "gn:dem":2960,
    "gn:feature_class":"P",
    "gn:feature_code":"PPL",
    "gn:name":"San Ignacio",
    "gn:population":0,
    "gn:timezone":"America/Bogota",
    "iso:country":"CO",
    "wof:name":"San Ignacio",
    "wof:placetype":"locality"
},
  "geometry": {"coordinates":[-73.88308000000001,4.78887],"type":"Point"}
}