{
  "type": "Feature",
  "properties": {
    "gn:admin1_code":"20",
    "gn:admin2_code":"52694.0",
    "gn:asciiname":"El Salitre",
    "gn:country_code":"CO",
    "gn:dem":2079,
    "gn:feature_class":"P",
    "gn:feature_code":"PPL",
    "gn:name":"El Salitre",
    "gn:population":0,
    "gn:timezone":"America/Bogota",
    "iso:country":"CO",
    "wof:name":"El Salitre",
    "wof:placetype":"locality"
},
  "geometry": {"coordinates":[-77.08299,1.50604],"type":"Point"}
}