{
  "type": "Feature",
  "properties": {
    "gn:admin1_code":"9",
    "gn:admin2_code":"19517.0",
    "gn:asciiname":"La Morena",
    "gn:country_code":"CO",
    "gn:dem":1968,
    "gn:feature_class":"P",
    "gn:feature_code":"PPL",
    "gn:name":"La Morena",
    "gn:population":0,
    "gn:timezone":"America/Bogota",
    "iso:country":"CO",
    "wof:name":"La Morena",
    "wof:placetype":"locality"
},
  "geometry": {"coordinates":[-75.91528000000002,2.55333],"type":"Point"}
}