{
  "type": "Feature",
  "properties": {
    "gn:admin1_code":"20",
    "gn:admin2_code":"52621.0",
    "gn:asciiname":"Las Lajas",
    "gn:country_code":"CO",
    "gn:dem":18,
    "gn:feature_class":"P",
    "gn:feature_code":"PPL",
    "gn:name":"Las Lajas",
    "gn:population":0,
    "gn:timezone":"America/Bogota",
    "iso:country":"CO",
    "name:und_x_variant":[
        "Pundi",
        "Pumb\u00ed",
        "Las Lajas"
    ],
    "wof:name":"Las Lajas",
    "wof:placetype":"locality"
},
  "geometry": {"coordinates":[-78.35464,1.86096],"type":"Point"}
}