{
  "type": "Feature",
  "properties": {
    "gn:admin1_code":"20.0",
    "gn:admin2_code":"52573.0",
    "gn:asciiname":"Yanale Bajo",
    "gn:country_code":"CO",
    "gn:dem":2732,
    "gn:feature_class":"P",
    "gn:feature_code":"PPL",
    "gn:name":"Yanale Bajo",
    "gn:population":0,
    "gn:timezone":"America/Bogota",
    "iso:country":"CO",
    "wof:name":"Yanale Bajo",
    "wof:placetype":"locality"
},
  "geometry": {"coordinates":[-77.52091999999998,0.90056],"type":"Point"}
}