{
  "type": "Feature",
  "properties": {
    "gn:admin1_code":"29",
    "gn:admin2_code":"76246.0",
    "gn:asciiname":"La Guardia",
    "gn:country_code":"CO",
    "gn:dem":1715,
    "gn:feature_class":"P",
    "gn:feature_code":"PPL",
    "gn:name":"La Guardia",
    "gn:population":0,
    "gn:timezone":"America/Bogota",
    "iso:country":"CO",
    "wof:name":"La Guardia",
    "wof:placetype":"locality"
},
  "geometry": {"coordinates":[-76.21557,4.69293],"type":"Point"}
}