{
  "type": "Feature",
  "properties": {
    "gn:admin1_code":"20.0",
    "gn:admin2_code":"52381.0",
    "gn:asciiname":"Yunguilla",
    "gn:country_code":"CO",
    "gn:dem":2027,
    "gn:feature_class":"P",
    "gn:feature_code":"PPL",
    "gn:name":"Yunguilla",
    "gn:population":0,
    "gn:timezone":"America/Bogota",
    "iso:country":"CO",
    "name:und_x_variant":[
        "Gunguilla",
        "Yunguilla"
    ],
    "wof:name":"Yunguilla",
    "wof:placetype":"locality"
},
  "geometry": {"coordinates":[-77.42376999999998,1.37939],"type":"Point"}
}