{
  "type": "Feature",
  "properties": {
    "gn:admin1_code":"36",
    "gn:admin2_code":"15632.0",
    "gn:asciiname":"San Ignacio",
    "gn:country_code":"CO",
    "gn:dem":2864,
    "gn:feature_class":"P",
    "gn:feature_code":"PPL",
    "gn:name":"San Ignacio",
    "gn:population":0,
    "gn:timezone":"America/Bogota",
    "iso:country":"CO",
    "wof:name":"San Ignacio",
    "wof:placetype":"locality"
},
  "geometry": {"coordinates":[-73.71916999999998,5.6525],"type":"Point"}
}