{
  "type": "Feature",
  "properties": {
    "gn:admin1_code":"33.0",
    "gn:admin2_code":"25815.0",
    "gn:asciiname":"Alto de La Viga",
    "gn:country_code":"CO",
    "gn:dem":347,
    "gn:feature_class":"P",
    "gn:feature_code":"PPL",
    "gn:name":"Alto de La Viga",
    "gn:population":0,
    "gn:timezone":"America/Bogota",
    "iso:country":"CO",
    "name:spa_x_preferred":[
        "Alto de La Viga"
    ],
    "wof:name":"Alto de La Viga",
    "wof:placetype":"locality"
},
  "geometry": {"coordinates":[-74.71194,4.41873],"type":"Point"}
}