{
  "type": "Feature",
  "properties": {
    "gn:admin1_code":"2.0",
    "gn:admin2_code":"5030.0",
    "gn:asciiname":"Guali",
    "gn:country_code":"CO",
    "gn:dem":1337,
    "gn:feature_class":"P",
    "gn:feature_code":"PPL",
    "gn:name":"Gual\u00ed",
    "gn:population":0,
    "gn:timezone":"America/Bogota",
    "iso:country":"CO",
    "name:spa_x_preferred":[
        "Gual\u00ed"
    ],
    "wof:name":"Guali",
    "wof:placetype":"locality"
},
  "geometry": {"coordinates":[-75.71026999999999,6.05977],"type":"Point"}
}