{
  "type": "Feature",
  "properties": {
    "gn:admin1_code":"38",
    "gn:admin2_code":"47318.0",
    "gn:asciiname":"La Plaza",
    "gn:country_code":"CO",
    "gn:dem":30,
    "gn:feature_class":"P",
    "gn:feature_code":"PPL",
    "gn:name":"La Plaza",
    "gn:population":0,
    "gn:timezone":"America/Bogota",
    "iso:country":"CO",
    "wof:name":"La Plaza",
    "wof:placetype":"locality"
},
  "geometry": {"coordinates":[-74.16667,9.23333],"type":"Point"}
}