{
  "type": "Feature",
  "properties": {
    "gn:admin1_code":"17",
    "gn:admin2_code":"44098.0",
    "gn:asciiname":"Canahuate",
    "gn:country_code":"CO",
    "gn:dem":250,
    "gn:feature_class":"P",
    "gn:feature_code":"PPL",
    "gn:name":"Ca\u00f1ahuate",
    "gn:population":0,
    "gn:timezone":"America/Bogota",
    "iso:country":"CO",
    "wof:name":"Canahuate",
    "wof:placetype":"locality"
},
  "geometry": {"coordinates":[-72.929,10.92183],"type":"Point"}
}