{
  "type": "Feature",
  "properties": {
    "gn:admin1_code":"16.0",
    "gn:admin2_code":"41206.0",
    "gn:asciiname":"Ojo de Agua",
    "gn:country_code":"CO",
    "gn:dem":1956,
    "gn:feature_class":"P",
    "gn:feature_code":"PPLL",
    "gn:name":"Ojo de Agua",
    "gn:population":0,
    "gn:timezone":"America/Bogota",
    "iso:country":"CO",
    "name:spa_x_preferred":[
        "Ojo de Agua"
    ],
    "wof:name":"Ojo de Agua",
    "wof:placetype":"locality"
},
  "geometry": {"coordinates":[-74.64199000000001,3.65705],"type":"Point"}
}