{
  "type": "Feature",
  "properties": {
    "gn:admin1_code":"2",
    "gn:admin2_code":"5250.0",
    "gn:asciiname":"Amaseri",
    "gn:country_code":"CO",
    "gn:dem":51,
    "gn:feature_class":"P",
    "gn:feature_code":"PPL",
    "gn:name":"Amaser\u00ed",
    "gn:population":0,
    "gn:timezone":"America/Bogota",
    "iso:country":"CO",
    "name:und_x_variant":[
        "Amacer\u00ed",
        "Amanser\u00ed",
        "Amaser\u00ed"
    ],
    "wof:name":"Amaseri",
    "wof:placetype":"locality"
},
  "geometry": {"coordinates":[-74.7225,7.73727],"type":"Point"}
}