{
  "type": "Feature",
  "properties": {
    "gn:admin1_code":"20",
    "gn:admin2_code":"52001.0",
    "gn:asciiname":"Botanilla",
    "gn:country_code":"CO",
    "gn:dem":2686,
    "gn:feature_class":"P",
    "gn:feature_code":"PPL",
    "gn:name":"Botanilla",
    "gn:population":0,
    "gn:timezone":"America/Bogota",
    "iso:country":"CO",
    "name:und_x_variant":[
        "Botana",
        "Botanilla"
    ],
    "wof:name":"Botanilla",
    "wof:placetype":"locality"
},
  "geometry": {"coordinates":[-77.26183,1.18566],"type":"Point"}
}