{
  "type": "Feature",
  "properties": {
    "gn:admin1_code":"8.0",
    "gn:admin2_code":"18094.0",
    "gn:asciiname":"La Pistola",
    "gn:country_code":"CO",
    "gn:dem":270,
    "gn:feature_class":"P",
    "gn:feature_code":"PPL",
    "gn:name":"La Pistola",
    "gn:population":0,
    "gn:timezone":"America/Bogota",
    "iso:country":"CO",
    "name:spa_x_preferred":[
        "La Pistola"
    ],
    "wof:name":"La Pistola",
    "wof:placetype":"locality"
},
  "geometry": {"coordinates":[-75.81225999999999,1.29376],"type":"Point"}
}