{
  "type": "Feature",
  "properties": {
    "gn:admin1_code":"29",
    "gn:admin2_code":"76130.0",
    "gn:asciiname":"Juanchito",
    "gn:country_code":"CO",
    "gn:dem":952,
    "gn:feature_class":"P",
    "gn:feature_code":"PPL",
    "gn:name":"Juanchito",
    "gn:population":0,
    "gn:timezone":"America/Bogota",
    "iso:country":"CO",
    "name:und_x_variant":[
        "Gual\u00ed",
        "Juanchito"
    ],
    "wof:name":"Juanchito",
    "wof:placetype":"locality"
},
  "geometry": {"coordinates":[-76.47458,3.45058],"type":"Point"}
}