{
  "type": "Feature",
  "properties": {
    "gn:admin1_code":"17",
    "gn:admin2_code":"44847.0",
    "gn:asciiname":"Jetsu",
    "gn:country_code":"CO",
    "gn:dem":85,
    "gn:feature_class":"P",
    "gn:feature_code":"PPL",
    "gn:name":"Jetsu",
    "gn:population":0,
    "gn:timezone":"America/Bogota",
    "iso:country":"CO",
    "name:und_x_variant":[
        "Jepisi",
        "Jetsu"
    ],
    "wof:name":"Jetsu",
    "wof:placetype":"locality"
},
  "geometry": {"coordinates":[-71.71160999999999,12.1279],"type":"Point"}
}