{
  "type": "Feature",
  "properties": {
    "gn:admin1_code":"20",
    "gn:admin2_code":"52256.0",
    "gn:asciiname":"La Sierra",
    "gn:country_code":"CO",
    "gn:dem":1555,
    "gn:feature_class":"P",
    "gn:feature_code":"PPL",
    "gn:name":"La Sierra",
    "gn:population":0,
    "gn:timezone":"America/Bogota",
    "iso:country":"CO",
    "wof:name":"La Sierra",
    "wof:placetype":"locality"
},
  "geometry": {"coordinates":[-77.37956,1.76395],"type":"Point"}
}