{
  "type": "Feature",
  "properties": {
    "gn:admin1_code":"19.0",
    "gn:admin2_code":"50150.0",
    "gn:asciiname":"San Vicente",
    "gn:country_code":"CO",
    "gn:dem":280,
    "gn:feature_class":"P",
    "gn:feature_code":"PPLL",
    "gn:name":"San Vicente",
    "gn:population":0,
    "gn:timezone":"America/Bogota",
    "iso:country":"CO",
    "name:spa_x_preferred":[
        "San Vicente"
    ],
    "wof:name":"San Vicente",
    "wof:placetype":"locality"
},
  "geometry": {"coordinates":[-73.44031,3.80521],"type":"Point"}
}