{
  "type": "Feature",
  "properties": {
    "iso:country":"CO",
    "name:ast_x_preferred":[
        "Guateque"
    ],
    "name:avk_x_preferred":[
        "Guateque"
    ],
    "name:ceb_x_preferred":[
        "Guateque"
    ],
    "name:eng_x_preferred":[
        "Guateque"
    ],
    "name:fas_x_preferred":[
        "\u06af\u0648\u0627\u062a\u06a9\u0647"
    ],
    "name:fra_x_preferred":[
        "Guateque"
    ],
    "name:gla_x_preferred":[
        "Guateque"
    ],
    "name:gle_x_preferred":[
        "Guateque"
    ],
    "name:glg_x_preferred":[
        "Guateque"
    ],
    "name:ita_x_preferred":[
        "Guateque"
    ],
    "name:kat_x_preferred":[
        "\u10d2\u10e3\u10d0\u10e2\u10d4\u10d9\u10d4"
    ],
    "name:msa_x_preferred":[
        "Guateque"
    ],
    "name:nan_x_preferred":[
        "Guateque"
    ],
    "name:nld_x_preferred":[
        "Guateque"
    ],
    "name:pol_x_preferred":[
        "Guateque"
    ],
    "name:por_x_preferred":[
        "Guateque"
    ],
    "name:rus_x_preferred":[
        "\u0413\u0443\u0430\u0442\u0435\u043a\u0435"
    ],
    "name:spa_x_preferred":[
        "Guateque"
    ],
    "name:swe_x_preferred":[
        "Guateque"
    ],
    "name:tgl_x_preferred":[
        "Guateque"
    ],
    "name:vie_x_preferred":[
        "Guateque"
    ],
    "name:war_x_preferred":[
        "Guateque"
    ],
    "name:zho_min_nan_x_preferred":[
        "Guateque"
    ],
    "name:zho_x_preferred":[
        "\u74dc\u7279\u514b"
    ],
    "qs:gn_country":"CO",
    "qs:gn_fcode":"PPL",
    "qs:gn_pop":7069,
    "qs:name":"Guateque",
    "qs:name_adm0":"Colombia",
    "qs:name_adm1":"Boyaca",
    "qs:photos":0,
    "qs:photos_1k":0,
    "qs:photos_9k":1,
    "qs:photos_9r":1,
    "qs:photos_all":24,
    "qs:photos_sr":0,
    "qs:placetype":"Town",
    "qs:pop_sr":"5",
    "qs:woe_adm0":23424787,
    "wd:wordcount":246,
    "wof:name":"Guateque",
    "wof:placetype":"locality",
    "wof:population":7069
},
  "geometry": {"coordinates":[-73.47274,5.00619],"type":"Point"}
}