{
  "type": "Feature",
  "properties": {
    "gn:admin1_code":"22.0",
    "gn:admin2_code":"86749.0",
    "gn:asciiname":"El Ejido",
    "gn:country_code":"CO",
    "gn:dem":2087,
    "gn:feature_class":"P",
    "gn:feature_code":"PPL",
    "gn:name":"El Ejido",
    "gn:population":0,
    "gn:timezone":"America/Bogota",
    "iso:country":"CO",
    "name:spa_x_preferred":[
        "El Ejido"
    ],
    "wof:name":"El Ejido",
    "wof:placetype":"locality"
},
  "geometry": {"coordinates":[-76.92778,1.19615],"type":"Point"}
}