{
  "type": "Feature",
  "properties": {
    "gn:admin1_code":"26.0",
    "gn:admin2_code":"68575.0",
    "gn:asciiname":"Vijagual",
    "gn:country_code":"CO",
    "gn:dem":46,
    "gn:feature_class":"P",
    "gn:feature_code":"PPL",
    "gn:name":"Vijagual",
    "gn:population":0,
    "gn:timezone":"America/Bogota",
    "iso:country":"CO",
    "name:und_x_variant":[
        "Corregimiento Vijagual",
        "Vijagual"
    ],
    "wof:name":"Vijagual",
    "wof:placetype":"locality"
},
  "geometry": {"coordinates":[-73.81581,7.84991],"type":"Point"}
}