{
  "type": "Feature",
  "properties": {
    "gn:admin1_code":"20.0",
    "gn:admin2_code":"52788.0",
    "gn:asciiname":"El Mirador",
    "gn:country_code":"CO",
    "gn:dem":3101,
    "gn:feature_class":"P",
    "gn:feature_code":"PPL",
    "gn:name":"El Mirador",
    "gn:population":0,
    "gn:timezone":"America/Bogota",
    "iso:country":"CO",
    "wof:name":"El Mirador",
    "wof:placetype":"locality"
},
  "geometry": {"coordinates":[-77.31343000000003,1.1026],"type":"Point"}
}