{
  "type": "Feature",
  "properties": {
    "gn:admin1_code":"20.0",
    "gn:admin2_code":"52227.0",
    "gn:asciiname":"La Escalera",
    "gn:country_code":"CO",
    "gn:dem":3243,
    "gn:feature_class":"P",
    "gn:feature_code":"PPL",
    "gn:name":"La Escalera",
    "gn:population":0,
    "gn:timezone":"America/Bogota",
    "iso:country":"CO",
    "wof:name":"La Escalera",
    "wof:placetype":"locality"
},
  "geometry": {"coordinates":[-77.82158000000003,0.90447],"type":"Point"}
}