{
  "type": "Feature",
  "properties": {
    "gn:admin1_code":"2.0",
    "gn:admin2_code":"5501.0",
    "gn:asciiname":"La Montanita",
    "gn:country_code":"CO",
    "gn:dem":2028,
    "gn:feature_class":"P",
    "gn:feature_code":"PPL",
    "gn:name":"La Monta\u00f1ita",
    "gn:population":0,
    "gn:timezone":"America/Bogota",
    "iso:country":"CO",
    "wof:name":"La Montanita",
    "wof:placetype":"locality"
},
  "geometry": {"coordinates":[-75.74916999999998,6.6275],"type":"Point"}
}