{
  "type": "Feature",
  "properties": {
    "gn:admin1_code":"10",
    "gn:admin2_code":"20238.0",
    "gn:asciiname":"Canaima",
    "gn:country_code":"CO",
    "gn:dem":488,
    "gn:feature_class":"P",
    "gn:feature_code":"PPL",
    "gn:name":"Canaima",
    "gn:population":0,
    "gn:timezone":"America/Bogota",
    "iso:country":"CO",
    "wof:name":"Canaima",
    "wof:placetype":"locality"
},
  "geometry": {"coordinates":[-73.8193,10.33592],"type":"Point"}
}