{
  "type": "Feature",
  "properties": {
    "gn:admin1_code":"32",
    "gn:admin2_code":"85410.0",
    "gn:asciiname":"San Felix",
    "gn:country_code":"CO",
    "gn:dem":163,
    "gn:feature_class":"P",
    "gn:feature_code":"PPL",
    "gn:name":"San F\u00e9lix",
    "gn:population":0,
    "gn:timezone":"America/Bogota",
    "iso:country":"CO",
    "wof:name":"San Felix",
    "wof:placetype":"locality"
},
  "geometry": {"coordinates":[-72.45739,4.35319],"type":"Point"}
}