{
  "type": "Feature",
  "properties": {
    "gn:admin1_code":"33",
    "gn:admin2_code":"25513.0",
    "gn:asciiname":"La Ramada",
    "gn:country_code":"CO",
    "gn:dem":2233,
    "gn:feature_class":"P",
    "gn:feature_code":"PPL",
    "gn:name":"La Ramada",
    "gn:population":0,
    "gn:timezone":"America/Bogota",
    "iso:country":"CO",
    "wof:name":"La Ramada",
    "wof:placetype":"locality"
},
  "geometry": {"coordinates":[-74.09999999999999,5.16667],"type":"Point"}
}