{
  "type": "Feature",
  "properties": {
    "gn:admin1_code":"2",
    "gn:admin2_code":"5790.0",
    "gn:asciiname":"Montanita",
    "gn:country_code":"CO",
    "gn:dem":197,
    "gn:feature_class":"P",
    "gn:feature_code":"PPL",
    "gn:name":"Montanita",
    "gn:population":0,
    "gn:timezone":"America/Bogota",
    "iso:country":"CO",
    "wof:name":"Montanita",
    "wof:placetype":"locality"
},
  "geometry": {"coordinates":[-75.28556,7.46179],"type":"Point"}
}