{
  "type": "Feature",
  "properties": {
    "gn:admin1_code":"35",
    "gn:admin2_code":"13430.0",
    "gn:asciiname":"Barranca",
    "gn:country_code":"CO",
    "gn:dem":52,
    "gn:feature_class":"P",
    "gn:feature_code":"PPL",
    "gn:name":"Barranca",
    "gn:population":0,
    "gn:timezone":"America/Bogota",
    "iso:country":"CO",
    "name:bre_x_preferred":[
        "Barranca"
    ],
    "name:ceb_x_preferred":[
        "Barranca"
    ],
    "name:deu_x_preferred":[
        "Barranca"
    ],
    "name:fra_x_preferred":[
        "Barranca"
    ],
    "name:nld_x_preferred":[
        "Barranca"
    ],
    "name:por_x_preferred":[
        "Barranca"
    ],
    "name:rus_x_preferred":[
        "\u0411\u0430\u0440\u0440\u0430\u043d\u043a\u0430"
    ],
    "name:spa_x_preferred":[
        "Barranca"
    ],
    "name:swe_x_preferred":[
        "Barranca"
    ],
    "name:und_x_variant":[
        "Caser\u00edo Barranca",
        "Barranco",
        "Berranca",
        "Barranco de Yuca",
        "Barranca"
    ],
    "wof:name":"Barranca",
    "wof:placetype":"locality"
},
  "geometry": {"coordinates":[-74.85290000000001,9.17889],"type":"Point"}
}