{
  "type": "Feature",
  "properties": {
    "gn:admin1_code":"28.0",
    "gn:admin2_code":"73168.0",
    "gn:asciiname":"La Floresta",
    "gn:country_code":"CO",
    "gn:dem":2346,
    "gn:feature_class":"P",
    "gn:feature_code":"PPL",
    "gn:name":"La Floresta",
    "gn:population":0,
    "gn:timezone":"America/Bogota",
    "iso:country":"CO",
    "wof:name":"La Floresta",
    "wof:placetype":"locality"
},
  "geometry": {"coordinates":[-75.68028000000002,3.81917],"type":"Point"}
}