{
  "type": "Feature",
  "properties": {
    "gn:admin1_code":"4",
    "gn:admin2_code":"8520.0",
    "gn:asciiname":"Juncalejo",
    "gn:country_code":"CO",
    "gn:dem":6,
    "gn:feature_class":"P",
    "gn:feature_code":"PPL",
    "gn:name":"Juncalejo",
    "gn:population":0,
    "gn:timezone":"America/Bogota",
    "iso:country":"CO",
    "wof:name":"Juncalejo",
    "wof:placetype":"locality"
},
  "geometry": {"coordinates":[-74.74944000000001,10.71],"type":"Point"}
}