{
  "type": "Feature",
  "properties": {
    "gn:admin1_code":"35",
    "gn:admin2_code":"13430.0",
    "gn:asciiname":"Caceres",
    "gn:country_code":"CO",
    "gn:dem":29,
    "gn:feature_class":"P",
    "gn:feature_code":"PPL",
    "gn:name":"C\u00e1ceres",
    "gn:population":0,
    "gn:timezone":"America/Bogota",
    "iso:country":"CO",
    "wof:name":"Caceres",
    "wof:placetype":"locality"
},
  "geometry": {"coordinates":[-74.81908,9.17398],"type":"Point"}
}