{
  "type": "Feature",
  "properties": {
    "gn:admin1_code":"2.0",
    "gn:admin2_code":"5364.0",
    "gn:asciiname":"La Mesenia",
    "gn:country_code":"CO",
    "gn:dem":2169,
    "gn:feature_class":"P",
    "gn:feature_code":"PPL",
    "gn:name":"La Mesenia",
    "gn:population":0,
    "gn:timezone":"America/Bogota",
    "iso:country":"CO",
    "wof:name":"La Mesenia",
    "wof:placetype":"locality"
},
  "geometry": {"coordinates":[-75.88221999999998,5.50861],"type":"Point"}
}