{
  "type": "Feature",
  "properties": {
    "gn:admin1_code":"17",
    "gn:admin2_code":"44847.0",
    "gn:asciiname":"Kepispa",
    "gn:country_code":"CO",
    "gn:dem":-48,
    "gn:feature_class":"P",
    "gn:feature_code":"PPL",
    "gn:name":"Kepispa",
    "gn:population":0,
    "gn:timezone":"America/Bogota",
    "iso:country":"CO",
    "wof:name":"Kepispa",
    "wof:placetype":"locality"
},
  "geometry": {"coordinates":[-71.40000000000001,12.35],"type":"Point"}
}