{
  "type": "Feature",
  "properties": {
    "gn:admin1_code":"21.0",
    "gn:admin2_code":"54099.0",
    "gn:asciiname":"San Jose de la Montana",
    "gn:country_code":"CO",
    "gn:dem":2002,
    "gn:feature_class":"P",
    "gn:feature_code":"PPL",
    "gn:name":"San Jos\u00e9 de la Monta\u00f1a",
    "gn:population":0,
    "gn:timezone":"America/Bogota",
    "iso:country":"CO",
    "name:und_x_variant":[
        "San Jos\u00e9 de la Monta\u00f1a"
    ],
    "wof:name":"San Jose de la Montana",
    "wof:placetype":"locality"
},
  "geometry": {"coordinates":[-72.71666999999999,7.58333],"type":"Point"}
}