{
  "type": "Feature",
  "properties": {
    "gn:admin1_code":"12",
    "gn:asciiname":"Cuenca",
    "gn:country_code":"CO",
    "gn:dem":27,
    "gn:feature_class":"P",
    "gn:feature_code":"PPL",
    "gn:name":"Cuenca",
    "gn:population":0,
    "gn:timezone":"America/Bogota",
    "iso:country":"CO",
    "name:bel_x_preferred":[
        "\u041a\u0443\u044d\u043d\u043a\u0430"
    ],
    "name:bre_x_preferred":[
        "Cuenca"
    ],
    "name:cat_x_preferred":[
        "Cuenca"
    ],
    "name:ceb_x_preferred":[
        "Cuenca"
    ],
    "name:ces_x_preferred":[
        "Cuenca"
    ],
    "name:dan_x_preferred":[
        "Cuenca"
    ],
    "name:deu_x_preferred":[
        "Cuenca"
    ],
    "name:ell_x_preferred":[
        "\u039a\u03bf\u03c5\u03ad\u03bd\u03ba\u03b1"
    ],
    "name:epo_x_preferred":[
        "Cuenca"
    ],
    "name:eus_x_preferred":[
        "Cuenca"
    ],
    "name:fas_x_preferred":[
        "\u06a9\u0648\u0626\u0646\u06a9\u0627"
    ],
    "name:fin_x_preferred":[
        "Cuenca"
    ],
    "name:fra_x_preferred":[
        "Cuenca"
    ],
    "name:gla_x_preferred":[
        "Cuenca"
    ],
    "name:glg_x_preferred":[
        "Cuenca"
    ],
    "name:heb_x_preferred":[
        "\u05e7\u05d5\u05d0\u05e0\u05e7\u05d4"
    ],
    "name:hrv_x_preferred":[
        "Cuenca"
    ],
    "name:hun_x_preferred":[
        "Cuenca"
    ],
    "name:hye_x_preferred":[
        "\u053f\u0578\u0582\u0565\u0576\u056f\u0561"
    ],
    "name:ita_x_preferred":[
        "Cuenca"
    ],
    "name:jpn_x_preferred":[
        "\u30af\u30a8\u30f3\u30ab"
    ],
    "name:kat_x_preferred":[
        "\u10d9\u10e3\u10d4\u10dc\u10d9\u10d0"
    ],
    "name:kor_x_preferred":[
        "\ucfe0\uc5e5\uce74"
    ],
    "name:lit_x_preferred":[
        "Kuenka"
    ],
    "name:ltz_x_preferred":[
        "Cuenca"
    ],
    "name:mlg_x_preferred":[
        "Cuenca"
    ],
    "name:nds_x_preferred":[
        "Cuenca"
    ],
    "name:nld_x_preferred":[
        "Cuenca"
    ],
    "name:nor_x_preferred":[
        "Cuenca"
    ],
    "name:pol_x_preferred":[
        "Cuenca"
    ],
    "name:por_x_preferred":[
        "Cuenca"
    ],
    "name:rus_x_preferred":[
        "\u041a\u0443\u044d\u043d\u043a\u0430"
    ],
    "name:sco_x_preferred":[
        "Cuenca"
    ],
    "name:slk_x_preferred":[
        "Cuenca"
    ],
    "name:spa_x_preferred":[
        "Cuenca"
    ],
    "name:srp_x_preferred":[
        "\u041a\u0443\u0435\u043d\u043a\u0430"
    ],
    "name:swe_x_preferred":[
        "Cuenca"
    ],
    "name:tur_x_preferred":[
        "Cuenca"
    ],
    "name:ukr_x_preferred":[
        "\u041a\u0443\u0435\u043d\u043a\u0430"
    ],
    "name:vie_x_preferred":[
        "Cuenca"
    ],
    "name:war_x_preferred":[
        "Cuenca"
    ],
    "wof:name":"Cuenca",
    "wof:placetype":"locality"
},
  "geometry": {"coordinates":[-75.25063,8.52299],"type":"Point"}
}