{
  "type": "Feature",
  "properties": {
    "gn:admin1_code":"12",
    "gn:asciiname":"Cuenca",
    "gn:country_code":"CO",
    "gn:dem":27,
    "gn:feature_class":"P",
    "gn:feature_code":"PPL",
    "gn:name":"Cuenca",
    "gn:population":0,
    "gn:timezone":"America/Bogota",
    "iso:country":"CO",
    "wof:name":"Cuenca",
    "wof:placetype":"locality"
},
  "geometry": {"coordinates":[-75.25063,8.52299],"type":"Point"}
}