{
  "type": "Feature",
  "properties": {
    "gn:admin1_code":"12.0",
    "gn:admin2_code":"23001.0",
    "gn:asciiname":"San Gabriel",
    "gn:country_code":"CO",
    "gn:dem":59,
    "gn:feature_class":"P",
    "gn:feature_code":"PPL",
    "gn:name":"San Gabriel",
    "gn:population":0,
    "gn:timezone":"America/Bogota",
    "iso:country":"CO",
    "wof:name":"San Gabriel",
    "wof:placetype":"locality"
},
  "geometry": {"coordinates":[-76.09246999999998,8.43473],"type":"Point"}
}