{
  "type": "Feature",
  "properties": {
    "gn:admin1_code":"2.0",
    "gn:admin2_code":"5887.0",
    "gn:asciiname":"La Gabriela",
    "gn:country_code":"CO",
    "gn:dem":2623,
    "gn:feature_class":"P",
    "gn:feature_code":"PPL",
    "gn:name":"La Gabriela",
    "gn:population":0,
    "gn:timezone":"America/Bogota",
    "iso:country":"CO",
    "wof:name":"La Gabriela",
    "wof:placetype":"locality"
},
  "geometry": {"coordinates":[-75.54139000000001,6.93222],"type":"Point"}
}