{
  "type": "Feature",
  "properties": {
    "gn:admin1_code":"2",
    "gn:admin2_code":"5585.0",
    "gn:asciiname":"El Brasil",
    "gn:country_code":"CO",
    "gn:dem":260,
    "gn:feature_class":"P",
    "gn:feature_code":"PPL",
    "gn:name":"El Brasil",
    "gn:population":0,
    "gn:timezone":"America/Bogota",
    "iso:country":"CO",
    "wof:name":"El Brasil",
    "wof:placetype":"locality"
},
  "geometry": {"coordinates":[-74.61610999999998,6.26722],"type":"Point"}
}