{
  "type": "Feature",
  "properties": {
    "gn:admin1_code":"16",
    "gn:admin2_code":"41016.0",
    "gn:asciiname":"Monserrate",
    "gn:country_code":"CO",
    "gn:dem":1686,
    "gn:feature_class":"P",
    "gn:feature_code":"PPL",
    "gn:name":"Monserrate",
    "gn:population":0,
    "gn:timezone":"America/Bogota",
    "iso:country":"CO",
    "name:cat_x_preferred":[
        "Monserrate"
    ],
    "name:ceb_x_preferred":[
        "Monserrate"
    ],
    "name:deu_x_preferred":[
        "Monserrate"
    ],
    "name:epo_x_preferred":[
        "Monserrate"
    ],
    "name:glg_x_preferred":[
        "Monserrate"
    ],
    "name:ita_x_preferred":[
        "Monserrate"
    ],
    "name:nld_x_preferred":[
        "Monserrate"
    ],
    "name:nor_x_preferred":[
        "Monserrate"
    ],
    "name:spa_x_preferred":[
        "Monserrate"
    ],
    "name:swe_x_preferred":[
        "Monserrate"
    ],
    "wof:name":"Monserrate",
    "wof:placetype":"locality"
},
  "geometry": {"coordinates":[-75.54000000000001,3.25889],"type":"Point"}
}