{
  "type": "Feature",
  "properties": {
    "gn:admin1_code":"16",
    "gn:admin2_code":"41016.0",
    "gn:asciiname":"Monserrate",
    "gn:country_code":"CO",
    "gn:dem":1686,
    "gn:feature_class":"P",
    "gn:feature_code":"PPL",
    "gn:name":"Monserrate",
    "gn:population":0,
    "gn:timezone":"America/Bogota",
    "iso:country":"CO",
    "wof:name":"Monserrate",
    "wof:placetype":"locality"
},
  "geometry": {"coordinates":[-75.54000000000001,3.25889],"type":"Point"}
}