{
  "type": "Feature",
  "properties": {
    "gn:admin1_code":"20",
    "gn:admin2_code":"52381.0",
    "gn:asciiname":"Arboleda",
    "gn:country_code":"CO",
    "gn:dem":1916,
    "gn:feature_class":"P",
    "gn:feature_code":"PPL",
    "gn:name":"Arboleda",
    "gn:population":0,
    "gn:timezone":"America/Bogota",
    "iso:country":"CO",
    "name:und_x_variant":[
        "La Arboleda"
    ],
    "wof:name":"Arboleda",
    "wof:placetype":"locality"
},
  "geometry": {"coordinates":[-77.43526999999997,1.38035],"type":"Point"}
}