{
  "type": "Feature",
  "properties": {
    "gn:admin1_code":"20",
    "gn:admin2_code":"52381.0",
    "gn:asciiname":"Arboleda",
    "gn:country_code":"CO",
    "gn:dem":1916,
    "gn:feature_class":"P",
    "gn:feature_code":"PPL",
    "gn:name":"Arboleda",
    "gn:population":0,
    "gn:timezone":"America/Bogota",
    "iso:country":"CO",
    "name:ceb_x_preferred":[
        "Arboleda"
    ],
    "name:deu_x_preferred":[
        "Arboleda"
    ],
    "name:fra_x_preferred":[
        "Arboleda"
    ],
    "name:ita_x_preferred":[
        "Arboleda"
    ],
    "name:kat_x_preferred":[
        "\u10d0\u10e0\u10d1\u10dd\u10d3\u10d4\u10da\u10d0"
    ],
    "name:msa_x_preferred":[
        "Arboleda"
    ],
    "name:nld_x_preferred":[
        "Arboleda"
    ],
    "name:por_x_preferred":[
        "Arboleda"
    ],
    "name:spa_x_preferred":[
        "Arboleda"
    ],
    "name:tgl_x_preferred":[
        "Arboleda"
    ],
    "name:und_x_variant":[
        "La Arboleda"
    ],
    "name:vie_x_preferred":[
        "Arboleda"
    ],
    "name:war_x_preferred":[
        "Arboleda"
    ],
    "name:zho_x_preferred":[
        "\u963f\u6c83\u840a\u9054"
    ],
    "wof:name":"Arboleda",
    "wof:placetype":"locality"
},
  "geometry": {"coordinates":[-77.43526999999997,1.38035],"type":"Point"}
}