{
  "type": "Feature",
  "properties": {
    "gn:admin1_code":"26",
    "gn:admin2_code":"68861.0",
    "gn:asciiname":"Gualillo",
    "gn:country_code":"CO",
    "gn:dem":1359,
    "gn:feature_class":"P",
    "gn:feature_code":"PPL",
    "gn:name":"Gualillo",
    "gn:population":0,
    "gn:timezone":"America/Bogota",
    "iso:country":"CO",
    "name:und_x_variant":[
        "Gualilo",
        "Gualillo"
    ],
    "wof:name":"Gualillo",
    "wof:placetype":"locality"
},
  "geometry": {"coordinates":[-73.71720999999999,6.18478],"type":"Point"}
}