{
  "type": "Feature",
  "properties": {
    "gn:admin1_code":"29",
    "gn:admin2_code":"76736.0",
    "gn:asciiname":"El Reflejo",
    "gn:country_code":"CO",
    "gn:dem":2063,
    "gn:feature_class":"P",
    "gn:feature_code":"PPL",
    "gn:name":"El Reflejo",
    "gn:population":0,
    "gn:timezone":"America/Bogota",
    "iso:country":"CO",
    "wof:name":"El Reflejo",
    "wof:placetype":"locality"
},
  "geometry": {"coordinates":[-75.87194000000002,4.15139],"type":"Point"}
}