{
  "type": "Feature",
  "properties": {
    "gn:admin1_code":"33.0",
    "gn:admin2_code":"25839.0",
    "gn:asciiname":"Hogar",
    "gn:country_code":"CO",
    "gn:dem":1923,
    "gn:feature_class":"P",
    "gn:feature_code":"PPL",
    "gn:name":"Hogar",
    "gn:population":0,
    "gn:timezone":"America/Bogota",
    "iso:country":"CO",
    "wof:name":"Hogar",
    "wof:placetype":"locality"
},
  "geometry": {"coordinates":[-73.53359,4.74829],"type":"Point"}
}