{
  "type": "Feature",
  "properties": {
    "gn:admin1_code":"10",
    "gn:asciiname":"La Puerta de Mora",
    "gn:country_code":"CO",
    "gn:dem":391,
    "gn:feature_class":"P",
    "gn:feature_code":"PPL",
    "gn:name":"La Puerta de Mora",
    "gn:population":0,
    "gn:timezone":"America/Bogota",
    "iso:country":"CO",
    "wof:name":"La Puerta de Mora",
    "wof:placetype":"locality"
},
  "geometry": {"coordinates":[-73.48439999999999,8.59511],"type":"Point"}
}