{
  "type": "Feature",
  "properties": {
    "gn:admin1_code":"28",
    "gn:admin2_code":"73483.0",
    "gn:asciiname":"Guasimal",
    "gn:country_code":"CO",
    "gn:dem":342,
    "gn:feature_class":"P",
    "gn:feature_code":"PPL",
    "gn:name":"Guasimal",
    "gn:population":0,
    "gn:timezone":"America/Bogota",
    "iso:country":"CO",
    "name:spa_x_preferred":[
        "Guasimal"
    ],
    "wof:name":"Guasimal",
    "wof:placetype":"locality"
},
  "geometry": {"coordinates":[-75.11667,3.58333],"type":"Point"}
}