{
  "type": "Feature",
  "properties": {
    "gn:admin1_code":"33",
    "gn:admin2_code":"25245.0",
    "gn:asciiname":"Las Granjas",
    "gn:country_code":"CO",
    "gn:dem":1446,
    "gn:feature_class":"P",
    "gn:feature_code":"PPL",
    "gn:name":"Las Granjas",
    "gn:population":0,
    "gn:timezone":"America/Bogota",
    "iso:country":"CO",
    "wof:name":"Las Granjas",
    "wof:placetype":"locality"
},
  "geometry": {"coordinates":[-74.41667,4.56667],"type":"Point"}
}