{
  "type": "Feature",
  "properties": {
    "gn:admin1_code":"26",
    "gn:admin2_code":"68572.0",
    "gn:asciiname":"El Coso",
    "gn:country_code":"CO",
    "gn:dem":1613,
    "gn:feature_class":"P",
    "gn:feature_code":"PPL",
    "gn:name":"El Coso",
    "gn:population":0,
    "gn:timezone":"America/Bogota",
    "iso:country":"CO",
    "wof:name":"El Coso",
    "wof:placetype":"locality"
},
  "geometry": {"coordinates":[-73.64006999999999,5.90538],"type":"Point"}
}