{
  "type": "Feature",
  "properties": {
    "gn:admin1_code":"10.0",
    "gn:admin2_code":"20295.0",
    "gn:asciiname":"Puerto Viejo",
    "gn:cc2":"CO",
    "gn:country_code":"CO",
    "gn:dem":41,
    "gn:feature_class":"P",
    "gn:feature_code":"PPL",
    "gn:name":"Puerto Viejo",
    "gn:population":0,
    "gn:timezone":"America/Bogota",
    "iso:country":"CO",
    "name:ceb_x_preferred":[
        "Puerto Viejo"
    ],
    "name:nor_x_preferred":[
        "Puerto Viejo"
    ],
    "name:spa_x_preferred":[
        "Puerto Viejo"
    ],
    "name:swe_x_preferred":[
        "Puerto Viejo"
    ],
    "name:und_x_variant":[
        "Caser\u00edo Puerto Nacional",
        "Puerto Nacional",
        "Puerto Viejo"
    ],
    "wof:name":"Puerto Viejo",
    "wof:placetype":"locality"
},
  "geometry": {"coordinates":[-73.75,8.35],"type":"Point"}
}