{
  "type": "Feature",
  "properties": {
    "gn:admin1_code":"29",
    "gn:admin2_code":"76126.0",
    "gn:asciiname":"Simon Bolivar",
    "gn:country_code":"CO",
    "gn:dem":1577,
    "gn:feature_class":"P",
    "gn:feature_code":"PPL",
    "gn:name":"Simon Bolivar",
    "gn:population":0,
    "gn:timezone":"America/Bogota",
    "iso:country":"CO",
    "wof:name":"Simon Bolivar",
    "wof:placetype":"locality"
},
  "geometry": {"coordinates":[-76.49583,3.92912],"type":"Point"}
}