{
  "type": "Feature",
  "properties": {
    "gn:admin1_code":"12",
    "gn:admin2_code":"23660.0",
    "gn:asciiname":"Dividive",
    "gn:country_code":"CO",
    "gn:dem":99,
    "gn:feature_class":"P",
    "gn:feature_code":"PPL",
    "gn:name":"Dividive",
    "gn:population":0,
    "gn:timezone":"America/Bogota",
    "iso:country":"CO",
    "name:und_x_variant":[
        "Las Dividivis",
        "Los Dividivis",
        "Dividive"
    ],
    "wof:name":"Dividive",
    "wof:placetype":"locality"
},
  "geometry": {"coordinates":[-75.38123,8.96614],"type":"Point"}
}