{
  "type": "Feature",
  "properties": {
    "gn:admin1_code":"9",
    "gn:admin2_code":"19450.0",
    "gn:asciiname":"Normal",
    "gn:country_code":"CO",
    "gn:dem":1143,
    "gn:feature_class":"P",
    "gn:feature_code":"PPL",
    "gn:name":"Normal",
    "gn:population":0,
    "gn:timezone":"America/Bogota",
    "iso:country":"CO",
    "wof:name":"Normal",
    "wof:placetype":"locality"
},
  "geometry": {"coordinates":[-77.16221,1.79647],"type":"Point"}
}