{
  "type": "Feature",
  "properties": {
    "gn:admin1_code":"9",
    "gn:admin2_code":"19450.0",
    "gn:asciiname":"Normal",
    "gn:country_code":"CO",
    "gn:dem":1143,
    "gn:feature_class":"P",
    "gn:feature_code":"PPL",
    "gn:name":"Normal",
    "gn:population":0,
    "gn:timezone":"America/Bogota",
    "iso:country":"CO",
    "name:cat_x_preferred":[
        "Normal"
    ],
    "name:ceb_x_preferred":[
        "Normal"
    ],
    "name:ces_x_preferred":[
        "Normal"
    ],
    "name:dan_x_preferred":[
        "Normal"
    ],
    "name:deu_x_preferred":[
        "Normal"
    ],
    "name:eus_x_preferred":[
        "Normal"
    ],
    "name:fas_x_preferred":[
        "\u0637\u0628\u06cc\u0639\u06cc"
    ],
    "name:fin_x_preferred":[
        "Normal"
    ],
    "name:fra_x_preferred":[
        "Normal"
    ],
    "name:hun_x_preferred":[
        "Norm\u00e1lis"
    ],
    "name:ind_x_preferred":[
        "Normal"
    ],
    "name:ita_x_preferred":[
        "Normal"
    ],
    "name:jpn_x_preferred":[
        "\u30ce\u30fc\u30de\u30eb"
    ],
    "name:nld_x_preferred":[
        "Normaal"
    ],
    "name:nor_x_preferred":[
        "Normal"
    ],
    "name:pol_x_preferred":[
        "Normal"
    ],
    "name:por_x_preferred":[
        "Normal"
    ],
    "name:spa_x_preferred":[
        "Normal"
    ],
    "name:swe_x_preferred":[
        "Normal"
    ],
    "name:ukr_x_preferred":[
        "\u041d\u043e\u0440\u043c\u0430\u043b\u044c"
    ],
    "name:uzb_x_preferred":[
        "Normal"
    ],
    "name:vol_x_preferred":[
        "Normal"
    ],
    "wof:name":"Normal",
    "wof:placetype":"locality"
},
  "geometry": {"coordinates":[-77.16221,1.79647],"type":"Point"}
}