{
  "type": "Feature",
  "properties": {
    "gn:admin1_code":"26.0",
    "gn:admin2_code":"68235.0",
    "gn:asciiname":"Estacion La Florida",
    "gn:country_code":"CO",
    "gn:dem":144,
    "gn:feature_class":"P",
    "gn:feature_code":"PPLL",
    "gn:name":"Estaci\u00f3n La Florida",
    "gn:population":0,
    "gn:timezone":"America/Bogota",
    "iso:country":"CO",
    "wof:name":"Estacion La Florida",
    "wof:placetype":"locality"
},
  "geometry": {"coordinates":[-73.70175999999999,6.71755],"type":"Point"}
}