{
  "type": "Feature",
  "properties": {
    "gn:admin1_code":"9",
    "gn:admin2_code":"19450.0",
    "gn:asciiname":"Alto La Campana",
    "gn:country_code":"CO",
    "gn:dem":1056,
    "gn:feature_class":"P",
    "gn:feature_code":"PPL",
    "gn:name":"Alto La Campana",
    "gn:population":0,
    "gn:timezone":"America/Bogota",
    "iso:country":"CO",
    "name:und_x_variant":[
        "Alto La Compana",
        "Alto La Campana"
    ],
    "wof:name":"Alto La Campana",
    "wof:placetype":"locality"
},
  "geometry": {"coordinates":[-77.18975,1.74911],"type":"Point"}
}