{
  "type": "Feature",
  "properties": {
    "gn:admin1_code":"21",
    "gn:admin2_code":"54245.0",
    "gn:asciiname":"Bohio Shiroko Kayra",
    "gn:country_code":"CO",
    "gn:dem":408,
    "gn:feature_class":"P",
    "gn:feature_code":"PPL",
    "gn:name":"Boh\u00edo Shiroko Kayra",
    "gn:population":0,
    "gn:timezone":"America/Bogota",
    "iso:country":"CO",
    "wof:name":"Bohio Shiroko Kayra",
    "wof:placetype":"locality"
},
  "geometry": {"coordinates":[-73.25721999999998,9.0087],"type":"Point"}
}