{
  "type": "Feature",
  "properties": {
    "gn:admin1_code":"10.0",
    "gn:asciiname":"Nuevo Tiempo",
    "gn:country_code":"CO",
    "gn:dem":64,
    "gn:feature_class":"P",
    "gn:feature_code":"PPL",
    "gn:name":"Nuevo Tiempo",
    "gn:population":0,
    "gn:timezone":"America/Bogota",
    "iso:country":"CO",
    "name:spa_x_preferred":[
        "Nuevo Tiempo Chile"
    ],
    "name:und_x_variant":[
        "Hacienda Nuevotiempo",
        "Nuevotiempo",
        "Nuevo Tiempo"
    ],
    "wof:name":"Nuevo Tiempo",
    "wof:placetype":"locality"
},
  "geometry": {"coordinates":[-73.96279,9.30267],"type":"Point"}
}