{
  "type": "Feature",
  "properties": {
    "gn:admin1_code":"33",
    "gn:admin2_code":"25407.0",
    "gn:asciiname":"Gibraltar",
    "gn:country_code":"CO",
    "gn:dem":2552,
    "gn:feature_class":"P",
    "gn:feature_code":"PPL",
    "gn:name":"Gibraltar",
    "gn:population":0,
    "gn:timezone":"America/Bogota",
    "iso:country":"CO",
    "wof:name":"Gibraltar",
    "wof:placetype":"locality"
},
  "geometry": {"coordinates":[-73.75,5.31667],"type":"Point"}
}