{
  "type": "Feature",
  "properties": {
    "gn:admin1_code":"36",
    "gn:admin2_code":"15572.0",
    "gn:asciiname":"El Marfil",
    "gn:country_code":"CO",
    "gn:dem":133,
    "gn:feature_class":"P",
    "gn:feature_code":"PPL",
    "gn:name":"El Marf\u00edl",
    "gn:population":0,
    "gn:timezone":"America/Bogota",
    "iso:country":"CO",
    "wof:name":"El Marfil",
    "wof:placetype":"locality"
},
  "geometry": {"coordinates":[-74.51165999999998,6.18389],"type":"Point"}
}