{
  "type": "Feature",
  "properties": {
    "gn:admin1_code":"19.0",
    "gn:admin2_code":"50150.0",
    "gn:asciiname":"Naranjitos",
    "gn:country_code":"CO",
    "gn:dem":417,
    "gn:feature_class":"P",
    "gn:feature_code":"PPL",
    "gn:name":"Naranjitos",
    "gn:population":0,
    "gn:timezone":"America/Bogota",
    "iso:country":"CO",
    "name:spa_x_preferred":[
        "Naranjitos"
    ],
    "wof:name":"Naranjitos",
    "wof:placetype":"locality"
},
  "geometry": {"coordinates":[-73.70426999999999,3.80922],"type":"Point"}
}