{
  "type": "Feature",
  "properties": {
    "gn:admin1_code":"12",
    "gn:admin2_code":"23574.0",
    "gn:asciiname":"Canaima",
    "gn:country_code":"CO",
    "gn:dem":13,
    "gn:feature_class":"P",
    "gn:feature_code":"PPL",
    "gn:name":"Canaima",
    "gn:population":0,
    "gn:timezone":"America/Bogota",
    "iso:country":"CO",
    "name:fra_x_preferred":[
        "Canaima"
    ],
    "name:spa_x_preferred":[
        "Canaima"
    ],
    "wof:name":"Canaima",
    "wof:placetype":"locality"
},
  "geometry": {"coordinates":[-76.23721999999999,8.97222],"type":"Point"}
}