{
  "type": "Feature",
  "properties": {
    "gn:admin1_code":"37",
    "gn:admin2_code":"17088.0",
    "gn:asciiname":"Alemania",
    "gn:country_code":"CO",
    "gn:dem":1361,
    "gn:feature_class":"P",
    "gn:feature_code":"PPL",
    "gn:name":"Alemania",
    "gn:population":0,
    "gn:timezone":"America/Bogota",
    "iso:country":"CO",
    "wof:name":"Alemania",
    "wof:placetype":"locality"
},
  "geometry": {"coordinates":[-75.83333,4.96667],"type":"Point"}
}