{
  "type": "Feature",
  "properties": {
    "gn:admin1_code":"36",
    "gn:admin2_code":"15681.0",
    "gn:asciiname":"Furatena",
    "gn:country_code":"CO",
    "gn:dem":1559,
    "gn:feature_class":"P",
    "gn:feature_code":"PPL",
    "gn:name":"Furatena",
    "gn:population":0,
    "gn:timezone":"America/Bogota",
    "iso:country":"CO",
    "wof:name":"Furatena",
    "wof:placetype":"locality"
},
  "geometry": {"coordinates":[-74.06999999999999,5.70444],"type":"Point"}
}