{
  "type": "Feature",
  "properties": {
    "gn:admin1_code":"2.0",
    "gn:admin2_code":"5001.0",
    "gn:asciiname":"Bella Amparo",
    "gn:country_code":"CO",
    "gn:dem":2071,
    "gn:feature_class":"P",
    "gn:feature_code":"PPL",
    "gn:name":"Bella Amparo",
    "gn:population":0,
    "gn:timezone":"America/Bogota",
    "iso:country":"CO",
    "name:spa_x_preferred":[
        "Bella Amparo"
    ],
    "wof:name":"Bella Amparo",
    "wof:placetype":"locality"
},
  "geometry": {"coordinates":[-75.62571,6.28906],"type":"Point"}
}