{
  "type": "Feature",
  "properties": {
    "gn:admin1_code":"33.0",
    "gn:admin2_code":"25377.0",
    "gn:asciiname":"Cachival",
    "gn:country_code":"CO",
    "gn:dem":3060,
    "gn:feature_class":"P",
    "gn:feature_code":"PPL",
    "gn:name":"Cachival",
    "gn:population":0,
    "gn:timezone":"America/Bogota",
    "iso:country":"CO",
    "wof:name":"Cachival",
    "wof:placetype":"locality"
},
  "geometry": {"coordinates":[-73.97293000000001,4.64519],"type":"Point"}
}