{
  "type": "Feature",
  "properties": {
    "gn:admin1_code":"36",
    "gn:admin2_code":"15507.0",
    "gn:asciiname":"La Belleza",
    "gn:country_code":"CO",
    "gn:dem":564,
    "gn:feature_class":"P",
    "gn:feature_code":"PPL",
    "gn:name":"La Belleza",
    "gn:population":0,
    "gn:timezone":"America/Bogota",
    "iso:country":"CO",
    "wof:name":"La Belleza",
    "wof:placetype":"locality"
},
  "geometry": {"coordinates":[-74.27431999999997,5.70036],"type":"Point"}
}