{
  "type": "Feature",
  "properties": {
    "gn:admin1_code":"28.0",
    "gn:admin2_code":"73275.0",
    "gn:asciiname":"Puerto Rico",
    "gn:country_code":"CO",
    "gn:dem":257,
    "gn:feature_class":"P",
    "gn:feature_code":"PPL",
    "gn:name":"Puerto Rico",
    "gn:population":0,
    "gn:timezone":"America/Bogota",
    "iso:country":"CO",
    "wof:name":"Puerto Rico",
    "wof:placetype":"locality"
},
  "geometry": {"coordinates":[-74.89424,4.28582],"type":"Point"}
}