{
  "type": "Feature",
  "properties": {
    "gn:admin1_code":"19.0",
    "gn:admin2_code":"50110.0",
    "gn:asciiname":"Tierra Grata",
    "gn:country_code":"CO",
    "gn:dem":254,
    "gn:feature_class":"P",
    "gn:feature_code":"PPL",
    "gn:name":"Tierra Grata",
    "gn:population":0,
    "gn:timezone":"America/Bogota",
    "iso:country":"CO",
    "wof:name":"Tierra Grata",
    "wof:placetype":"locality"
},
  "geometry": {"coordinates":[-73.02287,4.56501],"type":"Point"}
}