{
  "type": "Feature",
  "properties": {
    "gn:admin1_code":"29",
    "gn:admin2_code":"76890.0",
    "gn:asciiname":"Campoalegre",
    "gn:country_code":"CO",
    "gn:dem":1480,
    "gn:feature_class":"P",
    "gn:feature_code":"PPL",
    "gn:name":"Campoalegre",
    "gn:population":0,
    "gn:timezone":"America/Bogota",
    "iso:country":"CO",
    "wof:name":"Campoalegre",
    "wof:placetype":"locality"
},
  "geometry": {"coordinates":[-76.36917,3.99806],"type":"Point"}
}