{
  "type": "Feature",
  "properties": {
    "gn:admin1_code":"3",
    "gn:admin2_code":"81001.0",
    "gn:asciiname":"Maracay",
    "gn:country_code":"CO",
    "gn:dem":113,
    "gn:feature_class":"P",
    "gn:feature_code":"PPL",
    "gn:name":"Maracay",
    "gn:population":0,
    "gn:timezone":"America/Bogota",
    "iso:country":"CO",
    "name:spa_x_preferred":[
        "Maracay"
    ],
    "wof:name":"Maracay",
    "wof:placetype":"locality"
},
  "geometry": {"coordinates":[-70.31537,6.87991],"type":"Point"}
}