{
  "type": "Feature",
  "properties": {
    "gn:admin1_code":"3",
    "gn:admin2_code":"81001.0",
    "gn:asciiname":"Maracay",
    "gn:country_code":"CO",
    "gn:dem":113,
    "gn:feature_class":"P",
    "gn:feature_code":"PPL",
    "gn:name":"Maracay",
    "gn:population":0,
    "gn:timezone":"America/Bogota",
    "iso:country":"CO",
    "name:afr_x_preferred":[
        "Maracay"
    ],
    "name:ara_x_preferred":[
        "\u0645\u0627\u0631\u0627\u0643\u0627\u064a"
    ],
    "name:arg_x_preferred":[
        "Maracay"
    ],
    "name:aym_x_preferred":[
        "Marakay"
    ],
    "name:bul_x_preferred":[
        "\u041c\u0430\u0440\u0430\u043a\u0430\u0439"
    ],
    "name:cat_x_preferred":[
        "Maracay"
    ],
    "name:ceb_x_preferred":[
        "Maracay"
    ],
    "name:dan_x_preferred":[
        "Maracay"
    ],
    "name:deu_x_preferred":[
        "Maracay"
    ],
    "name:ell_x_preferred":[
        "\u039c\u03b1\u03c1\u03b1\u03ba\u03ac\u03b9"
    ],
    "name:epo_x_preferred":[
        "Marakajo"
    ],
    "name:eus_x_preferred":[
        "Maracay"
    ],
    "name:fas_x_preferred":[
        "\u0645\u0627\u0631\u0627\u06a9\u0627\u06cc"
    ],
    "name:fin_x_preferred":[
        "Maracay"
    ],
    "name:fra_x_preferred":[
        "Maracay"
    ],
    "name:ita_x_preferred":[
        "Maracay"
    ],
    "name:jpn_x_preferred":[
        "\u30de\u30e9\u30ab\u30a4"
    ],
    "name:kat_x_preferred":[
        "\u10db\u10d0\u10e0\u10d0\u10d9\u10d0\u10d8"
    ],
    "name:kaz_x_preferred":[
        "\u041c\u0430\u0440\u0430\u043a\u0430\u0439"
    ],
    "name:kor_x_preferred":[
        "\ub9c8\ub77c\uce74\uc774"
    ],
    "name:lit_x_preferred":[
        "Marakajus"
    ],
    "name:mdf_x_preferred":[
        "\u041c\u0430\u0440\u0430\u043a\u0430\u0439"
    ],
    "name:nld_x_preferred":[
        "Maracay"
    ],
    "name:nor_x_preferred":[
        "Maracay"
    ],
    "name:oss_x_preferred":[
        "\u041c\u0430\u0440\u0430\u043a\u0430\u0439"
    ],
    "name:pol_x_preferred":[
        "Maracay"
    ],
    "name:por_x_preferred":[
        "Maracay"
    ],
    "name:que_x_preferred":[
        "Marakay"
    ],
    "name:ron_x_preferred":[
        "Maracay"
    ],
    "name:rus_x_preferred":[
        "\u041c\u0430\u0440\u0430\u043a\u0430\u0439"
    ],
    "name:sco_x_preferred":[
        "Maracay"
    ],
    "name:spa_x_preferred":[
        "Maracay"
    ],
    "name:sqi_x_preferred":[
        "Maracay"
    ],
    "name:swe_x_preferred":[
        "Maracay"
    ],
    "name:tat_x_preferred":[
        "\u041c\u0430\u0440\u0430\u043a\u0430\u0439"
    ],
    "name:tur_x_preferred":[
        "Maracay"
    ],
    "name:ukr_x_preferred":[
        "\u041c\u0430\u0440\u0430\u043a\u0430\u0439"
    ],
    "name:urd_x_preferred":[
        "\u0645\u0627\u0631\u0627\u06a9\u0627\u06cc"
    ],
    "name:vep_x_preferred":[
        "Marakai"
    ],
    "name:vie_x_preferred":[
        "Maracay"
    ],
    "name:vol_x_preferred":[
        "Maracay"
    ],
    "name:war_x_preferred":[
        "Maracay"
    ],
    "name:zho_x_preferred":[
        "\u9a6c\u62c9\u51ef"
    ],
    "wof:name":"Maracay",
    "wof:placetype":"locality"
},
  "geometry": {"coordinates":[-70.31537,6.87991],"type":"Point"}
}