{
  "type": "Feature",
  "properties": {
    "gn:admin1_code":"15",
    "gn:admin2_code":"94884.0",
    "gn:asciiname":"Celestino",
    "gn:country_code":"CO",
    "gn:dem":118,
    "gn:feature_class":"P",
    "gn:feature_code":"PPL",
    "gn:name":"Celestino",
    "gn:population":0,
    "gn:timezone":"America/Bogota",
    "iso:country":"CO",
    "wof:name":"Celestino",
    "wof:placetype":"locality"
},
  "geometry": {"coordinates":[-67.65000000000001,2.48333],"type":"Point"}
}