{
  "type": "Feature",
  "properties": {
    "gn:admin1_code":"9.0",
    "gn:admin2_code":"19517.0",
    "gn:asciiname":"Ricaurte",
    "gn:country_code":"CO",
    "gn:dem":1254,
    "gn:feature_class":"P",
    "gn:feature_code":"PPL",
    "gn:name":"Ricaurte",
    "gn:population":0,
    "gn:timezone":"America/Bogota",
    "iso:country":"CO",
    "wof:name":"Ricaurte",
    "wof:placetype":"locality"
},
  "geometry": {"coordinates":[-75.95806999999998,2.52253],"type":"Point"}
}