{
  "type": "Feature",
  "properties": {
    "gn:admin1_code":"20",
    "gn:admin2_code":"52687.0",
    "gn:asciiname":"Charguayaco",
    "gn:country_code":"CO",
    "gn:dem":750,
    "gn:feature_class":"P",
    "gn:feature_code":"PPL",
    "gn:name":"Charguayaco",
    "gn:population":0,
    "gn:timezone":"America/Bogota",
    "iso:country":"CO",
    "name:und_x_variant":[
        "Charquayaco"
    ],
    "wof:name":"Charguayaco",
    "wof:placetype":"locality"
},
  "geometry": {"coordinates":[-77.25539999999999,1.64574],"type":"Point"}
}