{
  "type": "Feature",
  "properties": {
    "gn:admin1_code":"2.0",
    "gn:admin2_code":"5284.0",
    "gn:asciiname":"Las Bocas",
    "gn:country_code":"CO",
    "gn:dem":1415,
    "gn:feature_class":"P",
    "gn:feature_code":"PPL",
    "gn:name":"Las Bocas",
    "gn:population":0,
    "gn:timezone":"America/Bogota",
    "iso:country":"CO",
    "name:cat_x_preferred":[
        "Las Bocas"
    ],
    "name:ita_x_preferred":[
        "Las Bocas"
    ],
    "name:por_x_preferred":[
        "Las Bocas"
    ],
    "name:spa_x_preferred":[
        "Las Bocas"
    ],
    "wof:name":"Las Bocas",
    "wof:placetype":"locality"
},
  "geometry": {"coordinates":[-76.28222,6.66361],"type":"Point"}
}