{
  "type": "Feature",
  "properties": {
    "gn:admin1_code":"17",
    "gn:admin2_code":"44847.0",
    "gn:asciiname":"Aremasahin",
    "gn:country_code":"CO",
    "gn:dem":17,
    "gn:feature_class":"P",
    "gn:feature_code":"PPL",
    "gn:name":"Ar\u00e9masahin",
    "gn:population":0,
    "gn:timezone":"America/Bogota",
    "iso:country":"CO",
    "wof:name":"Aremasahin",
    "wof:placetype":"locality"
},
  "geometry": {"coordinates":[-71.81565999999999,12.1865],"type":"Point"}
}