{
  "type": "Feature",
  "properties": {
    "gn:admin1_code":"21",
    "gn:admin2_code":"54003.0",
    "gn:asciiname":"El Hatico",
    "gn:country_code":"CO",
    "gn:dem":1537,
    "gn:feature_class":"P",
    "gn:feature_code":"PPL",
    "gn:name":"El Hatico",
    "gn:population":0,
    "gn:timezone":"America/Bogota",
    "iso:country":"CO",
    "wof:name":"El Hatico",
    "wof:placetype":"locality"
},
  "geometry": {"coordinates":[-73.15278000000001,8.11722],"type":"Point"}
}