{
  "type": "Feature",
  "properties": {
    "gn:admin1_code":"29.0",
    "gn:admin2_code":"76520.0",
    "gn:asciiname":"Salina",
    "gn:cc2":"CO",
    "gn:country_code":"CO",
    "gn:dem":1468,
    "gn:feature_class":"P",
    "gn:feature_code":"PPL",
    "gn:name":"Salina",
    "gn:population":0,
    "gn:timezone":"America/Bogota",
    "iso:country":"CO",
    "name:und_x_variant":[
        "Salinas",
        "Salina"
    ],
    "wof:name":"Salina",
    "wof:placetype":"locality"
},
  "geometry": {"coordinates":[-76.1225,3.61361],"type":"Point"}
}