{
  "type": "Feature",
  "properties": {
    "iso:country":"CO",
    "name:ast_x_preferred":[
        "Fusagasug\u00e1"
    ],
    "name:cat_x_preferred":[
        "Fusagasug\u00e1"
    ],
    "name:ceb_x_preferred":[
        "Fusagasuga"
    ],
    "name:cym_x_preferred":[
        "Fusagasug\u00e1"
    ],
    "name:dan_x_preferred":[
        "Fusagasug\u00e1"
    ],
    "name:deu_x_preferred":[
        "Fusagasug\u00e1"
    ],
    "name:eng_x_preferred":[
        "Fusagasug\u00e1"
    ],
    "name:fao_x_preferred":[
        "Fusagasug\u00e1"
    ],
    "name:fas_x_preferred":[
        "\u0641\u0648\u0633\u0627\u06af\u0627\u0633\u0648\u06af\u0627"
    ],
    "name:fin_x_preferred":[
        "Fusagasug\u00e1"
    ],
    "name:fra_x_preferred":[
        "Fusagasug\u00e1"
    ],
    "name:glg_x_preferred":[
        "Fusagasug\u00e1"
    ],
    "name:ita_x_preferred":[
        "Fusagasug\u00e1"
    ],
    "name:kal_x_preferred":[
        "Fusagasug\u00e1"
    ],
    "name:kat_x_preferred":[
        "\u10e4\u10e3\u10e1\u10d0\u10d2\u10d0\u10e1\u10e3\u10d2\u10d0"
    ],
    "name:msa_x_preferred":[
        "Fusagasug\u00e1"
    ],
    "name:nan_x_preferred":[
        "Fusagasug\u00e1"
    ],
    "name:nld_x_preferred":[
        "Fusagasug\u00e1"
    ],
    "name:nno_x_preferred":[
        "Fusagasug\u00e1"
    ],
    "name:nob_x_preferred":[
        "Fusagasug\u00e1"
    ],
    "name:por_x_preferred":[
        "Fusagasug\u00e1"
    ],
    "name:rus_x_preferred":[
        "\u0424\u0443\u0441\u0430\u0433\u0430\u0441\u0443\u0433\u0430"
    ],
    "name:spa_x_preferred":[
        "Fusagasug\u00e1"
    ],
    "name:swe_x_preferred":[
        "Fusagasug\u00e1"
    ],
    "name:tgl_x_preferred":[
        "Fusagasug\u00e1"
    ],
    "name:unk_x_variant":[
        "Fusagasuga"
    ],
    "name:vie_x_preferred":[
        "Fusagasug\u00e1"
    ],
    "name:war_x_preferred":[
        "Fusagasug\u00e1"
    ],
    "name:zho_x_preferred":[
        "\u5bcc\u85a9\u52a0\u8607\u52a0"
    ],
    "qs:gn_country":"CO",
    "qs:gn_fcode":"PPL",
    "qs:gn_pop":88820,
    "qs:name":"Fusagasug\u00e1",
    "qs:name_adm0":"Colombia",
    "qs:name_adm1":"Cundinamarca",
    "qs:photos":404,
    "qs:photos_1k":82,
    "qs:photos_9k":2,
    "qs:photos_9r":5,
    "qs:photos_all":404,
    "qs:photos_sr":6,
    "qs:placetype":"Town",
    "qs:pop_sr":"8",
    "qs:woe_adm0":23424787,
    "wof:name":"Fusagasug\u00e1",
    "wof:placetype":"locality",
    "wof:population":88820
},
  "geometry": {"coordinates":[-74.36378000000001,4.33646],"type":"Point"}
}