{
  "type": "Feature",
  "properties": {
    "gn:admin1_code":"27",
    "gn:admin2_code":"70742.0",
    "gn:asciiname":"Matecana",
    "gn:country_code":"CO",
    "gn:dem":129,
    "gn:feature_class":"P",
    "gn:feature_code":"PPL",
    "gn:name":"Mateca\u00f1a",
    "gn:population":0,
    "gn:timezone":"America/Bogota",
    "iso:country":"CO",
    "wof:name":"Matecana",
    "wof:placetype":"locality"
},
  "geometry": {"coordinates":[-75.08095,9.31133],"type":"Point"}
}