{
  "type": "Feature",
  "properties": {
    "gn:admin1_code":"9.0",
    "gn:admin2_code":"19743.0",
    "gn:asciiname":"El Cofre",
    "gn:country_code":"CO",
    "gn:dem":3077,
    "gn:feature_class":"P",
    "gn:feature_code":"PPL",
    "gn:name":"El Cofre",
    "gn:population":0,
    "gn:timezone":"America/Bogota",
    "iso:country":"CO",
    "name:spa_x_preferred":[
        "El Cofre"
    ],
    "wof:name":"El Cofre",
    "wof:placetype":"locality"
},
  "geometry": {"coordinates":[-76.34491,2.5302],"type":"Point"}
}