{
  "type": "Feature",
  "properties": {
    "gn:admin1_code":"12.0",
    "gn:admin2_code":"23162.0",
    "gn:asciiname":"Pueblo de Vieja",
    "gn:country_code":"CO",
    "gn:dem":11,
    "gn:feature_class":"P",
    "gn:feature_code":"PPLL",
    "gn:name":"Pueblo de Vieja",
    "gn:population":0,
    "gn:timezone":"America/Bogota",
    "iso:country":"CO",
    "wof:name":"Pueblo de Vieja",
    "wof:placetype":"locality"
},
  "geometry": {"coordinates":[-75.89305999999998,8.87583],"type":"Point"}
}