{
  "type": "Feature",
  "properties": {
    "iso:country":"CO",
    "name:cat_x_preferred":[
        "Santa Mar\u00eda"
    ],
    "name:chi_x_preferred":[
        "\u8056\u99ac\u91cc\u4e9e"
    ],
    "name:dut_x_preferred":[
        "Santa Mar\u00eda"
    ],
    "name:eng_x_preferred":[
        "Santa Mar\u00eda"
    ],
    "name:fre_x_preferred":[
        "Santa Mar\u00eda"
    ],
    "name:geo_x_preferred":[
        "\u10e1\u10d0\u10dc\u10e2\u10d0-\u10db\u10d0\u10e0\u10d8\u10d0"
    ],
    "name:ita_x_preferred":[
        "Santa Mar\u00eda"
    ],
    "name:may_x_preferred":[
        "Santa Mar\u00eda"
    ],
    "name:nan_x_preferred":[
        "Santa Mar\u00eda"
    ],
    "name:por_x_preferred":[
        "Santa Mar\u00eda"
    ],
    "name:spa_x_preferred":[
        "Santa Mar\u00eda"
    ],
    "name:swe_x_preferred":[
        "Santa Mar\u00eda"
    ],
    "name:tgl_x_preferred":[
        "Santa Mar\u00eda"
    ],
    "name:vie_x_preferred":[
        "Santa Mar\u00eda"
    ],
    "name:war_x_preferred":[
        "Santa Mar\u00eda"
    ],
    "qs:gn_country":"CO",
    "qs:gn_fcode":"PPL",
    "qs:gn_pop":2238,
    "qs:name":"Santa Mar\u00eda",
    "qs:name_adm0":"Colombia",
    "qs:name_adm1":"Boyaca",
    "qs:photos":0,
    "qs:photos_1k":0,
    "qs:photos_9k":1,
    "qs:photos_9r":2,
    "qs:photos_all":43,
    "qs:photos_sr":0,
    "qs:placetype":"Town",
    "qs:pop_sr":"4",
    "qs:woe_adm0":23424787,
    "wof:name":"Santa Mar\u00eda",
    "wof:placetype":"locality",
    "wof:population":2238
},
  "geometry": {"coordinates":[-73.26233999999999,4.86048],"type":"Point"}
}