{
  "type": "Feature",
  "properties": {
    "iso:country":"CO",
    "name:ast_x_preferred":[
        "T\u00e1mesis"
    ],
    "name:avk_x_preferred":[
        "T\u00e1mesis"
    ],
    "name:ceb_x_preferred":[
        "T\u00e1mesis"
    ],
    "name:dan_x_preferred":[
        "T\u00e1mesis"
    ],
    "name:deu_x_preferred":[
        "T\u00e1mesis"
    ],
    "name:eng_x_preferred":[
        "T\u00e1mesis"
    ],
    "name:fao_x_preferred":[
        "T\u00e1mesis"
    ],
    "name:fas_x_preferred":[
        "\u062a\u0627\u0645\u0633\u06cc\u0633\u060c \u0627\u0646\u062a\u06cc\u0648\u06a9\u06cc\u0627"
    ],
    "name:fas_x_variant":[
        "\u062a\u0627\u0645\u0633\u06cc\u0633\u060c \u0627\u0646\u062a\u064a\u0648\u0643\u064a\u0627",
        "\u062a\u0627\u0645\u0633\u06cc\u0633"
    ],
    "name:fra_x_preferred":[
        "T\u00e1mesis"
    ],
    "name:gla_x_preferred":[
        "T\u00e1mesis"
    ],
    "name:gle_x_preferred":[
        "T\u00e1mesis"
    ],
    "name:ile_x_preferred":[
        "T\u00e1mesis"
    ],
    "name:ilo_x_preferred":[
        "T\u00e1mesis"
    ],
    "name:ita_x_preferred":[
        "T\u00e1mesis"
    ],
    "name:kal_x_preferred":[
        "T\u00e1mesis"
    ],
    "name:kat_x_preferred":[
        "\u10e2\u10d0\u10db\u10d4\u10e1\u10d8\u10e1\u10d8"
    ],
    "name:msa_x_preferred":[
        "T\u00e1mesis"
    ],
    "name:nan_x_preferred":[
        "T\u00e1mesis"
    ],
    "name:nld_x_preferred":[
        "T\u00e1mesis"
    ],
    "name:nno_x_preferred":[
        "T\u00e1mesis"
    ],
    "name:nob_x_preferred":[
        "T\u00e1mesis"
    ],
    "name:pol_x_preferred":[
        "T\u00e1mesis"
    ],
    "name:por_x_preferred":[
        "T\u00e1mesis"
    ],
    "name:ron_x_preferred":[
        "T\u00e1mesis"
    ],
    "name:rus_x_preferred":[
        "\u0422\u0430\u043c\u0435\u0441\u0438\u0441"
    ],
    "name:spa_x_preferred":[
        "T\u00e1mesis"
    ],
    "name:swe_x_preferred":[
        "T\u00e1mesis"
    ],
    "name:tgl_x_preferred":[
        "T\u00e1mesis"
    ],
    "name:vie_x_preferred":[
        "T\u00e1mesis"
    ],
    "name:war_x_preferred":[
        "T\u00e1mesis"
    ],
    "name:zho_x_preferred":[
        "\u5854\u6885\u897f\u65af"
    ],
    "qs:gn_country":"CO",
    "qs:gn_fcode":"PPL",
    "qs:gn_pop":6406,
    "qs:name":"T\u00e1mesis",
    "qs:name_adm0":"Colombia",
    "qs:name_adm1":"Antioquia",
    "qs:photos":151,
    "qs:photos_1k":31,
    "qs:photos_9k":1,
    "qs:photos_9r":4,
    "qs:photos_all":151,
    "qs:photos_sr":4,
    "qs:placetype":"Town",
    "qs:pop_sr":"5",
    "qs:woe_adm0":23424787,
    "wd:wordcount":146,
    "wof:name":"T\u00e1mesis",
    "wof:placetype":"locality",
    "wof:population":6406
},
  "geometry": {"coordinates":[-75.71339,5.66462],"type":"Point"}
}