{
  "type": "Feature",
  "properties": {
    "gn:admin1_code":"12",
    "gn:admin2_code":"23189.0",
    "gn:asciiname":"El Higal",
    "gn:country_code":"CO",
    "gn:dem":6,
    "gn:feature_class":"P",
    "gn:feature_code":"PPL",
    "gn:name":"El Higal",
    "gn:population":0,
    "gn:timezone":"America/Bogota",
    "iso:country":"CO",
    "wof:name":"El Higal",
    "wof:placetype":"locality"
},
  "geometry": {"coordinates":[-75.60774000000001,8.96613],"type":"Point"}
}