{
  "type": "Feature",
  "properties": {
    "iso:country":"CO",
    "name:ast_x_preferred":[
        "Sativanorte"
    ],
    "name:ceb_x_preferred":[
        "Sativanorte"
    ],
    "name:eng_x_preferred":[
        "Sativanorte"
    ],
    "name:fra_x_preferred":[
        "Sativanorte"
    ],
    "name:ita_x_preferred":[
        "Sativanorte"
    ],
    "name:kat_x_preferred":[
        "\u10e1\u10d0\u10e2\u10d8\u10d5\u10d0\u10dc\u10dd\u10e0\u10e2\u10d4"
    ],
    "name:msa_x_preferred":[
        "Sativanorte"
    ],
    "name:nan_x_preferred":[
        "Sativanorte"
    ],
    "name:nld_x_preferred":[
        "Sativanorte"
    ],
    "name:por_x_preferred":[
        "Sativanorte"
    ],
    "name:sco_x_preferred":[
        "Sativanorte"
    ],
    "name:spa_x_preferred":[
        "Sativanorte"
    ],
    "name:swe_x_preferred":[
        "Sativanorte"
    ],
    "name:tgl_x_preferred":[
        "Sativanorte"
    ],
    "name:vie_x_preferred":[
        "Sativanorte"
    ],
    "name:war_x_preferred":[
        "Sativanorte"
    ],
    "name:zho_min_nan_x_preferred":[
        "Sativanorte"
    ],
    "name:zho_x_preferred":[
        "\u85a9\u8482\u74e6\u8afe\u7279"
    ],
    "qs:gn_country":"CO",
    "qs:gn_fcode":"PPL",
    "qs:gn_pop":792,
    "qs:name":"Sativanorte",
    "qs:name_adm0":"Colombia",
    "qs:name_adm1":"Boyaca",
    "qs:photos":0,
    "qs:photos_1k":0,
    "qs:photos_9k":0,
    "qs:photos_9r":0,
    "qs:photos_all":0,
    "qs:photos_sr":0,
    "qs:placetype":"Town",
    "qs:pop_sr":"2",
    "qs:woe_adm0":23424787,
    "wd:wordcount":272,
    "wof:name":"Sativanorte",
    "wof:placetype":"locality",
    "wof:population":792
},
  "geometry": {"coordinates":[-72.70895,6.13156],"type":"Point"}
}