{
  "type": "Feature",
  "properties": {
    "gn:admin1_code":"9",
    "gn:admin2_code":"19450.0",
    "gn:asciiname":"Canaveral",
    "gn:country_code":"CO",
    "gn:dem":1327,
    "gn:feature_class":"P",
    "gn:feature_code":"PPL",
    "gn:name":"Ca\u00f1averal",
    "gn:population":0,
    "gn:timezone":"America/Bogota",
    "iso:country":"CO",
    "name:ceb_x_preferred":[
        "Ca\u00f1averal"
    ],
    "name:nld_x_preferred":[
        "Ca\u00f1averal"
    ],
    "name:por_x_preferred":[
        "Canaveral"
    ],
    "name:rus_x_preferred":[
        "\u041a\u0430\u043d\u044c\u044f\u0432\u0435\u0440\u0430\u043b\u044c"
    ],
    "name:spa_x_preferred":[
        "Ca\u00f1averal"
    ],
    "name:swe_x_preferred":[
        "Ca\u00f1averal"
    ],
    "wof:name":"Canaveral",
    "wof:placetype":"locality"
},
  "geometry": {"coordinates":[-77.1832,1.71141],"type":"Point"}
}