{
  "type": "Feature",
  "properties": {
    "gn:admin1_code":"28",
    "gn:admin2_code":"73547.0",
    "gn:asciiname":"El Hato de Doima",
    "gn:cc2":"CO",
    "gn:country_code":"CO",
    "gn:dem":561,
    "gn:feature_class":"P",
    "gn:feature_code":"PPL",
    "gn:name":"El Hato de Doima",
    "gn:population":0,
    "gn:timezone":"America/Bogota",
    "iso:country":"CO",
    "name:und_x_variant":[
        "Doima",
        "El Hato de Doima"
    ],
    "wof:name":"El Hato de Doima",
    "wof:placetype":"locality"
},
  "geometry": {"coordinates":[-74.95,4.45],"type":"Point"}
}