{
  "type": "Feature",
  "properties": {
    "gn:admin1_code":"21",
    "gn:admin2_code":"54206.0",
    "gn:asciiname":"Kantrakuigday-kayra",
    "gn:country_code":"CO",
    "gn:dem":640,
    "gn:feature_class":"P",
    "gn:feature_code":"PPL",
    "gn:name":"Kantrakuigday-kayra",
    "gn:population":0,
    "gn:timezone":"America/Bogota",
    "iso:country":"CO",
    "wof:name":"Kantrakuigday-kayra",
    "wof:placetype":"locality"
},
  "geometry": {"coordinates":[-73.15333000000003,9.00722],"type":"Point"}
}