{
  "type": "Feature",
  "properties": {
    "gn:admin1_code":"3",
    "gn:admin2_code":"81065.0",
    "gn:asciiname":"Babitas",
    "gn:country_code":"CO",
    "gn:dem":168,
    "gn:feature_class":"P",
    "gn:feature_code":"PPL",
    "gn:name":"Babitas",
    "gn:population":0,
    "gn:timezone":"America/Bogota",
    "iso:country":"CO",
    "wof:name":"Babitas",
    "wof:placetype":"locality"
},
  "geometry": {"coordinates":[-71.59591,7.03069],"type":"Point"}
}