{
  "type": "Feature",
  "properties": {
    "gn:admin1_code":"33.0",
    "gn:admin2_code":"25293.0",
    "gn:asciiname":"Hato Grande",
    "gn:country_code":"CO",
    "gn:dem":1864,
    "gn:feature_class":"P",
    "gn:feature_code":"PPL",
    "gn:name":"Hato Grande",
    "gn:population":0,
    "gn:timezone":"America/Bogota",
    "iso:country":"CO",
    "wof:name":"Hato Grande",
    "wof:placetype":"locality"
},
  "geometry": {"coordinates":[-73.52967,4.63282],"type":"Point"}
}