{
  "type": "Feature",
  "properties": {
    "gn:admin1_code":"9.0",
    "gn:admin2_code":"19743.0",
    "gn:asciiname":"El Placer",
    "gn:country_code":"CO",
    "gn:dem":3106,
    "gn:feature_class":"P",
    "gn:feature_code":"PPL",
    "gn:name":"El Placer",
    "gn:population":0,
    "gn:timezone":"America/Bogota",
    "iso:country":"CO",
    "name:spa_x_preferred":[
        "El Placer"
    ],
    "wof:name":"El Placer",
    "wof:placetype":"locality"
},
  "geometry": {"coordinates":[-76.31123000000002,2.74217],"type":"Point"}
}