{
  "type": "Feature",
  "properties": {
    "gn:admin1_code":"19.0",
    "gn:admin2_code":"50325.0",
    "gn:asciiname":"Chiguiro",
    "gn:country_code":"CO",
    "gn:dem":235,
    "gn:feature_class":"P",
    "gn:feature_code":"PPL",
    "gn:name":"Chiguiro",
    "gn:population":0,
    "gn:timezone":"America/Bogota",
    "iso:country":"CO",
    "wof:name":"Chiguiro",
    "wof:placetype":"locality"
},
  "geometry": {"coordinates":[-72.56411,3.20095],"type":"Point"}
}