{
  "type": "Feature",
  "properties": {
    "gn:admin1_code":"36.0",
    "gn:admin2_code":"15667.0",
    "gn:asciiname":"Los Alpes",
    "gn:country_code":"CO",
    "gn:dem":759,
    "gn:feature_class":"P",
    "gn:feature_code":"PPL",
    "gn:name":"Los Alpes",
    "gn:population":0,
    "gn:timezone":"America/Bogota",
    "iso:country":"CO",
    "wof:name":"Los Alpes",
    "wof:placetype":"locality"
},
  "geometry": {"coordinates":[-73.15416999999999,4.85306],"type":"Point"}
}