{
  "type": "Feature",
  "properties": {
    "gn:admin1_code":"33.0",
    "gn:admin2_code":"25322.0",
    "gn:asciiname":"Potosi",
    "gn:country_code":"CO",
    "gn:dem":3056,
    "gn:feature_class":"P",
    "gn:feature_code":"PPL",
    "gn:name":"Potos\u00ed",
    "gn:population":0,
    "gn:timezone":"America/Bogota",
    "iso:country":"CO",
    "name:ceb_x_preferred":[
        "Potosi"
    ],
    "name:dan_x_preferred":[
        "Potosi"
    ],
    "name:deu_x_preferred":[
        "Potosi"
    ],
    "name:fin_x_preferred":[
        "Potosi"
    ],
    "name:ita_x_preferred":[
        "Potosi"
    ],
    "name:rus_x_preferred":[
        "\u041f\u043e\u0442\u043e\u0441\u0438"
    ],
    "name:sco_x_preferred":[
        "Potosi"
    ],
    "name:srp_x_preferred":[
        "\u041f\u043e\u0442\u043e\u0441\u0438"
    ],
    "name:swe_x_preferred":[
        "Potosi"
    ],
    "name:ukr_x_preferred":[
        "\u041f\u043e\u0442\u043e\u0441\u0456"
    ],
    "name:vol_x_preferred":[
        "Potosi"
    ],
    "wof:name":"Potosi",
    "wof:placetype":"locality"
},
  "geometry": {"coordinates":[-73.92021,4.78662],"type":"Point"}
}