{
  "type": "Feature",
  "properties": {
    "gn:admin1_code":"28.0",
    "gn:admin2_code":"73616.0",
    "gn:asciiname":"Boqueron",
    "gn:country_code":"CO",
    "gn:dem":1375,
    "gn:feature_class":"P",
    "gn:feature_code":"PPL",
    "gn:name":"Boquer\u00f3n",
    "gn:population":0,
    "gn:timezone":"America/Bogota",
    "iso:country":"CO",
    "wof:name":"Boqueron",
    "wof:placetype":"locality"
},
  "geometry": {"coordinates":[-75.62666999999998,3.5475],"type":"Point"}
}