{
  "type": "Feature",
  "properties": {
    "gn:admin1_code":"2.0",
    "gn:admin2_code":"5658.0",
    "gn:asciiname":"El Otro Lado",
    "gn:country_code":"CO",
    "gn:dem":2598,
    "gn:feature_class":"P",
    "gn:feature_code":"PPL",
    "gn:name":"El Otro Lado",
    "gn:population":0,
    "gn:timezone":"America/Bogota",
    "iso:country":"CO",
    "wof:name":"El Otro Lado",
    "wof:placetype":"locality"
},
  "geometry": {"coordinates":[-75.67333000000001,6.85139],"type":"Point"}
}