{
  "type": "Feature",
  "properties": {
    "gn:admin1_code":"12",
    "gn:admin2_code":"23001.0",
    "gn:asciiname":"La Hermosa",
    "gn:country_code":"CO",
    "gn:dem":57,
    "gn:feature_class":"P",
    "gn:feature_code":"PPL",
    "gn:name":"La Hermosa",
    "gn:population":0,
    "gn:timezone":"America/Bogota",
    "iso:country":"CO",
    "wof:name":"La Hermosa",
    "wof:placetype":"locality"
},
  "geometry": {"coordinates":[-76.11111,8.64472],"type":"Point"}
}