{
  "type": "Feature",
  "properties": {
    "gn:admin1_code":"2",
    "gn:admin2_code":"5585.0",
    "gn:asciiname":"Puerto Antares Mula",
    "gn:country_code":"CO",
    "gn:dem":134,
    "gn:feature_class":"P",
    "gn:feature_code":"PPL",
    "gn:name":"Puerto Antares Mula",
    "gn:population":0,
    "gn:timezone":"America/Bogota",
    "iso:country":"CO",
    "wof:name":"Puerto Antares Mula",
    "wof:placetype":"locality"
},
  "geometry": {"coordinates":[-74.61499999999999,6.10528],"type":"Point"}
}