{
  "type": "Feature",
  "properties": {
    "gn:admin1_code":"3",
    "gn:admin2_code":"81001.0",
    "gn:asciiname":"El Ceibote",
    "gn:country_code":"CO",
    "gn:dem":133,
    "gn:feature_class":"P",
    "gn:feature_code":"PPL",
    "gn:name":"El Ceibote",
    "gn:population":0,
    "gn:timezone":"America/Bogota",
    "iso:country":"CO",
    "wof:name":"El Ceibote",
    "wof:placetype":"locality"
},
  "geometry": {"coordinates":[-70.94718,6.97008],"type":"Point"}
}