{
  "type": "Feature",
  "properties": {
    "gn:admin1_code":"35",
    "gn:admin2_code":"13433.0",
    "gn:asciiname":"Evitar",
    "gn:country_code":"CO",
    "gn:dem":6,
    "gn:feature_class":"P",
    "gn:feature_code":"PPL",
    "gn:name":"Evitar",
    "gn:population":0,
    "gn:timezone":"America/Bogota",
    "iso:country":"CO",
    "wof:name":"Evitar",
    "wof:placetype":"locality"
},
  "geometry": {"coordinates":[-75.15614000000002,10.27031],"type":"Point"}
}