{
  "type": "Feature",
  "properties": {
    "gn:admin1_code":"2.0",
    "gn:admin2_code":"5138.0",
    "gn:asciiname":"Media Cuesta",
    "gn:country_code":"CO",
    "gn:dem":1798,
    "gn:feature_class":"P",
    "gn:feature_code":"PPL",
    "gn:name":"Media Cuesta",
    "gn:population":0,
    "gn:timezone":"America/Bogota",
    "iso:country":"CO",
    "wof:name":"Media Cuesta",
    "wof:placetype":"locality"
},
  "geometry": {"coordinates":[-76.04722,6.74361],"type":"Point"}
}