{
  "type": "Feature",
  "properties": {
    "gn:admin1_code":"12.0",
    "gn:asciiname":"Neiva",
    "gn:country_code":"CO",
    "gn:dem":98,
    "gn:feature_class":"P",
    "gn:feature_code":"PPL",
    "gn:name":"Neiva",
    "gn:population":0,
    "gn:timezone":"America/Bogota",
    "iso:country":"CO",
    "wof:name":"Neiva",
    "wof:placetype":"locality"
},
  "geometry": {"coordinates":[-75.31901999999999,8.69787],"type":"Point"}
}