{
  "type": "Feature",
  "properties": {
    "iso:country":"CO",
    "name:ast_x_preferred":[
        "Bel\u00e9n"
    ],
    "name:avk_x_preferred":[
        "Bel\u00e9n"
    ],
    "name:ceb_x_preferred":[
        "Bel\u00e9n"
    ],
    "name:eng_x_preferred":[
        "Bel\u00e9n"
    ],
    "name:fas_x_preferred":[
        "\u0628\u0644\u0646"
    ],
    "name:fra_x_preferred":[
        "Bel\u00e9n"
    ],
    "name:gle_x_preferred":[
        "Bel\u00e9n"
    ],
    "name:ita_x_preferred":[
        "Bel\u00e9n"
    ],
    "name:kat_x_preferred":[
        "\u10d1\u10d4\u10da\u10d4\u10dc\u10d8"
    ],
    "name:msa_x_preferred":[
        "Bel\u00e9n"
    ],
    "name:nan_x_preferred":[
        "Bel\u00e9n"
    ],
    "name:nld_x_preferred":[
        "Bel\u00e9n"
    ],
    "name:pol_x_preferred":[
        "Bel\u00e9n"
    ],
    "name:por_x_preferred":[
        "Bel\u00e9n"
    ],
    "name:spa_x_preferred":[
        "Bel\u00e9n"
    ],
    "name:swe_x_preferred":[
        "Bel\u00e9n"
    ],
    "name:tgl_x_preferred":[
        "Bel\u00e9n"
    ],
    "name:vie_x_preferred":[
        "Bel\u00e9n"
    ],
    "name:war_x_preferred":[
        "Bel\u00e9n"
    ],
    "name:zho_x_preferred":[
        "\u8c9d\u502b"
    ],
    "qs:gn_country":"CO",
    "qs:gn_fcode":"PPL",
    "qs:gn_pop":3131,
    "qs:name":"Bel\u00e9n",
    "qs:name_adm0":"Colombia",
    "qs:name_adm1":"Narino",
    "qs:photos":0,
    "qs:photos_1k":0,
    "qs:photos_9k":0,
    "qs:photos_9r":0,
    "qs:photos_all":0,
    "qs:photos_sr":0,
    "qs:placetype":"Town",
    "qs:pop_sr":"4",
    "qs:woe_adm0":23424787,
    "wd:wordcount":30,
    "wof:name":"Bel\u00e9n",
    "wof:placetype":"locality",
    "wof:population":3131
},
  "geometry": {"coordinates":[-77.01399000000001,1.59787],"type":"Point"}
}