{
  "type": "Feature",
  "properties": {
    "gn:admin1_code":"29",
    "gn:admin2_code":"76834.0",
    "gn:asciiname":"Agua Clara",
    "gn:country_code":"CO",
    "gn:dem":954,
    "gn:feature_class":"P",
    "gn:feature_code":"PPL",
    "gn:name":"Agua Clara",
    "gn:population":0,
    "gn:timezone":"America/Bogota",
    "iso:country":"CO",
    "wof:name":"Agua Clara",
    "wof:placetype":"locality"
},
  "geometry": {"coordinates":[-76.19444,4.11583],"type":"Point"}
}