{
  "type": "Feature",
  "properties": {
    "gn:admin1_code":"33",
    "gn:admin2_code":"25885.0",
    "gn:asciiname":"La Primavera",
    "gn:country_code":"CO",
    "gn:dem":225,
    "gn:feature_class":"P",
    "gn:feature_code":"PPL",
    "gn:name":"La Primavera",
    "gn:population":0,
    "gn:timezone":"America/Bogota",
    "iso:country":"CO",
    "wof:name":"La Primavera",
    "wof:placetype":"locality"
},
  "geometry": {"coordinates":[-74.38916999999999,5.77917],"type":"Point"}
}