{
  "type": "Feature",
  "properties": {
    "gn:admin1_code":"36",
    "gn:admin2_code":"15759.0",
    "gn:asciiname":"Las Cintas",
    "gn:country_code":"CO",
    "gn:dem":3311,
    "gn:feature_class":"P",
    "gn:feature_code":"PPL",
    "gn:name":"Las Cintas",
    "gn:population":0,
    "gn:timezone":"America/Bogota",
    "iso:country":"CO",
    "wof:name":"Las Cintas",
    "wof:placetype":"locality"
},
  "geometry": {"coordinates":[-72.87626999999998,5.61555],"type":"Point"}
}