{
  "type": "Feature",
  "properties": {
    "gn:admin1_code":"28.0",
    "gn:admin2_code":"73483.0",
    "gn:asciiname":"El Hobo",
    "gn:country_code":"CO",
    "gn:dem":969,
    "gn:feature_class":"P",
    "gn:feature_code":"PPL",
    "gn:name":"El Hobo",
    "gn:population":0,
    "gn:timezone":"America/Bogota",
    "iso:country":"CO",
    "wof:name":"El Hobo",
    "wof:placetype":"locality"
},
  "geometry": {"coordinates":[-75.21389000000001,3.60861],"type":"Point"}
}