{
  "type": "Feature",
  "properties": {
    "gn:admin1_code":"36",
    "gn:admin2_code":"15764.0",
    "gn:asciiname":"Chaine",
    "gn:country_code":"CO",
    "gn:dem":3082,
    "gn:feature_class":"P",
    "gn:feature_code":"PPL",
    "gn:name":"Chaine",
    "gn:population":0,
    "gn:timezone":"America/Bogota",
    "iso:country":"CO",
    "wof:name":"Chaine",
    "wof:placetype":"locality"
},
  "geometry": {"coordinates":[-73.28282,5.51516],"type":"Point"}
}