{
  "type": "Feature",
  "properties": {
    "gn:admin1_code":"12.0",
    "gn:admin2_code":"23672.0",
    "gn:asciiname":"Puerto de Soledad",
    "gn:country_code":"CO",
    "gn:dem":12,
    "gn:feature_class":"P",
    "gn:feature_code":"PPL",
    "gn:name":"Puerto de Soledad",
    "gn:population":0,
    "gn:timezone":"America/Bogota",
    "iso:country":"CO",
    "name:und_x_variant":[
        "Soledad",
        "Puerto de Soledad"
    ],
    "wof:name":"Puerto de Soledad",
    "wof:placetype":"locality"
},
  "geometry": {"coordinates":[-75.85081,9.33722],"type":"Point"}
}