{
  "type": "Feature",
  "properties": {
    "gn:admin1_code":"33.0",
    "gn:admin2_code":"25320.0",
    "gn:asciiname":"Matadero",
    "gn:country_code":"CO",
    "gn:dem":988,
    "gn:feature_class":"P",
    "gn:feature_code":"PPL",
    "gn:name":"Matadero",
    "gn:population":0,
    "gn:timezone":"America/Bogota",
    "iso:country":"CO",
    "name:spa_x_preferred":[
        "Matadero"
    ],
    "wof:name":"Matadero",
    "wof:placetype":"locality"
},
  "geometry": {"coordinates":[-74.59735999999999,5.07884],"type":"Point"}
}