{
  "type": "Feature",
  "properties": {
    "gn:admin1_code":"16",
    "gn:admin2_code":"41001.0",
    "gn:asciiname":"Los Blanquitos",
    "gn:country_code":"CO",
    "gn:dem":891,
    "gn:feature_class":"P",
    "gn:feature_code":"PPL",
    "gn:name":"Los Blanquitos",
    "gn:population":0,
    "gn:timezone":"America/Bogota",
    "iso:country":"CO",
    "wof:name":"Los Blanquitos",
    "wof:placetype":"locality"
},
  "geometry": {"coordinates":[-75.39974000000002,3.08891],"type":"Point"}
}