{
  "type": "Feature",
  "properties": {
    "gn:admin1_code":"29.0",
    "gn:admin2_code":"76622.0",
    "gn:asciiname":"El Palmar",
    "gn:country_code":"CO",
    "gn:dem":912,
    "gn:feature_class":"P",
    "gn:feature_code":"PPL",
    "gn:name":"El Palmar",
    "gn:population":0,
    "gn:timezone":"America/Bogota",
    "iso:country":"CO",
    "wof:name":"El Palmar",
    "wof:placetype":"locality"
},
  "geometry": {"coordinates":[-76.10916999999998,4.4025],"type":"Point"}
}