{
  "type": "Feature",
  "properties": {
    "gn:admin1_code":"11",
    "gn:admin2_code":"27495.0",
    "gn:asciiname":"Jurubida",
    "gn:country_code":"CO",
    "gn:dem":3,
    "gn:feature_class":"P",
    "gn:feature_code":"PPL",
    "gn:name":"Jurubid\u00e1",
    "gn:population":0,
    "gn:timezone":"America/Bogota",
    "iso:country":"CO",
    "name:und_x_variant":[
        "Juruvid\u00e1",
        "Jurubid\u00e1"
    ],
    "wof:name":"Jurubida",
    "wof:placetype":"locality"
},
  "geometry": {"coordinates":[-77.27741999999998,5.84433],"type":"Point"}
}