{
  "type": "Feature",
  "properties": {
    "iso:country":"CO",
    "qs:gn_country":"CO",
    "qs:gn_fcode":"PPL",
    "qs:gn_pop":0,
    "qs:name":"Cumaca",
    "qs:name_adm0":"Colombia",
    "qs:name_adm1":"Cundinamarca",
    "qs:photos":45,
    "qs:photos_1k":9,
    "qs:photos_9k":1,
    "qs:photos_9r":2,
    "qs:photos_all":45,
    "qs:photos_sr":2,
    "qs:placetype":"Town",
    "qs:pop_sr":"0",
    "qs:woe_adm0":23424787,
    "wof:name":"Cumaca",
    "wof:placetype":"locality"
},
  "geometry": {"coordinates":[-74.46947,4.33656],"type":"Point"}
}