{
  "type": "Feature",
  "properties": {
    "gn:admin1_code":"11.0",
    "gn:admin2_code":"27745.0",
    "gn:asciiname":"La Loma",
    "gn:country_code":"CO",
    "gn:dem":26,
    "gn:feature_class":"P",
    "gn:feature_code":"PPLL",
    "gn:name":"La Loma",
    "gn:population":0,
    "gn:timezone":"America/Bogota",
    "iso:country":"CO",
    "name:ceb_x_preferred":[
        "La Loma"
    ],
    "name:deu_x_preferred":[
        "La Loma"
    ],
    "name:spa_x_preferred":[
        "La Loma"
    ],
    "name:srp_x_preferred":[
        "\u041b\u0430 \u041b\u043e\u043c\u0430"
    ],
    "name:swe_x_preferred":[
        "La Loma"
    ],
    "wof:name":"La Loma",
    "wof:placetype":"locality"
},
  "geometry": {"coordinates":[-76.74056,4.6849],"type":"Point"}
}