{
  "type": "Feature",
  "properties": {
    "gn:admin1_code":"29",
    "gn:admin2_code":"76109.0",
    "gn:asciiname":"Llanobajo",
    "gn:cc2":"CO",
    "gn:country_code":"CO",
    "gn:dem":45,
    "gn:feature_class":"P",
    "gn:feature_code":"PPL",
    "gn:name":"Llanobajo",
    "gn:population":0,
    "gn:timezone":"America/Bogota",
    "iso:country":"CO",
    "name:und_x_variant":[
        "Llano Abajo",
        "Llanobajo"
    ],
    "wof:name":"Llanobajo",
    "wof:placetype":"locality"
},
  "geometry": {"coordinates":[-76.95694,3.69861],"type":"Point"}
}