{
  "type": "Feature",
  "properties": {
    "gn:admin1_code":"10",
    "gn:admin2_code":"20621.0",
    "gn:asciiname":"Sabana Alta",
    "gn:country_code":"CO",
    "gn:dem":82,
    "gn:feature_class":"P",
    "gn:feature_code":"PPL",
    "gn:name":"Sabana Alta",
    "gn:population":0,
    "gn:timezone":"America/Bogota",
    "iso:country":"CO",
    "wof:name":"Sabana Alta",
    "wof:placetype":"locality"
},
  "geometry": {"coordinates":[-73.48948,9.92818],"type":"Point"}
}