{
  "type": "Feature",
  "properties": {
    "gn:admin1_code":"16",
    "gn:admin2_code":"41001",
    "gn:asciiname":"El Charco del Diablo",
    "gn:country_code":"CO",
    "gn:dem":643,
    "gn:feature_class":"P",
    "gn:feature_code":"PPL",
    "gn:name":"El Charco del Diablo",
    "gn:population":0,
    "gn:timezone":"America/Bogota",
    "iso:country":"CO",
    "name:spa_x_preferred":[
        "El Charco del Diablo"
    ],
    "wof:name":"El Charco del Diablo",
    "wof:placetype":"locality"
},
  "geometry": {"coordinates":[-75.15248000000003,2.94435],"type":"Point"}
}