{
  "type": "Feature",
  "properties": {
    "gn:admin1_code":"12",
    "gn:admin2_code":"23555.0",
    "gn:asciiname":"Los Manguitos",
    "gn:country_code":"CO",
    "gn:dem":79,
    "gn:feature_class":"P",
    "gn:feature_code":"PPL",
    "gn:name":"Los Manguitos",
    "gn:population":0,
    "gn:timezone":"America/Bogota",
    "iso:country":"CO",
    "wof:name":"Los Manguitos",
    "wof:placetype":"locality"
},
  "geometry": {"coordinates":[-75.56916,8.37404],"type":"Point"}
}