{
  "type": "Feature",
  "properties": {
    "gn:admin1_code":"25",
    "gn:asciiname":"McBeans",
    "gn:country_code":"CO",
    "gn:dem":-9999,
    "gn:feature_class":"P",
    "gn:feature_code":"PPL",
    "gn:name":"McBeans",
    "gn:population":0,
    "gn:timezone":"America/Bogota",
    "iso:country":"CO",
    "wof:name":"McBeans",
    "wof:placetype":"locality"
},
  "geometry": {"coordinates":[-81.34999999999999,13.36667],"type":"Point"}
}