{
  "type": "Feature",
  "properties": {
    "gn:admin1_code":"20.0",
    "gn:admin2_code":"52835.0",
    "gn:asciiname":"Bocas de Pilbi",
    "gn:country_code":"CO",
    "gn:dem":34,
    "gn:feature_class":"P",
    "gn:feature_code":"PPLL",
    "gn:name":"Bocas de Pilb\u00ed",
    "gn:population":0,
    "gn:timezone":"America/Bogota",
    "iso:country":"CO",
    "wof:name":"Bocas de Pilbi",
    "wof:placetype":"locality"
},
  "geometry": {"coordinates":[-78.47481999999999,1.68922],"type":"Point"}
}