{
  "type": "Feature",
  "properties": {
    "gn:admin1_code":"38",
    "gn:admin2_code":"47692.0",
    "gn:asciiname":"La Independencia",
    "gn:country_code":"CO",
    "gn:dem":92,
    "gn:feature_class":"P",
    "gn:feature_code":"PPL",
    "gn:name":"La Independencia",
    "gn:population":0,
    "gn:timezone":"America/Bogota",
    "iso:country":"CO",
    "name:und_x_variant":[
        "La Indepencia",
        "La Independencia"
    ],
    "wof:name":"La Independencia",
    "wof:placetype":"locality"
},
  "geometry": {"coordinates":[-74.13346999999997,9.43482],"type":"Point"}
}