{
  "type": "Feature",
  "properties": {
    "gn:admin1_code":"19.0",
    "gn:admin2_code":"50330.0",
    "gn:asciiname":"Inspeccion de Policia El Mirador",
    "gn:country_code":"CO",
    "gn:dem":991,
    "gn:feature_class":"P",
    "gn:feature_code":"PPL",
    "gn:name":"Inspecci\u00f3n de Polic\u00eda El Mirador",
    "gn:population":0,
    "gn:timezone":"America/Bogota",
    "iso:country":"CO",
    "wof:name":"Inspeccion de Policia El Mirador",
    "wof:placetype":"locality"
},
  "geometry": {"coordinates":[-74.12666999999998,3.41256],"type":"Point"}
}