{
  "type": "Feature",
  "properties": {
    "gn:admin1_code":"36.0",
    "gn:admin2_code":"15667.0",
    "gn:asciiname":"Arrayanes",
    "gn:country_code":"CO",
    "gn:dem":381,
    "gn:feature_class":"P",
    "gn:feature_code":"PPL",
    "gn:name":"Arrayanes",
    "gn:population":0,
    "gn:timezone":"America/Bogota",
    "iso:country":"CO",
    "wof:name":"Arrayanes",
    "wof:placetype":"locality"
},
  "geometry": {"coordinates":[-73.18584,4.81569],"type":"Point"}
}