{
  "type": "Feature",
  "properties": {
    "gn:admin1_code":"38",
    "gn:admin2_code":"47318.0",
    "gn:asciiname":"Cano de Palma",
    "gn:cc2":"CO",
    "gn:country_code":"CO",
    "gn:dem":80,
    "gn:feature_class":"P",
    "gn:feature_code":"PPL",
    "gn:name":"Ca\u00f1o de Palma",
    "gn:population":0,
    "gn:timezone":"America/Bogota",
    "iso:country":"CO",
    "name:und_x_variant":[
        "Hacienda Ca\u00f1o de Palma",
        "Ca\u00f1o de Palma"
    ],
    "wof:name":"Cano de Palma",
    "wof:placetype":"locality"
},
  "geometry": {"coordinates":[-74.01666999999998,9.36667],"type":"Point"}
}