{
  "type": "Feature",
  "properties": {
    "gn:admin1_code":"16.0",
    "gn:admin2_code":"41013.0",
    "gn:asciiname":"Albania",
    "gn:country_code":"CO",
    "gn:dem":769,
    "gn:feature_class":"P",
    "gn:feature_code":"PPL",
    "gn:name":"Albania",
    "gn:population":0,
    "gn:timezone":"America/Bogota",
    "iso:country":"CO",
    "wof:name":"Albania",
    "wof:placetype":"locality"
},
  "geometry": {"coordinates":[-75.7075,2.27361],"type":"Point"}
}