{
  "type": "Feature",
  "properties": {
    "iso:country":"CO",
    "name:eng_x_preferred":[
        "Santiago"
    ],
    "name:fra_x_preferred":[
        "Santiago"
    ],
    "name:ita_x_preferred":[
        "Santiago"
    ],
    "name:kat_x_preferred":[
        "\u10e1\u10d0\u10dc\u10e2\u10d8\u10d0\u10d2\u10dd"
    ],
    "name:msa_x_preferred":[
        "Santiago"
    ],
    "name:nan_x_preferred":[
        "Santiago"
    ],
    "name:nld_x_preferred":[
        "Santiago"
    ],
    "name:por_x_preferred":[
        "Santiago"
    ],
    "name:sco_x_preferred":[
        "Santiago"
    ],
    "name:spa_x_preferred":[
        "Santiago"
    ],
    "name:swe_x_preferred":[
        "Santiago"
    ],
    "name:tgl_x_preferred":[
        "Santiago"
    ],
    "name:vie_x_preferred":[
        "Santiago"
    ],
    "name:war_x_preferred":[
        "Santiago"
    ],
    "name:zho_x_preferred":[
        "\u8056\u5730\u7259\u54e5"
    ],
    "qs:gn_country":"CO",
    "qs:gn_fcode":"PPL",
    "qs:gn_pop":1032,
    "qs:name":"Santiago",
    "qs:name_adm0":"Colombia",
    "qs:name_adm1":"Norte de Santander",
    "qs:photos":0,
    "qs:photos_1k":0,
    "qs:photos_9k":0,
    "qs:photos_9r":0,
    "qs:photos_all":0,
    "qs:photos_sr":0,
    "qs:placetype":"Town",
    "qs:pop_sr":"3",
    "qs:woe_adm0":23424787,
    "wof:name":"Santiago",
    "wof:placetype":"locality",
    "wof:population":1032
},
  "geometry": {"coordinates":[-72.7162,7.86432],"type":"Point"}
}