{
  "type": "Feature",
  "properties": {
    "iso:country":"CO",
    "name:ara_x_preferred":[
        "\u0633\u0627\u0646\u062a\u064a\u0627\u063a\u0648"
    ],
    "name:ast_x_preferred":[
        "Santiago"
    ],
    "name:ben_x_preferred":[
        "\u09b8\u09be\u09a8\u09cd\u09a4\u09bf\u09af\u09bc\u09be\u0997\u09cb"
    ],
    "name:ceb_x_preferred":[
        "Santiago"
    ],
    "name:deu_x_preferred":[
        "Santiago"
    ],
    "name:ell_x_preferred":[
        "\u03a3\u03b1\u03bd\u03c4\u03b9\u03ac\u03b3\u03bf"
    ],
    "name:eng_x_preferred":[
        "Santiago"
    ],
    "name:fas_x_preferred":[
        "\u0633\u0627\u0646\u062a\u06cc\u0627\u06af\u0648"
    ],
    "name:fra_x_preferred":[
        "Santiago"
    ],
    "name:heb_x_preferred":[
        "\u05e1\u05e0\u05d8\u05d9\u05d0\u05d2\u05d5"
    ],
    "name:hin_x_preferred":[
        "\u0938\u0947\u0902\u091f\u093f\u092f\u093e\u0917\u094b"
    ],
    "name:hun_x_preferred":[
        "Santiago"
    ],
    "name:ind_x_preferred":[
        "Santiago"
    ],
    "name:ita_x_preferred":[
        "Santiago"
    ],
    "name:jpn_x_preferred":[
        "\u30b5\u30f3\u30c6\u30a3\u30a2\u30b4"
    ],
    "name:kat_x_preferred":[
        "\u10e1\u10d0\u10dc\u10e2\u10d8\u10d0\u10d2\u10dd"
    ],
    "name:kor_x_preferred":[
        "\uc0b0\ud2f0\uc544\uace0"
    ],
    "name:msa_x_preferred":[
        "Santiago"
    ],
    "name:nan_x_preferred":[
        "Santiago"
    ],
    "name:nld_x_preferred":[
        "Santiago"
    ],
    "name:pol_x_preferred":[
        "Santiago"
    ],
    "name:por_x_preferred":[
        "Santiago"
    ],
    "name:rus_x_preferred":[
        "\u0440\u0435\u043a\u0430 \u0421\u0430\u043d\u0442\u044c\u044f\u0433\u043e"
    ],
    "name:sco_x_preferred":[
        "Santiago"
    ],
    "name:spa_x_preferred":[
        "Santiago"
    ],
    "name:swe_x_preferred":[
        "Rio Santiago"
    ],
    "name:swe_x_variant":[
        "Santiago"
    ],
    "name:tgl_x_preferred":[
        "Santiago"
    ],
    "name:tur_x_preferred":[
        "Santiago"
    ],
    "name:ukr_x_preferred":[
        "\u0421\u0430\u043d\u0442\u044c\u044f\u0433\u043e"
    ],
    "name:urd_x_preferred":[
        "\u0633\u0627\u0646\u062a\u06cc\u0627\u06af\u0648"
    ],
    "name:vie_x_preferred":[
        "Santiago"
    ],
    "name:war_x_preferred":[
        "Santiago"
    ],
    "name:zho_cn_x_preferred":[
        "\u5723\u5730\u4e9a\u54e5\u6cb3"
    ],
    "name:zho_tw_x_preferred":[
        "\u8056\u5730\u7259\u54e5"
    ],
    "name:zho_x_preferred":[
        "\u8056\u5730\u7259\u54e5"
    ],
    "qs:gn_country":"CO",
    "qs:gn_fcode":"PPL",
    "qs:gn_pop":1032,
    "qs:name":"Santiago",
    "qs:name_adm0":"Colombia",
    "qs:name_adm1":"Norte de Santander",
    "qs:photos":0,
    "qs:photos_1k":0,
    "qs:photos_9k":0,
    "qs:photos_9r":0,
    "qs:photos_all":0,
    "qs:photos_sr":0,
    "qs:placetype":"Town",
    "qs:pop_sr":"3",
    "qs:woe_adm0":23424787,
    "wof:name":"Santiago",
    "wof:placetype":"locality",
    "wof:population":1032
},
  "geometry": {"coordinates":[-72.7162,7.86432],"type":"Point"}
}