{
  "type": "Feature",
  "properties": {
    "gn:admin1_code":"35.0",
    "gn:admin2_code":"13006.0",
    "gn:asciiname":"Tres Cruces",
    "gn:country_code":"CO",
    "gn:dem":21,
    "gn:feature_class":"P",
    "gn:feature_code":"PPL",
    "gn:name":"Tres Cruces",
    "gn:population":0,
    "gn:timezone":"America/Bogota",
    "iso:country":"CO",
    "name:cat_x_preferred":[
        "Tres Cruces"
    ],
    "name:deu_x_preferred":[
        "Tres Cruces"
    ],
    "name:spa_x_preferred":[
        "Tres Cruces"
    ],
    "name:und_x_variant":[
        "Corregimiento Tres Cruces"
    ],
    "wof:name":"Tres Cruces",
    "wof:placetype":"locality"
},
  "geometry": {"coordinates":[-74.51659000000002,8.70278],"type":"Point"}
}