{
  "type": "Feature",
  "properties": {
    "gn:admin1_code":"3.0",
    "gn:admin2_code":"81001.0",
    "gn:asciiname":"Todos Los Santos",
    "gn:country_code":"CO",
    "gn:dem":140,
    "gn:feature_class":"P",
    "gn:feature_code":"PPL",
    "gn:name":"Todos Los Santos",
    "gn:population":0,
    "gn:timezone":"America/Bogota",
    "iso:country":"CO",
    "wof:name":"Todos Los Santos",
    "wof:placetype":"locality"
},
  "geometry": {"coordinates":[-70.94955999999998,7.00586],"type":"Point"}
}