{
  "type": "Feature",
  "properties": {
    "gn:admin1_code":"28",
    "gn:admin2_code":"73168.0",
    "gn:asciiname":"Balcones",
    "gn:country_code":"CO",
    "gn:dem":2513,
    "gn:feature_class":"P",
    "gn:feature_code":"PPL",
    "gn:name":"Balcones",
    "gn:population":0,
    "gn:timezone":"America/Bogota",
    "iso:country":"CO",
    "wof:name":"Balcones",
    "wof:placetype":"locality"
},
  "geometry": {"coordinates":[-75.76416999999999,3.91833],"type":"Point"}
}