{
  "type": "Feature",
  "properties": {
    "gn:admin1_code":"19",
    "gn:admin2_code":"50689.0",
    "gn:asciiname":"El Cono",
    "gn:country_code":"CO",
    "gn:dem":210,
    "gn:feature_class":"P",
    "gn:feature_code":"PPL",
    "gn:name":"El Cono",
    "gn:population":0,
    "gn:timezone":"America/Bogota",
    "iso:country":"CO",
    "wof:name":"El Cono",
    "wof:placetype":"locality"
},
  "geometry": {"coordinates":[-72.61667,3.51667],"type":"Point"}
}