{
  "type": "Feature",
  "properties": {
    "gn:admin1_code":"22.0",
    "gn:admin2_code":"86571.0",
    "gn:asciiname":"La Punta",
    "gn:country_code":"CO",
    "gn:dem":276,
    "gn:feature_class":"P",
    "gn:feature_code":"PPL",
    "gn:name":"La Punta",
    "gn:population":0,
    "gn:timezone":"America/Bogota",
    "iso:country":"CO",
    "wof:name":"La Punta",
    "wof:placetype":"locality"
},
  "geometry": {"coordinates":[-76.40343,0.90087],"type":"Point"}
}