{
  "type": "Feature",
  "properties": {
    "gn:admin1_code":"29.0",
    "gn:admin2_code":"76622.0",
    "gn:asciiname":"Morelia",
    "gn:cc2":"CO",
    "gn:country_code":"CO",
    "gn:dem":936,
    "gn:feature_class":"P",
    "gn:feature_code":"PPL",
    "gn:name":"Morelia",
    "gn:population":0,
    "gn:timezone":"America/Bogota",
    "iso:country":"CO",
    "name:und_x_variant":[
        "Higuer\u00f3n",
        "Morelia"
    ],
    "wof:name":"Morelia",
    "wof:placetype":"locality"
},
  "geometry": {"coordinates":[-76.11721999999997,4.48111],"type":"Point"}
}