{
  "type": "Feature",
  "properties": {
    "gn:admin1_code":"1.0",
    "gn:admin2_code":"91669.0",
    "gn:asciiname":"Pama",
    "gn:country_code":"CO",
    "gn:dem":100,
    "gn:feature_class":"P",
    "gn:feature_code":"PPL",
    "gn:name":"Pam\u00e1",
    "gn:population":0,
    "gn:timezone":"America/Bogota",
    "iso:country":"CO",
    "name:ceb_x_preferred":[
        "Pama"
    ],
    "name:deu_x_preferred":[
        "Pama"
    ],
    "name:fra_x_preferred":[
        "Pama"
    ],
    "name:ita_x_preferred":[
        "Pama"
    ],
    "name:kor_x_preferred":[
        "\ud30c\ub9c8"
    ],
    "name:nld_x_preferred":[
        "Pama"
    ],
    "name:pol_x_preferred":[
        "Pama"
    ],
    "name:swe_x_preferred":[
        "Pama"
    ],
    "wof:name":"Pama",
    "wof:placetype":"locality"
},
  "geometry": {"coordinates":[-71.3528,-1.50693],"type":"Point"}
}