{
  "type": "Feature",
  "properties": {
    "gn:admin1_code":"10.0",
    "gn:asciiname":"San Jose de Ariguani",
    "gn:country_code":"CO",
    "gn:dem":61,
    "gn:feature_class":"P",
    "gn:feature_code":"PPL",
    "gn:name":"San Jos\u00e9 de Ariguan\u00ed",
    "gn:population":0,
    "gn:timezone":"America/Bogota",
    "iso:country":"CO",
    "wof:name":"San Jose de Ariguani",
    "wof:placetype":"locality"
},
  "geometry": {"coordinates":[-73.95899,9.92939],"type":"Point"}
}