{
  "type": "Feature",
  "properties": {
    "gn:admin1_code":"17",
    "gn:admin2_code":"44847.0",
    "gn:asciiname":"Kasimesh",
    "gn:country_code":"CO",
    "gn:dem":8,
    "gn:feature_class":"P",
    "gn:feature_code":"PPL",
    "gn:name":"Kasimesh",
    "gn:population":0,
    "gn:timezone":"America/Bogota",
    "iso:country":"CO",
    "wof:name":"Kasimesh",
    "wof:placetype":"locality"
},
  "geometry": {"coordinates":[-72.11667,12.22917],"type":"Point"}
}