{
  "type": "Feature",
  "properties": {
    "gn:admin1_code":"26.0",
    "gn:admin2_code":"68895.0",
    "gn:asciiname":"Nuevo Mundo",
    "gn:country_code":"CO",
    "gn:dem":2004,
    "gn:feature_class":"P",
    "gn:feature_code":"PPL",
    "gn:name":"Nuevo Mundo",
    "gn:population":0,
    "gn:timezone":"America/Bogota",
    "iso:country":"CO",
    "name:ceb_x_preferred":[
        "Nuevo Mundo"
    ],
    "name:deu_x_preferred":[
        "Nuevo Mundo"
    ],
    "name:fra_x_preferred":[
        "Nuevo Mundo"
    ],
    "name:por_x_preferred":[
        "Novo Mundo"
    ],
    "name:spa_x_preferred":[
        "Nuevo Mundo"
    ],
    "name:swe_x_preferred":[
        "Nuevo Mundo"
    ],
    "wof:name":"Nuevo Mundo",
    "wof:placetype":"locality"
},
  "geometry": {"coordinates":[-73.33333,6.76667],"type":"Point"}
}