{
  "type": "Feature",
  "properties": {
    "gn:admin1_code":"37",
    "gn:admin2_code":"17174.0",
    "gn:asciiname":"Alto de la Mina",
    "gn:country_code":"CO",
    "gn:dem":1510,
    "gn:feature_class":"P",
    "gn:feature_code":"PPL",
    "gn:name":"Alto de la Mina",
    "gn:population":0,
    "gn:timezone":"America/Bogota",
    "iso:country":"CO",
    "wof:name":"Alto de la Mina",
    "wof:placetype":"locality"
},
  "geometry": {"coordinates":[-75.68445,4.95139],"type":"Point"}
}