{
  "type": "Feature",
  "properties": {
    "gn:admin1_code":"2.0",
    "gn:admin2_code":"5607.0",
    "gn:asciiname":"Dollyana",
    "gn:country_code":"CO",
    "gn:dem":2163,
    "gn:feature_class":"P",
    "gn:feature_code":"PPL",
    "gn:name":"Dollyana",
    "gn:population":0,
    "gn:timezone":"America/Bogota",
    "iso:country":"CO",
    "name:spa_x_preferred":[
        "Dollyana"
    ],
    "wof:name":"Dollyana",
    "wof:placetype":"locality"
},
  "geometry": {"coordinates":[-75.50275999999999,6.06754],"type":"Point"}
}