{
  "type": "Feature",
  "properties": {
    "gn:admin1_code":"9",
    "gn:admin2_code":"19473.0",
    "gn:asciiname":"Puebillo",
    "gn:country_code":"CO",
    "gn:dem":1351,
    "gn:feature_class":"P",
    "gn:feature_code":"PPL",
    "gn:name":"Puebillo",
    "gn:population":0,
    "gn:timezone":"America/Bogota",
    "iso:country":"CO",
    "wof:name":"Puebillo",
    "wof:placetype":"locality"
},
  "geometry": {"coordinates":[-76.75223000000003,2.80951],"type":"Point"}
}