{
  "type": "Feature",
  "properties": {
    "gn:admin1_code":"10.0",
    "gn:admin2_code":"20032.0",
    "gn:asciiname":"Nereidas",
    "gn:country_code":"CO",
    "gn:dem":77,
    "gn:feature_class":"P",
    "gn:feature_code":"PPL",
    "gn:name":"Nereidas",
    "gn:population":0,
    "gn:timezone":"America/Bogota",
    "iso:country":"CO",
    "wof:name":"Nereidas",
    "wof:placetype":"locality"
},
  "geometry": {"coordinates":[-73.90000000000001,9.51667],"type":"Point"}
}