{
  "type": "Feature",
  "properties": {
    "gn:admin1_code":"16.0",
    "gn:admin2_code":"41078.0",
    "gn:asciiname":"Ginebra",
    "gn:country_code":"CO",
    "gn:dem":822,
    "gn:feature_class":"P",
    "gn:feature_code":"PPL",
    "gn:name":"Ginebra",
    "gn:population":0,
    "gn:timezone":"America/Bogota",
    "iso:country":"CO",
    "name:ast_x_preferred":[
        "Xinebra"
    ],
    "name:cat_x_preferred":[
        "Ginebra"
    ],
    "name:ceb_x_preferred":[
        "Ginebra"
    ],
    "name:deu_x_preferred":[
        "Ginebra"
    ],
    "name:fra_x_preferred":[
        "Ginebra"
    ],
    "name:glg_x_preferred":[
        "Xenebra"
    ],
    "name:spa_x_preferred":[
        "Ginebra"
    ],
    "name:swe_x_preferred":[
        "Ginebra"
    ],
    "wof:name":"Ginebra",
    "wof:placetype":"locality"
},
  "geometry": {"coordinates":[-74.96755999999998,3.24733],"type":"Point"}
}