{
  "type": "Feature",
  "properties": {
    "gn:admin1_code":"21",
    "gn:admin2_code":"54001.0",
    "gn:asciiname":"El Reposo",
    "gn:country_code":"CO",
    "gn:dem":224,
    "gn:feature_class":"P",
    "gn:feature_code":"PPL",
    "gn:name":"El Reposo",
    "gn:population":0,
    "gn:timezone":"America/Bogota",
    "iso:country":"CO",
    "wof:name":"El Reposo",
    "wof:placetype":"locality"
},
  "geometry": {"coordinates":[-72.40333000000003,8.08389],"type":"Point"}
}