{
  "type": "Feature",
  "properties": {
    "gn:admin1_code":"28.0",
    "gn:admin2_code":"73168.0",
    "gn:asciiname":"El Guamal",
    "gn:country_code":"CO",
    "gn:dem":895,
    "gn:feature_class":"P",
    "gn:feature_code":"PPL",
    "gn:name":"El Guamal",
    "gn:population":0,
    "gn:timezone":"America/Bogota",
    "iso:country":"CO",
    "wof:name":"El Guamal",
    "wof:placetype":"locality"
},
  "geometry": {"coordinates":[-75.52583,3.70167],"type":"Point"}
}