{
  "type": "Feature",
  "properties": {
    "gn:admin1_code":"27",
    "gn:admin2_code":"70702.0",
    "gn:asciiname":"Ceja Gorda",
    "gn:country_code":"CO",
    "gn:dem":132,
    "gn:feature_class":"P",
    "gn:feature_code":"PPL",
    "gn:name":"Ceja Gorda",
    "gn:population":0,
    "gn:timezone":"America/Bogota",
    "iso:country":"CO",
    "wof:name":"Ceja Gorda",
    "wof:placetype":"locality"
},
  "geometry": {"coordinates":[-75.25802,9.28348],"type":"Point"}
}