{
  "type": "Feature",
  "properties": {
    "gn:admin1_code":"4.0",
    "gn:asciiname":"Santo Tomas",
    "gn:country_code":"CO",
    "gn:dem":22,
    "gn:feature_class":"P",
    "gn:feature_code":"PPL",
    "gn:name":"Santo Tom\u00e1s",
    "gn:population":0,
    "gn:timezone":"America/Bogota",
    "iso:country":"CO",
    "name:ceb_x_preferred":[
        "Santo Tomas"
    ],
    "name:deu_x_preferred":[
        "Santo Tomas"
    ],
    "name:ilo_x_preferred":[
        "Santo Tomas"
    ],
    "name:lit_x_preferred":[
        "Santo Tomas"
    ],
    "name:nld_x_preferred":[
        "Santo Tomas"
    ],
    "name:sco_x_preferred":[
        "Santo Tomas"
    ],
    "name:srp_x_preferred":[
        "\u0421\u0430\u043d\u0442\u043e \u0422\u043e\u043c\u0430\u0441"
    ],
    "name:swe_x_preferred":[
        "Santo Tomas"
    ],
    "name:und_x_variant":[
        "Hacienda Santo Tom\u00e1s",
        "Santo Tom\u00e1s"
    ],
    "name:war_x_preferred":[
        "Santo Tomas"
    ],
    "wof:name":"Santo Tomas",
    "wof:placetype":"locality"
},
  "geometry": {"coordinates":[-75.23583000000001,10.62214],"type":"Point"}
}