{
  "type": "Feature",
  "properties": {
    "gn:admin1_code":"38",
    "gn:admin2_code":"47707.0",
    "gn:asciiname":"El Amparo",
    "gn:country_code":"CO",
    "gn:dem":25,
    "gn:feature_class":"P",
    "gn:feature_code":"PPL",
    "gn:name":"El Amparo",
    "gn:population":0,
    "gn:timezone":"America/Bogota",
    "iso:country":"CO",
    "name:spa_x_preferred":[
        "El Amparo"
    ],
    "name:und_x_variant":[
        "Amparo",
        "Hacienda El Amparo"
    ],
    "wof:name":"El Amparo",
    "wof:placetype":"locality"
},
  "geometry": {"coordinates":[-74.51775000000001,9.44484],"type":"Point"}
}