{
  "type": "Feature",
  "properties": {
    "gn:admin1_code":"10",
    "gn:admin2_code":"20175.0",
    "gn:asciiname":"La Rina",
    "gn:country_code":"CO",
    "gn:dem":55,
    "gn:feature_class":"P",
    "gn:feature_code":"PPL",
    "gn:name":"La Ri\u00f1a",
    "gn:population":0,
    "gn:timezone":"America/Bogota",
    "iso:country":"CO",
    "wof:name":"La Rina",
    "wof:placetype":"locality"
},
  "geometry": {"coordinates":[-73.92243000000001,9.32376],"type":"Point"}
}