{
  "type": "Feature",
  "properties": {
    "gn:admin1_code":"29",
    "gn:admin2_code":"76306.0",
    "gn:asciiname":"Las Hermosas",
    "gn:country_code":"CO",
    "gn:dem":2292,
    "gn:feature_class":"P",
    "gn:feature_code":"PPL",
    "gn:name":"Las Hermosas",
    "gn:population":0,
    "gn:timezone":"America/Bogota",
    "iso:country":"CO",
    "wof:name":"Las Hermosas",
    "wof:placetype":"locality"
},
  "geometry": {"coordinates":[-76.15000000000001,3.76667],"type":"Point"}
}