{
  "type": "Feature",
  "properties": {
    "iso:country":"CO",
    "name:ceb_x_preferred":[
        "Torib\u00edo"
    ],
    "name:deu_x_preferred":[
        "Torib\u00edo"
    ],
    "name:eng_x_preferred":[
        "Torib\u00edo"
    ],
    "name:fas_x_preferred":[
        "\u062a\u0648\u0631\u06cc\u0628\u06cc\u0648"
    ],
    "name:fra_x_preferred":[
        "Torib\u00edo"
    ],
    "name:ita_x_preferred":[
        "Torib\u00edo"
    ],
    "name:kat_x_preferred":[
        "\u10e2\u10dd\u10e0\u10d8\u10d1\u10d8\u10dd"
    ],
    "name:msa_x_preferred":[
        "Toribio"
    ],
    "name:nan_x_preferred":[
        "Toribio"
    ],
    "name:nld_x_preferred":[
        "Toribio"
    ],
    "name:por_x_preferred":[
        "Toribio"
    ],
    "name:spa_x_preferred":[
        "Torib\u00edo"
    ],
    "name:swe_x_preferred":[
        "Torib\u00edo"
    ],
    "name:tgl_x_preferred":[
        "Torib\u00edo"
    ],
    "name:war_x_preferred":[
        "Torib\u00edo"
    ],
    "name:zho_x_preferred":[
        "\u6258\u91cc\u6bd4\u5967"
    ],
    "qs:gn_country":"CO",
    "qs:gn_fcode":"PPL",
    "qs:gn_pop":3911,
    "qs:name":"Torib\u00edo",
    "qs:name_adm0":"Colombia",
    "qs:name_adm1":"Cauca",
    "qs:photos":0,
    "qs:photos_1k":0,
    "qs:photos_9k":1,
    "qs:photos_9r":1,
    "qs:photos_all":2,
    "qs:photos_sr":0,
    "qs:placetype":"Town",
    "qs:pop_sr":"4",
    "qs:woe_adm0":23424787,
    "wd:wordcount":44,
    "wof:name":"Torib\u00edo",
    "wof:placetype":"locality",
    "wof:population":3911
},
  "geometry": {"coordinates":[-76.26839,2.95481],"type":"Point"}
}