{
  "type": "Feature",
  "properties": {
    "gn:admin1_code":"12",
    "gn:admin2_code":"23162.0",
    "gn:asciiname":"El Chiquero",
    "gn:country_code":"CO",
    "gn:dem":10,
    "gn:feature_class":"P",
    "gn:feature_code":"PPL",
    "gn:name":"El Chiquero",
    "gn:population":0,
    "gn:timezone":"America/Bogota",
    "iso:country":"CO",
    "name:und_x_variant":[
        "Hacienda El Chiquero",
        "El Chiquero"
    ],
    "wof:name":"El Chiquero",
    "wof:placetype":"locality"
},
  "geometry": {"coordinates":[-75.73958,8.91716],"type":"Point"}
}