{
  "type": "Feature",
  "properties": {
    "gn:admin1_code":"2.0",
    "gn:admin2_code":"5847.0",
    "gn:asciiname":"La Clara",
    "gn:country_code":"CO",
    "gn:dem":2129,
    "gn:feature_class":"P",
    "gn:feature_code":"PPL",
    "gn:name":"La Clara",
    "gn:population":0,
    "gn:timezone":"America/Bogota",
    "iso:country":"CO",
    "wof:name":"La Clara",
    "wof:placetype":"locality"
},
  "geometry": {"coordinates":[-76.16278,6.51861],"type":"Point"}
}