{
  "type": "Feature",
  "properties": {
    "gn:admin1_code":"01",
    "gn:admin2_code":"91540",
    "gn:asciiname":"Caserio El Chorro",
    "gn:country_code":"CO",
    "gn:dem":94,
    "gn:feature_class":"P",
    "gn:feature_code":"PPL",
    "gn:name":"Caserio El Chorro",
    "gn:population":0,
    "gn:timezone":"America/Bogota",
    "iso:country":"CO",
    "wof:name":"Caserio El Chorro",
    "wof:placetype":"locality"
},
  "geometry": {"coordinates":[-70.34447,-3.79313],"type":"Point"}
}