{
  "type": "Feature",
  "properties": {
    "gn:admin1_code":"26",
    "gn:admin2_code":"68773.0",
    "gn:asciiname":"Los Bancos",
    "gn:country_code":"CO",
    "gn:dem":2722,
    "gn:feature_class":"P",
    "gn:feature_code":"PPL",
    "gn:name":"Los Bancos",
    "gn:population":0,
    "gn:timezone":"America/Bogota",
    "iso:country":"CO",
    "wof:name":"Los Bancos",
    "wof:placetype":"locality"
},
  "geometry": {"coordinates":[-73.86667,5.88],"type":"Point"}
}