{
  "type": "Feature",
  "properties": {
    "gn:admin1_code":"27",
    "gn:admin2_code":"70823.0",
    "gn:asciiname":"Los Altos",
    "gn:country_code":"CO",
    "gn:dem":106,
    "gn:feature_class":"P",
    "gn:feature_code":"PPL",
    "gn:name":"Los Altos",
    "gn:population":0,
    "gn:timezone":"America/Bogota",
    "iso:country":"CO",
    "name:cat_x_preferred":[
        "Los Altos"
    ],
    "name:ceb_x_preferred":[
        "Los Altos"
    ],
    "name:deu_x_preferred":[
        "Los Altos"
    ],
    "name:fra_x_preferred":[
        "Los Altos"
    ],
    "name:ita_x_preferred":[
        "Los Altos"
    ],
    "name:jpn_x_preferred":[
        "\u30ed\u30b9\u30a2\u30eb\u30c8\u30b9"
    ],
    "name:kat_x_preferred":[
        "\u10da\u10dd\u10e1-\u10d0\u10da\u10e2\u10dd\u10e1\u10d8"
    ],
    "name:kor_x_preferred":[
        "\ub85c\uc2a4\uc54c\ud1a0\uc2a4"
    ],
    "name:oci_x_preferred":[
        "Los Altos"
    ],
    "name:pol_x_preferred":[
        "Los Altos"
    ],
    "name:por_x_preferred":[
        "Los Altos"
    ],
    "name:rus_x_preferred":[
        "\u041b\u043e\u0441-\u0410\u043b\u044c\u0442\u043e\u0441"
    ],
    "name:spa_x_preferred":[
        "Los Altos"
    ],
    "name:srp_x_preferred":[
        "\u041b\u043e\u0441 \u0410\u043b\u0442\u043e\u0441"
    ],
    "name:swe_x_preferred":[
        "Los Altos"
    ],
    "name:tur_x_preferred":[
        "Los Altos"
    ],
    "name:ukr_x_preferred":[
        "\u041b\u043e\u0441-\u0410\u043b\u044c\u0442\u043e\u0441"
    ],
    "name:und_x_variant":[
        "Caser\u00edo Los Altos"
    ],
    "name:zho_x_preferred":[
        "\u6d1b\u65af\u963f\u723e\u6258\u65af"
    ],
    "wof:name":"Los Altos",
    "wof:placetype":"locality"
},
  "geometry": {"coordinates":[-75.40809,9.40198],"type":"Point"}
}