{
  "type": "Feature",
  "properties": {
    "gn:admin1_code":"27",
    "gn:admin2_code":"70823.0",
    "gn:asciiname":"Los Altos",
    "gn:country_code":"CO",
    "gn:dem":106,
    "gn:feature_class":"P",
    "gn:feature_code":"PPL",
    "gn:name":"Los Altos",
    "gn:population":0,
    "gn:timezone":"America/Bogota",
    "iso:country":"CO",
    "name:und_x_variant":[
        "Caser\u00edo Los Altos",
        "Los Altos"
    ],
    "wof:name":"Los Altos",
    "wof:placetype":"locality"
},
  "geometry": {"coordinates":[-75.40809,9.40198],"type":"Point"}
}