{
  "type": "Feature",
  "properties": {
    "gn:admin1_code":"9.0",
    "gn:admin2_code":"19397.0",
    "gn:asciiname":"Pancitara",
    "gn:country_code":"CO",
    "gn:dem":2562,
    "gn:feature_class":"P",
    "gn:feature_code":"PPL",
    "gn:name":"Pancitar\u00e1",
    "gn:population":0,
    "gn:timezone":"America/Bogota",
    "iso:country":"CO",
    "name:spa_x_preferred":[
        "Pancitar\u00e1"
    ],
    "wof:name":"Pancitara",
    "wof:placetype":"locality"
},
  "geometry": {"coordinates":[-76.76114,1.98531],"type":"Point"}
}