{
  "type": "Feature",
  "properties": {
    "gn:admin1_code":"35",
    "gn:admin2_code":"13683.0",
    "gn:asciiname":"Baldin",
    "gn:cc2":"CO",
    "gn:country_code":"CO",
    "gn:dem":16,
    "gn:feature_class":"P",
    "gn:feature_code":"PPL",
    "gn:name":"Bald\u00edn",
    "gn:population":0,
    "gn:timezone":"America/Bogota",
    "iso:country":"CO",
    "name:und_x_variant":[
        "Hacienda Baldin",
        "Bald\u00edn"
    ],
    "wof:name":"Baldin",
    "wof:placetype":"locality"
},
  "geometry": {"coordinates":[-75.41667,10.41667],"type":"Point"}
}