{
  "type": "Feature",
  "properties": {
    "gn:admin1_code":"32.0",
    "gn:admin2_code":"85010.0",
    "gn:asciiname":"Paraiso",
    "gn:country_code":"CO",
    "gn:dem":802,
    "gn:feature_class":"P",
    "gn:feature_code":"PPL",
    "gn:name":"Para\u00edso",
    "gn:population":0,
    "gn:timezone":"America/Bogota",
    "iso:country":"CO",
    "wof:name":"Paraiso",
    "wof:placetype":"locality"
},
  "geometry": {"coordinates":[-72.70105,5.20349],"type":"Point"}
}