{
  "type": "Feature",
  "properties": {
    "gn:admin1_code":"3",
    "gn:admin2_code":"81220.0",
    "gn:asciiname":"Lipa",
    "gn:country_code":"CO",
    "gn:dem":94,
    "gn:feature_class":"P",
    "gn:feature_code":"PPL",
    "gn:name":"Lipa",
    "gn:population":0,
    "gn:timezone":"America/Bogota",
    "iso:country":"CO",
    "name:spa_x_preferred":[
        "Lipa"
    ],
    "wof:name":"Lipa",
    "wof:placetype":"locality"
},
  "geometry": {"coordinates":[-69.75561999999999,6.0567],"type":"Point"}
}