{
  "type": "Feature",
  "properties": {
    "gn:country":"CO",
    "gn:fcode":"PPLX",
    "gn:population":34172,
    "iso:country":"CO",
    "name:bar_x_preferred":[
        "Sabaneta"
    ],
    "name:ceb_x_preferred":[
        "Sabaneta"
    ],
    "name:deu_x_preferred":[
        "Sabaneta"
    ],
    "name:fas_x_preferred":[
        "\u0633\u0627\u0628\u0627\u0646\u062a\u0627"
    ],
    "name:fra_x_preferred":[
        "Sabaneta"
    ],
    "name:ita_x_preferred":[
        "Sabaneta"
    ],
    "name:nld_x_preferred":[
        "Sabaneta"
    ],
    "name:pol_x_preferred":[
        "Sabaneta"
    ],
    "name:por_x_preferred":[
        "Sabaneta"
    ],
    "name:rus_x_preferred":[
        "\u0421\u0430\u0431\u0430\u043d\u0435\u0442\u0430"
    ],
    "name:sco_x_preferred":[
        "Sabaneta"
    ],
    "name:spa_x_preferred":[
        "Sabaneta"
    ],
    "name:srp_x_preferred":[
        "\u0421\u0430\u0431\u0430\u043d\u0435\u0442\u0430"
    ],
    "name:swe_x_preferred":[
        "Sabaneta"
    ],
    "name:und_x_variant":[
        "Sabanetas"
    ],
    "name:vie_x_preferred":[
        "Sabaneta"
    ],
    "name:zho_x_preferred":[
        "\u8428\u74e6\u5185\u5854"
    ],
    "qs:name":"Sabaneta",
    "qs:photos_9r":0,
    "qs:photos_sr":0,
    "qs:pop_sr":"7",
    "wd:wordcount":25,
    "wof:name":"Sabaneta",
    "wof:placetype":"neighbourhood",
    "wof:population":34172
},
  "geometry": {"coordinates":[-75.61658,6.15154],"type":"Point"}
}