{
  "type": "Feature",
  "properties": {
    "gn:admin1_code":"31.0",
    "gn:admin2_code":"99773.0",
    "gn:asciiname":"Rancheria Bogota",
    "gn:country_code":"CO",
    "gn:dem":172,
    "gn:feature_class":"P",
    "gn:feature_code":"PPL",
    "gn:name":"Rancher\u00eda Bogota",
    "gn:population":0,
    "gn:timezone":"America/Bogota",
    "iso:country":"CO",
    "wof:name":"Rancheria Bogota",
    "wof:placetype":"locality"
},
  "geometry": {"coordinates":[-70.21528000000001,4.22167],"type":"Point"}
}