{
  "type": "Feature",
  "properties": {
    "gn:admin1_code":"31.0",
    "gn:admin2_code":"99773.0",
    "gn:asciiname":"Puerto Umaipia",
    "gn:country_code":"CO",
    "gn:dem":106,
    "gn:feature_class":"P",
    "gn:feature_code":"PPL",
    "gn:name":"Puerto Umaipia",
    "gn:population":0,
    "gn:timezone":"America/Bogota",
    "iso:country":"CO",
    "wof:name":"Puerto Umaipia",
    "wof:placetype":"locality"
},
  "geometry": {"coordinates":[-69.75471999999999,4.435],"type":"Point"}
}