{
  "type": "Feature",
  "properties": {
    "gn:admin1_code":"2.0",
    "gn:admin2_code":"5129.0",
    "gn:asciiname":"La Milagrosa",
    "gn:country_code":"CO",
    "gn:dem":2022,
    "gn:feature_class":"P",
    "gn:feature_code":"PPL",
    "gn:name":"La Milagrosa",
    "gn:population":0,
    "gn:timezone":"America/Bogota",
    "iso:country":"CO",
    "name:spa_x_preferred":[
        "La Milagrosa"
    ],
    "wof:name":"La Milagrosa",
    "wof:placetype":"locality"
},
  "geometry": {"coordinates":[-75.65708000000002,6.01787],"type":"Point"}
}