{
  "type": "Feature",
  "properties": {
    "gn:admin1_code":"9",
    "gn:admin2_code":"19130.0",
    "gn:asciiname":"La Venta",
    "gn:country_code":"CO",
    "gn:dem":1842,
    "gn:feature_class":"P",
    "gn:feature_code":"PPL",
    "gn:name":"La Venta",
    "gn:population":0,
    "gn:timezone":"America/Bogota",
    "iso:country":"CO",
    "name:bel_x_preferred":[
        "\u041b\u0430-\u0412\u0435\u043d\u0442\u0430"
    ],
    "name:ces_x_preferred":[
        "La Venta"
    ],
    "name:deu_x_preferred":[
        "La Venta"
    ],
    "name:fra_x_preferred":[
        "La Venta"
    ],
    "name:hun_x_preferred":[
        "La Venta"
    ],
    "name:ind_x_preferred":[
        "La Venta"
    ],
    "name:ita_x_preferred":[
        "La Venta"
    ],
    "name:lit_x_preferred":[
        "La Venta"
    ],
    "name:nld_x_preferred":[
        "La Venta"
    ],
    "name:pol_x_preferred":[
        "La Venta"
    ],
    "name:por_x_preferred":[
        "La Venta"
    ],
    "name:rus_x_preferred":[
        "\u041b\u0430-\u0412\u0435\u043d\u0442\u0430"
    ],
    "name:slk_x_preferred":[
        "La Venta"
    ],
    "name:spa_x_preferred":[
        "La Venta"
    ],
    "wof:name":"La Venta",
    "wof:placetype":"locality"
},
  "geometry": {"coordinates":[-76.55240999999999,2.58892],"type":"Point"}
}