{
  "type": "Feature",
  "properties": {
    "gn:admin1_code":"33.0",
    "gn:admin2_code":"25322.0",
    "gn:asciiname":"Perico",
    "gn:country_code":"CO",
    "gn:dem":3092,
    "gn:feature_class":"P",
    "gn:feature_code":"PPL",
    "gn:name":"Perico",
    "gn:population":0,
    "gn:timezone":"America/Bogota",
    "iso:country":"CO",
    "name:ceb_x_preferred":[
        "Perico"
    ],
    "name:deu_x_preferred":[
        "Perico"
    ],
    "name:fra_x_preferred":[
        "Perico"
    ],
    "name:pol_x_preferred":[
        "Perico"
    ],
    "name:por_x_preferred":[
        "Perico"
    ],
    "name:sco_x_preferred":[
        "Perico"
    ],
    "name:spa_x_preferred":[
        "Perico"
    ],
    "name:swe_x_preferred":[
        "Perico"
    ],
    "wof:name":"Perico",
    "wof:placetype":"locality"
},
  "geometry": {"coordinates":[-73.89666,4.77382],"type":"Point"}
}