{
  "type": "Feature",
  "properties": {
    "gn:admin1_code":"26",
    "gn:admin2_code":"68572.0",
    "gn:asciiname":"El Pinito",
    "gn:country_code":"CO",
    "gn:dem":2348,
    "gn:feature_class":"P",
    "gn:feature_code":"PPL",
    "gn:name":"El Pinito",
    "gn:population":0,
    "gn:timezone":"America/Bogota",
    "iso:country":"CO",
    "wof:name":"El Pinito",
    "wof:placetype":"locality"
},
  "geometry": {"coordinates":[-73.71556,5.78389],"type":"Point"}
}