{
  "type": "Feature",
  "properties": {
    "gn:admin1_code":"27.0",
    "gn:admin2_code":"70124.0",
    "gn:asciiname":"Solera",
    "gn:country_code":"CO",
    "gn:dem":19,
    "gn:feature_class":"P",
    "gn:feature_code":"PPL",
    "gn:name":"Solera",
    "gn:population":0,
    "gn:timezone":"America/Bogota",
    "iso:country":"CO",
    "wof:name":"Solera",
    "wof:placetype":"locality"
},
  "geometry": {"coordinates":[-75.09139999999999,8.7714],"type":"Point"}
}