{
  "type": "Feature",
  "properties": {
    "gn:admin1_code":"27.0",
    "gn:admin2_code":"70124.0",
    "gn:asciiname":"Solera",
    "gn:country_code":"CO",
    "gn:dem":19,
    "gn:feature_class":"P",
    "gn:feature_code":"PPL",
    "gn:name":"Solera",
    "gn:population":0,
    "gn:timezone":"America/Bogota",
    "iso:country":"CO",
    "name:fin_x_preferred":[
        "Solera"
    ],
    "name:fra_x_preferred":[
        "Solera"
    ],
    "name:ita_x_preferred":[
        "Metodo soleras"
    ],
    "name:nld_x_preferred":[
        "Solera-systeem"
    ],
    "name:por_x_preferred":[
        "Soleira"
    ],
    "name:rus_x_preferred":[
        "\u0421\u043e\u043b\u0435\u0440\u0430"
    ],
    "name:ukr_x_preferred":[
        "\u0421\u043e\u043b\u0435\u0440\u0430"
    ],
    "name:zho_x_preferred":[
        "\u7d22\u96f7\u62c9\u9648\u917f\u7cfb\u7edf"
    ],
    "wof:name":"Solera",
    "wof:placetype":"locality"
},
  "geometry": {"coordinates":[-75.09139999999999,8.7714],"type":"Point"}
}