{
  "type": "Feature",
  "properties": {
    "gn:admin1_code":"2.0",
    "gn:admin2_code":"5264.0",
    "gn:asciiname":"Las Marias",
    "gn:country_code":"CO",
    "gn:dem":2352,
    "gn:feature_class":"P",
    "gn:feature_code":"PPL",
    "gn:name":"Las Mar\u00edas",
    "gn:population":0,
    "gn:timezone":"America/Bogota",
    "iso:country":"CO",
    "wof:name":"Las Marias",
    "wof:placetype":"locality"
},
  "geometry": {"coordinates":[-75.57083,6.58306],"type":"Point"}
}