{
  "type": "Feature",
  "properties": {
    "gn:admin1_code":"15",
    "gn:admin2_code":"94888.0",
    "gn:asciiname":"Culebra",
    "gn:country_code":"CO",
    "gn:dem":206,
    "gn:feature_class":"P",
    "gn:feature_code":"PPL",
    "gn:name":"Culebra",
    "gn:population":0,
    "gn:timezone":"America/Bogota",
    "iso:country":"CO",
    "name:ceb_x_preferred":[
        "Culebra"
    ],
    "name:fra_x_preferred":[
        "Culebra"
    ],
    "name:ita_x_preferred":[
        "Culebra"
    ],
    "name:pol_x_preferred":[
        "Culebra"
    ],
    "name:rus_x_preferred":[
        "\u041a\u0443\u043b\u0435\u0431\u0440\u0430"
    ],
    "name:spa_x_preferred":[
        "Culebra"
    ],
    "name:swe_x_preferred":[
        "Culebra"
    ],
    "wof:name":"Culebra",
    "wof:placetype":"locality"
},
  "geometry": {"coordinates":[-70.15000000000001,2.45],"type":"Point"}
}