{
  "type": "Feature",
  "properties": {
    "gn:admin1_code":"2.0",
    "gn:admin2_code":"5347.0",
    "gn:asciiname":"El Hatillo",
    "gn:country_code":"CO",
    "gn:dem":1428,
    "gn:feature_class":"P",
    "gn:feature_code":"PPL",
    "gn:name":"El Hatillo",
    "gn:population":0,
    "gn:timezone":"America/Bogota",
    "iso:country":"CO",
    "name:spa_x_preferred":[
        "El Hatillo"
    ],
    "wof:name":"El Hatillo",
    "wof:placetype":"locality"
},
  "geometry": {"coordinates":[-75.73143,6.20479],"type":"Point"}
}