{
  "type": "Feature",
  "properties": {
    "gn:admin1_code":"29.0",
    "gn:admin2_code":"76109.0",
    "gn:asciiname":"Silva",
    "gn:country_code":"CO",
    "gn:dem":13,
    "gn:feature_class":"P",
    "gn:feature_code":"PPL",
    "gn:name":"Silva",
    "gn:population":0,
    "gn:timezone":"America/Bogota",
    "iso:country":"CO",
    "name:ces_x_preferred":[
        "Silva"
    ],
    "name:deu_x_preferred":[
        "Silva"
    ],
    "name:fin_x_preferred":[
        "Silva"
    ],
    "name:fra_x_preferred":[
        "Silva"
    ],
    "name:glg_x_preferred":[
        "Silva"
    ],
    "name:nld_x_preferred":[
        "Silva"
    ],
    "name:por_x_preferred":[
        "Silva"
    ],
    "name:spa_x_preferred":[
        "Silva"
    ],
    "name:ukr_x_preferred":[
        "\u0421\u0456\u043b\u0432\u0430"
    ],
    "name:zho_x_preferred":[
        "\u5e2d\u5c14\u74e6"
    ],
    "wof:name":"Silva",
    "wof:placetype":"locality"
},
  "geometry": {"coordinates":[-77.21092,3.48314],"type":"Point"}
}