{
  "type": "Feature",
  "properties": {
    "gn:admin1_code":"10.0",
    "gn:admin2_code":"20621.0",
    "gn:asciiname":"Hacienda Ebano",
    "gn:country_code":"CO",
    "gn:dem":77,
    "gn:feature_class":"P",
    "gn:feature_code":"PPL",
    "gn:name":"Hacienda Ebano",
    "gn:population":0,
    "gn:timezone":"America/Bogota",
    "iso:country":"CO",
    "wof:name":"Hacienda Ebano",
    "wof:placetype":"locality"
},
  "geometry": {"coordinates":[-73.36995999999998,10.0631],"type":"Point"}
}