{
  "type": "Feature",
  "properties": {
    "gn:admin1_code":"17.0",
    "gn:admin2_code":"44847.0",
    "gn:asciiname":"Rancheria Routamahana",
    "gn:country_code":"CO",
    "gn:dem":122,
    "gn:feature_class":"P",
    "gn:feature_code":"PPLL",
    "gn:name":"Rancher\u00eda Routamahana",
    "gn:population":0,
    "gn:timezone":"America/Bogota",
    "iso:country":"CO",
    "name:und_x_variant":[
        "Rancher\u00eda Routamahana",
        "Routamahana"
    ],
    "wof:name":"Rancheria Routamahana",
    "wof:placetype":"locality"
},
  "geometry": {"coordinates":[-71.60751999999999,12.0041],"type":"Point"}
}