{
  "type": "Feature",
  "properties": {
    "gn:admin1_code":"21",
    "gn:admin2_code":"54810.0",
    "gn:asciiname":"La Colina",
    "gn:country_code":"CO",
    "gn:dem":46,
    "gn:feature_class":"P",
    "gn:feature_code":"PPL",
    "gn:name":"La Colina",
    "gn:population":0,
    "gn:timezone":"America/Bogota",
    "iso:country":"CO",
    "wof:name":"La Colina",
    "wof:placetype":"locality"
},
  "geometry": {"coordinates":[-72.64166999999998,8.52611],"type":"Point"}
}