{
  "type": "Feature",
  "properties": {
    "gn:admin1_code":"4.0",
    "gn:admin2_code":"8433.0",
    "gn:asciiname":"Mira Muertos",
    "gn:country_code":"CO",
    "gn:dem":25,
    "gn:feature_class":"P",
    "gn:feature_code":"PPL",
    "gn:name":"Mira Muertos",
    "gn:population":0,
    "gn:timezone":"America/Bogota",
    "iso:country":"CO",
    "wof:name":"Mira Muertos",
    "wof:placetype":"locality"
},
  "geometry": {"coordinates":[-74.78333000000001,10.85],"type":"Point"}
}