{
  "type": "Feature",
  "properties": {
    "gn:admin1_code":"29.0",
    "gn:asciiname":"La Playita",
    "gn:country_code":"CO",
    "gn:dem":12,
    "gn:feature_class":"P",
    "gn:feature_code":"PPLL",
    "gn:name":"La Playita",
    "gn:population":0,
    "gn:timezone":"America/Bogota",
    "iso:country":"CO",
    "name:spa_x_preferred":[
        "La Playita"
    ],
    "wof:name":"La Playita",
    "wof:placetype":"locality"
},
  "geometry": {"coordinates":[-77.08708,3.85392],"type":"Point"}
}