{
  "type": "Feature",
  "properties": {
    "gn:admin1_code":"32",
    "gn:admin2_code":"85001.0",
    "gn:asciiname":"La Independencia",
    "gn:country_code":"CO",
    "gn:dem":220,
    "gn:feature_class":"P",
    "gn:feature_code":"PPL",
    "gn:name":"La Independencia",
    "gn:population":0,
    "gn:timezone":"America/Bogota",
    "iso:country":"CO",
    "wof:name":"La Independencia",
    "wof:placetype":"locality"
},
  "geometry": {"coordinates":[-72.32066999999998,5.19802],"type":"Point"}
}