{
  "type": "Feature",
  "properties": {
    "gn:admin1_code":"28.0",
    "gn:admin2_code":"73504.0",
    "gn:asciiname":"Santuario",
    "gn:country_code":"CO",
    "gn:dem":2301,
    "gn:feature_class":"P",
    "gn:feature_code":"PPL",
    "gn:name":"Santuario",
    "gn:population":0,
    "gn:timezone":"America/Bogota",
    "iso:country":"CO",
    "wof:name":"Santuario",
    "wof:placetype":"locality"
},
  "geometry": {"coordinates":[-75.42305999999998,3.91917],"type":"Point"}
}