{
  "type": "Feature",
  "properties": {
    "gn:admin1_code":"26",
    "gn:admin2_code":"68255.0",
    "gn:asciiname":"Aguacaliente",
    "gn:country_code":"CO",
    "gn:dem":546,
    "gn:feature_class":"P",
    "gn:feature_code":"PPL",
    "gn:name":"Aguacaliente",
    "gn:population":0,
    "gn:timezone":"America/Bogota",
    "iso:country":"CO",
    "wof:name":"Aguacaliente",
    "wof:placetype":"locality"
},
  "geometry": {"coordinates":[-73.21666999999999,7.49833],"type":"Point"}
}