{
  "type": "Feature",
  "properties": {
    "iso:country":"CO",
    "name:ceb_x_preferred":[
        "Curillo"
    ],
    "name:eng_x_preferred":[
        "Curillo"
    ],
    "name:fra_x_preferred":[
        "Curillo"
    ],
    "name:ita_x_preferred":[
        "Curillo"
    ],
    "name:jpn_x_preferred":[
        "\u30af\u30ea\u30fc\u30b8\u30e7"
    ],
    "name:kat_x_preferred":[
        "\u10d9\u10e3\u10e0\u10d8\u10da\u10d8\u10dd"
    ],
    "name:msa_x_preferred":[
        "Curillo"
    ],
    "name:nan_x_preferred":[
        "Currillo"
    ],
    "name:nld_x_preferred":[
        "Currillo"
    ],
    "name:por_x_preferred":[
        "Curillo"
    ],
    "name:spa_x_preferred":[
        "Curillo"
    ],
    "name:swe_x_preferred":[
        "Curillo"
    ],
    "name:tgl_x_preferred":[
        "Curillo"
    ],
    "name:unk_x_variant":[
        "El Curillo"
    ],
    "name:vie_x_preferred":[
        "Curillo"
    ],
    "name:war_x_preferred":[
        "Curillo"
    ],
    "name:zho_min_nan_x_preferred":[
        "Currillo"
    ],
    "name:zho_x_preferred":[
        "\u5eab\u91cc\u7565"
    ],
    "qs:gn_country":"CO",
    "qs:gn_fcode":"PPL",
    "qs:gn_pop":9539,
    "qs:name":"Curillo",
    "qs:name_adm0":"Colombia",
    "qs:name_adm1":"Caqueta",
    "qs:photos":0,
    "qs:photos_1k":0,
    "qs:photos_9k":1,
    "qs:photos_9r":1,
    "qs:photos_all":12,
    "qs:photos_sr":0,
    "qs:placetype":"Town",
    "qs:pop_sr":"5",
    "qs:woe_adm0":23424787,
    "wd:wordcount":27,
    "wof:name":"Curillo",
    "wof:placetype":"locality",
    "wof:population":9539
},
  "geometry": {"coordinates":[-75.91906,1.03327],"type":"Point"}
}