{
  "type": "Feature",
  "properties": {
    "gn:admin1_code":"1",
    "gn:admin2_code":"91263.0",
    "gn:asciiname":"El Encanto",
    "gn:country_code":"CO",
    "gn:dem":124,
    "gn:feature_class":"P",
    "gn:feature_code":"PPL",
    "gn:name":"El Encanto",
    "gn:population":0,
    "gn:timezone":"America/Bogota",
    "iso:country":"CO",
    "name:eng_x_preferred":[
        "El Encanto"
    ],
    "name:fra_x_preferred":[
        "El Encanto"
    ],
    "name:spa_x_preferred":[
        "El Encanto"
    ],
    "wof:name":"El Encanto",
    "wof:placetype":"locality"
},
  "geometry": {"coordinates":[-73.20851,-1.74909],"type":"Point"}
}