{
  "type": "Feature",
  "properties": {
    "gn:admin1_code":"8.0",
    "gn:admin2_code":"18001.0",
    "gn:asciiname":"Holanda",
    "gn:country_code":"CO",
    "gn:dem":443,
    "gn:feature_class":"P",
    "gn:feature_code":"PPL",
    "gn:name":"Holanda",
    "gn:population":0,
    "gn:timezone":"America/Bogota",
    "iso:country":"CO",
    "wof:name":"Holanda",
    "wof:placetype":"locality"
},
  "geometry": {"coordinates":[-75.66558000000001,1.62197],"type":"Point"}
}