{
  "type": "Feature",
  "properties": {
    "gn:admin1_code":"28.0",
    "gn:admin2_code":"73616.0",
    "gn:asciiname":"El Prodigio",
    "gn:country_code":"CO",
    "gn:dem":2516,
    "gn:feature_class":"P",
    "gn:feature_code":"PPL",
    "gn:name":"El Prodigio",
    "gn:population":0,
    "gn:timezone":"America/Bogota",
    "iso:country":"CO",
    "wof:name":"El Prodigio",
    "wof:placetype":"locality"
},
  "geometry": {"coordinates":[-75.82916999999998,3.61333],"type":"Point"}
}