{
  "type": "Feature",
  "properties": {
    "gn:admin1_code":"35",
    "gn:admin2_code":"13650.0",
    "gn:asciiname":"Guasimal",
    "gn:country_code":"CO",
    "gn:dem":20,
    "gn:feature_class":"P",
    "gn:feature_code":"PPL",
    "gn:name":"Guasimal",
    "gn:population":0,
    "gn:timezone":"America/Bogota",
    "iso:country":"CO",
    "name:ceb_x_preferred":[
        "Guasimal"
    ],
    "name:deu_x_preferred":[
        "Guasimal"
    ],
    "name:hat_x_preferred":[
        "Guasimal"
    ],
    "name:nld_x_preferred":[
        "Guasimal"
    ],
    "name:und_x_variant":[
        "Caserio Guasimal"
    ],
    "wof:name":"Guasimal",
    "wof:placetype":"locality"
},
  "geometry": {"coordinates":[-74.34056,9.14323],"type":"Point"}
}