{
  "type": "Feature",
  "properties": {
    "gn:admin1_code":"8.0",
    "gn:admin2_code":"18150.0",
    "gn:asciiname":"Caserio Sardinata",
    "gn:country_code":"CO",
    "gn:dem":261,
    "gn:feature_class":"P",
    "gn:feature_code":"PPL",
    "gn:name":"Caser\u00edo Sardinata",
    "gn:population":0,
    "gn:timezone":"America/Bogota",
    "iso:country":"CO",
    "wof:name":"Caserio Sardinata",
    "wof:placetype":"locality"
},
  "geometry": {"coordinates":[-74.64185000000001,1.18337],"type":"Point"}
}