{
  "type": "Feature",
  "properties": {
    "gn:admin1_code":"28",
    "gn:admin2_code":"73622.0",
    "gn:asciiname":"La Rivera",
    "gn:country_code":"CO",
    "gn:dem":2672,
    "gn:feature_class":"P",
    "gn:feature_code":"PPL",
    "gn:name":"La Rivera",
    "gn:population":0,
    "gn:timezone":"America/Bogota",
    "iso:country":"CO",
    "name:ceb_x_preferred":[
        "La Rivera"
    ],
    "name:deu_x_preferred":[
        "La Rivera"
    ],
    "name:que_x_preferred":[
        "La Rivera"
    ],
    "name:rus_x_preferred":[
        "\u041b\u0430-\u0420\u0438\u0432\u0435\u0440\u0430"
    ],
    "name:spa_x_preferred":[
        "La Rivera"
    ],
    "name:urd_x_preferred":[
        "\u0644\u0627 \u0631\u06cc\u0648\u06cc\u0631\u0627"
    ],
    "name:war_x_preferred":[
        "La Rivera"
    ],
    "name:zho_x_preferred":[
        "\u62c9\u91cc\u97cb\u62c9"
    ],
    "wof:name":"La Rivera",
    "wof:placetype":"locality"
},
  "geometry": {"coordinates":[-75.61750000000001,3.99444],"type":"Point"}
}