{
  "type": "Feature",
  "properties": {
    "gn:admin1_code":"12",
    "gn:admin2_code":"23555.0",
    "gn:asciiname":"Placeres",
    "gn:country_code":"CO",
    "gn:dem":122,
    "gn:feature_class":"P",
    "gn:feature_code":"PPLL",
    "gn:name":"Placeres",
    "gn:population":0,
    "gn:timezone":"America/Bogota",
    "iso:country":"CO",
    "name:und_x_variant":[
        "Los Placeres",
        "Placeres"
    ],
    "wof:name":"Placeres",
    "wof:placetype":"locality"
},
  "geometry": {"coordinates":[-75.61159000000001,8.54281],"type":"Point"}
}