{
  "type": "Feature",
  "properties": {
    "gn:admin1_code":"36",
    "gn:admin2_code":"15638.0",
    "gn:asciiname":"Santa Teresita",
    "gn:country_code":"CO",
    "gn:dem":2156,
    "gn:feature_class":"P",
    "gn:feature_code":"PPL",
    "gn:name":"Santa Teresita",
    "gn:population":0,
    "gn:timezone":"America/Bogota",
    "iso:country":"CO",
    "name:ceb_x_preferred":[
        "Santa Teresita"
    ],
    "name:deu_x_preferred":[
        "Santa Teresita"
    ],
    "name:fra_x_preferred":[
        "Santa Teresita"
    ],
    "name:ilo_x_preferred":[
        "Santa Teresita"
    ],
    "name:ita_x_preferred":[
        "Santa Teresita"
    ],
    "name:nld_x_preferred":[
        "Santa Teresita"
    ],
    "name:sco_x_preferred":[
        "Santa Teresita"
    ],
    "name:spa_x_preferred":[
        "Santa Teresita"
    ],
    "name:srp_x_preferred":[
        "\u0421\u0430\u043d\u0442\u0430 \u0422\u0435\u0440\u0435\u0441\u0438\u0442\u0430"
    ],
    "name:swe_x_preferred":[
        "Santa Teresita"
    ],
    "name:war_x_preferred":[
        "Santa Teresita"
    ],
    "wof:name":"Santa Teresita",
    "wof:placetype":"locality"
},
  "geometry": {"coordinates":[-73.53361,5.58972],"type":"Point"}
}