{
  "type": "Feature",
  "properties": {
    "gn:admin1_code":"2.0",
    "gn:admin2_code":"5113.0",
    "gn:asciiname":"Araos",
    "gn:country_code":"CO",
    "gn:dem":1927,
    "gn:feature_class":"P",
    "gn:feature_code":"PPL",
    "gn:name":"Araos",
    "gn:population":0,
    "gn:timezone":"America/Bogota",
    "iso:country":"CO",
    "wof:name":"Araos",
    "wof:placetype":"locality"
},
  "geometry": {"coordinates":[-75.92278,6.70972],"type":"Point"}
}