{
  "type": "Feature",
  "properties": {
    "gn:admin1_code":"12.0",
    "gn:admin2_code":"23417.0",
    "gn:asciiname":"Narino",
    "gn:country_code":"CO",
    "gn:dem":8,
    "gn:feature_class":"P",
    "gn:feature_code":"PPL",
    "gn:name":"Nari\u00f1o",
    "gn:population":0,
    "gn:timezone":"America/Bogota",
    "iso:country":"CO",
    "name:und_x_variant":[
        "Corregimiento Nari\u00f1o",
        "Gallinazo",
        "Nari\u00f1o"
    ],
    "wof:name":"Narino",
    "wof:placetype":"locality"
},
  "geometry": {"coordinates":[-75.83685,9.16831],"type":"Point"}
}