{
  "type": "Feature",
  "properties": {
    "gn:admin1_code":"3.0",
    "gn:admin2_code":"81001.0",
    "gn:asciiname":"Santa Barbara",
    "gn:country_code":"CO",
    "gn:dem":109,
    "gn:feature_class":"P",
    "gn:feature_code":"PPL",
    "gn:name":"Santa B\u00e1rbara",
    "gn:population":0,
    "gn:timezone":"America/Bogota",
    "iso:country":"CO",
    "name:spa_x_preferred":[
        "Santa B\u00e1rbara"
    ],
    "name:spa_x_variant":[
        "Do\u00f1a B\u00e1rbara"
    ],
    "wof:name":"Santa Barbara",
    "wof:placetype":"locality"
},
  "geometry": {"coordinates":[-70.13574,6.93667],"type":"Point"}
}