{
  "type": "Feature",
  "properties": {
    "gn:admin1_code":"29.0",
    "gn:admin2_code":"76606.0",
    "gn:asciiname":"Madronal",
    "gn:country_code":"CO",
    "gn:dem":1565,
    "gn:feature_class":"P",
    "gn:feature_code":"PPL",
    "gn:name":"Madro\u00f1al",
    "gn:population":0,
    "gn:timezone":"America/Bogota",
    "iso:country":"CO",
    "wof:name":"Madronal",
    "wof:placetype":"locality"
},
  "geometry": {"coordinates":[-76.55441999999999,3.85608],"type":"Point"}
}