{
  "type": "Feature",
  "properties": {
    "gn:admin1_code":"36",
    "gn:admin2_code":"15507.0",
    "gn:asciiname":"Tapaz del Chipe",
    "gn:country_code":"CO",
    "gn:dem":1167,
    "gn:feature_class":"P",
    "gn:feature_code":"PPL",
    "gn:name":"Tapaz del Chipe",
    "gn:population":0,
    "gn:timezone":"America/Bogota",
    "iso:country":"CO",
    "wof:name":"Tapaz del Chipe",
    "wof:placetype":"locality"
},
  "geometry": {"coordinates":[-74.18861,5.60472],"type":"Point"}
}