{
  "type": "Feature",
  "properties": {
    "iso:country":"CO",
    "name:ast_x_preferred":[
        "Belmira"
    ],
    "name:ceb_x_preferred":[
        "Belmira"
    ],
    "name:eng_x_preferred":[
        "Belmira"
    ],
    "name:fra_x_preferred":[
        "Belmira"
    ],
    "name:ile_x_preferred":[
        "Belmira"
    ],
    "name:ilo_x_preferred":[
        "Belmira"
    ],
    "name:ita_x_preferred":[
        "Belmira"
    ],
    "name:kat_x_preferred":[
        "\u10d1\u10d4\u10da\u10db\u10d8\u10e0\u10d0"
    ],
    "name:lav_x_preferred":[
        "Belm\u012bra"
    ],
    "name:msa_x_preferred":[
        "Belmira"
    ],
    "name:nan_x_preferred":[
        "Belmira"
    ],
    "name:nld_x_preferred":[
        "Belmira"
    ],
    "name:por_x_preferred":[
        "Belmira"
    ],
    "name:ron_x_preferred":[
        "Belmira"
    ],
    "name:rus_x_preferred":[
        "\u0411\u0435\u043b\u044c\u043c\u0438\u0440\u0430"
    ],
    "name:spa_x_preferred":[
        "Belmira"
    ],
    "name:swe_x_preferred":[
        "Belmira"
    ],
    "name:tgl_x_preferred":[
        "Belmira"
    ],
    "name:vie_x_preferred":[
        "Belmira"
    ],
    "name:war_x_preferred":[
        "Belmira"
    ],
    "name:zho_min_nan_x_preferred":[
        "Belmira"
    ],
    "name:zho_x_preferred":[
        "\u97cb\u723e\u7c73\u62c9"
    ],
    "qs:gn_country":"CO",
    "qs:gn_fcode":"PPL",
    "qs:gn_pop":1388,
    "qs:name":"Belmira",
    "qs:name_adm0":"Colombia",
    "qs:name_adm1":"Antioquia",
    "qs:photos":124,
    "qs:photos_1k":25,
    "qs:photos_9k":1,
    "qs:photos_9r":3,
    "qs:photos_all":124,
    "qs:photos_sr":3,
    "qs:placetype":"Town",
    "qs:pop_sr":"3",
    "qs:woe_adm0":23424787,
    "wd:wordcount":33,
    "wof:name":"Belmira",
    "wof:placetype":"locality",
    "wof:population":1388
},
  "geometry": {"coordinates":[-75.66619,6.60508],"type":"Point"}
}