{
  "type": "Feature",
  "properties": {
    "gn:admin1_code":"10.0",
    "gn:admin2_code":"20032.0",
    "gn:asciiname":"Tolima",
    "gn:country_code":"CO",
    "gn:dem":60,
    "gn:feature_class":"P",
    "gn:feature_code":"PPL",
    "gn:name":"Tolima",
    "gn:population":0,
    "gn:timezone":"America/Bogota",
    "iso:country":"CO",
    "wof:name":"Tolima",
    "wof:placetype":"locality"
},
  "geometry": {"coordinates":[-73.88667,9.51],"type":"Point"}
}