{
  "type": "Feature",
  "properties": {
    "iso:country":"CO",
    "name:ceb_x_preferred":[
        "San Juanito"
    ],
    "name:deu_x_preferred":[
        "San Juanito"
    ],
    "name:eng_x_preferred":[
        "San Juanito"
    ],
    "name:hbs_x_preferred":[
        "San Juanito"
    ],
    "name:msa_x_preferred":[
        "San Juanito"
    ],
    "name:spa_x_preferred":[
        "San Juanito"
    ],
    "name:swe_x_preferred":[
        "San Juanito"
    ],
    "name:tgl_x_preferred":[
        "San Juanito"
    ],
    "name:vie_x_preferred":[
        "San Juanito"
    ],
    "qs:gn_country":"CO",
    "qs:gn_fcode":"PPL",
    "qs:gn_pop":396,
    "qs:name":"San Juanito",
    "qs:name_adm0":"Colombia",
    "qs:name_adm1":"Meta",
    "qs:photos":0,
    "qs:photos_1k":0,
    "qs:photos_9k":0,
    "qs:photos_9r":0,
    "qs:photos_all":0,
    "qs:photos_sr":0,
    "qs:placetype":"Town",
    "qs:pop_sr":"2",
    "qs:woe_adm0":23424787,
    "wd:wordcount":44,
    "wof:name":"San Juanito",
    "wof:placetype":"locality",
    "wof:population":396
},
  "geometry": {"coordinates":[-72.96849,4.50982],"type":"Point"}
}