{
  "type": "Feature",
  "properties": {
    "gn:admin1_code":"19",
    "gn:admin2_code":"50370.0",
    "gn:asciiname":"La Ilusion",
    "gn:cc2":"CO",
    "gn:country_code":"CO",
    "gn:dem":507,
    "gn:feature_class":"P",
    "gn:feature_code":"PPL",
    "gn:name":"La Ilusi\u00f3n",
    "gn:population":0,
    "gn:timezone":"America/Bogota",
    "iso:country":"CO",
    "name:und_x_variant":[
        "Ilusi\u00f3n",
        "La Ilusi\u00f3n"
    ],
    "wof:name":"La Ilusion",
    "wof:placetype":"locality"
},
  "geometry": {"coordinates":[-74.28333000000001,3.05],"type":"Point"}
}