{
  "type": "Feature",
  "properties": {
    "gn:admin1_code":"29.0",
    "gn:admin2_code":"76834.0",
    "gn:asciiname":"La Palmera",
    "gn:country_code":"CO",
    "gn:dem":927,
    "gn:feature_class":"P",
    "gn:feature_code":"PPL",
    "gn:name":"La Palmera",
    "gn:population":0,
    "gn:timezone":"America/Bogota",
    "iso:country":"CO",
    "wof:name":"La Palmera",
    "wof:placetype":"locality"
},
  "geometry": {"coordinates":[-76.251,4.12874],"type":"Point"}
}