{
  "type": "Feature",
  "properties": {
    "gn:admin1_code":"19.0",
    "gn:admin2_code":"50124.0",
    "gn:asciiname":"Pernambuco",
    "gn:country_code":"CO",
    "gn:dem":193,
    "gn:feature_class":"P",
    "gn:feature_code":"PPL",
    "gn:name":"Pernambuco",
    "gn:population":0,
    "gn:timezone":"America/Bogota",
    "iso:country":"CO",
    "wof:name":"Pernambuco",
    "wof:placetype":"locality"
},
  "geometry": {"coordinates":[-73.05237,4.28853],"type":"Point"}
}