{
  "type": "Feature",
  "properties": {
    "gn:admin1_code":"35",
    "gn:admin2_code":"13657.0",
    "gn:asciiname":"Corralito",
    "gn:country_code":"CO",
    "gn:dem":65,
    "gn:feature_class":"P",
    "gn:feature_code":"PPL",
    "gn:name":"Corralito",
    "gn:population":0,
    "gn:timezone":"America/Bogota",
    "iso:country":"CO",
    "name:cat_x_preferred":[
        "Corralito"
    ],
    "name:deu_x_preferred":[
        "Corralito"
    ],
    "name:epo_x_preferred":[
        "Bebokorteto"
    ],
    "name:eus_x_preferred":[
        "Corralito"
    ],
    "name:fra_x_preferred":[
        "Corralito"
    ],
    "name:ita_x_preferred":[
        "Corralito"
    ],
    "name:por_x_preferred":[
        "Corralito"
    ],
    "name:rus_x_preferred":[
        "\u041a\u043e\u0440\u0440\u0430\u043b\u0438\u0442\u043e"
    ],
    "name:spa_x_preferred":[
        "Corralito"
    ],
    "name:und_x_variant":[
        "Caser\u00edo Corralito"
    ],
    "wof:name":"Corralito",
    "wof:placetype":"locality"
},
  "geometry": {"coordinates":[-74.97551999999997,9.92724],"type":"Point"}
}