{
  "type": "Feature",
  "properties": {
    "gn:admin1_code":"35",
    "gn:admin2_code":"13657.0",
    "gn:asciiname":"Corralito",
    "gn:country_code":"CO",
    "gn:dem":65,
    "gn:feature_class":"P",
    "gn:feature_code":"PPL",
    "gn:name":"Corralito",
    "gn:population":0,
    "gn:timezone":"America/Bogota",
    "iso:country":"CO",
    "name:und_x_variant":[
        "Caser\u00edo Corralito",
        "Corralito"
    ],
    "wof:name":"Corralito",
    "wof:placetype":"locality"
},
  "geometry": {"coordinates":[-74.97551999999997,9.92724],"type":"Point"}
}