{
  "type": "Feature",
  "properties": {
    "gn:country":"CO",
    "gn:fcode":"PPLX",
    "gn:population":0,
    "iso:country":"CO",
    "name:arg_x_preferred":[
        "La Pe\u00f1a"
    ],
    "name:ast_x_preferred":[
        "La Pe\u00f1a"
    ],
    "name:ceb_x_preferred":[
        "La Pe\u00f1a"
    ],
    "name:deu_x_preferred":[
        "La Pe\u00f1a"
    ],
    "name:eus_x_preferred":[
        "La Pe\u00f1a"
    ],
    "name:fra_x_preferred":[
        "La Pe\u00f1a"
    ],
    "name:ita_x_preferred":[
        "La Pe\u00f1a"
    ],
    "name:nld_x_preferred":[
        "La Pe\u00f1a"
    ],
    "name:sco_x_preferred":[
        "La Pe\u00f1a"
    ],
    "name:spa_x_colloquial":[
        "La Penya",
        "La Pena"
    ],
    "name:spa_x_preferred":[
        "La Pe\u00f1a"
    ],
    "name:swe_x_preferred":[
        "La Pe\u00f1a"
    ],
    "name:war_x_preferred":[
        "La Pe\u00f1a"
    ],
    "qs:gn_adm0_cc":"CO",
    "qs:gn_fcode":"PPLX",
    "qs:gn_local":3688689,
    "qs:gn_namadm1":"34",
    "qs:gn_name":"La Pe\u00f1a",
    "qs:local_max":9363,
    "qs:local_sum":49081,
    "qs:localhoods":19,
    "qs:name":"La Pe\u00f1a",
    "qs:name_adm0":"Colombia",
    "qs:name_adm1":"Distrito Especial",
    "qs:name_adm2":"Santafe de Bogota D.c.",
    "qs:name_local":"Bogot\u00e1",
    "qs:photo_max":42,
    "qs:photo_sum":197,
    "qs:placetype":"Suburb",
    "qs:quad_count":23,
    "qs:woe_adm0":23424787,
    "qs:woe_adm1":2345079,
    "qs:woe_adm2":26796754,
    "qs:woe_lau":0,
    "qs:woe_local":368148,
    "qs:woe_ver":"7.10.0",
    "qs_pg:aaroncc":"CO",
    "qs_pg:gn_country":"CO",
    "qs_pg:gn_fcode":"PPLX",
    "qs_pg:gn_pop":0,
    "qs_pg:name":"La Pe\u00f1a",
    "qs_pg:name_adm0":"Colombia",
    "qs_pg:name_adm1":"Distrito Especial",
    "qs_pg:photos":145,
    "qs_pg:photos_1k":29,
    "qs_pg:photos_9k":1,
    "qs_pg:photos_9r":3,
    "qs_pg:photos_all":145,
    "qs_pg:photos_sr":3,
    "qs_pg:pop_sr":0,
    "qs_pg:qs_pg_placetype":"neighbourhood",
    "qs_pg:qs_pg_placetype_gp":"Suburb",
    "qs_pg:woe_adm0":23424787,
    "wof:lang":[
        "spa"
    ],
    "wof:name":"La Pe\u00f1a",
    "wof:placetype":"neighbourhood"
},
  "geometry": {"coordinates":[-74.06994899999999,4.587768],"type":"Point"}
}