{
  "type": "Feature",
  "properties": {
    "gn:admin1_code":"28",
    "gn:admin2_code":"73547.0",
    "gn:asciiname":"Chicala",
    "gn:country_code":"CO",
    "gn:dem":343,
    "gn:feature_class":"P",
    "gn:feature_code":"PPL",
    "gn:name":"Chical\u00e1",
    "gn:population":0,
    "gn:timezone":"America/Bogota",
    "iso:country":"CO",
    "name:por_x_preferred":[
        "Chicala"
    ],
    "name:und_x_variant":[
        "Chicaleo",
        "Chical\u00e1"
    ],
    "wof:name":"Chicala",
    "wof:placetype":"locality"
},
  "geometry": {"coordinates":[-74.85769000000001,4.55882],"type":"Point"}
}