{
  "type": "Feature",
  "properties": {
    "gn:admin1_code":"2.0",
    "gn:admin2_code":"5543.0",
    "gn:asciiname":"El Aquilon",
    "gn:country_code":"CO",
    "gn:dem":2660,
    "gn:feature_class":"P",
    "gn:feature_code":"PPL",
    "gn:name":"El Aquil\u00f3n",
    "gn:population":0,
    "gn:timezone":"America/Bogota",
    "iso:country":"CO",
    "wof:name":"El Aquilon",
    "wof:placetype":"locality"
},
  "geometry": {"coordinates":[-75.97610999999998,6.99444],"type":"Point"}
}