{
  "type": "Feature",
  "properties": {
    "gn:admin1_code":"38.0",
    "gn:admin2_code":"47980.0",
    "gn:asciiname":"Tucurinca",
    "gn:country_code":"CO",
    "gn:dem":37,
    "gn:feature_class":"P",
    "gn:feature_code":"PPL",
    "gn:name":"Tucurinca",
    "gn:population":0,
    "gn:timezone":"America/Bogota",
    "iso:country":"CO",
    "wof:name":"Tucurinca",
    "wof:placetype":"locality"
},
  "geometry": {"coordinates":[-74.16722,10.65166],"type":"Point"}
}