{
  "type": "Feature",
  "properties": {
    "gn:admin1_code":"26.0",
    "gn:admin2_code":"68167.0",
    "gn:asciiname":"La Alianza",
    "gn:country_code":"CO",
    "gn:dem":1784,
    "gn:feature_class":"P",
    "gn:feature_code":"PPL",
    "gn:name":"La Alianza",
    "gn:population":0,
    "gn:timezone":"America/Bogota",
    "iso:country":"CO",
    "wof:name":"La Alianza",
    "wof:placetype":"locality"
},
  "geometry": {"coordinates":[-73.2069,6.07858],"type":"Point"}
}