{
  "type": "Feature",
  "properties": {
    "gn:admin1_code":"35.0",
    "gn:admin2_code":"13657.0",
    "gn:asciiname":"El Desprecio",
    "gn:country_code":"CO",
    "gn:dem":192,
    "gn:feature_class":"P",
    "gn:feature_code":"PPL",
    "gn:name":"El Desprecio",
    "gn:population":0,
    "gn:timezone":"America/Bogota",
    "iso:country":"CO",
    "wof:name":"El Desprecio",
    "wof:placetype":"locality"
},
  "geometry": {"coordinates":[-75.02974,10.10373],"type":"Point"}
}