{
  "type": "Feature",
  "properties": {
    "gn:admin1_code":"28.0",
    "gn:admin2_code":"73616.0",
    "gn:asciiname":"Puerto Gaitan",
    "gn:country_code":"CO",
    "gn:dem":1557,
    "gn:feature_class":"P",
    "gn:feature_code":"PPL",
    "gn:name":"Puerto Gait\u00e1n",
    "gn:population":0,
    "gn:timezone":"America/Bogota",
    "iso:country":"CO",
    "wof:name":"Puerto Gaitan",
    "wof:placetype":"locality"
},
  "geometry": {"coordinates":[-75.74333,3.5775],"type":"Point"}
}