{
  "type": "Feature",
  "properties": {
    "gn:admin1_code":"19",
    "gn:admin2_code":"50689",
    "gn:asciiname":"El Embarcadero",
    "gn:country_code":"CO",
    "gn:dem":429,
    "gn:feature_class":"P",
    "gn:feature_code":"PPL",
    "gn:name":"El Embarcadero",
    "gn:population":0,
    "gn:timezone":"America/Bogota",
    "iso:country":"CO",
    "name:spa_x_preferred":[
        "El Embarcadero"
    ],
    "wof:name":"El Embarcadero",
    "wof:placetype":"locality"
},
  "geometry": {"coordinates":[-73.68170000000001,3.72636],"type":"Point"}
}