{
  "type": "Feature",
  "properties": {
    "gn:admin1_code":"2.0",
    "gn:admin2_code":"5411.0",
    "gn:asciiname":"Los Penoles",
    "gn:country_code":"CO",
    "gn:dem":2276,
    "gn:feature_class":"P",
    "gn:feature_code":"PPL",
    "gn:name":"Los Pe\u00f1oles",
    "gn:population":0,
    "gn:timezone":"America/Bogota",
    "iso:country":"CO",
    "wof:name":"Los Penoles",
    "wof:placetype":"locality"
},
  "geometry": {"coordinates":[-75.73639,6.7125],"type":"Point"}
}