{
  "type": "Feature",
  "properties": {
    "gn:admin1_code":"28",
    "gn:admin2_code":"73585.0",
    "gn:asciiname":"Florencia",
    "gn:country_code":"CO",
    "gn:dem":294,
    "gn:feature_class":"P",
    "gn:feature_code":"PPL",
    "gn:name":"Florencia",
    "gn:population":0,
    "gn:timezone":"America/Bogota",
    "iso:country":"CO",
    "wof:name":"Florencia",
    "wof:placetype":"locality"
},
  "geometry": {"coordinates":[-74.90000000000001,3.93333],"type":"Point"}
}