{
  "type": "Feature",
  "properties": {
    "gn:admin1_code":"28",
    "gn:admin2_code":"73585.0",
    "gn:asciiname":"Florencia",
    "gn:country_code":"CO",
    "gn:dem":294,
    "gn:feature_class":"P",
    "gn:feature_code":"PPL",
    "gn:name":"Florencia",
    "gn:population":0,
    "gn:timezone":"America/Bogota",
    "iso:country":"CO",
    "name:ceb_x_preferred":[
        "Florencia"
    ],
    "name:dan_x_preferred":[
        "Florencia"
    ],
    "name:deu_x_preferred":[
        "Florencia"
    ],
    "name:fra_x_preferred":[
        "Florencia"
    ],
    "name:glg_x_preferred":[
        "Florencia"
    ],
    "name:hun_x_preferred":[
        "Florencia"
    ],
    "name:ita_x_preferred":[
        "Florencia"
    ],
    "name:kor_x_preferred":[
        "\ud50c\ub85c\ub80c\uc2dc\uc544"
    ],
    "name:nld_x_preferred":[
        "Florencia"
    ],
    "name:por_x_preferred":[
        "Florencia"
    ],
    "name:sco_x_preferred":[
        "Florencia"
    ],
    "name:spa_x_preferred":[
        "Florencia"
    ],
    "name:swe_x_preferred":[
        "Florencia"
    ],
    "name:tgl_x_preferred":[
        "Florencia"
    ],
    "name:ukr_x_preferred":[
        "\u0424\u043b\u043e\u0440\u0435\u043d\u0446\u0456\u044f"
    ],
    "name:vie_x_preferred":[
        "Florencia"
    ],
    "name:war_x_preferred":[
        "Florencia"
    ],
    "wof:name":"Florencia",
    "wof:placetype":"locality"
},
  "geometry": {"coordinates":[-74.90000000000001,3.93333],"type":"Point"}
}