{
  "type": "Feature",
  "properties": {
    "gn:admin1_code":"28.0",
    "gn:admin2_code":"73352.0",
    "gn:asciiname":"Vereda Palmas",
    "gn:country_code":"CO",
    "gn:dem":1008,
    "gn:feature_class":"P",
    "gn:feature_code":"PPLL",
    "gn:name":"Vereda Palmas",
    "gn:population":0,
    "gn:timezone":"America/Bogota",
    "iso:country":"CO",
    "name:spa_x_preferred":[
        "Vereda Palmas"
    ],
    "wof:name":"Vereda Palmas",
    "wof:placetype":"locality"
},
  "geometry": {"coordinates":[-74.56222,4.24648],"type":"Point"}
}