{
  "type": "Feature",
  "properties": {
    "gn:admin1_code":"16.0",
    "gn:asciiname":"Alpes",
    "gn:country_code":"CO",
    "gn:dem":1717,
    "gn:feature_class":"P",
    "gn:feature_code":"PPL",
    "gn:name":"Alpes",
    "gn:population":0,
    "gn:timezone":"America/Bogota",
    "iso:country":"CO",
    "name:fas_x_preferred":[
        "\u0622\u0644\u067e"
    ],
    "name:fra_x_preferred":[
        "Alpes"
    ],
    "name:oci_x_preferred":[
        "Aups"
    ],
    "name:por_x_preferred":[
        "Alpes"
    ],
    "name:spa_x_preferred":[
        "Alpes"
    ],
    "wof:name":"Alpes",
    "wof:placetype":"locality"
},
  "geometry": {"coordinates":[-74.87385999999999,3.4485],"type":"Point"}
}