{
  "type": "Feature",
  "properties": {
    "gn:admin1_code":"10.0",
    "gn:admin2_code":"20001.0",
    "gn:asciiname":"Okla",
    "gn:country_code":"CO",
    "gn:dem":124,
    "gn:feature_class":"P",
    "gn:feature_code":"PPL",
    "gn:name":"Okla",
    "gn:population":0,
    "gn:timezone":"America/Bogota",
    "iso:country":"CO",
    "wof:name":"Okla",
    "wof:placetype":"locality"
},
  "geometry": {"coordinates":[-73.36848000000001,10.33967],"type":"Point"}
}