{
  "type": "Feature",
  "properties": {
    "gn:admin1_code":"9",
    "gn:admin2_code":"19780.0",
    "gn:asciiname":"La Toma",
    "gn:country_code":"CO",
    "gn:dem":1451,
    "gn:feature_class":"P",
    "gn:feature_code":"PPL",
    "gn:name":"La Toma",
    "gn:population":0,
    "gn:timezone":"America/Bogota",
    "iso:country":"CO",
    "wof:name":"La Toma",
    "wof:placetype":"locality"
},
  "geometry": {"coordinates":[-76.69620999999999,2.91402],"type":"Point"}
}