{
  "type": "Feature",
  "properties": {
    "gn:admin1_code":"9.0",
    "gn:admin2_code":"19142.0",
    "gn:asciiname":"San Nicolas",
    "gn:country_code":"CO",
    "gn:dem":1025,
    "gn:feature_class":"P",
    "gn:feature_code":"PPL",
    "gn:name":"San Nicol\u00e1s",
    "gn:population":0,
    "gn:timezone":"America/Bogota",
    "iso:country":"CO",
    "name:spa_x_preferred":[
        "San Nicol\u00e1s"
    ],
    "wof:name":"San Nicolas",
    "wof:placetype":"locality"
},
  "geometry": {"coordinates":[-76.43019,3.05062],"type":"Point"}
}