{
  "type": "Feature",
  "properties": {
    "gn:admin1_code":"12",
    "gn:admin2_code":"23580.0",
    "gn:asciiname":"Brillante",
    "gn:country_code":"CO",
    "gn:dem":70,
    "gn:feature_class":"P",
    "gn:feature_code":"PPL",
    "gn:name":"Brillante",
    "gn:population":0,
    "gn:timezone":"America/Bogota",
    "iso:country":"CO",
    "wof:name":"Brillante",
    "wof:placetype":"locality"
},
  "geometry": {"coordinates":[-75.68333,8.01667],"type":"Point"}
}