{
  "type": "Feature",
  "properties": {
    "gn:admin1_code":"38.0",
    "gn:admin2_code":"47551.0",
    "gn:asciiname":"Santuario",
    "gn:country_code":"CO",
    "gn:dem":56,
    "gn:feature_class":"P",
    "gn:feature_code":"PPL",
    "gn:name":"Santuario",
    "gn:population":0,
    "gn:timezone":"America/Bogota",
    "iso:country":"CO",
    "wof:name":"Santuario",
    "wof:placetype":"locality"
},
  "geometry": {"coordinates":[-74.26586,10.46828],"type":"Point"}
}