{
  "type": "Feature",
  "properties": {
    "gn:admin1_code":"12",
    "gn:admin2_code":"23168.0",
    "gn:asciiname":"Loma Retonio",
    "gn:country_code":"CO",
    "gn:dem":50,
    "gn:feature_class":"P",
    "gn:feature_code":"PPL",
    "gn:name":"Loma Retonio",
    "gn:population":0,
    "gn:timezone":"America/Bogota",
    "iso:country":"CO",
    "wof:name":"Loma Retonio",
    "wof:placetype":"locality"
},
  "geometry": {"coordinates":[-75.56995999999999,9.15372],"type":"Point"}
}