{
  "type": "Feature",
  "properties": {
    "gn:admin1_code":"10",
    "gn:admin2_code":"20517.0",
    "gn:asciiname":"Recreo",
    "gn:country_code":"CO",
    "gn:dem":99,
    "gn:feature_class":"P",
    "gn:feature_code":"PPL",
    "gn:name":"Recreo",
    "gn:population":0,
    "gn:timezone":"America/Bogota",
    "iso:country":"CO",
    "name:arg_x_preferred":[
        "Recreo"
    ],
    "name:cat_x_preferred":[
        "Recreo"
    ],
    "name:ces_x_preferred":[
        "Recreo"
    ],
    "name:deu_x_preferred":[
        "Recreo"
    ],
    "name:epo_x_preferred":[
        "Recreo"
    ],
    "name:fra_x_preferred":[
        "Recreo"
    ],
    "name:glg_x_preferred":[
        "Recreo"
    ],
    "name:hye_x_preferred":[
        "\u054c\u0565\u056f\u0580\u0565\u0578"
    ],
    "name:ind_x_preferred":[
        "Recreo"
    ],
    "name:ita_x_preferred":[
        "Recreo"
    ],
    "name:jpn_x_preferred":[
        "\u30ec\u30af\u30ec\u30aa"
    ],
    "name:kor_x_preferred":[
        "\ub808\ud06c\ub808\uc624"
    ],
    "name:lit_x_preferred":[
        "Rekreo"
    ],
    "name:nld_x_preferred":[
        "Recreo"
    ],
    "name:pol_x_preferred":[
        "Recreo"
    ],
    "name:por_x_preferred":[
        "Recreo"
    ],
    "name:rus_x_preferred":[
        "\u0420\u0435\u043a\u0440\u0435\u043e"
    ],
    "name:slk_x_preferred":[
        "Recreo"
    ],
    "name:spa_x_preferred":[
        "Recreo"
    ],
    "name:zho_x_preferred":[
        "\u96f7\u514b\u96f7\u5967"
    ],
    "wof:name":"Recreo",
    "wof:placetype":"locality"
},
  "geometry": {"coordinates":[-73.62975,9.01198],"type":"Point"}
}