{
  "type": "Feature",
  "properties": {
    "gn:admin1_code":"33",
    "gn:admin2_code":"25885.0",
    "gn:asciiname":"Cacagual",
    "gn:country_code":"CO",
    "gn:dem":444,
    "gn:feature_class":"P",
    "gn:feature_code":"PPL",
    "gn:name":"Cacagual",
    "gn:population":0,
    "gn:timezone":"America/Bogota",
    "iso:country":"CO",
    "wof:name":"Cacagual",
    "wof:placetype":"locality"
},
  "geometry": {"coordinates":[-74.45,5.66667],"type":"Point"}
}