{
  "type": "Feature",
  "properties": {
    "gn:admin1_code":"35",
    "gn:admin2_code":"13468.0",
    "gn:asciiname":"Ancon",
    "gn:country_code":"CO",
    "gn:dem":18,
    "gn:feature_class":"P",
    "gn:feature_code":"PPL",
    "gn:name":"Anc\u00f3n",
    "gn:population":0,
    "gn:timezone":"America/Bogota",
    "iso:country":"CO",
    "name:nld_x_preferred":[
        "Ancon"
    ],
    "name:und_x_variant":[
        "Caserio Ancon",
        "Anc\u00f3n"
    ],
    "wof:name":"Ancon",
    "wof:placetype":"locality"
},
  "geometry": {"coordinates":[-74.52698000000002,9.22594],"type":"Point"}
}