{
  "type": "Feature",
  "properties": {
    "gn:admin1_code":"33.0",
    "gn:admin2_code":"25758.0",
    "gn:asciiname":"San Carlos",
    "gn:country_code":"CO",
    "gn:dem":2784,
    "gn:feature_class":"P",
    "gn:feature_code":"PPL",
    "gn:name":"San Carlos",
    "gn:population":0,
    "gn:timezone":"America/Bogota",
    "iso:country":"CO",
    "wof:name":"San Carlos",
    "wof:placetype":"locality"
},
  "geometry": {"coordinates":[-73.93278000000002,4.85694],"type":"Point"}
}