{
  "type": "Feature",
  "properties": {
    "gn:admin1_code":"26.0",
    "gn:admin2_code":"68755.0",
    "gn:asciiname":"Morros",
    "gn:country_code":"CO",
    "gn:dem":1424,
    "gn:feature_class":"P",
    "gn:feature_code":"PPL",
    "gn:name":"Morros",
    "gn:population":0,
    "gn:timezone":"America/Bogota",
    "iso:country":"CO",
    "name:bpy_x_preferred":[
        "\u09ae\u09cb\u09b0\u09cd\u09b0\u09cb\u09b8"
    ],
    "name:ceb_x_preferred":[
        "Morros"
    ],
    "name:eus_x_preferred":[
        "Morros"
    ],
    "name:fra_x_preferred":[
        "Morros"
    ],
    "name:hye_x_preferred":[
        "\u0544\u0578\u057c\u0578\u0582\u057d"
    ],
    "name:ita_x_preferred":[
        "Morros"
    ],
    "name:kaz_x_preferred":[
        "\u041c\u043e\u0440\u0440\u0443\u0441"
    ],
    "name:nld_x_preferred":[
        "Morros"
    ],
    "name:nor_x_preferred":[
        "Morros"
    ],
    "name:por_x_preferred":[
        "Morros"
    ],
    "name:ron_x_preferred":[
        "Morros"
    ],
    "name:rus_x_preferred":[
        "\u041c\u043e\u0440\u0440\u0443\u0441"
    ],
    "name:vie_x_preferred":[
        "Morros"
    ],
    "name:vol_x_preferred":[
        "Morros"
    ],
    "name:war_x_preferred":[
        "Morros"
    ],
    "name:zho_x_preferred":[
        "\u83ab\u9c81\u65af"
    ],
    "wof:name":"Morros",
    "wof:placetype":"locality"
},
  "geometry": {"coordinates":[-73.22152,6.49729],"type":"Point"}
}