{
  "type": "Feature",
  "properties": {
    "gn:admin1_code":"32",
    "gn:admin2_code":"85410.0",
    "gn:asciiname":"Guayuriba",
    "gn:country_code":"CO",
    "gn:dem":159,
    "gn:feature_class":"P",
    "gn:feature_code":"PPL",
    "gn:name":"Guayuriba",
    "gn:population":0,
    "gn:timezone":"America/Bogota",
    "iso:country":"CO",
    "wof:name":"Guayuriba",
    "wof:placetype":"locality"
},
  "geometry": {"coordinates":[-72.56667,4.33333],"type":"Point"}
}