{
  "type": "Feature",
  "properties": {
    "gn:admin1_code":"28",
    "gn:admin2_code":"73236",
    "gn:asciiname":"Balalaica",
    "gn:country_code":"CO",
    "gn:dem":1067,
    "gn:feature_class":"P",
    "gn:feature_code":"PPL",
    "gn:name":"Balalaica",
    "gn:population":0,
    "gn:timezone":"America/Bogota",
    "iso:country":"CO",
    "name:spa_x_preferred":[
        "Balalaica"
    ],
    "wof:name":"Balalaica",
    "wof:placetype":"locality"
},
  "geometry": {"coordinates":[-74.89161999999997,3.57626],"type":"Point"}
}