{
  "type": "Feature",
  "properties": {
    "iso:country":"CO",
    "name:ast_x_preferred":[
        "Sumatansa"
    ],
    "name:ceb_x_preferred":[
        "Sutatausa"
    ],
    "name:eng_x_preferred":[
        "Sutatausa"
    ],
    "name:fra_x_preferred":[
        "Sutatausa"
    ],
    "name:ita_x_preferred":[
        "Sutatausa"
    ],
    "name:kat_x_preferred":[
        "\u10e1\u10e3\u10e2\u10d0\u10e2\u10d0\u10e3\u10e1\u10d0"
    ],
    "name:msa_x_preferred":[
        "Sutatausa"
    ],
    "name:nan_x_preferred":[
        "Sutatausa"
    ],
    "name:nld_x_preferred":[
        "Sutatausa"
    ],
    "name:sco_x_preferred":[
        "Sutatausa"
    ],
    "name:spa_x_preferred":[
        "Sutatausa"
    ],
    "name:spa_x_variant":[
        "Sumatansa"
    ],
    "name:swe_x_preferred":[
        "Sutatausa"
    ],
    "name:tgl_x_preferred":[
        "Sutatausa"
    ],
    "name:vie_x_preferred":[
        "Sutatausa"
    ],
    "name:war_x_preferred":[
        "Sutatausa"
    ],
    "name:zho_min_nan_x_preferred":[
        "Sutatausa"
    ],
    "name:zho_x_preferred":[
        "\u8607\u5854\u9676\u85a9"
    ],
    "qs:gn_country":"CO",
    "qs:gn_fcode":"PPL",
    "qs:gn_pop":1332,
    "qs:name":"Sutatausa",
    "qs:name_adm0":"Colombia",
    "qs:name_adm1":"Cundinamarca",
    "qs:photos":67,
    "qs:photos_1k":14,
    "qs:photos_9k":1,
    "qs:photos_9r":2,
    "qs:photos_all":67,
    "qs:photos_sr":2,
    "qs:placetype":"Town",
    "qs:pop_sr":"3",
    "qs:woe_adm0":23424787,
    "wof:name":"Sutatausa",
    "wof:placetype":"locality",
    "wof:population":1332
},
  "geometry": {"coordinates":[-73.85238,5.24779],"type":"Point"}
}