{
  "type": "Feature",
  "properties": {
    "gn:admin1_code":"9",
    "gn:admin2_code":"19130.0",
    "gn:asciiname":"Caserio La Capilla",
    "gn:country_code":"CO",
    "gn:dem":1754,
    "gn:feature_class":"P",
    "gn:feature_code":"PPL",
    "gn:name":"Caser\u00edo La Capilla",
    "gn:population":0,
    "gn:timezone":"America/Bogota",
    "iso:country":"CO",
    "wof:name":"Caserio La Capilla",
    "wof:placetype":"locality"
},
  "geometry": {"coordinates":[-76.62361,2.58806],"type":"Point"}
}