{
  "type": "Feature",
  "properties": {
    "gn:admin1_code":"11",
    "gn:admin2_code":"27135.0",
    "gn:asciiname":"Boca de Raspadura",
    "gn:country_code":"CO",
    "gn:dem":62,
    "gn:feature_class":"P",
    "gn:feature_code":"PPL",
    "gn:name":"Boca de Raspadura",
    "gn:population":0,
    "gn:timezone":"America/Bogota",
    "iso:country":"CO",
    "name:und_x_variant":[
        "Raspadura",
        "Boca de Raspadura"
    ],
    "wof:name":"Boca de Raspadura",
    "wof:placetype":"locality"
},
  "geometry": {"coordinates":[-76.71236999999998,5.26447],"type":"Point"}
}