{
  "type": "Feature",
  "properties": {
    "gn:admin1_code":"20.0",
    "gn:admin2_code":"52540.0",
    "gn:asciiname":"Restrepo",
    "gn:country_code":"CO",
    "gn:dem":363,
    "gn:feature_class":"P",
    "gn:feature_code":"PPL",
    "gn:name":"Restrepo",
    "gn:population":0,
    "gn:timezone":"America/Bogota",
    "iso:country":"CO",
    "wof:name":"Restrepo",
    "wof:placetype":"locality"
},
  "geometry": {"coordinates":[-77.48333000000002,1.65],"type":"Point"}
}