{
  "type": "Feature",
  "properties": {
    "gn:admin1_code":"20.0",
    "gn:admin2_code":"52540.0",
    "gn:asciiname":"Restrepo",
    "gn:country_code":"CO",
    "gn:dem":363,
    "gn:feature_class":"P",
    "gn:feature_code":"PPL",
    "gn:name":"Restrepo",
    "gn:population":0,
    "gn:timezone":"America/Bogota",
    "iso:country":"CO",
    "name:ceb_x_preferred":[
        "Restrepo"
    ],
    "name:deu_x_preferred":[
        "Restrepo"
    ],
    "name:fra_x_preferred":[
        "Restrepo"
    ],
    "name:ita_x_preferred":[
        "Restrepo"
    ],
    "name:nld_x_preferred":[
        "Restrepo"
    ],
    "name:rus_x_preferred":[
        "\u0420\u0435\u0441\u0442\u0440\u0435\u043f\u043e"
    ],
    "name:spa_x_preferred":[
        "Restrepo"
    ],
    "name:tgl_x_preferred":[
        "Restrepo"
    ],
    "name:vie_x_preferred":[
        "Restrepo"
    ],
    "wof:name":"Restrepo",
    "wof:placetype":"locality"
},
  "geometry": {"coordinates":[-77.48333000000002,1.65],"type":"Point"}
}