{
  "type": "Feature",
  "properties": {
    "gn:admin1_code":"9.0",
    "gn:admin2_code":"19318.0",
    "gn:asciiname":"La Franca",
    "gn:country_code":"CO",
    "gn:dem":139,
    "gn:feature_class":"P",
    "gn:feature_code":"PPL",
    "gn:name":"La Franca",
    "gn:population":0,
    "gn:timezone":"America/Bogota",
    "iso:country":"CO",
    "wof:name":"La Franca",
    "wof:placetype":"locality"
},
  "geometry": {"coordinates":[-77.70279000000002,2.18615],"type":"Point"}
}