{
  "type": "Feature",
  "properties": {
    "gn:admin1_code":"36.0",
    "gn:admin2_code":"15322.0",
    "gn:asciiname":"Las Juntas",
    "gn:country_code":"CO",
    "gn:dem":1402,
    "gn:feature_class":"P",
    "gn:feature_code":"PPL",
    "gn:name":"Las Juntas",
    "gn:population":0,
    "gn:timezone":"America/Bogota",
    "iso:country":"CO",
    "name:ceb_x_preferred":[
        "Las Juntas"
    ],
    "name:deu_x_preferred":[
        "Las Juntas"
    ],
    "name:spa_x_preferred":[
        "Las Juntas"
    ],
    "name:swe_x_preferred":[
        "Las Juntas"
    ],
    "wof:name":"Las Juntas",
    "wof:placetype":"locality"
},
  "geometry": {"coordinates":[-73.51028000000002,4.99861],"type":"Point"}
}