{
  "type": "Feature",
  "properties": {
    "gn:admin1_code":"9",
    "gn:asciiname":"Carpintero",
    "gn:country_code":"CO",
    "gn:dem":365,
    "gn:feature_class":"P",
    "gn:feature_code":"PPL",
    "gn:name":"Carpintero",
    "gn:population":0,
    "gn:timezone":"America/Bogota",
    "iso:country":"CO",
    "wof:name":"Carpintero",
    "wof:placetype":"locality"
},
  "geometry": {"coordinates":[-73.81528,2.79167],"type":"Point"}
}