{
  "type": "Feature",
  "properties": {
    "gn:admin1_code":"27",
    "gn:admin2_code":"70235.0",
    "gn:asciiname":"Los Borrachos",
    "gn:country_code":"CO",
    "gn:dem":111,
    "gn:feature_class":"P",
    "gn:feature_code":"PPL",
    "gn:name":"Los Borrachos",
    "gn:population":0,
    "gn:timezone":"America/Bogota",
    "iso:country":"CO",
    "wof:name":"Los Borrachos",
    "wof:placetype":"locality"
},
  "geometry": {"coordinates":[-75.05648000000002,9.19029],"type":"Point"}
}