{
  "type": "Feature",
  "properties": {
    "gn:admin1_code":"8.0",
    "gn:admin2_code":"18756.0",
    "gn:asciiname":"Palmeras",
    "gn:country_code":"CO",
    "gn:dem":293,
    "gn:feature_class":"P",
    "gn:feature_code":"PPL",
    "gn:name":"Palmeras",
    "gn:population":0,
    "gn:timezone":"America/Bogota",
    "iso:country":"CO",
    "name:spa_x_preferred":[
        "Palmeras"
    ],
    "name:und_x_variant":[
        "Caser\u00edo Palmeras"
    ],
    "wof:name":"Palmeras",
    "wof:placetype":"locality"
},
  "geometry": {"coordinates":[-75.06756999999998,1.08866],"type":"Point"}
}