{
  "type": "Feature",
  "properties": {
    "gn:admin1_code":"38",
    "gn:admin2_code":"47660.0",
    "gn:asciiname":"Palmira",
    "gn:country_code":"CO",
    "gn:dem":187,
    "gn:feature_class":"P",
    "gn:feature_code":"PPL",
    "gn:name":"Palmira",
    "gn:population":0,
    "gn:timezone":"America/Bogota",
    "iso:country":"CO",
    "name:rus_x_preferred":[
        "\u041f\u0430\u043b\u044c\u043c\u0438\u0440\u0430"
    ],
    "name:und_x_variant":[
        "La Algeria",
        "Palmira"
    ],
    "wof:name":"Palmira",
    "wof:placetype":"locality"
},
  "geometry": {"coordinates":[-74.27041,9.89958],"type":"Point"}
}