{
  "type": "Feature",
  "properties": {
    "gn:admin1_code":"2.0",
    "gn:admin2_code":"5001.0",
    "gn:asciiname":"Sector La Arenera",
    "gn:country_code":"CO",
    "gn:dem":2116,
    "gn:feature_class":"P",
    "gn:feature_code":"PPLL",
    "gn:name":"Sector La Arenera",
    "gn:population":0,
    "gn:timezone":"America/Bogota",
    "iso:country":"CO",
    "name:spa_x_preferred":[
        "Sector La Arenera"
    ],
    "wof:name":"Sector La Arenera",
    "wof:placetype":"locality"
},
  "geometry": {"coordinates":[-75.65576999999998,6.28172],"type":"Point"}
}