{
  "type": "Feature",
  "properties": {
    "gn:admin1_code":"20.0",
    "gn:admin2_code":"52110.0",
    "gn:asciiname":"Meneses",
    "gn:country_code":"CO",
    "gn:dem":2476,
    "gn:feature_class":"P",
    "gn:feature_code":"PPL",
    "gn:name":"Meneses",
    "gn:population":0,
    "gn:timezone":"America/Bogota",
    "iso:country":"CO",
    "wof:name":"Meneses",
    "wof:placetype":"locality"
},
  "geometry": {"coordinates":[-77.21904000000001,1.32068],"type":"Point"}
}