{
  "type": "Feature",
  "properties": {
    "gn:country":"CO",
    "gn:fcode":"PPL",
    "gn:pop":4313,
    "iso:country":"CO",
    "name:chi_x_preferred":[
        "\u5b54\u79d1\u723e\u8fea\u4e9e\u6e2f"
    ],
    "name:dut_x_preferred":[
        "Puerto Concordia"
    ],
    "name:eng_x_preferred":[
        "Puerto Concordia"
    ],
    "name:fre_x_preferred":[
        "Puerto Concordia"
    ],
    "name:geo_x_preferred":[
        "\u10de\u10e3\u10d4\u10e0\u10e2\u10dd-\u10d9\u10dd\u10dc\u10d9\u10dd\u10e0\u10d3\u10d8\u10d0"
    ],
    "name:ita_x_preferred":[
        "Puerto Concordia"
    ],
    "name:may_x_preferred":[
        "Puerto Concordia"
    ],
    "name:nan_x_preferred":[
        "Puerto Concordia"
    ],
    "name:por_x_preferred":[
        "Puerto Concordia"
    ],
    "name:spa_x_preferred":[
        "Puerto Concordia"
    ],
    "name:swe_x_preferred":[
        "Puerto Concordia"
    ],
    "name:tgl_x_preferred":[
        "Puerto Concordia"
    ],
    "name:unk_x_variant":[
        "Concordia"
    ],
    "name:war_x_preferred":[
        "Puerto Concordia"
    ],
    "qs:name":"Puerto Concordia",
    "qs:photos_9r":0,
    "qs:photos_sr":0,
    "qs:pop_sr":"4",
    "wd:wordcount":39,
    "wof:name":"Puerto Concordia",
    "wof:placetype":"locality",
    "wof:population":4313
},
  "geometry": {"coordinates":[-72.75724,2.62206],"type":"Point"}
}