{
  "type": "Feature",
  "properties": {
    "gn:country":"CO",
    "gn:fcode":"PPL",
    "gn:population":4313,
    "iso:country":"CO",
    "name:ast_x_preferred":[
        "Puerto Concordia"
    ],
    "name:ceb_x_preferred":[
        "Puerto Concordia"
    ],
    "name:deu_x_preferred":[
        "Puerto Concordia"
    ],
    "name:eng_x_preferred":[
        "Puerto Concordia"
    ],
    "name:fas_x_preferred":[
        "\u067e\u0648\u0631\u062a\u0648 \u06a9\u0646\u06a9\u0648\u0631\u062f\u06cc\u0627"
    ],
    "name:fra_x_preferred":[
        "Puerto Concordia"
    ],
    "name:gle_x_preferred":[
        "Puerto Concordia"
    ],
    "name:ita_x_preferred":[
        "Puerto Concordia"
    ],
    "name:jpn_x_preferred":[
        "\u30d7\u30a8\u30eb\u30c8\u30fb\u30b3\u30f3\u30b3\u30eb\u30c7\u30a3\u30a2"
    ],
    "name:kat_x_preferred":[
        "\u10de\u10e3\u10d4\u10e0\u10e2\u10dd-\u10d9\u10dd\u10dc\u10d9\u10dd\u10e0\u10d3\u10d8\u10d0"
    ],
    "name:msa_x_preferred":[
        "Puerto Concordia"
    ],
    "name:nan_x_preferred":[
        "Puerto Concordia"
    ],
    "name:nld_x_preferred":[
        "Puerto Concordia"
    ],
    "name:pol_x_preferred":[
        "Puerto Concordia"
    ],
    "name:por_x_preferred":[
        "Puerto Concordia"
    ],
    "name:spa_x_preferred":[
        "Puerto Concordia"
    ],
    "name:swe_x_preferred":[
        "Puerto Concordia"
    ],
    "name:tgl_x_preferred":[
        "Puerto Concordia"
    ],
    "name:und_x_variant":[
        "Concordia"
    ],
    "name:war_x_preferred":[
        "Puerto Concordia"
    ],
    "name:zho_x_preferred":[
        "\u5b54\u79d1\u723e\u8fea\u4e9e\u6e2f"
    ],
    "qs:name":"Puerto Concordia",
    "qs:photos_9r":0,
    "qs:photos_sr":0,
    "qs:pop_sr":"4",
    "wd:wordcount":39,
    "wof:name":"Puerto Concordia",
    "wof:placetype":"locality",
    "wof:population":4313
},
  "geometry": {"coordinates":[-72.75724,2.62206],"type":"Point"}
}