{
  "type": "Feature",
  "properties": {
    "gn:admin1_code":"36.0",
    "gn:admin2_code":"15401.0",
    "gn:asciiname":"La Victoria",
    "gn:country_code":"CO",
    "gn:dem":1450,
    "gn:feature_class":"P",
    "gn:feature_code":"PPLA2",
    "gn:name":"La Victoria",
    "gn:population":0,
    "gn:timezone":"America/Bogota",
    "iso:country":"CO",
    "name:bre_x_preferred":[
        "La Victoria"
    ],
    "name:ceb_x_preferred":[
        "La Victoria"
    ],
    "name:deu_x_preferred":[
        "La Victoria"
    ],
    "name:fra_x_preferred":[
        "La Victoria"
    ],
    "name:glg_x_preferred":[
        "La Victoria"
    ],
    "name:ita_x_preferred":[
        "La Victoria"
    ],
    "name:msa_x_preferred":[
        "La Victoria"
    ],
    "name:nld_x_preferred":[
        "La Victoria"
    ],
    "name:por_x_preferred":[
        "La Victoria"
    ],
    "name:rus_x_preferred":[
        "\u041b\u0430-\u0412\u0438\u043a\u0442\u043e\u0440\u0438\u044f"
    ],
    "name:swe_x_preferred":[
        "La Victoria"
    ],
    "name:und_x_variant":[
        "Victoria"
    ],
    "name:vie_x_preferred":[
        "La Victoria"
    ],
    "name:vol_x_preferred":[
        "La Victoria"
    ],
    "name:war_x_preferred":[
        "La Victoria"
    ],
    "wof:name":"La Victoria",
    "wof:placetype":"locality"
},
  "geometry": {"coordinates":[-74.23611,5.52583],"type":"Point"}
}