{
  "type": "Feature",
  "properties": {
    "gn:admin1_code":"36.0",
    "gn:admin2_code":"15401.0",
    "gn:asciiname":"La Victoria",
    "gn:country_code":"CO",
    "gn:dem":1450,
    "gn:feature_class":"P",
    "gn:feature_code":"PPLA2",
    "gn:name":"La Victoria",
    "gn:population":0,
    "gn:timezone":"America/Bogota",
    "iso:country":"CO",
    "name:und_x_variant":[
        "Victoria"
    ],
    "wof:name":"La Victoria",
    "wof:placetype":"locality"
},
  "geometry": {"coordinates":[-74.23611,5.52583],"type":"Point"}
}