{
  "type": "Feature",
  "properties": {
    "gn:admin1_code":"12",
    "gn:admin2_code":"23189.0",
    "gn:asciiname":"El Polito",
    "gn:cc2":"CO",
    "gn:country_code":"CO",
    "gn:dem":9,
    "gn:feature_class":"P",
    "gn:feature_code":"PPLL",
    "gn:name":"El Polito",
    "gn:population":0,
    "gn:timezone":"America/Bogota",
    "iso:country":"CO",
    "name:und_x_variant":[
        "Hacienda El Polo",
        "El Polito"
    ],
    "wof:name":"El Polito",
    "wof:placetype":"locality"
},
  "geometry": {"coordinates":[-75.69194,8.94889],"type":"Point"}
}