{
  "type": "Feature",
  "properties": {
    "gn:admin1_code":"33.0",
    "gn:admin2_code":"25322.0",
    "gn:asciiname":"Robayo",
    "gn:country_code":"CO",
    "gn:dem":2682,
    "gn:feature_class":"P",
    "gn:feature_code":"PPL",
    "gn:name":"Robayo",
    "gn:population":0,
    "gn:timezone":"America/Bogota",
    "iso:country":"CO",
    "wof:name":"Robayo",
    "wof:placetype":"locality"
},
  "geometry": {"coordinates":[-73.89825999999999,4.83412],"type":"Point"}
}