{
  "type": "Feature",
  "properties": {
    "gn:admin1_code":"27",
    "gn:admin2_code":"70265.0",
    "gn:asciiname":"Gavalda",
    "gn:cc2":"CO",
    "gn:country_code":"CO",
    "gn:dem":22,
    "gn:feature_class":"P",
    "gn:feature_code":"PPL",
    "gn:name":"Gavald\u00e1",
    "gn:population":0,
    "gn:timezone":"America/Bogota",
    "iso:country":"CO",
    "name:und_x_variant":[
        "Caserio Gabalda",
        "Gabalda",
        "Gavald\u00e1"
    ],
    "wof:name":"Gavalda",
    "wof:placetype":"locality"
},
  "geometry": {"coordinates":[-74.78333000000001,8.35],"type":"Point"}
}