{
  "type": "Feature",
  "properties": {
    "gn:admin1_code":"33",
    "gn:admin2_code":"25612.0",
    "gn:asciiname":"Llano de Pozo",
    "gn:country_code":"CO",
    "gn:dem":297,
    "gn:feature_class":"P",
    "gn:feature_code":"PPL",
    "gn:name":"Llano de Pozo",
    "gn:population":0,
    "gn:timezone":"America/Bogota",
    "iso:country":"CO",
    "name:spa_x_preferred":[
        "Llano de Pozo"
    ],
    "name:und_x_variant":[
        "Llano del Pozo"
    ],
    "wof:name":"Llano de Pozo",
    "wof:placetype":"locality"
},
  "geometry": {"coordinates":[-74.73475000000001,4.28992],"type":"Point"}
}