{
  "type": "Feature",
  "properties": {
    "gn:admin1_code":"38.0",
    "gn:admin2_code":"47551.0",
    "gn:asciiname":"Playon de Catalina",
    "gn:cc2":"CO",
    "gn:country_code":"CO",
    "gn:dem":43,
    "gn:feature_class":"P",
    "gn:feature_code":"PPL",
    "gn:name":"Play\u00f3n de Catalina",
    "gn:population":0,
    "gn:timezone":"America/Bogota",
    "iso:country":"CO",
    "name:und_x_variant":[
        "Caser\u00edo Playon de Catalina",
        "Playon De Catalino",
        "Play\u00f3n de Catalina"
    ],
    "wof:name":"Playon de Catalina",
    "wof:placetype":"locality"
},
  "geometry": {"coordinates":[-74.50917,10.37889],"type":"Point"}
}