{
  "type": "Feature",
  "properties": {
    "gn:admin1_code":"20",
    "gn:admin2_code":"52036.0",
    "gn:asciiname":"Limonal",
    "gn:country_code":"CO",
    "gn:dem":1366,
    "gn:feature_class":"P",
    "gn:feature_code":"PPL",
    "gn:name":"Limonal",
    "gn:population":0,
    "gn:timezone":"America/Bogota",
    "iso:country":"CO",
    "wof:name":"Limonal",
    "wof:placetype":"locality"
},
  "geometry": {"coordinates":[-77.51666999999998,1.25],"type":"Point"}
}