{
  "type": "Feature",
  "properties": {
    "gn:admin1_code":"38",
    "gn:admin2_code":"47675.0",
    "gn:asciiname":"El Loro",
    "gn:cc2":"CO",
    "gn:country_code":"CO",
    "gn:dem":6,
    "gn:feature_class":"P",
    "gn:feature_code":"PPL",
    "gn:name":"El Loro",
    "gn:population":0,
    "gn:timezone":"America/Bogota",
    "iso:country":"CO",
    "name:und_x_variant":[
        "Caser\u00edo El Loro",
        "El Loro"
    ],
    "wof:name":"El Loro",
    "wof:placetype":"locality"
},
  "geometry": {"coordinates":[-74.70056,10.52083],"type":"Point"}
}