{
  "type": "Feature",
  "properties": {
    "gn:admin1_code":"36",
    "gn:admin2_code":"15507.0",
    "gn:asciiname":"Trementino",
    "gn:country_code":"CO",
    "gn:dem":634,
    "gn:feature_class":"P",
    "gn:feature_code":"PPL",
    "gn:name":"Trementino",
    "gn:population":0,
    "gn:timezone":"America/Bogota",
    "iso:country":"CO",
    "wof:name":"Trementino",
    "wof:placetype":"locality"
},
  "geometry": {"coordinates":[-74.14806,5.78639],"type":"Point"}
}