{
  "type": "Feature",
  "properties": {
    "gn:admin1_code":"29.0",
    "gn:admin2_code":"76233.0",
    "gn:asciiname":"Tocota",
    "gn:country_code":"CO",
    "gn:dem":1520,
    "gn:feature_class":"P",
    "gn:feature_code":"PPL",
    "gn:name":"Tocot\u00e1",
    "gn:population":0,
    "gn:timezone":"America/Bogota",
    "iso:country":"CO",
    "wof:name":"Tocota",
    "wof:placetype":"locality"
},
  "geometry": {"coordinates":[-76.64931,3.50497],"type":"Point"}
}