{
  "type": "Feature",
  "properties": {
    "gn:admin1_code":"9",
    "gn:admin2_code":"19100.0",
    "gn:asciiname":"La Playa",
    "gn:country_code":"CO",
    "gn:dem":800,
    "gn:feature_class":"P",
    "gn:feature_code":"PPL",
    "gn:name":"La Playa",
    "gn:population":0,
    "gn:timezone":"America/Bogota",
    "iso:country":"CO",
    "name:ceb_x_preferred":[
        "La Playa"
    ],
    "name:fra_x_preferred":[
        "La Playa"
    ],
    "name:nld_x_preferred":[
        "La Playa"
    ],
    "name:spa_x_preferred":[
        "La Playa"
    ],
    "name:swe_x_preferred":[
        "La Playa"
    ],
    "wof:name":"La Playa",
    "wof:placetype":"locality"
},
  "geometry": {"coordinates":[-77.00523000000003,1.98024],"type":"Point"}
}