{
  "type": "Feature",
  "properties": {
    "gn:admin1_code":"2.0",
    "gn:admin2_code":"5842.0",
    "gn:asciiname":"La Berruga",
    "gn:country_code":"CO",
    "gn:dem":1442,
    "gn:feature_class":"P",
    "gn:feature_code":"PPL",
    "gn:name":"La Berruga",
    "gn:population":0,
    "gn:timezone":"America/Bogota",
    "iso:country":"CO",
    "wof:name":"La Berruga",
    "wof:placetype":"locality"
},
  "geometry": {"coordinates":[-76.1075,6.94222],"type":"Point"}
}