{
  "type": "Feature",
  "properties": {
    "gn:admin1_code":"8.0",
    "gn:admin2_code":"18753.0",
    "gn:asciiname":"La Abeja",
    "gn:country_code":"CO",
    "gn:dem":1583,
    "gn:feature_class":"P",
    "gn:feature_code":"PPL",
    "gn:name":"La Abeja",
    "gn:population":0,
    "gn:timezone":"America/Bogota",
    "iso:country":"CO",
    "wof:name":"La Abeja",
    "wof:placetype":"locality"
},
  "geometry": {"coordinates":[-74.84402,2.70453],"type":"Point"}
}