{
  "type": "Feature",
  "properties": {
    "gn:admin1_code":"12",
    "gn:admin2_code":"23574.0",
    "gn:asciiname":"Nuevo Rumbo",
    "gn:country_code":"CO",
    "gn:dem":54,
    "gn:feature_class":"P",
    "gn:feature_code":"PPL",
    "gn:name":"Nuevo Rumbo",
    "gn:population":0,
    "gn:timezone":"America/Bogota",
    "iso:country":"CO",
    "wof:name":"Nuevo Rumbo",
    "wof:placetype":"locality"
},
  "geometry": {"coordinates":[-76.17416999999998,8.96028],"type":"Point"}
}