{
  "type": "Feature",
  "properties": {
    "gn:admin1_code":"35",
    "gn:admin2_code":"13440.0",
    "gn:asciiname":"Causado",
    "gn:country_code":"CO",
    "gn:dem":20,
    "gn:feature_class":"P",
    "gn:feature_code":"PPL",
    "gn:name":"Causado",
    "gn:population":0,
    "gn:timezone":"America/Bogota",
    "iso:country":"CO",
    "name:und_x_variant":[
        "Corregimiento Causado",
        "Causado"
    ],
    "wof:name":"Causado",
    "wof:placetype":"locality"
},
  "geometry": {"coordinates":[-74.3205,9.13112],"type":"Point"}
}