{
  "type": "Feature",
  "properties": {
    "iso:country":"CO",
    "qs:gn_country":"CO",
    "qs:gn_fcode":"PPL",
    "qs:gn_pop":2779,
    "qs:name":"San Francisco",
    "qs:name_adm0":"Colombia",
    "qs:name_adm1":"Antioquia",
    "qs:photos":0,
    "qs:photos_1k":0,
    "qs:photos_9k":0,
    "qs:photos_9r":0,
    "qs:photos_all":0,
    "qs:photos_sr":0,
    "qs:placetype":"Town",
    "qs:pop_sr":"4",
    "qs:woe_adm0":23424787,
    "wof:name":"San Francisco",
    "wof:placetype":"locality",
    "wof:population":2779
},
  "geometry": {"coordinates":[-75.98333,6.11667],"type":"Point"}
}