{
  "type": "Feature",
  "properties": {
    "gn:admin1_code":"29",
    "gn:admin2_code":"76834.0",
    "gn:asciiname":"Bocas de Tulua",
    "gn:country_code":"CO",
    "gn:dem":926,
    "gn:feature_class":"P",
    "gn:feature_code":"PPL",
    "gn:name":"Bocas de Tulu\u00e1",
    "gn:population":0,
    "gn:timezone":"America/Bogota",
    "iso:country":"CO",
    "name:und_x_variant":[
        "Boca Tulua",
        "Bocas de Tulu\u00e1"
    ],
    "wof:name":"Bocas de Tulua",
    "wof:placetype":"locality"
},
  "geometry": {"coordinates":[-76.23243000000002,4.15609],"type":"Point"}
}