{
  "type": "Feature",
  "properties": {
    "gn:admin1_code":"16.0",
    "gn:admin2_code":"41503.0",
    "gn:asciiname":"Granates",
    "gn:country_code":"CO",
    "gn:dem":1639,
    "gn:feature_class":"P",
    "gn:feature_code":"PPL",
    "gn:name":"Granates",
    "gn:population":0,
    "gn:timezone":"America/Bogota",
    "iso:country":"CO",
    "name:spa_x_preferred":[
        "Granates"
    ],
    "wof:name":"Granates",
    "wof:placetype":"locality"
},
  "geometry": {"coordinates":[-76.05122,2.02181],"type":"Point"}
}