{
  "type": "Feature",
  "properties": {
    "gn:admin1_code":"16.0",
    "gn:admin2_code":"41551.0",
    "gn:asciiname":"Montebonito",
    "gn:country_code":"CO",
    "gn:dem":1720,
    "gn:feature_class":"P",
    "gn:feature_code":"PPL",
    "gn:name":"Montebonito",
    "gn:population":0,
    "gn:timezone":"America/Bogota",
    "iso:country":"CO",
    "wof:name":"Montebonito",
    "wof:placetype":"locality"
},
  "geometry": {"coordinates":[-76.09243000000002,1.91757],"type":"Point"}
}