{
  "type": "Feature",
  "properties": {
    "gn:admin1_code":"26.0",
    "gn:admin2_code":"68235.0",
    "gn:asciiname":"Centenario",
    "gn:country_code":"CO",
    "gn:dem":309,
    "gn:feature_class":"P",
    "gn:feature_code":"PPLL",
    "gn:name":"Centenario",
    "gn:population":0,
    "gn:timezone":"America/Bogota",
    "iso:country":"CO",
    "wof:name":"Centenario",
    "wof:placetype":"locality"
},
  "geometry": {"coordinates":[-73.57984,6.68723],"type":"Point"}
}