{
  "type": "Feature",
  "properties": {
    "gn:admin1_code":"9.0",
    "gn:admin2_code":"19142.0",
    "gn:asciiname":"Hacienda Carrizal",
    "gn:country_code":"CO",
    "gn:dem":1116,
    "gn:feature_class":"P",
    "gn:feature_code":"PPL",
    "gn:name":"Hacienda Carrizal",
    "gn:population":0,
    "gn:timezone":"America/Bogota",
    "iso:country":"CO",
    "name:spa_x_preferred":[
        "Hacienda Carrizal"
    ],
    "wof:name":"Hacienda Carrizal",
    "wof:placetype":"locality"
},
  "geometry": {"coordinates":[-76.33315,3.09473],"type":"Point"}
}