{
  "type": "Feature",
  "properties": {
    "gn:admin1_code":"2.0",
    "gn:admin2_code":"5790.0",
    "gn:asciiname":"Taraza",
    "gn:country_code":"CO",
    "gn:dem":92,
    "gn:feature_class":"P",
    "gn:feature_code":"PPLA2",
    "gn:name":"Taraz\u00e1",
    "gn:population":0,
    "gn:timezone":"America/Bogota",
    "iso:country":"CO",
    "name:ceb_x_preferred":[
        "Taraz\u00e1"
    ],
    "name:deu_x_preferred":[
        "Taraz\u00e1"
    ],
    "name:fas_x_preferred":[
        "\u062a\u0627\u0631\u0627\u0633\u0627"
    ],
    "name:fra_x_preferred":[
        "Taraz\u00e1"
    ],
    "name:ile_x_preferred":[
        "Taraz\u00e1"
    ],
    "name:ilo_x_preferred":[
        "Taraz\u00e1"
    ],
    "name:ita_x_preferred":[
        "Taraz\u00e1"
    ],
    "name:kat_x_preferred":[
        "\u10e2\u10d0\u10e0\u10d0\u10e1\u10d0"
    ],
    "name:msa_x_preferred":[
        "Taraz\u00e1"
    ],
    "name:nld_x_preferred":[
        "Taraz\u00e1"
    ],
    "name:por_x_preferred":[
        "Taraz\u00e1"
    ],
    "name:ron_x_preferred":[
        "Taraz\u00e1"
    ],
    "name:rus_x_preferred":[
        "\u0422\u0430\u0440\u0430\u0441\u0430"
    ],
    "name:spa_x_preferred":[
        "Taraz\u00e1"
    ],
    "name:swe_x_preferred":[
        "Taraz\u00e1"
    ],
    "name:tgl_x_preferred":[
        "Taraz\u00e1"
    ],
    "name:und_x_variant":[
        "Taraz\u00e1"
    ],
    "name:vie_x_preferred":[
        "Taraz\u00e1"
    ],
    "name:war_x_preferred":[
        "Taraz\u00e1"
    ],
    "name:zho_x_preferred":[
        "\u5854\u62c9\u85a9"
    ],
    "wof:name":"Taraza",
    "wof:placetype":"locality"
},
  "geometry": {"coordinates":[-75.40068000000002,7.58358],"type":"Point"}
}