{
  "type": "Feature",
  "properties": {
    "gn:admin1_code":"2.0",
    "gn:admin2_code":"5790.0",
    "gn:asciiname":"Taraza",
    "gn:country_code":"CO",
    "gn:dem":92,
    "gn:feature_class":"P",
    "gn:feature_code":"PPLA2",
    "gn:name":"Taraz\u00e1",
    "gn:population":0,
    "gn:timezone":"America/Bogota",
    "iso:country":"CO",
    "name:und_x_variant":[
        "Taraz\u00e1"
    ],
    "wof:name":"Taraza",
    "wof:placetype":"locality"
},
  "geometry": {"coordinates":[-75.40068000000002,7.58358],"type":"Point"}
}