{
  "type": "Feature",
  "properties": {
    "gn:admin1_code":"9",
    "gn:admin2_code":"19548.0",
    "gn:asciiname":"La Buitrera",
    "gn:country_code":"CO",
    "gn:dem":2033,
    "gn:feature_class":"P",
    "gn:feature_code":"PPL",
    "gn:name":"La Buitrera",
    "gn:population":0,
    "gn:timezone":"America/Bogota",
    "iso:country":"CO",
    "name:spa_x_preferred":[
        "La Buitrera"
    ],
    "wof:name":"La Buitrera",
    "wof:placetype":"locality"
},
  "geometry": {"coordinates":[-76.50576,2.62213],"type":"Point"}
}