{
  "type": "Feature",
  "properties": {
    "gn:admin1_code":"17",
    "gn:asciiname":"El Pintado",
    "gn:country_code":"CO",
    "gn:dem":1963,
    "gn:feature_class":"P",
    "gn:feature_code":"PPL",
    "gn:name":"El Pintado",
    "gn:population":0,
    "gn:timezone":"America/Bogota",
    "iso:country":"CO",
    "wof:name":"El Pintado",
    "wof:placetype":"locality"
},
  "geometry": {"coordinates":[-72.92341999999999,10.40365],"type":"Point"}
}