{
  "type": "Feature",
  "properties": {
    "gn:admin1_code":"33.0",
    "gn:admin2_code":"25293.0",
    "gn:asciiname":"Cocubal",
    "gn:country_code":"CO",
    "gn:dem":2240,
    "gn:feature_class":"P",
    "gn:feature_code":"PPL",
    "gn:name":"Cocubal",
    "gn:population":0,
    "gn:timezone":"America/Bogota",
    "iso:country":"CO",
    "wof:name":"Cocubal",
    "wof:placetype":"locality"
},
  "geometry": {"coordinates":[-73.6026,4.62684],"type":"Point"}
}