{
  "type": "Feature",
  "properties": {
    "gn:admin1_code":"29",
    "gn:admin2_code":"76248.0",
    "gn:asciiname":"La Monte Oscuro",
    "gn:country_code":"CO",
    "gn:dem":961,
    "gn:feature_class":"P",
    "gn:feature_code":"PPL",
    "gn:name":"La Monte Oscuro",
    "gn:population":0,
    "gn:timezone":"America/Bogota",
    "iso:country":"CO",
    "wof:name":"La Monte Oscuro",
    "wof:placetype":"locality"
},
  "geometry": {"coordinates":[-76.36778000000002,3.69556],"type":"Point"}
}