{
  "type": "Feature",
  "properties": {
    "gn:admin1_code":"28",
    "gn:admin2_code":"73124.0",
    "gn:asciiname":"La Torre",
    "gn:country_code":"CO",
    "gn:dem":2242,
    "gn:feature_class":"P",
    "gn:feature_code":"PPL",
    "gn:name":"La Torre",
    "gn:population":0,
    "gn:timezone":"America/Bogota",
    "iso:country":"CO",
    "wof:name":"La Torre",
    "wof:placetype":"locality"
},
  "geometry": {"coordinates":[-75.44055999999998,4.37833],"type":"Point"}
}