{
  "type": "Feature",
  "properties": {
    "gn:admin1_code":"12.0",
    "gn:admin2_code":"23079.0",
    "gn:asciiname":"Tierra Santa",
    "gn:country_code":"CO",
    "gn:dem":50,
    "gn:feature_class":"P",
    "gn:feature_code":"PPL",
    "gn:name":"Tierra Santa",
    "gn:population":0,
    "gn:timezone":"America/Bogota",
    "iso:country":"CO",
    "name:ceb_x_preferred":[
        "Tierra Santa"
    ],
    "name:spa_x_preferred":[
        "Tierra Santa"
    ],
    "name:swe_x_preferred":[
        "Tierra Santa"
    ],
    "wof:name":"Tierra Santa",
    "wof:placetype":"locality"
},
  "geometry": {"coordinates":[-75.31385,8.24544],"type":"Point"}
}