{
  "type": "Feature",
  "properties": {
    "gn:admin1_code":"28.0",
    "gn:admin2_code":"73624.0",
    "gn:asciiname":"Riomanso",
    "gn:country_code":"CO",
    "gn:dem":2034,
    "gn:feature_class":"P",
    "gn:feature_code":"PPL",
    "gn:name":"Riomanso",
    "gn:population":0,
    "gn:timezone":"America/Bogota",
    "iso:country":"CO",
    "wof:name":"Riomanso",
    "wof:placetype":"locality"
},
  "geometry": {"coordinates":[-75.41667,4.20639],"type":"Point"}
}