{
  "type": "Feature",
  "properties": {
    "gn:admin1_code":"16.0",
    "gn:admin2_code":"41206.0",
    "gn:asciiname":"Meseta",
    "gn:country_code":"CO",
    "gn:dem":1962,
    "gn:feature_class":"P",
    "gn:feature_code":"PPL",
    "gn:name":"Meseta",
    "gn:population":0,
    "gn:timezone":"America/Bogota",
    "iso:country":"CO",
    "name:spa_x_preferred":[
        "Meseta"
    ],
    "wof:name":"Meseta",
    "wof:placetype":"locality"
},
  "geometry": {"coordinates":[-74.81374,3.31114],"type":"Point"}
}