{
  "type": "Feature",
  "properties": {
    "gn:admin1_code":"3",
    "gn:admin2_code":"81001.0",
    "gn:asciiname":"Los Boquerones",
    "gn:country_code":"CO",
    "gn:dem":118,
    "gn:feature_class":"P",
    "gn:feature_code":"PPL",
    "gn:name":"Los Boquerones",
    "gn:population":0,
    "gn:timezone":"America/Bogota",
    "iso:country":"CO",
    "name:ceb_x_preferred":[
        "Los Boquerones"
    ],
    "wof:name":"Los Boquerones",
    "wof:placetype":"locality"
},
  "geometry": {"coordinates":[-70.46814999999999,6.84861],"type":"Point"}
}