{
  "type": "Feature",
  "properties": {
    "gn:admin1_code":"19.0",
    "gn:admin2_code":"50287.0",
    "gn:asciiname":"La Quinta",
    "gn:country_code":"CO",
    "gn:dem":302,
    "gn:feature_class":"P",
    "gn:feature_code":"PPLL",
    "gn:name":"La Quinta",
    "gn:population":0,
    "gn:timezone":"America/Bogota",
    "iso:country":"CO",
    "name:spa_x_preferred":[
        "La Quinta"
    ],
    "wof:name":"La Quinta",
    "wof:placetype":"locality"
},
  "geometry": {"coordinates":[-73.63521999999998,3.47083],"type":"Point"}
}