{
  "type": "Feature",
  "properties": {
    "gn:admin1_code":"9",
    "gn:admin2_code":"19130.0",
    "gn:asciiname":"El Carmelo",
    "gn:country_code":"CO",
    "gn:dem":1749,
    "gn:feature_class":"P",
    "gn:feature_code":"PPL",
    "gn:name":"El Carmelo",
    "gn:population":0,
    "gn:timezone":"America/Bogota",
    "iso:country":"CO",
    "wof:name":"El Carmelo",
    "wof:placetype":"locality"
},
  "geometry": {"coordinates":[-76.70269,2.66428],"type":"Point"}
}