{
  "type": "Feature",
  "properties": {
    "gn:admin1_code":"12.0",
    "gn:admin2_code":"23162.0",
    "gn:asciiname":"Toledo",
    "gn:country_code":"CO",
    "gn:dem":12,
    "gn:feature_class":"P",
    "gn:feature_code":"PPL",
    "gn:name":"Toledo",
    "gn:population":0,
    "gn:timezone":"America/Bogota",
    "iso:country":"CO",
    "wof:name":"Toledo",
    "wof:placetype":"locality"
},
  "geometry": {"coordinates":[-75.75561,8.87829],"type":"Point"}
}