{
  "type": "Feature",
  "properties": {
    "gn:admin1_code":"28",
    "gn:admin2_code":"73026.0",
    "gn:asciiname":"Calicanto",
    "gn:country_code":"CO",
    "gn:dem":600,
    "gn:feature_class":"P",
    "gn:feature_code":"PPL",
    "gn:name":"Calicanto",
    "gn:population":0,
    "gn:timezone":"America/Bogota",
    "iso:country":"CO",
    "wof:name":"Calicanto",
    "wof:placetype":"locality"
},
  "geometry": {"coordinates":[-75.00305999999998,4.47333],"type":"Point"}
}