{
  "type": "Feature",
  "properties": {
    "gn:admin1_code":"4.0",
    "gn:admin2_code":"8638.0",
    "gn:asciiname":"Saldana",
    "gn:country_code":"CO",
    "gn:dem":77,
    "gn:feature_class":"P",
    "gn:feature_code":"PPL",
    "gn:name":"Salda\u00f1a",
    "gn:population":0,
    "gn:timezone":"America/Bogota",
    "iso:country":"CO",
    "wof:name":"Saldana",
    "wof:placetype":"locality"
},
  "geometry": {"coordinates":[-74.88333,10.58333],"type":"Point"}
}