{
  "type": "Feature",
  "properties": {
    "gn:admin1_code":"29",
    "gn:admin2_code":"76616.0",
    "gn:asciiname":"La Zulia",
    "gn:country_code":"CO",
    "gn:dem":2145,
    "gn:feature_class":"P",
    "gn:feature_code":"PPL",
    "gn:name":"La Zulia",
    "gn:population":0,
    "gn:timezone":"America/Bogota",
    "iso:country":"CO",
    "wof:name":"La Zulia",
    "wof:placetype":"locality"
},
  "geometry": {"coordinates":[-76.44004,4.12578],"type":"Point"}
}