{
  "type": "Feature",
  "properties": {
    "gn:admin1_code":"28.0",
    "gn:admin2_code":"73001.0",
    "gn:asciiname":"Monte Bello",
    "gn:country_code":"CO",
    "gn:dem":2780,
    "gn:feature_class":"P",
    "gn:feature_code":"PPL",
    "gn:name":"Monte Bello",
    "gn:population":0,
    "gn:timezone":"America/Bogota",
    "iso:country":"CO",
    "name:ceb_x_preferred":[
        "Monte Bello"
    ],
    "name:swe_x_preferred":[
        "Monte Bello"
    ],
    "wof:name":"Monte Bello",
    "wof:placetype":"locality"
},
  "geometry": {"coordinates":[-75.42278,4.36444],"type":"Point"}
}