{
  "type": "Feature",
  "properties": {
    "gn:admin1_code":"9",
    "gn:admin2_code":"19075.0",
    "gn:asciiname":"Limon",
    "gn:country_code":"CO",
    "gn:dem":561,
    "gn:feature_class":"P",
    "gn:feature_code":"PPL",
    "gn:name":"Lim\u00f3n",
    "gn:population":0,
    "gn:timezone":"America/Bogota",
    "iso:country":"CO",
    "wof:name":"Limon",
    "wof:placetype":"locality"
},
  "geometry": {"coordinates":[-77.20033000000002,1.95676],"type":"Point"}
}