{
  "type": "Feature",
  "properties": {
    "gn:admin1_code":"38",
    "gn:admin2_code":"47460.0",
    "gn:asciiname":"Las Tinas",
    "gn:country_code":"CO",
    "gn:dem":81,
    "gn:feature_class":"P",
    "gn:feature_code":"PPL",
    "gn:name":"Las Tinas",
    "gn:population":0,
    "gn:timezone":"America/Bogota",
    "iso:country":"CO",
    "name:und_x_variant":[
        "Caser\u00edo Las Tinas",
        "Las Tinas"
    ],
    "wof:name":"Las Tinas",
    "wof:placetype":"locality"
},
  "geometry": {"coordinates":[-74.29993,9.70319],"type":"Point"}
}