{
  "type": "Feature",
  "properties": {
    "gn:admin1_code":"38",
    "gn:admin2_code":"47980.0",
    "gn:asciiname":"Eusebia",
    "gn:country_code":"CO",
    "gn:dem":12,
    "gn:feature_class":"P",
    "gn:feature_code":"PPL",
    "gn:name":"Eusebia",
    "gn:population":0,
    "gn:timezone":"America/Bogota",
    "iso:country":"CO",
    "name:bul_x_preferred":[
        "\u0415\u0432\u0441\u0435\u0432\u0438\u044f"
    ],
    "name:deu_x_preferred":[
        "Eusebia"
    ],
    "name:nld_x_preferred":[
        "Eusebia"
    ],
    "name:por_x_preferred":[
        "Eus\u00e9bia"
    ],
    "name:spa_x_preferred":[
        "Eusebia"
    ],
    "name:vie_x_preferred":[
        "Eusebia"
    ],
    "wof:name":"Eusebia",
    "wof:placetype":"locality"
},
  "geometry": {"coordinates":[-74.19100999999998,10.86514],"type":"Point"}
}