{
  "type": "Feature",
  "properties": {
    "gn:admin1_code":"17",
    "gn:admin2_code":"44847.0",
    "gn:asciiname":"Kauarainshimana",
    "gn:country_code":"CO",
    "gn:dem":109,
    "gn:feature_class":"P",
    "gn:feature_code":"PPL",
    "gn:name":"Kauarainshimana",
    "gn:population":0,
    "gn:timezone":"America/Bogota",
    "iso:country":"CO",
    "wof:name":"Kauarainshimana",
    "wof:placetype":"locality"
},
  "geometry": {"coordinates":[-71.93111,11.87278],"type":"Point"}
}