{
  "type": "Feature",
  "properties": {
    "gn:admin1_code":"3",
    "gn:admin2_code":"81065.0",
    "gn:asciiname":"La Reinera",
    "gn:country_code":"CO",
    "gn:dem":148,
    "gn:feature_class":"P",
    "gn:feature_code":"PPL",
    "gn:name":"La Reinera",
    "gn:population":0,
    "gn:timezone":"America/Bogota",
    "iso:country":"CO",
    "name:spa_x_preferred":[
        "Reinera"
    ],
    "wof:name":"La Reinera",
    "wof:placetype":"locality"
},
  "geometry": {"coordinates":[-71.18812,6.95089],"type":"Point"}
}