{
  "type": "Feature",
  "properties": {
    "gn:admin1_code":"20.0",
    "gn:admin2_code":"52022.0",
    "gn:asciiname":"La Comunidad",
    "gn:country_code":"CO",
    "gn:dem":3193,
    "gn:feature_class":"P",
    "gn:feature_code":"PPL",
    "gn:name":"La Comunidad",
    "gn:population":0,
    "gn:timezone":"America/Bogota",
    "iso:country":"CO",
    "wof:name":"La Comunidad",
    "wof:placetype":"locality"
},
  "geometry": {"coordinates":[-77.69311,0.92651],"type":"Point"}
}