{
  "type": "Feature",
  "properties": {
    "gn:admin1_code":"9.0",
    "gn:admin2_code":"19845.0",
    "gn:asciiname":"Chalo",
    "gn:country_code":"CO",
    "gn:dem":965,
    "gn:feature_class":"P",
    "gn:feature_code":"PPL",
    "gn:name":"Chalo",
    "gn:population":0,
    "gn:timezone":"America/Bogota",
    "iso:country":"CO",
    "name:spa_x_preferred":[
        "Chalo"
    ],
    "name:tel_x_preferred":[
        "\u0c1b\u0c32\u0c4b"
    ],
    "wof:name":"Chalo",
    "wof:placetype":"locality"
},
  "geometry": {"coordinates":[-76.44901999999998,3.22847],"type":"Point"}
}