{
  "type": "Feature",
  "properties": {
    "gn:admin1_code":"2.0",
    "gn:admin2_code":"5887.0",
    "gn:asciiname":"El Laurel",
    "gn:country_code":"CO",
    "gn:dem":2145,
    "gn:feature_class":"P",
    "gn:feature_code":"PPL",
    "gn:name":"El Laurel",
    "gn:population":0,
    "gn:timezone":"America/Bogota",
    "iso:country":"CO",
    "wof:name":"El Laurel",
    "wof:placetype":"locality"
},
  "geometry": {"coordinates":[-75.60019,6.97643],"type":"Point"}
}