{
  "type": "Feature",
  "properties": {
    "gn:admin1_code":"24.0",
    "gn:admin2_code":"66001.0",
    "gn:asciiname":"Choco",
    "gn:country_code":"CO",
    "gn:dem":1607,
    "gn:feature_class":"P",
    "gn:feature_code":"PPL",
    "gn:name":"Choco",
    "gn:population":0,
    "gn:timezone":"America/Bogota",
    "iso:country":"CO",
    "wof:name":"Choco",
    "wof:placetype":"locality"
},
  "geometry": {"coordinates":[-75.65833000000001,4.78722],"type":"Point"}
}