{
  "type": "Feature",
  "properties": {
    "gn:admin1_code":"24.0",
    "gn:admin2_code":"66001.0",
    "gn:asciiname":"Choco",
    "gn:country_code":"CO",
    "gn:dem":1607,
    "gn:feature_class":"P",
    "gn:feature_code":"PPL",
    "gn:name":"Choco",
    "gn:population":0,
    "gn:timezone":"America/Bogota",
    "iso:country":"CO",
    "name:ceb_x_preferred":[
        "Choco"
    ],
    "name:fra_x_preferred":[
        "Choco"
    ],
    "name:glg_x_preferred":[
        "Choco"
    ],
    "name:jpn_x_preferred":[
        "\u3061\u3087\u3053"
    ],
    "name:nds_x_preferred":[
        "Choco"
    ],
    "name:nld_x_preferred":[
        "Choco"
    ],
    "name:por_x_preferred":[
        "Choco"
    ],
    "name:rus_x_preferred":[
        "\u0427\u043e\u043a\u043e"
    ],
    "name:sco_x_preferred":[
        "Choco"
    ],
    "name:spa_x_preferred":[
        "Choco"
    ],
    "name:swe_x_preferred":[
        "Choco"
    ],
    "name:zho_x_preferred":[
        "Choco"
    ],
    "wof:name":"Choco",
    "wof:placetype":"locality"
},
  "geometry": {"coordinates":[-75.65833000000001,4.78722],"type":"Point"}
}