{
  "type": "Feature",
  "properties": {
    "gn:admin1_code":"10.0",
    "gn:admin2_code":"20013.0",
    "gn:asciiname":"Bachan",
    "gn:country_code":"CO",
    "gn:dem":149,
    "gn:feature_class":"P",
    "gn:feature_code":"PPL",
    "gn:name":"Bach\u00e1n",
    "gn:population":0,
    "gn:timezone":"America/Bogota",
    "iso:country":"CO",
    "wof:name":"Bachan",
    "wof:placetype":"locality"
},
  "geometry": {"coordinates":[-73.35906999999997,10.02809],"type":"Point"}
}