{
  "type": "Feature",
  "properties": {
    "gn:admin1_code":"1.0",
    "gn:admin2_code":"91407.0",
    "gn:asciiname":"Puerto Caiman",
    "gn:country_code":"CO",
    "gn:dem":107,
    "gn:feature_class":"P",
    "gn:feature_code":"PPL",
    "gn:name":"Puerto Caim\u00e1n",
    "gn:population":0,
    "gn:timezone":"America/Bogota",
    "iso:country":"CO",
    "wof:name":"Puerto Caiman",
    "wof:placetype":"locality"
},
  "geometry": {"coordinates":[-70.03331,-1.56663],"type":"Point"}
}