{
  "type": "Feature",
  "properties": {
    "gn:admin1_code":"20.0",
    "gn:admin2_code":"52233.0",
    "gn:asciiname":"Chimandango",
    "gn:country_code":"CO",
    "gn:dem":576,
    "gn:feature_class":"P",
    "gn:feature_code":"PPL",
    "gn:name":"Chimandango",
    "gn:population":0,
    "gn:timezone":"America/Bogota",
    "iso:country":"CO",
    "wof:name":"Chimandango",
    "wof:placetype":"locality"
},
  "geometry": {"coordinates":[-77.52568000000002,1.68071],"type":"Point"}
}