{
  "type": "Feature",
  "properties": {
    "gn:admin1_code":"32",
    "gn:admin2_code":"85430.0",
    "gn:asciiname":"La Palmita",
    "gn:country_code":"CO",
    "gn:dem":160,
    "gn:feature_class":"P",
    "gn:feature_code":"PPL",
    "gn:name":"La Palmita",
    "gn:population":0,
    "gn:timezone":"America/Bogota",
    "iso:country":"CO",
    "wof:name":"La Palmita",
    "wof:placetype":"locality"
},
  "geometry": {"coordinates":[-71.51666999999998,5.38333],"type":"Point"}
}