{
  "type": "Feature",
  "properties": {
    "gn:admin1_code":"36",
    "gn:admin2_code":"15720.0",
    "gn:asciiname":"Caldera",
    "gn:country_code":"CO",
    "gn:dem":2618,
    "gn:feature_class":"P",
    "gn:feature_code":"PPL",
    "gn:name":"Caldera",
    "gn:population":0,
    "gn:timezone":"America/Bogota",
    "iso:country":"CO",
    "wof:name":"Caldera",
    "wof:placetype":"locality"
},
  "geometry": {"coordinates":[-72.68333,6.08333],"type":"Point"}
}