{
  "type": "Feature",
  "properties": {
    "gn:admin1_code":"27",
    "gn:admin2_code":"70713.0",
    "gn:asciiname":"Cenicita",
    "gn:country_code":"CO",
    "gn:dem":19,
    "gn:feature_class":"P",
    "gn:feature_code":"PPL",
    "gn:name":"Cenicita",
    "gn:population":0,
    "gn:timezone":"America/Bogota",
    "iso:country":"CO",
    "wof:name":"Cenicita",
    "wof:placetype":"locality"
},
  "geometry": {"coordinates":[-75.56279000000001,9.92368],"type":"Point"}
}