{
  "type": "Feature",
  "properties": {
    "gn:admin1_code":"17",
    "gn:admin2_code":"44560.0",
    "gn:asciiname":"La Tuna",
    "gn:country_code":"CO",
    "gn:dem":-5,
    "gn:feature_class":"P",
    "gn:feature_code":"PPL",
    "gn:name":"La Tuna",
    "gn:population":0,
    "gn:timezone":"America/Bogota",
    "iso:country":"CO",
    "wof:name":"La Tuna",
    "wof:placetype":"locality"
},
  "geometry": {"coordinates":[-72.55833,11.74361],"type":"Point"}
}