{
  "type": "Feature",
  "properties": {
    "gn:admin1_code":"19",
    "gn:admin2_code":"50689",
    "gn:asciiname":"Villa Hermosa",
    "gn:country_code":"CO",
    "gn:dem":420,
    "gn:feature_class":"P",
    "gn:feature_code":"PPL",
    "gn:name":"Villa Hermosa",
    "gn:population":0,
    "gn:timezone":"America/Bogota",
    "iso:country":"CO",
    "name:spa_x_preferred":[
        "Villa Hermosa"
    ],
    "wof:name":"Villa Hermosa",
    "wof:placetype":"locality"
},
  "geometry": {"coordinates":[-73.68600000000001,3.76729],"type":"Point"}
}