{
  "type": "Feature",
  "properties": {
    "gn:admin1_code":"35.0",
    "gn:admin2_code":"13657.0",
    "gn:asciiname":"Carreto",
    "gn:country_code":"CO",
    "gn:dem":92,
    "gn:feature_class":"P",
    "gn:feature_code":"PPL",
    "gn:name":"Carreto",
    "gn:population":0,
    "gn:timezone":"America/Bogota",
    "iso:country":"CO",
    "wof:name":"Carreto",
    "wof:placetype":"locality"
},
  "geometry": {"coordinates":[-75.07292,10.06846],"type":"Point"}
}