{
  "type": "Feature",
  "properties": {
    "gn:admin1_code":"3",
    "gn:admin2_code":"81001.0",
    "gn:asciiname":"Sabana de Jose",
    "gn:country_code":"CO",
    "gn:dem":123,
    "gn:feature_class":"P",
    "gn:feature_code":"PPL",
    "gn:name":"Sabana de Jos\u00e9",
    "gn:population":0,
    "gn:timezone":"America/Bogota",
    "iso:country":"CO",
    "name:spa_x_preferred":[
        "Sabana de Jos\u00e9"
    ],
    "wof:name":"Sabana de Jose",
    "wof:placetype":"locality"
},
  "geometry": {"coordinates":[-70.90000000000001,6.66667],"type":"Point"}
}