{
  "type": "Feature",
  "properties": {
    "gn:admin1_code":"32",
    "gn:admin2_code":"85162.0",
    "gn:asciiname":"Los Alpes",
    "gn:country_code":"CO",
    "gn:dem":244,
    "gn:feature_class":"P",
    "gn:feature_code":"PPL",
    "gn:name":"Los Alpes",
    "gn:population":0,
    "gn:timezone":"America/Bogota",
    "iso:country":"CO",
    "wof:name":"Los Alpes",
    "wof:placetype":"locality"
},
  "geometry": {"coordinates":[-72.738,4.8308],"type":"Point"}
}