{
  "type": "Feature",
  "properties": {
    "gn:admin1_code":"38",
    "gn:admin2_code":"47675.0",
    "gn:asciiname":"La Retirada",
    "gn:cc2":"CO",
    "gn:country_code":"CO",
    "gn:dem":6,
    "gn:feature_class":"P",
    "gn:feature_code":"PPL",
    "gn:name":"La Retirada",
    "gn:population":0,
    "gn:timezone":"America/Bogota",
    "iso:country":"CO",
    "name:und_x_variant":[
        "Caser\u00edo La Retirada",
        "La Retirada"
    ],
    "wof:name":"La Retirada",
    "wof:placetype":"locality"
},
  "geometry": {"coordinates":[-74.67333000000001,10.48917],"type":"Point"}
}