{
  "type": "Feature",
  "properties": {
    "gn:admin1_code":"22.0",
    "gn:asciiname":"El Chiclal",
    "gn:country_code":"CO",
    "gn:dem":1854,
    "gn:feature_class":"P",
    "gn:feature_code":"PPL",
    "gn:name":"El Chiclal",
    "gn:population":0,
    "gn:timezone":"America/Bogota",
    "iso:country":"CO",
    "name:spa_x_preferred":[
        "El Chiclal"
    ],
    "wof:name":"El Chiclal",
    "wof:placetype":"locality"
},
  "geometry": {"coordinates":[-76.98364000000002,1.67153],"type":"Point"}
}