{
  "type": "Feature",
  "properties": {
    "gn:admin1_code":"2",
    "gn:admin2_code":"5107.0",
    "gn:asciiname":"Manizales",
    "gn:country_code":"CO",
    "gn:dem":2085,
    "gn:feature_class":"P",
    "gn:feature_code":"PPL",
    "gn:name":"Manizales",
    "gn:population":0,
    "gn:timezone":"America/Bogota",
    "iso:country":"CO",
    "wof:name":"Manizales",
    "wof:placetype":"locality"
},
  "geometry": {"coordinates":[-75.63778000000001,7.06361],"type":"Point"}
}