{
  "type": "Feature",
  "properties": {
    "gn:admin1_code":"2",
    "gn:admin2_code":"5107.0",
    "gn:asciiname":"Manizales",
    "gn:country_code":"CO",
    "gn:dem":2085,
    "gn:feature_class":"P",
    "gn:feature_code":"PPL",
    "gn:name":"Manizales",
    "gn:population":0,
    "gn:timezone":"America/Bogota",
    "iso:country":"CO",
    "name:ara_x_preferred":[
        "\u0645\u0627\u0646\u064a\u0632\u0627\u0644\u064a\u0633"
    ],
    "name:aym_x_preferred":[
        "Manizales"
    ],
    "name:aze_x_preferred":[
        "Manisales"
    ],
    "name:bul_x_preferred":[
        "\u041c\u0430\u043d\u0438\u0441\u0430\u043b\u0435\u0441"
    ],
    "name:cat_x_preferred":[
        "Manizales"
    ],
    "name:ceb_x_preferred":[
        "Manizales"
    ],
    "name:ces_x_preferred":[
        "Manizales"
    ],
    "name:dan_x_preferred":[
        "Manizales"
    ],
    "name:deu_x_preferred":[
        "Manizales"
    ],
    "name:epo_x_preferred":[
        "Manizales"
    ],
    "name:fas_x_preferred":[
        "\u0645\u0627\u0646\u06cc\u0633\u0627\u0644\u0633"
    ],
    "name:fin_x_preferred":[
        "Manizales"
    ],
    "name:fra_x_preferred":[
        "Manizales"
    ],
    "name:frr_x_preferred":[
        "Manizales"
    ],
    "name:gla_x_preferred":[
        "Manizales"
    ],
    "name:glg_x_preferred":[
        "Manizales"
    ],
    "name:ido_x_preferred":[
        "Manizales"
    ],
    "name:ind_x_preferred":[
        "Manizales"
    ],
    "name:isl_x_preferred":[
        "Manizales"
    ],
    "name:ita_x_preferred":[
        "Manizales"
    ],
    "name:jpn_x_preferred":[
        "\u30de\u30cb\u30b5\u30ec\u30b9"
    ],
    "name:kat_x_preferred":[
        "\u10db\u10d0\u10dc\u10d8\u10e1\u10d0\u10da\u10d4\u10e1\u10d8"
    ],
    "name:kor_x_preferred":[
        "\ub9c8\ub2c8\uc0b4\ub808\uc2a4"
    ],
    "name:lit_x_preferred":[
        "Manisalesas"
    ],
    "name:msa_x_preferred":[
        "Manizales"
    ],
    "name:nld_x_preferred":[
        "Manizales"
    ],
    "name:nor_x_preferred":[
        "Manizales"
    ],
    "name:oci_x_preferred":[
        "Manizales"
    ],
    "name:pnb_x_preferred":[
        "\u0645\u0646\u06cc\u0632\u0627\u0644\u0633"
    ],
    "name:pol_x_preferred":[
        "Manizales"
    ],
    "name:por_x_preferred":[
        "Manizales"
    ],
    "name:que_x_preferred":[
        "Manizales"
    ],
    "name:ron_x_preferred":[
        "Manizales"
    ],
    "name:rus_x_preferred":[
        "\u041c\u0430\u043d\u0438\u0441\u0430\u043b\u0435\u0441"
    ],
    "name:spa_x_preferred":[
        "Manizales"
    ],
    "name:swe_x_preferred":[
        "Manizales"
    ],
    "name:szl_x_preferred":[
        "Manizales"
    ],
    "name:tat_x_preferred":[
        "\u041c\u0430\u043d\u0438\u0441\u0430\u043b\u0435\u0441"
    ],
    "name:tgl_x_preferred":[
        "Manizales"
    ],
    "name:tur_x_preferred":[
        "Manizales"
    ],
    "name:ukr_x_preferred":[
        "\u041c\u0430\u043d\u0456\u0441\u0430\u043b\u0435\u0441"
    ],
    "name:urd_x_preferred":[
        "\u0645\u0627\u0646\u06cc\u0633\u0627\u0644\u0633"
    ],
    "name:vep_x_preferred":[
        "Manisales"
    ],
    "name:vie_x_preferred":[
        "Manizales"
    ],
    "name:vol_x_preferred":[
        "Manizales"
    ],
    "name:war_x_preferred":[
        "Manizales"
    ],
    "name:yor_x_preferred":[
        "Manizales"
    ],
    "name:zho_x_preferred":[
        "\u99ac\u5c3c\u85a9\u840a\u65af"
    ],
    "wof:name":"Manizales",
    "wof:placetype":"locality"
},
  "geometry": {"coordinates":[-75.63778000000001,7.06361],"type":"Point"}
}