{
  "type": "Feature",
  "properties": {
    "gn:admin1_code":"24.0",
    "gn:admin2_code":"66001.0",
    "gn:asciiname":"Alegrias",
    "gn:country_code":"CO",
    "gn:dem":1652,
    "gn:feature_class":"P",
    "gn:feature_code":"PPL",
    "gn:name":"Alegr\u00edas",
    "gn:population":0,
    "gn:timezone":"America/Bogota",
    "iso:country":"CO",
    "wof:name":"Alegrias",
    "wof:placetype":"locality"
},
  "geometry": {"coordinates":[-75.67278,4.75306],"type":"Point"}
}