{
  "type": "Feature",
  "properties": {
    "gn:admin1_code":"31.0",
    "gn:admin2_code":"99001.0",
    "gn:asciiname":"Inspeccion de Policia Puerto Murillo",
    "gn:country_code":"CO",
    "gn:dem":75,
    "gn:feature_class":"P",
    "gn:feature_code":"PPL",
    "gn:name":"Inspecci\u00f3n de Polic\u00eda Puerto Murillo",
    "gn:population":0,
    "gn:timezone":"America/Bogota",
    "iso:country":"CO",
    "name:spa_x_preferred":[
        "Inspecci\u00f3n de Polic\u00eda Puerto Murillo"
    ],
    "name:und_x_variant":[
        "Puerto Murillo",
        "Murillo"
    ],
    "wof:name":"Inspeccion de Policia Puerto Murillo",
    "wof:placetype":"locality"
},
  "geometry": {"coordinates":[-68.49115,6.16653],"type":"Point"}
}