{
  "type": "Feature",
  "properties": {
    "gn:admin1_code":"16.0",
    "gn:admin2_code":"41548.0",
    "gn:asciiname":"El Retiro",
    "gn:country_code":"CO",
    "gn:dem":1651,
    "gn:feature_class":"P",
    "gn:feature_code":"PPL",
    "gn:name":"El Retiro",
    "gn:population":0,
    "gn:timezone":"America/Bogota",
    "iso:country":"CO",
    "name:ceb_x_preferred":[
        "El Retiro"
    ],
    "name:glg_x_preferred":[
        "O Retiro"
    ],
    "name:srp_x_preferred":[
        "\u0415\u043b \u0420\u0435\u0442\u0438\u0440\u043e"
    ],
    "name:swe_x_preferred":[
        "El Retiro"
    ],
    "wof:name":"El Retiro",
    "wof:placetype":"locality"
},
  "geometry": {"coordinates":[-75.82968000000002,2.32534],"type":"Point"}
}