{
  "type": "Feature",
  "properties": {
    "gn:admin1_code":"3.0",
    "gn:admin2_code":"81065.0",
    "gn:asciiname":"Panama de Arauca",
    "gn:country_code":"CO",
    "gn:dem":146,
    "gn:feature_class":"P",
    "gn:feature_code":"PPL",
    "gn:name":"Panam\u00e1 de Arauca",
    "gn:population":0,
    "gn:timezone":"America/Bogota",
    "iso:country":"CO",
    "name:spa_x_preferred":[
        "Panam\u00e1 de Arauca"
    ],
    "wof:name":"Panama de Arauca",
    "wof:placetype":"locality"
},
  "geometry": {"coordinates":[-71.22662,6.82321],"type":"Point"}
}