{
  "type": "Feature",
  "properties": {
    "gn:admin1_code":"23",
    "gn:admin2_code":"63212.0",
    "gn:asciiname":"La Siria",
    "gn:country_code":"CO",
    "gn:dem":3129,
    "gn:feature_class":"P",
    "gn:feature_code":"PPL",
    "gn:name":"La Siria",
    "gn:population":0,
    "gn:timezone":"America/Bogota",
    "iso:country":"CO",
    "name:und_x_variant":[
        "Siria",
        "La Siria"
    ],
    "wof:name":"La Siria",
    "wof:placetype":"locality"
},
  "geometry": {"coordinates":[-75.62444000000001,4.39443],"type":"Point"}
}