{
  "type": "Feature",
  "properties": {
    "gn:admin1_code":"19",
    "gn:admin2_code":"50573.0",
    "gn:asciiname":"Las Hortencias",
    "gn:country_code":"CO",
    "gn:dem":204,
    "gn:feature_class":"P",
    "gn:feature_code":"PPL",
    "gn:name":"Las Hortencias",
    "gn:population":0,
    "gn:timezone":"America/Bogota",
    "iso:country":"CO",
    "wof:name":"Las Hortencias",
    "wof:placetype":"locality"
},
  "geometry": {"coordinates":[-72.66101999999999,4.19198],"type":"Point"}
}