{
  "type": "Feature",
  "properties": {
    "gn:admin1_code":"35",
    "gn:admin2_code":"13244.0",
    "gn:asciiname":"Mancomajan",
    "gn:country_code":"CO",
    "gn:dem":90,
    "gn:feature_class":"P",
    "gn:feature_code":"PPL",
    "gn:name":"Mancomaj\u00e1n",
    "gn:population":0,
    "gn:timezone":"America/Bogota",
    "iso:country":"CO",
    "name:und_x_variant":[
        "Mancomojan",
        "Mancomaj\u00e1n"
    ],
    "wof:name":"Mancomajan",
    "wof:placetype":"locality"
},
  "geometry": {"coordinates":[-75.00275999999999,9.57244],"type":"Point"}
}