{
  "type": "Feature",
  "properties": {
    "gn:admin1_code":"19.0",
    "gn:admin2_code":"50110.0",
    "gn:asciiname":"Angosturas",
    "gn:country_code":"CO",
    "gn:dem":245,
    "gn:feature_class":"P",
    "gn:feature_code":"PPL",
    "gn:name":"Angosturas",
    "gn:population":0,
    "gn:timezone":"America/Bogota",
    "iso:country":"CO",
    "wof:name":"Angosturas",
    "wof:placetype":"locality"
},
  "geometry": {"coordinates":[-73.00345,4.56226],"type":"Point"}
}