{
  "type": "Feature",
  "properties": {
    "gn:admin1_code":"33.0",
    "gn:admin2_code":"25320.0",
    "gn:asciiname":"Carbon",
    "gn:country_code":"CO",
    "gn:dem":625,
    "gn:feature_class":"P",
    "gn:feature_code":"PPL",
    "gn:name":"Carb\u00f3n",
    "gn:population":0,
    "gn:timezone":"America/Bogota",
    "iso:country":"CO",
    "name:spa_x_preferred":[
        "Carb\u00f3n"
    ],
    "wof:name":"Carbon",
    "wof:placetype":"locality"
},
  "geometry": {"coordinates":[-74.5677,5.1855],"type":"Point"}
}