{
  "type": "Feature",
  "properties": {
    "gn:admin1_code":"17.0",
    "gn:admin2_code":"44847.0",
    "gn:asciiname":"Jurruruyo",
    "gn:country_code":"CO",
    "gn:dem":26,
    "gn:feature_class":"P",
    "gn:feature_code":"PPL",
    "gn:name":"Jurruruyo",
    "gn:population":0,
    "gn:timezone":"America/Bogota",
    "iso:country":"CO",
    "name:und_x_variant":[
        "Turruruoho"
    ],
    "wof:name":"Jurruruyo",
    "wof:placetype":"locality"
},
  "geometry": {"coordinates":[-71.45,12.16667],"type":"Point"}
}