{
  "type": "Feature",
  "properties": {
    "gn:admin1_code":"03",
    "gn:asciiname":"La Dormida",
    "gn:country_code":"CO",
    "gn:dem":121,
    "gn:feature_class":"P",
    "gn:feature_code":"PPL",
    "gn:name":"La Dormida",
    "gn:population":0,
    "gn:timezone":"America/Bogota",
    "iso:country":"CO",
    "name:spa_x_preferred":[
        "La Dormida"
    ],
    "wof:name":"La Dormida",
    "wof:placetype":"locality"
},
  "geometry": {"coordinates":[-70.76614000000002,6.73867],"type":"Point"}
}