{
  "type": "Feature",
  "properties": {
    "gn:admin1_code":"36",
    "gn:admin2_code":"15531.0",
    "gn:asciiname":"Paramo",
    "gn:country_code":"CO",
    "gn:dem":1366,
    "gn:feature_class":"P",
    "gn:feature_code":"PPL",
    "gn:name":"P\u00e1ramo",
    "gn:population":0,
    "gn:timezone":"America/Bogota",
    "iso:country":"CO",
    "wof:name":"Paramo",
    "wof:placetype":"locality"
},
  "geometry": {"coordinates":[-73.98083000000003,5.61917],"type":"Point"}
}