{
  "type": "Feature",
  "properties": {
    "gn:admin1_code":"2.0",
    "gn:admin2_code":"5490.0",
    "gn:asciiname":"Nueva Fe",
    "gn:country_code":"CO",
    "gn:dem":62,
    "gn:feature_class":"P",
    "gn:feature_code":"PPL",
    "gn:name":"Nueva Fe",
    "gn:population":0,
    "gn:timezone":"America/Bogota",
    "iso:country":"CO",
    "name:spa_x_preferred":[
        "Nueva Fe"
    ],
    "wof:name":"Nueva Fe",
    "wof:placetype":"locality"
},
  "geometry": {"coordinates":[-76.58932,8.44811],"type":"Point"}
}