{
  "type": "Feature",
  "properties": {
    "gn:admin1_code":"26.0",
    "gn:admin2_code":"68689.0",
    "gn:asciiname":"Alto Viento",
    "gn:country_code":"CO",
    "gn:dem":844,
    "gn:feature_class":"P",
    "gn:feature_code":"PPLL",
    "gn:name":"Alto Viento",
    "gn:population":0,
    "gn:timezone":"America/Bogota",
    "iso:country":"CO",
    "wof:name":"Alto Viento",
    "wof:placetype":"locality"
},
  "geometry": {"coordinates":[-73.51231999999997,6.8136],"type":"Point"}
}