{
  "type": "Feature",
  "properties": {
    "gn:admin1_code":"26",
    "gn:admin2_code":"68655.0",
    "gn:asciiname":"Santa Fe",
    "gn:country_code":"CO",
    "gn:dem":123,
    "gn:feature_class":"P",
    "gn:feature_code":"PPL",
    "gn:name":"Santa F\u00e9",
    "gn:population":0,
    "gn:timezone":"America/Bogota",
    "iso:country":"CO",
    "name:ara_x_preferred":[
        "\u0633\u0627\u0646\u062a\u0627 \u0641\u064a"
    ],
    "name:bre_x_preferred":[
        "Santa Fe"
    ],
    "name:bul_x_preferred":[
        "\u0421\u0430\u043d\u0442\u0430 \u0424\u0435"
    ],
    "name:cat_x_preferred":[
        "Santa Fe"
    ],
    "name:ceb_x_preferred":[
        "Santa Fe"
    ],
    "name:ces_x_preferred":[
        "Santa Fe"
    ],
    "name:dan_x_preferred":[
        "Santa Fe"
    ],
    "name:deu_x_preferred":[
        "Santa Fe"
    ],
    "name:epo_x_preferred":[
        "Santa Fe"
    ],
    "name:est_x_preferred":[
        "Santa Fe"
    ],
    "name:eus_x_preferred":[
        "Santa Fe"
    ],
    "name:fas_x_preferred":[
        "\u0633\u0627\u0646\u062a\u0627 \u0641\u0647"
    ],
    "name:fin_x_preferred":[
        "Santa Fe"
    ],
    "name:fra_x_preferred":[
        "Santa Fe"
    ],
    "name:glg_x_preferred":[
        "Santa Fe"
    ],
    "name:heb_x_preferred":[
        "\u05e1\u05e0\u05d8\u05d4 \u05e4\u05d4"
    ],
    "name:hin_x_preferred":[
        "\u0938\u0948\u0928\u094d\u091f\u093e \u092b\u0948"
    ],
    "name:hrv_x_preferred":[
        "Santa Fe"
    ],
    "name:hun_x_preferred":[
        "Santa Fe"
    ],
    "name:hye_x_preferred":[
        "\u054d\u0561\u0576\u057f\u0561 \u0556\u0565"
    ],
    "name:ilo_x_preferred":[
        "Santa Fe"
    ],
    "name:ita_x_preferred":[
        "Santa Fe"
    ],
    "name:jpn_x_preferred":[
        "\u30b5\u30f3\u30bf\u30d5\u30a7"
    ],
    "name:kor_x_preferred":[
        "\uc0b0\ud0c0\ud398"
    ],
    "name:lit_x_preferred":[
        "Santa F\u0117"
    ],
    "name:nah_x_preferred":[
        "Santa Fe"
    ],
    "name:nld_x_preferred":[
        "Santa Fe"
    ],
    "name:nor_x_preferred":[
        "Santa Fe"
    ],
    "name:oss_x_preferred":[
        "\u0421\u0430\u043d\u0442\u0430-\u0424\u0435"
    ],
    "name:pol_x_preferred":[
        "Santa Fe"
    ],
    "name:ron_x_preferred":[
        "Santa Fe"
    ],
    "name:rus_x_preferred":[
        "\u0421\u0430\u043d\u0442\u0430-\u0424\u0435"
    ],
    "name:sco_x_preferred":[
        "Santa Fe"
    ],
    "name:slk_x_preferred":[
        "Santa Fe"
    ],
    "name:spa_x_preferred":[
        "Santa Fe"
    ],
    "name:srp_x_preferred":[
        "\u0421\u0430\u043d\u0442\u0430 \u0424\u0435"
    ],
    "name:swe_x_preferred":[
        "Santa Fe"
    ],
    "name:tur_x_preferred":[
        "Santa Fe"
    ],
    "name:ukr_x_preferred":[
        "\u0421\u0430\u043d\u0442\u0430-\u0424\u0435"
    ],
    "name:urd_x_preferred":[
        "\u0633\u0627\u0646\u062a\u0627 \u0641\u06d2"
    ],
    "name:vol_x_preferred":[
        "Santa Fe"
    ],
    "name:war_x_preferred":[
        "Santa Fe"
    ],
    "wof:name":"Santa Fe",
    "wof:placetype":"locality"
},
  "geometry": {"coordinates":[-73.44306,7.37083],"type":"Point"}
}