{
  "type": "Feature",
  "properties": {
    "gn:admin1_code":"35",
    "gn:admin2_code":"13468.0",
    "gn:asciiname":"Las Boquillas",
    "gn:country_code":"CO",
    "gn:dem":13,
    "gn:feature_class":"P",
    "gn:feature_code":"PPL",
    "gn:name":"Las Boquillas",
    "gn:population":0,
    "gn:timezone":"America/Bogota",
    "iso:country":"CO",
    "name:und_x_variant":[
        "Boquillas",
        "Corregimiento Las Boquillas",
        "Las Boquillas"
    ],
    "wof:name":"Las Boquillas",
    "wof:placetype":"locality"
},
  "geometry": {"coordinates":[-74.56532,9.11986],"type":"Point"}
}