{
  "type": "Feature",
  "properties": {
    "gn:admin1_code":"36",
    "gn:admin2_code":"15507.0",
    "gn:asciiname":"Sitio Nuevo",
    "gn:country_code":"CO",
    "gn:dem":815,
    "gn:feature_class":"P",
    "gn:feature_code":"PPL",
    "gn:name":"Sitio Nuevo",
    "gn:population":0,
    "gn:timezone":"America/Bogota",
    "iso:country":"CO",
    "wof:name":"Sitio Nuevo",
    "wof:placetype":"locality"
},
  "geometry": {"coordinates":[-74.12052,5.79902],"type":"Point"}
}