{
  "type": "Feature",
  "properties": {
    "gn:admin1_code":"35",
    "gn:admin2_code":"13244.0",
    "gn:asciiname":"La Puente",
    "gn:country_code":"CO",
    "gn:dem":136,
    "gn:feature_class":"P",
    "gn:feature_code":"PPL",
    "gn:name":"La Puente",
    "gn:population":0,
    "gn:timezone":"America/Bogota",
    "iso:country":"CO",
    "name:und_x_variant":[
        "Hacienda La Puente",
        "La Puente"
    ],
    "wof:name":"La Puente",
    "wof:placetype":"locality"
},
  "geometry": {"coordinates":[-75.06626999999997,9.60715],"type":"Point"}
}