{
  "type": "Feature",
  "properties": {
    "gn:admin1_code":"3",
    "gn:admin2_code":"81591.0",
    "gn:asciiname":"La Porfia",
    "gn:country_code":"CO",
    "gn:dem":118,
    "gn:feature_class":"P",
    "gn:feature_code":"PPL",
    "gn:name":"La Porf\u00eda",
    "gn:population":0,
    "gn:timezone":"America/Bogota",
    "iso:country":"CO",
    "name:und_x_variant":[
        "Tres Matas",
        "Hato La Porf\u00eda",
        "La Porf\u00eda"
    ],
    "wof:name":"La Porfia",
    "wof:placetype":"locality"
},
  "geometry": {"coordinates":[-70.70237,6.35986],"type":"Point"}
}