{
  "type": "Feature",
  "properties": {
    "gn:admin1_code":"19",
    "gn:admin2_code":"50270",
    "gn:asciiname":"El Encanto",
    "gn:country_code":"CO",
    "gn:dem":1300,
    "gn:feature_class":"P",
    "gn:feature_code":"PPL",
    "gn:name":"El Encanto",
    "gn:population":0,
    "gn:timezone":"America/Bogota",
    "iso:country":"CO",
    "name:spa_x_preferred":[
        "El Encanto"
    ],
    "wof:name":"El Encanto",
    "wof:placetype":"locality"
},
  "geometry": {"coordinates":[-73.89444,3.71288],"type":"Point"}
}