{
  "type": "Feature",
  "properties": {
    "gn:admin1_code":"9",
    "gn:admin2_code":"19256.0",
    "gn:asciiname":"Las Botas",
    "gn:country_code":"CO",
    "gn:dem":1671,
    "gn:feature_class":"P",
    "gn:feature_code":"PPL",
    "gn:name":"Las Botas",
    "gn:population":0,
    "gn:timezone":"America/Bogota",
    "iso:country":"CO",
    "name:und_x_variant":[
        "Botas",
        "Las Botas"
    ],
    "wof:name":"Las Botas",
    "wof:placetype":"locality"
},
  "geometry": {"coordinates":[-76.85214000000001,2.48172],"type":"Point"}
}