{
  "type": "Feature",
  "properties": {
    "gn:country":"CO",
    "gn:fcode":"PPL",
    "gn:pop":863,
    "iso:country":"CO",
    "name:ast_x_preferred":[
        "Nuevo Col\u00f3n"
    ],
    "name:ceb_x_preferred":[
        "Nuevo Col\u00f3n"
    ],
    "name:eng_x_preferred":[
        "Nuevo Col\u00f3n"
    ],
    "name:fra_x_preferred":[
        "Nuevo Col\u00f3n"
    ],
    "name:ita_x_preferred":[
        "Nuevo Col\u00f3n"
    ],
    "name:kat_x_preferred":[
        "\u10dc\u10e3\u10d4\u10d5\u10dd-\u10d9\u10dd\u10da\u10dd\u10dc\u10d8"
    ],
    "name:msa_x_preferred":[
        "Nuevo Col\u00f3n"
    ],
    "name:nan_x_preferred":[
        "Nuevo Col\u00f3n"
    ],
    "name:nld_x_preferred":[
        "Nuevo Col\u00f3n"
    ],
    "name:por_x_preferred":[
        "Nuevo Col\u00f3n"
    ],
    "name:rus_x_preferred":[
        "\u041d\u0443\u044d\u0432\u043e-\u041a\u043e\u043b\u043e\u043d"
    ],
    "name:sco_x_preferred":[
        "Nuevo Col\u00f3n"
    ],
    "name:spa_x_preferred":[
        "Nuevo Col\u00f3n"
    ],
    "name:swe_x_preferred":[
        "Nuevo Col\u00f3n"
    ],
    "name:tgl_x_preferred":[
        "Nuevo Col\u00f3n"
    ],
    "name:vie_x_preferred":[
        "Nuevo Col\u00f3n"
    ],
    "name:war_x_preferred":[
        "Nuevo Col\u00f3n"
    ],
    "name:zho_x_preferred":[
        "\u65b0\u79d1\u9686"
    ],
    "qs:name":"Nuevo Col\u00f3n",
    "qs:photos_9r":0,
    "qs:photos_sr":0,
    "qs:pop_sr":"2",
    "wof:name":"Nuevo Col\u00f3n",
    "wof:placetype":"locality",
    "wof:population":863
},
  "geometry": {"coordinates":[-73.45659999999999,5.35368],"type":"Point"}
}