{
  "type": "Feature",
  "properties": {
    "gn:admin1_code":"27.0",
    "gn:admin2_code":"70204.0",
    "gn:asciiname":"Yumal",
    "gn:country_code":"CO",
    "gn:dem":87,
    "gn:feature_class":"P",
    "gn:feature_code":"PPL",
    "gn:name":"Yumal",
    "gn:population":0,
    "gn:timezone":"America/Bogota",
    "iso:country":"CO",
    "name:und_x_variant":[
        "Caser\u00edo Yumal",
        "Yumal"
    ],
    "wof:name":"Yumal",
    "wof:placetype":"locality"
},
  "geometry": {"coordinates":[-75.36749,9.44752],"type":"Point"}
}