{
  "type": "Feature",
  "properties": {
    "gn:admin1_code":"11.0",
    "gn:admin2_code":"27050.0",
    "gn:asciiname":"Yuto",
    "gn:country_code":"CO",
    "gn:dem":53,
    "gn:feature_class":"P",
    "gn:feature_code":"PPLA2",
    "gn:name":"Yuto",
    "gn:population":0,
    "gn:timezone":"America/Bogota",
    "iso:country":"CO",
    "name:spa_x_preferred":[
        "Yuto"
    ],
    "wof:name":"Yuto",
    "wof:placetype":"locality"
},
  "geometry": {"coordinates":[-76.63512,5.53168],"type":"Point"}
}