{
  "type": "Feature",
  "properties": {
    "gn:admin1_code":"35.0",
    "gn:admin2_code":"13838.0",
    "gn:asciiname":"El Calvario",
    "gn:country_code":"CO",
    "gn:dem":28,
    "gn:feature_class":"P",
    "gn:feature_code":"PPL",
    "gn:name":"El Calvario",
    "gn:population":0,
    "gn:timezone":"America/Bogota",
    "iso:country":"CO",
    "wof:name":"El Calvario",
    "wof:placetype":"locality"
},
  "geometry": {"coordinates":[-75.42371999999997,10.22555],"type":"Point"}
}