{
  "type": "Feature",
  "properties": {
    "gn:admin1_code":"16.0",
    "gn:admin2_code":"41872.0",
    "gn:asciiname":"Palmichal",
    "gn:country_code":"CO",
    "gn:dem":1112,
    "gn:feature_class":"P",
    "gn:feature_code":"PPL",
    "gn:name":"Palmichal",
    "gn:population":0,
    "gn:timezone":"America/Bogota",
    "iso:country":"CO",
    "name:spa_x_preferred":[
        "Palmichal"
    ],
    "wof:name":"Palmichal",
    "wof:placetype":"locality"
},
  "geometry": {"coordinates":[-75.04743000000001,3.43018],"type":"Point"}
}