{
  "type": "Feature",
  "properties": {
    "gn:admin1_code":"38.0",
    "gn:asciiname":"Penoncito",
    "gn:country_code":"CO",
    "gn:dem":36,
    "gn:feature_class":"P",
    "gn:feature_code":"PPL",
    "gn:name":"Pe\u00f1oncito",
    "gn:population":0,
    "gn:timezone":"America/Bogota",
    "iso:country":"CO",
    "name:und_x_variant":[
        "Caser\u00edo Pe\u00f1oncito",
        "Pe\u00f1oncito"
    ],
    "wof:name":"Penoncito",
    "wof:placetype":"locality"
},
  "geometry": {"coordinates":[-73.93000000000001,8.97853],"type":"Point"}
}