{
  "type": "Feature",
  "properties": {
    "gn:admin1_code":"9.0",
    "gn:admin2_code":"19450.0",
    "gn:asciiname":"El Diviso",
    "gn:country_code":"CO",
    "gn:dem":1005,
    "gn:feature_class":"P",
    "gn:feature_code":"PPL",
    "gn:name":"El Diviso",
    "gn:population":0,
    "gn:timezone":"America/Bogota",
    "iso:country":"CO",
    "wof:name":"El Diviso",
    "wof:placetype":"locality"
},
  "geometry": {"coordinates":[-77.09863,1.77052],"type":"Point"}
}