{
  "type": "Feature",
  "properties": {
    "gn:admin1_code":"29",
    "gn:admin2_code":"76248.0",
    "gn:asciiname":"Las Vegas",
    "gn:country_code":"CO",
    "gn:dem":945,
    "gn:feature_class":"P",
    "gn:feature_code":"PPL",
    "gn:name":"Las Vegas",
    "gn:population":0,
    "gn:timezone":"America/Bogota",
    "iso:country":"CO",
    "wof:name":"Las Vegas",
    "wof:placetype":"locality"
},
  "geometry": {"coordinates":[-76.38722,3.74556],"type":"Point"}
}