{
  "type": "Feature",
  "properties": {
    "gn:admin1_code":"2.0",
    "gn:admin2_code":"5088.0",
    "gn:asciiname":"Yarumo",
    "gn:country_code":"CO",
    "gn:dem":2496,
    "gn:feature_class":"P",
    "gn:feature_code":"PPL",
    "gn:name":"Yarumo",
    "gn:population":0,
    "gn:timezone":"America/Bogota",
    "iso:country":"CO",
    "name:spa_x_preferred":[
        "Yarumo"
    ],
    "wof:name":"Yarumo",
    "wof:placetype":"locality"
},
  "geometry": {"coordinates":[-75.61208000000001,6.38705],"type":"Point"}
}