{
  "type": "Feature",
  "properties": {
    "gn:admin1_code":"16.0",
    "gn:admin2_code":"41518.0",
    "gn:asciiname":"Calota",
    "gn:country_code":"CO",
    "gn:dem":1506,
    "gn:feature_class":"P",
    "gn:feature_code":"PPL",
    "gn:name":"Calota",
    "gn:population":0,
    "gn:timezone":"America/Bogota",
    "iso:country":"CO",
    "wof:name":"Calota",
    "wof:placetype":"locality"
},
  "geometry": {"coordinates":[-75.81389,2.36778],"type":"Point"}
}