{
  "type": "Feature",
  "properties": {
    "gn:admin1_code":"16.0",
    "gn:admin2_code":"41078.0",
    "gn:asciiname":"Los Balsos",
    "gn:country_code":"CO",
    "gn:dem":729,
    "gn:feature_class":"P",
    "gn:feature_code":"PPL",
    "gn:name":"Los Balsos",
    "gn:population":0,
    "gn:timezone":"America/Bogota",
    "iso:country":"CO",
    "name:spa_x_preferred":[
        "Los Balsos"
    ],
    "wof:name":"Los Balsos",
    "wof:placetype":"locality"
},
  "geometry": {"coordinates":[-74.89791,3.25155],"type":"Point"}
}