{
  "type": "Feature",
  "properties": {
    "gn:admin1_code":"32.0",
    "gn:admin2_code":"85162.0",
    "gn:asciiname":"Rincon Seco",
    "gn:country_code":"CO",
    "gn:dem":236,
    "gn:feature_class":"P",
    "gn:feature_code":"PPL",
    "gn:name":"Rinc\u00f3n Seco",
    "gn:population":0,
    "gn:timezone":"America/Bogota",
    "iso:country":"CO",
    "wof:name":"Rincon Seco",
    "wof:placetype":"locality"
},
  "geometry": {"coordinates":[-72.78158000000001,4.76471],"type":"Point"}
}