{
  "type": "Feature",
  "properties": {
    "gn:admin1_code":"12",
    "gn:admin2_code":"23660.0",
    "gn:asciiname":"Catalina",
    "gn:country_code":"CO",
    "gn:dem":80,
    "gn:feature_class":"P",
    "gn:feature_code":"PPL",
    "gn:name":"Catalina",
    "gn:population":0,
    "gn:timezone":"America/Bogota",
    "iso:country":"CO",
    "wof:name":"Catalina",
    "wof:placetype":"locality"
},
  "geometry": {"coordinates":[-75.37629,8.86002],"type":"Point"}
}