{
  "type": "Feature",
  "properties": {
    "gn:admin1_code":"33.0",
    "gn:admin2_code":"25513.0",
    "gn:asciiname":"Portugal",
    "gn:country_code":"CO",
    "gn:dem":2366,
    "gn:feature_class":"P",
    "gn:feature_code":"PPL",
    "gn:name":"Portugal",
    "gn:population":0,
    "gn:timezone":"America/Bogota",
    "iso:country":"CO",
    "wof:name":"Portugal",
    "wof:placetype":"locality"
},
  "geometry": {"coordinates":[-74.10028,5.19448],"type":"Point"}
}