{
  "type": "Feature",
  "properties": {
    "gn:admin1_code":"38",
    "gn:admin2_code":"47551.0",
    "gn:asciiname":"Hacienda La Reserva",
    "gn:country_code":"CO",
    "gn:dem":69,
    "gn:feature_class":"P",
    "gn:feature_code":"PPL",
    "gn:name":"Hacienda La Reserva",
    "gn:population":0,
    "gn:timezone":"America/Bogota",
    "iso:country":"CO",
    "wof:name":"Hacienda La Reserva",
    "wof:placetype":"locality"
},
  "geometry": {"coordinates":[-74.43609000000002,10.25552],"type":"Point"}
}