{
  "type": "Feature",
  "properties": {
    "gn:admin1_code":"30",
    "gn:admin2_code":"97511.0",
    "gn:asciiname":"Campeon",
    "gn:country_code":"CO",
    "gn:dem":131,
    "gn:feature_class":"P",
    "gn:feature_code":"PPL",
    "gn:name":"Campe\u00f3n",
    "gn:population":0,
    "gn:timezone":"America/Bogota",
    "iso:country":"CO",
    "wof:name":"Campeon",
    "wof:placetype":"locality"
},
  "geometry": {"coordinates":[-70.2563,-0.37698],"type":"Point"}
}