{
  "type": "Feature",
  "properties": {
    "gn:admin1_code":"15",
    "gn:admin2_code":"94888.0",
    "gn:asciiname":"Francisco",
    "gn:country_code":"CO",
    "gn:dem":455,
    "gn:feature_class":"P",
    "gn:feature_code":"PPL",
    "gn:name":"Francisco",
    "gn:population":0,
    "gn:timezone":"America/Bogota",
    "iso:country":"CO",
    "wof:name":"Francisco",
    "wof:placetype":"locality"
},
  "geometry": {"coordinates":[-69.38333,2.65],"type":"Point"}
}