{
  "type": "Feature",
  "properties": {
    "gn:admin1_code":"10.0",
    "gn:admin2_code":"20228.0",
    "gn:asciiname":"Oca",
    "gn:cc2":"CO",
    "gn:country_code":"CO",
    "gn:dem":56,
    "gn:feature_class":"P",
    "gn:feature_code":"PPL",
    "gn:name":"Oca",
    "gn:population":0,
    "gn:timezone":"America/Bogota",
    "iso:country":"CO",
    "name:und_x_variant":[
        "Hacienda Oca",
        "Oca"
    ],
    "wof:name":"Oca",
    "wof:placetype":"locality"
},
  "geometry": {"coordinates":[-73.55,9.16667],"type":"Point"}
}