{
  "type": "Feature",
  "properties": {
    "gn:admin1_code":"29.0",
    "gn:admin2_code":"76109.0",
    "gn:asciiname":"Anchicaya",
    "gn:country_code":"CO",
    "gn:dem":404,
    "gn:feature_class":"P",
    "gn:feature_code":"PPL",
    "gn:name":"Anchicaya",
    "gn:population":0,
    "gn:timezone":"America/Bogota",
    "iso:country":"CO",
    "wof:name":"Anchicaya",
    "wof:placetype":"locality"
},
  "geometry": {"coordinates":[-76.91333,3.61861],"type":"Point"}
}