{
  "type": "Feature",
  "properties": {
    "gn:admin1_code":"19",
    "gn:admin2_code":"50573.0",
    "gn:asciiname":"Donde Cala",
    "gn:country_code":"CO",
    "gn:dem":239,
    "gn:feature_class":"P",
    "gn:feature_code":"PPL",
    "gn:name":"Donde Cala",
    "gn:population":0,
    "gn:timezone":"America/Bogota",
    "iso:country":"CO",
    "wof:name":"Donde Cala",
    "wof:placetype":"locality"
},
  "geometry": {"coordinates":[-72.84583000000001,4.11639],"type":"Point"}
}