{
  "type": "Feature",
  "properties": {
    "gn:gn_country":"CO",
    "gn:gn_fcode":"PPLX",
    "gn:gn_pop":0,
    "iso:country":"CO",
    "qs_pg:aaroncc":"CO",
    "qs_pg:gn_country":"CO",
    "qs_pg:gn_fcode":"PPLX",
    "qs_pg:gn_pop":0,
    "qs_pg:name":"Getseman\u00ed",
    "qs_pg:name_adm0":"Colombia",
    "qs_pg:name_adm1":"Bolivar",
    "qs_pg:photos":5052,
    "qs_pg:photos_1k":1000,
    "qs_pg:photos_9k":22,
    "qs_pg:photos_9r":14,
    "qs_pg:photos_all":5052,
    "qs_pg:photos_sr":24,
    "qs_pg:pop_sr":0,
    "qs_pg:qs_pg_placetype":"neighbourhood",
    "qs_pg:qs_pg_placetype_gp":"Suburb",
    "qs_pg:woe_adm0":23424787,
    "woe:adm0_id":23424787,
    "woe:name_adm0":"Colombia",
    "woe:name_adm1":"Bolivar",
    "woe:placetype":"Suburb",
    "wof:name":"Getseman\u00ed",
    "wof:placetype":"neighbourhood"
},
  "geometry": {"coordinates":[-75.55,10.41667],"type":"Point"}
}