{
  "type": "Feature",
  "properties": {
    "gn:admin1_code":"19",
    "gn:admin2_code":"50001.0",
    "gn:asciiname":"Bavaria",
    "gn:country_code":"CO",
    "gn:dem":496,
    "gn:feature_class":"P",
    "gn:feature_code":"PPL",
    "gn:name":"Bavaria",
    "gn:population":0,
    "gn:timezone":"America/Bogota",
    "iso:country":"CO",
    "wof:name":"Bavaria",
    "wof:placetype":"locality"
},
  "geometry": {"coordinates":[-73.64294,4.17768],"type":"Point"}
}