{
  "type": "Feature",
  "properties": {
    "gn:admin1_code":"20.0",
    "gn:admin2_code":"52788.0",
    "gn:asciiname":"Los Arrayanes",
    "gn:country_code":"CO",
    "gn:dem":3106,
    "gn:feature_class":"P",
    "gn:feature_code":"PPL",
    "gn:name":"Los Arrayanes",
    "gn:population":0,
    "gn:timezone":"America/Bogota",
    "iso:country":"CO",
    "wof:name":"Los Arrayanes",
    "wof:placetype":"locality"
},
  "geometry": {"coordinates":[-77.32592,1.05967],"type":"Point"}
}