{
  "type": "Feature",
  "properties": {
    "gn:admin1_code":"2",
    "gn:admin2_code":"5040.0",
    "gn:asciiname":"Paujil",
    "gn:country_code":"CO",
    "gn:dem":1003,
    "gn:feature_class":"P",
    "gn:feature_code":"PPL",
    "gn:name":"Paujil",
    "gn:population":0,
    "gn:timezone":"America/Bogota",
    "iso:country":"CO",
    "wof:name":"Paujil",
    "wof:placetype":"locality"
},
  "geometry": {"coordinates":[-75.24444,7.14167],"type":"Point"}
}