{
  "type": "Feature",
  "properties": {
    "gn:admin1_code":"33",
    "gn:admin2_code":"25885.0",
    "gn:asciiname":"Las Gallinetas",
    "gn:country_code":"CO",
    "gn:dem":1121,
    "gn:feature_class":"P",
    "gn:feature_code":"PPL",
    "gn:name":"Las Gallinetas",
    "gn:population":0,
    "gn:timezone":"America/Bogota",
    "iso:country":"CO",
    "wof:name":"Las Gallinetas",
    "wof:placetype":"locality"
},
  "geometry": {"coordinates":[-74.45097,5.60392],"type":"Point"}
}