{
  "type": "Feature",
  "properties": {
    "gn:admin1_code":"34",
    "gn:asciiname":"Paramillo",
    "gn:country_code":"CO",
    "gn:dem":3279,
    "gn:feature_class":"P",
    "gn:feature_code":"PPL",
    "gn:name":"Paramillo",
    "gn:population":0,
    "gn:timezone":"America/Bogota",
    "iso:country":"CO",
    "wof:name":"Paramillo",
    "wof:placetype":"locality"
},
  "geometry": {"coordinates":[-74.36667,4.07417],"type":"Point"}
}