{
  "type": "Feature",
  "properties": {
    "gn:admin1_code":"17",
    "gn:admin2_code":"44560.0",
    "gn:asciiname":"Joronjoromahana",
    "gn:country_code":"CO",
    "gn:dem":40,
    "gn:feature_class":"P",
    "gn:feature_code":"PPL",
    "gn:name":"Jor\u00f3njoromahana",
    "gn:population":0,
    "gn:timezone":"America/Bogota",
    "iso:country":"CO",
    "wof:name":"Joronjoromahana",
    "wof:placetype":"locality"
},
  "geometry": {"coordinates":[-72.59610000000001,11.49889],"type":"Point"}
}