{
  "type": "Feature",
  "properties": {
    "gn:admin1_code":"17",
    "gn:admin2_code":"44001.0",
    "gn:asciiname":"Moroconcira",
    "gn:country_code":"CO",
    "gn:dem":9,
    "gn:feature_class":"P",
    "gn:feature_code":"PPL",
    "gn:name":"Moroconcir\u00e1",
    "gn:population":0,
    "gn:timezone":"America/Bogota",
    "iso:country":"CO",
    "wof:name":"Moroconcira",
    "wof:placetype":"locality"
},
  "geometry": {"coordinates":[-72.82167,11.48528],"type":"Point"}
}