{
  "type": "Feature",
  "properties": {
    "gn:admin1_code":"12",
    "gn:admin2_code":"23001.0",
    "gn:asciiname":"La Habana",
    "gn:country_code":"CO",
    "gn:dem":26,
    "gn:feature_class":"P",
    "gn:feature_code":"PPLL",
    "gn:name":"La Habana",
    "gn:population":0,
    "gn:timezone":"America/Bogota",
    "iso:country":"CO",
    "wof:name":"La Habana",
    "wof:placetype":"locality"
},
  "geometry": {"coordinates":[-75.89737,8.62552],"type":"Point"}
}