{
  "type": "Feature",
  "properties": {
    "gn:admin1_code":"38",
    "gn:admin2_code":"47170.0",
    "gn:asciiname":"La Seda",
    "gn:cc2":"CO",
    "gn:country_code":"CO",
    "gn:dem":134,
    "gn:feature_class":"P",
    "gn:feature_code":"PPL",
    "gn:name":"La Seda",
    "gn:population":0,
    "gn:timezone":"America/Bogota",
    "iso:country":"CO",
    "name:und_x_variant":[
        "Hacienda La Seda",
        "La Seda"
    ],
    "wof:name":"La Seda",
    "wof:placetype":"locality"
},
  "geometry": {"coordinates":[-74.45,10.13333],"type":"Point"}
}