{
  "type": "Feature",
  "properties": {
    "gn:admin1_code":"17",
    "gn:admin2_code":"44078.0",
    "gn:asciiname":"Zulia",
    "gn:country_code":"CO",
    "gn:dem":1419,
    "gn:feature_class":"P",
    "gn:feature_code":"PPL",
    "gn:name":"Zulia",
    "gn:population":0,
    "gn:timezone":"America/Bogota",
    "iso:country":"CO",
    "name:ara_x_preferred":[
        "\u0632\u0648\u0644\u064a\u0627"
    ],
    "name:arg_x_preferred":[
        "Estato Zulia"
    ],
    "name:azb_x_preferred":[
        "\u0633\u0648\u0644\u06cc\u0627"
    ],
    "name:bel_x_preferred":[
        "\u0421\u0443\u043b\u0456\u044f"
    ],
    "name:bre_x_preferred":[
        "Zulia"
    ],
    "name:bul_x_preferred":[
        "\u0421\u0443\u043b\u0438\u044f"
    ],
    "name:cat_x_preferred":[
        "Zulia"
    ],
    "name:ceb_x_preferred":[
        "Estado Zulia"
    ],
    "name:ces_x_preferred":[
        "Zulia"
    ],
    "name:cor_x_preferred":[
        "Zulia"
    ],
    "name:dan_x_preferred":[
        "Zulia"
    ],
    "name:deu_x_preferred":[
        "Zulia"
    ],
    "name:epo_x_preferred":[
        "Zulia"
    ],
    "name:est_x_preferred":[
        "Zulia osariik"
    ],
    "name:eus_x_preferred":[
        "Zulia"
    ],
    "name:fas_x_preferred":[
        "\u0633\u0648\u0644\u06cc\u0627"
    ],
    "name:fin_x_preferred":[
        "Zulia"
    ],
    "name:glg_x_preferred":[
        "Zulia"
    ],
    "name:heb_x_preferred":[
        "\u05e1\u05d5\u05dc\u05d9\u05d4"
    ],
    "name:hrv_x_preferred":[
        "Zulia"
    ],
    "name:ita_x_preferred":[
        "Zulia"
    ],
    "name:jpn_x_preferred":[
        "\u30b9\u30ea\u30a2\u5dde"
    ],
    "name:kat_x_preferred":[
        "\u10e1\u10e3\u10da\u10d8\u10d0\u10e1 \u10e8\u10e2\u10d0\u10e2\u10d8"
    ],
    "name:kor_x_preferred":[
        "\uc220\ub9ac\uc544\uc8fc"
    ],
    "name:lad_x_preferred":[
        "Zulia"
    ],
    "name:lit_x_preferred":[
        "Sulija"
    ],
    "name:mkd_x_preferred":[
        "\u0421\u0443\u043b\u0438\u0458\u0430"
    ],
    "name:msa_x_preferred":[
        "Zulia"
    ],
    "name:nld_x_preferred":[
        "Zulia"
    ],
    "name:nno_x_preferred":[
        "Zulia"
    ],
    "name:nor_x_preferred":[
        "Zulia"
    ],
    "name:oss_x_preferred":[
        "\u0421\u0443\u043b\u0438"
    ],
    "name:pnb_x_preferred":[
        "\u0635\u0648\u0628\u06c1 \u0632\u0648\u0644\u06cc\u0627"
    ],
    "name:pol_x_preferred":[
        "Zulia"
    ],
    "name:por_x_preferred":[
        "Zulia"
    ],
    "name:que_x_preferred":[
        "Zulia suyu"
    ],
    "name:ron_x_preferred":[
        "Zulia"
    ],
    "name:rus_x_preferred":[
        "\u0421\u0443\u043b\u0438\u044f"
    ],
    "name:sco_x_preferred":[
        "Zulia"
    ],
    "name:spa_x_preferred":[
        "Estado Zulia"
    ],
    "name:srp_x_preferred":[
        "\u0417\u0443\u043b\u0438\u0458\u0430"
    ],
    "name:swe_x_preferred":[
        "Zulia"
    ],
    "name:tgk_x_preferred":[
        "\u0418\u0451\u043b\u043e\u0442\u0438 \u0417\u0443\u043b\u0438\u044f"
    ],
    "name:tha_x_preferred":[
        "\u0e23\u0e31\u0e10\u0e0b\u0e39\u0e40\u0e25\u0e35\u0e22"
    ],
    "name:ukr_x_preferred":[
        "\u0421\u0443\u043b\u0456\u044f"
    ],
    "name:urd_x_preferred":[
        "\u0633\u0648\u0644\u06cc\u0627"
    ],
    "name:vie_x_preferred":[
        "Zulia"
    ],
    "name:war_x_preferred":[
        "Zulia"
    ],
    "name:zho_x_preferred":[
        "\u82cf\u5229\u4e9a\u5dde"
    ],
    "wof:name":"Zulia",
    "wof:placetype":"locality"
},
  "geometry": {"coordinates":[-72.6875,10.84056],"type":"Point"}
}