{
  "type": "Feature",
  "properties": {
    "gn:admin1_code":"17",
    "gn:admin2_code":"44078.0",
    "gn:asciiname":"Zulia",
    "gn:country_code":"CO",
    "gn:dem":1419,
    "gn:feature_class":"P",
    "gn:feature_code":"PPL",
    "gn:name":"Zulia",
    "gn:population":0,
    "gn:timezone":"America/Bogota",
    "iso:country":"CO",
    "wof:name":"Zulia",
    "wof:placetype":"locality"
},
  "geometry": {"coordinates":[-72.6875,10.84056],"type":"Point"}
}