{
  "type": "Feature",
  "properties": {
    "gn:admin1_code":"16.0",
    "gn:admin2_code":"41206.0",
    "gn:asciiname":"San Antonio Bajo",
    "gn:country_code":"CO",
    "gn:dem":1147,
    "gn:feature_class":"P",
    "gn:feature_code":"PPL",
    "gn:name":"San Antonio Bajo",
    "gn:population":0,
    "gn:timezone":"America/Bogota",
    "iso:country":"CO",
    "name:spa_x_preferred":[
        "San Antonio Bajo"
    ],
    "wof:name":"San Antonio Bajo",
    "wof:placetype":"locality"
},
  "geometry": {"coordinates":[-74.74056999999998,3.47348],"type":"Point"}
}