{
  "type": "Feature",
  "properties": {
    "gn:admin1_code":"3",
    "gn:admin2_code":"81591.0",
    "gn:asciiname":"El Cairo",
    "gn:country_code":"CO",
    "gn:dem":120,
    "gn:feature_class":"P",
    "gn:feature_code":"PPL",
    "gn:name":"El Cairo",
    "gn:population":0,
    "gn:timezone":"America/Bogota",
    "iso:country":"CO",
    "name:ceb_x_preferred":[
        "El Cairo"
    ],
    "name:fra_x_preferred":[
        "El Cairo"
    ],
    "name:ita_x_preferred":[
        "El Cairo"
    ],
    "name:kat_x_preferred":[
        "\u10d4\u10da-\u10d9\u10d0\u10d8\u10e0\u10dd"
    ],
    "name:msa_x_preferred":[
        "El Cairo"
    ],
    "name:nld_x_preferred":[
        "El Cairo"
    ],
    "name:sco_x_preferred":[
        "El Cairo"
    ],
    "name:spa_x_preferred":[
        "El Cairo"
    ],
    "name:swe_x_preferred":[
        "El Cairo"
    ],
    "name:urd_x_preferred":[
        "\u0627\u06cc\u0644 \u0642\u0627\u0626\u0631\u0648"
    ],
    "name:vie_x_preferred":[
        "El Cairo"
    ],
    "name:war_x_preferred":[
        "El Cairo"
    ],
    "name:zho_x_preferred":[
        "\u57c3\u723e\u51f1\u7f85"
    ],
    "wof:name":"El Cairo",
    "wof:placetype":"locality"
},
  "geometry": {"coordinates":[-70.72374000000001,6.58086],"type":"Point"}
}