{
  "type": "Feature",
  "properties": {
    "gn:admin1_code":"3",
    "gn:admin2_code":"81591.0",
    "gn:asciiname":"El Cairo",
    "gn:country_code":"CO",
    "gn:dem":120,
    "gn:feature_class":"P",
    "gn:feature_code":"PPL",
    "gn:name":"El Cairo",
    "gn:population":0,
    "gn:timezone":"America/Bogota",
    "iso:country":"CO",
    "name:spa_x_preferred":[
        "El Cairo"
    ],
    "wof:name":"El Cairo",
    "wof:placetype":"locality"
},
  "geometry": {"coordinates":[-70.72374000000001,6.58086],"type":"Point"}
}