{
  "type": "Feature",
  "properties": {
    "gn:admin1_code":"2",
    "gn:admin2_code":"5585.0",
    "gn:asciiname":"Caserio Platanera",
    "gn:country_code":"CO",
    "gn:dem":125,
    "gn:feature_class":"P",
    "gn:feature_code":"PPL",
    "gn:name":"Caser\u00edo Platanera",
    "gn:population":0,
    "gn:timezone":"America/Bogota",
    "iso:country":"CO",
    "wof:name":"Caserio Platanera",
    "wof:placetype":"locality"
},
  "geometry": {"coordinates":[-74.59222,6.20056],"type":"Point"}
}