{
  "type": "Feature",
  "properties": {
    "gn:admin1_code":"38",
    "gn:admin2_code":"47720.0",
    "gn:asciiname":"El Treinta",
    "gn:country_code":"CO",
    "gn:dem":86,
    "gn:feature_class":"P",
    "gn:feature_code":"PPL",
    "gn:name":"El Treinta",
    "gn:population":0,
    "gn:timezone":"America/Bogota",
    "iso:country":"CO",
    "wof:name":"El Treinta",
    "wof:placetype":"locality"
},
  "geometry": {"coordinates":[-74.59805,9.5676],"type":"Point"}
}