{
  "type": "Feature",
  "properties": {
    "gn:admin1_code":"28.0",
    "gn:admin2_code":"73168.0",
    "gn:asciiname":"Florencia",
    "gn:country_code":"CO",
    "gn:dem":1593,
    "gn:feature_class":"P",
    "gn:feature_code":"PPL",
    "gn:name":"Florencia",
    "gn:population":0,
    "gn:timezone":"America/Bogota",
    "iso:country":"CO",
    "wof:name":"Florencia",
    "wof:placetype":"locality"
},
  "geometry": {"coordinates":[-75.60194,3.72111],"type":"Point"}
}