{
  "type": "Feature",
  "properties": {
    "gn:admin1_code":"3.0",
    "gn:admin2_code":"81300.0",
    "gn:asciiname":"Caserio Palmarito",
    "gn:country_code":"CO",
    "gn:dem":232,
    "gn:feature_class":"P",
    "gn:feature_code":"PPL",
    "gn:name":"Caser\u00edo Palmarito",
    "gn:population":0,
    "gn:timezone":"America/Bogota",
    "iso:country":"CO",
    "wof:name":"Caserio Palmarito",
    "wof:placetype":"locality"
},
  "geometry": {"coordinates":[-71.71250000000001,6.74444],"type":"Point"}
}