{
  "type": "Feature",
  "properties": {
    "gn:admin1_code":"12",
    "gn:admin2_code":"23001.0",
    "gn:asciiname":"La Tampa",
    "gn:country_code":"CO",
    "gn:dem":38,
    "gn:feature_class":"P",
    "gn:feature_code":"PPLL",
    "gn:name":"La Tampa",
    "gn:population":0,
    "gn:timezone":"America/Bogota",
    "iso:country":"CO",
    "wof:name":"La Tampa",
    "wof:placetype":"locality"
},
  "geometry": {"coordinates":[-75.76585,8.62255],"type":"Point"}
}