{
  "type": "Feature",
  "properties": {
    "gn:admin1_code":"22.0",
    "gn:admin2_code":"86573.0",
    "gn:asciiname":"Inspeccion de Policia Las Delicias",
    "gn:country_code":"CO",
    "gn:dem":194,
    "gn:feature_class":"P",
    "gn:feature_code":"PPL",
    "gn:name":"Inspecci\u00f3n de Polic\u00eda Las Delicias",
    "gn:population":0,
    "gn:timezone":"America/Bogota",
    "iso:country":"CO",
    "wof:name":"Inspeccion de Policia Las Delicias",
    "wof:placetype":"locality"
},
  "geometry": {"coordinates":[-75.41938,0.47578],"type":"Point"}
}