{
  "type": "Feature",
  "properties": {
    "gn:admin1_code":"2.0",
    "gn:admin2_code":"5042.0",
    "gn:asciiname":"Manglar",
    "gn:country_code":"CO",
    "gn:dem":1796,
    "gn:feature_class":"P",
    "gn:feature_code":"PPL",
    "gn:name":"Manglar",
    "gn:population":0,
    "gn:timezone":"America/Bogota",
    "iso:country":"CO",
    "wof:name":"Manglar",
    "wof:placetype":"locality"
},
  "geometry": {"coordinates":[-75.93944,6.55917],"type":"Point"}
}