{
  "type": "Feature",
  "properties": {
    "gn:admin1_code":"29",
    "gn:admin2_code":"76275.0",
    "gn:asciiname":"Chococito",
    "gn:country_code":"CO",
    "gn:dem":1007,
    "gn:feature_class":"P",
    "gn:feature_code":"PPL",
    "gn:name":"Chococito",
    "gn:population":0,
    "gn:timezone":"America/Bogota",
    "iso:country":"CO",
    "wof:name":"Chococito",
    "wof:placetype":"locality"
},
  "geometry": {"coordinates":[-76.30178000000002,3.28714],"type":"Point"}
}