{
  "type": "Feature",
  "properties": {
    "gn:admin1_code":"37.0",
    "gn:admin2_code":"17873.0",
    "gn:asciiname":"La Telarana",
    "gn:country_code":"CO",
    "gn:dem":2122,
    "gn:feature_class":"P",
    "gn:feature_code":"PPL",
    "gn:name":"La Telara\u00f1a",
    "gn:population":0,
    "gn:timezone":"America/Bogota",
    "iso:country":"CO",
    "wof:name":"La Telarana",
    "wof:placetype":"locality"
},
  "geometry": {"coordinates":[-75.50721999999998,4.93722],"type":"Point"}
}