{
  "type": "Feature",
  "properties": {
    "gn:admin1_code":"28",
    "gn:admin2_code":"73461.0",
    "gn:asciiname":"Granate",
    "gn:cc2":"CO",
    "gn:country_code":"CO",
    "gn:dem":3409,
    "gn:feature_class":"P",
    "gn:feature_code":"PPL",
    "gn:name":"Granate",
    "gn:population":0,
    "gn:timezone":"America/Bogota",
    "iso:country":"CO",
    "name:und_x_variant":[
        "Granates",
        "Granate"
    ],
    "wof:name":"Granate",
    "wof:placetype":"locality"
},
  "geometry": {"coordinates":[-75.23333000000002,4.85],"type":"Point"}
}