{
  "type": "Feature",
  "properties": {
    "gn:admin1_code":"35.0",
    "gn:admin2_code":"13655.0",
    "gn:asciiname":"Tenche",
    "gn:country_code":"CO",
    "gn:dem":25,
    "gn:feature_class":"P",
    "gn:feature_code":"PPL",
    "gn:name":"Tenche",
    "gn:population":0,
    "gn:timezone":"America/Bogota",
    "iso:country":"CO",
    "name:und_x_variant":[
        "Corregimiento Tenche",
        "Teche",
        "Teneche",
        "Tenche"
    ],
    "wof:name":"Tenche",
    "wof:placetype":"locality"
},
  "geometry": {"coordinates":[-74.64386,8.26222],"type":"Point"}
}