{
  "type": "Feature",
  "properties": {
    "gn:admin1_code":"2.0",
    "gn:admin2_code":"5306.0",
    "gn:asciiname":"El Filo",
    "gn:country_code":"CO",
    "gn:dem":1957,
    "gn:feature_class":"P",
    "gn:feature_code":"PPL",
    "gn:name":"El Filo",
    "gn:population":0,
    "gn:timezone":"America/Bogota",
    "iso:country":"CO",
    "wof:name":"El Filo",
    "wof:placetype":"locality"
},
  "geometry": {"coordinates":[-75.94333,6.66389],"type":"Point"}
}