{
  "type": "Feature",
  "properties": {
    "gn:admin1_code":"37",
    "gn:asciiname":"La Armenia",
    "gn:country_code":"CO",
    "gn:dem":1325,
    "gn:feature_class":"P",
    "gn:feature_code":"PPL",
    "gn:name":"La Armenia",
    "gn:population":0,
    "gn:timezone":"America/Bogota",
    "iso:country":"CO",
    "wof:name":"La Armenia",
    "wof:placetype":"locality"
},
  "geometry": {"coordinates":[-75.75667,4.97583],"type":"Point"}
}