{
  "type": "Feature",
  "properties": {
    "gn:admin1_code":"2",
    "gn:admin2_code":"5585.0",
    "gn:asciiname":"Puerto Nare",
    "gn:country_code":"CO",
    "gn:dem":129,
    "gn:feature_class":"P",
    "gn:feature_code":"PPL",
    "gn:name":"Puerto Nare",
    "gn:population":0,
    "gn:timezone":"America/Bogota",
    "iso:country":"CO",
    "name:eng_x_preferred":[
        "Puerto Nare"
    ],
    "name:fra_x_preferred":[
        "Puerto Nare"
    ],
    "name:und_x_variant":[
        "La Magdalena",
        "Nare",
        "Puerto Nare"
    ],
    "name:zho_x_preferred":[
        "\u7d0d\u96f7\u6e2f"
    ],
    "wof:name":"Puerto Nare",
    "wof:placetype":"locality"
},
  "geometry": {"coordinates":[-74.583,6.18643],"type":"Point"}
}