{
  "type": "Feature",
  "properties": {
    "gn:admin1_code":"21",
    "gn:admin2_code":"54125.0",
    "gn:asciiname":"Escalones",
    "gn:country_code":"CO",
    "gn:dem":2119,
    "gn:feature_class":"P",
    "gn:feature_code":"PPL",
    "gn:name":"Escalones",
    "gn:population":0,
    "gn:timezone":"America/Bogota",
    "iso:country":"CO",
    "wof:name":"Escalones",
    "wof:placetype":"locality"
},
  "geometry": {"coordinates":[-72.63333,7.25],"type":"Point"}
}