{
  "type": "Feature",
  "properties": {
    "gn:admin1_code":"36.0",
    "gn:admin2_code":"15790.0",
    "gn:asciiname":"Playon",
    "gn:country_code":"CO",
    "gn:dem":3083,
    "gn:feature_class":"P",
    "gn:feature_code":"PPL",
    "gn:name":"Play\u00f3n",
    "gn:population":0,
    "gn:timezone":"America/Bogota",
    "iso:country":"CO",
    "wof:name":"Playon",
    "wof:placetype":"locality"
},
  "geometry": {"coordinates":[-72.75060999999999,5.94003],"type":"Point"}
}