{
  "type": "Feature",
  "properties": {
    "gn:admin1_code":"26",
    "gn:admin2_code":"68020.0",
    "gn:asciiname":"Almorzadero",
    "gn:country_code":"CO",
    "gn:dem":2706,
    "gn:feature_class":"P",
    "gn:feature_code":"PPL",
    "gn:name":"Almorzadero",
    "gn:population":0,
    "gn:timezone":"America/Bogota",
    "iso:country":"CO",
    "wof:name":"Almorzadero",
    "wof:placetype":"locality"
},
  "geometry": {"coordinates":[-73.85139000000002,5.76389],"type":"Point"}
}