{
  "type": "Feature",
  "properties": {
    "gn:admin1_code":"26",
    "gn:admin2_code":"68176.0",
    "gn:asciiname":"Cueva Colorada",
    "gn:country_code":"CO",
    "gn:dem":2130,
    "gn:feature_class":"P",
    "gn:feature_code":"PPL",
    "gn:name":"Cueva Colorada",
    "gn:population":0,
    "gn:timezone":"America/Bogota",
    "iso:country":"CO",
    "wof:name":"Cueva Colorada",
    "wof:placetype":"locality"
},
  "geometry": {"coordinates":[-73.43583000000002,6.38618],"type":"Point"}
}