{
  "type": "Feature",
  "properties": {
    "gn:admin1_code":"2.0",
    "gn:admin2_code":"5664.0",
    "gn:asciiname":"El Telar",
    "gn:country_code":"CO",
    "gn:dem":2478,
    "gn:feature_class":"P",
    "gn:feature_code":"PPL",
    "gn:name":"El Telar",
    "gn:population":0,
    "gn:timezone":"America/Bogota",
    "iso:country":"CO",
    "wof:name":"El Telar",
    "wof:placetype":"locality"
},
  "geometry": {"coordinates":[-75.58972,6.50417],"type":"Point"}
}