{
  "type": "Feature",
  "properties": {
    "gn:admin1_code":"9.0",
    "gn:admin2_code":"19137.0",
    "gn:asciiname":"Guadualito",
    "gn:country_code":"CO",
    "gn:dem":1648,
    "gn:feature_class":"P",
    "gn:feature_code":"PPL",
    "gn:name":"Guadualito",
    "gn:population":0,
    "gn:timezone":"America/Bogota",
    "iso:country":"CO",
    "wof:name":"Guadualito",
    "wof:placetype":"locality"
},
  "geometry": {"coordinates":[-76.52311999999998,2.78033],"type":"Point"}
}