{
  "type": "Feature",
  "properties": {
    "gn:admin1_code":"9",
    "gn:admin2_code":"19455.0",
    "gn:asciiname":"El Potrerito",
    "gn:country_code":"CO",
    "gn:dem":1342,
    "gn:feature_class":"P",
    "gn:feature_code":"PPL",
    "gn:name":"El Potrerito",
    "gn:population":0,
    "gn:timezone":"America/Bogota",
    "iso:country":"CO",
    "name:und_x_variant":[
        "Potrerito",
        "El Potrerito"
    ],
    "wof:name":"El Potrerito",
    "wof:placetype":"locality"
},
  "geometry": {"coordinates":[-76.21195999999998,3.19687],"type":"Point"}
}