{
  "type": "Feature",
  "properties": {
    "gn:admin1_code":"20",
    "gn:admin2_code":"52418.0",
    "gn:asciiname":"Sidon",
    "gn:country_code":"CO",
    "gn:dem":779,
    "gn:feature_class":"P",
    "gn:feature_code":"PPL",
    "gn:name":"Sid\u00f3n",
    "gn:population":0,
    "gn:timezone":"America/Bogota",
    "iso:country":"CO",
    "wof:name":"Sidon",
    "wof:placetype":"locality"
},
  "geometry": {"coordinates":[-77.49333,1.5996],"type":"Point"}
}