{
  "type": "Feature",
  "properties": {
    "gn:admin1_code":"27",
    "gn:admin2_code":"70713.0",
    "gn:asciiname":"Boca Cerrada",
    "gn:country_code":"CO",
    "gn:dem":3,
    "gn:feature_class":"P",
    "gn:feature_code":"PPL",
    "gn:name":"Boca Cerrada",
    "gn:population":0,
    "gn:timezone":"America/Bogota",
    "iso:country":"CO",
    "wof:name":"Boca Cerrada",
    "wof:placetype":"locality"
},
  "geometry": {"coordinates":[-75.57066999999998,10.05924],"type":"Point"}
}