{
  "type": "Feature",
  "properties": {
    "gn:admin1_code":"20",
    "gn:admin2_code":"52207.0",
    "gn:asciiname":"Alto Cariaco",
    "gn:country_code":"CO",
    "gn:dem":1830,
    "gn:feature_class":"P",
    "gn:feature_code":"PPL",
    "gn:name":"Alto Cariaco",
    "gn:population":0,
    "gn:timezone":"America/Bogota",
    "iso:country":"CO",
    "name:und_x_variant":[
        "San Miguel de Cariaco",
        "Cariaco",
        "Bol\u00edvar",
        "Alto Cariaco"
    ],
    "wof:name":"Alto Cariaco",
    "wof:placetype":"locality"
},
  "geometry": {"coordinates":[-77.45350000000001,1.172],"type":"Point"}
}