{
  "type": "Feature",
  "properties": {
    "gn:admin1_code":"4.0",
    "gn:admin2_code":"8675.0",
    "gn:asciiname":"Rabon",
    "gn:cc2":"CO",
    "gn:country_code":"CO",
    "gn:dem":7,
    "gn:feature_class":"P",
    "gn:feature_code":"PPL",
    "gn:name":"Rab\u00f3n",
    "gn:population":0,
    "gn:timezone":"America/Bogota",
    "iso:country":"CO",
    "name:und_x_variant":[
        "Finca Rab\u00f3n",
        "Rab\u00f3n"
    ],
    "wof:name":"Rabon",
    "wof:placetype":"locality"
},
  "geometry": {"coordinates":[-74.96666999999999,10.36667],"type":"Point"}
}