{
  "type": "Feature",
  "properties": {
    "gn:admin1_code":"33.0",
    "gn:admin2_code":"25599.0",
    "gn:asciiname":"Bejucal",
    "gn:country_code":"CO",
    "gn:dem":574,
    "gn:feature_class":"P",
    "gn:feature_code":"PPL",
    "gn:name":"Bejucal",
    "gn:population":0,
    "gn:timezone":"America/Bogota",
    "iso:country":"CO",
    "name:spa_x_preferred":[
        "Bejucal"
    ],
    "wof:name":"Bejucal",
    "wof:placetype":"locality"
},
  "geometry": {"coordinates":[-74.56683000000002,4.45367],"type":"Point"}
}