{
  "type": "Feature",
  "properties": {
    "gn:admin1_code":"10",
    "gn:admin2_code":"20045.0",
    "gn:asciiname":"Cartagena",
    "gn:country_code":"CO",
    "gn:dem":122,
    "gn:feature_class":"P",
    "gn:feature_code":"PPL",
    "gn:name":"Cartagena",
    "gn:population":0,
    "gn:timezone":"America/Bogota",
    "iso:country":"CO",
    "wof:name":"Cartagena",
    "wof:placetype":"locality"
},
  "geometry": {"coordinates":[-73.26161999999999,9.68611],"type":"Point"}
}