{
  "type": "Feature",
  "properties": {
    "gn:admin1_code":"3.0",
    "gn:admin2_code":"81794.0",
    "gn:asciiname":"Caserio Pueblo Sucio",
    "gn:country_code":"CO",
    "gn:dem":185,
    "gn:feature_class":"P",
    "gn:feature_code":"PPL",
    "gn:name":"Caser\u00edo Pueblo Sucio",
    "gn:population":0,
    "gn:timezone":"America/Bogota",
    "iso:country":"CO",
    "wof:name":"Caserio Pueblo Sucio",
    "wof:placetype":"locality"
},
  "geometry": {"coordinates":[-71.51889,6.61833],"type":"Point"}
}