{
  "type": "Feature",
  "properties": {
    "gn:admin1_code":"9",
    "gn:admin2_code":"19022.0",
    "gn:asciiname":"Placeta",
    "gn:country_code":"CO",
    "gn:dem":2468,
    "gn:feature_class":"P",
    "gn:feature_code":"PPL",
    "gn:name":"Placeta",
    "gn:population":0,
    "gn:timezone":"America/Bogota",
    "iso:country":"CO",
    "wof:name":"Placeta",
    "wof:placetype":"locality"
},
  "geometry": {"coordinates":[-76.80193,1.90528],"type":"Point"}
}