{
  "type": "Feature",
  "properties": {
    "gn:admin1_code":"32",
    "gn:admin2_code":"85410.0",
    "gn:asciiname":"Cano Seco",
    "gn:country_code":"CO",
    "gn:dem":162,
    "gn:feature_class":"P",
    "gn:feature_code":"PPL",
    "gn:name":"Ca\u00f1o Seco",
    "gn:population":0,
    "gn:timezone":"America/Bogota",
    "iso:country":"CO",
    "wof:name":"Cano Seco",
    "wof:placetype":"locality"
},
  "geometry": {"coordinates":[-72.40838000000002,4.40336],"type":"Point"}
}