{
  "type": "Feature",
  "properties": {
    "gn:admin1_code":"4",
    "gn:admin2_code":"8832.0",
    "gn:asciiname":"Las Perdices",
    "gn:cc2":"CO",
    "gn:country_code":"CO",
    "gn:dem":93,
    "gn:feature_class":"P",
    "gn:feature_code":"PPL",
    "gn:name":"Las Perdices",
    "gn:population":0,
    "gn:timezone":"America/Bogota",
    "iso:country":"CO",
    "name:und_x_variant":[
        "Perdices",
        "Las Perdices"
    ],
    "wof:name":"Las Perdices",
    "wof:placetype":"locality"
},
  "geometry": {"coordinates":[-74.95,10.91667],"type":"Point"}
}