{
  "type": "Feature",
  "properties": {
    "gn:admin1_code":"12",
    "gn:admin2_code":"23555.0",
    "gn:asciiname":"Los Mosquitos",
    "gn:country_code":"CO",
    "gn:dem":57,
    "gn:feature_class":"P",
    "gn:feature_code":"PPL",
    "gn:name":"Los Mosquitos",
    "gn:population":0,
    "gn:timezone":"America/Bogota",
    "iso:country":"CO",
    "name:und_x_variant":[
        "Hacienda Los Mosquitos",
        "Los Mosquitos"
    ],
    "wof:name":"Los Mosquitos",
    "wof:placetype":"locality"
},
  "geometry": {"coordinates":[-75.52381,8.32521],"type":"Point"}
}