{
  "type": "Feature",
  "properties": {
    "iso:country":"CO",
    "name:ast_x_preferred":[
        "Vian\u00ed"
    ],
    "name:avk_x_preferred":[
        "Vian\u00ed"
    ],
    "name:ceb_x_preferred":[
        "Vian\u00ed"
    ],
    "name:eng_x_preferred":[
        "Vian\u00ed"
    ],
    "name:fas_x_preferred":[
        "\u0648\u06cc\u0627\u0646\u06cc"
    ],
    "name:fra_x_preferred":[
        "Vian\u00ed"
    ],
    "name:gle_x_preferred":[
        "Vian\u00ed"
    ],
    "name:glg_x_preferred":[
        "Vian\u00ed"
    ],
    "name:ita_x_preferred":[
        "Vian\u00ed"
    ],
    "name:kat_x_preferred":[
        "\u10d5\u10d8\u10d0\u10dc\u10d8"
    ],
    "name:msa_x_preferred":[
        "Vian\u00ed"
    ],
    "name:nan_x_preferred":[
        "Vian\u00ed"
    ],
    "name:nld_x_preferred":[
        "Vian\u00ed"
    ],
    "name:pol_x_preferred":[
        "Vian\u00ed"
    ],
    "name:por_x_preferred":[
        "Vian\u00ed"
    ],
    "name:sco_x_preferred":[
        "Vian\u00ed"
    ],
    "name:spa_x_preferred":[
        "Vian\u00ed"
    ],
    "name:swe_x_preferred":[
        "Vian\u00ed"
    ],
    "name:tgl_x_preferred":[
        "Viani"
    ],
    "name:vie_x_preferred":[
        "Vian\u00ed"
    ],
    "name:war_x_preferred":[
        "Vian\u00ed"
    ],
    "name:zho_x_preferred":[
        "\u6bd4\u4e9e\u5c3c"
    ],
    "qs:gn_country":"CO",
    "qs:gn_fcode":"PPL",
    "qs:gn_pop":1586,
    "qs:name":"Vian\u00ed",
    "qs:name_adm0":"Colombia",
    "qs:name_adm1":"Cundinamarca",
    "qs:photos":0,
    "qs:photos_1k":0,
    "qs:photos_9k":0,
    "qs:photos_9r":0,
    "qs:photos_all":0,
    "qs:photos_sr":0,
    "qs:placetype":"Town",
    "qs:pop_sr":"3",
    "qs:woe_adm0":23424787,
    "wd:wordcount":22,
    "wof:name":"Vian\u00ed",
    "wof:placetype":"locality",
    "wof:population":1586
},
  "geometry": {"coordinates":[-74.56244,4.87384],"type":"Point"}
}