{
  "type": "Feature",
  "properties": {
    "gn:admin1_code":"36",
    "gn:admin2_code":"15507.0",
    "gn:asciiname":"Mayorca",
    "gn:country_code":"CO",
    "gn:dem":738,
    "gn:feature_class":"P",
    "gn:feature_code":"PPL",
    "gn:name":"Mayorca",
    "gn:population":0,
    "gn:timezone":"America/Bogota",
    "iso:country":"CO",
    "wof:name":"Mayorca",
    "wof:placetype":"locality"
},
  "geometry": {"coordinates":[-74.21127,5.81552],"type":"Point"}
}