{
  "type": "Feature",
  "properties": {
    "iso:country":"CO",
    "name:ast_x_preferred":[
        "Chinchin\u00e1"
    ],
    "name:ceb_x_preferred":[
        "Chinchin\u00e1"
    ],
    "name:deu_x_preferred":[
        "Chinchin\u00e1"
    ],
    "name:eng_x_preferred":[
        "Chinchin\u00e1"
    ],
    "name:fas_x_preferred":[
        "\u0686\u06cc\u0646\u0686\u06cc\u0646\u0627"
    ],
    "name:fra_x_preferred":[
        "Chinchin\u00e1"
    ],
    "name:ita_x_preferred":[
        "Chinchin\u00e1"
    ],
    "name:kat_x_preferred":[
        "\u10e9\u10d8\u10dc\u10e9\u10d8\u10dc\u10d0"
    ],
    "name:msa_x_preferred":[
        "Chinchin\u00e1"
    ],
    "name:nan_x_preferred":[
        "Chinchin\u00e1"
    ],
    "name:nld_x_preferred":[
        "Chinchin\u00e1"
    ],
    "name:rus_x_preferred":[
        "\u0427\u0438\u043d\u0447\u0438\u043d\u044b"
    ],
    "name:spa_x_preferred":[
        "Chinchin\u00e1"
    ],
    "name:swe_x_preferred":[
        "Chinchin\u00e1"
    ],
    "name:tgl_x_preferred":[
        "Chinchin\u00e1"
    ],
    "name:ukr_x_preferred":[
        "\u0427\u0456\u043d\u0447\u0456\u043d\u0430"
    ],
    "name:vie_x_preferred":[
        "Chinchin\u00e1"
    ],
    "name:war_x_preferred":[
        "Chinchin\u00e1"
    ],
    "name:zho_x_preferred":[
        "\u91d1\u96de\u7d0d"
    ],
    "qs:gn_country":"CO",
    "qs:gn_fcode":"PPL",
    "qs:gn_pop":68512,
    "qs:name":"Chinchin\u00e1",
    "qs:name_adm0":"Colombia",
    "qs:name_adm1":"Caldas",
    "qs:photos":271,
    "qs:photos_1k":55,
    "qs:photos_9k":1,
    "qs:photos_9r":4,
    "qs:photos_all":271,
    "qs:photos_sr":5,
    "qs:placetype":"Town",
    "qs:pop_sr":"8",
    "qs:woe_adm0":23424787,
    "wof:name":"Chinchin\u00e1",
    "wof:placetype":"locality",
    "wof:population":68512
},
  "geometry": {"coordinates":[-75.60361,4.9825],"type":"Point"}
}