{
  "type": "Feature",
  "properties": {
    "gn:admin1_code":"2.0",
    "gn:admin2_code":"5001.0",
    "gn:asciiname":"Miraflores",
    "gn:country_code":"CO",
    "gn:dem":2500,
    "gn:feature_class":"P",
    "gn:feature_code":"PPL",
    "gn:name":"Miraflores",
    "gn:population":0,
    "gn:timezone":"America/Bogota",
    "iso:country":"CO",
    "name:spa_x_preferred":[
        "Miraflores"
    ],
    "wof:name":"Miraflores",
    "wof:placetype":"locality"
},
  "geometry": {"coordinates":[-75.51206999999999,6.28017],"type":"Point"}
}