{
  "type": "Feature",
  "properties": {
    "gn:admin1_code":"20",
    "gn:admin2_code":"52473.0",
    "gn:asciiname":"Cocalitos de Payanes",
    "gn:cc2":"CO",
    "gn:country_code":"CO",
    "gn:dem":2,
    "gn:feature_class":"P",
    "gn:feature_code":"PPL",
    "gn:name":"Cocalitos de Payanes",
    "gn:population":0,
    "gn:timezone":"America/Bogota",
    "iso:country":"CO",
    "name:und_x_variant":[
        "Cocalito de Payanes",
        "Cocalito",
        "Cocal",
        "Cocalitos de Payanes"
    ],
    "wof:name":"Cocalitos de Payanes",
    "wof:placetype":"locality"
},
  "geometry": {"coordinates":[-78.40000000000001,2.58333],"type":"Point"}
}