{
  "type": "Feature",
  "properties": {
    "gn:admin1_code":"28.0",
    "gn:admin2_code":"73168.0",
    "gn:asciiname":"Jamaica",
    "gn:country_code":"CO",
    "gn:dem":1581,
    "gn:feature_class":"P",
    "gn:feature_code":"PPL",
    "gn:name":"Jamaica",
    "gn:population":0,
    "gn:timezone":"America/Bogota",
    "iso:country":"CO",
    "wof:name":"Jamaica",
    "wof:placetype":"locality"
},
  "geometry": {"coordinates":[-75.62833000000001,3.67139],"type":"Point"}
}