{
  "type": "Feature",
  "properties": {
    "gn:admin1_code":"2",
    "gn:admin2_code":"5368.0",
    "gn:asciiname":"La Merced",
    "gn:country_code":"CO",
    "gn:dem":2308,
    "gn:feature_class":"P",
    "gn:feature_code":"PPL",
    "gn:name":"La Merced",
    "gn:population":0,
    "gn:timezone":"America/Bogota",
    "iso:country":"CO",
    "name:ceb_x_preferred":[
        "La Merced"
    ],
    "name:deu_x_preferred":[
        "La Merced"
    ],
    "name:fra_x_preferred":[
        "La Merced"
    ],
    "name:ita_x_preferred":[
        "La Merced"
    ],
    "name:nld_x_preferred":[
        "La Merced"
    ],
    "name:pol_x_preferred":[
        "La Merced"
    ],
    "name:por_x_preferred":[
        "La Merced"
    ],
    "name:spa_x_preferred":[
        "La Merced"
    ],
    "name:swe_x_preferred":[
        "La Merced"
    ],
    "name:vie_x_preferred":[
        "La Merced"
    ],
    "wof:name":"La Merced",
    "wof:placetype":"locality"
},
  "geometry": {"coordinates":[-75.77444,5.74222],"type":"Point"}
}