{
  "type": "Feature",
  "properties": {
    "gn:admin1_code":"20",
    "gn:admin2_code":"52621.0",
    "gn:asciiname":"Guabal",
    "gn:country_code":"CO",
    "gn:dem":28,
    "gn:feature_class":"P",
    "gn:feature_code":"PPL",
    "gn:name":"Guabal",
    "gn:population":0,
    "gn:timezone":"America/Bogota",
    "iso:country":"CO",
    "wof:name":"Guabal",
    "wof:placetype":"locality"
},
  "geometry": {"coordinates":[-78.26314000000001,1.76501],"type":"Point"}
}