{
  "type": "Feature",
  "properties": {
    "gn:admin1_code":"28.0",
    "gn:admin2_code":"73055.0",
    "gn:asciiname":"La Lorena",
    "gn:country_code":"CO",
    "gn:dem":340,
    "gn:feature_class":"P",
    "gn:feature_code":"PPL",
    "gn:name":"La Lorena",
    "gn:population":0,
    "gn:timezone":"America/Bogota",
    "iso:country":"CO",
    "name:spa_x_preferred":[
        "La Lorena"
    ],
    "wof:name":"La Lorena",
    "wof:placetype":"locality"
},
  "geometry": {"coordinates":[-74.88508,5.11453],"type":"Point"}
}