{
  "type": "Feature",
  "properties": {
    "gn:admin1_code":"2",
    "gn:admin2_code":"5361.0",
    "gn:asciiname":"Tinajas",
    "gn:country_code":"CO",
    "gn:dem":1313,
    "gn:feature_class":"P",
    "gn:feature_code":"PPL",
    "gn:name":"Tinajas",
    "gn:population":0,
    "gn:timezone":"America/Bogota",
    "iso:country":"CO",
    "name:ceb_x_preferred":[
        "Tinajas"
    ],
    "name:spa_x_preferred":[
        "Tinajas"
    ],
    "name:swe_x_preferred":[
        "Tinajas"
    ],
    "wof:name":"Tinajas",
    "wof:placetype":"locality"
},
  "geometry": {"coordinates":[-75.61140999999998,7.23547],"type":"Point"}
}