{
  "type": "Feature",
  "properties": {
    "gn:admin1_code":"8.0",
    "gn:admin2_code":"18592.0",
    "gn:asciiname":"Corregimiento de Aguililla",
    "gn:country_code":"CO",
    "gn:dem":987,
    "gn:feature_class":"P",
    "gn:feature_code":"PPL",
    "gn:name":"Corregimiento de Aguililla",
    "gn:population":0,
    "gn:timezone":"America/Bogota",
    "iso:country":"CO",
    "wof:name":"Corregimiento de Aguililla",
    "wof:placetype":"locality"
},
  "geometry": {"coordinates":[-75.05767,2.02723],"type":"Point"}
}