{
  "type": "Feature",
  "properties": {
    "gn:admin1_code":"36.0",
    "gn:admin2_code":"15686.0",
    "gn:asciiname":"La Chapa",
    "gn:country_code":"CO",
    "gn:dem":1656,
    "gn:feature_class":"P",
    "gn:feature_code":"PPL",
    "gn:name":"La Chapa",
    "gn:population":0,
    "gn:timezone":"America/Bogota",
    "iso:country":"CO",
    "wof:name":"La Chapa",
    "wof:placetype":"locality"
},
  "geometry": {"coordinates":[-73.48862,6.03907],"type":"Point"}
}