{
  "type": "Feature",
  "properties": {
    "gn:admin1_code":"38.0",
    "gn:admin2_code":"47551.0",
    "gn:asciiname":"Toledo",
    "gn:country_code":"CO",
    "gn:dem":47,
    "gn:feature_class":"P",
    "gn:feature_code":"PPL",
    "gn:name":"Toledo",
    "gn:population":0,
    "gn:timezone":"America/Bogota",
    "iso:country":"CO",
    "wof:name":"Toledo",
    "wof:placetype":"locality"
},
  "geometry": {"coordinates":[-74.51335999999998,10.33306],"type":"Point"}
}