{
  "type": "Feature",
  "properties": {
    "gn:admin1_code":"10.0",
    "gn:admin2_code":"20060.0",
    "gn:asciiname":"Paquesepa",
    "gn:country_code":"CO",
    "gn:dem":66,
    "gn:feature_class":"P",
    "gn:feature_code":"PPL",
    "gn:name":"Paquesepa",
    "gn:population":0,
    "gn:timezone":"America/Bogota",
    "iso:country":"CO",
    "wof:name":"Paquesepa",
    "wof:placetype":"locality"
},
  "geometry": {"coordinates":[-73.94880000000001,9.98871],"type":"Point"}
}