{
  "type": "Feature",
  "properties": {
    "gn:admin1_code":"26.0",
    "gn:admin2_code":"68575.0",
    "gn:asciiname":"Puente Sogamoso",
    "gn:country_code":"CO",
    "gn:dem":86,
    "gn:feature_class":"P",
    "gn:feature_code":"PPL",
    "gn:name":"Puente Sogamoso",
    "gn:population":0,
    "gn:timezone":"America/Bogota",
    "iso:country":"CO",
    "name:und_x_variant":[
        "Guayabo",
        "Puerto Sogamoso",
        "Puente Sogamoso"
    ],
    "wof:name":"Puente Sogamoso",
    "wof:placetype":"locality"
},
  "geometry": {"coordinates":[-73.78465,7.24597],"type":"Point"}
}