{
  "type": "Feature",
  "properties": {
    "gn:admin1_code":"10.0",
    "gn:admin2_code":"20250.0",
    "gn:asciiname":"La Esperanza",
    "gn:country_code":"CO",
    "gn:dem":40,
    "gn:feature_class":"P",
    "gn:feature_code":"PPL",
    "gn:name":"La Esperanza",
    "gn:population":0,
    "gn:timezone":"America/Bogota",
    "iso:country":"CO",
    "wof:name":"La Esperanza",
    "wof:placetype":"locality"
},
  "geometry": {"coordinates":[-73.73170999999998,9.68682],"type":"Point"}
}