{
  "type": "Feature",
  "properties": {
    "gn:admin1_code":"26.0",
    "gn:admin2_code":"68081.0",
    "gn:asciiname":"El Carino",
    "gn:country_code":"CO",
    "gn:dem":117,
    "gn:feature_class":"P",
    "gn:feature_code":"PPL",
    "gn:name":"El Cari\u00f1o",
    "gn:population":0,
    "gn:timezone":"America/Bogota",
    "iso:country":"CO",
    "wof:name":"El Carino",
    "wof:placetype":"locality"
},
  "geometry": {"coordinates":[-73.73416999999998,7.20056],"type":"Point"}
}