{
  "type": "Feature",
  "properties": {
    "gn:admin1_code":"03",
    "gn:asciiname":"Las Iguanas",
    "gn:country_code":"CO",
    "gn:dem":122,
    "gn:feature_class":"P",
    "gn:feature_code":"PPL",
    "gn:name":"Las Iguanas",
    "gn:population":0,
    "gn:timezone":"America/Bogota",
    "iso:country":"CO",
    "name:spa_x_preferred":[
        "Las Iguanas"
    ],
    "wof:name":"Las Iguanas",
    "wof:placetype":"locality"
},
  "geometry": {"coordinates":[-70.74339000000001,6.68274],"type":"Point"}
}