{
  "type": "Feature",
  "properties": {
    "gn:admin1_code":"12",
    "gn:admin2_code":"23570.0",
    "gn:asciiname":"El Paramo",
    "gn:country_code":"CO",
    "gn:dem":131,
    "gn:feature_class":"P",
    "gn:feature_code":"PPLL",
    "gn:name":"El P\u00e1ramo",
    "gn:population":0,
    "gn:timezone":"America/Bogota",
    "iso:country":"CO",
    "wof:name":"El Paramo",
    "wof:placetype":"locality"
},
  "geometry": {"coordinates":[-75.55128000000001,8.55346],"type":"Point"}
}