{
  "type": "Feature",
  "properties": {
    "gn:admin1_code":"38",
    "gn:admin2_code":"47692.0",
    "gn:asciiname":"Cali",
    "gn:country_code":"CO",
    "gn:dem":83,
    "gn:feature_class":"P",
    "gn:feature_code":"PPL",
    "gn:name":"Cali",
    "gn:population":0,
    "gn:timezone":"America/Bogota",
    "iso:country":"CO",
    "wof:name":"Cali",
    "wof:placetype":"locality"
},
  "geometry": {"coordinates":[-74.03028,9.40806],"type":"Point"}
}