{
  "type": "Feature",
  "properties": {
    "gn:admin1_code":"3",
    "gn:admin2_code":"81794.0",
    "gn:asciiname":"El Banco",
    "gn:country_code":"CO",
    "gn:dem":464,
    "gn:feature_class":"P",
    "gn:feature_code":"PPL",
    "gn:name":"El Banco",
    "gn:population":0,
    "gn:timezone":"America/Bogota",
    "iso:country":"CO",
    "name:und_x_variant":[
        "Banco",
        "El Bango",
        "El Banco"
    ],
    "wof:name":"El Banco",
    "wof:placetype":"locality"
},
  "geometry": {"coordinates":[-71.90183,6.28238],"type":"Point"}
}