{
  "type": "Feature",
  "properties": {
    "gn:admin1_code":"29",
    "gn:admin2_code":"76520.0",
    "gn:asciiname":"El Brillante",
    "gn:country_code":"CO",
    "gn:dem":3401,
    "gn:feature_class":"P",
    "gn:feature_code":"PPL",
    "gn:name":"El Brillante",
    "gn:population":0,
    "gn:timezone":"America/Bogota",
    "iso:country":"CO",
    "wof:name":"El Brillante",
    "wof:placetype":"locality"
},
  "geometry": {"coordinates":[-76.02306,3.52306],"type":"Point"}
}