{
  "type": "Feature",
  "properties": {
    "gn:admin1_code":"29",
    "gn:admin2_code":"76248.0",
    "gn:asciiname":"El Placer",
    "gn:country_code":"CO",
    "gn:dem":1022,
    "gn:feature_class":"P",
    "gn:feature_code":"PPL",
    "gn:name":"El Placer",
    "gn:population":0,
    "gn:timezone":"America/Bogota",
    "iso:country":"CO",
    "wof:name":"El Placer",
    "wof:placetype":"locality"
},
  "geometry": {"coordinates":[-76.26666999999998,3.6825],"type":"Point"}
}