{
  "type": "Feature",
  "properties": {
    "gn:admin1_code":"33.0",
    "gn:admin2_code":"25815.0",
    "gn:asciiname":"Zelandia",
    "gn:country_code":"CO",
    "gn:dem":431,
    "gn:feature_class":"P",
    "gn:feature_code":"PPL",
    "gn:name":"Zelandia",
    "gn:population":0,
    "gn:timezone":"America/Bogota",
    "iso:country":"CO",
    "name:und_x_variant":[
        "Celandia",
        "Zelandia",
        "El Pi\u00f1al"
    ],
    "wof:name":"Zelandia",
    "wof:placetype":"locality"
},
  "geometry": {"coordinates":[-74.58333,4.43333],"type":"Point"}
}