{
  "type": "Feature",
  "properties": {
    "gn:admin1_code":"32",
    "gn:admin2_code":"85139.0",
    "gn:asciiname":"Filadelfia",
    "gn:country_code":"CO",
    "gn:dem":172,
    "gn:feature_class":"P",
    "gn:feature_code":"PPL",
    "gn:name":"Filadelfia",
    "gn:population":0,
    "gn:timezone":"America/Bogota",
    "iso:country":"CO",
    "wof:name":"Filadelfia",
    "wof:placetype":"locality"
},
  "geometry": {"coordinates":[-72.28917,4.74],"type":"Point"}
}