{
  "type": "Feature",
  "properties": {
    "gn:admin1_code":"29",
    "gn:admin2_code":"76001.0",
    "gn:asciiname":"La Castilla",
    "gn:country_code":"CO",
    "gn:dem":1684,
    "gn:feature_class":"P",
    "gn:feature_code":"PPL",
    "gn:name":"La Castilla",
    "gn:population":0,
    "gn:timezone":"America/Bogota",
    "iso:country":"CO",
    "wof:name":"La Castilla",
    "wof:placetype":"locality"
},
  "geometry": {"coordinates":[-76.58479,3.49461],"type":"Point"}
}