{
  "type": "Feature",
  "properties": {
    "gn:admin1_code":"9",
    "gn:admin2_code":"19517.0",
    "gn:asciiname":"El Guamo",
    "gn:country_code":"CO",
    "gn:dem":1552,
    "gn:feature_class":"P",
    "gn:feature_code":"PPL",
    "gn:name":"El Guamo",
    "gn:population":0,
    "gn:timezone":"America/Bogota",
    "iso:country":"CO",
    "wof:name":"El Guamo",
    "wof:placetype":"locality"
},
  "geometry": {"coordinates":[-75.98379,2.70375],"type":"Point"}
}