{
  "type": "Feature",
  "properties": {
    "gn:admin1_code":"36.0",
    "gn:admin2_code":"15550.0",
    "gn:asciiname":"Tobaca",
    "gn:country_code":"CO",
    "gn:dem":1769,
    "gn:feature_class":"P",
    "gn:feature_code":"PPL",
    "gn:name":"Tobaca",
    "gn:population":0,
    "gn:timezone":"America/Bogota",
    "iso:country":"CO",
    "wof:name":"Tobaca",
    "wof:placetype":"locality"
},
  "geometry": {"coordinates":[-72.50715,5.7838],"type":"Point"}
}