{
  "type": "Feature",
  "properties": {
    "gn:admin1_code":"19.0",
    "gn:admin2_code":"50577.0",
    "gn:asciiname":"El Crucero",
    "gn:country_code":"CO",
    "gn:dem":266,
    "gn:feature_class":"P",
    "gn:feature_code":"PPL",
    "gn:name":"El Crucero",
    "gn:population":0,
    "gn:timezone":"America/Bogota",
    "iso:country":"CO",
    "wof:name":"El Crucero",
    "wof:placetype":"locality"
},
  "geometry": {"coordinates":[-72.9901,3.11992],"type":"Point"}
}