{
  "type": "Feature",
  "properties": {
    "gn:admin1_code":"8.0",
    "gn:admin2_code":"18756.0",
    "gn:asciiname":"Puerto Apolinar",
    "gn:country_code":"CO",
    "gn:dem":161,
    "gn:feature_class":"P",
    "gn:feature_code":"PPL",
    "gn:name":"Puerto Apolinar",
    "gn:population":0,
    "gn:timezone":"America/Bogota",
    "iso:country":"CO",
    "wof:name":"Puerto Apolinar",
    "wof:placetype":"locality"
},
  "geometry": {"coordinates":[-73.50133000000002,-0.52053],"type":"Point"}
}