{
  "type": "Feature",
  "properties": {
    "gn:admin1_code":"17",
    "gn:admin2_code":"44847.0",
    "gn:asciiname":"Jasainapu",
    "gn:country_code":"CO",
    "gn:dem":112,
    "gn:feature_class":"P",
    "gn:feature_code":"PPL",
    "gn:name":"Jas\u00e1inapu",
    "gn:population":0,
    "gn:timezone":"America/Bogota",
    "iso:country":"CO",
    "name:und_x_variant":[
        "Jas\u00e1inapu",
        "Jasanaipo"
    ],
    "wof:name":"Jasainapu",
    "wof:placetype":"locality"
},
  "geometry": {"coordinates":[-71.6349,12.06244],"type":"Point"}
}