{
  "type": "Feature",
  "properties": {
    "gn:country":"CO",
    "gn:fcode":"PPL",
    "gn:population":2214,
    "iso:country":"CO",
    "name:ast_x_preferred":[
        "Brice\u00f1o"
    ],
    "name:ceb_x_preferred":[
        "Brice\u00f1o"
    ],
    "name:eng_x_preferred":[
        "Brice\u00f1o"
    ],
    "name:fra_x_preferred":[
        "Brice\u00f1o"
    ],
    "name:ile_x_preferred":[
        "Brice\u00f1o"
    ],
    "name:ilo_x_preferred":[
        "Brice\u00f1o"
    ],
    "name:ita_x_preferred":[
        "Brice\u00f1o"
    ],
    "name:kat_x_preferred":[
        "\u10d1\u10e0\u10d8\u10e1\u10d4\u10dc\u10d8\u10dd"
    ],
    "name:msa_x_preferred":[
        "Brice\u00f1o"
    ],
    "name:nan_x_preferred":[
        "Brice\u00f1o"
    ],
    "name:nld_x_preferred":[
        "Brice\u00f1o"
    ],
    "name:por_x_preferred":[
        "Brice\u00f1o"
    ],
    "name:ron_x_preferred":[
        "Brice\u00f1o"
    ],
    "name:rus_x_preferred":[
        "\u0411\u0440\u0438\u0441\u0435\u043d\u044c\u043e"
    ],
    "name:spa_x_preferred":[
        "Brice\u00f1o"
    ],
    "name:swe_x_preferred":[
        "Brice\u00f1o"
    ],
    "name:tgl_x_preferred":[
        "Brice\u00f1o"
    ],
    "name:vie_x_preferred":[
        "Brice\u00f1o"
    ],
    "name:war_x_preferred":[
        "Brice\u00f1o"
    ],
    "name:zho_x_preferred":[
        "\u5e03\u91cc\u585e\u5c3c\u5967"
    ],
    "qs:name":"Brice\u00f1o",
    "qs:photos_9r":0,
    "qs:photos_sr":0,
    "qs:pop_sr":"4",
    "wd:wordcount":40,
    "wof:name":"Brice\u00f1o",
    "wof:placetype":"locality",
    "wof:population":2214
},
  "geometry": {"coordinates":[-75.55152,7.11096],"type":"Point"}
}