{
  "type": "Feature",
  "properties": {
    "gn:admin1_code":"9.0",
    "gn:admin2_code":"19821.0",
    "gn:asciiname":"La Llorona",
    "gn:country_code":"CO",
    "gn:dem":3173,
    "gn:feature_class":"P",
    "gn:feature_code":"PPL",
    "gn:name":"La Llorona",
    "gn:population":0,
    "gn:timezone":"America/Bogota",
    "iso:country":"CO",
    "name:ara_x_preferred":[
        "\u0644\u0627 \u064a\u0648\u0631\u0648\u0646\u0627"
    ],
    "name:bre_x_preferred":[
        "Llorona"
    ],
    "name:deu_x_preferred":[
        "Llorona"
    ],
    "name:fin_x_preferred":[
        "La Llorona"
    ],
    "name:fra_x_preferred":[
        "La Llorona"
    ],
    "name:gla_x_preferred":[
        "La Llorona"
    ],
    "name:heb_x_preferred":[
        "\u05dc\u05d4 \u05d9\u05d5\u05e8\u05d5\u05e0\u05d4"
    ],
    "name:hun_x_preferred":[
        "Llorona"
    ],
    "name:ita_x_preferred":[
        "Llorona"
    ],
    "name:lit_x_preferred":[
        "Verkianti moteris"
    ],
    "name:nah_x_preferred":[
        "Cihu\u0101chocani"
    ],
    "name:nld_x_preferred":[
        "Llorona"
    ],
    "name:por_x_preferred":[
        "A bela da meia-noite"
    ],
    "name:rus_x_preferred":[
        "\u041b\u0430 \u0419\u043e\u0440\u043e\u043d\u0430"
    ],
    "name:spa_x_preferred":[
        "La Llorona"
    ],
    "name:spa_x_variant":[
        "Llorona"
    ],
    "name:tur_x_preferred":[
        "La Llorona"
    ],
    "name:ukr_x_preferred":[
        "\u0419\u043e\u0440\u043e\u043d\u0430"
    ],
    "name:vie_x_preferred":[
        "La Llorona"
    ],
    "name:zho_x_preferred":[
        "\u54ed\u6ce3\u5973"
    ],
    "wof:name":"La Llorona",
    "wof:placetype":"locality"
},
  "geometry": {"coordinates":[-76.15026,2.97672],"type":"Point"}
}