{
  "type": "Feature",
  "properties": {
    "gn:admin1_code":"9.0",
    "gn:admin2_code":"19821.0",
    "gn:asciiname":"La Llorona",
    "gn:country_code":"CO",
    "gn:dem":3173,
    "gn:feature_class":"P",
    "gn:feature_code":"PPL",
    "gn:name":"La Llorona",
    "gn:population":0,
    "gn:timezone":"America/Bogota",
    "iso:country":"CO",
    "name:spa_x_preferred":[
        "La Llorona"
    ],
    "wof:name":"La Llorona",
    "wof:placetype":"locality"
},
  "geometry": {"coordinates":[-76.15026,2.97672],"type":"Point"}
}