{
  "type": "Feature",
  "properties": {
    "gn:admin1_code":"33",
    "gn:admin2_code":"25214.0",
    "gn:asciiname":"El Hoyo",
    "gn:country_code":"CO",
    "gn:dem":2709,
    "gn:feature_class":"P",
    "gn:feature_code":"PPL",
    "gn:name":"El Hoyo",
    "gn:population":0,
    "gn:timezone":"America/Bogota",
    "iso:country":"CO",
    "name:ita_x_preferred":[
        "El Hoyo"
    ],
    "name:spa_x_preferred":[
        "El Hoyo"
    ],
    "wof:name":"El Hoyo",
    "wof:placetype":"locality"
},
  "geometry": {"coordinates":[-74.09999999999999,4.83333],"type":"Point"}
}