{
  "type": "Feature",
  "properties": {
    "gn:admin1_code":"12.0",
    "gn:admin2_code":"23570.0",
    "gn:asciiname":"Versalles",
    "gn:country_code":"CO",
    "gn:dem":134,
    "gn:feature_class":"P",
    "gn:feature_code":"PPLL",
    "gn:name":"Versalles",
    "gn:population":0,
    "gn:timezone":"America/Bogota",
    "iso:country":"CO",
    "wof:name":"Versalles",
    "wof:placetype":"locality"
},
  "geometry": {"coordinates":[-75.52724000000001,8.5566],"type":"Point"}
}