{
  "type": "Feature",
  "properties": {
    "gn:admin1_code":"37",
    "gn:admin2_code":"17013.0",
    "gn:asciiname":"La Paz",
    "gn:country_code":"CO",
    "gn:dem":1190,
    "gn:feature_class":"P",
    "gn:feature_code":"PPL",
    "gn:name":"La Paz",
    "gn:population":0,
    "gn:timezone":"America/Bogota",
    "iso:country":"CO",
    "wof:name":"La Paz",
    "wof:placetype":"locality"
},
  "geometry": {"coordinates":[-75.53869,5.63508],"type":"Point"}
}