{
  "type": "Feature",
  "properties": {
    "gn:admin1_code":"21",
    "gn:admin2_code":"54398.0",
    "gn:asciiname":"Guanna",
    "gn:country_code":"CO",
    "gn:dem":1523,
    "gn:feature_class":"P",
    "gn:feature_code":"PPL",
    "gn:name":"Guanna",
    "gn:population":0,
    "gn:timezone":"America/Bogota",
    "iso:country":"CO",
    "wof:name":"Guanna",
    "wof:placetype":"locality"
},
  "geometry": {"coordinates":[-73.19221999999998,8.25833],"type":"Point"}
}