{
  "type": "Feature",
  "properties": {
    "gn:admin1_code":"28",
    "gn:admin2_code":"73168.0",
    "gn:asciiname":"Puente La Lejia",
    "gn:country_code":"CO",
    "gn:dem":2669,
    "gn:feature_class":"P",
    "gn:feature_code":"PPL",
    "gn:name":"Puente La Lej\u00eda",
    "gn:population":0,
    "gn:timezone":"America/Bogota",
    "iso:country":"CO",
    "wof:name":"Puente La Lejia",
    "wof:placetype":"locality"
},
  "geometry": {"coordinates":[-75.77249999999999,3.90167],"type":"Point"}
}