{
  "type": "Feature",
  "properties": {
    "gn:admin1_code":"19.0",
    "gn:admin2_code":"50573.0",
    "gn:asciiname":"Mata Azul",
    "gn:country_code":"CO",
    "gn:dem":245,
    "gn:feature_class":"P",
    "gn:feature_code":"PPLL",
    "gn:name":"Mata Azul",
    "gn:population":0,
    "gn:timezone":"America/Bogota",
    "iso:country":"CO",
    "name:spa_x_preferred":[
        "Mata Azul"
    ],
    "wof:name":"Mata Azul",
    "wof:placetype":"locality"
},
  "geometry": {"coordinates":[-73.06905,3.77116],"type":"Point"}
}