{
  "type": "Feature",
  "properties": {
    "gn:admin1_code":"12.0",
    "gn:admin2_code":"23574.0",
    "gn:asciiname":"Puya",
    "gn:country_code":"CO",
    "gn:dem":23,
    "gn:feature_class":"P",
    "gn:feature_code":"PPL",
    "gn:name":"Puya",
    "gn:population":0,
    "gn:timezone":"America/Bogota",
    "iso:country":"CO",
    "name:fra_x_preferred":[
        "Puya"
    ],
    "name:ita_x_preferred":[
        "Puya"
    ],
    "name:ron_x_preferred":[
        "Puya"
    ],
    "name:rus_x_preferred":[
        "\u041f\u0443\u0439\u044f"
    ],
    "name:spa_x_preferred":[
        "Puya"
    ],
    "name:vie_x_preferred":[
        "Puya"
    ],
    "wof:name":"Puya",
    "wof:placetype":"locality"
},
  "geometry": {"coordinates":[-76.25,8.91667],"type":"Point"}
}