{
  "type": "Feature",
  "properties": {
    "gn:admin1_code":"2.0",
    "gn:admin2_code":"5001.0",
    "gn:asciiname":"La Volcana",
    "gn:country_code":"CO",
    "gn:dem":1800,
    "gn:feature_class":"P",
    "gn:feature_code":"PPL",
    "gn:name":"La Volcana",
    "gn:population":0,
    "gn:timezone":"America/Bogota",
    "iso:country":"CO",
    "name:spa_x_preferred":[
        "La Volcana"
    ],
    "wof:name":"La Volcana",
    "wof:placetype":"locality"
},
  "geometry": {"coordinates":[-75.69096999999999,6.33693],"type":"Point"}
}