{
  "type": "Feature",
  "properties": {
    "gn:admin1_code":"35.0",
    "gn:admin2_code":"13647.0",
    "gn:asciiname":"Bollo de Yuca",
    "gn:country_code":"CO",
    "gn:dem":104,
    "gn:feature_class":"P",
    "gn:feature_code":"PPL",
    "gn:name":"Bollo de Yuca",
    "gn:population":0,
    "gn:timezone":"America/Bogota",
    "iso:country":"CO",
    "wof:name":"Bollo de Yuca",
    "wof:placetype":"locality"
},
  "geometry": {"coordinates":[-75.21160999999999,10.40965],"type":"Point"}
}