{
  "type": "Feature",
  "properties": {
    "gn:admin1_code":"35",
    "gn:admin2_code":"13810.0",
    "gn:asciiname":"Colorado",
    "gn:country_code":"CO",
    "gn:dem":23,
    "gn:feature_class":"P",
    "gn:feature_code":"PPL",
    "gn:name":"Colorado",
    "gn:population":0,
    "gn:timezone":"America/Bogota",
    "iso:country":"CO",
    "name:und_x_variant":[
        "Corregimiento Colorado",
        "Colorado"
    ],
    "wof:name":"Colorado",
    "wof:placetype":"locality"
},
  "geometry": {"coordinates":[-74.28279000000001,8.59947],"type":"Point"}
}