{
  "type": "Feature",
  "properties": {
    "gn:admin1_code":"4",
    "gn:admin2_code":"8758.0",
    "gn:asciiname":"Las Moras",
    "gn:country_code":"CO",
    "gn:dem":72,
    "gn:feature_class":"P",
    "gn:feature_code":"PPL",
    "gn:name":"Las Moras",
    "gn:population":0,
    "gn:timezone":"America/Bogota",
    "iso:country":"CO",
    "wof:name":"Las Moras",
    "wof:placetype":"locality"
},
  "geometry": {"coordinates":[-74.81667,10.91667],"type":"Point"}
}