{
  "type": "Feature",
  "properties": {
    "gn:admin1_code":"33",
    "gn:admin2_code":"25736.0",
    "gn:asciiname":"La Pesquera",
    "gn:country_code":"CO",
    "gn:dem":2565,
    "gn:feature_class":"P",
    "gn:feature_code":"PPL",
    "gn:name":"La Pesquera",
    "gn:population":0,
    "gn:timezone":"America/Bogota",
    "iso:country":"CO",
    "wof:name":"La Pesquera",
    "wof:placetype":"locality"
},
  "geometry": {"coordinates":[-73.84999999999999,5.03333],"type":"Point"}
}