{
  "type": "Feature",
  "properties": {
    "iso:country":"CO",
    "name:ceb_x_preferred":[
        "C\u00e1queza"
    ],
    "name:eng_x_preferred":[
        "C\u00e1queza"
    ],
    "name:fra_x_preferred":[
        "C\u00e1queza"
    ],
    "name:ita_x_preferred":[
        "C\u00e1queza"
    ],
    "name:kat_x_preferred":[
        "\u10d9\u10d0\u10d9\u10d4\u10e1\u10d0"
    ],
    "name:msa_x_preferred":[
        "C\u00e1queza"
    ],
    "name:msa_x_variant":[
        "Caqueza"
    ],
    "name:nan_x_preferred":[
        "C\u00e1queza"
    ],
    "name:nld_x_preferred":[
        "C\u00e1queza"
    ],
    "name:sco_x_preferred":[
        "C\u00e1queza"
    ],
    "name:spa_x_preferred":[
        "C\u00e1queza"
    ],
    "name:swe_x_preferred":[
        "C\u00e1queza"
    ],
    "name:tgl_x_preferred":[
        "C\u00e1queza"
    ],
    "name:vie_x_preferred":[
        "C\u00e1queza"
    ],
    "name:war_x_preferred":[
        "Caqueza"
    ],
    "name:zho_x_preferred":[
        "\u5361\u514b\u85a9"
    ],
    "qs:gn_country":"CO",
    "qs:gn_fcode":"PPL",
    "qs:gn_pop":7958,
    "qs:name":"C\u00e1queza",
    "qs:name_adm0":"Colombia",
    "qs:name_adm1":"Cundinamarca",
    "qs:photos":42,
    "qs:photos_1k":9,
    "qs:photos_9k":1,
    "qs:photos_9r":2,
    "qs:photos_all":42,
    "qs:photos_sr":2,
    "qs:placetype":"Town",
    "qs:pop_sr":"5",
    "qs:woe_adm0":23424787,
    "wof:name":"C\u00e1queza",
    "wof:placetype":"locality",
    "wof:population":7958
},
  "geometry": {"coordinates":[-73.94683000000001,4.40569],"type":"Point"}
}