{
  "type": "Feature",
  "properties": {
    "gn:admin1_code":"19",
    "gn:admin2_code":"50226.0",
    "gn:asciiname":"Pinalito",
    "gn:country_code":"CO",
    "gn:dem":229,
    "gn:feature_class":"P",
    "gn:feature_code":"PPL",
    "gn:name":"Pi\u00f1alito",
    "gn:population":0,
    "gn:timezone":"America/Bogota",
    "iso:country":"CO",
    "wof:name":"Pinalito",
    "wof:placetype":"locality"
},
  "geometry": {"coordinates":[-73.24852,4.20868],"type":"Point"}
}