{
  "type": "Feature",
  "properties": {
    "gn:admin1_code":"16.0",
    "gn:admin2_code":"41872.0",
    "gn:asciiname":"La Astilla",
    "gn:country_code":"CO",
    "gn:dem":515,
    "gn:feature_class":"P",
    "gn:feature_code":"PPL",
    "gn:name":"La Astilla",
    "gn:population":0,
    "gn:timezone":"America/Bogota",
    "iso:country":"CO",
    "name:spa_x_preferred":[
        "La Astilla"
    ],
    "wof:name":"La Astilla",
    "wof:placetype":"locality"
},
  "geometry": {"coordinates":[-75.10051,3.24871],"type":"Point"}
}