{
  "type": "Feature",
  "properties": {
    "gn:admin1_code":"16.0",
    "gn:admin2_code":"41306.0",
    "gn:asciiname":"Rodapaso",
    "gn:country_code":"CO",
    "gn:dem":625,
    "gn:feature_class":"P",
    "gn:feature_code":"PPL",
    "gn:name":"Rodapaso",
    "gn:population":0,
    "gn:timezone":"America/Bogota",
    "iso:country":"CO",
    "wof:name":"Rodapaso",
    "wof:placetype":"locality"
},
  "geometry": {"coordinates":[-75.57979,2.39537],"type":"Point"}
}