{
  "type": "Feature",
  "properties": {
    "gn:admin1_code":"32",
    "gn:admin2_code":"85410.0",
    "gn:asciiname":"Pinalito",
    "gn:country_code":"CO",
    "gn:dem":165,
    "gn:feature_class":"P",
    "gn:feature_code":"PPL",
    "gn:name":"Pi\u00f1alito",
    "gn:population":0,
    "gn:timezone":"America/Bogota",
    "iso:country":"CO",
    "wof:name":"Pinalito",
    "wof:placetype":"locality"
},
  "geometry": {"coordinates":[-72.65309999999999,4.42131],"type":"Point"}
}