{
  "type": "Feature",
  "properties": {
    "gn:admin1_code":"35",
    "gn:admin2_code":"13670.0",
    "gn:asciiname":"El Aceituno",
    "gn:country_code":"CO",
    "gn:dem":64,
    "gn:feature_class":"P",
    "gn:feature_code":"PPL",
    "gn:name":"El Aceituno",
    "gn:population":0,
    "gn:timezone":"America/Bogota",
    "iso:country":"CO",
    "wof:name":"El Aceituno",
    "wof:placetype":"locality"
},
  "geometry": {"coordinates":[-73.90000000000001,7.61667],"type":"Point"}
}