{
  "type": "Feature",
  "properties": {
    "gn:admin1_code":"1",
    "gn:admin2_code":"91530.0",
    "gn:asciiname":"Hayos",
    "gn:country_code":"CO",
    "gn:dem":165,
    "gn:feature_class":"P",
    "gn:feature_code":"PPL",
    "gn:name":"Hayos",
    "gn:population":0,
    "gn:timezone":"America/Bogota",
    "iso:country":"CO",
    "wof:name":"Hayos",
    "wof:placetype":"locality"
},
  "geometry": {"coordinates":[-73.59999999999999,-1.25],"type":"Point"}
}