{
  "type": "Feature",
  "properties": {
    "gn:admin1_code":"9",
    "gn:admin2_code":"19450.0",
    "gn:asciiname":"Tabloncito",
    "gn:country_code":"CO",
    "gn:dem":1228,
    "gn:feature_class":"P",
    "gn:feature_code":"PPL",
    "gn:name":"Tabloncito",
    "gn:population":0,
    "gn:timezone":"America/Bogota",
    "iso:country":"CO",
    "wof:name":"Tabloncito",
    "wof:placetype":"locality"
},
  "geometry": {"coordinates":[-77.16489,1.71077],"type":"Point"}
}