{
  "type": "Feature",
  "properties": {
    "gn:admin1_code":"36",
    "gn:admin2_code":"15763.0",
    "gn:asciiname":"El Alisal",
    "gn:country_code":"CO",
    "gn:dem":3027,
    "gn:feature_class":"P",
    "gn:feature_code":"PPL",
    "gn:name":"El Alisal",
    "gn:population":0,
    "gn:timezone":"America/Bogota",
    "iso:country":"CO",
    "name:und_x_variant":[
        "Hacienda El Alizal",
        "El Alisal"
    ],
    "wof:name":"El Alisal",
    "wof:placetype":"locality"
},
  "geometry": {"coordinates":[-73.32135,5.69669],"type":"Point"}
}