{
  "type": "Feature",
  "properties": {
    "gn:admin1_code":"33.0",
    "gn:admin2_code":"25290.0",
    "gn:asciiname":"Piamonte",
    "gn:country_code":"CO",
    "gn:dem":1669,
    "gn:feature_class":"P",
    "gn:feature_code":"PPL",
    "gn:name":"Piamonte",
    "gn:population":0,
    "gn:timezone":"America/Bogota",
    "iso:country":"CO",
    "wof:name":"Piamonte",
    "wof:placetype":"locality"
},
  "geometry": {"coordinates":[-74.36667,4.36667],"type":"Point"}
}