{
  "type": "Feature",
  "properties": {
    "gn:admin1_code":"33.0",
    "gn:admin2_code":"25290.0",
    "gn:asciiname":"Piamonte",
    "gn:country_code":"CO",
    "gn:dem":1669,
    "gn:feature_class":"P",
    "gn:feature_code":"PPL",
    "gn:name":"Piamonte",
    "gn:population":0,
    "gn:timezone":"America/Bogota",
    "iso:country":"CO",
    "name:ceb_x_preferred":[
        "Piamonte"
    ],
    "name:fra_x_preferred":[
        "Piamonte"
    ],
    "name:ita_x_preferred":[
        "Piamonte"
    ],
    "name:kat_x_preferred":[
        "\u10de\u10d8\u10d0\u10db\u10dd\u10dc\u10e2\u10d4"
    ],
    "name:msa_x_preferred":[
        "Piamonte"
    ],
    "name:nld_x_preferred":[
        "Piamonte"
    ],
    "name:sco_x_preferred":[
        "Piamonte"
    ],
    "name:spa_x_preferred":[
        "Piamonte"
    ],
    "name:swe_x_preferred":[
        "Piamonte"
    ],
    "name:tgl_x_preferred":[
        "Piamonte"
    ],
    "name:vie_x_preferred":[
        "Piamonte"
    ],
    "name:war_x_preferred":[
        "Piamonte"
    ],
    "name:zho_x_preferred":[
        "\u76ae\u4e9e\u8499\u7279"
    ],
    "wof:name":"Piamonte",
    "wof:placetype":"locality"
},
  "geometry": {"coordinates":[-74.36667,4.36667],"type":"Point"}
}