{
  "type": "Feature",
  "properties": {
    "gn:admin1_code":"19",
    "gn:admin2_code":"50573.0",
    "gn:asciiname":"Acapulco",
    "gn:country_code":"CO",
    "gn:dem":177,
    "gn:feature_class":"P",
    "gn:feature_code":"PPL",
    "gn:name":"Acapulco",
    "gn:population":0,
    "gn:timezone":"America/Bogota",
    "iso:country":"CO",
    "wof:name":"Acapulco",
    "wof:placetype":"locality"
},
  "geometry": {"coordinates":[-72.25338000000001,4.41031],"type":"Point"}
}