{
  "type": "Feature",
  "properties": {
    "gn:admin1_code":"36",
    "gn:admin2_code":"15480.0",
    "gn:asciiname":"Guajiro",
    "gn:country_code":"CO",
    "gn:dem":619,
    "gn:feature_class":"P",
    "gn:feature_code":"PPL",
    "gn:name":"Guajiro",
    "gn:population":0,
    "gn:timezone":"America/Bogota",
    "iso:country":"CO",
    "wof:name":"Guajiro",
    "wof:placetype":"locality"
},
  "geometry": {"coordinates":[-74.12721999999999,5.51528],"type":"Point"}
}