{
  "type": "Feature",
  "properties": {
    "gn:admin1_code":"9",
    "gn:admin2_code":"19256.0",
    "gn:asciiname":"La Cabana",
    "gn:country_code":"CO",
    "gn:dem":1845,
    "gn:feature_class":"P",
    "gn:feature_code":"PPL",
    "gn:name":"La Caba\u00f1a",
    "gn:population":0,
    "gn:timezone":"America/Bogota",
    "iso:country":"CO",
    "wof:name":"La Cabana",
    "wof:placetype":"locality"
},
  "geometry": {"coordinates":[-76.86666,2.50879],"type":"Point"}
}