{
  "type": "Feature",
  "properties": {
    "gn:admin1_code":"20.0",
    "gn:admin2_code":"52411.0",
    "gn:asciiname":"Tabiles",
    "gn:country_code":"CO",
    "gn:dem":1866,
    "gn:feature_class":"P",
    "gn:feature_code":"PPL",
    "gn:name":"Tabiles",
    "gn:population":0,
    "gn:timezone":"America/Bogota",
    "iso:country":"CO",
    "wof:name":"Tabiles",
    "wof:placetype":"locality"
},
  "geometry": {"coordinates":[-77.55141999999999,1.40224],"type":"Point"}
}