{
  "type": "Feature",
  "properties": {
    "iso:country":"CO",
    "name:ast_x_preferred":[
        "Manaure"
    ],
    "name:ceb_x_preferred":[
        "Manaure"
    ],
    "name:deu_x_preferred":[
        "Manaure"
    ],
    "name:eng_x_preferred":[
        "Manaure"
    ],
    "name:fas_x_preferred":[
        "\u0645\u0627\u0646\u0627\u0626\u0648\u0631\u0647"
    ],
    "name:fin_x_preferred":[
        "Manaure"
    ],
    "name:fra_x_preferred":[
        "Manaure"
    ],
    "name:gle_x_preferred":[
        "Manaure"
    ],
    "name:guc_x_preferred":[
        "Aleemasain"
    ],
    "name:heb_x_preferred":[
        "\u05de\u05e0\u05d0\u05d5\u05e8\u05d4"
    ],
    "name:ita_x_preferred":[
        "Manaure"
    ],
    "name:kat_x_preferred":[
        "\u10db\u10d0\u10dc\u10d0\u10e3\u10e0\u10d4"
    ],
    "name:msa_x_preferred":[
        "Manaure"
    ],
    "name:nan_x_preferred":[
        "Manaure"
    ],
    "name:nld_x_preferred":[
        "Manaure"
    ],
    "name:nno_x_preferred":[
        "Manaure"
    ],
    "name:nob_x_preferred":[
        "Manaure"
    ],
    "name:pol_x_preferred":[
        "Manaure"
    ],
    "name:por_x_preferred":[
        "Manaure"
    ],
    "name:rus_x_preferred":[
        "\u041c\u0430\u043d\u0430\u0443\u0440\u0435"
    ],
    "name:spa_x_preferred":[
        "Manaure"
    ],
    "name:swe_x_preferred":[
        "Manaure"
    ],
    "name:tat_x_preferred":[
        "\u041c\u0430\u043d\u0430\u0443\u0440\u0435"
    ],
    "name:tgl_x_preferred":[
        "Manaure"
    ],
    "name:und_x_variant":[
        "Manare"
    ],
    "name:vie_x_preferred":[
        "Manaure"
    ],
    "name:war_x_preferred":[
        "Manaure"
    ],
    "name:zho_min_nan_x_preferred":[
        "Manaure"
    ],
    "name:zho_x_preferred":[
        "\u99ac\u7459\u96f7"
    ],
    "qs:gn_country":"CO",
    "qs:gn_fcode":"PPL",
    "qs:gn_pop":9703,
    "qs:name":"Manaure",
    "qs:name_adm0":"Colombia",
    "qs:name_adm1":"La Guajira",
    "qs:photos":255,
    "qs:photos_1k":52,
    "qs:photos_9k":1,
    "qs:photos_9r":4,
    "qs:photos_all":255,
    "qs:photos_sr":5,
    "qs:placetype":"Town",
    "qs:pop_sr":"5",
    "qs:woe_adm0":23424787,
    "wd:wordcount":654,
    "wof:name":"Manaure",
    "wof:placetype":"locality",
    "wof:population":9703
},
  "geometry": {"coordinates":[-72.44447,11.77505],"type":"Point"}
}