{
  "type": "Feature",
  "properties": {
    "gn:admin1_code":"12.0",
    "gn:admin2_code":"23678.0",
    "gn:asciiname":"Cantagallo",
    "gn:country_code":"CO",
    "gn:dem":43,
    "gn:feature_class":"P",
    "gn:feature_code":"PPLL",
    "gn:name":"Cantagallo",
    "gn:population":0,
    "gn:timezone":"America/Bogota",
    "iso:country":"CO",
    "wof:name":"Cantagallo",
    "wof:placetype":"locality"
},
  "geometry": {"coordinates":[-75.67793,8.74874],"type":"Point"}
}