{
  "type": "Feature",
  "properties": {
    "gn:admin1_code":"31.0",
    "gn:admin2_code":"99773.0",
    "gn:asciiname":"Rancheria Docovia Piapocos",
    "gn:country_code":"CO",
    "gn:dem":188,
    "gn:feature_class":"P",
    "gn:feature_code":"PPL",
    "gn:name":"Rancher\u00eda Docovia Piapocos",
    "gn:population":0,
    "gn:timezone":"America/Bogota",
    "iso:country":"CO",
    "wof:name":"Rancheria Docovia Piapocos",
    "wof:placetype":"locality"
},
  "geometry": {"coordinates":[-70.32028000000001,4.09472],"type":"Point"}
}