{
  "type": "Feature",
  "properties": {
    "gn:admin1_code":"9",
    "gn:admin2_code":"19130.0",
    "gn:asciiname":"Dinde",
    "gn:country_code":"CO",
    "gn:dem":1308,
    "gn:feature_class":"P",
    "gn:feature_code":"PPL",
    "gn:name":"Dinde",
    "gn:population":0,
    "gn:timezone":"America/Bogota",
    "iso:country":"CO",
    "wof:name":"Dinde",
    "wof:placetype":"locality"
},
  "geometry": {"coordinates":[-76.7573,2.6931],"type":"Point"}
}