{
  "type": "Feature",
  "properties": {
    "gn:admin1_code":"9.0",
    "gn:admin2_code":"19473.0",
    "gn:asciiname":"Los Quingos",
    "gn:country_code":"CO",
    "gn:dem":1969,
    "gn:feature_class":"P",
    "gn:feature_code":"PPL",
    "gn:name":"Los Quingos",
    "gn:population":0,
    "gn:timezone":"America/Bogota",
    "iso:country":"CO",
    "wof:name":"Los Quingos",
    "wof:placetype":"locality"
},
  "geometry": {"coordinates":[-76.81471999999999,2.91847],"type":"Point"}
}