{
  "type": "Feature",
  "properties": {
    "gn:admin1_code":"21.0",
    "gn:admin2_code":"54347.0",
    "gn:asciiname":"Pamplonita",
    "gn:country_code":"CO",
    "gn:dem":1953,
    "gn:feature_class":"P",
    "gn:feature_code":"PPL",
    "gn:name":"Pamplonita",
    "gn:population":0,
    "gn:timezone":"America/Bogota",
    "iso:country":"CO",
    "name:ceb_x_preferred":[
        "Pamplonita"
    ],
    "name:fra_x_preferred":[
        "Pamplonita"
    ],
    "name:ita_x_preferred":[
        "Pamplonita"
    ],
    "name:kat_x_preferred":[
        "\u10de\u10d0\u10db\u10de\u10da\u10dd\u10dc\u10d8\u10e2\u10d0"
    ],
    "name:msa_x_preferred":[
        "Pamplonita"
    ],
    "name:nld_x_preferred":[
        "Pamplonita"
    ],
    "name:por_x_preferred":[
        "Pamplonita"
    ],
    "name:spa_x_preferred":[
        "Pamplonita"
    ],
    "name:swe_x_preferred":[
        "Pamplonita"
    ],
    "name:tgl_x_preferred":[
        "Pamplonita"
    ],
    "name:vie_x_preferred":[
        "Pamplonita"
    ],
    "name:war_x_preferred":[
        "Pamplonita"
    ],
    "name:zho_x_preferred":[
        "\u6f58\u666e\u6d1b\u5c3c\u5854"
    ],
    "wof:name":"Pamplonita",
    "wof:placetype":"locality"
},
  "geometry": {"coordinates":[-72.48442,7.54077],"type":"Point"}
}