{
  "type": "Feature",
  "properties": {
    "gn:admin1_code":"2.0",
    "gn:admin2_code":"5036.0",
    "gn:asciiname":"La Clara",
    "gn:country_code":"CO",
    "gn:dem":1703,
    "gn:feature_class":"P",
    "gn:feature_code":"PPL",
    "gn:name":"La Clara",
    "gn:population":0,
    "gn:timezone":"America/Bogota",
    "iso:country":"CO",
    "name:spa_x_preferred":[
        "La Clara"
    ],
    "wof:name":"La Clara",
    "wof:placetype":"locality"
},
  "geometry": {"coordinates":[-75.70146,6.09826],"type":"Point"}
}