{
  "type": "Feature",
  "properties": {
    "gn:admin1_code":"12",
    "gn:admin2_code":"23570.0",
    "gn:asciiname":"El Contento",
    "gn:country_code":"CO",
    "gn:dem":166,
    "gn:feature_class":"P",
    "gn:feature_code":"PPL",
    "gn:name":"El Contento",
    "gn:population":0,
    "gn:timezone":"America/Bogota",
    "iso:country":"CO",
    "name:und_x_variant":[
        "Contento",
        "Corregimiento El Contento",
        "El Contento"
    ],
    "wof:name":"El Contento",
    "wof:placetype":"locality"
},
  "geometry": {"coordinates":[-75.56725,8.59451],"type":"Point"}
}