{
  "type": "Feature",
  "properties": {
    "gn:admin1_code":"17",
    "gn:admin2_code":"44560.0",
    "gn:asciiname":"Carencho",
    "gn:country_code":"CO",
    "gn:dem":23,
    "gn:feature_class":"P",
    "gn:feature_code":"PPL",
    "gn:name":"Carencho",
    "gn:population":0,
    "gn:timezone":"America/Bogota",
    "iso:country":"CO",
    "wof:name":"Carencho",
    "wof:placetype":"locality"
},
  "geometry": {"coordinates":[-72.75374000000002,11.4864],"type":"Point"}
}