{
  "type": "Feature",
  "properties": {
    "gn:admin1_code":"9",
    "gn:admin2_code":"19300.0",
    "gn:asciiname":"Caponera",
    "gn:country_code":"CO",
    "gn:dem":975,
    "gn:feature_class":"P",
    "gn:feature_code":"PPL",
    "gn:name":"Caponera",
    "gn:population":0,
    "gn:timezone":"America/Bogota",
    "iso:country":"CO",
    "name:spa_x_preferred":[
        "Caponera"
    ],
    "wof:name":"Caponera",
    "wof:placetype":"locality"
},
  "geometry": {"coordinates":[-76.42359999999999,3.18415],"type":"Point"}
}