{
  "type": "Feature",
  "properties": {
    "gn:admin1_code":"26",
    "gn:admin2_code":"68418.0",
    "gn:asciiname":"La Fuente",
    "gn:country_code":"CO",
    "gn:dem":1628,
    "gn:feature_class":"P",
    "gn:feature_code":"PPL",
    "gn:name":"La Fuente",
    "gn:population":0,
    "gn:timezone":"America/Bogota",
    "iso:country":"CO",
    "wof:name":"La Fuente",
    "wof:placetype":"locality"
},
  "geometry": {"coordinates":[-73.08859,6.8212],"type":"Point"}
}