{
  "type": "Feature",
  "properties": {
    "gn:admin1_code":"26",
    "gn:admin2_code":"68229.0",
    "gn:asciiname":"Canaveral",
    "gn:country_code":"CO",
    "gn:dem":1722,
    "gn:feature_class":"P",
    "gn:feature_code":"PPL",
    "gn:name":"Ca\u00f1averal",
    "gn:population":0,
    "gn:timezone":"America/Bogota",
    "iso:country":"CO",
    "wof:name":"Canaveral",
    "wof:placetype":"locality"
},
  "geometry": {"coordinates":[-73.05,6.65],"type":"Point"}
}