{
  "type": "Feature",
  "properties": {
    "iso:country":"CO",
    "name:ast_x_preferred":[
        "Remolino"
    ],
    "name:ceb_x_preferred":[
        "Remolino"
    ],
    "name:eng_x_preferred":[
        "Remolino"
    ],
    "name:fra_x_preferred":[
        "Remolino"
    ],
    "name:ita_x_preferred":[
        "Remolino"
    ],
    "name:kat_x_preferred":[
        "\u10e0\u10d4\u10db\u10dd\u10da\u10d8\u10dc\u10dd"
    ],
    "name:msa_x_preferred":[
        "Remolino"
    ],
    "name:nan_x_preferred":[
        "Remolino"
    ],
    "name:nld_x_preferred":[
        "Remolino"
    ],
    "name:por_x_preferred":[
        "Remolino"
    ],
    "name:rus_x_preferred":[
        "\u0420\u0435\u043c\u043e\u043b\u0438\u043d\u043e"
    ],
    "name:sco_x_preferred":[
        "Remolino"
    ],
    "name:spa_x_preferred":[
        "Remolino"
    ],
    "name:swe_x_preferred":[
        "Remolino"
    ],
    "name:tgl_x_preferred":[
        "Remolino"
    ],
    "name:ukr_x_preferred":[
        "\u0420\u0435\u043c\u043e\u043b\u0456\u043d\u043e"
    ],
    "name:und_x_variant":[
        "Jaguey"
    ],
    "name:vie_x_preferred":[
        "Remolino"
    ],
    "name:war_x_preferred":[
        "Remolino"
    ],
    "name:zho_min_nan_x_preferred":[
        "Remolino"
    ],
    "name:zho_x_preferred":[
        "\u96f7\u83ab\u5229\u8afe"
    ],
    "qs:gn_country":"CO",
    "qs:gn_fcode":"PPL",
    "qs:gn_pop":8308,
    "qs:name":"Remolino",
    "qs:name_adm0":"Colombia",
    "qs:name_adm1":"Magdalena",
    "qs:photos":0,
    "qs:photos_1k":0,
    "qs:photos_9k":0,
    "qs:photos_9r":0,
    "qs:photos_all":0,
    "qs:photos_sr":0,
    "qs:placetype":"Town",
    "qs:pop_sr":"5",
    "qs:woe_adm0":23424787,
    "wd:wordcount":77,
    "wof:name":"Remolino",
    "wof:placetype":"locality",
    "wof:population":8308
},
  "geometry": {"coordinates":[-74.71602,10.70198],"type":"Point"}
}