{
  "type": "Feature",
  "properties": {
    "gn:admin1_code":"12",
    "gn:admin2_code":"23574.0",
    "gn:asciiname":"Las Mujeres",
    "gn:country_code":"CO",
    "gn:dem":45,
    "gn:feature_class":"P",
    "gn:feature_code":"PPL",
    "gn:name":"Las Mujeres",
    "gn:population":0,
    "gn:timezone":"America/Bogota",
    "iso:country":"CO",
    "wof:name":"Las Mujeres",
    "wof:placetype":"locality"
},
  "geometry": {"coordinates":[-76.18114,8.93101],"type":"Point"}
}