{
  "type": "Feature",
  "properties": {
    "gn:admin1_code":"26.0",
    "gn:admin2_code":"68745.0",
    "gn:asciiname":"Los Naranjitos",
    "gn:cc2":"CO",
    "gn:country_code":"CO",
    "gn:dem":85,
    "gn:feature_class":"P",
    "gn:feature_code":"PPLL",
    "gn:name":"Los Naranjitos",
    "gn:population":0,
    "gn:timezone":"America/Bogota",
    "iso:country":"CO",
    "name:und_x_variant":[
        "Los Nararjitos",
        "Los Naranjitos"
    ],
    "wof:name":"Los Naranjitos",
    "wof:placetype":"locality"
},
  "geometry": {"coordinates":[-73.85083,6.84917],"type":"Point"}
}