{
  "type": "Feature",
  "properties": {
    "gn:admin1_code":"10.0",
    "gn:admin2_code":"20001.0",
    "gn:asciiname":"Hacienda Filadelfia",
    "gn:country_code":"CO",
    "gn:dem":132,
    "gn:feature_class":"P",
    "gn:feature_code":"PPL",
    "gn:name":"Hacienda Filadelfia",
    "gn:population":0,
    "gn:timezone":"America/Bogota",
    "iso:country":"CO",
    "wof:name":"Hacienda Filadelfia",
    "wof:placetype":"locality"
},
  "geometry": {"coordinates":[-73.33888,10.37105],"type":"Point"}
}