{
  "type": "Feature",
  "properties": {
    "gn:admin1_code":"20",
    "gn:asciiname":"Caballos",
    "gn:country_code":"CO",
    "gn:dem":-9999,
    "gn:feature_class":"P",
    "gn:feature_code":"PPL",
    "gn:name":"Caballos",
    "gn:population":0,
    "gn:timezone":"America/Bogota",
    "iso:country":"CO",
    "wof:name":"Caballos",
    "wof:placetype":"locality"
},
  "geometry": {"coordinates":[-78.58139,2.46556],"type":"Point"}
}