{
  "type": "Feature",
  "properties": {
    "gn:admin1_code":"33",
    "gn:admin2_code":"25530.0",
    "gn:asciiname":"Guacavia",
    "gn:country_code":"CO",
    "gn:dem":204,
    "gn:feature_class":"P",
    "gn:feature_code":"PPL",
    "gn:name":"Guacavia",
    "gn:population":0,
    "gn:timezone":"America/Bogota",
    "iso:country":"CO",
    "wof:name":"Guacavia",
    "wof:placetype":"locality"
},
  "geometry": {"coordinates":[-73.15165999999998,4.22962],"type":"Point"}
}