{
  "type": "Feature",
  "properties": {
    "gn:admin1_code":"36",
    "gn:admin2_code":"15299.0",
    "gn:asciiname":"El Poleo",
    "gn:country_code":"CO",
    "gn:dem":2385,
    "gn:feature_class":"P",
    "gn:feature_code":"PPL",
    "gn:name":"El Poleo",
    "gn:population":0,
    "gn:timezone":"America/Bogota",
    "iso:country":"CO",
    "wof:name":"El Poleo",
    "wof:placetype":"locality"
},
  "geometry": {"coordinates":[-73.30410999999999,5.07594],"type":"Point"}
}