{
  "type": "Feature",
  "properties": {
    "gn:admin1_code":"17.0",
    "gn:admin2_code":"44847.0",
    "gn:asciiname":"Maluwayan",
    "gn:country_code":"CO",
    "gn:dem":96,
    "gn:feature_class":"P",
    "gn:feature_code":"PPLL",
    "gn:name":"Maluwayan",
    "gn:population":0,
    "gn:timezone":"America/Bogota",
    "iso:country":"CO",
    "wof:name":"Maluwayan",
    "wof:placetype":"locality"
},
  "geometry": {"coordinates":[-71.89943000000002,11.7372],"type":"Point"}
}