{
  "type": "Feature",
  "properties": {
    "gn:admin1_code":"9.0",
    "gn:admin2_code":"19418.0",
    "gn:asciiname":"Difunto Pedro",
    "gn:country_code":"CO",
    "gn:dem":54,
    "gn:feature_class":"P",
    "gn:feature_code":"PPL",
    "gn:name":"Difunto Pedro",
    "gn:population":0,
    "gn:timezone":"America/Bogota",
    "iso:country":"CO",
    "wof:name":"Difunto Pedro",
    "wof:placetype":"locality"
},
  "geometry": {"coordinates":[-77.22875000000001,3.07979],"type":"Point"}
}