{
  "type": "Feature",
  "properties": {
    "gn:admin1_code":"10",
    "gn:asciiname":"Chengue",
    "gn:cc2":"CO",
    "gn:country_code":"CO",
    "gn:dem":13,
    "gn:feature_class":"P",
    "gn:feature_code":"PPL",
    "gn:name":"Chengue",
    "gn:population":0,
    "gn:timezone":"America/Bogota",
    "iso:country":"CO",
    "name:und_x_variant":[
        "Corregimiento Chengue",
        "Rosario de Chengue",
        "Chengue"
    ],
    "wof:name":"Chengue",
    "wof:placetype":"locality"
},
  "geometry": {"coordinates":[-74.83333,10.25],"type":"Point"}
}