{
  "type": "Feature",
  "properties": {
    "gn:admin1_code":"28.0",
    "gn:admin2_code":"73563.0",
    "gn:asciiname":"El Placer",
    "gn:country_code":"CO",
    "gn:dem":322,
    "gn:feature_class":"P",
    "gn:feature_code":"PPLL",
    "gn:name":"El Placer",
    "gn:population":0,
    "gn:timezone":"America/Bogota",
    "iso:country":"CO",
    "name:spa_x_preferred":[
        "El Placer"
    ],
    "wof:name":"El Placer",
    "wof:placetype":"locality"
},
  "geometry": {"coordinates":[-74.93994000000001,3.69461],"type":"Point"}
}