{
  "type": "Feature",
  "properties": {
    "gn:admin1_code":"36",
    "gn:admin2_code":"15720.0",
    "gn:asciiname":"Jupa",
    "gn:country_code":"CO",
    "gn:dem":2339,
    "gn:feature_class":"P",
    "gn:feature_code":"PPL",
    "gn:name":"Jupa",
    "gn:population":0,
    "gn:timezone":"America/Bogota",
    "iso:country":"CO",
    "wof:name":"Jupa",
    "wof:placetype":"locality"
},
  "geometry": {"coordinates":[-72.67156,6.16347],"type":"Point"}
}