{
  "type": "Feature",
  "properties": {
    "gn:admin1_code":"10",
    "gn:admin2_code":"20614.0",
    "gn:asciiname":"La Popa",
    "gn:country_code":"CO",
    "gn:dem":974,
    "gn:feature_class":"P",
    "gn:feature_code":"PPL",
    "gn:name":"La Popa",
    "gn:population":0,
    "gn:timezone":"America/Bogota",
    "iso:country":"CO",
    "wof:name":"La Popa",
    "wof:placetype":"locality"
},
  "geometry": {"coordinates":[-73.47861,8.3325],"type":"Point"}
}