{
  "type": "Feature",
  "properties": {
    "gn:admin1_code":"20.0",
    "gn:admin2_code":"52001.0",
    "gn:asciiname":"Las Cuadras",
    "gn:country_code":"CO",
    "gn:dem":2552,
    "gn:feature_class":"P",
    "gn:feature_code":"PPL",
    "gn:name":"Las Cuadras",
    "gn:population":0,
    "gn:timezone":"America/Bogota",
    "iso:country":"CO",
    "wof:name":"Las Cuadras",
    "wof:placetype":"locality"
},
  "geometry": {"coordinates":[-77.32316999999998,1.25402],"type":"Point"}
}