{
  "type": "Feature",
  "properties": {
    "gn:admin1_code":"35",
    "gn:admin2_code":"13042.0",
    "gn:asciiname":"Los Penones",
    "gn:country_code":"CO",
    "gn:dem":41,
    "gn:feature_class":"P",
    "gn:feature_code":"PPL",
    "gn:name":"Los Pe\u00f1ones",
    "gn:population":0,
    "gn:timezone":"America/Bogota",
    "iso:country":"CO",
    "wof:name":"Los Penones",
    "wof:placetype":"locality"
},
  "geometry": {"coordinates":[-73.88551,8.44145],"type":"Point"}
}