{
  "type": "Feature",
  "properties": {
    "gn:admin1_code":"17",
    "gn:admin2_code":"44001.0",
    "gn:asciiname":"Jauairruhu",
    "gn:country_code":"CO",
    "gn:dem":66,
    "gn:feature_class":"P",
    "gn:feature_code":"PPL",
    "gn:name":"Jauairruhu",
    "gn:population":0,
    "gn:timezone":"America/Bogota",
    "iso:country":"CO",
    "name:und_x_variant":[
        "Quiebrapalo",
        "Jauairruhu"
    ],
    "wof:name":"Jauairruhu",
    "wof:placetype":"locality"
},
  "geometry": {"coordinates":[-72.70533,11.30677],"type":"Point"}
}