{
  "type": "Feature",
  "properties": {
    "gn:admin1_code":"32",
    "gn:admin2_code":"85250.0",
    "gn:asciiname":"La Chula",
    "gn:country_code":"CO",
    "gn:dem":104,
    "gn:feature_class":"P",
    "gn:feature_code":"PPL",
    "gn:name":"La Chula",
    "gn:population":0,
    "gn:timezone":"America/Bogota",
    "iso:country":"CO",
    "wof:name":"La Chula",
    "wof:placetype":"locality"
},
  "geometry": {"coordinates":[-70.45484999999999,5.5409],"type":"Point"}
}