{
  "type": "Feature",
  "properties": {
    "gn:admin1_code":"35",
    "gn:admin2_code":"13430.0",
    "gn:asciiname":"Tres Puntas",
    "gn:country_code":"CO",
    "gn:dem":51,
    "gn:feature_class":"P",
    "gn:feature_code":"PPL",
    "gn:name":"Tres Puntas",
    "gn:population":0,
    "gn:timezone":"America/Bogota",
    "iso:country":"CO",
    "wof:name":"Tres Puntas",
    "wof:placetype":"locality"
},
  "geometry": {"coordinates":[-74.89279000000001,9.19042],"type":"Point"}
}