{
  "type": "Feature",
  "properties": {
    "gn:admin1_code":"33.0",
    "gn:admin2_code":"25297.0",
    "gn:asciiname":"La Chamba",
    "gn:country_code":"CO",
    "gn:dem":1791,
    "gn:feature_class":"P",
    "gn:feature_code":"PPL",
    "gn:name":"La Chamba",
    "gn:population":0,
    "gn:timezone":"America/Bogota",
    "iso:country":"CO",
    "name:cat_x_preferred":[
        "La Chambaa"
    ],
    "name:ceb_x_preferred":[
        "La Chamba"
    ],
    "name:deu_x_preferred":[
        "La Chamba"
    ],
    "name:eus_x_preferred":[
        "La Chamba"
    ],
    "name:fra_x_preferred":[
        "La Chamba"
    ],
    "name:frp_x_preferred":[
        "La Chamb\u00e2"
    ],
    "name:hun_x_preferred":[
        "La Chamba"
    ],
    "name:ita_x_preferred":[
        "La Chamba"
    ],
    "name:lat_x_preferred":[
        "La Chamba"
    ],
    "name:lmo_x_preferred":[
        "La Chamba"
    ],
    "name:mlg_x_preferred":[
        "La Chamba"
    ],
    "name:msa_x_preferred":[
        "La Chamba"
    ],
    "name:nld_x_preferred":[
        "La Chamba"
    ],
    "name:oci_x_preferred":[
        "La Chambaa"
    ],
    "name:pms_x_preferred":[
        "La Chamba"
    ],
    "name:pol_x_preferred":[
        "La Chamba"
    ],
    "name:por_x_preferred":[
        "La Chamba"
    ],
    "name:ron_x_preferred":[
        "La Chamba"
    ],
    "name:slk_x_preferred":[
        "La Chamba"
    ],
    "name:spa_x_preferred":[
        "La Chamba"
    ],
    "name:srp_x_preferred":[
        "\u0428\u0430\u043c\u0431\u0430"
    ],
    "name:swe_x_preferred":[
        "La Chamba"
    ],
    "name:ukr_x_preferred":[
        "\u041b\u0430-\u0428\u0430\u043c\u0431\u0430"
    ],
    "name:urd_x_preferred":[
        "\u0644\u0627 \u0634\u0627\u0645\u0628\u0627"
    ],
    "name:uzb_x_preferred":[
        "La Chamba"
    ],
    "name:vie_x_preferred":[
        "La Chamba"
    ],
    "name:vol_x_preferred":[
        "La Chamba"
    ],
    "name:war_x_preferred":[
        "La Chamba"
    ],
    "name:zho_x_preferred":[
        "\u62c9\u5c1a\u5df4"
    ],
    "wof:name":"La Chamba",
    "wof:placetype":"locality"
},
  "geometry": {"coordinates":[-73.65453000000002,4.83869],"type":"Point"}
}