{
  "type": "Feature",
  "properties": {
    "gn:admin1_code":"2.0",
    "gn:admin2_code":"5086.0",
    "gn:asciiname":"Playas",
    "gn:cc2":"CO",
    "gn:country_code":"CO",
    "gn:dem":2519,
    "gn:feature_class":"P",
    "gn:feature_code":"PPL",
    "gn:name":"Playas",
    "gn:population":0,
    "gn:timezone":"America/Bogota",
    "iso:country":"CO",
    "name:und_x_variant":[
        "Playa",
        "Playas"
    ],
    "wof:name":"Playas",
    "wof:placetype":"locality"
},
  "geometry": {"coordinates":[-75.62361,6.54139],"type":"Point"}
}