{
  "type": "Feature",
  "properties": {
    "gn:admin1_code":"28",
    "gn:admin2_code":"73483",
    "gn:asciiname":"Jagual",
    "gn:country_code":"CO",
    "gn:dem":367,
    "gn:feature_class":"P",
    "gn:feature_code":"PPL",
    "gn:name":"Jagual",
    "gn:population":0,
    "gn:timezone":"America/Bogota",
    "iso:country":"CO",
    "name:spa_x_preferred":[
        "Jagual"
    ],
    "wof:name":"Jagual",
    "wof:placetype":"locality"
},
  "geometry": {"coordinates":[-75.02773000000001,3.597],"type":"Point"}
}