{
  "type": "Feature",
  "properties": {
    "gn:admin1_code":"2.0",
    "gn:admin2_code":"5789.0",
    "gn:asciiname":"Cartama",
    "gn:country_code":"CO",
    "gn:dem":1441,
    "gn:feature_class":"P",
    "gn:feature_code":"PPL",
    "gn:name":"Cartama",
    "gn:population":0,
    "gn:timezone":"America/Bogota",
    "iso:country":"CO",
    "wof:name":"Cartama",
    "wof:placetype":"locality"
},
  "geometry": {"coordinates":[-75.69889000000001,5.62111],"type":"Point"}
}