{
  "type": "Feature",
  "properties": {
    "gn:admin1_code":"33",
    "gn:admin2_code":"25148.0",
    "gn:asciiname":"El Puente",
    "gn:country_code":"CO",
    "gn:dem":377,
    "gn:feature_class":"P",
    "gn:feature_code":"PPL",
    "gn:name":"El Puente",
    "gn:population":0,
    "gn:timezone":"America/Bogota",
    "iso:country":"CO",
    "wof:name":"El Puente",
    "wof:placetype":"locality"
},
  "geometry": {"coordinates":[-74.56667,5.28333],"type":"Point"}
}