{
  "type": "Feature",
  "properties": {
    "gn:admin1_code":"26",
    "gn:admin2_code":"68167.0",
    "gn:asciiname":"La Morena",
    "gn:country_code":"CO",
    "gn:dem":1322,
    "gn:feature_class":"P",
    "gn:feature_code":"PPL",
    "gn:name":"La Morena",
    "gn:population":0,
    "gn:timezone":"America/Bogota",
    "iso:country":"CO",
    "wof:name":"La Morena",
    "wof:placetype":"locality"
},
  "geometry": {"coordinates":[-73.1635,6.23496],"type":"Point"}
}