{
  "type": "Feature",
  "properties": {
    "gn:admin1_code":"35",
    "gn:admin2_code":"13212.0",
    "gn:asciiname":"Arenal",
    "gn:country_code":"CO",
    "gn:dem":76,
    "gn:feature_class":"P",
    "gn:feature_code":"PPL",
    "gn:name":"Arenal",
    "gn:population":0,
    "gn:timezone":"America/Bogota",
    "iso:country":"CO",
    "name:cat_x_preferred":[
        "Arenal"
    ],
    "name:ceb_x_preferred":[
        "Arenal"
    ],
    "name:deu_x_preferred":[
        "Arenal"
    ],
    "name:epo_x_preferred":[
        "Arenal"
    ],
    "name:fas_x_preferred":[
        "\u0622\u0631\u0646\u0627\u0644"
    ],
    "name:fra_x_preferred":[
        "Arenal"
    ],
    "name:ita_x_preferred":[
        "Arenal"
    ],
    "name:nds_x_preferred":[
        "Arenal"
    ],
    "name:nld_x_preferred":[
        "Arenal"
    ],
    "name:pol_x_preferred":[
        "Arenal"
    ],
    "name:por_x_preferred":[
        "Arenal"
    ],
    "name:sco_x_preferred":[
        "Arenal"
    ],
    "name:spa_x_preferred":[
        "Arenal"
    ],
    "name:srp_x_preferred":[
        "\u0410\u0440\u0435\u043d\u0430\u043b"
    ],
    "name:swe_x_preferred":[
        "Arenal"
    ],
    "name:und_x_variant":[
        "Hacienda Arenal",
        "Arena",
        "Arenal"
    ],
    "wof:name":"Arenal",
    "wof:placetype":"locality"
},
  "geometry": {"coordinates":[-74.92285,9.50895],"type":"Point"}
}