{
  "type": "Feature",
  "properties": {
    "gn:admin1_code":"35",
    "gn:admin2_code":"13212.0",
    "gn:asciiname":"Arenal",
    "gn:country_code":"CO",
    "gn:dem":76,
    "gn:feature_class":"P",
    "gn:feature_code":"PPL",
    "gn:name":"Arenal",
    "gn:population":0,
    "gn:timezone":"America/Bogota",
    "iso:country":"CO",
    "name:und_x_variant":[
        "Hacienda Arenal",
        "Arena",
        "Arenal"
    ],
    "wof:name":"Arenal",
    "wof:placetype":"locality"
},
  "geometry": {"coordinates":[-74.92285,9.50895],"type":"Point"}
}