{
  "type": "Feature",
  "properties": {
    "gn:admin1_code":"27",
    "gn:admin2_code":"70678.0",
    "gn:asciiname":"Carreto",
    "gn:cc2":"CO",
    "gn:country_code":"CO",
    "gn:dem":25,
    "gn:feature_class":"P",
    "gn:feature_code":"PPL",
    "gn:name":"Carreto",
    "gn:population":0,
    "gn:timezone":"America/Bogota",
    "iso:country":"CO",
    "name:und_x_variant":[
        "Carreta",
        "Carreto"
    ],
    "wof:name":"Carreto",
    "wof:placetype":"locality"
},
  "geometry": {"coordinates":[-75.03333000000001,8.98333],"type":"Point"}
}