{
  "type": "Feature",
  "properties": {
    "gn:admin1_code":"36",
    "gn:asciiname":"El Tablon",
    "gn:country_code":"CO",
    "gn:dem":3177,
    "gn:feature_class":"P",
    "gn:feature_code":"PPL",
    "gn:name":"El Tabl\u00f3n",
    "gn:population":0,
    "gn:timezone":"America/Bogota",
    "iso:country":"CO",
    "wof:name":"El Tablon",
    "wof:placetype":"locality"
},
  "geometry": {"coordinates":[-73.81416999999998,5.72611],"type":"Point"}
}