{
  "type": "Feature",
  "properties": {
    "gn:admin1_code":"12.0",
    "gn:admin2_code":"23660.0",
    "gn:asciiname":"Sorrento",
    "gn:country_code":"CO",
    "gn:dem":102,
    "gn:feature_class":"P",
    "gn:feature_code":"PPLL",
    "gn:name":"Sorrento",
    "gn:population":0,
    "gn:timezone":"America/Bogota",
    "iso:country":"CO",
    "wof:name":"Sorrento",
    "wof:placetype":"locality"
},
  "geometry": {"coordinates":[-75.52471,8.71348],"type":"Point"}
}