{
  "type": "Feature",
  "properties": {
    "gn:admin1_code":"2",
    "gn:admin2_code":"5873.0",
    "gn:asciiname":"Buchado",
    "gn:country_code":"CO",
    "gn:dem":24,
    "gn:feature_class":"P",
    "gn:feature_code":"PPL",
    "gn:name":"Buchad\u00f3",
    "gn:population":0,
    "gn:timezone":"America/Bogota",
    "iso:country":"CO",
    "wof:name":"Buchado",
    "wof:placetype":"locality"
},
  "geometry": {"coordinates":[-76.77215,6.37085],"type":"Point"}
}