{
  "type": "Feature",
  "properties": {
    "gn:admin1_code":"29.0",
    "gn:admin2_code":"76001.0",
    "gn:asciiname":"Urbanizacion Las Cabanas",
    "gn:country_code":"CO",
    "gn:dem":1902,
    "gn:feature_class":"P",
    "gn:feature_code":"PPL",
    "gn:name":"Urbanizaci\u00f3n Las Caba\u00f1as",
    "gn:population":0,
    "gn:timezone":"America/Bogota",
    "iso:country":"CO",
    "name:spa_x_preferred":[
        "Urbanizaci\u00f3n Las Caba\u00f1as"
    ],
    "wof:name":"Urbanizacion Las Cabanas",
    "wof:placetype":"locality"
},
  "geometry": {"coordinates":[-76.63382,3.46932],"type":"Point"}
}