{
  "type": "Feature",
  "properties": {
    "gn:admin1_code":"36.0",
    "gn:admin2_code":"15667.0",
    "gn:asciiname":"Rio Chiquito",
    "gn:country_code":"CO",
    "gn:dem":474,
    "gn:feature_class":"P",
    "gn:feature_code":"PPL",
    "gn:name":"R\u00edo Chiquito",
    "gn:population":0,
    "gn:timezone":"America/Bogota",
    "iso:country":"CO",
    "wof:name":"Rio Chiquito",
    "wof:placetype":"locality"
},
  "geometry": {"coordinates":[-73.14502,4.68154],"type":"Point"}
}