{
  "type": "Feature",
  "properties": {
    "gn:admin1_code":"26.0",
    "gn:admin2_code":"68770.0",
    "gn:asciiname":"Quebradanegra",
    "gn:country_code":"CO",
    "gn:dem":1524,
    "gn:feature_class":"P",
    "gn:feature_code":"PPL",
    "gn:name":"Quebradanegra",
    "gn:population":0,
    "gn:timezone":"America/Bogota",
    "iso:country":"CO",
    "wof:name":"Quebradanegra",
    "wof:placetype":"locality"
},
  "geometry": {"coordinates":[-73.38724000000001,6.08451],"type":"Point"}
}