{
  "type": "Feature",
  "properties": {
    "gn:admin1_code":"26.0",
    "gn:admin2_code":"68770.0",
    "gn:asciiname":"Quebradanegra",
    "gn:country_code":"CO",
    "gn:dem":1524,
    "gn:feature_class":"P",
    "gn:feature_code":"PPL",
    "gn:name":"Quebradanegra",
    "gn:population":0,
    "gn:timezone":"America/Bogota",
    "iso:country":"CO",
    "name:ceb_x_preferred":[
        "Quebradanegra"
    ],
    "name:fra_x_preferred":[
        "Quebradanegra"
    ],
    "name:ita_x_preferred":[
        "Quebradanegra"
    ],
    "name:kat_x_preferred":[
        "\u10d9\u10d4\u10d1\u10e0\u10d0\u10d3\u10d0\u10dc\u10d4\u10d2\u10e0\u10d0"
    ],
    "name:msa_x_preferred":[
        "Quebradanegra"
    ],
    "name:nld_x_preferred":[
        "Quebradanegra"
    ],
    "name:por_x_preferred":[
        "Quebradanegra"
    ],
    "name:sco_x_preferred":[
        "Quebradanegra"
    ],
    "name:spa_x_preferred":[
        "Quebradanegra"
    ],
    "name:swe_x_preferred":[
        "Quebradanegra"
    ],
    "name:tgl_x_preferred":[
        "Quebradanegra"
    ],
    "name:vie_x_preferred":[
        "Quebradanegra"
    ],
    "name:war_x_preferred":[
        "Quebradanegra"
    ],
    "name:zho_x_preferred":[
        "\u514b\u5e03\u62c9\u9054\u5167\u683c\u62c9"
    ],
    "wof:name":"Quebradanegra",
    "wof:placetype":"locality"
},
  "geometry": {"coordinates":[-73.38724000000001,6.08451],"type":"Point"}
}