{
  "type": "Feature",
  "properties": {
    "gn:admin1_code":"28.0",
    "gn:admin2_code":"73449.0",
    "gn:asciiname":"Inali",
    "gn:country_code":"CO",
    "gn:dem":763,
    "gn:feature_class":"P",
    "gn:feature_code":"PPL",
    "gn:name":"Inal\u00ed",
    "gn:population":0,
    "gn:timezone":"America/Bogota",
    "iso:country":"CO",
    "name:spa_x_preferred":[
        "Inal\u00ed"
    ],
    "wof:name":"Inali",
    "wof:placetype":"locality"
},
  "geometry": {"coordinates":[-74.67936,4.11298],"type":"Point"}
}