{
  "type": "Feature",
  "properties": {
    "gn:admin1_code":"26.0",
    "gn:admin2_code":"68770.0",
    "gn:asciiname":"No Te Veo",
    "gn:country_code":"CO",
    "gn:dem":1947,
    "gn:feature_class":"P",
    "gn:feature_code":"PPL",
    "gn:name":"No Te Veo",
    "gn:population":0,
    "gn:timezone":"America/Bogota",
    "iso:country":"CO",
    "wof:name":"No Te Veo",
    "wof:placetype":"locality"
},
  "geometry": {"coordinates":[-73.27809999999999,6.12013],"type":"Point"}
}