{
  "type": "Feature",
  "properties": {
    "gn:admin1_code":"20.0",
    "gn:admin2_code":"52001.0",
    "gn:asciiname":"Ines",
    "gn:country_code":"CO",
    "gn:dem":2687,
    "gn:feature_class":"P",
    "gn:feature_code":"PPL",
    "gn:name":"Ines",
    "gn:population":0,
    "gn:timezone":"America/Bogota",
    "iso:country":"CO",
    "name:ceb_x_preferred":[
        "Ines"
    ],
    "name:deu_x_preferred":[
        "Ines"
    ],
    "name:fra_x_preferred":[
        "Ines"
    ],
    "wof:name":"Ines",
    "wof:placetype":"locality"
},
  "geometry": {"coordinates":[-77.25644,1.18858],"type":"Point"}
}