{
  "type": "Feature",
  "properties": {
    "gn:admin1_code":"9.0",
    "gn:admin2_code":"19532.0",
    "gn:asciiname":"La Fonda",
    "gn:country_code":"CO",
    "gn:dem":604,
    "gn:feature_class":"P",
    "gn:feature_code":"PPL",
    "gn:name":"La Fonda",
    "gn:population":0,
    "gn:timezone":"America/Bogota",
    "iso:country":"CO",
    "name:und_x_variant":[
        "Fonda"
    ],
    "wof:name":"La Fonda",
    "wof:placetype":"locality"
},
  "geometry": {"coordinates":[-77.06010000000001,2.1519],"type":"Point"}
}