{
  "type": "Feature",
  "properties": {
    "gn:admin1_code":"20.0",
    "gn:admin2_code":"52427.0",
    "gn:asciiname":"Nansalvi",
    "gn:country_code":"CO",
    "gn:dem":46,
    "gn:feature_class":"P",
    "gn:feature_code":"PPL",
    "gn:name":"Nansalv\u00ed",
    "gn:population":0,
    "gn:timezone":"America/Bogota",
    "iso:country":"CO",
    "name:und_x_variant":[
        "Mansalv\u00ed",
        "Nansalbi",
        "Nansalv\u00ed"
    ],
    "wof:name":"Nansalvi",
    "wof:placetype":"locality"
},
  "geometry": {"coordinates":[-78.10868000000001,1.88186],"type":"Point"}
}