{
  "type": "Feature",
  "properties": {
    "gn:admin1_code":"1",
    "gn:admin2_code":"91405.0",
    "gn:asciiname":"Ipunas",
    "gn:country_code":"CO",
    "gn:dem":180,
    "gn:feature_class":"P",
    "gn:feature_code":"PPL",
    "gn:name":"Ipunas",
    "gn:population":0,
    "gn:timezone":"America/Bogota",
    "iso:country":"CO",
    "wof:name":"Ipunas",
    "wof:placetype":"locality"
},
  "geometry": {"coordinates":[-73.56667,-0.53333],"type":"Point"}
}