{
  "type": "Feature",
  "properties": {
    "gn:admin1_code":"33.0",
    "gn:admin2_code":"25394.0",
    "gn:asciiname":"Minipi de Quijano",
    "gn:cc2":"CO",
    "gn:country_code":"CO",
    "gn:dem":1569,
    "gn:feature_class":"P",
    "gn:feature_code":"PPL",
    "gn:name":"Minip\u00ed de Quijano",
    "gn:population":0,
    "gn:timezone":"America/Bogota",
    "iso:country":"CO",
    "name:und_x_variant":[
        "Minip\u00ed",
        "Minip\u00ed de Quijano"
    ],
    "wof:name":"Minipi de Quijano",
    "wof:placetype":"locality"
},
  "geometry": {"coordinates":[-74.41667,5.41667],"type":"Point"}
}