{
  "type": "Feature",
  "properties": {
    "gn:admin1_code":"38.0",
    "gn:admin2_code":"47030.0",
    "gn:asciiname":"Montecarlo",
    "gn:country_code":"CO",
    "gn:dem":106,
    "gn:feature_class":"P",
    "gn:feature_code":"PPL",
    "gn:name":"Montecarlo",
    "gn:population":0,
    "gn:timezone":"America/Bogota",
    "iso:country":"CO",
    "wof:name":"Montecarlo",
    "wof:placetype":"locality"
},
  "geometry": {"coordinates":[-74.06693,10.1644],"type":"Point"}
}