{
  "type": "Feature",
  "properties": {
    "gn:admin1_code":"21",
    "gn:admin2_code":"54810.0",
    "gn:asciiname":"La Llana",
    "gn:country_code":"CO",
    "gn:dem":72,
    "gn:feature_class":"P",
    "gn:feature_code":"PPL",
    "gn:name":"La Llana",
    "gn:population":0,
    "gn:timezone":"America/Bogota",
    "iso:country":"CO",
    "wof:name":"La Llana",
    "wof:placetype":"locality"
},
  "geometry": {"coordinates":[-72.60021999999999,8.36642],"type":"Point"}
}