{
  "type": "Feature",
  "properties": {
    "gn:admin1_code":"26",
    "gn:admin2_code":"68377.0",
    "gn:asciiname":"El Achontillo",
    "gn:country_code":"CO",
    "gn:dem":625,
    "gn:feature_class":"P",
    "gn:feature_code":"PPL",
    "gn:name":"El Achontillo",
    "gn:population":0,
    "gn:timezone":"America/Bogota",
    "iso:country":"CO",
    "wof:name":"El Achontillo",
    "wof:placetype":"locality"
},
  "geometry": {"coordinates":[-74.04422,5.89352],"type":"Point"}
}