{
  "type": "Feature",
  "properties": {
    "gn:admin1_code":"26.0",
    "gn:admin2_code":"68575.0",
    "gn:asciiname":"Campo Alegre",
    "gn:country_code":"CO",
    "gn:dem":131,
    "gn:feature_class":"P",
    "gn:feature_code":"PPL",
    "gn:name":"Campo Alegre",
    "gn:population":0,
    "gn:timezone":"America/Bogota",
    "iso:country":"CO",
    "wof:name":"Campo Alegre",
    "wof:placetype":"locality"
},
  "geometry": {"coordinates":[-73.71306,7.26917],"type":"Point"}
}