{
  "type": "Feature",
  "properties": {
    "gn:admin1_code":"29",
    "gn:admin2_code":"76736.0",
    "gn:asciiname":"Santa Monica",
    "gn:country_code":"CO",
    "gn:dem":1586,
    "gn:feature_class":"P",
    "gn:feature_code":"PPL",
    "gn:name":"Santa M\u00f3nica",
    "gn:population":0,
    "gn:timezone":"America/Bogota",
    "iso:country":"CO",
    "wof:name":"Santa Monica",
    "wof:placetype":"locality"
},
  "geometry": {"coordinates":[-75.93639,4.19028],"type":"Point"}
}