{
  "type": "Feature",
  "properties": {
    "gn:admin1_code":"31",
    "gn:asciiname":"La Rubiera",
    "gn:country_code":"CO",
    "gn:dem":108,
    "gn:feature_class":"P",
    "gn:feature_code":"PPL",
    "gn:name":"La Rubiera",
    "gn:population":0,
    "gn:timezone":"America/Bogota",
    "iso:country":"CO",
    "name:spa_x_preferred":[
        "La Rubiera"
    ],
    "wof:name":"La Rubiera",
    "wof:placetype":"locality"
},
  "geometry": {"coordinates":[-69.76255999999999,5.98397],"type":"Point"}
}