{
  "type": "Feature",
  "properties": {
    "gn:admin1_code":"26",
    "gn:admin2_code":"68020.0",
    "gn:asciiname":"Guacos",
    "gn:country_code":"CO",
    "gn:dem":2802,
    "gn:feature_class":"P",
    "gn:feature_code":"PPL",
    "gn:name":"Guacos",
    "gn:population":0,
    "gn:timezone":"America/Bogota",
    "iso:country":"CO",
    "wof:name":"Guacos",
    "wof:placetype":"locality"
},
  "geometry": {"coordinates":[-73.85028,5.75139],"type":"Point"}
}