{
  "type": "Feature",
  "properties": {
    "gn:admin1_code":"28",
    "gn:admin2_code":"73585.0",
    "gn:asciiname":"Caserio El Papayo",
    "gn:country_code":"CO",
    "gn:dem":301,
    "gn:feature_class":"P",
    "gn:feature_code":"PPL",
    "gn:name":"Caser\u00edo El Papayo",
    "gn:population":0,
    "gn:timezone":"America/Bogota",
    "iso:country":"CO",
    "wof:name":"Caserio El Papayo",
    "wof:placetype":"locality"
},
  "geometry": {"coordinates":[-74.98333000000002,3.88333],"type":"Point"}
}