{
  "type": "Feature",
  "properties": {
    "gn:admin1_code":"2",
    "gn:admin2_code":"5142.0",
    "gn:asciiname":"La Frontera",
    "gn:country_code":"CO",
    "gn:dem":609,
    "gn:feature_class":"P",
    "gn:feature_code":"PPL",
    "gn:name":"La Frontera",
    "gn:population":0,
    "gn:timezone":"America/Bogota",
    "iso:country":"CO",
    "wof:name":"La Frontera",
    "wof:placetype":"locality"
},
  "geometry": {"coordinates":[-74.77056,6.28472],"type":"Point"}
}