{
  "type": "Feature",
  "properties": {
    "gn:admin1_code":"36.0",
    "gn:admin2_code":"15516.0",
    "gn:asciiname":"Salitre",
    "gn:country_code":"CO",
    "gn:dem":2520,
    "gn:feature_class":"P",
    "gn:feature_code":"PPL",
    "gn:name":"Salitre",
    "gn:population":0,
    "gn:timezone":"America/Bogota",
    "iso:country":"CO",
    "name:ceb_x_preferred":[
        "Salitre"
    ],
    "name:por_x_preferred":[
        "Salitre"
    ],
    "name:srp_x_preferred":[
        "\u0421\u0430\u043b\u0438\u0442\u0440\u0435"
    ],
    "name:swe_x_preferred":[
        "Salitre"
    ],
    "wof:name":"Salitre",
    "wof:placetype":"locality"
},
  "geometry": {"coordinates":[-73.13039999999999,5.74758],"type":"Point"}
}