{
  "type": "Feature",
  "properties": {
    "gn:admin1_code":"28.0",
    "gn:admin2_code":"73504.0",
    "gn:asciiname":"Topacio",
    "gn:country_code":"CO",
    "gn:dem":671,
    "gn:feature_class":"P",
    "gn:feature_code":"PPL",
    "gn:name":"Topacio",
    "gn:population":0,
    "gn:timezone":"America/Bogota",
    "iso:country":"CO",
    "wof:name":"Topacio",
    "wof:placetype":"locality"
},
  "geometry": {"coordinates":[-75.30972,3.9675],"type":"Point"}
}