{
  "type": "Feature",
  "properties": {
    "gn:admin1_code":"1.0",
    "gn:admin2_code":"91530.0",
    "gn:asciiname":"Puerto Victoria",
    "gn:country_code":"CO",
    "gn:dem":151,
    "gn:feature_class":"P",
    "gn:feature_code":"PPL",
    "gn:name":"Puerto Victoria",
    "gn:population":0,
    "gn:timezone":"America/Bogota",
    "iso:country":"CO",
    "wof:name":"Puerto Victoria",
    "wof:placetype":"locality"
},
  "geometry": {"coordinates":[-74.26666999999998,-0.93333],"type":"Point"}
}