{
  "type": "Feature",
  "properties": {
    "gn:admin1_code":"37",
    "gn:admin2_code":"17665.0",
    "gn:asciiname":"El Contento",
    "gn:country_code":"CO",
    "gn:dem":1657,
    "gn:feature_class":"P",
    "gn:feature_code":"PPL",
    "gn:name":"El Contento",
    "gn:population":0,
    "gn:timezone":"America/Bogota",
    "iso:country":"CO",
    "wof:name":"El Contento",
    "wof:placetype":"locality"
},
  "geometry": {"coordinates":[-75.79778,5.08722],"type":"Point"}
}