{
  "type": "Feature",
  "properties": {
    "gn:admin1_code":"35",
    "gn:admin2_code":"13780.0",
    "gn:asciiname":"Las Mendozas",
    "gn:cc2":"CO",
    "gn:country_code":"CO",
    "gn:dem":18,
    "gn:feature_class":"P",
    "gn:feature_code":"PPL",
    "gn:name":"Las Mendozas",
    "gn:population":0,
    "gn:timezone":"America/Bogota",
    "iso:country":"CO",
    "name:und_x_variant":[
        "Hacienda Las Mendozas",
        "Las Mendosas",
        "Las Mendozas"
    ],
    "wof:name":"Las Mendozas",
    "wof:placetype":"locality"
},
  "geometry": {"coordinates":[-74.53333000000001,9.25],"type":"Point"}
}