{
  "type": "Feature",
  "properties": {
    "gn:admin1_code":"11",
    "gn:admin2_code":"27099.0",
    "gn:asciiname":"Antado",
    "gn:country_code":"CO",
    "gn:dem":221,
    "gn:feature_class":"P",
    "gn:feature_code":"PPL",
    "gn:name":"Antad\u00f3",
    "gn:population":0,
    "gn:timezone":"America/Bogota",
    "iso:country":"CO",
    "wof:name":"Antado",
    "wof:placetype":"locality"
},
  "geometry": {"coordinates":[-77.33333,6.68333],"type":"Point"}
}