{
  "type": "Feature",
  "properties": {
    "gn:admin1_code":"20.0",
    "gn:admin2_code":"52287.0",
    "gn:asciiname":"El Cajon",
    "gn:country_code":"CO",
    "gn:dem":2437,
    "gn:feature_class":"P",
    "gn:feature_code":"PPL",
    "gn:name":"El Caj\u00f3n",
    "gn:population":0,
    "gn:timezone":"America/Bogota",
    "iso:country":"CO",
    "wof:name":"El Cajon",
    "wof:placetype":"locality"
},
  "geometry": {"coordinates":[-77.40215000000001,1.02001],"type":"Point"}
}