{
  "type": "Feature",
  "properties": {
    "gn:admin1_code":"33.0",
    "gn:admin2_code":"25649.0",
    "gn:asciiname":"Portones",
    "gn:country_code":"CO",
    "gn:dem":1566,
    "gn:feature_class":"P",
    "gn:feature_code":"PPL",
    "gn:name":"Portones",
    "gn:population":0,
    "gn:timezone":"America/Bogota",
    "iso:country":"CO",
    "wof:name":"Portones",
    "wof:placetype":"locality"
},
  "geometry": {"coordinates":[-74.43977,4.21603],"type":"Point"}
}