{
  "type": "Feature",
  "properties": {
    "gn:admin1_code":"3",
    "gn:admin2_code":"81001.0",
    "gn:asciiname":"Cocuicitas",
    "gn:country_code":"CO",
    "gn:dem":117,
    "gn:feature_class":"P",
    "gn:feature_code":"PPL",
    "gn:name":"Cocuicitas",
    "gn:population":0,
    "gn:timezone":"America/Bogota",
    "iso:country":"CO",
    "name:und_x_variant":[
        "Cocuisitas",
        "Cocuicitas"
    ],
    "wof:name":"Cocuicitas",
    "wof:placetype":"locality"
},
  "geometry": {"coordinates":[-70.40379,6.84991],"type":"Point"}
}