{
  "type": "Feature",
  "properties": {
    "gn:admin1_code":"31.0",
    "gn:admin2_code":"99773.0",
    "gn:asciiname":"Sibo",
    "gn:country_code":"CO",
    "gn:dem":140,
    "gn:feature_class":"P",
    "gn:feature_code":"PPL",
    "gn:name":"Sibo",
    "gn:population":0,
    "gn:timezone":"America/Bogota",
    "iso:country":"CO",
    "name:ceb_x_preferred":[
        "Sibo"
    ],
    "name:ita_x_preferred":[
        "Sibo"
    ],
    "name:nld_x_preferred":[
        "Sibo"
    ],
    "name:nno_x_preferred":[
        "Sibo"
    ],
    "name:nor_x_preferred":[
        "Sibo"
    ],
    "name:swe_x_preferred":[
        "Sibo"
    ],
    "wof:name":"Sibo",
    "wof:placetype":"locality"
},
  "geometry": {"coordinates":[-69.60221999999999,4.42778],"type":"Point"}
}