{
  "type": "Feature",
  "properties": {
    "gn:admin1_code":"16.0",
    "gn:admin2_code":"41518.0",
    "gn:asciiname":"El Alto",
    "gn:country_code":"CO",
    "gn:dem":1537,
    "gn:feature_class":"P",
    "gn:feature_code":"PPL",
    "gn:name":"El Alto",
    "gn:population":0,
    "gn:timezone":"America/Bogota",
    "iso:country":"CO",
    "wof:name":"El Alto",
    "wof:placetype":"locality"
},
  "geometry": {"coordinates":[-75.79515000000001,2.40147],"type":"Point"}
}