{
  "type": "Feature",
  "properties": {
    "gn:admin1_code":"12",
    "gn:asciiname":"La Angostura",
    "gn:country_code":"CO",
    "gn:dem":37,
    "gn:feature_class":"P",
    "gn:feature_code":"PPL",
    "gn:name":"La Angostura",
    "gn:population":0,
    "gn:timezone":"America/Bogota",
    "iso:country":"CO",
    "name:ceb_x_preferred":[
        "La Angostura"
    ],
    "name:deu_x_preferred":[
        "La Angostura"
    ],
    "name:spa_x_preferred":[
        "La Angostura"
    ],
    "name:srp_x_preferred":[
        "\u041b\u0430 \u0410\u043d\u0433\u043e\u0441\u0442\u0443\u0440\u0430"
    ],
    "name:swe_x_preferred":[
        "La Angostura"
    ],
    "name:und_x_variant":[
        "Caser\u00edo La Angostura"
    ],
    "wof:name":"La Angostura",
    "wof:placetype":"locality"
},
  "geometry": {"coordinates":[-75.20318,8.7874],"type":"Point"}
}