{
  "type": "Feature",
  "properties": {
    "gn:admin1_code":"29",
    "gn:admin2_code":"76001.0",
    "gn:asciiname":"Cascajal",
    "gn:country_code":"CO",
    "gn:dem":977,
    "gn:feature_class":"P",
    "gn:feature_code":"PPL",
    "gn:name":"Cascajal",
    "gn:population":0,
    "gn:timezone":"America/Bogota",
    "iso:country":"CO",
    "name:spa_x_preferred":[
        "Caserio Cascajal"
    ],
    "wof:name":"Cascajal",
    "wof:placetype":"locality"
},
  "geometry": {"coordinates":[-76.51120999999998,3.31798],"type":"Point"}
}