{
  "type": "Feature",
  "properties": {
    "gn:admin1_code":"26",
    "gn:admin2_code":"68406.0",
    "gn:asciiname":"Palonegro",
    "gn:country_code":"CO",
    "gn:dem":1108,
    "gn:feature_class":"P",
    "gn:feature_code":"PPL",
    "gn:name":"Palonegro",
    "gn:population":0,
    "gn:timezone":"America/Bogota",
    "iso:country":"CO",
    "wof:name":"Palonegro",
    "wof:placetype":"locality"
},
  "geometry": {"coordinates":[-73.19864,7.11989],"type":"Point"}
}