{
  "type": "Feature",
  "properties": {
    "gn:admin1_code":"20",
    "gn:admin2_code":"52001.0",
    "gn:asciiname":"Cabrera",
    "gn:country_code":"CO",
    "gn:dem":2953,
    "gn:feature_class":"P",
    "gn:feature_code":"PPL",
    "gn:name":"Cabrera",
    "gn:population":0,
    "gn:timezone":"America/Bogota",
    "iso:country":"CO",
    "wof:name":"Cabrera",
    "wof:placetype":"locality"
},
  "geometry": {"coordinates":[-77.20499000000002,1.23507],"type":"Point"}
}