{
  "type": "Feature",
  "properties": {
    "gn:admin1_code":"29.0",
    "gn:admin2_code":"76828.0",
    "gn:asciiname":"Bochiquila",
    "gn:country_code":"CO",
    "gn:dem":1753,
    "gn:feature_class":"P",
    "gn:feature_code":"PPL",
    "gn:name":"Bochiquila",
    "gn:population":0,
    "gn:timezone":"America/Bogota",
    "iso:country":"CO",
    "wof:name":"Bochiquila",
    "wof:placetype":"locality"
},
  "geometry": {"coordinates":[-76.38459,4.24277],"type":"Point"}
}