{
  "type": "Feature",
  "properties": {
    "gn:admin1_code":"10.0",
    "gn:admin2_code":"20614.0",
    "gn:asciiname":"La Solana",
    "gn:country_code":"CO",
    "gn:dem":64,
    "gn:feature_class":"P",
    "gn:feature_code":"PPL",
    "gn:name":"La Solana",
    "gn:population":0,
    "gn:timezone":"America/Bogota",
    "iso:country":"CO",
    "name:spa_x_preferred":[
        "La Solana"
    ],
    "wof:name":"La Solana",
    "wof:placetype":"locality"
},
  "geometry": {"coordinates":[-73.63958000000002,8.1039],"type":"Point"}
}