{
  "type": "Feature",
  "properties": {
    "gn:admin1_code":"10.0",
    "gn:admin2_code":"20614.0",
    "gn:asciiname":"La Solana",
    "gn:country_code":"CO",
    "gn:dem":64,
    "gn:feature_class":"P",
    "gn:feature_code":"PPL",
    "gn:name":"La Solana",
    "gn:population":0,
    "gn:timezone":"America/Bogota",
    "iso:country":"CO",
    "name:ara_x_preferred":[
        "\u0644\u0627 \u0633\u0648\u0644\u0627\u0646\u0627"
    ],
    "name:arg_x_preferred":[
        "La Solana"
    ],
    "name:cat_x_preferred":[
        "La Solana"
    ],
    "name:ceb_x_preferred":[
        "La Solana"
    ],
    "name:epo_x_preferred":[
        "La Solana"
    ],
    "name:eus_x_preferred":[
        "La Solana"
    ],
    "name:fra_x_preferred":[
        "La Solana"
    ],
    "name:glg_x_preferred":[
        "La Solana"
    ],
    "name:hun_x_preferred":[
        "La Solana"
    ],
    "name:ita_x_preferred":[
        "La Solana"
    ],
    "name:kaz_x_preferred":[
        "\u041b\u0430-\u0421\u043e\u043b\u0430\u043d\u0430"
    ],
    "name:msa_x_preferred":[
        "La Solana"
    ],
    "name:nld_x_preferred":[
        "La Solana"
    ],
    "name:oci_x_preferred":[
        "La Solana"
    ],
    "name:pol_x_preferred":[
        "La Solana"
    ],
    "name:por_x_preferred":[
        "La Solana"
    ],
    "name:ron_x_preferred":[
        "La Solana"
    ],
    "name:rus_x_preferred":[
        "\u041b\u0430-\u0421\u043e\u043b\u0430\u043d\u0430"
    ],
    "name:spa_x_preferred":[
        "La Solana"
    ],
    "name:sqi_x_preferred":[
        "La Solana"
    ],
    "name:swe_x_preferred":[
        "La Solana"
    ],
    "name:ukr_x_preferred":[
        "\u041b\u0430-\u0421\u043e\u043b\u0430\u043d\u0430"
    ],
    "name:urd_x_preferred":[
        "\u0644\u0627 \u0633\u0648\u0644\u0627\u0646\u0627"
    ],
    "name:vie_x_preferred":[
        "La Solana"
    ],
    "name:war_x_preferred":[
        "La Solana"
    ],
    "name:zho_x_preferred":[
        "\u62c9\u7d22\u62c9\u7eb3"
    ],
    "wof:name":"La Solana",
    "wof:placetype":"locality"
},
  "geometry": {"coordinates":[-73.63958000000002,8.1039],"type":"Point"}
}