{
  "type": "Feature",
  "properties": {
    "gn:admin1_code":"26",
    "gn:admin2_code":"68377.0",
    "gn:asciiname":"La Primavera",
    "gn:country_code":"CO",
    "gn:dem":987,
    "gn:feature_class":"P",
    "gn:feature_code":"PPL",
    "gn:name":"La Primavera",
    "gn:population":0,
    "gn:timezone":"America/Bogota",
    "iso:country":"CO",
    "wof:name":"La Primavera",
    "wof:placetype":"locality"
},
  "geometry": {"coordinates":[-74.02819000000002,5.88026],"type":"Point"}
}