{
  "type": "Feature",
  "properties": {
    "gn:admin1_code":"19.0",
    "gn:admin2_code":"50330.0",
    "gn:asciiname":"Caserio Muriba",
    "gn:country_code":"CO",
    "gn:dem":516,
    "gn:feature_class":"P",
    "gn:feature_code":"PPL",
    "gn:name":"Caser\u00edo Muriba",
    "gn:population":0,
    "gn:timezone":"America/Bogota",
    "iso:country":"CO",
    "wof:name":"Caserio Muriba",
    "wof:placetype":"locality"
},
  "geometry": {"coordinates":[-74.23871,3.11808],"type":"Point"}
}