{
  "type": "Feature",
  "properties": {
    "gn:admin1_code":"33.0",
    "gn:admin2_code":"25181.0",
    "gn:asciiname":"Junia",
    "gn:country_code":"CO",
    "gn:dem":2478,
    "gn:feature_class":"P",
    "gn:feature_code":"PPL",
    "gn:name":"Junia",
    "gn:population":0,
    "gn:timezone":"America/Bogota",
    "iso:country":"CO",
    "name:pol_x_preferred":[
        "Junia"
    ],
    "name:spa_x_preferred":[
        "Junia"
    ],
    "wof:name":"Junia",
    "wof:placetype":"locality"
},
  "geometry": {"coordinates":[-73.92806,4.60833],"type":"Point"}
}