{
  "type": "Feature",
  "properties": {
    "gn:admin1_code":"12.0",
    "gn:admin2_code":"23001.0",
    "gn:asciiname":"Grecia",
    "gn:country_code":"CO",
    "gn:dem":28,
    "gn:feature_class":"P",
    "gn:feature_code":"PPLL",
    "gn:name":"Grecia",
    "gn:population":0,
    "gn:timezone":"America/Bogota",
    "iso:country":"CO",
    "name:ceb_x_preferred":[
        "Grecia"
    ],
    "name:deu_x_preferred":[
        "Grecia"
    ],
    "name:ita_x_preferred":[
        "Grecia"
    ],
    "name:nld_x_preferred":[
        "Grecia"
    ],
    "name:ron_x_preferred":[
        "Grecia"
    ],
    "name:spa_x_preferred":[
        "Grecia"
    ],
    "wof:name":"Grecia",
    "wof:placetype":"locality"
},
  "geometry": {"coordinates":[-75.84397,8.69943],"type":"Point"}
}