{
  "type": "Feature",
  "properties": {
    "gn:admin1_code":"8.0",
    "gn:admin2_code":"18001.0",
    "gn:asciiname":"Corregimiento de Corcasia",
    "gn:country_code":"CO",
    "gn:dem":861,
    "gn:feature_class":"P",
    "gn:feature_code":"PPL",
    "gn:name":"Corregimiento de Corcasia",
    "gn:population":0,
    "gn:timezone":"America/Bogota",
    "iso:country":"CO",
    "wof:name":"Corregimiento de Corcasia",
    "wof:placetype":"locality"
},
  "geometry": {"coordinates":[-75.44,1.74],"type":"Point"}
}