{
  "type": "Feature",
  "properties": {
    "gn:admin1_code":"12",
    "gn:admin2_code":"23574.0",
    "gn:asciiname":"Florida",
    "gn:country_code":"CO",
    "gn:dem":23,
    "gn:feature_class":"P",
    "gn:feature_code":"PPL",
    "gn:name":"Florida",
    "gn:population":0,
    "gn:timezone":"America/Bogota",
    "iso:country":"CO",
    "wof:name":"Florida",
    "wof:placetype":"locality"
},
  "geometry": {"coordinates":[-76.25,8.93333],"type":"Point"}
}