{
  "type": "Feature",
  "properties": {
    "gn:admin1_code":"8.0",
    "gn:admin2_code":"18001.0",
    "gn:asciiname":"Buenavista",
    "gn:country_code":"CO",
    "gn:dem":2300,
    "gn:feature_class":"P",
    "gn:feature_code":"PPL",
    "gn:name":"Buenavista",
    "gn:population":0,
    "gn:timezone":"America/Bogota",
    "iso:country":"CO",
    "wof:name":"Buenavista",
    "wof:placetype":"locality"
},
  "geometry": {"coordinates":[-75.54778,2.05556],"type":"Point"}
}