{
  "type": "Feature",
  "properties": {
    "gn:admin1_code":"29",
    "gn:admin2_code":"76520.0",
    "gn:asciiname":"La Andrada",
    "gn:country_code":"CO",
    "gn:dem":1251,
    "gn:feature_class":"P",
    "gn:feature_code":"PPL",
    "gn:name":"La Andrada",
    "gn:population":0,
    "gn:timezone":"America/Bogota",
    "iso:country":"CO",
    "wof:name":"La Andrada",
    "wof:placetype":"locality"
},
  "geometry": {"coordinates":[-76.20596999999999,3.51163],"type":"Point"}
}