{
  "type": "Feature",
  "properties": {
    "gn:admin1_code":"2.0",
    "gn:admin2_code":"5658.0",
    "gn:asciiname":"Cambure",
    "gn:country_code":"CO",
    "gn:dem":2439,
    "gn:feature_class":"P",
    "gn:feature_code":"PPL",
    "gn:name":"Cambur\u00e9",
    "gn:population":0,
    "gn:timezone":"America/Bogota",
    "iso:country":"CO",
    "wof:name":"Cambure",
    "wof:placetype":"locality"
},
  "geometry": {"coordinates":[-75.67166999999998,6.87611],"type":"Point"}
}