{
  "type": "Feature",
  "properties": {
    "gn:admin1_code":"37.0",
    "gn:admin2_code":"17614.0",
    "gn:asciiname":"La Caucana",
    "gn:country_code":"CO",
    "gn:dem":2593,
    "gn:feature_class":"P",
    "gn:feature_code":"PPL",
    "gn:name":"La Caucana",
    "gn:population":0,
    "gn:timezone":"America/Bogota",
    "iso:country":"CO",
    "wof:name":"La Caucana",
    "wof:placetype":"locality"
},
  "geometry": {"coordinates":[-75.80214000000002,5.47253],"type":"Point"}
}