{
  "type": "Feature",
  "properties": {
    "gn:admin1_code":"20",
    "gn:admin2_code":"52835.0",
    "gn:asciiname":"Albania",
    "gn:country_code":"CO",
    "gn:dem":13,
    "gn:feature_class":"P",
    "gn:feature_code":"PPL",
    "gn:name":"Albania",
    "gn:population":0,
    "gn:timezone":"America/Bogota",
    "iso:country":"CO",
    "wof:name":"Albania",
    "wof:placetype":"locality"
},
  "geometry": {"coordinates":[-78.76416999999999,1.67528],"type":"Point"}
}