{
  "type": "Feature",
  "properties": {
    "gn:admin1_code":"2.0",
    "gn:admin2_code":"5001.0",
    "gn:asciiname":"Vereda Sector Playas",
    "gn:country_code":"CO",
    "gn:dem":2035,
    "gn:feature_class":"P",
    "gn:feature_code":"PPLL",
    "gn:name":"Vereda Sector Playas",
    "gn:population":0,
    "gn:timezone":"America/Bogota",
    "iso:country":"CO",
    "name:spa_x_preferred":[
        "Vereda Sector Playas"
    ],
    "wof:name":"Vereda Sector Playas",
    "wof:placetype":"locality"
},
  "geometry": {"coordinates":[-75.65509,6.28853],"type":"Point"}
}