{
  "type": "Feature",
  "properties": {
    "gn:admin1_code":"21",
    "gn:admin2_code":"54001.0",
    "gn:asciiname":"Barlovento",
    "gn:country_code":"CO",
    "gn:dem":85,
    "gn:feature_class":"P",
    "gn:feature_code":"PPL",
    "gn:name":"Barlovento",
    "gn:population":0,
    "gn:timezone":"America/Bogota",
    "iso:country":"CO",
    "name:ast_x_preferred":[
        "Barloventu"
    ],
    "name:ceb_x_preferred":[
        "Barlovento"
    ],
    "name:deu_x_preferred":[
        "Barlovento"
    ],
    "name:eus_x_preferred":[
        "Barlovento"
    ],
    "name:glg_x_preferred":[
        "Barlovento"
    ],
    "name:nld_x_preferred":[
        "Barlovento"
    ],
    "name:spa_x_preferred":[
        "Barlovento"
    ],
    "name:swe_x_preferred":[
        "Barlovento"
    ],
    "wof:name":"Barlovento",
    "wof:placetype":"locality"
},
  "geometry": {"coordinates":[-72.39444,8.16611],"type":"Point"}
}