{
  "type": "Feature",
  "properties": {
    "gn:admin1_code":"38",
    "gn:admin2_code":"47707.0",
    "gn:asciiname":"La Tolua",
    "gn:country_code":"CO",
    "gn:dem":70,
    "gn:feature_class":"P",
    "gn:feature_code":"PPL",
    "gn:name":"La Tol\u00faa",
    "gn:population":0,
    "gn:timezone":"America/Bogota",
    "iso:country":"CO",
    "name:und_x_variant":[
        "Hacienda La Tol\u00faa",
        "La Tol\u00faa"
    ],
    "wof:name":"La Tolua",
    "wof:placetype":"locality"
},
  "geometry": {"coordinates":[-74.40302,9.57611],"type":"Point"}
}