{
  "type": "Feature",
  "properties": {
    "gn:admin1_code":"10",
    "gn:admin2_code":"20770.0",
    "gn:asciiname":"Icotea",
    "gn:country_code":"CO",
    "gn:dem":156,
    "gn:feature_class":"P",
    "gn:feature_code":"PPL",
    "gn:name":"Icotea",
    "gn:population":0,
    "gn:timezone":"America/Bogota",
    "iso:country":"CO",
    "wof:name":"Icotea",
    "wof:placetype":"locality"
},
  "geometry": {"coordinates":[-73.48806,8.05972],"type":"Point"}
}