{
  "type": "Feature",
  "properties": {
    "gn:admin1_code":"17.0",
    "gn:admin2_code":"44847.0",
    "gn:asciiname":"Ranchogrande",
    "gn:country_code":"CO",
    "gn:dem":35,
    "gn:feature_class":"P",
    "gn:feature_code":"PPL",
    "gn:name":"Ranchogrande",
    "gn:population":0,
    "gn:timezone":"America/Bogota",
    "iso:country":"CO",
    "wof:name":"Ranchogrande",
    "wof:placetype":"locality"
},
  "geometry": {"coordinates":[-71.82944000000001,11.69278],"type":"Point"}
}