{
  "type": "Feature",
  "properties": {
    "gn:admin1_code":"29",
    "gn:admin2_code":"76869.0",
    "gn:asciiname":"La Fresneda",
    "gn:cc2":"CO",
    "gn:country_code":"CO",
    "gn:dem":1407,
    "gn:feature_class":"P",
    "gn:feature_code":"PPL",
    "gn:name":"La Fresneda",
    "gn:population":0,
    "gn:timezone":"America/Bogota",
    "iso:country":"CO",
    "name:und_x_variant":[
        "Fresneda",
        "La Fresneda"
    ],
    "wof:name":"La Fresneda",
    "wof:placetype":"locality"
},
  "geometry": {"coordinates":[-76.47499999999999,3.75889],"type":"Point"}
}