{
  "type": "Feature",
  "properties": {
    "gn:admin1_code":"29",
    "gn:admin2_code":"76869.0",
    "gn:asciiname":"La Fresneda",
    "gn:cc2":"CO",
    "gn:country_code":"CO",
    "gn:dem":1407,
    "gn:feature_class":"P",
    "gn:feature_code":"PPL",
    "gn:name":"La Fresneda",
    "gn:population":0,
    "gn:timezone":"America/Bogota",
    "iso:country":"CO",
    "name:arg_x_preferred":[
        "La Fraixneda"
    ],
    "name:azb_x_preferred":[
        "\u0644\u0627 \u0641\u0631\u0633\u0646\u062f\u0627"
    ],
    "name:cat_x_preferred":[
        "La Freixneda"
    ],
    "name:ceb_x_preferred":[
        "La Fresneda"
    ],
    "name:deu_x_preferred":[
        "La Fresneda"
    ],
    "name:eus_x_preferred":[
        "La Fresneda"
    ],
    "name:fas_x_preferred":[
        "\u0644\u0627 \u0641\u0631\u0633\u0646\u062f\u0627"
    ],
    "name:fra_x_preferred":[
        "La Fresneda"
    ],
    "name:hun_x_preferred":[
        "La Fresneda"
    ],
    "name:ita_x_preferred":[
        "La Fresneda"
    ],
    "name:kaz_x_preferred":[
        "\u041b\u0430-\u0424\u0440\u0435\u0441\u043d\u0435\u0434\u0430"
    ],
    "name:msa_x_preferred":[
        "La Fresneda"
    ],
    "name:nld_x_preferred":[
        "La Fresneda"
    ],
    "name:oci_x_preferred":[
        "La Freixneda"
    ],
    "name:pol_x_preferred":[
        "La Fresneda"
    ],
    "name:por_x_preferred":[
        "La Fresneda"
    ],
    "name:rus_x_preferred":[
        "\u041b\u0430-\u0424\u0440\u0435\u0441\u043d\u0435\u0434\u0430"
    ],
    "name:spa_x_preferred":[
        "La Fresneda"
    ],
    "name:swe_x_preferred":[
        "La Fresneda"
    ],
    "name:ukr_x_preferred":[
        "\u041b\u0430-\u0424\u0440\u0435\u0441\u043d\u0435\u0434\u0430"
    ],
    "name:und_x_variant":[
        "Fresneda"
    ],
    "name:urd_x_preferred":[
        "\u0644\u0627 \u0641\u0631\u06cc\u0633\u0646\u06cc\u0688\u0627"
    ],
    "name:uzb_x_preferred":[
        "La Fresneda"
    ],
    "name:vie_x_preferred":[
        "La Fresneda"
    ],
    "name:war_x_preferred":[
        "La Fresneda"
    ],
    "name:zho_x_preferred":[
        "\u62c9\u5f17\u96f7\u65af\u5185\u8fbe"
    ],
    "wof:name":"La Fresneda",
    "wof:placetype":"locality"
},
  "geometry": {"coordinates":[-76.47499999999999,3.75889],"type":"Point"}
}