{
  "type": "Feature",
  "properties": {
    "gn:admin1_code":"38.0",
    "gn:admin2_code":"47258.0",
    "gn:asciiname":"Monteria",
    "gn:country_code":"CO",
    "gn:dem":29,
    "gn:feature_class":"P",
    "gn:feature_code":"PPL",
    "gn:name":"Monter\u00eda",
    "gn:population":0,
    "gn:timezone":"America/Bogota",
    "iso:country":"CO",
    "name:und_x_variant":[
        "Hacienda Monter\u00eda",
        "Monter\u00eda"
    ],
    "wof:name":"Monteria",
    "wof:placetype":"locality"
},
  "geometry": {"coordinates":[-74.63786999999998,10.25662],"type":"Point"}
}