{
  "type": "Feature",
  "properties": {
    "gn:admin1_code":"33",
    "gn:admin2_code":"25899.0",
    "gn:asciiname":"Campina",
    "gn:country_code":"CO",
    "gn:dem":2557,
    "gn:feature_class":"P",
    "gn:feature_code":"PPL",
    "gn:name":"Campi\u00f1a",
    "gn:population":0,
    "gn:timezone":"America/Bogota",
    "iso:country":"CO",
    "name:ceb_x_preferred":[
        "Campina"
    ],
    "name:deu_x_preferred":[
        "Campina"
    ],
    "name:fra_x_preferred":[
        "Campina"
    ],
    "name:ita_x_preferred":[
        "Campina"
    ],
    "name:nld_x_preferred":[
        "Campina"
    ],
    "name:por_x_preferred":[
        "Campina"
    ],
    "name:swe_x_preferred":[
        "Campina"
    ],
    "wof:name":"Campina",
    "wof:placetype":"locality"
},
  "geometry": {"coordinates":[-73.95,5.03333],"type":"Point"}
}