{
  "type": "Feature",
  "properties": {
    "gn:admin1_code":"35",
    "gn:asciiname":"Colorado",
    "gn:country_code":"CO",
    "gn:dem":4,
    "gn:feature_class":"P",
    "gn:feature_code":"PPL",
    "gn:name":"Colorado",
    "gn:population":0,
    "gn:timezone":"America/Bogota",
    "iso:country":"CO",
    "wof:name":"Colorado",
    "wof:placetype":"locality"
},
  "geometry": {"coordinates":[-75.25072,10.67512],"type":"Point"}
}