{
  "type": "Feature",
  "properties": {
    "gn:admin1_code":"29",
    "gn:admin2_code":"76248.0",
    "gn:asciiname":"Santa Rita",
    "gn:country_code":"CO",
    "gn:dem":978,
    "gn:feature_class":"P",
    "gn:feature_code":"PPL",
    "gn:name":"Santa Rita",
    "gn:population":0,
    "gn:timezone":"America/Bogota",
    "iso:country":"CO",
    "name:ara_x_preferred":[
        "\u0633\u0627\u0646\u062a\u0627 \u0631\u064a\u062a\u0627"
    ],
    "name:ben_x_preferred":[
        "\u09b8\u09be\u09a8\u09cd\u09a4\u09be \u09b0\u09bf\u09a4\u09be"
    ],
    "name:bul_x_preferred":[
        "\u0421\u0430\u043d\u0442\u0430 \u0420\u0438\u0442\u0430"
    ],
    "name:ceb_x_preferred":[
        "Santa Rita"
    ],
    "name:deu_x_preferred":[
        "Santa Rita"
    ],
    "name:ell_x_preferred":[
        "\u03a3\u03ac\u03bd\u03c4\u03b1 \u03a1\u03af\u03c4\u03b1"
    ],
    "name:fas_x_preferred":[
        "\u0633\u0627\u0646\u062a\u0627 \u0631\u06cc\u062a\u0627"
    ],
    "name:fra_x_preferred":[
        "Santa Rita"
    ],
    "name:heb_x_preferred":[
        "\u05e1\u05e0\u05d8\u05d4 \u05e8\u05d9\u05d8\u05d4"
    ],
    "name:hin_x_preferred":[
        "\u0938\u0948\u0902\u091f\u093e \u0930\u0940\u0924\u093e"
    ],
    "name:hun_x_preferred":[
        "Santa Rita"
    ],
    "name:ilo_x_preferred":[
        "Santa Rita"
    ],
    "name:ind_x_preferred":[
        "Santa Rita"
    ],
    "name:ita_x_preferred":[
        "Santa Rita"
    ],
    "name:jpn_x_preferred":[
        "\u30b5\u30f3\u30bf\u30ea\u30bf"
    ],
    "name:kat_x_preferred":[
        "\u10e1\u10d0\u10dc\u10e2\u10d0-\u10e0\u10d8\u10e2\u10d0"
    ],
    "name:kor_x_preferred":[
        "\uc0b0\ud0c0 \ub9ac\ud0c0"
    ],
    "name:lit_x_preferred":[
        "Santa Rita"
    ],
    "name:mlg_x_preferred":[
        "Santa Rita"
    ],
    "name:nds_x_preferred":[
        "Santa Rita"
    ],
    "name:nld_x_preferred":[
        "Santa Rita"
    ],
    "name:nor_x_preferred":[
        "Santa Rita"
    ],
    "name:pol_x_preferred":[
        "Santa Rita"
    ],
    "name:por_x_preferred":[
        "Santa Rita"
    ],
    "name:ron_x_preferred":[
        "Santa Rita"
    ],
    "name:rus_x_preferred":[
        "\u0421\u0430\u043d\u0442\u0430-\u0420\u0438\u0442\u0430"
    ],
    "name:sco_x_preferred":[
        "Santa Rita"
    ],
    "name:spa_x_preferred":[
        "Santa Rita"
    ],
    "name:srp_x_preferred":[
        "\u0421\u0430\u043d\u0442\u0430 \u0420\u0438\u0442\u0430"
    ],
    "name:swe_x_preferred":[
        "Santa Rita"
    ],
    "name:tur_x_preferred":[
        "Santa Rita"
    ],
    "name:ukr_x_preferred":[
        "\u0421\u0430\u043d\u0442\u0430-\u0420\u0456\u0442\u0430"
    ],
    "name:urd_x_preferred":[
        "\u0633\u06cc\u0646\u0679\u0627 \u0631\u06cc\u0679\u0627"
    ],
    "name:vie_x_preferred":[
        "Santa Rita"
    ],
    "name:vol_x_preferred":[
        "Santa Rita"
    ],
    "name:war_x_preferred":[
        "Santa Rita"
    ],
    "wof:name":"Santa Rita",
    "wof:placetype":"locality"
},
  "geometry": {"coordinates":[-76.35056,3.66472],"type":"Point"}
}