{
  "type": "Feature",
  "properties": {
    "gn:admin1_code":"29",
    "gn:admin2_code":"76520.0",
    "gn:asciiname":"Villa Yolanda",
    "gn:country_code":"CO",
    "gn:dem":1129,
    "gn:feature_class":"P",
    "gn:feature_code":"PPL",
    "gn:name":"Villa Yolanda",
    "gn:population":0,
    "gn:timezone":"America/Bogota",
    "iso:country":"CO",
    "wof:name":"Villa Yolanda",
    "wof:placetype":"locality"
},
  "geometry": {"coordinates":[-76.205,3.61111],"type":"Point"}
}