{
  "type": "Feature",
  "properties": {
    "gn:admin1_code":"8.0",
    "gn:admin2_code":"18479.0",
    "gn:asciiname":"Argentina",
    "gn:country_code":"CO",
    "gn:dem":363,
    "gn:feature_class":"P",
    "gn:feature_code":"PPL",
    "gn:name":"Argentina",
    "gn:population":0,
    "gn:timezone":"America/Bogota",
    "iso:country":"CO",
    "name:spa_x_preferred":[
        "Argentina"
    ],
    "wof:name":"Argentina",
    "wof:placetype":"locality"
},
  "geometry": {"coordinates":[-75.74109,1.52225],"type":"Point"}
}