{
  "type": "Feature",
  "properties": {
    "gn:admin1_code":"2.0",
    "gn:admin2_code":"5001.0",
    "gn:asciiname":"La Primavera",
    "gn:country_code":"CO",
    "gn:dem":1599,
    "gn:feature_class":"P",
    "gn:feature_code":"PPL",
    "gn:name":"La Primavera",
    "gn:population":0,
    "gn:timezone":"America/Bogota",
    "iso:country":"CO",
    "name:spa_x_preferred":[
        "La Primavera"
    ],
    "wof:name":"La Primavera",
    "wof:placetype":"locality"
},
  "geometry": {"coordinates":[-75.70520999999999,6.34446],"type":"Point"}
}