{
  "type": "Feature",
  "properties": {
    "gn:admin1_code":"12",
    "gn:admin2_code":"23001.0",
    "gn:asciiname":"Indiano",
    "gn:cc2":"CO",
    "gn:country_code":"CO",
    "gn:dem":85,
    "gn:feature_class":"P",
    "gn:feature_code":"PPL",
    "gn:name":"Indiano",
    "gn:population":0,
    "gn:timezone":"America/Bogota",
    "iso:country":"CO",
    "name:und_x_variant":[
        "Indiana",
        "Indiano"
    ],
    "wof:name":"Indiano",
    "wof:placetype":"locality"
},
  "geometry": {"coordinates":[-76.11667,8.65],"type":"Point"}
}