{
  "type": "Feature",
  "properties": {
    "gn:admin1_code":"16.0",
    "gn:admin2_code":"41013.0",
    "gn:asciiname":"San Pacilo",
    "gn:country_code":"CO",
    "gn:dem":746,
    "gn:feature_class":"P",
    "gn:feature_code":"PPL",
    "gn:name":"San Pacilo",
    "gn:population":0,
    "gn:timezone":"America/Bogota",
    "iso:country":"CO",
    "wof:name":"San Pacilo",
    "wof:placetype":"locality"
},
  "geometry": {"coordinates":[-75.67884000000002,2.29349],"type":"Point"}
}