{
  "type": "Feature",
  "properties": {
    "gn:admin1_code":"12.0",
    "gn:admin2_code":"23001.0",
    "gn:asciiname":"Canomocho",
    "gn:country_code":"CO",
    "gn:dem":47,
    "gn:feature_class":"P",
    "gn:feature_code":"PPLL",
    "gn:name":"Ca\u00f1omocho",
    "gn:population":0,
    "gn:timezone":"America/Bogota",
    "iso:country":"CO",
    "wof:name":"Canomocho",
    "wof:placetype":"locality"
},
  "geometry": {"coordinates":[-75.76425,8.60464],"type":"Point"}
}