{
  "type": "Feature",
  "properties": {
    "gn:admin1_code":"20",
    "gn:admin2_code":"52835.0",
    "gn:asciiname":"La Sirena",
    "gn:country_code":"CO",
    "gn:dem":21,
    "gn:feature_class":"P",
    "gn:feature_code":"PPL",
    "gn:name":"La Sirena",
    "gn:population":0,
    "gn:timezone":"America/Bogota",
    "iso:country":"CO",
    "name:und_x_variant":[
        "Sirena",
        "Las Sirenas",
        "La Sirena"
    ],
    "wof:name":"La Sirena",
    "wof:placetype":"locality"
},
  "geometry": {"coordinates":[-78.48521,1.73125],"type":"Point"}
}