{
  "type": "Feature",
  "properties": {
    "gn:admin1_code":"38",
    "gn:admin2_code":"47245.0",
    "gn:asciiname":"Algarrobal",
    "gn:country_code":"CO",
    "gn:dem":29,
    "gn:feature_class":"P",
    "gn:feature_code":"PPL",
    "gn:name":"Algarrobal",
    "gn:population":0,
    "gn:timezone":"America/Bogota",
    "iso:country":"CO",
    "name:und_x_variant":[
        "Corregimiento Algarrobal",
        "Algarrobal"
    ],
    "wof:name":"Algarrobal",
    "wof:placetype":"locality"
},
  "geometry": {"coordinates":[-74.04476,9.12953],"type":"Point"}
}