{
  "type": "Feature",
  "properties": {
    "gn:admin1_code":"3.0",
    "gn:admin2_code":"81065.0",
    "gn:asciiname":"Caserio Los Colonos",
    "gn:country_code":"CO",
    "gn:dem":149,
    "gn:feature_class":"P",
    "gn:feature_code":"PPL",
    "gn:name":"Caser\u00edo Los Colonos",
    "gn:population":0,
    "gn:timezone":"America/Bogota",
    "iso:country":"CO",
    "wof:name":"Caserio Los Colonos",
    "wof:placetype":"locality"
},
  "geometry": {"coordinates":[-71.28889000000002,6.82806],"type":"Point"}
}