{
  "type": "Feature",
  "properties": {
    "gn:admin1_code":"28",
    "gn:admin2_code":"73124.0",
    "gn:asciiname":"La Paloma",
    "gn:country_code":"CO",
    "gn:dem":2848,
    "gn:feature_class":"P",
    "gn:feature_code":"PPL",
    "gn:name":"La Paloma",
    "gn:population":0,
    "gn:timezone":"America/Bogota",
    "iso:country":"CO",
    "wof:name":"La Paloma",
    "wof:placetype":"locality"
},
  "geometry": {"coordinates":[-75.51666999999998,4.45],"type":"Point"}
}