{
  "type": "Feature",
  "properties": {
    "gn:admin1_code":"38",
    "gn:admin2_code":"47030.0",
    "gn:asciiname":"Cartagena",
    "gn:country_code":"CO",
    "gn:dem":112,
    "gn:feature_class":"P",
    "gn:feature_code":"PPL",
    "gn:name":"Cartagena",
    "gn:population":0,
    "gn:timezone":"America/Bogota",
    "iso:country":"CO",
    "name:und_x_variant":[
        "Hacienda Carlagena",
        "Cartagena"
    ],
    "wof:name":"Cartagena",
    "wof:placetype":"locality"
},
  "geometry": {"coordinates":[-74.13337,10.33482],"type":"Point"}
}