{
  "type": "Feature",
  "properties": {
    "gn:admin1_code":"29",
    "gn:admin2_code":"76111.0",
    "gn:asciiname":"La Tribuna",
    "gn:country_code":"CO",
    "gn:dem":2699,
    "gn:feature_class":"P",
    "gn:feature_code":"PPL",
    "gn:name":"La Tribuna",
    "gn:population":0,
    "gn:timezone":"America/Bogota",
    "iso:country":"CO",
    "name:spa_x_preferred":[
        "La Tribuna"
    ],
    "wof:name":"La Tribuna",
    "wof:placetype":"locality"
},
  "geometry": {"coordinates":[-75.95694,3.88583],"type":"Point"}
}