{
  "type": "Feature",
  "properties": {
    "gn:admin1_code":"14",
    "gn:admin2_code":"95200.0",
    "gn:asciiname":"Las Brisas",
    "gn:country_code":"CO",
    "gn:dem":209,
    "gn:feature_class":"P",
    "gn:feature_code":"PPL",
    "gn:name":"Las Brisas",
    "gn:population":0,
    "gn:timezone":"America/Bogota",
    "iso:country":"CO",
    "wof:name":"Las Brisas",
    "wof:placetype":"locality"
},
  "geometry": {"coordinates":[-72.27788000000002,1.40493],"type":"Point"}
}