{
  "type": "Feature",
  "properties": {
    "gn:admin1_code":"20.0",
    "gn:admin2_code":"52215.0",
    "gn:asciiname":"Caserio Muesmueran",
    "gn:country_code":"CO",
    "gn:dem":2912,
    "gn:feature_class":"P",
    "gn:feature_code":"PPL",
    "gn:name":"Caser\u00edo Muesmueran",
    "gn:population":0,
    "gn:timezone":"America/Bogota",
    "iso:country":"CO",
    "wof:name":"Caserio Muesmueran",
    "wof:placetype":"locality"
},
  "geometry": {"coordinates":[-77.53591999999998,0.84688],"type":"Point"}
}