{
  "type": "Feature",
  "properties": {
    "gn:admin1_code":"3",
    "gn:admin2_code":"81001.0",
    "gn:asciiname":"La Dalia",
    "gn:country_code":"CO",
    "gn:dem":126,
    "gn:feature_class":"P",
    "gn:feature_code":"PPL",
    "gn:name":"La Dalia",
    "gn:population":0,
    "gn:timezone":"America/Bogota",
    "iso:country":"CO",
    "name:spa_x_preferred":[
        "La Dalia"
    ],
    "wof:name":"La Dalia",
    "wof:placetype":"locality"
},
  "geometry": {"coordinates":[-70.98812,6.72241],"type":"Point"}
}