{
  "type": "Feature",
  "properties": {
    "gn:admin1_code":"17",
    "gn:admin2_code":"44430.0",
    "gn:asciiname":"Cano Seco",
    "gn:country_code":"CO",
    "gn:dem":114,
    "gn:feature_class":"P",
    "gn:feature_code":"PPL",
    "gn:name":"Ca\u00f1o Seco",
    "gn:population":0,
    "gn:timezone":"America/Bogota",
    "iso:country":"CO",
    "wof:name":"Cano Seco",
    "wof:placetype":"locality"
},
  "geometry": {"coordinates":[-72.32068000000002,11.22071],"type":"Point"}
}