{
  "type": "Feature",
  "properties": {
    "gn:admin1_code":"9",
    "gn:admin2_code":"19418.0",
    "gn:asciiname":"La Ensenada",
    "gn:country_code":"CO",
    "gn:dem":19,
    "gn:feature_class":"P",
    "gn:feature_code":"PPL",
    "gn:name":"La Ensenada",
    "gn:population":0,
    "gn:timezone":"America/Bogota",
    "iso:country":"CO",
    "wof:name":"La Ensenada",
    "wof:placetype":"locality"
},
  "geometry": {"coordinates":[-77.42954,3.01098],"type":"Point"}
}