{
  "type": "Feature",
  "properties": {
    "gn:admin1_code":"28",
    "gn:admin2_code":"73622.0",
    "gn:asciiname":"Japon",
    "gn:country_code":"CO",
    "gn:dem":3231,
    "gn:feature_class":"P",
    "gn:feature_code":"PPL",
    "gn:name":"Jap\u00f3n",
    "gn:population":0,
    "gn:timezone":"America/Bogota",
    "iso:country":"CO",
    "wof:name":"Japon",
    "wof:placetype":"locality"
},
  "geometry": {"coordinates":[-75.61435,4.18617],"type":"Point"}
}