{
  "type": "Feature",
  "properties": {
    "gn:admin1_code":"19.0",
    "gn:admin2_code":"50689.0",
    "gn:asciiname":"Paco",
    "gn:country_code":"CO",
    "gn:dem":241,
    "gn:feature_class":"P",
    "gn:feature_code":"PPLL",
    "gn:name":"Paco",
    "gn:population":0,
    "gn:timezone":"America/Bogota",
    "iso:country":"CO",
    "name:ita_x_preferred":[
        "Paco"
    ],
    "name:spa_x_preferred":[
        "Paco"
    ],
    "wof:name":"Paco",
    "wof:placetype":"locality"
},
  "geometry": {"coordinates":[-73.32896,3.66764],"type":"Point"}
}