{
  "type": "Feature",
  "properties": {
    "gn:admin1_code":"38",
    "gn:admin2_code":"47460.0",
    "gn:asciiname":"Lo Voran",
    "gn:country_code":"CO",
    "gn:dem":100,
    "gn:feature_class":"P",
    "gn:feature_code":"PPL",
    "gn:name":"Lo Vor\u00e1n",
    "gn:population":0,
    "gn:timezone":"America/Bogota",
    "iso:country":"CO",
    "name:und_x_variant":[
        "Hacienda Lo Vor\u00e1n",
        "Lo Vor\u00e1n"
    ],
    "wof:name":"Lo Voran",
    "wof:placetype":"locality"
},
  "geometry": {"coordinates":[-74.36405000000001,9.75908],"type":"Point"}
}