{
  "type": "Feature",
  "properties": {
    "gn:admin1_code":"35",
    "gn:admin2_code":"13838.0",
    "gn:asciiname":"Ballestas",
    "gn:country_code":"CO",
    "gn:dem":28,
    "gn:feature_class":"P",
    "gn:feature_code":"PPL",
    "gn:name":"Ballestas",
    "gn:population":0,
    "gn:timezone":"America/Bogota",
    "iso:country":"CO",
    "name:und_x_variant":[
        "Corregimiento Balletas",
        "Balestas",
        "Ballestas"
    ],
    "wof:name":"Ballestas",
    "wof:placetype":"locality"
},
  "geometry": {"coordinates":[-75.43859999999999,10.2161],"type":"Point"}
}