{
  "type": "Feature",
  "properties": {
    "gn:admin1_code":"9.0",
    "gn:admin2_code":"19300.0",
    "gn:asciiname":"Hacienda Dorita",
    "gn:country_code":"CO",
    "gn:dem":984,
    "gn:feature_class":"P",
    "gn:feature_code":"PPL",
    "gn:name":"Hacienda Dorita",
    "gn:population":0,
    "gn:timezone":"America/Bogota",
    "iso:country":"CO",
    "name:spa_x_preferred":[
        "Hacienda Dorita"
    ],
    "wof:name":"Hacienda Dorita",
    "wof:placetype":"locality"
},
  "geometry": {"coordinates":[-76.35961999999998,3.17597],"type":"Point"}
}