{
  "type": "Feature",
  "properties": {
    "gn:admin1_code":"19",
    "gn:admin2_code":"50318",
    "gn:asciiname":"Berlin",
    "gn:country_code":"CO",
    "gn:dem":500,
    "gn:feature_class":"P",
    "gn:feature_code":"PPL",
    "gn:name":"Berlin",
    "gn:population":0,
    "gn:timezone":"America/Bogota",
    "iso:country":"CO",
    "name:spa_x_preferred":[
        "Berlin"
    ],
    "wof:name":"Berlin",
    "wof:placetype":"locality"
},
  "geometry": {"coordinates":[-73.76697,3.85378],"type":"Point"}
}