{
  "type": "Feature",
  "properties": {
    "gn:admin1_code":"16.0",
    "gn:admin2_code":"41298.0",
    "gn:asciiname":"Santa Ines",
    "gn:country_code":"CO",
    "gn:dem":1482,
    "gn:feature_class":"P",
    "gn:feature_code":"PPL",
    "gn:name":"Santa In\u00e9s",
    "gn:population":0,
    "gn:timezone":"America/Bogota",
    "iso:country":"CO",
    "wof:name":"Santa Ines",
    "wof:placetype":"locality"
},
  "geometry": {"coordinates":[-75.57937,2.1737],"type":"Point"}
}