{
  "type": "Feature",
  "properties": {
    "gn:admin1_code":"9.0",
    "gn:admin2_code":"19513.0",
    "gn:asciiname":"Yarumales",
    "gn:country_code":"CO",
    "gn:dem":981,
    "gn:feature_class":"P",
    "gn:feature_code":"PPL",
    "gn:name":"Yarumales",
    "gn:population":0,
    "gn:timezone":"America/Bogota",
    "iso:country":"CO",
    "wof:name":"Yarumales",
    "wof:placetype":"locality"
},
  "geometry": {"coordinates":[-76.35812,3.21853],"type":"Point"}
}