{
  "type": "Feature",
  "properties": {
    "gn:admin1_code":"31",
    "gn:admin2_code":"99001.0",
    "gn:asciiname":"Casuarito",
    "gn:country_code":"CO",
    "gn:dem":57,
    "gn:feature_class":"P",
    "gn:feature_code":"PPL",
    "gn:name":"Casuarito",
    "gn:population":0,
    "gn:timezone":"America/Bogota",
    "iso:country":"CO",
    "name:spa_x_preferred":[
        "Casuarito"
    ],
    "wof:name":"Casuarito",
    "wof:placetype":"locality"
},
  "geometry": {"coordinates":[-67.64083000000001,5.68194],"type":"Point"}
}