{
  "type": "Feature",
  "properties": {
    "gn:admin1_code":"12.0",
    "gn:admin2_code":"23001.0",
    "gn:asciiname":"El Congo",
    "gn:country_code":"CO",
    "gn:dem":75,
    "gn:feature_class":"P",
    "gn:feature_code":"PPLL",
    "gn:name":"El Congo",
    "gn:population":0,
    "gn:timezone":"America/Bogota",
    "iso:country":"CO",
    "name:ceb_x_preferred":[
        "El Congo"
    ],
    "name:ita_x_preferred":[
        "El Congo"
    ],
    "name:por_x_preferred":[
        "El Congo"
    ],
    "name:spa_x_preferred":[
        "El Congo"
    ],
    "name:zho_x_preferred":[
        "\u57c3\u723e\u5b54\u6208"
    ],
    "wof:name":"El Congo",
    "wof:placetype":"locality"
},
  "geometry": {"coordinates":[-75.88608000000001,8.55955],"type":"Point"}
}