{
  "type": "Feature",
  "properties": {
    "gn:admin1_code":"16",
    "gn:admin2_code":"41016.0",
    "gn:asciiname":"Vega del Muerto",
    "gn:country_code":"CO",
    "gn:dem":362,
    "gn:feature_class":"P",
    "gn:feature_code":"PPL",
    "gn:name":"Vega del Muerto",
    "gn:population":0,
    "gn:timezone":"America/Bogota",
    "iso:country":"CO",
    "wof:name":"Vega del Muerto",
    "wof:placetype":"locality"
},
  "geometry": {"coordinates":[-75.24361,3.29944],"type":"Point"}
}