{
  "type": "Feature",
  "properties": {
    "gn:admin1_code":"36",
    "gn:admin2_code":"15332.0",
    "gn:asciiname":"Bachira",
    "gn:country_code":"CO",
    "gn:dem":1894,
    "gn:feature_class":"P",
    "gn:feature_code":"PPL",
    "gn:name":"B\u00e1chira",
    "gn:population":0,
    "gn:timezone":"America/Bogota",
    "iso:country":"CO",
    "name:spa_x_preferred":[
        "B\u00e1chira"
    ],
    "wof:name":"Bachira",
    "wof:placetype":"locality"
},
  "geometry": {"coordinates":[-72.18703000000002,6.70008],"type":"Point"}
}