{
  "type": "Feature",
  "properties": {
    "gn:admin1_code":"26",
    "gn:admin2_code":"68500.0",
    "gn:asciiname":"Violetas",
    "gn:country_code":"CO",
    "gn:dem":1384,
    "gn:feature_class":"P",
    "gn:feature_code":"PPL",
    "gn:name":"Violetas",
    "gn:population":0,
    "gn:timezone":"America/Bogota",
    "iso:country":"CO",
    "wof:name":"Violetas",
    "wof:placetype":"locality"
},
  "geometry": {"coordinates":[-73.31323,6.21861],"type":"Point"}
}