{
  "type": "Feature",
  "properties": {
    "gn:admin1_code":"2",
    "gn:admin2_code":"5353.0",
    "gn:asciiname":"Hoyo Grande",
    "gn:country_code":"CO",
    "gn:dem":1449,
    "gn:feature_class":"P",
    "gn:feature_code":"PPL",
    "gn:name":"Hoyo Grande",
    "gn:population":0,
    "gn:timezone":"America/Bogota",
    "iso:country":"CO",
    "wof:name":"Hoyo Grande",
    "wof:placetype":"locality"
},
  "geometry": {"coordinates":[-75.87725,5.76649],"type":"Point"}
}