{
  "type": "Feature",
  "properties": {
    "gn:admin1_code":"32.0",
    "gn:admin2_code":"85139.0",
    "gn:asciiname":"Yopito",
    "gn:country_code":"CO",
    "gn:dem":157,
    "gn:feature_class":"P",
    "gn:feature_code":"PPL",
    "gn:name":"Yopito",
    "gn:population":0,
    "gn:timezone":"America/Bogota",
    "iso:country":"CO",
    "wof:name":"Yopito",
    "wof:placetype":"locality"
},
  "geometry": {"coordinates":[-72.32483000000001,4.42847],"type":"Point"}
}