{
  "type": "Feature",
  "properties": {
    "gn:admin1_code":"26.0",
    "gn:admin2_code":"68250.0",
    "gn:asciiname":"Ojo de Agua",
    "gn:country_code":"CO",
    "gn:dem":2609,
    "gn:feature_class":"P",
    "gn:feature_code":"PPL",
    "gn:name":"Ojo de Agua",
    "gn:population":0,
    "gn:timezone":"America/Bogota",
    "iso:country":"CO",
    "wof:name":"Ojo de Agua",
    "wof:placetype":"locality"
},
  "geometry": {"coordinates":[-73.78333000000001,6.06667],"type":"Point"}
}