{
  "type": "Feature",
  "properties": {
    "gn:admin1_code":"28.0",
    "gn:admin2_code":"73483.0",
    "gn:asciiname":"Los Planes",
    "gn:country_code":"CO",
    "gn:dem":345,
    "gn:feature_class":"P",
    "gn:feature_code":"PPL",
    "gn:name":"Los Planes",
    "gn:population":0,
    "gn:timezone":"America/Bogota",
    "iso:country":"CO",
    "name:spa_x_preferred":[
        "Los Planes"
    ],
    "wof:name":"Los Planes",
    "wof:placetype":"locality"
},
  "geometry": {"coordinates":[-75.01528,3.63278],"type":"Point"}
}