{
  "type": "Feature",
  "properties": {
    "gn:admin1_code":"36",
    "gn:admin2_code":"15531.0",
    "gn:asciiname":"El Consuelo",
    "gn:country_code":"CO",
    "gn:dem":2396,
    "gn:feature_class":"P",
    "gn:feature_code":"PPL",
    "gn:name":"El Consuelo",
    "gn:population":0,
    "gn:timezone":"America/Bogota",
    "iso:country":"CO",
    "wof:name":"El Consuelo",
    "wof:placetype":"locality"
},
  "geometry": {"coordinates":[-73.93028000000002,5.61278],"type":"Point"}
}