{
  "type": "Feature",
  "properties": {
    "gn:admin1_code":"17",
    "gn:admin2_code":"44847.0",
    "gn:asciiname":"Juanuta",
    "gn:country_code":"CO",
    "gn:dem":34,
    "gn:feature_class":"P",
    "gn:feature_code":"PPL",
    "gn:name":"Juanuta",
    "gn:population":0,
    "gn:timezone":"America/Bogota",
    "iso:country":"CO",
    "wof:name":"Juanuta",
    "wof:placetype":"locality"
},
  "geometry": {"coordinates":[-71.76151,12.25256],"type":"Point"}
}