{
  "type": "Feature",
  "properties": {
    "gn:admin1_code":"21",
    "gn:admin2_code":"54344.0",
    "gn:asciiname":"Limoncitos",
    "gn:country_code":"CO",
    "gn:dem":996,
    "gn:feature_class":"P",
    "gn:feature_code":"PPL",
    "gn:name":"Limoncitos",
    "gn:population":0,
    "gn:timezone":"America/Bogota",
    "iso:country":"CO",
    "wof:name":"Limoncitos",
    "wof:placetype":"locality"
},
  "geometry": {"coordinates":[-73.14556,8.29861],"type":"Point"}
}