{
  "type": "Feature",
  "properties": {
    "gn:admin1_code":"19.0",
    "gn:admin2_code":"50689.0",
    "gn:asciiname":"San Gabriel",
    "gn:country_code":"CO",
    "gn:dem":235,
    "gn:feature_class":"P",
    "gn:feature_code":"PPLL",
    "gn:name":"San Gabriel",
    "gn:population":0,
    "gn:timezone":"America/Bogota",
    "iso:country":"CO",
    "name:spa_x_preferred":[
        "San Gabriel"
    ],
    "wof:name":"San Gabriel",
    "wof:placetype":"locality"
},
  "geometry": {"coordinates":[-73.05736,3.67628],"type":"Point"}
}