{
  "type": "Feature",
  "properties": {
    "gn:admin1_code":"22.0",
    "gn:admin2_code":"86755.0",
    "gn:asciiname":"Refugio de Vida",
    "gn:country_code":"CO",
    "gn:dem":2166,
    "gn:feature_class":"P",
    "gn:feature_code":"PPL",
    "gn:name":"Refugio de Vida",
    "gn:population":0,
    "gn:timezone":"America/Bogota",
    "iso:country":"CO",
    "name:spa_x_preferred":[
        "Refugio de Vida"
    ],
    "wof:name":"Refugio de Vida",
    "wof:placetype":"locality"
},
  "geometry": {"coordinates":[-76.83211,1.08233],"type":"Point"}
}