{
  "type": "Feature",
  "properties": {
    "gn:admin1_code":"29.0",
    "gn:admin2_code":"76834.0",
    "gn:asciiname":"Rosario",
    "gn:country_code":"CO",
    "gn:dem":1903,
    "gn:feature_class":"P",
    "gn:feature_code":"PPL",
    "gn:name":"Rosario",
    "gn:population":0,
    "gn:timezone":"America/Bogota",
    "iso:country":"CO",
    "wof:name":"Rosario",
    "wof:placetype":"locality"
},
  "geometry": {"coordinates":[-76.08417,4.00583],"type":"Point"}
}