{
  "type": "Feature",
  "properties": {
    "gn:admin1_code":"29.0",
    "gn:admin2_code":"76834.0",
    "gn:asciiname":"Rosario",
    "gn:country_code":"CO",
    "gn:dem":1903,
    "gn:feature_class":"P",
    "gn:feature_code":"PPL",
    "gn:name":"Rosario",
    "gn:population":0,
    "gn:timezone":"America/Bogota",
    "iso:country":"CO",
    "name:ben_x_preferred":[
        "\u09b0\u09cb\u09b8\u09be\u09b0\u09bf\u0993"
    ],
    "name:ell_x_preferred":[
        "\u03a1\u03bf\u03b6\u03ac\u03c1\u03b9\u03bf"
    ],
    "name:hin_x_preferred":[
        "\u0930\u094b\u091c\u093c\u093e\u0930\u093f\u092f\u094b"
    ],
    "name:kor_x_preferred":[
        "\ub85c\uc0ac\ub9ac\uc624"
    ],
    "name:tur_x_preferred":[
        "Rosario"
    ],
    "name:urd_x_preferred":[
        "\u0631\u0627\u0632\u0627\u0631\u06cc\u0648"
    ],
    "name:vie_x_preferred":[
        "Rosario"
    ],
    "wof:name":"Rosario",
    "wof:placetype":"locality"
},
  "geometry": {"coordinates":[-76.08417,4.00583],"type":"Point"}
}