{
  "type": "Feature",
  "properties": {
    "gn:admin1_code":"38",
    "gn:admin2_code":"47555.0",
    "gn:asciiname":"La Cristina",
    "gn:country_code":"CO",
    "gn:dem":147,
    "gn:feature_class":"P",
    "gn:feature_code":"PPL",
    "gn:name":"La Cristina",
    "gn:population":0,
    "gn:timezone":"America/Bogota",
    "iso:country":"CO",
    "name:und_x_variant":[
        "Hacienda La Cristina",
        "La Cristina"
    ],
    "wof:name":"La Cristina",
    "wof:placetype":"locality"
},
  "geometry": {"coordinates":[-74.45304,9.93544],"type":"Point"}
}