{
  "type": "Feature",
  "properties": {
    "gn:admin1_code":"29",
    "gn:admin2_code":"76248.0",
    "gn:asciiname":"Carrizal",
    "gn:country_code":"CO",
    "gn:dem":2042,
    "gn:feature_class":"P",
    "gn:feature_code":"PPL",
    "gn:name":"Carrizal",
    "gn:population":0,
    "gn:timezone":"America/Bogota",
    "iso:country":"CO",
    "wof:name":"Carrizal",
    "wof:placetype":"locality"
},
  "geometry": {"coordinates":[-76.09028000000001,3.65722],"type":"Point"}
}