{
  "type": "Feature",
  "properties": {
    "gn:admin1_code":"8.0",
    "gn:admin2_code":"18410.0",
    "gn:asciiname":"Puerto Gaitan",
    "gn:country_code":"CO",
    "gn:dem":263,
    "gn:feature_class":"P",
    "gn:feature_code":"PPL",
    "gn:name":"Puerto Gait\u00e1n",
    "gn:population":0,
    "gn:timezone":"America/Bogota",
    "iso:country":"CO",
    "name:spa_x_preferred":[
        "Puerto Gait\u00e1n"
    ],
    "name:und_x_variant":[
        "Caser\u00edo Puerto Gait\u00e1n"
    ],
    "wof:name":"Puerto Gaitan",
    "wof:placetype":"locality"
},
  "geometry": {"coordinates":[-75.0132,1.15895],"type":"Point"}
}