{
  "type": "Feature",
  "properties": {
    "gn:admin1_code":"20",
    "gn:admin2_code":"52687.0",
    "gn:asciiname":"San Clemente",
    "gn:country_code":"CO",
    "gn:dem":1595,
    "gn:feature_class":"P",
    "gn:feature_code":"PPL",
    "gn:name":"San Clemente",
    "gn:population":0,
    "gn:timezone":"America/Bogota",
    "iso:country":"CO",
    "wof:name":"San Clemente",
    "wof:placetype":"locality"
},
  "geometry": {"coordinates":[-77.19379000000001,1.61193],"type":"Point"}
}