{
  "type": "Feature",
  "properties": {
    "gn:admin1_code":"19.0",
    "gn:admin2_code":"50573.0",
    "gn:asciiname":"Santaya",
    "gn:country_code":"CO",
    "gn:dem":178,
    "gn:feature_class":"P",
    "gn:feature_code":"PPL",
    "gn:name":"Santaya",
    "gn:population":0,
    "gn:timezone":"America/Bogota",
    "iso:country":"CO",
    "wof:name":"Santaya",
    "wof:placetype":"locality"
},
  "geometry": {"coordinates":[-72.82088,4.22793],"type":"Point"}
}