{
  "type": "Feature",
  "properties": {
    "gn:admin1_code":"19",
    "gn:admin2_code":"50251",
    "gn:asciiname":"El Recreo",
    "gn:country_code":"CO",
    "gn:dem":969,
    "gn:feature_class":"P",
    "gn:feature_code":"PPL",
    "gn:name":"El Recreo",
    "gn:population":0,
    "gn:timezone":"America/Bogota",
    "iso:country":"CO",
    "name:spa_x_preferred":[
        "El Recreo"
    ],
    "wof:name":"El Recreo",
    "wof:placetype":"locality"
},
  "geometry": {"coordinates":[-73.94603000000002,3.59595],"type":"Point"}
}