{
  "type": "Feature",
  "properties": {
    "gn:admin1_code":"35",
    "gn:admin2_code":"13657.0",
    "gn:asciiname":"San Pedro Consolado",
    "gn:country_code":"CO",
    "gn:dem":204,
    "gn:feature_class":"P",
    "gn:feature_code":"PPL",
    "gn:name":"San Pedro Consolado",
    "gn:population":0,
    "gn:timezone":"America/Bogota",
    "iso:country":"CO",
    "name:und_x_variant":[
        "Desconsolado",
        "Desconsolados",
        "San Pedro Consolado"
    ],
    "wof:name":"San Pedro Consolado",
    "wof:placetype":"locality"
},
  "geometry": {"coordinates":[-75.0467,10.01056],"type":"Point"}
}