{
  "type": "Feature",
  "properties": {
    "gn:admin1_code":"26.0",
    "gn:admin2_code":"68745.0",
    "gn:asciiname":"Santana de Flores",
    "gn:country_code":"CO",
    "gn:dem":1303,
    "gn:feature_class":"P",
    "gn:feature_code":"PPL",
    "gn:name":"Santana de Flores",
    "gn:population":0,
    "gn:timezone":"America/Bogota",
    "iso:country":"CO",
    "wof:name":"Santana de Flores",
    "wof:placetype":"locality"
},
  "geometry": {"coordinates":[-73.32455,6.46886],"type":"Point"}
}