{
  "type": "Feature",
  "properties": {
    "gn:admin1_code":"12.0",
    "gn:admin2_code":"23001.0",
    "gn:asciiname":"Trespuertas",
    "gn:country_code":"CO",
    "gn:dem":45,
    "gn:feature_class":"P",
    "gn:feature_code":"PPL",
    "gn:name":"Trespuertas",
    "gn:population":0,
    "gn:timezone":"America/Bogota",
    "iso:country":"CO",
    "wof:name":"Trespuertas",
    "wof:placetype":"locality"
},
  "geometry": {"coordinates":[-75.90131,8.58352],"type":"Point"}
}