{
  "type": "Feature",
  "properties": {
    "gn:admin1_code":"9.0",
    "gn:admin2_code":"19075.0",
    "gn:asciiname":"Capitanes",
    "gn:country_code":"CO",
    "gn:dem":1257,
    "gn:feature_class":"P",
    "gn:feature_code":"PPL",
    "gn:name":"Capitanes",
    "gn:population":0,
    "gn:timezone":"America/Bogota",
    "iso:country":"CO",
    "wof:name":"Capitanes",
    "wof:placetype":"locality"
},
  "geometry": {"coordinates":[-77.16571,2.10688],"type":"Point"}
}