{
  "type": "Feature",
  "properties": {
    "gn:admin1_code":"9",
    "gn:admin2_code":"19100.0",
    "gn:asciiname":"El Cuervo",
    "gn:country_code":"CO",
    "gn:dem":625,
    "gn:feature_class":"P",
    "gn:feature_code":"PPL",
    "gn:name":"El Cuervo",
    "gn:population":0,
    "gn:timezone":"America/Bogota",
    "iso:country":"CO",
    "wof:name":"El Cuervo",
    "wof:placetype":"locality"
},
  "geometry": {"coordinates":[-77.06338000000002,1.92042],"type":"Point"}
}