{
  "type": "Feature",
  "properties": {
    "gn:admin1_code":"29",
    "gn:admin2_code":"76892.0",
    "gn:asciiname":"Arauca",
    "gn:country_code":"CO",
    "gn:dem":950,
    "gn:feature_class":"P",
    "gn:feature_code":"PPL",
    "gn:name":"Arauca",
    "gn:population":0,
    "gn:timezone":"America/Bogota",
    "iso:country":"CO",
    "wof:name":"Arauca",
    "wof:placetype":"locality"
},
  "geometry": {"coordinates":[-76.45028000000001,3.65056],"type":"Point"}
}