{
  "type": "Feature",
  "properties": {
    "gn:admin1_code":"29",
    "gn:admin2_code":"76892.0",
    "gn:asciiname":"Arauca",
    "gn:country_code":"CO",
    "gn:dem":950,
    "gn:feature_class":"P",
    "gn:feature_code":"PPL",
    "gn:name":"Arauca",
    "gn:population":0,
    "gn:timezone":"America/Bogota",
    "iso:country":"CO",
    "name:bre_x_preferred":[
        "Arauca"
    ],
    "name:ceb_x_preferred":[
        "Arauca"
    ],
    "name:ces_x_preferred":[
        "Arauca"
    ],
    "name:deu_x_preferred":[
        "Arauca"
    ],
    "name:fra_x_preferred":[
        "Arauca"
    ],
    "name:gla_x_preferred":[
        "Arauca"
    ],
    "name:heb_x_preferred":[
        "\u05d0\u05e8\u05d0\u05d5\u05e7\u05d4"
    ],
    "name:hrv_x_preferred":[
        "Arauca"
    ],
    "name:ita_x_preferred":[
        "Arauca"
    ],
    "name:kor_x_preferred":[
        "\uc544\ub77c\uc6b0\uce74"
    ],
    "name:lit_x_preferred":[
        "Arauka"
    ],
    "name:nld_x_preferred":[
        "Arauca"
    ],
    "name:nor_x_preferred":[
        "Arauca"
    ],
    "name:pol_x_preferred":[
        "Arauca"
    ],
    "name:rus_x_preferred":[
        "\u0410\u0440\u0430\u0443\u043a\u0430"
    ],
    "name:sco_x_preferred":[
        "Arauca"
    ],
    "name:slk_x_preferred":[
        "Arauca"
    ],
    "name:spa_x_preferred":[
        "Arauca"
    ],
    "name:srp_x_preferred":[
        "\u0410\u0440\u0430\u0443\u043a\u0430"
    ],
    "name:swe_x_preferred":[
        "Arauca"
    ],
    "name:ukr_x_preferred":[
        "\u0410\u0440\u0430\u0443\u043a\u0430"
    ],
    "wof:name":"Arauca",
    "wof:placetype":"locality"
},
  "geometry": {"coordinates":[-76.45028000000001,3.65056],"type":"Point"}
}