{
  "type": "Feature",
  "properties": {
    "gn:admin1_code":"33.0",
    "gn:admin2_code":"25438.0",
    "gn:asciiname":"Jagua",
    "gn:country_code":"CO",
    "gn:dem":505,
    "gn:feature_class":"P",
    "gn:feature_code":"PPL",
    "gn:name":"Jagua",
    "gn:population":0,
    "gn:timezone":"America/Bogota",
    "iso:country":"CO",
    "name:ceb_x_preferred":[
        "Jagua"
    ],
    "name:ita_x_preferred":[
        "Jagua"
    ],
    "name:swe_x_preferred":[
        "Jagua"
    ],
    "wof:name":"Jagua",
    "wof:placetype":"locality"
},
  "geometry": {"coordinates":[-73.29718000000003,4.6158],"type":"Point"}
}