{
  "type": "Feature",
  "properties": {
    "gn:admin1_code":"33",
    "gn:admin2_code":"25426.0",
    "gn:asciiname":"Casablanca",
    "gn:country_code":"CO",
    "gn:dem":2210,
    "gn:feature_class":"P",
    "gn:feature_code":"PPL",
    "gn:name":"Casablanca",
    "gn:population":0,
    "gn:timezone":"America/Bogota",
    "iso:country":"CO",
    "wof:name":"Casablanca",
    "wof:placetype":"locality"
},
  "geometry": {"coordinates":[-73.61667,5.08333],"type":"Point"}
}