{
  "type": "Feature",
  "properties": {
    "gn:admin1_code":"3.0",
    "gn:admin2_code":"81794.0",
    "gn:asciiname":"Morichal",
    "gn:country_code":"CO",
    "gn:dem":153,
    "gn:feature_class":"P",
    "gn:feature_code":"PPL",
    "gn:name":"Morichal",
    "gn:population":0,
    "gn:timezone":"America/Bogota",
    "iso:country":"CO",
    "name:und_x_variant":[
        "Marichal",
        "Morichal"
    ],
    "wof:name":"Morichal",
    "wof:placetype":"locality"
},
  "geometry": {"coordinates":[-71.34713000000001,6.33309],"type":"Point"}
}