{
  "type": "Feature",
  "properties": {
    "gn:admin1_code":"19",
    "gn:admin2_code":"50251",
    "gn:asciiname":"Las Mesas",
    "gn:country_code":"CO",
    "gn:dem":516,
    "gn:feature_class":"P",
    "gn:feature_code":"PPL",
    "gn:name":"Las Mesas",
    "gn:population":0,
    "gn:timezone":"America/Bogota",
    "iso:country":"CO",
    "name:spa_x_preferred":[
        "Las Mesas"
    ],
    "wof:name":"Las Mesas",
    "wof:placetype":"locality"
},
  "geometry": {"coordinates":[-73.88462,3.63388],"type":"Point"}
}