{
  "type": "Feature",
  "properties": {
    "gn:gn_country":"CO",
    "gn:gn_fcode":"PPL",
    "gn:gn_pop":9224,
    "gn:population":9224,
    "iso:country":"CO",
    "name:chi_x_preferred":[
        "\u99ac\u963f\u7279\u65af"
    ],
    "name:dut_x_preferred":[
        "Mahates"
    ],
    "name:eng_x_preferred":[
        "Mahates"
    ],
    "name:fre_x_preferred":[
        "Mahates"
    ],
    "name:geo_x_preferred":[
        "\u10db\u10d0\u10d0\u10e2\u10d4\u10e1\u10d8"
    ],
    "name:ita_x_preferred":[
        "Mahates"
    ],
    "name:may_x_preferred":[
        "Mahates"
    ],
    "name:nan_x_preferred":[
        "Mahates"
    ],
    "name:per_x_preferred":[
        "\u0645\u0627\u0622\u062a\u0633"
    ],
    "name:por_x_preferred":[
        "Mahates"
    ],
    "name:spa_x_preferred":[
        "Mahates"
    ],
    "name:swe_x_preferred":[
        "Mahates"
    ],
    "name:tgl_x_preferred":[
        "Mahates"
    ],
    "name:unk_x_variant":[
        "Mahales"
    ],
    "name:vie_x_preferred":[
        "Mahates"
    ],
    "name:war_x_preferred":[
        "Mahates"
    ],
    "qs_pg:aaroncc":"CO",
    "qs_pg:gn_country":"CO",
    "qs_pg:gn_fcode":"PPL",
    "qs_pg:gn_pop":9224,
    "qs_pg:name":"Mahates",
    "qs_pg:photos_9r":0,
    "qs_pg:photos_sr":0,
    "qs_pg:pop_sr":5,
    "qs_pg:qs_pg_placetype":"locality",
    "wof:name":"Mahates",
    "wof:placetype":"locality",
    "wof:population":9224
},
  "geometry": {"coordinates":[-75.18985000000001,10.23293],"type":"Point"}
}