{
  "type": "Feature",
  "properties": {
    "gn:admin1_code":"26",
    "gn:admin2_code":"68502.0",
    "gn:asciiname":"Chaguaca",
    "gn:cc2":"CO",
    "gn:country_code":"CO",
    "gn:dem":2373,
    "gn:feature_class":"P",
    "gn:feature_code":"PPL",
    "gn:name":"Chaguaca",
    "gn:population":0,
    "gn:timezone":"America/Bogota",
    "iso:country":"CO",
    "name:und_x_variant":[
        "Escuela Chaguaca",
        "Chaguaca"
    ],
    "wof:name":"Chaguaca",
    "wof:placetype":"locality"
},
  "geometry": {"coordinates":[-72.81667,6.31667],"type":"Point"}
}