{
  "type": "Feature",
  "properties": {
    "gn:admin1_code":"2",
    "gn:admin2_code":"5790.0",
    "gn:asciiname":"El Silencio",
    "gn:country_code":"CO",
    "gn:dem":1451,
    "gn:feature_class":"P",
    "gn:feature_code":"PPL",
    "gn:name":"El Silencio",
    "gn:population":0,
    "gn:timezone":"America/Bogota",
    "iso:country":"CO",
    "name:ceb_x_preferred":[
        "El Silencio"
    ],
    "name:spa_x_preferred":[
        "El Silencio"
    ],
    "name:swe_x_preferred":[
        "El Silencio"
    ],
    "wof:name":"El Silencio",
    "wof:placetype":"locality"
},
  "geometry": {"coordinates":[-75.73416999999998,7.40694],"type":"Point"}
}