{
  "type": "Feature",
  "properties": {
    "gn:admin1_code":"16.0",
    "gn:admin2_code":"41206.0",
    "gn:asciiname":"Bernasa",
    "gn:country_code":"CO",
    "gn:dem":1939,
    "gn:feature_class":"P",
    "gn:feature_code":"PPL",
    "gn:name":"Bernasa",
    "gn:population":0,
    "gn:timezone":"America/Bogota",
    "iso:country":"CO",
    "name:spa_x_preferred":[
        "Bernasa"
    ],
    "wof:name":"Bernasa",
    "wof:placetype":"locality"
},
  "geometry": {"coordinates":[-74.77454,3.26565],"type":"Point"}
}