{
  "type": "Feature",
  "properties": {
    "gn:admin1_code":"28.0",
    "gn:admin2_code":"73217.0",
    "gn:asciiname":"La Quinta",
    "gn:country_code":"CO",
    "gn:dem":318,
    "gn:feature_class":"P",
    "gn:feature_code":"PPL",
    "gn:name":"La Quinta",
    "gn:population":0,
    "gn:timezone":"America/Bogota",
    "iso:country":"CO",
    "name:spa_x_preferred":[
        "La Quinta"
    ],
    "wof:name":"La Quinta",
    "wof:placetype":"locality"
},
  "geometry": {"coordinates":[-75.06999999999999,3.66833],"type":"Point"}
}