{
  "type": "Feature",
  "properties": {
    "gn:admin1_code":"9.0",
    "gn:admin2_code":"19517.0",
    "gn:asciiname":"Vereda La Cruz",
    "gn:country_code":"CO",
    "gn:dem":2313,
    "gn:feature_class":"P",
    "gn:feature_code":"PPLL",
    "gn:name":"Vereda La Cruz",
    "gn:population":0,
    "gn:timezone":"America/Bogota",
    "iso:country":"CO",
    "wof:name":"Vereda La Cruz",
    "wof:placetype":"locality"
},
  "geometry": {"coordinates":[-76.07337,2.72246],"type":"Point"}
}