{
  "type": "Feature",
  "properties": {
    "gn:admin1_code":"9.0",
    "gn:admin2_code":"19450.0",
    "gn:asciiname":"Alto La Canada",
    "gn:country_code":"CO",
    "gn:dem":987,
    "gn:feature_class":"P",
    "gn:feature_code":"PPL",
    "gn:name":"Alto La Ca\u00f1ada",
    "gn:population":0,
    "gn:timezone":"America/Bogota",
    "iso:country":"CO",
    "wof:name":"Alto La Canada",
    "wof:placetype":"locality"
},
  "geometry": {"coordinates":[-77.21946,1.69271],"type":"Point"}
}