{
  "type": "Feature",
  "properties": {
    "gn:admin1_code":"33.0",
    "gn:admin2_code":"25430.0",
    "gn:asciiname":"Montecristo",
    "gn:country_code":"CO",
    "gn:dem":2560,
    "gn:feature_class":"P",
    "gn:feature_code":"PPL",
    "gn:name":"Montecristo",
    "gn:population":0,
    "gn:timezone":"America/Bogota",
    "iso:country":"CO",
    "wof:name":"Montecristo",
    "wof:placetype":"locality"
},
  "geometry": {"coordinates":[-74.28076,4.76238],"type":"Point"}
}