{
  "type": "Feature",
  "properties": {
    "gn:admin1_code":"20",
    "gn:admin2_code":"52260.0",
    "gn:asciiname":"Azoque",
    "gn:country_code":"CO",
    "gn:dem":2463,
    "gn:feature_class":"P",
    "gn:feature_code":"PPL",
    "gn:name":"Azoque",
    "gn:population":0,
    "gn:timezone":"America/Bogota",
    "iso:country":"CO",
    "wof:name":"Azoque",
    "wof:placetype":"locality"
},
  "geometry": {"coordinates":[-77.36895,1.42269],"type":"Point"}
}