{
  "type": "Feature",
  "properties": {
    "gn:admin1_code":"35.0",
    "gn:admin2_code":"13647.0",
    "gn:asciiname":"Sitio Nuevo",
    "gn:country_code":"CO",
    "gn:dem":131,
    "gn:feature_class":"P",
    "gn:feature_code":"PPL",
    "gn:name":"Sitio Nuevo",
    "gn:population":0,
    "gn:timezone":"America/Bogota",
    "iso:country":"CO",
    "wof:name":"Sitio Nuevo",
    "wof:placetype":"locality"
},
  "geometry": {"coordinates":[-75.27929,10.34581],"type":"Point"}
}