{
  "type": "Feature",
  "properties": {
    "gn:admin1_code":"26.0",
    "gn:admin2_code":"68307.0",
    "gn:asciiname":"Motoso",
    "gn:country_code":"CO",
    "gn:dem":1301,
    "gn:feature_class":"P",
    "gn:feature_code":"PPL",
    "gn:name":"Motoso",
    "gn:population":0,
    "gn:timezone":"America/Bogota",
    "iso:country":"CO",
    "wof:name":"Motoso",
    "wof:placetype":"locality"
},
  "geometry": {"coordinates":[-73.26666999999998,7.05],"type":"Point"}
}