{
  "type": "Feature",
  "properties": {
    "gn:admin1_code":"26",
    "gn:admin2_code":"68368.0",
    "gn:asciiname":"El Encenillo",
    "gn:country_code":"CO",
    "gn:dem":2253,
    "gn:feature_class":"P",
    "gn:feature_code":"PPL",
    "gn:name":"El Encenillo",
    "gn:population":0,
    "gn:timezone":"America/Bogota",
    "iso:country":"CO",
    "wof:name":"El Encenillo",
    "wof:placetype":"locality"
},
  "geometry": {"coordinates":[-73.84528,5.82083],"type":"Point"}
}