{
  "type": "Feature",
  "properties": {
    "gn:admin1_code":"9.0",
    "gn:admin2_code":"19397.0",
    "gn:asciiname":"Santa Juana",
    "gn:country_code":"CO",
    "gn:dem":1516,
    "gn:feature_class":"P",
    "gn:feature_code":"PPL",
    "gn:name":"Santa Juana",
    "gn:population":0,
    "gn:timezone":"America/Bogota",
    "iso:country":"CO",
    "wof:name":"Santa Juana",
    "wof:placetype":"locality"
},
  "geometry": {"coordinates":[-76.80553,2.12966],"type":"Point"}
}