{
  "type": "Feature",
  "properties": {
    "gn:admin1_code":"29",
    "gn:admin2_code":"76248.0",
    "gn:asciiname":"El Brillante",
    "gn:country_code":"CO",
    "gn:dem":2832,
    "gn:feature_class":"P",
    "gn:feature_code":"PPL",
    "gn:name":"El Brillante",
    "gn:population":0,
    "gn:timezone":"America/Bogota",
    "iso:country":"CO",
    "wof:name":"El Brillante",
    "wof:placetype":"locality"
},
  "geometry": {"coordinates":[-76.10528000000002,3.67861],"type":"Point"}
}