{
  "type": "Feature",
  "properties": {
    "gn:admin1_code":"12.0",
    "gn:admin2_code":"23189.0",
    "gn:asciiname":"El Carreto",
    "gn:country_code":"CO",
    "gn:dem":76,
    "gn:feature_class":"P",
    "gn:feature_code":"PPLL",
    "gn:name":"El Carreto",
    "gn:population":0,
    "gn:timezone":"America/Bogota",
    "iso:country":"CO",
    "wof:name":"El Carreto",
    "wof:placetype":"locality"
},
  "geometry": {"coordinates":[-75.60164,8.85898],"type":"Point"}
}