{
  "type": "Feature",
  "properties": {
    "gn:admin1_code":"36",
    "gn:admin2_code":"15425.0",
    "gn:asciiname":"Bata",
    "gn:country_code":"CO",
    "gn:dem":1287,
    "gn:feature_class":"P",
    "gn:feature_code":"PPL",
    "gn:name":"Bat\u00e1",
    "gn:population":0,
    "gn:timezone":"America/Bogota",
    "iso:country":"CO",
    "name:ast_x_preferred":[
        "Bata"
    ],
    "name:cat_x_preferred":[
        "Bata"
    ],
    "name:ceb_x_preferred":[
        "Bata"
    ],
    "name:ces_x_preferred":[
        "Bata"
    ],
    "name:deu_x_preferred":[
        "Bata"
    ],
    "name:epo_x_preferred":[
        "Bata"
    ],
    "name:fra_x_preferred":[
        "Bata"
    ],
    "name:glg_x_preferred":[
        "Bata"
    ],
    "name:hun_x_preferred":[
        "Bata"
    ],
    "name:ind_x_preferred":[
        "Bata"
    ],
    "name:ita_x_preferred":[
        "Bata"
    ],
    "name:lit_x_preferred":[
        "Bata"
    ],
    "name:nld_x_preferred":[
        "Bata"
    ],
    "name:pol_x_preferred":[
        "Bata"
    ],
    "name:por_x_preferred":[
        "Bata"
    ],
    "name:ron_x_preferred":[
        "Bata"
    ],
    "name:slk_x_preferred":[
        "Bata"
    ],
    "name:spa_x_preferred":[
        "Bata"
    ],
    "name:swe_x_preferred":[
        "Bata"
    ],
    "wof:name":"Bata",
    "wof:placetype":"locality"
},
  "geometry": {"coordinates":[-73.33333,4.96667],"type":"Point"}
}