{
  "type": "Feature",
  "properties": {
    "gn:admin1_code":"36",
    "gn:admin2_code":"15425.0",
    "gn:asciiname":"Bata",
    "gn:country_code":"CO",
    "gn:dem":1287,
    "gn:feature_class":"P",
    "gn:feature_code":"PPL",
    "gn:name":"Bat\u00e1",
    "gn:population":0,
    "gn:timezone":"America/Bogota",
    "iso:country":"CO",
    "wof:name":"Bata",
    "wof:placetype":"locality"
},
  "geometry": {"coordinates":[-73.33333,4.96667],"type":"Point"}
}