{
  "type": "Feature",
  "properties": {
    "gn:admin1_code":"38.0",
    "gn:admin2_code":"47551.0",
    "gn:asciiname":"Tamalameque",
    "gn:country_code":"CO",
    "gn:dem":38,
    "gn:feature_class":"P",
    "gn:feature_code":"PPL",
    "gn:name":"Tamalameque",
    "gn:population":0,
    "gn:timezone":"America/Bogota",
    "iso:country":"CO",
    "name:ceb_x_preferred":[
        "Tamalameque"
    ],
    "name:epo_x_preferred":[
        "Tamalameque"
    ],
    "name:fra_x_preferred":[
        "Tamalameque"
    ],
    "name:ita_x_preferred":[
        "Tamalameque"
    ],
    "name:kat_x_preferred":[
        "\u10e2\u10d0\u10db\u10d0\u10db\u10d0\u10da\u10d4\u10d9\u10d4"
    ],
    "name:msa_x_preferred":[
        "Tamalameque"
    ],
    "name:nld_x_preferred":[
        "Tamalameque"
    ],
    "name:por_x_preferred":[
        "Tamalameque"
    ],
    "name:rus_x_preferred":[
        "\u0422\u0430\u043c\u0430\u043b\u0430\u043c\u0435\u043a\u0435"
    ],
    "name:spa_x_preferred":[
        "Tamalameque"
    ],
    "name:swe_x_preferred":[
        "Tamalameque"
    ],
    "name:tgl_x_preferred":[
        "Tamalameque"
    ],
    "name:ukr_x_preferred":[
        "\u0422\u0430\u043c\u0430\u043b\u0430\u043c\u0435\u043a\u0435"
    ],
    "name:vie_x_preferred":[
        "Tamalameque"
    ],
    "name:war_x_preferred":[
        "Tamalameque"
    ],
    "name:zho_x_preferred":[
        "\u5854\u99ac\u62c9\u6885\u514b"
    ],
    "wof:name":"Tamalameque",
    "wof:placetype":"locality"
},
  "geometry": {"coordinates":[-74.53753,10.32795],"type":"Point"}
}