{
  "type": "Feature",
  "properties": {
    "gn:admin1_code":"38.0",
    "gn:admin2_code":"47551.0",
    "gn:asciiname":"Tamalameque",
    "gn:country_code":"CO",
    "gn:dem":38,
    "gn:feature_class":"P",
    "gn:feature_code":"PPL",
    "gn:name":"Tamalameque",
    "gn:population":0,
    "gn:timezone":"America/Bogota",
    "iso:country":"CO",
    "wof:name":"Tamalameque",
    "wof:placetype":"locality"
},
  "geometry": {"coordinates":[-74.53753,10.32795],"type":"Point"}
}