{
  "type": "Feature",
  "properties": {
    "iso:country":"CO",
    "name:ast_x_preferred":[
        "Sutatenza"
    ],
    "name:ceb_x_preferred":[
        "Sutatenza"
    ],
    "name:eng_x_preferred":[
        "Sutatenza"
    ],
    "name:fra_x_preferred":[
        "Sutatenza"
    ],
    "name:ita_x_preferred":[
        "Sutatenza"
    ],
    "name:kat_x_preferred":[
        "\u10e1\u10e3\u10e2\u10d0\u10e2\u10d4\u10dc\u10e1\u10d0"
    ],
    "name:msa_x_preferred":[
        "Sutatenza"
    ],
    "name:nan_x_preferred":[
        "Sutatenza"
    ],
    "name:nld_x_preferred":[
        "Sutatenza"
    ],
    "name:por_x_preferred":[
        "Sutatenza"
    ],
    "name:rus_x_preferred":[
        "\u0421\u0443\u0442\u0430\u0442\u0435\u043d\u0441\u0430"
    ],
    "name:spa_x_preferred":[
        "Sutatenza"
    ],
    "name:swe_x_preferred":[
        "Sutatenza"
    ],
    "name:tgl_x_preferred":[
        "Sutatenza"
    ],
    "name:vie_x_preferred":[
        "Sutatenza"
    ],
    "name:war_x_preferred":[
        "Sutatenza"
    ],
    "name:zho_min_nan_x_preferred":[
        "Sutatenza"
    ],
    "name:zho_x_preferred":[
        "\u8607\u5854\u6ed5\u85a9"
    ],
    "qs:gn_country":"CO",
    "qs:gn_fcode":"PPL",
    "qs:gn_pop":827,
    "qs:name":"Sutatenza",
    "qs:name_adm0":"Colombia",
    "qs:name_adm1":"Boyaca",
    "qs:photos":0,
    "qs:photos_1k":0,
    "qs:photos_9k":1,
    "qs:photos_9r":1,
    "qs:photos_all":15,
    "qs:photos_sr":0,
    "qs:placetype":"Town",
    "qs:pop_sr":"2",
    "qs:woe_adm0":23424787,
    "wd:wordcount":186,
    "wof:name":"Sutatenza",
    "wof:placetype":"locality",
    "wof:population":827
},
  "geometry": {"coordinates":[-73.4405,5.02403],"type":"Point"}
}