{
  "type": "Feature",
  "properties": {
    "gn:admin1_code":"26",
    "gn:admin2_code":"68255.0",
    "gn:asciiname":"San Cayeteao",
    "gn:country_code":"CO",
    "gn:dem":600,
    "gn:feature_class":"P",
    "gn:feature_code":"PPL",
    "gn:name":"San Cayeteao",
    "gn:population":0,
    "gn:timezone":"America/Bogota",
    "iso:country":"CO",
    "wof:name":"San Cayeteao",
    "wof:placetype":"locality"
},
  "geometry": {"coordinates":[-73.28721999999998,7.49056],"type":"Point"}
}