{
  "type": "Feature",
  "properties": {
    "gn:admin1_code":"28",
    "gn:admin2_code":"73236.0",
    "gn:asciiname":"Primavera",
    "gn:country_code":"CO",
    "gn:dem":1705,
    "gn:feature_class":"P",
    "gn:feature_code":"PPLL",
    "gn:name":"Primavera",
    "gn:population":0,
    "gn:timezone":"America/Bogota",
    "iso:country":"CO",
    "name:spa_x_preferred":[
        "Primavera"
    ],
    "wof:name":"Primavera",
    "wof:placetype":"locality"
},
  "geometry": {"coordinates":[-74.78222,3.60861],"type":"Point"}
}