{
  "type": "Feature",
  "properties": {
    "gn:admin1_code":"17",
    "gn:admin2_code":"44001.0",
    "gn:asciiname":"Cucurumana",
    "gn:country_code":"CO",
    "gn:dem":13,
    "gn:feature_class":"P",
    "gn:feature_code":"PPL",
    "gn:name":"Cucurumana",
    "gn:population":0,
    "gn:timezone":"America/Bogota",
    "iso:country":"CO",
    "wof:name":"Cucurumana",
    "wof:placetype":"locality"
},
  "geometry": {"coordinates":[-72.81036999999998,11.46906],"type":"Point"}
}