{
  "type": "Feature",
  "properties": {
    "gn:admin1_code":"38",
    "gn:admin2_code":"47745.0",
    "gn:asciiname":"Corral Manuel Granados",
    "gn:country_code":"CO",
    "gn:dem":3,
    "gn:feature_class":"P",
    "gn:feature_code":"PPL",
    "gn:name":"Corral Manuel Granados",
    "gn:population":0,
    "gn:timezone":"America/Bogota",
    "iso:country":"CO",
    "wof:name":"Corral Manuel Granados",
    "wof:placetype":"locality"
},
  "geometry": {"coordinates":[-74.64,10.90056],"type":"Point"}
}