{
  "type": "Feature",
  "properties": {
    "gn:admin1_code":"37",
    "gn:admin2_code":"17653.0",
    "gn:asciiname":"Cruces",
    "gn:country_code":"CO",
    "gn:dem":2945,
    "gn:feature_class":"P",
    "gn:feature_code":"PPL",
    "gn:name":"Cruces",
    "gn:population":0,
    "gn:timezone":"America/Bogota",
    "iso:country":"CO",
    "name:bre_x_preferred":[
        "Cruces"
    ],
    "name:ceb_x_preferred":[
        "Cruces"
    ],
    "name:glg_x_preferred":[
        "Cruces"
    ],
    "name:por_x_preferred":[
        "Cruces"
    ],
    "name:spa_x_preferred":[
        "Cruces"
    ],
    "name:swe_x_preferred":[
        "Cruces"
    ],
    "wof:name":"Cruces",
    "wof:placetype":"locality"
},
  "geometry": {"coordinates":[-75.34999999999999,5.36667],"type":"Point"}
}