{
  "type": "Feature",
  "properties": {
    "gn:admin1_code":"20.0",
    "gn:admin2_code":"52227.0",
    "gn:asciiname":"La Empalizada",
    "gn:country_code":"CO",
    "gn:dem":3222,
    "gn:feature_class":"P",
    "gn:feature_code":"PPL",
    "gn:name":"La Empalizada",
    "gn:population":0,
    "gn:timezone":"America/Bogota",
    "iso:country":"CO",
    "wof:name":"La Empalizada",
    "wof:placetype":"locality"
},
  "geometry": {"coordinates":[-77.81171999999999,0.89994],"type":"Point"}
}