{
  "type": "Feature",
  "properties": {
    "gn:admin1_code":"38",
    "gn:admin2_code":"47660.0",
    "gn:asciiname":"La Gloria Vieja",
    "gn:country_code":"CO",
    "gn:dem":135,
    "gn:feature_class":"P",
    "gn:feature_code":"PPL",
    "gn:name":"La Gloria Vieja",
    "gn:population":0,
    "gn:timezone":"America/Bogota",
    "iso:country":"CO",
    "wof:name":"La Gloria Vieja",
    "wof:placetype":"locality"
},
  "geometry": {"coordinates":[-74.35368000000003,10.07034],"type":"Point"}
}