{
  "type": "Feature",
  "properties": {
    "gn:admin1_code":"20.0",
    "gn:admin2_code":"52699.0",
    "gn:asciiname":"Piarama",
    "gn:country_code":"CO",
    "gn:dem":2704,
    "gn:feature_class":"P",
    "gn:feature_code":"PPL",
    "gn:name":"Piaram\u00e1",
    "gn:population":0,
    "gn:timezone":"America/Bogota",
    "iso:country":"CO",
    "wof:name":"Piarama",
    "wof:placetype":"locality"
},
  "geometry": {"coordinates":[-77.68901,1.15186],"type":"Point"}
}