{
  "type": "Feature",
  "properties": {
    "gn:admin1_code":"38",
    "gn:admin2_code":"47318.0",
    "gn:asciiname":"Guamomacho",
    "gn:country_code":"CO",
    "gn:dem":32,
    "gn:feature_class":"P",
    "gn:feature_code":"PPL",
    "gn:name":"Guamomacho",
    "gn:population":0,
    "gn:timezone":"America/Bogota",
    "iso:country":"CO",
    "wof:name":"Guamomacho",
    "wof:placetype":"locality"
},
  "geometry": {"coordinates":[-74.11667,9.23333],"type":"Point"}
}