{
  "type": "Feature",
  "properties": {
    "gn:admin1_code":"36",
    "gn:admin2_code":"15572.0",
    "gn:asciiname":"Serviez",
    "gn:country_code":"CO",
    "gn:dem":129,
    "gn:feature_class":"P",
    "gn:feature_code":"PPL",
    "gn:name":"Serviez",
    "gn:population":0,
    "gn:timezone":"America/Bogota",
    "iso:country":"CO",
    "wof:name":"Serviez",
    "wof:placetype":"locality"
},
  "geometry": {"coordinates":[-74.56471999999999,6.22278],"type":"Point"}
}