{
  "type": "Feature",
  "properties": {
    "gn:admin1_code":"27",
    "gn:admin2_code":"70001.0",
    "gn:asciiname":"La Estancia",
    "gn:country_code":"CO",
    "gn:dem":78,
    "gn:feature_class":"P",
    "gn:feature_code":"PPL",
    "gn:name":"La Estancia",
    "gn:population":0,
    "gn:timezone":"America/Bogota",
    "iso:country":"CO",
    "name:ceb_x_preferred":[
        "La Estancia"
    ],
    "name:deu_x_preferred":[
        "La Estancia"
    ],
    "name:spa_x_preferred":[
        "La Estancia"
    ],
    "name:swe_x_preferred":[
        "La Estancia"
    ],
    "name:und_x_variant":[
        "Hacienda La Estancia",
        "La Estancia"
    ],
    "wof:name":"La Estancia",
    "wof:placetype":"locality"
},
  "geometry": {"coordinates":[-75.46764,9.30307],"type":"Point"}
}