{
  "type": "Feature",
  "properties": {
    "iso:country":"CO",
    "name:ast_x_preferred":[
        "Mercaderes"
    ],
    "name:ceb_x_preferred":[
        "Mercaderes"
    ],
    "name:eng_x_preferred":[
        "Mercaderes"
    ],
    "name:fra_x_preferred":[
        "Mercaderes"
    ],
    "name:ita_x_preferred":[
        "Mercaderes"
    ],
    "name:kat_x_preferred":[
        "\u10db\u10d4\u10e0\u10d9\u10d0\u10d3\u10d4\u10e0\u10d4\u10e1\u10d8"
    ],
    "name:msa_x_preferred":[
        "Mercaderes"
    ],
    "name:nan_x_preferred":[
        "Mercaderes"
    ],
    "name:nld_x_preferred":[
        "Mercaderes"
    ],
    "name:por_x_preferred":[
        "Mercaderes"
    ],
    "name:spa_x_preferred":[
        "Mercaderes"
    ],
    "name:swe_x_preferred":[
        "Mercaderes"
    ],
    "name:tgl_x_preferred":[
        "Mercaderes"
    ],
    "name:vie_x_preferred":[
        "Mercaderes"
    ],
    "name:war_x_preferred":[
        "Mercaderes"
    ],
    "name:zho_min_nan_x_preferred":[
        "Mercaderes"
    ],
    "name:zho_x_preferred":[
        "\u6885\u5361\u5fb7\u96f7\u65af"
    ],
    "qs:gn_country":"CO",
    "qs:gn_fcode":"PPL",
    "qs:gn_pop":4684,
    "qs:name":"Mercaderes",
    "qs:name_adm0":"Colombia",
    "qs:name_adm1":"Cauca",
    "qs:photos":0,
    "qs:photos_1k":0,
    "qs:photos_9k":0,
    "qs:photos_9r":0,
    "qs:photos_all":0,
    "qs:photos_sr":0,
    "qs:placetype":"Town",
    "qs:pop_sr":"4",
    "qs:woe_adm0":23424787,
    "wd:wordcount":31,
    "wof:name":"Mercaderes",
    "wof:placetype":"locality",
    "wof:population":4684
},
  "geometry": {"coordinates":[-77.16596,1.80094],"type":"Point"}
}