{
  "type": "Feature",
  "properties": {
    "gn:admin1_code":"33.0",
    "gn:admin2_code":"25148.0",
    "gn:asciiname":"Muzarro",
    "gn:country_code":"CO",
    "gn:dem":743,
    "gn:feature_class":"P",
    "gn:feature_code":"PPL",
    "gn:name":"Muzarro",
    "gn:population":0,
    "gn:timezone":"America/Bogota",
    "iso:country":"CO",
    "name:spa_x_preferred":[
        "Muzarro"
    ],
    "wof:name":"Muzarro",
    "wof:placetype":"locality"
},
  "geometry": {"coordinates":[-74.54054000000002,5.35282],"type":"Point"}
}