{
  "type": "Feature",
  "properties": {
    "gn:admin1_code":"20.0",
    "gn:admin2_code":"52585.0",
    "gn:asciiname":"Inbulachico",
    "gn:country_code":"CO",
    "gn:dem":3143,
    "gn:feature_class":"P",
    "gn:feature_code":"PPL",
    "gn:name":"Inbulachico",
    "gn:population":0,
    "gn:timezone":"America/Bogota",
    "iso:country":"CO",
    "wof:name":"Inbulachico",
    "wof:placetype":"locality"
},
  "geometry": {"coordinates":[-77.61735,0.95266],"type":"Point"}
}