{
  "type": "Feature",
  "properties": {
    "gn:admin1_code":"38",
    "gn:admin2_code":"47660.0",
    "gn:asciiname":"La Zarcita",
    "gn:country_code":"CO",
    "gn:dem":170,
    "gn:feature_class":"P",
    "gn:feature_code":"PPL",
    "gn:name":"La Zarcita",
    "gn:population":0,
    "gn:timezone":"America/Bogota",
    "iso:country":"CO",
    "wof:name":"La Zarcita",
    "wof:placetype":"locality"
},
  "geometry": {"coordinates":[-74.28738,10.12439],"type":"Point"}
}