{
  "type": "Feature",
  "properties": {
    "gn:admin1_code":"12",
    "gn:admin2_code":"23419.0",
    "gn:asciiname":"Hacienda La Cana",
    "gn:country_code":"CO",
    "gn:dem":32,
    "gn:feature_class":"P",
    "gn:feature_code":"PPL",
    "gn:name":"Hacienda La Ca\u00f1a",
    "gn:population":0,
    "gn:timezone":"America/Bogota",
    "iso:country":"CO",
    "wof:name":"Hacienda La Cana",
    "wof:placetype":"locality"
},
  "geometry": {"coordinates":[-76.24250000000001,8.87028],"type":"Point"}
}