{
  "type": "Feature",
  "properties": {
    "gn:admin1_code":"2",
    "gn:admin2_code":"5670.0",
    "gn:asciiname":"El Pital",
    "gn:country_code":"CO",
    "gn:dem":1214,
    "gn:feature_class":"P",
    "gn:feature_code":"PPL",
    "gn:name":"El Pital",
    "gn:population":0,
    "gn:timezone":"America/Bogota",
    "iso:country":"CO",
    "wof:name":"El Pital",
    "wof:placetype":"locality"
},
  "geometry": {"coordinates":[-74.95971999999998,6.41444],"type":"Point"}
}