{
  "type": "Feature",
  "properties": {
    "gn:admin1_code":"26",
    "gn:asciiname":"El Libano",
    "gn:country_code":"CO",
    "gn:dem":1661,
    "gn:feature_class":"P",
    "gn:feature_code":"PPL",
    "gn:name":"El L\u00edbano",
    "gn:population":0,
    "gn:timezone":"America/Bogota",
    "iso:country":"CO",
    "wof:name":"El Libano",
    "wof:placetype":"locality"
},
  "geometry": {"coordinates":[-73.59824,5.91608],"type":"Point"}
}