{
  "type": "Feature",
  "properties": {
    "gn:admin1_code":"2",
    "gn:admin2_code":"5667.0",
    "gn:asciiname":"Cristalina",
    "gn:country_code":"CO",
    "gn:dem":1218,
    "gn:feature_class":"P",
    "gn:feature_code":"PPL",
    "gn:name":"Cristalina",
    "gn:population":0,
    "gn:timezone":"America/Bogota",
    "iso:country":"CO",
    "wof:name":"Cristalina",
    "wof:placetype":"locality"
},
  "geometry": {"coordinates":[-74.94167,6.3275],"type":"Point"}
}