{
  "type": "Feature",
  "properties": {
    "gn:admin1_code":"2.0",
    "gn:admin2_code":"5284.0",
    "gn:asciiname":"Tangado",
    "gn:country_code":"CO",
    "gn:dem":1678,
    "gn:feature_class":"P",
    "gn:feature_code":"PPL",
    "gn:name":"Tangado",
    "gn:population":0,
    "gn:timezone":"America/Bogota",
    "iso:country":"CO",
    "wof:name":"Tangado",
    "wof:placetype":"locality"
},
  "geometry": {"coordinates":[-76.22198,6.74939],"type":"Point"}
}