{
  "type": "Feature",
  "properties": {
    "gn:admin1_code":"12.0",
    "gn:admin2_code":"23678.0",
    "gn:asciiname":"El Oriente",
    "gn:country_code":"CO",
    "gn:dem":177,
    "gn:feature_class":"P",
    "gn:feature_code":"PPLL",
    "gn:name":"El Oriente",
    "gn:population":0,
    "gn:timezone":"America/Bogota",
    "iso:country":"CO",
    "wof:name":"El Oriente",
    "wof:placetype":"locality"
},
  "geometry": {"coordinates":[-75.62664000000002,8.66148],"type":"Point"}
}