{
  "type": "Feature",
  "properties": {
    "gn:admin1_code":"17",
    "gn:admin2_code":"44001.0",
    "gn:asciiname":"Guamaca",
    "gn:country_code":"CO",
    "gn:dem":984,
    "gn:feature_class":"P",
    "gn:feature_code":"PPL",
    "gn:name":"Guamaca",
    "gn:population":0,
    "gn:timezone":"America/Bogota",
    "iso:country":"CO",
    "wof:name":"Guamaca",
    "wof:placetype":"locality"
},
  "geometry": {"coordinates":[-73.20604,10.98075],"type":"Point"}
}