{
  "type": "Feature",
  "properties": {
    "gn:admin1_code":"9",
    "gn:admin2_code":"19100.0",
    "gn:asciiname":"El Cerro",
    "gn:country_code":"CO",
    "gn:dem":1976,
    "gn:feature_class":"P",
    "gn:feature_code":"PPL",
    "gn:name":"El Cerro",
    "gn:population":0,
    "gn:timezone":"America/Bogota",
    "iso:country":"CO",
    "name:spa_x_preferred":[
        "El Cerro"
    ],
    "wof:name":"El Cerro",
    "wof:placetype":"locality"
},
  "geometry": {"coordinates":[-77.01685999999999,1.77027],"type":"Point"}
}