{
  "type": "Feature",
  "properties": {
    "gn:admin1_code":"26.0",
    "gn:admin2_code":"68298.0",
    "gn:asciiname":"Castame",
    "gn:country_code":"CO",
    "gn:dem":1722,
    "gn:feature_class":"P",
    "gn:feature_code":"PPL",
    "gn:name":"Castame",
    "gn:population":0,
    "gn:timezone":"America/Bogota",
    "iso:country":"CO",
    "wof:name":"Castame",
    "wof:placetype":"locality"
},
  "geometry": {"coordinates":[-73.33162,6.05144],"type":"Point"}
}