{
  "type": "Feature",
  "properties": {
    "gn:admin1_code":"33",
    "gn:admin2_code":"25099.0",
    "gn:asciiname":"Barroblanco",
    "gn:country_code":"CO",
    "gn:dem":2609,
    "gn:feature_class":"P",
    "gn:feature_code":"PPL",
    "gn:name":"Barroblanco",
    "gn:population":0,
    "gn:timezone":"America/Bogota",
    "iso:country":"CO",
    "wof:name":"Barroblanco",
    "wof:placetype":"locality"
},
  "geometry": {"coordinates":[-74.31067,4.67548],"type":"Point"}
}