{
  "type": "Feature",
  "properties": {
    "gn:admin1_code":"29.0",
    "gn:admin2_code":"76364.0",
    "gn:asciiname":"Quinamayo",
    "gn:country_code":"CO",
    "gn:dem":979,
    "gn:feature_class":"P",
    "gn:feature_code":"PPL",
    "gn:name":"Quinamayo",
    "gn:population":0,
    "gn:timezone":"America/Bogota",
    "iso:country":"CO",
    "wof:name":"Quinamayo",
    "wof:placetype":"locality"
},
  "geometry": {"coordinates":[-76.55754,3.12793],"type":"Point"}
}