{
  "type": "Feature",
  "properties": {
    "gn:admin1_code":"20",
    "gn:admin2_code":"52378.0",
    "gn:asciiname":"Lema de Ortiz",
    "gn:country_code":"CO",
    "gn:dem":2846,
    "gn:feature_class":"P",
    "gn:feature_code":"PPL",
    "gn:name":"Lema de Ortiz",
    "gn:population":0,
    "gn:timezone":"America/Bogota",
    "iso:country":"CO",
    "name:spa_x_preferred":[
        "Lema de Ortiz"
    ],
    "wof:name":"Lema de Ortiz",
    "wof:placetype":"locality"
},
  "geometry": {"coordinates":[-77.00468000000002,1.5643],"type":"Point"}
}