{
  "type": "Feature",
  "properties": {
    "gn:admin1_code":"14.0",
    "gn:admin2_code":"95001.0",
    "gn:asciiname":"Guayabero",
    "gn:country_code":"CO",
    "gn:dem":186,
    "gn:feature_class":"P",
    "gn:feature_code":"PPL",
    "gn:name":"Guayabero",
    "gn:population":0,
    "gn:timezone":"America/Bogota",
    "iso:country":"CO",
    "name:und_x_variant":[
        "Inspecci\u00f3n de Polic\u00eda Guayabero",
        "Guayabero"
    ],
    "wof:name":"Guayabero",
    "wof:placetype":"locality"
},
  "geometry": {"coordinates":[-72.80253,2.61081],"type":"Point"}
}