{
  "type": "Feature",
  "properties": {
    "gn:admin1_code":"2.0",
    "gn:admin2_code":"5045.0",
    "gn:asciiname":"La Trinidad",
    "gn:country_code":"CO",
    "gn:dem":26,
    "gn:feature_class":"P",
    "gn:feature_code":"PPL",
    "gn:name":"La Trinidad",
    "gn:population":0,
    "gn:timezone":"America/Bogota",
    "iso:country":"CO",
    "name:ceb_x_preferred":[
        "La Trinidad"
    ],
    "name:deu_x_preferred":[
        "La Trinidad"
    ],
    "name:ita_x_preferred":[
        "La Trinidad"
    ],
    "name:nld_x_preferred":[
        "La Trinidad"
    ],
    "name:srp_x_preferred":[
        "\u041b\u0430 \u0422\u0440\u0438\u043d\u0438\u0434\u0430\u0434"
    ],
    "name:swe_x_preferred":[
        "La Trinidad"
    ],
    "name:vie_x_preferred":[
        "La Trinidad"
    ],
    "wof:name":"La Trinidad",
    "wof:placetype":"locality"
},
  "geometry": {"coordinates":[-76.64,7.85778],"type":"Point"}
}