{
  "type": "Feature",
  "properties": {
    "gn:admin1_code":"2.0",
    "gn:admin2_code":"5585.0",
    "gn:asciiname":"Puerto Zaragoza",
    "gn:country_code":"CO",
    "gn:dem":131,
    "gn:feature_class":"P",
    "gn:feature_code":"PPL",
    "gn:name":"Puerto Zaragoza",
    "gn:population":0,
    "gn:timezone":"America/Bogota",
    "iso:country":"CO",
    "wof:name":"Puerto Zaragoza",
    "wof:placetype":"locality"
},
  "geometry": {"coordinates":[-74.61667,6.11667],"type":"Point"}
}