{
  "type": "Feature",
  "properties": {
    "gn:admin1_code":"36",
    "gn:admin2_code":"15776.0",
    "gn:asciiname":"Las Cuevas",
    "gn:country_code":"CO",
    "gn:dem":2974,
    "gn:feature_class":"P",
    "gn:feature_code":"PPL",
    "gn:name":"Las Cuevas",
    "gn:population":0,
    "gn:timezone":"America/Bogota",
    "iso:country":"CO",
    "wof:name":"Las Cuevas",
    "wof:placetype":"locality"
},
  "geometry": {"coordinates":[-73.66096999999998,5.65099],"type":"Point"}
}