{
  "type": "Feature",
  "properties": {
    "gn:admin1_code":"19.0",
    "gn:admin2_code":"50001.0",
    "gn:asciiname":"Puerto Colombia",
    "gn:country_code":"CO",
    "gn:dem":220,
    "gn:feature_class":"P",
    "gn:feature_code":"PPL",
    "gn:name":"Puerto Colombia",
    "gn:population":0,
    "gn:timezone":"America/Bogota",
    "iso:country":"CO",
    "name:ast_x_preferred":[
        "Puerto Colombia"
    ],
    "name:deu_x_preferred":[
        "Puerto Colombia"
    ],
    "name:fas_x_preferred":[
        "\u067e\u0648\u0631\u062a\u0648 \u06a9\u0644\u0645\u0628\u06cc\u0627"
    ],
    "name:fra_x_preferred":[
        "Puerto Colombia"
    ],
    "name:ita_x_preferred":[
        "Puerto Colombia"
    ],
    "name:kat_x_preferred":[
        "\u10de\u10e3\u10d4\u10e0\u10e2\u10dd-\u10d9\u10dd\u10da\u10e3\u10db\u10d1\u10d8\u10d0"
    ],
    "name:msa_x_preferred":[
        "Puerto Colombia"
    ],
    "name:nld_x_preferred":[
        "Puerto Colombia"
    ],
    "name:por_x_preferred":[
        "Puerto Colombia"
    ],
    "name:rus_x_preferred":[
        "\u041f\u0443\u044d\u0440\u0442\u043e-\u041a\u043e\u043b\u043e\u043c\u0431\u0438\u044f"
    ],
    "name:sco_x_preferred":[
        "Puerto Colombia"
    ],
    "name:spa_x_preferred":[
        "Puerto Colombia"
    ],
    "name:tgl_x_preferred":[
        "Puerto Colombia"
    ],
    "name:vie_x_preferred":[
        "Puerto Colombia"
    ],
    "name:war_x_preferred":[
        "Puerto Colombia"
    ],
    "name:zho_x_preferred":[
        "\u54e5\u502b\u6bd4\u4e9e\u6e2f"
    ],
    "wof:name":"Puerto Colombia",
    "wof:placetype":"locality"
},
  "geometry": {"coordinates":[-73.23323000000001,4.00306],"type":"Point"}
}