{
  "type": "Feature",
  "properties": {
    "gn:admin1_code":"26.0",
    "gn:admin2_code":"68307.0",
    "gn:asciiname":"Rionegro",
    "gn:country_code":"CO",
    "gn:dem":692,
    "gn:feature_class":"P",
    "gn:feature_code":"PPL",
    "gn:name":"Rionegro",
    "gn:population":0,
    "gn:timezone":"America/Bogota",
    "iso:country":"CO",
    "name:deu_x_preferred":[
        "Rionegro"
    ],
    "name:fas_x_preferred":[
        "\u0631\u06cc\u0648\u0646\u06af\u0631\u0648"
    ],
    "name:fra_x_preferred":[
        "Rionegro"
    ],
    "name:glg_x_preferred":[
        "Rionegro"
    ],
    "name:ita_x_preferred":[
        "Rionegro"
    ],
    "name:kat_x_preferred":[
        "\u10e0\u10d8\u10dd\u10dc\u10d4\u10d2\u10e0\u10dd"
    ],
    "name:msa_x_preferred":[
        "Rionegro"
    ],
    "name:nld_x_preferred":[
        "Rionegro"
    ],
    "name:spa_x_preferred":[
        "Rionegro"
    ],
    "name:tgl_x_preferred":[
        "Rionegro"
    ],
    "name:vie_x_preferred":[
        "Rionegro"
    ],
    "name:war_x_preferred":[
        "Rionegro"
    ],
    "name:zho_x_preferred":[
        "\u91cc\u5967\u5167\u683c\u7f85"
    ],
    "wof:name":"Rionegro",
    "wof:placetype":"locality"
},
  "geometry": {"coordinates":[-73.15361,7.15361],"type":"Point"}
}