{
  "type": "Feature",
  "properties": {
    "gn:admin1_code":"17",
    "gn:admin2_code":"44847.0",
    "gn:asciiname":"Ishishomuhuna",
    "gn:country_code":"CO",
    "gn:dem":-8,
    "gn:feature_class":"P",
    "gn:feature_code":"PPL",
    "gn:name":"Ish\u00edshomuhuna",
    "gn:population":0,
    "gn:timezone":"America/Bogota",
    "iso:country":"CO",
    "wof:name":"Ishishomuhuna",
    "wof:placetype":"locality"
},
  "geometry": {"coordinates":[-71.45,12.28333],"type":"Point"}
}