{
  "type": "Feature",
  "properties": {
    "gn:admin1_code":"12",
    "gn:admin2_code":"23555.0",
    "gn:asciiname":"La Nueva Esperanza",
    "gn:country_code":"CO",
    "gn:dem":67,
    "gn:feature_class":"P",
    "gn:feature_code":"PPL",
    "gn:name":"La Nueva Esperanza",
    "gn:population":0,
    "gn:timezone":"America/Bogota",
    "iso:country":"CO",
    "name:und_x_variant":[
        "Nueva Esperanza",
        "La Nueva Esperanza"
    ],
    "wof:name":"La Nueva Esperanza",
    "wof:placetype":"locality"
},
  "geometry": {"coordinates":[-75.68526999999997,8.33463],"type":"Point"}
}