{
  "type": "Feature",
  "properties": {
    "gn:admin1_code":"33.0",
    "gn:admin2_code":"25320.0",
    "gn:asciiname":"Bayon",
    "gn:country_code":"CO",
    "gn:dem":968,
    "gn:feature_class":"P",
    "gn:feature_code":"PPL",
    "gn:name":"Bayon",
    "gn:population":0,
    "gn:timezone":"America/Bogota",
    "iso:country":"CO",
    "name:afr_x_preferred":[
        "Bayon"
    ],
    "name:bre_x_preferred":[
        "Bayon"
    ],
    "name:ces_x_preferred":[
        "Bayon"
    ],
    "name:dan_x_preferred":[
        "Bayon"
    ],
    "name:deu_x_preferred":[
        "Bayon"
    ],
    "name:eus_x_preferred":[
        "Bayon"
    ],
    "name:fas_x_preferred":[
        "\u0645\u0639\u0628\u062f \u0628\u0627\u06cc\u0648\u0646"
    ],
    "name:fin_x_preferred":[
        "Bayon"
    ],
    "name:fra_x_preferred":[
        "Bayon"
    ],
    "name:glg_x_preferred":[
        "Bayon"
    ],
    "name:hin_x_preferred":[
        "\u092c\u093e\u092f\u094b\u0902 \u092e\u0928\u094d\u0926\u093f\u0930"
    ],
    "name:hrv_x_preferred":[
        "Bayon"
    ],
    "name:hun_x_preferred":[
        "Bajon"
    ],
    "name:ind_x_preferred":[
        "Bayon"
    ],
    "name:ita_x_preferred":[
        "Bayon"
    ],
    "name:jpn_x_preferred":[
        "\u30d0\u30a4\u30e8\u30f3"
    ],
    "name:khm_x_preferred":[
        "\u1794\u17d2\u179a\u17b6\u179f\u17b6\u1791\u1794\u17b6\u1799\u17d0\u1793"
    ],
    "name:kor_x_preferred":[
        "\ubc14\uc774\uc698"
    ],
    "name:lit_x_preferred":[
        "Bajonas"
    ],
    "name:mal_x_preferred":[
        "\u0d2c\u0d46\u0d2f\u0d4b\u0d7a"
    ],
    "name:nld_x_preferred":[
        "Bayon"
    ],
    "name:nor_x_preferred":[
        "Bayon"
    ],
    "name:pol_x_preferred":[
        "Bajon"
    ],
    "name:por_x_preferred":[
        "Bayon"
    ],
    "name:rus_x_preferred":[
        "\u0411\u0430\u0439\u043e\u043d"
    ],
    "name:spa_x_preferred":[
        "Bayon"
    ],
    "name:spa_x_variant":[
        "Bay\u00f3n"
    ],
    "name:swe_x_preferred":[
        "Bayon"
    ],
    "name:tha_x_preferred":[
        "\u0e1b\u0e23\u0e32\u0e2a\u0e32\u0e17\u0e1a\u0e32\u0e22\u0e19"
    ],
    "name:tur_x_preferred":[
        "Bayon"
    ],
    "name:ukr_x_preferred":[
        "\u0411\u0430\u0439\u043e\u043d"
    ],
    "name:vie_x_preferred":[
        "Bayon"
    ],
    "name:zho_x_preferred":[
        "\u5df4\u620e\u5bfa"
    ],
    "wof:name":"Bayon",
    "wof:placetype":"locality"
},
  "geometry": {"coordinates":[-74.61296,5.09919],"type":"Point"}
}