{
  "type": "Feature",
  "properties": {
    "gn:admin1_code":"33.0",
    "gn:admin2_code":"25320.0",
    "gn:asciiname":"Bayon",
    "gn:country_code":"CO",
    "gn:dem":968,
    "gn:feature_class":"P",
    "gn:feature_code":"PPL",
    "gn:name":"Bayon",
    "gn:population":0,
    "gn:timezone":"America/Bogota",
    "iso:country":"CO",
    "name:spa_x_preferred":[
        "Bayon"
    ],
    "wof:name":"Bayon",
    "wof:placetype":"locality"
},
  "geometry": {"coordinates":[-74.61296,5.09919],"type":"Point"}
}