{
  "type": "Feature",
  "properties": {
    "gn:admin1_code":"29",
    "gn:admin2_code":"76306.0",
    "gn:asciiname":"Hojas",
    "gn:country_code":"CO",
    "gn:dem":2119,
    "gn:feature_class":"P",
    "gn:feature_code":"PPL",
    "gn:name":"Hojas",
    "gn:population":0,
    "gn:timezone":"America/Bogota",
    "iso:country":"CO",
    "wof:name":"Hojas",
    "wof:placetype":"locality"
},
  "geometry": {"coordinates":[-76.16833000000003,3.70361],"type":"Point"}
}