{
  "type": "Feature",
  "properties": {
    "gn:admin1_code":"2",
    "gn:admin2_code":"5411.0",
    "gn:asciiname":"La Honda",
    "gn:country_code":"CO",
    "gn:dem":1237,
    "gn:feature_class":"P",
    "gn:feature_code":"PPL",
    "gn:name":"La Honda",
    "gn:population":0,
    "gn:timezone":"America/Bogota",
    "iso:country":"CO",
    "wof:name":"La Honda",
    "wof:placetype":"locality"
},
  "geometry": {"coordinates":[-75.82833000000002,6.78028],"type":"Point"}
}