{
  "type": "Feature",
  "properties": {
    "gn:admin1_code":"38",
    "gn:admin2_code":"47980.0",
    "gn:asciiname":"Antonia",
    "gn:country_code":"CO",
    "gn:dem":15,
    "gn:feature_class":"P",
    "gn:feature_code":"PPL",
    "gn:name":"Antonia",
    "gn:population":0,
    "gn:timezone":"America/Bogota",
    "iso:country":"CO",
    "name:bre_x_preferred":[
        "Antonia"
    ],
    "name:bul_x_preferred":[
        "\u0410\u043d\u0442\u043e\u043d\u0438\u044f"
    ],
    "name:deu_x_preferred":[
        "Antonia"
    ],
    "name:fin_x_preferred":[
        "Antonia"
    ],
    "name:fra_x_preferred":[
        "Antonia"
    ],
    "name:heb_x_preferred":[
        "\u05d0\u05e0\u05d8\u05d5\u05e0\u05d9\u05d4"
    ],
    "name:ita_x_preferred":[
        "Antonia"
    ],
    "name:jpn_x_preferred":[
        "\u30a2\u30f3\u30c8\u30cb\u30a2"
    ],
    "name:lat_x_preferred":[
        "Antonia"
    ],
    "name:nld_x_preferred":[
        "Antonia"
    ],
    "name:pol_x_preferred":[
        "Antonia"
    ],
    "name:por_x_preferred":[
        "Ant\u00f4nia"
    ],
    "name:ron_x_preferred":[
        "Antonia"
    ],
    "name:rus_x_preferred":[
        "\u0410\u043d\u0442\u043e\u043d\u0438\u044f"
    ],
    "name:spa_x_preferred":[
        "Antonia"
    ],
    "name:ukr_x_preferred":[
        "\u0410\u043d\u0442\u043e\u043d\u0456\u044f"
    ],
    "wof:name":"Antonia",
    "wof:placetype":"locality"
},
  "geometry": {"coordinates":[-74.18284,10.87054],"type":"Point"}
}