{
  "type": "Feature",
  "properties": {
    "gn:admin1_code":"22.0",
    "gn:asciiname":"Nasaya",
    "gn:country_code":"CO",
    "gn:dem":163,
    "gn:feature_class":"P",
    "gn:feature_code":"PPL",
    "gn:name":"Nasay\u00e1",
    "gn:population":0,
    "gn:timezone":"America/Bogota",
    "iso:country":"CO",
    "wof:name":"Nasaya",
    "wof:placetype":"locality"
},
  "geometry": {"coordinates":[-73.84639,-0.40306],"type":"Point"}
}