{
  "type": "Feature",
  "properties": {
    "gn:admin1_code":"35",
    "gn:admin2_code":"13074.0",
    "gn:asciiname":"Hatillo",
    "gn:country_code":"CO",
    "gn:dem":26,
    "gn:feature_class":"P",
    "gn:feature_code":"PPL",
    "gn:name":"Hatillo",
    "gn:population":0,
    "gn:timezone":"America/Bogota",
    "iso:country":"CO",
    "name:ceb_x_preferred":[
        "Hatillo"
    ],
    "name:fra_x_preferred":[
        "Hatillo"
    ],
    "name:ita_x_preferred":[
        "Hatillo"
    ],
    "name:nld_x_preferred":[
        "Hatillo"
    ],
    "name:pol_x_preferred":[
        "Hatillo"
    ],
    "name:spa_x_preferred":[
        "Hatillo"
    ],
    "name:swe_x_preferred":[
        "Hatillo"
    ],
    "wof:name":"Hatillo",
    "wof:placetype":"locality"
},
  "geometry": {"coordinates":[-74.1242,8.8519],"type":"Point"}
}