{
  "type": "Feature",
  "properties": {
    "gn:admin1_code":"29",
    "gn:admin2_code":"76109.0",
    "gn:asciiname":"Cordoba",
    "gn:country_code":"CO",
    "gn:dem":39,
    "gn:feature_class":"P",
    "gn:feature_code":"PPL",
    "gn:name":"C\u00f3rdoba",
    "gn:population":0,
    "gn:timezone":"America/Bogota",
    "iso:country":"CO",
    "wof:name":"Cordoba",
    "wof:placetype":"locality"
},
  "geometry": {"coordinates":[-76.92833,3.87528],"type":"Point"}
}