{
  "type": "Feature",
  "properties": {
    "gn:admin1_code":"17",
    "gn:admin2_code":"44650.0",
    "gn:asciiname":"Curazao",
    "gn:country_code":"CO",
    "gn:dem":330,
    "gn:feature_class":"P",
    "gn:feature_code":"PPL",
    "gn:name":"Curazao",
    "gn:population":0,
    "gn:timezone":"America/Bogota",
    "iso:country":"CO",
    "wof:name":"Curazao",
    "wof:placetype":"locality"
},
  "geometry": {"coordinates":[-73.15000000000001,10.76667],"type":"Point"}
}