{
  "type": "Feature",
  "properties": {
    "gn:admin1_code":"36",
    "gn:admin2_code":"15776.0",
    "gn:asciiname":"El Timal",
    "gn:country_code":"CO",
    "gn:dem":2695,
    "gn:feature_class":"P",
    "gn:feature_code":"PPL",
    "gn:name":"El Timal",
    "gn:population":0,
    "gn:timezone":"America/Bogota",
    "iso:country":"CO",
    "wof:name":"El Timal",
    "wof:placetype":"locality"
},
  "geometry": {"coordinates":[-73.65694000000001,5.63194],"type":"Point"}
}