{
  "type": "Feature",
  "properties": {
    "gn:admin1_code":"19.0",
    "gn:admin2_code":"50683.0",
    "gn:asciiname":"Penas Frias",
    "gn:country_code":"CO",
    "gn:dem":433,
    "gn:feature_class":"P",
    "gn:feature_code":"PPLL",
    "gn:name":"Pe\u00f1as Fr\u00edas",
    "gn:population":0,
    "gn:timezone":"America/Bogota",
    "iso:country":"CO",
    "name:spa_x_preferred":[
        "Pe\u00f1as Fr\u00edas"
    ],
    "wof:name":"Penas Frias",
    "wof:placetype":"locality"
},
  "geometry": {"coordinates":[-73.91898,3.336],"type":"Point"}
}