{
  "type": "Feature",
  "properties": {
    "iso:country":"CO",
    "name:ast_x_preferred":[
        "San Fernando"
    ],
    "name:ceb_x_preferred":[
        "San Fernando"
    ],
    "name:eng_x_preferred":[
        "San Fernando"
    ],
    "name:fra_x_preferred":[
        "San Fernando"
    ],
    "name:ita_x_preferred":[
        "San Fernando"
    ],
    "name:jpn_x_preferred":[
        "\u30b5\u30f3\u30fb\u30d5\u30a7\u30eb\u30ca\u30f3\u30c9"
    ],
    "name:msa_x_preferred":[
        "San Fernando"
    ],
    "name:nan_x_preferred":[
        "San Fernando"
    ],
    "name:nld_x_preferred":[
        "San Fernando"
    ],
    "name:por_x_preferred":[
        "San Fernando"
    ],
    "name:rus_x_preferred":[
        "\u0421\u0430\u043d-\u0424\u0435\u0440\u043d\u0430\u043d\u0434\u043e"
    ],
    "name:sco_x_preferred":[
        "San Fernando"
    ],
    "name:spa_x_preferred":[
        "San Fernando"
    ],
    "name:swe_x_preferred":[
        "San Fernando"
    ],
    "name:tgl_x_preferred":[
        "San Fernando"
    ],
    "name:war_x_preferred":[
        "San Fernando"
    ],
    "name:zho_x_preferred":[
        "\u8056\u8cbb\u723e\u5357\u591a"
    ],
    "qs:gn_country":"CO",
    "qs:gn_fcode":"PPL",
    "qs:gn_pop":1615,
    "qs:name":"San Fernando",
    "qs:name_adm0":"Colombia",
    "qs:name_adm1":"Bolivar",
    "qs:photos":0,
    "qs:photos_1k":0,
    "qs:photos_9k":0,
    "qs:photos_9r":0,
    "qs:photos_all":0,
    "qs:photos_sr":0,
    "qs:placetype":"Town",
    "qs:pop_sr":"3",
    "qs:woe_adm0":23424787,
    "wd:wordcount":33,
    "wof:name":"San Fernando",
    "wof:placetype":"locality",
    "wof:population":1615
},
  "geometry": {"coordinates":[-74.53389,9.27972],"type":"Point"}
}