{
  "type": "Feature",
  "properties": {
    "gn:admin1_code":"12",
    "gn:admin2_code":"23855.0",
    "gn:asciiname":"El Vueltoso",
    "gn:country_code":"CO",
    "gn:dem":37,
    "gn:feature_class":"P",
    "gn:feature_code":"PPL",
    "gn:name":"El Vueltoso",
    "gn:population":0,
    "gn:timezone":"America/Bogota",
    "iso:country":"CO",
    "wof:name":"El Vueltoso",
    "wof:placetype":"locality"
},
  "geometry": {"coordinates":[-76.09999999999999,8.31667],"type":"Point"}
}