{
  "type": "Feature",
  "properties": {
    "gn:admin1_code":"26",
    "gn:admin2_code":"68020.0",
    "gn:asciiname":"El Hatillo",
    "gn:country_code":"CO",
    "gn:dem":2204,
    "gn:feature_class":"P",
    "gn:feature_code":"PPL",
    "gn:name":"El Hatillo",
    "gn:population":0,
    "gn:timezone":"America/Bogota",
    "iso:country":"CO",
    "wof:name":"El Hatillo",
    "wof:placetype":"locality"
},
  "geometry": {"coordinates":[-73.76787,5.8148],"type":"Point"}
}