{
  "type": "Feature",
  "properties": {
    "gn:admin1_code":"10",
    "gn:asciiname":"Martinete",
    "gn:country_code":"CO",
    "gn:dem":78,
    "gn:feature_class":"P",
    "gn:feature_code":"PPL",
    "gn:name":"Martinete",
    "gn:population":0,
    "gn:timezone":"America/Bogota",
    "iso:country":"CO",
    "wof:name":"Martinete",
    "wof:placetype":"locality"
},
  "geometry": {"coordinates":[-74.51501,9.65055],"type":"Point"}
}