{
  "type": "Feature",
  "properties": {
    "gn:admin1_code":"9.0",
    "gn:admin2_code":"19318.0",
    "gn:asciiname":"Charcolargo",
    "gn:country_code":"CO",
    "gn:dem":43,
    "gn:feature_class":"P",
    "gn:feature_code":"PPL",
    "gn:name":"Charcolargo",
    "gn:population":0,
    "gn:timezone":"America/Bogota",
    "iso:country":"CO",
    "wof:name":"Charcolargo",
    "wof:placetype":"locality"
},
  "geometry": {"coordinates":[-77.68716999999999,2.50923],"type":"Point"}
}