{
  "type": "Feature",
  "properties": {
    "gn:admin1_code":"26.0",
    "gn:admin2_code":"68575.0",
    "gn:asciiname":"Tropezon",
    "gn:cc2":"CO",
    "gn:country_code":"CO",
    "gn:dem":110,
    "gn:feature_class":"P",
    "gn:feature_code":"PPL",
    "gn:name":"Tropez\u00f3n",
    "gn:population":0,
    "gn:timezone":"America/Bogota",
    "iso:country":"CO",
    "name:und_x_variant":[
        "Hacienda Tropez\u00f3n",
        "Tropez\u00f3n"
    ],
    "wof:name":"Tropezon",
    "wof:placetype":"locality"
},
  "geometry": {"coordinates":[-73.69639000000002,7.34722],"type":"Point"}
}