{
  "type": "Feature",
  "properties": {
    "gn:admin1_code":"3",
    "gn:asciiname":"Puerto Lleras",
    "gn:country_code":"CO",
    "gn:dem":172,
    "gn:feature_class":"P",
    "gn:feature_code":"PPL",
    "gn:name":"Puerto Lleras",
    "gn:population":0,
    "gn:timezone":"America/Bogota",
    "iso:country":"CO",
    "name:spa_x_preferred":[
        "Puerto Lleras"
    ],
    "wof:name":"Puerto Lleras",
    "wof:placetype":"locality"
},
  "geometry": {"coordinates":[-71.69499,7.03702],"type":"Point"}
}