{
  "type": "Feature",
  "properties": {
    "gn:admin1_code":"3",
    "gn:asciiname":"Puerto Lleras",
    "gn:country_code":"CO",
    "gn:dem":172,
    "gn:feature_class":"P",
    "gn:feature_code":"PPL",
    "gn:name":"Puerto Lleras",
    "gn:population":0,
    "gn:timezone":"America/Bogota",
    "iso:country":"CO",
    "name:ceb_x_preferred":[
        "Puerto Lleras"
    ],
    "name:fra_x_preferred":[
        "Puerto Lleras"
    ],
    "name:ita_x_preferred":[
        "Puerto Lleras"
    ],
    "name:kat_x_preferred":[
        "\u10de\u10e3\u10d4\u10e0\u10e2\u10dd-\u10da\u10d8\u10d4\u10e0\u10d0\u10e1\u10d8"
    ],
    "name:msa_x_preferred":[
        "Puerto Lleras"
    ],
    "name:nld_x_preferred":[
        "Puerto Lleras"
    ],
    "name:por_x_preferred":[
        "Puerto Lleras"
    ],
    "name:spa_x_preferred":[
        "Puerto Lleras"
    ],
    "name:swe_x_preferred":[
        "Puerto Lleras"
    ],
    "name:tgl_x_preferred":[
        "Puerto Lleras"
    ],
    "name:vie_x_preferred":[
        "Puerto Lleras"
    ],
    "name:war_x_preferred":[
        "Puerto Lleras"
    ],
    "name:zho_x_preferred":[
        "\u5217\u62c9\u65af\u6e2f"
    ],
    "wof:name":"Puerto Lleras",
    "wof:placetype":"locality"
},
  "geometry": {"coordinates":[-71.69499,7.03702],"type":"Point"}
}