{
  "type": "Feature",
  "properties": {
    "gn:admin1_code":"27",
    "gn:asciiname":"Las Vacas",
    "gn:country_code":"CO",
    "gn:dem":225,
    "gn:feature_class":"P",
    "gn:feature_code":"PPL",
    "gn:name":"Las Vacas",
    "gn:population":0,
    "gn:timezone":"America/Bogota",
    "iso:country":"CO",
    "wof:name":"Las Vacas",
    "wof:placetype":"locality"
},
  "geometry": {"coordinates":[-75.09557,9.65386],"type":"Point"}
}