{
  "type": "Feature",
  "properties": {
    "gn:admin1_code":"8.0",
    "gn:admin2_code":"18247.0",
    "gn:asciiname":"Rio Negro",
    "gn:country_code":"CO",
    "gn:dem":237,
    "gn:feature_class":"P",
    "gn:feature_code":"PPL",
    "gn:name":"R\u00edo Negro",
    "gn:population":0,
    "gn:timezone":"America/Bogota",
    "iso:country":"CO",
    "wof:name":"Rio Negro",
    "wof:placetype":"locality"
},
  "geometry": {"coordinates":[-74.99511,1.61253],"type":"Point"}
}