{
  "type": "Feature",
  "properties": {
    "gn:admin1_code":"8.0",
    "gn:admin2_code":"18001.0",
    "gn:asciiname":"Socorro",
    "gn:country_code":"CO",
    "gn:dem":300,
    "gn:feature_class":"P",
    "gn:feature_code":"PPL",
    "gn:name":"Socorro",
    "gn:population":0,
    "gn:timezone":"America/Bogota",
    "iso:country":"CO",
    "name:ceb_x_preferred":[
        "Socorro"
    ],
    "name:dan_x_preferred":[
        "Socorro"
    ],
    "name:deu_x_preferred":[
        "Socorro"
    ],
    "name:fin_x_preferred":[
        "Socorro"
    ],
    "name:fra_x_preferred":[
        "Socorro"
    ],
    "name:hun_x_preferred":[
        "Socorro"
    ],
    "name:ita_x_preferred":[
        "Socorro"
    ],
    "name:kor_x_preferred":[
        "\uc18c\ucf54\ub85c"
    ],
    "name:nds_x_preferred":[
        "Socorro"
    ],
    "name:nld_x_preferred":[
        "Socorro"
    ],
    "name:pol_x_preferred":[
        "Socorro"
    ],
    "name:por_x_preferred":[
        "Socorro"
    ],
    "name:rus_x_preferred":[
        "\u0421\u043e\u043a\u043e\u0440\u0440\u043e"
    ],
    "name:spa_x_preferred":[
        "Socorro"
    ],
    "name:srp_x_preferred":[
        "\u0421\u043e\u043a\u043e\u0440\u043e"
    ],
    "name:swe_x_preferred":[
        "Socorro"
    ],
    "name:ukr_x_preferred":[
        "\u0421\u043e\u043a\u043e\u0440\u0440\u0443"
    ],
    "name:vol_x_preferred":[
        "Socorro"
    ],
    "name:war_x_preferred":[
        "Socorro"
    ],
    "name:zho_x_preferred":[
        "\u7d22\u79d1\u7f57"
    ],
    "wof:name":"Socorro",
    "wof:placetype":"locality"
},
  "geometry": {"coordinates":[-75.63315,1.62763],"type":"Point"}
}