{
  "type": "Feature",
  "properties": {
    "gn:admin1_code":"36",
    "gn:admin2_code":"15442.0",
    "gn:asciiname":"El Boqueron",
    "gn:country_code":"CO",
    "gn:dem":1303,
    "gn:feature_class":"P",
    "gn:feature_code":"PPL",
    "gn:name":"El Boquer\u00f3n",
    "gn:population":0,
    "gn:timezone":"America/Bogota",
    "iso:country":"CO",
    "wof:name":"El Boqueron",
    "wof:placetype":"locality"
},
  "geometry": {"coordinates":[-74.01000000000001,5.57833],"type":"Point"}
}