{
  "type": "Feature",
  "properties": {
    "gn:admin1_code":"4.0",
    "gn:asciiname":"Monterrey",
    "gn:country_code":"CO",
    "gn:dem":5,
    "gn:feature_class":"P",
    "gn:feature_code":"PPL",
    "gn:name":"Monterrey",
    "gn:population":0,
    "gn:timezone":"America/Bogota",
    "iso:country":"CO",
    "wof:name":"Monterrey",
    "wof:placetype":"locality"
},
  "geometry": {"coordinates":[-74.73166999999999,10.85056],"type":"Point"}
}