{
  "type": "Feature",
  "properties": {
    "gn:admin1_code":"4.0",
    "gn:admin2_code":"8436.0",
    "gn:asciiname":"Auyamal",
    "gn:country_code":"CO",
    "gn:dem":6,
    "gn:feature_class":"P",
    "gn:feature_code":"PPL",
    "gn:name":"Auyamal",
    "gn:population":0,
    "gn:timezone":"America/Bogota",
    "iso:country":"CO",
    "wof:name":"Auyamal",
    "wof:placetype":"locality"
},
  "geometry": {"coordinates":[-75.04841999999999,10.44966],"type":"Point"}
}