{
  "type": "Feature",
  "properties": {
    "gn:admin1_code":"27",
    "gn:asciiname":"El Islote",
    "gn:country_code":"CO",
    "gn:dem":-9999,
    "gn:feature_class":"P",
    "gn:feature_code":"PPL",
    "gn:name":"El Islote",
    "gn:population":0,
    "gn:timezone":"America/Bogota",
    "iso:country":"CO",
    "name:und_x_variant":[
        "Islote",
        "El Islote"
    ],
    "wof:name":"El Islote",
    "wof:placetype":"locality"
},
  "geometry": {"coordinates":[-75.85876,9.78499],"type":"Point"}
}