{
  "type": "Feature",
  "properties": {
    "gn:admin1_code":"38.0",
    "gn:admin2_code":"47555.0",
    "gn:asciiname":"Tres Reales",
    "gn:country_code":"CO",
    "gn:dem":113,
    "gn:feature_class":"P",
    "gn:feature_code":"PPL",
    "gn:name":"Tres Reales",
    "gn:population":0,
    "gn:timezone":"America/Bogota",
    "iso:country":"CO",
    "wof:name":"Tres Reales",
    "wof:placetype":"locality"
},
  "geometry": {"coordinates":[-74.50558000000002,9.8307],"type":"Point"}
}