{
  "type": "Feature",
  "properties": {
    "gn:country":"CO",
    "gn:fcode":"PPL",
    "gn:pop":1432,
    "iso:country":"CO",
    "name:ast_x_preferred":[
        "Sutamarch\u00e1n"
    ],
    "name:ceb_x_preferred":[
        "Sutamarch\u00e1n"
    ],
    "name:eng_x_preferred":[
        "Sutamarch\u00e1n"
    ],
    "name:fra_x_preferred":[
        "Sutamarch\u00e1n"
    ],
    "name:ita_x_preferred":[
        "Sutamarch\u00e1n"
    ],
    "name:kat_x_preferred":[
        "\u10e1\u10e3\u10e2\u10d0\u10db\u10d0\u10e0\u10e9\u10d0\u10dc\u10d8"
    ],
    "name:msa_x_preferred":[
        "Sutamarch\u00e1n"
    ],
    "name:nan_x_preferred":[
        "Sutamarch\u00e1n"
    ],
    "name:nld_x_preferred":[
        "Sutamarch\u00e1n"
    ],
    "name:por_x_preferred":[
        "Sutamarchan"
    ],
    "name:rus_x_preferred":[
        "\u0421\u0443\u0442\u0430\u043c\u0430\u0440\u0447\u0430\u043d"
    ],
    "name:spa_x_preferred":[
        "Sutamarch\u00e1n"
    ],
    "name:swe_x_preferred":[
        "Sutamarch\u00e1n"
    ],
    "name:tgl_x_preferred":[
        "Sutamarch\u00e1n"
    ],
    "name:vie_x_preferred":[
        "Sutamarch\u00e1n"
    ],
    "name:war_x_preferred":[
        "Sutamarch\u00e1n"
    ],
    "name:zho_x_preferred":[
        "\u8607\u5854\u99ac\u9322"
    ],
    "qs:name":"Sutamarch\u00e1n",
    "qs:photos_9r":0,
    "qs:photos_sr":0,
    "qs:pop_sr":"3",
    "wd:wordcount":262,
    "wof:name":"Sutamarch\u00e1n",
    "wof:placetype":"locality",
    "wof:population":1432
},
  "geometry": {"coordinates":[-73.61700999999999,5.61538],"type":"Point"}
}