{
  "type": "Feature",
  "properties": {
    "gn:admin1_code":"26",
    "gn:admin2_code":"68572.0",
    "gn:asciiname":"Alto La Meseta",
    "gn:country_code":"CO",
    "gn:dem":1631,
    "gn:feature_class":"P",
    "gn:feature_code":"PPL",
    "gn:name":"Alto La Meseta",
    "gn:population":0,
    "gn:timezone":"America/Bogota",
    "iso:country":"CO",
    "wof:name":"Alto La Meseta",
    "wof:placetype":"locality"
},
  "geometry": {"coordinates":[-73.63265,5.90465],"type":"Point"}
}