{
  "type": "Feature",
  "properties": {
    "gn:admin1_code":"2.0",
    "gn:admin2_code":"5360.0",
    "gn:asciiname":"Vereda Loma De Los Zuelta",
    "gn:country_code":"CO",
    "gn:dem":1791,
    "gn:feature_class":"P",
    "gn:feature_code":"PPLL",
    "gn:name":"Vereda Loma De Los Zuelta",
    "gn:population":0,
    "gn:timezone":"America/Bogota",
    "iso:country":"CO",
    "name:spa_x_preferred":[
        "Vereda Loma De Los Zuelta"
    ],
    "wof:name":"Vereda Loma De Los Zuelta",
    "wof:placetype":"locality"
},
  "geometry": {"coordinates":[-75.62011,6.17947],"type":"Point"}
}