{
  "type": "Feature",
  "properties": {
    "gn:admin1_code":"16",
    "gn:admin2_code":"41885.0",
    "gn:asciiname":"Chile",
    "gn:country_code":"CO",
    "gn:dem":829,
    "gn:feature_class":"P",
    "gn:feature_code":"PPL",
    "gn:name":"Chile",
    "gn:population":0,
    "gn:timezone":"America/Bogota",
    "iso:country":"CO",
    "wof:name":"Chile",
    "wof:placetype":"locality"
},
  "geometry": {"coordinates":[-75.54889,2.68028],"type":"Point"}
}