{
  "type": "Feature",
  "properties": {
    "gn:admin1_code":"10",
    "gn:admin2_code":"20178.0",
    "gn:asciiname":"Hacienda La Sierra",
    "gn:country_code":"CO",
    "gn:dem":54,
    "gn:feature_class":"P",
    "gn:feature_code":"PPL",
    "gn:name":"Hacienda La Sierra",
    "gn:population":0,
    "gn:timezone":"America/Bogota",
    "iso:country":"CO",
    "name:und_x_variant":[
        "La Sierra"
    ],
    "wof:name":"Hacienda La Sierra",
    "wof:placetype":"locality"
},
  "geometry": {"coordinates":[-73.5197,9.37008],"type":"Point"}
}