{
  "type": "Feature",
  "properties": {
    "gn:admin1_code":"19.0",
    "gn:admin2_code":"50573.0",
    "gn:asciiname":"Vuelta Larga",
    "gn:country_code":"CO",
    "gn:dem":179,
    "gn:feature_class":"P",
    "gn:feature_code":"PPL",
    "gn:name":"Vuelta Larga",
    "gn:population":0,
    "gn:timezone":"America/Bogota",
    "iso:country":"CO",
    "wof:name":"Vuelta Larga",
    "wof:placetype":"locality"
},
  "geometry": {"coordinates":[-72.22346,3.91739],"type":"Point"}
}