{
  "type": "Feature",
  "properties": {
    "gn:admin1_code":"33.0",
    "gn:admin2_code":"25841.0",
    "gn:asciiname":"Alejandria",
    "gn:country_code":"CO",
    "gn:dem":1998,
    "gn:feature_class":"P",
    "gn:feature_code":"PPL",
    "gn:name":"Alejandr\u00eda",
    "gn:population":0,
    "gn:timezone":"America/Bogota",
    "iso:country":"CO",
    "wof:name":"Alejandria",
    "wof:placetype":"locality"
},
  "geometry": {"coordinates":[-73.95636,4.47949],"type":"Point"}
}