{
  "type": "Feature",
  "properties": {
    "gn:admin1_code":"28.0",
    "gn:admin2_code":"73024.0",
    "gn:asciiname":"Vega Grande",
    "gn:country_code":"CO",
    "gn:dem":700,
    "gn:feature_class":"P",
    "gn:feature_code":"PPL",
    "gn:name":"Vega Grande",
    "gn:population":0,
    "gn:timezone":"America/Bogota",
    "iso:country":"CO",
    "name:spa_x_preferred":[
        "Vega Grande"
    ],
    "wof:name":"Vega Grande",
    "wof:placetype":"locality"
},
  "geometry": {"coordinates":[-74.83816999999998,3.36786],"type":"Point"}
}