{
  "type": "Feature",
  "properties": {
    "gn:admin1_code":"9",
    "gn:admin2_code":"19130.0",
    "gn:asciiname":"Los Lorios",
    "gn:country_code":"CO",
    "gn:dem":1693,
    "gn:feature_class":"P",
    "gn:feature_code":"PPL",
    "gn:name":"Los Lorios",
    "gn:population":0,
    "gn:timezone":"America/Bogota",
    "iso:country":"CO",
    "wof:name":"Los Lorios",
    "wof:placetype":"locality"
},
  "geometry": {"coordinates":[-76.73990000000001,2.65055],"type":"Point"}
}