{
  "type": "Feature",
  "properties": {
    "gn:admin1_code":"37",
    "gn:admin2_code":"17013.0",
    "gn:asciiname":"El Oro",
    "gn:country_code":"CO",
    "gn:dem":957,
    "gn:feature_class":"P",
    "gn:feature_code":"PPL",
    "gn:name":"El Oro",
    "gn:population":0,
    "gn:timezone":"America/Bogota",
    "iso:country":"CO",
    "name:ceb_x_preferred":[
        "El Oro"
    ],
    "name:deu_x_preferred":[
        "El Oro"
    ],
    "name:epo_x_preferred":[
        "El Oro"
    ],
    "name:ita_x_preferred":[
        "El Oro"
    ],
    "name:lad_x_preferred":[
        "El Oro"
    ],
    "name:sco_x_preferred":[
        "El Oro"
    ],
    "name:spa_x_preferred":[
        "El Oro"
    ],
    "name:srp_x_preferred":[
        "\u0415\u043b \u041e\u0440\u043e"
    ],
    "name:swe_x_preferred":[
        "El Oro"
    ],
    "wof:name":"El Oro",
    "wof:placetype":"locality"
},
  "geometry": {"coordinates":[-75.54544,5.68901],"type":"Point"}
}