{
  "type": "Feature",
  "properties": {
    "gn:admin1_code":"27",
    "gn:admin2_code":"70124.0",
    "gn:asciiname":"Hispania",
    "gn:country_code":"CO",
    "gn:dem":20,
    "gn:feature_class":"P",
    "gn:feature_code":"PPL",
    "gn:name":"Hispania",
    "gn:population":0,
    "gn:timezone":"America/Bogota",
    "iso:country":"CO",
    "wof:name":"Hispania",
    "wof:placetype":"locality"
},
  "geometry": {"coordinates":[-75.10939,8.78128],"type":"Point"}
}