{
  "type": "Feature",
  "properties": {
    "gn:admin1_code":"9.0",
    "gn:admin2_code":"19142.0",
    "gn:asciiname":"Camilo Torres",
    "gn:country_code":"CO",
    "gn:dem":1045,
    "gn:feature_class":"P",
    "gn:feature_code":"PPL",
    "gn:name":"Camilo Torres",
    "gn:population":0,
    "gn:timezone":"America/Bogota",
    "iso:country":"CO",
    "name:rus_x_preferred":[
        "\u0422\u043e\u0440\u0440\u0435\u0441"
    ],
    "name:spa_x_preferred":[
        "Camilo Torres"
    ],
    "wof:name":"Camilo Torres",
    "wof:placetype":"locality"
},
  "geometry": {"coordinates":[-76.4104,3.06859],"type":"Point"}
}