{
  "type": "Feature",
  "properties": {
    "gn:admin1_code":"19.0",
    "gn:admin2_code":"50001.0",
    "gn:asciiname":"Playa Linda",
    "gn:country_code":"CO",
    "gn:dem":491,
    "gn:feature_class":"P",
    "gn:feature_code":"PPL",
    "gn:name":"Playa Linda",
    "gn:population":0,
    "gn:timezone":"America/Bogota",
    "iso:country":"CO",
    "name:spa_x_preferred":[
        "Playa Linda"
    ],
    "wof:name":"Playa Linda",
    "wof:placetype":"locality"
},
  "geometry": {"coordinates":[-73.73298,4.03583],"type":"Point"}
}