{
  "type": "Feature",
  "properties": {
    "gn:admin1_code":"26.0",
    "gn:admin2_code":"68655.0",
    "gn:asciiname":"Veracruz",
    "gn:country_code":"CO",
    "gn:dem":65,
    "gn:feature_class":"P",
    "gn:feature_code":"PPL",
    "gn:name":"Veracruz",
    "gn:population":0,
    "gn:timezone":"America/Bogota",
    "iso:country":"CO",
    "wof:name":"Veracruz",
    "wof:placetype":"locality"
},
  "geometry": {"coordinates":[-73.65889,7.48583],"type":"Point"}
}