{
  "type": "Feature",
  "properties": {
    "gn:admin1_code":"33.0",
    "gn:admin2_code":"25799.0",
    "gn:asciiname":"Tiquisa",
    "gn:country_code":"CO",
    "gn:dem":2700,
    "gn:feature_class":"P",
    "gn:feature_code":"PPL",
    "gn:name":"Tiquisa",
    "gn:population":0,
    "gn:timezone":"America/Bogota",
    "iso:country":"CO",
    "wof:name":"Tiquisa",
    "wof:placetype":"locality"
},
  "geometry": {"coordinates":[-74.08333,4.88333],"type":"Point"}
}