{
  "type": "Feature",
  "properties": {
    "gn:admin1_code":"27",
    "gn:asciiname":"Los Deseos",
    "gn:country_code":"CO",
    "gn:dem":144,
    "gn:feature_class":"P",
    "gn:feature_code":"PPL",
    "gn:name":"Los Deseos",
    "gn:population":0,
    "gn:timezone":"America/Bogota",
    "iso:country":"CO",
    "name:und_x_variant":[
        "Hacienda Los Deseos",
        "Los Deseos"
    ],
    "wof:name":"Los Deseos",
    "wof:placetype":"locality"
},
  "geometry": {"coordinates":[-75.34144999999999,9.68651],"type":"Point"}
}