{
  "type": "Feature",
  "properties": {
    "iso:country":"CO",
    "name:unk_x_variant":[
        "Corregimiento Puerto Rico"
    ],
    "qs:gn_country":"CO",
    "qs:gn_fcode":"PPL",
    "qs:gn_pop":0,
    "qs:name":"Puerto Rico",
    "qs:name_adm0":"Colombia",
    "qs:name_adm1":"Bolivar",
    "qs:photos":5,
    "qs:photos_1k":1,
    "qs:photos_9k":1,
    "qs:photos_9r":1,
    "qs:photos_all":5,
    "qs:photos_sr":1,
    "qs:placetype":"Town",
    "qs:pop_sr":"0",
    "qs:woe_adm0":23424787,
    "wof:name":"Puerto Rico",
    "wof:placetype":"locality"
},
  "geometry": {"coordinates":[-74.26331,8.55644],"type":"Point"}
}