{
  "type": "Feature",
  "properties": {
    "gn:admin1_code":"29.0",
    "gn:admin2_code":"76109.0",
    "gn:asciiname":"Campo Alegre",
    "gn:country_code":"CO",
    "gn:dem":11,
    "gn:feature_class":"P",
    "gn:feature_code":"PPL",
    "gn:name":"Campo Alegre",
    "gn:population":0,
    "gn:timezone":"America/Bogota",
    "iso:country":"CO",
    "wof:name":"Campo Alegre",
    "wof:placetype":"locality"
},
  "geometry": {"coordinates":[-77.03842,3.81205],"type":"Point"}
}