{
  "type": "Feature",
  "properties": {
    "gn:admin1_code":"36.0",
    "gn:admin2_code":"15572.0",
    "gn:asciiname":"Palonegro",
    "gn:country_code":"CO",
    "gn:dem":153,
    "gn:feature_class":"P",
    "gn:feature_code":"PPL",
    "gn:name":"Palonegro",
    "gn:population":0,
    "gn:timezone":"America/Bogota",
    "iso:country":"CO",
    "wof:name":"Palonegro",
    "wof:placetype":"locality"
},
  "geometry": {"coordinates":[-74.61667,5.88333],"type":"Point"}
}