{
  "type": "Feature",
  "properties": {
    "gn:admin1_code":"29",
    "gn:admin2_code":"76606.0",
    "gn:asciiname":"Los Cedros",
    "gn:country_code":"CO",
    "gn:dem":1657,
    "gn:feature_class":"P",
    "gn:feature_code":"PPL",
    "gn:name":"Los Cedros",
    "gn:population":0,
    "gn:timezone":"America/Bogota",
    "iso:country":"CO",
    "wof:name":"Los Cedros",
    "wof:placetype":"locality"
},
  "geometry": {"coordinates":[-76.58333,3.83333],"type":"Point"}
}