{
  "type": "Feature",
  "properties": {
    "iso:country":"CO",
    "name:ast_x_preferred":[
        "Roncesvalles"
    ],
    "name:avk_x_preferred":[
        "Roncesvalles"
    ],
    "name:cat_x_preferred":[
        "Roncesvalles"
    ],
    "name:ceb_x_preferred":[
        "Roncesvalles"
    ],
    "name:eng_x_preferred":[
        "Roncesvalles"
    ],
    "name:fas_x_preferred":[
        "\u0631\u0648\u0646\u0633\u0633\u0648\u0627\u0644\u0633"
    ],
    "name:fra_x_preferred":[
        "Roncesvalles"
    ],
    "name:gle_x_preferred":[
        "Roncesvalles"
    ],
    "name:ita_x_preferred":[
        "Roncesvalles"
    ],
    "name:kat_x_preferred":[
        "\u10e0\u10dd\u10dc\u10e1\u10d4\u10e1\u10d5\u10d0\u10da\u10d8\u10d4\u10e1\u10d8"
    ],
    "name:msa_x_preferred":[
        "Roncesvalles"
    ],
    "name:nan_x_preferred":[
        "Roncesvalles"
    ],
    "name:nld_x_preferred":[
        "Roncesvalles"
    ],
    "name:pol_x_preferred":[
        "Roncesvalles"
    ],
    "name:spa_x_preferred":[
        "Roncesvalles"
    ],
    "name:swe_x_preferred":[
        "Roncesvalles"
    ],
    "name:war_x_preferred":[
        "Roncesvalles"
    ],
    "name:zho_min_nan_x_preferred":[
        "Roncesvalles"
    ],
    "name:zho_x_preferred":[
        "\u9f8d\u585e\u65af\u74e6\u8036\u65af"
    ],
    "qs:gn_country":"CO",
    "qs:gn_fcode":"PPL",
    "qs:gn_pop":3918,
    "qs:name":"Roncesvalles",
    "qs:name_adm0":"Colombia",
    "qs:name_adm1":"Tolima",
    "qs:photos":0,
    "qs:photos_1k":0,
    "qs:photos_9k":1,
    "qs:photos_9r":2,
    "qs:photos_all":41,
    "qs:photos_sr":0,
    "qs:placetype":"Town",
    "qs:pop_sr":"4",
    "qs:woe_adm0":23424787,
    "wd:wordcount":45,
    "wof:name":"Roncesvalles",
    "wof:placetype":"locality",
    "wof:population":3918
},
  "geometry": {"coordinates":[-75.60493,4.0108],"type":"Point"}
}