{
  "type": "Feature",
  "properties": {
    "gn:admin1_code":"2",
    "gn:admin2_code":"5250.0",
    "gn:asciiname":"La Corona",
    "gn:country_code":"CO",
    "gn:dem":98,
    "gn:feature_class":"P",
    "gn:feature_code":"PPL",
    "gn:name":"La Corona",
    "gn:population":0,
    "gn:timezone":"America/Bogota",
    "iso:country":"CO",
    "wof:name":"La Corona",
    "wof:placetype":"locality"
},
  "geometry": {"coordinates":[-74.67814,7.63456],"type":"Point"}
}