{
  "type": "Feature",
  "properties": {
    "gn:admin1_code":"2",
    "gn:admin2_code":"5250.0",
    "gn:asciiname":"La Corona",
    "gn:country_code":"CO",
    "gn:dem":98,
    "gn:feature_class":"P",
    "gn:feature_code":"PPL",
    "gn:name":"La Corona",
    "gn:population":0,
    "gn:timezone":"America/Bogota",
    "iso:country":"CO",
    "name:deu_x_preferred":[
        "La Corona"
    ],
    "name:epo_x_preferred":[
        "La Corona"
    ],
    "name:fra_x_preferred":[
        "La Corona"
    ],
    "name:ita_x_preferred":[
        "La Corona"
    ],
    "name:jpn_x_preferred":[
        "\u30e9\u30fb\u30b3\u30ed\u30ca"
    ],
    "name:rus_x_preferred":[
        "\u041b\u0430-\u041a\u043e\u0440\u043e\u043d\u0430"
    ],
    "name:spa_x_preferred":[
        "La Corona"
    ],
    "name:ukr_x_preferred":[
        "\u041b\u0430-\u041a\u043e\u0440\u043e\u043d\u0430"
    ],
    "wof:name":"La Corona",
    "wof:placetype":"locality"
},
  "geometry": {"coordinates":[-74.67814,7.63456],"type":"Point"}
}