{
  "type": "Feature",
  "properties": {
    "gn:admin1_code":"16.0",
    "gn:admin2_code":"41298.0",
    "gn:asciiname":"El Pantano",
    "gn:country_code":"CO",
    "gn:dem":786,
    "gn:feature_class":"P",
    "gn:feature_code":"PPL",
    "gn:name":"El Pantano",
    "gn:population":0,
    "gn:timezone":"America/Bogota",
    "iso:country":"CO",
    "name:ita_x_preferred":[
        "El Pantano"
    ],
    "name:spa_x_preferred":[
        "El Pantano"
    ],
    "name:zho_x_preferred":[
        "\u57c3\u5c14\u6f58\u5854\u8bfa"
    ],
    "wof:name":"El Pantano",
    "wof:placetype":"locality"
},
  "geometry": {"coordinates":[-75.63444,2.21583],"type":"Point"}
}