{
  "type": "Feature",
  "properties": {
    "gn:admin1_code":"26",
    "gn:admin2_code":"68573.0",
    "gn:asciiname":"Garceros",
    "gn:country_code":"CO",
    "gn:dem":90,
    "gn:feature_class":"P",
    "gn:feature_code":"PPL",
    "gn:name":"Garceros",
    "gn:population":0,
    "gn:timezone":"America/Bogota",
    "iso:country":"CO",
    "wof:name":"Garceros",
    "wof:placetype":"locality"
},
  "geometry": {"coordinates":[-74.09999999999999,6.65],"type":"Point"}
}