{
  "type": "Feature",
  "properties": {
    "iso:country":"CO",
    "name:ast_x_preferred":[
        "Puerto Escondido"
    ],
    "name:ceb_x_preferred":[
        "Puerto Escondido"
    ],
    "name:deu_x_preferred":[
        "Puerto Escondido"
    ],
    "name:eng_x_preferred":[
        "Puerto Escondido"
    ],
    "name:fas_x_preferred":[
        "\u067e\u0648\u0631\u062a\u0648 \u0627\u0633\u06a9\u0648\u0646\u062f\u06cc\u062f\u0648"
    ],
    "name:fra_x_preferred":[
        "Puerto Escondido"
    ],
    "name:ita_x_preferred":[
        "Puerto Escondido"
    ],
    "name:jpn_x_preferred":[
        "\u30d7\u30a8\u30eb\u30c8\u30fb\u30a8\u30b9\u30b3\u30f3\u30c7\u30a3\u30fc\u30c9"
    ],
    "name:kat_x_preferred":[
        "\u10de\u10e3\u10d4\u10e0\u10e2\u10dd-\u10d4\u10e1\u10d9\u10dd\u10dc\u10d3\u10d8\u10d3\u10dd"
    ],
    "name:msa_x_preferred":[
        "Puerto Escondido"
    ],
    "name:nan_x_preferred":[
        "Puerto Escondido"
    ],
    "name:nld_x_preferred":[
        "Puerto Escondido"
    ],
    "name:pol_x_preferred":[
        "Puerto Escondido"
    ],
    "name:por_x_preferred":[
        "Puerto Escondido"
    ],
    "name:rus_x_preferred":[
        "\u041f\u0443\u044d\u0440\u0442\u043e-\u042d\u0441\u043a\u043e\u043d\u0434\u0438\u0434\u043e"
    ],
    "name:sco_x_preferred":[
        "Puerto Escondido"
    ],
    "name:spa_x_preferred":[
        "Puerto Escondido"
    ],
    "name:swe_x_preferred":[
        "Puerto Escondido"
    ],
    "name:tgl_x_preferred":[
        "Puerto Escondido"
    ],
    "name:unk_x_variant":[
        "Puerto Escondito"
    ],
    "name:vie_x_preferred":[
        "Puerto Escondido"
    ],
    "name:war_x_preferred":[
        "Puerto Escondido"
    ],
    "name:zho_x_preferred":[
        "\u57c3\u65af\u5b54\u8fea\u591a\u6e2f"
    ],
    "qs:gn_country":"CO",
    "qs:gn_fcode":"PPL",
    "qs:gn_pop":3020,
    "qs:name":"Puerto Escondido",
    "qs:name_adm0":"Colombia",
    "qs:name_adm1":"Cordoba",
    "qs:photos":13,
    "qs:photos_1k":3,
    "qs:photos_9k":1,
    "qs:photos_9r":1,
    "qs:photos_all":13,
    "qs:photos_sr":1,
    "qs:placetype":"Town",
    "qs:pop_sr":"4",
    "qs:woe_adm0":23424787,
    "wd:wordcount":26,
    "wof:name":"Puerto Escondido",
    "wof:placetype":"locality",
    "wof:population":3020
},
  "geometry": {"coordinates":[-76.26412999999999,9.0181],"type":"Point"}
}