{
  "type": "Feature",
  "properties": {
    "gn:admin1_code":"2.0",
    "gn:admin2_code":"5761.0",
    "gn:asciiname":"Corral Falso",
    "gn:country_code":"CO",
    "gn:dem":464,
    "gn:feature_class":"P",
    "gn:feature_code":"PPL",
    "gn:name":"Corral Falso",
    "gn:population":0,
    "gn:timezone":"America/Bogota",
    "iso:country":"CO",
    "wof:name":"Corral Falso",
    "wof:placetype":"locality"
},
  "geometry": {"coordinates":[-75.79666999999998,6.51083],"type":"Point"}
}