{
  "type": "Feature",
  "properties": {
    "gn:admin1_code":"17",
    "gn:admin2_code":"44001.0",
    "gn:asciiname":"La Courrita",
    "gn:country_code":"CO",
    "gn:dem":30,
    "gn:feature_class":"P",
    "gn:feature_code":"PPL",
    "gn:name":"La Courrita",
    "gn:population":0,
    "gn:timezone":"America/Bogota",
    "iso:country":"CO",
    "wof:name":"La Courrita",
    "wof:placetype":"locality"
},
  "geometry": {"coordinates":[-72.91611,11.49583],"type":"Point"}
}