{
  "type": "Feature",
  "properties": {
    "gn:admin1_code":"36",
    "gn:admin2_code":"15816.0",
    "gn:asciiname":"El Mirto",
    "gn:country_code":"CO",
    "gn:dem":1805,
    "gn:feature_class":"P",
    "gn:feature_code":"PPL",
    "gn:name":"El Mirto",
    "gn:population":0,
    "gn:timezone":"America/Bogota",
    "iso:country":"CO",
    "wof:name":"El Mirto",
    "wof:placetype":"locality"
},
  "geometry": {"coordinates":[-73.48728,5.95765],"type":"Point"}
}