{
  "type": "Feature",
  "properties": {
    "gn:admin1_code":"32",
    "gn:admin2_code":"85430.0",
    "gn:asciiname":"La Libertad",
    "gn:country_code":"CO",
    "gn:dem":145,
    "gn:feature_class":"P",
    "gn:feature_code":"PPL",
    "gn:name":"La Libertad",
    "gn:population":0,
    "gn:timezone":"America/Bogota",
    "iso:country":"CO",
    "wof:name":"La Libertad",
    "wof:placetype":"locality"
},
  "geometry": {"coordinates":[-71.38333,5.36667],"type":"Point"}
}