{
  "type": "Feature",
  "properties": {
    "gn:admin1_code":"2.0",
    "gn:admin2_code":"5658.0",
    "gn:asciiname":"El Cedral",
    "gn:country_code":"CO",
    "gn:dem":2489,
    "gn:feature_class":"P",
    "gn:feature_code":"PPL",
    "gn:name":"El Cedral",
    "gn:population":0,
    "gn:timezone":"America/Bogota",
    "iso:country":"CO",
    "wof:name":"El Cedral",
    "wof:placetype":"locality"
},
  "geometry": {"coordinates":[-75.67833,6.88083],"type":"Point"}
}