{
  "type": "Feature",
  "properties": {
    "gn:admin1_code":"38",
    "gn:admin2_code":"47245.0",
    "gn:asciiname":"Sabaneta",
    "gn:country_code":"CO",
    "gn:dem":45,
    "gn:feature_class":"P",
    "gn:feature_code":"PPL",
    "gn:name":"Sabaneta",
    "gn:population":0,
    "gn:timezone":"America/Bogota",
    "iso:country":"CO",
    "wof:name":"Sabaneta",
    "wof:placetype":"locality"
},
  "geometry": {"coordinates":[-73.97778000000002,9.24611],"type":"Point"}
}