{
  "type": "Feature",
  "properties": {
    "gn:admin1_code":"10.0",
    "gn:admin2_code":"20614.0",
    "gn:asciiname":"Once Reses",
    "gn:cc2":"CO",
    "gn:country_code":"CO",
    "gn:dem":103,
    "gn:feature_class":"P",
    "gn:feature_code":"PPL",
    "gn:name":"Once Reses",
    "gn:population":0,
    "gn:timezone":"America/Bogota",
    "iso:country":"CO",
    "name:und_x_variant":[
        "Once Recetas",
        "Once Reses"
    ],
    "wof:name":"Once Reses",
    "wof:placetype":"locality"
},
  "geometry": {"coordinates":[-73.56667,8.11667],"type":"Point"}
}