{
  "type": "Feature",
  "properties": {
    "gn:admin1_code":"3",
    "gn:admin2_code":"81001.0",
    "gn:asciiname":"Las Queseras",
    "gn:country_code":"CO",
    "gn:dem":119,
    "gn:feature_class":"P",
    "gn:feature_code":"PPL",
    "gn:name":"Las Queseras",
    "gn:population":0,
    "gn:timezone":"America/Bogota",
    "iso:country":"CO",
    "name:spa_x_preferred":[
        "Las Queseras"
    ],
    "wof:name":"Las Queseras",
    "wof:placetype":"locality"
},
  "geometry": {"coordinates":[-70.67508000000002,6.5525],"type":"Point"}
}