{
  "type": "Feature",
  "properties": {
    "gn:admin1_code":"12.0",
    "gn:admin2_code":"23189.0",
    "gn:asciiname":"Pasatiempo",
    "gn:country_code":"CO",
    "gn:dem":74,
    "gn:feature_class":"P",
    "gn:feature_code":"PPLL",
    "gn:name":"Pasatiempo",
    "gn:population":0,
    "gn:timezone":"America/Bogota",
    "iso:country":"CO",
    "wof:name":"Pasatiempo",
    "wof:placetype":"locality"
},
  "geometry": {"coordinates":[-75.5612,8.81983],"type":"Point"}
}