{
  "type": "Feature",
  "properties": {
    "gn:admin1_code":"1",
    "gn:admin2_code":"91263.0",
    "gn:asciiname":"Barras",
    "gn:country_code":"CO",
    "gn:dem":136,
    "gn:feature_class":"P",
    "gn:feature_code":"PPL",
    "gn:name":"Barras",
    "gn:population":0,
    "gn:timezone":"America/Bogota",
    "iso:country":"CO",
    "name:ceb_x_preferred":[
        "Barras"
    ],
    "name:deu_x_preferred":[
        "Barras"
    ],
    "name:fra_x_preferred":[
        "Barras"
    ],
    "name:ita_x_preferred":[
        "Barras"
    ],
    "name:jpn_x_preferred":[
        "\u30d0\u30e9\u30b9"
    ],
    "name:kat_x_preferred":[
        "\u10d1\u10d0\u10e0\u10d0\u10e1\u10d8"
    ],
    "name:nld_x_preferred":[
        "Barras"
    ],
    "name:pol_x_preferred":[
        "Barras"
    ],
    "name:por_x_preferred":[
        "Barras"
    ],
    "name:rus_x_preferred":[
        "\u0411\u0430\u0440\u0440\u0430\u0441"
    ],
    "name:slk_x_preferred":[
        "Barras"
    ],
    "name:spa_x_preferred":[
        "Barras"
    ],
    "name:sqi_x_preferred":[
        "Barras"
    ],
    "name:swe_x_preferred":[
        "Barras"
    ],
    "name:vol_x_preferred":[
        "Barras"
    ],
    "wof:name":"Barras",
    "wof:placetype":"locality"
},
  "geometry": {"coordinates":[-73.20386999999999,-1.757],"type":"Point"}
}