{
  "type": "Feature",
  "properties": {
    "iso:country":"CO",
    "name:ast_x_preferred":[
        "\u00datica"
    ],
    "name:avk_x_preferred":[
        "\u00datica"
    ],
    "name:cat_x_preferred":[
        "\u00datica"
    ],
    "name:ceb_x_preferred":[
        "Utica"
    ],
    "name:ceb_x_variant":[
        "\u00datica"
    ],
    "name:eng_x_preferred":[
        "\u00datica"
    ],
    "name:fas_x_preferred":[
        "\u0627\u0648\u062a\u06cc\u06a9\u0627"
    ],
    "name:fra_x_preferred":[
        "\u00datica"
    ],
    "name:gle_x_preferred":[
        "\u00datica"
    ],
    "name:glg_x_preferred":[
        "\u00datica"
    ],
    "name:ita_x_preferred":[
        "\u00datica"
    ],
    "name:kat_x_preferred":[
        "\u10e3\u10e2\u10d8\u10d9\u10d0"
    ],
    "name:msa_x_preferred":[
        "\u00datica"
    ],
    "name:nan_x_preferred":[
        "\u00datica"
    ],
    "name:nld_x_preferred":[
        "\u00datica"
    ],
    "name:nob_x_preferred":[
        "\u00datica"
    ],
    "name:nor_x_preferred":[
        "\u00datica"
    ],
    "name:pol_x_preferred":[
        "\u00datica"
    ],
    "name:por_x_preferred":[
        "\u00datica"
    ],
    "name:spa_x_preferred":[
        "\u00datica"
    ],
    "name:swe_x_preferred":[
        "Utica"
    ],
    "name:swe_x_variant":[
        "\u00datica"
    ],
    "name:tgl_x_preferred":[
        "\u00datica"
    ],
    "name:vie_x_preferred":[
        "\u00datica"
    ],
    "name:war_x_preferred":[
        "\u00datica"
    ],
    "name:zho_x_preferred":[
        "\u70cf\u8482\u5361"
    ],
    "qs:gn_country":"CO",
    "qs:gn_fcode":"PPL",
    "qs:gn_pop":2945,
    "qs:name":"Utica",
    "qs:name_adm0":"Colombia",
    "qs:name_adm1":"Cundinamarca",
    "qs:photos":0,
    "qs:photos_1k":0,
    "qs:photos_9k":1,
    "qs:photos_9r":1,
    "qs:photos_all":1,
    "qs:photos_sr":0,
    "qs:placetype":"Town",
    "qs:pop_sr":"4",
    "qs:woe_adm0":23424787,
    "wd:wordcount":142,
    "wof:name":"Utica",
    "wof:placetype":"locality",
    "wof:population":2945
},
  "geometry": {"coordinates":[-74.48105,5.18727],"type":"Point"}
}