{
  "type": "Feature",
  "properties": {
    "gn:admin1_code":"37.0",
    "gn:admin2_code":"17867.0",
    "gn:asciiname":"Cimitarra",
    "gn:country_code":"CO",
    "gn:dem":248,
    "gn:feature_class":"P",
    "gn:feature_code":"PPL",
    "gn:name":"Cimitarra",
    "gn:population":0,
    "gn:timezone":"America/Bogota",
    "iso:country":"CO",
    "name:ceb_x_preferred":[
        "Cimitarra"
    ],
    "name:deu_x_preferred":[
        "Cimitarra"
    ],
    "name:fas_x_preferred":[
        "\u0633\u06cc\u0645\u06cc\u062a\u0627\u0631\u0627"
    ],
    "name:fra_x_preferred":[
        "Cimitarra"
    ],
    "name:glg_x_preferred":[
        "Cimitarra"
    ],
    "name:ita_x_preferred":[
        "Cimitarra"
    ],
    "name:msa_x_preferred":[
        "Cimitarra"
    ],
    "name:nld_x_preferred":[
        "Cimitarra"
    ],
    "name:spa_x_preferred":[
        "Cimitarra"
    ],
    "name:swe_x_preferred":[
        "Cimitarra"
    ],
    "name:tgl_x_preferred":[
        "Cimitarra"
    ],
    "name:vie_x_preferred":[
        "Cimitarra"
    ],
    "name:war_x_preferred":[
        "Cimitarra"
    ],
    "name:zho_x_preferred":[
        "\u932b\u7c73\u5854\u62c9"
    ],
    "wof:name":"Cimitarra",
    "wof:placetype":"locality"
},
  "geometry": {"coordinates":[-74.84402,5.46672],"type":"Point"}
}