{
  "type": "Feature",
  "properties": {
    "gn:admin1_code":"37.0",
    "gn:admin2_code":"17867.0",
    "gn:asciiname":"Cimitarra",
    "gn:country_code":"CO",
    "gn:dem":248,
    "gn:feature_class":"P",
    "gn:feature_code":"PPL",
    "gn:name":"Cimitarra",
    "gn:population":0,
    "gn:timezone":"America/Bogota",
    "iso:country":"CO",
    "name:spa_x_preferred":[
        "Cimitarra"
    ],
    "wof:name":"Cimitarra",
    "wof:placetype":"locality"
},
  "geometry": {"coordinates":[-74.84402,5.46672],"type":"Point"}
}