{
  "type": "Feature",
  "properties": {
    "gn:admin1_code":"28",
    "gn:admin2_code":"73563.0",
    "gn:asciiname":"Aco Nuevo",
    "gn:country_code":"CO",
    "gn:dem":372,
    "gn:feature_class":"P",
    "gn:feature_code":"PPL",
    "gn:name":"Aco Nuevo",
    "gn:population":0,
    "gn:timezone":"America/Bogota",
    "iso:country":"CO",
    "name:spa_x_preferred":[
        "Aco Nuevo"
    ],
    "wof:name":"Aco Nuevo",
    "wof:placetype":"locality"
},
  "geometry": {"coordinates":[-74.81118000000002,3.74871],"type":"Point"}
}