{
  "type": "Feature",
  "properties": {
    "gn:admin1_code":"17",
    "gn:admin2_code":"44430.0",
    "gn:asciiname":"Kaushamhana",
    "gn:country_code":"CO",
    "gn:dem":81,
    "gn:feature_class":"P",
    "gn:feature_code":"PPL",
    "gn:name":"Kaushamhana",
    "gn:population":0,
    "gn:timezone":"America/Bogota",
    "iso:country":"CO",
    "wof:name":"Kaushamhana",
    "wof:placetype":"locality"
},
  "geometry": {"coordinates":[-72.2475,11.23389],"type":"Point"}
}