{
  "type": "Feature",
  "properties": {
    "gn:admin1_code":"27",
    "gn:admin2_code":"70702.0",
    "gn:asciiname":"Loma El Latigo",
    "gn:country_code":"CO",
    "gn:dem":136,
    "gn:feature_class":"P",
    "gn:feature_code":"PPL",
    "gn:name":"Loma El L\u00e1tigo",
    "gn:population":0,
    "gn:timezone":"America/Bogota",
    "iso:country":"CO",
    "name:und_x_variant":[
        "Loma del Latigo",
        "Loma El L\u00e1tigo"
    ],
    "wof:name":"Loma El Latigo",
    "wof:placetype":"locality"
},
  "geometry": {"coordinates":[-75.22825999999998,9.21667],"type":"Point"}
}