{
  "type": "Feature",
  "properties": {
    "gn:admin1_code":"19",
    "gn:admin2_code":"50689",
    "gn:asciiname":"Molino El Ruiz",
    "gn:country_code":"CO",
    "gn:dem":422,
    "gn:feature_class":"P",
    "gn:feature_code":"PPL",
    "gn:name":"Molino El Ru\u00edz",
    "gn:population":0,
    "gn:timezone":"America/Bogota",
    "iso:country":"CO",
    "name:spa_x_preferred":[
        "Molino El Ru\u00edz"
    ],
    "wof:name":"Molino El Ruiz",
    "wof:placetype":"locality"
},
  "geometry": {"coordinates":[-73.71755999999998,3.67988],"type":"Point"}
}