{
  "type": "Feature",
  "properties": {
    "gn:admin1_code":"9",
    "gn:asciiname":"Loma Alta",
    "gn:country_code":"CO",
    "gn:dem":576,
    "gn:feature_class":"P",
    "gn:feature_code":"PPL",
    "gn:name":"Loma Alta",
    "gn:population":0,
    "gn:timezone":"America/Bogota",
    "iso:country":"CO",
    "wof:name":"Loma Alta",
    "wof:placetype":"locality"
},
  "geometry": {"coordinates":[-77.20968000000001,1.96298],"type":"Point"}
}