{
  "type": "Feature",
  "properties": {
    "gn:admin1_code":"33",
    "gn:admin2_code":"25320.0",
    "gn:asciiname":"Guacamayas",
    "gn:cc2":"CO",
    "gn:country_code":"CO",
    "gn:dem":1087,
    "gn:feature_class":"P",
    "gn:feature_code":"PPL",
    "gn:name":"Guacamayas",
    "gn:population":0,
    "gn:timezone":"America/Bogota",
    "iso:country":"CO",
    "name:und_x_variant":[
        "Guacamaya",
        "Guacamayas"
    ],
    "wof:name":"Guacamayas",
    "wof:placetype":"locality"
},
  "geometry": {"coordinates":[-74.61667,5.16667],"type":"Point"}
}