{
  "type": "Feature",
  "properties": {
    "gn:admin1_code":"38.0",
    "gn:admin2_code":"47707.0",
    "gn:asciiname":"Reparo de Guineo",
    "gn:country_code":"CO",
    "gn:dem":63,
    "gn:feature_class":"P",
    "gn:feature_code":"PPL",
    "gn:name":"Reparo de Guineo",
    "gn:population":0,
    "gn:timezone":"America/Bogota",
    "iso:country":"CO",
    "name:und_x_variant":[
        "Hacienda Reparo de Guineo",
        "Reparo de Guineo"
    ],
    "wof:name":"Reparo de Guineo",
    "wof:placetype":"locality"
},
  "geometry": {"coordinates":[-74.35468,9.43473],"type":"Point"}
}