{
  "type": "Feature",
  "properties": {
    "gn:admin1_code":"2.0",
    "gn:admin2_code":"5036.0",
    "gn:asciiname":"Corregimiento La Honda",
    "gn:country_code":"CO",
    "gn:dem":1560,
    "gn:feature_class":"P",
    "gn:feature_code":"PPLL",
    "gn:name":"Corregimiento La Honda",
    "gn:population":0,
    "gn:timezone":"America/Bogota",
    "iso:country":"CO",
    "name:spa_x_preferred":[
        "Corregimiento La Honda"
    ],
    "wof:name":"Corregimiento La Honda",
    "wof:placetype":"locality"
},
  "geometry": {"coordinates":[-75.70329,6.08386],"type":"Point"}
}