{
  "type": "Feature",
  "properties": {
    "gn:admin1_code":"15",
    "gn:admin2_code":"94883.0",
    "gn:asciiname":"Bocas de Casiquiare",
    "gn:country_code":"CO",
    "gn:dem":82,
    "gn:feature_class":"P",
    "gn:feature_code":"PPL",
    "gn:name":"Bocas de Casiquiare",
    "gn:population":0,
    "gn:timezone":"America/Bogota",
    "iso:country":"CO",
    "wof:name":"Bocas de Casiquiare",
    "wof:placetype":"locality"
},
  "geometry": {"coordinates":[-67.1293,1.99943],"type":"Point"}
}