{
  "type": "Feature",
  "properties": {
    "gn:admin1_code":"34.0",
    "gn:admin2_code":"11001.0",
    "gn:admin3_code":"3.0",
    "gn:asciiname":"Sede G CUN",
    "gn:country_code":"CO",
    "gn:dem":2625,
    "gn:elevation":"2625.0",
    "gn:feature_class":"P",
    "gn:feature_code":"PPLF",
    "gn:name":"Sede G CUN",
    "gn:population":0,
    "gn:timezone":"America/Bogota",
    "iso:country":"CO",
    "wof:name":"Sede G CUN",
    "wof:placetype":"locality"
},
  "geometry": {"coordinates":[-74.06922,4.60248],"type":"Point"}
}