{
  "type": "Feature",
  "properties": {
    "gn:country":"CO",
    "gn:fcode":"PPL",
    "gn:pop":4880,
    "iso:country":"CO",
    "name:eng_x_preferred":[
        "Cotorra"
    ],
    "name:fra_x_preferred":[
        "Cotorra"
    ],
    "name:ita_x_preferred":[
        "Cotorra"
    ],
    "name:kat_x_preferred":[
        "\u10d9\u10dd\u10e2\u10dd\u10e0\u10d0"
    ],
    "name:msa_x_preferred":[
        "Cotorra"
    ],
    "name:nan_x_preferred":[
        "Cotorra"
    ],
    "name:nld_x_preferred":[
        "Cotorra"
    ],
    "name:por_x_preferred":[
        "Cotorra"
    ],
    "name:spa_x_preferred":[
        "Cotorra"
    ],
    "name:swe_x_preferred":[
        "Cotorra"
    ],
    "name:tgl_x_preferred":[
        "Cotorra"
    ],
    "name:unk_x_variant":[
        "Corregimiento Cotorra"
    ],
    "name:vie_x_preferred":[
        "Cotorra"
    ],
    "name:war_x_preferred":[
        "Cotorra"
    ],
    "name:zho_x_preferred":[
        "\u79d1\u6258\u62c9"
    ],
    "qs:name":"Cotorra",
    "qs:photos_9r":0,
    "qs:photos_sr":0,
    "qs:pop_sr":"4",
    "wd:wordcount":35,
    "wof:name":"Cotorra",
    "wof:placetype":"locality",
    "wof:population":4880
},
  "geometry": {"coordinates":[-75.78968999999999,9.03886],"type":"Point"}
}