{
  "type": "Feature",
  "properties": {
    "gn:country":"CO",
    "gn:fcode":"PPL",
    "gn:population":4880,
    "iso:country":"CO",
    "name:ast_x_preferred":[
        "Cotorra"
    ],
    "name:avk_x_preferred":[
        "Cotorra"
    ],
    "name:ceb_x_preferred":[
        "Cotorra"
    ],
    "name:eng_x_preferred":[
        "Cotorra"
    ],
    "name:fas_x_preferred":[
        "\u06a9\u0648\u062a\u0648\u0631\u0627"
    ],
    "name:fra_x_preferred":[
        "Cotorra"
    ],
    "name:gle_x_preferred":[
        "Cotorra"
    ],
    "name:hye_x_preferred":[
        "\u053f\u0578\u057f\u0578\u0580\u0561"
    ],
    "name:ita_x_preferred":[
        "Cotorra"
    ],
    "name:kat_x_preferred":[
        "\u10d9\u10dd\u10e2\u10dd\u10e0\u10d0"
    ],
    "name:msa_x_preferred":[
        "Cotorra"
    ],
    "name:nan_x_preferred":[
        "Cotorra"
    ],
    "name:nld_x_preferred":[
        "Cotorra"
    ],
    "name:pol_x_preferred":[
        "Cotorra"
    ],
    "name:por_x_preferred":[
        "Cotorra"
    ],
    "name:rus_x_preferred":[
        "\u041a\u043e\u0442\u043e\u0440\u0440\u0430"
    ],
    "name:spa_x_preferred":[
        "Cotorra"
    ],
    "name:swe_x_preferred":[
        "Cotorra"
    ],
    "name:tgl_x_preferred":[
        "Cotorra"
    ],
    "name:und_x_variant":[
        "Corregimiento Cotorra"
    ],
    "name:vie_x_preferred":[
        "Cotorra"
    ],
    "name:war_x_preferred":[
        "Cotorra"
    ],
    "name:zho_x_preferred":[
        "\u79d1\u6258\u62c9"
    ],
    "qs:name":"Cotorra",
    "qs:photos_9r":0,
    "qs:photos_sr":0,
    "qs:pop_sr":"4",
    "wd:wordcount":35,
    "wof:name":"Cotorra",
    "wof:placetype":"locality",
    "wof:population":4880
},
  "geometry": {"coordinates":[-75.78968999999999,9.03886],"type":"Point"}
}