{
  "type": "Feature",
  "properties": {
    "gn:admin1_code":"12.0",
    "gn:admin2_code":"23678.0",
    "gn:asciiname":"La Infanta",
    "gn:country_code":"CO",
    "gn:dem":72,
    "gn:feature_class":"P",
    "gn:feature_code":"PPLL",
    "gn:name":"La Infanta",
    "gn:population":0,
    "gn:timezone":"America/Bogota",
    "iso:country":"CO",
    "wof:name":"La Infanta",
    "wof:placetype":"locality"
},
  "geometry": {"coordinates":[-75.70294,8.61877],"type":"Point"}
}