{
  "type": "Feature",
  "properties": {
    "gn:admin1_code":"1.0",
    "gn:admin2_code":"91001.0",
    "gn:asciiname":"San Fernando",
    "gn:country_code":"CO",
    "gn:dem":79,
    "gn:feature_class":"P",
    "gn:feature_code":"PPL",
    "gn:name":"San Fernando",
    "gn:population":0,
    "gn:timezone":"America/Bogota",
    "iso:country":"CO",
    "wof:name":"San Fernando",
    "wof:placetype":"locality"
},
  "geometry": {"coordinates":[-69.95666999999999,-4.15361],"type":"Point"}
}