{
  "type": "Feature",
  "properties": {
    "gn:admin1_code":"3",
    "gn:admin2_code":"81001.0",
    "gn:asciiname":"Las Tres Eras",
    "gn:country_code":"CO",
    "gn:dem":120,
    "gn:feature_class":"P",
    "gn:feature_code":"PPL",
    "gn:name":"Las Tres Eras",
    "gn:population":0,
    "gn:timezone":"America/Bogota",
    "iso:country":"CO",
    "name:spa_x_preferred":[
        "Las Tres Eras"
    ],
    "wof:name":"Las Tres Eras",
    "wof:placetype":"locality"
},
  "geometry": {"coordinates":[-70.6572,6.7057],"type":"Point"}
}