{
  "type": "Feature",
  "properties": {
    "gn:admin1_code":"12",
    "gn:admin2_code":"23686.0",
    "gn:asciiname":"Margarita",
    "gn:country_code":"CO",
    "gn:dem":59,
    "gn:feature_class":"P",
    "gn:feature_code":"PPL",
    "gn:name":"Margarita",
    "gn:population":0,
    "gn:timezone":"America/Bogota",
    "iso:country":"CO",
    "wof:name":"Margarita",
    "wof:placetype":"locality"
},
  "geometry": {"coordinates":[-76.08644,8.98789],"type":"Point"}
}