{
  "type": "Feature",
  "properties": {
    "gn:admin1_code":"20.0",
    "gn:admin2_code":"52051.0",
    "gn:asciiname":"Olaya",
    "gn:country_code":"CO",
    "gn:dem":1801,
    "gn:feature_class":"P",
    "gn:feature_code":"PPL",
    "gn:name":"Olaya",
    "gn:population":0,
    "gn:timezone":"America/Bogota",
    "iso:country":"CO",
    "wof:name":"Olaya",
    "wof:placetype":"locality"
},
  "geometry": {"coordinates":[-77.15575,1.49601],"type":"Point"}
}