{
  "type": "Feature",
  "properties": {
    "gn:admin1_code":"1.0",
    "gn:admin2_code":"91530.0",
    "gn:asciiname":"Remolino",
    "gn:country_code":"CO",
    "gn:dem":152,
    "gn:feature_class":"P",
    "gn:feature_code":"PPL",
    "gn:name":"Remolino",
    "gn:population":0,
    "gn:timezone":"America/Bogota",
    "iso:country":"CO",
    "wof:name":"Remolino",
    "wof:placetype":"locality"
},
  "geometry": {"coordinates":[-73.62528,-1.25627],"type":"Point"}
}