{
  "type": "Feature",
  "properties": {
    "gn:admin1_code":"1.0",
    "gn:admin2_code":"91530.0",
    "gn:asciiname":"Remolino",
    "gn:country_code":"CO",
    "gn:dem":152,
    "gn:feature_class":"P",
    "gn:feature_code":"PPL",
    "gn:name":"Remolino",
    "gn:population":0,
    "gn:timezone":"America/Bogota",
    "iso:country":"CO",
    "name:ceb_x_preferred":[
        "Remolino"
    ],
    "name:fra_x_preferred":[
        "Remolino"
    ],
    "name:ita_x_preferred":[
        "Remolino"
    ],
    "name:kat_x_preferred":[
        "\u10e0\u10d4\u10db\u10dd\u10da\u10d8\u10dc\u10dd"
    ],
    "name:msa_x_preferred":[
        "Remolino"
    ],
    "name:nld_x_preferred":[
        "Remolino"
    ],
    "name:por_x_preferred":[
        "Remolino"
    ],
    "name:rus_x_preferred":[
        "\u0420\u0435\u043c\u043e\u043b\u0438\u043d\u043e"
    ],
    "name:sco_x_preferred":[
        "Remolino"
    ],
    "name:spa_x_preferred":[
        "Remolino"
    ],
    "name:swe_x_preferred":[
        "Remolino"
    ],
    "name:tgl_x_preferred":[
        "Remolino"
    ],
    "name:ukr_x_preferred":[
        "\u0420\u0435\u043c\u043e\u043b\u0456\u043d\u043e"
    ],
    "name:vie_x_preferred":[
        "Remolino"
    ],
    "name:war_x_preferred":[
        "Remolino"
    ],
    "name:zho_x_preferred":[
        "\u96f7\u83ab\u5229\u8afe"
    ],
    "wof:name":"Remolino",
    "wof:placetype":"locality"
},
  "geometry": {"coordinates":[-73.62528,-1.25627],"type":"Point"}
}