{
  "type": "Feature",
  "properties": {
    "gn:admin1_code":"9.0",
    "gn:admin2_code":"19418.0",
    "gn:asciiname":"La Sagrada Familia",
    "gn:country_code":"CO",
    "gn:dem":70,
    "gn:feature_class":"P",
    "gn:feature_code":"PPL",
    "gn:name":"La Sagrada Familia",
    "gn:population":0,
    "gn:timezone":"America/Bogota",
    "iso:country":"CO",
    "wof:name":"La Sagrada Familia",
    "wof:placetype":"locality"
},
  "geometry": {"coordinates":[-77.36969000000001,3.15107],"type":"Point"}
}