{
  "type": "Feature",
  "properties": {
    "gn:admin1_code":"29",
    "gn:admin2_code":"76246.0",
    "gn:asciiname":"Las Brisas",
    "gn:country_code":"CO",
    "gn:dem":1809,
    "gn:feature_class":"P",
    "gn:feature_code":"PPL",
    "gn:name":"Las Brisas",
    "gn:population":0,
    "gn:timezone":"America/Bogota",
    "iso:country":"CO",
    "name:fra_x_preferred":[
        "Las Brisas"
    ],
    "name:und_x_variant":[
        "Brisas",
        "Las Brisas"
    ],
    "wof:name":"Las Brisas",
    "wof:placetype":"locality"
},
  "geometry": {"coordinates":[-76.15714,4.76921],"type":"Point"}
}