{
  "type": "Feature",
  "properties": {
    "gn:admin1_code":"9.0",
    "gn:admin2_code":"19137.0",
    "gn:asciiname":"Vereda Cristo Rey",
    "gn:country_code":"CO",
    "gn:dem":2484,
    "gn:feature_class":"P",
    "gn:feature_code":"PPLL",
    "gn:name":"Vereda Cristo Rey",
    "gn:population":0,
    "gn:timezone":"America/Bogota",
    "iso:country":"CO",
    "name:spa_x_preferred":[
        "Vereda Cristo Rey"
    ],
    "wof:name":"Vereda Cristo Rey",
    "wof:placetype":"locality"
},
  "geometry": {"coordinates":[-76.41216999999997,2.74159],"type":"Point"}
}