{
  "type": "Feature",
  "properties": {
    "gn:admin1_code":"32",
    "gn:admin2_code":"85139.0",
    "gn:asciiname":"Guarumito",
    "gn:country_code":"CO",
    "gn:dem":155,
    "gn:feature_class":"P",
    "gn:feature_code":"PPL",
    "gn:name":"Guarumito",
    "gn:population":0,
    "gn:timezone":"America/Bogota",
    "iso:country":"CO",
    "wof:name":"Guarumito",
    "wof:placetype":"locality"
},
  "geometry": {"coordinates":[-72.02360999999998,4.71528],"type":"Point"}
}