{
  "type": "Feature",
  "properties": {
    "gn:admin1_code":"26.0",
    "gn:admin2_code":"68235.0",
    "gn:asciiname":"La Victoria",
    "gn:country_code":"CO",
    "gn:dem":189,
    "gn:feature_class":"P",
    "gn:feature_code":"PPLL",
    "gn:name":"La Victoria",
    "gn:population":0,
    "gn:timezone":"America/Bogota",
    "iso:country":"CO",
    "wof:name":"La Victoria",
    "wof:placetype":"locality"
},
  "geometry": {"coordinates":[-73.7218,6.64516],"type":"Point"}
}