{
  "type": "Feature",
  "properties": {
    "gn:admin1_code":"32",
    "gn:admin2_code":"85125.0",
    "gn:asciiname":"Guarataro",
    "gn:country_code":"CO",
    "gn:dem":124,
    "gn:feature_class":"P",
    "gn:feature_code":"PPL",
    "gn:name":"Guarataro",
    "gn:population":0,
    "gn:timezone":"America/Bogota",
    "iso:country":"CO",
    "wof:name":"Guarataro",
    "wof:placetype":"locality"
},
  "geometry": {"coordinates":[-70.81667,6.21667],"type":"Point"}
}