{
  "type": "Feature",
  "properties": {
    "gn:admin1_code":"10.0",
    "gn:admin2_code":"20295.0",
    "gn:asciiname":"Balconcitos",
    "gn:country_code":"CO",
    "gn:dem":51,
    "gn:feature_class":"P",
    "gn:feature_code":"PPL",
    "gn:name":"Balconcitos",
    "gn:population":0,
    "gn:timezone":"America/Bogota",
    "iso:country":"CO",
    "name:spa_x_preferred":[
        "Balconcitos"
    ],
    "wof:name":"Balconcitos",
    "wof:placetype":"locality"
},
  "geometry": {"coordinates":[-73.6977,8.35642],"type":"Point"}
}