{
  "type": "Feature",
  "properties": {
    "gn:admin1_code":"8.0",
    "gn:admin2_code":"18001.0",
    "gn:asciiname":"El Mochilero",
    "gn:country_code":"CO",
    "gn:dem":240,
    "gn:feature_class":"P",
    "gn:feature_code":"PPL",
    "gn:name":"El Mochilero",
    "gn:population":0,
    "gn:timezone":"America/Bogota",
    "iso:country":"CO",
    "name:spa_x_preferred":[
        "El Mochilero"
    ],
    "wof:name":"El Mochilero",
    "wof:placetype":"locality"
},
  "geometry": {"coordinates":[-75.68431,1.49838],"type":"Point"}
}