{
  "type": "Feature",
  "properties": {
    "gn:admin1_code":"19",
    "gn:admin2_code":"50001.0",
    "gn:asciiname":"La Providencia",
    "gn:cc2":"CO",
    "gn:country_code":"CO",
    "gn:dem":350,
    "gn:feature_class":"P",
    "gn:feature_code":"PPL",
    "gn:name":"La Providencia",
    "gn:population":0,
    "gn:timezone":"America/Bogota",
    "iso:country":"CO",
    "name:und_x_variant":[
        "La Provincia",
        "La Providencia"
    ],
    "wof:name":"La Providencia",
    "wof:placetype":"locality"
},
  "geometry": {"coordinates":[-73.53333000000001,4.03333],"type":"Point"}
}