{
  "type": "Feature",
  "properties": {
    "gn:admin1_code":"4.0",
    "gn:admin2_code":"8078.0",
    "gn:asciiname":"Pital",
    "gn:country_code":"CO",
    "gn:dem":131,
    "gn:feature_class":"P",
    "gn:feature_code":"PPL",
    "gn:name":"Pital",
    "gn:population":0,
    "gn:timezone":"America/Bogota",
    "iso:country":"CO",
    "name:ceb_x_preferred":[
        "Pital"
    ],
    "name:spa_x_preferred":[
        "Pital"
    ],
    "name:swe_x_preferred":[
        "Pital"
    ],
    "wof:name":"Pital",
    "wof:placetype":"locality"
},
  "geometry": {"coordinates":[-74.9175,10.84028],"type":"Point"}
}