{
  "type": "Feature",
  "properties": {
    "gn:admin1_code":"2",
    "gn:admin2_code":"5819.0",
    "gn:asciiname":"El Valle",
    "gn:country_code":"CO",
    "gn:dem":484,
    "gn:feature_class":"P",
    "gn:feature_code":"PPL",
    "gn:name":"El Valle",
    "gn:population":0,
    "gn:timezone":"America/Bogota",
    "iso:country":"CO",
    "name:ast_x_preferred":[
        "El Valle"
    ],
    "name:ceb_x_preferred":[
        "El Valle"
    ],
    "name:deu_x_preferred":[
        "El Valle"
    ],
    "name:fra_x_preferred":[
        "El Valle"
    ],
    "name:jpn_x_preferred":[
        "\u30a8\u30eb\u30d0\u30b8\u30a7"
    ],
    "name:nld_x_preferred":[
        "El Valle"
    ],
    "name:spa_x_preferred":[
        "El Valle"
    ],
    "name:swe_x_preferred":[
        "El Valle"
    ],
    "wof:name":"El Valle",
    "wof:placetype":"locality"
},
  "geometry": {"coordinates":[-75.67314,7.05347],"type":"Point"}
}