{
  "type": "Feature",
  "properties": {
    "gn:admin1_code":"16.0",
    "gn:admin2_code":"41078.0",
    "gn:asciiname":"Villa Cecilia",
    "gn:country_code":"CO",
    "gn:dem":560,
    "gn:feature_class":"P",
    "gn:feature_code":"PPL",
    "gn:name":"Villa Cecilia",
    "gn:population":0,
    "gn:timezone":"America/Bogota",
    "iso:country":"CO",
    "name:spa_x_preferred":[
        "Villa Cecilia"
    ],
    "wof:name":"Villa Cecilia",
    "wof:placetype":"locality"
},
  "geometry": {"coordinates":[-74.97144,3.27528],"type":"Point"}
}