{
  "type": "Feature",
  "properties": {
    "gn:admin1_code":"20.0",
    "gn:admin2_code":"52079.0",
    "gn:asciiname":"Penon",
    "gn:country_code":"CO",
    "gn:dem":279,
    "gn:feature_class":"P",
    "gn:feature_code":"PPL",
    "gn:name":"Pe\u00f1\u00f3n",
    "gn:population":0,
    "gn:timezone":"America/Bogota",
    "iso:country":"CO",
    "wof:name":"Penon",
    "wof:placetype":"locality"
},
  "geometry": {"coordinates":[-78.25,1.48333],"type":"Point"}
}