{
  "type": "Feature",
  "properties": {
    "gn:admin1_code":"28.0",
    "gn:admin2_code":"73024.0",
    "gn:asciiname":"Belinda",
    "gn:country_code":"CO",
    "gn:dem":1081,
    "gn:feature_class":"P",
    "gn:feature_code":"PPL",
    "gn:name":"Belinda",
    "gn:population":0,
    "gn:timezone":"America/Bogota",
    "iso:country":"CO",
    "name:spa_x_preferred":[
        "Belinda"
    ],
    "name:spa_x_variant":[
        "Bilanda"
    ],
    "wof:name":"Belinda",
    "wof:placetype":"locality"
},
  "geometry": {"coordinates":[-74.97972,3.42389],"type":"Point"}
}