{
  "type": "Feature",
  "properties": {
    "gn:admin1_code":"28.0",
    "gn:admin2_code":"73024.0",
    "gn:asciiname":"Belinda",
    "gn:country_code":"CO",
    "gn:dem":1081,
    "gn:feature_class":"P",
    "gn:feature_code":"PPL",
    "gn:name":"Belinda",
    "gn:population":0,
    "gn:timezone":"America/Bogota",
    "iso:country":"CO",
    "name:ces_x_preferred":[
        "Belinda"
    ],
    "name:deu_x_preferred":[
        "Belinda"
    ],
    "name:fin_x_preferred":[
        "Belinda"
    ],
    "name:hun_x_preferred":[
        "Belinda"
    ],
    "name:isl_x_preferred":[
        "Belinda"
    ],
    "name:ita_x_preferred":[
        "Belinda"
    ],
    "name:nld_x_preferred":[
        "Belinda"
    ],
    "name:nno_x_preferred":[
        "Belinda"
    ],
    "name:nor_x_preferred":[
        "Belinda"
    ],
    "name:rus_x_preferred":[
        "\u0411\u0435\u043b\u0438\u043d\u0434\u0430"
    ],
    "name:sco_x_preferred":[
        "Belinda"
    ],
    "name:slv_x_preferred":[
        "Belinda"
    ],
    "name:spa_x_preferred":[
        "Belinda"
    ],
    "name:spa_x_variant":[
        "Bilanda"
    ],
    "name:swe_x_preferred":[
        "Belinda"
    ],
    "wof:name":"Belinda",
    "wof:placetype":"locality"
},
  "geometry": {"coordinates":[-74.97972,3.42389],"type":"Point"}
}