{
  "type": "Feature",
  "properties": {
    "gn:admin1_code":"29",
    "gn:admin2_code":"76113.0",
    "gn:asciiname":"Casa de Balcon",
    "gn:country_code":"CO",
    "gn:dem":1415,
    "gn:feature_class":"P",
    "gn:feature_code":"PPL",
    "gn:name":"Casa de Balc\u00f3n",
    "gn:population":0,
    "gn:timezone":"America/Bogota",
    "iso:country":"CO",
    "wof:name":"Casa de Balcon",
    "wof:placetype":"locality"
},
  "geometry": {"coordinates":[-75.98305999999999,4.13306],"type":"Point"}
}