{
  "type": "Feature",
  "properties": {
    "gn:admin1_code":"8",
    "gn:admin2_code":"18753.0",
    "gn:asciiname":"La Estrella",
    "gn:country_code":"CO",
    "gn:dem":488,
    "gn:feature_class":"P",
    "gn:feature_code":"PPL",
    "gn:name":"La Estrella",
    "gn:population":0,
    "gn:timezone":"America/Bogota",
    "iso:country":"CO",
    "wof:name":"La Estrella",
    "wof:placetype":"locality"
},
  "geometry": {"coordinates":[-74.89667,2.38889],"type":"Point"}
}