{
  "type": "Feature",
  "properties": {
    "iso:country":"CO",
    "name:ast_x_preferred":[
        "Guayat\u00e1"
    ],
    "name:avk_x_preferred":[
        "Guayat\u00e1"
    ],
    "name:ceb_x_preferred":[
        "Guayat\u00e1"
    ],
    "name:eng_x_preferred":[
        "Guayat\u00e1"
    ],
    "name:fas_x_preferred":[
        "\u06af\u0648\u0622\u06cc\u0627\u062a\u0627"
    ],
    "name:fra_x_preferred":[
        "Guayat\u00e1"
    ],
    "name:gle_x_preferred":[
        "Guayat\u00e1"
    ],
    "name:glg_x_preferred":[
        "Guayat\u00e1"
    ],
    "name:ita_x_preferred":[
        "Guayat\u00e1"
    ],
    "name:kat_x_preferred":[
        "\u10d2\u10e3\u10d0\u10d8\u10d0\u10e2\u10d0"
    ],
    "name:msa_x_preferred":[
        "Guayat\u00e1"
    ],
    "name:nan_x_preferred":[
        "Guayat\u00e1"
    ],
    "name:nld_x_preferred":[
        "Guayat\u00e1"
    ],
    "name:pol_x_preferred":[
        "Guayat\u00e1"
    ],
    "name:por_x_preferred":[
        "Guayat\u00e1"
    ],
    "name:por_x_variant":[
        "Guayata"
    ],
    "name:rus_x_preferred":[
        "\u0413\u0443\u0430\u044f\u0442\u0430"
    ],
    "name:spa_x_preferred":[
        "Guayat\u00e1"
    ],
    "name:swe_x_preferred":[
        "Guayat\u00e1"
    ],
    "name:tgl_x_preferred":[
        "Guayat\u00e1"
    ],
    "name:vie_x_preferred":[
        "Guayat\u00e1"
    ],
    "name:war_x_preferred":[
        "Guayat\u00e1"
    ],
    "name:zho_x_preferred":[
        "\u74dc\u4e9e\u5854"
    ],
    "qs:gn_country":"CO",
    "qs:gn_fcode":"PPL",
    "qs:gn_pop":2857,
    "qs:name":"Guayat\u00e1",
    "qs:name_adm0":"Colombia",
    "qs:name_adm1":"Boyaca",
    "qs:photos":27,
    "qs:photos_1k":5,
    "qs:photos_9k":1,
    "qs:photos_9r":2,
    "qs:photos_all":27,
    "qs:photos_sr":2,
    "qs:placetype":"Town",
    "qs:pop_sr":"4",
    "qs:woe_adm0":23424787,
    "wd:wordcount":333,
    "wof:name":"Guayat\u00e1",
    "wof:placetype":"locality",
    "wof:population":2857
},
  "geometry": {"coordinates":[-73.4875,4.96417],"type":"Point"}
}