{
  "type": "Feature",
  "properties": {
    "gn:admin1_code":"29",
    "gn:admin2_code":"76041.0",
    "gn:asciiname":"Lusitania",
    "gn:country_code":"CO",
    "gn:dem":1370,
    "gn:feature_class":"P",
    "gn:feature_code":"PPL",
    "gn:name":"Lusitania",
    "gn:population":0,
    "gn:timezone":"America/Bogota",
    "iso:country":"CO",
    "wof:name":"Lusitania",
    "wof:placetype":"locality"
},
  "geometry": {"coordinates":[-76.03333000000001,4.78333],"type":"Point"}
}