{
  "type": "Feature",
  "properties": {
    "iso:country":"CO",
    "name:ast_x_preferred":[
        "Morales"
    ],
    "name:avk_x_preferred":[
        "Morales"
    ],
    "name:cat_x_preferred":[
        "Morales"
    ],
    "name:ceb_x_preferred":[
        "Morales"
    ],
    "name:deu_x_preferred":[
        "Morales"
    ],
    "name:eng_x_preferred":[
        "Morales"
    ],
    "name:fas_x_preferred":[
        "\u0645\u0648\u0631\u0627\u0644\u0633"
    ],
    "name:fra_x_preferred":[
        "Morales"
    ],
    "name:gle_x_preferred":[
        "Morales"
    ],
    "name:ita_x_preferred":[
        "Morales"
    ],
    "name:kat_x_preferred":[
        "\u10db\u10dd\u10e0\u10d0\u10da\u10d4\u10e1\u10d8"
    ],
    "name:msa_x_preferred":[
        "Morales"
    ],
    "name:nan_x_preferred":[
        "Morales"
    ],
    "name:nld_x_preferred":[
        "Morales"
    ],
    "name:pol_x_preferred":[
        "Morales"
    ],
    "name:por_x_preferred":[
        "Morales"
    ],
    "name:rus_x_preferred":[
        "\u041c\u043e\u0440\u0430\u043b\u0435\u0441"
    ],
    "name:sco_x_preferred":[
        "Morales"
    ],
    "name:spa_x_preferred":[
        "Morales"
    ],
    "name:swe_x_preferred":[
        "Morales"
    ],
    "name:tgl_x_preferred":[
        "Morales"
    ],
    "name:und_x_variant":[
        "Corregimiento Morales"
    ],
    "name:war_x_preferred":[
        "Morales"
    ],
    "name:zho_x_preferred":[
        "\u83ab\u62c9\u840a\u65af"
    ],
    "name:zho_x_variant":[
        "\u74dc\u9054\u76e7\u666e"
    ],
    "qs:gn_country":"CO",
    "qs:gn_fcode":"PPL",
    "qs:gn_pop":20375,
    "qs:name":"Morales",
    "qs:name_adm0":"Colombia",
    "qs:name_adm1":"Bolivar",
    "qs:photos":0,
    "qs:photos_1k":0,
    "qs:photos_9k":0,
    "qs:photos_9r":0,
    "qs:photos_all":0,
    "qs:photos_sr":0,
    "qs:placetype":"Town",
    "qs:pop_sr":"7",
    "qs:woe_adm0":23424787,
    "wd:wordcount":36,
    "wof:name":"Morales",
    "wof:placetype":"locality",
    "wof:population":20375
},
  "geometry": {"coordinates":[-73.86884000000001,8.2752],"type":"Point"}
}