{
  "type": "Feature",
  "properties": {
    "iso:country":"CO",
    "name:ceb_x_preferred":[
        "Pueblo Nuevo"
    ],
    "name:deu_x_preferred":[
        "Pueblo Nuevo"
    ],
    "name:epo_x_preferred":[
        "Pueblo Nuevo"
    ],
    "name:fra_x_preferred":[
        "Pueblo Nuevo"
    ],
    "name:ita_x_preferred":[
        "Pueblo Nuevo"
    ],
    "name:nds_x_preferred":[
        "Pueblo Nuevo"
    ],
    "name:nld_x_preferred":[
        "Pueblo Nuevo"
    ],
    "name:pol_x_preferred":[
        "Pueblo Nuevo"
    ],
    "name:por_x_preferred":[
        "Pueblo Nuevo"
    ],
    "name:rus_x_preferred":[
        "\u041f\u0443\u044d\u0431\u043b\u043e-\u041d\u0443\u044d\u0432\u043e"
    ],
    "name:sco_x_preferred":[
        "Pueblo Nuevo"
    ],
    "name:spa_x_preferred":[
        "Pueblo Nuevo"
    ],
    "name:srp_x_preferred":[
        "\u041f\u0443\u0435\u0431\u043b\u043e \u041d\u0443\u0435\u0432\u043e"
    ],
    "name:swe_x_preferred":[
        "Pueblo Nuevo"
    ],
    "name:unk_x_variant":[
        "Caserio Pueblonuevo"
    ],
    "name:vie_x_preferred":[
        "Pueblo Nuevo"
    ],
    "qs:gn_country":"CO",
    "qs:gn_fcode":"PPL",
    "qs:gn_pop":9075,
    "qs:name":"Pueblo Nuevo",
    "qs:name_adm0":"Colombia",
    "qs:name_adm1":"Cordoba",
    "qs:photos":0,
    "qs:photos_1k":0,
    "qs:photos_9k":0,
    "qs:photos_9r":0,
    "qs:photos_all":0,
    "qs:photos_sr":0,
    "qs:placetype":"Town",
    "qs:pop_sr":"5",
    "qs:woe_adm0":23424787,
    "wof:name":"Pueblo Nuevo",
    "wof:placetype":"locality",
    "wof:population":9075
},
  "geometry": {"coordinates":[-74.95815,8.2411],"type":"Point"}
}