{
  "type": "Feature",
  "properties": {
    "gn:admin1_code":"26",
    "gn:admin2_code":"68895.0",
    "gn:asciiname":"Loma Redonda",
    "gn:country_code":"CO",
    "gn:dem":1487,
    "gn:feature_class":"P",
    "gn:feature_code":"PPL",
    "gn:name":"Loma Redonda",
    "gn:population":0,
    "gn:timezone":"America/Bogota",
    "iso:country":"CO",
    "wof:name":"Loma Redonda",
    "wof:placetype":"locality"
},
  "geometry": {"coordinates":[-73.34023000000001,6.91754],"type":"Point"}
}