{
  "type": "Feature",
  "properties": {
    "gn:admin1_code":"2.0",
    "gn:admin2_code":"5647.0",
    "gn:asciiname":"La Chorrera",
    "gn:country_code":"CO",
    "gn:dem":2785,
    "gn:feature_class":"P",
    "gn:feature_code":"PPL",
    "gn:name":"La Chorrera",
    "gn:population":0,
    "gn:timezone":"America/Bogota",
    "iso:country":"CO",
    "name:ceb_x_preferred":[
        "La Chorrera"
    ],
    "name:fra_x_preferred":[
        "La Chorrera"
    ],
    "name:ita_x_preferred":[
        "La Chorrera"
    ],
    "name:nld_x_preferred":[
        "La Chorrera"
    ],
    "name:que_x_preferred":[
        "La Chorrera"
    ],
    "name:rus_x_preferred":[
        "\u041b\u0430-\u0427\u043e\u0440\u0440\u0435\u0440\u0430"
    ],
    "name:spa_x_preferred":[
        "La Chorrera"
    ],
    "name:swe_x_preferred":[
        "La Chorrera"
    ],
    "wof:name":"La Chorrera",
    "wof:placetype":"locality"
},
  "geometry": {"coordinates":[-75.62166999999999,6.88944],"type":"Point"}
}