{
  "type": "Feature",
  "properties": {
    "gn:admin1_code":"2.0",
    "gn:admin2_code":"5647.0",
    "gn:asciiname":"La Chorrera",
    "gn:country_code":"CO",
    "gn:dem":2785,
    "gn:feature_class":"P",
    "gn:feature_code":"PPL",
    "gn:name":"La Chorrera",
    "gn:population":0,
    "gn:timezone":"America/Bogota",
    "iso:country":"CO",
    "wof:name":"La Chorrera",
    "wof:placetype":"locality"
},
  "geometry": {"coordinates":[-75.62166999999999,6.88944],"type":"Point"}
}