{
  "type": "Feature",
  "properties": {
    "gn:admin1_code":"17",
    "gn:admin2_code":"44001.0",
    "gn:asciiname":"El Horno",
    "gn:country_code":"CO",
    "gn:dem":8,
    "gn:feature_class":"P",
    "gn:feature_code":"PPL",
    "gn:name":"El Horno",
    "gn:population":0,
    "gn:timezone":"America/Bogota",
    "iso:country":"CO",
    "wof:name":"El Horno",
    "wof:placetype":"locality"
},
  "geometry": {"coordinates":[-72.98396,11.49792],"type":"Point"}
}