{
  "type": "Feature",
  "properties": {
    "gn:admin1_code":"12",
    "gn:admin2_code":"23182.0",
    "gn:asciiname":"Algarrobo",
    "gn:country_code":"CO",
    "gn:dem":102,
    "gn:feature_class":"P",
    "gn:feature_code":"PPL",
    "gn:name":"Algarrobo",
    "gn:population":0,
    "gn:timezone":"America/Bogota",
    "iso:country":"CO",
    "name:und_x_variant":[
        "Algorrobo",
        "Algarrobo"
    ],
    "wof:name":"Algarrobo",
    "wof:placetype":"locality"
},
  "geometry": {"coordinates":[-75.44615999999998,9.09439],"type":"Point"}
}