{
  "type": "Feature",
  "properties": {
    "gn:admin1_code":"10",
    "gn:admin2_code":"20032.0",
    "gn:asciiname":"El Brillante",
    "gn:country_code":"CO",
    "gn:dem":50,
    "gn:feature_class":"P",
    "gn:feature_code":"PPL",
    "gn:name":"El Brillante",
    "gn:population":0,
    "gn:timezone":"America/Bogota",
    "iso:country":"CO",
    "wof:name":"El Brillante",
    "wof:placetype":"locality"
},
  "geometry": {"coordinates":[-73.86610999999998,9.54333],"type":"Point"}
}