{
  "type": "Feature",
  "properties": {
    "gn:admin1_code":"19.0",
    "gn:admin2_code":"50001.0",
    "gn:asciiname":"Vanguardia",
    "gn:country_code":"CO",
    "gn:dem":413,
    "gn:feature_class":"P",
    "gn:feature_code":"PPL",
    "gn:name":"Vanguardia",
    "gn:population":0,
    "gn:timezone":"America/Bogota",
    "iso:country":"CO",
    "name:deu_x_preferred":[
        "Vanguardia"
    ],
    "name:spa_x_preferred":[
        "Vanguardia"
    ],
    "wof:name":"Vanguardia",
    "wof:placetype":"locality"
},
  "geometry": {"coordinates":[-73.60668000000003,4.18743],"type":"Point"}
}