{
  "type": "Feature",
  "properties": {
    "gn:admin1_code":"9.0",
    "gn:admin2_code":"19532.0",
    "gn:asciiname":"Angulo",
    "gn:country_code":"CO",
    "gn:dem":575,
    "gn:feature_class":"P",
    "gn:feature_code":"PPL",
    "gn:name":"Angulo",
    "gn:population":0,
    "gn:timezone":"America/Bogota",
    "iso:country":"CO",
    "wof:name":"Angulo",
    "wof:placetype":"locality"
},
  "geometry": {"coordinates":[-77.10777,2.05189],"type":"Point"}
}