{
  "type": "Feature",
  "properties": {
    "gn:admin1_code":"33",
    "gn:admin2_code":"25535.0",
    "gn:asciiname":"Aguadulce",
    "gn:country_code":"CO",
    "gn:dem":3095,
    "gn:feature_class":"P",
    "gn:feature_code":"PPL",
    "gn:name":"Aguadulce",
    "gn:population":0,
    "gn:timezone":"America/Bogota",
    "iso:country":"CO",
    "wof:name":"Aguadulce",
    "wof:placetype":"locality"
},
  "geometry": {"coordinates":[-74.25229,4.2674],"type":"Point"}
}