{
  "type": "Feature",
  "properties": {
    "gn:admin1_code":"16",
    "gn:admin2_code":"41799",
    "gn:asciiname":"Villalba",
    "gn:country_code":"CO",
    "gn:dem":972,
    "gn:feature_class":"P",
    "gn:feature_code":"PPL",
    "gn:name":"Villalba",
    "gn:population":0,
    "gn:timezone":"America/Bogota",
    "iso:country":"CO",
    "name:arg_x_preferred":[
        "Villalba"
    ],
    "name:bre_x_preferred":[
        "Villalba"
    ],
    "name:cat_x_preferred":[
        "Villalba"
    ],
    "name:ceb_x_preferred":[
        "Villalba"
    ],
    "name:deu_x_preferred":[
        "Villalba"
    ],
    "name:epo_x_preferred":[
        "Villalba"
    ],
    "name:fra_x_preferred":[
        "Villalba"
    ],
    "name:glg_x_preferred":[
        "Villalba"
    ],
    "name:ita_x_preferred":[
        "Villalba"
    ],
    "name:nld_x_preferred":[
        "Villalba"
    ],
    "name:pol_x_preferred":[
        "Villalba"
    ],
    "name:rus_x_preferred":[
        "\u0412\u0438\u043b\u044c\u044f\u043b\u044c\u0431\u0430"
    ],
    "name:sco_x_preferred":[
        "Villalba"
    ],
    "name:spa_x_preferred":[
        "Villalba"
    ],
    "name:srp_x_preferred":[
        "Vilalba"
    ],
    "name:swe_x_preferred":[
        "Villalba"
    ],
    "wof:name":"Villalba",
    "wof:placetype":"locality"
},
  "geometry": {"coordinates":[-75.0885,2.94331],"type":"Point"}
}