{
  "type": "Feature",
  "properties": {
    "gn:admin1_code":"16",
    "gn:admin2_code":"41799",
    "gn:asciiname":"Villalba",
    "gn:country_code":"CO",
    "gn:dem":972,
    "gn:feature_class":"P",
    "gn:feature_code":"PPL",
    "gn:name":"Villalba",
    "gn:population":0,
    "gn:timezone":"America/Bogota",
    "iso:country":"CO",
    "name:spa_x_preferred":[
        "Villalba"
    ],
    "wof:name":"Villalba",
    "wof:placetype":"locality"
},
  "geometry": {"coordinates":[-75.0885,2.94331],"type":"Point"}
}