{
  "type": "Feature",
  "properties": {
    "gn:admin1_code":"27.0",
    "gn:admin2_code":"70204.0",
    "gn:asciiname":"Vijagual",
    "gn:country_code":"CO",
    "gn:dem":106,
    "gn:feature_class":"P",
    "gn:feature_code":"PPL",
    "gn:name":"Vijagual",
    "gn:population":0,
    "gn:timezone":"America/Bogota",
    "iso:country":"CO",
    "wof:name":"Vijagual",
    "wof:placetype":"locality"
},
  "geometry": {"coordinates":[-75.34566,9.47868],"type":"Point"}
}