{
  "type": "Feature",
  "properties": {
    "gn:admin1_code":"26",
    "gn:admin2_code":"68406.0",
    "gn:asciiname":"Los Cacaos",
    "gn:country_code":"CO",
    "gn:dem":709,
    "gn:feature_class":"P",
    "gn:feature_code":"PPL",
    "gn:name":"Los Cacaos",
    "gn:population":0,
    "gn:timezone":"America/Bogota",
    "iso:country":"CO",
    "name:ita_x_preferred":[
        "Los Cacaos"
    ],
    "name:por_x_preferred":[
        "Los Cacaos"
    ],
    "name:spa_x_preferred":[
        "Los Cacaos"
    ],
    "name:zho_x_preferred":[
        "\u6d1b\u65af\u5361\u8003\u65af"
    ],
    "wof:name":"Los Cacaos",
    "wof:placetype":"locality"
},
  "geometry": {"coordinates":[-73.32139000000002,7.23833],"type":"Point"}
}