{
  "type": "Feature",
  "properties": {
    "gn:admin1_code":"23",
    "gn:admin2_code":"63470",
    "gn:asciiname":"Pueblo Tapao",
    "gn:country_code":"CO",
    "gn:dem":1265,
    "gn:elevation":"0.0",
    "gn:feature_class":"P",
    "gn:feature_code":"PPL",
    "gn:name":"Pueblo Tapao",
    "gn:population":0,
    "gn:timezone":"America/Bogota",
    "iso:country":"CO",
    "wof:name":"Pueblo Tapao",
    "wof:placetype":"locality"
},
  "geometry": {"coordinates":[-75.78506999999998,4.51499],"type":"Point"}
}