{
  "type": "Feature",
  "properties": {
    "gn:admin1_code":"35.0",
    "gn:admin2_code":"13873.0",
    "gn:asciiname":"El Alcazar",
    "gn:country_code":"CO",
    "gn:dem":56,
    "gn:feature_class":"P",
    "gn:feature_code":"PPL",
    "gn:name":"El Alcazar",
    "gn:population":0,
    "gn:timezone":"America/Bogota",
    "iso:country":"CO",
    "wof:name":"El Alcazar",
    "wof:placetype":"locality"
},
  "geometry": {"coordinates":[-75.31728000000003,10.40447],"type":"Point"}
}