{
  "type": "Feature",
  "properties": {
    "gn:admin1_code":"36.0",
    "gn:asciiname":"Potrero Grande",
    "gn:country_code":"CO",
    "gn:dem":1607,
    "gn:feature_class":"P",
    "gn:feature_code":"PPL",
    "gn:name":"Potrero Grande",
    "gn:population":0,
    "gn:timezone":"America/Bogota",
    "iso:country":"CO",
    "name:ceb_x_preferred":[
        "Potrero Grande"
    ],
    "wof:name":"Potrero Grande",
    "wof:placetype":"locality"
},
  "geometry": {"coordinates":[-73.38333,6.05],"type":"Point"}
}