{
  "type": "Feature",
  "properties": {
    "iso:country":"CO",
    "name:ast_x_preferred":[
        "Casabianca"
    ],
    "name:avk_x_preferred":[
        "Casabianca"
    ],
    "name:ceb_x_preferred":[
        "Casabianca"
    ],
    "name:cym_x_preferred":[
        "Casabianca"
    ],
    "name:eng_x_preferred":[
        "Casabianca"
    ],
    "name:fas_x_preferred":[
        "\u06a9\u0627\u0633\u0627\u0628\u06cc\u0627\u0646\u06a9\u0627"
    ],
    "name:fra_x_preferred":[
        "Casabianca"
    ],
    "name:gle_x_preferred":[
        "Casabianca"
    ],
    "name:ita_x_preferred":[
        "Casabianca"
    ],
    "name:kat_x_preferred":[
        "\u10d9\u10d0\u10e1\u10d0\u10d1\u10d8\u10d0\u10dc\u10d9\u10d0"
    ],
    "name:msa_x_preferred":[
        "Casabianca"
    ],
    "name:nan_x_preferred":[
        "Casabianca"
    ],
    "name:nld_x_preferred":[
        "Casabianca"
    ],
    "name:pol_x_preferred":[
        "Casabianca"
    ],
    "name:spa_x_preferred":[
        "Casabianca"
    ],
    "name:swe_x_preferred":[
        "Casabianca"
    ],
    "name:und_x_variant":[
        "Casablanca"
    ],
    "name:war_x_preferred":[
        "Casabianca"
    ],
    "name:zho_x_preferred":[
        "\u5361\u85a9\u7dad\u5b89\u5361"
    ],
    "qs:gn_country":"CO",
    "qs:gn_fcode":"PPL",
    "qs:gn_pop":1593,
    "qs:name":"Casabianca",
    "qs:name_adm0":"Colombia",
    "qs:name_adm1":"Tolima",
    "qs:photos":0,
    "qs:photos_1k":0,
    "qs:photos_9k":1,
    "qs:photos_9r":1,
    "qs:photos_all":14,
    "qs:photos_sr":0,
    "qs:placetype":"Town",
    "qs:pop_sr":"3",
    "qs:woe_adm0":23424787,
    "wof:name":"Casabianca",
    "wof:placetype":"locality",
    "wof:population":1593
},
  "geometry": {"coordinates":[-75.12059000000001,5.07959],"type":"Point"}
}