{
  "type": "Feature",
  "properties": {
    "gn:admin1_code":"36",
    "gn:admin2_code":"15572.0",
    "gn:asciiname":"Marfil",
    "gn:country_code":"CO",
    "gn:dem":243,
    "gn:feature_class":"P",
    "gn:feature_code":"PPL",
    "gn:name":"Marf\u00edl",
    "gn:population":0,
    "gn:timezone":"America/Bogota",
    "iso:country":"CO",
    "name:ceb_x_preferred":[
        "Marfil"
    ],
    "name:glg_x_preferred":[
        "Marfil"
    ],
    "name:spa_x_preferred":[
        "Marfil"
    ],
    "name:srp_x_preferred":[
        "\u041c\u0430\u0440\u0444\u0438\u043b"
    ],
    "name:swe_x_preferred":[
        "Marfil"
    ],
    "wof:name":"Marfil",
    "wof:placetype":"locality"
},
  "geometry": {"coordinates":[-74.34833,5.90667],"type":"Point"}
}