{
  "type": "Feature",
  "properties": {
    "gn:admin1_code":"2",
    "gn:asciiname":"Bobal",
    "gn:country_code":"CO",
    "gn:dem":1,
    "gn:feature_class":"P",
    "gn:feature_code":"PPL",
    "gn:name":"Bobal",
    "gn:population":0,
    "gn:timezone":"America/Bogota",
    "iso:country":"CO",
    "name:cat_x_preferred":[
        "Boval"
    ],
    "name:chv_x_preferred":[
        "\u0411\u043e\u0431\u0430\u043b\u044c"
    ],
    "name:deu_x_preferred":[
        "Bobal"
    ],
    "name:fra_x_preferred":[
        "Bobal"
    ],
    "name:nld_x_preferred":[
        "Bobal"
    ],
    "name:rus_x_preferred":[
        "\u0411\u043e\u0431\u0430\u043b\u044c"
    ],
    "name:spa_x_preferred":[
        "Bobal"
    ],
    "name:ukr_x_preferred":[
        "\u0411\u043e\u0431\u0430\u043b\u044c"
    ],
    "wof:name":"Bobal",
    "wof:placetype":"locality"
},
  "geometry": {"coordinates":[-76.91667,8.58333],"type":"Point"}
}