{
  "type": "Feature",
  "properties": {
    "gn:admin1_code":"17",
    "gn:admin2_code":"44279.0",
    "gn:asciiname":"Siberia",
    "gn:country_code":"CO",
    "gn:dem":435,
    "gn:feature_class":"P",
    "gn:feature_code":"PPL",
    "gn:name":"Siberia",
    "gn:population":0,
    "gn:timezone":"America/Bogota",
    "iso:country":"CO",
    "wof:name":"Siberia",
    "wof:placetype":"locality"
},
  "geometry": {"coordinates":[-72.80028,10.71056],"type":"Point"}
}