{
  "type": "Feature",
  "properties": {
    "gn:admin1_code":"35",
    "gn:admin2_code":"13473.0",
    "gn:asciiname":"Boca de La Cienaga",
    "gn:country_code":"CO",
    "gn:dem":35,
    "gn:feature_class":"P",
    "gn:feature_code":"PPL",
    "gn:name":"Boca de La Ci\u00e9naga",
    "gn:population":0,
    "gn:timezone":"America/Bogota",
    "iso:country":"CO",
    "wof:name":"Boca de La Cienaga",
    "wof:placetype":"locality"
},
  "geometry": {"coordinates":[-73.80009,8.31425],"type":"Point"}
}