{
  "type": "Feature",
  "properties": {
    "gn:admin1_code":"28",
    "gn:admin2_code":"73200.0",
    "gn:asciiname":"Gallinazo",
    "gn:country_code":"CO",
    "gn:dem":275,
    "gn:feature_class":"P",
    "gn:feature_code":"PPL",
    "gn:name":"Gallinazo",
    "gn:population":0,
    "gn:timezone":"America/Bogota",
    "iso:country":"CO",
    "wof:name":"Gallinazo",
    "wof:placetype":"locality"
},
  "geometry": {"coordinates":[-74.88438000000002,4.30829],"type":"Point"}
}