{
  "type": "Feature",
  "properties": {
    "gn:admin1_code":"12.0",
    "gn:admin2_code":"23686.0",
    "gn:asciiname":"Bonga Mella",
    "gn:country_code":"CO",
    "gn:dem":46,
    "gn:feature_class":"P",
    "gn:feature_code":"PPL",
    "gn:name":"Bonga Mella",
    "gn:population":0,
    "gn:timezone":"America/Bogota",
    "iso:country":"CO",
    "wof:name":"Bonga Mella",
    "wof:placetype":"locality"
},
  "geometry": {"coordinates":[-75.93614000000002,8.99235],"type":"Point"}
}