{
  "type": "Feature",
  "properties": {
    "gn:admin1_code":"36",
    "gn:admin2_code":"15442.0",
    "gn:asciiname":"Guazo",
    "gn:country_code":"CO",
    "gn:dem":1026,
    "gn:feature_class":"P",
    "gn:feature_code":"PPL",
    "gn:name":"Guazo",
    "gn:population":0,
    "gn:timezone":"America/Bogota",
    "iso:country":"CO",
    "wof:name":"Guazo",
    "wof:placetype":"locality"
},
  "geometry": {"coordinates":[-74.05833,5.54528],"type":"Point"}
}