{
  "type": "Feature",
  "properties": {
    "gn:admin1_code":"26",
    "gn:admin2_code":"68406.0",
    "gn:asciiname":"Zaragoza",
    "gn:country_code":"CO",
    "gn:dem":242,
    "gn:feature_class":"P",
    "gn:feature_code":"PPL",
    "gn:name":"Zaragoza",
    "gn:population":0,
    "gn:timezone":"America/Bogota",
    "iso:country":"CO",
    "wof:name":"Zaragoza",
    "wof:placetype":"locality"
},
  "geometry": {"coordinates":[-73.40285,7.16081],"type":"Point"}
}