{
  "type": "Feature",
  "properties": {
    "gn:admin1_code":"16.0",
    "gn:admin2_code":"41306.0",
    "gn:asciiname":"La Ensillada",
    "gn:country_code":"CO",
    "gn:dem":918,
    "gn:feature_class":"P",
    "gn:feature_code":"PPL",
    "gn:name":"La Ensillada",
    "gn:population":0,
    "gn:timezone":"America/Bogota",
    "iso:country":"CO",
    "wof:name":"La Ensillada",
    "wof:placetype":"locality"
},
  "geometry": {"coordinates":[-75.62639,2.37111],"type":"Point"}
}