{
  "type": "Feature",
  "properties": {
    "gn:admin1_code":"9.0",
    "gn:admin2_code":"19392.0",
    "gn:asciiname":"San Pedro Alto",
    "gn:country_code":"CO",
    "gn:dem":2336,
    "gn:feature_class":"P",
    "gn:feature_code":"PPL",
    "gn:name":"San Pedro Alto",
    "gn:population":0,
    "gn:timezone":"America/Bogota",
    "iso:country":"CO",
    "wof:name":"San Pedro Alto",
    "wof:placetype":"locality"
},
  "geometry": {"coordinates":[-76.65765999999998,2.18731],"type":"Point"}
}