{
  "type": "Feature",
  "properties": {
    "gn:admin1_code":"36",
    "gn:admin2_code":"15531.0",
    "gn:asciiname":"Guadales",
    "gn:country_code":"CO",
    "gn:dem":691,
    "gn:feature_class":"P",
    "gn:feature_code":"PPL",
    "gn:name":"Guadales",
    "gn:population":0,
    "gn:timezone":"America/Bogota",
    "iso:country":"CO",
    "wof:name":"Guadales",
    "wof:placetype":"locality"
},
  "geometry": {"coordinates":[-74.08750000000001,5.75722],"type":"Point"}
}