{
  "type": "Feature",
  "properties": {
    "gn:admin1_code":"20",
    "gn:admin2_code":"52079.0",
    "gn:asciiname":"La Ladera",
    "gn:country_code":"CO",
    "gn:dem":339,
    "gn:feature_class":"P",
    "gn:feature_code":"PPL",
    "gn:name":"La Ladera",
    "gn:population":0,
    "gn:timezone":"America/Bogota",
    "iso:country":"CO",
    "wof:name":"La Ladera",
    "wof:placetype":"locality"
},
  "geometry": {"coordinates":[-78.25,1.53333],"type":"Point"}
}