{
  "type": "Feature",
  "properties": {
    "gn:admin1_code":"26.0",
    "gn:admin2_code":"68689.0",
    "gn:asciiname":"El Porvenir",
    "gn:country_code":"CO",
    "gn:dem":108,
    "gn:feature_class":"P",
    "gn:feature_code":"PPLL",
    "gn:name":"El Porvenir",
    "gn:population":0,
    "gn:timezone":"America/Bogota",
    "iso:country":"CO",
    "wof:name":"El Porvenir",
    "wof:placetype":"locality"
},
  "geometry": {"coordinates":[-73.58487,6.9554],"type":"Point"}
}