{
  "type": "Feature",
  "properties": {
    "gn:admin1_code":"35",
    "gn:admin2_code":"13212.0",
    "gn:asciiname":"Jacinto",
    "gn:country_code":"CO",
    "gn:dem":84,
    "gn:feature_class":"P",
    "gn:feature_code":"PPL",
    "gn:name":"Jacinto",
    "gn:population":0,
    "gn:timezone":"America/Bogota",
    "iso:country":"CO",
    "name:und_x_variant":[
        "Hacienda Jacinto",
        "Jacinto"
    ],
    "wof:name":"Jacinto",
    "wof:placetype":"locality"
},
  "geometry": {"coordinates":[-74.98205,9.57126],"type":"Point"}
}