{
  "type": "Feature",
  "properties": {
    "gn:admin1_code":"28.0",
    "gn:admin2_code":"73443.0",
    "gn:asciiname":"Granja Mariquita",
    "gn:country_code":"CO",
    "gn:dem":458,
    "gn:feature_class":"P",
    "gn:feature_code":"PPL",
    "gn:name":"Granja Mariquita",
    "gn:population":0,
    "gn:timezone":"America/Bogota",
    "iso:country":"CO",
    "name:spa_x_preferred":[
        "Granja Mariquita"
    ],
    "wof:name":"Granja Mariquita",
    "wof:placetype":"locality"
},
  "geometry": {"coordinates":[-74.88061,5.1876],"type":"Point"}
}