{
  "type": "Feature",
  "properties": {
    "gn:admin1_code":"26",
    "gn:admin2_code":"68533.0",
    "gn:asciiname":"La Maseta",
    "gn:country_code":"CO",
    "gn:dem":1284,
    "gn:feature_class":"P",
    "gn:feature_code":"PPL",
    "gn:name":"La Maseta",
    "gn:population":0,
    "gn:timezone":"America/Bogota",
    "iso:country":"CO",
    "wof:name":"La Maseta",
    "wof:placetype":"locality"
},
  "geometry": {"coordinates":[-73.16875,6.37815],"type":"Point"}
}