{
  "type": "Feature",
  "properties": {
    "gn:admin1_code":"29.0",
    "gn:admin2_code":"76364.0",
    "gn:asciiname":"Velez",
    "gn:country_code":"CO",
    "gn:dem":1516,
    "gn:feature_class":"P",
    "gn:feature_code":"PPL",
    "gn:name":"V\u00e9lez",
    "gn:population":0,
    "gn:timezone":"America/Bogota",
    "iso:country":"CO",
    "name:ceb_x_preferred":[
        "Velez"
    ],
    "name:ita_x_preferred":[
        "Velez"
    ],
    "name:kor_x_preferred":[
        "\ubca8\ub808\uc2a4"
    ],
    "name:spa_x_preferred":[
        "V\u00e9lez"
    ],
    "name:swe_x_preferred":[
        "Velez"
    ],
    "wof:name":"Velez",
    "wof:placetype":"locality"
},
  "geometry": {"coordinates":[-76.63887,3.25665],"type":"Point"}
}