{
  "type": "Feature",
  "properties": {
    "gn:admin1_code":"29",
    "gn:admin2_code":"76233.0",
    "gn:asciiname":"Los Alpes",
    "gn:country_code":"CO",
    "gn:dem":1118,
    "gn:feature_class":"P",
    "gn:feature_code":"PPL",
    "gn:name":"Los Alpes",
    "gn:population":0,
    "gn:timezone":"America/Bogota",
    "iso:country":"CO",
    "wof:name":"Los Alpes",
    "wof:placetype":"locality"
},
  "geometry": {"coordinates":[-76.69110999999999,3.72194],"type":"Point"}
}