{
  "type": "Feature",
  "properties": {
    "gn:admin1_code":"20.0",
    "gn:admin2_code":"52418.0",
    "gn:asciiname":"Las Vueltas",
    "gn:country_code":"CO",
    "gn:dem":1376,
    "gn:feature_class":"P",
    "gn:feature_code":"PPL",
    "gn:name":"Las Vueltas",
    "gn:population":0,
    "gn:timezone":"America/Bogota",
    "iso:country":"CO",
    "wof:name":"Las Vueltas",
    "wof:placetype":"locality"
},
  "geometry": {"coordinates":[-77.47545,1.54045],"type":"Point"}
}