{
  "type": "Feature",
  "properties": {
    "gn:admin1_code":"20.0",
    "gn:admin2_code":"52418.0",
    "gn:asciiname":"Las Vueltas",
    "gn:country_code":"CO",
    "gn:dem":1376,
    "gn:feature_class":"P",
    "gn:feature_code":"PPL",
    "gn:name":"Las Vueltas",
    "gn:population":0,
    "gn:timezone":"America/Bogota",
    "iso:country":"CO",
    "name:ceb_x_preferred":[
        "Las Vueltas"
    ],
    "name:deu_x_preferred":[
        "Las Vueltas"
    ],
    "name:fas_x_preferred":[
        "\u0644\u0627\u0633 \u0648\u0648\u0626\u0644\u062a\u0627\u0633"
    ],
    "name:fra_x_preferred":[
        "Las Vueltas"
    ],
    "name:ita_x_preferred":[
        "Las Vueltas"
    ],
    "name:por_x_preferred":[
        "Las Vueltas"
    ],
    "name:spa_x_preferred":[
        "Las Vueltas"
    ],
    "name:urd_x_preferred":[
        "\u0644\u0627\u0633 \u0648\u0648\u06cc\u0644\u0679\u0627\u0633"
    ],
    "name:zho_x_preferred":[
        "\u62c9\u65af\u5e03\u57c3\u723e\u5854\u65af"
    ],
    "wof:name":"Las Vueltas",
    "wof:placetype":"locality"
},
  "geometry": {"coordinates":[-77.47545,1.54045],"type":"Point"}
}