{
  "type": "Feature",
  "properties": {
    "gn:admin1_code":"9.0",
    "gn:admin2_code":"19256.0",
    "gn:asciiname":"La Libertad",
    "gn:country_code":"CO",
    "gn:dem":273,
    "gn:feature_class":"P",
    "gn:feature_code":"PPL",
    "gn:name":"La Libertad",
    "gn:population":0,
    "gn:timezone":"America/Bogota",
    "iso:country":"CO",
    "name:ceb_x_preferred":[
        "La Libertad"
    ],
    "name:deu_x_preferred":[
        "La Libertad"
    ],
    "name:ell_x_preferred":[
        "\u039b\u03b1 \u039b\u03b9\u03bc\u03c0\u03b5\u03c1\u03c4\u03ac\u03b4"
    ],
    "name:epo_x_preferred":[
        "La Libertad"
    ],
    "name:fra_x_preferred":[
        "La Libertad"
    ],
    "name:glg_x_preferred":[
        "La Libertad"
    ],
    "name:ita_x_preferred":[
        "La Libertad"
    ],
    "name:kor_x_preferred":[
        "\ub77c \ub9ac\ubca0\ub974\ud0c0\ub4dc"
    ],
    "name:kor_x_variant":[
        "\ub77c\ub9ac\ubca0\ub974\ud0c0\ub4dc"
    ],
    "name:lit_x_preferred":[
        "La Libertadas"
    ],
    "name:nds_x_preferred":[
        "La Libertad"
    ],
    "name:nld_x_preferred":[
        "La Libertad"
    ],
    "name:pol_x_preferred":[
        "La Libertad"
    ],
    "name:por_x_preferred":[
        "La Libertad"
    ],
    "name:que_x_preferred":[
        "La Libertad"
    ],
    "name:rus_x_preferred":[
        "\u041b\u0430-\u041b\u0438\u0431\u0435\u0440\u0442\u0430\u0434"
    ],
    "name:sco_x_preferred":[
        "La Libertad"
    ],
    "name:spa_x_preferred":[
        "La Libertad"
    ],
    "name:srp_x_preferred":[
        "\u041b\u0430 \u041b\u0438\u0431\u0435\u0440\u0442\u0430\u0434"
    ],
    "name:swe_x_preferred":[
        "La Libertad"
    ],
    "name:tur_x_preferred":[
        "La Libertad"
    ],
    "name:ukr_x_preferred":[
        "\u041b\u0430-\u041b\u0456\u0431\u0435\u0440\u0442\u0430\u0434"
    ],
    "name:urd_x_preferred":[
        "\u0644\u0627 \u0644\u0628\u0631\u062a\u0627\u062f"
    ],
    "name:vie_x_preferred":[
        "La Libertad"
    ],
    "name:war_x_preferred":[
        "La Libertad"
    ],
    "wof:name":"La Libertad",
    "wof:placetype":"locality"
},
  "geometry": {"coordinates":[-77.15040999999999,2.63703],"type":"Point"}
}