{
  "type": "Feature",
  "properties": {
    "gn:admin1_code":"9",
    "gn:admin2_code":"19256.0",
    "gn:asciiname":"California",
    "gn:country_code":"CO",
    "gn:dem":1960,
    "gn:feature_class":"P",
    "gn:feature_code":"PPL",
    "gn:name":"California",
    "gn:population":0,
    "gn:timezone":"America/Bogota",
    "iso:country":"CO",
    "wof:name":"California",
    "wof:placetype":"locality"
},
  "geometry": {"coordinates":[-76.91014,2.50944],"type":"Point"}
}