{
  "type": "Feature",
  "properties": {
    "gn:admin1_code":"29",
    "gn:admin2_code":"76520.0",
    "gn:asciiname":"La Reserva",
    "gn:country_code":"CO",
    "gn:dem":970,
    "gn:feature_class":"P",
    "gn:feature_code":"PPL",
    "gn:name":"La Reserva",
    "gn:population":0,
    "gn:timezone":"America/Bogota",
    "iso:country":"CO",
    "wof:name":"La Reserva",
    "wof:placetype":"locality"
},
  "geometry": {"coordinates":[-76.36667,3.52694],"type":"Point"}
}