{
  "type": "Feature",
  "properties": {
    "gn:admin1_code":"19.0",
    "gn:admin2_code":"50577.0",
    "gn:asciiname":"Venezuela",
    "gn:country_code":"CO",
    "gn:dem":217,
    "gn:feature_class":"P",
    "gn:feature_code":"PPLL",
    "gn:name":"Venezuela",
    "gn:population":0,
    "gn:timezone":"America/Bogota",
    "iso:country":"CO",
    "name:spa_x_preferred":[
        "Venezuela"
    ],
    "wof:name":"Venezuela",
    "wof:placetype":"locality"
},
  "geometry": {"coordinates":[-73.247,3.101],"type":"Point"}
}