{
  "type": "Feature",
  "properties": {
    "gn:admin1_code":"19",
    "gn:admin2_code":"50689",
    "gn:asciiname":"Santa Monica",
    "gn:country_code":"CO",
    "gn:dem":329,
    "gn:feature_class":"P",
    "gn:feature_code":"PPL",
    "gn:name":"Santa Monica",
    "gn:population":0,
    "gn:timezone":"America/Bogota",
    "iso:country":"CO",
    "name:spa_x_preferred":[
        "Santa Monica"
    ],
    "wof:name":"Santa Monica",
    "wof:placetype":"locality"
},
  "geometry": {"coordinates":[-73.61721999999997,3.54278],"type":"Point"}
}