{
  "type": "Feature",
  "properties": {
    "gn:admin1_code":"26",
    "gn:admin2_code":"68655.0",
    "gn:asciiname":"Casanueva",
    "gn:country_code":"CO",
    "gn:dem":78,
    "gn:feature_class":"P",
    "gn:feature_code":"PPL",
    "gn:name":"Casanueva",
    "gn:population":0,
    "gn:timezone":"America/Bogota",
    "iso:country":"CO",
    "wof:name":"Casanueva",
    "wof:placetype":"locality"
},
  "geometry": {"coordinates":[-73.53333000000001,7.53333],"type":"Point"}
}