{
  "type": "Feature",
  "properties": {
    "gn:admin1_code":"32.0",
    "gn:admin2_code":"85001.0",
    "gn:asciiname":"Tachuelo",
    "gn:country_code":"CO",
    "gn:dem":491,
    "gn:feature_class":"P",
    "gn:feature_code":"PPL",
    "gn:name":"Tachuelo",
    "gn:population":0,
    "gn:timezone":"America/Bogota",
    "iso:country":"CO",
    "wof:name":"Tachuelo",
    "wof:placetype":"locality"
},
  "geometry": {"coordinates":[-72.31248000000002,5.43949],"type":"Point"}
}