{
  "type": "Feature",
  "properties": {
    "gn:admin1_code":"36",
    "gn:admin2_code":"15837.0",
    "gn:asciiname":"El Dividivi",
    "gn:country_code":"CO",
    "gn:dem":2683,
    "gn:feature_class":"P",
    "gn:feature_code":"PPL",
    "gn:name":"El Dividivi",
    "gn:population":0,
    "gn:timezone":"America/Bogota",
    "iso:country":"CO",
    "wof:name":"El Dividivi",
    "wof:placetype":"locality"
},
  "geometry": {"coordinates":[-73.11667,5.66667],"type":"Point"}
}