{
  "type": "Feature",
  "properties": {
    "gn:admin1_code":"12",
    "gn:admin2_code":"23807.0",
    "gn:asciiname":"Carrizola",
    "gn:cc2":"CO",
    "gn:country_code":"CO",
    "gn:dem":54,
    "gn:feature_class":"P",
    "gn:feature_code":"PPL",
    "gn:name":"Carrizola",
    "gn:population":0,
    "gn:timezone":"America/Bogota",
    "iso:country":"CO",
    "name:und_x_variant":[
        "Carrisola",
        "Carrizola"
    ],
    "wof:name":"Carrizola",
    "wof:placetype":"locality"
},
  "geometry": {"coordinates":[-75.88333,8.23333],"type":"Point"}
}