{
  "type": "Feature",
  "properties": {
    "gn:admin1_code":"32",
    "gn:admin2_code":"85400.0",
    "gn:asciiname":"La Parroquia",
    "gn:country_code":"CO",
    "gn:dem":924,
    "gn:feature_class":"P",
    "gn:feature_code":"PPL",
    "gn:name":"La Parroquia",
    "gn:population":0,
    "gn:timezone":"America/Bogota",
    "iso:country":"CO",
    "wof:name":"La Parroquia",
    "wof:placetype":"locality"
},
  "geometry": {"coordinates":[-72.27816999999997,5.8695],"type":"Point"}
}