{
  "type": "Feature",
  "properties": {
    "gn:admin1_code":"1.0",
    "gn:admin2_code":"91263.0",
    "gn:asciiname":"Soledad",
    "gn:country_code":"CO",
    "gn:dem":104,
    "gn:feature_class":"P",
    "gn:feature_code":"PPL",
    "gn:name":"Soledad",
    "gn:population":0,
    "gn:timezone":"America/Bogota",
    "iso:country":"CO",
    "wof:name":"Soledad",
    "wof:placetype":"locality"
},
  "geometry": {"coordinates":[-72.45344,-1.84696],"type":"Point"}
}