{
  "type": "Feature",
  "properties": {
    "gn:admin1_code":"9.0",
    "gn:admin2_code":"19001.0",
    "gn:asciiname":"Vereda San Juan",
    "gn:country_code":"CO",
    "gn:dem":2324,
    "gn:feature_class":"P",
    "gn:feature_code":"PPLL",
    "gn:name":"Vereda San Juan",
    "gn:population":0,
    "gn:timezone":"America/Bogota",
    "iso:country":"CO",
    "wof:name":"Vereda San Juan",
    "wof:placetype":"locality"
},
  "geometry": {"coordinates":[-76.47869,2.47017],"type":"Point"}
}