{
  "type": "Feature",
  "properties": {
    "gn:admin1_code":"8.0",
    "gn:admin2_code":"18001.0",
    "gn:asciiname":"La Alejandria",
    "gn:country_code":"CO",
    "gn:dem":273,
    "gn:feature_class":"P",
    "gn:feature_code":"PPL",
    "gn:name":"La Alejandr\u00eda",
    "gn:population":0,
    "gn:timezone":"America/Bogota",
    "iso:country":"CO",
    "name:spa_x_preferred":[
        "La Alejandr\u00eda"
    ],
    "wof:name":"La Alejandria",
    "wof:placetype":"locality"
},
  "geometry": {"coordinates":[-75.66512,1.53638],"type":"Point"}
}