{
  "type": "Feature",
  "properties": {
    "gn:admin1_code":"26",
    "gn:admin2_code":"68745.0",
    "gn:asciiname":"Placita",
    "gn:country_code":"CO",
    "gn:dem":2255,
    "gn:feature_class":"P",
    "gn:feature_code":"PPL",
    "gn:name":"Placita",
    "gn:population":0,
    "gn:timezone":"America/Bogota",
    "iso:country":"CO",
    "wof:name":"Placita",
    "wof:placetype":"locality"
},
  "geometry": {"coordinates":[-73.42036999999998,6.48671],"type":"Point"}
}