{
  "type": "Feature",
  "properties": {
    "gn:admin1_code":"2",
    "gn:admin2_code":"5107.0",
    "gn:asciiname":"La Providencia",
    "gn:country_code":"CO",
    "gn:dem":1176,
    "gn:feature_class":"P",
    "gn:feature_code":"PPL",
    "gn:name":"La Providencia",
    "gn:population":0,
    "gn:timezone":"America/Bogota",
    "iso:country":"CO",
    "wof:name":"La Providencia",
    "wof:placetype":"locality"
},
  "geometry": {"coordinates":[-75.62306,7.04778],"type":"Point"}
}