{
  "type": "Feature",
  "properties": {
    "iso:country":"CO",
    "name:ara_x_preferred":[
        "\u0633\u0627\u0646\u062a\u0627\u0646\u062f\u064a\u0631 \u062f\u064a \u0643\u064a\u0644\u064a\u062c\u0627\u0648"
    ],
    "name:bel_x_preferred":[
        "\u0421\u0430\u043d\u0442\u0430\u043d\u0434\u044d\u0440-\u0434\u044d-\u041a\u0456\u043b\u0456\u0447\u0430\u0430"
    ],
    "name:ceb_x_preferred":[
        "Santander de Quilichao"
    ],
    "name:deu_x_preferred":[
        "Santander de Quilichao"
    ],
    "name:eng_x_preferred":[
        "Santander de Quilichao"
    ],
    "name:fas_x_preferred":[
        "\u0633\u0627\u0646\u062a\u0627\u0646\u062f\u0631 \u062f\u0647 \u06a9\u06cc\u0644\u06cc\u0686\u0627\u0626\u0648"
    ],
    "name:fra_x_preferred":[
        "Santander de Quilichao"
    ],
    "name:heb_x_preferred":[
        "\u05e1\u05e0\u05d8\u05e0\u05d3\u05e8 \u05d3\u05d4 \u05e7\u05d9\u05dc\u05d9\u05e6'\u05d0\u05d5"
    ],
    "name:ita_x_preferred":[
        "Santander de Quilichao"
    ],
    "name:jpn_x_preferred":[
        "\u30b5\u30f3\u30bf\u30f3\u30c7\u30eb\u30fb\u30c7\u30fb\u30ad\u30ea\u30c1\u30e3\u30aa"
    ],
    "name:kat_x_preferred":[
        "\u10e1\u10d0\u10dc\u10e2\u10d0\u10dc\u10d3\u10d4\u10e0-\u10d3\u10d4-\u10d9\u10d8\u10da\u10d8\u10e9\u10d0\u10dd"
    ],
    "name:msa_x_preferred":[
        "Santander de Quilichao"
    ],
    "name:nan_x_preferred":[
        "Santander de Quilichao"
    ],
    "name:nld_x_preferred":[
        "Santander de Quilichao"
    ],
    "name:nno_x_preferred":[
        "Santander de Quilichao"
    ],
    "name:nob_x_preferred":[
        "Santander de Quilichao"
    ],
    "name:por_x_preferred":[
        "Santander de Quilichao"
    ],
    "name:rus_x_preferred":[
        "\u0421\u0430\u043d\u0442\u0430\u043d\u0434\u0435\u0440-\u0434\u0435-\u041a\u0438\u043b\u0438\u0447\u0430\u043e"
    ],
    "name:spa_x_preferred":[
        "Santander de Quilichao"
    ],
    "name:swe_x_preferred":[
        "Santander de Quilichao"
    ],
    "name:tgl_x_preferred":[
        "Santander de Quilichao"
    ],
    "name:unk_x_variant":[
        "Quilichao"
    ],
    "name:vie_x_preferred":[
        "Santander de Quilichao"
    ],
    "name:war_x_preferred":[
        "Santander de Quilichao"
    ],
    "name:zho_min_nan_x_preferred":[
        "Santander de Quilichao"
    ],
    "name:zho_x_preferred":[
        "\u6851\u5766\u5fb7\u57fa\u5229\u55ac"
    ],
    "qs:gn_country":"CO",
    "qs:gn_fcode":"PPL",
    "qs:gn_pop":40798,
    "qs:name":"Santander de Quilichao",
    "qs:name_adm0":"Colombia",
    "qs:name_adm1":"Cauca",
    "qs:photos":92,
    "qs:photos_1k":19,
    "qs:photos_9k":1,
    "qs:photos_9r":3,
    "qs:photos_all":92,
    "qs:photos_sr":3,
    "qs:placetype":"Town",
    "qs:pop_sr":"7",
    "qs:woe_adm0":23424787,
    "wof:name":"Santander de Quilichao",
    "wof:placetype":"locality",
    "wof:population":40798
},
  "geometry": {"coordinates":[-76.48493999999999,3.00945],"type":"Point"}
}