{
  "type": "Feature",
  "properties": {
    "gn:admin1_code":"31",
    "gn:admin2_code":"99773.0",
    "gn:asciiname":"Mataveni",
    "gn:country_code":"CO",
    "gn:dem":94,
    "gn:feature_class":"P",
    "gn:feature_code":"PPL",
    "gn:name":"Mataven\u00ed",
    "gn:population":0,
    "gn:timezone":"America/Bogota",
    "iso:country":"CO",
    "wof:name":"Mataveni",
    "wof:placetype":"locality"
},
  "geometry": {"coordinates":[-67.8085,4.28446],"type":"Point"}
}