{
  "type": "Feature",
  "properties": {
    "gn:admin1_code":"21",
    "gn:admin2_code":"54820.0",
    "gn:asciiname":"Miralindo",
    "gn:country_code":"CO",
    "gn:dem":2238,
    "gn:feature_class":"P",
    "gn:feature_code":"PPL",
    "gn:name":"Miralindo",
    "gn:population":0,
    "gn:timezone":"America/Bogota",
    "iso:country":"CO",
    "wof:name":"Miralindo",
    "wof:placetype":"locality"
},
  "geometry": {"coordinates":[-72.33719000000001,7.11768],"type":"Point"}
}