{
  "type": "Feature",
  "properties": {
    "gn:admin1_code":"26.0",
    "gn:admin2_code":"68773.0",
    "gn:asciiname":"Sabana Grande",
    "gn:country_code":"CO",
    "gn:dem":2512,
    "gn:feature_class":"P",
    "gn:feature_code":"PPL",
    "gn:name":"Sabana Grande",
    "gn:population":0,
    "gn:timezone":"America/Bogota",
    "iso:country":"CO",
    "wof:name":"Sabana Grande",
    "wof:placetype":"locality"
},
  "geometry": {"coordinates":[-73.91,5.99222],"type":"Point"}
}