{
  "type": "Feature",
  "properties": {
    "gn:admin1_code":"35",
    "gn:admin2_code":"13042.0",
    "gn:asciiname":"Carnisal",
    "gn:country_code":"CO",
    "gn:dem":43,
    "gn:feature_class":"P",
    "gn:feature_code":"PPL",
    "gn:name":"Carnisal",
    "gn:population":0,
    "gn:timezone":"America/Bogota",
    "iso:country":"CO",
    "name:und_x_variant":[
        "Caser\u00edo Carnisala",
        "Carnisal",
        "Carnisala"
    ],
    "wof:name":"Carnisal",
    "wof:placetype":"locality"
},
  "geometry": {"coordinates":[-73.90082,8.45497],"type":"Point"}
}