{
  "type": "Feature",
  "properties": {
    "gn:admin1_code":"4",
    "gn:admin2_code":"8141.0",
    "gn:asciiname":"Loma Quemada",
    "gn:country_code":"CO",
    "gn:dem":37,
    "gn:feature_class":"P",
    "gn:feature_code":"PPL",
    "gn:name":"Loma Quemada",
    "gn:population":0,
    "gn:timezone":"America/Bogota",
    "iso:country":"CO",
    "wof:name":"Loma Quemada",
    "wof:placetype":"locality"
},
  "geometry": {"coordinates":[-74.86667,10.55],"type":"Point"}
}