{
  "type": "Feature",
  "properties": {
    "gn:admin1_code":"26.0",
    "gn:admin2_code":"68498.0",
    "gn:asciiname":"El Atigal",
    "gn:country_code":"CO",
    "gn:dem":1875,
    "gn:feature_class":"P",
    "gn:feature_code":"PPL",
    "gn:name":"El Atigal",
    "gn:population":0,
    "gn:timezone":"America/Bogota",
    "iso:country":"CO",
    "wof:name":"El Atigal",
    "wof:placetype":"locality"
},
  "geometry": {"coordinates":[-73.12084,6.37184],"type":"Point"}
}