{
  "type": "Feature",
  "properties": {
    "gn:admin1_code":"3.0",
    "gn:admin2_code":"81001.0",
    "gn:asciiname":"San Jorge",
    "gn:country_code":"CO",
    "gn:dem":123,
    "gn:feature_class":"P",
    "gn:feature_code":"PPL",
    "gn:name":"San Jorge",
    "gn:population":0,
    "gn:timezone":"America/Bogota",
    "iso:country":"CO",
    "name:spa_x_preferred":[
        "San Jorge"
    ],
    "wof:name":"San Jorge",
    "wof:placetype":"locality"
},
  "geometry": {"coordinates":[-70.92319000000001,6.70053],"type":"Point"}
}