{
  "type": "Feature",
  "properties": {
    "gn:admin1_code":"4",
    "gn:admin2_code":"8685.0",
    "gn:asciiname":"Ballesteros",
    "gn:country_code":"CO",
    "gn:dem":51,
    "gn:feature_class":"P",
    "gn:feature_code":"PPL",
    "gn:name":"Ballesteros",
    "gn:population":0,
    "gn:timezone":"America/Bogota",
    "iso:country":"CO",
    "name:cat_x_preferred":[
        "Ballesteros"
    ],
    "name:ceb_x_preferred":[
        "Ballesteros"
    ],
    "name:deu_x_preferred":[
        "Ballesteros"
    ],
    "name:fra_x_preferred":[
        "Ballesteros"
    ],
    "name:ita_x_preferred":[
        "Ballesteros"
    ],
    "name:nld_x_preferred":[
        "Ballesteros"
    ],
    "name:rus_x_preferred":[
        "\u0411\u0430\u043b\u044c\u0435\u0441\u0442\u0435\u0440\u043e\u0441"
    ],
    "name:spa_x_preferred":[
        "Ballesteros"
    ],
    "name:swe_x_preferred":[
        "Ballesteros"
    ],
    "name:war_x_preferred":[
        "Ballesteros"
    ],
    "wof:name":"Ballesteros",
    "wof:placetype":"locality"
},
  "geometry": {"coordinates":[-74.83333,10.71667],"type":"Point"}
}