{
  "type": "Feature",
  "properties": {
    "gn:admin1_code":"12",
    "gn:admin2_code":"23660.0",
    "gn:asciiname":"Callelarga",
    "gn:cc2":"CO",
    "gn:country_code":"CO",
    "gn:dem":150,
    "gn:feature_class":"P",
    "gn:feature_code":"PPL",
    "gn:name":"Callelarga",
    "gn:population":0,
    "gn:timezone":"America/Bogota",
    "iso:country":"CO",
    "name:und_x_variant":[
        "Calle Largo",
        "Callelarga"
    ],
    "wof:name":"Callelarga",
    "wof:placetype":"locality"
},
  "geometry": {"coordinates":[-75.46666999999999,8.68333],"type":"Point"}
}