{
  "type": "Feature",
  "properties": {
    "gn:admin1_code":"16",
    "gn:admin2_code":"41078.0",
    "gn:asciiname":"Los Andes",
    "gn:country_code":"CO",
    "gn:dem":643,
    "gn:feature_class":"P",
    "gn:feature_code":"PPL",
    "gn:name":"Los Andes",
    "gn:population":0,
    "gn:timezone":"America/Bogota",
    "iso:country":"CO",
    "name:spa_x_preferred":[
        "Los Andes"
    ],
    "wof:name":"Los Andes",
    "wof:placetype":"locality"
},
  "geometry": {"coordinates":[-74.96666999999999,3.26667],"type":"Point"}
}