{
  "type": "Feature",
  "properties": {
    "gn:admin1_code":"23",
    "gn:admin2_code":"63302.0",
    "gn:asciiname":"La Judea",
    "gn:country_code":"CO",
    "gn:dem":3187,
    "gn:feature_class":"P",
    "gn:feature_code":"PPL",
    "gn:name":"La Judea",
    "gn:population":0,
    "gn:timezone":"America/Bogota",
    "iso:country":"CO",
    "wof:name":"La Judea",
    "wof:placetype":"locality"
},
  "geometry": {"coordinates":[-75.71611,4.15361],"type":"Point"}
}