{
  "type": "Feature",
  "properties": {
    "gn:admin1_code":"20",
    "gn:admin2_code":"52001.0",
    "gn:asciiname":"Cruz de Amarillo",
    "gn:country_code":"CO",
    "gn:dem":3115,
    "gn:feature_class":"P",
    "gn:feature_code":"PPL",
    "gn:name":"Cruz de Amarillo",
    "gn:population":0,
    "gn:timezone":"America/Bogota",
    "iso:country":"CO",
    "name:und_x_variant":[
        "Cruz de Amarillos",
        "Cruz de Amarillo"
    ],
    "wof:name":"Cruz de Amarillo",
    "wof:placetype":"locality"
},
  "geometry": {"coordinates":[-77.30597,1.13767],"type":"Point"}
}