{
  "type": "Feature",
  "properties": {
    "gn:admin1_code":"26.0",
    "gn:admin2_code":"68572.0",
    "gn:asciiname":"Providencia",
    "gn:country_code":"CO",
    "gn:dem":1985,
    "gn:feature_class":"P",
    "gn:feature_code":"PPL",
    "gn:name":"Providencia",
    "gn:population":0,
    "gn:timezone":"America/Bogota",
    "iso:country":"CO",
    "wof:name":"Providencia",
    "wof:placetype":"locality"
},
  "geometry": {"coordinates":[-73.66083,5.82861],"type":"Point"}
}