{
  "type": "Feature",
  "properties": {
    "gn:admin1_code":"26.0",
    "gn:admin2_code":"68770.0",
    "gn:asciiname":"Samaria",
    "gn:country_code":"CO",
    "gn:dem":1567,
    "gn:feature_class":"P",
    "gn:feature_code":"PPL",
    "gn:name":"Samaria",
    "gn:population":0,
    "gn:timezone":"America/Bogota",
    "iso:country":"CO",
    "wof:name":"Samaria",
    "wof:placetype":"locality"
},
  "geometry": {"coordinates":[-73.30282,6.13656],"type":"Point"}
}