{
  "type": "Feature",
  "properties": {
    "gn:admin1_code":"35",
    "gn:admin2_code":"13600.0",
    "gn:asciiname":"Macedonia",
    "gn:country_code":"CO",
    "gn:dem":31,
    "gn:feature_class":"P",
    "gn:feature_code":"PPL",
    "gn:name":"Macedonia",
    "gn:population":0,
    "gn:timezone":"America/Bogota",
    "iso:country":"CO",
    "name:und_x_variant":[
        "Caserio Macedonia",
        "Macedonia"
    ],
    "wof:name":"Macedonia",
    "wof:placetype":"locality"
},
  "geometry": {"coordinates":[-73.9217,8.64529],"type":"Point"}
}