{
  "type": "Feature",
  "properties": {
    "iso:country":"CO",
    "name:ast_x_preferred":[
        "La Belleza"
    ],
    "name:ceb_x_preferred":[
        "La Belleza"
    ],
    "name:deu_x_preferred":[
        "La Belleza"
    ],
    "name:eng_x_preferred":[
        "La Belleza"
    ],
    "name:fra_x_preferred":[
        "La Belleza"
    ],
    "name:ita_x_preferred":[
        "La Belleza"
    ],
    "name:kat_x_preferred":[
        "\u10da\u10d0-\u10d1\u10d4\u10da\u10d8\u10d4\u10e1\u10d0"
    ],
    "name:msa_x_preferred":[
        "La Belleza"
    ],
    "name:nan_x_preferred":[
        "La Belleza"
    ],
    "name:nld_x_preferred":[
        "La Belleza"
    ],
    "name:sco_x_preferred":[
        "La Belleza"
    ],
    "name:spa_x_preferred":[
        "La Belleza"
    ],
    "name:swe_x_preferred":[
        "La Belleza"
    ],
    "name:tgl_x_preferred":[
        "La Belleza"
    ],
    "name:urd_x_preferred":[
        "\u0644\u0627 \u0628\u06cc\u0644\u06cc\u0632\u0627"
    ],
    "name:vie_x_preferred":[
        "La Belleza"
    ],
    "name:war_x_preferred":[
        "La Belleza"
    ],
    "name:zho_min_nan_x_preferred":[
        "La Belleza"
    ],
    "name:zho_x_preferred":[
        "\u62c9\u8c9d\u5217\u85a9"
    ],
    "qs:gn_country":"CO",
    "qs:gn_fcode":"PPL",
    "qs:gn_pop":1649,
    "qs:name":"La Belleza",
    "qs:name_adm0":"Colombia",
    "qs:name_adm1":"Santander",
    "qs:photos":0,
    "qs:photos_1k":0,
    "qs:photos_9k":0,
    "qs:photos_9r":0,
    "qs:photos_all":0,
    "qs:photos_sr":0,
    "qs:placetype":"Town",
    "qs:pop_sr":"3",
    "qs:woe_adm0":23424787,
    "wd:wordcount":33,
    "wof:name":"La Belleza",
    "wof:placetype":"locality",
    "wof:population":1649
},
  "geometry": {"coordinates":[-73.96167,5.86371],"type":"Point"}
}