{
  "type": "Feature",
  "properties": {
    "gn:admin1_code":"20",
    "gn:admin2_code":"52399.0",
    "gn:asciiname":"Campo Bello",
    "gn:country_code":"CO",
    "gn:dem":1916,
    "gn:feature_class":"P",
    "gn:feature_code":"PPL",
    "gn:name":"Campo Bello",
    "gn:population":0,
    "gn:timezone":"America/Bogota",
    "iso:country":"CO",
    "wof:name":"Campo Bello",
    "wof:placetype":"locality"
},
  "geometry": {"coordinates":[-77.09078000000002,1.60993],"type":"Point"}
}