{
  "type": "Feature",
  "properties": {
    "gn:admin1_code":"33",
    "gn:admin2_code":"25372.0",
    "gn:asciiname":"Alemania",
    "gn:country_code":"CO",
    "gn:dem":2427,
    "gn:feature_class":"P",
    "gn:feature_code":"PPL",
    "gn:name":"Alemania",
    "gn:population":0,
    "gn:timezone":"America/Bogota",
    "iso:country":"CO",
    "wof:name":"Alemania",
    "wof:placetype":"locality"
},
  "geometry": {"coordinates":[-73.6782,4.78105],"type":"Point"}
}