{
  "type": "Feature",
  "properties": {
    "gn:admin1_code":"33",
    "gn:admin2_code":"25178.0",
    "gn:asciiname":"Frutica",
    "gn:country_code":"CO",
    "gn:dem":3355,
    "gn:feature_class":"P",
    "gn:feature_code":"PPL",
    "gn:name":"Frutica",
    "gn:population":0,
    "gn:timezone":"America/Bogota",
    "iso:country":"CO",
    "wof:name":"Frutica",
    "wof:placetype":"locality"
},
  "geometry": {"coordinates":[-74.08333,4.35],"type":"Point"}
}