{
  "type": "Feature",
  "properties": {
    "gn:admin1_code":"2.0",
    "gn:admin2_code":"5664.0",
    "gn:asciiname":"Chuscalito",
    "gn:country_code":"CO",
    "gn:dem":2625,
    "gn:feature_class":"P",
    "gn:feature_code":"PPL",
    "gn:name":"Chuscalito",
    "gn:population":0,
    "gn:timezone":"America/Bogota",
    "iso:country":"CO",
    "wof:name":"Chuscalito",
    "wof:placetype":"locality"
},
  "geometry": {"coordinates":[-75.61471999999998,6.50417],"type":"Point"}
}