{
  "type": "Feature",
  "properties": {
    "gn:admin1_code":"10",
    "gn:admin2_code":"20614.0",
    "gn:asciiname":"Sabanas",
    "gn:country_code":"CO",
    "gn:dem":1393,
    "gn:feature_class":"P",
    "gn:feature_code":"PPL",
    "gn:name":"Sabanas",
    "gn:population":0,
    "gn:timezone":"America/Bogota",
    "iso:country":"CO",
    "wof:name":"Sabanas",
    "wof:placetype":"locality"
},
  "geometry": {"coordinates":[-73.42667,8.33472],"type":"Point"}
}