{
  "type": "Feature",
  "properties": {
    "gn:admin1_code":"9.0",
    "gn:admin2_code":"19743.0",
    "gn:asciiname":"Valle Nuevo",
    "gn:country_code":"CO",
    "gn:dem":2454,
    "gn:feature_class":"P",
    "gn:feature_code":"PPLL",
    "gn:name":"Valle Nuevo",
    "gn:population":0,
    "gn:timezone":"America/Bogota",
    "iso:country":"CO",
    "wof:name":"Valle Nuevo",
    "wof:placetype":"locality"
},
  "geometry": {"coordinates":[-76.46924,2.65977],"type":"Point"}
}