{
  "type": "Feature",
  "properties": {
    "iso:country":"CO",
    "name:ast_x_preferred":[
        "Flandes"
    ],
    "name:ceb_x_preferred":[
        "Flandes"
    ],
    "name:deu_x_preferred":[
        "Flandes"
    ],
    "name:eng_x_preferred":[
        "Flandes"
    ],
    "name:fas_x_preferred":[
        "\u0641\u0644\u0627\u0646\u062f\u0633"
    ],
    "name:fra_x_preferred":[
        "Flandes"
    ],
    "name:ita_x_preferred":[
        "Flandes"
    ],
    "name:jpn_x_preferred":[
        "\u30d5\u30e9\u30f3\u30c7\u30b9"
    ],
    "name:kat_x_preferred":[
        "\u10e4\u10da\u10d0\u10dc\u10d3\u10d4\u10e1\u10d8"
    ],
    "name:msa_x_preferred":[
        "Flandes"
    ],
    "name:nan_x_preferred":[
        "Flandes"
    ],
    "name:nld_x_preferred":[
        "Flandes"
    ],
    "name:spa_x_preferred":[
        "Flandes"
    ],
    "name:swe_x_preferred":[
        "Flandes"
    ],
    "name:vie_x_preferred":[
        "Flandes"
    ],
    "name:war_x_preferred":[
        "Flandes"
    ],
    "name:zho_x_preferred":[
        "\u5f17\u862d\u5fb7\u65af"
    ],
    "qs:gn_country":"CO",
    "qs:gn_fcode":"PPL",
    "qs:gn_pop":20919,
    "qs:name":"Flandes",
    "qs:name_adm0":"Colombia",
    "qs:name_adm1":"Tolima",
    "qs:photos":240,
    "qs:photos_1k":49,
    "qs:photos_9k":1,
    "qs:photos_9r":4,
    "qs:photos_all":240,
    "qs:photos_sr":4,
    "qs:placetype":"Town",
    "qs:pop_sr":"7",
    "qs:woe_adm0":23424787,
    "wof:name":"Flandes",
    "wof:placetype":"locality",
    "wof:population":20919
},
  "geometry": {"coordinates":[-74.81901000000001,4.29413],"type":"Point"}
}