{
  "type": "Feature",
  "properties": {
    "gn:admin1_code":"8.0",
    "gn:asciiname":"Vereda Bajo Caldas",
    "gn:country_code":"CO",
    "gn:dem":271,
    "gn:feature_class":"P",
    "gn:feature_code":"PPLL",
    "gn:name":"Vereda Bajo Caldas",
    "gn:population":0,
    "gn:timezone":"America/Bogota",
    "iso:country":"CO",
    "name:spa_x_preferred":[
        "Vereda Bajo Caldas"
    ],
    "wof:name":"Vereda Bajo Caldas",
    "wof:placetype":"locality"
},
  "geometry": {"coordinates":[-75.63056999999998,1.61228],"type":"Point"}
}