{
  "type": "Feature",
  "properties": {
    "gn:admin1_code":"26.0",
    "gn:admin2_code":"68689.0",
    "gn:asciiname":"Tambo Redondo",
    "gn:country_code":"CO",
    "gn:dem":2252,
    "gn:feature_class":"P",
    "gn:feature_code":"PPL",
    "gn:name":"Tambo Redondo",
    "gn:population":0,
    "gn:timezone":"America/Bogota",
    "iso:country":"CO",
    "wof:name":"Tambo Redondo",
    "wof:placetype":"locality"
},
  "geometry": {"coordinates":[-73.40000000000001,6.76667],"type":"Point"}
}