{
  "type": "Feature",
  "properties": {
    "gn:admin1_code":"10.0",
    "gn:admin2_code":"20011.0",
    "gn:asciiname":"Arrocera Cabezas",
    "gn:country_code":"CO",
    "gn:dem":99,
    "gn:feature_class":"P",
    "gn:feature_code":"PPL",
    "gn:name":"Arrocera Cabezas",
    "gn:population":0,
    "gn:timezone":"America/Bogota",
    "iso:country":"CO",
    "name:spa_x_preferred":[
        "Arrocera Cabezas"
    ],
    "wof:name":"Arrocera Cabezas",
    "wof:placetype":"locality"
},
  "geometry": {"coordinates":[-73.60366999999999,8.17322],"type":"Point"}
}