{
  "type": "Feature",
  "properties": {
    "gn:admin1_code":"28.0",
    "gn:admin2_code":"73624.0",
    "gn:asciiname":"Luisa",
    "gn:country_code":"CO",
    "gn:dem":1222,
    "gn:feature_class":"P",
    "gn:feature_code":"PPL",
    "gn:name":"Luisa",
    "gn:population":0,
    "gn:timezone":"America/Bogota",
    "iso:country":"CO",
    "name:bre_x_preferred":[
        "Luisa"
    ],
    "name:ceb_x_preferred":[
        "Luisa"
    ],
    "name:deu_x_preferred":[
        "Luisa"
    ],
    "name:kor_x_preferred":[
        "\ub8e8\uc774\uc0ac"
    ],
    "name:por_x_preferred":[
        "Lu\u00edsa"
    ],
    "name:srp_x_preferred":[
        "Luisa"
    ],
    "name:swe_x_preferred":[
        "Luisa"
    ],
    "wof:name":"Luisa",
    "wof:placetype":"locality"
},
  "geometry": {"coordinates":[-75.29833000000001,4.24889],"type":"Point"}
}