{
  "type": "Feature",
  "properties": {
    "gn:admin1_code":"21",
    "gn:admin2_code":"54003.0",
    "gn:asciiname":"La Aguada",
    "gn:country_code":"CO",
    "gn:dem":1638,
    "gn:feature_class":"P",
    "gn:feature_code":"PPL",
    "gn:name":"La Aguada",
    "gn:population":0,
    "gn:timezone":"America/Bogota",
    "iso:country":"CO",
    "wof:name":"La Aguada",
    "wof:placetype":"locality"
},
  "geometry": {"coordinates":[-73.16370000000001,8.17035],"type":"Point"}
}