{
  "type": "Feature",
  "properties": {
    "gn:admin1_code":"9.0",
    "gn:admin2_code":"19212.0",
    "gn:asciiname":"Boqueron",
    "gn:country_code":"CO",
    "gn:dem":2326,
    "gn:feature_class":"P",
    "gn:feature_code":"PPL",
    "gn:name":"Boqueron",
    "gn:population":0,
    "gn:timezone":"America/Bogota",
    "iso:country":"CO",
    "name:spa_x_preferred":[
        "Boqueron"
    ],
    "wof:name":"Boqueron",
    "wof:placetype":"locality"
},
  "geometry": {"coordinates":[-76.21038,3.0641],"type":"Point"}
}