{
  "type": "Feature",
  "properties": {
    "gn:admin1_code":"16.0",
    "gn:admin2_code":"41872.0",
    "gn:asciiname":"Hacienda El Arepal",
    "gn:country_code":"CO",
    "gn:dem":395,
    "gn:feature_class":"P",
    "gn:feature_code":"PPL",
    "gn:name":"Hacienda El Arepal",
    "gn:population":0,
    "gn:timezone":"America/Bogota",
    "iso:country":"CO",
    "name:spa_x_preferred":[
        "Hacienda El Arepal"
    ],
    "wof:name":"Hacienda El Arepal",
    "wof:placetype":"locality"
},
  "geometry": {"coordinates":[-75.14285,3.37499],"type":"Point"}
}