{
  "type": "Feature",
  "properties": {
    "gn:admin1_code":"2",
    "gn:admin2_code":"5585.0",
    "gn:asciiname":"Juntas",
    "gn:country_code":"CO",
    "gn:dem":201,
    "gn:feature_class":"P",
    "gn:feature_code":"PPL",
    "gn:name":"Juntas",
    "gn:population":0,
    "gn:timezone":"America/Bogota",
    "iso:country":"CO",
    "wof:name":"Juntas",
    "wof:placetype":"locality"
},
  "geometry": {"coordinates":[-74.71222,6.2375],"type":"Point"}
}