{
  "type": "Feature",
  "properties": {
    "gn:admin1_code":"36",
    "gn:admin2_code":"15531.0",
    "gn:asciiname":"Topo Grande",
    "gn:country_code":"CO",
    "gn:dem":732,
    "gn:feature_class":"P",
    "gn:feature_code":"PPL",
    "gn:name":"Topo Grande",
    "gn:population":0,
    "gn:timezone":"America/Bogota",
    "iso:country":"CO",
    "wof:name":"Topo Grande",
    "wof:placetype":"locality"
},
  "geometry": {"coordinates":[-74.02464000000001,5.65372],"type":"Point"}
}