{
  "type": "Feature",
  "properties": {
    "gn:admin1_code":"2.0",
    "gn:admin2_code":"5607.0",
    "gn:asciiname":"Alta Vista",
    "gn:country_code":"CO",
    "gn:dem":2714,
    "gn:feature_class":"P",
    "gn:feature_code":"PPL",
    "gn:name":"Alta Vista",
    "gn:population":0,
    "gn:timezone":"America/Bogota",
    "iso:country":"CO",
    "name:spa_x_preferred":[
        "Alta Vista"
    ],
    "wof:name":"Alta Vista",
    "wof:placetype":"locality"
},
  "geometry": {"coordinates":[-75.54094000000001,6.09586],"type":"Point"}
}