{
  "type": "Feature",
  "properties": {
    "gn:admin1_code":"17",
    "gn:admin2_code":"44650.0",
    "gn:asciiname":"Los Haticos",
    "gn:country_code":"CO",
    "gn:dem":223,
    "gn:feature_class":"P",
    "gn:feature_code":"PPL",
    "gn:name":"Los Haticos",
    "gn:population":0,
    "gn:timezone":"America/Bogota",
    "iso:country":"CO",
    "name:spa_x_preferred":[
        "Los Haticos"
    ],
    "name:und_x_variant":[
        "Haticos",
        "Hato",
        "Hatillo",
        "Los Haticos"
    ],
    "wof:name":"Los Haticos",
    "wof:placetype":"locality"
},
  "geometry": {"coordinates":[-73.07415999999998,10.74505],"type":"Point"}
}