{
  "type": "Feature",
  "properties": {
    "gn:admin1_code":"35.0",
    "gn:admin2_code":"13188.0",
    "gn:asciiname":"Pena de Mompos",
    "gn:country_code":"CO",
    "gn:dem":19,
    "gn:feature_class":"P",
    "gn:feature_code":"PPL",
    "gn:name":"Pe\u00f1a de Momp\u00f3s",
    "gn:population":0,
    "gn:timezone":"America/Bogota",
    "iso:country":"CO",
    "name:und_x_variant":[
        "Corregimiento Pe\u00f1a de Mompos",
        "Pe\u00f1a da Monpos",
        "Pe\u00f1a",
        "La Pe\u00f1a",
        "Pe\u00f1a de Momp\u00f3s"
    ],
    "wof:name":"Pena de Mompos",
    "wof:placetype":"locality"
},
  "geometry": {"coordinates":[-74.73904,9.22614],"type":"Point"}
}