{
  "type": "Feature",
  "properties": {
    "gn:admin1_code":"27",
    "gn:admin2_code":"70678.0",
    "gn:asciiname":"La Pradera",
    "gn:country_code":"CO",
    "gn:dem":17,
    "gn:feature_class":"P",
    "gn:feature_code":"PPL",
    "gn:name":"La Pradera",
    "gn:population":0,
    "gn:timezone":"America/Bogota",
    "iso:country":"CO",
    "wof:name":"La Pradera",
    "wof:placetype":"locality"
},
  "geometry": {"coordinates":[-74.87680999999998,8.98295],"type":"Point"}
}