{
  "type": "Feature",
  "properties": {
    "gn:admin1_code":"2",
    "gn:admin2_code":"5649.0",
    "gn:asciiname":"Campeche",
    "gn:country_code":"CO",
    "gn:dem":762,
    "gn:feature_class":"P",
    "gn:feature_code":"PPL",
    "gn:name":"Campeche",
    "gn:population":0,
    "gn:timezone":"America/Bogota",
    "iso:country":"CO",
    "wof:name":"Campeche",
    "wof:placetype":"locality"
},
  "geometry": {"coordinates":[-74.82444,6.30472],"type":"Point"}
}