{
  "type": "Feature",
  "properties": {
    "gn:admin1_code":"12.0",
    "gn:admin2_code":"23162.0",
    "gn:asciiname":"Nuevo Reino",
    "gn:country_code":"CO",
    "gn:dem":38,
    "gn:feature_class":"P",
    "gn:feature_code":"PPLL",
    "gn:name":"Nuevo Reino",
    "gn:population":0,
    "gn:timezone":"America/Bogota",
    "iso:country":"CO",
    "wof:name":"Nuevo Reino",
    "wof:placetype":"locality"
},
  "geometry": {"coordinates":[-75.95088,8.92052],"type":"Point"}
}