{
  "type": "Feature",
  "properties": {
    "gn:admin1_code":"2.0",
    "gn:admin2_code":"5837.0",
    "gn:asciiname":"Puerto Bonito",
    "gn:country_code":"CO",
    "gn:dem":141,
    "gn:feature_class":"P",
    "gn:feature_code":"PPL",
    "gn:name":"Puerto Bonito",
    "gn:population":0,
    "gn:timezone":"America/Bogota",
    "iso:country":"CO",
    "wof:name":"Puerto Bonito",
    "wof:placetype":"locality"
},
  "geometry": {"coordinates":[-76.49539,8.19111],"type":"Point"}
}