{
  "type": "Feature",
  "properties": {
    "gn:admin1_code":"26",
    "gn:admin2_code":"68615.0",
    "gn:asciiname":"Puerto Arturo",
    "gn:country_code":"CO",
    "gn:dem":671,
    "gn:feature_class":"P",
    "gn:feature_code":"PPL",
    "gn:name":"Puerto Arturo",
    "gn:population":0,
    "gn:timezone":"America/Bogota",
    "iso:country":"CO",
    "wof:name":"Puerto Arturo",
    "wof:placetype":"locality"
},
  "geometry": {"coordinates":[-73.18528000000001,7.37694],"type":"Point"}
}