{
  "type": "Feature",
  "properties": {
    "gn:admin1_code":"8.0",
    "gn:admin2_code":"18460.0",
    "gn:asciiname":"La Virginia",
    "gn:country_code":"CO",
    "gn:dem":223,
    "gn:feature_class":"P",
    "gn:feature_code":"PPL",
    "gn:name":"La Virginia",
    "gn:population":0,
    "gn:timezone":"America/Bogota",
    "iso:country":"CO",
    "name:spa_x_preferred":[
        "La Virginia"
    ],
    "wof:name":"La Virginia",
    "wof:placetype":"locality"
},
  "geometry": {"coordinates":[-75.51515000000001,1.20604],"type":"Point"}
}