{
  "type": "Feature",
  "properties": {
    "gn:admin1_code":"11",
    "gn:admin2_code":"27372.0",
    "gn:asciiname":"Curiche",
    "gn:country_code":"CO",
    "gn:dem":10,
    "gn:feature_class":"P",
    "gn:feature_code":"PPL",
    "gn:name":"Curiche",
    "gn:population":0,
    "gn:timezone":"America/Bogota",
    "iso:country":"CO",
    "wof:name":"Curiche",
    "wof:placetype":"locality"
},
  "geometry": {"coordinates":[-77.69150999999999,7.03865],"type":"Point"}
}