{
  "type": "Feature",
  "properties": {
    "gn:admin1_code":"10.0",
    "gn:admin2_code":"20001.0",
    "gn:asciiname":"La Victoria",
    "gn:country_code":"CO",
    "gn:dem":81,
    "gn:feature_class":"P",
    "gn:feature_code":"PPL",
    "gn:name":"La Victoria",
    "gn:population":0,
    "gn:timezone":"America/Bogota",
    "iso:country":"CO",
    "wof:name":"La Victoria",
    "wof:placetype":"locality"
},
  "geometry": {"coordinates":[-73.71672,10.00804],"type":"Point"}
}