{
  "type": "Feature",
  "properties": {
    "gn:admin1_code":"16.0",
    "gn:asciiname":"La Cumbre",
    "gn:country_code":"CO",
    "gn:dem":2018,
    "gn:feature_class":"P",
    "gn:feature_code":"PPL",
    "gn:name":"La Cumbre",
    "gn:population":0,
    "gn:timezone":"America/Bogota",
    "iso:country":"CO",
    "name:spa_x_preferred":[
        "La Cumbre"
    ],
    "wof:name":"La Cumbre",
    "wof:placetype":"locality"
},
  "geometry": {"coordinates":[-74.88261999999997,3.39602],"type":"Point"}
}