{
  "type": "Feature",
  "properties": {
    "gn:admin1_code":"26",
    "gn:admin2_code":"68820.0",
    "gn:asciiname":"Guarumales",
    "gn:country_code":"CO",
    "gn:dem":2180,
    "gn:feature_class":"P",
    "gn:feature_code":"PPL",
    "gn:name":"Guarumales",
    "gn:population":0,
    "gn:timezone":"America/Bogota",
    "iso:country":"CO",
    "wof:name":"Guarumales",
    "wof:placetype":"locality"
},
  "geometry": {"coordinates":[-73.01071,7.14856],"type":"Point"}
}