{
  "type": "Feature",
  "properties": {
    "gn:admin1_code":"19.0",
    "gn:admin2_code":"50223.0",
    "gn:asciiname":"Palo Negro",
    "gn:country_code":"CO",
    "gn:dem":889,
    "gn:feature_class":"P",
    "gn:feature_code":"PPL",
    "gn:name":"Palo Negro",
    "gn:population":0,
    "gn:timezone":"America/Bogota",
    "iso:country":"CO",
    "name:spa_x_preferred":[
        "Palo Negro"
    ],
    "wof:name":"Palo Negro",
    "wof:placetype":"locality"
},
  "geometry": {"coordinates":[-73.94604,3.79529],"type":"Point"}
}