{
  "type": "Feature",
  "properties": {
    "gn:admin1_code":"16.0",
    "gn:admin2_code":"41770.0",
    "gn:asciiname":"Hato Viejo",
    "gn:country_code":"CO",
    "gn:dem":978,
    "gn:feature_class":"P",
    "gn:feature_code":"PPL",
    "gn:name":"Hato Viejo",
    "gn:population":0,
    "gn:timezone":"America/Bogota",
    "iso:country":"CO",
    "name:spa_x_preferred":[
        "Hato Viejo"
    ],
    "wof:name":"Hato Viejo",
    "wof:placetype":"locality"
},
  "geometry": {"coordinates":[-75.79132,1.95002],"type":"Point"}
}