{
  "type": "Feature",
  "properties": {
    "gn:admin1_code":"38",
    "gn:admin2_code":"47555.0",
    "gn:asciiname":"Cardonal",
    "gn:country_code":"CO",
    "gn:dem":97,
    "gn:feature_class":"P",
    "gn:feature_code":"PPL",
    "gn:name":"Cardonal",
    "gn:population":0,
    "gn:timezone":"America/Bogota",
    "iso:country":"CO",
    "wof:name":"Cardonal",
    "wof:placetype":"locality"
},
  "geometry": {"coordinates":[-74.60184,9.82267],"type":"Point"}
}