{
  "type": "Feature",
  "properties": {
    "gn:admin1_code":"38",
    "gn:admin2_code":"47555.0",
    "gn:asciiname":"Cardonal",
    "gn:country_code":"CO",
    "gn:dem":97,
    "gn:feature_class":"P",
    "gn:feature_code":"PPL",
    "gn:name":"Cardonal",
    "gn:population":0,
    "gn:timezone":"America/Bogota",
    "iso:country":"CO",
    "name:ceb_x_preferred":[
        "Cardonal"
    ],
    "name:epo_x_preferred":[
        "Cardonal"
    ],
    "name:eus_x_preferred":[
        "Cardonal"
    ],
    "name:ita_x_preferred":[
        "Cardonal"
    ],
    "name:mal_x_preferred":[
        "\u0d15\u0d3e\u0d7c\u0d21\u0d4b\u0d23\u0d7d"
    ],
    "name:sco_x_preferred":[
        "Cardonal"
    ],
    "name:spa_x_preferred":[
        "Cardonal"
    ],
    "name:srp_x_preferred":[
        "\u041e\u043f\u0448\u0442\u0438\u043d\u0430 \u041a\u0430\u0440\u0434\u043e\u043d\u0430\u043b"
    ],
    "name:swe_x_preferred":[
        "Cardonal"
    ],
    "name:vie_x_preferred":[
        "Cardonal"
    ],
    "wof:name":"Cardonal",
    "wof:placetype":"locality"
},
  "geometry": {"coordinates":[-74.60184,9.82267],"type":"Point"}
}