{
  "type": "Feature",
  "properties": {
    "gn:admin1_code":"10",
    "gn:admin2_code":"20060.0",
    "gn:asciiname":"El Guamo",
    "gn:country_code":"CO",
    "gn:dem":59,
    "gn:feature_class":"P",
    "gn:feature_code":"PPL",
    "gn:name":"El Guamo",
    "gn:population":0,
    "gn:timezone":"America/Bogota",
    "iso:country":"CO",
    "name:ceb_x_preferred":[
        "El Guamo"
    ],
    "name:fra_x_preferred":[
        "El Guamo"
    ],
    "name:ita_x_preferred":[
        "El Guamo"
    ],
    "name:kat_x_preferred":[
        "\u10d4\u10da-\u10d2\u10e3\u10d0\u10db\u10dd"
    ],
    "name:msa_x_preferred":[
        "El Guamo"
    ],
    "name:nld_x_preferred":[
        "El Guamo"
    ],
    "name:por_x_preferred":[
        "El Guamo"
    ],
    "name:rus_x_preferred":[
        "\u042d\u043b\u044c-\u0413\u0443\u0430\u043c\u043e"
    ],
    "name:spa_x_preferred":[
        "El Guamo"
    ],
    "name:swe_x_preferred":[
        "El Guamo"
    ],
    "name:tgl_x_preferred":[
        "El Guamo"
    ],
    "name:und_x_variant":[
        "Guamo",
        "Hacienda El Guamo",
        "El Guamo"
    ],
    "name:vie_x_preferred":[
        "El Guamo"
    ],
    "name:war_x_preferred":[
        "El Guamo"
    ],
    "name:zho_x_preferred":[
        "\u57c3\u723e\u74dc\u83ab"
    ],
    "wof:name":"El Guamo",
    "wof:placetype":"locality"
},
  "geometry": {"coordinates":[-73.96666999999999,9.95],"type":"Point"}
}