{
  "type": "Feature",
  "properties": {
    "gn:admin1_code":"10",
    "gn:admin2_code":"20060.0",
    "gn:asciiname":"El Guamo",
    "gn:country_code":"CO",
    "gn:dem":59,
    "gn:feature_class":"P",
    "gn:feature_code":"PPL",
    "gn:name":"El Guamo",
    "gn:population":0,
    "gn:timezone":"America/Bogota",
    "iso:country":"CO",
    "name:und_x_variant":[
        "Guamo",
        "Hacienda El Guamo",
        "El Guamo"
    ],
    "wof:name":"El Guamo",
    "wof:placetype":"locality"
},
  "geometry": {"coordinates":[-73.96666999999999,9.95],"type":"Point"}
}