{
  "type": "Feature",
  "properties": {
    "gn:admin1_code":"12",
    "gn:admin2_code":"23419.0",
    "gn:asciiname":"La Seba",
    "gn:country_code":"CO",
    "gn:dem":63,
    "gn:feature_class":"P",
    "gn:feature_code":"PPL",
    "gn:name":"La Seba",
    "gn:population":0,
    "gn:timezone":"America/Bogota",
    "iso:country":"CO",
    "wof:name":"La Seba",
    "wof:placetype":"locality"
},
  "geometry": {"coordinates":[-76.15731,8.84332],"type":"Point"}
}