{
  "type": "Feature",
  "properties": {
    "gn:admin1_code":"17.0",
    "gn:admin2_code":"44847.0",
    "gn:asciiname":"Ouruchom",
    "gn:country_code":"CO",
    "gn:dem":17,
    "gn:feature_class":"P",
    "gn:feature_code":"PPL",
    "gn:name":"Ouruchom",
    "gn:population":0,
    "gn:timezone":"America/Bogota",
    "iso:country":"CO",
    "wof:name":"Ouruchom",
    "wof:placetype":"locality"
},
  "geometry": {"coordinates":[-72.16360999999998,11.53556],"type":"Point"}
}