{
  "type": "Feature",
  "properties": {
    "gn:admin1_code":"16",
    "gn:admin2_code":"41524.0",
    "gn:asciiname":"Veracruz",
    "gn:country_code":"CO",
    "gn:dem":738,
    "gn:feature_class":"P",
    "gn:feature_code":"PPL",
    "gn:name":"Veracruz",
    "gn:population":0,
    "gn:timezone":"America/Bogota",
    "iso:country":"CO",
    "wof:name":"Veracruz",
    "wof:placetype":"locality"
},
  "geometry": {"coordinates":[-75.51966,2.80851],"type":"Point"}
}