{
  "type": "Feature",
  "properties": {
    "gn:admin1_code":"26",
    "gn:admin2_code":"68406.0",
    "gn:asciiname":"Vaiven",
    "gn:country_code":"CO",
    "gn:dem":708,
    "gn:feature_class":"P",
    "gn:feature_code":"PPL",
    "gn:name":"Vaiv\u00e9n",
    "gn:population":0,
    "gn:timezone":"America/Bogota",
    "iso:country":"CO",
    "wof:name":"Vaiven",
    "wof:placetype":"locality"
},
  "geometry": {"coordinates":[-73.33610999999998,7.1825],"type":"Point"}
}