{
  "type": "Feature",
  "properties": {
    "iso:country":"CO",
    "name:ceb_x_preferred":[
        "San Jos\u00e9 de Pare"
    ],
    "name:chi_x_preferred":[
        "\u8056\u4f55\u585e\u5fb7\u5e15\u96f7"
    ],
    "name:dut_x_preferred":[
        "San Jos\u00e9 de Pare"
    ],
    "name:eng_x_preferred":[
        "San Jos\u00e9 de Pare"
    ],
    "name:fra_x_preferred":[
        "San Jos\u00e9 de Pare"
    ],
    "name:fre_x_preferred":[
        "San Jos\u00e9 de Pare"
    ],
    "name:geo_x_preferred":[
        "\u10e1\u10d0\u10dc-\u10ee\u10dd\u10e1\u10d4-\u10d3\u10d4-\u10de\u10d0\u10e0\u10d4"
    ],
    "name:ita_x_preferred":[
        "San Jos\u00e9 de Pare"
    ],
    "name:kat_x_preferred":[
        "\u10e1\u10d0\u10dc-\u10ee\u10dd\u10e1\u10d4-\u10d3\u10d4-\u10de\u10d0\u10e0\u10d4"
    ],
    "name:may_x_preferred":[
        "San Jos\u00e9 de Pare"
    ],
    "name:msa_x_preferred":[
        "San Jos\u00e9 de Pare"
    ],
    "name:nan_x_preferred":[
        "San Jos\u00e9 de Pare"
    ],
    "name:nld_x_preferred":[
        "San Jos\u00e9 de Pare"
    ],
    "name:por_x_preferred":[
        "San Jose de Pare"
    ],
    "name:spa_x_preferred":[
        "San Jos\u00e9 de Pare"
    ],
    "name:swe_x_preferred":[
        "San Jos\u00e9 de Pare"
    ],
    "name:tgl_x_preferred":[
        "San Jos\u00e9 de Pare"
    ],
    "name:unk_x_variant":[
        "Pare"
    ],
    "name:vie_x_preferred":[
        "San Jos\u00e9 de Pare"
    ],
    "name:war_x_preferred":[
        "San Jos\u00e9 de Pare"
    ],
    "qs:gn_country":"CO",
    "qs:gn_fcode":"PPL",
    "qs:gn_pop":941,
    "qs:name":"San Jos\u00e9 de Pare",
    "qs:name_adm0":"Colombia",
    "qs:name_adm1":"Boyaca",
    "qs:photos":0,
    "qs:photos_1k":0,
    "qs:photos_9k":1,
    "qs:photos_9r":1,
    "qs:photos_all":2,
    "qs:photos_sr":0,
    "qs:placetype":"Town",
    "qs:pop_sr":"2",
    "qs:woe_adm0":23424787,
    "wd:wordcount":38,
    "wof:name":"San Jos\u00e9 de Pare",
    "wof:placetype":"locality",
    "wof:population":941
},
  "geometry": {"coordinates":[-73.54704,6.01746],"type":"Point"}
}