{
  "type": "Feature",
  "properties": {
    "gn:admin1_code":"28",
    "gn:admin2_code":"73200.0",
    "gn:asciiname":"La Esmeralda",
    "gn:country_code":"CO",
    "gn:dem":329,
    "gn:feature_class":"P",
    "gn:feature_code":"PPL",
    "gn:name":"La Esmeralda",
    "gn:population":0,
    "gn:timezone":"America/Bogota",
    "iso:country":"CO",
    "name:ceb_x_preferred":[
        "La Esmeralda"
    ],
    "name:deu_x_preferred":[
        "La Esmeralda"
    ],
    "name:ita_x_preferred":[
        "La Esmeralda"
    ],
    "name:sco_x_preferred":[
        "La Esmeralda"
    ],
    "name:spa_x_preferred":[
        "La Esmeralda"
    ],
    "name:srp_x_preferred":[
        "\u041b\u0430 \u0415\u0441\u043c\u0435\u0440\u0430\u043b\u0434\u0430"
    ],
    "name:swe_x_preferred":[
        "La Esmeralda"
    ],
    "wof:name":"La Esmeralda",
    "wof:placetype":"locality"
},
  "geometry": {"coordinates":[-74.93333,4.25],"type":"Point"}
}