{
  "type": "Feature",
  "properties": {
    "gn:admin1_code":"33.0",
    "gn:admin2_code":"25377.0",
    "gn:asciiname":"El Boqueron",
    "gn:country_code":"CO",
    "gn:dem":3139,
    "gn:feature_class":"P",
    "gn:feature_code":"PPL",
    "gn:name":"El Boquer\u00f3n",
    "gn:population":0,
    "gn:timezone":"America/Bogota",
    "iso:country":"CO",
    "wof:name":"El Boqueron",
    "wof:placetype":"locality"
},
  "geometry": {"coordinates":[-73.92194000000001,4.76889],"type":"Point"}
}