{
  "type": "Feature",
  "properties": {
    "gn:admin1_code":"28",
    "gn:admin2_code":"73616.0",
    "gn:asciiname":"Finlandia",
    "gn:country_code":"CO",
    "gn:dem":1679,
    "gn:feature_class":"P",
    "gn:feature_code":"PPL",
    "gn:name":"Finlandia",
    "gn:population":0,
    "gn:timezone":"America/Bogota",
    "iso:country":"CO",
    "wof:name":"Finlandia",
    "wof:placetype":"locality"
},
  "geometry": {"coordinates":[-75.82306,3.28722],"type":"Point"}
}