{
  "type": "Feature",
  "properties": {
    "gn:admin1_code":"9.0",
    "gn:admin2_code":"19355.0",
    "gn:asciiname":"El Penon",
    "gn:country_code":"CO",
    "gn:dem":2064,
    "gn:feature_class":"P",
    "gn:feature_code":"PPL",
    "gn:name":"El Pe\u00f1\u00f3n",
    "gn:population":0,
    "gn:timezone":"America/Bogota",
    "iso:country":"CO",
    "wof:name":"El Penon",
    "wof:placetype":"locality"
},
  "geometry": {"coordinates":[-76.06998,2.4372],"type":"Point"}
}