{
  "type": "Feature",
  "properties": {
    "gn:admin1_code":"26.0",
    "gn:admin2_code":"68266.0",
    "gn:asciiname":"Puertas",
    "gn:country_code":"CO",
    "gn:dem":2091,
    "gn:feature_class":"P",
    "gn:feature_code":"PPL",
    "gn:name":"Puertas",
    "gn:population":0,
    "gn:timezone":"America/Bogota",
    "iso:country":"CO",
    "name:arg_x_preferred":[
        "Puertas"
    ],
    "name:cat_x_preferred":[
        "Puertas"
    ],
    "name:ceb_x_preferred":[
        "Puertas"
    ],
    "name:eus_x_preferred":[
        "Puertas"
    ],
    "name:fra_x_preferred":[
        "Puertas"
    ],
    "name:hun_x_preferred":[
        "Puertas"
    ],
    "name:ina_x_preferred":[
        "Puertas"
    ],
    "name:ita_x_preferred":[
        "Puertas"
    ],
    "name:kaz_x_preferred":[
        "\u041f\u0443\u044d\u0440\u0442\u0430\u0441"
    ],
    "name:msa_x_preferred":[
        "Puertas"
    ],
    "name:nld_x_preferred":[
        "Puertas"
    ],
    "name:oci_x_preferred":[
        "Puertas"
    ],
    "name:pol_x_preferred":[
        "Puertas"
    ],
    "name:por_x_preferred":[
        "Puertas"
    ],
    "name:rus_x_preferred":[
        "\u041f\u0443\u044d\u0440\u0442\u0430\u0441"
    ],
    "name:spa_x_preferred":[
        "Puertas"
    ],
    "name:swe_x_preferred":[
        "Puertas"
    ],
    "name:ukr_x_preferred":[
        "\u041f\u0443\u0435\u0440\u0442\u0430\u0441"
    ],
    "name:uzb_x_preferred":[
        "Puertas"
    ],
    "name:vie_x_preferred":[
        "Puertas"
    ],
    "name:war_x_preferred":[
        "Puertas"
    ],
    "name:zho_x_preferred":[
        "\u666e\u57c3\u5c14\u5854\u65af"
    ],
    "wof:name":"Puertas",
    "wof:placetype":"locality"
},
  "geometry": {"coordinates":[-72.67488,6.63332],"type":"Point"}
}