{
  "type": "Feature",
  "properties": {
    "gn:admin1_code":"26.0",
    "gn:admin2_code":"68266.0",
    "gn:asciiname":"Puertas",
    "gn:country_code":"CO",
    "gn:dem":2091,
    "gn:feature_class":"P",
    "gn:feature_code":"PPL",
    "gn:name":"Puertas",
    "gn:population":0,
    "gn:timezone":"America/Bogota",
    "iso:country":"CO",
    "wof:name":"Puertas",
    "wof:placetype":"locality"
},
  "geometry": {"coordinates":[-72.67488,6.63332],"type":"Point"}
}