{
  "type": "Feature",
  "properties": {
    "gn:admin1_code":"26.0",
    "gn:admin2_code":"68745.0",
    "gn:asciiname":"La Carmelita",
    "gn:country_code":"CO",
    "gn:dem":99,
    "gn:feature_class":"P",
    "gn:feature_code":"PPLL",
    "gn:name":"La Carmelita",
    "gn:population":0,
    "gn:timezone":"America/Bogota",
    "iso:country":"CO",
    "wof:name":"La Carmelita",
    "wof:placetype":"locality"
},
  "geometry": {"coordinates":[-73.87222,6.7875],"type":"Point"}
}