{
  "type": "Feature",
  "properties": {
    "gn:admin1_code":"2.0",
    "gn:admin2_code":"5034.0",
    "gn:asciiname":"Canaveral",
    "gn:country_code":"CO",
    "gn:dem":1835,
    "gn:feature_class":"P",
    "gn:feature_code":"PPL",
    "gn:name":"Ca\u00f1averal",
    "gn:population":0,
    "gn:timezone":"America/Bogota",
    "iso:country":"CO",
    "wof:name":"Canaveral",
    "wof:placetype":"locality"
},
  "geometry": {"coordinates":[-75.83806,5.65889],"type":"Point"}
}