{
  "type": "Feature",
  "properties": {
    "iso:country":"CO",
    "name:ceb_x_preferred":[
        "Somondoco"
    ],
    "name:eng_x_preferred":[
        "Somondoco"
    ],
    "name:fas_x_preferred":[
        "\u0633\u0648\u0645\u0648\u0646\u062f\u0648\u06a9\u0648"
    ],
    "name:fra_x_preferred":[
        "Somondoco"
    ],
    "name:ita_x_preferred":[
        "Somondoco"
    ],
    "name:kat_x_preferred":[
        "\u10e1\u10dd\u10db\u10dd\u10dc\u10d3\u10dd\u10d9\u10dd"
    ],
    "name:msa_x_preferred":[
        "Somondoco"
    ],
    "name:nan_x_preferred":[
        "Somondoco"
    ],
    "name:nld_x_preferred":[
        "Somondoco"
    ],
    "name:por_x_preferred":[
        "Somondoco"
    ],
    "name:spa_x_preferred":[
        "Somondoco"
    ],
    "name:swe_x_preferred":[
        "Somondoco"
    ],
    "name:tgl_x_preferred":[
        "Somondoco"
    ],
    "name:vie_x_preferred":[
        "Somondoco"
    ],
    "name:war_x_preferred":[
        "Somondoco"
    ],
    "name:zho_min_nan_x_preferred":[
        "Somondoco"
    ],
    "name:zho_x_preferred":[
        "\u7d22\u8499\u591a\u79d1"
    ],
    "qs:gn_country":"CO",
    "qs:gn_fcode":"PPL",
    "qs:gn_pop":1029,
    "qs:name":"Somondoco",
    "qs:name_adm0":"Colombia",
    "qs:name_adm1":"Boyaca",
    "qs:photos":0,
    "qs:photos_1k":0,
    "qs:photos_9k":1,
    "qs:photos_9r":1,
    "qs:photos_all":3,
    "qs:photos_sr":0,
    "qs:placetype":"Town",
    "qs:pop_sr":"3",
    "qs:woe_adm0":23424787,
    "wd:wordcount":229,
    "wof:name":"Somondoco",
    "wof:placetype":"locality",
    "wof:population":1029
},
  "geometry": {"coordinates":[-73.43611,4.98778],"type":"Point"}
}