{
  "type": "Feature",
  "properties": {
    "iso:country":"CO",
    "name:chi_x_preferred":[
        "\u6bd4\u8d6b\u65af"
    ],
    "name:dut_x_preferred":[
        "Vijes"
    ],
    "name:eng_x_preferred":[
        "Vijes"
    ],
    "name:fre_x_preferred":[
        "Vijes"
    ],
    "name:geo_x_preferred":[
        "\u10d5\u10d8\u10ee\u10d4\u10e1\u10d8"
    ],
    "name:ita_x_preferred":[
        "Vijes"
    ],
    "name:may_x_preferred":[
        "Vijes"
    ],
    "name:nan_x_preferred":[
        "Vijes"
    ],
    "name:sco_x_preferred":[
        "Vijes"
    ],
    "name:spa_x_preferred":[
        "Vijes"
    ],
    "name:swe_x_preferred":[
        "Vijes"
    ],
    "name:vie_x_preferred":[
        "Vijes"
    ],
    "name:war_x_preferred":[
        "Vijes"
    ],
    "qs:gn_country":"CO",
    "qs:gn_fcode":"PPL",
    "qs:gn_pop":4070,
    "qs:name":"Vijes",
    "qs:name_adm0":"Colombia",
    "qs:name_adm1":"Valle del Cauca",
    "qs:photos":4,
    "qs:photos_1k":1,
    "qs:photos_9k":1,
    "qs:photos_9r":1,
    "qs:photos_all":4,
    "qs:photos_sr":1,
    "qs:placetype":"Town",
    "qs:pop_sr":"4",
    "qs:woe_adm0":23424787,
    "wof:name":"Vijes",
    "wof:placetype":"locality",
    "wof:population":4070
},
  "geometry": {"coordinates":[-76.4423,3.69934],"type":"Point"}
}