{
  "type": "Feature",
  "properties": {
    "iso:country":"CO",
    "name:ceb_x_preferred":[
        "La Uni\u00f3n"
    ],
    "name:chi_x_preferred":[
        "\u62c9\u70cf\u5c3c\u7fc1"
    ],
    "name:dut_x_preferred":[
        "La Uni\u00f3n"
    ],
    "name:eng_x_preferred":[
        "La Uni\u00f3n"
    ],
    "name:fra_x_preferred":[
        "La Uni\u00f3n"
    ],
    "name:fre_x_preferred":[
        "La Uni\u00f3n"
    ],
    "name:geo_x_preferred":[
        "\u10da\u10d0-\u10e3\u10dc\u10d8\u10dd\u10dc\u10d8"
    ],
    "name:ger_x_preferred":[
        "La Uni\u00f3n"
    ],
    "name:ita_x_preferred":[
        "La Uni\u00f3n"
    ],
    "name:kat_x_preferred":[
        "\u10da\u10d0-\u10e3\u10dc\u10d8\u10dd\u10dc\u10d8"
    ],
    "name:may_x_preferred":[
        "La Uni\u00f3n"
    ],
    "name:msa_x_preferred":[
        "La Uni\u00f3n"
    ],
    "name:nan_x_preferred":[
        "La Uni\u00f3n"
    ],
    "name:nld_x_preferred":[
        "La Uni\u00f3n"
    ],
    "name:sco_x_preferred":[
        "La Uni\u00f3n"
    ],
    "name:spa_x_preferred":[
        "La Uni\u00f3n"
    ],
    "name:swe_x_preferred":[
        "La Uni\u00f3n"
    ],
    "name:urd_x_preferred":[
        "\u0644\u0627 \u0648\u0646\u06cc\u0648\u0646\u060c \u0633\u0648\u06a9\u0631\u06cc"
    ],
    "name:war_x_preferred":[
        "La Uni\u00f3n"
    ],
    "qs:gn_country":"CO",
    "qs:gn_fcode":"PPL",
    "qs:gn_pop":4427,
    "qs:name":"La Uni\u00f3n",
    "qs:name_adm0":"Colombia",
    "qs:name_adm1":"Sucre",
    "qs:photos":0,
    "qs:photos_1k":0,
    "qs:photos_9k":0,
    "qs:photos_9r":0,
    "qs:photos_all":0,
    "qs:photos_sr":0,
    "qs:placetype":"Town",
    "qs:pop_sr":"4",
    "qs:woe_adm0":23424787,
    "wd:wordcount":44,
    "wof:name":"La Uni\u00f3n",
    "wof:placetype":"locality",
    "wof:population":4427
},
  "geometry": {"coordinates":[-75.28055999999999,8.86056],"type":"Point"}
}