{
  "type": "Feature",
  "properties": {
    "gn:admin1_code":"38",
    "gn:admin2_code":"47692.0",
    "gn:asciiname":"Los Angelitos",
    "gn:country_code":"CO",
    "gn:dem":80,
    "gn:feature_class":"P",
    "gn:feature_code":"PPL",
    "gn:name":"Los Angelitos",
    "gn:population":0,
    "gn:timezone":"America/Bogota",
    "iso:country":"CO",
    "wof:name":"Los Angelitos",
    "wof:placetype":"locality"
},
  "geometry": {"coordinates":[-74.17323,9.42164],"type":"Point"}
}