{
  "type": "Feature",
  "properties": {
    "gn:admin1_code":"19.0",
    "gn:admin2_code":"50001.0",
    "gn:asciiname":"Socaegro",
    "gn:country_code":"CO",
    "gn:dem":443,
    "gn:feature_class":"P",
    "gn:feature_code":"PPL",
    "gn:name":"Socaegro",
    "gn:population":0,
    "gn:timezone":"America/Bogota",
    "iso:country":"CO",
    "name:spa_x_preferred":[
        "Socaegro"
    ],
    "wof:name":"Socaegro",
    "wof:placetype":"locality"
},
  "geometry": {"coordinates":[-73.65123,4.11193],"type":"Point"}
}