{
  "type": "Feature",
  "properties": {
    "gn:admin1_code":"33",
    "gn:admin2_code":"25307.0",
    "gn:asciiname":"Balastera",
    "gn:country_code":"CO",
    "gn:dem":293,
    "gn:feature_class":"P",
    "gn:feature_code":"PPL",
    "gn:name":"Balastera",
    "gn:population":0,
    "gn:timezone":"America/Bogota",
    "iso:country":"CO",
    "wof:name":"Balastera",
    "wof:placetype":"locality"
},
  "geometry": {"coordinates":[-74.83543,4.28312],"type":"Point"}
}