{
  "type": "Feature",
  "properties": {
    "gn:admin1_code":"26.0",
    "gn:admin2_code":"68655.0",
    "gn:asciiname":"El Cortijo",
    "gn:country_code":"CO",
    "gn:dem":90,
    "gn:feature_class":"P",
    "gn:feature_code":"PPL",
    "gn:name":"El Cortijo",
    "gn:population":0,
    "gn:timezone":"America/Bogota",
    "iso:country":"CO",
    "wof:name":"El Cortijo",
    "wof:placetype":"locality"
},
  "geometry": {"coordinates":[-73.68333,7.40222],"type":"Point"}
}