{
  "type": "Feature",
  "properties": {
    "gn:admin1_code":"26",
    "gn:admin2_code":"68572.0",
    "gn:asciiname":"Villa Luz",
    "gn:country_code":"CO",
    "gn:dem":1565,
    "gn:feature_class":"P",
    "gn:feature_code":"PPL",
    "gn:name":"Villa Luz",
    "gn:population":0,
    "gn:timezone":"America/Bogota",
    "iso:country":"CO",
    "wof:name":"Villa Luz",
    "wof:placetype":"locality"
},
  "geometry": {"coordinates":[-73.63670999999999,5.9082],"type":"Point"}
}