{
  "type": "Feature",
  "properties": {
    "gn:admin1_code":"9.0",
    "gn:admin2_code":"19418.0",
    "gn:asciiname":"Martha",
    "gn:country_code":"CO",
    "gn:dem":128,
    "gn:feature_class":"P",
    "gn:feature_code":"PPL",
    "gn:name":"Martha",
    "gn:population":0,
    "gn:timezone":"America/Bogota",
    "iso:country":"CO",
    "name:ara_x_preferred":[
        "\u0645\u0631\u062b\u0627"
    ],
    "name:bre_x_preferred":[
        "Marta Betania"
    ],
    "name:ces_x_preferred":[
        "Svat\u00e1 Marta"
    ],
    "name:csb_x_preferred":[
        "Sw. Marta"
    ],
    "name:eus_x_preferred":[
        "Marta Betaniakoa"
    ],
    "name:fin_x_preferred":[
        "Martta"
    ],
    "name:heb_x_preferred":[
        "\u05de\u05e8\u05ea\u05d0"
    ],
    "name:ind_x_preferred":[
        "Marta"
    ],
    "name:jpn_x_preferred":[
        "\u30de\u30eb\u30bf"
    ],
    "name:kor_x_preferred":[
        "\ubca0\ud0c0\ub2c8\uc544\uc758 \ub9c8\ub974\ud0c0"
    ],
    "name:mar_x_preferred":[
        "\u092e\u093e\u0930\u094d\u0925\u093e"
    ],
    "name:mkd_x_preferred":[
        "\u041c\u0430\u0440\u0442\u0430"
    ],
    "name:nld_x_preferred":[
        "Marta"
    ],
    "name:rus_x_preferred":[
        "\u0421\u0432\u044f\u0442\u0430\u044f \u041c\u0430\u0440\u0444\u0430"
    ],
    "name:sco_x_preferred":[
        "Martha"
    ],
    "name:swe_x_preferred":[
        "Marta"
    ],
    "name:tam_x_preferred":[
        "\u0bae\u0bbe\u0bb0\u0bcd\u0ba4\u0bcd\u0ba4\u0bbe"
    ],
    "name:ukr_x_preferred":[
        "\u0421\u0432\u044f\u0442\u0430 \u041c\u0430\u0440\u0442\u0430"
    ],
    "name:urd_x_preferred":[
        "\u0645\u0631\u062a\u06be\u0627"
    ],
    "wof:name":"Martha",
    "wof:placetype":"locality"
},
  "geometry": {"coordinates":[-77.18179000000001,3.04679],"type":"Point"}
}