{
  "type": "Feature",
  "properties": {
    "gn:admin1_code":"9.0",
    "gn:admin2_code":"19418.0",
    "gn:asciiname":"Martha",
    "gn:country_code":"CO",
    "gn:dem":128,
    "gn:feature_class":"P",
    "gn:feature_code":"PPL",
    "gn:name":"Martha",
    "gn:population":0,
    "gn:timezone":"America/Bogota",
    "iso:country":"CO",
    "wof:name":"Martha",
    "wof:placetype":"locality"
},
  "geometry": {"coordinates":[-77.18179000000001,3.04679],"type":"Point"}
}