{
  "type": "Feature",
  "properties": {
    "gn:admin1_code":"21",
    "gn:admin2_code":"54810.0",
    "gn:asciiname":"La Motilona",
    "gn:country_code":"CO",
    "gn:dem":89,
    "gn:feature_class":"P",
    "gn:feature_code":"PPL",
    "gn:name":"La Motilona",
    "gn:population":0,
    "gn:timezone":"America/Bogota",
    "iso:country":"CO",
    "wof:name":"La Motilona",
    "wof:placetype":"locality"
},
  "geometry": {"coordinates":[-72.90321999999998,9.00424],"type":"Point"}
}