{
  "type": "Feature",
  "properties": {
    "gn:admin1_code":"26",
    "gn:admin2_code":"68572.0",
    "gn:asciiname":"El Reten",
    "gn:country_code":"CO",
    "gn:dem":1680,
    "gn:feature_class":"P",
    "gn:feature_code":"PPL",
    "gn:name":"El Ret\u00e9n",
    "gn:population":0,
    "gn:timezone":"America/Bogota",
    "iso:country":"CO",
    "wof:name":"El Reten",
    "wof:placetype":"locality"
},
  "geometry": {"coordinates":[-73.74247,5.88102],"type":"Point"}
}