{
  "type": "Feature",
  "properties": {
    "gn:admin1_code":"36",
    "gn:admin2_code":"15507.0",
    "gn:asciiname":"Pedregales",
    "gn:country_code":"CO",
    "gn:dem":380,
    "gn:feature_class":"P",
    "gn:feature_code":"PPL",
    "gn:name":"Pedregales",
    "gn:population":0,
    "gn:timezone":"America/Bogota",
    "iso:country":"CO",
    "wof:name":"Pedregales",
    "wof:placetype":"locality"
},
  "geometry": {"coordinates":[-74.11278,5.75417],"type":"Point"}
}