{
  "type": "Feature",
  "properties": {
    "gn:admin1_code":"33.0",
    "gn:admin2_code":"25320.0",
    "gn:asciiname":"Las Tibayes",
    "gn:country_code":"CO",
    "gn:dem":1893,
    "gn:feature_class":"P",
    "gn:feature_code":"PPL",
    "gn:name":"Las Tibayes",
    "gn:population":0,
    "gn:timezone":"America/Bogota",
    "iso:country":"CO",
    "name:spa_x_preferred":[
        "Las Tibayes"
    ],
    "wof:name":"Las Tibayes",
    "wof:placetype":"locality"
},
  "geometry": {"coordinates":[-74.54619,5.05258],"type":"Point"}
}