{
  "type": "Feature",
  "properties": {
    "gn:admin1_code":"2",
    "gn:admin2_code":"5579.0",
    "gn:asciiname":"Estacion Cristalina",
    "gn:country_code":"CO",
    "gn:dem":302,
    "gn:feature_class":"P",
    "gn:feature_code":"PPL",
    "gn:name":"Estaci\u00f3n Cristalina",
    "gn:population":0,
    "gn:timezone":"America/Bogota",
    "iso:country":"CO",
    "wof:name":"Estacion Cristalina",
    "wof:placetype":"locality"
},
  "geometry": {"coordinates":[-74.57639,6.41194],"type":"Point"}
}