{
  "type": "Feature",
  "properties": {
    "gn:admin1_code":"2.0",
    "gn:admin2_code":"5042.0",
    "gn:asciiname":"Casteja",
    "gn:country_code":"CO",
    "gn:dem":2119,
    "gn:feature_class":"P",
    "gn:feature_code":"PPL",
    "gn:name":"Casteja",
    "gn:population":0,
    "gn:timezone":"America/Bogota",
    "iso:country":"CO",
    "wof:name":"Casteja",
    "wof:placetype":"locality"
},
  "geometry": {"coordinates":[-75.98666999999998,6.59333],"type":"Point"}
}