{
  "type": "Feature",
  "properties": {
    "gn:admin1_code":"17",
    "gn:admin2_code":"44430.0",
    "gn:asciiname":"Karrapatamahana",
    "gn:country_code":"CO",
    "gn:dem":111,
    "gn:feature_class":"P",
    "gn:feature_code":"PPL",
    "gn:name":"Karrapatamahana",
    "gn:population":0,
    "gn:timezone":"America/Bogota",
    "iso:country":"CO",
    "wof:name":"Karrapatamahana",
    "wof:placetype":"locality"
},
  "geometry": {"coordinates":[-72.40839,11.27324],"type":"Point"}
}