{
  "type": "Feature",
  "properties": {
    "gn:admin1_code":"28",
    "gn:admin2_code":"73067.0",
    "gn:asciiname":"La Faustina",
    "gn:country_code":"CO",
    "gn:dem":792,
    "gn:feature_class":"P",
    "gn:feature_code":"PPL",
    "gn:name":"La Faustina",
    "gn:population":0,
    "gn:timezone":"America/Bogota",
    "iso:country":"CO",
    "wof:name":"La Faustina",
    "wof:placetype":"locality"
},
  "geometry": {"coordinates":[-75.62056,3.36472],"type":"Point"}
}