{
  "type": "Feature",
  "properties": {
    "gn:admin1_code":"19",
    "gn:admin2_code":"50573.0",
    "gn:asciiname":"El Pinal",
    "gn:country_code":"CO",
    "gn:dem":223,
    "gn:feature_class":"P",
    "gn:feature_code":"PPL",
    "gn:name":"El Pi\u00f1al",
    "gn:population":0,
    "gn:timezone":"America/Bogota",
    "iso:country":"CO",
    "wof:name":"El Pinal",
    "wof:placetype":"locality"
},
  "geometry": {"coordinates":[-72.68944,4.15917],"type":"Point"}
}