{
  "type": "Feature",
  "properties": {
    "gn:admin1_code":"20",
    "gn:admin2_code":"52399.0",
    "gn:asciiname":"El Guabo",
    "gn:country_code":"CO",
    "gn:dem":1539,
    "gn:feature_class":"P",
    "gn:feature_code":"PPL",
    "gn:name":"El Guabo",
    "gn:population":0,
    "gn:timezone":"America/Bogota",
    "iso:country":"CO",
    "name:ceb_x_preferred":[
        "El Guabo"
    ],
    "name:ita_x_preferred":[
        "El Guabo"
    ],
    "name:spa_x_preferred":[
        "El Guabo"
    ],
    "name:swe_x_preferred":[
        "El Guabo"
    ],
    "wof:name":"El Guabo",
    "wof:placetype":"locality"
},
  "geometry": {"coordinates":[-77.11832,1.61716],"type":"Point"}
}