{
  "type": "Feature",
  "properties": {
    "gn:admin1_code":"2",
    "gn:admin2_code":"5670.0",
    "gn:asciiname":"Las Juanas",
    "gn:country_code":"CO",
    "gn:dem":972,
    "gn:feature_class":"P",
    "gn:feature_code":"PPL",
    "gn:name":"Las Juanas",
    "gn:population":0,
    "gn:timezone":"America/Bogota",
    "iso:country":"CO",
    "wof:name":"Las Juanas",
    "wof:placetype":"locality"
},
  "geometry": {"coordinates":[-74.85666999999999,6.40194],"type":"Point"}
}