{
  "type": "Feature",
  "properties": {
    "gn:admin1_code":"33.0",
    "gn:admin2_code":"25377.0",
    "gn:asciiname":"Concentracion Marquez",
    "gn:country_code":"CO",
    "gn:dem":2613,
    "gn:feature_class":"P",
    "gn:feature_code":"PPL",
    "gn:name":"Concentraci\u00f3n M\u00e1rquez",
    "gn:population":0,
    "gn:timezone":"America/Bogota",
    "iso:country":"CO",
    "wof:name":"Concentracion Marquez",
    "wof:placetype":"locality"
},
  "geometry": {"coordinates":[-73.98083000000003,4.78389],"type":"Point"}
}