{
  "type": "Feature",
  "properties": {
    "gn:admin1_code":"36",
    "gn:admin2_code":"15572.0",
    "gn:asciiname":"Las Pavas",
    "gn:country_code":"CO",
    "gn:dem":201,
    "gn:feature_class":"P",
    "gn:feature_code":"PPL",
    "gn:name":"Las Pavas",
    "gn:population":0,
    "gn:timezone":"America/Bogota",
    "iso:country":"CO",
    "wof:name":"Las Pavas",
    "wof:placetype":"locality"
},
  "geometry": {"coordinates":[-74.44388000000002,5.87389],"type":"Point"}
}