{
  "type": "Feature",
  "properties": {
    "gn:admin1_code":"20",
    "gn:admin2_code":"52256.0",
    "gn:asciiname":"La Sierra",
    "gn:country_code":"CO",
    "gn:dem":1712,
    "gn:feature_class":"P",
    "gn:feature_code":"PPL",
    "gn:name":"La Sierra",
    "gn:population":0,
    "gn:timezone":"America/Bogota",
    "iso:country":"CO",
    "name:ast_x_preferred":[
        "La Sierra"
    ],
    "name:ceb_x_preferred":[
        "La Sierra"
    ],
    "name:ita_x_preferred":[
        "La Sierra"
    ],
    "name:spa_x_preferred":[
        "La Sierra"
    ],
    "name:swe_x_preferred":[
        "La Sierra"
    ],
    "name:vie_x_preferred":[
        "La Sierra"
    ],
    "wof:name":"La Sierra",
    "wof:placetype":"locality"
},
  "geometry": {"coordinates":[-77.36955,1.72456],"type":"Point"}
}