{
  "type": "Feature",
  "properties": {
    "gn:admin1_code":"38.0",
    "gn:admin2_code":"47555.0",
    "gn:asciiname":"Santo Eccehomo",
    "gn:country_code":"CO",
    "gn:dem":114,
    "gn:feature_class":"P",
    "gn:feature_code":"PPL",
    "gn:name":"Santo Eccehomo",
    "gn:population":0,
    "gn:timezone":"America/Bogota",
    "iso:country":"CO",
    "wof:name":"Santo Eccehomo",
    "wof:placetype":"locality"
},
  "geometry": {"coordinates":[-74.41308000000002,9.7635],"type":"Point"}
}