{
  "type": "Feature",
  "properties": {
    "gn:admin1_code":"33.0",
    "gn:admin2_code":"25281.0",
    "gn:asciiname":"Granadillo",
    "gn:country_code":"CO",
    "gn:dem":1867,
    "gn:feature_class":"P",
    "gn:feature_code":"PPL",
    "gn:name":"Granadillo",
    "gn:population":0,
    "gn:timezone":"America/Bogota",
    "iso:country":"CO",
    "name:spa_x_preferred":[
        "Granadillo"
    ],
    "wof:name":"Granadillo",
    "wof:placetype":"locality"
},
  "geometry": {"coordinates":[-73.91636,4.32804],"type":"Point"}
}