{
  "type": "Feature",
  "properties": {
    "gn:admin1_code":"28.0",
    "gn:admin2_code":"73217.0",
    "gn:asciiname":"Hilarco Guayaquil",
    "gn:country_code":"CO",
    "gn:dem":325,
    "gn:feature_class":"P",
    "gn:feature_code":"PPL",
    "gn:name":"Hilarco Guayaqu\u00edl",
    "gn:population":0,
    "gn:timezone":"America/Bogota",
    "iso:country":"CO",
    "name:spa_x_preferred":[
        "Hilarco Guayaqu\u00edl"
    ],
    "wof:name":"Hilarco Guayaquil",
    "wof:placetype":"locality"
},
  "geometry": {"coordinates":[-75.02694,3.70111],"type":"Point"}
}