{
  "type": "Feature",
  "properties": {
    "gn:admin1_code":"9",
    "gn:admin2_code":"19450.0",
    "gn:asciiname":"El Saladero de Mayo",
    "gn:country_code":"CO",
    "gn:dem":598,
    "gn:feature_class":"P",
    "gn:feature_code":"PPL",
    "gn:name":"El Saladero de Mayo",
    "gn:population":0,
    "gn:timezone":"America/Bogota",
    "iso:country":"CO",
    "name:und_x_variant":[
        "El Salada de Mayo",
        "El Saladero de Mayo"
    ],
    "wof:name":"El Saladero de Mayo",
    "wof:placetype":"locality"
},
  "geometry": {"coordinates":[-77.31271,1.70524],"type":"Point"}
}