{
  "type": "Feature",
  "properties": {
    "gn:admin1_code":"3.0",
    "gn:admin2_code":"81794.0",
    "gn:asciiname":"Puerto Gaitan",
    "gn:country_code":"CO",
    "gn:dem":156,
    "gn:feature_class":"P",
    "gn:feature_code":"PPL",
    "gn:name":"Puerto Gait\u00e1n",
    "gn:population":0,
    "gn:timezone":"America/Bogota",
    "iso:country":"CO",
    "name:und_x_variant":[
        "Puerto Gait\u00e1n"
    ],
    "wof:name":"Puerto Gaitan",
    "wof:placetype":"locality"
},
  "geometry": {"coordinates":[-71.45040999999998,6.24536],"type":"Point"}
}