{
  "type": "Feature",
  "properties": {
    "gn:admin1_code":"32",
    "gn:admin2_code":"85400.0",
    "gn:asciiname":"Cuneque",
    "gn:country_code":"CO",
    "gn:dem":1320,
    "gn:feature_class":"P",
    "gn:feature_code":"PPL",
    "gn:name":"Cuneque",
    "gn:population":0,
    "gn:timezone":"America/Bogota",
    "iso:country":"CO",
    "wof:name":"Cuneque",
    "wof:placetype":"locality"
},
  "geometry": {"coordinates":[-72.15000000000001,5.86667],"type":"Point"}
}