{
  "type": "Feature",
  "properties": {
    "gn:admin1_code":"1.0",
    "gn:asciiname":"Puerto Lopez",
    "gn:country_code":"CO",
    "gn:dem":93,
    "gn:feature_class":"P",
    "gn:feature_code":"PPL",
    "gn:name":"Puerto L\u00f3pez",
    "gn:population":0,
    "gn:timezone":"America/Bogota",
    "iso:country":"CO",
    "wof:name":"Puerto Lopez",
    "wof:placetype":"locality"
},
  "geometry": {"coordinates":[-70.86066,-2.22255],"type":"Point"}
}