{
  "type": "Feature",
  "properties": {
    "gn:admin1_code":"33.0",
    "gn:admin2_code":"25293.0",
    "gn:asciiname":"Termopilas",
    "gn:country_code":"CO",
    "gn:dem":2132,
    "gn:feature_class":"P",
    "gn:feature_code":"PPL",
    "gn:name":"Term\u00f3pilas",
    "gn:population":0,
    "gn:timezone":"America/Bogota",
    "iso:country":"CO",
    "wof:name":"Termopilas",
    "wof:placetype":"locality"
},
  "geometry": {"coordinates":[-73.51075,4.62942],"type":"Point"}
}