{
  "type": "Feature",
  "properties": {
    "gn:admin1_code":"19.0",
    "gn:admin2_code":"50711.0",
    "gn:asciiname":"Caserio El Triunfo",
    "gn:country_code":"CO",
    "gn:dem":295,
    "gn:feature_class":"P",
    "gn:feature_code":"PPL",
    "gn:name":"Caser\u00edo El Triunfo",
    "gn:population":0,
    "gn:timezone":"America/Bogota",
    "iso:country":"CO",
    "wof:name":"Caserio El Triunfo",
    "wof:placetype":"locality"
},
  "geometry": {"coordinates":[-73.83020999999999,2.93655],"type":"Point"}
}