{
  "type": "Feature",
  "properties": {
    "gn:admin1_code":"28.0",
    "gn:admin2_code":"73001.0",
    "gn:asciiname":"Mirolindo",
    "gn:country_code":"CO",
    "gn:dem":1053,
    "gn:feature_class":"P",
    "gn:feature_code":"PPL",
    "gn:name":"Mirolindo",
    "gn:population":0,
    "gn:timezone":"America/Bogota",
    "iso:country":"CO",
    "wof:name":"Mirolindo",
    "wof:placetype":"locality"
},
  "geometry": {"coordinates":[-75.18333,4.41667],"type":"Point"}
}