{
  "type": "Feature",
  "properties": {
    "gn:admin1_code":"8.0",
    "gn:admin2_code":"18460.0",
    "gn:asciiname":"Inspeccion de Policia Remolino de Aricunti",
    "gn:country_code":"CO",
    "gn:dem":203,
    "gn:feature_class":"P",
    "gn:feature_code":"PPL",
    "gn:name":"Inspecci\u00f3n de Polic\u00eda Remolino de Aricunti",
    "gn:population":0,
    "gn:timezone":"America/Bogota",
    "iso:country":"CO",
    "wof:name":"Inspeccion de Policia Remolino de Aricunti",
    "wof:placetype":"locality"
},
  "geometry": {"coordinates":[-75.35615,1.01439],"type":"Point"}
}