{
  "type": "Feature",
  "properties": {
    "gn:admin1_code":"35",
    "gn:admin2_code":"13836.0",
    "gn:asciiname":"Atascosas",
    "gn:cc2":"CO",
    "gn:country_code":"CO",
    "gn:dem":44,
    "gn:feature_class":"P",
    "gn:feature_code":"PPL",
    "gn:name":"Atascosas",
    "gn:population":0,
    "gn:timezone":"America/Bogota",
    "iso:country":"CO",
    "name:und_x_variant":[
        "Hacienda Atascosos",
        "Atescos",
        "Atascosas"
    ],
    "wof:name":"Atascosas",
    "wof:placetype":"locality"
},
  "geometry": {"coordinates":[-75.34999999999999,10.41667],"type":"Point"}
}