{
  "type": "Feature",
  "properties": {
    "gn:admin1_code":"2.0",
    "gn:admin2_code":"5042.0",
    "gn:asciiname":"Doncel",
    "gn:country_code":"CO",
    "gn:dem":1135,
    "gn:feature_class":"P",
    "gn:feature_code":"PPL",
    "gn:name":"Doncel",
    "gn:population":0,
    "gn:timezone":"America/Bogota",
    "iso:country":"CO",
    "wof:name":"Doncel",
    "wof:placetype":"locality"
},
  "geometry": {"coordinates":[-75.85944000000001,6.61389],"type":"Point"}
}