{
  "type": "Feature",
  "properties": {
    "gn:admin1_code":"33",
    "gn:admin2_code":"25513.0",
    "gn:asciiname":"La Ferreria",
    "gn:country_code":"CO",
    "gn:dem":1647,
    "gn:feature_class":"P",
    "gn:feature_code":"PPL",
    "gn:name":"La Ferrer\u00eda",
    "gn:population":0,
    "gn:timezone":"America/Bogota",
    "iso:country":"CO",
    "wof:name":"La Ferreria",
    "wof:placetype":"locality"
},
  "geometry": {"coordinates":[-74.16667,5.15],"type":"Point"}
}