{
  "type": "Feature",
  "properties": {
    "gn:admin1_code":"3.0",
    "gn:admin2_code":"81001.0",
    "gn:asciiname":"Cana Brava",
    "gn:country_code":"CO",
    "gn:dem":129,
    "gn:feature_class":"P",
    "gn:feature_code":"PPL",
    "gn:name":"Ca\u00f1a Brava",
    "gn:population":0,
    "gn:timezone":"America/Bogota",
    "iso:country":"CO",
    "name:spa_x_preferred":[
        "Ca\u00f1a Brava"
    ],
    "wof:name":"Cana Brava",
    "wof:placetype":"locality"
},
  "geometry": {"coordinates":[-70.98626,6.72679],"type":"Point"}
}