{
  "type": "Feature",
  "properties": {
    "gn:admin1_code":"22.0",
    "gn:admin2_code":"86571.0",
    "gn:asciiname":"Cachamaque",
    "gn:country_code":"CO",
    "gn:dem":208,
    "gn:feature_class":"P",
    "gn:feature_code":"PPL",
    "gn:name":"Cachamaque",
    "gn:population":0,
    "gn:timezone":"America/Bogota",
    "iso:country":"CO",
    "name:und_x_variant":[
        "Chachamaque"
    ],
    "wof:name":"Cachamaque",
    "wof:placetype":"locality"
},
  "geometry": {"coordinates":[-75.51874000000002,0.76682],"type":"Point"}
}