{
  "type": "Feature",
  "properties": {
    "gn:admin1_code":"36",
    "gn:admin2_code":"15572.0",
    "gn:asciiname":"Cano El Retiro",
    "gn:country_code":"CO",
    "gn:dem":203,
    "gn:feature_class":"P",
    "gn:feature_code":"PPL",
    "gn:name":"Ca\u00f1o El Retiro",
    "gn:population":0,
    "gn:timezone":"America/Bogota",
    "iso:country":"CO",
    "wof:name":"Cano El Retiro",
    "wof:placetype":"locality"
},
  "geometry": {"coordinates":[-74.45019000000001,5.85825],"type":"Point"}
}