{
  "type": "Feature",
  "properties": {
    "gn:admin1_code":"2",
    "gn:admin2_code":"5495.0",
    "gn:asciiname":"Le Fe",
    "gn:country_code":"CO",
    "gn:dem":45,
    "gn:feature_class":"P",
    "gn:feature_code":"PPL",
    "gn:name":"Le F\u00e9",
    "gn:population":0,
    "gn:timezone":"America/Bogota",
    "iso:country":"CO",
    "wof:name":"Le Fe",
    "wof:placetype":"locality"
},
  "geometry": {"coordinates":[-74.78468000000002,8.02733],"type":"Point"}
}