{
  "type": "Feature",
  "properties": {
    "gn:admin1_code":"22",
    "gn:admin2_code":"86757.0",
    "gn:asciiname":"Puerto Colon",
    "gn:country_code":"CO",
    "gn:dem":290,
    "gn:feature_class":"P",
    "gn:feature_code":"PPL",
    "gn:name":"Puerto Col\u00f3n",
    "gn:population":0,
    "gn:timezone":"America/Bogota",
    "iso:country":"CO",
    "name:und_x_variant":[
        "Puerto Col\u00f3n"
    ],
    "wof:name":"Puerto Colon",
    "wof:placetype":"locality"
},
  "geometry": {"coordinates":[-76.93056,0.28056],"type":"Point"}
}