{
  "type": "Feature",
  "properties": {
    "gn:admin1_code":"17",
    "gn:admin2_code":"44847.0",
    "gn:asciiname":"Masharerain",
    "gn:country_code":"CO",
    "gn:dem":113,
    "gn:feature_class":"P",
    "gn:feature_code":"PPL",
    "gn:name":"M\u00e1sharerain",
    "gn:population":0,
    "gn:timezone":"America/Bogota",
    "iso:country":"CO",
    "wof:name":"Masharerain",
    "wof:placetype":"locality"
},
  "geometry": {"coordinates":[-71.75944,11.97528],"type":"Point"}
}