{
  "type": "Feature",
  "properties": {
    "gn:admin1_code":"10",
    "gn:admin2_code":"20001.0",
    "gn:asciiname":"Badillo",
    "gn:country_code":"CO",
    "gn:dem":180,
    "gn:feature_class":"P",
    "gn:feature_code":"PPL",
    "gn:name":"Badillo",
    "gn:population":0,
    "gn:timezone":"America/Bogota",
    "iso:country":"CO",
    "wof:name":"Badillo",
    "wof:placetype":"locality"
},
  "geometry": {"coordinates":[-73.1285,10.63011],"type":"Point"}
}