{
  "type": "Feature",
  "properties": {
    "gn:admin1_code":"28",
    "gn:admin2_code":"73168.0",
    "gn:asciiname":"La Cimarrona",
    "gn:cc2":"CO",
    "gn:country_code":"CO",
    "gn:dem":1745,
    "gn:feature_class":"P",
    "gn:feature_code":"PPL",
    "gn:name":"La Cimarrona",
    "gn:population":0,
    "gn:timezone":"America/Bogota",
    "iso:country":"CO",
    "name:und_x_variant":[
        "Guimarrana",
        "La Cimarrona"
    ],
    "wof:name":"La Cimarrona",
    "wof:placetype":"locality"
},
  "geometry": {"coordinates":[-75.55,3.81667],"type":"Point"}
}