{
  "type": "Feature",
  "properties": {
    "gn:admin1_code":"3",
    "gn:admin2_code":"81001.0",
    "gn:asciiname":"Lorena",
    "gn:country_code":"CO",
    "gn:dem":126,
    "gn:feature_class":"P",
    "gn:feature_code":"PPL",
    "gn:name":"Lorena",
    "gn:population":0,
    "gn:timezone":"America/Bogota",
    "iso:country":"CO",
    "name:arg_x_preferred":[
        "Lorena"
    ],
    "name:cat_x_preferred":[
        "Lorena"
    ],
    "name:ceb_x_preferred":[
        "Lorena"
    ],
    "name:deu_x_preferred":[
        "Lorena"
    ],
    "name:epo_x_preferred":[
        "Lorena"
    ],
    "name:fra_x_preferred":[
        "Lorena"
    ],
    "name:glg_x_preferred":[
        "Lorena"
    ],
    "name:ita_x_preferred":[
        "Lorena"
    ],
    "name:nld_x_preferred":[
        "Lorena"
    ],
    "name:oci_x_preferred":[
        "Lorena"
    ],
    "name:por_x_preferred":[
        "Lorena"
    ],
    "name:sco_x_preferred":[
        "Lorena"
    ],
    "name:slv_x_preferred":[
        "Lorena"
    ],
    "name:spa_x_preferred":[
        "Lorena"
    ],
    "name:swe_x_preferred":[
        "Lorena"
    ],
    "wof:name":"Lorena",
    "wof:placetype":"locality"
},
  "geometry": {"coordinates":[-70.58693000000002,7.06543],"type":"Point"}
}