{
  "type": "Feature",
  "properties": {
    "gn:admin1_code":"35.0",
    "gn:admin2_code":"13052.0",
    "gn:asciiname":"Turbaquito",
    "gn:country_code":"CO",
    "gn:dem":62,
    "gn:feature_class":"P",
    "gn:feature_code":"PPL",
    "gn:name":"Turbaquito",
    "gn:population":0,
    "gn:timezone":"America/Bogota",
    "iso:country":"CO",
    "wof:name":"Turbaquito",
    "wof:placetype":"locality"
},
  "geometry": {"coordinates":[-75.34999999999999,10.26667],"type":"Point"}
}