{
  "type": "Feature",
  "properties": {
    "gn:admin1_code":"4",
    "gn:admin2_code":"8520.0",
    "gn:asciiname":"Mamon Gacho",
    "gn:country_code":"CO",
    "gn:dem":26,
    "gn:feature_class":"P",
    "gn:feature_code":"PPL",
    "gn:name":"Mam\u00f3n Gacho",
    "gn:population":0,
    "gn:timezone":"America/Bogota",
    "iso:country":"CO",
    "wof:name":"Mamon Gacho",
    "wof:placetype":"locality"
},
  "geometry": {"coordinates":[-74.78333000000001,10.66667],"type":"Point"}
}