{
  "type": "Feature",
  "properties": {
    "gn:admin1_code":"16.0",
    "gn:admin2_code":"41206.0",
    "gn:asciiname":"Berlin",
    "gn:country_code":"CO",
    "gn:dem":1666,
    "gn:feature_class":"P",
    "gn:feature_code":"PPL",
    "gn:name":"Berlin",
    "gn:population":0,
    "gn:timezone":"America/Bogota",
    "iso:country":"CO",
    "name:spa_x_preferred":[
        "Berlin"
    ],
    "wof:name":"Berlin",
    "wof:placetype":"locality"
},
  "geometry": {"coordinates":[-74.86466999999998,3.25856],"type":"Point"}
}