{
  "type": "Feature",
  "properties": {
    "gn:admin1_code":"20",
    "gn:admin2_code":"52835.0",
    "gn:asciiname":"Caunapi",
    "gn:cc2":"CO",
    "gn:country_code":"CO",
    "gn:dem":82,
    "gn:feature_class":"P",
    "gn:feature_code":"PPL",
    "gn:name":"Caunap\u00ed",
    "gn:population":0,
    "gn:timezone":"America/Bogota",
    "iso:country":"CO",
    "name:und_x_variant":[
        "Counopi",
        "Caunap\u00ed"
    ],
    "wof:name":"Caunapi",
    "wof:placetype":"locality"
},
  "geometry": {"coordinates":[-78.59778,1.41222],"type":"Point"}
}