{
  "type": "Feature",
  "properties": {
    "gn:admin1_code":"23",
    "gn:admin2_code":"63302.0",
    "gn:asciiname":"Esmeralda",
    "gn:country_code":"CO",
    "gn:dem":2046,
    "gn:feature_class":"P",
    "gn:feature_code":"PPL",
    "gn:name":"Esmeralda",
    "gn:population":0,
    "gn:timezone":"America/Bogota",
    "iso:country":"CO",
    "wof:name":"Esmeralda",
    "wof:placetype":"locality"
},
  "geometry": {"coordinates":[-75.80889000000001,4.15806],"type":"Point"}
}