{
  "type": "Feature",
  "properties": {
    "gn:admin1_code":"23",
    "gn:admin2_code":"63302.0",
    "gn:asciiname":"Esmeralda",
    "gn:country_code":"CO",
    "gn:dem":2046,
    "gn:feature_class":"P",
    "gn:feature_code":"PPL",
    "gn:name":"Esmeralda",
    "gn:population":0,
    "gn:timezone":"America/Bogota",
    "iso:country":"CO",
    "name:bul_x_preferred":[
        "\u0415\u0441\u043c\u0435\u0440\u0430\u043b\u0434\u0430"
    ],
    "name:ceb_x_preferred":[
        "Esmeralda"
    ],
    "name:ces_x_preferred":[
        "Esmeralda"
    ],
    "name:deu_x_preferred":[
        "Esmeralda"
    ],
    "name:ell_x_preferred":[
        "\u0395\u03c3\u03bc\u03b5\u03c1\u03ac\u03bb\u03b4\u03b1"
    ],
    "name:epo_x_preferred":[
        "Esmeralda"
    ],
    "name:est_x_preferred":[
        "Esmeralda"
    ],
    "name:fin_x_preferred":[
        "Esmeralda"
    ],
    "name:fra_x_preferred":[
        "Esmeralda"
    ],
    "name:ita_x_preferred":[
        "Esmeralda"
    ],
    "name:jpn_x_preferred":[
        "\u30a8\u30b9\u30e1\u30e9\u30eb\u30c0"
    ],
    "name:kor_x_preferred":[
        "\uc5d0\uc2a4\uba54\ub784\ub2e4"
    ],
    "name:nld_x_preferred":[
        "Esmeralda"
    ],
    "name:pol_x_preferred":[
        "Esmeralda"
    ],
    "name:por_x_preferred":[
        "Esmeralda"
    ],
    "name:ron_x_preferred":[
        "Esmeralda"
    ],
    "name:rus_x_preferred":[
        "Esmeralda"
    ],
    "name:spa_x_preferred":[
        "Esmeralda"
    ],
    "name:srp_x_preferred":[
        "\u0415\u0441\u043c\u0435\u0440\u0430\u043b\u0434\u0430"
    ],
    "name:swe_x_preferred":[
        "Esmeralda"
    ],
    "name:zho_x_preferred":[
        "\u57c3\u65af\u6885\u62c9\u9054"
    ],
    "wof:name":"Esmeralda",
    "wof:placetype":"locality"
},
  "geometry": {"coordinates":[-75.80889000000001,4.15806],"type":"Point"}
}