{
  "type": "Feature",
  "properties": {
    "gn:admin1_code":"2.0",
    "gn:admin2_code":"5628.0",
    "gn:asciiname":"Orobajo",
    "gn:country_code":"CO",
    "gn:dem":320,
    "gn:feature_class":"P",
    "gn:feature_code":"PPL",
    "gn:name":"Orobajo",
    "gn:population":0,
    "gn:timezone":"America/Bogota",
    "iso:country":"CO",
    "wof:name":"Orobajo",
    "wof:placetype":"locality"
},
  "geometry": {"coordinates":[-75.79299,7.02608],"type":"Point"}
}