{
  "type": "Feature",
  "properties": {
    "gn:admin1_code":"29",
    "gn:admin2_code":"76248.0",
    "gn:asciiname":"Genova",
    "gn:country_code":"CO",
    "gn:dem":961,
    "gn:feature_class":"P",
    "gn:feature_code":"PPL",
    "gn:name":"G\u00e9nova",
    "gn:population":0,
    "gn:timezone":"America/Bogota",
    "iso:country":"CO",
    "name:ben_x_preferred":[
        "\u099c\u09c7\u09a8\u09cb\u09ad\u09be"
    ],
    "wof:name":"Genova",
    "wof:placetype":"locality"
},
  "geometry": {"coordinates":[-76.38472,3.67028],"type":"Point"}
}