{
  "type": "Feature",
  "properties": {
    "gn:admin1_code":"38",
    "gn:admin2_code":"47692.0",
    "gn:asciiname":"Corozal",
    "gn:country_code":"CO",
    "gn:dem":72,
    "gn:feature_class":"P",
    "gn:feature_code":"PPL",
    "gn:name":"Corozal",
    "gn:population":0,
    "gn:timezone":"America/Bogota",
    "iso:country":"CO",
    "name:und_x_variant":[
        "Hacienda Corozal",
        "Corozal"
    ],
    "wof:name":"Corozal",
    "wof:placetype":"locality"
},
  "geometry": {"coordinates":[-74.18867,9.42939],"type":"Point"}
}