{
  "type": "Feature",
  "properties": {
    "gn:admin1_code":"21",
    "gn:admin2_code":"54250.0",
    "gn:asciiname":"La Gomez",
    "gn:country_code":"CO",
    "gn:dem":101,
    "gn:feature_class":"P",
    "gn:feature_code":"PPL",
    "gn:name":"La G\u00f3mez",
    "gn:population":0,
    "gn:timezone":"America/Bogota",
    "iso:country":"CO",
    "wof:name":"La Gomez",
    "wof:placetype":"locality"
},
  "geometry": {"coordinates":[-72.92639,8.70583],"type":"Point"}
}