{
  "type": "Feature",
  "properties": {
    "gn:admin1_code":"9.0",
    "gn:admin2_code":"19256.0",
    "gn:asciiname":"Altamira",
    "gn:country_code":"CO",
    "gn:dem":450,
    "gn:feature_class":"P",
    "gn:feature_code":"PPL",
    "gn:name":"Altamira",
    "gn:population":0,
    "gn:timezone":"America/Bogota",
    "iso:country":"CO",
    "wof:name":"Altamira",
    "wof:placetype":"locality"
},
  "geometry": {"coordinates":[-77.1187,2.60518],"type":"Point"}
}