{
  "type": "Feature",
  "properties": {
    "iso:country":"CO",
    "name:ceb_x_preferred":[
        "Castilla La Nueva"
    ],
    "name:chi_x_preferred":[
        "\u65b0\u5361\u65af\u8482\u5229\u4e9e"
    ],
    "name:dut_x_preferred":[
        "Castilla la Nueva"
    ],
    "name:eng_x_preferred":[
        "Castilla la Nueva"
    ],
    "name:fra_x_preferred":[
        "Castilla la Nueva"
    ],
    "name:fre_x_preferred":[
        "Castilla la Nueva"
    ],
    "name:geo_x_preferred":[
        "\u10d9\u10d0\u10e1\u10e2\u10d8\u10da\u10d8\u10d0-\u10da\u10d0-\u10dc\u10e3\u10d4\u10d5\u10d0"
    ],
    "name:ita_x_preferred":[
        "Castilla la Nueva"
    ],
    "name:kat_x_preferred":[
        "\u10d9\u10d0\u10e1\u10e2\u10d8\u10da\u10d8\u10d0-\u10da\u10d0-\u10dc\u10e3\u10d4\u10d5\u10d0"
    ],
    "name:may_x_preferred":[
        "Castilla la Nueva"
    ],
    "name:msa_x_preferred":[
        "Castilla la Nueva"
    ],
    "name:nan_x_preferred":[
        "Castilla la Nueva"
    ],
    "name:nld_x_preferred":[
        "Castilla la Nueva"
    ],
    "name:por_x_preferred":[
        "Castilla la Nueva"
    ],
    "name:spa_x_preferred":[
        "Castilla la Nueva"
    ],
    "name:swe_x_preferred":[
        "Castilla La Nueva"
    ],
    "name:tgl_x_preferred":[
        "Castilla la Nueva"
    ],
    "name:unk_x_variant":[
        "Shell"
    ],
    "name:vie_x_preferred":[
        "Castilla la Nueva"
    ],
    "name:war_x_preferred":[
        "Castilla la Nueva"
    ],
    "name:zho_min_nan_x_preferred":[
        "Castilla la Nueva"
    ],
    "name:zho_x_preferred":[
        "\u65b0\u5361\u65af\u8482\u5229\u4e9e"
    ],
    "qs:gn_country":"CO",
    "qs:gn_fcode":"PPL",
    "qs:gn_pop":1543,
    "qs:name":"Castilla la Nueva",
    "qs:name_adm0":"Colombia",
    "qs:name_adm1":"Meta",
    "qs:photos":0,
    "qs:photos_1k":0,
    "qs:photos_9k":1,
    "qs:photos_9r":1,
    "qs:photos_all":9,
    "qs:photos_sr":0,
    "qs:placetype":"Town",
    "qs:pop_sr":"3",
    "qs:woe_adm0":23424787,
    "wd:wordcount":21,
    "wof:name":"Castilla la Nueva",
    "wof:placetype":"locality",
    "wof:population":1543
},
  "geometry": {"coordinates":[-73.67986999999999,3.82845],"type":"Point"}
}