{
  "type": "Feature",
  "properties": {
    "gn:admin1_code":"32",
    "gn:admin2_code":"85230.0",
    "gn:asciiname":"Los Catalanes",
    "gn:country_code":"CO",
    "gn:dem":164,
    "gn:feature_class":"P",
    "gn:feature_code":"PPL",
    "gn:name":"Los Catalanes",
    "gn:population":0,
    "gn:timezone":"America/Bogota",
    "iso:country":"CO",
    "wof:name":"Los Catalanes",
    "wof:placetype":"locality"
},
  "geometry": {"coordinates":[-72.0175,4.8475],"type":"Point"}
}