{
  "type": "Feature",
  "properties": {
    "gn:admin1_code":"27",
    "gn:asciiname":"Majagual",
    "gn:cc2":"CO",
    "gn:country_code":"CO",
    "gn:dem":1,
    "gn:feature_class":"P",
    "gn:feature_code":"PPL",
    "gn:name":"Majagual",
    "gn:population":0,
    "gn:timezone":"America/Bogota",
    "iso:country":"CO",
    "name:ceb_x_preferred":[
        "Majagual"
    ],
    "name:sco_x_preferred":[
        "Majagual"
    ],
    "name:swe_x_preferred":[
        "Majagual"
    ],
    "name:und_x_variant":[
        "Hacienda Majagual",
        "Puerto Majagual",
        "Majagual"
    ],
    "name:vie_x_preferred":[
        "Majagual"
    ],
    "wof:name":"Majagual",
    "wof:placetype":"locality"
},
  "geometry": {"coordinates":[-75.61667,9.85],"type":"Point"}
}