{
  "type": "Feature",
  "properties": {
    "gn:admin1_code":"29",
    "gn:admin2_code":"76823.0",
    "gn:asciiname":"La Chica",
    "gn:country_code":"CO",
    "gn:dem":1475,
    "gn:feature_class":"P",
    "gn:feature_code":"PPL",
    "gn:name":"La Chica",
    "gn:population":0,
    "gn:timezone":"America/Bogota",
    "iso:country":"CO",
    "wof:name":"La Chica",
    "wof:placetype":"locality"
},
  "geometry": {"coordinates":[-76.13333,4.58333],"type":"Point"}
}