{
  "type": "Feature",
  "properties": {
    "gn:admin1_code":"26.0",
    "gn:admin2_code":"68770.0",
    "gn:asciiname":"El Tambor",
    "gn:country_code":"CO",
    "gn:dem":1487,
    "gn:feature_class":"P",
    "gn:feature_code":"PPL",
    "gn:name":"El Tambor",
    "gn:population":0,
    "gn:timezone":"America/Bogota",
    "iso:country":"CO",
    "wof:name":"El Tambor",
    "wof:placetype":"locality"
},
  "geometry": {"coordinates":[-73.38655,6.09183],"type":"Point"}
}