{
  "type": "Feature",
  "properties": {
    "gn:country":"CO",
    "gn:fcode":"DPOF",
    "gn:population":15,
    "iso:country":"CO",
    "qs:name":"Estacion de servicio | Texaco",
    "qs:photos_9r":0,
    "qs:photos_sr":0,
    "qs:pop_sr":"1",
    "wof:name":"Estacion de servicio | Texaco",
    "wof:placetype":"locality",
    "wof:population":15
},
  "geometry": {"coordinates":[-76.54116999999999,3.43522],"type":"Point"}
}