{
  "type": "Feature",
  "properties": {
    "gn:admin1_code":"28.0",
    "gn:admin2_code":"73217.0",
    "gn:asciiname":"Los Guayabos",
    "gn:country_code":"CO",
    "gn:dem":323,
    "gn:feature_class":"P",
    "gn:feature_code":"PPL",
    "gn:name":"Los Guayabos",
    "gn:population":0,
    "gn:timezone":"America/Bogota",
    "iso:country":"CO",
    "name:spa_x_preferred":[
        "Los Guayabos"
    ],
    "wof:name":"Los Guayabos",
    "wof:placetype":"locality"
},
  "geometry": {"coordinates":[-75.10535,3.81161],"type":"Point"}
}