{
  "type": "Feature",
  "properties": {
    "gn:admin1_code":"17.0",
    "gn:admin2_code":"44847.0",
    "gn:asciiname":"Rancheria San Andres",
    "gn:country_code":"CO",
    "gn:dem":-33,
    "gn:feature_class":"P",
    "gn:feature_code":"PPL",
    "gn:name":"Rancher\u00eda San Andr\u00e9s",
    "gn:population":0,
    "gn:timezone":"America/Bogota",
    "iso:country":"CO",
    "name:und_x_variant":[
        "Rancher\u00eda San Andr\u00e9s",
        "San Andr\u00e9s"
    ],
    "wof:name":"Rancheria San Andres",
    "wof:placetype":"locality"
},
  "geometry": {"coordinates":[-71.22623,12.18785],"type":"Point"}
}