{
  "type": "Feature",
  "properties": {
    "gn:admin1_code":"16.0",
    "gn:admin2_code":"41206.0",
    "gn:asciiname":"La Ranrada",
    "gn:country_code":"CO",
    "gn:dem":1371,
    "gn:feature_class":"P",
    "gn:feature_code":"PPL",
    "gn:name":"La Ranrada",
    "gn:population":0,
    "gn:timezone":"America/Bogota",
    "iso:country":"CO",
    "name:spa_x_preferred":[
        "La Ranrada"
    ],
    "wof:name":"La Ranrada",
    "wof:placetype":"locality"
},
  "geometry": {"coordinates":[-74.81879000000001,3.20943],"type":"Point"}
}