{
  "type": "Feature",
  "properties": {
    "gn:admin1_code":"33.0",
    "gn:admin2_code":"25297.0",
    "gn:asciiname":"El Santuario",
    "gn:country_code":"CO",
    "gn:dem":1747,
    "gn:feature_class":"P",
    "gn:feature_code":"PPL",
    "gn:name":"El Santuario",
    "gn:population":0,
    "gn:timezone":"America/Bogota",
    "iso:country":"CO",
    "wof:name":"El Santuario",
    "wof:placetype":"locality"
},
  "geometry": {"coordinates":[-73.65968000000002,4.82965],"type":"Point"}
}