{
  "type": "Feature",
  "properties": {
    "gn:admin1_code":"33.0",
    "gn:admin2_code":"25297.0",
    "gn:asciiname":"El Santuario",
    "gn:country_code":"CO",
    "gn:dem":1747,
    "gn:feature_class":"P",
    "gn:feature_code":"PPL",
    "gn:name":"El Santuario",
    "gn:population":0,
    "gn:timezone":"America/Bogota",
    "iso:country":"CO",
    "name:deu_x_preferred":[
        "El Santuario"
    ],
    "name:fas_x_preferred":[
        "\u0627\u0644 \u0633\u0627\u0646\u062a\u0648\u0622\u0631\u06cc\u0648"
    ],
    "name:fra_x_preferred":[
        "El Santuario"
    ],
    "name:gla_x_preferred":[
        "El Santuario"
    ],
    "name:ilo_x_preferred":[
        "El Santuario"
    ],
    "name:ita_x_preferred":[
        "El Santuario"
    ],
    "name:kat_x_preferred":[
        "\u10d4\u10da-\u10e1\u10d0\u10dc\u10e2\u10e3\u10d0\u10e0\u10d8\u10dd"
    ],
    "name:msa_x_preferred":[
        "Santuario"
    ],
    "name:nld_x_preferred":[
        "El Santuario"
    ],
    "name:por_x_preferred":[
        "El Santuario"
    ],
    "name:ron_x_preferred":[
        "El Santuario"
    ],
    "name:rus_x_preferred":[
        "\u042d\u043b\u044c-\u0421\u0430\u043d\u0442\u0443\u0430\u0440\u0438\u043e"
    ],
    "name:sco_x_preferred":[
        "El Santuario"
    ],
    "name:spa_x_preferred":[
        "El Santuario"
    ],
    "name:vie_x_preferred":[
        "Santuario"
    ],
    "name:war_x_preferred":[
        "Santuario"
    ],
    "name:zho_x_preferred":[
        "\u57c3\u723e\u6851\u5716\u963f\u91cc\u5967"
    ],
    "wof:name":"El Santuario",
    "wof:placetype":"locality"
},
  "geometry": {"coordinates":[-73.65968000000002,4.82965],"type":"Point"}
}