{
  "type": "Feature",
  "properties": {
    "gn:admin1_code":"20.0",
    "gn:admin2_code":"52835.0",
    "gn:asciiname":"Rosario",
    "gn:country_code":"CO",
    "gn:dem":4,
    "gn:feature_class":"P",
    "gn:feature_code":"PPL",
    "gn:name":"Rosario",
    "gn:population":0,
    "gn:timezone":"America/Bogota",
    "iso:country":"CO",
    "name:und_x_variant":[
        "Santa Mar\u00eda",
        "Rosario"
    ],
    "wof:name":"Rosario",
    "wof:placetype":"locality"
},
  "geometry": {"coordinates":[-78.64853000000002,1.67104],"type":"Point"}
}