{
  "type": "Feature",
  "properties": {
    "gn:admin1_code":"17",
    "gn:admin2_code":"44847.0",
    "gn:asciiname":"Kepechirou",
    "gn:country_code":"CO",
    "gn:dem":166,
    "gn:feature_class":"P",
    "gn:feature_code":"PPL",
    "gn:name":"Kep\u00e9chirou",
    "gn:population":0,
    "gn:timezone":"America/Bogota",
    "iso:country":"CO",
    "name:und_x_variant":[
        "Kep\u00e9chirou",
        "Kep\u00e9chiru"
    ],
    "wof:name":"Kepechirou",
    "wof:placetype":"locality"
},
  "geometry": {"coordinates":[-71.59084,12.07267],"type":"Point"}
}