{
  "type": "Feature",
  "properties": {
    "gn:admin1_code":"2.0",
    "gn:admin2_code":"5656.0",
    "gn:asciiname":"La Curia",
    "gn:country_code":"CO",
    "gn:dem":1747,
    "gn:feature_class":"P",
    "gn:feature_code":"PPL",
    "gn:name":"La Curia",
    "gn:population":0,
    "gn:timezone":"America/Bogota",
    "iso:country":"CO",
    "name:spa_x_preferred":[
        "La Curia"
    ],
    "wof:name":"La Curia",
    "wof:placetype":"locality"
},
  "geometry": {"coordinates":[-75.68301,6.49429],"type":"Point"}
}