{
  "type": "Feature",
  "properties": {
    "gn:admin1_code":"16.0",
    "gn:admin2_code":"41791.0",
    "gn:asciiname":"La Alegria",
    "gn:country_code":"CO",
    "gn:dem":1057,
    "gn:feature_class":"P",
    "gn:feature_code":"PPL",
    "gn:name":"La Alegr\u00eda",
    "gn:population":0,
    "gn:timezone":"America/Bogota",
    "iso:country":"CO",
    "wof:name":"La Alegria",
    "wof:placetype":"locality"
},
  "geometry": {"coordinates":[-75.83835000000001,2.17549],"type":"Point"}
}