{
  "type": "Feature",
  "properties": {
    "gn:admin1_code":"20.0",
    "gn:admin2_code":"52240.0",
    "gn:asciiname":"Pasisara",
    "gn:country_code":"CO",
    "gn:dem":1857,
    "gn:feature_class":"P",
    "gn:feature_code":"PPL",
    "gn:name":"Pasisar\u00e1",
    "gn:population":0,
    "gn:timezone":"America/Bogota",
    "iso:country":"CO",
    "wof:name":"Pasisara",
    "wof:placetype":"locality"
},
  "geometry": {"coordinates":[-77.25147,1.38655],"type":"Point"}
}