{
  "type": "Feature",
  "properties": {
    "gn:admin1_code":"36",
    "gn:admin2_code":"15442.0",
    "gn:asciiname":"Pantano Largo",
    "gn:country_code":"CO",
    "gn:dem":1737,
    "gn:feature_class":"P",
    "gn:feature_code":"PPL",
    "gn:name":"Pantano Largo",
    "gn:population":0,
    "gn:timezone":"America/Bogota",
    "iso:country":"CO",
    "wof:name":"Pantano Largo",
    "wof:placetype":"locality"
},
  "geometry": {"coordinates":[-73.98083000000003,5.57944],"type":"Point"}
}