{
  "type": "Feature",
  "properties": {
    "gn:admin1_code":"9",
    "gn:admin2_code":"19450.0",
    "gn:asciiname":"El Trapiche",
    "gn:country_code":"CO",
    "gn:dem":956,
    "gn:feature_class":"P",
    "gn:feature_code":"PPL",
    "gn:name":"El Trapiche",
    "gn:population":0,
    "gn:timezone":"America/Bogota",
    "iso:country":"CO",
    "wof:name":"El Trapiche",
    "wof:placetype":"locality"
},
  "geometry": {"coordinates":[-77.26611,1.73111],"type":"Point"}
}