{
  "type": "Feature",
  "properties": {
    "gn:admin1_code":"33.0",
    "gn:admin2_code":"25151.0",
    "gn:asciiname":"La Chapa",
    "gn:country_code":"CO",
    "gn:dem":2440,
    "gn:feature_class":"P",
    "gn:feature_code":"PPL",
    "gn:name":"La Chapa",
    "gn:population":0,
    "gn:timezone":"America/Bogota",
    "iso:country":"CO",
    "name:spa_x_preferred":[
        "La Chapa"
    ],
    "wof:name":"La Chapa",
    "wof:placetype":"locality"
},
  "geometry": {"coordinates":[-73.96374,4.37939],"type":"Point"}
}