{
  "type": "Feature",
  "properties": {
    "gn:admin1_code":"11.0",
    "gn:admin2_code":"27615.0",
    "gn:asciiname":"Guacuco",
    "gn:country_code":"CO",
    "gn:dem":5,
    "gn:feature_class":"P",
    "gn:feature_code":"PPL",
    "gn:name":"Guacuco",
    "gn:population":0,
    "gn:timezone":"America/Bogota",
    "iso:country":"CO",
    "name:spa_x_preferred":[
        "Guacuco"
    ],
    "wof:name":"Guacuco",
    "wof:placetype":"locality"
},
  "geometry": {"coordinates":[-77.09265000000001,7.48121],"type":"Point"}
}