{
  "type": "Feature",
  "properties": {
    "gn:admin1_code":"3",
    "gn:admin2_code":"81001.0",
    "gn:asciiname":"La Sonrisa",
    "gn:country_code":"CO",
    "gn:dem":118,
    "gn:feature_class":"P",
    "gn:feature_code":"PPL",
    "gn:name":"La Sonrisa",
    "gn:population":0,
    "gn:timezone":"America/Bogota",
    "iso:country":"CO",
    "name:cat_x_preferred":[
        "La Sonrisa"
    ],
    "name:deu_x_preferred":[
        "La Sonrisa"
    ],
    "name:fra_x_preferred":[
        "La Sonrisa"
    ],
    "name:urd_x_preferred":[
        "\u0644\u0627 \u0633\u0648\u0646\u0631\u06cc\u0633\u0627"
    ],
    "wof:name":"La Sonrisa",
    "wof:placetype":"locality"
},
  "geometry": {"coordinates":[-70.50638000000002,6.58166],"type":"Point"}
}