{
  "type": "Feature",
  "properties": {
    "gn:admin1_code":"26.0",
    "gn:admin2_code":"68547.0",
    "gn:asciiname":"Pescadero",
    "gn:country_code":"CO",
    "gn:dem":577,
    "gn:feature_class":"P",
    "gn:feature_code":"PPL",
    "gn:name":"Pescadero",
    "gn:population":0,
    "gn:timezone":"America/Bogota",
    "iso:country":"CO",
    "name:ceb_x_preferred":[
        "Pescadero"
    ],
    "name:spa_x_preferred":[
        "Pescadero"
    ],
    "name:swe_x_preferred":[
        "Pescadero"
    ],
    "wof:name":"Pescadero",
    "wof:placetype":"locality"
},
  "geometry": {"coordinates":[-72.99065,6.82439],"type":"Point"}
}