{
  "type": "Feature",
  "properties": {
    "gn:admin1_code":"12",
    "gn:admin2_code":"23555.0",
    "gn:asciiname":"Cantarrana",
    "gn:country_code":"CO",
    "gn:dem":115,
    "gn:feature_class":"P",
    "gn:feature_code":"PPL",
    "gn:name":"Cantarrana",
    "gn:population":0,
    "gn:timezone":"America/Bogota",
    "iso:country":"CO",
    "name:und_x_variant":[
        "Canta Rana",
        "Cantarrana"
    ],
    "wof:name":"Cantarrana",
    "wof:placetype":"locality"
},
  "geometry": {"coordinates":[-75.65325,8.40187],"type":"Point"}
}