{
  "type": "Feature",
  "properties": {
    "gn:admin1_code":"12.0",
    "gn:admin2_code":"23660.0",
    "gn:asciiname":"Arenas del Norte",
    "gn:country_code":"CO",
    "gn:dem":51,
    "gn:feature_class":"P",
    "gn:feature_code":"PPLL",
    "gn:name":"Arenas del Norte",
    "gn:population":0,
    "gn:timezone":"America/Bogota",
    "iso:country":"CO",
    "wof:name":"Arenas del Norte",
    "wof:placetype":"locality"
},
  "geometry": {"coordinates":[-75.50083000000002,8.98611],"type":"Point"}
}