{
  "type": "Feature",
  "properties": {
    "gn:admin1_code":"3",
    "gn:admin2_code":"81591.0",
    "gn:asciiname":"California",
    "gn:country_code":"CO",
    "gn:dem":126,
    "gn:feature_class":"P",
    "gn:feature_code":"PPL",
    "gn:name":"California",
    "gn:population":0,
    "gn:timezone":"America/Bogota",
    "iso:country":"CO",
    "wof:name":"California",
    "wof:placetype":"locality"
},
  "geometry": {"coordinates":[-70.99229,6.47582],"type":"Point"}
}