{
  "type": "Feature",
  "properties": {
    "gn:admin1_code":"20",
    "gn:admin2_code":"52683.0",
    "gn:asciiname":"El Ingenio",
    "gn:country_code":"CO",
    "gn:dem":1559,
    "gn:feature_class":"P",
    "gn:feature_code":"PPL",
    "gn:name":"El Ingenio",
    "gn:population":0,
    "gn:timezone":"America/Bogota",
    "iso:country":"CO",
    "name:und_x_variant":[
        "Ingenio",
        "El Ingenio"
    ],
    "wof:name":"El Ingenio",
    "wof:placetype":"locality"
},
  "geometry": {"coordinates":[-77.46365,1.30939],"type":"Point"}
}