{
  "type": "Feature",
  "properties": {
    "gn:admin1_code":"17",
    "gn:admin2_code":"44650.0",
    "gn:asciiname":"Loma de El Potrero",
    "gn:country_code":"CO",
    "gn:dem":580,
    "gn:feature_class":"P",
    "gn:feature_code":"PPL",
    "gn:name":"Loma de El Potrero",
    "gn:population":0,
    "gn:timezone":"America/Bogota",
    "iso:country":"CO",
    "wof:name":"Loma de El Potrero",
    "wof:placetype":"locality"
},
  "geometry": {"coordinates":[-73.09956,10.88684],"type":"Point"}
}