{
  "type": "Feature",
  "properties": {
    "gn:admin1_code":"24",
    "gn:asciiname":"La Julia",
    "gn:country_code":"CO",
    "gn:dem":1050,
    "gn:feature_class":"P",
    "gn:feature_code":"PPL",
    "gn:name":"La Julia",
    "gn:population":0,
    "gn:timezone":"America/Bogota",
    "iso:country":"CO",
    "name:ceb_x_preferred":[
        "La Julia"
    ],
    "name:swe_x_preferred":[
        "La Julia"
    ],
    "name:urd_x_preferred":[
        "\u0644\u0627 \u062c\u0648\u0644\u06cc\u0627"
    ],
    "wof:name":"La Julia",
    "wof:placetype":"locality"
},
  "geometry": {"coordinates":[-75.88083,5.1075],"type":"Point"}
}