{
  "type": "Feature",
  "properties": {
    "gn:admin1_code":"2.0",
    "gn:admin2_code":"5664.0",
    "gn:asciiname":"San Juan Zapata",
    "gn:country_code":"CO",
    "gn:dem":2462,
    "gn:feature_class":"P",
    "gn:feature_code":"PPL",
    "gn:name":"San J\u00faan Zapata",
    "gn:population":0,
    "gn:timezone":"America/Bogota",
    "iso:country":"CO",
    "name:spa_x_preferred":[
        "San J\u00faan Zapata"
    ],
    "wof:name":"San Juan Zapata",
    "wof:placetype":"locality"
},
  "geometry": {"coordinates":[-75.59356,6.49671],"type":"Point"}
}