{
  "type": "Feature",
  "properties": {
    "gn:admin1_code":"28",
    "gn:admin2_code":"73168.0",
    "gn:asciiname":"Mameyal",
    "gn:country_code":"CO",
    "gn:dem":2243,
    "gn:feature_class":"P",
    "gn:feature_code":"PPL",
    "gn:name":"Mameyal",
    "gn:population":0,
    "gn:timezone":"America/Bogota",
    "iso:country":"CO",
    "name:spa_x_preferred":[
        "Mameyal"
    ],
    "wof:name":"Mameyal",
    "wof:placetype":"locality"
},
  "geometry": {"coordinates":[-75.67778,3.89778],"type":"Point"}
}