{
  "type": "Feature",
  "properties": {
    "gn:admin1_code":"33.0",
    "gn:admin2_code":"25473.0",
    "gn:asciiname":"Entrerrios",
    "gn:country_code":"CO",
    "gn:dem":2555,
    "gn:feature_class":"P",
    "gn:feature_code":"PPL",
    "gn:name":"Entrerr\u00edos",
    "gn:population":0,
    "gn:timezone":"America/Bogota",
    "iso:country":"CO",
    "name:spa_x_preferred":[
        "Entrerr\u00edos"
    ],
    "wof:name":"Entrerrios",
    "wof:placetype":"locality"
},
  "geometry": {"coordinates":[-74.24287,4.65013],"type":"Point"}
}