{
  "type": "Feature",
  "properties": {
    "gn:admin1_code":"12",
    "gn:admin2_code":"23189.0",
    "gn:asciiname":"Egipto",
    "gn:country_code":"CO",
    "gn:dem":21,
    "gn:feature_class":"P",
    "gn:feature_code":"PPL",
    "gn:name":"Egipto",
    "gn:population":0,
    "gn:timezone":"America/Bogota",
    "iso:country":"CO",
    "wof:name":"Egipto",
    "wof:placetype":"locality"
},
  "geometry": {"coordinates":[-75.56914,8.92201],"type":"Point"}
}