{
  "type": "Feature",
  "properties": {
    "gn:admin1_code":"17",
    "gn:admin2_code":"44098.0",
    "gn:asciiname":"Sopresa",
    "gn:country_code":"CO",
    "gn:dem":218,
    "gn:feature_class":"P",
    "gn:feature_code":"PPL",
    "gn:name":"Sopresa",
    "gn:population":0,
    "gn:timezone":"America/Bogota",
    "iso:country":"CO",
    "wof:name":"Sopresa",
    "wof:placetype":"locality"
},
  "geometry": {"coordinates":[-72.9002,10.89263],"type":"Point"}
}