{
  "type": "Feature",
  "properties": {
    "gn:admin1_code":"19.0",
    "gn:admin2_code":"50313.0",
    "gn:asciiname":"Puerto Caldas",
    "gn:country_code":"CO",
    "gn:dem":292,
    "gn:feature_class":"P",
    "gn:feature_code":"PPL",
    "gn:name":"Puerto Caldas",
    "gn:population":0,
    "gn:timezone":"America/Bogota",
    "iso:country":"CO",
    "wof:name":"Puerto Caldas",
    "wof:placetype":"locality"
},
  "geometry": {"coordinates":[-73.70028000000001,3.47222],"type":"Point"}
}