{
  "type": "Feature",
  "properties": {
    "gn:admin1_code":"32",
    "gn:admin2_code":"85430.0",
    "gn:asciiname":"El Campin",
    "gn:country_code":"CO",
    "gn:dem":111,
    "gn:feature_class":"P",
    "gn:feature_code":"PPL",
    "gn:name":"El Campin",
    "gn:population":0,
    "gn:timezone":"America/Bogota",
    "iso:country":"CO",
    "wof:name":"El Campin",
    "wof:placetype":"locality"
},
  "geometry": {"coordinates":[-70.63280999999998,5.44676],"type":"Point"}
}