{
  "type": "Feature",
  "properties": {
    "gn:admin1_code":"2.0",
    "gn:admin2_code":"5501.0",
    "gn:asciiname":"El Hato",
    "gn:country_code":"CO",
    "gn:dem":1052,
    "gn:feature_class":"P",
    "gn:feature_code":"PPL",
    "gn:name":"El Hato",
    "gn:population":0,
    "gn:timezone":"America/Bogota",
    "iso:country":"CO",
    "name:ita_x_preferred":[
        "El Hato"
    ],
    "name:spa_x_preferred":[
        "El Hato"
    ],
    "name:zho_x_preferred":[
        "\u57c3\u723e\u963f\u6258"
    ],
    "wof:name":"El Hato",
    "wof:placetype":"locality"
},
  "geometry": {"coordinates":[-75.76306,6.57389],"type":"Point"}
}