{
  "type": "Feature",
  "properties": {
    "gn:admin1_code":"16.0",
    "gn:admin2_code":"41396.0",
    "gn:asciiname":"El Salado",
    "gn:country_code":"CO",
    "gn:dem":1153,
    "gn:feature_class":"P",
    "gn:feature_code":"PPL",
    "gn:name":"El Salado",
    "gn:population":0,
    "gn:timezone":"America/Bogota",
    "iso:country":"CO",
    "wof:name":"El Salado",
    "wof:placetype":"locality"
},
  "geometry": {"coordinates":[-75.94376,2.32764],"type":"Point"}
}