{
  "type": "Feature",
  "properties": {
    "gn:admin1_code":"26",
    "gn:admin2_code":"68572.0",
    "gn:asciiname":"Las Palmas",
    "gn:country_code":"CO",
    "gn:dem":2045,
    "gn:feature_class":"P",
    "gn:feature_code":"PPL",
    "gn:name":"Las Palmas",
    "gn:population":0,
    "gn:timezone":"America/Bogota",
    "iso:country":"CO",
    "wof:name":"Las Palmas",
    "wof:placetype":"locality"
},
  "geometry": {"coordinates":[-73.64055999999999,5.82444],"type":"Point"}
}