{
  "type": "Feature",
  "properties": {
    "gn:admin1_code":"31",
    "gn:admin2_code":"99624.0",
    "gn:asciiname":"Burrunay",
    "gn:country_code":"CO",
    "gn:dem":114,
    "gn:feature_class":"P",
    "gn:feature_code":"PPL",
    "gn:name":"Burrunay",
    "gn:population":0,
    "gn:timezone":"America/Bogota",
    "iso:country":"CO",
    "wof:name":"Burrunay",
    "wof:placetype":"locality"
},
  "geometry": {"coordinates":[-70.67729,5.34927],"type":"Point"}
}