{
  "type": "Feature",
  "properties": {
    "gn:admin1_code":"19.0",
    "gn:admin2_code":"50590.0",
    "gn:asciiname":"Barranco Colorado",
    "gn:country_code":"CO",
    "gn:dem":207,
    "gn:feature_class":"P",
    "gn:feature_code":"PPL",
    "gn:name":"Barranco Colorado",
    "gn:population":0,
    "gn:timezone":"America/Bogota",
    "iso:country":"CO",
    "name:spa_x_preferred":[
        "Barranco Colorado"
    ],
    "wof:name":"Barranco Colorado",
    "wof:placetype":"locality"
},
  "geometry": {"coordinates":[-73.116,2.823],"type":"Point"}
}