{
  "type": "Feature",
  "properties": {
    "gn:admin1_code":"28",
    "gn:admin2_code":"73622.0",
    "gn:asciiname":"Villa Ersila",
    "gn:country_code":"CO",
    "gn:dem":2818,
    "gn:feature_class":"P",
    "gn:feature_code":"PPL",
    "gn:name":"Villa Ersila",
    "gn:population":0,
    "gn:timezone":"America/Bogota",
    "iso:country":"CO",
    "wof:name":"Villa Ersila",
    "wof:placetype":"locality"
},
  "geometry": {"coordinates":[-75.62222,4.04667],"type":"Point"}
}