{
  "type": "Feature",
  "properties": {
    "gn:admin1_code":"16.0",
    "gn:admin2_code":"41791.0",
    "gn:asciiname":"La Pradera",
    "gn:country_code":"CO",
    "gn:dem":1621,
    "gn:feature_class":"P",
    "gn:feature_code":"PPL",
    "gn:name":"La Pradera",
    "gn:population":0,
    "gn:timezone":"America/Bogota",
    "iso:country":"CO",
    "wof:name":"La Pradera",
    "wof:placetype":"locality"
},
  "geometry": {"coordinates":[-75.9529,2.0807],"type":"Point"}
}