{
  "type": "Feature",
  "properties": {
    "gn:admin1_code":"35.0",
    "gn:admin2_code":"13006.0",
    "gn:asciiname":"Puerto Lopez",
    "gn:country_code":"CO",
    "gn:dem":18,
    "gn:feature_class":"P",
    "gn:feature_code":"PPL",
    "gn:name":"Puerto L\u00f3pez",
    "gn:population":0,
    "gn:timezone":"America/Bogota",
    "iso:country":"CO",
    "wof:name":"Puerto Lopez",
    "wof:placetype":"locality"
},
  "geometry": {"coordinates":[-74.47228,8.79564],"type":"Point"}
}