{
  "type": "Feature",
  "properties": {
    "gn:admin1_code":"11.0",
    "gn:admin2_code":"27660.0",
    "gn:asciiname":"Valencia",
    "gn:country_code":"CO",
    "gn:dem":202,
    "gn:feature_class":"P",
    "gn:feature_code":"PPL",
    "gn:name":"Valencia",
    "gn:population":0,
    "gn:timezone":"America/Bogota",
    "iso:country":"CO",
    "wof:name":"Valencia",
    "wof:placetype":"locality"
},
  "geometry": {"coordinates":[-76.40373000000002,4.93453],"type":"Point"}
}