{
  "type": "Feature",
  "properties": {
    "gn:admin1_code":"17.0",
    "gn:admin2_code":"44847.0",
    "gn:asciiname":"Uritkahin",
    "gn:country_code":"CO",
    "gn:dem":255,
    "gn:feature_class":"P",
    "gn:feature_code":"PPL",
    "gn:name":"Uritkahin",
    "gn:population":0,
    "gn:timezone":"America/Bogota",
    "iso:country":"CO",
    "wof:name":"Uritkahin",
    "wof:placetype":"locality"
},
  "geometry": {"coordinates":[-71.59809,12.14005],"type":"Point"}
}