{
  "type": "Feature",
  "properties": {
    "gn:admin1_code":"27.0",
    "gn:admin2_code":"70508.0",
    "gn:asciiname":"Tunez",
    "gn:country_code":"CO",
    "gn:dem":146,
    "gn:feature_class":"P",
    "gn:feature_code":"PPL",
    "gn:name":"T\u00fanez",
    "gn:population":0,
    "gn:timezone":"America/Bogota",
    "iso:country":"CO",
    "wof:name":"Tunez",
    "wof:placetype":"locality"
},
  "geometry": {"coordinates":[-75.11667,9.45],"type":"Point"}
}