{
  "type": "Feature",
  "properties": {
    "gn:admin1_code":"19",
    "gn:admin2_code":"50124.0",
    "gn:asciiname":"Los Caballeros",
    "gn:country_code":"CO",
    "gn:dem":176,
    "gn:feature_class":"P",
    "gn:feature_code":"PPL",
    "gn:name":"Los Caballeros",
    "gn:population":0,
    "gn:timezone":"America/Bogota",
    "iso:country":"CO",
    "wof:name":"Los Caballeros",
    "wof:placetype":"locality"
},
  "geometry": {"coordinates":[-72.83811,4.32899],"type":"Point"}
}