{
  "type": "Feature",
  "properties": {
    "gn:admin1_code":"12.0",
    "gn:admin2_code":"23182.0",
    "gn:asciiname":"Pensilvania",
    "gn:country_code":"CO",
    "gn:dem":47,
    "gn:feature_class":"P",
    "gn:feature_code":"PPL",
    "gn:name":"Pensilvania",
    "gn:population":0,
    "gn:timezone":"America/Bogota",
    "iso:country":"CO",
    "wof:name":"Pensilvania",
    "wof:placetype":"locality"
},
  "geometry": {"coordinates":[-75.27949,8.94187],"type":"Point"}
}