{
  "type": "Feature",
  "properties": {
    "gn:admin1_code":"37",
    "gn:admin2_code":"17665.0",
    "gn:asciiname":"Asia",
    "gn:country_code":"CO",
    "gn:dem":965,
    "gn:feature_class":"P",
    "gn:feature_code":"PPL",
    "gn:name":"Asia",
    "gn:population":0,
    "gn:timezone":"America/Bogota",
    "iso:country":"CO",
    "wof:name":"Asia",
    "wof:placetype":"locality"
},
  "geometry": {"coordinates":[-75.84999999999999,5.06667],"type":"Point"}
}