{
  "type": "Feature",
  "properties": {
    "gn:admin1_code":"2.0",
    "gn:admin2_code":"5147.0",
    "gn:asciiname":"Los Alamos",
    "gn:country_code":"CO",
    "gn:dem":25,
    "gn:feature_class":"P",
    "gn:feature_code":"PPL",
    "gn:name":"Los Alamos",
    "gn:population":0,
    "gn:timezone":"America/Bogota",
    "iso:country":"CO",
    "name:ceb_x_preferred":[
        "Los Alamos"
    ],
    "name:deu_x_preferred":[
        "Los Alamos"
    ],
    "name:nld_x_preferred":[
        "Los Alamos"
    ],
    "name:pol_x_preferred":[
        "Los Alamos"
    ],
    "name:por_x_preferred":[
        "Los Alamos"
    ],
    "name:rus_x_preferred":[
        "\u041b\u043e\u0441-\u0410\u043b\u0430\u043c\u043e\u0441"
    ],
    "name:swe_x_preferred":[
        "Los Alamos"
    ],
    "name:tur_x_preferred":[
        "Los Alamos"
    ],
    "name:ukr_x_preferred":[
        "\u041b\u043e\u0441-\u0410\u043b\u0430\u043c\u043e\u0441"
    ],
    "name:vie_x_preferred":[
        "Los Alamos"
    ],
    "name:vol_x_preferred":[
        "Los Alamos"
    ],
    "wof:name":"Los Alamos",
    "wof:placetype":"locality"
},
  "geometry": {"coordinates":[-76.68056,7.78556],"type":"Point"}
}