{
  "type": "Feature",
  "properties": {
    "gn:admin1_code":"26.0",
    "gn:admin2_code":"68573.0",
    "gn:asciiname":"Brisas del Opon",
    "gn:country_code":"CO",
    "gn:dem":108,
    "gn:feature_class":"P",
    "gn:feature_code":"PPLL",
    "gn:name":"Brisas del Op\u00f3n",
    "gn:population":0,
    "gn:timezone":"America/Bogota",
    "iso:country":"CO",
    "wof:name":"Brisas del Opon",
    "wof:placetype":"locality"
},
  "geometry": {"coordinates":[-73.84574000000001,6.66577],"type":"Point"}
}