{
  "type": "Feature",
  "properties": {
    "gn:admin1_code":"17",
    "gn:admin2_code":"44847.0",
    "gn:asciiname":"Machinkamahana",
    "gn:country_code":"CO",
    "gn:dem":128,
    "gn:feature_class":"P",
    "gn:feature_code":"PPL",
    "gn:name":"Machinkamahana",
    "gn:population":0,
    "gn:timezone":"America/Bogota",
    "iso:country":"CO",
    "wof:name":"Machinkamahana",
    "wof:placetype":"locality"
},
  "geometry": {"coordinates":[-71.95828,11.89734],"type":"Point"}
}