{
  "type": "Feature",
  "properties": {
    "gn:admin1_code":"20",
    "gn:admin2_code":"52051.0",
    "gn:asciiname":"San Cayetano",
    "gn:country_code":"CO",
    "gn:dem":2320,
    "gn:feature_class":"P",
    "gn:feature_code":"PPL",
    "gn:name":"San Cayetano",
    "gn:population":0,
    "gn:timezone":"America/Bogota",
    "iso:country":"CO",
    "name:ceb_x_preferred":[
        "San Cayetano"
    ],
    "name:deu_x_preferred":[
        "San Cayetano"
    ],
    "name:fra_x_preferred":[
        "San Cayetano"
    ],
    "name:ita_x_preferred":[
        "San Cayetano"
    ],
    "name:msa_x_preferred":[
        "San Cayetano"
    ],
    "name:nld_x_preferred":[
        "San Cayetano"
    ],
    "name:por_x_preferred":[
        "San Cayetano"
    ],
    "name:sco_x_preferred":[
        "San Cayetano"
    ],
    "name:spa_x_preferred":[
        "San Cayetano"
    ],
    "name:swe_x_preferred":[
        "San Cayetano"
    ],
    "name:und_x_variant":[
        "San Cayetono",
        "San Cayetano"
    ],
    "name:war_x_preferred":[
        "San Cayetano"
    ],
    "wof:name":"San Cayetano",
    "wof:placetype":"locality"
},
  "geometry": {"coordinates":[-77.14904,1.50996],"type":"Point"}
}