{
  "type": "Feature",
  "properties": {
    "gn:admin1_code":"21",
    "gn:admin2_code":"54245.0",
    "gn:asciiname":"Cerro Redondo",
    "gn:country_code":"CO",
    "gn:dem":1792,
    "gn:feature_class":"P",
    "gn:feature_code":"PPL",
    "gn:name":"Cerro Redondo",
    "gn:population":0,
    "gn:timezone":"America/Bogota",
    "iso:country":"CO",
    "wof:name":"Cerro Redondo",
    "wof:placetype":"locality"
},
  "geometry": {"coordinates":[-73.47,8.47944],"type":"Point"}
}