{
  "type": "Feature",
  "properties": {
    "gn:admin1_code":"28",
    "gn:admin2_code":"73067.0",
    "gn:asciiname":"Manzanares",
    "gn:country_code":"CO",
    "gn:dem":1569,
    "gn:feature_class":"P",
    "gn:feature_code":"PPL",
    "gn:name":"Manzanares",
    "gn:population":0,
    "gn:timezone":"America/Bogota",
    "iso:country":"CO",
    "wof:name":"Manzanares",
    "wof:placetype":"locality"
},
  "geometry": {"coordinates":[-75.58944,3.23639],"type":"Point"}
}