{
  "type": "Feature",
  "properties": {
    "gn:admin1_code":"2.0",
    "gn:admin2_code":"5113.0",
    "gn:asciiname":"Angelina",
    "gn:country_code":"CO",
    "gn:dem":835,
    "gn:feature_class":"P",
    "gn:feature_code":"PPL",
    "gn:name":"Angelina",
    "gn:population":0,
    "gn:timezone":"America/Bogota",
    "iso:country":"CO",
    "name:ceb_x_preferred":[
        "Angelina"
    ],
    "name:deu_x_preferred":[
        "Angelina"
    ],
    "name:fra_x_preferred":[
        "Angelina"
    ],
    "name:ita_x_preferred":[
        "Angelina"
    ],
    "name:jpn_x_preferred":[
        "\u30a2\u30f3\u30b8\u30a7\u30ea\u30fc\u30ca"
    ],
    "name:kor_x_preferred":[
        "\uc564\uc824\ub9ac\ub098"
    ],
    "name:nld_x_preferred":[
        "Angelina"
    ],
    "name:por_x_preferred":[
        "Angelina"
    ],
    "name:rus_x_preferred":[
        "\u0410\u043d\u0433\u0435\u043b\u0438\u043d\u0430"
    ],
    "name:spa_x_preferred":[
        "Angelina"
    ],
    "name:swe_x_preferred":[
        "Angelina"
    ],
    "name:tur_x_preferred":[
        "Angelina"
    ],
    "wof:name":"Angelina",
    "wof:placetype":"locality"
},
  "geometry": {"coordinates":[-75.88667,6.715],"type":"Point"}
}