{
  "type": "Feature",
  "properties": {
    "gn:admin1_code":"2.0",
    "gn:admin2_code":"5113.0",
    "gn:asciiname":"Angelina",
    "gn:country_code":"CO",
    "gn:dem":835,
    "gn:feature_class":"P",
    "gn:feature_code":"PPL",
    "gn:name":"Angelina",
    "gn:population":0,
    "gn:timezone":"America/Bogota",
    "iso:country":"CO",
    "wof:name":"Angelina",
    "wof:placetype":"locality"
},
  "geometry": {"coordinates":[-75.88667,6.715],"type":"Point"}
}