{
  "type": "Feature",
  "properties": {
    "gn:admin1_code":"36",
    "gn:admin2_code":"15183.0",
    "gn:asciiname":"El Encomendero",
    "gn:country_code":"CO",
    "gn:dem":2778,
    "gn:feature_class":"P",
    "gn:feature_code":"PPL",
    "gn:name":"El Encomendero",
    "gn:population":0,
    "gn:timezone":"America/Bogota",
    "iso:country":"CO",
    "wof:name":"El Encomendero",
    "wof:placetype":"locality"
},
  "geometry": {"coordinates":[-72.41086999999997,6.01007],"type":"Point"}
}