{
  "type": "Feature",
  "properties": {
    "gn:admin1_code":"9.0",
    "gn:admin2_code":"19256.0",
    "gn:asciiname":"Loma Bajo",
    "gn:country_code":"CO",
    "gn:dem":1251,
    "gn:feature_class":"P",
    "gn:feature_code":"PPL",
    "gn:name":"Loma Bajo",
    "gn:population":0,
    "gn:timezone":"America/Bogota",
    "iso:country":"CO",
    "wof:name":"Loma Bajo",
    "wof:placetype":"locality"
},
  "geometry": {"coordinates":[-76.80894000000001,2.25906],"type":"Point"}
}