{
  "type": "Feature",
  "properties": {
    "gn:admin1_code":"15.0",
    "gn:asciiname":"Boca Cano Mina",
    "gn:country_code":"CO",
    "gn:dem":116,
    "gn:feature_class":"P",
    "gn:feature_code":"PPL",
    "gn:name":"Boca Ca\u00f1o Mina",
    "gn:population":0,
    "gn:timezone":"America/Bogota",
    "iso:country":"CO",
    "wof:name":"Boca Cano Mina",
    "wof:placetype":"locality"
},
  "geometry": {"coordinates":[-69.79778,3.50806],"type":"Point"}
}