{
  "type": "Feature",
  "properties": {
    "gn:admin1_code":"38.0",
    "gn:admin2_code":"47555.0",
    "gn:asciiname":"Nocabes",
    "gn:country_code":"CO",
    "gn:dem":133,
    "gn:feature_class":"P",
    "gn:feature_code":"PPL",
    "gn:name":"Nocabes",
    "gn:population":0,
    "gn:timezone":"America/Bogota",
    "iso:country":"CO",
    "name:und_x_variant":[
        "Hacienda Nocabes",
        "Nocabes"
    ],
    "wof:name":"Nocabes",
    "wof:placetype":"locality"
},
  "geometry": {"coordinates":[-74.38897,9.97961],"type":"Point"}
}