{
  "type": "Feature",
  "properties": {
    "gn:admin1_code":"38",
    "gn:admin2_code":"47460.0",
    "gn:asciiname":"Altas Claras",
    "gn:country_code":"CO",
    "gn:dem":101,
    "gn:feature_class":"P",
    "gn:feature_code":"PPL",
    "gn:name":"Altas Claras",
    "gn:population":0,
    "gn:timezone":"America/Bogota",
    "iso:country":"CO",
    "wof:name":"Altas Claras",
    "wof:placetype":"locality"
},
  "geometry": {"coordinates":[-74.34793000000001,9.70991],"type":"Point"}
}