{
  "type": "Feature",
  "properties": {
    "gn:admin1_code":"33.0",
    "gn:admin2_code":"25320.0",
    "gn:asciiname":"Monte Corrales",
    "gn:country_code":"CO",
    "gn:dem":663,
    "gn:feature_class":"P",
    "gn:feature_code":"PPL",
    "gn:name":"Monte Corrales",
    "gn:population":0,
    "gn:timezone":"America/Bogota",
    "iso:country":"CO",
    "name:spa_x_preferred":[
        "Monte Corrales"
    ],
    "wof:name":"Monte Corrales",
    "wof:placetype":"locality"
},
  "geometry": {"coordinates":[-74.69391,5.31512],"type":"Point"}
}