{
  "type": "Feature",
  "properties": {
    "gn:admin1_code":"9",
    "gn:admin2_code":"19532.0",
    "gn:asciiname":"Las Tallas",
    "gn:country_code":"CO",
    "gn:dem":615,
    "gn:feature_class":"P",
    "gn:feature_code":"PPL",
    "gn:name":"Las Tallas",
    "gn:population":0,
    "gn:timezone":"America/Bogota",
    "iso:country":"CO",
    "wof:name":"Las Tallas",
    "wof:placetype":"locality"
},
  "geometry": {"coordinates":[-77.08547,2.1166],"type":"Point"}
}