{
  "type": "Feature",
  "properties": {
    "gn:admin1_code":"19",
    "gn:admin2_code":"50573.0",
    "gn:asciiname":"La Veguita",
    "gn:country_code":"CO",
    "gn:dem":159,
    "gn:feature_class":"P",
    "gn:feature_code":"PPL",
    "gn:name":"La Veguita",
    "gn:population":0,
    "gn:timezone":"America/Bogota",
    "iso:country":"CO",
    "wof:name":"La Veguita",
    "wof:placetype":"locality"
},
  "geometry": {"coordinates":[-72.22920999999999,4.43163],"type":"Point"}
}