{
  "type": "Feature",
  "properties": {
    "gn:country":"CO",
    "gn:fcode":"PPL",
    "gn:population":1448,
    "iso:country":"CO",
    "name:ceb_x_preferred":[
        "El Litoral del San Juan"
    ],
    "name:eng_x_preferred":[
        "Litoral del San Juan"
    ],
    "name:fas_x_preferred":[
        "\u0644\u06cc\u062a\u0648\u0631\u0627\u0644 \u062f\u0644 \u0633\u0646 \u062e\u0648\u0627\u0646"
    ],
    "name:fra_x_preferred":[
        "Litoral del San Juan"
    ],
    "name:gle_x_preferred":[
        "Litoral del San Juan"
    ],
    "name:ita_x_preferred":[
        "El Litoral del San Juan"
    ],
    "name:kat_x_preferred":[
        "\u10da\u10d8\u10e2\u10dd\u10e0\u10d0\u10da-\u10d3\u10d4\u10da-\u10e1\u10d0\u10dc\u10ee\u10e3\u10d0\u10dc\u10d8"
    ],
    "name:msa_x_preferred":[
        "Litoral del Sanju\u00e1n"
    ],
    "name:nan_x_preferred":[
        "Litoral del San Juan"
    ],
    "name:nld_x_preferred":[
        "Litoral de San Juan"
    ],
    "name:por_x_preferred":[
        "Litoral del Sanju\u00e1n"
    ],
    "name:sco_x_preferred":[
        "Litoral del Sanju\u00e1n"
    ],
    "name:spa_x_preferred":[
        "Litoral de San Juan"
    ],
    "name:swe_x_preferred":[
        "Santa Genoveva de Docorod\u00f3"
    ],
    "name:swe_x_variant":[
        "El Litoral del San Juan"
    ],
    "name:tgl_x_preferred":[
        "Litoral del Sanju\u00e1n"
    ],
    "name:vie_x_preferred":[
        "El Litoral del San Juan"
    ],
    "name:war_x_preferred":[
        "Litoral del Sanju\u00e1n"
    ],
    "name:zho_x_preferred":[
        "\u6ff1\u6d77\u8056\u80e1\u5b89"
    ],
    "qs:name":"Santa Genoveva de Docorod\u00f3",
    "qs:photos_9r":0,
    "qs:photos_sr":0,
    "qs:pop_sr":"3",
    "wof:name":"Santa Genoveva de Docorod\u00f3",
    "wof:placetype":"locality",
    "wof:population":1448
},
  "geometry": {"coordinates":[-77.36516,4.25875],"type":"Point"}
}