{
  "type": "Feature",
  "properties": {
    "gn:admin1_code":"17.0",
    "gn:admin2_code":"44847.0",
    "gn:asciiname":"Narap",
    "gn:country_code":"CO",
    "gn:dem":135,
    "gn:feature_class":"P",
    "gn:feature_code":"PPL",
    "gn:name":"Narap",
    "gn:population":0,
    "gn:timezone":"America/Bogota",
    "iso:country":"CO",
    "name:fas_x_preferred":[
        "\u0646\u0631\u0627\u067e"
    ],
    "wof:name":"Narap",
    "wof:placetype":"locality"
},
  "geometry": {"coordinates":[-71.64191,12.10972],"type":"Point"}
}