{
  "type": "Feature",
  "properties": {
    "gn:admin1_code":"33.0",
    "gn:admin2_code":"25293.0",
    "gn:asciiname":"La Providencia",
    "gn:country_code":"CO",
    "gn:dem":2119,
    "gn:feature_class":"P",
    "gn:feature_code":"PPL",
    "gn:name":"La Providencia",
    "gn:population":0,
    "gn:timezone":"America/Bogota",
    "iso:country":"CO",
    "wof:name":"La Providencia",
    "wof:placetype":"locality"
},
  "geometry": {"coordinates":[-73.59576,4.63433],"type":"Point"}
}