{
  "type": "Feature",
  "properties": {
    "gn:admin1_code":"22.0",
    "gn:admin2_code":"86885.0",
    "gn:asciiname":"El Cormen",
    "gn:country_code":"CO",
    "gn:dem":563,
    "gn:feature_class":"P",
    "gn:feature_code":"PPL",
    "gn:name":"El Cormen",
    "gn:population":0,
    "gn:timezone":"America/Bogota",
    "iso:country":"CO",
    "name:spa_x_preferred":[
        "El Cormen"
    ],
    "wof:name":"El Cormen",
    "wof:placetype":"locality"
},
  "geometry": {"coordinates":[-76.69291,0.9949],"type":"Point"}
}