{
  "type": "Feature",
  "properties": {
    "gn:admin1_code":"1.0",
    "gn:admin2_code":"91530.0",
    "gn:asciiname":"Reserva",
    "gn:country_code":"CO",
    "gn:dem":139,
    "gn:feature_class":"P",
    "gn:feature_code":"PPL",
    "gn:name":"Reserva",
    "gn:population":0,
    "gn:timezone":"America/Bogota",
    "iso:country":"CO",
    "wof:name":"Reserva",
    "wof:placetype":"locality"
},
  "geometry": {"coordinates":[-73.453,-1.24963],"type":"Point"}
}