{
  "type": "Feature",
  "properties": {
    "gn:admin1_code":"2.0",
    "gn:admin2_code":"5113.0",
    "gn:asciiname":"Mariscal",
    "gn:country_code":"CO",
    "gn:dem":1908,
    "gn:feature_class":"P",
    "gn:feature_code":"PPL",
    "gn:name":"Mariscal",
    "gn:population":0,
    "gn:timezone":"America/Bogota",
    "iso:country":"CO",
    "wof:name":"Mariscal",
    "wof:placetype":"locality"
},
  "geometry": {"coordinates":[-75.88389000000002,6.65972],"type":"Point"}
}