{
  "type": "Feature",
  "properties": {
    "gn:admin1_code":"3.0",
    "gn:admin2_code":"81300.0",
    "gn:asciiname":"Sinsiga",
    "gn:cc2":"CO",
    "gn:country_code":"CO",
    "gn:dem":3449,
    "gn:feature_class":"P",
    "gn:feature_code":"PPL",
    "gn:name":"Sinsiga",
    "gn:population":0,
    "gn:timezone":"America/Bogota",
    "iso:country":"CO",
    "name:und_x_variant":[
        "Sisiga",
        "Sisinga",
        "Sinsiga"
    ],
    "wof:name":"Sinsiga",
    "wof:placetype":"locality"
},
  "geometry": {"coordinates":[-72.08333,6.63333],"type":"Point"}
}