{
  "type": "Feature",
  "properties": {
    "gn:admin1_code":"36",
    "gn:admin2_code":"15632.0",
    "gn:asciiname":"El Corona",
    "gn:country_code":"CO",
    "gn:dem":2605,
    "gn:feature_class":"P",
    "gn:feature_code":"PPL",
    "gn:name":"El Corona",
    "gn:population":0,
    "gn:timezone":"America/Bogota",
    "iso:country":"CO",
    "wof:name":"El Corona",
    "wof:placetype":"locality"
},
  "geometry": {"coordinates":[-73.76805999999998,5.65694],"type":"Point"}
}