{
  "type": "Feature",
  "properties": {
    "gn:admin1_code":"10.0",
    "gn:admin2_code":"20001.0",
    "gn:asciiname":"Algodonera Los Llanos",
    "gn:country_code":"CO",
    "gn:dem":108,
    "gn:feature_class":"P",
    "gn:feature_code":"PPL",
    "gn:name":"Algodonera Los Llanos",
    "gn:population":0,
    "gn:timezone":"America/Bogota",
    "iso:country":"CO",
    "wof:name":"Algodonera Los Llanos",
    "wof:placetype":"locality"
},
  "geometry": {"coordinates":[-73.2945,10.34363],"type":"Point"}
}