{
  "type": "Feature",
  "properties": {
    "gn:admin1_code":"9.0",
    "gn:admin2_code":"19809.0",
    "gn:asciiname":"Jaragua",
    "gn:country_code":"CO",
    "gn:dem":36,
    "gn:feature_class":"P",
    "gn:feature_code":"PPL",
    "gn:name":"Jaragua",
    "gn:population":0,
    "gn:timezone":"America/Bogota",
    "iso:country":"CO",
    "wof:name":"Jaragua",
    "wof:placetype":"locality"
},
  "geometry": {"coordinates":[-77.65657,2.7868],"type":"Point"}
}