{
  "type": "Feature",
  "properties": {
    "gn:admin1_code":"33",
    "gn:admin2_code":"25372.0",
    "gn:asciiname":"Claraval",
    "gn:country_code":"CO",
    "gn:dem":2177,
    "gn:feature_class":"P",
    "gn:feature_code":"PPL",
    "gn:name":"Claraval",
    "gn:population":0,
    "gn:timezone":"America/Bogota",
    "iso:country":"CO",
    "name:bpy_x_preferred":[
        "\u0995\u09b2\u09be\u09b0\u09be\u09ad\u09be\u09b2"
    ],
    "name:ceb_x_preferred":[
        "Claraval"
    ],
    "name:epo_x_preferred":[
        "Claraval"
    ],
    "name:eus_x_preferred":[
        "Claraval"
    ],
    "name:fra_x_preferred":[
        "Claraval"
    ],
    "name:ita_x_preferred":[
        "Claraval"
    ],
    "name:kat_x_preferred":[
        "\u10d9\u10da\u10d0\u10e0\u10d0\u10d5\u10d0\u10da\u10d8"
    ],
    "name:kaz_x_preferred":[
        "\u041a\u043b\u0430\u0440\u0430\u0432\u0430\u043b"
    ],
    "name:mlg_x_preferred":[
        "Claraval"
    ],
    "name:nld_x_preferred":[
        "Claraval"
    ],
    "name:nor_x_preferred":[
        "Claraval"
    ],
    "name:pol_x_preferred":[
        "Claraval"
    ],
    "name:por_x_preferred":[
        "Claraval"
    ],
    "name:ron_x_preferred":[
        "Claraval"
    ],
    "name:rus_x_preferred":[
        "\u041a\u043b\u0430\u0440\u0430\u0432\u0430\u043b"
    ],
    "name:swe_x_preferred":[
        "Claraval"
    ],
    "name:vie_x_preferred":[
        "Claraval"
    ],
    "name:vol_x_preferred":[
        "Claraval"
    ],
    "name:war_x_preferred":[
        "Claraval"
    ],
    "name:zho_x_preferred":[
        "\u514b\u62c9\u62c9\u74e6\u5c14"
    ],
    "wof:name":"Claraval",
    "wof:placetype":"locality"
},
  "geometry": {"coordinates":[-73.63778000000001,4.65028],"type":"Point"}
}