{
  "type": "Feature",
  "properties": {
    "gn:admin1_code":"33.0",
    "gn:admin2_code":"25320.0",
    "gn:asciiname":"Alto El Morro",
    "gn:country_code":"CO",
    "gn:dem":849,
    "gn:feature_class":"P",
    "gn:feature_code":"PPL",
    "gn:name":"Alto El Morro",
    "gn:population":0,
    "gn:timezone":"America/Bogota",
    "iso:country":"CO",
    "name:spa_x_preferred":[
        "Alto El Morro"
    ],
    "wof:name":"Alto El Morro",
    "wof:placetype":"locality"
},
  "geometry": {"coordinates":[-74.56053,5.15466],"type":"Point"}
}