{
  "type": "Feature",
  "properties": {
    "gn:admin1_code":"28.0",
    "gn:admin2_code":"73616.0",
    "gn:asciiname":"Cruz Verede",
    "gn:country_code":"CO",
    "gn:dem":1373,
    "gn:feature_class":"P",
    "gn:feature_code":"PPL",
    "gn:name":"Cruz Verede",
    "gn:population":0,
    "gn:timezone":"America/Bogota",
    "iso:country":"CO",
    "wof:name":"Cruz Verede",
    "wof:placetype":"locality"
},
  "geometry": {"coordinates":[-75.60110999999998,3.53833],"type":"Point"}
}