{
  "type": "Feature",
  "properties": {
    "gn:admin1_code":"19.0",
    "gn:admin2_code":"50001.0",
    "gn:asciiname":"Portugal",
    "gn:country_code":"CO",
    "gn:dem":352,
    "gn:feature_class":"P",
    "gn:feature_code":"PPL",
    "gn:name":"Portugal",
    "gn:population":0,
    "gn:timezone":"America/Bogota",
    "iso:country":"CO",
    "wof:name":"Portugal",
    "wof:placetype":"locality"
},
  "geometry": {"coordinates":[-73.53333000000001,4.16667],"type":"Point"}
}