{
  "type": "Feature",
  "properties": {
    "gn:admin1_code":"28",
    "gn:admin2_code":"73873.0",
    "gn:asciiname":"El Porvenir",
    "gn:country_code":"CO",
    "gn:dem":1222,
    "gn:feature_class":"P",
    "gn:feature_code":"PPLL",
    "gn:name":"El Porvenir",
    "gn:population":0,
    "gn:timezone":"America/Bogota",
    "iso:country":"CO",
    "name:spa_x_preferred":[
        "El Porvenir"
    ],
    "wof:name":"El Porvenir",
    "wof:placetype":"locality"
},
  "geometry": {"coordinates":[-74.66320999999998,3.8638],"type":"Point"}
}