{
  "type": "Feature",
  "properties": {
    "gn:admin1_code":"14.0",
    "gn:admin2_code":"95001.0",
    "gn:asciiname":"Cano Dorado",
    "gn:country_code":"CO",
    "gn:dem":243,
    "gn:feature_class":"P",
    "gn:feature_code":"PPL",
    "gn:name":"Ca\u00f1o Dorado",
    "gn:population":0,
    "gn:timezone":"America/Bogota",
    "iso:country":"CO",
    "wof:name":"Cano Dorado",
    "wof:placetype":"locality"
},
  "geometry": {"coordinates":[-72.88409,2.39412],"type":"Point"}
}