{
  "type": "Feature",
  "properties": {
    "gn:admin1_code":"17",
    "gn:admin2_code":"44430.0",
    "gn:asciiname":"Atkusirro",
    "gn:country_code":"CO",
    "gn:dem":56,
    "gn:feature_class":"P",
    "gn:feature_code":"PPL",
    "gn:name":"Atkusirro",
    "gn:population":0,
    "gn:timezone":"America/Bogota",
    "iso:country":"CO",
    "wof:name":"Atkusirro",
    "wof:placetype":"locality"
},
  "geometry": {"coordinates":[-72.58179,11.43707],"type":"Point"}
}