{
  "type": "Feature",
  "properties": {
    "gn:admin1_code":"8",
    "gn:admin2_code":"18753.0",
    "gn:asciiname":"La Ceiba",
    "gn:country_code":"CO",
    "gn:dem":271,
    "gn:feature_class":"P",
    "gn:feature_code":"PPL",
    "gn:name":"La Ceiba",
    "gn:population":0,
    "gn:timezone":"America/Bogota",
    "iso:country":"CO",
    "name:spa_x_preferred":[
        "La Ceiba"
    ],
    "name:und_x_variant":[
        "La Ceibas"
    ],
    "wof:name":"La Ceiba",
    "wof:placetype":"locality"
},
  "geometry": {"coordinates":[-74.86750000000001,2.09417],"type":"Point"}
}