{
  "type": "Feature",
  "properties": {
    "gn:admin1_code":"38",
    "gn:admin2_code":"47258.0",
    "gn:asciiname":"Los Caballos",
    "gn:cc2":"CO",
    "gn:country_code":"CO",
    "gn:dem":25,
    "gn:feature_class":"P",
    "gn:feature_code":"PPL",
    "gn:name":"Los Caballos",
    "gn:population":0,
    "gn:timezone":"America/Bogota",
    "iso:country":"CO",
    "name:und_x_variant":[
        "Hacienda Los Caballos",
        "Los Caballos"
    ],
    "wof:name":"Los Caballos",
    "wof:placetype":"locality"
},
  "geometry": {"coordinates":[-74.63333,10.26667],"type":"Point"}
}