{
  "type": "Feature",
  "properties": {
    "gn:admin1_code":"2.0",
    "gn:admin2_code":"5284.0",
    "gn:asciiname":"Morron",
    "gn:country_code":"CO",
    "gn:dem":1497,
    "gn:feature_class":"P",
    "gn:feature_code":"PPL",
    "gn:name":"Morr\u00f3n",
    "gn:population":0,
    "gn:timezone":"America/Bogota",
    "iso:country":"CO",
    "wof:name":"Morron",
    "wof:placetype":"locality"
},
  "geometry": {"coordinates":[-76.25528,6.67889],"type":"Point"}
}