{
  "type": "Feature",
  "properties": {
    "gn:admin1_code":"38",
    "gn:admin2_code":"47551.0",
    "gn:asciiname":"Leticia",
    "gn:country_code":"CO",
    "gn:dem":64,
    "gn:feature_class":"P",
    "gn:feature_code":"PPL",
    "gn:name":"Leticia",
    "gn:population":0,
    "gn:timezone":"America/Bogota",
    "iso:country":"CO",
    "name:bre_x_preferred":[
        "Leticia"
    ],
    "name:ceb_x_preferred":[
        "Leticia"
    ],
    "name:deu_x_preferred":[
        "Laetitia"
    ],
    "name:fra_x_preferred":[
        "L\u00e6titia"
    ],
    "name:hat_x_preferred":[
        "Laetitia"
    ],
    "name:hun_x_preferred":[
        "Let\u00edcia"
    ],
    "name:ita_x_preferred":[
        "Letizia"
    ],
    "name:nld_x_preferred":[
        "Laetitia"
    ],
    "name:pol_x_preferred":[
        "Letycja"
    ],
    "name:por_x_preferred":[
        "Let\u00edcia"
    ],
    "name:ron_x_preferred":[
        "Leticia"
    ],
    "name:rus_x_preferred":[
        "\u041b\u0435\u0442\u0438\u0441\u0438\u044f"
    ],
    "name:spa_x_preferred":[
        "Leticia"
    ],
    "wof:name":"Leticia",
    "wof:placetype":"locality"
},
  "geometry": {"coordinates":[-74.46483000000001,10.36722],"type":"Point"}
}