{
  "type": "Feature",
  "properties": {
    "gn:admin1_code":"16.0",
    "gn:asciiname":"Las Torres",
    "gn:country_code":"CO",
    "gn:dem":632,
    "gn:feature_class":"P",
    "gn:feature_code":"PPL",
    "gn:name":"Las Torres",
    "gn:population":0,
    "gn:timezone":"America/Bogota",
    "iso:country":"CO",
    "name:spa_x_preferred":[
        "Las Torres"
    ],
    "wof:name":"Las Torres",
    "wof:placetype":"locality"
},
  "geometry": {"coordinates":[-74.88745,3.30831],"type":"Point"}
}