{
  "type": "Feature",
  "properties": {
    "gn:admin1_code":"19",
    "gn:admin2_code":"50568.0",
    "gn:asciiname":"El Algarrobo",
    "gn:country_code":"CO",
    "gn:dem":155,
    "gn:feature_class":"P",
    "gn:feature_code":"PPL",
    "gn:name":"El Algarrobo",
    "gn:population":0,
    "gn:timezone":"America/Bogota",
    "iso:country":"CO",
    "wof:name":"El Algarrobo",
    "wof:placetype":"locality"
},
  "geometry": {"coordinates":[-72.07424,4.27384],"type":"Point"}
}