{
  "type": "Feature",
  "properties": {
    "gn:admin1_code":"10.0",
    "gn:admin2_code":"20001.0",
    "gn:asciiname":"Hacienda El Cano",
    "gn:country_code":"CO",
    "gn:dem":103,
    "gn:feature_class":"P",
    "gn:feature_code":"PPL",
    "gn:name":"Hacienda El Ca\u00f1o",
    "gn:population":0,
    "gn:timezone":"America/Bogota",
    "iso:country":"CO",
    "wof:name":"Hacienda El Cano",
    "wof:placetype":"locality"
},
  "geometry": {"coordinates":[-73.26751999999998,10.25825],"type":"Point"}
}