{
  "type": "Feature",
  "properties": {
    "gn:admin1_code":"19",
    "gn:admin2_code":"50370.0",
    "gn:asciiname":"La Caucha",
    "gn:country_code":"CO",
    "gn:dem":1751,
    "gn:feature_class":"P",
    "gn:feature_code":"PPL",
    "gn:name":"La Caucha",
    "gn:population":0,
    "gn:timezone":"America/Bogota",
    "iso:country":"CO",
    "name:spa_x_preferred":[
        "La Caucha"
    ],
    "wof:name":"La Caucha",
    "wof:placetype":"locality"
},
  "geometry": {"coordinates":[-74.37036999999999,3.54743],"type":"Point"}
}