{
  "type": "Feature",
  "properties": {
    "gn:admin1_code":"2.0",
    "gn:admin2_code":"5093.0",
    "gn:asciiname":"Morito",
    "gn:country_code":"CO",
    "gn:dem":1035,
    "gn:feature_class":"P",
    "gn:feature_code":"PPL",
    "gn:name":"Morito",
    "gn:population":0,
    "gn:timezone":"America/Bogota",
    "iso:country":"CO",
    "wof:name":"Morito",
    "wof:placetype":"locality"
},
  "geometry": {"coordinates":[-75.86667,6.16667],"type":"Point"}
}