{
  "type": "Feature",
  "properties": {
    "gn:admin1_code":"4.0",
    "gn:admin2_code":"8001.0",
    "gn:asciiname":"Villa Nueva",
    "gn:country_code":"CO",
    "gn:dem":6,
    "gn:feature_class":"P",
    "gn:feature_code":"PPL",
    "gn:name":"Villa Nueva",
    "gn:population":0,
    "gn:timezone":"America/Bogota",
    "iso:country":"CO",
    "wof:name":"Villa Nueva",
    "wof:placetype":"locality"
},
  "geometry": {"coordinates":[-74.76374,10.97986],"type":"Point"}
}