{
  "type": "Feature",
  "properties": {
    "gn:admin1_code":"8",
    "gn:admin2_code":"18860.0",
    "gn:asciiname":"Playa Rica",
    "gn:country_code":"CO",
    "gn:dem":236,
    "gn:feature_class":"P",
    "gn:feature_code":"PPL",
    "gn:name":"Playa Rica",
    "gn:population":0,
    "gn:timezone":"America/Bogota",
    "iso:country":"CO",
    "name:spa_x_preferred":[
        "Playa Rica"
    ],
    "wof:name":"Playa Rica",
    "wof:placetype":"locality"
},
  "geometry": {"coordinates":[-75.59629,1.06996],"type":"Point"}
}