{
  "type": "Feature",
  "properties": {
    "gn:admin1_code":"16.0",
    "gn:admin2_code":"41206.0",
    "gn:asciiname":"La Argentina",
    "gn:country_code":"CO",
    "gn:dem":2053,
    "gn:feature_class":"P",
    "gn:feature_code":"PPL",
    "gn:name":"La Argentina",
    "gn:population":0,
    "gn:timezone":"America/Bogota",
    "iso:country":"CO",
    "name:ceb_x_preferred":[
        "La Argentina"
    ],
    "name:deu_x_preferred":[
        "La Argentina"
    ],
    "name:fra_x_preferred":[
        "La Argentina"
    ],
    "name:ita_x_preferred":[
        "La Argentina"
    ],
    "name:spa_x_preferred":[
        "La Argentina"
    ],
    "name:swe_x_preferred":[
        "La Argentina"
    ],
    "name:tur_x_preferred":[
        "La Argentina"
    ],
    "wof:name":"La Argentina",
    "wof:placetype":"locality"
},
  "geometry": {"coordinates":[-74.7325,3.24472],"type":"Point"}
}