{
  "type": "Feature",
  "properties": {
    "gn:admin1_code":"29.0",
    "gn:admin2_code":"76403.0",
    "gn:asciiname":"Matazarza",
    "gn:country_code":"CO",
    "gn:dem":935,
    "gn:feature_class":"P",
    "gn:feature_code":"PPL",
    "gn:name":"Matazarza",
    "gn:population":0,
    "gn:timezone":"America/Bogota",
    "iso:country":"CO",
    "wof:name":"Matazarza",
    "wof:placetype":"locality"
},
  "geometry": {"coordinates":[-76.00333000000001,4.4925],"type":"Point"}
}