{
  "type": "Feature",
  "properties": {
    "gn:admin1_code":"16.0",
    "gn:admin2_code":"41244.0",
    "gn:asciiname":"La Aguada",
    "gn:country_code":"CO",
    "gn:dem":1362,
    "gn:feature_class":"P",
    "gn:feature_code":"PPL",
    "gn:name":"La Aguada",
    "gn:population":0,
    "gn:timezone":"America/Bogota",
    "iso:country":"CO",
    "name:spa_x_preferred":[
        "La Aguada"
    ],
    "wof:name":"La Aguada",
    "wof:placetype":"locality"
},
  "geometry": {"coordinates":[-75.95544,2.01617],"type":"Point"}
}