{
  "type": "Feature",
  "properties": {
    "gn:admin1_code":"36",
    "gn:admin2_code":"15469.0",
    "gn:asciiname":"Monserate",
    "gn:country_code":"CO",
    "gn:dem":2002,
    "gn:feature_class":"P",
    "gn:feature_code":"PPL",
    "gn:name":"Monserate",
    "gn:population":0,
    "gn:timezone":"America/Bogota",
    "iso:country":"CO",
    "wof:name":"Monserate",
    "wof:placetype":"locality"
},
  "geometry": {"coordinates":[-73.58610999999998,5.80611],"type":"Point"}
}