{
  "type": "Feature",
  "properties": {
    "gn:admin1_code":"2.0",
    "gn:admin2_code":"5113.0",
    "gn:asciiname":"La Fonda",
    "gn:country_code":"CO",
    "gn:dem":2287,
    "gn:feature_class":"P",
    "gn:feature_code":"PPL",
    "gn:name":"La Fonda",
    "gn:population":0,
    "gn:timezone":"America/Bogota",
    "iso:country":"CO",
    "wof:name":"La Fonda",
    "wof:placetype":"locality"
},
  "geometry": {"coordinates":[-75.91306,6.965],"type":"Point"}
}