{
  "type": "Feature",
  "properties": {
    "gn:admin1_code":"2",
    "gn:admin2_code":"5138.0",
    "gn:asciiname":"Lona de Goez",
    "gn:cc2":"CO",
    "gn:country_code":"CO",
    "gn:dem":1040,
    "gn:feature_class":"P",
    "gn:feature_code":"PPL",
    "gn:name":"Lona de Goez",
    "gn:population":0,
    "gn:timezone":"America/Bogota",
    "iso:country":"CO",
    "name:und_x_variant":[
        "Lona de Goes",
        "Lona de Goez"
    ],
    "wof:name":"Lona de Goez",
    "wof:placetype":"locality"
},
  "geometry": {"coordinates":[-76.06667,6.81667],"type":"Point"}
}