{
  "type": "Feature",
  "properties": {
    "gn:admin1_code":"26",
    "gn:admin2_code":"68101.0",
    "gn:asciiname":"Seccion Gaital",
    "gn:country_code":"CO",
    "gn:dem":3032,
    "gn:feature_class":"P",
    "gn:feature_code":"PPL",
    "gn:name":"Secc\u00edon Gaital",
    "gn:population":0,
    "gn:timezone":"America/Bogota",
    "iso:country":"CO",
    "wof:name":"Seccion Gaital",
    "wof:placetype":"locality"
},
  "geometry": {"coordinates":[-73.80722,5.98806],"type":"Point"}
}