{
  "type": "Feature",
  "properties": {
    "iso:country":"CO",
    "name:ast_x_preferred":[
        "La Plata"
    ],
    "name:ceb_x_preferred":[
        "La Plata"
    ],
    "name:deu_x_preferred":[
        "La Plata"
    ],
    "name:eng_x_preferred":[
        "La Plata"
    ],
    "name:fas_x_preferred":[
        "\u0644\u0627 \u067e\u0644\u0627\u062a\u0627\u060c \u0627\u0648\u06cc\u0644\u0627"
    ],
    "name:fas_x_variant":[
        "\u0644\u0627 \u067e\u0644\u0627\u062a\u0627"
    ],
    "name:fra_x_preferred":[
        "La Plata"
    ],
    "name:ita_x_preferred":[
        "La Plata"
    ],
    "name:jpn_x_preferred":[
        "\u30e9\u30fb\u30d7\u30e9\u30bf"
    ],
    "name:kat_x_preferred":[
        "\u10da\u10d0-\u10de\u10da\u10d0\u10e2\u10d0"
    ],
    "name:msa_x_preferred":[
        "La Plata"
    ],
    "name:nan_x_preferred":[
        "La Plata"
    ],
    "name:nld_x_preferred":[
        "La Plata"
    ],
    "name:por_x_preferred":[
        "La Plata"
    ],
    "name:spa_x_preferred":[
        "La Plata"
    ],
    "name:swe_x_preferred":[
        "La Plata"
    ],
    "name:tgl_x_preferred":[
        "La Plata"
    ],
    "name:urd_x_preferred":[
        "\u0644\u0627 \u067e\u0644\u0627\u0679\u0627\u060c \u06c1\u0648\u06cc\u0644\u0627"
    ],
    "name:urd_x_variant":[
        "\u0644\u0627 \u067e\u0644\u0627\u0679\u0627"
    ],
    "name:war_x_preferred":[
        "La Plata"
    ],
    "name:zho_min_nan_x_preferred":[
        "La Plata"
    ],
    "name:zho_x_preferred":[
        "\u62c9\u666e\u62c9\u5854"
    ],
    "qs:gn_country":"CO",
    "qs:gn_fcode":"PPL",
    "qs:gn_pop":19275,
    "qs:name":"La Plata",
    "qs:name_adm0":"Colombia",
    "qs:name_adm1":"Huila",
    "qs:photos":82,
    "qs:photos_1k":17,
    "qs:photos_9k":1,
    "qs:photos_9r":3,
    "qs:photos_all":82,
    "qs:photos_sr":3,
    "qs:placetype":"Town",
    "qs:pop_sr":"6",
    "qs:woe_adm0":23424787,
    "wd:wordcount":1172,
    "wof:name":"La Plata",
    "wof:placetype":"locality",
    "wof:population":19275
},
  "geometry": {"coordinates":[-75.89232,2.39341],"type":"Point"}
}