{
  "type": "Feature",
  "properties": {
    "gn:admin1_code":"12",
    "gn:admin2_code":"23675.0",
    "gn:asciiname":"Las Canas",
    "gn:country_code":"CO",
    "gn:dem":5,
    "gn:feature_class":"P",
    "gn:feature_code":"PPL",
    "gn:name":"Las Ca\u00f1as",
    "gn:population":0,
    "gn:timezone":"America/Bogota",
    "iso:country":"CO",
    "wof:name":"Las Canas",
    "wof:placetype":"locality"
},
  "geometry": {"coordinates":[-75.95910000000001,9.28752],"type":"Point"}
}