{
  "type": "Feature",
  "properties": {
    "gn:admin1_code":"29.0",
    "gn:admin2_code":"76001.0",
    "gn:asciiname":"Gualanday",
    "gn:country_code":"CO",
    "gn:dem":1367,
    "gn:feature_class":"P",
    "gn:feature_code":"PPL",
    "gn:name":"Gualanday",
    "gn:population":0,
    "gn:timezone":"America/Bogota",
    "iso:country":"CO",
    "name:spa_x_preferred":[
        "Gualanday"
    ],
    "wof:name":"Gualanday",
    "wof:placetype":"locality"
},
  "geometry": {"coordinates":[-76.59539000000002,3.40515],"type":"Point"}
}