{
  "type": "Feature",
  "properties": {
    "gn:admin1_code":"2.0",
    "gn:admin2_code":"5147.0",
    "gn:asciiname":"La Cabana dos",
    "gn:country_code":"CO",
    "gn:dem":30,
    "gn:feature_class":"P",
    "gn:feature_code":"PPL",
    "gn:name":"La Caba\u00f1a dos",
    "gn:population":0,
    "gn:timezone":"America/Bogota",
    "iso:country":"CO",
    "wof:name":"La Cabana dos",
    "wof:placetype":"locality"
},
  "geometry": {"coordinates":[-76.68083,7.78],"type":"Point"}
}