{
  "type": "Feature",
  "properties": {
    "gn:admin1_code":"16.0",
    "gn:admin2_code":"41013.0",
    "gn:asciiname":"Victor F. Silva",
    "gn:country_code":"CO",
    "gn:dem":734,
    "gn:feature_class":"P",
    "gn:feature_code":"PPL",
    "gn:name":"V\u00edctor F. Silva",
    "gn:population":0,
    "gn:timezone":"America/Bogota",
    "iso:country":"CO",
    "wof:name":"Victor F. Silva",
    "wof:placetype":"locality"
},
  "geometry": {"coordinates":[-75.69595,2.23203],"type":"Point"}
}