{
  "type": "Feature",
  "properties": {
    "gn:admin1_code":"17.0",
    "gn:admin2_code":"44847.0",
    "gn:asciiname":"Sauainraruhu",
    "gn:country_code":"CO",
    "gn:dem":32,
    "gn:feature_class":"P",
    "gn:feature_code":"PPL",
    "gn:name":"Sauainraruhu",
    "gn:population":0,
    "gn:timezone":"America/Bogota",
    "iso:country":"CO",
    "wof:name":"Sauainraruhu",
    "wof:placetype":"locality"
},
  "geometry": {"coordinates":[-72.25083000000002,11.655],"type":"Point"}
}