{
  "type": "Feature",
  "properties": {
    "gn:admin1_code":"36",
    "gn:admin2_code":"15531.0",
    "gn:asciiname":"El Panal",
    "gn:country_code":"CO",
    "gn:dem":2626,
    "gn:feature_class":"P",
    "gn:feature_code":"PPL",
    "gn:name":"El Panal",
    "gn:population":0,
    "gn:timezone":"America/Bogota",
    "iso:country":"CO",
    "wof:name":"El Panal",
    "wof:placetype":"locality"
},
  "geometry": {"coordinates":[-73.92778,5.59111],"type":"Point"}
}