{
  "type": "Feature",
  "properties": {
    "gn:admin1_code":"9.0",
    "gn:admin2_code":"19809.0",
    "gn:asciiname":"Zocabon",
    "gn:country_code":"CO",
    "gn:dem":15,
    "gn:feature_class":"P",
    "gn:feature_code":"PPL",
    "gn:name":"Zocab\u00f3n",
    "gn:population":0,
    "gn:timezone":"America/Bogota",
    "iso:country":"CO",
    "name:und_x_variant":[
        "Zocab\u00e1n",
        "Zocab\u00f3n"
    ],
    "wof:name":"Zocabon",
    "wof:placetype":"locality"
},
  "geometry": {"coordinates":[-77.72009,2.72702],"type":"Point"}
}