{
  "type": "Feature",
  "properties": {
    "gn:admin1_code":"16",
    "gn:admin2_code":"41676.0",
    "gn:asciiname":"El Peru",
    "gn:country_code":"CO",
    "gn:dem":1280,
    "gn:feature_class":"P",
    "gn:feature_code":"PPL",
    "gn:name":"El Per\u00fa",
    "gn:population":0,
    "gn:timezone":"America/Bogota",
    "iso:country":"CO",
    "wof:name":"El Peru",
    "wof:placetype":"locality"
},
  "geometry": {"coordinates":[-75.5425,2.91972],"type":"Point"}
}