{
  "type": "Feature",
  "properties": {
    "gn:admin1_code":"27",
    "gn:admin2_code":"70124.0",
    "gn:asciiname":"Los Cayitos",
    "gn:country_code":"CO",
    "gn:dem":39,
    "gn:feature_class":"P",
    "gn:feature_code":"PPL",
    "gn:name":"Los Cayitos",
    "gn:population":0,
    "gn:timezone":"America/Bogota",
    "iso:country":"CO",
    "name:und_x_variant":[
        "Caser\u00edo Los Cayitos",
        "Los Cayitos"
    ],
    "wof:name":"Los Cayitos",
    "wof:placetype":"locality"
},
  "geometry": {"coordinates":[-75.13200000000001,8.85701],"type":"Point"}
}