{
  "type": "Feature",
  "properties": {
    "gn:admin1_code":"26.0",
    "gn:admin2_code":"68689.0",
    "gn:asciiname":"Yarima",
    "gn:country_code":"CO",
    "gn:dem":167,
    "gn:feature_class":"P",
    "gn:feature_code":"PPL",
    "gn:name":"Yarima",
    "gn:population":0,
    "gn:timezone":"America/Bogota",
    "iso:country":"CO",
    "wof:name":"Yarima",
    "wof:placetype":"locality"
},
  "geometry": {"coordinates":[-73.71477,6.83373],"type":"Point"}
}