{
  "type": "Feature",
  "properties": {
    "gn:admin1_code":"9",
    "gn:admin2_code":"19256.0",
    "gn:asciiname":"La Empresa",
    "gn:country_code":"CO",
    "gn:dem":1787,
    "gn:feature_class":"P",
    "gn:feature_code":"PPL",
    "gn:name":"La Empresa",
    "gn:population":0,
    "gn:timezone":"America/Bogota",
    "iso:country":"CO",
    "wof:name":"La Empresa",
    "wof:placetype":"locality"
},
  "geometry": {"coordinates":[-76.85061,2.60424],"type":"Point"}
}