{
  "type": "Feature",
  "properties": {
    "gn:admin1_code":"9",
    "gn:admin2_code":"19450.0",
    "gn:asciiname":"Los Nacederos",
    "gn:country_code":"CO",
    "gn:dem":720,
    "gn:feature_class":"P",
    "gn:feature_code":"PPL",
    "gn:name":"Los Nacederos",
    "gn:population":0,
    "gn:timezone":"America/Bogota",
    "iso:country":"CO",
    "wof:name":"Los Nacederos",
    "wof:placetype":"locality"
},
  "geometry": {"coordinates":[-77.27083,1.78083],"type":"Point"}
}