{
  "type": "Feature",
  "properties": {
    "gn:admin1_code":"9",
    "gn:admin2_code":"19130.0",
    "gn:asciiname":"La Pedregosa",
    "gn:country_code":"CO",
    "gn:dem":1693,
    "gn:feature_class":"P",
    "gn:feature_code":"PPL",
    "gn:name":"La Pedregosa",
    "gn:population":0,
    "gn:timezone":"America/Bogota",
    "iso:country":"CO",
    "wof:name":"La Pedregosa",
    "wof:placetype":"locality"
},
  "geometry": {"coordinates":[-76.65408000000002,2.69154],"type":"Point"}
}