{
  "type": "Feature",
  "properties": {
    "gn:admin1_code":"32",
    "gn:admin2_code":"85001.0",
    "gn:asciiname":"La Fruta",
    "gn:country_code":"CO",
    "gn:dem":1006,
    "gn:feature_class":"P",
    "gn:feature_code":"PPL",
    "gn:name":"La Fruta",
    "gn:population":0,
    "gn:timezone":"America/Bogota",
    "iso:country":"CO",
    "wof:name":"La Fruta",
    "wof:placetype":"locality"
},
  "geometry": {"coordinates":[-72.39915999999999,5.50585],"type":"Point"}
}