{
  "type": "Feature",
  "properties": {
    "gn:admin1_code":"28",
    "gn:admin2_code":"73622.0",
    "gn:asciiname":"San Carlos",
    "gn:country_code":"CO",
    "gn:dem":2415,
    "gn:feature_class":"P",
    "gn:feature_code":"PPL",
    "gn:name":"San Carlos",
    "gn:population":0,
    "gn:timezone":"America/Bogota",
    "iso:country":"CO",
    "wof:name":"San Carlos",
    "wof:placetype":"locality"
},
  "geometry": {"coordinates":[-75.57333,4.02583],"type":"Point"}
}