{
  "type": "Feature",
  "properties": {
    "gn:admin1_code":"20",
    "gn:admin2_code":"52473.0",
    "gn:asciiname":"Barrerita",
    "gn:country_code":"CO",
    "gn:dem":0,
    "gn:feature_class":"P",
    "gn:feature_code":"PPL",
    "gn:name":"Barrerita",
    "gn:population":0,
    "gn:timezone":"America/Bogota",
    "iso:country":"CO",
    "wof:name":"Barrerita",
    "wof:placetype":"locality"
},
  "geometry": {"coordinates":[-78.55,2.45],"type":"Point"}
}