{
  "type": "Feature",
  "properties": {
    "gn:admin1_code":"36",
    "gn:admin2_code":"15507.0",
    "gn:asciiname":"Los Micos",
    "gn:country_code":"CO",
    "gn:dem":919,
    "gn:feature_class":"P",
    "gn:feature_code":"PPL",
    "gn:name":"Los Micos",
    "gn:population":0,
    "gn:timezone":"America/Bogota",
    "iso:country":"CO",
    "wof:name":"Los Micos",
    "wof:placetype":"locality"
},
  "geometry": {"coordinates":[-74.28494999999999,5.7674],"type":"Point"}
}