{
  "type": "Feature",
  "properties": {
    "gn:admin1_code":"33.0",
    "gn:admin2_code":"25322.0",
    "gn:asciiname":"Camargo",
    "gn:country_code":"CO",
    "gn:dem":3156,
    "gn:feature_class":"P",
    "gn:feature_code":"PPL",
    "gn:name":"Camargo",
    "gn:population":0,
    "gn:timezone":"America/Bogota",
    "iso:country":"CO",
    "wof:name":"Camargo",
    "wof:placetype":"locality"
},
  "geometry": {"coordinates":[-73.87246,4.78284],"type":"Point"}
}