{
  "type": "Feature",
  "properties": {
    "gn:admin1_code":"33.0",
    "gn:admin2_code":"25322.0",
    "gn:asciiname":"Camargo",
    "gn:country_code":"CO",
    "gn:dem":3156,
    "gn:feature_class":"P",
    "gn:feature_code":"PPL",
    "gn:name":"Camargo",
    "gn:population":0,
    "gn:timezone":"America/Bogota",
    "iso:country":"CO",
    "name:cat_x_preferred":[
        "Camargo"
    ],
    "name:ceb_x_preferred":[
        "Camargo"
    ],
    "name:deu_x_preferred":[
        "Camargo"
    ],
    "name:epo_x_preferred":[
        "Camargo"
    ],
    "name:fin_x_preferred":[
        "Camargo"
    ],
    "name:fra_x_preferred":[
        "Camargo"
    ],
    "name:glg_x_preferred":[
        "Camargo"
    ],
    "name:ita_x_preferred":[
        "Camargo"
    ],
    "name:jpn_x_preferred":[
        "\u30ab\u30de\u30eb\u30b4"
    ],
    "name:kor_x_preferred":[
        "\uce74\ub9c8\ub974\uace0"
    ],
    "name:nld_x_preferred":[
        "Camargo"
    ],
    "name:pol_x_preferred":[
        "Camargo"
    ],
    "name:por_x_preferred":[
        "Camargo"
    ],
    "name:rus_x_preferred":[
        "\u041a\u0430\u043c\u0430\u0440\u0433\u043e"
    ],
    "name:sco_x_preferred":[
        "Camargo"
    ],
    "name:spa_x_preferred":[
        "Camargo"
    ],
    "name:srp_x_preferred":[
        "\u041a\u0430\u043c\u0430\u0440\u0433\u043e"
    ],
    "name:swe_x_preferred":[
        "Camargo"
    ],
    "name:ukr_x_preferred":[
        "\u041a\u0430\u043c\u0430\u0440\u0433\u043e"
    ],
    "name:vie_x_preferred":[
        "Camargo"
    ],
    "name:vol_x_preferred":[
        "Camargo"
    ],
    "name:war_x_preferred":[
        "Camargo"
    ],
    "wof:name":"Camargo",
    "wof:placetype":"locality"
},
  "geometry": {"coordinates":[-73.87246,4.78284],"type":"Point"}
}