{
  "type": "Feature",
  "properties": {
    "gn:admin1_code":"33.0",
    "gn:admin2_code":"25322.0",
    "gn:asciiname":"Camargo",
    "gn:country_code":"CO",
    "gn:dem":3156,
    "gn:feature_class":"P",
    "gn:feature_code":"PPL",
    "gn:name":"Camargo",
    "gn:population":0,
    "gn:timezone":"America/Bogota",
    "iso:country":"CO",
    "name:ben_x_preferred":[
        "\u0995\u09be\u09ae\u09be\u09b0\u0997\u09cb"
    ],
    "name:cat_x_preferred":[
        "Camargo"
    ],
    "name:ceb_x_preferred":[
        "Camargo"
    ],
    "name:deu_x_preferred":[
        "Camargo"
    ],
    "name:ell_x_preferred":[
        "\u039a\u03b1\u03bc\u03ac\u03c1\u03b3\u03ba\u03bf"
    ],
    "name:epo_x_preferred":[
        "Camargo"
    ],
    "name:fas_x_preferred":[
        "\u06a9\u0627\u0645\u0627\u0631\u06af\u0648"
    ],
    "name:fin_x_preferred":[
        "Camargo"
    ],
    "name:fra_x_preferred":[
        "Camargo"
    ],
    "name:glg_x_preferred":[
        "Camargo"
    ],
    "name:heb_x_preferred":[
        "\u05e7\u05de\u05e8\u05d2\u05d5"
    ],
    "name:hin_x_preferred":[
        "\u0915\u092e\u093e\u0930\u094d\u0917\u094b"
    ],
    "name:hun_x_preferred":[
        "Camargo"
    ],
    "name:ind_x_preferred":[
        "Camargo"
    ],
    "name:ita_x_preferred":[
        "Camargo"
    ],
    "name:jpn_x_preferred":[
        "\u30ab\u30de\u30eb\u30b4"
    ],
    "name:kor_x_preferred":[
        "\uce74\ub9c8\ub974\uace0"
    ],
    "name:nld_x_preferred":[
        "Camargo"
    ],
    "name:pol_x_preferred":[
        "Camargo"
    ],
    "name:por_x_preferred":[
        "Camargo"
    ],
    "name:rus_x_preferred":[
        "\u041a\u0430\u043c\u0430\u0440\u0433\u043e"
    ],
    "name:sco_x_preferred":[
        "Camargo"
    ],
    "name:spa_x_preferred":[
        "Camargo"
    ],
    "name:srp_x_preferred":[
        "\u041a\u0430\u043c\u0430\u0440\u0433\u043e"
    ],
    "name:swe_x_preferred":[
        "Camargo"
    ],
    "name:tur_x_preferred":[
        "Camargo"
    ],
    "name:ukr_x_preferred":[
        "\u041a\u0430\u043c\u0430\u0440\u0433\u043e"
    ],
    "name:urd_x_preferred":[
        "\u06a9\u06cc\u0645\u0627\u0631\u06af\u0648"
    ],
    "name:vie_x_preferred":[
        "Camargo"
    ],
    "name:vol_x_preferred":[
        "Camargo"
    ],
    "name:war_x_preferred":[
        "Camargo"
    ],
    "wof:name":"Camargo",
    "wof:placetype":"locality"
},
  "geometry": {"coordinates":[-73.87246,4.78284],"type":"Point"}
}