{
  "type": "Feature",
  "properties": {
    "gn:admin1_code":"36",
    "gn:admin2_code":"15676.0",
    "gn:asciiname":"El Naranito",
    "gn:country_code":"CO",
    "gn:dem":2574,
    "gn:feature_class":"P",
    "gn:feature_code":"PPL",
    "gn:name":"El Naranito",
    "gn:population":0,
    "gn:timezone":"America/Bogota",
    "iso:country":"CO",
    "wof:name":"El Naranito",
    "wof:placetype":"locality"
},
  "geometry": {"coordinates":[-73.73860999999999,5.52583],"type":"Point"}
}