{
  "type": "Feature",
  "properties": {
    "gn:admin1_code":"24.0",
    "gn:admin2_code":"66456.0",
    "gn:asciiname":"Risaralda",
    "gn:country_code":"CO",
    "gn:dem":2483,
    "gn:feature_class":"P",
    "gn:feature_code":"PPL",
    "gn:name":"Risaralda",
    "gn:population":0,
    "gn:timezone":"America/Bogota",
    "iso:country":"CO",
    "name:ceb_x_preferred":[
        "Risaralda"
    ],
    "name:ita_x_preferred":[
        "Risaralda"
    ],
    "name:nld_x_preferred":[
        "Risaralda"
    ],
    "name:spa_x_preferred":[
        "Risaralda"
    ],
    "wof:name":"Risaralda",
    "wof:placetype":"locality"
},
  "geometry": {"coordinates":[-75.85611,5.48333],"type":"Point"}
}