{
  "type": "Feature",
  "properties": {
    "gn:admin1_code":"28",
    "gn:admin2_code":"73168.0",
    "gn:asciiname":"Balsora",
    "gn:country_code":"CO",
    "gn:dem":2749,
    "gn:feature_class":"P",
    "gn:feature_code":"PPL",
    "gn:name":"Balsora",
    "gn:population":0,
    "gn:timezone":"America/Bogota",
    "iso:country":"CO",
    "wof:name":"Balsora",
    "wof:placetype":"locality"
},
  "geometry": {"coordinates":[-75.64166999999998,3.88611],"type":"Point"}
}