{
  "type": "Feature",
  "properties": {
    "gn:admin1_code":"12",
    "gn:admin2_code":"23672.0",
    "gn:asciiname":"Amaya",
    "gn:country_code":"CO",
    "gn:dem":6,
    "gn:feature_class":"P",
    "gn:feature_code":"PPL",
    "gn:name":"Amaya",
    "gn:population":0,
    "gn:timezone":"America/Bogota",
    "iso:country":"CO",
    "name:und_x_variant":[
        "Hacienda Amaya",
        "Amaya"
    ],
    "wof:name":"Amaya",
    "wof:placetype":"locality"
},
  "geometry": {"coordinates":[-75.77131,9.39343],"type":"Point"}
}