{
  "type": "Feature",
  "properties": {
    "gn:admin1_code":"9",
    "gn:admin2_code":"19130.0",
    "gn:asciiname":"Planadas",
    "gn:country_code":"CO",
    "gn:dem":1725,
    "gn:feature_class":"P",
    "gn:feature_code":"PPL",
    "gn:name":"Planadas",
    "gn:population":0,
    "gn:timezone":"America/Bogota",
    "iso:country":"CO",
    "name:ceb_x_preferred":[
        "Planadas"
    ],
    "name:deu_x_preferred":[
        "Planadas"
    ],
    "name:fas_x_preferred":[
        "\u067e\u0644\u0627\u0646\u0627\u062f\u0627\u0633"
    ],
    "name:fra_x_preferred":[
        "Planadas"
    ],
    "name:ita_x_preferred":[
        "Planadas"
    ],
    "name:kat_x_preferred":[
        "\u10de\u10da\u10d0\u10dc\u10d0\u10d3\u10d0\u10e1\u10d8"
    ],
    "name:msa_x_preferred":[
        "Planadas"
    ],
    "name:nld_x_preferred":[
        "Planadas"
    ],
    "name:spa_x_preferred":[
        "Planadas"
    ],
    "name:swe_x_preferred":[
        "Planadas"
    ],
    "name:vie_x_preferred":[
        "Planadas"
    ],
    "name:war_x_preferred":[
        "Planadas"
    ],
    "name:zho_x_preferred":[
        "\u666e\u62c9\u7d0d\u9054"
    ],
    "wof:name":"Planadas",
    "wof:placetype":"locality"
},
  "geometry": {"coordinates":[-76.73433,2.70087],"type":"Point"}
}