{
  "type": "Feature",
  "properties": {
    "gn:admin1_code":"27",
    "gn:admin2_code":"70204.0",
    "gn:asciiname":"El Principio",
    "gn:country_code":"CO",
    "gn:dem":91,
    "gn:feature_class":"P",
    "gn:feature_code":"PPL",
    "gn:name":"El Principio",
    "gn:population":0,
    "gn:timezone":"America/Bogota",
    "iso:country":"CO",
    "wof:name":"El Principio",
    "wof:placetype":"locality"
},
  "geometry": {"coordinates":[-75.35921999999999,9.45052],"type":"Point"}
}