{
  "type": "Feature",
  "properties": {
    "gn:admin1_code":"28",
    "gn:admin2_code":"73001.0",
    "gn:asciiname":"La Argentina",
    "gn:country_code":"CO",
    "gn:dem":1760,
    "gn:feature_class":"P",
    "gn:feature_code":"PPL",
    "gn:name":"La Argentina",
    "gn:population":0,
    "gn:timezone":"America/Bogota",
    "iso:country":"CO",
    "wof:name":"La Argentina",
    "wof:placetype":"locality"
},
  "geometry": {"coordinates":[-75.36667,4.41667],"type":"Point"}
}