{
  "type": "Feature",
  "properties": {
    "gn:admin1_code":"26",
    "gn:admin2_code":"68780.0",
    "gn:asciiname":"La Reserva",
    "gn:country_code":"CO",
    "gn:dem":2122,
    "gn:feature_class":"P",
    "gn:feature_code":"PPL",
    "gn:name":"La Reserva",
    "gn:population":0,
    "gn:timezone":"America/Bogota",
    "iso:country":"CO",
    "wof:name":"La Reserva",
    "wof:placetype":"locality"
},
  "geometry": {"coordinates":[-73.02028,7.49222],"type":"Point"}
}