{
  "type": "Feature",
  "properties": {
    "gn:admin1_code":"29",
    "gn:admin2_code":"76233.0",
    "gn:asciiname":"El Naranjo",
    "gn:cc2":"CO",
    "gn:country_code":"CO",
    "gn:dem":581,
    "gn:feature_class":"P",
    "gn:feature_code":"PPL",
    "gn:name":"El Naranjo",
    "gn:population":0,
    "gn:timezone":"America/Bogota",
    "iso:country":"CO",
    "name:und_x_variant":[
        "Naranjo",
        "El Naranjo"
    ],
    "wof:name":"El Naranjo",
    "wof:placetype":"locality"
},
  "geometry": {"coordinates":[-76.72055999999998,3.78389],"type":"Point"}
}