{
  "type": "Feature",
  "properties": {
    "gn:admin1_code":"36",
    "gn:admin2_code":"15676.0",
    "gn:asciiname":"Mirado",
    "gn:country_code":"CO",
    "gn:dem":2696,
    "gn:feature_class":"P",
    "gn:feature_code":"PPL",
    "gn:name":"Mirado",
    "gn:population":0,
    "gn:timezone":"America/Bogota",
    "iso:country":"CO",
    "wof:name":"Mirado",
    "wof:placetype":"locality"
},
  "geometry": {"coordinates":[-73.69722,5.51611],"type":"Point"}
}