{
  "type": "Feature",
  "properties": {
    "iso:country":"CO",
    "name:ast_x_preferred":[
        "Repel\u00f3n"
    ],
    "name:ceb_x_preferred":[
        "Repel\u00f3n"
    ],
    "name:deu_x_preferred":[
        "Repel\u00f3n"
    ],
    "name:eng_x_preferred":[
        "Repel\u00f3n"
    ],
    "name:fas_x_preferred":[
        "\u0631\u067e\u0644\u0648\u0646"
    ],
    "name:fra_x_preferred":[
        "Repel\u00f3n"
    ],
    "name:ita_x_preferred":[
        "Repel\u00f3n"
    ],
    "name:kat_x_preferred":[
        "\u10e0\u10d4\u10de\u10d4\u10da\u10dd\u10dc\u10d8"
    ],
    "name:msa_x_preferred":[
        "Repelon"
    ],
    "name:nan_x_preferred":[
        "Repel\u00f3n"
    ],
    "name:nld_x_preferred":[
        "Repel\u00f3n"
    ],
    "name:por_x_preferred":[
        "Repelon"
    ],
    "name:rus_x_preferred":[
        "\u0420\u0435\u043f\u0435\u043b\u043e\u043d"
    ],
    "name:sco_x_preferred":[
        "Repel\u00f3n"
    ],
    "name:spa_x_preferred":[
        "Repel\u00f3n"
    ],
    "name:swe_x_preferred":[
        "Repel\u00f3n"
    ],
    "name:tgl_x_preferred":[
        "Repel\u00f3n"
    ],
    "name:vie_x_preferred":[
        "Repel\u00f3n"
    ],
    "name:war_x_preferred":[
        "Repel\u00f3n"
    ],
    "name:zho_x_preferred":[
        "\u96f7\u4f69\u9686"
    ],
    "qs:gn_country":"CO",
    "qs:gn_fcode":"PPL",
    "qs:gn_pop":18685,
    "qs:name":"Repel\u00f3n",
    "qs:name_adm0":"Colombia",
    "qs:name_adm1":"Atlantico",
    "qs:photos":0,
    "qs:photos_1k":0,
    "qs:photos_9k":1,
    "qs:photos_9r":1,
    "qs:photos_all":15,
    "qs:photos_sr":0,
    "qs:placetype":"Town",
    "qs:pop_sr":"6",
    "qs:woe_adm0":23424787,
    "wd:wordcount":54,
    "wof:name":"Repel\u00f3n",
    "wof:placetype":"locality",
    "wof:population":18685
},
  "geometry": {"coordinates":[-75.12917,10.49194],"type":"Point"}
}