{
  "type": "Feature",
  "properties": {
    "gn:admin1_code":"2.0",
    "gn:admin2_code":"5001.0",
    "gn:asciiname":"Puente Colgante",
    "gn:country_code":"CO",
    "gn:dem":1821,
    "gn:feature_class":"P",
    "gn:feature_code":"PPL",
    "gn:name":"Puente Colgante",
    "gn:population":0,
    "gn:timezone":"America/Bogota",
    "iso:country":"CO",
    "name:deu_x_preferred":[
        "Puente Colgante"
    ],
    "name:spa_x_preferred":[
        "Puente Colgante"
    ],
    "wof:name":"Puente Colgante",
    "wof:placetype":"locality"
},
  "geometry": {"coordinates":[-75.62891,6.27836],"type":"Point"}
}