{
  "type": "Feature",
  "properties": {
    "gn:admin1_code":"2.0",
    "gn:admin2_code":"5658.0",
    "gn:asciiname":"La Arabia",
    "gn:country_code":"CO",
    "gn:dem":3120,
    "gn:feature_class":"P",
    "gn:feature_code":"PPL",
    "gn:name":"La Arabia",
    "gn:population":0,
    "gn:timezone":"America/Bogota",
    "iso:country":"CO",
    "wof:name":"La Arabia",
    "wof:placetype":"locality"
},
  "geometry": {"coordinates":[-75.69389,6.79111],"type":"Point"}
}