{
  "type": "Feature",
  "properties": {
    "gn:admin1_code":"20.0",
    "gn:admin2_code":"52835.0",
    "gn:asciiname":"Travesia",
    "gn:country_code":"CO",
    "gn:dem":244,
    "gn:feature_class":"P",
    "gn:feature_code":"PPL",
    "gn:name":"Traves\u00eda",
    "gn:population":0,
    "gn:timezone":"America/Bogota",
    "iso:country":"CO",
    "wof:name":"Travesia",
    "wof:placetype":"locality"
},
  "geometry": {"coordinates":[-78.43333,1.45],"type":"Point"}
}