{
  "type": "Feature",
  "properties": {
    "iso:country":"CO",
    "name:ceb_x_preferred":[
        "Nemoc\u00f3n"
    ],
    "name:eng_x_preferred":[
        "Nemoc\u00f3n"
    ],
    "name:fra_x_preferred":[
        "Nemoc\u00f3n"
    ],
    "name:ita_x_preferred":[
        "Nemoc\u00f3n"
    ],
    "name:kat_x_preferred":[
        "\u10dc\u10d4\u10db\u10dd\u10d9\u10dd\u10dc\u10d8"
    ],
    "name:msa_x_preferred":[
        "Nemoc\u00f3n"
    ],
    "name:nan_x_preferred":[
        "Nemoc\u00f3n"
    ],
    "name:nld_x_preferred":[
        "Nemoc\u00f3n"
    ],
    "name:spa_x_preferred":[
        "Nemoc\u00f3n"
    ],
    "name:swe_x_preferred":[
        "Nemoc\u00f3n"
    ],
    "name:tgl_x_preferred":[
        "Nemoc\u00f3n"
    ],
    "name:vie_x_preferred":[
        "Nemoc\u00f3n"
    ],
    "name:war_x_preferred":[
        "Nemoc\u00f3n"
    ],
    "name:zho_x_preferred":[
        "\u5167\u83ab\u5b54"
    ],
    "qs:gn_country":"CO",
    "qs:gn_fcode":"PPL",
    "qs:gn_pop":5466,
    "qs:name":"Nemoc\u00f3n",
    "qs:name_adm0":"Colombia",
    "qs:name_adm1":"Cundinamarca",
    "qs:photos":515,
    "qs:photos_1k":104,
    "qs:photos_9k":2,
    "qs:photos_9r":5,
    "qs:photos_all":515,
    "qs:photos_sr":7,
    "qs:placetype":"Town",
    "qs:pop_sr":"5",
    "qs:woe_adm0":23424787,
    "wof:name":"Nemoc\u00f3n",
    "wof:placetype":"locality",
    "wof:population":5466
},
  "geometry": {"coordinates":[-73.88333,5.05],"type":"Point"}
}