{
  "type": "Feature",
  "properties": {
    "gn:admin1_code":"28",
    "gn:admin2_code":"73168.0",
    "gn:asciiname":"Penaranda",
    "gn:country_code":"CO",
    "gn:dem":2431,
    "gn:feature_class":"P",
    "gn:feature_code":"PPL",
    "gn:name":"Pe\u00f1aranda",
    "gn:population":0,
    "gn:timezone":"America/Bogota",
    "iso:country":"CO",
    "wof:name":"Penaranda",
    "wof:placetype":"locality"
},
  "geometry": {"coordinates":[-75.59389,3.885],"type":"Point"}
}