{
  "type": "Feature",
  "properties": {
    "gn:admin1_code":"20",
    "gn:admin2_code":"52256.0",
    "gn:asciiname":"Complementaria",
    "gn:country_code":"CO",
    "gn:dem":1456,
    "gn:feature_class":"P",
    "gn:feature_code":"PPL",
    "gn:name":"Complementaria",
    "gn:population":0,
    "gn:timezone":"America/Bogota",
    "iso:country":"CO",
    "wof:name":"Complementaria",
    "wof:placetype":"locality"
},
  "geometry": {"coordinates":[-77.33224,1.73987],"type":"Point"}
}