{
  "type": "Feature",
  "properties": {
    "gn:admin1_code":"17",
    "gn:admin2_code":"44847.0",
    "gn:asciiname":"Rancheria Warut'tamana",
    "gn:country_code":"CO",
    "gn:dem":136,
    "gn:feature_class":"P",
    "gn:feature_code":"PPL",
    "gn:name":"Rancher\u00eda Warut\u2019tamana",
    "gn:population":0,
    "gn:timezone":"America/Bogota",
    "iso:country":"CO",
    "name:und_x_variant":[
        "Waruttamana",
        "Huar\u00fattamahana",
        "Rancher\u00eda Warut\u2019tamana"
    ],
    "wof:name":"Rancheria Warut'tamana",
    "wof:placetype":"locality"
},
  "geometry": {"coordinates":[-71.4345,12.09466],"type":"Point"}
}