{
  "type": "Feature",
  "properties": {
    "gn:admin1_code":"9",
    "gn:admin2_code":"19300.0",
    "gn:asciiname":"Dominga",
    "gn:country_code":"CO",
    "gn:dem":1022,
    "gn:feature_class":"P",
    "gn:feature_code":"PPL",
    "gn:name":"Dominga",
    "gn:population":0,
    "gn:timezone":"America/Bogota",
    "iso:country":"CO",
    "name:spa_x_preferred":[
        "Dominga"
    ],
    "name:und_x_variant":[
        "La Dominga"
    ],
    "wof:name":"Dominga",
    "wof:placetype":"locality"
},
  "geometry": {"coordinates":[-76.40049999999999,3.09816],"type":"Point"}
}