{
  "type": "Feature",
  "properties": {
    "gn:admin1_code":"2.0",
    "gn:admin2_code":"5138.0",
    "gn:asciiname":"El Hoyo",
    "gn:country_code":"CO",
    "gn:dem":2022,
    "gn:feature_class":"P",
    "gn:feature_code":"PPL",
    "gn:name":"El Hoyo",
    "gn:population":0,
    "gn:timezone":"America/Bogota",
    "iso:country":"CO",
    "name:ita_x_preferred":[
        "El Hoyo"
    ],
    "name:spa_x_preferred":[
        "El Hoyo"
    ],
    "wof:name":"El Hoyo",
    "wof:placetype":"locality"
},
  "geometry": {"coordinates":[-75.98083000000003,6.90139],"type":"Point"}
}