{
  "type": "Feature",
  "properties": {
    "gn:admin1_code":"2",
    "gn:admin2_code":"5893.0",
    "gn:asciiname":"El Salado",
    "gn:country_code":"CO",
    "gn:dem":70,
    "gn:feature_class":"P",
    "gn:feature_code":"PPL",
    "gn:name":"El Salado",
    "gn:population":0,
    "gn:timezone":"America/Bogota",
    "iso:country":"CO",
    "wof:name":"El Salado",
    "wof:placetype":"locality"
},
  "geometry": {"coordinates":[-74.10637,7.0983],"type":"Point"}
}