{
  "type": "Feature",
  "properties": {
    "gn:admin1_code":"10",
    "gn:admin2_code":"20045.0",
    "gn:asciiname":"Malagana",
    "gn:country_code":"CO",
    "gn:dem":46,
    "gn:feature_class":"P",
    "gn:feature_code":"PPL",
    "gn:name":"Malagana",
    "gn:population":0,
    "gn:timezone":"America/Bogota",
    "iso:country":"CO",
    "name:epo_x_preferred":[
        "Malagana"
    ],
    "name:spa_x_preferred":[
        "Cultura Malagana"
    ],
    "wof:name":"Malagana",
    "wof:placetype":"locality"
},
  "geometry": {"coordinates":[-73.63734000000002,9.68906],"type":"Point"}
}