{
  "type": "Feature",
  "properties": {
    "gn:admin1_code":"26",
    "gn:admin2_code":"68377.0",
    "gn:asciiname":"Monte Bello",
    "gn:country_code":"CO",
    "gn:dem":2654,
    "gn:feature_class":"P",
    "gn:feature_code":"PPL",
    "gn:name":"Monte Bello",
    "gn:population":0,
    "gn:timezone":"America/Bogota",
    "iso:country":"CO",
    "name:ceb_x_preferred":[
        "Monte Bello"
    ],
    "name:swe_x_preferred":[
        "Monte Bello"
    ],
    "wof:name":"Monte Bello",
    "wof:placetype":"locality"
},
  "geometry": {"coordinates":[-73.90167,5.86111],"type":"Point"}
}