{
  "type": "Feature",
  "properties": {
    "gn:admin1_code":"38",
    "gn:admin2_code":"47980.0",
    "gn:asciiname":"La Cuba",
    "gn:country_code":"CO",
    "gn:dem":18,
    "gn:feature_class":"P",
    "gn:feature_code":"PPL",
    "gn:name":"La Cuba",
    "gn:population":0,
    "gn:timezone":"America/Bogota",
    "iso:country":"CO",
    "wof:name":"La Cuba",
    "wof:placetype":"locality"
},
  "geometry": {"coordinates":[-74.19251,10.95368],"type":"Point"}
}