{
  "type": "Feature",
  "properties": {
    "gn:admin1_code":"19.0",
    "gn:admin2_code":"50251.0",
    "gn:asciiname":"Medellin del Ariari",
    "gn:country_code":"CO",
    "gn:dem":392,
    "gn:feature_class":"P",
    "gn:feature_code":"PPL",
    "gn:name":"Medell\u00edn del Ariari",
    "gn:population":0,
    "gn:timezone":"America/Bogota",
    "iso:country":"CO",
    "name:spa_x_preferred":[
        "Medell\u00edn del Ariari"
    ],
    "wof:name":"Medellin del Ariari",
    "wof:placetype":"locality"
},
  "geometry": {"coordinates":[-73.80405,3.62858],"type":"Point"}
}