{
  "type": "Feature",
  "properties": {
    "iso:country":"CO",
    "name:ast_x_preferred":[
        "Dosquebradas"
    ],
    "name:ceb_x_preferred":[
        "Dos Quebradas"
    ],
    "name:deu_x_preferred":[
        "Dosquebradas"
    ],
    "name:eng_x_preferred":[
        "Dosquebradas"
    ],
    "name:epo_x_preferred":[
        "Dosquebradas"
    ],
    "name:fas_x_preferred":[
        "\u062f\u0648\u0633\u06a9\u0628\u0631\u0627\u062f\u0627\u0633"
    ],
    "name:fin_x_preferred":[
        "Dosquebradas"
    ],
    "name:fra_x_preferred":[
        "Dosquebradas"
    ],
    "name:ita_x_preferred":[
        "Dosquebradas"
    ],
    "name:jpn_x_preferred":[
        "\u30c9\u30b9\u30b1\u30d6\u30e9\u30fc\u30c0\u30b9"
    ],
    "name:kat_x_preferred":[
        "\u10d3\u10dd\u10e1\u10d9\u10d4\u10d1\u10e0\u10d0\u10d3\u10d0\u10e1\u10d8"
    ],
    "name:lit_x_preferred":[
        "Doskebradas"
    ],
    "name:msa_x_preferred":[
        "Dosquebradas"
    ],
    "name:nan_x_preferred":[
        "Dosquebradas"
    ],
    "name:nld_x_preferred":[
        "Dosquebradas"
    ],
    "name:pol_x_preferred":[
        "Dosquebradas"
    ],
    "name:rus_x_preferred":[
        "\u0414\u043e\u0441\u043a\u0435\u0431\u0440\u0430\u0434\u0430\u0441"
    ],
    "name:spa_x_preferred":[
        "Dos Quebradas"
    ],
    "name:spa_x_variant":[
        "Dosquebradas"
    ],
    "name:swe_x_preferred":[
        "Dosquebradas"
    ],
    "name:tat_x_preferred":[
        "\u0414\u043e\u0441\u043a\u0435\u0431\u0440\u0430\u0434\u0430\u0441"
    ],
    "name:tgl_x_preferred":[
        "Dosquebradas"
    ],
    "name:urd_x_preferred":[
        "\u062f\u0648\u0633\u06a9\u06d2\u0628\u0631\u0627\u062f\u0627\u0633"
    ],
    "name:vie_x_preferred":[
        "Dosquebradas"
    ],
    "name:vol_x_preferred":[
        "Dosquebradas"
    ],
    "name:war_x_preferred":[
        "Dosquebradas"
    ],
    "name:zho_x_preferred":[
        "\u591a\u65af\u514b\u5e03\u62c9\u9054\u65af"
    ],
    "qs:gn_country":"CO",
    "qs:gn_fcode":"PPL",
    "qs:gn_pop":179583,
    "qs:name":"Dos Quebradas",
    "qs:name_adm0":"Colombia",
    "qs:name_adm1":"Risaralda",
    "qs:photos":247,
    "qs:photos_1k":50,
    "qs:photos_9k":1,
    "qs:photos_9r":4,
    "qs:photos_all":247,
    "qs:photos_sr":4,
    "qs:placetype":"Town",
    "qs:pop_sr":"9",
    "qs:woe_adm0":23424787,
    "wof:name":"Dos Quebradas",
    "wof:placetype":"locality",
    "wof:population":179583
},
  "geometry": {"coordinates":[-75.66726,4.83916],"type":"Point"}
}