{
  "type": "Feature",
  "properties": {
    "gn:admin1_code":"29.0",
    "gn:admin2_code":"76890.0",
    "gn:asciiname":"Piedras",
    "gn:cc2":"CO",
    "gn:country_code":"CO",
    "gn:dem":951,
    "gn:feature_class":"P",
    "gn:feature_code":"PPL",
    "gn:name":"Piedras",
    "gn:population":0,
    "gn:timezone":"America/Bogota",
    "iso:country":"CO",
    "name:cat_x_preferred":[
        "Piedras"
    ],
    "name:ceb_x_preferred":[
        "Piedras"
    ],
    "name:fra_x_preferred":[
        "Piedras"
    ],
    "name:gla_x_preferred":[
        "Piedras"
    ],
    "name:ita_x_preferred":[
        "Piedras"
    ],
    "name:kat_x_preferred":[
        "\u10de\u10d8\u10d4\u10d3\u10e0\u10d0\u10e1\u10d8"
    ],
    "name:msa_x_preferred":[
        "Piedras"
    ],
    "name:nld_x_preferred":[
        "Piedras"
    ],
    "name:spa_x_preferred":[
        "Piedras"
    ],
    "name:swe_x_preferred":[
        "Piedras"
    ],
    "name:und_x_variant":[
        "San Antonio de Piedras",
        "Piedras"
    ],
    "name:vie_x_preferred":[
        "Piedras"
    ],
    "name:war_x_preferred":[
        "Piedras"
    ],
    "name:zho_x_preferred":[
        "\u5f7c\u5fb7\u62c9\u65af"
    ],
    "wof:name":"Piedras",
    "wof:placetype":"locality"
},
  "geometry": {"coordinates":[-76.3325,4.05528],"type":"Point"}
}