{
  "type": "Feature",
  "properties": {
    "gn:admin1_code":"20.0",
    "gn:admin2_code":"52835.0",
    "gn:asciiname":"El Charro",
    "gn:country_code":"CO",
    "gn:dem":25,
    "gn:feature_class":"P",
    "gn:feature_code":"PPL",
    "gn:name":"El Charro",
    "gn:population":0,
    "gn:timezone":"America/Bogota",
    "iso:country":"CO",
    "wof:name":"El Charro",
    "wof:placetype":"locality"
},
  "geometry": {"coordinates":[-78.46042,1.75668],"type":"Point"}
}