{
  "type": "Feature",
  "properties": {
    "gn:admin1_code":"10.0",
    "gn:admin2_code":"20013.0",
    "gn:asciiname":"Hacienda Guayaquil",
    "gn:country_code":"CO",
    "gn:dem":1478,
    "gn:feature_class":"P",
    "gn:feature_code":"PPL",
    "gn:name":"Hacienda Guayaquil",
    "gn:population":0,
    "gn:timezone":"America/Bogota",
    "iso:country":"CO",
    "wof:name":"Hacienda Guayaquil",
    "wof:placetype":"locality"
},
  "geometry": {"coordinates":[-73.10642,10.02675],"type":"Point"}
}