{
  "type": "Feature",
  "properties": {
    "gn:admin1_code":"12",
    "gn:admin2_code":"23570.0",
    "gn:asciiname":"El Tesoro",
    "gn:country_code":"CO",
    "gn:dem":53,
    "gn:feature_class":"P",
    "gn:feature_code":"PPL",
    "gn:name":"El Tesoro",
    "gn:population":0,
    "gn:timezone":"America/Bogota",
    "iso:country":"CO",
    "wof:name":"El Tesoro",
    "wof:placetype":"locality"
},
  "geometry": {"coordinates":[-75.35154,8.52788],"type":"Point"}
}