{
  "type": "Feature",
  "properties": {
    "gn:admin1_code":"20",
    "gn:admin2_code":"52051.0",
    "gn:asciiname":"La Honda",
    "gn:country_code":"CO",
    "gn:dem":1434,
    "gn:feature_class":"P",
    "gn:feature_code":"PPL",
    "gn:name":"La Honda",
    "gn:population":0,
    "gn:timezone":"America/Bogota",
    "iso:country":"CO",
    "wof:name":"La Honda",
    "wof:placetype":"locality"
},
  "geometry": {"coordinates":[-77.1241,1.44604],"type":"Point"}
}