{
  "type": "Feature",
  "properties": {
    "gn:admin1_code":"38",
    "gn:admin2_code":"47707.0",
    "gn:asciiname":"El Horizonte",
    "gn:country_code":"CO",
    "gn:dem":71,
    "gn:feature_class":"P",
    "gn:feature_code":"PPL",
    "gn:name":"El Horizonte",
    "gn:population":0,
    "gn:timezone":"America/Bogota",
    "iso:country":"CO",
    "wof:name":"El Horizonte",
    "wof:placetype":"locality"
},
  "geometry": {"coordinates":[-74.20408,9.56896],"type":"Point"}
}