{
  "type": "Feature",
  "properties": {
    "gn:admin1_code":"17",
    "gn:admin2_code":"44110.0",
    "gn:asciiname":"Macuira",
    "gn:country_code":"CO",
    "gn:dem":363,
    "gn:feature_class":"P",
    "gn:feature_code":"PPL",
    "gn:name":"Macuira",
    "gn:population":0,
    "gn:timezone":"America/Bogota",
    "iso:country":"CO",
    "wof:name":"Macuira",
    "wof:placetype":"locality"
},
  "geometry": {"coordinates":[-72.89636,10.62494],"type":"Point"}
}