{
  "type": "Feature",
  "properties": {
    "gn:admin1_code":"26.0",
    "gn:admin2_code":"68745.0",
    "gn:asciiname":"El Danto",
    "gn:country_code":"CO",
    "gn:dem":140,
    "gn:feature_class":"P",
    "gn:feature_code":"PPLL",
    "gn:name":"El Danto",
    "gn:population":0,
    "gn:timezone":"America/Bogota",
    "iso:country":"CO",
    "name:und_x_variant":[
        "Campo Nuevo",
        "El Danto"
    ],
    "wof:name":"El Danto",
    "wof:placetype":"locality"
},
  "geometry": {"coordinates":[-73.75646999999999,6.69861],"type":"Point"}
}