{
  "type": "Feature",
  "properties": {
    "gn:admin1_code":"16.0",
    "gn:admin2_code":"41078.0",
    "gn:asciiname":"Hacienda Buenos Aires",
    "gn:country_code":"CO",
    "gn:dem":439,
    "gn:feature_class":"P",
    "gn:feature_code":"PPL",
    "gn:name":"Hacienda Buenos Aires",
    "gn:population":0,
    "gn:timezone":"America/Bogota",
    "iso:country":"CO",
    "name:spa_x_preferred":[
        "Hacienda Buenos Aires"
    ],
    "wof:name":"Hacienda Buenos Aires",
    "wof:placetype":"locality"
},
  "geometry": {"coordinates":[-75.14471999999998,3.19699],"type":"Point"}
}