{
  "type": "Feature",
  "properties": {
    "gn:country":"CO",
    "gn:fcode":"PPL",
    "gn:pop":1617,
    "iso:country":"CO",
    "name:eng_x_preferred":[
        "Caicedo"
    ],
    "name:fra_x_preferred":[
        "Caicedo"
    ],
    "name:ile_x_preferred":[
        "Caicedo"
    ],
    "name:ita_x_preferred":[
        "Caicedo"
    ],
    "name:kat_x_preferred":[
        "\u10d9\u10d0\u10d8\u10e1\u10d4\u10d3\u10dd"
    ],
    "name:msa_x_preferred":[
        "Caicedo"
    ],
    "name:nan_x_preferred":[
        "Caicedo"
    ],
    "name:nld_x_preferred":[
        "Caicedo"
    ],
    "name:por_x_preferred":[
        "Caicedo"
    ],
    "name:ron_x_preferred":[
        "Caicedo"
    ],
    "name:rus_x_preferred":[
        "\u041a\u0430\u0439\u0441\u0435\u0434\u043e"
    ],
    "name:spa_x_preferred":[
        "Caicedo"
    ],
    "name:swe_x_preferred":[
        "Caicedo"
    ],
    "name:tgl_x_preferred":[
        "Caicedo"
    ],
    "name:vie_x_preferred":[
        "Caicedo"
    ],
    "name:war_x_preferred":[
        "Caicedo"
    ],
    "name:zho_x_preferred":[
        "\u51f1\u585e\u591a"
    ],
    "qs:name":"Caicedo",
    "qs:photos_9r":0,
    "qs:photos_sr":0,
    "qs:pop_sr":"3",
    "wd:wordcount":45,
    "wof:name":"Caicedo",
    "wof:placetype":"locality",
    "wof:population":1617
},
  "geometry": {"coordinates":[-75.98255,6.40511],"type":"Point"}
}