{
  "type": "Feature",
  "properties": {
    "gn:admin1_code":"36.0",
    "gn:admin2_code":"15425.0",
    "gn:asciiname":"Perdiguiz Grande",
    "gn:country_code":"CO",
    "gn:dem":2006,
    "gn:feature_class":"P",
    "gn:feature_code":"PPL",
    "gn:name":"Perdiguiz Grande",
    "gn:population":0,
    "gn:timezone":"America/Bogota",
    "iso:country":"CO",
    "wof:name":"Perdiguiz Grande",
    "wof:placetype":"locality"
},
  "geometry": {"coordinates":[-73.31869,5.03309],"type":"Point"}
}