{
  "type": "Feature",
  "properties": {
    "gn:admin1_code":"2.0",
    "gn:admin2_code":"5604.0",
    "gn:asciiname":"Monte Verde",
    "gn:country_code":"CO",
    "gn:dem":583,
    "gn:feature_class":"P",
    "gn:feature_code":"PPL",
    "gn:name":"Monte Verde",
    "gn:population":0,
    "gn:timezone":"America/Bogota",
    "iso:country":"CO",
    "name:cat_x_preferred":[
        "Monte Verde"
    ],
    "name:deu_x_preferred":[
        "Monte Verde"
    ],
    "name:fas_x_preferred":[
        "\u0645\u0648\u0646\u062a\u0647 \u0648\u0631\u062f\u0647"
    ],
    "name:fra_x_preferred":[
        "Monte Verde"
    ],
    "name:heb_x_preferred":[
        "\u05de\u05d5\u05e0\u05d8\u05d4 \u05d5\u05e8\u05d3\u05d4"
    ],
    "name:ind_x_preferred":[
        "Monte Verde"
    ],
    "name:ita_x_preferred":[
        "Monte Verde"
    ],
    "name:kat_x_preferred":[
        "\u10db\u10dd\u10dc\u10e2\u10d4-\u10d5\u10d4\u10e0\u10d3\u10d4"
    ],
    "name:lit_x_preferred":[
        "Monte Verd\u0117"
    ],
    "name:nld_x_preferred":[
        "Monte Verde"
    ],
    "name:oci_x_preferred":[
        "Monte Verde"
    ],
    "name:pol_x_preferred":[
        "Monte Verde"
    ],
    "name:por_x_preferred":[
        "Monte Verde"
    ],
    "name:rus_x_preferred":[
        "\u041c\u043e\u043d\u0442\u0435-\u0412\u0435\u0440\u0434\u0435"
    ],
    "name:spa_x_preferred":[
        "Monte Verde"
    ],
    "name:swe_x_preferred":[
        "Monte Verde"
    ],
    "name:ukr_x_preferred":[
        "\u041c\u043e\u043d\u0442\u0435-\u0412\u0435\u0440\u0434\u0435"
    ],
    "wof:name":"Monte Verde",
    "wof:placetype":"locality"
},
  "geometry": {"coordinates":[-74.54576999999998,7.15196],"type":"Point"}
}