{
  "type": "Feature",
  "properties": {
    "gn:admin1_code":"38",
    "gn:admin2_code":"47001.0",
    "gn:asciiname":"Hato de Simon",
    "gn:country_code":"CO",
    "gn:dem":2948,
    "gn:feature_class":"P",
    "gn:feature_code":"PPL",
    "gn:name":"Hato de Sim\u00f3n",
    "gn:population":0,
    "gn:timezone":"America/Bogota",
    "iso:country":"CO",
    "wof:name":"Hato de Simon",
    "wof:placetype":"locality"
},
  "geometry": {"coordinates":[-73.84106,10.93551],"type":"Point"}
}