{
  "type": "Feature",
  "properties": {
    "gn:admin1_code":"8.0",
    "gn:admin2_code":"18410.0",
    "gn:asciiname":"La Nutria",
    "gn:country_code":"CO",
    "gn:dem":255,
    "gn:feature_class":"P",
    "gn:feature_code":"PPL",
    "gn:name":"La Nutria",
    "gn:population":0,
    "gn:timezone":"America/Bogota",
    "iso:country":"CO",
    "name:spa_x_preferred":[
        "La Nutria"
    ],
    "wof:name":"La Nutria",
    "wof:placetype":"locality"
},
  "geometry": {"coordinates":[-75.36098,1.39691],"type":"Point"}
}