{
  "type": "Feature",
  "properties": {
    "gn:admin1_code":"19",
    "gn:admin2_code":"50270",
    "gn:asciiname":"Pueblo Sanchez",
    "gn:country_code":"CO",
    "gn:dem":454,
    "gn:feature_class":"P",
    "gn:feature_code":"PPL",
    "gn:name":"Pueblo Sanchez",
    "gn:population":0,
    "gn:timezone":"America/Bogota",
    "iso:country":"CO",
    "name:spa_x_preferred":[
        "Pueblo Sanchez"
    ],
    "wof:name":"Pueblo Sanchez",
    "wof:placetype":"locality"
},
  "geometry": {"coordinates":[-73.79776,3.70228],"type":"Point"}
}