{
  "type": "Feature",
  "properties": {
    "gn:admin1_code":"33",
    "gn:admin2_code":"25580.0",
    "gn:asciiname":"Manantial",
    "gn:country_code":"CO",
    "gn:dem":947,
    "gn:feature_class":"P",
    "gn:feature_code":"PPL",
    "gn:name":"Manantial",
    "gn:population":0,
    "gn:timezone":"America/Bogota",
    "iso:country":"CO",
    "wof:name":"Manantial",
    "wof:placetype":"locality"
},
  "geometry": {"coordinates":[-74.68333,4.68333],"type":"Point"}
}