{
  "type": "Feature",
  "properties": {
    "gn:admin1_code":"27.0",
    "gn:admin2_code":"70233.0",
    "gn:asciiname":"Patillal",
    "gn:country_code":"CO",
    "gn:dem":64,
    "gn:feature_class":"P",
    "gn:feature_code":"PPL",
    "gn:name":"Patillal",
    "gn:population":0,
    "gn:timezone":"America/Bogota",
    "iso:country":"CO",
    "name:fra_x_preferred":[
        "Patillal"
    ],
    "name:spa_x_preferred":[
        "Patillal"
    ],
    "name:und_x_variant":[
        "Caser\u00edo Patillal"
    ],
    "wof:name":"Patillal",
    "wof:placetype":"locality"
},
  "geometry": {"coordinates":[-75.08185999999998,9.07787],"type":"Point"}
}