{
  "type": "Feature",
  "properties": {
    "gn:admin1_code":"35",
    "gn:asciiname":"Las Balsas",
    "gn:country_code":"CO",
    "gn:dem":4,
    "gn:feature_class":"P",
    "gn:feature_code":"PPL",
    "gn:name":"Las Balsas",
    "gn:population":0,
    "gn:timezone":"America/Bogota",
    "iso:country":"CO",
    "wof:name":"Las Balsas",
    "wof:placetype":"locality"
},
  "geometry": {"coordinates":[-75.48333000000002,10.03333],"type":"Point"}
}