{
  "type": "Feature",
  "properties": {
    "gn:admin1_code":"11",
    "gn:admin2_code":"27430.0",
    "gn:asciiname":"Carmen Abadia",
    "gn:country_code":"CO",
    "gn:dem":34,
    "gn:feature_class":"P",
    "gn:feature_code":"PPL",
    "gn:name":"Carmen Abad\u00eda",
    "gn:population":0,
    "gn:timezone":"America/Bogota",
    "iso:country":"CO",
    "wof:name":"Carmen Abadia",
    "wof:placetype":"locality"
},
  "geometry": {"coordinates":[-76.96666999999999,5.16667],"type":"Point"}
}