{
  "type": "Feature",
  "properties": {
    "gn:admin1_code":"12",
    "gn:admin2_code":"23660.0",
    "gn:asciiname":"El Guarumo",
    "gn:country_code":"CO",
    "gn:dem":100,
    "gn:feature_class":"P",
    "gn:feature_code":"PPL",
    "gn:name":"El Guarumo",
    "gn:population":0,
    "gn:timezone":"America/Bogota",
    "iso:country":"CO",
    "name:und_x_variant":[
        "Hacienda El Guarumo",
        "El Guarumo"
    ],
    "wof:name":"El Guarumo",
    "wof:placetype":"locality"
},
  "geometry": {"coordinates":[-75.42229,8.79751],"type":"Point"}
}