{
  "type": "Feature",
  "properties": {
    "iso:country":"CO",
    "name:ast_x_preferred":[
        "Jord\u00e1n"
    ],
    "name:ceb_x_preferred":[
        "Jord\u00e1n"
    ],
    "name:eng_x_preferred":[
        "Jord\u00e1n"
    ],
    "name:fra_x_preferred":[
        "Jord\u00e1n"
    ],
    "name:glg_x_preferred":[
        "Jord\u00e1n"
    ],
    "name:ita_x_preferred":[
        "Jord\u00e1n"
    ],
    "name:kat_x_preferred":[
        "\u10ee\u10dd\u10e0\u10d3\u10d0\u10dc\u10d8"
    ],
    "name:msa_x_preferred":[
        "Jordan"
    ],
    "name:nan_x_preferred":[
        "Jord\u00e1n"
    ],
    "name:nld_x_preferred":[
        "Jord\u00e1n"
    ],
    "name:spa_x_preferred":[
        "Jord\u00e1n"
    ],
    "name:swe_x_preferred":[
        "Jord\u00e1n"
    ],
    "name:tgl_x_preferred":[
        "Jordan"
    ],
    "name:und_x_variant":[
        "El Jordan"
    ],
    "name:vie_x_preferred":[
        "Jord\u00e1n"
    ],
    "name:war_x_preferred":[
        "Jordan"
    ],
    "name:zho_x_preferred":[
        "\u970d\u723e\u4e39"
    ],
    "qs:gn_country":"CO",
    "qs:gn_fcode":"PPL",
    "qs:gn_pop":112,
    "qs:name":"Jord\u00e1n",
    "qs:name_adm0":"Colombia",
    "qs:name_adm1":"Santander",
    "qs:photos":0,
    "qs:photos_1k":0,
    "qs:photos_9k":0,
    "qs:photos_9r":0,
    "qs:photos_all":0,
    "qs:photos_sr":0,
    "qs:placetype":"Town",
    "qs:pop_sr":"1",
    "qs:woe_adm0":23424787,
    "wof:name":"Jord\u00e1n",
    "wof:placetype":"locality",
    "wof:population":112
},
  "geometry": {"coordinates":[-73.09587999999999,6.733],"type":"Point"}
}