{
  "type": "Feature",
  "properties": {
    "gn:admin1_code":"35",
    "gn:admin2_code":"13654.0",
    "gn:asciiname":"Las Lauras",
    "gn:country_code":"CO",
    "gn:dem":351,
    "gn:feature_class":"P",
    "gn:feature_code":"PPL",
    "gn:name":"Las Lauras",
    "gn:population":0,
    "gn:timezone":"America/Bogota",
    "iso:country":"CO",
    "name:und_x_variant":[
        "Hacienda Las Lauras",
        "Las Lauras"
    ],
    "wof:name":"Las Lauras",
    "wof:placetype":"locality"
},
  "geometry": {"coordinates":[-75.17685,9.80593],"type":"Point"}
}