{
  "type": "Feature",
  "properties": {
    "gn:admin1_code":"12.0",
    "gn:admin2_code":"23001.0",
    "gn:asciiname":"Pueblo Mocho",
    "gn:country_code":"CO",
    "gn:dem":37,
    "gn:feature_class":"P",
    "gn:feature_code":"PPL",
    "gn:name":"Pueblo Mocho",
    "gn:population":0,
    "gn:timezone":"America/Bogota",
    "iso:country":"CO",
    "wof:name":"Pueblo Mocho",
    "wof:placetype":"locality"
},
  "geometry": {"coordinates":[-76.04389,8.44083],"type":"Point"}
}