{
  "type": "Feature",
  "properties": {
    "gn:admin1_code":"11.0",
    "gn:admin2_code":"27615.0",
    "gn:asciiname":"Tilupo",
    "gn:country_code":"CO",
    "gn:dem":87,
    "gn:feature_class":"P",
    "gn:feature_code":"PPL",
    "gn:name":"Tilupo",
    "gn:population":0,
    "gn:timezone":"America/Bogota",
    "iso:country":"CO",
    "wof:name":"Tilupo",
    "wof:placetype":"locality"
},
  "geometry": {"coordinates":[-77.12573,7.89833],"type":"Point"}
}