{
  "type": "Feature",
  "properties": {
    "gn:admin1_code":"33",
    "gn:admin2_code":"25312.0",
    "gn:asciiname":"Luchal",
    "gn:country_code":"CO",
    "gn:dem":2656,
    "gn:feature_class":"P",
    "gn:feature_code":"PPL",
    "gn:name":"Luchal",
    "gn:population":0,
    "gn:timezone":"America/Bogota",
    "iso:country":"CO",
    "wof:name":"Luchal",
    "wof:placetype":"locality"
},
  "geometry": {"coordinates":[-74.33333,4.55],"type":"Point"}
}