{
  "type": "Feature",
  "properties": {
    "gn:admin1_code":"8.0",
    "gn:admin2_code":"18205.0",
    "gn:asciiname":"La Maravilla",
    "gn:country_code":"CO",
    "gn:dem":225,
    "gn:feature_class":"P",
    "gn:feature_code":"PPL",
    "gn:name":"La Maravilla",
    "gn:population":0,
    "gn:timezone":"America/Bogota",
    "iso:country":"CO",
    "name:spa_x_preferred":[
        "La Maravilla"
    ],
    "wof:name":"La Maravilla",
    "wof:placetype":"locality"
},
  "geometry": {"coordinates":[-75.94938,1.03546],"type":"Point"}
}