{
  "type": "Feature",
  "properties": {
    "gn:admin1_code":"17",
    "gn:admin2_code":"44110.0",
    "gn:asciiname":"Los Barriales",
    "gn:country_code":"CO",
    "gn:dem":372,
    "gn:feature_class":"P",
    "gn:feature_code":"PPL",
    "gn:name":"Los Barriales",
    "gn:population":0,
    "gn:timezone":"America/Bogota",
    "iso:country":"CO",
    "wof:name":"Los Barriales",
    "wof:placetype":"locality"
},
  "geometry": {"coordinates":[-72.89055999999999,10.62194],"type":"Point"}
}