{
  "type": "Feature",
  "properties": {
    "gn:admin1_code":"9.0",
    "gn:admin2_code":"19050.0",
    "gn:asciiname":"Las Perlas",
    "gn:country_code":"CO",
    "gn:dem":1550,
    "gn:feature_class":"P",
    "gn:feature_code":"PPL",
    "gn:name":"Las Perlas",
    "gn:population":0,
    "gn:timezone":"America/Bogota",
    "iso:country":"CO",
    "name:rus_x_preferred":[
        "\u041b\u0430\u0441-\u041f\u0435\u0440\u043b\u0430\u0441"
    ],
    "name:spa_x_preferred":[
        "Las Perlas"
    ],
    "name:urd_x_preferred":[
        "\u0644\u0627\u0633 \u067e\u06cc\u0631\u0644\u0627\u0633"
    ],
    "wof:name":"Las Perlas",
    "wof:placetype":"locality"
},
  "geometry": {"coordinates":[-77.21441,2.27264],"type":"Point"}
}