{
  "type": "Feature",
  "properties": {
    "gn:admin1_code":"2",
    "gn:admin2_code":"5686.0",
    "gn:asciiname":"Hoyorrico",
    "gn:country_code":"CO",
    "gn:dem":2527,
    "gn:feature_class":"P",
    "gn:feature_code":"PPL",
    "gn:name":"Hoyorrico",
    "gn:population":0,
    "gn:timezone":"America/Bogota",
    "iso:country":"CO",
    "name:und_x_variant":[
        "Hoyo Rico",
        "Hoyorrico"
    ],
    "wof:name":"Hoyorrico",
    "wof:placetype":"locality"
},
  "geometry": {"coordinates":[-75.42607,6.60471],"type":"Point"}
}