{
  "type": "Feature",
  "properties": {
    "gn:admin1_code":"16.0",
    "gn:admin2_code":"41396.0",
    "gn:asciiname":"Las Juntas",
    "gn:country_code":"CO",
    "gn:dem":953,
    "gn:feature_class":"P",
    "gn:feature_code":"PPL",
    "gn:name":"Las Juntas",
    "gn:population":0,
    "gn:timezone":"America/Bogota",
    "iso:country":"CO",
    "name:ceb_x_preferred":[
        "Las Juntas"
    ],
    "name:deu_x_preferred":[
        "Las Juntas"
    ],
    "name:spa_x_preferred":[
        "Las Juntas"
    ],
    "name:swe_x_preferred":[
        "Las Juntas"
    ],
    "wof:name":"Las Juntas",
    "wof:placetype":"locality"
},
  "geometry": {"coordinates":[-75.85694000000002,2.42278],"type":"Point"}
}