{
  "type": "Feature",
  "properties": {
    "gn:admin1_code":"9.0",
    "gn:admin2_code":"19110.0",
    "gn:asciiname":"Timba",
    "gn:country_code":"CO",
    "gn:dem":1002,
    "gn:feature_class":"P",
    "gn:feature_code":"PPL",
    "gn:name":"Timba",
    "gn:population":0,
    "gn:timezone":"America/Bogota",
    "iso:country":"CO",
    "wof:name":"Timba",
    "wof:placetype":"locality"
},
  "geometry": {"coordinates":[-76.62621,3.11415],"type":"Point"}
}