{
  "type": "Feature",
  "properties": {
    "gn:admin1_code":"8",
    "gn:admin2_code":"18753.0",
    "gn:asciiname":"Quimbaya",
    "gn:country_code":"CO",
    "gn:dem":691,
    "gn:feature_class":"P",
    "gn:feature_code":"PPLL",
    "gn:name":"Quimbaya",
    "gn:population":0,
    "gn:timezone":"America/Bogota",
    "iso:country":"CO",
    "wof:name":"Quimbaya",
    "wof:placetype":"locality"
},
  "geometry": {"coordinates":[-74.85005,2.22307],"type":"Point"}
}