{
  "type": "Feature",
  "properties": {
    "gn:admin1_code":"33.0",
    "gn:admin2_code":"25473.0",
    "gn:asciiname":"La Holanda",
    "gn:country_code":"CO",
    "gn:dem":2540,
    "gn:feature_class":"P",
    "gn:feature_code":"PPL",
    "gn:name":"La Holanda",
    "gn:population":0,
    "gn:timezone":"America/Bogota",
    "iso:country":"CO",
    "name:spa_x_preferred":[
        "La Holanda"
    ],
    "wof:name":"La Holanda",
    "wof:placetype":"locality"
},
  "geometry": {"coordinates":[-74.23364000000002,4.69868],"type":"Point"}
}