{
  "type": "Feature",
  "properties": {
    "gn:admin1_code":"9.0",
    "gn:admin2_code":"19455.0",
    "gn:asciiname":"Potrerito",
    "gn:country_code":"CO",
    "gn:dem":1372,
    "gn:feature_class":"P",
    "gn:feature_code":"PPL",
    "gn:name":"Potrerito",
    "gn:population":0,
    "gn:timezone":"America/Bogota",
    "iso:country":"CO",
    "wof:name":"Potrerito",
    "wof:placetype":"locality"
},
  "geometry": {"coordinates":[-76.21056999999998,3.19733],"type":"Point"}
}