{
  "type": "Feature",
  "properties": {
    "gn:admin1_code":"20.0",
    "gn:admin2_code":"52227.0",
    "gn:asciiname":"Cristo Rey",
    "gn:country_code":"CO",
    "gn:dem":3253,
    "gn:feature_class":"P",
    "gn:feature_code":"PPL",
    "gn:name":"Cristo Rey",
    "gn:population":0,
    "gn:timezone":"America/Bogota",
    "iso:country":"CO",
    "name:ceb_x_preferred":[
        "Cristo Rey"
    ],
    "name:fra_x_preferred":[
        "Statue du Christ-Roi"
    ],
    "name:hun_x_preferred":[
        "Krisztus kir\u00e1ly szobor"
    ],
    "name:nds_x_preferred":[
        "Cristo Rey"
    ],
    "name:spa_x_preferred":[
        "Cristo Rey"
    ],
    "name:swe_x_preferred":[
        "Cristo Rey"
    ],
    "wof:name":"Cristo Rey",
    "wof:placetype":"locality"
},
  "geometry": {"coordinates":[-77.85757,0.81807],"type":"Point"}
}