{
  "type": "Feature",
  "properties": {
    "gn:admin1_code":"2.0",
    "gn:admin2_code":"5240.0",
    "gn:asciiname":"Bedoya",
    "gn:country_code":"CO",
    "gn:dem":2494,
    "gn:feature_class":"P",
    "gn:feature_code":"PPL",
    "gn:name":"Bedoya",
    "gn:population":0,
    "gn:timezone":"America/Bogota",
    "iso:country":"CO",
    "name:spa_x_preferred":[
        "Bedoya"
    ],
    "wof:name":"Bedoya",
    "wof:placetype":"locality"
},
  "geometry": {"coordinates":[-75.72586,6.28362],"type":"Point"}
}