{
  "type": "Feature",
  "properties": {
    "gn:admin1_code":"28.0",
    "gn:admin2_code":"73563.0",
    "gn:asciiname":"La Reforma",
    "gn:country_code":"CO",
    "gn:dem":518,
    "gn:feature_class":"P",
    "gn:feature_code":"PPLL",
    "gn:name":"La Reforma",
    "gn:population":0,
    "gn:timezone":"America/Bogota",
    "iso:country":"CO",
    "name:cym_x_preferred":[
        "La Reforma"
    ],
    "name:nld_x_preferred":[
        "Reforma"
    ],
    "name:por_x_preferred":[
        "La Reforma"
    ],
    "name:spa_x_preferred":[
        "La Reforma"
    ],
    "wof:name":"La Reforma",
    "wof:placetype":"locality"
},
  "geometry": {"coordinates":[-74.91615,3.71439],"type":"Point"}
}