{
  "type": "Feature",
  "properties": {
    "gn:admin1_code":"20",
    "gn:admin2_code":"52693.0",
    "gn:asciiname":"Antonio Narino",
    "gn:country_code":"CO",
    "gn:dem":1723,
    "gn:feature_class":"P",
    "gn:feature_code":"PPL",
    "gn:name":"Antonio Nari\u00f1o",
    "gn:population":0,
    "gn:timezone":"America/Bogota",
    "iso:country":"CO",
    "name:spa_x_preferred":[
        "Antonio Nari\u00f1o"
    ],
    "wof:name":"Antonio Narino",
    "wof:placetype":"locality"
},
  "geometry": {"coordinates":[-77.01739999999999,1.66324],"type":"Point"}
}