{
  "type": "Feature",
  "properties": {
    "gn:admin1_code":"12.0",
    "gn:admin2_code":"23807.0",
    "gn:asciiname":"Palmira",
    "gn:country_code":"CO",
    "gn:dem":73,
    "gn:feature_class":"P",
    "gn:feature_code":"PPL",
    "gn:name":"Palmira",
    "gn:population":0,
    "gn:timezone":"America/Bogota",
    "iso:country":"CO",
    "wof:name":"Palmira",
    "wof:placetype":"locality"
},
  "geometry": {"coordinates":[-76.02303000000001,8.11404],"type":"Point"}
}