{
  "type": "Feature",
  "properties": {
    "gn:admin1_code":"12.0",
    "gn:admin2_code":"23001.0",
    "gn:asciiname":"Los Taburetes",
    "gn:country_code":"CO",
    "gn:dem":35,
    "gn:feature_class":"P",
    "gn:feature_code":"PPL",
    "gn:name":"Los Taburetes",
    "gn:population":0,
    "gn:timezone":"America/Bogota",
    "iso:country":"CO",
    "wof:name":"Los Taburetes",
    "wof:placetype":"locality"
},
  "geometry": {"coordinates":[-76.04879,8.43048],"type":"Point"}
}