{
  "type": "Feature",
  "properties": {
    "iso:country":"CO",
    "name:ast_x_preferred":[
        "Tubar\u00e1"
    ],
    "name:ceb_x_preferred":[
        "Tubar\u00e1"
    ],
    "name:eng_x_preferred":[
        "Tubara"
    ],
    "name:eng_x_variant":[
        "Tubar\u00e1"
    ],
    "name:fas_x_preferred":[
        "\u062a\u0648\u0628\u0627\u0631\u0627"
    ],
    "name:fra_x_preferred":[
        "Tubar\u00e1"
    ],
    "name:gla_x_preferred":[
        "Tubar\u00e1"
    ],
    "name:ita_x_preferred":[
        "Tubar\u00e1"
    ],
    "name:kat_x_preferred":[
        "\u10e2\u10e3\u10d1\u10d0\u10e0\u10d0"
    ],
    "name:msa_x_preferred":[
        "Tubar\u00e1"
    ],
    "name:nan_x_preferred":[
        "Tubar\u00e1"
    ],
    "name:nld_x_preferred":[
        "Tubar\u00e1"
    ],
    "name:por_x_preferred":[
        "Tubar\u00e1"
    ],
    "name:rus_x_preferred":[
        "\u0422\u0443\u0431\u0430\u0440\u0430"
    ],
    "name:spa_x_preferred":[
        "Tubar\u00e1"
    ],
    "name:swe_x_preferred":[
        "Tubar\u00e1"
    ],
    "name:tgl_x_preferred":[
        "Tubar\u00e1"
    ],
    "name:urd_x_preferred":[
        "\u062a\u0648\u0628\u0627\u0631\u0627"
    ],
    "name:vie_x_preferred":[
        "Tubar\u00e1"
    ],
    "name:war_x_preferred":[
        "Tubar\u00e1"
    ],
    "name:zho_x_preferred":[
        "\u5716\u74e6\u62c9"
    ],
    "qs:gn_country":"CO",
    "qs:gn_fcode":"PPL",
    "qs:gn_pop":8180,
    "qs:name":"Tubar\u00e1",
    "qs:name_adm0":"Colombia",
    "qs:name_adm1":"Atlantico",
    "qs:photos":0,
    "qs:photos_1k":0,
    "qs:photos_9k":1,
    "qs:photos_9r":1,
    "qs:photos_all":15,
    "qs:photos_sr":0,
    "qs:placetype":"Town",
    "qs:pop_sr":"5",
    "qs:woe_adm0":23424787,
    "wof:name":"Tubar\u00e1",
    "wof:placetype":"locality",
    "wof:population":8180
},
  "geometry": {"coordinates":[-74.97889000000001,10.87444],"type":"Point"}
}