{
  "type": "Feature",
  "properties": {
    "gn:admin1_code":"16.0",
    "gn:admin2_code":"41306.0",
    "gn:asciiname":"La Falla",
    "gn:country_code":"CO",
    "gn:dem":656,
    "gn:feature_class":"P",
    "gn:feature_code":"PPL",
    "gn:name":"La Falla",
    "gn:population":0,
    "gn:timezone":"America/Bogota",
    "iso:country":"CO",
    "wof:name":"La Falla",
    "wof:placetype":"locality"
},
  "geometry": {"coordinates":[-75.57971999999999,2.37639],"type":"Point"}
}