{
  "type": "Feature",
  "properties": {
    "gn:admin1_code":"26",
    "gn:admin2_code":"68020.0",
    "gn:asciiname":"El Salvio",
    "gn:country_code":"CO",
    "gn:dem":2810,
    "gn:feature_class":"P",
    "gn:feature_code":"PPL",
    "gn:name":"El Salvio",
    "gn:population":0,
    "gn:timezone":"America/Bogota",
    "iso:country":"CO",
    "wof:name":"El Salvio",
    "wof:placetype":"locality"
},
  "geometry": {"coordinates":[-73.85139000000002,5.74361],"type":"Point"}
}