{
  "type": "Feature",
  "properties": {
    "gn:admin1_code":"11.0",
    "gn:admin2_code":"27001.0",
    "gn:asciiname":"Pacurita",
    "gn:country_code":"CO",
    "gn:dem":35,
    "gn:feature_class":"P",
    "gn:feature_code":"PPL",
    "gn:name":"Pacurita",
    "gn:population":0,
    "gn:timezone":"America/Bogota",
    "iso:country":"CO",
    "wof:name":"Pacurita",
    "wof:placetype":"locality"
},
  "geometry": {"coordinates":[-76.59599,5.68218],"type":"Point"}
}