{
  "type": "Feature",
  "properties": {
    "gn:admin1_code":"3",
    "gn:admin2_code":"81220.0",
    "gn:asciiname":"La Sonrisa",
    "gn:country_code":"CO",
    "gn:dem":111,
    "gn:feature_class":"P",
    "gn:feature_code":"PPL",
    "gn:name":"La Sonrisa",
    "gn:population":0,
    "gn:timezone":"America/Bogota",
    "iso:country":"CO",
    "wof:name":"La Sonrisa",
    "wof:placetype":"locality"
},
  "geometry": {"coordinates":[-70.48985999999999,6.43677],"type":"Point"}
}