{
  "type": "Feature",
  "properties": {
    "gn:admin1_code":"36.0",
    "gn:admin2_code":"15667.0",
    "gn:asciiname":"Guichirales",
    "gn:country_code":"CO",
    "gn:dem":430,
    "gn:feature_class":"P",
    "gn:feature_code":"PPL",
    "gn:name":"Guichirales",
    "gn:population":0,
    "gn:timezone":"America/Bogota",
    "iso:country":"CO",
    "wof:name":"Guichirales",
    "wof:placetype":"locality"
},
  "geometry": {"coordinates":[-73.12486,4.85077],"type":"Point"}
}