{
  "type": "Feature",
  "properties": {
    "gn:admin1_code":"8",
    "gn:admin2_code":"18094.0",
    "gn:asciiname":"La Miranda",
    "gn:country_code":"CO",
    "gn:dem":232,
    "gn:feature_class":"P",
    "gn:feature_code":"PPL",
    "gn:name":"La Miranda",
    "gn:population":0,
    "gn:timezone":"America/Bogota",
    "iso:country":"CO",
    "name:spa_x_preferred":[
        "La Miranda"
    ],
    "name:zho_x_preferred":[
        "\u62c9\u7c73\u862d\u9054\u5c71"
    ],
    "wof:name":"La Miranda",
    "wof:placetype":"locality"
},
  "geometry": {"coordinates":[-75.74743000000002,1.22686],"type":"Point"}
}