{
  "type": "Feature",
  "properties": {
    "gn:admin1_code":"27.0",
    "gn:admin2_code":"70508.0",
    "gn:asciiname":"Pospos",
    "gn:country_code":"CO",
    "gn:dem":127,
    "gn:feature_class":"P",
    "gn:feature_code":"PPL",
    "gn:name":"Pospos",
    "gn:population":0,
    "gn:timezone":"America/Bogota",
    "iso:country":"CO",
    "wof:name":"Pospos",
    "wof:placetype":"locality"
},
  "geometry": {"coordinates":[-75.06667,9.51667],"type":"Point"}
}