{
  "type": "Feature",
  "properties": {
    "gn:admin1_code":"35",
    "gn:admin2_code":"13006.0",
    "gn:asciiname":"Centro Alegre",
    "gn:country_code":"CO",
    "gn:dem":22,
    "gn:feature_class":"P",
    "gn:feature_code":"PPL",
    "gn:name":"Centro Alegre",
    "gn:population":0,
    "gn:timezone":"America/Bogota",
    "iso:country":"CO",
    "name:und_x_variant":[
        "Campo Alegre",
        "Caserio Centro Alegre",
        "Centro Alegre"
    ],
    "wof:name":"Centro Alegre",
    "wof:placetype":"locality"
},
  "geometry": {"coordinates":[-74.49384000000001,8.50496],"type":"Point"}
}