{
  "type": "Feature",
  "properties": {
    "gn:admin1_code":"32",
    "gn:admin2_code":"85010.0",
    "gn:asciiname":"La Graciela",
    "gn:country_code":"CO",
    "gn:dem":199,
    "gn:feature_class":"P",
    "gn:feature_code":"PPL",
    "gn:name":"La Graciela",
    "gn:population":0,
    "gn:timezone":"America/Bogota",
    "iso:country":"CO",
    "wof:name":"La Graciela",
    "wof:placetype":"locality"
},
  "geometry": {"coordinates":[-72.4674,4.88372],"type":"Point"}
}