{
  "type": "Feature",
  "properties": {
    "gn:admin1_code":"36",
    "gn:asciiname":"La Escuadra",
    "gn:country_code":"CO",
    "gn:dem":276,
    "gn:feature_class":"P",
    "gn:feature_code":"PPL",
    "gn:name":"La Escuadra",
    "gn:population":0,
    "gn:timezone":"America/Bogota",
    "iso:country":"CO",
    "wof:name":"La Escuadra",
    "wof:placetype":"locality"
},
  "geometry": {"coordinates":[-74.33551,5.82798],"type":"Point"}
}