{
  "type": "Feature",
  "properties": {
    "gn:admin1_code":"28.0",
    "gn:asciiname":"Vereda La Ruidosa",
    "gn:country_code":"CO",
    "gn:dem":819,
    "gn:feature_class":"P",
    "gn:feature_code":"PPLL",
    "gn:name":"Vereda La Ruidosa",
    "gn:population":0,
    "gn:timezone":"America/Bogota",
    "iso:country":"CO",
    "name:spa_x_preferred":[
        "Vereda La Ruidosa"
    ],
    "wof:name":"Vereda La Ruidosa",
    "wof:placetype":"locality"
},
  "geometry": {"coordinates":[-74.48165,4.48648],"type":"Point"}
}