{
  "type": "Feature",
  "properties": {
    "gn:admin1_code":"2.0",
    "gn:admin2_code":"5045.0",
    "gn:asciiname":"Campo Alegre",
    "gn:country_code":"CO",
    "gn:dem":29,
    "gn:feature_class":"P",
    "gn:feature_code":"PPL",
    "gn:name":"Campo Alegre",
    "gn:population":0,
    "gn:timezone":"America/Bogota",
    "iso:country":"CO",
    "wof:name":"Campo Alegre",
    "wof:placetype":"locality"
},
  "geometry": {"coordinates":[-76.63556,7.8625],"type":"Point"}
}