{
  "type": "Feature",
  "properties": {
    "gn:admin1_code":"22.0",
    "gn:admin2_code":"86568.0",
    "gn:asciiname":"Concaya",
    "gn:country_code":"CO",
    "gn:dem":255,
    "gn:feature_class":"P",
    "gn:feature_code":"PPL",
    "gn:name":"Concaya",
    "gn:population":0,
    "gn:timezone":"America/Bogota",
    "iso:country":"CO",
    "wof:name":"Concaya",
    "wof:placetype":"locality"
},
  "geometry": {"coordinates":[-76.49036,0.54065],"type":"Point"}
}