{
  "type": "Feature",
  "properties": {
    "gn:admin1_code":"2.0",
    "gn:admin2_code":"5172.0",
    "gn:asciiname":"Bohio",
    "gn:country_code":"CO",
    "gn:dem":7,
    "gn:feature_class":"P",
    "gn:feature_code":"PPL",
    "gn:name":"Boh\u00edo",
    "gn:population":0,
    "gn:timezone":"America/Bogota",
    "iso:country":"CO",
    "wof:name":"Bohio",
    "wof:placetype":"locality"
},
  "geometry": {"coordinates":[-76.77360999999998,7.63417],"type":"Point"}
}