{
  "type": "Feature",
  "properties": {
    "gn:admin1_code":"20.0",
    "gn:admin2_code":"52233.0",
    "gn:asciiname":"Cristo Rey",
    "gn:country_code":"CO",
    "gn:dem":1412,
    "gn:feature_class":"P",
    "gn:feature_code":"PPL",
    "gn:name":"Cristo Rey",
    "gn:population":0,
    "gn:timezone":"America/Bogota",
    "iso:country":"CO",
    "wof:name":"Cristo Rey",
    "wof:placetype":"locality"
},
  "geometry": {"coordinates":[-77.56305,1.69366],"type":"Point"}
}