{
  "type": "Feature",
  "properties": {
    "gn:admin1_code":"10.0",
    "gn:asciiname":"La Estacion",
    "gn:country_code":"CO",
    "gn:dem":91,
    "gn:feature_class":"P",
    "gn:feature_code":"PPL",
    "gn:name":"La Estaci\u00f3n",
    "gn:population":0,
    "gn:timezone":"America/Bogota",
    "iso:country":"CO",
    "wof:name":"La Estacion",
    "wof:placetype":"locality"
},
  "geometry": {"coordinates":[-74.04321999999998,9.70292],"type":"Point"}
}