{
  "type": "Feature",
  "properties": {
    "gn:admin1_code":"28.0",
    "gn:admin2_code":"73236.0",
    "gn:asciiname":"Cuchilla Bandoleros",
    "gn:country_code":"CO",
    "gn:dem":990,
    "gn:feature_class":"P",
    "gn:feature_code":"PPLL",
    "gn:name":"Cuchilla Bandoleros",
    "gn:population":0,
    "gn:timezone":"America/Bogota",
    "iso:country":"CO",
    "name:spa_x_preferred":[
        "Cuchilla Bandoleros"
    ],
    "wof:name":"Cuchilla Bandoleros",
    "wof:placetype":"locality"
},
  "geometry": {"coordinates":[-74.96905,3.52574],"type":"Point"}
}