{
  "type": "Feature",
  "properties": {
    "gn:admin1_code":"16",
    "gn:admin2_code":"41016.0",
    "gn:asciiname":"Mirador",
    "gn:country_code":"CO",
    "gn:dem":623,
    "gn:feature_class":"P",
    "gn:feature_code":"PPL",
    "gn:name":"Mirador",
    "gn:population":0,
    "gn:timezone":"America/Bogota",
    "iso:country":"CO",
    "wof:name":"Mirador",
    "wof:placetype":"locality"
},
  "geometry": {"coordinates":[-75.36209000000002,3.12672],"type":"Point"}
}