{
  "type": "Feature",
  "properties": {
    "gn:admin1_code":"12.0",
    "gn:admin2_code":"23168.0",
    "gn:asciiname":"Paula Verde",
    "gn:country_code":"CO",
    "gn:dem":5,
    "gn:feature_class":"P",
    "gn:feature_code":"PPL",
    "gn:name":"Paula Verde",
    "gn:population":0,
    "gn:timezone":"America/Bogota",
    "iso:country":"CO",
    "wof:name":"Paula Verde",
    "wof:placetype":"locality"
},
  "geometry": {"coordinates":[-75.71666999999999,9.01667],"type":"Point"}
}