{
  "type": "Feature",
  "properties": {
    "gn:admin1_code":"33.0",
    "gn:admin2_code":"25339.0",
    "gn:asciiname":"El Carmen Arriba",
    "gn:country_code":"CO",
    "gn:dem":2250,
    "gn:feature_class":"P",
    "gn:feature_code":"PPL",
    "gn:name":"El Carmen Arriba",
    "gn:population":0,
    "gn:timezone":"America/Bogota",
    "iso:country":"CO",
    "name:spa_x_preferred":[
        "El Carmen Arriba"
    ],
    "wof:name":"El Carmen Arriba",
    "wof:placetype":"locality"
},
  "geometry": {"coordinates":[-73.97816999999998,4.24655],"type":"Point"}
}