{
  "type": "Feature",
  "properties": {
    "gn:admin1_code":"38",
    "gn:admin2_code":"47053.0",
    "gn:asciiname":"Arizona",
    "gn:country_code":"CO",
    "gn:dem":64,
    "gn:feature_class":"P",
    "gn:feature_code":"PPL",
    "gn:name":"Arizona",
    "gn:population":0,
    "gn:timezone":"America/Bogota",
    "iso:country":"CO",
    "name:und_x_variant":[
        "Hacienda Arizona",
        "Arizona"
    ],
    "wof:name":"Arizona",
    "wof:placetype":"locality"
},
  "geometry": {"coordinates":[-74.13696,10.57197],"type":"Point"}
}