{
  "type": "Feature",
  "properties": {
    "iso:country":"CO",
    "name:ceb_x_preferred":[
        "Yavarat\u00e9"
    ],
    "name:cym_x_preferred":[
        "Yavarate"
    ],
    "name:eng_x_preferred":[
        "Yavarate"
    ],
    "name:fas_x_preferred":[
        "\u06cc\u0627\u0648\u0627\u0631\u0627\u062a\u0647"
    ],
    "name:fra_x_preferred":[
        "Yavarat\u00e9"
    ],
    "name:ita_x_preferred":[
        "Yavarat\u00e9"
    ],
    "name:kat_x_preferred":[
        "\u10d8\u10d0\u10d5\u10d0\u10e0\u10d0\u10e2\u10d4"
    ],
    "name:msa_x_preferred":[
        "Yavarate"
    ],
    "name:nan_x_preferred":[
        "Yavarat\u00e9"
    ],
    "name:nld_x_preferred":[
        "Yavarat\u00e9"
    ],
    "name:rus_x_preferred":[
        "\u042f\u0432\u0430\u0440\u0430\u0442\u0435"
    ],
    "name:sco_x_preferred":[
        "Yavarate"
    ],
    "name:spa_x_preferred":[
        "Yavarat\u00e9"
    ],
    "name:swe_x_preferred":[
        "Yavarat\u00e9"
    ],
    "name:urd_x_preferred":[
        "\u06cc\u0648\u0631\u0627\u062a\u06d2"
    ],
    "name:vie_x_preferred":[
        "Yavarat\u00e9"
    ],
    "name:war_x_preferred":[
        "Yavarate"
    ],
    "name:zho_min_nan_x_preferred":[
        "Yavarat\u00e9"
    ],
    "name:zho_x_preferred":[
        "\u4e9e\u74e6\u62c9\u7279"
    ],
    "qs:gn_country":"CO",
    "qs:gn_fcode":"PPL",
    "qs:gn_pop":38,
    "qs:name":"Yavarat\u00e9",
    "qs:name_adm0":"Colombia",
    "qs:name_adm1":"Vaupes",
    "qs:photos":0,
    "qs:photos_1k":0,
    "qs:photos_9k":0,
    "qs:photos_9r":0,
    "qs:photos_all":0,
    "qs:photos_sr":0,
    "qs:placetype":"Town",
    "qs:pop_sr":"1",
    "qs:woe_adm0":23424787,
    "wd:wordcount":71,
    "wof:name":"Yavarat\u00e9",
    "wof:placetype":"locality",
    "wof:population":38
},
  "geometry": {"coordinates":[-69.20806,0.615],"type":"Point"}
}