{
  "type": "Feature",
  "properties": {
    "gn:admin1_code":"2.0",
    "gn:admin2_code":"5837.0",
    "gn:asciiname":"Juan Moreno",
    "gn:country_code":"CO",
    "gn:dem":12,
    "gn:feature_class":"P",
    "gn:feature_code":"PPL",
    "gn:name":"Juan Moreno",
    "gn:population":0,
    "gn:timezone":"America/Bogota",
    "iso:country":"CO",
    "name:spa_x_preferred":[
        "Juan Moreno"
    ],
    "wof:name":"Juan Moreno",
    "wof:placetype":"locality"
},
  "geometry": {"coordinates":[-76.69295,8.00292],"type":"Point"}
}