{
  "type": "Feature",
  "properties": {
    "gn:admin1_code":"15.0",
    "gn:admin2_code":"94888.0",
    "gn:asciiname":"Puerto Valencia",
    "gn:country_code":"CO",
    "gn:dem":151,
    "gn:feature_class":"P",
    "gn:feature_code":"PPL",
    "gn:name":"Puerto Valencia",
    "gn:population":0,
    "gn:timezone":"America/Bogota",
    "iso:country":"CO",
    "wof:name":"Puerto Valencia",
    "wof:placetype":"locality"
},
  "geometry": {"coordinates":[-69.65000000000001,2.55],"type":"Point"}
}