{
  "type": "Feature",
  "properties": {
    "gn:admin1_code":"2.0",
    "gn:admin2_code":"5036.0",
    "gn:asciiname":"Quebrada Balastera",
    "gn:country_code":"CO",
    "gn:dem":1736,
    "gn:feature_class":"P",
    "gn:feature_code":"PPL",
    "gn:name":"Quebrada Balastera",
    "gn:population":0,
    "gn:timezone":"America/Bogota",
    "iso:country":"CO",
    "name:spa_x_preferred":[
        "Quebrada Balastera"
    ],
    "name:und_x_variant":[
        "Quebrada Mazo"
    ],
    "wof:name":"Quebrada Balastera",
    "wof:placetype":"locality"
},
  "geometry": {"coordinates":[-75.70640999999998,6.10098],"type":"Point"}
}