{
  "type": "Feature",
  "properties": {
    "gn:admin1_code":"36",
    "gn:asciiname":"El Cape",
    "gn:country_code":"CO",
    "gn:dem":2920,
    "gn:feature_class":"P",
    "gn:feature_code":"PPL",
    "gn:name":"El Cape",
    "gn:population":0,
    "gn:timezone":"America/Bogota",
    "iso:country":"CO",
    "wof:name":"El Cape",
    "wof:placetype":"locality"
},
  "geometry": {"coordinates":[-73.90528,5.51611],"type":"Point"}
}