{
  "type": "Feature",
  "properties": {
    "gn:admin1_code":"29",
    "gn:admin2_code":"76111.0",
    "gn:asciiname":"Laureles",
    "gn:country_code":"CO",
    "gn:dem":3448,
    "gn:feature_class":"P",
    "gn:feature_code":"PPL",
    "gn:name":"Laureles",
    "gn:population":0,
    "gn:timezone":"America/Bogota",
    "iso:country":"CO",
    "name:ceb_x_preferred":[
        "Laureles"
    ],
    "name:eus_x_preferred":[
        "Laureles"
    ],
    "name:ita_x_preferred":[
        "Laureles"
    ],
    "name:por_x_preferred":[
        "Laureles"
    ],
    "name:spa_x_preferred":[
        "Laureles"
    ],
    "name:zho_x_preferred":[
        "\u52de\u96f7\u840a\u65af"
    ],
    "wof:name":"Laureles",
    "wof:placetype":"locality"
},
  "geometry": {"coordinates":[-76.06806,3.79278],"type":"Point"}
}