{
  "type": "Feature",
  "properties": {
    "gn:admin1_code":"29.0",
    "gn:admin2_code":"76041.0",
    "gn:asciiname":"Calabazas",
    "gn:country_code":"CO",
    "gn:dem":915,
    "gn:feature_class":"P",
    "gn:feature_code":"PPL",
    "gn:name":"Calabazas",
    "gn:population":0,
    "gn:timezone":"America/Bogota",
    "iso:country":"CO",
    "wof:name":"Calabazas",
    "wof:placetype":"locality"
},
  "geometry": {"coordinates":[-75.91639000000001,4.82694],"type":"Point"}
}