{
  "type": "Feature",
  "properties": {
    "gn:admin1_code":"17",
    "gn:admin2_code":"44090.0",
    "gn:asciiname":"Jesus del Mar",
    "gn:cc2":"CO",
    "gn:country_code":"CO",
    "gn:dem":26,
    "gn:feature_class":"P",
    "gn:feature_code":"PPL",
    "gn:name":"Jes\u00fas del Mar",
    "gn:population":0,
    "gn:timezone":"America/Bogota",
    "iso:country":"CO",
    "name:und_x_variant":[
        "Hacienda Altapino",
        "Hacienda Jesus del Mar",
        "Jes\u00fas del Mar"
    ],
    "wof:name":"Jesus del Mar",
    "wof:placetype":"locality"
},
  "geometry": {"coordinates":[-73.19722,11.23528],"type":"Point"}
}