{
  "type": "Feature",
  "properties": {
    "gn:admin1_code":"36",
    "gn:admin2_code":"15632.0",
    "gn:asciiname":"Merchan Bajo",
    "gn:country_code":"CO",
    "gn:dem":2793,
    "gn:feature_class":"P",
    "gn:feature_code":"PPL",
    "gn:name":"Merch\u00e1n Bajo",
    "gn:population":0,
    "gn:timezone":"America/Bogota",
    "iso:country":"CO",
    "wof:name":"Merchan Bajo",
    "wof:placetype":"locality"
},
  "geometry": {"coordinates":[-73.71666999999999,5.69278],"type":"Point"}
}