{
  "type": "Feature",
  "properties": {
    "iso:country":"CO",
    "name:ast_x_preferred":[
        "Floresta"
    ],
    "name:ceb_x_preferred":[
        "Floresta"
    ],
    "name:eng_x_preferred":[
        "Floresta"
    ],
    "name:fra_x_preferred":[
        "Floresta"
    ],
    "name:ita_x_preferred":[
        "Floresta"
    ],
    "name:jpn_x_preferred":[
        "\u30d5\u30ed\u30ec\u30b9\u30bf"
    ],
    "name:kat_x_preferred":[
        "\u10e4\u10da\u10dd\u10e0\u10d4\u10e1\u10e2\u10d0"
    ],
    "name:msa_x_preferred":[
        "Floresta"
    ],
    "name:nan_x_preferred":[
        "Floresta"
    ],
    "name:nld_x_preferred":[
        "Floresta"
    ],
    "name:por_x_preferred":[
        "Floresta"
    ],
    "name:rus_x_preferred":[
        "\u0424\u043b\u043e\u0440\u0435\u0441\u0442\u0430"
    ],
    "name:spa_x_preferred":[
        "Floresta"
    ],
    "name:swe_x_preferred":[
        "Floresta"
    ],
    "name:tgl_x_preferred":[
        "Floresta"
    ],
    "name:war_x_preferred":[
        "Floresta"
    ],
    "name:zho_x_preferred":[
        "\u5f17\u7f85\u96f7\u65af\u5854"
    ],
    "qs:gn_country":"CO",
    "qs:gn_fcode":"PPL",
    "qs:gn_pop":1127,
    "qs:name":"Floresta",
    "qs:name_adm0":"Colombia",
    "qs:name_adm1":"Boyaca",
    "qs:photos":0,
    "qs:photos_1k":0,
    "qs:photos_9k":1,
    "qs:photos_9r":3,
    "qs:photos_all":93,
    "qs:photos_sr":0,
    "qs:placetype":"Town",
    "qs:pop_sr":"3",
    "qs:woe_adm0":23424787,
    "wof:name":"Floresta",
    "wof:placetype":"locality",
    "wof:population":1127
},
  "geometry": {"coordinates":[-72.91882,5.85903],"type":"Point"}
}