{
  "type": "Feature",
  "properties": {
    "gn:admin1_code":"35.0",
    "gn:admin2_code":"13549.0",
    "gn:asciiname":"Palenquito",
    "gn:country_code":"CO",
    "gn:dem":16,
    "gn:feature_class":"P",
    "gn:feature_code":"PPL",
    "gn:name":"Palenquito",
    "gn:population":0,
    "gn:timezone":"America/Bogota",
    "iso:country":"CO",
    "wof:name":"Palenquito",
    "wof:placetype":"locality"
},
  "geometry": {"coordinates":[-74.46739000000002,8.99455],"type":"Point"}
}