{
  "type": "Feature",
  "properties": {
    "gn:admin1_code":"29",
    "gn:admin2_code":"76111.0",
    "gn:asciiname":"Santa Helena",
    "gn:country_code":"CO",
    "gn:dem":3096,
    "gn:feature_class":"P",
    "gn:feature_code":"PPL",
    "gn:name":"Santa Helena",
    "gn:population":0,
    "gn:timezone":"America/Bogota",
    "iso:country":"CO",
    "wof:name":"Santa Helena",
    "wof:placetype":"locality"
},
  "geometry": {"coordinates":[-75.87721999999999,3.925],"type":"Point"}
}