{
  "type": "Feature",
  "properties": {
    "gn:admin1_code":"28.0",
    "gn:admin2_code":"73168.0",
    "gn:asciiname":"El Canelo",
    "gn:country_code":"CO",
    "gn:dem":1168,
    "gn:feature_class":"P",
    "gn:feature_code":"PPL",
    "gn:name":"El Canelo",
    "gn:population":0,
    "gn:timezone":"America/Bogota",
    "iso:country":"CO",
    "wof:name":"El Canelo",
    "wof:placetype":"locality"
},
  "geometry": {"coordinates":[-75.59111,3.74417],"type":"Point"}
}