{
  "type": "Feature",
  "properties": {
    "gn:admin1_code":"33.0",
    "gn:admin2_code":"25524.0",
    "gn:asciiname":"La Corelia",
    "gn:country_code":"CO",
    "gn:dem":1124,
    "gn:feature_class":"P",
    "gn:feature_code":"PPL",
    "gn:name":"La Corelia",
    "gn:population":0,
    "gn:timezone":"America/Bogota",
    "iso:country":"CO",
    "name:spa_x_preferred":[
        "La Corelia"
    ],
    "wof:name":"La Corelia",
    "wof:placetype":"locality"
},
  "geometry": {"coordinates":[-74.49500999999999,4.21661],"type":"Point"}
}