{
  "type": "Feature",
  "properties": {
    "gn:admin1_code":"2.0",
    "gn:admin2_code":"5113.0",
    "gn:asciiname":"Remolino",
    "gn:country_code":"CO",
    "gn:dem":427,
    "gn:feature_class":"P",
    "gn:feature_code":"PPL",
    "gn:name":"Remolino",
    "gn:population":0,
    "gn:timezone":"America/Bogota",
    "iso:country":"CO",
    "wof:name":"Remolino",
    "wof:placetype":"locality"
},
  "geometry": {"coordinates":[-75.83333,6.68333],"type":"Point"}
}