{
  "type": "Feature",
  "properties": {
    "gn:admin1_code":"28",
    "gn:admin2_code":"73168.0",
    "gn:asciiname":"Versalles",
    "gn:country_code":"CO",
    "gn:dem":2322,
    "gn:feature_class":"P",
    "gn:feature_code":"PPL",
    "gn:name":"Versalles",
    "gn:population":0,
    "gn:timezone":"America/Bogota",
    "iso:country":"CO",
    "wof:name":"Versalles",
    "wof:placetype":"locality"
},
  "geometry": {"coordinates":[-75.68694000000001,3.91667],"type":"Point"}
}