{
  "type": "Feature",
  "properties": {
    "iso:country":"CO",
    "name:ast_x_preferred":[
        "Planadas"
    ],
    "name:avk_x_preferred":[
        "Planadas"
    ],
    "name:ceb_x_preferred":[
        "Planadas"
    ],
    "name:deu_x_preferred":[
        "Planadas"
    ],
    "name:eng_x_preferred":[
        "Planadas"
    ],
    "name:fas_x_preferred":[
        "\u067e\u0644\u0627\u0646\u0627\u062f\u0627\u0633"
    ],
    "name:fra_x_preferred":[
        "Planadas"
    ],
    "name:gle_x_preferred":[
        "Planadas"
    ],
    "name:ita_x_preferred":[
        "Planadas"
    ],
    "name:kat_x_preferred":[
        "\u10de\u10da\u10d0\u10dc\u10d0\u10d3\u10d0\u10e1\u10d8"
    ],
    "name:msa_x_preferred":[
        "Planadas"
    ],
    "name:nan_x_preferred":[
        "Planadas"
    ],
    "name:nld_x_preferred":[
        "Planadas"
    ],
    "name:pol_x_preferred":[
        "Planadas"
    ],
    "name:spa_x_preferred":[
        "Planadas"
    ],
    "name:swe_x_preferred":[
        "Planadas"
    ],
    "name:vie_x_preferred":[
        "Planadas"
    ],
    "name:war_x_preferred":[
        "Planadas"
    ],
    "name:zho_min_nan_x_preferred":[
        "Planadas"
    ],
    "name:zho_x_preferred":[
        "\u666e\u62c9\u7d0d\u9054"
    ],
    "qs:gn_country":"CO",
    "qs:gn_fcode":"PPL",
    "qs:gn_pop":9709,
    "qs:name":"Planadas",
    "qs:name_adm0":"Colombia",
    "qs:name_adm1":"Tolima",
    "qs:photos":0,
    "qs:photos_1k":0,
    "qs:photos_9k":0,
    "qs:photos_9r":0,
    "qs:photos_all":0,
    "qs:photos_sr":0,
    "qs:placetype":"Town",
    "qs:pop_sr":"5",
    "qs:woe_adm0":23424787,
    "wd:wordcount":410,
    "wof:name":"Planadas",
    "wof:placetype":"locality",
    "wof:population":9709
},
  "geometry": {"coordinates":[-75.64506,3.19698],"type":"Point"}
}