{
  "type": "Feature",
  "properties": {
    "gn:admin1_code":"31.0",
    "gn:admin2_code":"99001.0",
    "gn:asciiname":"Monserrate",
    "gn:country_code":"CO",
    "gn:dem":77,
    "gn:feature_class":"P",
    "gn:feature_code":"PPL",
    "gn:name":"Monserrate",
    "gn:population":0,
    "gn:timezone":"America/Bogota",
    "iso:country":"CO",
    "name:spa_x_preferred":[
        "Monserrate"
    ],
    "wof:name":"Monserrate",
    "wof:placetype":"locality"
},
  "geometry": {"coordinates":[-67.91056,6.20455],"type":"Point"}
}