{
  "type": "Feature",
  "properties": {
    "gn:admin1_code":"20.0",
    "gn:admin2_code":"52320.0",
    "gn:asciiname":"San Alejandro",
    "gn:country_code":"CO",
    "gn:dem":2280,
    "gn:feature_class":"P",
    "gn:feature_code":"PPL",
    "gn:name":"San Alejandro",
    "gn:population":0,
    "gn:timezone":"America/Bogota",
    "iso:country":"CO",
    "wof:name":"San Alejandro",
    "wof:placetype":"locality"
},
  "geometry": {"coordinates":[-77.51191999999998,1.16255],"type":"Point"}
}