{
  "type": "Feature",
  "properties": {
    "gn:admin1_code":"35.0",
    "gn:admin2_code":"13549.0",
    "gn:asciiname":"Rufina Nuevo",
    "gn:country_code":"CO",
    "gn:dem":63,
    "gn:feature_class":"P",
    "gn:feature_code":"PPL",
    "gn:name":"Rufina Nuevo",
    "gn:population":0,
    "gn:timezone":"America/Bogota",
    "iso:country":"CO",
    "name:und_x_variant":[
        "Caserio Rufina Nuevo",
        "Rufina Nuevo"
    ],
    "wof:name":"Rufina Nuevo",
    "wof:placetype":"locality"
},
  "geometry": {"coordinates":[-74.26775000000001,8.696],"type":"Point"}
}