{
  "type": "Feature",
  "properties": {
    "gn:admin1_code":"35",
    "gn:admin2_code":"13657.0",
    "gn:asciiname":"El Ceibal",
    "gn:country_code":"CO",
    "gn:dem":188,
    "gn:feature_class":"P",
    "gn:feature_code":"PPL",
    "gn:name":"El Ceibal",
    "gn:population":0,
    "gn:timezone":"America/Bogota",
    "iso:country":"CO",
    "wof:name":"El Ceibal",
    "wof:placetype":"locality"
},
  "geometry": {"coordinates":[-75.08333,10.06667],"type":"Point"}
}