{
  "type": "Feature",
  "properties": {
    "gn:admin1_code":"12.0",
    "gn:admin2_code":"23570.0",
    "gn:asciiname":"El Palmar",
    "gn:country_code":"CO",
    "gn:dem":127,
    "gn:feature_class":"P",
    "gn:feature_code":"PPLL",
    "gn:name":"El Palmar",
    "gn:population":0,
    "gn:timezone":"America/Bogota",
    "iso:country":"CO",
    "name:ceb_x_preferred":[
        "El Palmar"
    ],
    "name:fra_x_preferred":[
        "El Palmar"
    ],
    "name:glg_x_preferred":[
        "El Palmar"
    ],
    "name:lit_x_preferred":[
        "El Palmaras"
    ],
    "name:spa_x_preferred":[
        "El Palmar"
    ],
    "name:srp_x_preferred":[
        "\u0415\u043b \u041f\u0430\u043b\u043c\u0430\u0440"
    ],
    "name:swe_x_preferred":[
        "El Palmar"
    ],
    "wof:name":"El Palmar",
    "wof:placetype":"locality"
},
  "geometry": {"coordinates":[-75.57915,8.56712],"type":"Point"}
}