{
  "type": "Feature",
  "properties": {
    "gn:admin1_code":"10",
    "gn:admin2_code":"20045.0",
    "gn:asciiname":"La Guajira",
    "gn:country_code":"CO",
    "gn:dem":86,
    "gn:feature_class":"P",
    "gn:feature_code":"PPL",
    "gn:name":"La Guajira",
    "gn:population":0,
    "gn:timezone":"America/Bogota",
    "iso:country":"CO",
    "wof:name":"La Guajira",
    "wof:placetype":"locality"
},
  "geometry": {"coordinates":[-73.31896999999999,9.75213],"type":"Point"}
}