{
  "type": "Feature",
  "properties": {
    "gn:admin1_code":"20.0",
    "gn:admin2_code":"52418.0",
    "gn:asciiname":"Arrayanal",
    "gn:country_code":"CO",
    "gn:dem":2801,
    "gn:feature_class":"P",
    "gn:feature_code":"PPL",
    "gn:name":"Arrayanal",
    "gn:population":0,
    "gn:timezone":"America/Bogota",
    "iso:country":"CO",
    "wof:name":"Arrayanal",
    "wof:placetype":"locality"
},
  "geometry": {"coordinates":[-77.57993,1.52896],"type":"Point"}
}