{
  "type": "Feature",
  "properties": {
    "gn:admin1_code":"20",
    "gn:admin2_code":"52250.0",
    "gn:asciiname":"Los Gongoras",
    "gn:country_code":"CO",
    "gn:dem":1429,
    "gn:feature_class":"P",
    "gn:feature_code":"PPL",
    "gn:name":"Los G\u00f3ngoras",
    "gn:population":0,
    "gn:timezone":"America/Bogota",
    "iso:country":"CO",
    "name:und_x_variant":[
        "Los Congoras",
        "Los Congares",
        "Los G\u00f3ngoras"
    ],
    "wof:name":"Los Gongoras",
    "wof:placetype":"locality"
},
  "geometry": {"coordinates":[-77.47111,2.05638],"type":"Point"}
}