{
  "type": "Feature",
  "properties": {
    "gn:admin1_code":"2.0",
    "gn:admin2_code":"5284.0",
    "gn:asciiname":"Murri",
    "gn:cc2":"CO",
    "gn:country_code":"CO",
    "gn:dem":788,
    "gn:feature_class":"P",
    "gn:feature_code":"PPL",
    "gn:name":"Murr\u00ed",
    "gn:population":0,
    "gn:timezone":"America/Bogota",
    "iso:country":"CO",
    "name:und_x_variant":[
        "Murr\u00ed Alto",
        "Murr\u00ed"
    ],
    "wof:name":"Murri",
    "wof:placetype":"locality"
},
  "geometry": {"coordinates":[-76.36889000000002,6.74499],"type":"Point"}
}