{
  "type": "Feature",
  "properties": {
    "gn:admin1_code":"29",
    "gn:admin2_code":"76670.0",
    "gn:asciiname":"Angosturas",
    "gn:country_code":"CO",
    "gn:dem":1262,
    "gn:feature_class":"P",
    "gn:feature_code":"PPL",
    "gn:name":"Angosturas",
    "gn:population":0,
    "gn:timezone":"America/Bogota",
    "iso:country":"CO",
    "wof:name":"Angosturas",
    "wof:placetype":"locality"
},
  "geometry": {"coordinates":[-76.18092,3.9754],"type":"Point"}
}