{
  "type": "Feature",
  "properties": {
    "gn:admin1_code":"3",
    "gn:admin2_code":"81001.0",
    "gn:asciiname":"El Tesoro",
    "gn:country_code":"CO",
    "gn:dem":125,
    "gn:feature_class":"P",
    "gn:feature_code":"PPL",
    "gn:name":"El Tesoro",
    "gn:population":0,
    "gn:timezone":"America/Bogota",
    "iso:country":"CO",
    "name:spa_x_preferred":[
        "El Tesoro"
    ],
    "wof:name":"El Tesoro",
    "wof:placetype":"locality"
},
  "geometry": {"coordinates":[-70.74096999999998,6.66108],"type":"Point"}
}