{
  "type": "Feature",
  "properties": {
    "gn:admin1_code":"16",
    "gn:admin2_code":"41357.0",
    "gn:asciiname":"El Cielo",
    "gn:country_code":"CO",
    "gn:dem":2028,
    "gn:feature_class":"P",
    "gn:feature_code":"PPL",
    "gn:name":"El Cielo",
    "gn:population":0,
    "gn:timezone":"America/Bogota",
    "iso:country":"CO",
    "wof:name":"El Cielo",
    "wof:placetype":"locality"
},
  "geometry": {"coordinates":[-75.63553,2.77148],"type":"Point"}
}