{
  "type": "Feature",
  "properties": {
    "iso:country":"CO",
    "name:eng_x_preferred":[
        "Betulia"
    ],
    "name:fra_x_preferred":[
        "Betulia"
    ],
    "name:ita_x_preferred":[
        "Betulia"
    ],
    "name:kat_x_preferred":[
        "\u10d1\u10d4\u10e2\u10e3\u10da\u10d8\u10d0"
    ],
    "name:msa_x_preferred":[
        "Betulia"
    ],
    "name:nan_x_preferred":[
        "Betulia"
    ],
    "name:nld_x_preferred":[
        "Betulia"
    ],
    "name:sco_x_preferred":[
        "Betulia"
    ],
    "name:spa_x_preferred":[
        "Betulia"
    ],
    "name:swe_x_preferred":[
        "Betulia"
    ],
    "name:tgl_x_preferred":[
        "Betulia"
    ],
    "name:vie_x_preferred":[
        "Betulia"
    ],
    "name:war_x_preferred":[
        "Betulia"
    ],
    "name:zho_x_preferred":[
        "\u8c9d\u5716\u5229\u4e9e"
    ],
    "qs:gn_country":"CO",
    "qs:gn_fcode":"PPL",
    "qs:gn_pop":1716,
    "qs:name":"Betulia",
    "qs:name_adm0":"Colombia",
    "qs:name_adm1":"Santander",
    "qs:photos":0,
    "qs:photos_1k":0,
    "qs:photos_9k":0,
    "qs:photos_9r":0,
    "qs:photos_all":0,
    "qs:photos_sr":0,
    "qs:placetype":"Town",
    "qs:pop_sr":"3",
    "qs:woe_adm0":23424787,
    "wd:wordcount":34,
    "wof:name":"Betulia",
    "wof:placetype":"locality",
    "wof:population":1716
},
  "geometry": {"coordinates":[-73.28346999999999,6.90069],"type":"Point"}
}