{
  "type": "Feature",
  "properties": {
    "iso:country":"CO",
    "name:ast_x_preferred":[
        "Betulia"
    ],
    "name:avk_x_preferred":[
        "Betulia"
    ],
    "name:cat_x_preferred":[
        "Betulia"
    ],
    "name:ceb_x_preferred":[
        "Betulia"
    ],
    "name:eng_x_preferred":[
        "Betulia"
    ],
    "name:fas_x_preferred":[
        "\u0628\u062a\u0648\u0644\u06cc\u0627"
    ],
    "name:fra_x_preferred":[
        "Betulia"
    ],
    "name:gle_x_preferred":[
        "Betulia"
    ],
    "name:ita_x_preferred":[
        "Betulia"
    ],
    "name:kat_x_preferred":[
        "\u10d1\u10d4\u10e2\u10e3\u10da\u10d8\u10d0"
    ],
    "name:msa_x_preferred":[
        "Betulia"
    ],
    "name:nan_x_preferred":[
        "Betulia"
    ],
    "name:nld_x_preferred":[
        "Betulia"
    ],
    "name:pol_x_preferred":[
        "Betulia"
    ],
    "name:rus_x_preferred":[
        "\u0411\u0435\u0442\u0443\u043b\u0438\u044f"
    ],
    "name:sco_x_preferred":[
        "Betulia"
    ],
    "name:spa_x_preferred":[
        "Betulia"
    ],
    "name:swe_x_preferred":[
        "Betulia"
    ],
    "name:tgl_x_preferred":[
        "Betulia"
    ],
    "name:vie_x_preferred":[
        "Betulia"
    ],
    "name:war_x_preferred":[
        "Betulia"
    ],
    "name:zho_x_preferred":[
        "\u8c9d\u5716\u5229\u4e9e"
    ],
    "name:zho_x_variant":[
        "Tobia"
    ],
    "qs:gn_country":"CO",
    "qs:gn_fcode":"PPL",
    "qs:gn_pop":1716,
    "qs:name":"Betulia",
    "qs:name_adm0":"Colombia",
    "qs:name_adm1":"Santander",
    "qs:photos":0,
    "qs:photos_1k":0,
    "qs:photos_9k":0,
    "qs:photos_9r":0,
    "qs:photos_all":0,
    "qs:photos_sr":0,
    "qs:placetype":"Town",
    "qs:pop_sr":"3",
    "qs:woe_adm0":23424787,
    "wd:wordcount":34,
    "wof:name":"Betulia",
    "wof:placetype":"locality",
    "wof:population":1716
},
  "geometry": {"coordinates":[-73.28346999999999,6.90069],"type":"Point"}
}