{
  "type": "Feature",
  "properties": {
    "gn:admin1_code":"9",
    "gn:admin2_code":"19001.0",
    "gn:asciiname":"San Alfredo",
    "gn:country_code":"CO",
    "gn:dem":1669,
    "gn:feature_class":"P",
    "gn:feature_code":"PPL",
    "gn:name":"San Alfredo",
    "gn:population":0,
    "gn:timezone":"America/Bogota",
    "iso:country":"CO",
    "name:eus_x_preferred":[
        "San Alfredo"
    ],
    "name:por_x_preferred":[
        "San Alfredo"
    ],
    "name:spa_x_preferred":[
        "San Alfredo"
    ],
    "wof:name":"San Alfredo",
    "wof:placetype":"locality"
},
  "geometry": {"coordinates":[-76.68774999999999,2.51098],"type":"Point"}
}