{
  "type": "Feature",
  "properties": {
    "iso:country":"CO",
    "name:ceb_x_preferred":[
        "Caucasia"
    ],
    "name:chi_x_preferred":[
        "\u8003\u5361\u897f\u4e9e"
    ],
    "name:deu_x_preferred":[
        "Caucasia"
    ],
    "name:dut_x_preferred":[
        "Caucasia"
    ],
    "name:eng_x_preferred":[
        "Caucasia"
    ],
    "name:fas_x_preferred":[
        "\u06a9\u0627\u0648\u06a9\u0627\u0633\u06cc\u0627"
    ],
    "name:fin_x_preferred":[
        "Caucasia"
    ],
    "name:fra_x_preferred":[
        "Caucasia"
    ],
    "name:fre_x_preferred":[
        "Caucasia"
    ],
    "name:geo_x_preferred":[
        "\u10d9\u10d0\u10e3\u10d9\u10d0\u10e1\u10d8\u10d0"
    ],
    "name:ger_x_preferred":[
        "Caucasia"
    ],
    "name:ile_x_preferred":[
        "Caucasia"
    ],
    "name:ita_x_preferred":[
        "Caucasia"
    ],
    "name:jpn_x_preferred":[
        "\u30ab\u30a6\u30ab\u30b7\u30a2"
    ],
    "name:kat_x_preferred":[
        "\u10d9\u10d0\u10e3\u10d9\u10d0\u10e1\u10d8\u10d0"
    ],
    "name:may_x_preferred":[
        "Caucasia"
    ],
    "name:msa_x_preferred":[
        "Caucasia"
    ],
    "name:nah_x_preferred":[
        "Caucasia"
    ],
    "name:nan_x_preferred":[
        "Caucasia"
    ],
    "name:nld_x_preferred":[
        "Caucasia"
    ],
    "name:per_x_preferred":[
        "\u06a9\u0627\u0648\u06a9\u0627\u0633\u06cc\u0627"
    ],
    "name:pol_x_preferred":[
        "Caucasia"
    ],
    "name:por_x_preferred":[
        "Caucasia"
    ],
    "name:ron_x_preferred":[
        "Caucasia"
    ],
    "name:rum_x_preferred":[
        "Caucasia"
    ],
    "name:rus_x_preferred":[
        "\u041a\u0430\u0443\u043a\u0430\u0441\u0438\u044f"
    ],
    "name:rus_x_variant":[
        "\u041a\u0430\u0432\u043a\u0430\u0437"
    ],
    "name:spa_x_preferred":[
        "Caucasia"
    ],
    "name:swe_x_preferred":[
        "Caucasia"
    ],
    "name:tgl_x_preferred":[
        "Caucasia"
    ],
    "name:unk_x_variant":[
        "Ca\u00f1af\u00edstola"
    ],
    "name:war_x_preferred":[
        "Caucasia"
    ],
    "name:zho_min_nan_x_preferred":[
        "Caucasia"
    ],
    "name:zho_x_preferred":[
        "\u8003\u5361\u897f\u4e9e"
    ],
    "qs:gn_country":"CO",
    "qs:gn_fcode":"PPL",
    "qs:gn_pop":58034,
    "qs:name":"Caucasia",
    "qs:name_adm0":"Colombia",
    "qs:name_adm1":"Antioquia",
    "qs:photos":113,
    "qs:photos_1k":23,
    "qs:photos_9k":1,
    "qs:photos_9r":3,
    "qs:photos_all":113,
    "qs:photos_sr":3,
    "qs:placetype":"Town",
    "qs:pop_sr":"8",
    "qs:woe_adm0":23424787,
    "wd:wordcount":544,
    "wof:name":"Caucasia",
    "wof:placetype":"locality",
    "wof:population":58034
},
  "geometry": {"coordinates":[-75.19349,7.98654],"type":"Point"}
}