{
  "type": "Feature",
  "properties": {
    "gn:admin1_code":"21",
    "gn:admin2_code":"54051.0",
    "gn:asciiname":"Bateas",
    "gn:country_code":"CO",
    "gn:dem":721,
    "gn:feature_class":"P",
    "gn:feature_code":"PPL",
    "gn:name":"Bateas",
    "gn:population":0,
    "gn:timezone":"America/Bogota",
    "iso:country":"CO",
    "wof:name":"Bateas",
    "wof:placetype":"locality"
},
  "geometry": {"coordinates":[-72.75,7.66667],"type":"Point"}
}