{
  "type": "Feature",
  "properties": {
    "gn:admin1_code":"9.0",
    "gn:admin2_code":"19821.0",
    "gn:asciiname":"Natala",
    "gn:country_code":"CO",
    "gn:dem":1588,
    "gn:feature_class":"P",
    "gn:feature_code":"PPL",
    "gn:name":"Natal\u00e1",
    "gn:population":0,
    "gn:timezone":"America/Bogota",
    "iso:country":"CO",
    "name:spa_x_preferred":[
        "Natal\u00e1"
    ],
    "wof:name":"Natala",
    "wof:placetype":"locality"
},
  "geometry": {"coordinates":[-76.2863,3.00787],"type":"Point"}
}