{
  "type": "Feature",
  "properties": {
    "gn:admin1_code":"26",
    "gn:admin2_code":"68655.0",
    "gn:asciiname":"Halliburton",
    "gn:country_code":"CO",
    "gn:dem":117,
    "gn:feature_class":"P",
    "gn:feature_code":"PPL",
    "gn:name":"Halliburton",
    "gn:population":0,
    "gn:timezone":"America/Bogota",
    "iso:country":"CO",
    "name:ara_x_preferred":[
        "\u0647\u0627\u0644\u064a\u0628\u0631\u062a\u0648\u0646"
    ],
    "name:azb_x_preferred":[
        "\u0647\u0627\u0644\u06cc\u0628\u0631\u062a\u0648\u0646"
    ],
    "name:bul_x_preferred":[
        "\u0425\u0430\u043b\u0438\u0431\u044a\u0440\u0442\u044a\u043d"
    ],
    "name:ces_x_preferred":[
        "Halliburton"
    ],
    "name:dan_x_preferred":[
        "Halliburton"
    ],
    "name:deu_x_preferred":[
        "Halliburton"
    ],
    "name:epo_x_preferred":[
        "Halliburton"
    ],
    "name:est_x_preferred":[
        "Halliburton"
    ],
    "name:eus_x_preferred":[
        "Halliburton"
    ],
    "name:fas_x_preferred":[
        "\u0647\u0627\u0644\u06cc\u0628\u0631\u062a\u0648\u0646"
    ],
    "name:fin_x_preferred":[
        "Halliburton"
    ],
    "name:fra_x_preferred":[
        "Halliburton"
    ],
    "name:heb_x_preferred":[
        "\u05d4\u05dc\u05d9\u05d1\u05e8\u05d8\u05d5\u05df"
    ],
    "name:ind_x_preferred":[
        "Halliburton"
    ],
    "name:ita_x_preferred":[
        "Halliburton"
    ],
    "name:jpn_x_preferred":[
        "\u30cf\u30ea\u30d0\u30fc\u30c8\u30f3"
    ],
    "name:kor_x_preferred":[
        "\ud560\ub9ac\ubc84\ud2bc"
    ],
    "name:msa_x_preferred":[
        "Halliburton"
    ],
    "name:nld_x_preferred":[
        "Halliburton"
    ],
    "name:nor_x_preferred":[
        "Halliburton"
    ],
    "name:pol_x_preferred":[
        "Halliburton"
    ],
    "name:por_x_preferred":[
        "Halliburton"
    ],
    "name:ron_x_preferred":[
        "Halliburton"
    ],
    "name:rus_x_preferred":[
        "Halliburton"
    ],
    "name:slv_x_preferred":[
        "Halliburton"
    ],
    "name:spa_x_preferred":[
        "Halliburton"
    ],
    "name:swe_x_preferred":[
        "Halliburton"
    ],
    "name:tur_x_preferred":[
        "Halliburton"
    ],
    "name:ukr_x_preferred":[
        "Halliburton"
    ],
    "name:vie_x_preferred":[
        "Halliburton"
    ],
    "name:zho_x_preferred":[
        "\u54c8\u91cc\u4f2f\u987f"
    ],
    "wof:name":"Halliburton",
    "wof:placetype":"locality"
},
  "geometry": {"coordinates":[-73.4725,7.35167],"type":"Point"}
}