{
  "type": "Feature",
  "properties": {
    "iso:country":"CO",
    "name:ast_x_preferred":[
        "Buenos Aires"
    ],
    "name:avk_x_preferred":[
        "Buenos Aires"
    ],
    "name:ceb_x_preferred":[
        "Buenos Aires"
    ],
    "name:deu_x_preferred":[
        "Buenos Aires"
    ],
    "name:eng_x_preferred":[
        "Buenos Aires"
    ],
    "name:fas_x_preferred":[
        "\u0628\u0648\u0626\u0646\u0648\u0633 \u0622\u06cc\u0631\u0633"
    ],
    "name:fra_x_preferred":[
        "Buenos Aires"
    ],
    "name:gle_x_preferred":[
        "Buenos Aires"
    ],
    "name:ita_x_preferred":[
        "Buenos Aires"
    ],
    "name:kat_x_preferred":[
        "\u10d1\u10e3\u10d4\u10dc\u10dd\u10e1-\u10d0\u10d8\u10e0\u10d4\u10e1\u10d8"
    ],
    "name:msa_x_preferred":[
        "Buenos Aires"
    ],
    "name:nan_x_preferred":[
        "Buenos Aires"
    ],
    "name:nld_x_preferred":[
        "Buenos Aires"
    ],
    "name:pol_x_preferred":[
        "Buenos Aires"
    ],
    "name:por_x_preferred":[
        "Buenos Aires"
    ],
    "name:rus_x_preferred":[
        "\u0411\u0443\u044d\u043d\u043e\u0441-\u0410\u0439\u0440\u0435\u0441"
    ],
    "name:sco_x_preferred":[
        "Buenos Aires"
    ],
    "name:spa_x_preferred":[
        "Buenos Aires"
    ],
    "name:swe_x_preferred":[
        "Buenos Aires"
    ],
    "name:tgl_x_preferred":[
        "Buenos Aires"
    ],
    "name:ukr_x_preferred":[
        "\u0411\u0443\u0435\u043d\u043e\u0441-\u0410\u0439\u0440\u0435\u0441"
    ],
    "name:vie_x_preferred":[
        "Buenos Aires"
    ],
    "name:war_x_preferred":[
        "Buenos Aires"
    ],
    "name:zho_x_preferred":[
        "\u5e03\u5b9c\u8afe\u65af\u827e\u5229\u65af"
    ],
    "qs:gn_country":"CO",
    "qs:gn_fcode":"PPL",
    "qs:gn_pop":2144,
    "qs:name":"Buenos Aires",
    "qs:name_adm0":"Colombia",
    "qs:name_adm1":"Cauca",
    "qs:photos":0,
    "qs:photos_1k":0,
    "qs:photos_9k":1,
    "qs:photos_9r":1,
    "qs:photos_all":1,
    "qs:photos_sr":0,
    "qs:placetype":"Town",
    "qs:pop_sr":"4",
    "qs:woe_adm0":23424787,
    "wof:name":"Buenos Aires",
    "wof:placetype":"locality",
    "wof:population":2144
},
  "geometry": {"coordinates":[-76.64275000000001,3.01503],"type":"Point"}
}