{
  "type": "Feature",
  "properties": {
    "gn:admin1_code":"10",
    "gn:admin2_code":"20178.0",
    "gn:asciiname":"Carbonero",
    "gn:cc2":"CO",
    "gn:country_code":"CO",
    "gn:dem":29,
    "gn:feature_class":"P",
    "gn:feature_code":"PPL",
    "gn:name":"Carbonero",
    "gn:population":0,
    "gn:timezone":"America/Bogota",
    "iso:country":"CO",
    "name:und_x_variant":[
        "Hacienda Carbonero",
        "Carbonero"
    ],
    "wof:name":"Carbonero",
    "wof:placetype":"locality"
},
  "geometry": {"coordinates":[-73.63333,9.33333],"type":"Point"}
}