{
  "type": "Feature",
  "properties": {
    "gn:admin1_code":"12",
    "gn:admin2_code":"23570.0",
    "gn:asciiname":"La Balastrera",
    "gn:country_code":"CO",
    "gn:dem":100,
    "gn:feature_class":"P",
    "gn:feature_code":"PPL",
    "gn:name":"La Balastrera",
    "gn:population":0,
    "gn:timezone":"America/Bogota",
    "iso:country":"CO",
    "wof:name":"La Balastrera",
    "wof:placetype":"locality"
},
  "geometry": {"coordinates":[-75.50199000000001,8.44627],"type":"Point"}
}