{
  "type": "Feature",
  "properties": {
    "gn:admin1_code":"36",
    "gn:admin2_code":"15507.0",
    "gn:asciiname":"Samal",
    "gn:country_code":"CO",
    "gn:dem":770,
    "gn:feature_class":"P",
    "gn:feature_code":"PPL",
    "gn:name":"Samal",
    "gn:population":0,
    "gn:timezone":"America/Bogota",
    "iso:country":"CO",
    "name:cat_x_preferred":[
        "Samal"
    ],
    "name:ceb_x_preferred":[
        "Samal"
    ],
    "name:deu_x_preferred":[
        "Samal"
    ],
    "name:fra_x_preferred":[
        "Samal"
    ],
    "name:hun_x_preferred":[
        "Szamal"
    ],
    "name:ilo_x_preferred":[
        "Samal"
    ],
    "name:nld_x_preferred":[
        "Samal"
    ],
    "name:rus_x_preferred":[
        "\u0421\u0430\u043c\u0430\u043b\u044c"
    ],
    "name:swe_x_preferred":[
        "Samal"
    ],
    "name:tgl_x_preferred":[
        "Samal"
    ],
    "name:vie_x_preferred":[
        "Samal"
    ],
    "name:war_x_preferred":[
        "Samal"
    ],
    "wof:name":"Samal",
    "wof:placetype":"locality"
},
  "geometry": {"coordinates":[-74.27583,5.67528],"type":"Point"}
}