{
  "type": "Feature",
  "properties": {
    "gn:admin1_code":"2",
    "gn:admin2_code":"5659.0",
    "gn:asciiname":"El Oriente",
    "gn:country_code":"CO",
    "gn:dem":21,
    "gn:feature_class":"P",
    "gn:feature_code":"PPL",
    "gn:name":"El Oriente",
    "gn:population":0,
    "gn:timezone":"America/Bogota",
    "iso:country":"CO",
    "wof:name":"El Oriente",
    "wof:placetype":"locality"
},
  "geometry": {"coordinates":[-76.48822,8.71682],"type":"Point"}
}