{
  "type": "Feature",
  "properties": {
    "gn:admin1_code":"16.0",
    "gn:admin2_code":"41078.0",
    "gn:asciiname":"Mundo Viejo",
    "gn:country_code":"CO",
    "gn:dem":1244,
    "gn:feature_class":"P",
    "gn:feature_code":"PPL",
    "gn:name":"Mundo Viejo",
    "gn:population":0,
    "gn:timezone":"America/Bogota",
    "iso:country":"CO",
    "name:spa_x_preferred":[
        "Mundo Viejo"
    ],
    "wof:name":"Mundo Viejo",
    "wof:placetype":"locality"
},
  "geometry": {"coordinates":[-74.96583000000003,3.17333],"type":"Point"}
}