{
  "type": "Feature",
  "properties": {
    "gn:admin1_code":"17",
    "gn:admin2_code":"44847.0",
    "gn:asciiname":"Carrizal",
    "gn:country_code":"CO",
    "gn:dem":-1,
    "gn:feature_class":"P",
    "gn:feature_code":"PPL",
    "gn:name":"Carrizal",
    "gn:population":0,
    "gn:timezone":"America/Bogota",
    "iso:country":"CO",
    "wof:name":"Carrizal",
    "wof:placetype":"locality"
},
  "geometry": {"coordinates":[-72.17939,12.00942],"type":"Point"}
}