{
  "type": "Feature",
  "properties": {
    "gn:admin1_code":"33",
    "gn:admin2_code":"25290.0",
    "gn:asciiname":"Cutucumayo",
    "gn:country_code":"CO",
    "gn:dem":1372,
    "gn:feature_class":"P",
    "gn:feature_code":"PPL",
    "gn:name":"Cutucumayo",
    "gn:population":0,
    "gn:timezone":"America/Bogota",
    "iso:country":"CO",
    "wof:name":"Cutucumayo",
    "wof:placetype":"locality"
},
  "geometry": {"coordinates":[-74.43003,4.3181],"type":"Point"}
}