{
  "type": "Feature",
  "properties": {
    "iso:country":"CO",
    "name:ceb_x_preferred":[
        "Las Nieves"
    ],
    "name:deu_x_preferred":[
        "Las Nieves"
    ],
    "name:ita_x_preferred":[
        "Las Nieves"
    ],
    "name:nld_x_preferred":[
        "Las Nieves"
    ],
    "name:spa_x_preferred":[
        "Las Nieves"
    ],
    "name:swe_x_preferred":[
        "Las Nieves"
    ],
    "name:unk_x_variant":[
        "Las Nieves"
    ],
    "qs:gn_adm0_cc":"CO",
    "qs:gn_fcode":"PPL",
    "qs:gn_local":3674962,
    "qs:gn_namadm1":"02",
    "qs:gn_name":"Las Nieves",
    "qs:local_max":5883,
    "qs:local_sum":29357,
    "qs:localhoods":18,
    "qs:name":"Las Nieves",
    "qs:name_adm0":"Colombia",
    "qs:name_adm1":"Antioquia",
    "qs:name_adm2":"Medellin",
    "qs:name_local":"Medell\u00edn",
    "qs:photo_max":154,
    "qs:photo_sum":388,
    "qs:placetype":"Suburb",
    "qs:quad_count":18,
    "qs:woe_adm0":23424787,
    "qs:woe_adm1":2345048,
    "qs:woe_adm2":26796607,
    "qs:woe_lau":0,
    "qs:woe_local":368150,
    "qs:woe_ver":"7.10.0",
    "wof:lang":[
        "spa"
    ],
    "wof:name":"Las Nieves",
    "wof:placetype":"neighbourhood"
},
  "geometry": {"coordinates":[-75.55124000000001,6.269077],"type":"Point"}
}