{
  "type": "Feature",
  "properties": {
    "gn:admin1_code":"2.0",
    "gn:admin2_code":"5266.0",
    "gn:asciiname":"Vivero Los Geranios",
    "gn:country_code":"CO",
    "gn:dem":2556,
    "gn:feature_class":"P",
    "gn:feature_code":"PPL",
    "gn:name":"Vivero Los Geranios",
    "gn:population":0,
    "gn:timezone":"America/Bogota",
    "iso:country":"CO",
    "name:spa_x_preferred":[
        "Vivero Los Geranios"
    ],
    "wof:name":"Vivero Los Geranios",
    "wof:placetype":"locality"
},
  "geometry": {"coordinates":[-75.52068,6.15746],"type":"Point"}
}