{
  "type": "Feature",
  "properties": {
    "gn:admin1_code":"17",
    "gn:admin2_code":"44847.0",
    "gn:asciiname":"La Trampa",
    "gn:country_code":"CO",
    "gn:dem":0,
    "gn:feature_class":"P",
    "gn:feature_code":"PPL",
    "gn:name":"La Trampa",
    "gn:population":0,
    "gn:timezone":"America/Bogota",
    "iso:country":"CO",
    "name:spa_x_preferred":[
        "La Trampa"
    ],
    "wof:name":"La Trampa",
    "wof:placetype":"locality"
},
  "geometry": {"coordinates":[-72.15548000000003,12.00394],"type":"Point"}
}