{
  "type": "Feature",
  "properties": {
    "gn:admin1_code":"27",
    "gn:admin2_code":"70823.0",
    "gn:asciiname":"El Prado",
    "gn:country_code":"CO",
    "gn:dem":70,
    "gn:feature_class":"P",
    "gn:feature_code":"PPL",
    "gn:name":"El Prado",
    "gn:population":0,
    "gn:timezone":"America/Bogota",
    "iso:country":"CO",
    "name:ceb_x_preferred":[
        "El Prado"
    ],
    "name:spa_x_preferred":[
        "El Prado"
    ],
    "name:srp_x_preferred":[
        "\u0415\u043b \u041f\u0440\u0430\u0434\u043e"
    ],
    "name:swe_x_preferred":[
        "El Prado"
    ],
    "name:und_x_variant":[
        "Hacienda El Prado",
        "El Prado"
    ],
    "wof:name":"El Prado",
    "wof:placetype":"locality"
},
  "geometry": {"coordinates":[-75.42010999999999,9.42067],"type":"Point"}
}