{
  "type": "Feature",
  "properties": {
    "gn:admin1_code":"38",
    "gn:admin2_code":"47555.0",
    "gn:asciiname":"Callelarga",
    "gn:country_code":"CO",
    "gn:dem":151,
    "gn:feature_class":"P",
    "gn:feature_code":"PPL",
    "gn:name":"Callelarga",
    "gn:population":0,
    "gn:timezone":"America/Bogota",
    "iso:country":"CO",
    "name:und_x_variant":[
        "Hacienda Callelarga",
        "Callelarga"
    ],
    "wof:name":"Callelarga",
    "wof:placetype":"locality"
},
  "geometry": {"coordinates":[-74.35028,9.93414],"type":"Point"}
}