{
  "type": "Feature",
  "properties": {
    "gn:admin1_code":"29.0",
    "gn:admin2_code":"76100.0",
    "gn:asciiname":"El Catre",
    "gn:country_code":"CO",
    "gn:dem":965,
    "gn:feature_class":"P",
    "gn:feature_code":"PPL",
    "gn:name":"El Catre",
    "gn:population":0,
    "gn:timezone":"America/Bogota",
    "iso:country":"CO",
    "wof:name":"El Catre",
    "wof:placetype":"locality"
},
  "geometry": {"coordinates":[-76.42497,4.34594],"type":"Point"}
}