{
  "type": "Feature",
  "properties": {
    "gn:admin1_code":"38.0",
    "gn:admin2_code":"47707.0",
    "gn:asciiname":"Pringamoza",
    "gn:country_code":"CO",
    "gn:dem":91,
    "gn:feature_class":"P",
    "gn:feature_code":"PPL",
    "gn:name":"Pringamoza",
    "gn:population":0,
    "gn:timezone":"America/Bogota",
    "iso:country":"CO",
    "name:und_x_variant":[
        "Hacienda Pringamoza",
        "Pringamoza"
    ],
    "wof:name":"Pringamoza",
    "wof:placetype":"locality"
},
  "geometry": {"coordinates":[-74.13024,9.61001],"type":"Point"}
}