{
  "type": "Feature",
  "properties": {
    "gn:admin1_code":"28",
    "gn:admin2_code":"73555.0",
    "gn:asciiname":"Las Brisas",
    "gn:country_code":"CO",
    "gn:dem":1829,
    "gn:feature_class":"P",
    "gn:feature_code":"PPL",
    "gn:name":"Las Brisas",
    "gn:population":0,
    "gn:timezone":"America/Bogota",
    "iso:country":"CO",
    "wof:name":"Las Brisas",
    "wof:placetype":"locality"
},
  "geometry": {"coordinates":[-75.66889,3.2025],"type":"Point"}
}