{
  "type": "Feature",
  "properties": {
    "gn:admin1_code":"29.0",
    "gn:admin2_code":"76113.0",
    "gn:asciiname":"La Glorieta",
    "gn:country_code":"CO",
    "gn:dem":1137,
    "gn:feature_class":"P",
    "gn:feature_code":"PPL",
    "gn:name":"La Glorieta",
    "gn:population":0,
    "gn:timezone":"America/Bogota",
    "iso:country":"CO",
    "wof:name":"La Glorieta",
    "wof:placetype":"locality"
},
  "geometry": {"coordinates":[-76.10333,4.17472],"type":"Point"}
}