{
  "type": "Feature",
  "properties": {
    "iso:country":"CO",
    "name:ceb_x_preferred":[
        "Tarso"
    ],
    "name:eng_x_preferred":[
        "Tarso"
    ],
    "name:fra_x_preferred":[
        "Tarso"
    ],
    "name:ile_x_preferred":[
        "Tarso"
    ],
    "name:ita_x_preferred":[
        "Tarso"
    ],
    "name:kat_x_preferred":[
        "\u10e2\u10d0\u10e0\u10e1\u10dd"
    ],
    "name:msa_x_preferred":[
        "Tarso"
    ],
    "name:nan_x_preferred":[
        "Tarso"
    ],
    "name:nld_x_preferred":[
        "Tarso"
    ],
    "name:por_x_preferred":[
        "Tarso"
    ],
    "name:ron_x_preferred":[
        "Tarso"
    ],
    "name:rus_x_preferred":[
        "\u0422\u0430\u0440\u0441\u043e"
    ],
    "name:spa_x_preferred":[
        "Tarso"
    ],
    "name:swe_x_preferred":[
        "Tarso"
    ],
    "name:tgl_x_preferred":[
        "Tarso"
    ],
    "name:vie_x_preferred":[
        "Tarso"
    ],
    "name:war_x_preferred":[
        "Tarso"
    ],
    "name:zho_min_nan_x_preferred":[
        "Tarso"
    ],
    "name:zho_x_preferred":[
        "\u5854\u723e\u7d22"
    ],
    "qs:gn_country":"CO",
    "qs:gn_fcode":"PPL",
    "qs:gn_pop":2700,
    "qs:name":"Tarso",
    "qs:name_adm0":"Colombia",
    "qs:name_adm1":"Antioquia",
    "qs:photos":49,
    "qs:photos_1k":10,
    "qs:photos_9k":1,
    "qs:photos_9r":2,
    "qs:photos_all":49,
    "qs:photos_sr":2,
    "qs:placetype":"Town",
    "qs:pop_sr":"4",
    "qs:woe_adm0":23424787,
    "wof:name":"Tarso",
    "wof:placetype":"locality",
    "wof:population":2700
},
  "geometry": {"coordinates":[-75.82192000000001,5.86467],"type":"Point"}
}