{
  "type": "Feature",
  "properties": {
    "gn:admin1_code":"9",
    "gn:admin2_code":"19450.0",
    "gn:asciiname":"Monteredondo",
    "gn:country_code":"CO",
    "gn:dem":1553,
    "gn:feature_class":"P",
    "gn:feature_code":"PPL",
    "gn:name":"Monteredondo",
    "gn:population":0,
    "gn:timezone":"America/Bogota",
    "iso:country":"CO",
    "wof:name":"Monteredondo",
    "wof:placetype":"locality"
},
  "geometry": {"coordinates":[-77.09366,1.72835],"type":"Point"}
}