{
  "type": "Feature",
  "properties": {
    "gn:admin1_code":"2",
    "gn:admin2_code":"5887.0",
    "gn:asciiname":"La Lluvia",
    "gn:country_code":"CO",
    "gn:dem":1164,
    "gn:feature_class":"P",
    "gn:feature_code":"PPL",
    "gn:name":"La Lluvia",
    "gn:population":0,
    "gn:timezone":"America/Bogota",
    "iso:country":"CO",
    "wof:name":"La Lluvia",
    "wof:placetype":"locality"
},
  "geometry": {"coordinates":[-75.39064,7.09765],"type":"Point"}
}