{
  "type": "Feature",
  "properties": {
    "gn:admin1_code":"3.0",
    "gn:admin2_code":"81220.0",
    "gn:asciiname":"Planchon de Palo Herrado",
    "gn:country_code":"CO",
    "gn:dem":113,
    "gn:feature_class":"P",
    "gn:feature_code":"PPL",
    "gn:name":"Planch\u00f3n de Palo Herrado",
    "gn:population":0,
    "gn:timezone":"America/Bogota",
    "iso:country":"CO",
    "wof:name":"Planchon de Palo Herrado",
    "wof:placetype":"locality"
},
  "geometry": {"coordinates":[-70.59611,6.45778],"type":"Point"}
}