{
  "type": "Feature",
  "properties": {
    "gn:admin1_code":"17.0",
    "gn:admin2_code":"44001.0",
    "gn:asciiname":"Villa Martin",
    "gn:country_code":"CO",
    "gn:dem":52,
    "gn:feature_class":"P",
    "gn:feature_code":"PPL",
    "gn:name":"Villa Mart\u00edn",
    "gn:population":0,
    "gn:timezone":"America/Bogota",
    "iso:country":"CO",
    "name:und_x_variant":[
        "Macho Bajo",
        "Corregimiento Villa Martin",
        "Macho Bayo",
        "Villa Mart\u00edn"
    ],
    "wof:name":"Villa Martin",
    "wof:placetype":"locality"
},
  "geometry": {"coordinates":[-72.79174999999999,11.2173],"type":"Point"}
}