{
  "type": "Feature",
  "properties": {
    "gn:admin1_code":"16.0",
    "gn:admin2_code":"41132.0",
    "gn:asciiname":"Pirabante",
    "gn:country_code":"CO",
    "gn:dem":608,
    "gn:feature_class":"P",
    "gn:feature_code":"PPL",
    "gn:name":"Pirabante",
    "gn:population":0,
    "gn:timezone":"America/Bogota",
    "iso:country":"CO",
    "wof:name":"Pirabante",
    "wof:placetype":"locality"
},
  "geometry": {"coordinates":[-75.28841,2.72142],"type":"Point"}
}