{
  "type": "Feature",
  "properties": {
    "gn:admin1_code":"38.0",
    "gn:admin2_code":"47980.0",
    "gn:asciiname":"Monte Carmelo",
    "gn:country_code":"CO",
    "gn:dem":7,
    "gn:feature_class":"P",
    "gn:feature_code":"PPL",
    "gn:name":"Monte Carmelo",
    "gn:population":0,
    "gn:timezone":"America/Bogota",
    "iso:country":"CO",
    "wof:name":"Monte Carmelo",
    "wof:placetype":"locality"
},
  "geometry": {"coordinates":[-74.2243,10.85613],"type":"Point"}
}