{
  "type": "Feature",
  "properties": {
    "gn:admin1_code":"38.0",
    "gn:admin2_code":"47980.0",
    "gn:asciiname":"Monte Carmelo",
    "gn:country_code":"CO",
    "gn:dem":7,
    "gn:feature_class":"P",
    "gn:feature_code":"PPL",
    "gn:name":"Monte Carmelo",
    "gn:population":0,
    "gn:timezone":"America/Bogota",
    "iso:country":"CO",
    "name:bpy_x_preferred":[
        "\u09ae\u09cb\u09a8\u09cd\u099f\u09c7 \u0995\u09be\u09b0\u09cd\u09ae\u09c7\u09b2\u09cb"
    ],
    "name:ceb_x_preferred":[
        "Monte Carmelo"
    ],
    "name:epo_x_preferred":[
        "Monte Carmelo"
    ],
    "name:eus_x_preferred":[
        "Monte Carmelo"
    ],
    "name:fra_x_preferred":[
        "Monte Carmelo"
    ],
    "name:ita_x_preferred":[
        "Monte Carmelo"
    ],
    "name:kat_x_preferred":[
        "\u10db\u10dd\u10dc\u10e2\u10d8-\u10d9\u10d0\u10e0\u10db\u10d4\u10da\u10e3"
    ],
    "name:kaz_x_preferred":[
        "\u041c\u043e\u043d\u0442\u0438-\u041a\u0430\u0440\u043c\u0435\u043b\u0443"
    ],
    "name:mlg_x_preferred":[
        "Monte Carmelo"
    ],
    "name:nld_x_preferred":[
        "Monte Carmelo"
    ],
    "name:nor_x_preferred":[
        "Monte Carmelo"
    ],
    "name:pol_x_preferred":[
        "Monte Carmelo"
    ],
    "name:por_x_preferred":[
        "Monte Carmelo"
    ],
    "name:ron_x_preferred":[
        "Monte Carmelo"
    ],
    "name:rus_x_preferred":[
        "\u041c\u043e\u043d\u0442\u0438-\u041a\u0430\u0440\u043c\u0435\u043b\u0443"
    ],
    "name:swe_x_preferred":[
        "Monte Carmelo"
    ],
    "name:vol_x_preferred":[
        "Monte Carmelo"
    ],
    "name:war_x_preferred":[
        "Monte Carmelo"
    ],
    "name:zho_x_preferred":[
        "\u8499\u8482\u5361\u6885\u5362"
    ],
    "wof:name":"Monte Carmelo",
    "wof:placetype":"locality"
},
  "geometry": {"coordinates":[-74.2243,10.85613],"type":"Point"}
}