{
  "type": "Feature",
  "properties": {
    "gn:admin1_code":"20.0",
    "gn:admin2_code":"52490.0",
    "gn:asciiname":"Barro Caliente",
    "gn:country_code":"CO",
    "gn:dem":19,
    "gn:feature_class":"P",
    "gn:feature_code":"PPL",
    "gn:name":"Barro Caliente",
    "gn:population":0,
    "gn:timezone":"America/Bogota",
    "iso:country":"CO",
    "wof:name":"Barro Caliente",
    "wof:placetype":"locality"
},
  "geometry": {"coordinates":[-78.2264,2.21234],"type":"Point"}
}