{
  "type": "Feature",
  "properties": {
    "gn:admin1_code":"10.0",
    "gn:admin2_code":"20250.0",
    "gn:asciiname":"Vallito",
    "gn:country_code":"CO",
    "gn:dem":50,
    "gn:feature_class":"P",
    "gn:feature_code":"PPL",
    "gn:name":"Vallito",
    "gn:population":0,
    "gn:timezone":"America/Bogota",
    "iso:country":"CO",
    "name:und_x_variant":[
        "Caserio Vallito",
        "El Vallito",
        "Vallito"
    ],
    "wof:name":"Vallito",
    "wof:placetype":"locality"
},
  "geometry": {"coordinates":[-73.64896999999998,9.82262],"type":"Point"}
}