{
  "type": "Feature",
  "properties": {
    "gn:admin1_code":"4.0",
    "gn:admin2_code":"8606.0",
    "gn:asciiname":"Piedra de Moler",
    "gn:cc2":"CO",
    "gn:country_code":"CO",
    "gn:dem":12,
    "gn:feature_class":"P",
    "gn:feature_code":"PPL",
    "gn:name":"Piedra de Moler",
    "gn:population":0,
    "gn:timezone":"America/Bogota",
    "iso:country":"CO",
    "name:und_x_variant":[
        "Hacienda Piedra de Moler",
        "Piedra de Moler"
    ],
    "wof:name":"Piedra de Moler",
    "wof:placetype":"locality"
},
  "geometry": {"coordinates":[-75.13333,10.45],"type":"Point"}
}