{
  "type": "Feature",
  "properties": {
    "gn:admin1_code":"38",
    "gn:admin2_code":"47318.0",
    "gn:asciiname":"El Veinticinco",
    "gn:country_code":"CO",
    "gn:dem":71,
    "gn:feature_class":"P",
    "gn:feature_code":"PPL",
    "gn:name":"El Veinticinco",
    "gn:population":0,
    "gn:timezone":"America/Bogota",
    "iso:country":"CO",
    "wof:name":"El Veinticinco",
    "wof:placetype":"locality"
},
  "geometry": {"coordinates":[-74.06,9.335],"type":"Point"}
}