{
  "type": "Feature",
  "properties": {
    "gn:admin1_code":"31.0",
    "gn:admin2_code":"99773.0",
    "gn:asciiname":"Cunaca",
    "gn:cc2":"CO",
    "gn:country_code":"CO",
    "gn:dem":129,
    "gn:feature_class":"P",
    "gn:feature_code":"PPL",
    "gn:name":"Cunaca",
    "gn:population":0,
    "gn:timezone":"America/Bogota",
    "iso:country":"CO",
    "name:und_x_variant":[
        "Curraca",
        "Cunaca"
    ],
    "wof:name":"Cunaca",
    "wof:placetype":"locality"
},
  "geometry": {"coordinates":[-70.59917,4.16278],"type":"Point"}
}