{
  "type": "Feature",
  "properties": {
    "gn:admin1_code":"36",
    "gn:admin2_code":"15632.0",
    "gn:asciiname":"La Colmena",
    "gn:country_code":"CO",
    "gn:dem":2785,
    "gn:feature_class":"P",
    "gn:feature_code":"PPL",
    "gn:name":"La Colmena",
    "gn:population":0,
    "gn:timezone":"America/Bogota",
    "iso:country":"CO",
    "name:ceb_x_preferred":[
        "La Colmena"
    ],
    "name:fra_x_preferred":[
        "La Colmena"
    ],
    "name:glg_x_preferred":[
        "La colmena"
    ],
    "name:nld_x_preferred":[
        "La colmena"
    ],
    "name:spa_x_preferred":[
        "La colmena"
    ],
    "name:swe_x_preferred":[
        "La Colmena"
    ],
    "wof:name":"La Colmena",
    "wof:placetype":"locality"
},
  "geometry": {"coordinates":[-73.75028,5.74806],"type":"Point"}
}