{
  "type": "Feature",
  "properties": {
    "gn:admin1_code":"33",
    "gn:admin2_code":"25053.0",
    "gn:asciiname":"El Chucharo",
    "gn:country_code":"CO",
    "gn:dem":1498,
    "gn:feature_class":"P",
    "gn:feature_code":"PPL",
    "gn:name":"El Chucharo",
    "gn:population":0,
    "gn:timezone":"America/Bogota",
    "iso:country":"CO",
    "wof:name":"El Chucharo",
    "wof:placetype":"locality"
},
  "geometry": {"coordinates":[-74.4066,4.26241],"type":"Point"}
}