{
  "type": "Feature",
  "properties": {
    "iso:country":"CO",
    "name:ceb_x_preferred":[
        "Tena"
    ],
    "name:chi_x_preferred":[
        "\u7279\u7d0d"
    ],
    "name:dut_x_preferred":[
        "Tena"
    ],
    "name:eng_x_preferred":[
        "Tena"
    ],
    "name:fra_x_preferred":[
        "Tena"
    ],
    "name:fre_x_preferred":[
        "Tena"
    ],
    "name:geo_x_preferred":[
        "\u10e2\u10d4\u10dc\u10d0"
    ],
    "name:ita_x_preferred":[
        "Tena"
    ],
    "name:kat_x_preferred":[
        "\u10e2\u10d4\u10dc\u10d0"
    ],
    "name:may_x_preferred":[
        "Tena"
    ],
    "name:msa_x_preferred":[
        "Tena"
    ],
    "name:nan_x_preferred":[
        "Tena"
    ],
    "name:nld_x_preferred":[
        "Tena"
    ],
    "name:sco_x_preferred":[
        "Tena"
    ],
    "name:spa_x_preferred":[
        "Tena"
    ],
    "name:swe_x_preferred":[
        "Tena"
    ],
    "name:tgl_x_preferred":[
        "Tena"
    ],
    "name:war_x_preferred":[
        "Tena"
    ],
    "name:zho_min_nan_x_preferred":[
        "Tena"
    ],
    "name:zho_x_preferred":[
        "\u7279\u7d0d"
    ],
    "qs:gn_country":"CO",
    "qs:gn_fcode":"PPL",
    "qs:gn_pop":696,
    "qs:name":"Tena",
    "qs:name_adm0":"Colombia",
    "qs:name_adm1":"Cundinamarca",
    "qs:photos":102,
    "qs:photos_1k":21,
    "qs:photos_9k":1,
    "qs:photos_9r":3,
    "qs:photos_all":102,
    "qs:photos_sr":3,
    "qs:placetype":"Town",
    "qs:pop_sr":"2",
    "qs:woe_adm0":23424787,
    "wd:wordcount":145,
    "wof:name":"Tena",
    "wof:placetype":"locality",
    "wof:population":696
},
  "geometry": {"coordinates":[-74.39258,4.66001],"type":"Point"}
}