{
  "type": "Feature",
  "properties": {
    "gn:admin1_code":"29.0",
    "gn:admin2_code":"76147.0",
    "gn:asciiname":"Zaragoza",
    "gn:country_code":"CO",
    "gn:dem":923,
    "gn:feature_class":"P",
    "gn:feature_code":"PPL",
    "gn:name":"Zaragoza",
    "gn:population":0,
    "gn:timezone":"America/Bogota",
    "iso:country":"CO",
    "wof:name":"Zaragoza",
    "wof:placetype":"locality"
},
  "geometry": {"coordinates":[-75.92556,4.69889],"type":"Point"}
}