{
  "type": "Feature",
  "properties": {
    "gn:admin1_code":"3",
    "gn:admin2_code":"81001.0",
    "gn:asciiname":"Los Iguanitos",
    "gn:country_code":"CO",
    "gn:dem":118,
    "gn:feature_class":"P",
    "gn:feature_code":"PPL",
    "gn:name":"Los Iguanitos",
    "gn:population":0,
    "gn:timezone":"America/Bogota",
    "iso:country":"CO",
    "name:und_x_variant":[
        "Fundo Los Iguanitos",
        "Los Iguanitos"
    ],
    "wof:name":"Los Iguanitos",
    "wof:placetype":"locality"
},
  "geometry": {"coordinates":[-70.59584,6.68361],"type":"Point"}
}