{
  "type": "Feature",
  "properties": {
    "gn:admin1_code":"12",
    "gn:asciiname":"Dona Maria",
    "gn:country_code":"CO",
    "gn:dem":19,
    "gn:feature_class":"P",
    "gn:feature_code":"PPL",
    "gn:name":"Do\u00f1a Mar\u00eda",
    "gn:population":0,
    "gn:timezone":"America/Bogota",
    "iso:country":"CO",
    "wof:name":"Dona Maria",
    "wof:placetype":"locality"
},
  "geometry": {"coordinates":[-75.0857,8.48844],"type":"Point"}
}