{
  "type": "Feature",
  "properties": {
    "gn:admin1_code":"20.0",
    "gn:admin2_code":"52786.0",
    "gn:asciiname":"La Senda",
    "gn:country_code":"CO",
    "gn:dem":926,
    "gn:feature_class":"P",
    "gn:feature_code":"PPL",
    "gn:name":"La Senda",
    "gn:population":0,
    "gn:timezone":"America/Bogota",
    "iso:country":"CO",
    "wof:name":"La Senda",
    "wof:placetype":"locality"
},
  "geometry": {"coordinates":[-77.35491999999998,1.64111],"type":"Point"}
}