{
  "type": "Feature",
  "properties": {
    "gn:admin1_code":"3",
    "gn:admin2_code":"81001.0",
    "gn:asciiname":"Flor Amarillo",
    "gn:country_code":"CO",
    "gn:dem":117,
    "gn:feature_class":"P",
    "gn:feature_code":"PPL",
    "gn:name":"Flor Amarillo",
    "gn:population":0,
    "gn:timezone":"America/Bogota",
    "iso:country":"CO",
    "wof:name":"Flor Amarillo",
    "wof:placetype":"locality"
},
  "geometry": {"coordinates":[-70.42860999999998,6.68111],"type":"Point"}
}