{
  "type": "Feature",
  "properties": {
    "gn:admin1_code":"35",
    "gn:admin2_code":"13442.0",
    "gn:asciiname":"Mampujan",
    "gn:country_code":"CO",
    "gn:dem":43,
    "gn:feature_class":"P",
    "gn:feature_code":"PPL",
    "gn:name":"Mampuj\u00e1n",
    "gn:population":0,
    "gn:timezone":"America/Bogota",
    "iso:country":"CO",
    "name:und_x_variant":[
        "Caser\u00edo Mampujan",
        "Mampuj\u00e1n"
    ],
    "wof:name":"Mampujan",
    "wof:placetype":"locality"
},
  "geometry": {"coordinates":[-75.23444000000001,9.99242],"type":"Point"}
}