{
  "type": "Feature",
  "properties": {
    "gn:admin1_code":"20",
    "gn:admin2_code":"52540.0",
    "gn:asciiname":"La Punta",
    "gn:country_code":"CO",
    "gn:dem":1104,
    "gn:feature_class":"P",
    "gn:feature_code":"PPL",
    "gn:name":"La Punta",
    "gn:population":0,
    "gn:timezone":"America/Bogota",
    "iso:country":"CO",
    "wof:name":"La Punta",
    "wof:placetype":"locality"
},
  "geometry": {"coordinates":[-77.3642,1.67794],"type":"Point"}
}