{
  "type": "Feature",
  "properties": {
    "gn:admin1_code":"20",
    "gn:admin2_code":"52540.0",
    "gn:asciiname":"La Punta",
    "gn:country_code":"CO",
    "gn:dem":1104,
    "gn:feature_class":"P",
    "gn:feature_code":"PPL",
    "gn:name":"La Punta",
    "gn:population":0,
    "gn:timezone":"America/Bogota",
    "iso:country":"CO",
    "name:cat_x_preferred":[
        "La Punta"
    ],
    "name:ceb_x_preferred":[
        "La Punta"
    ],
    "name:deu_x_preferred":[
        "La Punta"
    ],
    "name:jpn_x_preferred":[
        "\u30e9\u30fb\u30d7\u30f3\u30bf"
    ],
    "name:nld_x_preferred":[
        "La Punta"
    ],
    "name:srp_x_preferred":[
        "La Punta"
    ],
    "name:swe_x_preferred":[
        "La Punta"
    ],
    "wof:name":"La Punta",
    "wof:placetype":"locality"
},
  "geometry": {"coordinates":[-77.3642,1.67794],"type":"Point"}
}