{
  "type": "Feature",
  "properties": {
    "gn:admin1_code":"38",
    "gn:admin2_code":"47798.0",
    "gn:asciiname":"El Mocho",
    "gn:country_code":"CO",
    "gn:dem":128,
    "gn:feature_class":"P",
    "gn:feature_code":"PPL",
    "gn:name":"El Mocho",
    "gn:population":0,
    "gn:timezone":"America/Bogota",
    "iso:country":"CO",
    "wof:name":"El Mocho",
    "wof:placetype":"locality"
},
  "geometry": {"coordinates":[-74.61166999999998,9.97738],"type":"Point"}
}