{
  "type": "Feature",
  "properties": {
    "gn:admin1_code":"33",
    "gn:admin2_code":"25885.0",
    "gn:asciiname":"Alto Seco",
    "gn:country_code":"CO",
    "gn:dem":1373,
    "gn:feature_class":"P",
    "gn:feature_code":"PPL",
    "gn:name":"Alto Seco",
    "gn:population":0,
    "gn:timezone":"America/Bogota",
    "iso:country":"CO",
    "wof:name":"Alto Seco",
    "wof:placetype":"locality"
},
  "geometry": {"coordinates":[-74.36861,5.59833],"type":"Point"}
}