{
  "type": "Feature",
  "properties": {
    "iso:country":"CO",
    "name:ast_x_preferred":[
        "El Espino"
    ],
    "name:ceb_x_preferred":[
        "El Espino"
    ],
    "name:eng_x_preferred":[
        "El Espino"
    ],
    "name:fra_x_preferred":[
        "El Espino"
    ],
    "name:ita_x_preferred":[
        "El Espino"
    ],
    "name:kat_x_preferred":[
        "\u10d4\u10da-\u10d4\u10e1\u10de\u10d8\u10dc\u10dd"
    ],
    "name:msa_x_preferred":[
        "El Espino"
    ],
    "name:nan_x_preferred":[
        "El Espino"
    ],
    "name:nld_x_preferred":[
        "El Espino"
    ],
    "name:por_x_preferred":[
        "El Espino"
    ],
    "name:spa_x_preferred":[
        "El Espino"
    ],
    "name:swe_x_preferred":[
        "El Espino"
    ],
    "name:tgl_x_preferred":[
        "El Espino"
    ],
    "name:unk_x_variant":[
        "Espino"
    ],
    "name:vie_x_preferred":[
        "El Espino"
    ],
    "name:war_x_preferred":[
        "El Espino"
    ],
    "name:zho_x_preferred":[
        "\u57c3\u723e\u57c3\u65af\u76ae\u8afe"
    ],
    "qs:gn_country":"CO",
    "qs:gn_fcode":"PPL",
    "qs:gn_pop":1313,
    "qs:name":"El Espino",
    "qs:name_adm0":"Colombia",
    "qs:name_adm1":"Boyaca",
    "qs:photos":0,
    "qs:photos_1k":0,
    "qs:photos_9k":0,
    "qs:photos_9r":0,
    "qs:photos_all":0,
    "qs:photos_sr":0,
    "qs:placetype":"Town",
    "qs:pop_sr":"3",
    "qs:woe_adm0":23424787,
    "wd:wordcount":21,
    "wof:name":"El Espino",
    "wof:placetype":"locality",
    "wof:population":1313
},
  "geometry": {"coordinates":[-72.49718,6.48277],"type":"Point"}
}