{
  "type": "Feature",
  "properties": {
    "gn:admin1_code":"30",
    "gn:admin2_code":"97001.0",
    "gn:asciiname":"Enrique",
    "gn:country_code":"CO",
    "gn:dem":224,
    "gn:feature_class":"P",
    "gn:feature_code":"PPL",
    "gn:name":"Enrique",
    "gn:population":0,
    "gn:timezone":"America/Bogota",
    "iso:country":"CO",
    "wof:name":"Enrique",
    "wof:placetype":"locality"
},
  "geometry": {"coordinates":[-70.46666999999999,0.88333],"type":"Point"}
}