{
  "type": "Feature",
  "properties": {
    "gn:admin1_code":"23.0",
    "gn:admin2_code":"63130.0",
    "gn:asciiname":"Alto del Rio",
    "gn:country_code":"CO",
    "gn:dem":1541,
    "gn:feature_class":"P",
    "gn:feature_code":"PPL",
    "gn:name":"Alto del R\u00edo",
    "gn:population":0,
    "gn:timezone":"America/Bogota",
    "iso:country":"CO",
    "wof:name":"Alto del Rio",
    "wof:placetype":"locality"
},
  "geometry": {"coordinates":[-75.65028000000002,4.53972],"type":"Point"}
}