{
  "type": "Feature",
  "properties": {
    "gn:admin1_code":"1",
    "gn:admin2_code":"91405.0",
    "gn:asciiname":"Guidones",
    "gn:country_code":"CO",
    "gn:dem":191,
    "gn:feature_class":"P",
    "gn:feature_code":"PPL",
    "gn:name":"Guidones",
    "gn:population":0,
    "gn:timezone":"America/Bogota",
    "iso:country":"CO",
    "wof:name":"Guidones",
    "wof:placetype":"locality"
},
  "geometry": {"coordinates":[-73.23333000000002,-1.16667],"type":"Point"}
}