{
  "type": "Feature",
  "properties": {
    "gn:admin1_code":"38",
    "gn:admin2_code":"47030.0",
    "gn:asciiname":"Bella Flor",
    "gn:country_code":"CO",
    "gn:dem":138,
    "gn:feature_class":"P",
    "gn:feature_code":"PPL",
    "gn:name":"Bella Flor",
    "gn:population":0,
    "gn:timezone":"America/Bogota",
    "iso:country":"CO",
    "wof:name":"Bella Flor",
    "wof:placetype":"locality"
},
  "geometry": {"coordinates":[-74.0398,10.2847],"type":"Point"}
}