{
  "type": "Feature",
  "properties": {
    "gn:admin1_code":"28.0",
    "gn:admin2_code":"73461.0",
    "gn:asciiname":"Penones",
    "gn:country_code":"CO",
    "gn:dem":2402,
    "gn:feature_class":"P",
    "gn:feature_code":"PPL",
    "gn:name":"Pe\u00f1ones",
    "gn:population":0,
    "gn:timezone":"America/Bogota",
    "iso:country":"CO",
    "wof:name":"Penones",
    "wof:placetype":"locality"
},
  "geometry": {"coordinates":[-75.13333,4.88333],"type":"Point"}
}