{
  "type": "Feature",
  "properties": {
    "gn:admin1_code":"16.0",
    "gn:admin2_code":"41791.0",
    "gn:asciiname":"El Rodeito",
    "gn:country_code":"CO",
    "gn:dem":977,
    "gn:feature_class":"P",
    "gn:feature_code":"PPL",
    "gn:name":"El Rodeito",
    "gn:population":0,
    "gn:timezone":"America/Bogota",
    "iso:country":"CO",
    "wof:name":"El Rodeito",
    "wof:placetype":"locality"
},
  "geometry": {"coordinates":[-75.82004999999999,2.15368],"type":"Point"}
}