{
  "type": "Feature",
  "properties": {
    "gn:admin1_code":"33.0",
    "gn:admin2_code":"25320.0",
    "gn:asciiname":"San Vincente",
    "gn:country_code":"CO",
    "gn:dem":1861,
    "gn:feature_class":"P",
    "gn:feature_code":"PPL",
    "gn:name":"San Vincente",
    "gn:population":0,
    "gn:timezone":"America/Bogota",
    "iso:country":"CO",
    "name:spa_x_preferred":[
        "San Vincente"
    ],
    "wof:name":"San Vincente",
    "wof:placetype":"locality"
},
  "geometry": {"coordinates":[-74.53854,5.01834],"type":"Point"}
}