{
  "type": "Feature",
  "properties": {
    "gn:admin1_code":"27",
    "gn:admin2_code":"70823.0",
    "gn:asciiname":"Gualon",
    "gn:country_code":"CO",
    "gn:dem":74,
    "gn:feature_class":"P",
    "gn:feature_code":"PPL",
    "gn:name":"Gual\u00f3n",
    "gn:population":0,
    "gn:timezone":"America/Bogota",
    "iso:country":"CO",
    "name:und_x_variant":[
        "Caserio Gualon",
        "Gual\u00f3n"
    ],
    "wof:name":"Gualon",
    "wof:placetype":"locality"
},
  "geometry": {"coordinates":[-75.46565,9.40063],"type":"Point"}
}