{
  "type": "Feature",
  "properties": {
    "gn:admin1_code":"36",
    "gn:admin2_code":"15816.0",
    "gn:asciiname":"Funcional",
    "gn:country_code":"CO",
    "gn:dem":1866,
    "gn:feature_class":"P",
    "gn:feature_code":"PPL",
    "gn:name":"Funcional",
    "gn:population":0,
    "gn:timezone":"America/Bogota",
    "iso:country":"CO",
    "wof:name":"Funcional",
    "wof:placetype":"locality"
},
  "geometry": {"coordinates":[-73.52043,5.9629],"type":"Point"}
}