{
  "type": "Feature",
  "properties": {
    "gn:admin1_code":"28",
    "gn:admin2_code":"73001.0",
    "gn:asciiname":"Laureles",
    "gn:country_code":"CO",
    "gn:dem":2174,
    "gn:feature_class":"P",
    "gn:feature_code":"PPL",
    "gn:name":"Laureles",
    "gn:population":0,
    "gn:timezone":"America/Bogota",
    "iso:country":"CO",
    "name:ceb_x_preferred":[
        "Laureles"
    ],
    "name:eus_x_preferred":[
        "Laureles"
    ],
    "name:ita_x_preferred":[
        "Laureles"
    ],
    "name:por_x_preferred":[
        "Laureles"
    ],
    "name:spa_x_preferred":[
        "Laureles"
    ],
    "name:zho_x_preferred":[
        "\u52de\u96f7\u840a\u65af"
    ],
    "wof:name":"Laureles",
    "wof:placetype":"locality"
},
  "geometry": {"coordinates":[-75.40000000000001,4.33333],"type":"Point"}
}