{
  "type": "Feature",
  "properties": {
    "gn:admin1_code":"32.0",
    "gn:admin2_code":"85250.0",
    "gn:asciiname":"Puerto Infante",
    "gn:country_code":"CO",
    "gn:dem":130,
    "gn:feature_class":"P",
    "gn:feature_code":"PPL",
    "gn:name":"Puerto Infante",
    "gn:population":0,
    "gn:timezone":"America/Bogota",
    "iso:country":"CO",
    "wof:name":"Puerto Infante",
    "wof:placetype":"locality"
},
  "geometry": {"coordinates":[-71.00528,5.71028],"type":"Point"}
}