{
  "type": "Feature",
  "properties": {
    "gn:admin1_code":"8.0",
    "gn:admin2_code":"18460.0",
    "gn:asciiname":"Betania",
    "gn:country_code":"CO",
    "gn:dem":210,
    "gn:feature_class":"P",
    "gn:feature_code":"PPL",
    "gn:name":"Betania",
    "gn:population":0,
    "gn:timezone":"America/Bogota",
    "iso:country":"CO",
    "name:bre_x_preferred":[
        "Betania"
    ],
    "name:ceb_x_preferred":[
        "Betania"
    ],
    "name:deu_x_preferred":[
        "Betania"
    ],
    "name:ita_x_preferred":[
        "Betania"
    ],
    "name:nld_x_preferred":[
        "Betania"
    ],
    "name:nor_x_preferred":[
        "Betania"
    ],
    "name:ron_x_preferred":[
        "Betania"
    ],
    "name:sco_x_preferred":[
        "Betania"
    ],
    "name:spa_x_preferred":[
        "Betania"
    ],
    "name:swe_x_preferred":[
        "Betania"
    ],
    "name:tgl_x_preferred":[
        "Betania"
    ],
    "name:war_x_preferred":[
        "Betania"
    ],
    "wof:name":"Betania",
    "wof:placetype":"locality"
},
  "geometry": {"coordinates":[-75.50944,1.19151],"type":"Point"}
}