{
  "type": "Feature",
  "properties": {
    "gn:admin1_code":"8.0",
    "gn:admin2_code":"18460.0",
    "gn:asciiname":"Betania",
    "gn:country_code":"CO",
    "gn:dem":210,
    "gn:feature_class":"P",
    "gn:feature_code":"PPL",
    "gn:name":"Betania",
    "gn:population":0,
    "gn:timezone":"America/Bogota",
    "iso:country":"CO",
    "name:spa_x_preferred":[
        "Betania"
    ],
    "wof:name":"Betania",
    "wof:placetype":"locality"
},
  "geometry": {"coordinates":[-75.50944,1.19151],"type":"Point"}
}