{
  "type": "Feature",
  "properties": {
    "gn:admin1_code":"35",
    "gn:admin2_code":"13030.0",
    "gn:asciiname":"Alto de Cuatro Bocas",
    "gn:country_code":"CO",
    "gn:dem":73,
    "gn:feature_class":"P",
    "gn:feature_code":"PPL",
    "gn:name":"Alto de Cuatro Bocas",
    "gn:population":0,
    "gn:timezone":"America/Bogota",
    "iso:country":"CO",
    "wof:name":"Alto de Cuatro Bocas",
    "wof:placetype":"locality"
},
  "geometry": {"coordinates":[-74.14539000000001,8.72238],"type":"Point"}
}