{
  "type": "Feature",
  "properties": {
    "gn:admin1_code":"28",
    "gn:admin2_code":"73563.0",
    "gn:asciiname":"Viviendas Hidroprado",
    "gn:country_code":"CO",
    "gn:dem":364,
    "gn:feature_class":"P",
    "gn:feature_code":"PPL",
    "gn:name":"Viviendas Hidroprado",
    "gn:population":0,
    "gn:timezone":"America/Bogota",
    "iso:country":"CO",
    "name:spa_x_preferred":[
        "Viviendas Hidroprado"
    ],
    "wof:name":"Viviendas Hidroprado",
    "wof:placetype":"locality"
},
  "geometry": {"coordinates":[-74.89842,3.7507],"type":"Point"}
}