{
  "type": "Feature",
  "properties": {
    "gn:admin1_code":"29",
    "gn:admin2_code":"76130.0",
    "gn:asciiname":"La Gorgona",
    "gn:country_code":"CO",
    "gn:dem":968,
    "gn:feature_class":"P",
    "gn:feature_code":"PPL",
    "gn:name":"La Gorgona",
    "gn:population":0,
    "gn:timezone":"America/Bogota",
    "iso:country":"CO",
    "name:und_x_variant":[
        "Gorgona",
        "La Gorgona"
    ],
    "wof:name":"La Gorgona",
    "wof:placetype":"locality"
},
  "geometry": {"coordinates":[-76.38685,3.39572],"type":"Point"}
}