{
  "type": "Feature",
  "properties": {
    "gn:admin1_code":"12",
    "gn:admin2_code":"23090.0",
    "gn:asciiname":"Risaranda",
    "gn:country_code":"CO",
    "gn:dem":76,
    "gn:feature_class":"P",
    "gn:feature_code":"PPL",
    "gn:name":"Risaranda",
    "gn:population":0,
    "gn:timezone":"America/Bogota",
    "iso:country":"CO",
    "wof:name":"Risaranda",
    "wof:placetype":"locality"
},
  "geometry": {"coordinates":[-76.16224,8.80116],"type":"Point"}
}