{
  "type": "Feature",
  "properties": {
    "gn:admin1_code":"38",
    "gn:admin2_code":"47555.0",
    "gn:asciiname":"Disciplina",
    "gn:country_code":"CO",
    "gn:dem":92,
    "gn:feature_class":"P",
    "gn:feature_code":"PPL",
    "gn:name":"Disciplina",
    "gn:population":0,
    "gn:timezone":"America/Bogota",
    "iso:country":"CO",
    "name:und_x_variant":[
        "Hacienda Disciplina",
        "Diciplina",
        "Disciplina"
    ],
    "wof:name":"Disciplina",
    "wof:placetype":"locality"
},
  "geometry": {"coordinates":[-74.50876,9.65637],"type":"Point"}
}