{
  "type": "Feature",
  "properties": {
    "gn:admin1_code":"19.0",
    "gn:admin2_code":"50683.0",
    "gn:asciiname":"Costarrica",
    "gn:country_code":"CO",
    "gn:dem":321,
    "gn:feature_class":"P",
    "gn:feature_code":"PPL",
    "gn:name":"Costarrica",
    "gn:population":0,
    "gn:timezone":"America/Bogota",
    "iso:country":"CO",
    "wof:name":"Costarrica",
    "wof:placetype":"locality"
},
  "geometry": {"coordinates":[-73.85139000000002,3.24556],"type":"Point"}
}