{
  "type": "Feature",
  "properties": {
    "gn:admin1_code":"10.0",
    "gn:admin2_code":"20045.0",
    "gn:asciiname":"La Chiquita",
    "gn:country_code":"CO",
    "gn:dem":47,
    "gn:feature_class":"P",
    "gn:feature_code":"PPL",
    "gn:name":"La Chiquita",
    "gn:population":0,
    "gn:timezone":"America/Bogota",
    "iso:country":"CO",
    "name:spa_x_preferred":[
        "La Chiquita"
    ],
    "name:urd_x_preferred":[
        "\u0644\u0627 \u0686\u06cc\u06a9\u0648\u06cc\u062a\u0627"
    ],
    "wof:name":"La Chiquita",
    "wof:placetype":"locality"
},
  "geometry": {"coordinates":[-73.55412,9.72953],"type":"Point"}
}