{
  "type": "Feature",
  "properties": {
    "gn:admin1_code":"16.0",
    "gn:admin2_code":"41078.0",
    "gn:asciiname":"Los Canchos",
    "gn:country_code":"CO",
    "gn:dem":864,
    "gn:feature_class":"P",
    "gn:feature_code":"PPL",
    "gn:name":"Los Canchos",
    "gn:population":0,
    "gn:timezone":"America/Bogota",
    "iso:country":"CO",
    "name:spa_x_preferred":[
        "Los Canchos"
    ],
    "wof:name":"Los Canchos",
    "wof:placetype":"locality"
},
  "geometry": {"coordinates":[-74.98806,3.20917],"type":"Point"}
}