{
  "type": "Feature",
  "properties": {
    "gn:admin1_code":"38",
    "gn:admin2_code":"47258.0",
    "gn:asciiname":"Cantagallar",
    "gn:country_code":"CO",
    "gn:dem":13,
    "gn:feature_class":"P",
    "gn:feature_code":"PPL",
    "gn:name":"Cantagallar",
    "gn:population":0,
    "gn:timezone":"America/Bogota",
    "iso:country":"CO",
    "name:und_x_variant":[
        "Corregimiento Cantagallar",
        "Cantagallo",
        "Cantagallar"
    ],
    "wof:name":"Cantagallar",
    "wof:placetype":"locality"
},
  "geometry": {"coordinates":[-74.80083,10.34862],"type":"Point"}
}