{
  "type": "Feature",
  "properties": {
    "gn:admin1_code":"38",
    "gn:admin2_code":"47980.0",
    "gn:asciiname":"Latal",
    "gn:country_code":"CO",
    "gn:dem":20,
    "gn:feature_class":"P",
    "gn:feature_code":"PPL",
    "gn:name":"Latal",
    "gn:population":0,
    "gn:timezone":"America/Bogota",
    "iso:country":"CO",
    "name:und_x_variant":[
        "Campamento Latal",
        "Lata",
        "Latal"
    ],
    "wof:name":"Latal",
    "wof:placetype":"locality"
},
  "geometry": {"coordinates":[-74.16185,10.79364],"type":"Point"}
}