{
  "type": "Feature",
  "properties": {
    "gn:admin1_code":"10",
    "gn:admin2_code":"20032.0",
    "gn:asciiname":"Casablanca",
    "gn:country_code":"CO",
    "gn:dem":52,
    "gn:feature_class":"P",
    "gn:feature_code":"PPL",
    "gn:name":"Casablanca",
    "gn:population":0,
    "gn:timezone":"America/Bogota",
    "iso:country":"CO",
    "wof:name":"Casablanca",
    "wof:placetype":"locality"
},
  "geometry": {"coordinates":[-73.87121999999999,9.4836],"type":"Point"}
}