{
  "type": "Feature",
  "properties": {
    "gn:admin1_code":"8.0",
    "gn:admin2_code":"18460.0",
    "gn:asciiname":"San Francisco",
    "gn:country_code":"CO",
    "gn:dem":217,
    "gn:feature_class":"P",
    "gn:feature_code":"PPL",
    "gn:name":"San Francisco",
    "gn:population":0,
    "gn:timezone":"America/Bogota",
    "iso:country":"CO",
    "name:spa_x_preferred":[
        "San Francisco"
    ],
    "name:spa_x_variant":[
        "Caser\u00edo San Francisco"
    ],
    "name:und_x_variant":[
        "Caser\u00edo San Francisco"
    ],
    "wof:name":"San Francisco",
    "wof:placetype":"locality"
},
  "geometry": {"coordinates":[-75.30826,1.02227],"type":"Point"}
}