{
  "type": "Feature",
  "properties": {
    "gn:admin1_code":"16.0",
    "gn:admin2_code":"41206.0",
    "gn:asciiname":"San Ezequiel",
    "gn:country_code":"CO",
    "gn:dem":1955,
    "gn:feature_class":"P",
    "gn:feature_code":"PPL",
    "gn:name":"San Ezequiel",
    "gn:population":0,
    "gn:timezone":"America/Bogota",
    "iso:country":"CO",
    "name:spa_x_preferred":[
        "San Ezequiel"
    ],
    "wof:name":"San Ezequiel",
    "wof:placetype":"locality"
},
  "geometry": {"coordinates":[-74.81288000000001,3.18914],"type":"Point"}
}