{
  "type": "Feature",
  "properties": {
    "gn:admin1_code":"17",
    "gn:admin2_code":"44378.0",
    "gn:asciiname":"Caracoli",
    "gn:country_code":"CO",
    "gn:dem":173,
    "gn:feature_class":"P",
    "gn:feature_code":"PPL",
    "gn:name":"Caracol\u00ed",
    "gn:population":0,
    "gn:timezone":"America/Bogota",
    "iso:country":"CO",
    "wof:name":"Caracoli",
    "wof:placetype":"locality"
},
  "geometry": {"coordinates":[-72.69984000000002,11.0822],"type":"Point"}
}