{
  "type": "Feature",
  "properties": {
    "gn:admin1_code":"38",
    "gn:admin2_code":"47318.0",
    "gn:asciiname":"Los Tamaquitos",
    "gn:country_code":"CO",
    "gn:dem":56,
    "gn:feature_class":"P",
    "gn:feature_code":"PPL",
    "gn:name":"Los Tamaquitos",
    "gn:population":0,
    "gn:timezone":"America/Bogota",
    "iso:country":"CO",
    "name:und_x_variant":[
        "Caser\u00edo Los Tamaquitos",
        "Los Tamaquitos"
    ],
    "wof:name":"Los Tamaquitos",
    "wof:placetype":"locality"
},
  "geometry": {"coordinates":[-74.16086,9.30815],"type":"Point"}
}