{
  "type": "Feature",
  "properties": {
    "gn:admin1_code":"22.0",
    "gn:asciiname":"El Cedro",
    "gn:country_code":"CO",
    "gn:dem":252,
    "gn:feature_class":"P",
    "gn:feature_code":"PPL",
    "gn:name":"El Cedro",
    "gn:population":0,
    "gn:timezone":"America/Bogota",
    "iso:country":"CO",
    "name:ceb_x_preferred":[
        "El Cedro"
    ],
    "name:fra_x_preferred":[
        "El Cedro"
    ],
    "name:ita_x_preferred":[
        "El Cedro"
    ],
    "name:spa_x_preferred":[
        "El Cedro"
    ],
    "name:swe_x_preferred":[
        "El Cedro"
    ],
    "wof:name":"El Cedro",
    "wof:placetype":"locality"
},
  "geometry": {"coordinates":[-76.22425,0.97788],"type":"Point"}
}