{
  "type": "Feature",
  "properties": {
    "gn:admin1_code":"4.0",
    "gn:admin2_code":"8001.0",
    "gn:asciiname":"La Cabana",
    "gn:country_code":"CO",
    "gn:dem":29,
    "gn:feature_class":"P",
    "gn:feature_code":"PPL",
    "gn:name":"La Caba\u00f1a",
    "gn:population":0,
    "gn:timezone":"America/Bogota",
    "iso:country":"CO",
    "wof:name":"La Cabana",
    "wof:placetype":"locality"
},
  "geometry": {"coordinates":[-74.88245999999999,10.97235],"type":"Point"}
}