{
  "type": "Feature",
  "properties": {
    "gn:admin1_code":"8.0",
    "gn:admin2_code":"18860.0",
    "gn:asciiname":"La Nueva Colombia",
    "gn:country_code":"CO",
    "gn:dem":230,
    "gn:feature_class":"P",
    "gn:feature_code":"PPL",
    "gn:name":"La Nueva Colombia",
    "gn:population":0,
    "gn:timezone":"America/Bogota",
    "iso:country":"CO",
    "name:spa_x_preferred":[
        "La Nueva Colombia"
    ],
    "wof:name":"La Nueva Colombia",
    "wof:placetype":"locality"
},
  "geometry": {"coordinates":[-75.70703,1.18771],"type":"Point"}
}