{
  "type": "Feature",
  "properties": {
    "gn:admin1_code":"36",
    "gn:admin2_code":"15676.0",
    "gn:asciiname":"La Congaja",
    "gn:country_code":"CO",
    "gn:dem":2756,
    "gn:feature_class":"P",
    "gn:feature_code":"PPL",
    "gn:name":"La Congaja",
    "gn:population":0,
    "gn:timezone":"America/Bogota",
    "iso:country":"CO",
    "wof:name":"La Congaja",
    "wof:placetype":"locality"
},
  "geometry": {"coordinates":[-73.68861,5.52083],"type":"Point"}
}