{
  "type": "Feature",
  "properties": {
    "iso:country":"CO",
    "name:cat_x_preferred":[
        "Tocaima"
    ],
    "name:chi_x_preferred":[
        "\u6258\u51f1\u99ac"
    ],
    "name:dut_x_preferred":[
        "Tocaima"
    ],
    "name:eng_x_preferred":[
        "Tocaima"
    ],
    "name:fre_x_preferred":[
        "Tocaima"
    ],
    "name:geo_x_preferred":[
        "\u10e2\u10dd\u10d9\u10d0\u10d8\u10db\u10d0"
    ],
    "name:ger_x_preferred":[
        "Tocaima"
    ],
    "name:gla_x_preferred":[
        "Tocaima"
    ],
    "name:ita_x_preferred":[
        "Tocaima"
    ],
    "name:may_x_preferred":[
        "Tocaima"
    ],
    "name:nan_x_preferred":[
        "Tocaima"
    ],
    "name:por_x_preferred":[
        "Tocaima"
    ],
    "name:spa_x_preferred":[
        "Tocaima"
    ],
    "name:swe_x_preferred":[
        "Tocaima"
    ],
    "name:tgl_x_preferred":[
        "Tocaima"
    ],
    "name:vie_x_preferred":[
        "Tocaima"
    ],
    "name:war_x_preferred":[
        "Tocaima"
    ],
    "qs:gn_country":"CO",
    "qs:gn_fcode":"PPL",
    "qs:gn_pop":10235,
    "qs:name":"Tocaima",
    "qs:name_adm0":"Colombia",
    "qs:name_adm1":"Cundinamarca",
    "qs:photos":223,
    "qs:photos_1k":45,
    "qs:photos_9k":1,
    "qs:photos_9r":4,
    "qs:photos_all":223,
    "qs:photos_sr":4,
    "qs:placetype":"Town",
    "qs:pop_sr":"6",
    "qs:woe_adm0":23424787,
    "wof:name":"Tocaima",
    "wof:placetype":"locality",
    "wof:population":10235
},
  "geometry": {"coordinates":[-74.63433999999999,4.4582],"type":"Point"}
}