{
  "type": "Feature",
  "properties": {
    "iso:country":"CO",
    "name:ast_x_preferred":[
        "Tocaima"
    ],
    "name:avk_x_preferred":[
        "Tocaima"
    ],
    "name:cat_x_preferred":[
        "Tocaima"
    ],
    "name:ceb_x_preferred":[
        "Tocaima"
    ],
    "name:deu_x_preferred":[
        "Tocaima"
    ],
    "name:eng_x_preferred":[
        "Tocaima"
    ],
    "name:fas_x_preferred":[
        "\u062a\u0648\u06a9\u0627\u06cc\u0645\u0627"
    ],
    "name:fra_x_preferred":[
        "Tocaima"
    ],
    "name:gla_x_preferred":[
        "Tocaima"
    ],
    "name:gle_x_preferred":[
        "Tocaima"
    ],
    "name:glg_x_preferred":[
        "Tocaima"
    ],
    "name:ita_x_preferred":[
        "Tocaima"
    ],
    "name:kat_x_preferred":[
        "\u10e2\u10dd\u10d9\u10d0\u10d8\u10db\u10d0"
    ],
    "name:msa_x_preferred":[
        "Tocaima"
    ],
    "name:nan_x_preferred":[
        "Tocaima"
    ],
    "name:nld_x_preferred":[
        "Tocaima"
    ],
    "name:pol_x_preferred":[
        "Tocaima"
    ],
    "name:por_x_preferred":[
        "Tocaima"
    ],
    "name:rus_x_preferred":[
        "\u0422\u043e\u043a\u0430\u0439\u043c\u0430"
    ],
    "name:spa_x_preferred":[
        "Tocaima"
    ],
    "name:swe_x_preferred":[
        "Tocaima"
    ],
    "name:tgl_x_preferred":[
        "Tocaima"
    ],
    "name:ukr_x_preferred":[
        "\u0422\u043e\u043a\u0430\u0457\u043c\u0430"
    ],
    "name:vie_x_preferred":[
        "Tocaima"
    ],
    "name:war_x_preferred":[
        "Tocaima"
    ],
    "name:zho_x_preferred":[
        "\u6258\u51f1\u99ac"
    ],
    "qs:gn_country":"CO",
    "qs:gn_fcode":"PPL",
    "qs:gn_pop":10235,
    "qs:name":"Tocaima",
    "qs:name_adm0":"Colombia",
    "qs:name_adm1":"Cundinamarca",
    "qs:photos":223,
    "qs:photos_1k":45,
    "qs:photos_9k":1,
    "qs:photos_9r":4,
    "qs:photos_all":223,
    "qs:photos_sr":4,
    "qs:placetype":"Town",
    "qs:pop_sr":"6",
    "qs:woe_adm0":23424787,
    "wof:name":"Tocaima",
    "wof:placetype":"locality",
    "wof:population":10235
},
  "geometry": {"coordinates":[-74.63433999999999,4.4582],"type":"Point"}
}