{
  "type": "Feature",
  "properties": {
    "gn:admin1_code":"17",
    "gn:admin2_code":"44874.0",
    "gn:asciiname":"Aruba",
    "gn:country_code":"CO",
    "gn:dem":1207,
    "gn:feature_class":"P",
    "gn:feature_code":"PPL",
    "gn:name":"Aruba",
    "gn:population":0,
    "gn:timezone":"America/Bogota",
    "iso:country":"CO",
    "wof:name":"Aruba",
    "wof:placetype":"locality"
},
  "geometry": {"coordinates":[-72.9175,10.54111],"type":"Point"}
}