{
  "type": "Feature",
  "properties": {
    "gn:admin1_code":"35",
    "gn:admin2_code":"13442.0",
    "gn:asciiname":"Arroyo Grande",
    "gn:country_code":"CO",
    "gn:dem":25,
    "gn:feature_class":"P",
    "gn:feature_code":"PPL",
    "gn:name":"Arroyo Grande",
    "gn:population":0,
    "gn:timezone":"America/Bogota",
    "iso:country":"CO",
    "name:und_x_variant":[
        "Caserio Arroyo Grande",
        "Arroyo Grande"
    ],
    "wof:name":"Arroyo Grande",
    "wof:placetype":"locality"
},
  "geometry": {"coordinates":[-75.35508,9.89517],"type":"Point"}
}