{
  "type": "Feature",
  "properties": {
    "gn:admin1_code":"8",
    "gn:admin2_code":"18150.0",
    "gn:asciiname":"Los Cotudos",
    "gn:country_code":"CO",
    "gn:dem":184,
    "gn:feature_class":"P",
    "gn:feature_code":"PPL",
    "gn:name":"Los Cotudos",
    "gn:population":0,
    "gn:timezone":"America/Bogota",
    "iso:country":"CO",
    "wof:name":"Los Cotudos",
    "wof:placetype":"locality"
},
  "geometry": {"coordinates":[-74.21939999999999,0.20459],"type":"Point"}
}