{
  "type": "Feature",
  "properties": {
    "gn:admin1_code":"10",
    "gn:admin2_code":"20175.0",
    "gn:asciiname":"Democracia",
    "gn:country_code":"CO",
    "gn:dem":44,
    "gn:feature_class":"P",
    "gn:feature_code":"PPL",
    "gn:name":"Democracia",
    "gn:population":0,
    "gn:timezone":"America/Bogota",
    "iso:country":"CO",
    "wof:name":"Democracia",
    "wof:placetype":"locality"
},
  "geometry": {"coordinates":[-73.79210999999999,9.36599],"type":"Point"}
}