{
  "type": "Feature",
  "properties": {
    "gn:admin1_code":"16.0",
    "gn:admin2_code":"41791.0",
    "gn:asciiname":"Jagualito",
    "gn:country_code":"CO",
    "gn:dem":939,
    "gn:feature_class":"P",
    "gn:feature_code":"PPL",
    "gn:name":"Jagualito",
    "gn:population":0,
    "gn:timezone":"America/Bogota",
    "iso:country":"CO",
    "wof:name":"Jagualito",
    "wof:placetype":"locality"
},
  "geometry": {"coordinates":[-75.81166999999998,2.19139],"type":"Point"}
}