{
  "type": "Feature",
  "properties": {
    "gn:admin1_code":"29",
    "gn:admin2_code":"76834.0",
    "gn:asciiname":"Calle Larga",
    "gn:country_code":"CO",
    "gn:dem":2894,
    "gn:feature_class":"P",
    "gn:feature_code":"PPL",
    "gn:name":"Calle Larga",
    "gn:population":0,
    "gn:timezone":"America/Bogota",
    "iso:country":"CO",
    "wof:name":"Calle Larga",
    "wof:placetype":"locality"
},
  "geometry": {"coordinates":[-75.88361,4.03944],"type":"Point"}
}