{
  "type": "Feature",
  "properties": {
    "gn:admin1_code":"20",
    "gn:admin2_code":"52694.0",
    "gn:asciiname":"Capuli",
    "gn:country_code":"CO",
    "gn:dem":2505,
    "gn:feature_class":"P",
    "gn:feature_code":"PPL",
    "gn:name":"Capuli",
    "gn:population":0,
    "gn:timezone":"America/Bogota",
    "iso:country":"CO",
    "name:spa_x_preferred":[
        "Capul\u00ed"
    ],
    "wof:name":"Capuli",
    "wof:placetype":"locality"
},
  "geometry": {"coordinates":[-77.10293,1.52506],"type":"Point"}
}