{
  "type": "Feature",
  "properties": {
    "gn:admin1_code":"11.0",
    "gn:asciiname":"Loma de Pulgas",
    "gn:country_code":"CO",
    "gn:dem":7,
    "gn:feature_class":"P",
    "gn:feature_code":"PPL",
    "gn:name":"Loma de Pulgas",
    "gn:population":0,
    "gn:timezone":"America/Bogota",
    "iso:country":"CO",
    "wof:name":"Loma de Pulgas",
    "wof:placetype":"locality"
},
  "geometry": {"coordinates":[-77.11575000000001,7.79022],"type":"Point"}
}