{
  "type": "Feature",
  "properties": {
    "gn:admin1_code":"17.0",
    "gn:admin2_code":"44847.0",
    "gn:asciiname":"Rancheria Amace",
    "gn:country_code":"CO",
    "gn:dem":14,
    "gn:feature_class":"P",
    "gn:feature_code":"PPLL",
    "gn:name":"Rancher\u00eda Amace",
    "gn:population":0,
    "gn:timezone":"America/Bogota",
    "iso:country":"CO",
    "name:spa_x_preferred":[
        "Rancher\u00eda Amace"
    ],
    "name:und_x_variant":[
        "Amace"
    ],
    "wof:name":"Rancheria Amace",
    "wof:placetype":"locality"
},
  "geometry": {"coordinates":[-71.36969999999999,12.01772],"type":"Point"}
}