{
  "type": "Feature",
  "properties": {
    "gn:admin1_code":"35.0",
    "gn:admin2_code":"13440.0",
    "gn:asciiname":"Sandoval",
    "gn:country_code":"CO",
    "gn:dem":25,
    "gn:feature_class":"P",
    "gn:feature_code":"PPL",
    "gn:name":"Sandoval",
    "gn:population":0,
    "gn:timezone":"America/Bogota",
    "iso:country":"CO",
    "name:heb_x_preferred":[
        "\u05e1\u05e0\u05d3\u05d5\u05d1\u05dc"
    ],
    "name:rus_x_preferred":[
        "\u0421\u0430\u043d\u0434\u043e\u0432\u0430\u043b"
    ],
    "name:und_x_variant":[
        "Corregimiento Sandoval",
        "Sandoval"
    ],
    "wof:name":"Sandoval",
    "wof:placetype":"locality"
},
  "geometry": {"coordinates":[-74.2435,9.13168],"type":"Point"}
}