{
  "type": "Feature",
  "properties": {
    "gn:admin1_code":"26",
    "gn:admin2_code":"68773.0",
    "gn:asciiname":"Villa Alicia",
    "gn:country_code":"CO",
    "gn:dem":2730,
    "gn:feature_class":"P",
    "gn:feature_code":"PPL",
    "gn:name":"Villa Alicia",
    "gn:population":0,
    "gn:timezone":"America/Bogota",
    "iso:country":"CO",
    "wof:name":"Villa Alicia",
    "wof:placetype":"locality"
},
  "geometry": {"coordinates":[-73.83306,5.915],"type":"Point"}
}