{
  "type": "Feature",
  "properties": {
    "gn:admin1_code":"19.0",
    "gn:admin2_code":"50573.0",
    "gn:asciiname":"Mozambique",
    "gn:country_code":"CO",
    "gn:dem":193,
    "gn:feature_class":"P",
    "gn:feature_code":"PPLL",
    "gn:name":"Mozambique",
    "gn:population":0,
    "gn:timezone":"America/Bogota",
    "iso:country":"CO",
    "name:spa_x_preferred":[
        "Mozambique"
    ],
    "wof:name":"Mozambique",
    "wof:placetype":"locality"
},
  "geometry": {"coordinates":[-73.05070000000001,3.96515],"type":"Point"}
}