{
  "type": "Feature",
  "properties": {
    "gn:admin1_code":"2.0",
    "gn:admin2_code":"5001.0",
    "gn:asciiname":"La Mayoria",
    "gn:country_code":"CO",
    "gn:dem":2410,
    "gn:feature_class":"P",
    "gn:feature_code":"PPL",
    "gn:name":"La Mayor\u00eda",
    "gn:population":0,
    "gn:timezone":"America/Bogota",
    "iso:country":"CO",
    "name:spa_x_preferred":[
        "La Mayor\u00eda"
    ],
    "wof:name":"La Mayoria",
    "wof:placetype":"locality"
},
  "geometry": {"coordinates":[-75.67629000000002,6.25752],"type":"Point"}
}