{
  "type": "Feature",
  "properties": {
    "gn:admin1_code":"36",
    "gn:admin2_code":"15469.0",
    "gn:asciiname":"La Laguna",
    "gn:country_code":"CO",
    "gn:dem":1636,
    "gn:feature_class":"P",
    "gn:feature_code":"PPL",
    "gn:name":"La Laguna",
    "gn:population":0,
    "gn:timezone":"America/Bogota",
    "iso:country":"CO",
    "wof:name":"La Laguna",
    "wof:placetype":"locality"
},
  "geometry": {"coordinates":[-73.56401,5.94879],"type":"Point"}
}