{
  "type": "Feature",
  "properties": {
    "gn:admin1_code":"29.0",
    "gn:asciiname":"Hacienda Brasil",
    "gn:country_code":"CO",
    "gn:dem":960,
    "gn:feature_class":"P",
    "gn:feature_code":"PPL",
    "gn:name":"Hacienda Brasil",
    "gn:population":0,
    "gn:timezone":"America/Bogota",
    "iso:country":"CO",
    "name:spa_x_preferred":[
        "Hacienda Brasil"
    ],
    "wof:name":"Hacienda Brasil",
    "wof:placetype":"locality"
},
  "geometry": {"coordinates":[-76.44292,3.30989],"type":"Point"}
}