{
  "type": "Feature",
  "properties": {
    "iso:country":"CO",
    "name:ast_x_preferred":[
        "Santa Mar\u00eda"
    ],
    "name:ceb_x_preferred":[
        "Santa Mar\u00eda"
    ],
    "name:eng_x_preferred":[
        "Santa Mar\u00eda"
    ],
    "name:fra_x_preferred":[
        "Santa Mar\u00eda"
    ],
    "name:ita_x_preferred":[
        "Santa Mar\u00eda"
    ],
    "name:kat_x_preferred":[
        "\u10e1\u10d0\u10dc\u10e2\u10d0-\u10db\u10d0\u10e0\u10d8\u10d0"
    ],
    "name:msa_x_preferred":[
        "Santa Mar\u00eda"
    ],
    "name:nan_x_preferred":[
        "Santa Mar\u00eda"
    ],
    "name:nld_x_preferred":[
        "Santa Mar\u00eda"
    ],
    "name:por_x_preferred":[
        "Santa Mar\u00eda"
    ],
    "name:spa_x_preferred":[
        "Santa Mar\u00eda"
    ],
    "name:swe_x_preferred":[
        "Santa Mar\u00eda"
    ],
    "name:tgl_x_preferred":[
        "Santa Mar\u00eda"
    ],
    "name:vie_x_preferred":[
        "Santa Mar\u00eda"
    ],
    "name:war_x_preferred":[
        "Santa Mar\u00eda"
    ],
    "name:zho_x_preferred":[
        "\u8056\u746a\u5229\u4e9e"
    ],
    "qs:gn_country":"CO",
    "qs:gn_fcode":"PPL",
    "qs:gn_pop":2761,
    "qs:name":"Santa Mar\u00eda",
    "qs:name_adm0":"Colombia",
    "qs:name_adm1":"Huila",
    "qs:photos":0,
    "qs:photos_1k":0,
    "qs:photos_9k":0,
    "qs:photos_9r":0,
    "qs:photos_all":0,
    "qs:photos_sr":0,
    "qs:placetype":"Town",
    "qs:pop_sr":"4",
    "qs:woe_adm0":23424787,
    "wd:wordcount":29,
    "wof:name":"Santa Mar\u00eda",
    "wof:placetype":"locality",
    "wof:population":2761
},
  "geometry": {"coordinates":[-75.65000000000001,2.95],"type":"Point"}
}