{
  "type": "Feature",
  "properties": {
    "gn:admin1_code":"9",
    "gn:admin2_code":"19364.0",
    "gn:asciiname":"Loma Redonda",
    "gn:country_code":"CO",
    "gn:dem":1860,
    "gn:feature_class":"P",
    "gn:feature_code":"PPL",
    "gn:name":"Loma Redonda",
    "gn:population":0,
    "gn:timezone":"America/Bogota",
    "iso:country":"CO",
    "name:spa_x_preferred":[
        "Loma Redonda"
    ],
    "wof:name":"Loma Redonda",
    "wof:placetype":"locality"
},
  "geometry": {"coordinates":[-76.32903,2.94444],"type":"Point"}
}