{
  "type": "Feature",
  "properties": {
    "gn:admin1_code":"26.0",
    "gn:admin2_code":"68655.0",
    "gn:asciiname":"Pescado",
    "gn:country_code":"CO",
    "gn:dem":63,
    "gn:feature_class":"P",
    "gn:feature_code":"PPL",
    "gn:name":"Pescado",
    "gn:population":0,
    "gn:timezone":"America/Bogota",
    "iso:country":"CO",
    "wof:name":"Pescado",
    "wof:placetype":"locality"
},
  "geometry": {"coordinates":[-73.66944000000002,7.49417],"type":"Point"}
}