{
  "type": "Feature",
  "properties": {
    "gn:admin1_code":"2.0",
    "gn:admin2_code":"5088.0",
    "gn:asciiname":"El Espejo",
    "gn:country_code":"CO",
    "gn:dem":1979,
    "gn:feature_class":"P",
    "gn:feature_code":"PPL",
    "gn:name":"El Espejo",
    "gn:population":0,
    "gn:timezone":"America/Bogota",
    "iso:country":"CO",
    "name:spa_x_preferred":[
        "El Espejo"
    ],
    "wof:name":"El Espejo",
    "wof:placetype":"locality"
},
  "geometry": {"coordinates":[-75.58864,6.33929],"type":"Point"}
}