{
  "type": "Feature",
  "properties": {
    "gn:admin1_code":"12.0",
    "gn:admin2_code":"23855.0",
    "gn:asciiname":"Soplaviento",
    "gn:country_code":"CO",
    "gn:dem":113,
    "gn:feature_class":"P",
    "gn:feature_code":"PPL",
    "gn:name":"Soplaviento",
    "gn:population":0,
    "gn:timezone":"America/Bogota",
    "iso:country":"CO",
    "name:ceb_x_preferred":[
        "Soplaviento"
    ],
    "name:fra_x_preferred":[
        "Soplaviento"
    ],
    "name:ita_x_preferred":[
        "Soplaviento"
    ],
    "name:kat_x_preferred":[
        "\u10e1\u10dd\u10de\u10da\u10d0\u10d5\u10d8\u10d4\u10dc\u10e2\u10dd"
    ],
    "name:msa_x_preferred":[
        "Soplaviento"
    ],
    "name:nld_x_preferred":[
        "Soplaviento"
    ],
    "name:por_x_preferred":[
        "Soplaviento"
    ],
    "name:rus_x_preferred":[
        "\u0421\u043e\u043f\u043b\u0430\u0432\u044c\u0435\u043d\u0442\u043e"
    ],
    "name:spa_x_preferred":[
        "Soplaviento"
    ],
    "name:swe_x_preferred":[
        "Soplaviento"
    ],
    "name:tgl_x_preferred":[
        "Soplaviento"
    ],
    "name:vie_x_preferred":[
        "Soplaviento"
    ],
    "name:war_x_preferred":[
        "Soplaviento"
    ],
    "name:zho_x_preferred":[
        "\u7d22\u666e\u62c9\u7dad\u6069\u6258"
    ],
    "wof:name":"Soplaviento",
    "wof:placetype":"locality"
},
  "geometry": {"coordinates":[-76.18333,8.28333],"type":"Point"}
}