{
  "type": "Feature",
  "properties": {
    "gn:admin1_code":"2.0",
    "gn:admin2_code":"5604.0",
    "gn:asciiname":"Platanares",
    "gn:country_code":"CO",
    "gn:dem":436,
    "gn:feature_class":"P",
    "gn:feature_code":"PPL",
    "gn:name":"Platanares",
    "gn:population":0,
    "gn:timezone":"America/Bogota",
    "iso:country":"CO",
    "wof:name":"Platanares",
    "wof:placetype":"locality"
},
  "geometry": {"coordinates":[-74.74406,7.08988],"type":"Point"}
}