{
  "type": "Feature",
  "properties": {
    "gn:admin1_code":"12",
    "gn:admin2_code":"23675.0",
    "gn:asciiname":"Chingui",
    "gn:country_code":"CO",
    "gn:dem":7,
    "gn:feature_class":"P",
    "gn:feature_code":"PPL",
    "gn:name":"Chingui",
    "gn:population":0,
    "gn:timezone":"America/Bogota",
    "iso:country":"CO",
    "name:und_x_variant":[
        "Chiqui",
        "Chingui"
    ],
    "wof:name":"Chingui",
    "wof:placetype":"locality"
},
  "geometry": {"coordinates":[-75.97958,9.33314],"type":"Point"}
}