{
  "type": "Feature",
  "properties": {
    "gn:admin1_code":"2.0",
    "gn:admin2_code":"5347.0",
    "gn:asciiname":"Morritos",
    "gn:country_code":"CO",
    "gn:dem":2064,
    "gn:feature_class":"P",
    "gn:feature_code":"PPL",
    "gn:name":"Morritos",
    "gn:population":0,
    "gn:timezone":"America/Bogota",
    "iso:country":"CO",
    "name:spa_x_preferred":[
        "Morritos"
    ],
    "wof:name":"Morritos",
    "wof:placetype":"locality"
},
  "geometry": {"coordinates":[-75.71481999999997,6.20628],"type":"Point"}
}