{
  "type": "Feature",
  "properties": {
    "gn:admin1_code":"16",
    "gn:admin2_code":"41676.0",
    "gn:asciiname":"El Cisne",
    "gn:country_code":"CO",
    "gn:dem":1536,
    "gn:feature_class":"P",
    "gn:feature_code":"PPL",
    "gn:name":"El Cisne",
    "gn:population":0,
    "gn:timezone":"America/Bogota",
    "iso:country":"CO",
    "name:ceb_x_preferred":[
        "El Cisne"
    ],
    "name:que_x_preferred":[
        "El Cisne"
    ],
    "name:swe_x_preferred":[
        "El Cisne"
    ],
    "wof:name":"El Cisne",
    "wof:placetype":"locality"
},
  "geometry": {"coordinates":[-75.5925,2.92583],"type":"Point"}
}