{
  "type": "Feature",
  "properties": {
    "gn:admin1_code":"2.0",
    "gn:admin2_code":"5034.0",
    "gn:asciiname":"Villa Cesar",
    "gn:country_code":"CO",
    "gn:dem":2018,
    "gn:feature_class":"P",
    "gn:feature_code":"PPL",
    "gn:name":"Villa C\u00e9sar",
    "gn:population":0,
    "gn:timezone":"America/Bogota",
    "iso:country":"CO",
    "wof:name":"Villa Cesar",
    "wof:placetype":"locality"
},
  "geometry": {"coordinates":[-75.98333000000002,5.68333],"type":"Point"}
}