{
  "type": "Feature",
  "properties": {
    "gn:admin1_code":"33",
    "gn:admin2_code":"25899.0",
    "gn:asciiname":"El Abra",
    "gn:country_code":"CO",
    "gn:dem":2595,
    "gn:feature_class":"P",
    "gn:feature_code":"PPL",
    "gn:name":"El Abra",
    "gn:population":0,
    "gn:timezone":"America/Bogota",
    "iso:country":"CO",
    "name:deu_x_preferred":[
        "El Abra"
    ],
    "name:fas_x_preferred":[
        "\u0627\u0644 \u0622\u0628\u0631\u0627"
    ],
    "name:fra_x_preferred":[
        "El Abra"
    ],
    "name:ita_x_preferred":[
        "El Abra"
    ],
    "name:rus_x_preferred":[
        "\u042d\u043b\u044c-\u0410\u0431\u0440\u0430"
    ],
    "name:spa_x_preferred":[
        "El Abra"
    ],
    "wof:name":"El Abra",
    "wof:placetype":"locality"
},
  "geometry": {"coordinates":[-73.95,5.01667],"type":"Point"}
}