{
  "type": "Feature",
  "properties": {
    "gn:admin1_code":"2.0",
    "gn:admin2_code":"5686.0",
    "gn:asciiname":"El Eden",
    "gn:country_code":"CO",
    "gn:dem":2568,
    "gn:feature_class":"P",
    "gn:feature_code":"PPL",
    "gn:name":"El Ed\u00e9n",
    "gn:population":0,
    "gn:timezone":"America/Bogota",
    "iso:country":"CO",
    "wof:name":"El Eden",
    "wof:placetype":"locality"
},
  "geometry": {"coordinates":[-75.59305999999999,6.71972],"type":"Point"}
}