{
  "type": "Feature",
  "properties": {
    "gn:admin1_code":"37",
    "gn:admin2_code":"17013.0",
    "gn:asciiname":"Alegrias",
    "gn:country_code":"CO",
    "gn:dem":2363,
    "gn:feature_class":"P",
    "gn:feature_code":"PPL",
    "gn:name":"Alegr\u00edas",
    "gn:population":0,
    "gn:timezone":"America/Bogota",
    "iso:country":"CO",
    "wof:name":"Alegrias",
    "wof:placetype":"locality"
},
  "geometry": {"coordinates":[-75.38333,5.56667],"type":"Point"}
}