{
  "type": "Feature",
  "properties": {
    "gn:admin1_code":"3.0",
    "gn:admin2_code":"81001.0",
    "gn:asciiname":"Los Medanos",
    "gn:country_code":"CO",
    "gn:dem":126,
    "gn:feature_class":"P",
    "gn:feature_code":"PPL",
    "gn:name":"Los Medanos",
    "gn:population":0,
    "gn:timezone":"America/Bogota",
    "iso:country":"CO",
    "name:ceb_x_preferred":[
        "Los Medanos"
    ],
    "name:srp_x_preferred":[
        "\u041b\u043e\u0441 \u041c\u0435\u0434\u0430\u043d\u043e\u0441"
    ],
    "name:swe_x_preferred":[
        "Los Medanos"
    ],
    "name:und_x_variant":[
        "M\u00e9danos",
        "Los Medanos"
    ],
    "wof:name":"Los Medanos",
    "wof:placetype":"locality"
},
  "geometry": {"coordinates":[-70.49349000000002,6.61404],"type":"Point"}
}