{
  "type": "Feature",
  "properties": {
    "iso:country":"CO",
    "name:ceb_x_preferred":[
        "Galeras"
    ],
    "name:chi_x_preferred":[
        "\u52a0\u840a\u62c9\u65af"
    ],
    "name:dut_x_preferred":[
        "Galeras"
    ],
    "name:eng_x_preferred":[
        "Galeras"
    ],
    "name:est_x_preferred":[
        "Galeras"
    ],
    "name:fra_x_preferred":[
        "Galeras"
    ],
    "name:fre_x_preferred":[
        "Galeras"
    ],
    "name:geo_x_preferred":[
        "\u10d2\u10d0\u10da\u10d4\u10e0\u10d0\u10e1\u10d8"
    ],
    "name:ita_x_preferred":[
        "Galeras"
    ],
    "name:kat_x_preferred":[
        "\u10d2\u10d0\u10da\u10d4\u10e0\u10d0\u10e1\u10d8"
    ],
    "name:may_x_preferred":[
        "Galeras"
    ],
    "name:msa_x_preferred":[
        "Galeras"
    ],
    "name:nan_x_preferred":[
        "Galeras"
    ],
    "name:nld_x_preferred":[
        "Galeras"
    ],
    "name:spa_x_preferred":[
        "Galeras"
    ],
    "name:swe_x_preferred":[
        "Galeras"
    ],
    "name:unk_x_variant":[
        "Corregimiento Nueva Granada"
    ],
    "name:vie_x_preferred":[
        "Galeras"
    ],
    "name:war_x_preferred":[
        "Galeras"
    ],
    "name:zho_min_nan_x_preferred":[
        "Galeras"
    ],
    "name:zho_x_preferred":[
        "\u52a0\u840a\u62c9\u65af"
    ],
    "qs:gn_country":"CO",
    "qs:gn_fcode":"PPL",
    "qs:gn_pop":9459,
    "qs:name":"Galeras",
    "qs:name_adm0":"Colombia",
    "qs:name_adm1":"Sucre",
    "qs:photos":0,
    "qs:photos_1k":0,
    "qs:photos_9k":0,
    "qs:photos_9r":0,
    "qs:photos_all":0,
    "qs:photos_sr":0,
    "qs:placetype":"Town",
    "qs:pop_sr":"5",
    "qs:woe_adm0":23424787,
    "wd:wordcount":159,
    "wof:name":"Galeras",
    "wof:placetype":"locality",
    "wof:population":9459
},
  "geometry": {"coordinates":[-75.04810999999999,9.16095],"type":"Point"}
}