{
  "type": "Feature",
  "properties": {
    "gn:admin1_code":"2.0",
    "gn:admin2_code":"5055.0",
    "gn:asciiname":"Zancudo",
    "gn:country_code":"CO",
    "gn:dem":1552,
    "gn:feature_class":"P",
    "gn:feature_code":"PPL",
    "gn:name":"Zancudo",
    "gn:population":0,
    "gn:timezone":"America/Bogota",
    "iso:country":"CO",
    "wof:name":"Zancudo",
    "wof:placetype":"locality"
},
  "geometry": {"coordinates":[-75.15691,5.70523],"type":"Point"}
}