{
  "type": "Feature",
  "properties": {
    "gn:admin1_code":"21",
    "gn:admin2_code":"54250.0",
    "gn:asciiname":"Nueva Granada",
    "gn:country_code":"CO",
    "gn:dem":611,
    "gn:feature_class":"P",
    "gn:feature_code":"PPL",
    "gn:name":"Nueva Granada",
    "gn:population":0,
    "gn:timezone":"America/Bogota",
    "iso:country":"CO",
    "wof:name":"Nueva Granada",
    "wof:placetype":"locality"
},
  "geometry": {"coordinates":[-73.12893000000003,8.58498],"type":"Point"}
}