{
  "type": "Feature",
  "properties": {
    "gn:admin1_code":"38.0",
    "gn:admin2_code":"47318.0",
    "gn:asciiname":"Ricaurte",
    "gn:country_code":"CO",
    "gn:dem":23,
    "gn:feature_class":"P",
    "gn:feature_code":"PPL",
    "gn:name":"Ricaurte",
    "gn:population":0,
    "gn:timezone":"America/Bogota",
    "iso:country":"CO",
    "name:bar_x_preferred":[
        "Ricaurte"
    ],
    "name:ceb_x_preferred":[
        "Ricaurte"
    ],
    "name:deu_x_preferred":[
        "Ricaurte"
    ],
    "name:fra_x_preferred":[
        "Ricaurte"
    ],
    "name:ita_x_preferred":[
        "Ricaurte"
    ],
    "name:nld_x_preferred":[
        "Ricaurte"
    ],
    "name:por_x_preferred":[
        "Ricaurte"
    ],
    "name:sco_x_preferred":[
        "Ricaurte"
    ],
    "name:spa_x_preferred":[
        "Ricaurte"
    ],
    "name:swe_x_preferred":[
        "Ricaurte"
    ],
    "name:und_x_variant":[
        "Corregimiento Ricaurte",
        "Ricaurte"
    ],
    "wof:name":"Ricaurte",
    "wof:placetype":"locality"
},
  "geometry": {"coordinates":[-74.23179,9.24047],"type":"Point"}
}