{
  "type": "Feature",
  "properties": {
    "gn:admin1_code":"2.0",
    "gn:admin2_code":"5837.0",
    "gn:asciiname":"Cope",
    "gn:country_code":"CO",
    "gn:dem":13,
    "gn:feature_class":"P",
    "gn:feature_code":"PPL",
    "gn:name":"Cope",
    "gn:population":0,
    "gn:timezone":"America/Bogota",
    "iso:country":"CO",
    "name:ast_x_preferred":[
        "Capa pluvial"
    ],
    "name:bel_x_preferred":[
        "\u041a\u0430\u043f\u0430"
    ],
    "name:cat_x_preferred":[
        "Capa pluvial"
    ],
    "name:ces_x_preferred":[
        "Pluvi\u00e1l"
    ],
    "name:deu_x_preferred":[
        "Pluviale"
    ],
    "name:epo_x_preferred":[
        "Pluvialo"
    ],
    "name:fin_x_preferred":[
        "Kuorikaapu"
    ],
    "name:fra_x_preferred":[
        "Chape"
    ],
    "name:hrv_x_preferred":[
        "Pluvijal"
    ],
    "name:ido_x_preferred":[
        "Chapo"
    ],
    "name:ita_x_preferred":[
        "Piviale"
    ],
    "name:lat_x_preferred":[
        "Pluviale"
    ],
    "name:nld_x_preferred":[
        "Koorkap"
    ],
    "name:nor_x_preferred":[
        "Kork\u00e5pe"
    ],
    "name:pol_x_preferred":[
        "Kapa"
    ],
    "name:por_x_preferred":[
        "Pluvial"
    ],
    "name:rus_x_preferred":[
        "\u041a\u0430\u043f\u043f\u0430 \u041c\u0430\u0433\u043d\u0430"
    ],
    "name:slk_x_preferred":[
        "Pluvi\u00e1l"
    ],
    "name:spa_x_preferred":[
        "Cope"
    ],
    "name:spa_x_variant":[
        "Capa pluvial"
    ],
    "name:swe_x_preferred":[
        "Kork\u00e5pa"
    ],
    "name:ukr_x_preferred":[
        "\u041a\u0430\u043f\u043f\u0430 \u043c\u0430\u0433\u043d\u0430"
    ],
    "wof:name":"Cope",
    "wof:placetype":"locality"
},
  "geometry": {"coordinates":[-76.72775,8.16554],"type":"Point"}
}