{
  "type": "Feature",
  "properties": {
    "gn:admin1_code":"19.0",
    "gn:admin2_code":"50568.0",
    "gn:asciiname":"San Pedro de Arimena",
    "gn:country_code":"CO",
    "gn:dem":159,
    "gn:feature_class":"P",
    "gn:feature_code":"PPL",
    "gn:name":"San Pedro de Arimena",
    "gn:population":0,
    "gn:timezone":"America/Bogota",
    "iso:country":"CO",
    "wof:name":"San Pedro de Arimena",
    "wof:placetype":"locality"
},
  "geometry": {"coordinates":[-71.6223,4.6089],"type":"Point"}
}