{
  "type": "Feature",
  "properties": {
    "gn:admin1_code":"27",
    "gn:admin2_code":"70742.0",
    "gn:asciiname":"La Vivienda",
    "gn:country_code":"CO",
    "gn:dem":82,
    "gn:feature_class":"P",
    "gn:feature_code":"PPL",
    "gn:name":"La Vivienda",
    "gn:population":0,
    "gn:timezone":"America/Bogota",
    "iso:country":"CO",
    "name:und_x_variant":[
        "Caser\u00edo La Vivienda",
        "La Vivienda"
    ],
    "wof:name":"La Vivienda",
    "wof:placetype":"locality"
},
  "geometry": {"coordinates":[-74.9988,9.23368],"type":"Point"}
}