{
  "type": "Feature",
  "properties": {
    "gn:admin1_code":"36",
    "gn:admin2_code":"15507.0",
    "gn:asciiname":"Campobello",
    "gn:country_code":"CO",
    "gn:dem":955,
    "gn:feature_class":"P",
    "gn:feature_code":"PPL",
    "gn:name":"Campobello",
    "gn:population":0,
    "gn:timezone":"America/Bogota",
    "iso:country":"CO",
    "wof:name":"Campobello",
    "wof:placetype":"locality"
},
  "geometry": {"coordinates":[-74.18639,5.76889],"type":"Point"}
}