{
  "type": "Feature",
  "properties": {
    "iso:country":"CO",
    "name:ceb_x_preferred":[
        "Charta"
    ],
    "name:chi_x_preferred":[
        "\u67e5\u723e\u5854"
    ],
    "name:dut_x_preferred":[
        "Charta"
    ],
    "name:eng_x_preferred":[
        "Charta"
    ],
    "name:fra_x_preferred":[
        "Charta"
    ],
    "name:fre_x_preferred":[
        "Charta"
    ],
    "name:geo_x_preferred":[
        "\u10e9\u10d0\u10e0\u10e2\u10d0"
    ],
    "name:ita_x_preferred":[
        "Charta"
    ],
    "name:kat_x_preferred":[
        "\u10e9\u10d0\u10e0\u10e2\u10d0"
    ],
    "name:may_x_preferred":[
        "Charta"
    ],
    "name:msa_x_preferred":[
        "Charta"
    ],
    "name:nan_x_preferred":[
        "Charta"
    ],
    "name:nld_x_preferred":[
        "Charta"
    ],
    "name:spa_x_preferred":[
        "Charta"
    ],
    "name:swe_x_preferred":[
        "Charta"
    ],
    "name:tgl_x_preferred":[
        "Charta"
    ],
    "name:vie_x_preferred":[
        "Charta"
    ],
    "name:war_x_preferred":[
        "Charta"
    ],
    "name:zho_min_nan_x_preferred":[
        "Charta"
    ],
    "name:zho_x_preferred":[
        "\u67e5\u723e\u5854"
    ],
    "qs:gn_country":"CO",
    "qs:gn_fcode":"PPL",
    "qs:gn_pop":650,
    "qs:name":"Charta",
    "qs:name_adm0":"Colombia",
    "qs:name_adm1":"Santander",
    "qs:photos":0,
    "qs:photos_1k":0,
    "qs:photos_9k":1,
    "qs:photos_9r":1,
    "qs:photos_all":5,
    "qs:photos_sr":0,
    "qs:placetype":"Town",
    "qs:pop_sr":"2",
    "qs:woe_adm0":23424787,
    "wd:wordcount":30,
    "wof:name":"Charta",
    "wof:placetype":"locality",
    "wof:population":650
},
  "geometry": {"coordinates":[-72.96782,7.28025],"type":"Point"}
}