{
  "type": "Feature",
  "properties": {
    "gn:admin1_code":"38.0",
    "gn:admin2_code":"47555.0",
    "gn:asciiname":"Sincelejo",
    "gn:country_code":"CO",
    "gn:dem":104,
    "gn:feature_class":"P",
    "gn:feature_code":"PPL",
    "gn:name":"Sincelejo",
    "gn:population":0,
    "gn:timezone":"America/Bogota",
    "iso:country":"CO",
    "wof:name":"Sincelejo",
    "wof:placetype":"locality"
},
  "geometry": {"coordinates":[-74.48566,9.71869],"type":"Point"}
}