{
  "type": "Feature",
  "properties": {
    "gn:admin1_code":"20",
    "gn:admin2_code":"52320.0",
    "gn:asciiname":"Ales",
    "gn:country_code":"CO",
    "gn:dem":2080,
    "gn:feature_class":"P",
    "gn:feature_code":"PPL",
    "gn:name":"Ales",
    "gn:population":0,
    "gn:timezone":"America/Bogota",
    "iso:country":"CO",
    "name:cat_x_preferred":[
        "Ales"
    ],
    "name:ceb_x_preferred":[
        "Ales"
    ],
    "name:deu_x_preferred":[
        "Ales"
    ],
    "name:epo_x_preferred":[
        "Ales"
    ],
    "name:fra_x_preferred":[
        "Al\u00e8s"
    ],
    "name:ita_x_preferred":[
        "Ales"
    ],
    "name:kor_x_preferred":[
        "\uc54c\ub808\uc2a4"
    ],
    "name:nld_x_preferred":[
        "Ales"
    ],
    "name:pms_x_preferred":[
        "Ales"
    ],
    "name:rus_x_preferred":[
        "\u0410\u043b\u0435\u0441"
    ],
    "name:slv_x_preferred":[
        "Ales"
    ],
    "name:spa_x_preferred":[
        "Ales"
    ],
    "name:swe_x_preferred":[
        "Ales"
    ],
    "name:ukr_x_preferred":[
        "\u0410\u043b\u0435\u0441"
    ],
    "wof:name":"Ales",
    "wof:placetype":"locality"
},
  "geometry": {"coordinates":[-77.49311,1.18686],"type":"Point"}
}