{
  "type": "Feature",
  "properties": {
    "gn:admin1_code":"20",
    "gn:admin2_code":"52320.0",
    "gn:asciiname":"Ales",
    "gn:country_code":"CO",
    "gn:dem":2080,
    "gn:feature_class":"P",
    "gn:feature_code":"PPL",
    "gn:name":"Ales",
    "gn:population":0,
    "gn:timezone":"America/Bogota",
    "iso:country":"CO",
    "wof:name":"Ales",
    "wof:placetype":"locality"
},
  "geometry": {"coordinates":[-77.49311,1.18686],"type":"Point"}
}