{
  "type": "Feature",
  "properties": {
    "gn:admin1_code":"26.0",
    "gn:admin2_code":"68162.0",
    "gn:asciiname":"Servita",
    "gn:country_code":"CO",
    "gn:dem":2568,
    "gn:feature_class":"P",
    "gn:feature_code":"PPL",
    "gn:name":"Servit\u00e1",
    "gn:population":0,
    "gn:timezone":"America/Bogota",
    "iso:country":"CO",
    "wof:name":"Servita",
    "wof:placetype":"locality"
},
  "geometry": {"coordinates":[-72.70269,6.82017],"type":"Point"}
}