{
  "type": "Feature",
  "properties": {
    "gn:admin1_code":"4",
    "gn:asciiname":"Cruz de Hierro",
    "gn:country_code":"CO",
    "gn:dem":180,
    "gn:feature_class":"P",
    "gn:feature_code":"PPL",
    "gn:name":"Cruz de Hierro",
    "gn:population":0,
    "gn:timezone":"America/Bogota",
    "iso:country":"CO",
    "wof:name":"Cruz de Hierro",
    "wof:placetype":"locality"
},
  "geometry": {"coordinates":[-75.26666999999998,10.53333],"type":"Point"}
}