{
  "type": "Feature",
  "properties": {
    "gn:admin1_code":"10.0",
    "gn:admin2_code":"20750.0",
    "gn:asciiname":"Hacienda Monte Rico",
    "gn:country_code":"CO",
    "gn:dem":99,
    "gn:feature_class":"P",
    "gn:feature_code":"PPL",
    "gn:name":"Hacienda Monte Rico",
    "gn:population":0,
    "gn:timezone":"America/Bogota",
    "iso:country":"CO",
    "wof:name":"Hacienda Monte Rico",
    "wof:placetype":"locality"
},
  "geometry": {"coordinates":[-73.26428,10.20564],"type":"Point"}
}