{
  "type": "Feature",
  "properties": {
    "gn:admin1_code":"29",
    "gn:admin2_code":"76109",
    "gn:asciiname":"Umanes - Mar",
    "gn:country_code":"CO",
    "gn:dem":21,
    "gn:feature_class":"P",
    "gn:feature_code":"PPL",
    "gn:name":"Umanes - Mar",
    "gn:population":0,
    "gn:timezone":"America/Bogota",
    "iso:country":"CO",
    "wof:name":"Umanes - Mar",
    "wof:placetype":"locality"
},
  "geometry": {"coordinates":[-77.16904,3.74436],"type":"Point"}
}