{
  "type": "Feature",
  "properties": {
    "gn:admin1_code":"16.0",
    "gn:admin2_code":"41791.0",
    "gn:asciiname":"Rica Brisa",
    "gn:country_code":"CO",
    "gn:dem":2304,
    "gn:feature_class":"P",
    "gn:feature_code":"PPL",
    "gn:name":"Rica Brisa",
    "gn:population":0,
    "gn:timezone":"America/Bogota",
    "iso:country":"CO",
    "wof:name":"Rica Brisa",
    "wof:placetype":"locality"
},
  "geometry": {"coordinates":[-75.91049,2.20285],"type":"Point"}
}