{
  "type": "Feature",
  "properties": {
    "gn:admin1_code":"16.0",
    "gn:admin2_code":"41548.0",
    "gn:asciiname":"El Uvital",
    "gn:country_code":"CO",
    "gn:dem":1822,
    "gn:feature_class":"P",
    "gn:feature_code":"PPL",
    "gn:name":"El Uvital",
    "gn:population":0,
    "gn:timezone":"America/Bogota",
    "iso:country":"CO",
    "wof:name":"El Uvital",
    "wof:placetype":"locality"
},
  "geometry": {"coordinates":[-75.86268000000003,2.31819],"type":"Point"}
}