{
  "type": "Feature",
  "properties": {
    "gn:admin1_code":"21",
    "gn:admin2_code":"54670.0",
    "gn:asciiname":"Puente Real",
    "gn:country_code":"CO",
    "gn:dem":402,
    "gn:feature_class":"P",
    "gn:feature_code":"PPL",
    "gn:name":"Puente Real",
    "gn:population":0,
    "gn:timezone":"America/Bogota",
    "iso:country":"CO",
    "wof:name":"Puente Real",
    "wof:placetype":"locality"
},
  "geometry": {"coordinates":[-73.16083,8.55389],"type":"Point"}
}