{
  "type": "Feature",
  "properties": {
    "gn:admin1_code":"2.0",
    "gn:admin2_code":"5318.0",
    "gn:asciiname":"Betania",
    "gn:country_code":"CO",
    "gn:dem":2436,
    "gn:feature_class":"P",
    "gn:feature_code":"PPL",
    "gn:name":"Betania",
    "gn:population":0,
    "gn:timezone":"America/Bogota",
    "iso:country":"CO",
    "wof:name":"Betania",
    "wof:placetype":"locality"
},
  "geometry": {"coordinates":[-75.47306999999998,6.20461],"type":"Point"}
}