{
  "type": "Feature",
  "properties": {
    "gn:admin1_code":"2",
    "gn:admin2_code":"5495.0",
    "gn:asciiname":"El Contento",
    "gn:country_code":"CO",
    "gn:dem":42,
    "gn:feature_class":"P",
    "gn:feature_code":"PPL",
    "gn:name":"El Contento",
    "gn:population":0,
    "gn:timezone":"America/Bogota",
    "iso:country":"CO",
    "wof:name":"El Contento",
    "wof:placetype":"locality"
},
  "geometry": {"coordinates":[-74.79026999999998,8.03093],"type":"Point"}
}