{
  "type": "Feature",
  "properties": {
    "gn:admin1_code":"22.0",
    "gn:admin2_code":"86568.0",
    "gn:asciiname":"Nuevo Pensar",
    "gn:country_code":"CO",
    "gn:dem":244,
    "gn:feature_class":"P",
    "gn:feature_code":"PPL",
    "gn:name":"Nuevo Pensar",
    "gn:population":0,
    "gn:timezone":"America/Bogota",
    "iso:country":"CO",
    "wof:name":"Nuevo Pensar",
    "wof:placetype":"locality"
},
  "geometry": {"coordinates":[-76.28360000000001,0.50671],"type":"Point"}
}