{
  "type": "Feature",
  "properties": {
    "gn:admin1_code":"28",
    "gn:admin2_code":"73001.0",
    "gn:asciiname":"La Virginia",
    "gn:country_code":"CO",
    "gn:dem":1316,
    "gn:feature_class":"P",
    "gn:feature_code":"PPL",
    "gn:name":"La Virginia",
    "gn:population":0,
    "gn:timezone":"America/Bogota",
    "iso:country":"CO",
    "wof:name":"La Virginia",
    "wof:placetype":"locality"
},
  "geometry": {"coordinates":[-75.21583000000003,4.36278],"type":"Point"}
}