{
  "type": "Feature",
  "properties": {
    "gn:admin1_code":"9.0",
    "gn:admin2_code":"19397.0",
    "gn:asciiname":"San Miguel",
    "gn:country_code":"CO",
    "gn:dem":1576,
    "gn:feature_class":"P",
    "gn:feature_code":"PPL",
    "gn:name":"San Miguel",
    "gn:population":0,
    "gn:timezone":"America/Bogota",
    "iso:country":"CO",
    "name:und_x_variant":[
        "L\u00f3pez",
        "San Miguel"
    ],
    "wof:name":"San Miguel",
    "wof:placetype":"locality"
},
  "geometry": {"coordinates":[-76.77525,2.1177],"type":"Point"}
}