{
  "type": "Feature",
  "properties": {
    "gn:admin1_code":"4.0",
    "gn:admin2_code":"8078.0",
    "gn:asciiname":"Riojaneiro",
    "gn:cc2":"CO",
    "gn:country_code":"CO",
    "gn:dem":101,
    "gn:feature_class":"P",
    "gn:feature_code":"PPL",
    "gn:name":"R\u00edojaneiro",
    "gn:population":0,
    "gn:timezone":"America/Bogota",
    "iso:country":"CO",
    "name:und_x_variant":[
        "Hacienda Riojaneiro",
        "R\u00edojaneiro"
    ],
    "wof:name":"Riojaneiro",
    "wof:placetype":"locality"
},
  "geometry": {"coordinates":[-74.91667,10.76667],"type":"Point"}
}