{
  "type": "Feature",
  "properties": {
    "gn:admin1_code":"10",
    "gn:admin2_code":"20310.0",
    "gn:asciiname":"Tequendama",
    "gn:country_code":"CO",
    "gn:dem":1661,
    "gn:feature_class":"P",
    "gn:feature_code":"PPL",
    "gn:name":"Tequendama",
    "gn:population":0,
    "gn:timezone":"America/Bogota",
    "iso:country":"CO",
    "wof:name":"Tequendama",
    "wof:placetype":"locality"
},
  "geometry": {"coordinates":[-73.39972,8.43361],"type":"Point"}
}