{
  "type": "Feature",
  "properties": {
    "gn:admin1_code":"2.0",
    "gn:admin2_code":"5138.0",
    "gn:asciiname":"Cotove",
    "gn:country_code":"CO",
    "gn:dem":1946,
    "gn:feature_class":"P",
    "gn:feature_code":"PPL",
    "gn:name":"Cotove",
    "gn:population":0,
    "gn:timezone":"America/Bogota",
    "iso:country":"CO",
    "wof:name":"Cotove",
    "wof:placetype":"locality"
},
  "geometry": {"coordinates":[-75.9875,6.88583],"type":"Point"}
}