{
  "type": "Feature",
  "properties": {
    "gn:admin1_code":"10",
    "gn:admin2_code":"20175.0",
    "gn:asciiname":"Villa Nueva",
    "gn:country_code":"CO",
    "gn:dem":47,
    "gn:feature_class":"P",
    "gn:feature_code":"PPL",
    "gn:name":"Villa Nueva",
    "gn:population":0,
    "gn:timezone":"America/Bogota",
    "iso:country":"CO",
    "name:ceb_x_preferred":[
        "Villa Nueva"
    ],
    "name:deu_x_preferred":[
        "Villa Nueva"
    ],
    "name:fra_x_preferred":[
        "Villa Nueva"
    ],
    "name:ita_x_preferred":[
        "Villa Nueva"
    ],
    "name:nld_x_preferred":[
        "Villa Nueva"
    ],
    "name:pol_x_preferred":[
        "Villa Nueva"
    ],
    "name:por_x_preferred":[
        "Villa Nueva"
    ],
    "name:sco_x_preferred":[
        "Villa Nueva"
    ],
    "name:spa_x_preferred":[
        "Villa Nueva"
    ],
    "name:swe_x_preferred":[
        "Villa Nueva"
    ],
    "wof:name":"Villa Nueva",
    "wof:placetype":"locality"
},
  "geometry": {"coordinates":[-73.85278000000002,9.45556],"type":"Point"}
}