{
  "type": "Feature",
  "properties": {
    "gn:gn_country":"CO",
    "gn:gn_fcode":"PPLA2",
    "gn:gn_pop":16225,
    "gn:population":16225,
    "iso:country":"CO",
    "name:eng_x_preferred":[
        "Ciudad Bol\u00edvar"
    ],
    "name:fas_x_preferred":[
        "\u0633\u06cc\u0648\u062f\u0627\u062f \u0628\u0648\u0644\u06cc\u0648\u0627\u0631"
    ],
    "name:fra_x_preferred":[
        "Bol\u00edvar"
    ],
    "name:ile_x_preferred":[
        "Ciudad Bol\u00edvar"
    ],
    "name:ita_x_preferred":[
        "Ciudad Bol\u00edvar"
    ],
    "name:kat_x_preferred":[
        "\u10e1\u10d8\u10e3\u10d3\u10d0\u10d3-\u10d1\u10dd\u10da\u10d8\u10d5\u10d0\u10e0\u10d8"
    ],
    "name:mkd_x_preferred":[
        "\u0421\u0438\u0443\u0434\u0430\u0434 \u0411\u043e\u043b\u0438\u0432\u0430\u0440"
    ],
    "name:msa_x_preferred":[
        "Bol\u00edvar"
    ],
    "name:nan_x_preferred":[
        "Ciudad Bol\u00edvar"
    ],
    "name:nld_x_preferred":[
        "Ciudad Bol\u00edvar"
    ],
    "name:por_x_preferred":[
        "Ciudad Bol\u00edvar"
    ],
    "name:ron_x_preferred":[
        "Ciudad Bol\u00edvar"
    ],
    "name:rus_x_preferred":[
        "\u0421\u044c\u044e\u0434\u0430\u0434-\u0411\u043e\u043b\u0438\u0432\u0430\u0440"
    ],
    "name:spa_x_preferred":[
        "Ciudad Bol\u00edvar"
    ],
    "name:swe_x_preferred":[
        "Ciudad Bol\u00edvar"
    ],
    "name:tgl_x_preferred":[
        "Ciudad Bol\u00edvar"
    ],
    "name:war_x_preferred":[
        "Ciudad Bol\u00edvar"
    ],
    "name:zho_x_preferred":[
        "\u73bb\u5229\u74e6\u723e\u57ce"
    ],
    "qs_pg:aaroncc":"CO",
    "qs_pg:gn_country":"CO",
    "qs_pg:gn_fcode":"PPLA2",
    "qs_pg:gn_pop":16225,
    "qs_pg:name":"Ciudad Bol\u00edvar",
    "qs_pg:photos_9r":0,
    "qs_pg:photos_sr":0,
    "qs_pg:pop_sr":6,
    "qs_pg:qs_pg_placetype":"locality",
    "wof:name":"Ciudad Bol\u00edvar",
    "wof:placetype":"locality",
    "wof:population":16225
},
  "geometry": {"coordinates":[-76.02528,5.85389],"type":"Point"}
}