{
  "type": "Feature",
  "properties": {
    "gn:admin1_code":"12",
    "gn:admin2_code":"23001.0",
    "gn:asciiname":"Guasimal",
    "gn:country_code":"CO",
    "gn:dem":38,
    "gn:feature_class":"P",
    "gn:feature_code":"PPL",
    "gn:name":"Guasimal",
    "gn:population":0,
    "gn:timezone":"America/Bogota",
    "iso:country":"CO",
    "name:ceb_x_preferred":[
        "Guasimal"
    ],
    "name:deu_x_preferred":[
        "Guasimal"
    ],
    "name:hat_x_preferred":[
        "Guasimal"
    ],
    "name:nld_x_preferred":[
        "Guasimal"
    ],
    "wof:name":"Guasimal",
    "wof:placetype":"locality"
},
  "geometry": {"coordinates":[-76.07512,8.36562],"type":"Point"}
}