{
  "type": "Feature",
  "properties": {
    "gn:admin1_code":"9.0",
    "gn:admin2_code":"19622.0",
    "gn:asciiname":"El Libano",
    "gn:country_code":"CO",
    "gn:dem":1744,
    "gn:feature_class":"P",
    "gn:feature_code":"PPL",
    "gn:name":"El L\u00edbano",
    "gn:population":0,
    "gn:timezone":"America/Bogota",
    "iso:country":"CO",
    "wof:name":"El Libano",
    "wof:placetype":"locality"
},
  "geometry": {"coordinates":[-76.71373,2.26282],"type":"Point"}
}