{
  "type": "Feature",
  "properties": {
    "gn:admin1_code":"17",
    "gn:admin2_code":"44078.0",
    "gn:asciiname":"Carbonalito",
    "gn:country_code":"CO",
    "gn:dem":205,
    "gn:feature_class":"P",
    "gn:feature_code":"PPL",
    "gn:name":"Carbonalito",
    "gn:population":0,
    "gn:timezone":"America/Bogota",
    "iso:country":"CO",
    "wof:name":"Carbonalito",
    "wof:placetype":"locality"
},
  "geometry": {"coordinates":[-72.72169,10.91001],"type":"Point"}
}