{
  "type": "Feature",
  "properties": {
    "gn:admin1_code":"35",
    "gn:admin2_code":"13248.0",
    "gn:asciiname":"Lata",
    "gn:country_code":"CO",
    "gn:dem":141,
    "gn:feature_class":"P",
    "gn:feature_code":"PPL",
    "gn:name":"Lata",
    "gn:population":0,
    "gn:timezone":"America/Bogota",
    "iso:country":"CO",
    "name:und_x_variant":[
        "Caser\u00edo Lata",
        "Lata"
    ],
    "wof:name":"Lata",
    "wof:placetype":"locality"
},
  "geometry": {"coordinates":[-75.02736,10.04777],"type":"Point"}
}