{
  "type": "Feature",
  "properties": {
    "gn:admin1_code":"12.0",
    "gn:admin2_code":"23001.0",
    "gn:asciiname":"Majagua",
    "gn:country_code":"CO",
    "gn:dem":18,
    "gn:feature_class":"P",
    "gn:feature_code":"PPLL",
    "gn:name":"Majagua",
    "gn:population":0,
    "gn:timezone":"America/Bogota",
    "iso:country":"CO",
    "name:ceb_x_preferred":[
        "Majagua"
    ],
    "name:fra_x_preferred":[
        "Majagua"
    ],
    "name:pol_x_preferred":[
        "Majagua"
    ],
    "name:spa_x_preferred":[
        "Majagua"
    ],
    "name:swe_x_preferred":[
        "Majagua"
    ],
    "wof:name":"Majagua",
    "wof:placetype":"locality"
},
  "geometry": {"coordinates":[-75.92583,8.71806],"type":"Point"}
}