{
  "type": "Feature",
  "properties": {
    "gn:admin1_code":"36.0",
    "gn:asciiname":"Los Bancos",
    "gn:country_code":"CO",
    "gn:dem":3428,
    "gn:feature_class":"P",
    "gn:feature_code":"PPL",
    "gn:name":"Los Bancos",
    "gn:population":0,
    "gn:timezone":"America/Bogota",
    "iso:country":"CO",
    "name:spa_x_preferred":[
        "Los Bancos"
    ],
    "wof:name":"Los Bancos",
    "wof:placetype":"locality"
},
  "geometry": {"coordinates":[-72.55110000000001,6.58986],"type":"Point"}
}