{
  "type": "Feature",
  "properties": {
    "iso:country":"CO",
    "name:ast_x_preferred":[
        "Piendam\u00f3"
    ],
    "name:avk_x_preferred":[
        "Piendam\u00f3"
    ],
    "name:ceb_x_preferred":[
        "Piendam\u00f3"
    ],
    "name:deu_x_preferred":[
        "Piendam\u00f3"
    ],
    "name:eng_x_preferred":[
        "Piendam\u00f3"
    ],
    "name:fas_x_preferred":[
        "\u067e\u06cc\u0646\u062f\u0627\u0645\u0648"
    ],
    "name:fra_x_preferred":[
        "Piendam\u00f3"
    ],
    "name:gle_x_preferred":[
        "Piendam\u00f3"
    ],
    "name:ita_x_preferred":[
        "Piendam\u00f3"
    ],
    "name:kat_x_preferred":[
        "\u10de\u10d8\u10d4\u10dc\u10d3\u10d0\u10db\u10dd"
    ],
    "name:msa_x_preferred":[
        "Piendam\u00f3"
    ],
    "name:nan_x_preferred":[
        "Piendam\u00f3"
    ],
    "name:nld_x_preferred":[
        "Piendam\u00f3"
    ],
    "name:pol_x_preferred":[
        "Piendam\u00f3"
    ],
    "name:por_x_preferred":[
        "Piendam\u00f3"
    ],
    "name:rus_x_preferred":[
        "\u041f\u044c\u0435\u043d\u0434\u0430\u043c\u043e"
    ],
    "name:spa_x_preferred":[
        "Piendam\u00f3"
    ],
    "name:swe_x_preferred":[
        "Piendam\u00f3"
    ],
    "name:tgl_x_preferred":[
        "Piendam\u00f3"
    ],
    "name:und_x_variant":[
        "Tun\u00eda"
    ],
    "name:vie_x_preferred":[
        "Piendam\u00f3"
    ],
    "name:war_x_preferred":[
        "Piendam\u00f3"
    ],
    "name:zho_x_preferred":[
        "\u76ae\u6069\u9054\u83ab"
    ],
    "qs:gn_country":"CO",
    "qs:gn_fcode":"PPL",
    "qs:gn_pop":0,
    "qs:name":"Piendam\u00f3",
    "qs:name_adm0":"Colombia",
    "qs:name_adm1":"Cauca",
    "qs:photos":97,
    "qs:photos_1k":20,
    "qs:photos_9k":1,
    "qs:photos_9r":3,
    "qs:photos_all":97,
    "qs:photos_sr":3,
    "qs:placetype":"Town",
    "qs:pop_sr":"0",
    "qs:woe_adm0":23424787,
    "wof:name":"Piendam\u00f3",
    "wof:placetype":"locality"
},
  "geometry": {"coordinates":[-76.98917,2.64306],"type":"Point"}
}