{
  "type": "Feature",
  "properties": {
    "gn:country":"CO",
    "gn:fcode":"PPL",
    "gn:population":4165,
    "iso:country":"CO",
    "name:und_x_variant":[
        "Pueblorrico"
    ],
    "qs:name":"Pueblo Rico",
    "qs:photos_9r":0,
    "qs:photos_sr":0,
    "qs:pop_sr":"4",
    "wof:name":"Pueblo Rico",
    "wof:placetype":"locality",
    "wof:population":4165
},
  "geometry": {"coordinates":[-76.03639,5.23833],"type":"Point"}
}