{
  "type": "Feature",
  "properties": {
    "gn:admin1_code":"26.0",
    "gn:admin2_code":"68167.0",
    "gn:asciiname":"Virolin",
    "gn:country_code":"CO",
    "gn:dem":1742,
    "gn:feature_class":"P",
    "gn:feature_code":"PPL",
    "gn:name":"Virol\u00edn",
    "gn:population":0,
    "gn:timezone":"America/Bogota",
    "iso:country":"CO",
    "wof:name":"Virolin",
    "wof:placetype":"locality"
},
  "geometry": {"coordinates":[-73.19821999999998,6.10728],"type":"Point"}
}