{
  "type": "Feature",
  "properties": {
    "gn:admin1_code":"20.0",
    "gn:admin2_code":"52786.0",
    "gn:asciiname":"Pichanguillo",
    "gn:country_code":"CO",
    "gn:dem":914,
    "gn:feature_class":"P",
    "gn:feature_code":"PPL",
    "gn:name":"Pichanguillo",
    "gn:population":0,
    "gn:timezone":"America/Bogota",
    "iso:country":"CO",
    "wof:name":"Pichanguillo",
    "wof:placetype":"locality"
},
  "geometry": {"coordinates":[-77.27798,1.62393],"type":"Point"}
}