{
  "type": "Feature",
  "properties": {
    "gn:admin1_code":"29",
    "gn:admin2_code":"76306.0",
    "gn:asciiname":"Barranco",
    "gn:country_code":"CO",
    "gn:dem":1106,
    "gn:feature_class":"P",
    "gn:feature_code":"PPL",
    "gn:name":"Barranco",
    "gn:population":0,
    "gn:timezone":"America/Bogota",
    "iso:country":"CO",
    "name:ceb_x_preferred":[
        "Barranco"
    ],
    "name:deu_x_preferred":[
        "Barranco"
    ],
    "name:glg_x_preferred":[
        "Barranco"
    ],
    "name:nds_x_preferred":[
        "Barranco"
    ],
    "name:por_x_preferred":[
        "Barranco"
    ],
    "name:spa_x_preferred":[
        "Barranco"
    ],
    "name:swe_x_preferred":[
        "Barranco"
    ],
    "wof:name":"Barranco",
    "wof:placetype":"locality"
},
  "geometry": {"coordinates":[-76.22903000000002,3.70173],"type":"Point"}
}