{
  "type": "Feature",
  "properties": {
    "gn:admin1_code":"16",
    "gn:admin2_code":"41799",
    "gn:asciiname":"La Mesa del Trapiche",
    "gn:country_code":"CO",
    "gn:dem":678,
    "gn:feature_class":"P",
    "gn:feature_code":"PPL",
    "gn:name":"La Mesa del Trapiche",
    "gn:population":0,
    "gn:timezone":"America/Bogota",
    "iso:country":"CO",
    "name:spa_x_preferred":[
        "La Mesa del Trapiche"
    ],
    "wof:name":"La Mesa del Trapiche",
    "wof:placetype":"locality"
},
  "geometry": {"coordinates":[-75.12749000000002,3.01645],"type":"Point"}
}