{
  "type": "Feature",
  "properties": {
    "gn:admin1_code":"2.0",
    "gn:admin2_code":"5837.0",
    "gn:asciiname":"Las Pavas",
    "gn:country_code":"CO",
    "gn:dem":267,
    "gn:feature_class":"P",
    "gn:feature_code":"PPL",
    "gn:name":"Las Pavas",
    "gn:population":0,
    "gn:timezone":"America/Bogota",
    "iso:country":"CO",
    "wof:name":"Las Pavas",
    "wof:placetype":"locality"
},
  "geometry": {"coordinates":[-76.48900999999999,8.11993],"type":"Point"}
}