{
  "type": "Feature",
  "properties": {
    "gn:admin1_code":"22.0",
    "gn:admin2_code":"86885.0",
    "gn:asciiname":"Urcusique",
    "gn:country_code":"CO",
    "gn:dem":409,
    "gn:feature_class":"P",
    "gn:feature_code":"PPL",
    "gn:name":"Urcusique",
    "gn:population":0,
    "gn:timezone":"America/Bogota",
    "iso:country":"CO",
    "wof:name":"Urcusique",
    "wof:placetype":"locality"
},
  "geometry": {"coordinates":[-76.61667,1.01667],"type":"Point"}
}