{
  "type": "Feature",
  "properties": {
    "gn:admin1_code":"17",
    "gn:admin2_code":"44874.0",
    "gn:asciiname":"El Eneal",
    "gn:country_code":"CO",
    "gn:dem":187,
    "gn:feature_class":"P",
    "gn:feature_code":"PPL",
    "gn:name":"El Eneal",
    "gn:population":0,
    "gn:timezone":"America/Bogota",
    "iso:country":"CO",
    "name:und_x_variant":[
        "Eneal",
        "El Enea",
        "El Eneal"
    ],
    "wof:name":"El Eneal",
    "wof:placetype":"locality"
},
  "geometry": {"coordinates":[-73.03055999999999,10.59981],"type":"Point"}
}