{
  "type": "Feature",
  "properties": {
    "gn:admin1_code":"9",
    "gn:admin2_code":"19355.0",
    "gn:asciiname":"Danubio",
    "gn:country_code":"CO",
    "gn:dem":1191,
    "gn:feature_class":"P",
    "gn:feature_code":"PPL",
    "gn:name":"Danubio",
    "gn:population":0,
    "gn:timezone":"America/Bogota",
    "iso:country":"CO",
    "name:spa_x_preferred":[
        "Danubio"
    ],
    "wof:name":"Danubio",
    "wof:placetype":"locality"
},
  "geometry": {"coordinates":[-75.96313000000001,2.5136],"type":"Point"}
}