{
  "type": "Feature",
  "properties": {
    "gn:admin1_code":"17.0",
    "gn:admin2_code":"44001.0",
    "gn:asciiname":"Tigrera",
    "gn:country_code":"CO",
    "gn:dem":24,
    "gn:feature_class":"P",
    "gn:feature_code":"PPL",
    "gn:name":"Tigrera",
    "gn:population":0,
    "gn:timezone":"America/Bogota",
    "iso:country":"CO",
    "name:und_x_variant":[
        "Caser\u00edo Tigrera",
        "Tigrera"
    ],
    "wof:name":"Tigrera",
    "wof:placetype":"locality"
},
  "geometry": {"coordinates":[-73.09813,11.28643],"type":"Point"}
}