{
  "type": "Feature",
  "properties": {
    "gn:admin1_code":"16",
    "gn:admin2_code":"41020",
    "gn:asciiname":"El Suspiro",
    "gn:country_code":"CO",
    "gn:dem":2044,
    "gn:feature_class":"P",
    "gn:feature_code":"PPL",
    "gn:name":"El Suspiro",
    "gn:population":0,
    "gn:timezone":"America/Bogota",
    "iso:country":"CO",
    "wof:name":"El Suspiro",
    "wof:placetype":"locality"
},
  "geometry": {"coordinates":[-75.17348,2.62014],"type":"Point"}
}