{
  "type": "Feature",
  "properties": {
    "gn:admin1_code":"10.0",
    "gn:admin2_code":"20001.0",
    "gn:asciiname":"Valencia de Jesus",
    "gn:country_code":"CO",
    "gn:dem":125,
    "gn:feature_class":"P",
    "gn:feature_code":"PPL",
    "gn:name":"Valencia de Jes\u00fas",
    "gn:population":0,
    "gn:timezone":"America/Bogota",
    "iso:country":"CO",
    "name:und_x_variant":[
        "Valencia",
        "Valencia de Jes\u00fas"
    ],
    "wof:name":"Valencia de Jesus",
    "wof:placetype":"locality"
},
  "geometry": {"coordinates":[-73.39588000000001,10.30365],"type":"Point"}
}