{
  "type": "Feature",
  "properties": {
    "gn:admin1_code":"26.0",
    "gn:admin2_code":"68081.0",
    "gn:asciiname":"La Expansion",
    "gn:country_code":"CO",
    "gn:dem":102,
    "gn:feature_class":"P",
    "gn:feature_code":"PPLL",
    "gn:name":"La Expansi\u00f3n",
    "gn:population":0,
    "gn:timezone":"America/Bogota",
    "iso:country":"CO",
    "wof:name":"La Expansion",
    "wof:placetype":"locality"
},
  "geometry": {"coordinates":[-73.68411999999999,6.91974],"type":"Point"}
}