{
  "type": "Feature",
  "properties": {
    "gn:admin1_code":"4",
    "gn:admin2_code":"8560.0",
    "gn:asciiname":"Cumaco",
    "gn:country_code":"CO",
    "gn:dem":58,
    "gn:feature_class":"P",
    "gn:feature_code":"PPL",
    "gn:name":"Cumaco",
    "gn:population":0,
    "gn:timezone":"America/Bogota",
    "iso:country":"CO",
    "wof:name":"Cumaco",
    "wof:placetype":"locality"
},
  "geometry": {"coordinates":[-74.84999999999999,10.65],"type":"Point"}
}