{
  "type": "Feature",
  "properties": {
    "gn:admin1_code":"16.0",
    "gn:admin2_code":"41298.0",
    "gn:asciiname":"La Bolsa",
    "gn:country_code":"CO",
    "gn:dem":1185,
    "gn:feature_class":"P",
    "gn:feature_code":"PPL",
    "gn:name":"La Bolsa",
    "gn:population":0,
    "gn:timezone":"America/Bogota",
    "iso:country":"CO",
    "wof:name":"La Bolsa",
    "wof:placetype":"locality"
},
  "geometry": {"coordinates":[-75.62425999999998,2.1326],"type":"Point"}
}