{
  "type": "Feature",
  "properties": {
    "gn:admin1_code":"37",
    "gn:asciiname":"Manzanillo",
    "gn:cc2":"CO",
    "gn:country_code":"CO",
    "gn:dem":1735,
    "gn:feature_class":"P",
    "gn:feature_code":"PPL",
    "gn:name":"Manzanillo",
    "gn:population":0,
    "gn:timezone":"America/Bogota",
    "iso:country":"CO",
    "name:und_x_variant":[
        "Alto del Manzanillo",
        "Manzanillo"
    ],
    "wof:name":"Manzanillo",
    "wof:placetype":"locality"
},
  "geometry": {"coordinates":[-75.65139000000001,4.92639],"type":"Point"}
}