{
  "type": "Feature",
  "properties": {
    "gn:admin1_code":"21",
    "gn:admin2_code":"54720.0",
    "gn:asciiname":"Cuesta de Macho",
    "gn:country_code":"CO",
    "gn:dem":508,
    "gn:feature_class":"P",
    "gn:feature_code":"PPL",
    "gn:name":"Cuesta de Macho",
    "gn:population":0,
    "gn:timezone":"America/Bogota",
    "iso:country":"CO",
    "wof:name":"Cuesta de Macho",
    "wof:placetype":"locality"
},
  "geometry": {"coordinates":[-72.77444,8.27333],"type":"Point"}
}