{
  "type": "Feature",
  "properties": {
    "gn:admin1_code":"2.0",
    "gn:admin2_code":"5761.0",
    "gn:asciiname":"La Casa de Zinc",
    "gn:country_code":"CO",
    "gn:dem":1621,
    "gn:feature_class":"P",
    "gn:feature_code":"PPL",
    "gn:name":"La Casa de Zinc",
    "gn:population":0,
    "gn:timezone":"America/Bogota",
    "iso:country":"CO",
    "wof:name":"La Casa de Zinc",
    "wof:placetype":"locality"
},
  "geometry": {"coordinates":[-75.7255,6.56856],"type":"Point"}
}