{
  "type": "Feature",
  "properties": {
    "gn:admin1_code":"16.0",
    "gn:admin2_code":"41872.0",
    "gn:asciiname":"Cabuyal",
    "gn:country_code":"CO",
    "gn:dem":438,
    "gn:feature_class":"P",
    "gn:feature_code":"PPL",
    "gn:name":"Cabuyal",
    "gn:population":0,
    "gn:timezone":"America/Bogota",
    "iso:country":"CO",
    "name:spa_x_preferred":[
        "Cabuyal"
    ],
    "wof:name":"Cabuyal",
    "wof:placetype":"locality"
},
  "geometry": {"coordinates":[-75.13842,3.26955],"type":"Point"}
}