{
  "type": "Feature",
  "properties": {
    "gn:admin1_code":"10.0",
    "gn:admin2_code":"20621.0",
    "gn:asciiname":"El Martirio",
    "gn:country_code":"CO",
    "gn:dem":54,
    "gn:feature_class":"P",
    "gn:feature_code":"PPL",
    "gn:name":"El Martirio",
    "gn:population":0,
    "gn:timezone":"America/Bogota",
    "iso:country":"CO",
    "wof:name":"El Martirio",
    "wof:placetype":"locality"
},
  "geometry": {"coordinates":[-73.56104000000001,9.82964],"type":"Point"}
}