{
  "type": "Feature",
  "properties": {
    "gn:admin1_code":"10",
    "gn:admin2_code":"20400.0",
    "gn:asciiname":"Villa Caro",
    "gn:country_code":"CO",
    "gn:dem":206,
    "gn:feature_class":"P",
    "gn:feature_code":"PPL",
    "gn:name":"Villa Caro",
    "gn:population":0,
    "gn:timezone":"America/Bogota",
    "iso:country":"CO",
    "name:und_x_variant":[
        "Vila Caro Caser\u00edo",
        "Villa Caro"
    ],
    "wof:name":"Villa Caro",
    "wof:placetype":"locality"
},
  "geometry": {"coordinates":[-73.23569999999999,9.59014],"type":"Point"}
}