{
  "type": "Feature",
  "properties": {
    "gn:admin1_code":"10",
    "gn:admin2_code":"20400.0",
    "gn:asciiname":"Villa Caro",
    "gn:country_code":"CO",
    "gn:dem":206,
    "gn:feature_class":"P",
    "gn:feature_code":"PPL",
    "gn:name":"Villa Caro",
    "gn:population":0,
    "gn:timezone":"America/Bogota",
    "iso:country":"CO",
    "name:ceb_x_preferred":[
        "Villa Caro"
    ],
    "name:fra_x_preferred":[
        "Villa Caro"
    ],
    "name:ita_x_preferred":[
        "Villa Caro"
    ],
    "name:kat_x_preferred":[
        "\u10d5\u10d8\u10da\u10d8\u10d0-\u10d9\u10d0\u10e0\u10dd"
    ],
    "name:msa_x_preferred":[
        "Villa Caro"
    ],
    "name:nld_x_preferred":[
        "Villa Caro"
    ],
    "name:por_x_preferred":[
        "Villa Caro"
    ],
    "name:sco_x_preferred":[
        "Villa Caro"
    ],
    "name:spa_x_preferred":[
        "Villa Caro"
    ],
    "name:swe_x_preferred":[
        "Villa Caro"
    ],
    "name:tgl_x_preferred":[
        "Villa Caro"
    ],
    "name:und_x_variant":[
        "Vila Caro Caser\u00edo"
    ],
    "name:vie_x_preferred":[
        "Villa Caro"
    ],
    "name:war_x_preferred":[
        "Villa Caro"
    ],
    "name:zho_x_preferred":[
        "\u5361\u7f85\u93ae"
    ],
    "wof:name":"Villa Caro",
    "wof:placetype":"locality"
},
  "geometry": {"coordinates":[-73.23569999999999,9.59014],"type":"Point"}
}