{
  "type": "Feature",
  "properties": {
    "iso:country":"CO",
    "qs:gn_pop":0,
    "qs:name":"Caserio Palomino",
    "qs:name_adm0":"Colombia",
    "qs:name_adm1":"La Guajira",
    "qs:photos":139,
    "qs:photos_1k":28,
    "qs:photos_9k":1,
    "qs:photos_9r":3,
    "qs:photos_all":139,
    "qs:photos_sr":3,
    "qs:placetype":"Town",
    "qs:pop_sr":"0",
    "qs:woe_adm0":23424787,
    "wof:name":"Caserio Palomino",
    "wof:placetype":"locality"
},
  "geometry": {"coordinates":[-73.55913,11.255716],"type":"Point"}
}