{
  "type": "Feature",
  "properties": {
    "gn:admin1_code":"26",
    "gn:admin2_code":"68190.0",
    "gn:asciiname":"La Porfia",
    "gn:country_code":"CO",
    "gn:dem":125,
    "gn:feature_class":"P",
    "gn:feature_code":"PPL",
    "gn:name":"La Porfia",
    "gn:population":0,
    "gn:timezone":"America/Bogota",
    "iso:country":"CO",
    "wof:name":"La Porfia",
    "wof:placetype":"locality"
},
  "geometry": {"coordinates":[-74.22360999999999,6.48861],"type":"Point"}
}