{
  "type": "Feature",
  "properties": {
    "gn:admin1_code":"9.0",
    "gn:admin2_code":"19845.0",
    "gn:asciiname":"Vereda La Arrobleda",
    "gn:country_code":"CO",
    "gn:dem":989,
    "gn:feature_class":"P",
    "gn:feature_code":"PPLL",
    "gn:name":"Vereda La Arrobleda",
    "gn:population":0,
    "gn:timezone":"America/Bogota",
    "iso:country":"CO",
    "name:spa_x_preferred":[
        "Vereda La Arrobleda"
    ],
    "wof:name":"Vereda La Arrobleda",
    "wof:placetype":"locality"
},
  "geometry": {"coordinates":[-76.44385,3.11748],"type":"Point"}
}