{
  "type": "Feature",
  "properties": {
    "gn:admin1_code":"26",
    "gn:admin2_code":"68081.0",
    "gn:asciiname":"El Reposo",
    "gn:country_code":"CO",
    "gn:dem":110,
    "gn:feature_class":"P",
    "gn:feature_code":"PPL",
    "gn:name":"El Reposo",
    "gn:population":0,
    "gn:timezone":"America/Bogota",
    "iso:country":"CO",
    "wof:name":"El Reposo",
    "wof:placetype":"locality"
},
  "geometry": {"coordinates":[-73.73333000000002,6.95],"type":"Point"}
}