{
  "type": "Feature",
  "properties": {
    "gn:admin1_code":"26",
    "gn:admin2_code":"68572.0",
    "gn:asciiname":"Alto Capilla",
    "gn:country_code":"CO",
    "gn:dem":2034,
    "gn:feature_class":"P",
    "gn:feature_code":"PPL",
    "gn:name":"Alto Capilla",
    "gn:population":0,
    "gn:timezone":"America/Bogota",
    "iso:country":"CO",
    "wof:name":"Alto Capilla",
    "wof:placetype":"locality"
},
  "geometry": {"coordinates":[-73.63500000000001,5.83472],"type":"Point"}
}