{
  "type": "Feature",
  "properties": {
    "gn:admin1_code":"32",
    "gn:admin2_code":"85250.0",
    "gn:asciiname":"El Fundo",
    "gn:country_code":"CO",
    "gn:dem":130,
    "gn:feature_class":"P",
    "gn:feature_code":"PPL",
    "gn:name":"El Fundo",
    "gn:population":0,
    "gn:timezone":"America/Bogota",
    "iso:country":"CO",
    "wof:name":"El Fundo",
    "wof:placetype":"locality"
},
  "geometry": {"coordinates":[-70.98333000000002,5.91667],"type":"Point"}
}