{
  "type": "Feature",
  "properties": {
    "gn:admin1_code":"10.0",
    "gn:admin2_code":"20621.0",
    "gn:asciiname":"La Selva",
    "gn:country_code":"CO",
    "gn:dem":1550,
    "gn:feature_class":"P",
    "gn:feature_code":"PPL",
    "gn:name":"La Selva",
    "gn:population":0,
    "gn:timezone":"America/Bogota",
    "iso:country":"CO",
    "wof:name":"La Selva",
    "wof:placetype":"locality"
},
  "geometry": {"coordinates":[-73.00466,10.31809],"type":"Point"}
}