{
  "type": "Feature",
  "properties": {
    "gn:admin1_code":"12.0",
    "gn:admin2_code":"23189.0",
    "gn:asciiname":"Malabrigo",
    "gn:country_code":"CO",
    "gn:dem":73,
    "gn:feature_class":"P",
    "gn:feature_code":"PPLL",
    "gn:name":"Malabrigo",
    "gn:population":0,
    "gn:timezone":"America/Bogota",
    "iso:country":"CO",
    "wof:name":"Malabrigo",
    "wof:placetype":"locality"
},
  "geometry": {"coordinates":[-75.53430999999998,8.77466],"type":"Point"}
}