{
  "type": "Feature",
  "properties": {
    "gn:admin1_code":"27",
    "gn:admin2_code":"70001.0",
    "gn:asciiname":"La Gallera",
    "gn:country_code":"CO",
    "gn:dem":173,
    "gn:feature_class":"P",
    "gn:feature_code":"PPL",
    "gn:name":"La Gallera",
    "gn:population":0,
    "gn:timezone":"America/Bogota",
    "iso:country":"CO",
    "name:und_x_variant":[
        "Gallera",
        "La Gallera"
    ],
    "wof:name":"La Gallera",
    "wof:placetype":"locality"
},
  "geometry": {"coordinates":[-75.41989000000002,9.23689],"type":"Point"}
}