{
  "type": "Feature",
  "properties": {
    "gn:admin1_code":"20.0",
    "gn:admin2_code":"52022.0",
    "gn:asciiname":"El Rosa",
    "gn:country_code":"CO",
    "gn:dem":3207,
    "gn:feature_class":"P",
    "gn:feature_code":"PPL",
    "gn:name":"El Rosa",
    "gn:population":0,
    "gn:timezone":"America/Bogota",
    "iso:country":"CO",
    "wof:name":"El Rosa",
    "wof:placetype":"locality"
},
  "geometry": {"coordinates":[-77.70565999999999,0.90686],"type":"Point"}
}