{
  "type": "Feature",
  "properties": {
    "gn:admin1_code":"37.0",
    "gn:admin2_code":"17614.0",
    "gn:asciiname":"Lomitas",
    "gn:country_code":"CO",
    "gn:dem":1639,
    "gn:feature_class":"P",
    "gn:feature_code":"PPL",
    "gn:name":"Lomitas",
    "gn:population":0,
    "gn:timezone":"America/Bogota",
    "iso:country":"CO",
    "wof:name":"Lomitas",
    "wof:placetype":"locality"
},
  "geometry": {"coordinates":[-75.71106999999998,5.47804],"type":"Point"}
}