{
  "type": "Feature",
  "properties": {
    "gn:admin1_code":"2.0",
    "gn:admin2_code":"5647.0",
    "gn:asciiname":"La Redonda",
    "gn:country_code":"CO",
    "gn:dem":1891,
    "gn:feature_class":"P",
    "gn:feature_code":"PPL",
    "gn:name":"La Redonda",
    "gn:population":0,
    "gn:timezone":"America/Bogota",
    "iso:country":"CO",
    "wof:name":"La Redonda",
    "wof:placetype":"locality"
},
  "geometry": {"coordinates":[-75.69028,6.93889],"type":"Point"}
}