{
  "type": "Feature",
  "properties": {
    "gn:admin1_code":"16",
    "gn:admin2_code":"41016.0",
    "gn:asciiname":"El Arrayan",
    "gn:country_code":"CO",
    "gn:dem":427,
    "gn:feature_class":"P",
    "gn:feature_code":"PPL",
    "gn:name":"El Array\u00e1n",
    "gn:population":0,
    "gn:timezone":"America/Bogota",
    "iso:country":"CO",
    "name:und_x_variant":[
        "Array\u00e1n",
        "El Array\u00e1n"
    ],
    "wof:name":"El Arrayan",
    "wof:placetype":"locality"
},
  "geometry": {"coordinates":[-75.33417,3.13389],"type":"Point"}
}