{
  "type": "Feature",
  "properties": {
    "gn:admin1_code":"28.0",
    "gn:admin2_code":"73616.0",
    "gn:asciiname":"La Catalina",
    "gn:country_code":"CO",
    "gn:dem":2007,
    "gn:feature_class":"P",
    "gn:feature_code":"PPL",
    "gn:name":"La Catalina",
    "gn:population":0,
    "gn:timezone":"America/Bogota",
    "iso:country":"CO",
    "wof:name":"La Catalina",
    "wof:placetype":"locality"
},
  "geometry": {"coordinates":[-75.80389,3.59083],"type":"Point"}
}