{
  "type": "Feature",
  "properties": {
    "gn:admin1_code":"27",
    "gn:admin2_code":"70418.0",
    "gn:asciiname":"Los Chiqueros",
    "gn:country_code":"CO",
    "gn:dem":194,
    "gn:feature_class":"P",
    "gn:feature_code":"PPL",
    "gn:name":"Los Chiqueros",
    "gn:population":0,
    "gn:timezone":"America/Bogota",
    "iso:country":"CO",
    "wof:name":"Los Chiqueros",
    "wof:placetype":"locality"
},
  "geometry": {"coordinates":[-75.22395,9.37561],"type":"Point"}
}