{
  "type": "Feature",
  "properties": {
    "gn:admin1_code":"20.0",
    "gn:admin2_code":"52585.0",
    "gn:asciiname":"Caserio Chires Centro",
    "gn:country_code":"CO",
    "gn:dem":3214,
    "gn:feature_class":"P",
    "gn:feature_code":"PPL",
    "gn:name":"Caser\u00edo Ch\u00edres Centro",
    "gn:population":0,
    "gn:timezone":"America/Bogota",
    "iso:country":"CO",
    "wof:name":"Caserio Chires Centro",
    "wof:placetype":"locality"
},
  "geometry": {"coordinates":[-77.65439000000001,0.93484],"type":"Point"}
}