{
  "type": "Feature",
  "properties": {
    "gn:admin1_code":"10",
    "gn:admin2_code":"20570.0",
    "gn:asciiname":"Hacienda El Canon",
    "gn:country_code":"CO",
    "gn:dem":1030,
    "gn:feature_class":"P",
    "gn:feature_code":"PPL",
    "gn:name":"Hacienda El Ca\u00f1\u00f3n",
    "gn:population":0,
    "gn:timezone":"America/Bogota",
    "iso:country":"CO",
    "wof:name":"Hacienda El Canon",
    "wof:placetype":"locality"
},
  "geometry": {"coordinates":[-73.63333,10.41667],"type":"Point"}
}