{
  "type": "Feature",
  "properties": {
    "gn:admin1_code":"26",
    "gn:admin2_code":"68307.0",
    "gn:asciiname":"El Lindero",
    "gn:country_code":"CO",
    "gn:dem":323,
    "gn:feature_class":"P",
    "gn:feature_code":"PPL",
    "gn:name":"El Lindero",
    "gn:population":0,
    "gn:timezone":"America/Bogota",
    "iso:country":"CO",
    "name:spa_x_preferred":[
        "El Lindero"
    ],
    "wof:name":"El Lindero",
    "wof:placetype":"locality"
},
  "geometry": {"coordinates":[-73.39014,7.09258],"type":"Point"}
}