{
  "type": "Feature",
  "properties": {
    "gn:admin1_code":"17",
    "gn:admin2_code":"44001.0",
    "gn:asciiname":"El Contento",
    "gn:country_code":"CO",
    "gn:dem":40,
    "gn:feature_class":"P",
    "gn:feature_code":"PPL",
    "gn:name":"El Contento",
    "gn:population":0,
    "gn:timezone":"America/Bogota",
    "iso:country":"CO",
    "wof:name":"El Contento",
    "wof:placetype":"locality"
},
  "geometry": {"coordinates":[-72.95444000000001,11.29153],"type":"Point"}
}