{
  "type": "Feature",
  "properties": {
    "iso:country":"CO",
    "name:ceb_x_preferred":[
        "Miraflores"
    ],
    "name:chi_x_preferred":[
        "\u7c73\u62c9\u5f17\u6d1b\u96f7\u65af"
    ],
    "name:dut_x_preferred":[
        "Miraflores"
    ],
    "name:eng_x_preferred":[
        "Miraflores"
    ],
    "name:fra_x_preferred":[
        "Miraflores"
    ],
    "name:fre_x_preferred":[
        "Miraflores"
    ],
    "name:ita_x_preferred":[
        "Miraflores"
    ],
    "name:jpn_x_preferred":[
        "\u30df\u30e9\u30d5\u30ed\u30ec\u30b9"
    ],
    "name:may_x_preferred":[
        "Miraflores"
    ],
    "name:msa_x_preferred":[
        "Miraflores"
    ],
    "name:nan_x_preferred":[
        "Miraflores"
    ],
    "name:nld_x_preferred":[
        "Miraflores"
    ],
    "name:pol_x_preferred":[
        "Miraflores"
    ],
    "name:por_x_preferred":[
        "Miraflores"
    ],
    "name:sco_x_preferred":[
        "Miraflores"
    ],
    "name:spa_x_preferred":[
        "Miraflores"
    ],
    "name:swe_x_preferred":[
        "Miraflores"
    ],
    "name:tgl_x_preferred":[
        "Miraflores"
    ],
    "name:vie_x_preferred":[
        "Miraflores"
    ],
    "name:war_x_preferred":[
        "Miraflores"
    ],
    "name:zho_min_nan_x_preferred":[
        "Miraflores"
    ],
    "name:zho_x_preferred":[
        "\u7c73\u62c9\u5f17\u6d1b\u96f7\u65af"
    ],
    "qs:gn_country":"CO",
    "qs:gn_fcode":"PPL",
    "qs:gn_pop":4864,
    "qs:name":"Miraflores",
    "qs:name_adm0":"Colombia",
    "qs:name_adm1":"Guavaire",
    "qs:photos":0,
    "qs:photos_1k":0,
    "qs:photos_9k":0,
    "qs:photos_9r":0,
    "qs:photos_all":0,
    "qs:photos_sr":0,
    "qs:placetype":"Town",
    "qs:pop_sr":"4",
    "qs:woe_adm0":23424787,
    "wd:wordcount":289,
    "wof:name":"Miraflores",
    "wof:placetype":"locality",
    "wof:population":4864
},
  "geometry": {"coordinates":[-71.95111,1.33667],"type":"Point"}
}