{
  "type": "Feature",
  "properties": {
    "gn:admin1_code":"31",
    "gn:admin2_code":"99773.0",
    "gn:asciiname":"Capitan",
    "gn:country_code":"CO",
    "gn:dem":118,
    "gn:feature_class":"P",
    "gn:feature_code":"PPL",
    "gn:name":"Capit\u00e1n",
    "gn:population":0,
    "gn:timezone":"America/Bogota",
    "iso:country":"CO",
    "name:ceb_x_preferred":[
        "Capitan"
    ],
    "name:deu_x_preferred":[
        "Capitan"
    ],
    "name:fas_x_preferred":[
        "\u06a9\u0627\u067e\u06cc\u062a\u0627\u0646"
    ],
    "name:fra_x_preferred":[
        "Capitan"
    ],
    "name:nld_x_preferred":[
        "Capitan"
    ],
    "name:spa_x_preferred":[
        "Capit\u00e1n"
    ],
    "name:swe_x_preferred":[
        "Capitan"
    ],
    "wof:name":"Capitan",
    "wof:placetype":"locality"
},
  "geometry": {"coordinates":[-69.85825,3.62928],"type":"Point"}
}