{
  "type": "Feature",
  "properties": {
    "gn:admin1_code":"19",
    "gn:admin2_code":"50223",
    "gn:asciiname":"San Luis de Marayal",
    "gn:country_code":"CO",
    "gn:dem":526,
    "gn:feature_class":"P",
    "gn:feature_code":"PPL",
    "gn:name":"San Luis de Marayal",
    "gn:population":0,
    "gn:timezone":"America/Bogota",
    "iso:country":"CO",
    "name:spa_x_preferred":[
        "San Luis de Marayal"
    ],
    "wof:name":"San Luis de Marayal",
    "wof:placetype":"locality"
},
  "geometry": {"coordinates":[-73.79815000000001,3.76963],"type":"Point"}
}