{
  "type": "Feature",
  "properties": {
    "gn:admin1_code":"12",
    "gn:admin2_code":"23168.0",
    "gn:asciiname":"Chamarra",
    "gn:country_code":"CO",
    "gn:dem":7,
    "gn:feature_class":"P",
    "gn:feature_code":"PPL",
    "gn:name":"Chamarra",
    "gn:population":0,
    "gn:timezone":"America/Bogota",
    "iso:country":"CO",
    "wof:name":"Chamarra",
    "wof:placetype":"locality"
},
  "geometry": {"coordinates":[-75.71476,9.03209],"type":"Point"}
}