{
  "type": "Feature",
  "properties": {
    "gn:admin1_code":"28",
    "gn:admin2_code":"73001.0",
    "gn:asciiname":"La Maria",
    "gn:country_code":"CO",
    "gn:dem":2431,
    "gn:feature_class":"P",
    "gn:feature_code":"PPL",
    "gn:name":"La Mar\u00eda",
    "gn:population":0,
    "gn:timezone":"America/Bogota",
    "iso:country":"CO",
    "wof:name":"La Maria",
    "wof:placetype":"locality"
},
  "geometry": {"coordinates":[-75.41667,4.33333],"type":"Point"}
}