{
  "type": "Feature",
  "properties": {
    "gn:admin1_code":"17.0",
    "gn:admin2_code":"44847.0",
    "gn:asciiname":"Samurrerap",
    "gn:country_code":"CO",
    "gn:dem":12,
    "gn:feature_class":"P",
    "gn:feature_code":"PPL",
    "gn:name":"Sam\u00farrerap",
    "gn:population":0,
    "gn:timezone":"America/Bogota",
    "iso:country":"CO",
    "wof:name":"Samurrerap",
    "wof:placetype":"locality"
},
  "geometry": {"coordinates":[-71.84138,12.16491],"type":"Point"}
}