{
  "type": "Feature",
  "properties": {
    "gn:admin1_code":"10.0",
    "gn:admin2_code":"20228.0",
    "gn:asciiname":"Pesqueria",
    "gn:country_code":"CO",
    "gn:dem":26,
    "gn:feature_class":"P",
    "gn:feature_code":"PPL",
    "gn:name":"Pesquer\u00eda",
    "gn:population":0,
    "gn:timezone":"America/Bogota",
    "iso:country":"CO",
    "wof:name":"Pesqueria",
    "wof:placetype":"locality"
},
  "geometry": {"coordinates":[-73.68333,9.25],"type":"Point"}
}