{
  "type": "Feature",
  "properties": {
    "gn:admin1_code":"12.0",
    "gn:admin2_code":"23001.0",
    "gn:asciiname":"El Faro",
    "gn:country_code":"CO",
    "gn:dem":15,
    "gn:feature_class":"P",
    "gn:feature_code":"PPL",
    "gn:name":"El Faro",
    "gn:population":0,
    "gn:timezone":"America/Bogota",
    "iso:country":"CO",
    "name:ceb_x_preferred":[
        "El Faro"
    ],
    "name:srp_x_preferred":[
        "\u0415\u043b \u0424\u0430\u0440\u043e"
    ],
    "name:swe_x_preferred":[
        "El Faro"
    ],
    "wof:name":"El Faro",
    "wof:placetype":"locality"
},
  "geometry": {"coordinates":[-75.81944,8.80556],"type":"Point"}
}