{
  "type": "Feature",
  "properties": {
    "gn:admin1_code":"12.0",
    "gn:admin2_code":"23855.0",
    "gn:asciiname":"Villanueva",
    "gn:country_code":"CO",
    "gn:dem":53,
    "gn:feature_class":"P",
    "gn:feature_code":"PPL",
    "gn:name":"Villanueva",
    "gn:population":0,
    "gn:timezone":"America/Bogota",
    "iso:country":"CO",
    "name:und_x_variant":[
        "Villa Nueva",
        "Villaneueva",
        "Villanueva"
    ],
    "wof:name":"Villanueva",
    "wof:placetype":"locality"
},
  "geometry": {"coordinates":[-76.11796,8.34082],"type":"Point"}
}