{
  "type": "Feature",
  "properties": {
    "gn:admin1_code":"38",
    "gn:admin2_code":"47960.0",
    "gn:asciiname":"Henequen",
    "gn:cc2":"CO",
    "gn:country_code":"CO",
    "gn:dem":13,
    "gn:feature_class":"P",
    "gn:feature_code":"PPL",
    "gn:name":"Henequ\u00e9n",
    "gn:population":0,
    "gn:timezone":"America/Bogota",
    "iso:country":"CO",
    "name:und_x_variant":[
        "Hacienda Henequ\u00e9n",
        "Henequ\u00e9n"
    ],
    "wof:name":"Henequen",
    "wof:placetype":"locality"
},
  "geometry": {"coordinates":[-74.68889,10.22722],"type":"Point"}
}