{
  "type": "Feature",
  "properties": {
    "gn:admin1_code":"2.0",
    "gn:admin2_code":"5686.0",
    "gn:asciiname":"San Francisco Medina",
    "gn:country_code":"CO",
    "gn:dem":2534,
    "gn:feature_class":"P",
    "gn:feature_code":"PPL",
    "gn:name":"San Francisco Medina",
    "gn:population":0,
    "gn:timezone":"America/Bogota",
    "iso:country":"CO",
    "wof:name":"San Francisco Medina",
    "wof:placetype":"locality"
},
  "geometry": {"coordinates":[-75.51278000000001,6.66861],"type":"Point"}
}