{
  "type": "Feature",
  "properties": {
    "iso:country":"CO",
    "name:msa_x_preferred":[
        "Valle San Jos\u00e9"
    ],
    "name:tgl_x_preferred":[
        "Valle San Jos\u00e9"
    ],
    "name:und_x_variant":[
        "El Valle"
    ],
    "name:war_x_preferred":[
        "Valle San Jos\u00e9"
    ],
    "qs:gn_country":"CO",
    "qs:gn_fcode":"PPL",
    "qs:gn_pop":2522,
    "qs:name":"Valle de San Jos\u00e9",
    "qs:name_adm0":"Colombia",
    "qs:name_adm1":"Santander",
    "qs:photos":0,
    "qs:photos_1k":0,
    "qs:photos_9k":1,
    "qs:photos_9r":1,
    "qs:photos_all":13,
    "qs:photos_sr":0,
    "qs:placetype":"Town",
    "qs:pop_sr":"4",
    "qs:woe_adm0":23424787,
    "wof:name":"Valle de San Jos\u00e9",
    "wof:placetype":"locality",
    "wof:population":2522
},
  "geometry": {"coordinates":[-73.14361,6.4475],"type":"Point"}
}