{
  "type": "Feature",
  "properties": {
    "gn:admin1_code":"24.0",
    "gn:admin2_code":"66594.0",
    "gn:asciiname":"Murrapal",
    "gn:country_code":"CO",
    "gn:dem":1793,
    "gn:feature_class":"P",
    "gn:feature_code":"PPL",
    "gn:name":"Murrapal",
    "gn:population":0,
    "gn:timezone":"America/Bogota",
    "iso:country":"CO",
    "wof:name":"Murrapal",
    "wof:placetype":"locality"
},
  "geometry": {"coordinates":[-75.74162,5.33147],"type":"Point"}
}