{
  "type": "Feature",
  "properties": {
    "gn:admin1_code":"20.0",
    "gn:admin2_code":"52356.0",
    "gn:asciiname":"La Vuelta del Encino",
    "gn:country_code":"CO",
    "gn:dem":3376,
    "gn:feature_class":"P",
    "gn:feature_code":"PPL",
    "gn:name":"La Vuelta del Encino",
    "gn:population":0,
    "gn:timezone":"America/Bogota",
    "iso:country":"CO",
    "wof:name":"La Vuelta del Encino",
    "wof:placetype":"locality"
},
  "geometry": {"coordinates":[-77.66901999999997,0.73432],"type":"Point"}
}