{
  "type": "Feature",
  "properties": {
    "gn:admin1_code":"8.0",
    "gn:admin2_code":"18753.0",
    "gn:asciiname":"La Lampa",
    "gn:country_code":"CO",
    "gn:dem":1718,
    "gn:feature_class":"P",
    "gn:feature_code":"PPL",
    "gn:name":"La Lampa",
    "gn:population":0,
    "gn:timezone":"America/Bogota",
    "iso:country":"CO",
    "name:spa_x_preferred":[
        "La Lampa"
    ],
    "wof:name":"La Lampa",
    "wof:placetype":"locality"
},
  "geometry": {"coordinates":[-74.86055999999998,2.82417],"type":"Point"}
}