{
  "type": "Feature",
  "properties": {
    "gn:admin1_code":"26",
    "gn:admin2_code":"68655.0",
    "gn:asciiname":"Si Dios Quiere",
    "gn:country_code":"CO",
    "gn:dem":164,
    "gn:feature_class":"P",
    "gn:feature_code":"PPL",
    "gn:name":"Si Dios Quiere",
    "gn:population":0,
    "gn:timezone":"America/Bogota",
    "iso:country":"CO",
    "wof:name":"Si Dios Quiere",
    "wof:placetype":"locality"
},
  "geometry": {"coordinates":[-73.41306,7.36972],"type":"Point"}
}