{
  "type": "Feature",
  "properties": {
    "gn:admin1_code":"24.0",
    "gn:admin2_code":"66170.0",
    "gn:asciiname":"Aguazul",
    "gn:country_code":"CO",
    "gn:dem":1782,
    "gn:feature_class":"P",
    "gn:feature_code":"PPL",
    "gn:name":"Aguazul",
    "gn:population":0,
    "gn:timezone":"America/Bogota",
    "iso:country":"CO",
    "wof:name":"Aguazul",
    "wof:placetype":"locality"
},
  "geometry": {"coordinates":[-75.64889000000002,4.87667],"type":"Point"}
}