{
  "type": "Feature",
  "properties": {
    "gn:admin1_code":"24.0",
    "gn:admin2_code":"66170.0",
    "gn:asciiname":"Aguazul",
    "gn:country_code":"CO",
    "gn:dem":1782,
    "gn:feature_class":"P",
    "gn:feature_code":"PPL",
    "gn:name":"Aguazul",
    "gn:population":0,
    "gn:timezone":"America/Bogota",
    "iso:country":"CO",
    "name:bre_x_preferred":[
        "Aguazul"
    ],
    "name:ceb_x_preferred":[
        "Aguazul"
    ],
    "name:deu_x_preferred":[
        "Aguazul"
    ],
    "name:fas_x_preferred":[
        "\u0627\u06af\u0648\u0627\u0632\u0648\u0644"
    ],
    "name:fin_x_preferred":[
        "Aguazul"
    ],
    "name:fra_x_preferred":[
        "Aguazul"
    ],
    "name:ita_x_preferred":[
        "Aguazul"
    ],
    "name:kat_x_preferred":[
        "\u10d0\u10d2\u10e3\u10d0\u10e1\u10e3\u10da\u10d8"
    ],
    "name:msa_x_preferred":[
        "Aguazul"
    ],
    "name:nld_x_preferred":[
        "Aguazul"
    ],
    "name:por_x_preferred":[
        "Aguazul"
    ],
    "name:spa_x_preferred":[
        "Aguazul"
    ],
    "name:swe_x_preferred":[
        "Aguazul"
    ],
    "name:tgl_x_preferred":[
        "Aguazul"
    ],
    "name:urd_x_preferred":[
        "\u0627\u06af\u0648\u0627\u0632\u0648\u0644"
    ],
    "name:vie_x_preferred":[
        "Aguazul"
    ],
    "name:war_x_preferred":[
        "Aguazul"
    ],
    "name:zho_x_preferred":[
        "\u963f\u74dc\u8607\u723e"
    ],
    "wof:name":"Aguazul",
    "wof:placetype":"locality"
},
  "geometry": {"coordinates":[-75.64889000000002,4.87667],"type":"Point"}
}