{
  "type": "Feature",
  "properties": {
    "gn:admin1_code":"28",
    "gn:admin2_code":"73624.0",
    "gn:asciiname":"Waterloo",
    "gn:country_code":"CO",
    "gn:dem":2821,
    "gn:feature_class":"P",
    "gn:feature_code":"PPL",
    "gn:name":"Waterloo",
    "gn:population":0,
    "gn:timezone":"America/Bogota",
    "iso:country":"CO",
    "wof:name":"Waterloo",
    "wof:placetype":"locality"
},
  "geometry": {"coordinates":[-75.34,4.31889],"type":"Point"}
}