{
  "type": "Feature",
  "properties": {
    "iso:country":"CO",
    "name:ast_x_preferred":[
        "El Rosario"
    ],
    "name:ceb_x_preferred":[
        "El Rosario"
    ],
    "name:eng_x_preferred":[
        "El Rosario"
    ],
    "name:fra_x_preferred":[
        "El Rosario"
    ],
    "name:ita_x_preferred":[
        "El Rosario"
    ],
    "name:kat_x_preferred":[
        "\u10d4\u10da-\u10e0\u10dd\u10e1\u10d0\u10e0\u10d8\u10dd"
    ],
    "name:msa_x_preferred":[
        "El Rosario"
    ],
    "name:nan_x_preferred":[
        "El Rosario"
    ],
    "name:nld_x_preferred":[
        "El Rosario"
    ],
    "name:por_x_preferred":[
        "El Rosario"
    ],
    "name:sco_x_preferred":[
        "El Rosario"
    ],
    "name:spa_x_preferred":[
        "El Rosario"
    ],
    "name:swe_x_preferred":[
        "El Rosario"
    ],
    "name:tgl_x_preferred":[
        "El Rosario"
    ],
    "name:und_x_variant":[
        "Rosario"
    ],
    "name:war_x_preferred":[
        "El Rosario"
    ],
    "name:zho_x_preferred":[
        "\u57c3\u723e\u7f85\u85a9\u91cc\u5967"
    ],
    "qs:gn_country":"CO",
    "qs:gn_fcode":"PPL",
    "qs:gn_pop":2607,
    "qs:name":"El Rosario",
    "qs:name_adm0":"Colombia",
    "qs:name_adm1":"Narino",
    "qs:photos":0,
    "qs:photos_1k":0,
    "qs:photos_9k":0,
    "qs:photos_9r":0,
    "qs:photos_all":0,
    "qs:photos_sr":0,
    "qs:placetype":"Town",
    "qs:pop_sr":"4",
    "qs:woe_adm0":23424787,
    "wof:name":"El Rosario",
    "wof:placetype":"locality",
    "wof:population":2607
},
  "geometry": {"coordinates":[-77.3352,1.74173],"type":"Point"}
}