{
  "type": "Feature",
  "properties": {
    "gn:admin1_code":"26.0",
    "gn:admin2_code":"68307.0",
    "gn:asciiname":"Socara",
    "gn:country_code":"CO",
    "gn:dem":857,
    "gn:feature_class":"P",
    "gn:feature_code":"PPL",
    "gn:name":"Socara",
    "gn:population":0,
    "gn:timezone":"America/Bogota",
    "iso:country":"CO",
    "name:spa_x_preferred":[
        "Socara"
    ],
    "wof:name":"Socara",
    "wof:placetype":"locality"
},
  "geometry": {"coordinates":[-73.18655,7.01165],"type":"Point"}
}