{
  "type": "Feature",
  "properties": {
    "gn:admin1_code":"2",
    "gn:admin2_code":"5854.0",
    "gn:asciiname":"Claveles",
    "gn:country_code":"CO",
    "gn:dem":481,
    "gn:feature_class":"P",
    "gn:feature_code":"PPL",
    "gn:name":"Claveles",
    "gn:population":0,
    "gn:timezone":"America/Bogota",
    "iso:country":"CO",
    "wof:name":"Claveles",
    "wof:placetype":"locality"
},
  "geometry": {"coordinates":[-75.40756,7.35968],"type":"Point"}
}