{
  "type": "Feature",
  "properties": {
    "gn:admin1_code":"38",
    "gn:admin2_code":"47189.0",
    "gn:asciiname":"Hacienda La Lucha",
    "gn:country_code":"CO",
    "gn:dem":10,
    "gn:feature_class":"P",
    "gn:feature_code":"PPL",
    "gn:name":"Hacienda La Lucha",
    "gn:population":0,
    "gn:timezone":"America/Bogota",
    "iso:country":"CO",
    "wof:name":"Hacienda La Lucha",
    "wof:placetype":"locality"
},
  "geometry": {"coordinates":[-74.24231,10.897],"type":"Point"}
}