{
  "type": "Feature",
  "properties": {
    "gn:admin1_code":"10",
    "gn:admin2_code":"20045.0",
    "gn:asciiname":"Santa Barbara",
    "gn:country_code":"CO",
    "gn:dem":52,
    "gn:feature_class":"P",
    "gn:feature_code":"PPL",
    "gn:name":"Santa B\u00e1rbara",
    "gn:population":0,
    "gn:timezone":"America/Bogota",
    "iso:country":"CO",
    "wof:name":"Santa Barbara",
    "wof:placetype":"locality"
},
  "geometry": {"coordinates":[-73.47239999999999,9.75053],"type":"Point"}
}