{
  "type": "Feature",
  "properties": {
    "gn:admin1_code":"17",
    "gn:admin2_code":"44650.0",
    "gn:asciiname":"Guayacanal",
    "gn:country_code":"CO",
    "gn:dem":362,
    "gn:feature_class":"P",
    "gn:feature_code":"PPL",
    "gn:name":"Guayacanal",
    "gn:population":0,
    "gn:timezone":"America/Bogota",
    "iso:country":"CO",
    "wof:name":"Guayacanal",
    "wof:placetype":"locality"
},
  "geometry": {"coordinates":[-73.08333,10.83333],"type":"Point"}
}