{
  "type": "Feature",
  "properties": {
    "gn:admin1_code":"16",
    "gn:admin2_code":"41799",
    "gn:asciiname":"La Habana",
    "gn:country_code":"CO",
    "gn:dem":1893,
    "gn:feature_class":"P",
    "gn:feature_code":"PPL",
    "gn:name":"La Habana",
    "gn:population":0,
    "gn:timezone":"America/Bogota",
    "iso:country":"CO",
    "name:spa_x_preferred":[
        "La Habana"
    ],
    "wof:name":"La Habana",
    "wof:placetype":"locality"
},
  "geometry": {"coordinates":[-74.94020999999999,3.03934],"type":"Point"}
}