{
  "type": "Feature",
  "properties": {
    "gn:admin1_code":"8",
    "gn:admin2_code":"18410.0",
    "gn:asciiname":"La Union Peneya",
    "gn:country_code":"CO",
    "gn:dem":217,
    "gn:feature_class":"P",
    "gn:feature_code":"PPL",
    "gn:name":"La Uni\u00f3n Peneya",
    "gn:population":0,
    "gn:timezone":"America/Bogota",
    "iso:country":"CO",
    "name:spa_x_preferred":[
        "La Uni\u00f3n Peneya"
    ],
    "name:und_x_variant":[
        "Inspecci\u00f3n de Polic\u00eda La Uni\u00f3n Peneya"
    ],
    "wof:name":"La Union Peneya",
    "wof:placetype":"locality"
},
  "geometry": {"coordinates":[-75.20848000000002,1.2814],"type":"Point"}
}