{
  "type": "Feature",
  "properties": {
    "gn:admin1_code":"12.0",
    "gn:admin2_code":"23001.0",
    "gn:asciiname":"El Cielo",
    "gn:country_code":"CO",
    "gn:dem":66,
    "gn:feature_class":"P",
    "gn:feature_code":"PPLL",
    "gn:name":"El Cielo",
    "gn:population":0,
    "gn:timezone":"America/Bogota",
    "iso:country":"CO",
    "wof:name":"El Cielo",
    "wof:placetype":"locality"
},
  "geometry": {"coordinates":[-75.78718000000001,8.567],"type":"Point"}
}