{
  "type": "Feature",
  "properties": {
    "gn:admin1_code":"33.0",
    "gn:admin2_code":"25377.0",
    "gn:asciiname":"Vereda El Verjon",
    "gn:country_code":"CO",
    "gn:dem":3120,
    "gn:feature_class":"P",
    "gn:feature_code":"PPLL",
    "gn:name":"Vereda El Verj\u00f3n",
    "gn:population":0,
    "gn:timezone":"America/Bogota",
    "iso:country":"CO",
    "name:spa_x_preferred":[
        "Vereda El Verj\u00f3n"
    ],
    "wof:name":"Vereda El Verjon",
    "wof:placetype":"locality"
},
  "geometry": {"coordinates":[-74.00066,4.62729],"type":"Point"}
}