{
  "type": "Feature",
  "properties": {
    "gn:admin1_code":"1.0",
    "gn:admin2_code":"91669.0",
    "gn:asciiname":"Mequeranio",
    "gn:country_code":"CO",
    "gn:dem":122,
    "gn:feature_class":"P",
    "gn:feature_code":"PPL",
    "gn:name":"Mequeranio",
    "gn:population":0,
    "gn:timezone":"America/Bogota",
    "iso:country":"CO",
    "wof:name":"Mequeranio",
    "wof:placetype":"locality"
},
  "geometry": {"coordinates":[-71.51666999999998,-1.43333],"type":"Point"}
}