{
  "type": "Feature",
  "properties": {
    "gn:admin1_code":"9.0",
    "gn:admin2_code":"19130.0",
    "gn:asciiname":"San Jose de la Laguna",
    "gn:country_code":"CO",
    "gn:dem":1904,
    "gn:feature_class":"P",
    "gn:feature_code":"PPL",
    "gn:name":"San Jose de la Laguna",
    "gn:population":0,
    "gn:timezone":"America/Bogota",
    "iso:country":"CO",
    "wof:name":"San Jose de la Laguna",
    "wof:placetype":"locality"
},
  "geometry": {"coordinates":[-76.53413,2.62541],"type":"Point"}
}