{
  "type": "Feature",
  "properties": {
    "gn:admin1_code":"14.0",
    "gn:admin2_code":"95200.0",
    "gn:asciiname":"Santa Teresita",
    "gn:country_code":"CO",
    "gn:dem":207,
    "gn:feature_class":"P",
    "gn:feature_code":"PPL",
    "gn:name":"Santa Teresita",
    "gn:population":0,
    "gn:timezone":"America/Bogota",
    "iso:country":"CO",
    "wof:name":"Santa Teresita",
    "wof:placetype":"locality"
},
  "geometry": {"coordinates":[-72.26885,1.3998],"type":"Point"}
}