{
  "type": "Feature",
  "properties": {
    "gn:admin1_code":"16",
    "gn:admin2_code":"41357.0",
    "gn:asciiname":"Las Mesitas",
    "gn:country_code":"CO",
    "gn:dem":755,
    "gn:feature_class":"P",
    "gn:feature_code":"PPL",
    "gn:name":"Las Mesitas",
    "gn:population":0,
    "gn:timezone":"America/Bogota",
    "iso:country":"CO",
    "wof:name":"Las Mesitas",
    "wof:placetype":"locality"
},
  "geometry": {"coordinates":[-75.61939,2.60272],"type":"Point"}
}