{
  "type": "Feature",
  "properties": {
    "gn:admin1_code":"38",
    "gn:admin2_code":"47551.0",
    "gn:asciiname":"El Jardin",
    "gn:country_code":"CO",
    "gn:dem":40,
    "gn:feature_class":"P",
    "gn:feature_code":"PPL",
    "gn:name":"El Jard\u00edn",
    "gn:population":0,
    "gn:timezone":"America/Bogota",
    "iso:country":"CO",
    "name:und_x_variant":[
        "Hacienda El Jard\u00edn",
        "El Jard\u00edn"
    ],
    "wof:name":"El Jardin",
    "wof:placetype":"locality"
},
  "geometry": {"coordinates":[-74.34371999999998,10.48752],"type":"Point"}
}