{
  "type": "Feature",
  "properties": {
    "gn:admin1_code":"2",
    "gn:admin2_code":"5887.0",
    "gn:asciiname":"Casa de Ordeno",
    "gn:country_code":"CO",
    "gn:dem":1955,
    "gn:feature_class":"P",
    "gn:feature_code":"PPL",
    "gn:name":"Casa de Ordeno",
    "gn:population":0,
    "gn:timezone":"America/Bogota",
    "iso:country":"CO",
    "wof:name":"Casa de Ordeno",
    "wof:placetype":"locality"
},
  "geometry": {"coordinates":[-75.50019,7.00749],"type":"Point"}
}