{
  "type": "Feature",
  "properties": {
    "gn:admin1_code":"20.0",
    "gn:admin2_code":"52678.0",
    "gn:asciiname":"Sarancocho",
    "gn:cc2":"CO",
    "gn:country_code":"CO",
    "gn:dem":1858,
    "gn:feature_class":"P",
    "gn:feature_code":"PPL",
    "gn:name":"Sarancocho",
    "gn:population":0,
    "gn:timezone":"America/Bogota",
    "iso:country":"CO",
    "name:und_x_variant":[
        "Saraconcho",
        "Sarancocho"
    ],
    "wof:name":"Sarancocho",
    "wof:placetype":"locality"
},
  "geometry": {"coordinates":[-77.59999999999999,1.35],"type":"Point"}
}