{
  "type": "Feature",
  "properties": {
    "gn:admin1_code":"2.0",
    "gn:admin2_code":"5113.0",
    "gn:asciiname":"Cordillerita",
    "gn:country_code":"CO",
    "gn:dem":2001,
    "gn:feature_class":"P",
    "gn:feature_code":"PPL",
    "gn:name":"Cordillerita",
    "gn:population":0,
    "gn:timezone":"America/Bogota",
    "iso:country":"CO",
    "wof:name":"Cordillerita",
    "wof:placetype":"locality"
},
  "geometry": {"coordinates":[-75.91611,6.82889],"type":"Point"}
}