{
  "type": "Feature",
  "properties": {
    "gn:admin1_code":"2.0",
    "gn:admin2_code":"5001.0",
    "gn:asciiname":"Los Arrayanes",
    "gn:country_code":"CO",
    "gn:dem":2545,
    "gn:feature_class":"P",
    "gn:feature_code":"PPL",
    "gn:name":"Los Arrayanes",
    "gn:population":0,
    "gn:timezone":"America/Bogota",
    "iso:country":"CO",
    "name:spa_x_preferred":[
        "Los Arrayanes"
    ],
    "wof:name":"Los Arrayanes",
    "wof:placetype":"locality"
},
  "geometry": {"coordinates":[-75.50258000000002,6.2159],"type":"Point"}
}