{
  "type": "Feature",
  "properties": {
    "gn:admin1_code":"30.0",
    "gn:admin2_code":"97001.0",
    "gn:asciiname":"Puerto Colombia",
    "gn:country_code":"CO",
    "gn:dem":165,
    "gn:feature_class":"P",
    "gn:feature_code":"PPL",
    "gn:name":"Puerto Colombia",
    "gn:population":0,
    "gn:timezone":"America/Bogota",
    "iso:country":"CO",
    "wof:name":"Puerto Colombia",
    "wof:placetype":"locality"
},
  "geometry": {"coordinates":[-70.05028,0.26472],"type":"Point"}
}