{
  "type": "Feature",
  "properties": {
    "gn:admin1_code":"17.0",
    "gn:admin2_code":"44078.0",
    "gn:asciiname":"Papayal",
    "gn:country_code":"CO",
    "gn:dem":145,
    "gn:feature_class":"P",
    "gn:feature_code":"PPL",
    "gn:name":"Papayal",
    "gn:population":0,
    "gn:timezone":"America/Bogota",
    "iso:country":"CO",
    "name:und_x_variant":[
        "Papejel",
        "Papayel",
        "Papayal"
    ],
    "wof:name":"Papayal",
    "wof:placetype":"locality"
},
  "geometry": {"coordinates":[-72.7765,10.99646],"type":"Point"}
}