{
  "type": "Feature",
  "properties": {
    "gn:admin1_code":"37.0",
    "gn:admin2_code":"17444.0",
    "gn:asciiname":"El Bosque",
    "gn:country_code":"CO",
    "gn:dem":1101,
    "gn:feature_class":"P",
    "gn:feature_code":"PPL",
    "gn:name":"El Bosque",
    "gn:population":0,
    "gn:timezone":"America/Bogota",
    "iso:country":"CO",
    "name:spa_x_preferred":[
        "El Bosque"
    ],
    "wof:name":"El Bosque",
    "wof:placetype":"locality"
},
  "geometry": {"coordinates":[-74.97654,5.31058],"type":"Point"}
}