{
  "type": "Feature",
  "properties": {
    "gn:admin1_code":"19.0",
    "gn:admin2_code":"50689.0",
    "gn:asciiname":"La Escondida",
    "gn:country_code":"CO",
    "gn:dem":253,
    "gn:feature_class":"P",
    "gn:feature_code":"PPLL",
    "gn:name":"La Escondida",
    "gn:population":0,
    "gn:timezone":"America/Bogota",
    "iso:country":"CO",
    "name:spa_x_preferred":[
        "La Escondida"
    ],
    "wof:name":"La Escondida",
    "wof:placetype":"locality"
},
  "geometry": {"coordinates":[-73.38545999999999,3.68659],"type":"Point"}
}