{
  "type": "Feature",
  "properties": {
    "gn:admin1_code":"2",
    "gn:admin2_code":"5361.0",
    "gn:asciiname":"Los Volcanes",
    "gn:country_code":"CO",
    "gn:dem":1678,
    "gn:feature_class":"P",
    "gn:feature_code":"PPL",
    "gn:name":"Los Volcanes",
    "gn:population":0,
    "gn:timezone":"America/Bogota",
    "iso:country":"CO",
    "wof:name":"Los Volcanes",
    "wof:placetype":"locality"
},
  "geometry": {"coordinates":[-75.63694,7.26889],"type":"Point"}
}