{
  "type": "Feature",
  "properties": {
    "gn:admin1_code":"33",
    "gn:asciiname":"El Espejo",
    "gn:country_code":"CO",
    "gn:dem":1135,
    "gn:feature_class":"P",
    "gn:feature_code":"PPL",
    "gn:name":"El Espejo",
    "gn:population":0,
    "gn:timezone":"America/Bogota",
    "iso:country":"CO",
    "wof:name":"El Espejo",
    "wof:placetype":"locality"
},
  "geometry": {"coordinates":[-75.13806,4.48333],"type":"Point"}
}