{
  "type": "Feature",
  "properties": {
    "gn:admin1_code":"27",
    "gn:admin2_code":"70508.0",
    "gn:asciiname":"El Charcon",
    "gn:country_code":"CO",
    "gn:dem":236,
    "gn:feature_class":"P",
    "gn:feature_code":"PPL",
    "gn:name":"El Charc\u00f3n",
    "gn:population":0,
    "gn:timezone":"America/Bogota",
    "iso:country":"CO",
    "wof:name":"El Charcon",
    "wof:placetype":"locality"
},
  "geometry": {"coordinates":[-75.188,9.56419],"type":"Point"}
}