{
  "type": "Feature",
  "properties": {
    "gn:admin1_code":"38",
    "gn:admin2_code":"47555.0",
    "gn:asciiname":"Cuatro Vientos",
    "gn:cc2":"CO",
    "gn:country_code":"CO",
    "gn:dem":8,
    "gn:feature_class":"P",
    "gn:feature_code":"PPL",
    "gn:name":"Cuatro Vientos",
    "gn:population":0,
    "gn:timezone":"America/Bogota",
    "iso:country":"CO",
    "name:cat_x_preferred":[
        "Cuatro Vientos"
    ],
    "name:eus_x_preferred":[
        "Cuatro Vientos"
    ],
    "name:por_x_preferred":[
        "Cuatro Vientos"
    ],
    "name:spa_x_preferred":[
        "Cuatro Vientos"
    ],
    "name:und_x_variant":[
        "Caser\u00edo Cuatro Vientos"
    ],
    "wof:name":"Cuatro Vientos",
    "wof:placetype":"locality"
},
  "geometry": {"coordinates":[-74.78889000000002,9.70889],"type":"Point"}
}