{
  "type": "Feature",
  "properties": {
    "gn:admin1_code":"16.0",
    "gn:admin2_code":"41078.0",
    "gn:asciiname":"El Totumo",
    "gn:country_code":"CO",
    "gn:dem":1054,
    "gn:feature_class":"P",
    "gn:feature_code":"PPL",
    "gn:name":"El Totumo",
    "gn:population":0,
    "gn:timezone":"America/Bogota",
    "iso:country":"CO",
    "name:ces_x_preferred":[
        "El Totumo"
    ],
    "name:fas_x_preferred":[
        "\u0627\u0644 \u062a\u0648\u062a\u0648\u0645\u0648"
    ],
    "name:kor_x_preferred":[
        "\uc5d8\ud1a0\ud22c\ubaa8\uc0b0"
    ],
    "name:nld_x_preferred":[
        "El Totumo"
    ],
    "name:por_x_preferred":[
        "El Totumo"
    ],
    "name:spa_x_preferred":[
        "El Totumo"
    ],
    "name:spa_x_variant":[
        "Volc\u00e1n del Totumo"
    ],
    "name:zho_x_preferred":[
        "\u57c3\u723e\u6258\u5716\u83ab\u706b\u5c71"
    ],
    "wof:name":"El Totumo",
    "wof:placetype":"locality"
},
  "geometry": {"coordinates":[-75.00055999999999,3.17472],"type":"Point"}
}