{
  "type": "Feature",
  "properties": {
    "gn:admin1_code":"9",
    "gn:admin2_code":"19473.0",
    "gn:asciiname":"Chirriadero",
    "gn:country_code":"CO",
    "gn:dem":1436,
    "gn:feature_class":"P",
    "gn:feature_code":"PPL",
    "gn:name":"Chirriadero",
    "gn:population":0,
    "gn:timezone":"America/Bogota",
    "iso:country":"CO",
    "wof:name":"Chirriadero",
    "wof:placetype":"locality"
},
  "geometry": {"coordinates":[-76.77413,2.82211],"type":"Point"}
}