{
  "type": "Feature",
  "properties": {
    "gn:admin1_code":"33.0",
    "gn:admin2_code":"25817.0",
    "gn:asciiname":"Villa Diana",
    "gn:country_code":"CO",
    "gn:dem":2568,
    "gn:feature_class":"P",
    "gn:feature_code":"PPL",
    "gn:name":"Villa Diana",
    "gn:population":0,
    "gn:timezone":"America/Bogota",
    "iso:country":"CO",
    "wof:name":"Villa Diana",
    "wof:placetype":"locality"
},
  "geometry": {"coordinates":[-73.92054,4.98759],"type":"Point"}
}