{
  "type": "Feature",
  "properties": {
    "gn:admin1_code":"20.0",
    "gn:admin2_code":"52250.0",
    "gn:asciiname":"Perolindo",
    "gn:country_code":"CO",
    "gn:dem":26,
    "gn:feature_class":"P",
    "gn:feature_code":"PPL",
    "gn:name":"Perolindo",
    "gn:population":0,
    "gn:timezone":"America/Bogota",
    "iso:country":"CO",
    "wof:name":"Perolindo",
    "wof:placetype":"locality"
},
  "geometry": {"coordinates":[-78.08071,2.26398],"type":"Point"}
}