{
  "type": "Feature",
  "properties": {
    "gn:admin1_code":"32",
    "gn:admin2_code":"85410.0",
    "gn:asciiname":"Moriche",
    "gn:country_code":"CO",
    "gn:dem":204,
    "gn:feature_class":"P",
    "gn:feature_code":"PPL",
    "gn:name":"Moriche",
    "gn:population":0,
    "gn:timezone":"America/Bogota",
    "iso:country":"CO",
    "wof:name":"Moriche",
    "wof:placetype":"locality"
},
  "geometry": {"coordinates":[-72.58143000000003,4.84444],"type":"Point"}
}