{
  "type": "Feature",
  "properties": {
    "gn:admin1_code":"1.0",
    "gn:asciiname":"Renaldo Rivadeneira",
    "gn:country_code":"CO",
    "gn:dem":187,
    "gn:feature_class":"P",
    "gn:feature_code":"PPL",
    "gn:name":"Renaldo Rivadeneira",
    "gn:population":0,
    "gn:timezone":"America/Bogota",
    "iso:country":"CO",
    "wof:name":"Renaldo Rivadeneira",
    "wof:placetype":"locality"
},
  "geometry": {"coordinates":[-74.39429,0.61582],"type":"Point"}
}