{
  "type": "Feature",
  "properties": {
    "gn:admin1_code":"12",
    "gn:admin2_code":"23555.0",
    "gn:asciiname":"Las Empanadas",
    "gn:country_code":"CO",
    "gn:dem":60,
    "gn:feature_class":"P",
    "gn:feature_code":"PPL",
    "gn:name":"Las Empanadas",
    "gn:population":0,
    "gn:timezone":"America/Bogota",
    "iso:country":"CO",
    "wof:name":"Las Empanadas",
    "wof:placetype":"locality"
},
  "geometry": {"coordinates":[-75.44455000000001,8.35503],"type":"Point"}
}