{
  "type": "Feature",
  "properties": {
    "iso:country":"CO",
    "name:ceb_x_preferred":[
        "Nari\u00f1o"
    ],
    "name:chi_x_preferred":[
        "\u7d0d\u91cc\u5c3c\u5967"
    ],
    "name:dut_x_preferred":[
        "Nari\u00f1o"
    ],
    "name:eng_x_preferred":[
        "Nari\u00f1o"
    ],
    "name:fra_x_preferred":[
        "Nari\u00f1o"
    ],
    "name:fre_x_preferred":[
        "Nari\u00f1o"
    ],
    "name:geo_x_preferred":[
        "\u10dc\u10d0\u10e0\u10d8\u10dc\u10d8\u10dd"
    ],
    "name:ile_x_preferred":[
        "Nari\u00f1o"
    ],
    "name:ita_x_preferred":[
        "Nari\u00f1o"
    ],
    "name:kat_x_preferred":[
        "\u10dc\u10d0\u10e0\u10d8\u10dc\u10d8\u10dd"
    ],
    "name:may_x_preferred":[
        "Nari\u00f1o"
    ],
    "name:msa_x_preferred":[
        "Nari\u00f1o"
    ],
    "name:nan_x_preferred":[
        "Nari\u00f1o"
    ],
    "name:nld_x_preferred":[
        "Nari\u00f1o"
    ],
    "name:por_x_preferred":[
        "Nari\u00f1o"
    ],
    "name:rus_x_preferred":[
        "\u041d\u0430\u0440\u0438\u043d\u044c\u043e"
    ],
    "name:sco_x_preferred":[
        "Nari\u00f1o"
    ],
    "name:spa_x_preferred":[
        "Nari\u00f1o"
    ],
    "name:swe_x_preferred":[
        "Nari\u00f1o"
    ],
    "name:tgl_x_preferred":[
        "Nari\u00f1o"
    ],
    "name:vie_x_preferred":[
        "Nari\u00f1o"
    ],
    "name:war_x_preferred":[
        "Nari\u00f1o"
    ],
    "qs:gn_country":"CO",
    "qs:gn_fcode":"PPL",
    "qs:gn_pop":3186,
    "qs:name":"Nari\u00f1o",
    "qs:name_adm0":"Colombia",
    "qs:name_adm1":"Antioquia",
    "qs:photos":0,
    "qs:photos_1k":0,
    "qs:photos_9k":0,
    "qs:photos_9r":0,
    "qs:photos_all":0,
    "qs:photos_sr":0,
    "qs:placetype":"Town",
    "qs:pop_sr":"4",
    "qs:woe_adm0":23424787,
    "wd:wordcount":38,
    "wof:name":"Nari\u00f1o",
    "wof:placetype":"locality",
    "wof:population":3186
},
  "geometry": {"coordinates":[-75.17655999999999,5.60893],"type":"Point"}
}