{
  "type": "Feature",
  "properties": {
    "gn:admin1_code":"9",
    "gn:admin2_code":"19001.0",
    "gn:asciiname":"El Uvo",
    "gn:country_code":"CO",
    "gn:dem":1645,
    "gn:feature_class":"P",
    "gn:feature_code":"PPL",
    "gn:name":"El Uvo",
    "gn:population":0,
    "gn:timezone":"America/Bogota",
    "iso:country":"CO",
    "wof:name":"El Uvo",
    "wof:placetype":"locality"
},
  "geometry": {"coordinates":[-76.72256999999998,2.54779],"type":"Point"}
}