{
  "type": "Feature",
  "properties": {
    "gn:admin1_code":"29",
    "gn:admin2_code":"76111.0",
    "gn:asciiname":"La Aurora",
    "gn:country_code":"CO",
    "gn:dem":3109,
    "gn:feature_class":"P",
    "gn:feature_code":"PPL",
    "gn:name":"La Aurora",
    "gn:population":0,
    "gn:timezone":"America/Bogota",
    "iso:country":"CO",
    "name:ceb_x_preferred":[
        "La Aurora"
    ],
    "name:deu_x_preferred":[
        "La Aurora"
    ],
    "name:glg_x_preferred":[
        "La Aurora"
    ],
    "name:rus_x_preferred":[
        "\u041b\u0430-\u0410\u0443\u0440\u043e\u0440\u0430"
    ],
    "name:spa_x_preferred":[
        "La Aurora"
    ],
    "name:srp_x_preferred":[
        "\u041b\u0430 \u0410\u0443\u0440\u043e\u0440\u0430"
    ],
    "name:swe_x_preferred":[
        "La Aurora"
    ],
    "wof:name":"La Aurora",
    "wof:placetype":"locality"
},
  "geometry": {"coordinates":[-76.03667,3.84861],"type":"Point"}
}