{
  "type": "Feature",
  "properties": {
    "gn:admin1_code":"32.0",
    "gn:admin2_code":"85139.0",
    "gn:asciiname":"Pupure",
    "gn:country_code":"CO",
    "gn:dem":140,
    "gn:feature_class":"P",
    "gn:feature_code":"PPL",
    "gn:name":"Pupure",
    "gn:population":0,
    "gn:timezone":"America/Bogota",
    "iso:country":"CO",
    "wof:name":"Pupure",
    "wof:placetype":"locality"
},
  "geometry": {"coordinates":[-71.98333000000002,4.41667],"type":"Point"}
}