{
  "type": "Feature",
  "properties": {
    "gn:admin1_code":"10",
    "gn:admin2_code":"20060.0",
    "gn:asciiname":"La Luna",
    "gn:country_code":"CO",
    "gn:dem":60,
    "gn:feature_class":"P",
    "gn:feature_code":"PPL",
    "gn:name":"La Luna",
    "gn:population":0,
    "gn:timezone":"America/Bogota",
    "iso:country":"CO",
    "name:ceb_x_preferred":[
        "La Luna"
    ],
    "name:deu_x_preferred":[
        "La Luna"
    ],
    "name:fra_x_preferred":[
        "La Luna"
    ],
    "name:ita_x_preferred":[
        "La luna"
    ],
    "name:nld_x_preferred":[
        "La Luna"
    ],
    "name:srp_x_preferred":[
        "\u041b\u0430 \u041b\u0443\u043d\u0430"
    ],
    "name:swe_x_preferred":[
        "La Luna"
    ],
    "name:uzb_x_preferred":[
        "La Luna"
    ],
    "wof:name":"La Luna",
    "wof:placetype":"locality"
},
  "geometry": {"coordinates":[-73.79978,9.90275],"type":"Point"}
}