{
  "type": "Feature",
  "properties": {
    "gn:admin1_code":"10",
    "gn:admin2_code":"20060.0",
    "gn:asciiname":"La Luna",
    "gn:country_code":"CO",
    "gn:dem":60,
    "gn:feature_class":"P",
    "gn:feature_code":"PPL",
    "gn:name":"La Luna",
    "gn:population":0,
    "gn:timezone":"America/Bogota",
    "iso:country":"CO",
    "wof:name":"La Luna",
    "wof:placetype":"locality"
},
  "geometry": {"coordinates":[-73.79978,9.90275],"type":"Point"}
}