{
  "type": "Feature",
  "properties": {
    "gn:admin1_code":"22.0",
    "gn:admin2_code":"86573.0",
    "gn:asciiname":"Puerto Antonio",
    "gn:country_code":"CO",
    "gn:dem":222,
    "gn:feature_class":"P",
    "gn:feature_code":"PPL",
    "gn:name":"Puerto Antonio",
    "gn:population":0,
    "gn:timezone":"America/Bogota",
    "iso:country":"CO",
    "wof:name":"Puerto Antonio",
    "wof:placetype":"locality"
},
  "geometry": {"coordinates":[-75.38464,0.30313],"type":"Point"}
}