{
  "type": "Feature",
  "properties": {
    "gn:admin1_code":"4.0",
    "gn:asciiname":"Cedron",
    "gn:country_code":"CO",
    "gn:dem":253,
    "gn:feature_class":"P",
    "gn:feature_code":"PPL",
    "gn:name":"Cedr\u00f3n",
    "gn:population":0,
    "gn:timezone":"America/Bogota",
    "iso:country":"CO",
    "wof:name":"Cedron",
    "wof:placetype":"locality"
},
  "geometry": {"coordinates":[-75.23444000000001,10.49139],"type":"Point"}
}