{
  "type": "Feature",
  "properties": {
    "gn:admin1_code":"32",
    "gn:admin2_code":"85410.0",
    "gn:asciiname":"La Ibaguerena",
    "gn:country_code":"CO",
    "gn:dem":191,
    "gn:feature_class":"P",
    "gn:feature_code":"PPL",
    "gn:name":"La Ibaguere\u00f1a",
    "gn:population":0,
    "gn:timezone":"America/Bogota",
    "iso:country":"CO",
    "wof:name":"La Ibaguerena",
    "wof:placetype":"locality"
},
  "geometry": {"coordinates":[-72.7236,4.65686],"type":"Point"}
}