{
  "type": "Feature",
  "properties": {
    "gn:admin1_code":"26.0",
    "gn:admin2_code":"68081.0",
    "gn:asciiname":"Puerto Central",
    "gn:country_code":"CO",
    "gn:dem":75,
    "gn:feature_class":"P",
    "gn:feature_code":"PPL",
    "gn:name":"Puerto Central",
    "gn:population":0,
    "gn:timezone":"America/Bogota",
    "iso:country":"CO",
    "wof:name":"Puerto Central",
    "wof:placetype":"locality"
},
  "geometry": {"coordinates":[-73.74746,7.0502],"type":"Point"}
}