{
  "type": "Feature",
  "properties": {
    "gn:admin1_code":"26",
    "gn:admin2_code":"68773.0",
    "gn:asciiname":"La Curva",
    "gn:country_code":"CO",
    "gn:dem":2704,
    "gn:feature_class":"P",
    "gn:feature_code":"PPL",
    "gn:name":"La Curva",
    "gn:population":0,
    "gn:timezone":"America/Bogota",
    "iso:country":"CO",
    "wof:name":"La Curva",
    "wof:placetype":"locality"
},
  "geometry": {"coordinates":[-73.88516,5.88321],"type":"Point"}
}