{
  "type": "Feature",
  "properties": {
    "gn:admin1_code":"22.0",
    "gn:admin2_code":"86001.0",
    "gn:asciiname":"Nueva La Tolda",
    "gn:country_code":"CO",
    "gn:dem":797,
    "gn:feature_class":"P",
    "gn:feature_code":"PPL",
    "gn:name":"Nueva La Tolda",
    "gn:population":0,
    "gn:timezone":"America/Bogota",
    "iso:country":"CO",
    "name:spa_x_preferred":[
        "Nueva La Tolda"
    ],
    "wof:name":"Nueva La Tolda",
    "wof:placetype":"locality"
},
  "geometry": {"coordinates":[-76.62539,1.21975],"type":"Point"}
}