{
  "type": "Feature",
  "properties": {
    "gn:admin1_code":"9.0",
    "gn:admin2_code":"19455.0",
    "gn:asciiname":"Guatemala",
    "gn:country_code":"CO",
    "gn:dem":1084,
    "gn:feature_class":"P",
    "gn:feature_code":"PPL",
    "gn:name":"Guatemala",
    "gn:population":0,
    "gn:timezone":"America/Bogota",
    "iso:country":"CO",
    "name:spa_x_preferred":[
        "Guatemala"
    ],
    "wof:name":"Guatemala",
    "wof:placetype":"locality"
},
  "geometry": {"coordinates":[-76.23083000000003,3.23386],"type":"Point"}
}