{
  "type": "Feature",
  "properties": {
    "gn:admin1_code":"15",
    "gn:admin2_code":"94885.0",
    "gn:asciiname":"Galilea",
    "gn:country_code":"CO",
    "gn:dem":83,
    "gn:feature_class":"P",
    "gn:feature_code":"PPL",
    "gn:name":"Galilea",
    "gn:population":0,
    "gn:timezone":"America/Bogota",
    "iso:country":"CO",
    "wof:name":"Galilea",
    "wof:placetype":"locality"
},
  "geometry": {"coordinates":[-66.96339,1.63184],"type":"Point"}
}