{
  "type": "Feature",
  "properties": {
    "gn:admin1_code":"21",
    "gn:admin2_code":"54001.0",
    "gn:asciiname":"Alcala",
    "gn:cc2":"CO",
    "gn:country_code":"CO",
    "gn:dem":227,
    "gn:feature_class":"P",
    "gn:feature_code":"PPL",
    "gn:name":"Alcal\u00e1",
    "gn:population":0,
    "gn:timezone":"America/Bogota",
    "iso:country":"CO",
    "name:und_x_variant":[
        "Aical\u00e1",
        "Alcal\u00e1"
    ],
    "wof:name":"Alcala",
    "wof:placetype":"locality"
},
  "geometry": {"coordinates":[-72.38333,8.09139],"type":"Point"}
}