{
  "type": "Feature",
  "properties": {
    "gn:admin1_code":"2",
    "gn:admin2_code":"5887.0",
    "gn:asciiname":"Carolina",
    "gn:country_code":"CO",
    "gn:dem":985,
    "gn:feature_class":"P",
    "gn:feature_code":"PPL",
    "gn:name":"Carolina",
    "gn:population":0,
    "gn:timezone":"America/Bogota",
    "iso:country":"CO",
    "wof:name":"Carolina",
    "wof:placetype":"locality"
},
  "geometry": {"coordinates":[-75.38916999999999,7.10611],"type":"Point"}
}