{
  "type": "Feature",
  "properties": {
    "gn:admin1_code":"2",
    "gn:admin2_code":"5887.0",
    "gn:asciiname":"Carolina",
    "gn:country_code":"CO",
    "gn:dem":985,
    "gn:feature_class":"P",
    "gn:feature_code":"PPL",
    "gn:name":"Carolina",
    "gn:population":0,
    "gn:timezone":"America/Bogota",
    "iso:country":"CO",
    "name:bel_x_preferred":[
        "\u041a\u0430\u0440\u0430\u043b\u0456\u043d\u0430"
    ],
    "name:bre_x_preferred":[
        "Carolina"
    ],
    "name:cat_x_preferred":[
        "Carolina"
    ],
    "name:ceb_x_preferred":[
        "Carolina"
    ],
    "name:cym_x_preferred":[
        "Carolina"
    ],
    "name:deu_x_preferred":[
        "Carolina"
    ],
    "name:ell_x_preferred":[
        "\u039a\u03b1\u03c1\u03bf\u03bb\u03af\u03bd\u03b1"
    ],
    "name:fas_x_preferred":[
        "\u06a9\u0627\u0631\u0648\u0644\u06cc\u0646\u0627"
    ],
    "name:fin_x_preferred":[
        "Carolina"
    ],
    "name:fra_x_preferred":[
        "Carolina"
    ],
    "name:glg_x_preferred":[
        "Carolina"
    ],
    "name:heb_x_preferred":[
        "\u05e7\u05e8\u05d5\u05dc\u05d9\u05d9\u05e0\u05d4"
    ],
    "name:hun_x_preferred":[
        "Carolina"
    ],
    "name:ind_x_preferred":[
        "Carolina"
    ],
    "name:ita_x_preferred":[
        "Carolina"
    ],
    "name:jpn_x_preferred":[
        "\u30ab\u30ed\u30e9\u30a4\u30ca"
    ],
    "name:kor_x_preferred":[
        "\uce90\ub864\ub77c\uc774\ub098"
    ],
    "name:lat_x_preferred":[
        "Carolina"
    ],
    "name:nds_x_preferred":[
        "Carolina"
    ],
    "name:nld_x_preferred":[
        "Carolina"
    ],
    "name:nor_x_preferred":[
        "Carolina"
    ],
    "name:pol_x_preferred":[
        "Carolina"
    ],
    "name:por_x_preferred":[
        "Carolina"
    ],
    "name:ron_x_preferred":[
        "Carolina"
    ],
    "name:rus_x_preferred":[
        "\u041a\u0430\u0440\u043e\u043b\u0438\u043d\u0430"
    ],
    "name:sco_x_preferred":[
        "Carolina"
    ],
    "name:spa_x_preferred":[
        "Carolina"
    ],
    "name:srp_x_preferred":[
        "\u041a\u0430\u0440\u043e\u043b\u0430\u0458\u043d\u0430"
    ],
    "name:swe_x_preferred":[
        "Carolina"
    ],
    "name:ukr_x_preferred":[
        "\u041a\u0430\u0440\u043e\u043b\u0456\u043d\u0430"
    ],
    "name:vie_x_preferred":[
        "Carolina"
    ],
    "name:vol_x_preferred":[
        "Carolina"
    ],
    "name:zho_x_preferred":[
        "Carolina"
    ],
    "wof:name":"Carolina",
    "wof:placetype":"locality"
},
  "geometry": {"coordinates":[-75.38916999999999,7.10611],"type":"Point"}
}