{
  "type": "Feature",
  "properties": {
    "gn:admin1_code":"28",
    "gn:admin2_code":"73275.0",
    "gn:asciiname":"Guayacana",
    "gn:country_code":"CO",
    "gn:dem":286,
    "gn:feature_class":"P",
    "gn:feature_code":"PPL",
    "gn:name":"Guayacana",
    "gn:population":0,
    "gn:timezone":"America/Bogota",
    "iso:country":"CO",
    "wof:name":"Guayacana",
    "wof:placetype":"locality"
},
  "geometry": {"coordinates":[-74.81341,4.2234],"type":"Point"}
}