{
  "type": "Feature",
  "properties": {
    "gn:admin1_code":"2.0",
    "gn:admin2_code":"5266.0",
    "gn:asciiname":"La Rochela",
    "gn:country_code":"CO",
    "gn:dem":2558,
    "gn:feature_class":"P",
    "gn:feature_code":"PPL",
    "gn:name":"La Rochela",
    "gn:population":0,
    "gn:timezone":"America/Bogota",
    "iso:country":"CO",
    "name:spa_x_preferred":[
        "La Rochela"
    ],
    "wof:name":"La Rochela",
    "wof:placetype":"locality"
},
  "geometry": {"coordinates":[-75.52933,6.17366],"type":"Point"}
}