{
  "type": "Feature",
  "properties": {
    "gn:admin1_code":"2.0",
    "gn:admin2_code":"5045.0",
    "gn:asciiname":"Tumba",
    "gn:cc2":"CO",
    "gn:country_code":"CO",
    "gn:dem":29,
    "gn:feature_class":"P",
    "gn:feature_code":"PPL",
    "gn:name":"Tumba",
    "gn:population":0,
    "gn:timezone":"America/Bogota",
    "iso:country":"CO",
    "name:ceb_x_preferred":[
        "Tumba"
    ],
    "name:ces_x_preferred":[
        "Tumba"
    ],
    "name:deu_x_preferred":[
        "Tumba"
    ],
    "name:fin_x_preferred":[
        "Tumba"
    ],
    "name:fra_x_preferred":[
        "Tumba"
    ],
    "name:hrv_x_preferred":[
        "Tumba"
    ],
    "name:ita_x_preferred":[
        "Tumba"
    ],
    "name:lat_x_preferred":[
        "Tumba"
    ],
    "name:lav_x_preferred":[
        "Tumba"
    ],
    "name:nld_x_preferred":[
        "Tumba"
    ],
    "name:pol_x_preferred":[
        "Tumba"
    ],
    "name:slk_x_preferred":[
        "Tumba"
    ],
    "name:swe_x_preferred":[
        "Tumba"
    ],
    "name:und_x_variant":[
        "El Tambo"
    ],
    "wof:name":"Tumba",
    "wof:placetype":"locality"
},
  "geometry": {"coordinates":[-76.63333,7.88333],"type":"Point"}
}