{
  "type": "Feature",
  "properties": {
    "iso:country":"CO",
    "name:ara_x_preferred":[
        "\u0643\u0627\u0632\u0627\u0645\u064a\u0644\u0627"
    ],
    "name:aze_x_preferred":[
        "Kasa Mila"
    ],
    "name:cat_x_preferred":[
        "Casa Mil\u00e0"
    ],
    "name:ces_x_preferred":[
        "Casa Mil\u00e0"
    ],
    "name:deu_x_preferred":[
        "Casa Mil\u00e0"
    ],
    "name:ell_x_preferred":[
        "\u039a\u03ac\u03b6\u03b1 \u039c\u03b9\u03bb\u03ac"
    ],
    "name:epo_x_preferred":[
        "Casa Mil\u00e0"
    ],
    "name:eus_x_preferred":[
        "Mil\u00e0 Etxea"
    ],
    "name:fas_x_preferred":[
        "\u06a9\u0627\u0632\u0627 \u0645\u06cc\u0644\u0627"
    ],
    "name:spa_x_preferred":[
        "La Pedrera",
        "Casa Mil\u00e0"
    ],
    "name:unk_x_variant":[
        "La Pedrera"
    ],
    "qs:gn_adm0_cc":"CO",
    "qs:gn_fcode":"PPLX",
    "qs:gn_local":8051263,
    "qs:gn_nam_loc":"santa marta",
    "qs:gn_namadm1":"38",
    "qs:gn_name":"La Pedrera",
    "qs:local_max":2404,
    "qs:local_sum":4136,
    "qs:localhoods":6,
    "qs:name":"La Pedrera",
    "qs:name_adm0":"Colombia",
    "qs:name_adm1":"Magdalena",
    "qs:name_adm2":"Santa Marta",
    "qs:name_local":"Santa Marta",
    "qs:photo_max":424,
    "qs:photo_sum":426,
    "qs:placetype":"Suburb",
    "qs:quad_count":3,
    "qs:woe_adm0":23424787,
    "qs:woe_adm1":2345063,
    "qs:woe_adm2":26797230,
    "qs:woe_lau":0,
    "qs:woe_local":368170,
    "qs:woe_ver":"7.10.0",
    "wof:lang":[
        "spa"
    ],
    "wof:name":"La Pedrera",
    "wof:placetype":"neighbourhood"
},
  "geometry": {"coordinates":[-74.18930899999999,11.249777],"type":"Point"}
}