{
  "type": "Feature",
  "properties": {
    "gn:admin1_code":"17.0",
    "gn:admin2_code":"44847.0",
    "gn:asciiname":"Tumamana",
    "gn:country_code":"CO",
    "gn:dem":85,
    "gn:feature_class":"P",
    "gn:feature_code":"PPL",
    "gn:name":"Tumamana",
    "gn:population":0,
    "gn:timezone":"America/Bogota",
    "iso:country":"CO",
    "name:und_x_variant":[
        "Tumamanana"
    ],
    "wof:name":"Tumamana",
    "wof:placetype":"locality"
},
  "geometry": {"coordinates":[-71.71691,12.23138],"type":"Point"}
}