{
  "type": "Feature",
  "properties": {
    "gn:admin1_code":"29",
    "gn:admin2_code":"76828.0",
    "gn:asciiname":"El Tabor",
    "gn:cc2":"CO",
    "gn:country_code":"CO",
    "gn:dem":2031,
    "gn:feature_class":"P",
    "gn:feature_code":"PPL",
    "gn:name":"El Tabor",
    "gn:population":0,
    "gn:timezone":"America/Bogota",
    "iso:country":"CO",
    "name:und_x_variant":[
        "Tabor",
        "El Tabor"
    ],
    "wof:name":"El Tabor",
    "wof:placetype":"locality"
},
  "geometry": {"coordinates":[-76.34444000000001,4.24722],"type":"Point"}
}