{
  "type": "Feature",
  "properties": {
    "gn:admin1_code":"33.0",
    "gn:admin2_code":"25488.0",
    "gn:asciiname":"Pisilago",
    "gn:country_code":"CO",
    "gn:dem":390,
    "gn:feature_class":"P",
    "gn:feature_code":"PPL",
    "gn:name":"Pisilago",
    "gn:population":0,
    "gn:timezone":"America/Bogota",
    "iso:country":"CO",
    "name:spa_x_preferred":[
        "Pisilago"
    ],
    "wof:name":"Pisilago",
    "wof:placetype":"locality"
},
  "geometry": {"coordinates":[-74.67456,4.21758],"type":"Point"}
}