{
  "type": "Feature",
  "properties": {
    "gn:admin1_code":"29.0",
    "gn:admin2_code":"76020.0",
    "gn:asciiname":"La Estrella",
    "gn:country_code":"CO",
    "gn:dem":1182,
    "gn:feature_class":"P",
    "gn:feature_code":"PPL",
    "gn:name":"La Estrella",
    "gn:population":0,
    "gn:timezone":"America/Bogota",
    "iso:country":"CO",
    "wof:name":"La Estrella",
    "wof:placetype":"locality"
},
  "geometry": {"coordinates":[-75.82361,4.69028],"type":"Point"}
}