{
  "type": "Feature",
  "properties": {
    "gn:admin1_code":"29",
    "gn:admin2_code":"76109.0",
    "gn:asciiname":"El Guineo",
    "gn:cc2":"CO",
    "gn:country_code":"CO",
    "gn:dem":21,
    "gn:feature_class":"P",
    "gn:feature_code":"PPL",
    "gn:name":"El Guineo",
    "gn:population":0,
    "gn:timezone":"America/Bogota",
    "iso:country":"CO",
    "name:und_x_variant":[
        "Guineo",
        "El Guineo"
    ],
    "wof:name":"El Guineo",
    "wof:placetype":"locality"
},
  "geometry": {"coordinates":[-77.05,4.06667],"type":"Point"}
}