{
  "type": "Feature",
  "properties": {
    "gn:admin1_code":"27.0",
    "gn:admin2_code":"70204.0",
    "gn:asciiname":"Villa Maria",
    "gn:country_code":"CO",
    "gn:dem":124,
    "gn:feature_class":"P",
    "gn:feature_code":"PPL",
    "gn:name":"Villa Mar\u00eda",
    "gn:population":0,
    "gn:timezone":"America/Bogota",
    "iso:country":"CO",
    "wof:name":"Villa Maria",
    "wof:placetype":"locality"
},
  "geometry": {"coordinates":[-75.38499,9.45931],"type":"Point"}
}