{
  "type": "Feature",
  "properties": {
    "gn:country":"CO",
    "gn:fcode":"PPL",
    "gn:pop":2007,
    "iso:country":"CO",
    "name:ast_x_preferred":[
        "T\u00e1mara"
    ],
    "name:ceb_x_preferred":[
        "Tamara"
    ],
    "name:eng_x_preferred":[
        "Tamara"
    ],
    "name:fra_x_preferred":[
        "T\u00e1mara"
    ],
    "name:ita_x_preferred":[
        "T\u00e1mara"
    ],
    "name:kat_x_preferred":[
        "\u10e2\u10d0\u10db\u10d0\u10e0\u10d0"
    ],
    "name:msa_x_preferred":[
        "Tamara"
    ],
    "name:nan_x_preferred":[
        "T\u00e1mara"
    ],
    "name:nld_x_preferred":[
        "T\u00e1mara"
    ],
    "name:por_x_preferred":[
        "Tamara"
    ],
    "name:rus_x_preferred":[
        "\u0422\u0430\u043c\u0430\u0440\u0430"
    ],
    "name:spa_x_preferred":[
        "T\u00e1mara"
    ],
    "name:swe_x_preferred":[
        "Tamara"
    ],
    "name:tgl_x_preferred":[
        "Tamara"
    ],
    "name:vie_x_preferred":[
        "T\u00e1mara"
    ],
    "name:war_x_preferred":[
        "Tamara"
    ],
    "name:zho_x_preferred":[
        "\u5854\u99ac\u62c9"
    ],
    "qs:name":"Tamara",
    "qs:photos_9r":0,
    "qs:photos_sr":0,
    "qs:pop_sr":"4",
    "wd:wordcount":90,
    "wof:name":"Tamara",
    "wof:placetype":"locality",
    "wof:population":2007
},
  "geometry": {"coordinates":[-72.16333,5.82972],"type":"Point"}
}