{
  "type": "Feature",
  "properties": {
    "gn:admin1_code":"37.0",
    "gn:admin2_code":"17614.0",
    "gn:asciiname":"La Palermo",
    "gn:country_code":"CO",
    "gn:dem":2423,
    "gn:feature_class":"P",
    "gn:feature_code":"PPL",
    "gn:name":"La Palermo",
    "gn:population":0,
    "gn:timezone":"America/Bogota",
    "iso:country":"CO",
    "wof:name":"La Palermo",
    "wof:placetype":"locality"
},
  "geometry": {"coordinates":[-75.80741999999999,5.44763],"type":"Point"}
}