{
  "type": "Feature",
  "properties": {
    "gn:admin1_code":"12",
    "gn:admin2_code":"23068.0",
    "gn:asciiname":"El Totumo",
    "gn:country_code":"CO",
    "gn:dem":18,
    "gn:feature_class":"P",
    "gn:feature_code":"PPL",
    "gn:name":"El Totumo",
    "gn:population":0,
    "gn:timezone":"America/Bogota",
    "iso:country":"CO",
    "wof:name":"El Totumo",
    "wof:placetype":"locality"
},
  "geometry": {"coordinates":[-74.93333,8.41667],"type":"Point"}
}