{
  "type": "Feature",
  "properties": {
    "gn:admin1_code":"26",
    "gn:admin2_code":"68861.0",
    "gn:asciiname":"Portachuelo",
    "gn:country_code":"CO",
    "gn:dem":1906,
    "gn:feature_class":"P",
    "gn:feature_code":"PPL",
    "gn:name":"Portachuelo",
    "gn:population":0,
    "gn:timezone":"America/Bogota",
    "iso:country":"CO",
    "wof:name":"Portachuelo",
    "wof:placetype":"locality"
},
  "geometry": {"coordinates":[-73.66734,5.95462],"type":"Point"}
}