{
  "type": "Feature",
  "properties": {
    "gn:admin1_code":"28",
    "gn:admin2_code":"73547.0",
    "gn:asciiname":"Colombia",
    "gn:country_code":"CO",
    "gn:dem":637,
    "gn:feature_class":"P",
    "gn:feature_code":"PPL",
    "gn:name":"Colombia",
    "gn:population":0,
    "gn:timezone":"America/Bogota",
    "iso:country":"CO",
    "wof:name":"Colombia",
    "wof:placetype":"locality"
},
  "geometry": {"coordinates":[-74.97771,4.37836],"type":"Point"}
}