{
  "type": "Feature",
  "properties": {
    "gn:admin1_code":"8",
    "gn:admin2_code":"18610.0",
    "gn:asciiname":"Marquetalia",
    "gn:country_code":"CO",
    "gn:dem":272,
    "gn:feature_class":"P",
    "gn:feature_code":"PPL",
    "gn:name":"Marquetalia",
    "gn:population":0,
    "gn:timezone":"America/Bogota",
    "iso:country":"CO",
    "name:ceb_x_preferred":[
        "Marquetalia"
    ],
    "name:sco_x_preferred":[
        "Marquetalia"
    ],
    "name:spa_x_preferred":[
        "Marquetalia"
    ],
    "name:swe_x_preferred":[
        "Marquetalia"
    ],
    "name:vie_x_preferred":[
        "Marquetalia"
    ],
    "wof:name":"Marquetalia",
    "wof:placetype":"locality"
},
  "geometry": {"coordinates":[-75.96878000000002,1.2713],"type":"Point"}
}