{
  "type": "Feature",
  "properties": {
    "gn:admin1_code":"20",
    "gn:admin2_code":"52381.0",
    "gn:asciiname":"Catauca",
    "gn:country_code":"CO",
    "gn:dem":2171,
    "gn:feature_class":"P",
    "gn:feature_code":"PPL",
    "gn:name":"Catauca",
    "gn:population":0,
    "gn:timezone":"America/Bogota",
    "iso:country":"CO",
    "wof:name":"Catauca",
    "wof:placetype":"locality"
},
  "geometry": {"coordinates":[-77.43333,1.36667],"type":"Point"}
}