{
  "type": "Feature",
  "properties": {
    "gn:admin1_code":"4",
    "gn:admin2_code":"8549.0",
    "gn:asciiname":"Cienaguita",
    "gn:country_code":"CO",
    "gn:dem":82,
    "gn:feature_class":"P",
    "gn:feature_code":"PPL",
    "gn:name":"Cienaguita",
    "gn:population":0,
    "gn:timezone":"America/Bogota",
    "iso:country":"CO",
    "wof:name":"Cienaguita",
    "wof:placetype":"locality"
},
  "geometry": {"coordinates":[-75.15000000000001,10.75],"type":"Point"}
}