{
  "type": "Feature",
  "properties": {
    "gn:admin1_code":"10",
    "gn:admin2_code":"20001.0",
    "gn:asciiname":"Bomba de Viento",
    "gn:country_code":"CO",
    "gn:dem":81,
    "gn:feature_class":"P",
    "gn:feature_code":"PPL",
    "gn:name":"Bomba de Viento",
    "gn:population":0,
    "gn:timezone":"America/Bogota",
    "iso:country":"CO",
    "wof:name":"Bomba de Viento",
    "wof:placetype":"locality"
},
  "geometry": {"coordinates":[-73.74398000000002,9.98618],"type":"Point"}
}