{
  "type": "Feature",
  "properties": {
    "gn:admin1_code":"16",
    "gn:admin2_code":"41357.0",
    "gn:asciiname":"Jamaica",
    "gn:country_code":"CO",
    "gn:dem":934,
    "gn:feature_class":"P",
    "gn:feature_code":"PPL",
    "gn:name":"Jamaica",
    "gn:population":0,
    "gn:timezone":"America/Bogota",
    "iso:country":"CO",
    "wof:name":"Jamaica",
    "wof:placetype":"locality"
},
  "geometry": {"coordinates":[-75.62276999999997,2.67434],"type":"Point"}
}