{
  "type": "Feature",
  "properties": {
    "gn:admin1_code":"29",
    "gn:admin2_code":"76111.0",
    "gn:asciiname":"Balsora",
    "gn:country_code":"CO",
    "gn:dem":2980,
    "gn:feature_class":"P",
    "gn:feature_code":"PPL",
    "gn:name":"Balsora",
    "gn:population":0,
    "gn:timezone":"America/Bogota",
    "iso:country":"CO",
    "wof:name":"Balsora",
    "wof:placetype":"locality"
},
  "geometry": {"coordinates":[-76.00861,3.83861],"type":"Point"}
}