{
  "type": "Feature",
  "properties": {
    "gn:admin1_code":"19.0",
    "gn:admin2_code":"50606.0",
    "gn:asciiname":"Salinas de Cumaral",
    "gn:cc2":"CO",
    "gn:country_code":"CO",
    "gn:dem":959,
    "gn:feature_class":"P",
    "gn:feature_code":"PPL",
    "gn:name":"Salinas de Cumaral",
    "gn:population":0,
    "gn:timezone":"America/Bogota",
    "iso:country":"CO",
    "name:und_x_variant":[
        "Salina de Up\u00edn",
        "Salinas de Cumaral"
    ],
    "wof:name":"Salinas de Cumaral",
    "wof:placetype":"locality"
},
  "geometry": {"coordinates":[-73.59999999999999,4.28333],"type":"Point"}
}