{
  "type": "Feature",
  "properties": {
    "gn:admin1_code":"21",
    "gn:admin2_code":"54001.0",
    "gn:asciiname":"Polo Norte",
    "gn:country_code":"CO",
    "gn:dem":217,
    "gn:feature_class":"P",
    "gn:feature_code":"PPL",
    "gn:name":"Polo Norte",
    "gn:population":0,
    "gn:timezone":"America/Bogota",
    "iso:country":"CO",
    "wof:name":"Polo Norte",
    "wof:placetype":"locality"
},
  "geometry": {"coordinates":[-72.37769,8.10574],"type":"Point"}
}