{
  "type": "Feature",
  "properties": {
    "gn:admin1_code":"19.0",
    "gn:admin2_code":"50689.0",
    "gn:asciiname":"Cumaral",
    "gn:country_code":"CO",
    "gn:dem":221,
    "gn:feature_class":"P",
    "gn:feature_code":"PPLL",
    "gn:name":"Cumaral",
    "gn:population":0,
    "gn:timezone":"America/Bogota",
    "iso:country":"CO",
    "name:spa_x_preferred":[
        "Cumaral"
    ],
    "wof:name":"Cumaral",
    "wof:placetype":"locality"
},
  "geometry": {"coordinates":[-73.25756,3.67388],"type":"Point"}
}