{
  "type": "Feature",
  "properties": {
    "gn:admin1_code":"17.0",
    "gn:admin2_code":"44847.0",
    "gn:asciiname":"Taiuachon",
    "gn:country_code":"CO",
    "gn:dem":49,
    "gn:feature_class":"P",
    "gn:feature_code":"PPL",
    "gn:name":"T\u00e1iuachon",
    "gn:population":0,
    "gn:timezone":"America/Bogota",
    "iso:country":"CO",
    "wof:name":"Taiuachon",
    "wof:placetype":"locality"
},
  "geometry": {"coordinates":[-72.15824000000001,11.78496],"type":"Point"}
}