{
  "type": "Feature",
  "properties": {
    "gn:admin1_code":"16",
    "gn:admin2_code":"41801.0",
    "gn:asciiname":"San Francisco",
    "gn:country_code":"CO",
    "gn:dem":1554,
    "gn:feature_class":"P",
    "gn:feature_code":"PPL",
    "gn:name":"San Francisco",
    "gn:population":0,
    "gn:timezone":"America/Bogota",
    "iso:country":"CO",
    "wof:name":"San Francisco",
    "wof:placetype":"locality"
},
  "geometry": {"coordinates":[-75.5956,2.77988],"type":"Point"}
}