{
  "type": "Feature",
  "properties": {
    "gn:admin1_code":"12",
    "gn:admin2_code":"23807.0",
    "gn:asciiname":"Manta Gordal",
    "gn:country_code":"CO",
    "gn:dem":62,
    "gn:feature_class":"P",
    "gn:feature_code":"PPL",
    "gn:name":"Manta Gordal",
    "gn:population":0,
    "gn:timezone":"America/Bogota",
    "iso:country":"CO",
    "wof:name":"Manta Gordal",
    "wof:placetype":"locality"
},
  "geometry": {"coordinates":[-75.82226999999997,8.22143],"type":"Point"}
}