{
  "type": "Feature",
  "properties": {
    "gn:admin1_code":"17",
    "gn:admin2_code":"44847.0",
    "gn:asciiname":"Castilletes",
    "gn:country_code":"CO",
    "gn:dem":-2,
    "gn:feature_class":"P",
    "gn:feature_code":"PPL",
    "gn:name":"Castilletes",
    "gn:population":0,
    "gn:timezone":"America/Bogota",
    "iso:country":"CO",
    "name:und_x_variant":[
        "Los Castilletes",
        "Castilletes"
    ],
    "wof:name":"Castilletes",
    "wof:placetype":"locality"
},
  "geometry": {"coordinates":[-71.32765000000001,11.84815],"type":"Point"}
}