{
  "type": "Feature",
  "properties": {
    "gn:admin1_code":"26",
    "gn:admin2_code":"68575.0",
    "gn:asciiname":"Badillo",
    "gn:country_code":"CO",
    "gn:dem":43,
    "gn:feature_class":"P",
    "gn:feature_code":"PPL",
    "gn:name":"Badillo",
    "gn:population":0,
    "gn:timezone":"America/Bogota",
    "iso:country":"CO",
    "name:und_x_variant":[
        "Corregimiento Badillo",
        "Badillo"
    ],
    "wof:name":"Badillo",
    "wof:placetype":"locality"
},
  "geometry": {"coordinates":[-73.8511,7.96903],"type":"Point"}
}