{
  "type": "Feature",
  "properties": {
    "gn:admin1_code":"28",
    "gn:admin2_code":"73616.0",
    "gn:asciiname":"El Venado",
    "gn:country_code":"CO",
    "gn:dem":2441,
    "gn:feature_class":"P",
    "gn:feature_code":"PPL",
    "gn:name":"El Venado",
    "gn:population":0,
    "gn:timezone":"America/Bogota",
    "iso:country":"CO",
    "wof:name":"El Venado",
    "wof:placetype":"locality"
},
  "geometry": {"coordinates":[-75.91833000000003,3.28417],"type":"Point"}
}