{
  "type": "Feature",
  "properties": {
    "iso:country":"CO",
    "name:deu_x_preferred":[
        "Las Nieves"
    ],
    "name:hbs_x_preferred":[
        "Las Nieves"
    ],
    "name:ita_x_preferred":[
        "Las Nieves"
    ],
    "name:nld_x_preferred":[
        "Las Nieves"
    ],
    "name:spa_x_preferred":[
        "Las Nieves"
    ],
    "qs:gn_country":"CO",
    "qs:gn_fcode":"PPLX",
    "qs:gn_pop":0,
    "qs:name":"Las Nieves",
    "qs:name_adm0":"Colombia",
    "qs:name_adm1":"Atlantico",
    "qs:photos":403,
    "qs:photos_1k":82,
    "qs:photos_9k":2,
    "qs:photos_9r":5,
    "qs:photos_all":403,
    "qs:photos_sr":6,
    "qs:placetype":"Suburb",
    "qs:pop_sr":"0",
    "qs:woe_adm0":23424787,
    "wof:name":"Las Nieves",
    "wof:placetype":"neighbourhood"
},
  "geometry": {"coordinates":[-74.78333000000001,10.95],"type":"Point"}
}