{
  "type": "Feature",
  "properties": {
    "gn:admin1_code":"9",
    "gn:admin2_code":"19418.0",
    "gn:asciiname":"Bugnavisia",
    "gn:country_code":"CO",
    "gn:dem":9,
    "gn:feature_class":"P",
    "gn:feature_code":"PPL",
    "gn:name":"Bugnavisia",
    "gn:population":0,
    "gn:timezone":"America/Bogota",
    "iso:country":"CO",
    "wof:name":"Bugnavisia",
    "wof:placetype":"locality"
},
  "geometry": {"coordinates":[-77.48318,2.99229],"type":"Point"}
}