{
  "type": "Feature",
  "properties": {
    "gn:admin1_code":"32.0",
    "gn:admin2_code":"85139.0",
    "gn:asciiname":"Valledupar",
    "gn:country_code":"CO",
    "gn:dem":188,
    "gn:feature_class":"P",
    "gn:feature_code":"PPL",
    "gn:name":"Valledupar",
    "gn:population":0,
    "gn:timezone":"America/Bogota",
    "iso:country":"CO",
    "name:ara_x_preferred":[
        "\u0641\u0627\u0644\u064a\u062f\u0648\u0628\u0627\u0631"
    ],
    "name:aze_x_preferred":[
        "Valyedupar"
    ],
    "name:bre_x_preferred":[
        "Valledupar"
    ],
    "name:bul_x_preferred":[
        "\u0412\u0430\u043b\u0435\u0434\u0443\u043f\u0430\u0440"
    ],
    "name:cat_x_preferred":[
        "Valledupar"
    ],
    "name:ceb_x_preferred":[
        "Valledupar"
    ],
    "name:ces_x_preferred":[
        "Valledupar"
    ],
    "name:dan_x_preferred":[
        "Valledupar"
    ],
    "name:deu_x_preferred":[
        "Valledupar"
    ],
    "name:epo_x_preferred":[
        "Valledupar"
    ],
    "name:eus_x_preferred":[
        "Valledupar"
    ],
    "name:fas_x_preferred":[
        "\u0648\u0627\u06cc\u06cc\u062f\u0648\u067e\u0627\u0631"
    ],
    "name:fin_x_preferred":[
        "Valledupar"
    ],
    "name:fra_x_preferred":[
        "Valledupar"
    ],
    "name:frr_x_preferred":[
        "Valledupar"
    ],
    "name:gla_x_preferred":[
        "Valledupar"
    ],
    "name:glg_x_preferred":[
        "Valledupar"
    ],
    "name:hun_x_preferred":[
        "Valledupar"
    ],
    "name:ind_x_preferred":[
        "Valledupar"
    ],
    "name:ita_x_preferred":[
        "Valledupar"
    ],
    "name:jpn_x_preferred":[
        "\u30d0\u30b8\u30a7\u30c9\u30a5\u30d1\u30eb"
    ],
    "name:kat_x_preferred":[
        "\u10d5\u10d0\u10da\u10d8\u10d4\u10d3\u10e3\u10de\u10d0\u10e0\u10d8"
    ],
    "name:kor_x_preferred":[
        "\ubc14\uc608\ub450\ud30c\ub974"
    ],
    "name:lit_x_preferred":[
        "Valjeduparas"
    ],
    "name:msa_x_preferred":[
        "Valledupar"
    ],
    "name:nld_x_preferred":[
        "Valledupar"
    ],
    "name:nor_x_preferred":[
        "Valledupar"
    ],
    "name:pnb_x_preferred":[
        "\u0648\u06cc\u0644\u06cc\u062f\u0648\u067e\u0627\u0631"
    ],
    "name:pol_x_preferred":[
        "Valledupar"
    ],
    "name:por_x_preferred":[
        "Valledupar"
    ],
    "name:que_x_preferred":[
        "Valledupar"
    ],
    "name:rus_x_preferred":[
        "\u0412\u0430\u043b\u044c\u0435\u0434\u0443\u043f\u0430\u0440"
    ],
    "name:spa_x_preferred":[
        "Valledupar"
    ],
    "name:swe_x_preferred":[
        "Valledupar"
    ],
    "name:tat_x_preferred":[
        "\u0412\u0430\u043b\u044c\u0435\u0434\u0443\u043f\u0430\u0440"
    ],
    "name:tgl_x_preferred":[
        "Valledupar"
    ],
    "name:tur_x_preferred":[
        "Valledupar"
    ],
    "name:urd_x_preferred":[
        "\u0648\u0627\u06cc\u062f\u0648\u067e\u0627\u0631"
    ],
    "name:vie_x_preferred":[
        "Valledupar"
    ],
    "name:vol_x_preferred":[
        "Valledupar"
    ],
    "name:war_x_preferred":[
        "Valledupar"
    ],
    "name:zho_x_preferred":[
        "\u5df4\u8036\u675c\u5e15\u5c14"
    ],
    "wof:name":"Valledupar",
    "wof:placetype":"locality"
},
  "geometry": {"coordinates":[-72.41471999999997,4.84389],"type":"Point"}
}