{
  "type": "Feature",
  "properties": {
    "gn:admin1_code":"32.0",
    "gn:admin2_code":"85139.0",
    "gn:asciiname":"Valledupar",
    "gn:country_code":"CO",
    "gn:dem":188,
    "gn:feature_class":"P",
    "gn:feature_code":"PPL",
    "gn:name":"Valledupar",
    "gn:population":0,
    "gn:timezone":"America/Bogota",
    "iso:country":"CO",
    "wof:name":"Valledupar",
    "wof:placetype":"locality"
},
  "geometry": {"coordinates":[-72.41471999999997,4.84389],"type":"Point"}
}