{
  "type": "Feature",
  "properties": {
    "gn:admin1_code":"27",
    "gn:admin2_code":"70473.0",
    "gn:asciiname":"Las Piedras",
    "gn:country_code":"CO",
    "gn:dem":86,
    "gn:feature_class":"P",
    "gn:feature_code":"PPL",
    "gn:name":"Las Piedras",
    "gn:population":0,
    "gn:timezone":"America/Bogota",
    "iso:country":"CO",
    "name:bul_x_preferred":[
        "\u041b\u0430\u0441 \u041f\u0438\u0435\u0434\u0440\u0430\u0441"
    ],
    "name:cat_x_preferred":[
        "Las Piedras"
    ],
    "name:ceb_x_preferred":[
        "Las Piedras"
    ],
    "name:deu_x_preferred":[
        "Las Piedras"
    ],
    "name:glg_x_preferred":[
        "Las Piedras"
    ],
    "name:hye_x_preferred":[
        "\u053c\u0561\u057d \u054a\u0565\u0564\u0580\u0561\u057d"
    ],
    "name:ita_x_preferred":[
        "Las Piedras"
    ],
    "name:mlg_x_preferred":[
        "Las Piedras"
    ],
    "name:nld_x_preferred":[
        "Las Piedras"
    ],
    "name:pol_x_preferred":[
        "Las Piedras"
    ],
    "name:por_x_preferred":[
        "Las Piedras"
    ],
    "name:rus_x_preferred":[
        "\u041b\u0430\u0441-\u041f\u044c\u0435\u0434\u0440\u0430\u0441"
    ],
    "name:spa_x_preferred":[
        "Las Piedras"
    ],
    "name:swe_x_preferred":[
        "Las Piedras"
    ],
    "name:und_x_variant":[
        "Caser\u00edo Las Piedras",
        "Piedros",
        "Las Piedras"
    ],
    "name:vep_x_preferred":[
        "Las Pjedras"
    ],
    "wof:name":"Las Piedras",
    "wof:placetype":"locality"
},
  "geometry": {"coordinates":[-75.36181999999999,9.43954],"type":"Point"}
}