{
  "type": "Feature",
  "properties": {
    "gn:admin1_code":"9.0",
    "gn:admin2_code":"19256.0",
    "gn:asciiname":"La Aguadita",
    "gn:country_code":"CO",
    "gn:dem":1304,
    "gn:feature_class":"P",
    "gn:feature_code":"PPL",
    "gn:name":"La Aguadita",
    "gn:population":0,
    "gn:timezone":"America/Bogota",
    "iso:country":"CO",
    "wof:name":"La Aguadita",
    "wof:placetype":"locality"
},
  "geometry": {"coordinates":[-76.84470999999998,2.38702],"type":"Point"}
}