{
  "type": "Feature",
  "properties": {
    "gn:admin1_code":"28",
    "gn:admin2_code":"73001.0",
    "gn:asciiname":"El Totumo",
    "gn:country_code":"CO",
    "gn:dem":955,
    "gn:feature_class":"P",
    "gn:feature_code":"PPL",
    "gn:name":"El Totumo",
    "gn:population":0,
    "gn:timezone":"America/Bogota",
    "iso:country":"CO",
    "wof:name":"El Totumo",
    "wof:placetype":"locality"
},
  "geometry": {"coordinates":[-75.18306,4.37806],"type":"Point"}
}