{
  "type": "Feature",
  "properties": {
    "gn:admin1_code":"10",
    "gn:admin2_code":"20787.0",
    "gn:asciiname":"La Siria",
    "gn:country_code":"CO",
    "gn:dem":38,
    "gn:feature_class":"P",
    "gn:feature_code":"PPL",
    "gn:name":"La Siria",
    "gn:population":0,
    "gn:timezone":"America/Bogota",
    "iso:country":"CO",
    "wof:name":"La Siria",
    "wof:placetype":"locality"
},
  "geometry": {"coordinates":[-73.72103,8.9631],"type":"Point"}
}