{
  "type": "Feature",
  "properties": {
    "gn:admin1_code":"34.0",
    "gn:asciiname":"Normandia",
    "gn:country_code":"CO",
    "gn:dem":2545,
    "gn:feature_class":"P",
    "gn:feature_code":"PPL",
    "gn:name":"Normand\u00eda",
    "gn:population":0,
    "gn:timezone":"America/Bogota",
    "iso:country":"CO",
    "name:por_x_preferred":[
        "Normandia"
    ],
    "name:und_x_variant":[
        "Normand\u00eda",
        "Hacienda Normand\u00eda"
    ],
    "wof:name":"Normandia",
    "wof:placetype":"locality"
},
  "geometry": {"coordinates":[-74.18106,4.66413],"type":"Point"}
}