{
  "type": "Feature",
  "properties": {
    "gn:admin1_code":"10",
    "gn:admin2_code":"20228.0",
    "gn:asciiname":"Villa Graciela",
    "gn:country_code":"CO",
    "gn:dem":60,
    "gn:feature_class":"P",
    "gn:feature_code":"PPL",
    "gn:name":"Villa Graciela",
    "gn:population":0,
    "gn:timezone":"America/Bogota",
    "iso:country":"CO",
    "wof:name":"Villa Graciela",
    "wof:placetype":"locality"
},
  "geometry": {"coordinates":[-73.51361,9.23028],"type":"Point"}
}