{
  "type": "Feature",
  "properties": {
    "gn:admin1_code":"28.0",
    "gn:admin2_code":"73024.0",
    "gn:asciiname":"Hacienda Alpujarrita",
    "gn:country_code":"CO",
    "gn:dem":1109,
    "gn:feature_class":"P",
    "gn:feature_code":"PPL",
    "gn:name":"Hacienda Alpujarrita",
    "gn:population":0,
    "gn:timezone":"America/Bogota",
    "iso:country":"CO",
    "name:spa_x_preferred":[
        "Hacienda Alpujarrita"
    ],
    "name:spa_x_variant":[
        "Alpujarrita"
    ],
    "wof:name":"Hacienda Alpujarrita",
    "wof:placetype":"locality"
},
  "geometry": {"coordinates":[-74.98278000000001,3.36167],"type":"Point"}
}