{
  "type": "Feature",
  "properties": {
    "gn:admin1_code":"10",
    "gn:admin2_code":"20383.0",
    "gn:asciiname":"Bella Cruz",
    "gn:country_code":"CO",
    "gn:dem":66,
    "gn:feature_class":"P",
    "gn:feature_code":"PPL",
    "gn:name":"Bella Cruz",
    "gn:population":0,
    "gn:timezone":"America/Bogota",
    "iso:country":"CO",
    "name:und_x_variant":[
        "Hacienda Bella Cruz",
        "Bella Cruz"
    ],
    "wof:name":"Bella Cruz",
    "wof:placetype":"locality"
},
  "geometry": {"coordinates":[-73.684,8.6245],"type":"Point"}
}