{
  "type": "Feature",
  "properties": {
    "gn:admin1_code":"26",
    "gn:admin2_code":"68176.0",
    "gn:asciiname":"San Diego",
    "gn:country_code":"CO",
    "gn:dem":989,
    "gn:feature_class":"P",
    "gn:feature_code":"PPL",
    "gn:name":"San Diego",
    "gn:population":0,
    "gn:timezone":"America/Bogota",
    "iso:country":"CO",
    "wof:name":"San Diego",
    "wof:placetype":"locality"
},
  "geometry": {"coordinates":[-73.40345000000001,6.33952],"type":"Point"}
}