{
  "type": "Feature",
  "properties": {
    "gn:admin1_code":"28",
    "gn:admin2_code":"73168.0",
    "gn:asciiname":"Las Bolsas",
    "gn:country_code":"CO",
    "gn:dem":3048,
    "gn:feature_class":"P",
    "gn:feature_code":"PPL",
    "gn:name":"Las Bolsas",
    "gn:population":0,
    "gn:timezone":"America/Bogota",
    "iso:country":"CO",
    "wof:name":"Las Bolsas",
    "wof:placetype":"locality"
},
  "geometry": {"coordinates":[-75.64083000000002,3.89667],"type":"Point"}
}