{
  "type": "Feature",
  "properties": {
    "gn:admin1_code":"29.0",
    "gn:admin2_code":"76100.0",
    "gn:asciiname":"Playa Rica",
    "gn:country_code":"CO",
    "gn:dem":979,
    "gn:feature_class":"P",
    "gn:feature_code":"PPL",
    "gn:name":"Playa Rica",
    "gn:population":0,
    "gn:timezone":"America/Bogota",
    "iso:country":"CO",
    "wof:name":"Playa Rica",
    "wof:placetype":"locality"
},
  "geometry": {"coordinates":[-76.39343000000002,4.4594],"type":"Point"}
}