{
  "type": "Feature",
  "properties": {
    "gn:admin1_code":"2",
    "gn:admin2_code":"5034.0",
    "gn:asciiname":"Llano Redondo",
    "gn:country_code":"CO",
    "gn:dem":1783,
    "gn:feature_class":"P",
    "gn:feature_code":"PPL",
    "gn:name":"Llano Redondo",
    "gn:population":0,
    "gn:timezone":"America/Bogota",
    "iso:country":"CO",
    "wof:name":"Llano Redondo",
    "wof:placetype":"locality"
},
  "geometry": {"coordinates":[-75.90091,5.6437],"type":"Point"}
}