{
  "type": "Feature",
  "properties": {
    "gn:admin1_code":"29",
    "gn:admin2_code":"76111.0",
    "gn:asciiname":"La Floresta",
    "gn:country_code":"CO",
    "gn:dem":3292,
    "gn:feature_class":"P",
    "gn:feature_code":"PPL",
    "gn:name":"La Floresta",
    "gn:population":0,
    "gn:timezone":"America/Bogota",
    "iso:country":"CO",
    "wof:name":"La Floresta",
    "wof:placetype":"locality"
},
  "geometry": {"coordinates":[-75.88833000000002,3.87583],"type":"Point"}
}