{
  "type": "Feature",
  "properties": {
    "gn:admin1_code":"19",
    "gn:admin2_code":"50001.0",
    "gn:asciiname":"La Fallita",
    "gn:country_code":"CO",
    "gn:dem":245,
    "gn:feature_class":"P",
    "gn:feature_code":"PPL",
    "gn:name":"La Fallita",
    "gn:population":0,
    "gn:timezone":"America/Bogota",
    "iso:country":"CO",
    "wof:name":"La Fallita",
    "wof:placetype":"locality"
},
  "geometry": {"coordinates":[-73.30121,4.10286],"type":"Point"}
}