{
  "type": "Feature",
  "properties": {
    "gn:admin1_code":"29",
    "gn:admin2_code":"76020.0",
    "gn:asciiname":"Maravelez",
    "gn:country_code":"CO",
    "gn:dem":1523,
    "gn:feature_class":"P",
    "gn:feature_code":"PPL",
    "gn:name":"Marav\u00e9lez",
    "gn:population":0,
    "gn:timezone":"America/Bogota",
    "iso:country":"CO",
    "wof:name":"Maravelez",
    "wof:placetype":"locality"
},
  "geometry": {"coordinates":[-75.71916999999998,4.6775],"type":"Point"}
}