{
  "type": "Feature",
  "properties": {
    "gn:admin1_code":"19",
    "gn:admin2_code":"50573.0",
    "gn:asciiname":"La Samaria",
    "gn:country_code":"CO",
    "gn:dem":223,
    "gn:feature_class":"P",
    "gn:feature_code":"PPL",
    "gn:name":"La Samaria",
    "gn:population":0,
    "gn:timezone":"America/Bogota",
    "iso:country":"CO",
    "wof:name":"La Samaria",
    "wof:placetype":"locality"
},
  "geometry": {"coordinates":[-72.866,4.10355],"type":"Point"}
}