{
  "type": "Feature",
  "properties": {
    "gn:admin1_code":"28.0",
    "gn:admin2_code":"73236.0",
    "gn:asciiname":"Penas Blancas",
    "gn:country_code":"CO",
    "gn:dem":1306,
    "gn:feature_class":"P",
    "gn:feature_code":"PPLL",
    "gn:name":"Pe\u00f1as Blancas",
    "gn:population":0,
    "gn:timezone":"America/Bogota",
    "iso:country":"CO",
    "name:spa_x_preferred":[
        "Pe\u00f1as Blancas"
    ],
    "wof:name":"Penas Blancas",
    "wof:placetype":"locality"
},
  "geometry": {"coordinates":[-74.74491999999999,3.67948],"type":"Point"}
}