{
  "type": "Feature",
  "properties": {
    "gn:admin1_code":"2.0",
    "gn:admin2_code":"5001.0",
    "gn:asciiname":"Pedregal Bajo",
    "gn:country_code":"CO",
    "gn:dem":1864,
    "gn:feature_class":"P",
    "gn:feature_code":"PPL",
    "gn:name":"Pedregal Bajo",
    "gn:population":0,
    "gn:timezone":"America/Bogota",
    "iso:country":"CO",
    "name:spa_x_preferred":[
        "Pedregal Bajo"
    ],
    "wof:name":"Pedregal Bajo",
    "wof:placetype":"locality"
},
  "geometry": {"coordinates":[-75.6237,6.28122],"type":"Point"}
}