{
  "type": "Feature",
  "properties": {
    "gn:admin1_code":"33",
    "gn:admin2_code":"25885.0",
    "gn:asciiname":"La Lucia",
    "gn:country_code":"CO",
    "gn:dem":639,
    "gn:feature_class":"P",
    "gn:feature_code":"PPL",
    "gn:name":"La Lucia",
    "gn:population":0,
    "gn:timezone":"America/Bogota",
    "iso:country":"CO",
    "name:afr_x_preferred":[
        "La Lucia"
    ],
    "wof:name":"La Lucia",
    "wof:placetype":"locality"
},
  "geometry": {"coordinates":[-74.35056,5.74694],"type":"Point"}
}