{
  "type": "Feature",
  "properties": {
    "gn:admin1_code":"10",
    "gn:admin2_code":"20045.0",
    "gn:asciiname":"Los Inguensos",
    "gn:country_code":"CO",
    "gn:dem":40,
    "gn:feature_class":"P",
    "gn:feature_code":"PPL",
    "gn:name":"Los Inguensos",
    "gn:population":0,
    "gn:timezone":"America/Bogota",
    "iso:country":"CO",
    "wof:name":"Los Inguensos",
    "wof:placetype":"locality"
},
  "geometry": {"coordinates":[-73.64012,9.66924],"type":"Point"}
}