{
  "type": "Feature",
  "properties": {
    "gn:admin1_code":"38",
    "gn:admin2_code":"47692.0",
    "gn:asciiname":"La Concordia",
    "gn:country_code":"CO",
    "gn:dem":28,
    "gn:feature_class":"P",
    "gn:feature_code":"PPL",
    "gn:name":"La Concordia",
    "gn:population":0,
    "gn:timezone":"America/Bogota",
    "iso:country":"CO",
    "name:und_x_variant":[
        "Concordia",
        "La Concordia"
    ],
    "wof:name":"La Concordia",
    "wof:placetype":"locality"
},
  "geometry": {"coordinates":[-74.26893000000003,9.26867],"type":"Point"}
}