{
  "type": "Feature",
  "properties": {
    "gn:admin1_code":"38",
    "gn:admin2_code":"47692.0",
    "gn:asciiname":"La Concordia",
    "gn:country_code":"CO",
    "gn:dem":28,
    "gn:feature_class":"P",
    "gn:feature_code":"PPL",
    "gn:name":"La Concordia",
    "gn:population":0,
    "gn:timezone":"America/Bogota",
    "iso:country":"CO",
    "name:ceb_x_preferred":[
        "La Concordia"
    ],
    "name:deu_x_preferred":[
        "La Concordia"
    ],
    "name:nld_x_preferred":[
        "La Concordia"
    ],
    "name:rus_x_preferred":[
        "\u041b\u0430-\u041a\u043e\u043d\u043a\u043e\u0440\u0434\u0438\u044f"
    ],
    "name:sco_x_preferred":[
        "La Concordia"
    ],
    "name:spa_x_preferred":[
        "La Concordia"
    ],
    "name:swe_x_preferred":[
        "La Concordia"
    ],
    "name:und_x_variant":[
        "Concordia"
    ],
    "wof:name":"La Concordia",
    "wof:placetype":"locality"
},
  "geometry": {"coordinates":[-74.26893000000003,9.26867],"type":"Point"}
}