{
  "type": "Feature",
  "properties": {
    "gn:admin1_code":"9.0",
    "gn:admin2_code":"19050.0",
    "gn:asciiname":"Aguaclara",
    "gn:country_code":"CO",
    "gn:dem":1492,
    "gn:feature_class":"P",
    "gn:feature_code":"PPL",
    "gn:name":"Aguaclara",
    "gn:population":0,
    "gn:timezone":"America/Bogota",
    "iso:country":"CO",
    "wof:name":"Aguaclara",
    "wof:placetype":"locality"
},
  "geometry": {"coordinates":[-77.26125,2.40053],"type":"Point"}
}