{
  "type": "Feature",
  "properties": {
    "gn:admin1_code":"25",
    "gn:admin2_code":"88564.0",
    "gn:asciiname":"Archibolds",
    "gn:country_code":"CO",
    "gn:dem":14,
    "gn:feature_class":"P",
    "gn:feature_code":"PPL",
    "gn:name":"Archibolds",
    "gn:population":0,
    "gn:timezone":"America/Bogota",
    "iso:country":"CO",
    "wof:name":"Archibolds",
    "wof:placetype":"locality"
},
  "geometry": {"coordinates":[-81.36667,13.33333],"type":"Point"}
}