{
  "type": "Feature",
  "properties": {
    "iso:country":"CO",
    "name:ceb_x_preferred":[
        "Montel\u00edbano"
    ],
    "name:chi_x_preferred":[
        "\u8499\u7279\u5229\u74e6\u8afe"
    ],
    "name:deu_x_preferred":[
        "Montel\u00edbano"
    ],
    "name:dut_x_preferred":[
        "Montel\u00edbano"
    ],
    "name:eng_x_preferred":[
        "Montel\u00edbano"
    ],
    "name:fas_x_preferred":[
        "\u0645\u0648\u0646\u062a\u0644\u06cc\u0628\u0627\u0646\u0648"
    ],
    "name:fra_x_preferred":[
        "Montel\u00edbano"
    ],
    "name:fre_x_preferred":[
        "Montel\u00edbano"
    ],
    "name:geo_x_preferred":[
        "\u10db\u10dd\u10dc\u10e2\u10d4\u10da\u10d8\u10d1\u10d0\u10dc\u10dd"
    ],
    "name:ger_x_preferred":[
        "Montel\u00edbano"
    ],
    "name:ita_x_preferred":[
        "Montel\u00edbano"
    ],
    "name:jpn_x_preferred":[
        "\u30e2\u30f3\u30c6\u30ea\u30d0\u30ce"
    ],
    "name:kat_x_preferred":[
        "\u10db\u10dd\u10dc\u10e2\u10d4\u10da\u10d8\u10d1\u10d0\u10dc\u10dd"
    ],
    "name:may_x_preferred":[
        "Montel\u00edbano"
    ],
    "name:msa_x_preferred":[
        "Montel\u00edbano"
    ],
    "name:nan_x_preferred":[
        "Montel\u00edbano"
    ],
    "name:nld_x_preferred":[
        "Montel\u00edbano"
    ],
    "name:per_x_preferred":[
        "\u0645\u0648\u0646\u062a\u0644\u06cc\u0628\u0627\u0646\u0648"
    ],
    "name:por_x_preferred":[
        "Montel\u00edbano"
    ],
    "name:spa_x_preferred":[
        "Montel\u00edbano"
    ],
    "name:swe_x_preferred":[
        "Montel\u00edbano"
    ],
    "name:tgl_x_preferred":[
        "Montel\u00edbano"
    ],
    "name:vie_x_preferred":[
        "Montel\u00edbano"
    ],
    "name:war_x_preferred":[
        "Montel\u00edbano"
    ],
    "qs:gn_country":"CO",
    "qs:gn_fcode":"PPL",
    "qs:gn_pop":85000,
    "qs:name":"Montel\u00edbano",
    "qs:name_adm0":"Colombia",
    "qs:name_adm1":"Cordoba",
    "qs:photos":0,
    "qs:photos_1k":0,
    "qs:photos_9k":1,
    "qs:photos_9r":2,
    "qs:photos_all":44,
    "qs:photos_sr":0,
    "qs:placetype":"Town",
    "qs:pop_sr":"8",
    "qs:woe_adm0":23424787,
    "wd:wordcount":76,
    "wof:name":"Montel\u00edbano",
    "wof:placetype":"locality",
    "wof:population":85000
},
  "geometry": {"coordinates":[-75.42292999999999,7.98288],"type":"Point"}
}