{
  "type": "Feature",
  "properties": {
    "gn:admin1_code":"28.0",
    "gn:admin2_code":"73319.0",
    "gn:asciiname":"Rincon Santo",
    "gn:country_code":"CO",
    "gn:dem":297,
    "gn:feature_class":"P",
    "gn:feature_code":"PPL",
    "gn:name":"Rinc\u00f3n Santo",
    "gn:population":0,
    "gn:timezone":"America/Bogota",
    "iso:country":"CO",
    "name:und_x_variant":[
        "Ricon Santa",
        "Rinc\u00f3n Santo"
    ],
    "wof:name":"Rincon Santo",
    "wof:placetype":"locality"
},
  "geometry": {"coordinates":[-74.89686,4.00803],"type":"Point"}
}