{
  "type": "Feature",
  "properties": {
    "iso:country":"CO",
    "name:ast_x_preferred":[
        "\u00cdquira"
    ],
    "name:avk_x_preferred":[
        "\u00cdquira"
    ],
    "name:ceb_x_preferred":[
        "\u00cdquira"
    ],
    "name:ceb_x_variant":[
        "Iquira"
    ],
    "name:eng_x_preferred":[
        "Iquira"
    ],
    "name:fas_x_preferred":[
        "\u0627\u06cc\u06a9\u06cc\u0631\u0627"
    ],
    "name:fra_x_preferred":[
        "Iquira"
    ],
    "name:gle_x_preferred":[
        "Iquira"
    ],
    "name:ita_x_preferred":[
        "Iquira"
    ],
    "name:kat_x_preferred":[
        "\u10d8\u10d9\u10d8\u10e0\u10d0"
    ],
    "name:msa_x_preferred":[
        "Iquira"
    ],
    "name:nan_x_preferred":[
        "Iquira"
    ],
    "name:nld_x_preferred":[
        "Iquira"
    ],
    "name:pol_x_preferred":[
        "Iquira"
    ],
    "name:por_x_preferred":[
        "Iquira"
    ],
    "name:spa_x_preferred":[
        "\u00cdquira"
    ],
    "name:swe_x_preferred":[
        "\u00cdquira"
    ],
    "name:swe_x_variant":[
        "Iquira"
    ],
    "name:tgl_x_preferred":[
        "Iquira"
    ],
    "name:vie_x_preferred":[
        "Iquira"
    ],
    "name:war_x_preferred":[
        "Iquira"
    ],
    "name:zho_min_nan_x_preferred":[
        "Iquira"
    ],
    "name:zho_x_preferred":[
        "\u4f0a\u57fa\u62c9"
    ],
    "qs:gn_country":"CO",
    "qs:gn_fcode":"PPL",
    "qs:gn_pop":3942,
    "qs:name":"Iquira",
    "qs:name_adm0":"Colombia",
    "qs:name_adm1":"Huila",
    "qs:photos":0,
    "qs:photos_1k":0,
    "qs:photos_9k":1,
    "qs:photos_9r":1,
    "qs:photos_all":11,
    "qs:photos_sr":0,
    "qs:placetype":"Town",
    "qs:pop_sr":"4",
    "qs:woe_adm0":23424787,
    "wd:wordcount":28,
    "wof:name":"Iquira",
    "wof:placetype":"locality",
    "wof:population":3942
},
  "geometry": {"coordinates":[-75.63457,2.64867],"type":"Point"}
}