{
  "type": "Feature",
  "properties": {
    "gn:admin1_code":"26",
    "gn:admin2_code":"68377.0",
    "gn:asciiname":"Guadalito",
    "gn:country_code":"CO",
    "gn:dem":1860,
    "gn:feature_class":"P",
    "gn:feature_code":"PPL",
    "gn:name":"Guadalito",
    "gn:population":0,
    "gn:timezone":"America/Bogota",
    "iso:country":"CO",
    "wof:name":"Guadalito",
    "wof:placetype":"locality"
},
  "geometry": {"coordinates":[-73.97583,5.90528],"type":"Point"}
}