{
  "type": "Feature",
  "properties": {
    "gn:admin1_code":"33.0",
    "gn:admin2_code":"25001.0",
    "gn:asciiname":"Altamira",
    "gn:country_code":"CO",
    "gn:dem":338,
    "gn:feature_class":"P",
    "gn:feature_code":"PPL",
    "gn:name":"Altamira",
    "gn:population":0,
    "gn:timezone":"America/Bogota",
    "iso:country":"CO",
    "name:spa_x_preferred":[
        "Altamira"
    ],
    "wof:name":"Altamira",
    "wof:placetype":"locality"
},
  "geometry": {"coordinates":[-74.69485999999998,4.36027],"type":"Point"}
}