{
  "type": "Feature",
  "properties": {
    "iso:country":"CO",
    "name:bul_x_preferred":[
        "\u0421\u043e\u0442\u0430\u0440\u0430"
    ],
    "name:deu_x_preferred":[
        "Sotar\u00e1"
    ],
    "name:eng_x_preferred":[
        "Sotar\u00e1"
    ],
    "name:fra_x_preferred":[
        "Sotar\u00e1"
    ],
    "name:ita_x_preferred":[
        "Sotar\u00e1"
    ],
    "name:kat_x_preferred":[
        "\u10e1\u10dd\u10e2\u10d0\u10e0\u10d0"
    ],
    "name:msa_x_preferred":[
        "Sotara"
    ],
    "name:nan_x_preferred":[
        "Sotar\u00e1"
    ],
    "name:nld_x_preferred":[
        "Sotar\u00e1"
    ],
    "name:por_x_preferred":[
        "Sotar\u00e1"
    ],
    "name:spa_x_preferred":[
        "Sotar\u00e1"
    ],
    "name:swe_x_preferred":[
        "Sotara"
    ],
    "name:tgl_x_preferred":[
        "Sotara"
    ],
    "name:unk_x_variant":[
        "Sotar\u00e1"
    ],
    "name:war_x_preferred":[
        "Sotara"
    ],
    "name:zho_x_preferred":[
        "\u7d22\u5854\u62c9"
    ],
    "qs:gn_country":"CO",
    "qs:gn_fcode":"PPL",
    "qs:gn_pop":1390,
    "qs:name":"Pa\u00eds Pamba",
    "qs:name_adm0":"Colombia",
    "qs:name_adm1":"Cauca",
    "qs:photos":0,
    "qs:photos_1k":0,
    "qs:photos_9k":1,
    "qs:photos_9r":1,
    "qs:photos_all":4,
    "qs:photos_sr":0,
    "qs:placetype":"Town",
    "qs:pop_sr":"3",
    "qs:woe_adm0":23424787,
    "wof:name":"Pa\u00eds Pamba",
    "wof:placetype":"locality",
    "wof:population":1390
},
  "geometry": {"coordinates":[-76.61086,2.25462],"type":"Point"}
}