{
  "type": "Feature",
  "properties": {
    "gn:admin1_code":"26",
    "gn:admin2_code":"68705.0",
    "gn:asciiname":"El Tope",
    "gn:country_code":"CO",
    "gn:dem":1748,
    "gn:feature_class":"P",
    "gn:feature_code":"PPL",
    "gn:name":"El Tope",
    "gn:population":0,
    "gn:timezone":"America/Bogota",
    "iso:country":"CO",
    "wof:name":"El Tope",
    "wof:placetype":"locality"
},
  "geometry": {"coordinates":[-72.91441,6.97143],"type":"Point"}
}