{
  "type": "Feature",
  "properties": {
    "gn:admin1_code":"3",
    "gn:admin2_code":"81065.0",
    "gn:asciiname":"Mata Palito",
    "gn:country_code":"CO",
    "gn:dem":146,
    "gn:feature_class":"P",
    "gn:feature_code":"PPL",
    "gn:name":"Mata Palito",
    "gn:population":0,
    "gn:timezone":"America/Bogota",
    "iso:country":"CO",
    "wof:name":"Mata Palito",
    "wof:placetype":"locality"
},
  "geometry": {"coordinates":[-71.11667,6.99667],"type":"Point"}
}