{
  "type": "Feature",
  "properties": {
    "gn:admin1_code":"16.0",
    "gn:admin2_code":"41206.0",
    "gn:asciiname":"El Amparo",
    "gn:country_code":"CO",
    "gn:dem":1960,
    "gn:feature_class":"P",
    "gn:feature_code":"PPLL",
    "gn:name":"El Amparo",
    "gn:population":0,
    "gn:timezone":"America/Bogota",
    "iso:country":"CO",
    "name:spa_x_preferred":[
        "El Amparo"
    ],
    "wof:name":"El Amparo",
    "wof:placetype":"locality"
},
  "geometry": {"coordinates":[-74.65916999999997,3.67507],"type":"Point"}
}