{
  "type": "Feature",
  "properties": {
    "gn:admin1_code":"20.0",
    "gn:admin2_code":"52317.0",
    "gn:asciiname":"Puente Alto",
    "gn:country_code":"CO",
    "gn:dem":3133,
    "gn:feature_class":"P",
    "gn:feature_code":"PPL",
    "gn:name":"Puente Alto",
    "gn:population":0,
    "gn:timezone":"America/Bogota",
    "iso:country":"CO",
    "wof:name":"Puente Alto",
    "wof:placetype":"locality"
},
  "geometry": {"coordinates":[-77.78194000000001,0.92944],"type":"Point"}
}