{
  "type": "Feature",
  "properties": {
    "gn:admin1_code":"20.0",
    "gn:admin2_code":"52317.0",
    "gn:asciiname":"Puente Alto",
    "gn:country_code":"CO",
    "gn:dem":3133,
    "gn:feature_class":"P",
    "gn:feature_code":"PPL",
    "gn:name":"Puente Alto",
    "gn:population":0,
    "gn:timezone":"America/Bogota",
    "iso:country":"CO",
    "name:ara_x_preferred":[
        "\u0628\u0648\u064a\u0646\u062a\u064a \u0622\u0644\u062a\u0648"
    ],
    "name:bar_x_preferred":[
        "Puente Alto"
    ],
    "name:bul_x_preferred":[
        "\u041f\u0443\u0435\u043d\u0442\u0435 \u0410\u043b\u0442\u043e"
    ],
    "name:deu_x_preferred":[
        "Puente Alto"
    ],
    "name:epo_x_preferred":[
        "Puente Alto"
    ],
    "name:eus_x_preferred":[
        "Puente Alto"
    ],
    "name:fas_x_preferred":[
        "\u067e\u0648\u0646\u062a\u0647 \u0622\u0644\u062a\u0648"
    ],
    "name:fin_x_preferred":[
        "Puente Alto"
    ],
    "name:fra_x_preferred":[
        "Puente Alto"
    ],
    "name:ita_x_preferred":[
        "Puente Alto"
    ],
    "name:kat_x_preferred":[
        "\u10de\u10e3\u10d4\u10dc\u10e2\u10d4-\u10d0\u10da\u10e2\u10dd"
    ],
    "name:kor_x_preferred":[
        "\ud478\uc5d4\ud14c\uc54c\ud1a0"
    ],
    "name:lav_x_preferred":[
        "Puente Alto"
    ],
    "name:lit_x_preferred":[
        "Puento Altas"
    ],
    "name:nld_x_preferred":[
        "Puente Alto"
    ],
    "name:pol_x_preferred":[
        "Puente Alto"
    ],
    "name:por_x_preferred":[
        "Puente Alto"
    ],
    "name:que_x_preferred":[
        "Puente Alto"
    ],
    "name:ron_x_preferred":[
        "Puente Alto"
    ],
    "name:rus_x_preferred":[
        "\u041f\u0443\u044d\u043d\u0442\u0435-\u0410\u043b\u044c\u0442\u043e"
    ],
    "name:sco_x_preferred":[
        "Puente Alto"
    ],
    "name:spa_x_preferred":[
        "Puente Alto"
    ],
    "name:srp_x_preferred":[
        "\u041f\u0443\u0435\u043d\u0442\u0435 \u0410\u043b\u0442\u043e"
    ],
    "name:swe_x_preferred":[
        "Puente Alto"
    ],
    "name:tat_x_preferred":[
        "\u041f\u0432\u0435\u043d\u0442\u0435-\u0410\u043b\u044c\u0442\u043e"
    ],
    "name:tur_x_preferred":[
        "Puente Alto"
    ],
    "name:urd_x_preferred":[
        "\u067e\u0648\u06cc\u0646\u062a\u06d2 \u0622\u0644\u062a\u0648"
    ],
    "name:vol_x_preferred":[
        "Puente Alto"
    ],
    "name:war_x_preferred":[
        "Puente Alto"
    ],
    "name:zho_x_preferred":[
        "\u4e0a\u666e\u6069\u7279"
    ],
    "wof:name":"Puente Alto",
    "wof:placetype":"locality"
},
  "geometry": {"coordinates":[-77.78194000000001,0.92944],"type":"Point"}
}