{
  "type": "Feature",
  "properties": {
    "gn:admin1_code":"2.0",
    "gn:admin2_code":"5113.0",
    "gn:asciiname":"Mesas",
    "gn:country_code":"CO",
    "gn:dem":2541,
    "gn:feature_class":"P",
    "gn:feature_code":"PPL",
    "gn:name":"Mesas",
    "gn:population":0,
    "gn:timezone":"America/Bogota",
    "iso:country":"CO",
    "wof:name":"Mesas",
    "wof:placetype":"locality"
},
  "geometry": {"coordinates":[-75.96666999999999,6.75],"type":"Point"}
}