{
  "type": "Feature",
  "properties": {
    "gn:admin1_code":"2.0",
    "gn:admin2_code":"5347.0",
    "gn:asciiname":"Canada Sela",
    "gn:country_code":"CO",
    "gn:dem":2079,
    "gn:feature_class":"P",
    "gn:feature_code":"PPL",
    "gn:name":"Ca\u00f1ada Sela",
    "gn:population":0,
    "gn:timezone":"America/Bogota",
    "iso:country":"CO",
    "name:spa_x_preferred":[
        "Ca\u00f1ada Sela"
    ],
    "wof:name":"Canada Sela",
    "wof:placetype":"locality"
},
  "geometry": {"coordinates":[-75.70938000000002,6.20233],"type":"Point"}
}