{
  "type": "Feature",
  "properties": {
    "gn:admin1_code":"2",
    "gn:admin2_code":"5368.0",
    "gn:asciiname":"La Aguada",
    "gn:country_code":"CO",
    "gn:dem":2047,
    "gn:feature_class":"P",
    "gn:feature_code":"PPL",
    "gn:name":"La Aguada",
    "gn:population":0,
    "gn:timezone":"America/Bogota",
    "iso:country":"CO",
    "wof:name":"La Aguada",
    "wof:placetype":"locality"
},
  "geometry": {"coordinates":[-75.81286999999998,5.7609],"type":"Point"}
}