{
  "type": "Feature",
  "properties": {
    "gn:admin1_code":"38",
    "gn:admin2_code":"47541.0",
    "gn:asciiname":"Martinete",
    "gn:country_code":"CO",
    "gn:dem":12,
    "gn:feature_class":"P",
    "gn:feature_code":"PPL",
    "gn:name":"Martinete",
    "gn:population":0,
    "gn:timezone":"America/Bogota",
    "iso:country":"CO",
    "wof:name":"Martinete",
    "wof:placetype":"locality"
},
  "geometry": {"coordinates":[-74.76666999999998,10.11667],"type":"Point"}
}