{
  "type": "Feature",
  "properties": {
    "gn:admin1_code":"38",
    "gn:admin2_code":"47001.0",
    "gn:asciiname":"Arimaca",
    "gn:country_code":"CO",
    "gn:dem":802,
    "gn:feature_class":"P",
    "gn:feature_code":"PPL",
    "gn:name":"Arimaca",
    "gn:population":0,
    "gn:timezone":"America/Bogota",
    "iso:country":"CO",
    "wof:name":"Arimaca",
    "wof:placetype":"locality"
},
  "geometry": {"coordinates":[-74.1116,11.12637],"type":"Point"}
}