{
  "type": "Feature",
  "properties": {
    "gn:admin1_code":"19",
    "gn:admin2_code":"50568.0",
    "gn:asciiname":"Bengala",
    "gn:country_code":"CO",
    "gn:dem":253,
    "gn:feature_class":"P",
    "gn:feature_code":"PPL",
    "gn:name":"Bengala",
    "gn:population":0,
    "gn:timezone":"America/Bogota",
    "iso:country":"CO",
    "name:cat_x_preferred":[
        "Bengala"
    ],
    "name:glg_x_preferred":[
        "Bengala"
    ],
    "name:ita_x_preferred":[
        "Bengala"
    ],
    "name:por_x_preferred":[
        "Bengala"
    ],
    "name:spa_x_preferred":[
        "Bengala"
    ],
    "wof:name":"Bengala",
    "wof:placetype":"locality"
},
  "geometry": {"coordinates":[-72.02619,4.07518],"type":"Point"}
}