{
  "type": "Feature",
  "properties": {
    "gn:admin1_code":"2.0",
    "gn:admin2_code":"5001.0",
    "gn:asciiname":"Villa Luz",
    "gn:country_code":"CO",
    "gn:dem":2064,
    "gn:feature_class":"P",
    "gn:feature_code":"PPL",
    "gn:name":"Villa Luz",
    "gn:population":0,
    "gn:timezone":"America/Bogota",
    "iso:country":"CO",
    "name:spa_x_preferred":[
        "Villa Luz"
    ],
    "wof:name":"Villa Luz",
    "wof:placetype":"locality"
},
  "geometry": {"coordinates":[-75.54814,6.18309],"type":"Point"}
}