{
  "type": "Feature",
  "properties": {
    "gn:admin1_code":"28",
    "gn:admin2_code":"73563",
    "gn:asciiname":"Las Nubes",
    "gn:country_code":"CO",
    "gn:dem":351,
    "gn:feature_class":"P",
    "gn:feature_code":"PPL",
    "gn:name":"Las Nubes",
    "gn:population":0,
    "gn:timezone":"America/Bogota",
    "iso:country":"CO",
    "name:spa_x_preferred":[
        "Las Nubes"
    ],
    "wof:name":"Las Nubes",
    "wof:placetype":"locality"
},
  "geometry": {"coordinates":[-74.90873000000001,3.77577],"type":"Point"}
}