{
  "type": "Feature",
  "properties": {
    "gn:admin1_code":"35",
    "gn:admin2_code":"13836.0",
    "gn:asciiname":"Juan Congo",
    "gn:country_code":"CO",
    "gn:dem":63,
    "gn:feature_class":"P",
    "gn:feature_code":"PPL",
    "gn:name":"Juan Congo",
    "gn:population":0,
    "gn:timezone":"America/Bogota",
    "iso:country":"CO",
    "wof:name":"Juan Congo",
    "wof:placetype":"locality"
},
  "geometry": {"coordinates":[-75.36395,10.39866],"type":"Point"}
}