{
  "type": "Feature",
  "properties": {
    "gn:admin1_code":"9",
    "gn:admin2_code":"19450.0",
    "gn:asciiname":"Hornillos",
    "gn:country_code":"CO",
    "gn:dem":1138,
    "gn:feature_class":"P",
    "gn:feature_code":"PPL",
    "gn:name":"Hornillos",
    "gn:population":0,
    "gn:timezone":"America/Bogota",
    "iso:country":"CO",
    "wof:name":"Hornillos",
    "wof:placetype":"locality"
},
  "geometry": {"coordinates":[-77.15085999999999,1.75652],"type":"Point"}
}