{
  "type": "Feature",
  "properties": {
    "gn:admin1_code":"20.0",
    "gn:admin2_code":"52788.0",
    "gn:asciiname":"El Tambor",
    "gn:country_code":"CO",
    "gn:dem":3005,
    "gn:feature_class":"P",
    "gn:feature_code":"PPL",
    "gn:name":"El Tambor",
    "gn:population":0,
    "gn:timezone":"America/Bogota",
    "iso:country":"CO",
    "name:und_x_variant":[
        "Tambor"
    ],
    "wof:name":"El Tambor",
    "wof:placetype":"locality"
},
  "geometry": {"coordinates":[-77.36424,1.12926],"type":"Point"}
}