{
  "type": "Feature",
  "properties": {
    "gn:admin1_code":"16",
    "gn:admin2_code":"41001.0",
    "gn:asciiname":"Las Lajas",
    "gn:country_code":"CO",
    "gn:dem":1295,
    "gn:feature_class":"P",
    "gn:feature_code":"PPL",
    "gn:name":"Las Lajas",
    "gn:population":0,
    "gn:timezone":"America/Bogota",
    "iso:country":"CO",
    "wof:name":"Las Lajas",
    "wof:placetype":"locality"
},
  "geometry": {"coordinates":[-75.47528,3.09917],"type":"Point"}
}