{
  "type": "Feature",
  "properties": {
    "gn:admin1_code":"10",
    "gn:admin2_code":"20250.0",
    "gn:asciiname":"Gabriel",
    "gn:country_code":"CO",
    "gn:dem":49,
    "gn:feature_class":"P",
    "gn:feature_code":"PPL",
    "gn:name":"Gabriel",
    "gn:population":0,
    "gn:timezone":"America/Bogota",
    "iso:country":"CO",
    "wof:name":"Gabriel",
    "wof:placetype":"locality"
},
  "geometry": {"coordinates":[-73.75,9.76667],"type":"Point"}
}