{
  "type": "Feature",
  "properties": {
    "gn:admin1_code":"36",
    "gn:admin2_code":"15533.0",
    "gn:asciiname":"Descansadero",
    "gn:country_code":"CO",
    "gn:dem":877,
    "gn:feature_class":"P",
    "gn:feature_code":"PPL",
    "gn:name":"Descansadero",
    "gn:population":0,
    "gn:timezone":"America/Bogota",
    "iso:country":"CO",
    "wof:name":"Descansadero",
    "wof:placetype":"locality"
},
  "geometry": {"coordinates":[-72.32536999999998,5.61456],"type":"Point"}
}