{
  "type": "Feature",
  "properties": {
    "gn:admin1_code":"2.0",
    "gn:admin2_code":"5004.0",
    "gn:asciiname":"La Golondrina",
    "gn:country_code":"CO",
    "gn:dem":2271,
    "gn:feature_class":"P",
    "gn:feature_code":"PPL",
    "gn:name":"La Golondrina",
    "gn:population":0,
    "gn:timezone":"America/Bogota",
    "iso:country":"CO",
    "wof:name":"La Golondrina",
    "wof:placetype":"locality"
},
  "geometry": {"coordinates":[-76.10829,6.63249],"type":"Point"}
}