{
  "type": "Feature",
  "properties": {
    "gn:admin1_code":"12",
    "gn:admin2_code":"23068.0",
    "gn:asciiname":"Alfonso Lopez",
    "gn:country_code":"CO",
    "gn:dem":27,
    "gn:feature_class":"P",
    "gn:feature_code":"PPL",
    "gn:name":"Alfonso L\u00f3pez",
    "gn:population":0,
    "gn:timezone":"America/Bogota",
    "iso:country":"CO",
    "name:und_x_variant":[
        "Corregimiento Alfonso Lopez",
        "Alfonso L\u00f3pez"
    ],
    "wof:name":"Alfonso Lopez",
    "wof:placetype":"locality"
},
  "geometry": {"coordinates":[-74.90245999999998,8.39392],"type":"Point"}
}