{
  "type": "Feature",
  "properties": {
    "gn:admin1_code":"24.0",
    "gn:admin2_code":"66594.0",
    "gn:asciiname":"Insambra",
    "gn:country_code":"CO",
    "gn:dem":1738,
    "gn:feature_class":"P",
    "gn:feature_code":"PPL",
    "gn:name":"Insambra",
    "gn:population":0,
    "gn:timezone":"America/Bogota",
    "iso:country":"CO",
    "wof:name":"Insambra",
    "wof:placetype":"locality"
},
  "geometry": {"coordinates":[-75.75705000000001,5.33052],"type":"Point"}
}