{
  "type": "Feature",
  "properties": {
    "gn:admin1_code":"29.0",
    "gn:admin2_code":"76895.0",
    "gn:asciiname":"Porro Belo",
    "gn:country_code":"CO",
    "gn:dem":976,
    "gn:feature_class":"P",
    "gn:feature_code":"PPL",
    "gn:name":"Porro Belo",
    "gn:population":0,
    "gn:timezone":"America/Bogota",
    "iso:country":"CO",
    "wof:name":"Porro Belo",
    "wof:placetype":"locality"
},
  "geometry": {"coordinates":[-76.02417,4.35778],"type":"Point"}
}