{
  "type": "Feature",
  "properties": {
    "gn:admin1_code":"2",
    "gn:admin2_code":"5585.0",
    "gn:asciiname":"La Zona",
    "gn:country_code":"CO",
    "gn:dem":324,
    "gn:feature_class":"P",
    "gn:feature_code":"PPL",
    "gn:name":"La Zona",
    "gn:population":0,
    "gn:timezone":"America/Bogota",
    "iso:country":"CO",
    "name:srp_x_preferred":[
        "\u041b\u0430 \u0417\u043e\u043d\u0430"
    ],
    "wof:name":"La Zona",
    "wof:placetype":"locality"
},
  "geometry": {"coordinates":[-74.65000000000001,6.21611],"type":"Point"}
}