{
  "type": "Feature",
  "properties": {
    "gn:admin1_code":"36.0",
    "gn:admin2_code":"15135.0",
    "gn:asciiname":"Soata",
    "gn:cc2":"CO",
    "gn:country_code":"CO",
    "gn:dem":2142,
    "gn:feature_class":"P",
    "gn:feature_code":"PPL",
    "gn:name":"Soat\u00e1",
    "gn:population":0,
    "gn:timezone":"America/Bogota",
    "iso:country":"CO",
    "name:und_x_variant":[
        "Finca Soat\u00e1",
        "Soat\u00e1"
    ],
    "wof:name":"Soata",
    "wof:placetype":"locality"
},
  "geometry": {"coordinates":[-73.13333,5.08333],"type":"Point"}
}