{
  "type": "Feature",
  "properties": {
    "gn:admin1_code":"15",
    "gn:admin2_code":"94001.0",
    "gn:asciiname":"Las Palmeras",
    "gn:country_code":"CO",
    "gn:dem":92,
    "gn:feature_class":"P",
    "gn:feature_code":"PPL",
    "gn:name":"Las Palmeras",
    "gn:population":0,
    "gn:timezone":"America/Bogota",
    "iso:country":"CO",
    "wof:name":"Las Palmeras",
    "wof:placetype":"locality"
},
  "geometry": {"coordinates":[-68.19084000000001,3.66292],"type":"Point"}
}