{
  "type": "Feature",
  "properties": {
    "gn:admin1_code":"19.0",
    "gn:admin2_code":"50325.0",
    "gn:asciiname":"Puerto Alegre",
    "gn:country_code":"CO",
    "gn:dem":177,
    "gn:feature_class":"P",
    "gn:feature_code":"PPL",
    "gn:name":"Puerto Alegre",
    "gn:population":0,
    "gn:timezone":"America/Bogota",
    "iso:country":"CO",
    "name:spa_x_preferred":[
        "Puerto Alegre"
    ],
    "wof:name":"Puerto Alegre",
    "wof:placetype":"locality"
},
  "geometry": {"coordinates":[-71.8742,2.84905],"type":"Point"}
}