{
  "type": "Feature",
  "properties": {
    "gn:admin1_code":"12.0",
    "gn:admin2_code":"23686.0",
    "gn:asciiname":"Chunchunal",
    "gn:country_code":"CO",
    "gn:dem":13,
    "gn:feature_class":"P",
    "gn:feature_code":"PPLL",
    "gn:name":"Chunchunal",
    "gn:population":0,
    "gn:timezone":"America/Bogota",
    "iso:country":"CO",
    "wof:name":"Chunchunal",
    "wof:placetype":"locality"
},
  "geometry": {"coordinates":[-75.88751999999999,8.96963],"type":"Point"}
}