{
  "type": "Feature",
  "properties": {
    "gn:admin1_code":"20.0",
    "gn:admin2_code":"52788.0",
    "gn:asciiname":"Santander",
    "gn:country_code":"CO",
    "gn:dem":2916,
    "gn:feature_class":"P",
    "gn:feature_code":"PPL",
    "gn:name":"Santander",
    "gn:population":0,
    "gn:timezone":"America/Bogota",
    "iso:country":"CO",
    "wof:name":"Santander",
    "wof:placetype":"locality"
},
  "geometry": {"coordinates":[-77.31693,1.07515],"type":"Point"}
}