{
  "type": "Feature",
  "properties": {
    "gn:admin1_code":"17",
    "gn:admin2_code":"44279.0",
    "gn:asciiname":"El Barrial",
    "gn:country_code":"CO",
    "gn:dem":175,
    "gn:feature_class":"P",
    "gn:feature_code":"PPL",
    "gn:name":"El Barrial",
    "gn:population":0,
    "gn:timezone":"America/Bogota",
    "iso:country":"CO",
    "name:spa_x_preferred":[
        "El Barrial"
    ],
    "wof:name":"El Barrial",
    "wof:placetype":"locality"
},
  "geometry": {"coordinates":[-72.82916999999998,10.89389],"type":"Point"}
}