{
  "type": "Feature",
  "properties": {
    "gn:admin1_code":"12",
    "gn:admin2_code":"23574.0",
    "gn:asciiname":"Cerro Pelado",
    "gn:country_code":"CO",
    "gn:dem":16,
    "gn:feature_class":"P",
    "gn:feature_code":"PPL",
    "gn:name":"Cerro Pelado",
    "gn:population":0,
    "gn:timezone":"America/Bogota",
    "iso:country":"CO",
    "name:cat_x_preferred":[
        "Cerro Pelado"
    ],
    "name:deu_x_preferred":[
        "Cerro Pelado"
    ],
    "name:fra_x_preferred":[
        "Cerro Pelado"
    ],
    "wof:name":"Cerro Pelado",
    "wof:placetype":"locality"
},
  "geometry": {"coordinates":[-76.30195000000001,8.96687],"type":"Point"}
}