{
  "type": "Feature",
  "properties": {
    "gn:admin1_code":"29.0",
    "gn:admin2_code":"76122.0",
    "gn:asciiname":"San Gerardo",
    "gn:country_code":"CO",
    "gn:dem":1414,
    "gn:feature_class":"P",
    "gn:feature_code":"PPL",
    "gn:name":"San Gerardo",
    "gn:population":0,
    "gn:timezone":"America/Bogota",
    "iso:country":"CO",
    "name:ceb_x_preferred":[
        "San Gerardo"
    ],
    "name:ita_x_preferred":[
        "San Gerardo"
    ],
    "name:por_x_preferred":[
        "San Gerardo"
    ],
    "name:spa_x_preferred":[
        "San Gerardo"
    ],
    "name:zho_x_preferred":[
        "\u8056\u8d6b\u62c9\u723e\u591a"
    ],
    "wof:name":"San Gerardo",
    "wof:placetype":"locality"
},
  "geometry": {"coordinates":[-75.81964000000001,4.29354],"type":"Point"}
}