{
  "type": "Feature",
  "properties": {
    "gn:admin1_code":"20",
    "gn:admin2_code":"52405.0",
    "gn:asciiname":"Caballero",
    "gn:country_code":"CO",
    "gn:dem":807,
    "gn:feature_class":"P",
    "gn:feature_code":"PPL",
    "gn:name":"Caballero",
    "gn:population":0,
    "gn:timezone":"America/Bogota",
    "iso:country":"CO",
    "name:bul_x_preferred":[
        "\u041a\u0430\u0431\u0430\u043b\u0435\u0440\u043e"
    ],
    "name:ceb_x_preferred":[
        "Caballero"
    ],
    "name:deu_x_preferred":[
        "Caballero"
    ],
    "name:fra_x_preferred":[
        "Caballero"
    ],
    "name:glg_x_preferred":[
        "Caballero"
    ],
    "name:ita_x_preferred":[
        "Caballero"
    ],
    "name:jpn_x_preferred":[
        "\u30ad\u30e3\u30d0\u30ec\u30ed"
    ],
    "name:kor_x_preferred":[
        "\uce74\ubc14\uc608\ub85c"
    ],
    "name:nld_x_preferred":[
        "Caballero"
    ],
    "name:rus_x_preferred":[
        "\u041a\u0430\u0431\u0430\u043b\u044c\u0435\u0440\u043e"
    ],
    "name:spa_x_preferred":[
        "Caballero"
    ],
    "name:swe_x_preferred":[
        "Caballero"
    ],
    "name:ukr_x_preferred":[
        "\u041a\u0430\u0431\u0430\u043b\u044c\u0454\u0440\u043e"
    ],
    "wof:name":"Caballero",
    "wof:placetype":"locality"
},
  "geometry": {"coordinates":[-77.29196999999998,1.90076],"type":"Point"}
}