{
  "type": "Feature",
  "properties": {
    "gn:admin1_code":"20",
    "gn:admin2_code":"52405.0",
    "gn:asciiname":"Caballero",
    "gn:country_code":"CO",
    "gn:dem":807,
    "gn:feature_class":"P",
    "gn:feature_code":"PPL",
    "gn:name":"Caballero",
    "gn:population":0,
    "gn:timezone":"America/Bogota",
    "iso:country":"CO",
    "wof:name":"Caballero",
    "wof:placetype":"locality"
},
  "geometry": {"coordinates":[-77.29196999999998,1.90076],"type":"Point"}
}