{
  "type": "Feature",
  "properties": {
    "iso:country":"CO",
    "name:deu_x_preferred":[
        "Curit\u00ed"
    ],
    "name:eng_x_preferred":[
        "Curit\u00ed"
    ],
    "name:fra_x_preferred":[
        "Curit\u00ed"
    ],
    "name:glg_x_preferred":[
        "Curit\u00ed"
    ],
    "name:ita_x_preferred":[
        "Curit\u00ed"
    ],
    "name:kat_x_preferred":[
        "\u10d9\u10e3\u10e0\u10d8\u10e2\u10d8"
    ],
    "name:msa_x_preferred":[
        "Curiti"
    ],
    "name:nan_x_preferred":[
        "Curit\u00ed"
    ],
    "name:nld_x_preferred":[
        "Curit\u00ed"
    ],
    "name:spa_x_preferred":[
        "Curit\u00ed"
    ],
    "name:tgl_x_preferred":[
        "Curiti"
    ],
    "name:unk_x_variant":[
        "Curuti"
    ],
    "name:vie_x_preferred":[
        "Curit\u00ed"
    ],
    "name:war_x_preferred":[
        "Curiti"
    ],
    "name:zho_x_preferred":[
        "\u5eab\u91cc\u8482"
    ],
    "qs:gn_country":"CO",
    "qs:gn_fcode":"PPL",
    "qs:gn_pop":3417,
    "qs:name":"Curit\u00ed",
    "qs:name_adm0":"Colombia",
    "qs:name_adm1":"Santander",
    "qs:photos":160,
    "qs:photos_1k":32,
    "qs:photos_9k":1,
    "qs:photos_9r":4,
    "qs:photos_all":160,
    "qs:photos_sr":4,
    "qs:placetype":"Town",
    "qs:pop_sr":"4",
    "qs:woe_adm0":23424787,
    "wof:name":"Curit\u00ed",
    "wof:placetype":"locality",
    "wof:population":3417
},
  "geometry": {"coordinates":[-73.06809,6.60519],"type":"Point"}
}