{
  "type": "Feature",
  "properties": {
    "gn:admin1_code":"17.0",
    "gn:admin2_code":"44430.0",
    "gn:asciiname":"Santander",
    "gn:country_code":"CO",
    "gn:dem":62,
    "gn:feature_class":"P",
    "gn:feature_code":"PPL",
    "gn:name":"Santander",
    "gn:population":0,
    "gn:timezone":"America/Bogota",
    "iso:country":"CO",
    "name:afr_x_preferred":[
        "Santander"
    ],
    "name:ast_x_preferred":[
        "Santander"
    ],
    "name:bre_x_preferred":[
        "Santander"
    ],
    "name:ceb_x_preferred":[
        "Santander"
    ],
    "name:deu_x_preferred":[
        "Santander"
    ],
    "name:epo_x_preferred":[
        "Santandero"
    ],
    "name:fas_x_preferred":[
        "\u0633\u0627\u0646\u062a\u0627\u0646\u062f\u0631"
    ],
    "name:fra_x_preferred":[
        "Santander"
    ],
    "name:fry_x_preferred":[
        "Santander"
    ],
    "name:glg_x_preferred":[
        "Santander"
    ],
    "name:heb_x_preferred":[
        "\u05e1\u05e0\u05d8\u05e0\u05d3\u05e8"
    ],
    "name:ind_x_preferred":[
        "Santander"
    ],
    "name:ita_x_preferred":[
        "Santander"
    ],
    "name:jpn_x_preferred":[
        "\u30b5\u30f3\u30bf\u30f3\u30c7\u30fc\u30eb"
    ],
    "name:kor_x_preferred":[
        "\uc0b0\ud0c4\ub370\ub974"
    ],
    "name:mlg_x_preferred":[
        "Santander"
    ],
    "name:msa_x_preferred":[
        "Santander"
    ],
    "name:nld_x_preferred":[
        "Santander"
    ],
    "name:nor_x_preferred":[
        "Santander"
    ],
    "name:pol_x_preferred":[
        "Santander"
    ],
    "name:por_x_preferred":[
        "Santander"
    ],
    "name:ron_x_preferred":[
        "Santander"
    ],
    "name:rus_x_preferred":[
        "\u0421\u0430\u043d\u0442\u0430\u043d\u0434\u0435\u0440"
    ],
    "name:san_x_preferred":[
        "\u0938\u0928\u094d\u0924\u093e\u0928\u094d\u0926\u0947\u0930"
    ],
    "name:scn_x_preferred":[
        "Santander"
    ],
    "name:sco_x_preferred":[
        "Santander"
    ],
    "name:slk_x_preferred":[
        "Santander"
    ],
    "name:spa_x_preferred":[
        "Santander"
    ],
    "name:srp_x_preferred":[
        "\u0421\u0430\u043d\u0442\u0430\u043d\u0434\u0435\u0440"
    ],
    "name:swe_x_preferred":[
        "Santander"
    ],
    "name:ukr_x_preferred":[
        "\u0421\u0430\u043d\u0442\u0430\u043d\u0434\u0435\u0440"
    ],
    "name:vie_x_preferred":[
        "Santander"
    ],
    "name:war_x_preferred":[
        "Santander"
    ],
    "name:zho_x_preferred":[
        "\u6851\u5766\u5fb7"
    ],
    "wof:name":"Santander",
    "wof:placetype":"locality"
},
  "geometry": {"coordinates":[-72.405,11.46],"type":"Point"}
}