{
  "type": "Feature",
  "properties": {
    "gn:admin1_code":"12",
    "gn:admin2_code":"23162.0",
    "gn:asciiname":"Chilin",
    "gn:country_code":"CO",
    "gn:dem":15,
    "gn:feature_class":"P",
    "gn:feature_code":"PPL",
    "gn:name":"Chil\u00edn",
    "gn:population":0,
    "gn:timezone":"America/Bogota",
    "iso:country":"CO",
    "wof:name":"Chilin",
    "wof:placetype":"locality"
},
  "geometry": {"coordinates":[-75.87739000000001,8.90872],"type":"Point"}
}