{
  "type": "Feature",
  "properties": {
    "gn:admin1_code":"16.0",
    "gn:admin2_code":"41615.0",
    "gn:asciiname":"Riverita",
    "gn:country_code":"CO",
    "gn:dem":566,
    "gn:feature_class":"P",
    "gn:feature_code":"PPL",
    "gn:name":"Riverita",
    "gn:population":0,
    "gn:timezone":"America/Bogota",
    "iso:country":"CO",
    "wof:name":"Riverita",
    "wof:placetype":"locality"
},
  "geometry": {"coordinates":[-75.28969000000002,2.75769],"type":"Point"}
}