{
  "type": "Feature",
  "properties": {
    "gn:admin1_code":"33.0",
    "gn:admin2_code":"25281.0",
    "gn:asciiname":"Saname",
    "gn:country_code":"CO",
    "gn:dem":1551,
    "gn:feature_class":"P",
    "gn:feature_code":"PPL",
    "gn:name":"S\u00e1name",
    "gn:population":0,
    "gn:timezone":"America/Bogota",
    "iso:country":"CO",
    "wof:name":"Saname",
    "wof:placetype":"locality"
},
  "geometry": {"coordinates":[-73.90153000000002,4.34567],"type":"Point"}
}