{
  "type": "Feature",
  "properties": {
    "gn:admin1_code":"9.0",
    "gn:admin2_code":"19743.0",
    "gn:asciiname":"Quichaya",
    "gn:country_code":"CO",
    "gn:dem":2436,
    "gn:feature_class":"P",
    "gn:feature_code":"PPL",
    "gn:name":"Quichay\u00e1",
    "gn:population":0,
    "gn:timezone":"America/Bogota",
    "iso:country":"CO",
    "name:und_x_variant":[
        "Quinchaya",
        "Quichay\u00e1"
    ],
    "wof:name":"Quichaya",
    "wof:placetype":"locality"
},
  "geometry": {"coordinates":[-76.38231,2.71896],"type":"Point"}
}