{
  "type": "Feature",
  "properties": {
    "gn:admin1_code":"24",
    "gn:admin2_code":"66045.0",
    "gn:asciiname":"La Tolda",
    "gn:country_code":"CO",
    "gn:dem":2083,
    "gn:feature_class":"P",
    "gn:feature_code":"PPL",
    "gn:name":"La Tolda",
    "gn:population":0,
    "gn:timezone":"America/Bogota",
    "iso:country":"CO",
    "wof:name":"La Tolda",
    "wof:placetype":"locality"
},
  "geometry": {"coordinates":[-75.94889000000001,5.1825],"type":"Point"}
}