{
  "type": "Feature",
  "properties": {
    "gn:admin1_code":"10",
    "gn:admin2_code":"20238.0",
    "gn:asciiname":"Alejandria",
    "gn:country_code":"CO",
    "gn:dem":115,
    "gn:feature_class":"P",
    "gn:feature_code":"PPL",
    "gn:name":"Alejandria",
    "gn:population":0,
    "gn:timezone":"America/Bogota",
    "iso:country":"CO",
    "wof:name":"Alejandria",
    "wof:placetype":"locality"
},
  "geometry": {"coordinates":[-73.98333000000002,10.13333],"type":"Point"}
}