{
  "type": "Feature",
  "properties": {
    "gn:admin1_code":"12",
    "gn:admin2_code":"23090.0",
    "gn:asciiname":"Bruselas",
    "gn:country_code":"CO",
    "gn:dem":122,
    "gn:feature_class":"P",
    "gn:feature_code":"PPL",
    "gn:name":"Bruselas",
    "gn:population":0,
    "gn:timezone":"America/Bogota",
    "iso:country":"CO",
    "wof:name":"Bruselas",
    "wof:placetype":"locality"
},
  "geometry": {"coordinates":[-76.20860999999999,8.63667],"type":"Point"}
}