{
  "type": "Feature",
  "properties": {
    "gn:admin1_code":"1.0",
    "gn:admin2_code":"91669.0",
    "gn:asciiname":"Tolima B",
    "gn:country_code":"CO",
    "gn:dem":123,
    "gn:feature_class":"P",
    "gn:feature_code":"PPL",
    "gn:name":"Tolima B",
    "gn:population":0,
    "gn:timezone":"America/Bogota",
    "iso:country":"CO",
    "wof:name":"Tolima B",
    "wof:placetype":"locality"
},
  "geometry": {"coordinates":[-71.98349,-1.52773],"type":"Point"}
}