{
  "type": "Feature",
  "properties": {
    "gn:admin1_code":"2.0",
    "gn:admin2_code":"5480.0",
    "gn:asciiname":"Porroso",
    "gn:country_code":"CO",
    "gn:dem":77,
    "gn:feature_class":"P",
    "gn:feature_code":"PPL",
    "gn:name":"Porroso",
    "gn:population":0,
    "gn:timezone":"America/Bogota",
    "iso:country":"CO",
    "wof:name":"Porroso",
    "wof:placetype":"locality"
},
  "geometry": {"coordinates":[-76.5325,7.4225],"type":"Point"}
}