{
  "type": "Feature",
  "properties": {
    "gn:admin1_code":"10",
    "gn:admin2_code":"20001.0",
    "gn:asciiname":"Caracoli",
    "gn:country_code":"CO",
    "gn:dem":126,
    "gn:feature_class":"P",
    "gn:feature_code":"PPL",
    "gn:name":"Caracol\u00ed",
    "gn:population":0,
    "gn:timezone":"America/Bogota",
    "iso:country":"CO",
    "wof:name":"Caracoli",
    "wof:placetype":"locality"
},
  "geometry": {"coordinates":[-73.73333000000002,10.06667],"type":"Point"}
}