{
  "type": "Feature",
  "properties": {
    "gn:admin1_code":"38.0",
    "gn:admin2_code":"47030.0",
    "gn:asciiname":"Si Dios Quiere",
    "gn:country_code":"CO",
    "gn:dem":149,
    "gn:feature_class":"P",
    "gn:feature_code":"PPL",
    "gn:name":"Si Dios Quiere",
    "gn:population":0,
    "gn:timezone":"America/Bogota",
    "iso:country":"CO",
    "name:und_x_variant":[
        "Caser\u00edo Si Dios Quiere",
        "Si Dios Quiere"
    ],
    "wof:name":"Si Dios Quiere",
    "wof:placetype":"locality"
},
  "geometry": {"coordinates":[-74.03913,10.29597],"type":"Point"}
}