{
  "type": "Feature",
  "properties": {
    "gn:admin1_code":"20.0",
    "gn:admin2_code":"52573.0",
    "gn:asciiname":"San Mateo",
    "gn:country_code":"CO",
    "gn:dem":2496,
    "gn:feature_class":"P",
    "gn:feature_code":"PPL",
    "gn:name":"San Mateo",
    "gn:population":0,
    "gn:timezone":"America/Bogota",
    "iso:country":"CO",
    "wof:name":"San Mateo",
    "wof:placetype":"locality"
},
  "geometry": {"coordinates":[-77.48364000000002,0.91983],"type":"Point"}
}