{
  "type": "Feature",
  "properties": {
    "gn:admin1_code":"33.0",
    "gn:admin2_code":"25839.0",
    "gn:asciiname":"Chusneque",
    "gn:country_code":"CO",
    "gn:dem":1956,
    "gn:feature_class":"P",
    "gn:feature_code":"PPL",
    "gn:name":"Chusnequ\u00e9",
    "gn:population":0,
    "gn:timezone":"America/Bogota",
    "iso:country":"CO",
    "wof:name":"Chusneque",
    "wof:placetype":"locality"
},
  "geometry": {"coordinates":[-73.57677,4.77886],"type":"Point"}
}