{
  "type": "Feature",
  "properties": {
    "gn:admin1_code":"17.0",
    "gn:admin2_code":"44847.0",
    "gn:asciiname":"Jalalou",
    "gn:country_code":"CO",
    "gn:dem":79,
    "gn:feature_class":"P",
    "gn:feature_code":"PPLL",
    "gn:name":"Jalalou",
    "gn:population":0,
    "gn:timezone":"America/Bogota",
    "iso:country":"CO",
    "name:spa_x_preferred":[
        "Jalalou"
    ],
    "wof:name":"Jalalou",
    "wof:placetype":"locality"
},
  "geometry": {"coordinates":[-71.30322,12.18052],"type":"Point"}
}