{
  "type": "Feature",
  "properties": {
    "gn:admin1_code":"30",
    "gn:admin2_code":"97001.0",
    "gn:asciiname":"Enambu",
    "gn:cc2":"CO",
    "gn:country_code":"CO",
    "gn:dem":202,
    "gn:feature_class":"P",
    "gn:feature_code":"PPL",
    "gn:name":"Enamb\u00fa",
    "gn:population":0,
    "gn:timezone":"America/Bogota",
    "iso:country":"CO",
    "name:und_x_variant":[
        "I\u00f1amb\u00fa",
        "Enamb\u00fa"
    ],
    "wof:name":"Enambu",
    "wof:placetype":"locality"
},
  "geometry": {"coordinates":[-70.28333000000001,1.01667],"type":"Point"}
}