{
  "type": "Feature",
  "properties": {
    "gn:admin1_code":"36",
    "gn:admin2_code":"15693.0",
    "gn:asciiname":"Crecientes",
    "gn:country_code":"CO",
    "gn:dem":2506,
    "gn:feature_class":"P",
    "gn:feature_code":"PPL",
    "gn:name":"Crecientes",
    "gn:population":0,
    "gn:timezone":"America/Bogota",
    "iso:country":"CO",
    "wof:name":"Crecientes",
    "wof:placetype":"locality"
},
  "geometry": {"coordinates":[-72.96794,5.82166],"type":"Point"}
}