{
  "type": "Feature",
  "properties": {
    "gn:admin1_code":"30",
    "gn:admin2_code":"97001.0",
    "gn:asciiname":"Puerto Tolima",
    "gn:country_code":"CO",
    "gn:dem":178,
    "gn:feature_class":"P",
    "gn:feature_code":"PPL",
    "gn:name":"Puerto Tolima",
    "gn:population":0,
    "gn:timezone":"America/Bogota",
    "iso:country":"CO",
    "wof:name":"Puerto Tolima",
    "wof:placetype":"locality"
},
  "geometry": {"coordinates":[-69.91028,1.1975],"type":"Point"}
}