{
  "type": "Feature",
  "properties": {
    "gn:admin1_code":"4",
    "gn:admin2_code":"8558.0",
    "gn:asciiname":"Andrea",
    "gn:cc2":"CO",
    "gn:country_code":"CO",
    "gn:dem":56,
    "gn:feature_class":"P",
    "gn:feature_code":"PPL",
    "gn:name":"Andrea",
    "gn:population":0,
    "gn:timezone":"America/Bogota",
    "iso:country":"CO",
    "name:und_x_variant":[
        "Hacienda Andrea",
        "Andrea"
    ],
    "wof:name":"Andrea",
    "wof:placetype":"locality"
},
  "geometry": {"coordinates":[-74.83333,10.76667],"type":"Point"}
}