{
  "type": "Feature",
  "properties": {
    "gn:admin1_code":"4",
    "gn:admin2_code":"8558.0",
    "gn:asciiname":"Andrea",
    "gn:cc2":"CO",
    "gn:country_code":"CO",
    "gn:dem":56,
    "gn:feature_class":"P",
    "gn:feature_code":"PPL",
    "gn:name":"Andrea",
    "gn:population":0,
    "gn:timezone":"America/Bogota",
    "iso:country":"CO",
    "name:ara_x_preferred":[
        "\u0623\u0646\u062f\u0631\u064a\u0627"
    ],
    "name:bre_x_preferred":[
        "Andrea"
    ],
    "name:cat_x_preferred":[
        "Andrea"
    ],
    "name:ces_x_preferred":[
        "Andrea"
    ],
    "name:dan_x_preferred":[
        "Andrea"
    ],
    "name:deu_x_preferred":[
        "Andrea"
    ],
    "name:eml_x_preferred":[
        "Andrea"
    ],
    "name:epo_x_preferred":[
        "Andreo"
    ],
    "name:fas_x_preferred":[
        "\u0622\u0646\u062f\u0631\u0647\u200c\u0622"
    ],
    "name:fin_x_preferred":[
        "Andrea"
    ],
    "name:isl_x_preferred":[
        "Andrea"
    ],
    "name:ita_x_preferred":[
        "Andrea"
    ],
    "name:lat_x_preferred":[
        "Andrea"
    ],
    "name:nld_x_preferred":[
        "Andrea"
    ],
    "name:nno_x_preferred":[
        "Andrea"
    ],
    "name:nor_x_preferred":[
        "Andrea"
    ],
    "name:pol_x_preferred":[
        "Andrea"
    ],
    "name:slk_x_preferred":[
        "Andrea"
    ],
    "name:slv_x_preferred":[
        "Andrea"
    ],
    "name:spa_x_preferred":[
        "Andrea"
    ],
    "name:swe_x_preferred":[
        "Andrea"
    ],
    "name:und_x_variant":[
        "Hacienda Andrea"
    ],
    "wof:name":"Andrea",
    "wof:placetype":"locality"
},
  "geometry": {"coordinates":[-74.83333,10.76667],"type":"Point"}
}