{
  "type": "Feature",
  "properties": {
    "gn:admin1_code":"19.0",
    "gn:admin2_code":"50577.0",
    "gn:asciiname":"El Viso",
    "gn:country_code":"CO",
    "gn:dem":235,
    "gn:feature_class":"P",
    "gn:feature_code":"PPLL",
    "gn:name":"El Viso",
    "gn:population":0,
    "gn:timezone":"America/Bogota",
    "iso:country":"CO",
    "name:ara_x_preferred":[
        "\u0625\u0644 \u0641\u064a\u0632\u0648"
    ],
    "name:arg_x_preferred":[
        "El Viso"
    ],
    "name:ast_x_preferred":[
        "El Viso"
    ],
    "name:azb_x_preferred":[
        "\u0627\u0644 \u0648\u06cc\u0633\u0648"
    ],
    "name:bul_x_preferred":[
        "\u0415\u043b \u0412\u0438\u0441\u043e"
    ],
    "name:cat_x_preferred":[
        "El Viso"
    ],
    "name:ceb_x_preferred":[
        "El Viso"
    ],
    "name:deu_x_preferred":[
        "El Viso"
    ],
    "name:epo_x_preferred":[
        "El Viso"
    ],
    "name:eus_x_preferred":[
        "El Viso"
    ],
    "name:fas_x_preferred":[
        "\u0627\u0644 \u0648\u06cc\u0633\u0648"
    ],
    "name:fra_x_preferred":[
        "El Viso"
    ],
    "name:glg_x_preferred":[
        "El Viso"
    ],
    "name:hat_x_preferred":[
        "El Viso"
    ],
    "name:hun_x_preferred":[
        "El Viso"
    ],
    "name:ina_x_preferred":[
        "El Viso"
    ],
    "name:ita_x_preferred":[
        "El Viso"
    ],
    "name:msa_x_preferred":[
        "El Viso"
    ],
    "name:nld_x_preferred":[
        "El Viso"
    ],
    "name:oci_x_preferred":[
        "El Viso"
    ],
    "name:pol_x_preferred":[
        "El Viso"
    ],
    "name:por_x_preferred":[
        "El Viso"
    ],
    "name:ron_x_preferred":[
        "El Viso"
    ],
    "name:rus_x_preferred":[
        "\u042d\u043b\u044c-\u0412\u0438\u0441\u043e"
    ],
    "name:spa_x_preferred":[
        "El Viso"
    ],
    "name:swe_x_preferred":[
        "El Viso"
    ],
    "name:tur_x_preferred":[
        "El Viso"
    ],
    "name:ukr_x_preferred":[
        "\u0415\u043b\u044c-\u0412\u0456\u0441\u043e"
    ],
    "name:uzb_x_preferred":[
        "El Viso"
    ],
    "name:vie_x_preferred":[
        "El Viso"
    ],
    "name:war_x_preferred":[
        "El Viso"
    ],
    "name:zho_x_preferred":[
        "\u57c3\u5c14\u7ef4\u7d22"
    ],
    "wof:name":"El Viso",
    "wof:placetype":"locality"
},
  "geometry": {"coordinates":[-73.21916,3.29622],"type":"Point"}
}