{
  "type": "Feature",
  "properties": {
    "gn:admin1_code":"4.0",
    "gn:admin2_code":"8296.0",
    "gn:asciiname":"Los Colinas",
    "gn:country_code":"CO",
    "gn:dem":94,
    "gn:feature_class":"P",
    "gn:feature_code":"PPL",
    "gn:name":"Los Colinas",
    "gn:population":0,
    "gn:timezone":"America/Bogota",
    "iso:country":"CO",
    "wof:name":"Los Colinas",
    "wof:placetype":"locality"
},
  "geometry": {"coordinates":[-74.87366,10.88419],"type":"Point"}
}