{
  "type": "Feature",
  "properties": {
    "gn:admin1_code":"33.0",
    "gn:admin2_code":"25839.0",
    "gn:asciiname":"Nazareth",
    "gn:country_code":"CO",
    "gn:dem":2018,
    "gn:feature_class":"P",
    "gn:feature_code":"PPL",
    "gn:name":"Nazareth",
    "gn:population":0,
    "gn:timezone":"America/Bogota",
    "iso:country":"CO",
    "wof:name":"Nazareth",
    "wof:placetype":"locality"
},
  "geometry": {"coordinates":[-73.52675000000001,4.75996],"type":"Point"}
}