{
  "type": "Feature",
  "properties": {
    "gn:admin1_code":"29",
    "gn:admin2_code":"76834.0",
    "gn:asciiname":"Ranco Largo",
    "gn:country_code":"CO",
    "gn:dem":3562,
    "gn:feature_class":"P",
    "gn:feature_code":"PPL",
    "gn:name":"Ranco Largo",
    "gn:population":0,
    "gn:timezone":"America/Bogota",
    "iso:country":"CO",
    "wof:name":"Ranco Largo",
    "wof:placetype":"locality"
},
  "geometry": {"coordinates":[-75.84333000000002,3.93333],"type":"Point"}
}