{
  "type": "Feature",
  "properties": {
    "gn:admin1_code":"3.0",
    "gn:admin2_code":"81736.0",
    "gn:asciiname":"Pescado",
    "gn:country_code":"CO",
    "gn:dem":199,
    "gn:feature_class":"P",
    "gn:feature_code":"PPL",
    "gn:name":"Pescado",
    "gn:population":0,
    "gn:timezone":"America/Bogota",
    "iso:country":"CO",
    "name:spa_x_preferred":[
        "Pescado"
    ],
    "wof:name":"Pescado",
    "wof:placetype":"locality"
},
  "geometry": {"coordinates":[-71.87954000000001,6.98637],"type":"Point"}
}