{
  "type": "Feature",
  "properties": {
    "gn:admin1_code":"2",
    "gn:admin2_code":"5660.0",
    "gn:asciiname":"Los Arrayanes",
    "gn:country_code":"CO",
    "gn:dem":820,
    "gn:feature_class":"P",
    "gn:feature_code":"PPL",
    "gn:name":"Los Arrayanes",
    "gn:population":0,
    "gn:timezone":"America/Bogota",
    "iso:country":"CO",
    "wof:name":"Los Arrayanes",
    "wof:placetype":"locality"
},
  "geometry": {"coordinates":[-74.86333,6.04528],"type":"Point"}
}