{
  "type": "Feature",
  "properties": {
    "iso:country":"CO",
    "name:ast_x_preferred":[
        "Encino"
    ],
    "name:ceb_x_preferred":[
        "Encino"
    ],
    "name:eng_x_preferred":[
        "Encino"
    ],
    "name:fra_x_preferred":[
        "Encino"
    ],
    "name:ita_x_preferred":[
        "Encino"
    ],
    "name:kat_x_preferred":[
        "\u10d4\u10dc\u10e1\u10d8\u10dc\u10dd"
    ],
    "name:msa_x_preferred":[
        "Encino"
    ],
    "name:nan_x_preferred":[
        "Encino"
    ],
    "name:nld_x_preferred":[
        "Encino"
    ],
    "name:spa_x_preferred":[
        "Encino"
    ],
    "name:swe_x_preferred":[
        "Encino"
    ],
    "name:tgl_x_preferred":[
        "Encino"
    ],
    "name:war_x_preferred":[
        "Encino"
    ],
    "name:zho_min_nan_x_preferred":[
        "Encino"
    ],
    "name:zho_x_preferred":[
        "\u6069\u897f\u8afe"
    ],
    "qs:gn_country":"CO",
    "qs:gn_fcode":"PPL",
    "qs:gn_pop":412,
    "qs:name":"Encino",
    "qs:name_adm0":"Colombia",
    "qs:name_adm1":"Santander",
    "qs:photos":0,
    "qs:photos_1k":0,
    "qs:photos_9k":1,
    "qs:photos_9r":1,
    "qs:photos_all":1,
    "qs:photos_sr":0,
    "qs:placetype":"Town",
    "qs:pop_sr":"2",
    "qs:woe_adm0":23424787,
    "wd:wordcount":36,
    "wof:name":"Encino",
    "wof:placetype":"locality",
    "wof:population":412
},
  "geometry": {"coordinates":[-73.09847000000001,6.13735],"type":"Point"}
}