{
  "type": "Feature",
  "properties": {
    "iso:country":"CO",
    "name:ast_x_preferred":[
        "Pinchote"
    ],
    "name:ceb_x_preferred":[
        "Pinchote"
    ],
    "name:eng_x_preferred":[
        "Pinchote"
    ],
    "name:fra_x_preferred":[
        "Pinchote"
    ],
    "name:ita_x_preferred":[
        "Pinchote"
    ],
    "name:kat_x_preferred":[
        "\u10de\u10d8\u10dc\u10e9\u10dd\u10e2\u10d4"
    ],
    "name:msa_x_preferred":[
        "Pinchote"
    ],
    "name:nan_x_preferred":[
        "Pinchote"
    ],
    "name:nld_x_preferred":[
        "Pinchote"
    ],
    "name:spa_x_preferred":[
        "Pinchote"
    ],
    "name:swe_x_preferred":[
        "Pinchote"
    ],
    "name:tgl_x_preferred":[
        "Pinchote"
    ],
    "name:vie_x_preferred":[
        "Pinchote"
    ],
    "name:war_x_preferred":[
        "Pinchote"
    ],
    "name:zho_min_nan_x_preferred":[
        "Pinchote"
    ],
    "name:zho_x_preferred":[
        "\u5e73\u55ac\u7279"
    ],
    "qs:gn_country":"CO",
    "qs:gn_fcode":"PPL",
    "qs:gn_pop":674,
    "qs:name":"Pinchote",
    "qs:name_adm0":"Colombia",
    "qs:name_adm1":"Santander",
    "qs:photos":30,
    "qs:photos_1k":6,
    "qs:photos_9k":1,
    "qs:photos_9r":2,
    "qs:photos_all":30,
    "qs:photos_sr":2,
    "qs:placetype":"Town",
    "qs:pop_sr":"2",
    "qs:woe_adm0":23424787,
    "wd:wordcount":30,
    "wof:name":"Pinchote",
    "wof:placetype":"locality",
    "wof:population":674
},
  "geometry": {"coordinates":[-73.17309,6.53226],"type":"Point"}
}