{
  "type": "Feature",
  "properties": {
    "gn:admin1_code":"27",
    "gn:admin2_code":"70742.0",
    "gn:asciiname":"Libra",
    "gn:country_code":"CO",
    "gn:dem":143,
    "gn:feature_class":"P",
    "gn:feature_code":"PPL",
    "gn:name":"Libra",
    "gn:population":0,
    "gn:timezone":"America/Bogota",
    "iso:country":"CO",
    "name:ast_x_preferred":[
        "Llibra"
    ],
    "name:ces_x_preferred":[
        "Libra"
    ],
    "name:deu_x_preferred":[
        "Libra"
    ],
    "name:ell_x_preferred":[
        "\u0396\u03c5\u03b3\u03cc\u03c2"
    ],
    "name:est_x_preferred":[
        "Libra"
    ],
    "name:eus_x_preferred":[
        "Libra"
    ],
    "name:fin_x_preferred":[
        "Libra"
    ],
    "name:fra_x_preferred":[
        "Libra"
    ],
    "name:glg_x_preferred":[
        "Libra"
    ],
    "name:heb_x_preferred":[
        "\u05dc\u05d9\u05d1\u05e8\u05d4"
    ],
    "name:hun_x_preferred":[
        "Libra"
    ],
    "name:ina_x_preferred":[
        "Libra"
    ],
    "name:ind_x_preferred":[
        "Libra"
    ],
    "name:ita_x_preferred":[
        "Libra"
    ],
    "name:jpn_x_preferred":[
        "\u30dd\u30f3\u30c9"
    ],
    "name:kor_x_preferred":[
        "\ub9ac\ube0c\ub77c"
    ],
    "name:lat_x_preferred":[
        "Libra"
    ],
    "name:msa_x_preferred":[
        "Libra"
    ],
    "name:nld_x_preferred":[
        "Libra"
    ],
    "name:nno_x_preferred":[
        "Libra"
    ],
    "name:pol_x_preferred":[
        "Libra"
    ],
    "name:por_x_preferred":[
        "Libra"
    ],
    "name:rus_x_preferred":[
        "Libra"
    ],
    "name:slk_x_preferred":[
        "Libra"
    ],
    "name:spa_x_preferred":[
        "Libra"
    ],
    "name:swe_x_preferred":[
        "Libra"
    ],
    "name:tgl_x_preferred":[
        "Libra"
    ],
    "name:tha_x_preferred":[
        "Libra"
    ],
    "name:ukr_x_preferred":[
        "\u041b\u0456\u0431\u0440\u0430"
    ],
    "name:vie_x_preferred":[
        "Libra"
    ],
    "wof:name":"Libra",
    "wof:placetype":"locality"
},
  "geometry": {"coordinates":[-75.17701,9.33068],"type":"Point"}
}