{
  "type": "Feature",
  "properties": {
    "gn:admin1_code":"27",
    "gn:admin2_code":"70742.0",
    "gn:asciiname":"Libra",
    "gn:country_code":"CO",
    "gn:dem":143,
    "gn:feature_class":"P",
    "gn:feature_code":"PPL",
    "gn:name":"Libra",
    "gn:population":0,
    "gn:timezone":"America/Bogota",
    "iso:country":"CO",
    "wof:name":"Libra",
    "wof:placetype":"locality"
},
  "geometry": {"coordinates":[-75.17701,9.33068],"type":"Point"}
}