{
  "type": "Feature",
  "properties": {
    "iso:country":"CO",
    "name:ceb_x_preferred":[
        "Santa Rosa de Viterbo"
    ],
    "name:eng_x_preferred":[
        "Santa Rosa de Viterbo"
    ],
    "name:fra_x_preferred":[
        "Santa Rosa de Viterbo"
    ],
    "name:gla_x_preferred":[
        "Santa Rosa de Viterbo"
    ],
    "name:ita_x_preferred":[
        "Santa Rosa de Viterbo"
    ],
    "name:kat_x_preferred":[
        "\u10e1\u10d0\u10dc\u10e2\u10d0-\u10e0\u10dd\u10e1\u10d0-\u10d3\u10d4-\u10d5\u10d8\u10e2\u10d4\u10e0\u10d1\u10dd"
    ],
    "name:msa_x_preferred":[
        "Santa Rosa de Viterbo"
    ],
    "name:nan_x_preferred":[
        "Santa Rosa de Viterbo"
    ],
    "name:nld_x_preferred":[
        "Santa Rosa de Viterbo"
    ],
    "name:por_x_preferred":[
        "Santa Rosa de Viterbo"
    ],
    "name:spa_x_preferred":[
        "Santa Rosa de Viterbo"
    ],
    "name:swe_x_preferred":[
        "Santa Rosa de Viterbo"
    ],
    "name:tgl_x_preferred":[
        "Santa Rosa de Viterbo"
    ],
    "name:unk_x_variant":[
        "Santa Rosa"
    ],
    "name:war_x_preferred":[
        "Santa Rosa de Viterbo"
    ],
    "name:zho_x_preferred":[
        "\u8056\u7f85\u838e\u5fb7\u6bd4\u7279\u6c83"
    ],
    "qs:gn_country":"CO",
    "qs:gn_fcode":"PPL",
    "qs:gn_pop":6923,
    "qs:name":"Santa Rosa de Viterbo",
    "qs:name_adm0":"Colombia",
    "qs:name_adm1":"Boyaca",
    "qs:photos":0,
    "qs:photos_1k":0,
    "qs:photos_9k":1,
    "qs:photos_9r":2,
    "qs:photos_all":52,
    "qs:photos_sr":0,
    "qs:placetype":"Town",
    "qs:pop_sr":"5",
    "qs:woe_adm0":23424787,
    "wd:wordcount":211,
    "wof:name":"Santa Rosa de Viterbo",
    "wof:placetype":"locality",
    "wof:population":6923
},
  "geometry": {"coordinates":[-72.98217,5.87401],"type":"Point"}
}