{
  "type": "Feature",
  "properties": {
    "gn:admin1_code":"8.0",
    "gn:admin2_code":"18460.0",
    "gn:asciiname":"Ceilan",
    "gn:country_code":"CO",
    "gn:dem":200,
    "gn:feature_class":"P",
    "gn:feature_code":"PPL",
    "gn:name":"Ceil\u00e1n",
    "gn:population":0,
    "gn:timezone":"America/Bogota",
    "iso:country":"CO",
    "name:spa_x_preferred":[
        "Ceil\u00e1n"
    ],
    "wof:name":"Ceilan",
    "wof:placetype":"locality"
},
  "geometry": {"coordinates":[-75.30183000000002,0.95446],"type":"Point"}
}