{
  "type": "Feature",
  "properties": {
    "gn:admin1_code":"2.0",
    "gn:admin2_code":"5665.0",
    "gn:asciiname":"Zapindonga",
    "gn:country_code":"CO",
    "gn:dem":69,
    "gn:feature_class":"P",
    "gn:feature_code":"PPL",
    "gn:name":"Zapindonga",
    "gn:population":0,
    "gn:timezone":"America/Bogota",
    "iso:country":"CO",
    "wof:name":"Zapindonga",
    "wof:placetype":"locality"
},
  "geometry": {"coordinates":[-76.26909999999999,8.48515],"type":"Point"}
}