{
  "type": "Feature",
  "properties": {
    "gn:country":"CO",
    "gn:fcode":"PPL",
    "gn:pop":1879,
    "iso:country":"CO",
    "name:chi_x_preferred":[
        "\u4f0a\u840a\u65af"
    ],
    "name:dut_x_preferred":[
        "Iles"
    ],
    "name:eng_x_preferred":[
        "Iles"
    ],
    "name:fre_x_preferred":[
        "Iles"
    ],
    "name:geo_x_preferred":[
        "\u10d8\u10da\u10d8\u10d4\u10e1\u10d8"
    ],
    "name:ita_x_preferred":[
        "Iles"
    ],
    "name:may_x_preferred":[
        "Iles"
    ],
    "name:nan_x_preferred":[
        "Iles"
    ],
    "name:por_x_preferred":[
        "Iles"
    ],
    "name:spa_x_preferred":[
        "Iles"
    ],
    "name:swe_x_preferred":[
        "Iles"
    ],
    "name:tgl_x_preferred":[
        "Iles"
    ],
    "name:vie_x_preferred":[
        "Iles"
    ],
    "name:war_x_preferred":[
        "Iles"
    ],
    "qs:name":"Iles",
    "qs:photos_9r":0,
    "qs:photos_sr":0,
    "qs:pop_sr":"3",
    "wd:wordcount":122,
    "wof:name":"Iles",
    "wof:placetype":"locality",
    "wof:population":1879
},
  "geometry": {"coordinates":[-77.52741,0.97491],"type":"Point"}
}