{
  "type": "Feature",
  "properties": {
    "gn:admin1_code":"33.0",
    "gn:admin2_code":"25297.0",
    "gn:asciiname":"El Tablon",
    "gn:country_code":"CO",
    "gn:dem":2198,
    "gn:feature_class":"P",
    "gn:feature_code":"PPL",
    "gn:name":"El Tabl\u00f3n",
    "gn:population":0,
    "gn:timezone":"America/Bogota",
    "iso:country":"CO",
    "wof:name":"El Tablon",
    "wof:placetype":"locality"
},
  "geometry": {"coordinates":[-73.62026999999998,4.83914],"type":"Point"}
}