{
  "type": "Feature",
  "properties": {
    "gn:admin1_code":"32",
    "gn:admin2_code":"85410.0",
    "gn:asciiname":"Las Angosturas",
    "gn:country_code":"CO",
    "gn:dem":152,
    "gn:feature_class":"P",
    "gn:feature_code":"PPL",
    "gn:name":"Las Angosturas",
    "gn:population":0,
    "gn:timezone":"America/Bogota",
    "iso:country":"CO",
    "wof:name":"Las Angosturas",
    "wof:placetype":"locality"
},
  "geometry": {"coordinates":[-72.36248000000001,4.39243],"type":"Point"}
}