{
  "type": "Feature",
  "properties": {
    "gn:admin1_code":"10",
    "gn:admin2_code":"20175.0",
    "gn:asciiname":"Luna Nueva",
    "gn:country_code":"CO",
    "gn:dem":57,
    "gn:feature_class":"P",
    "gn:feature_code":"PPL",
    "gn:name":"Luna Nueva",
    "gn:population":0,
    "gn:timezone":"America/Bogota",
    "iso:country":"CO",
    "wof:name":"Luna Nueva",
    "wof:placetype":"locality"
},
  "geometry": {"coordinates":[-73.84528,9.32722],"type":"Point"}
}