{
  "type": "Feature",
  "properties": {
    "gn:admin1_code":"35",
    "gn:admin2_code":"13650.0",
    "gn:asciiname":"Calamar",
    "gn:cc2":"CO",
    "gn:country_code":"CO",
    "gn:dem":16,
    "gn:feature_class":"P",
    "gn:feature_code":"PPL",
    "gn:name":"Calamar",
    "gn:population":0,
    "gn:timezone":"America/Bogota",
    "iso:country":"CO",
    "name:deu_x_preferred":[
        "Calamar"
    ],
    "name:epo_x_preferred":[
        "Kalamaro"
    ],
    "name:fas_x_preferred":[
        "\u06a9\u0627\u0644\u0627\u0645\u0627\u0631"
    ],
    "name:fra_x_preferred":[
        "Calamar"
    ],
    "name:ita_x_preferred":[
        "Calamar"
    ],
    "name:kat_x_preferred":[
        "\u10d9\u10d0\u10da\u10d0\u10db\u10d0\u10e0\u10d8"
    ],
    "name:msa_x_preferred":[
        "Calamar"
    ],
    "name:nld_x_preferred":[
        "Calamar"
    ],
    "name:por_x_preferred":[
        "Calamar"
    ],
    "name:rus_x_preferred":[
        "\u041a\u0430\u043b\u0430\u043c\u0430\u0440"
    ],
    "name:spa_x_preferred":[
        "Calamar"
    ],
    "name:tgl_x_preferred":[
        "Calamar"
    ],
    "name:und_x_variant":[
        "Corregimiento Calamar"
    ],
    "name:vie_x_preferred":[
        "Calamar"
    ],
    "name:war_x_preferred":[
        "Calamar"
    ],
    "name:zho_x_preferred":[
        "\u5361\u62c9\u99ac\u723e"
    ],
    "wof:name":"Calamar",
    "wof:placetype":"locality"
},
  "geometry": {"coordinates":[-74.36944,9.01528],"type":"Point"}
}