{
  "type": "Feature",
  "properties": {
    "gn:admin1_code":"35",
    "gn:admin2_code":"13650.0",
    "gn:asciiname":"Calamar",
    "gn:cc2":"CO",
    "gn:country_code":"CO",
    "gn:dem":16,
    "gn:feature_class":"P",
    "gn:feature_code":"PPL",
    "gn:name":"Calamar",
    "gn:population":0,
    "gn:timezone":"America/Bogota",
    "iso:country":"CO",
    "name:und_x_variant":[
        "Corregimiento Calamar",
        "Calamar"
    ],
    "wof:name":"Calamar",
    "wof:placetype":"locality"
},
  "geometry": {"coordinates":[-74.36944,9.01528],"type":"Point"}
}