{
  "type": "Feature",
  "properties": {
    "gn:admin1_code":"36",
    "gn:admin2_code":"15542.0",
    "gn:asciiname":"El Guachal",
    "gn:country_code":"CO",
    "gn:dem":3389,
    "gn:feature_class":"P",
    "gn:feature_code":"PPL",
    "gn:name":"El Guachal",
    "gn:population":0,
    "gn:timezone":"America/Bogota",
    "iso:country":"CO",
    "wof:name":"El Guachal",
    "wof:placetype":"locality"
},
  "geometry": {"coordinates":[-73.09585,5.54154],"type":"Point"}
}