{
  "type": "Feature",
  "properties": {
    "gn:admin1_code":"2",
    "gn:admin2_code":"5051.0",
    "gn:asciiname":"Coracas",
    "gn:country_code":"CO",
    "gn:dem":22,
    "gn:feature_class":"P",
    "gn:feature_code":"PPL",
    "gn:name":"Coracas",
    "gn:population":0,
    "gn:timezone":"America/Bogota",
    "iso:country":"CO",
    "wof:name":"Coracas",
    "wof:placetype":"locality"
},
  "geometry": {"coordinates":[-76.41471999999997,8.83222],"type":"Point"}
}