{
  "type": "Feature",
  "properties": {
    "gn:admin1_code":"28.0",
    "gn:admin2_code":"73275.0",
    "gn:asciiname":"Upito",
    "gn:country_code":"CO",
    "gn:dem":311,
    "gn:feature_class":"P",
    "gn:feature_code":"PPL",
    "gn:name":"Upito",
    "gn:population":0,
    "gn:timezone":"America/Bogota",
    "iso:country":"CO",
    "name:und_x_variant":[
        "Sitio Upito",
        "Upito"
    ],
    "wof:name":"Upito",
    "wof:placetype":"locality"
},
  "geometry": {"coordinates":[-74.87993,4.25554],"type":"Point"}
}