{
  "type": "Feature",
  "properties": {
    "iso:country":"CO",
    "name:ast_x_preferred":[
        "Piedecuesta"
    ],
    "name:avk_x_preferred":[
        "Piedecuesta"
    ],
    "name:cat_x_preferred":[
        "Piedecuesta"
    ],
    "name:ceb_x_preferred":[
        "Piedecuesta"
    ],
    "name:dan_x_preferred":[
        "Piedecuesta"
    ],
    "name:deu_x_preferred":[
        "Piedecuesta"
    ],
    "name:eng_x_preferred":[
        "Piedecuesta"
    ],
    "name:fas_x_preferred":[
        "\u067e\u06cc\u062f\u0647 \u06a9\u0648\u0626\u0633\u062a\u0627"
    ],
    "name:fin_x_preferred":[
        "Piedecuesta"
    ],
    "name:fra_x_preferred":[
        "Piedecuesta"
    ],
    "name:gle_x_preferred":[
        "Piedecuesta"
    ],
    "name:glg_x_preferred":[
        "Piedecuesta"
    ],
    "name:ita_x_preferred":[
        "Piedecuesta"
    ],
    "name:kat_x_preferred":[
        "\u10de\u10d8\u10d4\u10d3\u10d4\u10d9\u10e3\u10d4\u10e1\u10e2\u10d0"
    ],
    "name:mlg_x_preferred":[
        "Piedecuesta"
    ],
    "name:msa_x_preferred":[
        "Piedecuesta"
    ],
    "name:nan_x_preferred":[
        "Piedecuesta"
    ],
    "name:nld_x_preferred":[
        "Piedecuesta"
    ],
    "name:nob_x_preferred":[
        "Piedecuesta"
    ],
    "name:pol_x_preferred":[
        "Piedecuesta"
    ],
    "name:rus_x_preferred":[
        "\u041f\u044c\u0435\u0434\u0435\u043a\u0443\u044d\u0441\u0442\u0430"
    ],
    "name:spa_x_preferred":[
        "Piedecuesta"
    ],
    "name:swe_x_preferred":[
        "Piedecuesta"
    ],
    "name:tat_x_preferred":[
        "\u041f\u044c\u0435\u0434\u0435\u043a\u0432\u0435\u0441\u0442\u0430"
    ],
    "name:tgl_x_preferred":[
        "Piedecuesta"
    ],
    "name:vie_x_preferred":[
        "Piedecuesta"
    ],
    "name:war_x_preferred":[
        "Piedecuesta"
    ],
    "name:zho_min_nan_x_preferred":[
        "Piedecuesta"
    ],
    "name:zho_x_preferred":[
        "\u5f7c\u5fb7\u594e\u65af\u5854"
    ],
    "qs:gn_country":"CO",
    "qs:gn_fcode":"PPL",
    "qs:gn_pop":86387,
    "qs:name":"Piedecuesta",
    "qs:name_adm0":"Colombia",
    "qs:name_adm1":"Santander",
    "qs:photos":202,
    "qs:photos_1k":41,
    "qs:photos_9k":1,
    "qs:photos_9r":4,
    "qs:photos_all":202,
    "qs:photos_sr":4,
    "qs:placetype":"Town",
    "qs:pop_sr":"8",
    "qs:woe_adm0":23424787,
    "wd:wordcount":416,
    "wof:name":"Piedecuesta",
    "wof:placetype":"locality",
    "wof:population":86387
},
  "geometry": {"coordinates":[-73.04953,6.98789],"type":"Point"}
}