{
  "type": "Feature",
  "properties": {
    "gn:country":"CO",
    "gn:fcode":"PPL",
    "gn:pop":21204,
    "iso:country":"CO",
    "name:eng_x_preferred":[
        "Sampu\u00e9s"
    ],
    "name:fas_x_preferred":[
        "\u0633\u0627\u0645\u067e\u0648\u0626\u0633"
    ],
    "name:fra_x_preferred":[
        "Sampu\u00e9s"
    ],
    "name:ita_x_preferred":[
        "Sampu\u00e9s"
    ],
    "name:kat_x_preferred":[
        "\u10e1\u10d0\u10db\u10de\u10e3\u10d4\u10e1\u10d8"
    ],
    "name:msa_x_preferred":[
        "Sampu\u00e9s"
    ],
    "name:nan_x_preferred":[
        "Sampu\u00e9s"
    ],
    "name:nld_x_preferred":[
        "Sampu\u00e9s"
    ],
    "name:spa_x_preferred":[
        "Sampu\u00e9s"
    ],
    "name:swe_x_preferred":[
        "Sampu\u00e9s"
    ],
    "name:vie_x_preferred":[
        "Sampu\u00e9s"
    ],
    "name:war_x_preferred":[
        "Sampu\u00e9s"
    ],
    "name:zho_x_preferred":[
        "\u6851\u666e\u57c3\u65af"
    ],
    "qs:name":"Sampu\u00e9s",
    "qs:photos_9r":0,
    "qs:photos_sr":0,
    "qs:pop_sr":"7",
    "wd:wordcount":63,
    "wof:name":"Sampu\u00e9s",
    "wof:placetype":"locality",
    "wof:population":21204
},
  "geometry": {"coordinates":[-75.38167,9.18361],"type":"Point"}
}