{
  "type": "Feature",
  "properties": {
    "gn:admin1_code":"29",
    "gn:admin2_code":"76364.0",
    "gn:asciiname":"Palmeras",
    "gn:country_code":"CO",
    "gn:dem":982,
    "gn:feature_class":"P",
    "gn:feature_code":"PPL",
    "gn:name":"Palmeras",
    "gn:population":0,
    "gn:timezone":"America/Bogota",
    "iso:country":"CO",
    "wof:name":"Palmeras",
    "wof:placetype":"locality"
},
  "geometry": {"coordinates":[-76.5475,3.23389],"type":"Point"}
}