{
  "type": "Feature",
  "properties": {
    "gn:admin1_code":"26",
    "gn:admin2_code":"68020.0",
    "gn:asciiname":"Verdugo",
    "gn:country_code":"CO",
    "gn:dem":2945,
    "gn:feature_class":"P",
    "gn:feature_code":"PPL",
    "gn:name":"Verdugo",
    "gn:population":0,
    "gn:timezone":"America/Bogota",
    "iso:country":"CO",
    "wof:name":"Verdugo",
    "wof:placetype":"locality"
},
  "geometry": {"coordinates":[-73.79194,5.74611],"type":"Point"}
}