{
  "type": "Feature",
  "properties": {
    "gn:admin1_code":"2",
    "gn:admin2_code":"5736.0",
    "gn:asciiname":"El Encantado",
    "gn:country_code":"CO",
    "gn:dem":238,
    "gn:feature_class":"P",
    "gn:feature_code":"PPL",
    "gn:name":"El Encantado",
    "gn:population":0,
    "gn:timezone":"America/Bogota",
    "iso:country":"CO",
    "wof:name":"El Encantado",
    "wof:placetype":"locality"
},
  "geometry": {"coordinates":[-74.79043,7.17847],"type":"Point"}
}