{
  "type": "Feature",
  "properties": {
    "gn:admin1_code":"20",
    "gn:admin2_code":"52287.0",
    "gn:asciiname":"Chapal",
    "gn:country_code":"CO",
    "gn:dem":2470,
    "gn:feature_class":"P",
    "gn:feature_code":"PPL",
    "gn:name":"Chapal",
    "gn:population":0,
    "gn:timezone":"America/Bogota",
    "iso:country":"CO",
    "name:und_x_variant":[
        "Chapa"
    ],
    "wof:name":"Chapal",
    "wof:placetype":"locality"
},
  "geometry": {"coordinates":[-77.45763000000002,0.94725],"type":"Point"}
}