{
  "type": "Feature",
  "properties": {
    "gn:admin1_code":"19",
    "gn:admin2_code":"50573.0",
    "gn:asciiname":"Cumaral",
    "gn:country_code":"CO",
    "gn:dem":164,
    "gn:feature_class":"P",
    "gn:feature_code":"PPL",
    "gn:name":"Cumaral",
    "gn:population":0,
    "gn:timezone":"America/Bogota",
    "iso:country":"CO",
    "name:ceb_x_preferred":[
        "Cumaral"
    ],
    "name:fra_x_preferred":[
        "Cumaral"
    ],
    "name:ita_x_preferred":[
        "Cumaral"
    ],
    "name:kat_x_preferred":[
        "\u10d9\u10e3\u10db\u10d0\u10e0\u10d0\u10da\u10d8"
    ],
    "name:msa_x_preferred":[
        "Cumaral"
    ],
    "name:nld_x_preferred":[
        "Cumaral"
    ],
    "name:por_x_preferred":[
        "Cumaral"
    ],
    "name:spa_x_preferred":[
        "Cumaral"
    ],
    "name:swe_x_preferred":[
        "Cumaral"
    ],
    "name:tgl_x_preferred":[
        "Cumaral"
    ],
    "name:vie_x_preferred":[
        "Cumaral"
    ],
    "name:war_x_preferred":[
        "Cumaral"
    ],
    "name:zho_x_preferred":[
        "\u5eab\u99ac\u62c9\u723e"
    ],
    "wof:name":"Cumaral",
    "wof:placetype":"locality"
},
  "geometry": {"coordinates":[-72.46193000000002,4.31909],"type":"Point"}
}