{
  "type": "Feature",
  "properties": {
    "gn:admin1_code":"19",
    "gn:admin2_code":"50573.0",
    "gn:asciiname":"Cumaral",
    "gn:country_code":"CO",
    "gn:dem":164,
    "gn:feature_class":"P",
    "gn:feature_code":"PPL",
    "gn:name":"Cumaral",
    "gn:population":0,
    "gn:timezone":"America/Bogota",
    "iso:country":"CO",
    "wof:name":"Cumaral",
    "wof:placetype":"locality"
},
  "geometry": {"coordinates":[-72.46193000000002,4.31909],"type":"Point"}
}