{
  "type": "Feature",
  "properties": {
    "gn:admin1_code":"3",
    "gn:admin2_code":"81591.0",
    "gn:asciiname":"El Paeno",
    "gn:country_code":"CO",
    "gn:dem":117,
    "gn:feature_class":"P",
    "gn:feature_code":"PPL",
    "gn:name":"El Pae\u00f1o",
    "gn:population":0,
    "gn:timezone":"America/Bogota",
    "iso:country":"CO",
    "name:spa_x_preferred":[
        "El Pae\u00f1o"
    ],
    "wof:name":"El Paeno",
    "wof:placetype":"locality"
},
  "geometry": {"coordinates":[-70.68952,6.53622],"type":"Point"}
}