{
  "type": "Feature",
  "properties": {
    "gn:admin1_code":"2.0",
    "gn:admin2_code":"5501.0",
    "gn:asciiname":"El Hoyo de La Pena",
    "gn:country_code":"CO",
    "gn:dem":2199,
    "gn:feature_class":"P",
    "gn:feature_code":"PPL",
    "gn:name":"El Hoyo de La Pe\u00f1a",
    "gn:population":0,
    "gn:timezone":"America/Bogota",
    "iso:country":"CO",
    "wof:name":"El Hoyo de La Pena",
    "wof:placetype":"locality"
},
  "geometry": {"coordinates":[-75.74583,6.63611],"type":"Point"}
}