{
  "type": "Feature",
  "properties": {
    "gn:admin1_code":"9.0",
    "gn:admin2_code":"19300.0",
    "gn:asciiname":"El Llanito",
    "gn:country_code":"CO",
    "gn:dem":1004,
    "gn:feature_class":"P",
    "gn:feature_code":"PPL",
    "gn:name":"El Llanito",
    "gn:population":0,
    "gn:timezone":"America/Bogota",
    "iso:country":"CO",
    "name:spa_x_preferred":[
        "El Llanito"
    ],
    "wof:name":"El Llanito",
    "wof:placetype":"locality"
},
  "geometry": {"coordinates":[-76.36884000000001,3.11072],"type":"Point"}
}