{
  "type": "Feature",
  "properties": {
    "gn:admin1_code":"10.0",
    "gn:admin2_code":"20570.0",
    "gn:asciiname":"Arizona",
    "gn:country_code":"CO",
    "gn:dem":316,
    "gn:feature_class":"P",
    "gn:feature_code":"PPL",
    "gn:name":"Arizona",
    "gn:population":0,
    "gn:timezone":"America/Bogota",
    "iso:country":"CO",
    "wof:name":"Arizona",
    "wof:placetype":"locality"
},
  "geometry": {"coordinates":[-73.48161999999998,10.36374],"type":"Point"}
}