{
  "type": "Feature",
  "properties": {
    "gn:admin1_code":"19.0",
    "gn:admin2_code":"50370.0",
    "gn:asciiname":"La Uribe",
    "gn:country_code":"CO",
    "gn:dem":705,
    "gn:feature_class":"P",
    "gn:feature_code":"PPL",
    "gn:name":"La Uribe",
    "gn:population":0,
    "gn:timezone":"America/Bogota",
    "iso:country":"CO",
    "name:und_x_variant":[
        "Uribe",
        "La Uribe"
    ],
    "wof:name":"La Uribe",
    "wof:placetype":"locality"
},
  "geometry": {"coordinates":[-74.35496999999999,3.2409],"type":"Point"}
}