{
  "type": "Feature",
  "properties": {
    "gn:admin1_code":"19.0",
    "gn:admin2_code":"50370.0",
    "gn:asciiname":"La Uribe",
    "gn:country_code":"CO",
    "gn:dem":705,
    "gn:feature_class":"P",
    "gn:feature_code":"PPL",
    "gn:name":"La Uribe",
    "gn:population":0,
    "gn:timezone":"America/Bogota",
    "iso:country":"CO",
    "name:fra_x_preferred":[
        "La Uribe"
    ],
    "name:ita_x_preferred":[
        "Uribe"
    ],
    "name:kat_x_preferred":[
        "\u10da\u10d0-\u10e3\u10e0\u10d8\u10d1\u10d4"
    ],
    "name:msa_x_preferred":[
        "La Uribe"
    ],
    "name:nld_x_preferred":[
        "Uribe"
    ],
    "name:por_x_preferred":[
        "La Uribe"
    ],
    "name:spa_x_preferred":[
        "La Uribe"
    ],
    "name:tgl_x_preferred":[
        "La Uribe"
    ],
    "name:urd_x_preferred":[
        "\u0644\u0627 \u06cc\u0648\u0631\u0627\u0626\u0628"
    ],
    "name:vie_x_preferred":[
        "La Uribe"
    ],
    "name:war_x_preferred":[
        "La Uribe"
    ],
    "name:zho_x_preferred":[
        "\u62c9\u70cf\u91cc\u97cb"
    ],
    "wof:name":"La Uribe",
    "wof:placetype":"locality"
},
  "geometry": {"coordinates":[-74.35496999999999,3.2409],"type":"Point"}
}