{
  "type": "Feature",
  "properties": {
    "gn:admin1_code":"9",
    "gn:admin2_code":"19450.0",
    "gn:asciiname":"Guatacama",
    "gn:country_code":"CO",
    "gn:dem":860,
    "gn:feature_class":"P",
    "gn:feature_code":"PPL",
    "gn:name":"Guatacama",
    "gn:population":0,
    "gn:timezone":"America/Bogota",
    "iso:country":"CO",
    "wof:name":"Guatacama",
    "wof:placetype":"locality"
},
  "geometry": {"coordinates":[-77.17282,1.85663],"type":"Point"}
}