{
  "type": "Feature",
  "properties": {
    "gn:admin1_code":"14.0",
    "gn:admin2_code":"95200.0",
    "gn:asciiname":"Pompeya",
    "gn:country_code":"CO",
    "gn:dem":213,
    "gn:feature_class":"P",
    "gn:feature_code":"PPL",
    "gn:name":"Pompeya",
    "gn:population":0,
    "gn:timezone":"America/Bogota",
    "iso:country":"CO",
    "wof:name":"Pompeya",
    "wof:placetype":"locality"
},
  "geometry": {"coordinates":[-71.94977,1.28211],"type":"Point"}
}