{
  "type": "Feature",
  "properties": {
    "gn:admin1_code":"28",
    "gn:admin2_code":"73067.0",
    "gn:asciiname":"Las Ceibas",
    "gn:country_code":"CO",
    "gn:dem":1038,
    "gn:feature_class":"P",
    "gn:feature_code":"PPL",
    "gn:name":"Las Ceibas",
    "gn:population":0,
    "gn:timezone":"America/Bogota",
    "iso:country":"CO",
    "wof:name":"Las Ceibas",
    "wof:placetype":"locality"
},
  "geometry": {"coordinates":[-75.51028000000002,3.43972],"type":"Point"}
}