{
  "type": "Feature",
  "properties": {
    "gn:admin1_code":"2",
    "gn:admin2_code":"5237.0",
    "gn:asciiname":"Bocatoma",
    "gn:country_code":"CO",
    "gn:dem":2147,
    "gn:feature_class":"P",
    "gn:feature_code":"PPL",
    "gn:name":"Bocatoma",
    "gn:population":0,
    "gn:timezone":"America/Bogota",
    "iso:country":"CO",
    "name:und_x_variant":[
        "Bocatara",
        "Bocatoma"
    ],
    "wof:name":"Bocatoma",
    "wof:placetype":"locality"
},
  "geometry": {"coordinates":[-75.40734999999999,6.50698],"type":"Point"}
}