{
  "type": "Feature",
  "properties": {
    "gn:admin1_code":"36",
    "gn:admin2_code":"15776.0",
    "gn:asciiname":"Matacolorada",
    "gn:country_code":"CO",
    "gn:dem":3192,
    "gn:feature_class":"P",
    "gn:feature_code":"PPL",
    "gn:name":"Matacolorada",
    "gn:population":0,
    "gn:timezone":"America/Bogota",
    "iso:country":"CO",
    "wof:name":"Matacolorada",
    "wof:placetype":"locality"
},
  "geometry": {"coordinates":[-73.645,5.70056],"type":"Point"}
}