{
  "type": "Feature",
  "properties": {
    "gn:admin1_code":"19",
    "gn:admin2_code":"50370.0",
    "gn:asciiname":"La Guajira",
    "gn:country_code":"CO",
    "gn:dem":1517,
    "gn:feature_class":"P",
    "gn:feature_code":"PPL",
    "gn:name":"La Guajira",
    "gn:population":0,
    "gn:timezone":"America/Bogota",
    "iso:country":"CO",
    "name:spa_x_preferred":[
        "La Guajira"
    ],
    "wof:name":"La Guajira",
    "wof:placetype":"locality"
},
  "geometry": {"coordinates":[-74.37915,3.57524],"type":"Point"}
}