{
  "type": "Feature",
  "properties": {
    "gn:admin1_code":"33.0",
    "gn:admin2_code":"25320.0",
    "gn:asciiname":"Balooncito",
    "gn:country_code":"CO",
    "gn:dem":1381,
    "gn:feature_class":"P",
    "gn:feature_code":"PPL",
    "gn:name":"Balooncito",
    "gn:population":0,
    "gn:timezone":"America/Bogota",
    "iso:country":"CO",
    "name:spa_x_preferred":[
        "Balooncito"
    ],
    "wof:name":"Balooncito",
    "wof:placetype":"locality"
},
  "geometry": {"coordinates":[-74.58436,5.00212],"type":"Point"}
}