{
  "type": "Feature",
  "properties": {
    "gn:admin1_code":"2.0",
    "gn:admin2_code":"5887.0",
    "gn:asciiname":"El Penol",
    "gn:country_code":"CO",
    "gn:dem":2703,
    "gn:feature_class":"P",
    "gn:feature_code":"PPL",
    "gn:name":"El Pe\u00f1ol",
    "gn:population":0,
    "gn:timezone":"America/Bogota",
    "iso:country":"CO",
    "wof:name":"El Penol",
    "wof:placetype":"locality"
},
  "geometry": {"coordinates":[-75.51167,6.88861],"type":"Point"}
}