{
  "type": "Feature",
  "properties": {
    "gn:admin1_code":"9.0",
    "gn:admin2_code":"19824.0",
    "gn:asciiname":"Hacienda Santa Teresa",
    "gn:country_code":"CO",
    "gn:dem":2585,
    "gn:feature_class":"P",
    "gn:feature_code":"PPL",
    "gn:name":"Hacienda Santa Teresa",
    "gn:population":0,
    "gn:timezone":"America/Bogota",
    "iso:country":"CO",
    "name:spa_x_preferred":[
        "Hacienda Santa Teresa"
    ],
    "wof:name":"Hacienda Santa Teresa",
    "wof:placetype":"locality"
},
  "geometry": {"coordinates":[-76.44058000000003,2.46449],"type":"Point"}
}