{
  "type": "Feature",
  "properties": {
    "gn:admin1_code":"2",
    "gn:admin2_code":"5361.0",
    "gn:asciiname":"El Filo",
    "gn:country_code":"CO",
    "gn:dem":1683,
    "gn:feature_class":"P",
    "gn:feature_code":"PPL",
    "gn:name":"El Filo",
    "gn:population":0,
    "gn:timezone":"America/Bogota",
    "iso:country":"CO",
    "wof:name":"El Filo",
    "wof:placetype":"locality"
},
  "geometry": {"coordinates":[-75.72833,7.29472],"type":"Point"}
}