{
  "type": "Feature",
  "properties": {
    "gn:admin1_code":"36.0",
    "gn:admin2_code":"15223.0",
    "gn:asciiname":"Tegria",
    "gn:country_code":"CO",
    "gn:dem":1475,
    "gn:feature_class":"P",
    "gn:feature_code":"PPL",
    "gn:name":"Tegr\u00eda",
    "gn:population":0,
    "gn:timezone":"America/Bogota",
    "iso:country":"CO",
    "wof:name":"Tegria",
    "wof:placetype":"locality"
},
  "geometry": {"coordinates":[-72.15000000000001,6.86667],"type":"Point"}
}