{
  "type": "Feature",
  "properties": {
    "gn:admin1_code":"27",
    "gn:admin2_code":"70823.0",
    "gn:asciiname":"El Suan",
    "gn:country_code":"CO",
    "gn:dem":121,
    "gn:feature_class":"P",
    "gn:feature_code":"PPL",
    "gn:name":"El Suan",
    "gn:population":0,
    "gn:timezone":"America/Bogota",
    "iso:country":"CO",
    "wof:name":"El Suan",
    "wof:placetype":"locality"
},
  "geometry": {"coordinates":[-75.39461999999997,9.46874],"type":"Point"}
}