{
  "type": "Feature",
  "properties": {
    "gn:admin1_code":"20",
    "gn:admin2_code":"52835.0",
    "gn:asciiname":"Chontal",
    "gn:country_code":"CO",
    "gn:dem":4,
    "gn:feature_class":"P",
    "gn:feature_code":"PPL",
    "gn:name":"Chontal",
    "gn:population":0,
    "gn:timezone":"America/Bogota",
    "iso:country":"CO",
    "name:deu_x_preferred":[
        "Chontal"
    ],
    "name:nld_x_preferred":[
        "Chontal"
    ],
    "name:rus_x_preferred":[
        "\u0427\u043e\u043d\u0442\u0430\u043b\u0438"
    ],
    "name:spa_x_preferred":[
        "Chontal"
    ],
    "name:tur_x_preferred":[
        "\u00c7ontal"
    ],
    "wof:name":"Chontal",
    "wof:placetype":"locality"
},
  "geometry": {"coordinates":[-78.89234,1.54931],"type":"Point"}
}