{
  "type": "Feature",
  "properties": {
    "gn:admin1_code":"19.0",
    "gn:admin2_code":"50711.0",
    "gn:asciiname":"Cunimia",
    "gn:country_code":"CO",
    "gn:dem":236,
    "gn:feature_class":"P",
    "gn:feature_code":"PPL",
    "gn:name":"Cunim\u00eda",
    "gn:population":0,
    "gn:timezone":"America/Bogota",
    "iso:country":"CO",
    "wof:name":"Cunimia",
    "wof:placetype":"locality"
},
  "geometry": {"coordinates":[-73.59389,3.15917],"type":"Point"}
}