{
  "type": "Feature",
  "properties": {
    "gn:admin1_code":"29",
    "gn:admin2_code":"76622.0",
    "gn:asciiname":"Cajamarca",
    "gn:country_code":"CO",
    "gn:dem":1459,
    "gn:feature_class":"P",
    "gn:feature_code":"PPL",
    "gn:name":"Cajamarca",
    "gn:population":0,
    "gn:timezone":"America/Bogota",
    "iso:country":"CO",
    "wof:name":"Cajamarca",
    "wof:placetype":"locality"
},
  "geometry": {"coordinates":[-76.21465999999999,4.48217],"type":"Point"}
}