{
  "type": "Feature",
  "properties": {
    "iso:country":"CO",
    "name:ast_x_preferred":[
        "Arboledas"
    ],
    "name:ceb_x_preferred":[
        "Arboledas"
    ],
    "name:eng_x_preferred":[
        "Arboledas"
    ],
    "name:fra_x_preferred":[
        "Arboledas"
    ],
    "name:ita_x_preferred":[
        "Arboledas"
    ],
    "name:kat_x_preferred":[
        "\u10d0\u10e0\u10d1\u10dd\u10da\u10d4\u10d3\u10d0\u10e1\u10d8"
    ],
    "name:msa_x_preferred":[
        "Arboledas"
    ],
    "name:nan_x_preferred":[
        "Arboledas"
    ],
    "name:nld_x_preferred":[
        "Arboledas"
    ],
    "name:por_x_preferred":[
        "Arboledas"
    ],
    "name:spa_x_preferred":[
        "Arboledas"
    ],
    "name:swe_x_preferred":[
        "Arboledas"
    ],
    "name:tgl_x_preferred":[
        "Arboledas"
    ],
    "name:vie_x_preferred":[
        "Arboledas"
    ],
    "name:war_x_preferred":[
        "Arboledas"
    ],
    "name:zho_x_preferred":[
        "\u963f\u6c83\u840a\u9054\u65af"
    ],
    "qs:gn_country":"CO",
    "qs:gn_fcode":"PPL",
    "qs:gn_pop":2702,
    "qs:name":"Arboledas",
    "qs:name_adm0":"Colombia",
    "qs:name_adm1":"Norte de Santander",
    "qs:photos":0,
    "qs:photos_1k":0,
    "qs:photos_9k":1,
    "qs:photos_9r":1,
    "qs:photos_all":7,
    "qs:photos_sr":0,
    "qs:placetype":"Town",
    "qs:pop_sr":"4",
    "qs:woe_adm0":23424787,
    "wof:name":"Arboledas",
    "wof:placetype":"locality",
    "wof:population":2702
},
  "geometry": {"coordinates":[-72.79944,7.64233],"type":"Point"}
}