{
  "type": "Feature",
  "properties": {
    "gn:admin1_code":"12",
    "gn:admin2_code":"23001.0",
    "gn:asciiname":"Cuchara",
    "gn:country_code":"CO",
    "gn:dem":74,
    "gn:feature_class":"P",
    "gn:feature_code":"PPL",
    "gn:name":"Cuchara",
    "gn:population":0,
    "gn:timezone":"America/Bogota",
    "iso:country":"CO",
    "wof:name":"Cuchara",
    "wof:placetype":"locality"
},
  "geometry": {"coordinates":[-76.15805,8.91546],"type":"Point"}
}