{
  "type": "Feature",
  "properties": {
    "gn:admin1_code":"27.0",
    "gn:admin2_code":"70702.0",
    "gn:asciiname":"Sacateca",
    "gn:country_code":"CO",
    "gn:dem":123,
    "gn:feature_class":"P",
    "gn:feature_code":"PPL",
    "gn:name":"Sacateca",
    "gn:population":0,
    "gn:timezone":"America/Bogota",
    "iso:country":"CO",
    "wof:name":"Sacateca",
    "wof:placetype":"locality"
},
  "geometry": {"coordinates":[-75.22215,9.28183],"type":"Point"}
}