{
  "type": "Feature",
  "properties": {
    "gn:admin1_code":"2.0",
    "gn:admin2_code":"5086.0",
    "gn:asciiname":"El Cateo",
    "gn:country_code":"CO",
    "gn:dem":2688,
    "gn:feature_class":"P",
    "gn:feature_code":"PPL",
    "gn:name":"El Cateo",
    "gn:population":0,
    "gn:timezone":"America/Bogota",
    "iso:country":"CO",
    "wof:name":"El Cateo",
    "wof:placetype":"locality"
},
  "geometry": {"coordinates":[-75.65000000000001,6.74472],"type":"Point"}
}