{
  "type": "Feature",
  "properties": {
    "gn:admin1_code":"3",
    "gn:admin2_code":"81001.0",
    "gn:asciiname":"Los Cocuisos",
    "gn:country_code":"CO",
    "gn:dem":116,
    "gn:feature_class":"P",
    "gn:feature_code":"PPL",
    "gn:name":"Los Cocuisos",
    "gn:population":0,
    "gn:timezone":"America/Bogota",
    "iso:country":"CO",
    "wof:name":"Los Cocuisos",
    "wof:placetype":"locality"
},
  "geometry": {"coordinates":[-70.48283000000001,6.68451],"type":"Point"}
}