{
  "type": "Feature",
  "properties": {
    "gn:admin1_code":"8.0",
    "gn:asciiname":"La Tebaida",
    "gn:country_code":"CO",
    "gn:dem":196,
    "gn:feature_class":"P",
    "gn:feature_code":"PPL",
    "gn:name":"La Tebaida",
    "gn:population":0,
    "gn:timezone":"America/Bogota",
    "iso:country":"CO",
    "name:spa_x_preferred":[
        "La Tebaida"
    ],
    "wof:name":"La Tebaida",
    "wof:placetype":"locality"
},
  "geometry": {"coordinates":[-75.26317,0.69712],"type":"Point"}
}