{
  "type": "Feature",
  "properties": {
    "gn:admin1_code":"26.0",
    "gn:admin2_code":"68001.0",
    "gn:asciiname":"Vistahermosa",
    "gn:country_code":"CO",
    "gn:dem":1638,
    "gn:feature_class":"P",
    "gn:feature_code":"PPL",
    "gn:name":"Vistahermosa",
    "gn:population":0,
    "gn:timezone":"America/Bogota",
    "iso:country":"CO",
    "name:spa_x_preferred":[
        "Vistahermosa"
    ],
    "wof:name":"Vistahermosa",
    "wof:placetype":"locality"
},
  "geometry": {"coordinates":[-73.05982,7.13376],"type":"Point"}
}