{
  "type": "Feature",
  "properties": {
    "gn:admin1_code":"26",
    "gn:admin2_code":"68176.0",
    "gn:asciiname":"La Teja",
    "gn:country_code":"CO",
    "gn:dem":910,
    "gn:feature_class":"P",
    "gn:feature_code":"PPL",
    "gn:name":"La Teja",
    "gn:population":0,
    "gn:timezone":"America/Bogota",
    "iso:country":"CO",
    "name:cat_x_preferred":[
        "La Teja"
    ],
    "name:deu_x_preferred":[
        "La Teja"
    ],
    "name:spa_x_preferred":[
        "La Teja"
    ],
    "name:urd_x_preferred":[
        "\u0644\u0627 \u062a\u06cc\u062d\u0627"
    ],
    "wof:name":"La Teja",
    "wof:placetype":"locality"
},
  "geometry": {"coordinates":[-73.33333,6.38333],"type":"Point"}
}