{
  "type": "Feature",
  "properties": {
    "gn:admin1_code":"8.0",
    "gn:admin2_code":"18860.0",
    "gn:asciiname":"Kilometro Dieciocho",
    "gn:country_code":"CO",
    "gn:dem":231,
    "gn:feature_class":"P",
    "gn:feature_code":"PPL",
    "gn:name":"Kil\u00f3metro Dieciocho",
    "gn:population":0,
    "gn:timezone":"America/Bogota",
    "iso:country":"CO",
    "name:spa_x_preferred":[
        "Kil\u00f3metro Dieciocho"
    ],
    "name:und_x_variant":[
        "Kil\u00f3metro 18"
    ],
    "wof:name":"Kilometro Dieciocho",
    "wof:placetype":"locality"
},
  "geometry": {"coordinates":[-75.67514,1.08681],"type":"Point"}
}