{
  "type": "Feature",
  "properties": {
    "gn:admin1_code":"26.0",
    "gn:admin2_code":"68575.0",
    "gn:asciiname":"Pradilla",
    "gn:country_code":"CO",
    "gn:dem":121,
    "gn:feature_class":"P",
    "gn:feature_code":"PPL",
    "gn:name":"Pradilla",
    "gn:population":0,
    "gn:timezone":"America/Bogota",
    "iso:country":"CO",
    "name:und_x_variant":[
        "Corregimiento Pradilla",
        "Pradilla"
    ],
    "wof:name":"Pradilla",
    "wof:placetype":"locality"
},
  "geometry": {"coordinates":[-73.67964000000001,7.34852],"type":"Point"}
}