{
  "type": "Feature",
  "properties": {
    "gn:admin1_code":"24",
    "gn:admin2_code":"66440.0",
    "gn:asciiname":"Beltran",
    "gn:country_code":"CO",
    "gn:dem":925,
    "gn:feature_class":"P",
    "gn:feature_code":"PPL",
    "gn:name":"Beltr\u00e1n",
    "gn:population":0,
    "gn:timezone":"America/Bogota",
    "iso:country":"CO",
    "wof:name":"Beltran",
    "wof:placetype":"locality"
},
  "geometry": {"coordinates":[-75.79194,4.96194],"type":"Point"}
}