{
  "type": "Feature",
  "properties": {
    "gn:admin1_code":"2",
    "gn:admin2_code":"5034.0",
    "gn:asciiname":"La Quinta",
    "gn:country_code":"CO",
    "gn:dem":1852,
    "gn:feature_class":"P",
    "gn:feature_code":"PPL",
    "gn:name":"La Quinta",
    "gn:population":0,
    "gn:timezone":"America/Bogota",
    "iso:country":"CO",
    "wof:name":"La Quinta",
    "wof:placetype":"locality"
},
  "geometry": {"coordinates":[-75.91533000000003,5.59843],"type":"Point"}
}