{
  "type": "Feature",
  "properties": {
    "gn:admin1_code":"19",
    "gn:admin2_code":"50568.0",
    "gn:asciiname":"El Avelinero",
    "gn:country_code":"CO",
    "gn:dem":196,
    "gn:feature_class":"P",
    "gn:feature_code":"PPL",
    "gn:name":"El Avelinero",
    "gn:population":0,
    "gn:timezone":"America/Bogota",
    "iso:country":"CO",
    "wof:name":"El Avelinero",
    "wof:placetype":"locality"
},
  "geometry": {"coordinates":[-72.03933000000001,4.26318],"type":"Point"}
}