{
  "type": "Feature",
  "properties": {
    "gn:admin1_code":"9.0",
    "gn:admin2_code":"19300.0",
    "gn:asciiname":"El Guabal",
    "gn:country_code":"CO",
    "gn:dem":973,
    "gn:feature_class":"P",
    "gn:feature_code":"PPL",
    "gn:name":"El Guabal",
    "gn:population":0,
    "gn:timezone":"America/Bogota",
    "iso:country":"CO",
    "name:spa_x_preferred":[
        "El Guabal"
    ],
    "wof:name":"El Guabal",
    "wof:placetype":"locality"
},
  "geometry": {"coordinates":[-76.40819999999999,3.18688],"type":"Point"}
}