{
  "type": "Feature",
  "properties": {
    "gn:admin1_code":"20",
    "gn:admin2_code":"52788.0",
    "gn:asciiname":"Chavez",
    "gn:country_code":"CO",
    "gn:dem":2689,
    "gn:feature_class":"P",
    "gn:feature_code":"PPL",
    "gn:name":"Chavez",
    "gn:population":0,
    "gn:timezone":"America/Bogota",
    "iso:country":"CO",
    "name:und_x_variant":[
        "Chaves"
    ],
    "wof:name":"Chavez",
    "wof:placetype":"locality"
},
  "geometry": {"coordinates":[-77.37181,1.10161],"type":"Point"}
}