{
  "type": "Feature",
  "properties": {
    "gn:admin1_code":"3",
    "gn:admin2_code":"81001.0",
    "gn:asciiname":"El Cid",
    "gn:country_code":"CO",
    "gn:dem":125,
    "gn:feature_class":"P",
    "gn:feature_code":"PPL",
    "gn:name":"El Cid",
    "gn:population":0,
    "gn:timezone":"America/Bogota",
    "iso:country":"CO",
    "wof:name":"El Cid",
    "wof:placetype":"locality"
},
  "geometry": {"coordinates":[-70.8734,6.77266],"type":"Point"}
}