{
  "type": "Feature",
  "properties": {
    "gn:admin1_code":"16.0",
    "gn:admin2_code":"41013.0",
    "gn:asciiname":"La Tunica",
    "gn:country_code":"CO",
    "gn:dem":1156,
    "gn:feature_class":"P",
    "gn:feature_code":"PPL",
    "gn:name":"La T\u00fanica",
    "gn:population":0,
    "gn:timezone":"America/Bogota",
    "iso:country":"CO",
    "wof:name":"La Tunica",
    "wof:placetype":"locality"
},
  "geometry": {"coordinates":[-75.74594,2.33268],"type":"Point"}
}