{
  "type": "Feature",
  "properties": {
    "gn:admin1_code":"2",
    "gn:admin2_code":"5051.0",
    "gn:asciiname":"Pelayo",
    "gn:country_code":"CO",
    "gn:dem":65,
    "gn:feature_class":"P",
    "gn:feature_code":"PPL",
    "gn:name":"Pelayo",
    "gn:population":0,
    "gn:timezone":"America/Bogota",
    "iso:country":"CO",
    "name:bre_x_preferred":[
        "Pelayo"
    ],
    "name:cat_x_preferred":[
        "Pelayo"
    ],
    "name:deu_x_preferred":[
        "Pelayo"
    ],
    "name:fra_x_preferred":[
        "Pelayo"
    ],
    "name:rus_x_preferred":[
        "\u041f\u0435\u043b\u0430\u0439\u043e"
    ],
    "name:spa_x_preferred":[
        "Pelayo"
    ],
    "wof:name":"Pelayo",
    "wof:placetype":"locality"
},
  "geometry": {"coordinates":[-76.33374000000001,8.53003],"type":"Point"}
}