{
  "type": "Feature",
  "properties": {
    "gn:admin1_code":"9",
    "gn:admin2_code":"19137.0",
    "gn:asciiname":"La Floresia",
    "gn:country_code":"CO",
    "gn:dem":1665,
    "gn:feature_class":"P",
    "gn:feature_code":"PPL",
    "gn:name":"La Floresia",
    "gn:population":0,
    "gn:timezone":"America/Bogota",
    "iso:country":"CO",
    "wof:name":"La Floresia",
    "wof:placetype":"locality"
},
  "geometry": {"coordinates":[-76.51383,2.78237],"type":"Point"}
}