{
  "type": "Feature",
  "properties": {
    "gn:admin1_code":"29",
    "gn:admin2_code":"76736.0",
    "gn:asciiname":"La Traviata",
    "gn:country_code":"CO",
    "gn:dem":3221,
    "gn:feature_class":"P",
    "gn:feature_code":"PPL",
    "gn:name":"La Traviata",
    "gn:population":0,
    "gn:timezone":"America/Bogota",
    "iso:country":"CO",
    "wof:name":"La Traviata",
    "wof:placetype":"locality"
},
  "geometry": {"coordinates":[-75.80944000000002,3.99611],"type":"Point"}
}