{
  "type": "Feature",
  "properties": {
    "gn:admin1_code":"2",
    "gn:admin2_code":"5120.0",
    "gn:asciiname":"Guarumo",
    "gn:country_code":"CO",
    "gn:dem":59,
    "gn:feature_class":"P",
    "gn:feature_code":"PPL",
    "gn:name":"Guarumo",
    "gn:population":0,
    "gn:timezone":"America/Bogota",
    "iso:country":"CO",
    "wof:name":"Guarumo",
    "wof:placetype":"locality"
},
  "geometry": {"coordinates":[-75.20753000000001,7.86059],"type":"Point"}
}