{
  "type": "Feature",
  "properties": {
    "gn:admin1_code":"16.0",
    "gn:admin2_code":"41872.0",
    "gn:asciiname":"Pena Amarilla",
    "gn:country_code":"CO",
    "gn:dem":394,
    "gn:feature_class":"P",
    "gn:feature_code":"PPL",
    "gn:name":"Pe\u00f1a Amarilla",
    "gn:population":0,
    "gn:timezone":"America/Bogota",
    "iso:country":"CO",
    "wof:name":"Pena Amarilla",
    "wof:placetype":"locality"
},
  "geometry": {"coordinates":[-75.26666999999998,3.15],"type":"Point"}
}