{
  "type": "Feature",
  "properties": {
    "gn:admin1_code":"9",
    "gn:admin2_code":"19050.0",
    "gn:asciiname":"La Belleza",
    "gn:country_code":"CO",
    "gn:dem":2034,
    "gn:feature_class":"P",
    "gn:feature_code":"PPL",
    "gn:name":"La Belleza",
    "gn:population":0,
    "gn:timezone":"America/Bogota",
    "iso:country":"CO",
    "wof:name":"La Belleza",
    "wof:placetype":"locality"
},
  "geometry": {"coordinates":[-77.21666999999999,2.25],"type":"Point"}
}