{
  "type": "Feature",
  "properties": {
    "gn:admin1_code":"12",
    "gn:admin2_code":"23001.0",
    "gn:asciiname":"Boca de la Balsa",
    "gn:cc2":"CO",
    "gn:country_code":"CO",
    "gn:dem":93,
    "gn:feature_class":"P",
    "gn:feature_code":"PPL",
    "gn:name":"Boca de la Balsa",
    "gn:population":0,
    "gn:timezone":"America/Bogota",
    "iso:country":"CO",
    "name:und_x_variant":[
        "Boca de Balsa",
        "Boca de la Balsa"
    ],
    "wof:name":"Boca de la Balsa",
    "wof:placetype":"locality"
},
  "geometry": {"coordinates":[-76.20999999999999,8.53111],"type":"Point"}
}