{
  "type": "Feature",
  "properties": {
    "gn:admin1_code":"16.0",
    "gn:asciiname":"La Arenera",
    "gn:country_code":"CO",
    "gn:dem":1924,
    "gn:feature_class":"P",
    "gn:feature_code":"PPL",
    "gn:name":"La Arenera",
    "gn:population":0,
    "gn:timezone":"America/Bogota",
    "iso:country":"CO",
    "name:spa_x_preferred":[
        "La Arenera"
    ],
    "wof:name":"La Arenera",
    "wof:placetype":"locality"
},
  "geometry": {"coordinates":[-74.83866,3.46633],"type":"Point"}
}