{
  "type": "Feature",
  "properties": {
    "gn:admin1_code":"26",
    "gn:admin2_code":"68020.0",
    "gn:asciiname":"Tauces",
    "gn:country_code":"CO",
    "gn:dem":1849,
    "gn:feature_class":"P",
    "gn:feature_code":"PPL",
    "gn:name":"Tauces",
    "gn:population":0,
    "gn:timezone":"America/Bogota",
    "iso:country":"CO",
    "wof:name":"Tauces",
    "wof:placetype":"locality"
},
  "geometry": {"coordinates":[-73.81166999999998,5.81472],"type":"Point"}
}