{
  "type": "Feature",
  "properties": {
    "gn:admin1_code":"31",
    "gn:admin2_code":"99773.0",
    "gn:asciiname":"Maipures",
    "gn:country_code":"CO",
    "gn:dem":87,
    "gn:feature_class":"P",
    "gn:feature_code":"PPL",
    "gn:name":"Maipures",
    "gn:population":0,
    "gn:timezone":"America/Bogota",
    "iso:country":"CO",
    "wof:name":"Maipures",
    "wof:placetype":"locality"
},
  "geometry": {"coordinates":[-67.83386999999999,5.20026],"type":"Point"}
}