{
  "type": "Feature",
  "properties": {
    "gn:admin1_code":"38.0",
    "gn:admin2_code":"47268.0",
    "gn:asciiname":"Zacapa",
    "gn:country_code":"CO",
    "gn:dem":36,
    "gn:feature_class":"P",
    "gn:feature_code":"PPL",
    "gn:name":"Zacapa",
    "gn:population":0,
    "gn:timezone":"America/Bogota",
    "iso:country":"CO",
    "name:ara_x_preferred":[
        "\u062b\u0627\u0643\u0627\u0628\u0627"
    ],
    "name:ceb_x_preferred":[
        "Zacapa"
    ],
    "name:dan_x_preferred":[
        "Zacapa"
    ],
    "name:deu_x_preferred":[
        "Zacapa"
    ],
    "name:fra_x_preferred":[
        "Zacapa"
    ],
    "name:ind_x_preferred":[
        "Zacapa"
    ],
    "name:ita_x_preferred":[
        "Zacapa"
    ],
    "name:kor_x_preferred":[
        "\uc0ac\uce74\ud30c"
    ],
    "name:lit_x_preferred":[
        "Sakapa"
    ],
    "name:nld_x_preferred":[
        "Zacapa"
    ],
    "name:pol_x_preferred":[
        "Zacapa"
    ],
    "name:por_x_preferred":[
        "Zacapa"
    ],
    "name:sco_x_preferred":[
        "Zacapa"
    ],
    "name:sme_x_preferred":[
        "Zacapa"
    ],
    "name:spa_x_preferred":[
        "Zacapa"
    ],
    "name:swe_x_preferred":[
        "Zacapa"
    ],
    "name:ukr_x_preferred":[
        "\u0421\u0430\u043a\u0430\u043f\u0430"
    ],
    "name:und_x_variant":[
        "Hacienda Zacapa"
    ],
    "name:urd_x_preferred":[
        "\u0632\u06a9\u067e\u0627"
    ],
    "name:zho_x_preferred":[
        "\u85a9\u5361\u5e15"
    ],
    "wof:name":"Zacapa",
    "wof:placetype":"locality"
},
  "geometry": {"coordinates":[-74.24565,10.58333],"type":"Point"}
}