{
  "type": "Feature",
  "properties": {
    "gn:admin1_code":"26",
    "gn:admin2_code":"68655.0",
    "gn:asciiname":"Copebarro",
    "gn:country_code":"CO",
    "gn:dem":78,
    "gn:feature_class":"P",
    "gn:feature_code":"PPL",
    "gn:name":"Copebarro",
    "gn:population":0,
    "gn:timezone":"America/Bogota",
    "iso:country":"CO",
    "wof:name":"Copebarro",
    "wof:placetype":"locality"
},
  "geometry": {"coordinates":[-73.61610999999998,7.48167],"type":"Point"}
}