{
  "type": "Feature",
  "properties": {
    "gn:admin1_code":"11.0",
    "gn:admin2_code":"27491.0",
    "gn:asciiname":"Calle Honda",
    "gn:country_code":"CO",
    "gn:dem":31,
    "gn:feature_class":"P",
    "gn:feature_code":"PPLL",
    "gn:name":"Calle Honda",
    "gn:population":0,
    "gn:timezone":"America/Bogota",
    "iso:country":"CO",
    "wof:name":"Calle Honda",
    "wof:placetype":"locality"
},
  "geometry": {"coordinates":[-76.76888000000002,4.8214],"type":"Point"}
}