{
  "type": "Feature",
  "properties": {
    "gn:admin1_code":"21",
    "gn:admin2_code":"54810.0",
    "gn:asciiname":"Campoyuca",
    "gn:country_code":"CO",
    "gn:dem":60,
    "gn:feature_class":"P",
    "gn:feature_code":"PPL",
    "gn:name":"Campoyuca",
    "gn:population":0,
    "gn:timezone":"America/Bogota",
    "iso:country":"CO",
    "wof:name":"Campoyuca",
    "wof:placetype":"locality"
},
  "geometry": {"coordinates":[-72.76557,8.62353],"type":"Point"}
}