{
  "type": "Feature",
  "properties": {
    "gn:admin1_code":"8",
    "gn:admin2_code":"18001.0",
    "gn:asciiname":"Corleon",
    "gn:country_code":"CO",
    "gn:dem":251,
    "gn:feature_class":"P",
    "gn:feature_code":"PPL",
    "gn:name":"Corle\u00f3n",
    "gn:population":0,
    "gn:timezone":"America/Bogota",
    "iso:country":"CO",
    "wof:name":"Corleon",
    "wof:placetype":"locality"
},
  "geometry": {"coordinates":[-75.48333000000002,1.48333],"type":"Point"}
}