{
  "type": "Feature",
  "properties": {
    "gn:admin1_code":"28",
    "gn:admin2_code":"73678.0",
    "gn:asciiname":"Malnombre",
    "gn:country_code":"CO",
    "gn:dem":315,
    "gn:feature_class":"P",
    "gn:feature_code":"PPL",
    "gn:name":"Malnombre",
    "gn:population":0,
    "gn:timezone":"America/Bogota",
    "iso:country":"CO",
    "wof:name":"Malnombre",
    "wof:placetype":"locality"
},
  "geometry": {"coordinates":[-75.04666999999998,3.94],"type":"Point"}
}