{
  "type": "Feature",
  "properties": {
    "gn:admin1_code":"15",
    "gn:admin2_code":"94884.0",
    "gn:asciiname":"Mapiripana",
    "gn:country_code":"CO",
    "gn:dem":110,
    "gn:feature_class":"P",
    "gn:feature_code":"PPL",
    "gn:name":"Mapiripana",
    "gn:population":0,
    "gn:timezone":"America/Bogota",
    "iso:country":"CO",
    "wof:name":"Mapiripana",
    "wof:placetype":"locality"
},
  "geometry": {"coordinates":[-68.05611,2.62713],"type":"Point"}
}