{
  "type": "Feature",
  "properties": {
    "gn:admin1_code":"33",
    "gn:admin2_code":"25572.0",
    "gn:asciiname":"Santa Lucia",
    "gn:country_code":"CO",
    "gn:dem":188,
    "gn:feature_class":"P",
    "gn:feature_code":"PPL",
    "gn:name":"Santa Luc\u00eda",
    "gn:population":0,
    "gn:timezone":"America/Bogota",
    "iso:country":"CO",
    "wof:name":"Santa Lucia",
    "wof:placetype":"locality"
},
  "geometry": {"coordinates":[-74.48528,5.76417],"type":"Point"}
}