{
  "type": "Feature",
  "properties": {
    "gn:admin1_code":"29",
    "gn:admin2_code":"76111.0",
    "gn:asciiname":"Cajones",
    "gn:country_code":"CO",
    "gn:dem":2593,
    "gn:feature_class":"P",
    "gn:feature_code":"PPL",
    "gn:name":"Cajones",
    "gn:population":0,
    "gn:timezone":"America/Bogota",
    "iso:country":"CO",
    "wof:name":"Cajones",
    "wof:placetype":"locality"
},
  "geometry": {"coordinates":[-75.91315999999998,3.8912],"type":"Point"}
}