{
  "type": "Feature",
  "properties": {
    "gn:admin1_code":"38",
    "gn:admin2_code":"47318.0",
    "gn:asciiname":"La Puntica",
    "gn:country_code":"CO",
    "gn:dem":26,
    "gn:feature_class":"P",
    "gn:feature_code":"PPL",
    "gn:name":"La Puntica",
    "gn:population":0,
    "gn:timezone":"America/Bogota",
    "iso:country":"CO",
    "name:und_x_variant":[
        "Caser\u00edo La Puntical",
        "La Puntica"
    ],
    "wof:name":"La Puntica",
    "wof:placetype":"locality"
},
  "geometry": {"coordinates":[-74.24784,9.21155],"type":"Point"}
}