{
  "type": "Feature",
  "properties": {
    "gn:admin1_code":"36.0",
    "gn:asciiname":"El Pavo",
    "gn:country_code":"CO",
    "gn:dem":4018,
    "gn:feature_class":"P",
    "gn:feature_code":"PPL",
    "gn:name":"El Pavo",
    "gn:population":0,
    "gn:timezone":"America/Bogota",
    "iso:country":"CO",
    "name:spa_x_preferred":[
        "El Pavo"
    ],
    "wof:name":"El Pavo",
    "wof:placetype":"locality"
},
  "geometry": {"coordinates":[-72.5287,6.71596],"type":"Point"}
}