{
  "type": "Feature",
  "properties": {
    "iso:country":"CO",
    "name:spa_x_preferred":[
        "La Tebaida"
    ],
    "name:unk_x_variant":[
        "Tebaida"
    ],
    "qs:gn_country":"CO",
    "qs:gn_fcode":"PPL",
    "qs:gn_pop":0,
    "qs:name":"La Tebaida",
    "qs:name_adm0":"Colombia",
    "qs:name_adm1":"Quindio",
    "qs:photos":354,
    "qs:photos_1k":72,
    "qs:photos_9k":2,
    "qs:photos_9r":5,
    "qs:photos_all":354,
    "qs:photos_sr":6,
    "qs:placetype":"Town",
    "qs:pop_sr":"0",
    "qs:woe_adm0":23424787,
    "wof:name":"La Tebaida",
    "wof:placetype":"locality"
},
  "geometry": {"coordinates":[-75.64082999999999,5.10028],"type":"Point"}
}