{
  "type": "Feature",
  "properties": {
    "gn:admin1_code":"2",
    "gn:admin2_code":"5895.0",
    "gn:asciiname":"La Guinea",
    "gn:cc2":"CO",
    "gn:country_code":"CO",
    "gn:dem":47,
    "gn:feature_class":"P",
    "gn:feature_code":"PPL",
    "gn:name":"La Guinea",
    "gn:population":0,
    "gn:timezone":"America/Bogota",
    "iso:country":"CO",
    "name:ita_x_preferred":[
        "La Guinea"
    ],
    "name:spa_x_preferred":[
        "La Guinea"
    ],
    "name:und_x_variant":[
        "Guinea"
    ],
    "name:zho_x_preferred":[
        "\u62c9\u5e7e\u5167\u4e9e"
    ],
    "wof:name":"La Guinea",
    "wof:placetype":"locality"
},
  "geometry": {"coordinates":[-74.83333,7.61667],"type":"Point"}
}