{
  "type": "Feature",
  "properties": {
    "gn:admin1_code":"2",
    "gn:admin2_code":"5895.0",
    "gn:asciiname":"La Guinea",
    "gn:cc2":"CO",
    "gn:country_code":"CO",
    "gn:dem":47,
    "gn:feature_class":"P",
    "gn:feature_code":"PPL",
    "gn:name":"La Guinea",
    "gn:population":0,
    "gn:timezone":"America/Bogota",
    "iso:country":"CO",
    "name:und_x_variant":[
        "Guinea",
        "La Guinea"
    ],
    "wof:name":"La Guinea",
    "wof:placetype":"locality"
},
  "geometry": {"coordinates":[-74.83333,7.61667],"type":"Point"}
}