{
  "type": "Feature",
  "properties": {
    "gn:admin1_code":"9.0",
    "gn:admin2_code":"19142.0",
    "gn:asciiname":"Mingo",
    "gn:country_code":"CO",
    "gn:dem":976,
    "gn:feature_class":"P",
    "gn:feature_code":"PPL",
    "gn:name":"Mingo",
    "gn:population":0,
    "gn:timezone":"America/Bogota",
    "iso:country":"CO",
    "name:bul_x_preferred":[
        "\u041c\u0438\u043d\u0433\u043e"
    ],
    "name:deu_x_preferred":[
        "Mingo"
    ],
    "name:fin_x_preferred":[
        "Mingot"
    ],
    "name:fra_x_preferred":[
        "Mingos"
    ],
    "name:ita_x_preferred":[
        "Mingo"
    ],
    "name:kor_x_preferred":[
        "\ubc0d\uace0\uc871"
    ],
    "name:nor_x_preferred":[
        "Mingo"
    ],
    "name:rus_x_preferred":[
        "\u041c\u0438\u043d\u0433\u043e"
    ],
    "name:spa_x_preferred":[
        "Mingo"
    ],
    "name:swe_x_preferred":[
        "Mingo"
    ],
    "wof:name":"Mingo",
    "wof:placetype":"locality"
},
  "geometry": {"coordinates":[-76.41916999999999,3.20492],"type":"Point"}
}