{
  "type": "Feature",
  "properties": {
    "gn:admin1_code":"9.0",
    "gn:admin2_code":"19142.0",
    "gn:asciiname":"Mingo",
    "gn:country_code":"CO",
    "gn:dem":976,
    "gn:feature_class":"P",
    "gn:feature_code":"PPL",
    "gn:name":"Mingo",
    "gn:population":0,
    "gn:timezone":"America/Bogota",
    "iso:country":"CO",
    "wof:name":"Mingo",
    "wof:placetype":"locality"
},
  "geometry": {"coordinates":[-76.41916999999999,3.20492],"type":"Point"}
}