{
  "type": "Feature",
  "properties": {
    "gn:admin1_code":"16.0",
    "gn:admin2_code":"41668.0",
    "gn:asciiname":"Cascajal",
    "gn:country_code":"CO",
    "gn:dem":1728,
    "gn:feature_class":"P",
    "gn:feature_code":"PPL",
    "gn:name":"Cascajal",
    "gn:population":0,
    "gn:timezone":"America/Bogota",
    "iso:country":"CO",
    "wof:name":"Cascajal",
    "wof:placetype":"locality"
},
  "geometry": {"coordinates":[-76.3357,1.93243],"type":"Point"}
}