{
  "type": "Feature",
  "properties": {
    "gn:admin1_code":"12",
    "gn:admin2_code":"23189.0",
    "gn:asciiname":"El Reparo",
    "gn:country_code":"CO",
    "gn:dem":29,
    "gn:feature_class":"P",
    "gn:feature_code":"PPLL",
    "gn:name":"El Reparo",
    "gn:population":0,
    "gn:timezone":"America/Bogota",
    "iso:country":"CO",
    "wof:name":"El Reparo",
    "wof:placetype":"locality"
},
  "geometry": {"coordinates":[-75.57755,8.88753],"type":"Point"}
}