{
  "type": "Feature",
  "properties": {
    "iso:country":"CO",
    "name:ast_x_preferred":[
        "Calarc\u00e1"
    ],
    "name:deu_x_preferred":[
        "Calarc\u00e1"
    ],
    "name:eng_x_preferred":[
        "Calarc\u00e1"
    ],
    "name:eng_x_variant":[
        "Opita"
    ],
    "name:fas_x_preferred":[
        "\u06a9\u0627\u0644\u0627\u0631\u06a9\u0627"
    ],
    "name:fra_x_preferred":[
        "Calarc\u00e1"
    ],
    "name:ita_x_preferred":[
        "Calarc\u00e1"
    ],
    "name:jpn_x_preferred":[
        "\u30ab\u30e9\u30eb\u30ab\u30fc"
    ],
    "name:kat_x_preferred":[
        "\u10d9\u10d0\u10da\u10d0\u10e0\u10d9\u10d0"
    ],
    "name:lit_x_preferred":[
        "Kalarka"
    ],
    "name:msa_x_preferred":[
        "Calarca"
    ],
    "name:nan_x_preferred":[
        "Calarc\u00e1"
    ],
    "name:nld_x_preferred":[
        "Calarc\u00e1"
    ],
    "name:nob_x_preferred":[
        "Calarc\u00e1"
    ],
    "name:por_x_preferred":[
        "Calarc\u00e1"
    ],
    "name:rus_x_preferred":[
        "\u041a\u0430\u043b\u0430\u0440\u043a\u0430"
    ],
    "name:slv_x_preferred":[
        "Calarc\u00e1"
    ],
    "name:spa_x_preferred":[
        "Calarc\u00e1"
    ],
    "name:tgl_x_preferred":[
        "Calarc\u00e1"
    ],
    "name:unk_x_variant":[
        "Calarca"
    ],
    "name:vie_x_preferred":[
        "Calarc\u00e1"
    ],
    "name:war_x_preferred":[
        "Calarc\u00e1"
    ],
    "name:zho_x_preferred":[
        "\u5361\u62c9\u723e\u5361"
    ],
    "qs:gn_country":"CO",
    "qs:gn_fcode":"PPL",
    "qs:gn_pop":62170,
    "qs:name":"Calarc\u00e1",
    "qs:name_adm0":"Colombia",
    "qs:name_adm1":"Quindio",
    "qs:photos":601,
    "qs:photos_1k":122,
    "qs:photos_9k":3,
    "qs:photos_9r":5,
    "qs:photos_all":601,
    "qs:photos_sr":8,
    "qs:placetype":"Town",
    "qs:pop_sr":"8",
    "qs:woe_adm0":23424787,
    "wof:name":"Calarc\u00e1",
    "wof:placetype":"locality",
    "wof:population":62170
},
  "geometry": {"coordinates":[-75.64091000000001,4.52949],"type":"Point"}
}