{
  "type": "Feature",
  "properties": {
    "gn:admin1_code":"2.0",
    "gn:admin2_code":"5138.0",
    "gn:asciiname":"Pananos",
    "gn:country_code":"CO",
    "gn:dem":1990,
    "gn:feature_class":"P",
    "gn:feature_code":"PPL",
    "gn:name":"Pananos",
    "gn:population":0,
    "gn:timezone":"America/Bogota",
    "iso:country":"CO",
    "wof:name":"Pananos",
    "wof:placetype":"locality"
},
  "geometry": {"coordinates":[-75.98056,6.71833],"type":"Point"}
}