{
  "type": "Feature",
  "properties": {
    "gn:admin1_code":"16",
    "gn:admin2_code":"41001",
    "gn:asciiname":"Villa Vieja",
    "gn:country_code":"CO",
    "gn:dem":1908,
    "gn:feature_class":"P",
    "gn:feature_code":"PPL",
    "gn:name":"Villa Vieja",
    "gn:population":0,
    "gn:timezone":"America/Bogota",
    "iso:country":"CO",
    "name:fra_x_preferred":[
        "Villavieja"
    ],
    "name:ita_x_preferred":[
        "Villavieja"
    ],
    "name:kat_x_preferred":[
        "\u10d5\u10d8\u10da\u10d8\u10d0\u10d5\u10d8\u10d4\u10ee\u10d0"
    ],
    "name:msa_x_preferred":[
        "Villavieja"
    ],
    "name:nld_x_preferred":[
        "Villavieja"
    ],
    "name:por_x_preferred":[
        "Villavieja"
    ],
    "name:spa_x_preferred":[
        "Villa Vieja"
    ],
    "name:spa_x_variant":[
        "Villavieja"
    ],
    "name:tgl_x_preferred":[
        "Villavieja"
    ],
    "name:war_x_preferred":[
        "Villavieja"
    ],
    "name:zho_x_preferred":[
        "\u6bd4\u5229\u4e9e\u7dad\u54c8"
    ],
    "wof:name":"Villa Vieja",
    "wof:placetype":"locality"
},
  "geometry": {"coordinates":[-75.03322,2.91236],"type":"Point"}
}