{
  "type": "Feature",
  "properties": {
    "gn:admin1_code":"2",
    "gn:admin2_code":"5282.0",
    "gn:asciiname":"Murrapal",
    "gn:country_code":"CO",
    "gn:dem":1828,
    "gn:feature_class":"P",
    "gn:feature_code":"PPL",
    "gn:name":"Murrapal",
    "gn:population":0,
    "gn:timezone":"America/Bogota",
    "iso:country":"CO",
    "wof:name":"Murrapal",
    "wof:placetype":"locality"
},
  "geometry": {"coordinates":[-75.68453000000002,5.90694],"type":"Point"}
}