{
  "type": "Feature",
  "properties": {
    "gn:admin1_code":"12",
    "gn:admin2_code":"23001.0",
    "gn:asciiname":"La Estrella",
    "gn:country_code":"CO",
    "gn:dem":75,
    "gn:feature_class":"P",
    "gn:feature_code":"PPL",
    "gn:name":"La Estrella",
    "gn:population":0,
    "gn:timezone":"America/Bogota",
    "iso:country":"CO",
    "wof:name":"La Estrella",
    "wof:placetype":"locality"
},
  "geometry": {"coordinates":[-76.06278,8.77694],"type":"Point"}
}