{
  "type": "Feature",
  "properties": {
    "iso:country":"CO",
    "name:ara_x_preferred":[
        "\u0644\u0627 \u064a\u0648\u0646\u064a\u0648\u0646"
    ],
    "name:arm_x_preferred":[
        "\u0545\u0561 \u0545\u0578\u0582\u0576\u056b\u0578\u0576"
    ],
    "name:cat_x_preferred":[
        "La Uni\u00f3n"
    ],
    "name:chi_x_preferred":[
        "\u62c9\u70cf\u5c3c\u7fc1"
    ],
    "name:dut_x_preferred":[
        "La Uni\u00f3n"
    ],
    "name:eng_x_preferred":[
        "La Uni\u00f3n"
    ],
    "name:fre_x_preferred":[
        "La Uni\u00f3n"
    ],
    "name:geo_x_preferred":[
        "\u10da\u10d0-\u10e3\u10dc\u10d8\u10dd\u10dc\u10d8"
    ],
    "name:ger_x_preferred":[
        "La Uni\u00f3n"
    ],
    "name:ile_x_preferred":[
        "La Uni\u00f3n"
    ],
    "name:ind_x_preferred":[
        "La Uni\u00f3n"
    ],
    "name:ita_x_preferred":[
        "La Uni\u00f3n"
    ],
    "name:kor_x_preferred":[
        "\ub77c\uc6b0\ub2c8\uc628"
    ],
    "name:may_x_preferred":[
        "La Uni\u00f3n"
    ],
    "name:nan_x_preferred":[
        "La Uni\u00f3n"
    ],
    "name:por_x_preferred":[
        "La Uni\u00f3n"
    ],
    "name:rum_x_preferred":[
        "La Uni\u00f3n"
    ],
    "name:rus_x_preferred":[
        "\u041b\u0430-\u0423\u043d\u0438\u043e\u043d"
    ],
    "name:sco_x_preferred":[
        "La Uni\u00f3n"
    ],
    "name:spa_x_preferred":[
        "La Uni\u00f3n"
    ],
    "name:swe_x_preferred":[
        "La Uni\u00f3n"
    ],
    "name:tgl_x_preferred":[
        "La Uni\u00f3n"
    ],
    "name:urd_x_preferred":[
        "\u0644\u0627 \u0648\u0646\u06cc\u0648\u0646\u060c \u0627\u0646\u0679\u06cc\u0648\u06a9\u0648\u06cc\u0627"
    ],
    "name:vie_x_preferred":[
        "La Uni\u00f3n"
    ],
    "name:war_x_preferred":[
        "La Uni\u00f3n"
    ],
    "qs:gn_country":"CO",
    "qs:gn_fcode":"PPL",
    "qs:gn_pop":8361,
    "qs:name":"La Uni\u00f3n",
    "qs:name_adm0":"Colombia",
    "qs:name_adm1":"Antioquia",
    "qs:photos":381,
    "qs:photos_1k":77,
    "qs:photos_9k":2,
    "qs:photos_9r":5,
    "qs:photos_all":381,
    "qs:photos_sr":6,
    "qs:placetype":"Town",
    "qs:pop_sr":"5",
    "qs:woe_adm0":23424787,
    "wof:name":"La Uni\u00f3n",
    "wof:placetype":"locality",
    "wof:population":8361
},
  "geometry": {"coordinates":[-75.36194999999999,5.97431],"type":"Point"}
}