{
  "type": "Feature",
  "properties": {
    "gn:admin1_code":"9",
    "gn:admin2_code":"19517.0",
    "gn:asciiname":"Delicias",
    "gn:country_code":"CO",
    "gn:dem":1852,
    "gn:feature_class":"P",
    "gn:feature_code":"PPL",
    "gn:name":"Del\u00edcias",
    "gn:population":0,
    "gn:timezone":"America/Bogota",
    "iso:country":"CO",
    "wof:name":"Delicias",
    "wof:placetype":"locality"
},
  "geometry": {"coordinates":[-75.81694,2.6525],"type":"Point"}
}