{
  "type": "Feature",
  "properties": {
    "gn:admin1_code":"29",
    "gn:asciiname":"El Ceral",
    "gn:country_code":"CO",
    "gn:dem":1077,
    "gn:feature_class":"P",
    "gn:feature_code":"PPL",
    "gn:name":"El Ceral",
    "gn:population":0,
    "gn:timezone":"America/Bogota",
    "iso:country":"CO",
    "name:und_x_variant":[
        "El Cerol"
    ],
    "wof:name":"El Ceral",
    "wof:placetype":"locality"
},
  "geometry": {"coordinates":[-76.66998000000002,3.0916],"type":"Point"}
}