{
  "type": "Feature",
  "properties": {
    "gn:admin1_code":"16.0",
    "gn:admin2_code":"41791.0",
    "gn:asciiname":"El Chorrito",
    "gn:country_code":"CO",
    "gn:dem":2016,
    "gn:feature_class":"P",
    "gn:feature_code":"PPL",
    "gn:name":"El Chorrito",
    "gn:population":0,
    "gn:timezone":"America/Bogota",
    "iso:country":"CO",
    "name:spa_x_preferred":[
        "El Chorrito"
    ],
    "wof:name":"El Chorrito",
    "wof:placetype":"locality"
},
  "geometry": {"coordinates":[-75.89972,2.16361],"type":"Point"}
}