{
  "type": "Feature",
  "properties": {
    "gn:admin1_code":"27",
    "gn:admin2_code":"70820.0",
    "gn:asciiname":"La Garlopa",
    "gn:country_code":"CO",
    "gn:dem":25,
    "gn:feature_class":"P",
    "gn:feature_code":"PPL",
    "gn:name":"La Garlopa",
    "gn:population":0,
    "gn:timezone":"America/Bogota",
    "iso:country":"CO",
    "name:und_x_variant":[
        "Hacienda La Garlopa",
        "La Garlopa"
    ],
    "wof:name":"La Garlopa",
    "wof:placetype":"locality"
},
  "geometry": {"coordinates":[-75.53621,9.45028],"type":"Point"}
}