{
  "type": "Feature",
  "properties": {
    "gn:admin1_code":"9.0",
    "gn:admin2_code":"19743.0",
    "gn:asciiname":"Jebala",
    "gn:country_code":"CO",
    "gn:dem":2341,
    "gn:feature_class":"P",
    "gn:feature_code":"PPL",
    "gn:name":"Jebal\u00e1",
    "gn:population":0,
    "gn:timezone":"America/Bogota",
    "iso:country":"CO",
    "wof:name":"Jebala",
    "wof:placetype":"locality"
},
  "geometry": {"coordinates":[-76.41231999999999,2.5786],"type":"Point"}
}