{
  "type": "Feature",
  "properties": {
    "gn:admin1_code":"36",
    "gn:admin2_code":"15572.0",
    "gn:asciiname":"El Mandanno",
    "gn:country_code":"CO",
    "gn:dem":815,
    "gn:feature_class":"P",
    "gn:feature_code":"PPL",
    "gn:name":"El Mandanno",
    "gn:population":0,
    "gn:timezone":"America/Bogota",
    "iso:country":"CO",
    "wof:name":"El Mandanno",
    "wof:placetype":"locality"
},
  "geometry": {"coordinates":[-74.29083,5.80417],"type":"Point"}
}