{
  "type": "Feature",
  "properties": {
    "gn:admin1_code":"10.0",
    "gn:admin2_code":"20001.0",
    "gn:asciiname":"Rio Branco",
    "gn:country_code":"CO",
    "gn:dem":84,
    "gn:feature_class":"P",
    "gn:feature_code":"PPL",
    "gn:name":"R\u00edo Branco",
    "gn:population":0,
    "gn:timezone":"America/Bogota",
    "iso:country":"CO",
    "name:bar_x_preferred":[
        "Rio Branco"
    ],
    "name:bre_x_preferred":[
        "Rio Branco"
    ],
    "name:ceb_x_preferred":[
        "Rio Branco"
    ],
    "name:ces_x_preferred":[
        "Rio Branco"
    ],
    "name:deu_x_preferred":[
        "Rio Branco"
    ],
    "name:est_x_preferred":[
        "Rio Branco"
    ],
    "name:fra_x_preferred":[
        "Rio Branco"
    ],
    "name:grn_x_preferred":[
        "Rio Branco"
    ],
    "name:heb_x_preferred":[
        "\u05e8\u05d9\u05d5 \u05d1\u05e8\u05e0\u05e7\u05d5"
    ],
    "name:hye_x_preferred":[
        "\u054c\u056b\u0578\u0582 \u0532\u0580\u0561\u0576\u056f\u0578\u0582"
    ],
    "name:ita_x_preferred":[
        "Rio Branco"
    ],
    "name:jpn_x_preferred":[
        "\u30ea\u30aa\u30fb\u30d6\u30e9\u30f3\u30b3"
    ],
    "name:kor_x_preferred":[
        "\ub9ac\uc624\ube0c\ub791\ucf54"
    ],
    "name:lit_x_preferred":[
        "Brankas"
    ],
    "name:nld_x_preferred":[
        "Rio Branco"
    ],
    "name:nor_x_preferred":[
        "Rio Branco"
    ],
    "name:pol_x_preferred":[
        "Rio Branco"
    ],
    "name:por_x_preferred":[
        "Rio Branco"
    ],
    "name:rus_x_preferred":[
        "\u0420\u0438\u0443-\u0411\u0440\u0430\u043d\u043a\u0443"
    ],
    "name:spa_x_preferred":[
        "Rio Branco"
    ],
    "name:swe_x_preferred":[
        "Rio Branco"
    ],
    "name:vol_x_preferred":[
        "Rio Branco"
    ],
    "wof:name":"Rio Branco",
    "wof:placetype":"locality"
},
  "geometry": {"coordinates":[-73.45093,10.1917],"type":"Point"}
}