{
  "type": "Feature",
  "properties": {
    "gn:admin1_code":"2.0",
    "gn:admin2_code":"5656.0",
    "gn:asciiname":"Cienaquita",
    "gn:country_code":"CO",
    "gn:dem":1831,
    "gn:feature_class":"P",
    "gn:feature_code":"PPL",
    "gn:name":"Cienaquita",
    "gn:population":0,
    "gn:timezone":"America/Bogota",
    "iso:country":"CO",
    "name:spa_x_preferred":[
        "Cienaquita"
    ],
    "wof:name":"Cienaquita",
    "wof:placetype":"locality"
},
  "geometry": {"coordinates":[-75.68401999999998,6.43322],"type":"Point"}
}