{
  "type": "Feature",
  "properties": {
    "gn:admin1_code":"38",
    "gn:admin2_code":"47551.0",
    "gn:asciiname":"El Codo",
    "gn:country_code":"CO",
    "gn:dem":58,
    "gn:feature_class":"P",
    "gn:feature_code":"PPL",
    "gn:name":"El Codo",
    "gn:population":0,
    "gn:timezone":"America/Bogota",
    "iso:country":"CO",
    "name:und_x_variant":[
        "Hacienda El Codo",
        "El Codo"
    ],
    "wof:name":"El Codo",
    "wof:placetype":"locality"
},
  "geometry": {"coordinates":[-74.25419000000002,10.48943],"type":"Point"}
}