{
  "type": "Feature",
  "properties": {
    "gn:admin1_code":"8.0",
    "gn:admin2_code":"18756.0",
    "gn:asciiname":"Jerusalen",
    "gn:country_code":"CO",
    "gn:dem":151,
    "gn:feature_class":"P",
    "gn:feature_code":"PPL",
    "gn:name":"Jerusal\u00e9n",
    "gn:population":0,
    "gn:timezone":"America/Bogota",
    "iso:country":"CO",
    "wof:name":"Jerusalen",
    "wof:placetype":"locality"
},
  "geometry": {"coordinates":[-73.27892,-0.53749],"type":"Point"}
}