{
  "type": "Feature",
  "properties": {
    "gn:admin1_code":"20",
    "gn:admin2_code":"52885.0",
    "gn:asciiname":"Aguada",
    "gn:country_code":"CO",
    "gn:dem":2897,
    "gn:feature_class":"P",
    "gn:feature_code":"PPL",
    "gn:name":"Aguada",
    "gn:population":0,
    "gn:timezone":"America/Bogota",
    "iso:country":"CO",
    "wof:name":"Aguada",
    "wof:placetype":"locality"
},
  "geometry": {"coordinates":[-77.37815999999999,1.13203],"type":"Point"}
}