{
  "type": "Feature",
  "properties": {
    "gn:admin1_code":"2.0",
    "gn:admin2_code":"5591.0",
    "gn:asciiname":"Socha",
    "gn:country_code":"CO",
    "gn:dem":204,
    "gn:feature_class":"P",
    "gn:feature_code":"PPL",
    "gn:name":"Socha",
    "gn:population":0,
    "gn:timezone":"America/Bogota",
    "iso:country":"CO",
    "wof:name":"Socha",
    "wof:placetype":"locality"
},
  "geometry": {"coordinates":[-74.69583,5.98444],"type":"Point"}
}