{
  "type": "Feature",
  "properties": {
    "gn:admin1_code":"2.0",
    "gn:admin2_code":"5591.0",
    "gn:asciiname":"Socha",
    "gn:country_code":"CO",
    "gn:dem":204,
    "gn:feature_class":"P",
    "gn:feature_code":"PPL",
    "gn:name":"Socha",
    "gn:population":0,
    "gn:timezone":"America/Bogota",
    "iso:country":"CO",
    "name:ceb_x_preferred":[
        "Socha"
    ],
    "name:fra_x_preferred":[
        "Socha"
    ],
    "name:ita_x_preferred":[
        "Socha"
    ],
    "name:kat_x_preferred":[
        "\u10e1\u10dd\u10e9\u10d0"
    ],
    "name:msa_x_preferred":[
        "Socha"
    ],
    "name:nld_x_preferred":[
        "Socha"
    ],
    "name:por_x_preferred":[
        "Socha"
    ],
    "name:rus_x_preferred":[
        "\u0421\u043e\u0447\u0430"
    ],
    "name:spa_x_preferred":[
        "Socha"
    ],
    "name:swe_x_preferred":[
        "Socha"
    ],
    "name:tgl_x_preferred":[
        "Socha"
    ],
    "name:vie_x_preferred":[
        "Socha"
    ],
    "name:war_x_preferred":[
        "Socha"
    ],
    "wof:name":"Socha",
    "wof:placetype":"locality"
},
  "geometry": {"coordinates":[-74.69583,5.98444],"type":"Point"}
}