{
  "type": "Feature",
  "properties": {
    "gn:admin1_code":"36.0",
    "gn:admin2_code":"15522.0",
    "gn:asciiname":"La Ovejera",
    "gn:country_code":"CO",
    "gn:dem":2363,
    "gn:feature_class":"P",
    "gn:feature_code":"PPL",
    "gn:name":"La Ovejera",
    "gn:population":0,
    "gn:timezone":"America/Bogota",
    "iso:country":"CO",
    "name:spa_x_preferred":[
        "La Ovejera"
    ],
    "wof:name":"La Ovejera",
    "wof:placetype":"locality"
},
  "geometry": {"coordinates":[-72.45421999999998,6.43926],"type":"Point"}
}