{
  "type": "Feature",
  "properties": {
    "gn:admin1_code":"2",
    "gn:admin2_code":"5579.0",
    "gn:asciiname":"Estacion Cabanas",
    "gn:country_code":"CO",
    "gn:dem":640,
    "gn:feature_class":"P",
    "gn:feature_code":"PPL",
    "gn:name":"Estaci\u00f3n Caba\u00f1as",
    "gn:population":0,
    "gn:timezone":"America/Bogota",
    "iso:country":"CO",
    "wof:name":"Estacion Cabanas",
    "wof:placetype":"locality"
},
  "geometry": {"coordinates":[-74.68083,6.39333],"type":"Point"}
}