{
  "type": "Feature",
  "properties": {
    "gn:admin1_code":"38",
    "gn:admin2_code":"47030.0",
    "gn:asciiname":"Costarrica",
    "gn:country_code":"CO",
    "gn:dem":108,
    "gn:feature_class":"P",
    "gn:feature_code":"PPL",
    "gn:name":"Costarrica",
    "gn:population":0,
    "gn:timezone":"America/Bogota",
    "iso:country":"CO",
    "name:und_x_variant":[
        "Hacienda Costarica",
        "Hacienda Costarrica",
        "Costarrica"
    ],
    "wof:name":"Costarrica",
    "wof:placetype":"locality"
},
  "geometry": {"coordinates":[-74.10009000000002,10.23245],"type":"Point"}
}