{
  "type": "Feature",
  "properties": {
    "gn:admin1_code":"19",
    "gn:admin2_code":"50124.0",
    "gn:asciiname":"Remanzon",
    "gn:country_code":"CO",
    "gn:dem":166,
    "gn:feature_class":"P",
    "gn:feature_code":"PPL",
    "gn:name":"Remanzon",
    "gn:population":0,
    "gn:timezone":"America/Bogota",
    "iso:country":"CO",
    "wof:name":"Remanzon",
    "wof:placetype":"locality"
},
  "geometry": {"coordinates":[-72.87459,4.25066],"type":"Point"}
}