{
  "type": "Feature",
  "properties": {
    "gn:admin1_code":"29",
    "gn:admin2_code":"76520.0",
    "gn:asciiname":"Trapiche",
    "gn:country_code":"CO",
    "gn:dem":1288,
    "gn:feature_class":"P",
    "gn:feature_code":"PPL",
    "gn:name":"Trapiche",
    "gn:population":0,
    "gn:timezone":"America/Bogota",
    "iso:country":"CO",
    "name:cat_x_preferred":[
        "Trapig"
    ],
    "name:fra_x_preferred":[
        "Trapiche"
    ],
    "name:por_x_preferred":[
        "Trapiche"
    ],
    "name:spa_x_preferred":[
        "Trapiche"
    ],
    "wof:name":"Trapiche",
    "wof:placetype":"locality"
},
  "geometry": {"coordinates":[-76.197,3.522],"type":"Point"}
}