{
  "type": "Feature",
  "properties": {
    "gn:admin1_code":"29.0",
    "gn:admin2_code":"76122.0",
    "gn:asciiname":"Montegrande",
    "gn:country_code":"CO",
    "gn:dem":1114,
    "gn:feature_class":"P",
    "gn:feature_code":"PPL",
    "gn:name":"Montegrande",
    "gn:population":0,
    "gn:timezone":"America/Bogota",
    "iso:country":"CO",
    "wof:name":"Montegrande",
    "wof:placetype":"locality"
},
  "geometry": {"coordinates":[-75.82529,4.38639],"type":"Point"}
}