{
  "type": "Feature",
  "properties": {
    "gn:admin1_code":"35.0",
    "gn:admin2_code":"13212.0",
    "gn:asciiname":"Monte Firme",
    "gn:country_code":"CO",
    "gn:dem":47,
    "gn:feature_class":"P",
    "gn:feature_code":"PPL",
    "gn:name":"Monte Firme",
    "gn:population":0,
    "gn:timezone":"America/Bogota",
    "iso:country":"CO",
    "wof:name":"Monte Firme",
    "wof:placetype":"locality"
},
  "geometry": {"coordinates":[-74.8707,9.41182],"type":"Point"}
}