{
  "type": "Feature",
  "properties": {
    "iso:country":"CO",
    "name:ast_x_preferred":[
        "Becerril"
    ],
    "name:avk_x_preferred":[
        "Becerril"
    ],
    "name:ceb_x_preferred":[
        "Becerril"
    ],
    "name:deu_x_preferred":[
        "Becerril"
    ],
    "name:eng_x_preferred":[
        "Becerril"
    ],
    "name:fas_x_preferred":[
        "\u0628\u0633\u0631\u06cc\u0644"
    ],
    "name:fra_x_preferred":[
        "Becerril"
    ],
    "name:gle_x_preferred":[
        "Becerril"
    ],
    "name:ita_x_preferred":[
        "Becerril"
    ],
    "name:jpn_x_preferred":[
        "\u30d9\u30bb\u30df\u30eb"
    ],
    "name:kat_x_preferred":[
        "\u10d1\u10d4\u10e1\u10d4\u10e0\u10d8\u10da\u10d8"
    ],
    "name:ltz_x_preferred":[
        "Becerril"
    ],
    "name:mlt_x_preferred":[
        "Becerril"
    ],
    "name:msa_x_preferred":[
        "Becerril"
    ],
    "name:nan_x_preferred":[
        "Becerril"
    ],
    "name:nld_x_preferred":[
        "Becerril"
    ],
    "name:pol_x_preferred":[
        "Becerril"
    ],
    "name:por_x_preferred":[
        "Becerril"
    ],
    "name:rus_x_preferred":[
        "\u0411\u0435\u0441\u0435\u0440\u0440\u0438\u043b\u044c"
    ],
    "name:spa_x_preferred":[
        "Becerril"
    ],
    "name:swe_x_preferred":[
        "Becerril"
    ],
    "name:tgl_x_preferred":[
        "Becerril"
    ],
    "name:tha_x_preferred":[
        "\u0e40\u0e1a\u0e40\u0e0b\u0e23\u0e4c\u0e23\u0e34\u0e25"
    ],
    "name:vie_x_preferred":[
        "Becerril"
    ],
    "name:war_x_preferred":[
        "Becerril"
    ],
    "name:zho_min_nan_x_preferred":[
        "Becerril"
    ],
    "name:zho_x_preferred":[
        "\u8c9d\u585e\u91cc\u723e"
    ],
    "qs:gn_country":"CO",
    "qs:gn_fcode":"PPL",
    "qs:gn_pop":9002,
    "qs:name":"Becerril",
    "qs:name_adm0":"Colombia",
    "qs:name_adm1":"Cesar",
    "qs:photos":0,
    "qs:photos_1k":0,
    "qs:photos_9k":0,
    "qs:photos_9r":0,
    "qs:photos_all":0,
    "qs:photos_sr":0,
    "qs:placetype":"Town",
    "qs:pop_sr":"5",
    "qs:woe_adm0":23424787,
    "wd:wordcount":342,
    "wof:name":"Becerril",
    "wof:placetype":"locality",
    "wof:population":9002
},
  "geometry": {"coordinates":[-73.27930000000001,9.70413],"type":"Point"}
}