{
  "type": "Feature",
  "properties": {
    "gn:admin1_code":"29.0",
    "gn:admin2_code":"76100.0",
    "gn:asciiname":"El Fosforo",
    "gn:country_code":"CO",
    "gn:dem":1378,
    "gn:feature_class":"P",
    "gn:feature_code":"PPL",
    "gn:name":"El F\u00f3sforo",
    "gn:population":0,
    "gn:timezone":"America/Bogota",
    "iso:country":"CO",
    "wof:name":"El Fosforo",
    "wof:placetype":"locality"
},
  "geometry": {"coordinates":[-76.22221999999999,4.355],"type":"Point"}
}