{
  "type": "Feature",
  "properties": {
    "gn:admin1_code":"36.0",
    "gn:admin2_code":"15180.0",
    "gn:asciiname":"Zuriga",
    "gn:country_code":"CO",
    "gn:dem":3010,
    "gn:feature_class":"P",
    "gn:feature_code":"PPL",
    "gn:name":"Z\u00fariga",
    "gn:population":0,
    "gn:timezone":"America/Bogota",
    "iso:country":"CO",
    "name:spa_x_preferred":[
        "Z\u00fariga"
    ],
    "wof:name":"Zuriga",
    "wof:placetype":"locality"
},
  "geometry": {"coordinates":[-72.45054,6.5521],"type":"Point"}
}