{
  "type": "Feature",
  "properties": {
    "gn:admin1_code":"9.0",
    "gn:admin2_code":"19022.0",
    "gn:asciiname":"Sauji",
    "gn:country_code":"CO",
    "gn:dem":1891,
    "gn:feature_class":"P",
    "gn:feature_code":"PPL",
    "gn:name":"Sauji",
    "gn:population":0,
    "gn:timezone":"America/Bogota",
    "iso:country":"CO",
    "name:spa_x_preferred":[
        "Sauji"
    ],
    "wof:name":"Sauji",
    "wof:placetype":"locality"
},
  "geometry": {"coordinates":[-76.85789,1.93144],"type":"Point"}
}