{
  "type": "Feature",
  "properties": {
    "gn:admin1_code":"19.0",
    "gn:admin2_code":"50287.0",
    "gn:asciiname":"Inspeccion de Policia Cano Blanco",
    "gn:country_code":"CO",
    "gn:dem":248,
    "gn:feature_class":"P",
    "gn:feature_code":"PPL",
    "gn:name":"Inspecci\u00f3n de Polic\u00eda Ca\u00f1o Blanco",
    "gn:population":0,
    "gn:timezone":"America/Bogota",
    "iso:country":"CO",
    "name:und_x_variant":[
        "Ca\u00f1o Blanco",
        "Inspecci\u00f3n de Polic\u00eda Ca\u00f1o Blanco"
    ],
    "wof:name":"Inspeccion de Policia Cano Blanco",
    "wof:placetype":"locality"
},
  "geometry": {"coordinates":[-73.53203000000001,3.31996],"type":"Point"}
}