{
  "type": "Feature",
  "properties": {
    "gn:admin1_code":"35.0",
    "gn:admin2_code":"13836.0",
    "gn:asciiname":"Praga",
    "gn:country_code":"CO",
    "gn:dem":128,
    "gn:feature_class":"P",
    "gn:feature_code":"PPL",
    "gn:name":"Praga",
    "gn:population":0,
    "gn:timezone":"America/Bogota",
    "iso:country":"CO",
    "wof:name":"Praga",
    "wof:placetype":"locality"
},
  "geometry": {"coordinates":[-75.35847,10.34657],"type":"Point"}
}