{
  "type": "Feature",
  "properties": {
    "gn:admin1_code":"2",
    "gn:admin2_code":"5134.0",
    "gn:asciiname":"La Olleta",
    "gn:country_code":"CO",
    "gn:dem":1978,
    "gn:feature_class":"P",
    "gn:feature_code":"PPL",
    "gn:name":"La Olleta",
    "gn:population":0,
    "gn:timezone":"America/Bogota",
    "iso:country":"CO",
    "wof:name":"La Olleta",
    "wof:placetype":"locality"
},
  "geometry": {"coordinates":[-75.31111,7.02556],"type":"Point"}
}