{
  "type": "Feature",
  "properties": {
    "gn:admin1_code":"35.0",
    "gn:admin2_code":"13657.0",
    "gn:asciiname":"Aguas Vivas",
    "gn:country_code":"CO",
    "gn:dem":115,
    "gn:feature_class":"P",
    "gn:feature_code":"PPL",
    "gn:name":"Aguas Vivas",
    "gn:population":0,
    "gn:timezone":"America/Bogota",
    "iso:country":"CO",
    "wof:name":"Aguas Vivas",
    "wof:placetype":"locality"
},
  "geometry": {"coordinates":[-75.07988,10.0433],"type":"Point"}
}