{
  "type": "Feature",
  "properties": {
    "gn:admin1_code":"8.0",
    "gn:admin2_code":"18410.0",
    "gn:asciiname":"Hato Versalles",
    "gn:country_code":"CO",
    "gn:dem":337,
    "gn:feature_class":"P",
    "gn:feature_code":"PPL",
    "gn:name":"Hato Versalles",
    "gn:population":0,
    "gn:timezone":"America/Bogota",
    "iso:country":"CO",
    "name:spa_x_preferred":[
        "Hato Versalles"
    ],
    "wof:name":"Hato Versalles",
    "wof:placetype":"locality"
},
  "geometry": {"coordinates":[-75.41016999999999,1.47518],"type":"Point"}
}