{
  "type": "Feature",
  "properties": {
    "gn:admin1_code":"17.0",
    "gn:admin2_code":"44560.0",
    "gn:asciiname":"Poroshi",
    "gn:country_code":"CO",
    "gn:dem":13,
    "gn:feature_class":"P",
    "gn:feature_code":"PPL",
    "gn:name":"Poroshi",
    "gn:population":0,
    "gn:timezone":"America/Bogota",
    "iso:country":"CO",
    "wof:name":"Poroshi",
    "wof:placetype":"locality"
},
  "geometry": {"coordinates":[-72.43631999999999,11.70965],"type":"Point"}
}