{
  "type": "Feature",
  "properties": {
    "gn:admin1_code":"19.0",
    "gn:admin2_code":"50689.0",
    "gn:asciiname":"Indostan",
    "gn:country_code":"CO",
    "gn:dem":266,
    "gn:feature_class":"P",
    "gn:feature_code":"PPLL",
    "gn:name":"Indost\u00e1n",
    "gn:population":0,
    "gn:timezone":"America/Bogota",
    "iso:country":"CO",
    "name:spa_x_preferred":[
        "Indost\u00e1n"
    ],
    "wof:name":"Indostan",
    "wof:placetype":"locality"
},
  "geometry": {"coordinates":[-73.1842,3.56596],"type":"Point"}
}