{
  "type": "Feature",
  "properties": {
    "gn:admin1_code":"16",
    "gn:admin2_code":"41483.0",
    "gn:asciiname":"Las Nanes",
    "gn:country_code":"CO",
    "gn:dem":1556,
    "gn:feature_class":"P",
    "gn:feature_code":"PPL",
    "gn:name":"Las Nanes",
    "gn:population":0,
    "gn:timezone":"America/Bogota",
    "iso:country":"CO",
    "wof:name":"Las Nanes",
    "wof:placetype":"locality"
},
  "geometry": {"coordinates":[-75.80989,2.5551],"type":"Point"}
}