{
  "type": "Feature",
  "properties": {
    "gn:admin1_code":"19",
    "gn:admin2_code":"50313",
    "gn:asciiname":"El Bambu",
    "gn:country_code":"CO",
    "gn:dem":346,
    "gn:feature_class":"P",
    "gn:feature_code":"PPL",
    "gn:name":"El Bamb\u00fa",
    "gn:population":0,
    "gn:timezone":"America/Bogota",
    "iso:country":"CO",
    "name:spa_x_preferred":[
        "El Bamb\u00fa"
    ],
    "wof:name":"El Bambu",
    "wof:placetype":"locality"
},
  "geometry": {"coordinates":[-73.69816,3.56595],"type":"Point"}
}