{
  "type": "Feature",
  "properties": {
    "gn:admin1_code":"17",
    "gn:admin2_code":"44560.0",
    "gn:asciiname":"Jepirraruhu",
    "gn:country_code":"CO",
    "gn:dem":41,
    "gn:feature_class":"P",
    "gn:feature_code":"PPL",
    "gn:name":"Jepirraruhu",
    "gn:population":0,
    "gn:timezone":"America/Bogota",
    "iso:country":"CO",
    "wof:name":"Jepirraruhu",
    "wof:placetype":"locality"
},
  "geometry": {"coordinates":[-72.51000000000001,11.47694],"type":"Point"}
}