{
  "type": "Feature",
  "properties": {
    "gn:admin1_code":"9.0",
    "gn:admin2_code":"19142.0",
    "gn:asciiname":"Guatava",
    "gn:country_code":"CO",
    "gn:dem":1613,
    "gn:feature_class":"P",
    "gn:feature_code":"PPL",
    "gn:name":"Guatava",
    "gn:population":0,
    "gn:timezone":"America/Bogota",
    "iso:country":"CO",
    "name:spa_x_preferred":[
        "Guatava"
    ],
    "wof:name":"Guatava",
    "wof:placetype":"locality"
},
  "geometry": {"coordinates":[-76.33989,3.02721],"type":"Point"}
}