{
  "type": "Feature",
  "properties": {
    "gn:admin1_code":"2",
    "gn:admin2_code":"5361.0",
    "gn:asciiname":"La Silleta",
    "gn:country_code":"CO",
    "gn:dem":1083,
    "gn:feature_class":"P",
    "gn:feature_code":"PPL",
    "gn:name":"La Silleta",
    "gn:population":0,
    "gn:timezone":"America/Bogota",
    "iso:country":"CO",
    "wof:name":"La Silleta",
    "wof:placetype":"locality"
},
  "geometry": {"coordinates":[-75.7925,7.40694],"type":"Point"}
}