{
  "type": "Feature",
  "properties": {
    "gn:admin1_code":"38",
    "gn:admin2_code":"47980.0",
    "gn:asciiname":"El Impulso",
    "gn:country_code":"CO",
    "gn:dem":11,
    "gn:feature_class":"P",
    "gn:feature_code":"PPL",
    "gn:name":"El Impulso",
    "gn:population":0,
    "gn:timezone":"America/Bogota",
    "iso:country":"CO",
    "wof:name":"El Impulso",
    "wof:placetype":"locality"
},
  "geometry": {"coordinates":[-74.20331,10.77979],"type":"Point"}
}