{
  "type": "Feature",
  "properties": {
    "gn:admin1_code":"23",
    "gn:admin2_code":"63302.0",
    "gn:asciiname":"El Morelia",
    "gn:country_code":"CO",
    "gn:dem":1706,
    "gn:feature_class":"P",
    "gn:feature_code":"PPL",
    "gn:name":"El Morelia",
    "gn:population":0,
    "gn:timezone":"America/Bogota",
    "iso:country":"CO",
    "wof:name":"El Morelia",
    "wof:placetype":"locality"
},
  "geometry": {"coordinates":[-75.80916999999999,4.20917],"type":"Point"}
}