{
  "type": "Feature",
  "properties": {
    "gn:admin1_code":"9",
    "gn:admin2_code":"19130.0",
    "gn:asciiname":"El Guabal",
    "gn:country_code":"CO",
    "gn:dem":1561,
    "gn:feature_class":"P",
    "gn:feature_code":"PPL",
    "gn:name":"El Guabal",
    "gn:population":0,
    "gn:timezone":"America/Bogota",
    "iso:country":"CO",
    "wof:name":"El Guabal",
    "wof:placetype":"locality"
},
  "geometry": {"coordinates":[-76.74101999999998,2.6905],"type":"Point"}
}