{
  "type": "Feature",
  "properties": {
    "gn:admin1_code":"19",
    "gn:admin2_code":"50251",
    "gn:asciiname":"Vda. Yamenes",
    "gn:country_code":"CO",
    "gn:dem":1047,
    "gn:feature_class":"P",
    "gn:feature_code":"PPL",
    "gn:name":"Vda. Yamenes",
    "gn:population":0,
    "gn:timezone":"America/Bogota",
    "iso:country":"CO",
    "wof:name":"Vda. Yamenes",
    "wof:placetype":"locality"
},
  "geometry": {"coordinates":[-73.94150999999999,3.59673],"type":"Point"}
}