{
  "type": "Feature",
  "properties": {
    "gn:admin1_code":"10",
    "gn:admin2_code":"20750.0",
    "gn:asciiname":"El Toco",
    "gn:country_code":"CO",
    "gn:dem":87,
    "gn:feature_class":"P",
    "gn:feature_code":"PPL",
    "gn:name":"El Toco",
    "gn:population":0,
    "gn:timezone":"America/Bogota",
    "iso:country":"CO",
    "name:und_x_variant":[
        "Hacienda El Toco",
        "El Toco"
    ],
    "wof:name":"El Toco",
    "wof:placetype":"locality"
},
  "geometry": {"coordinates":[-73.36154000000001,10.16441],"type":"Point"}
}