{
  "type": "Feature",
  "properties": {
    "gn:admin1_code":"19.0",
    "gn:admin2_code":"50577.0",
    "gn:asciiname":"La Guajira",
    "gn:country_code":"CO",
    "gn:dem":255,
    "gn:feature_class":"P",
    "gn:feature_code":"PPLL",
    "gn:name":"La Guajira",
    "gn:population":0,
    "gn:timezone":"America/Bogota",
    "iso:country":"CO",
    "name:spa_x_preferred":[
        "La Guajira"
    ],
    "wof:name":"La Guajira",
    "wof:placetype":"locality"
},
  "geometry": {"coordinates":[-73.40023000000002,3.32406],"type":"Point"}
}